{
  "type": "Feature",
  "properties": {
    "iso:country":"US",
    "sg:address":"77 Bayshore Pl",
    "sg:city":"Guntersville",
    "sg:classifiers":[
        {
            "category":"Building & Trades",
            "subcategory":"Construction",
            "type":"Services"
        }
    ],
    "sg:phone":"+1 256 582 9299",
    "sg:postcode":"35976",
    "sg:province":"AL",
    "sg:tags":[
        "frame",
        "timber"
    ],
    "wof:name":"Southern Timberwrights LLC",
    "wof:placetype":"venue"
},
  "geometry": {"coordinates":[-86.281069,34.400167],"type":"Point"}
}