{
  "type": "Feature",
  "properties": {
    "iso:country":"US",
    "sg:address":"7218 Greenfield Rd",
    "sg:city":"Montgomery",
    "sg:classifiers":[
        {
            "category":"Health Services",
            "subcategory":"Doctor",
            "type":"Services"
        }
    ],
    "sg:phone":"+1 334 270 0260",
    "sg:postcode":"36117",
    "sg:province":"AL",
    "sg:tags":[
        "physician"
    ],
    "wof:name":"Calvin R Johns Jr",
    "wof:placetype":"venue"
},
  "geometry": {"coordinates":[-86.16042899999999,32.394758],"type":"Point"}
}