{
  "type": "Feature",
  "properties": {
    "iso:country":"US",
    "sg:address":"114 Harrand Creek Dr",
    "sg:city":"Enterprise",
    "sg:classifiers":[
        {
            "category":"Building & Trades",
            "subcategory":"Cleaning & Sanitation",
            "type":"Services"
        }
    ],
    "sg:phone":"+1 334 393 4574",
    "sg:postcode":"36330",
    "sg:province":"AL",
    "sg:tags":[
        "maintenance"
    ],
    "wof:name":"B N Enterprises",
    "wof:placetype":"venue"
},
  "geometry": {"coordinates":[-85.819583,31.337757],"type":"Point"}
}