{
  "type": "Feature",
  "properties": {
    "iso:country":"US",
    "sg:address":"6404 State Rte 69",
    "sg:city":"Tuscaloosa",
    "sg:classifiers":[
        {
            "category":"Professional",
            "subcategory":"Accounting & Tax Preparation",
            "type":"Services"
        }
    ],
    "sg:phone":"+1 205 344 4424",
    "sg:postcode":"35405",
    "sg:province":"AL",
    "wof:name":"Ward Skelton Services",
    "wof:placetype":"venue"
},
  "geometry": {"coordinates":[-87.54615,33.149667],"type":"Point"}
}