{
  "type": "Feature",
  "properties": {
    "addr:full":"2140 Wenonah Oxmoor Rd Birmingham AL 35211",
    "addr:housenumber":"2140",
    "addr:postcode":"35211",
    "addr:street":"Wenonah Oxmoor Rd",
    "iso:country":"US",
    "sg:address":"2140 Wenonah Oxmoor Rd",
    "sg:city":"Birmingham",
    "sg:classifiers":[
        {
            "category":"Freight",
            "type":"Transportation"
        }
    ],
    "sg:phone":"+1 205 942 9477",
    "sg:postcode":"35211",
    "sg:province":"AL",
    "sg:tags":[
        "storage"
    ],
    "wof:name":"Coggins Mini Storage",
    "wof:placetype":"venue"
},
  "geometry": {"coordinates":[-86.871448,33.435321],"type":"Point"}
}