{
  "type": "Feature",
  "properties": {
    "iso:country":"US",
    "sg:address":"46615 US Hwy 280",
    "sg:city":"Sylacauga",
    "sg:classifiers":[
        {
            "category":"Shopping",
            "type":"Retail Goods"
        }
    ],
    "sg:phone":"+1 256 245 8116",
    "sg:postcode":"35150",
    "sg:province":"AL",
    "sg:tags":[
        "product",
        "wood"
    ],
    "wof:name":"C & C Wood Products LLC",
    "wof:placetype":"venue"
},
  "geometry": {"coordinates":[-86.23438,33.111475],"type":"Point"}
}