{
  "type": "Feature",
  "properties": {
    "iso:country":"US",
    "sg:address":"3101 Kauloosa Ave",
    "sg:city":"Tuscaloosa",
    "sg:classifiers":[
        {
            "category":"Home & Garden",
            "subcategory":"Furniture",
            "type":"Retail Goods"
        }
    ],
    "sg:phone":"+1 205 345 4800",
    "sg:postcode":"35401",
    "sg:province":"AL",
    "sg:tags":[
        "equipment",
        "kitchen",
        "cabinet"
    ],
    "sg:website":"www.montgomerywoodworks.com",
    "wof:name":"Montgomery Woodworks Inc",
    "wof:placetype":"venue"
},
  "geometry": {"coordinates":[-87.56282299999999,33.181878],"type":"Point"}
}