{
  "type": "Feature",
  "properties": {
    "iso:country":"US",
    "sg:address":"2248 Co Rd 1659",
    "sg:city":"Cullman",
    "sg:classifiers":[
        {
            "category":"Banks & Credit Unions",
            "subcategory":"Financial Services",
            "type":"Services"
        }
    ],
    "sg:phone":"+1 256 796 5673",
    "sg:postcode":"35058",
    "sg:province":"AL",
    "sg:tags":[
        "it",
        "investment"
    ],
    "wof:name":"G & G Investments LLC",
    "wof:placetype":"venue"
},
  "geometry": {"coordinates":[-86.66980100000001,34.223558],"type":"Point"}
}