{
  "type": "Feature",
  "properties": {
    "addr:full":"1976 Posey Rd Gadsden AL 35903",
    "addr:housenumber":"1976",
    "addr:postcode":"35903",
    "addr:street":"Posey Rd",
    "iso:country":"US",
    "sg:address":"1976 Posey Rd",
    "sg:city":"Gadsden",
    "sg:classifiers":[
        {
            "category":"Retail",
            "subcategory":"Repair Shop",
            "type":"Services"
        }
    ],
    "sg:phone":"+1 256 492 0629",
    "sg:postcode":"35903",
    "sg:province":"AL",
    "sg:tags":[
        "equipment"
    ],
    "wof:name":"Total PM Refrigeration Inc",
    "wof:placetype":"venue"
},
  "geometry": {"coordinates":[-85.839974,34.014276],"type":"Point"}
}