{
  "type": "Feature",
  "properties": {
    "iso:country":"US",
    "sg:address":"309 S 6th St",
    "sg:city":"Gadsden",
    "sg:classifiers":[
        {
            "category":"Organizations",
            "subcategory":"Community Association",
            "type":"Services"
        }
    ],
    "sg:phone":"+1 256 549 1198",
    "sg:postcode":"35901",
    "sg:province":"AL",
    "sg:tags":[
        "fraternal"
    ],
    "wof:name":"Gadsden Fraternal Order-Police",
    "wof:placetype":"venue"
},
  "geometry": {"coordinates":[-86.008377,34.010422],"type":"Point"}
}