{
  "type": "Feature",
  "properties": {
    "addr:full":"400 S Washington St Tuscumbia AL 35674",
    "addr:housenumber":"400",
    "addr:postcode":"35674",
    "addr:street":"S Washington St",
    "iso:country":"US",
    "sg:address":"400 S Washington St",
    "sg:city":"Tuscumbia",
    "sg:classifiers":[
        {
            "category":"Retail",
            "subcategory":"Funeral Services",
            "type":"Services"
        }
    ],
    "sg:phone":"+1 256 383 2402",
    "sg:postcode":"35674",
    "sg:province":"AL",
    "sg:tags":[
        "director"
    ],
    "wof:name":"Thompson & Son Funeral Home",
    "wof:placetype":"venue"
},
  "geometry": {"coordinates":[-87.696437,34.728276],"type":"Point"}
}