{
  "type": "Feature",
  "properties": {
    "iso:country":"US",
    "sg:address":"2324 Trenton Dr",
    "sg:city":"Tuscaloosa",
    "sg:classifiers":[
        {
            "category":"Travel",
            "subcategory":"Travel Agent",
            "type":"Entertainment"
        }
    ],
    "sg:phone":"+1 205 752 4374",
    "sg:postcode":"35406",
    "sg:province":"AL",
    "sg:tags":[
        "operator",
        "tour",
        "agency",
        "bureau"
    ],
    "wof:name":"Watkins Travel & Tour LLC",
    "wof:placetype":"venue"
},
  "geometry": {"coordinates":[-87.525597,33.239254],"type":"Point"}
}