{
  "type": "Feature",
  "properties": {
    "addr:full":"12 Sharon Ave Courtland AL 35618",
    "addr:housenumber":"12",
    "addr:postcode":"35618",
    "addr:street":"Sharon Ave",
    "iso:country":"US",
    "sg:address":"12 Sharon Ave",
    "sg:city":"Courtland",
    "sg:classifiers":[
        {
            "category":"Arts & Performance",
            "subcategory":"Theater",
            "type":"Entertainment"
        }
    ],
    "sg:phone":"+1 256 637 2778",
    "sg:postcode":"35618",
    "sg:province":"AL",
    "sg:tags":[
        "group"
    ],
    "wof:name":"Alabama Blues Brothers",
    "wof:placetype":"venue"
},
  "geometry": {"coordinates":[-87.288909,34.661829],"type":"Point"}
}