{
  "type": "Feature",
  "properties": {
    "iso:country":"US",
    "sg:address":"3682 Hobbs Island Rd SE",
    "sg:city":"Huntsville",
    "sg:classifiers":[
        {
            "category":"Retail",
            "subcategory":"Repair Shop",
            "type":"Services"
        }
    ],
    "sg:phone":"+1 256 725 5144",
    "sg:postcode":"35803",
    "sg:province":"AL",
    "sg:tags":[
        "body",
        "auto"
    ],
    "wof:name":"Alabama Custom Cycles",
    "wof:placetype":"venue"
},
  "geometry": {"coordinates":[-86.479788,34.541475],"type":"Point"}
}