{
  "type": "Feature",
  "properties": {
    "iso:country":"US",
    "sg:address":"301 W Jeff Davis Ave",
    "sg:city":"Montgomery",
    "sg:classifiers":[
        {
            "category":"Organizations",
            "subcategory":"Religious Organization",
            "type":"Services"
        }
    ],
    "sg:phone":"+1 334 263 7922",
    "sg:postcode":"36104",
    "sg:province":"AL",
    "wof:name":"Faith Crusades Haven",
    "wof:placetype":"venue"
},
  "geometry": {"coordinates":[-86.31300299999999,32.366174],"type":"Point"}
}