{
  "type": "Feature",
  "properties": {
    "iso:country":"US",
    "sg:address":"1148 11th Ave S",
    "sg:city":"Birmingham",
    "sg:classifiers":[
        {
            "category":"Restaurant",
            "type":"Food & Drink"
        }
    ],
    "sg:phone":"+1 205 326 2832",
    "sg:postcode":"35205",
    "sg:province":"AL",
    "wof:name":"Little Island Cafe",
    "wof:placetype":"venue"
},
  "geometry": {"coordinates":[-86.809947,33.494833],"type":"Point"}
}