{
  "type": "Feature",
  "properties": {
    "addr:full":"6001 Monticello Dr Montgomery AL 36117",
    "addr:housenumber":"6001",
    "addr:postcode":"36117",
    "addr:street":"Monticello Dr",
    "iso:country":"US",
    "sg:address":"6001 Monticello Dr",
    "sg:city":"Montgomery",
    "sg:classifiers":[
        {
            "category":"Communications",
            "subcategory":"Film & Video Production",
            "type":"Services"
        }
    ],
    "sg:phone":"+1 334 274 9155",
    "sg:postcode":"36117",
    "sg:province":"AL",
    "sg:tags":[
        "motion"
    ],
    "wof:name":"Whisper Video Productions",
    "wof:placetype":"venue"
},
  "geometry": {"coordinates":[-86.20513200000001,32.365412],"type":"Point"}
}