{
  "type": "Feature",
  "properties": {
    "addr:full":"12631 Covered Bridge Rd Brookwood AL 35444",
    "addr:housenumber":"12631",
    "addr:postcode":"35444",
    "addr:street":"Covered Bridge Rd",
    "iso:country":"US",
    "sg:address":"12631 Covered Bridge Rd",
    "sg:city":"Brookwood",
    "sg:classifiers":[
        {
            "category":"Home & Garden",
            "subcategory":"Hardware",
            "type":"Retail Goods"
        }
    ],
    "sg:phone":"+1 205 556 8500",
    "sg:postcode":"35444",
    "sg:province":"AL",
    "wof:name":"Ken's General Store",
    "wof:placetype":"venue"
},
  "geometry": {"coordinates":[-87.32285899999999,33.240743],"type":"Point"}
}