{
  "type": "Feature",
  "properties": {
    "addr:full":"1619 Weldon Rd Tallassee AL 36078",
    "addr:housenumber":"1619",
    "addr:postcode":"36078",
    "addr:street":"Weldon Rd",
    "iso:country":"US",
    "sg:address":"1619 Weldon Rd",
    "sg:city":"Tallassee",
    "sg:classifiers":[
        {
            "category":"Building & Trades",
            "subcategory":"Construction",
            "type":"Services"
        }
    ],
    "sg:phone":"+1 334 283 6629",
    "sg:postcode":"36078",
    "sg:province":"AL",
    "sg:tags":[
        "house"
    ],
    "wof:name":"Corbin Home Maint Aaron",
    "wof:placetype":"venue"
},
  "geometry": {"coordinates":[-85.93440699999999,32.5872],"type":"Point"}
}