{
  "type": "Feature",
  "properties": {
    "iso:country":"US",
    "sg:address":"453 Mobile St",
    "sg:city":"Mobile",
    "sg:classifiers":[
        {
            "category":"Retail",
            "subcategory":"Auto Repair",
            "type":"Services"
        }
    ],
    "sg:phone":"+1 251 471 9360",
    "sg:postcode":"36607",
    "sg:province":"AL",
    "sg:tags":[
        "body",
        "automobile",
        "painting"
    ],
    "wof:name":"Mitchell's Paint & Body",
    "wof:placetype":"venue"
},
  "geometry": {"coordinates":[-88.103075,30.702825],"type":"Point"}
}