{
  "type": "Feature",
  "properties": {
    "iso:country":"US",
    "sg:address":"135 Refreshment Pl",
    "sg:city":"Decatur",
    "sg:classifiers":[
        {
            "category":"Building & Trades",
            "subcategory":"Electrical",
            "type":"Services"
        }
    ],
    "sg:phone":"+1 256 350 5057",
    "sg:postcode":"35601",
    "sg:province":"AL",
    "sg:tags":[
        "electric",
        "contractor"
    ],
    "wof:name":"North Alabama Electric",
    "wof:placetype":"venue"
},
  "geometry": {"coordinates":[-87.038088,34.610352],"type":"Point"}
}