{
  "type": "Feature",
  "properties": {
    "addr:full":"4136 Co Rd 71 Killen AL 35645",
    "addr:housenumber":"4136;71",
    "addr:postcode":"35645",
    "addr:street":"Co Rd",
    "iso:country":"US",
    "sg:address":"4136 Co Rd 71",
    "sg:city":"Killen",
    "sg:classifiers":[
        {
            "category":"Retail",
            "subcategory":"Animal Services",
            "type":"Services"
        }
    ],
    "sg:phone":"+1 256 757 8602",
    "sg:postcode":"35645",
    "sg:province":"AL",
    "sg:tags":[
        "pet",
        "grooming",
        "washing"
    ],
    "wof:name":"Claire's Canine Care",
    "wof:placetype":"venue"
},
  "geometry": {"coordinates":[-87.467589,34.898001],"type":"Point"}
}