{
  "type": "Feature",
  "properties": {
    "addr:full":"2502 University Blvd E Tuscaloosa AL 35404",
    "addr:housenumber":"2502",
    "addr:postcode":"35404",
    "addr:street":"University Blvd E",
    "iso:country":"US",
    "sg:address":"2502 University Blvd E",
    "sg:city":"Tuscaloosa",
    "sg:classifiers":[
        {
            "category":"Autos & Motor Vehicles",
            "subcategory":"Fuel & Gas Station",
            "type":"Retail Goods"
        }
    ],
    "sg:phone":"+1 205 556 4821",
    "sg:postcode":"35404",
    "sg:province":"AL",
    "sg:tags":[
        "oil"
    ],
    "wof:name":"Shell",
    "wof:placetype":"venue"
},
  "geometry": {"coordinates":[-87.50404,33.206456],"type":"Point"}
}