{
  "type": "Feature",
  "properties": {
    "iso:country":"US",
    "sg:address":"5950 Chalkville Rd Ste 102",
    "sg:city":"Birmingham",
    "sg:classifiers":[
        {
            "category":"Shopping",
            "subcategory":"Mobile Phones",
            "type":"Retail Goods"
        }
    ],
    "sg:phone":"+1 205 655 5188",
    "sg:postcode":"35235",
    "sg:province":"AL",
    "wof:name":"Radioshack",
    "wof:placetype":"venue"
},
  "geometry": {"coordinates":[-86.62249799999999,33.640099],"type":"Point"}
}