{
  "type": "Feature",
  "properties": {
    "iso:country":"US",
    "sg:address":"1309 Ave C SE",
    "sg:city":"Cullman",
    "sg:classifiers":[
        {
            "category":"Real Estate",
            "subcategory":"Real Estate Operator",
            "type":"Services"
        }
    ],
    "sg:phone":"+1 256 735 1075",
    "sg:postcode":"35055",
    "sg:province":"AL",
    "sg:tags":[
        "apartment"
    ],
    "wof:name":"Topre",
    "wof:placetype":"venue"
},
  "geometry": {"coordinates":[-86.828109,34.167789],"type":"Point"}
}