{
  "type": "Feature",
  "properties": {
    "iso:country":"US",
    "sg:address":"270 W Cook Rd",
    "sg:city":"Dothan",
    "sg:classifiers":[
        {
            "category":"Autos & Motor Vehicles",
            "subcategory":"Auto Supplies",
            "type":"Retail Goods"
        }
    ],
    "sg:phone":"+1 334 794 1112",
    "sg:postcode":"36301",
    "sg:province":"AL",
    "wof:name":"Taylors Tire & Cylinder Head",
    "wof:placetype":"venue"
},
  "geometry": {"coordinates":[-85.472596,31.157475],"type":"Point"}
}