{
  "type": "Feature",
  "properties": {
    "iso:country":"US",
    "sg:address":"662 Springhill Ave",
    "sg:city":"Mobile",
    "sg:classifiers":[
        {
            "category":"Insurance",
            "subcategory":"Insurance Agent",
            "type":"Services"
        }
    ],
    "sg:phone":"+1 251 433 3111",
    "sg:postcode":"36602",
    "sg:province":"AL",
    "wof:name":"Farmers Insurance Group",
    "wof:placetype":"venue"
},
  "geometry": {"coordinates":[-88.050875,30.688881],"type":"Point"}
}