{
  "type": "Feature",
  "properties": {
    "iso:country":"US",
    "sg:address":"513 3rd St SE",
    "sg:city":"Aliceville",
    "sg:classifiers":[
        {
            "category":"Farming",
            "subcategory":"Farm",
            "type":"Manufacturing & Wholesale Goods"
        }
    ],
    "sg:phone":"+1 205 373 2286",
    "sg:postcode":"35442",
    "sg:province":"AL",
    "sg:tags":[
        "crop",
        "general"
    ],
    "wof:name":"Parker Farming Company",
    "wof:placetype":"venue"
},
  "geometry": {"coordinates":[-88.148839,33.122271],"type":"Point"}
}