{
  "type": "Feature",
  "properties": {
    "iso:country":"US",
    "sg:address":"22301 Cain Rd",
    "sg:city":"Silverhill",
    "sg:classifiers":[
        {
            "category":"Building & Trades",
            "subcategory":"Construction",
            "type":"Services"
        }
    ],
    "sg:phone":"+1 251 945 1661",
    "sg:postcode":"36576",
    "sg:province":"AL",
    "sg:tags":[
        "floor",
        "laying",
        "contractor"
    ],
    "wof:name":"Family Ceramic Tile & Stone",
    "wof:placetype":"venue"
},
  "geometry": {"coordinates":[-87.776855,30.551015],"type":"Point"}
}