{
  "type": "Feature",
  "properties": {
    "iso:country":"US",
    "sg:address":"6055 Evelyn Rd",
    "sg:city":"Pinson",
    "sg:classifiers":[
        {
            "category":"Organizations",
            "subcategory":"Religious Organization",
            "type":"Services"
        }
    ],
    "sg:phone":"+1 205 680 0589",
    "sg:postcode":"35126",
    "sg:province":"AL",
    "wof:name":"Hagood Chapel Baptist Church",
    "wof:placetype":"venue"
},
  "geometry": {"coordinates":[-86.65445,33.681959],"type":"Point"}
}