{
  "type": "Feature",
  "properties": {
    "iso:country":"US",
    "sg:address":"200 S Lawrence St",
    "sg:city":"Montgomery",
    "sg:classifiers":[
        {
            "category":"Professional",
            "type":"Services"
        }
    ],
    "sg:phone":"+1 334 240 2421",
    "sg:postcode":"36104",
    "sg:province":"AL",
    "wof:name":"Debray Hendon",
    "wof:placetype":"venue"
},
  "geometry": {"coordinates":[-86.30618800000001,32.375719],"type":"Point"}
}