{
  "type": "Feature",
  "properties": {
    "iso:country":"US",
    "sg:address":"18045 State Hwy 160",
    "sg:city":"Cleveland",
    "sg:classifiers":[
        {
            "category":"Banks & Credit Unions",
            "subcategory":"Bank",
            "type":"Services"
        }
    ],
    "sg:phone":"+1 205 274 8054",
    "sg:postcode":"35049",
    "sg:province":"AL",
    "wof:name":"Community Bank",
    "wof:placetype":"venue"
},
  "geometry": {"coordinates":[-86.581748,33.987617],"type":"Point"}
}