{
  "type": "Feature",
  "properties": {
    "addr:full":"616 Chastain Blvd W Gadsden AL 35905",
    "addr:housenumber":"616",
    "addr:postcode":"35905",
    "addr:street":"Chastain Blvd W",
    "iso:country":"US",
    "sg:address":"616 Chastain Blvd W",
    "sg:city":"Gadsden",
    "sg:classifiers":[
        {
            "category":"Restaurant",
            "type":"Food & Drink"
        }
    ],
    "sg:menulink":"http://www.allmenus.com/al/gadsden/190185-mcdonalds/menu/",
    "sg:postcode":"35905",
    "sg:province":"AL",
    "sg:tags":[
        "burger",
        "american"
    ],
    "wof:name":"McDonald's",
    "wof:placetype":"venue"
},
  "geometry": {"coordinates":[-85.941923,33.965227],"type":"Point"}
}