{
  "type": "Feature",
  "properties": {
    "addr:full":"26835 Nick Davis Rd Athens AL 35613",
    "addr:postcode":"26835;35613",
    "addr:street":"Nick Davis Rd",
    "iso:country":"US",
    "sg:address":"26835 Nick Davis Rd",
    "sg:city":"Athens",
    "sg:classifiers":[
        {
            "category":"Retail",
            "subcategory":"Repair Shop",
            "type":"Services"
        },
        {
            "category":"Wholesale",
            "subcategory":"Electrical",
            "type":"Manufacturing & Wholesale Goods"
        }
    ],
    "sg:phone":"+1 256 232 1118",
    "sg:postcode":"35613",
    "sg:province":"AL",
    "sg:tags":[
        "generator"
    ],
    "wof:name":"Pettie Maintenance Co",
    "wof:placetype":"venue"
},
  "geometry": {"coordinates":[-86.848713,34.802992],"type":"Point"}
}