{
  "type": "Feature",
  "properties": {
    "iso:country":"US",
    "sg:address":"9225 Bridge Pointe",
    "sg:city":"Montgomery",
    "sg:classifiers":[
        {
            "category":"Recreation",
            "type":"Entertainment"
        }
    ],
    "sg:phone":"+1 334 215 7128",
    "sg:postcode":"36117",
    "sg:province":"AL",
    "wof:name":"Monster Mountain Inc",
    "wof:placetype":"venue"
},
  "geometry": {"coordinates":[-86.13406,32.376428],"type":"Point"}
}