{
  "type": "Feature",
  "properties": {
    "iso:country":"US",
    "sg:address":"1033 2nd Ave NE",
    "sg:city":"Fayette",
    "sg:classifiers":[
        {
            "category":"Manufacturing",
            "subcategory":"Printing",
            "type":"Manufacturing & Wholesale Goods"
        }
    ],
    "sg:phone":"+1 205 932 7389",
    "sg:postcode":"35555",
    "sg:province":"AL",
    "sg:tags":[
        "lithographic",
        "b",
        "commercial",
        "typesetting"
    ],
    "wof:name":"Tl Printing",
    "wof:placetype":"venue"
},
  "geometry": {"coordinates":[-87.828578,33.697304],"type":"Point"}
}