{
  "type": "Feature",
  "properties": {
    "iso:country":"US",
    "sg:address":"2353 Carson Rd",
    "sg:city":"Birmingham",
    "sg:classifiers":[
        {
            "category":"Building & Trades",
            "subcategory":"Construction",
            "type":"Services"
        }
    ],
    "sg:phone":"+1 205 815 5306",
    "sg:postcode":"35215",
    "sg:province":"AL",
    "sg:tags":[
        "house"
    ],
    "wof:name":"Home Investment and Cnstr",
    "wof:placetype":"venue"
},
  "geometry": {"coordinates":[-86.708689,33.645029],"type":"Point"}
}