{
  "type": "Feature",
  "properties": {
    "addr:full":"462 S Union St Montgomery AL 36104",
    "addr:housenumber":"462",
    "addr:postcode":"36104",
    "addr:street":"S Union St",
    "iso:country":"US",
    "sg:address":"462 S Union St",
    "sg:city":"Montgomery",
    "sg:classifiers":[
        {
            "category":"Organizations",
            "subcategory":"Professional Association",
            "type":"Services"
        }
    ],
    "sg:phone":"+1 334 834 9707",
    "sg:postcode":"36104",
    "sg:province":"AL",
    "wof:name":"Alabama Petroleum Council",
    "wof:placetype":"venue"
},
  "geometry": {"coordinates":[-86.29950100000001,32.372299],"type":"Point"}
}