{
  "type": "Feature",
  "properties": {
    "addr:full":"89 S Main St Goodwater AL 35072",
    "addr:housenumber":"89",
    "addr:postcode":"35072",
    "addr:street":"S Main St",
    "iso:country":"US",
    "sg:address":"89 S Main St",
    "sg:city":"Goodwater",
    "sg:classifiers":[
        {
            "category":"Personal",
            "subcategory":"Beauty Salon",
            "type":"Services"
        }
    ],
    "sg:phone":"+1 256 839 0000",
    "sg:postcode":"35072",
    "sg:province":"AL",
    "wof:name":"Sandra's Beauty & Fashion Shop",
    "wof:placetype":"venue"
},
  "geometry": {"coordinates":[-86.054856,33.054228],"type":"Point"}
}