{
  "type": "Feature",
  "properties": {
    "iso:country":"US",
    "sg:address":"1000 Eagle Point Corporate Dr",
    "sg:city":"Birmingham",
    "sg:classifiers":[
        {
            "category":"Building & Trades",
            "subcategory":"Construction",
            "type":"Services"
        }
    ],
    "sg:phone":"+1 205 408 1003",
    "sg:postcode":"35242",
    "sg:province":"AL",
    "sg:tags":[
        "house"
    ],
    "wof:name":"Benson Custom Homes Inc",
    "wof:placetype":"venue"
},
  "geometry": {"coordinates":[-86.66563,33.399884],"type":"Point"}
}