{
  "type": "Feature",
  "properties": {
    "iso:country":"US",
    "sg:address":"3440 Argonne Rd",
    "sg:city":"Duncanville",
    "sg:classifiers":[
        {
            "category":"Retail",
            "subcategory":"Repair Shop",
            "type":"Services"
        }
    ],
    "sg:phone":"+1 205 752 6373",
    "sg:postcode":"35456",
    "sg:province":"AL",
    "sg:tags":[
        "welding"
    ],
    "wof:name":"T and T Welding",
    "wof:placetype":"venue"
},
  "geometry": {"coordinates":[-87.499328,33.128571],"type":"Point"}
}