{
  "type": "Feature",
  "properties": {
    "iso:country":"US",
    "sg:address":"525 Co Rd 86",
    "sg:city":"Collinsville",
    "sg:classifiers":[
        {
            "category":"Freight",
            "type":"Transportation"
        }
    ],
    "sg:phone":"+1 256 524 2004",
    "sg:postcode":"35961",
    "sg:province":"AL",
    "sg:tags":[
        "operator",
        "local",
        "trucking"
    ],
    "wof:name":"Phillip Myers Trucking",
    "wof:placetype":"venue"
},
  "geometry": {"coordinates":[-85.901332,34.291355],"type":"Point"}
}