{
  "type": "Feature",
  "properties": {
    "iso:country":"US",
    "sg:address":"22 Norman Dr",
    "sg:city":"Birmingham",
    "sg:classifiers":[
        {
            "category":"Wholesale",
            "subcategory":"Machinery & Supplies",
            "type":"Manufacturing & Wholesale Goods"
        }
    ],
    "sg:phone":"+1 205 821 4498",
    "sg:postcode":"35213",
    "sg:province":"AL",
    "sg:tags":[
        "equipment",
        "industrial"
    ],
    "wof:name":"Alabama Air Filter",
    "wof:placetype":"venue"
},
  "geometry": {"coordinates":[-86.75919500000001,33.490577],"type":"Point"}
}