{
  "type": "Feature",
  "properties": {
    "addr:full":"501 16th Pl Opelika AL 36801",
    "addr:housenumber":"501",
    "addr:postcode":"36801",
    "addr:street":"16Th Pl",
    "iso:country":"US",
    "sg:address":"501 16th Pl",
    "sg:city":"Opelika",
    "sg:classifiers":[
        {
            "category":"Professional",
            "subcategory":"Business Services",
            "type":"Services"
        }
    ],
    "sg:phone":"+1 334 705 0712",
    "sg:postcode":"36801",
    "sg:province":"AL",
    "sg:tags":[
        "textile",
        "representative"
    ],
    "wof:name":"Complete Textile Mfg",
    "wof:placetype":"venue"
},
  "geometry": {"coordinates":[-85.39767999999999,32.642964],"type":"Point"}
}