{
  "type": "Feature",
  "properties": {
    "iso:country":"US",
    "sg:address":"607 Candle Ln",
    "sg:city":"Birmingham",
    "sg:classifiers":[
        {
            "category":"Organizations",
            "subcategory":"Religious Organization",
            "type":"Services"
        }
    ],
    "sg:phone":"+1 205 798 0979",
    "sg:postcode":"35214",
    "sg:province":"AL",
    "wof:name":"Jimmy L Burton Rev",
    "wof:placetype":"venue"
},
  "geometry": {"coordinates":[-86.865565,33.541451],"type":"Point"}
}