{
  "type": "Feature",
  "properties": {
    "addr:full":"2 Mcfarland Blvd Northport AL 35476",
    "addr:housenumber":"2",
    "addr:postcode":"35476",
    "addr:street":"Mcfarland Blvd",
    "iso:country":"US",
    "sg:address":"2 Mcfarland Blvd",
    "sg:city":"Northport",
    "sg:classifiers":[
        {
            "category":"Ice Cream",
            "type":"Food & Drink"
        }
    ],
    "sg:menulink":"http://www.allmenus.com/al/northport/208836-tcby/menu/",
    "sg:phone":"+1 205 758 6855",
    "sg:postcode":"35476",
    "sg:province":"AL",
    "sg:tags":[
        "smoothy",
        "juice",
        "american"
    ],
    "wof:name":"TCBY",
    "wof:placetype":"venue"
},
  "geometry": {"coordinates":[-87.559682,33.236899],"type":"Point"}
}