{
  "type": "Feature",
  "properties": {
    "addr:full":"1817 Montgomery Hwy Birmingham AL 35244",
    "addr:housenumber":"1817",
    "addr:postcode":"35244",
    "addr:street":"Montgomery Hwy",
    "iso:country":"US",
    "sg:address":"1817 Montgomery Hwy",
    "sg:city":"Birmingham",
    "sg:classifiers":[
        {
            "category":"Restaurant",
            "type":"Food & Drink"
        }
    ],
    "sg:phone":"+1 205 733 1142",
    "sg:postcode":"35244",
    "sg:province":"AL",
    "sg:tags":[
        "eating"
    ],
    "wof:name":"Guthries Restaurant Hoover",
    "wof:placetype":"venue"
},
  "geometry": {"coordinates":[-86.795119,33.349715],"type":"Point"}
}