{
  "type": "Feature",
  "properties": {
    "addr:full":"3414 9th Ave SW Huntsville AL 35805",
    "addr:housenumber":"3414",
    "addr:postcode":"35805",
    "addr:street":"9Th Ave Sw",
    "iso:country":"US",
    "sg:address":"3414 9th Ave SW",
    "sg:city":"Huntsville",
    "sg:classifiers":[
        {
            "category":"Building & Trades",
            "subcategory":"Electrical",
            "type":"Services"
        }
    ],
    "sg:phone":"+1 256 533 7730",
    "sg:postcode":"35805",
    "sg:province":"AL",
    "sg:tags":[
        "general",
        "electrical",
        "contractor"
    ],
    "wof:name":"Jesse Stutts Inc",
    "wof:placetype":"venue"
},
  "geometry": {"coordinates":[-86.613124,34.71588],"type":"Point"}
}