{
  "type": "Feature",
  "properties": {
    "iso:country":"US",
    "sg:address":"7511 Moffett Rd",
    "sg:city":"Mobile",
    "sg:classifiers":[
        {
            "category":"Food & Beverages",
            "subcategory":"Liquor & Beverages",
            "type":"Retail Goods"
        }
    ],
    "sg:phone":"+1 251 649 1210",
    "sg:postcode":"36618",
    "sg:province":"AL",
    "wof:name":"Moffat Road Package Store",
    "wof:placetype":"venue"
},
  "geometry": {"coordinates":[-88.222766,30.759529],"type":"Point"}
}