{
  "type": "Feature",
  "properties": {
    "iso:country":"US",
    "sg:address":"449 Fish Hatchery Ln",
    "sg:city":"Eastaboga",
    "sg:classifiers":[
        {
            "category":"Professional",
            "subcategory":"Management & Consulting",
            "type":"Services"
        }
    ],
    "sg:phone":"+1 256 831 2415",
    "sg:postcode":"36260",
    "sg:province":"AL",
    "wof:name":"Hanvey Enterprise",
    "wof:placetype":"venue"
},
  "geometry": {"coordinates":[-86.003716,33.60621],"type":"Point"}
}