{
  "type": "Feature",
  "properties": {
    "addr:full":"365 W Cotton Rd Eclectic AL 36024",
    "addr:housenumber":"365",
    "addr:postcode":"36024",
    "addr:street":"W Cotton Rd",
    "iso:country":"US",
    "sg:address":"365 W Cotton Rd",
    "sg:city":"Eclectic",
    "sg:classifiers":[
        {
            "category":"Building & Trades",
            "subcategory":"Construction",
            "type":"Services"
        }
    ],
    "sg:phone":"+1 334 541 2741",
    "sg:postcode":"36024",
    "sg:province":"AL",
    "sg:tags":[
        "concrete",
        "carpentry",
        "contractor"
    ],
    "wof:name":"Patterson Concrete",
    "wof:placetype":"venue"
},
  "geometry": {"coordinates":[-86.02487499999999,32.695389],"type":"Point"}
}