{
  "type": "Feature",
  "properties": {
    "iso:country":"US",
    "sg:address":"365 W Cotton Rd",
    "sg:city":"Eclectic",
    "sg:classifiers":[
        {
            "category":"Building & Trades",
            "subcategory":"Construction",
            "type":"Services"
        }
    ],
    "sg:phone":"+1 334 541 2741",
    "sg:postcode":"36024",
    "sg:province":"AL",
    "sg:tags":[
        "concrete",
        "carpentry",
        "contractor"
    ],
    "wof:name":"Patterson Concrete",
    "wof:placetype":"venue"
},
  "geometry": {"coordinates":[-86.024875,32.695389],"type":"Point"}
}