{
  "type": "Feature",
  "properties": {
    "iso:country":"US",
    "sg:address":"1535 Graymont Ave W",
    "sg:city":"Birmingham",
    "sg:classifiers":[
        {
            "category":"Personal",
            "subcategory":"Beauty Salon",
            "type":"Services"
        }
    ],
    "sg:phone":"+1 205 786 1696",
    "sg:postcode":"35208",
    "sg:province":"AL",
    "sg:tags":[
        "shop"
    ],
    "wof:name":"Lessentials Hair Salon Inc",
    "wof:placetype":"venue"
},
  "geometry": {"coordinates":[-86.863342,33.513019],"type":"Point"}
}