{
  "type": "Feature",
  "properties": {
    "addr:full":"7080 Sydney Curve Montgomery AL 36117",
    "addr:housenumber":"7080",
    "addr:postcode":"36117",
    "addr:street":"Sydney Curve",
    "iso:country":"US",
    "sg:address":"7080 Sydney Curve",
    "sg:city":"Montgomery",
    "sg:classifiers":[
        {
            "category":"Health Services",
            "subcategory":"Doctor",
            "type":"Services"
        }
    ],
    "sg:phone":"+1 334 215 3971",
    "sg:postcode":"36117",
    "sg:province":"AL",
    "sg:tags":[
        "physician",
        "surgeon"
    ],
    "wof:name":"Paul A Corbier MD LLC",
    "wof:placetype":"venue"
},
  "geometry": {"coordinates":[-86.17108399999999,32.373561],"type":"Point"}
}