{
  "type": "Feature",
  "properties": {
    "iso:country":"US",
    "sg:address":"2108 5th Ave N",
    "sg:city":"Bessemer",
    "sg:classifiers":[
        {
            "category":"Retail",
            "subcategory":"Auto Repair",
            "type":"Services"
        }
    ],
    "sg:phone":"+1 205 426 6881",
    "sg:postcode":"35020",
    "sg:province":"AL",
    "sg:tags":[
        "body"
    ],
    "wof:name":"Quality Auto Body",
    "wof:placetype":"venue"
},
  "geometry": {"coordinates":[-86.953014,33.407051],"type":"Point"}
}