{
  "type": "Feature",
  "properties": {
    "addr:full":"7750 1st Ave N Birmingham AL 35206",
    "addr:housenumber":"7750",
    "addr:postcode":"35206",
    "addr:street":"1St Ave N",
    "iso:country":"US",
    "sg:address":"7750 1st Ave N",
    "sg:city":"Birmingham",
    "sg:classifiers":[
        {
            "category":"Home & Garden",
            "subcategory":"Garden Supply",
            "type":"Retail Goods"
        }
    ],
    "sg:phone":"+1 205 251 5336",
    "sg:postcode":"35206",
    "sg:province":"AL",
    "sg:tags":[
        "nursery",
        "gardening"
    ],
    "wof:name":"Massey Mercantile Co",
    "wof:placetype":"venue"
},
  "geometry": {"coordinates":[-86.72806199999999,33.563265],"type":"Point"}
}