{
  "type": "Feature",
  "properties": {
    "addr:full":"3611 Old Scott Rd Blountsville AL 35031",
    "addr:housenumber":"3611",
    "addr:postcode":"35031",
    "addr:street":"Old Scott Rd",
    "iso:country":"US",
    "sg:address":"3611 Old Scott Rd",
    "sg:city":"Blountsville",
    "sg:classifiers":[
        {
            "category":"Building & Trades",
            "subcategory":"Construction",
            "type":"Services"
        }
    ],
    "sg:phone":"+1 205 429 4531",
    "sg:postcode":"35031",
    "sg:province":"AL",
    "sg:tags":[
        "excavation",
        "contractor"
    ],
    "wof:name":"Jones Greg Excavating",
    "wof:placetype":"venue"
},
  "geometry": {"coordinates":[-86.4873,34.129336],"type":"Point"}
}