{
  "type": "Feature",
  "properties": {
    "iso:country":"US",
    "sg:address":"2992 Spring Hill Ave",
    "sg:city":"Mobile",
    "sg:classifiers":[
        {
            "category":"Shopping",
            "subcategory":"Shoes",
            "type":"Retail Goods"
        }
    ],
    "sg:phone":"+1 251 473 2905",
    "sg:postcode":"36607",
    "sg:province":"AL",
    "wof:name":"Shoe Show 726",
    "wof:placetype":"venue"
},
  "geometry": {"coordinates":[-88.110778,30.699735],"type":"Point"}
}