{
  "type": "Feature",
  "properties": {
    "iso:country":"US",
    "sg:address":"1132 Dailey St",
    "sg:city":"Brewton",
    "sg:classifiers":[
        {
            "category":"Personal",
            "subcategory":"Beauty Salon",
            "type":"Services"
        }
    ],
    "sg:phone":"+1 251 867 2869",
    "sg:postcode":"36426",
    "sg:province":"AL",
    "wof:name":"Janice's Beauty Shop",
    "wof:placetype":"venue"
},
  "geometry": {"coordinates":[-87.044772,31.094147],"type":"Point"}
}