{
  "type": "Feature",
  "properties": {
    "iso:country":"US",
    "sg:address":"261 Co Rd 707",
    "sg:city":"Cullman",
    "sg:classifiers":[
        {
            "category":"Food & Beverages",
            "subcategory":"Groceries & Convenience Stores",
            "type":"Retail Goods"
        }
    ],
    "sg:phone":"+1 256 739 2126",
    "sg:postcode":"35055",
    "sg:province":"AL",
    "wof:name":"Mayo Smith Grocery",
    "wof:placetype":"venue"
},
  "geometry": {"coordinates":[-86.786051,34.160083],"type":"Point"}
}