{
  "type": "Feature",
  "properties": {
    "addr:full":"9238 Madison Blvd Madison AL 35758",
    "addr:housenumber":"9238",
    "addr:postcode":"35758",
    "addr:street":"Madison Blvd",
    "iso:country":"US",
    "sg:address":"9238 Madison Blvd",
    "sg:city":"Madison",
    "sg:classifiers":[
        {
            "category":"Professional",
            "subcategory":"Engineering",
            "type":"Services"
        },
        {
            "category":"Shopping",
            "subcategory":"Computers & Home Electronics",
            "type":"Retail Goods"
        }
    ],
    "sg:phone":"+1 256 461 1313",
    "sg:postcode":"35758",
    "sg:province":"AL",
    "sg:tags":[
        "manufacture",
        "develop",
        "supply",
        "equipment",
        "measurement",
        "electronic"
    ],
    "wof:name":"Origin Technologies Corp",
    "wof:placetype":"venue"
},
  "geometry": {"coordinates":[-86.759883,34.673463],"type":"Point"}
}