{
  "type": "Feature",
  "properties": {
    "iso:country":"US",
    "sg:address":"4838 Emerald Dr E",
    "sg:city":"Mobile",
    "sg:classifiers":[
        {
            "category":"Autos & Motor Vehicles",
            "subcategory":"Automobile Sales",
            "type":"Retail Goods"
        }
    ],
    "sg:phone":"+1 251 665 1391",
    "sg:postcode":"36619",
    "sg:province":"AL",
    "sg:tags":[
        "car",
        "dealer"
    ],
    "wof:name":"Creative Car Sales",
    "wof:placetype":"venue"
},
  "geometry": {"coordinates":[-88.202347,30.590472],"type":"Point"}
}