{
  "type": "Feature",
  "properties": {
    "iso:country":"US",
    "sg:address":"123 2nd Ave SE",
    "sg:city":"Decatur",
    "sg:classifiers":[
        {
            "category":"Shopping",
            "subcategory":"Gifts & Souvenirs",
            "type":"Retail Goods"
        }
    ],
    "sg:phone":"+1 256 351 1953",
    "sg:postcode":"35601",
    "sg:province":"AL",
    "wof:name":"Suprises Galore",
    "wof:placetype":"venue"
},
  "geometry": {"coordinates":[-86.985156,34.603117],"type":"Point"}
}