{
  "type": "Feature",
  "properties": {
    "addr:full":"2460 Wall St Millbrook AL 36054",
    "addr:housenumber":"2460",
    "addr:postcode":"36054",
    "addr:street":"Wall St",
    "iso:country":"US",
    "sg:address":"2460 Wall St",
    "sg:city":"Millbrook",
    "sg:classifiers":[
        {
            "category":"Shopping",
            "subcategory":"Clothing, Apparel, & Fashions",
            "type":"Retail Goods"
        }
    ],
    "sg:phone":"+1 334 285 9898",
    "sg:postcode":"36054",
    "sg:province":"AL",
    "sg:tags":[
        "uniform",
        "supply"
    ],
    "wof:name":"Uni First Corp",
    "wof:placetype":"venue"
},
  "geometry": {"coordinates":[-86.380516,32.45826],"type":"Point"}
}