{
  "type": "Feature",
  "properties": {
    "addr:full":"1550 Montgomery Hwy S Birmingham AL 35216",
    "addr:housenumber":"1550",
    "addr:postcode":"35216",
    "addr:street":"Montgomery Hwy S",
    "iso:country":"US",
    "sg:address":"1550 Montgomery Hwy S",
    "sg:city":"Birmingham",
    "sg:classifiers":[
        {
            "category":"Shopping",
            "subcategory":"Clothing, Apparel, & Fashions",
            "type":"Retail Goods"
        }
    ],
    "sg:phone":"+1 205 979 7726",
    "sg:postcode":"35216",
    "sg:province":"AL",
    "sg:tags":[
        "shop",
        "occasion",
        "bridal",
        "dress",
        "special"
    ],
    "wof:name":"David's Bridal",
    "wof:placetype":"venue"
},
  "geometry": {"coordinates":[-86.806742,33.409138],"type":"Point"}
}