{
  "type": "Feature",
  "properties": {
    "addr:full":"1003 E 3rd St Luverne AL 36049",
    "addr:housenumber":"1003",
    "addr:postcode":"36049",
    "addr:street":"E 3Rd St",
    "iso:country":"US",
    "sg:address":"1003 E 3rd St",
    "sg:city":"Luverne",
    "sg:classifiers":[
        {
            "category":"Shopping",
            "subcategory":"News",
            "type":"Retail Goods"
        }
    ],
    "sg:phone":"+1 334 335 4066",
    "sg:postcode":"36049",
    "sg:province":"AL",
    "sg:tags":[
        "dealer"
    ],
    "wof:name":"Crenshaw County Online",
    "wof:placetype":"venue"
},
  "geometry": {"coordinates":[-86.253461,31.716279],"type":"Point"}
}