{
  "type": "Feature",
  "properties": {
    "addr:full":"5890 Monticello Dr Montgomery AL 36117",
    "addr:housenumber":"5890",
    "addr:postcode":"36117",
    "addr:street":"Monticello Dr",
    "iso:country":"US",
    "sg:address":"5890 Monticello Dr",
    "sg:city":"Montgomery",
    "sg:classifiers":[
        {
            "category":"Wholesale",
            "subcategory":"Machinery & Supplies",
            "type":"Manufacturing & Wholesale Goods"
        }
    ],
    "sg:phone":"+1 334 396 8202",
    "sg:postcode":"36117",
    "sg:province":"AL",
    "sg:tags":[
        "equipment",
        "irrigation",
        "system"
    ],
    "wof:name":"Ewing Irrigation & Ind Prods",
    "wof:placetype":"venue"
},
  "geometry": {"coordinates":[-86.208417,32.365168],"type":"Point"}
}