{
  "type": "Feature",
  "properties": {
    "addr:full":"2840 Cahawba Trl Birmingham AL 35243",
    "addr:housenumber":"2840",
    "addr:postcode":"35243",
    "addr:street":"Cahawba Trl",
    "iso:country":"US",
    "sg:address":"2840 Cahawba Trl",
    "sg:city":"Birmingham",
    "sg:classifiers":[
        {
            "category":"Organizations",
            "subcategory":"Religious Organization",
            "type":"Services"
        }
    ],
    "sg:phone":"+1 205 776 5200",
    "sg:postcode":"35243",
    "sg:province":"AL",
    "wof:name":"Briarwood Presbyterian Church",
    "wof:placetype":"venue"
},
  "geometry": {"coordinates":[-86.736817,33.419949],"type":"Point"}
}