{
  "type": "Feature",
  "properties": {
    "iso:country":"US",
    "sg:address":"2118 US Hwy 72",
    "sg:city":"Huntsville",
    "sg:classifiers":[
        {
            "category":"Personal",
            "subcategory":"Beauty Salon",
            "type":"Services"
        }
    ],
    "sg:phone":"+1 256 859 0997",
    "sg:postcode":"35811",
    "sg:province":"AL",
    "wof:name":"Hair Safari",
    "wof:placetype":"venue"
},
  "geometry": {"coordinates":[-86.513484,34.77177],"type":"Point"}
}