{
  "type": "Feature",
  "properties": {
    "iso:country":"US",
    "sg:address":"1402 US Hwy 31",
    "sg:city":"Bay Minette",
    "sg:classifiers":[
        {
            "category":"Bars & Pubs",
            "type":"Food & Drink"
        }
    ],
    "sg:phone":"+1 251 580 3773",
    "sg:postcode":"36507",
    "sg:province":"AL",
    "wof:name":"Cole's Bar & Grill",
    "wof:placetype":"venue"
},
  "geometry": {"coordinates":[-87.776381,30.862],"type":"Point"}
}