{
  "type": "Feature",
  "properties": {
    "addr:full":"10004 Memorial Pkwy SW Huntsville AL 35803",
    "addr:housenumber":"10004",
    "addr:postcode":"35803",
    "addr:street":"Memorial Pkwy Sw",
    "iso:country":"US",
    "sg:address":"10004 Memorial Pkwy SW",
    "sg:city":"Huntsville",
    "sg:classifiers":[
        {
            "category":"Utilities",
            "subcategory":"Mobile Phone",
            "type":"Services"
        },
        {
            "category":"Shopping",
            "subcategory":"Computers & Home Electronics",
            "type":"Retail Goods"
        }
    ],
    "sg:phone":"+1 256 883 0050",
    "sg:postcode":"35803",
    "sg:province":"AL",
    "sg:tags":[
        "telephone",
        "cellular"
    ],
    "sg:website":"www.radioshack.com",
    "wof:name":"Radio Shack",
    "wof:placetype":"venue"
},
  "geometry": {"coordinates":[-86.566937,34.643115],"type":"Point"}
}