{
  "type": "Feature",
  "properties": {
    "addr:full":"9464 State Rte 168 Boaz AL 35957",
    "addr:housenumber":"9464",
    "addr:postcode":"35957",
    "addr:street":"State Rte 168",
    "iso:country":"US",
    "sg:address":"9464 State Rte 168",
    "sg:city":"Boaz",
    "sg:classifiers":[
        {
            "category":"Wholesale",
            "subcategory":"Electrical",
            "type":"Manufacturing & Wholesale Goods"
        }
    ],
    "sg:phone":"+1 256 593 4030",
    "sg:postcode":"35957",
    "sg:province":"AL",
    "wof:name":"Direct Distributing Co",
    "wof:placetype":"venue"
},
  "geometry": {"coordinates":[-86.17742699999999,34.198161],"type":"Point"}
}