{
  "type": "Feature",
  "properties": {
    "addr:full":"8665 Four Mile Rd Irvington AL 36544",
    "addr:housenumber":"8665",
    "addr:postcode":"36544",
    "addr:street":"Four Mile Rd",
    "iso:country":"US",
    "sg:address":"8665 Four Mile Rd",
    "sg:city":"Irvington",
    "sg:classifiers":[
        {
            "category":"Education",
            "subcategory":"Dance Studio",
            "type":"Public Place"
        }
    ],
    "sg:phone":"+1 251 824 3666",
    "sg:postcode":"36544",
    "sg:province":"AL",
    "sg:tags":[
        "instruction",
        "dancing"
    ],
    "wof:name":"Robinson's School Of Dance 7",
    "wof:placetype":"venue"
},
  "geometry": {"coordinates":[-88.245665,30.443595],"type":"Point"}
}