{
  "type": "Feature",
  "properties": {
    "iso:country":"US",
    "sg:address":"400 Pinson St",
    "sg:city":"Birmingham",
    "sg:classifiers":[
        {
            "category":"Manufacturing",
            "subcategory":"Printing",
            "type":"Manufacturing & Wholesale Goods"
        }
    ],
    "sg:phone":"+1 205 841 2212",
    "sg:postcode":"35217",
    "sg:province":"AL",
    "sg:tags":[
        "publishing"
    ],
    "wof:name":"Campus Publishing Services",
    "wof:placetype":"venue"
},
  "geometry": {"coordinates":[-86.785568,33.569141],"type":"Point"}
}