{
  "type": "Feature",
  "properties": {
    "iso:country":"US",
    "sg:address":"1916 Airport Blvd",
    "sg:city":"Mobile",
    "sg:classifiers":[
        {
            "category":"Retail",
            "subcategory":"Portrait Studio",
            "type":"Services"
        },
        {
            "category":"Professional",
            "subcategory":"Art Services",
            "type":"Services"
        }
    ],
    "sg:phone":"+1 251 476 4331",
    "sg:postcode":"36606",
    "sg:province":"AL",
    "sg:tags":[
        "photographic",
        "photographer",
        "commercial"
    ],
    "sg:website":"www.lcantrellphoto.com",
    "wof:name":"Cantrell Photography Inc",
    "wof:placetype":"venue"
},
  "geometry": {"coordinates":[-88.086142,30.67701],"type":"Point"}
}