{
  "type": "Feature",
  "properties": {
    "iso:country":"US",
    "sg:address":"21858 Co Rd 48",
    "sg:city":"Robertsdale",
    "sg:classifiers":[
        {
            "category":"Professional",
            "subcategory":"Business Services",
            "type":"Services"
        }
    ],
    "sg:phone":"+1 251 987 5646",
    "sg:postcode":"36567",
    "sg:province":"AL",
    "sg:tags":[
        "embroidery"
    ],
    "wof:name":"Perdido Beach Embroidery",
    "wof:placetype":"venue"
},
  "geometry": {"coordinates":[-87.651454,30.531083],"type":"Point"}
}