{
  "type": "Feature",
  "properties": {
    "addr:full":"715 Thames Ct Pelham AL 35124",
    "addr:housenumber":"715",
    "addr:postcode":"35124",
    "addr:street":"Thames Ct",
    "iso:country":"US",
    "sg:address":"715 Thames Ct",
    "sg:city":"Pelham",
    "sg:classifiers":[
        {
            "category":"Retail",
            "subcategory":"Repair Shop",
            "type":"Services"
        },
        {
            "category":"Retail",
            "subcategory":"Auto Repair",
            "type":"Services"
        }
    ],
    "sg:phone":"+1 205 664 8620",
    "sg:postcode":"35124",
    "sg:province":"AL",
    "sg:tags":[
        "heavy",
        "equipment",
        "truck",
        "maintenance"
    ],
    "wof:name":"Double Eagle Fleet Service",
    "wof:placetype":"venue"
},
  "geometry": {"coordinates":[-86.817785,33.29662],"type":"Point"}
}