{
  "type": "Feature",
  "properties": {
    "iso:country":"US",
    "sg:address":"2531 Noble St",
    "sg:city":"Anniston",
    "sg:classifiers":[
        {
            "category":"Retail",
            "subcategory":"Repair Shop",
            "type":"Services"
        }
    ],
    "sg:phone":"+1 256 237 5000",
    "sg:postcode":"36201",
    "sg:province":"AL",
    "sg:tags":[
        "related"
    ],
    "wof:name":"Smith Drive In Appl Repair",
    "wof:placetype":"venue"
},
  "geometry": {"coordinates":[-85.829787,33.676701],"type":"Point"}
}