{
  "type": "Feature",
  "properties": {
    "addr:full":"8459 Co Rd 246 Smiths Station AL 36877",
    "addr:housenumber":"8459",
    "addr:postcode":"36877",
    "addr:street":"Co Rd 246 Smiths Station",
    "iso:country":"US",
    "sg:address":"8459 Co Rd 246",
    "sg:city":"Smiths Station",
    "sg:classifiers":[
        {
            "category":"Personal",
            "subcategory":"Beauty Salon",
            "type":"Services"
        }
    ],
    "sg:phone":"+1 334 297 8866",
    "sg:postcode":"36877",
    "sg:province":"AL",
    "sg:tags":[
        "shop"
    ],
    "wof:name":"All That Beauty & Barber Shop",
    "wof:placetype":"venue"
},
  "geometry": {"coordinates":[-85.08514700000001,32.512435],"type":"Point"}
}