{
  "type": "Feature",
  "properties": {
    "iso:country":"US",
    "sg:address":"2413 Center Point Pkwy",
    "sg:city":"Birmingham",
    "sg:classifiers":[
        {
            "category":"Retail",
            "subcategory":"Veterinary Services",
            "type":"Services"
        }
    ],
    "sg:phone":"+1 205 854 4614",
    "sg:postcode":"35215",
    "sg:province":"AL",
    "sg:tags":[
        "veterinarian"
    ],
    "wof:name":"Parkway Veterinary Clinic",
    "wof:placetype":"venue"
},
  "geometry": {"coordinates":[-86.683701,33.649601],"type":"Point"}
}