{
  "type": "Feature",
  "properties": {
    "iso:country":"US",
    "sg:address":"9301 State Rte 69",
    "sg:city":"Northport",
    "sg:classifiers":[
        {
            "category":"Professional",
            "type":"Services"
        }
    ],
    "sg:phone":"+1 205 333 7149",
    "sg:postcode":"35473",
    "sg:province":"AL",
    "wof:name":"Affordable Decks",
    "wof:placetype":"venue"
},
  "geometry": {"coordinates":[-87.569549,33.280877],"type":"Point"}
}