{
  "type": "Feature",
  "properties": {
    "addr:full":"3313 Anderson Rd Opelika AL 36801",
    "addr:housenumber":"3313",
    "addr:postcode":"36801",
    "addr:street":"Anderson Rd",
    "iso:country":"US",
    "sg:address":"3313 Anderson Rd",
    "sg:city":"Opelika",
    "sg:classifiers":[
        {
            "category":"Building & Trades",
            "subcategory":"Construction",
            "type":"Services"
        }
    ],
    "sg:phone":"+1 334 749 3960",
    "sg:postcode":"36801",
    "sg:province":"AL",
    "sg:tags":[
        "water",
        "line",
        "sewer",
        "utility"
    ],
    "wof:name":"Gorees Cable Construction",
    "wof:placetype":"venue"
},
  "geometry": {"coordinates":[-85.337576,32.689643],"type":"Point"}
}