{
  "type": "Feature",
  "properties": {
    "addr:full":"214 Holmes Ave NE Huntsville AL 35801",
    "addr:housenumber":"214",
    "addr:postcode":"35801",
    "addr:street":"Holmes Ave Ne",
    "iso:country":"US",
    "sg:address":"214 Holmes Ave NE",
    "sg:city":"Huntsville",
    "sg:classifiers":[
        {
            "category":"Manufacturing",
            "subcategory":"Food",
            "type":"Manufacturing & Wholesale Goods"
        }
    ],
    "sg:phone":"+1 256 564 7442",
    "sg:postcode":"35801",
    "sg:province":"AL",
    "sg:tags":[
        "brewer"
    ],
    "wof:name":"Olde Towne Brewing Co",
    "wof:placetype":"venue"
},
  "geometry": {"coordinates":[-86.58524199999999,34.733042],"type":"Point"}
}