{
  "type": "Feature",
  "properties": {
    "addr:full":"260 Old Jasmine Hill Rd Wetumpka AL 36093",
    "addr:housenumber":"260",
    "addr:postcode":"36093",
    "addr:street":"Old Jasmine Hill Rd",
    "iso:country":"US",
    "sg:address":"260 Old Jasmine Hill Rd",
    "sg:city":"Wetumpka",
    "sg:classifiers":[
        {
            "category":"Manufacturing",
            "subcategory":"Printing",
            "type":"Manufacturing & Wholesale Goods"
        },
        {
            "category":"Social Services",
            "type":"Services"
        }
    ],
    "sg:phone":"+1 334 514 1349",
    "sg:postcode":"36093",
    "sg:province":"AL",
    "sg:tags":[
        "publisher"
    ],
    "wof:name":"Pastoral Publications LLC",
    "wof:placetype":"venue"
},
  "geometry": {"coordinates":[-86.186089,32.476555],"type":"Point"}
}