{
  "type": "Feature",
  "properties": {
    "addr:full":"2821 5th Aly S Birmingham AL 35233",
    "addr:housenumber":"2821",
    "addr:postcode":"35233",
    "addr:street":"5Th Aly S",
    "iso:country":"US",
    "sg:address":"2821 5th Aly S",
    "sg:city":"Birmingham",
    "sg:classifiers":[
        {
            "category":"Wholesale",
            "subcategory":"Painting Supplies",
            "type":"Manufacturing & Wholesale Goods"
        }
    ],
    "sg:phone":"+1 205 251 0273",
    "sg:postcode":"35233",
    "sg:province":"AL",
    "sg:tags":[
        "paint"
    ],
    "wof:name":"ICI Dulux Paint",
    "wof:placetype":"venue"
},
  "geometry": {"coordinates":[-86.788864,33.513282],"type":"Point"}
}