{
  "type": "Feature",
  "properties": {
    "iso:country":"US",
    "sg:address":"1914 Erskine Ave",
    "sg:city":"Florence",
    "sg:classifiers":[
        {
            "category":"Building & Trades",
            "subcategory":"Construction",
            "type":"Services"
        }
    ],
    "sg:phone":"+1 256 766 4298",
    "sg:postcode":"35630",
    "sg:province":"AL",
    "sg:tags":[
        "floor",
        "laying",
        "contractor"
    ],
    "wof:name":"Hart Floor Finishing",
    "wof:placetype":"venue"
},
  "geometry": {"coordinates":[-87.693457,34.827167],"type":"Point"}
}