{
  "type": "Feature",
  "properties": {
    "iso:country":"US",
    "sg:address":"1545 Gulf Shores Pkwy",
    "sg:city":"Gulf Shores",
    "sg:classifiers":[
        {
            "category":"Shopping",
            "subcategory":"Computers & Home Electronics",
            "type":"Retail Goods"
        }
    ],
    "sg:phone":"+1 251 968 7425",
    "sg:postcode":"36542",
    "sg:province":"AL",
    "sg:tags":[
        "equipment",
        "satellite",
        "system"
    ],
    "wof:name":"Radio Shack",
    "wof:placetype":"venue"
},
  "geometry": {"coordinates":[-87.688165,30.270026],"type":"Point"}
}