{
  "type": "Feature",
  "properties": {
    "addr:full":"10445 Kimbrell Rd Athens AL 35614",
    "addr:housenumber":"10445",
    "addr:postcode":"35614",
    "addr:street":"Kimbrell Rd",
    "iso:country":"US",
    "sg:address":"10445 Kimbrell Rd",
    "sg:city":"Athens",
    "sg:classifiers":[
        {
            "category":"Freight",
            "type":"Transportation"
        }
    ],
    "sg:phone":"+1 256 729 6094",
    "sg:postcode":"35614",
    "sg:province":"AL",
    "sg:tags":[
        "farm",
        "horse",
        "trucking"
    ],
    "wof:name":"Marcus and Jackie Romine",
    "wof:placetype":"venue"
},
  "geometry": {"coordinates":[-87.137164,34.854736],"type":"Point"}
}