{
  "type": "Feature",
  "properties": {
    "iso:country":"US",
    "sg:address":"431 Co Rd 617",
    "sg:city":"Enterprise",
    "sg:classifiers":[
        {
            "category":"Organizations",
            "subcategory":"Community Association",
            "type":"Services"
        }
    ],
    "sg:phone":"+1 334 393 5402",
    "sg:postcode":"36330",
    "sg:province":"AL",
    "wof:name":"Hoca Home Owners Consult",
    "wof:placetype":"venue"
},
  "geometry": {"coordinates":[-85.949411,31.255716],"type":"Point"}
}