{
  "type": "Feature",
  "properties": {
    "iso:country":"US",
    "sg:address":"414 Glover Ave",
    "sg:city":"Enterprise",
    "sg:classifiers":[
        {
            "category":"Health Services",
            "subcategory":"Medical Lab",
            "type":"Services"
        }
    ],
    "sg:phone":"+1 334 347 6600",
    "sg:postcode":"36330",
    "sg:province":"AL",
    "sg:tags":[
        "laboratory"
    ],
    "wof:name":"Enterprise Dental Lab",
    "wof:placetype":"venue"
},
  "geometry": {"coordinates":[-85.851107,31.3177],"type":"Point"}
}