{
  "type": "Feature",
  "properties": {
    "addr:full":"3304 Dauphin Island Pkwy Mobile AL 36605",
    "addr:housenumber":"3304",
    "addr:postcode":"36605",
    "addr:street":"Dauphin Island Pkwy",
    "iso:country":"US",
    "sg:address":"3304 Dauphin Island Pkwy",
    "sg:city":"Mobile",
    "sg:classifiers":[
        {
            "category":"Manufacturing",
            "subcategory":"Apparel",
            "type":"Manufacturing & Wholesale Goods"
        }
    ],
    "sg:phone":"+1 251 476 4029",
    "sg:postcode":"36605",
    "sg:province":"AL",
    "sg:tags":[
        "product",
        "boat",
        "mfg"
    ],
    "wof:name":"Dabney Sailmakers Inc",
    "wof:placetype":"venue"
},
  "geometry": {"coordinates":[-88.076516,30.602993],"type":"Point"}
}