{
  "type": "Feature",
  "properties": {
    "iso:country":"US",
    "sg:address":"2509 State Rte 69",
    "sg:city":"Cullman",
    "sg:classifiers":[
        {
            "category":"Retail",
            "subcategory":"Auto Repair",
            "type":"Services"
        }
    ],
    "sg:phone":"+1 256 796 7106",
    "sg:postcode":"35058",
    "sg:province":"AL",
    "sg:tags":[
        "body",
        "automobile",
        "painting"
    ],
    "wof:name":"Smith Burl Body Shop",
    "wof:placetype":"venue"
},
  "geometry": {"coordinates":[-86.763261,34.211108],"type":"Point"}
}