{
  "type": "Feature",
  "properties": {
    "addr:full":"222 S Mulberry Ave Butler AL 36904",
    "addr:housenumber":"222",
    "addr:postcode":"36904",
    "addr:street":"S Mulberry Ave",
    "iso:country":"US",
    "sg:address":"222 S Mulberry Ave",
    "sg:city":"Butler",
    "sg:classifiers":[
        {
            "category":"Shopping",
            "subcategory":"Discount & Variety Stores",
            "type":"Retail Goods"
        }
    ],
    "sg:phone":"+1 205 459 7713",
    "sg:postcode":"36904",
    "sg:province":"AL",
    "wof:name":"Super 10",
    "wof:placetype":"venue"
},
  "geometry": {"coordinates":[-88.221205,32.087032],"type":"Point"}
}