{
  "type": "Feature",
  "properties": {
    "iso:country":"US",
    "sg:address":"4749 Appletree Ln",
    "sg:city":"Tuscaloosa",
    "sg:classifiers":[
        {
            "category":"Manufacturing",
            "subcategory":"Tools & Machinery",
            "type":"Manufacturing & Wholesale Goods"
        }
    ],
    "sg:phone":"+1 205 553 4453",
    "sg:postcode":"35405",
    "sg:province":"AL",
    "sg:tags":[
        "physician",
        "surgeon"
    ],
    "sg:website":"www.howardinstruments.com",
    "wof:name":"Howard Instruments Inc",
    "wof:placetype":"venue"
},
  "geometry": {"coordinates":[-87.46634,33.163269],"type":"Point"}
}