{
  "type": "Feature",
  "properties": {
    "iso:country":"US",
    "sg:address":"2407 River Rd",
    "sg:city":"Tuscaloosa",
    "sg:classifiers":[
        {
            "category":"Food & Beverages",
            "subcategory":"Fruits & Vegetables",
            "type":"Retail Goods"
        },
        {
            "category":"Wholesale",
            "subcategory":"Fruits & Vegetables",
            "type":"Manufacturing & Wholesale Goods"
        }
    ],
    "sg:phone":"+1 205 349 0368",
    "sg:postcode":"35401",
    "sg:province":"AL",
    "sg:tags":[
        "produce"
    ],
    "wof:name":"Tuscaloosa Farmers Market",
    "wof:placetype":"venue"
},
  "geometry": {"coordinates":[-87.570334,33.212231],"type":"Point"}
}