{
  "type": "Feature",
  "properties": {
    "iso:country":"US",
    "sg:address":"221 Distribution Dr",
    "sg:city":"Homewood",
    "sg:classifiers":[
        {
            "category":"Freight",
            "type":"Transportation"
        }
    ],
    "sg:phone":"+1 205 942 1200",
    "sg:postcode":"35209",
    "sg:province":"AL",
    "sg:tags":[
        "warehouse",
        "merchandise"
    ],
    "wof:name":"Birmingham Distribution Ctr",
    "wof:placetype":"venue"
},
  "geometry": {"coordinates":[-86.84376899999999,33.44492],"type":"Point"}
}