{
  "type": "Feature",
  "properties": {
    "addr:full":"16077 Parker Rd Athens AL 35611",
    "addr:housenumber":"16077",
    "addr:postcode":"35611",
    "addr:street":"Parker Rd",
    "iso:country":"US",
    "sg:address":"16077 Parker Rd",
    "sg:city":"Athens",
    "sg:classifiers":[
        {
            "category":"Freight",
            "type":"Transportation"
        }
    ],
    "sg:phone":"+1 256 233 5600",
    "sg:postcode":"35611",
    "sg:province":"AL",
    "sg:tags":[
        "trucking"
    ],
    "wof:name":"Green Trucking",
    "wof:placetype":"venue"
},
  "geometry": {"coordinates":[-87.107173,34.79445],"type":"Point"}
}