{
  "type": "Feature",
  "properties": {
    "iso:country":"US",
    "sg:address":"600 S Court St",
    "sg:city":"Montgomery",
    "sg:classifiers":[
        {
            "category":"Professional",
            "subcategory":"Management & Consulting",
            "type":"Services"
        }
    ],
    "sg:phone":"+1 334 834 1010",
    "sg:postcode":"36104",
    "sg:province":"AL",
    "sg:tags":[
        "consultant",
        "business"
    ],
    "wof:name":"Cfo Strategies",
    "wof:placetype":"venue"
},
  "geometry": {"coordinates":[-86.308749,32.368237],"type":"Point"}
}