{
  "type": "Feature",
  "properties": {
    "iso:country":"US",
    "sg:address":"2002 Summit Pkwy",
    "sg:city":"Prattville",
    "sg:classifiers":[
        {
            "category":"Real Estate",
            "subcategory":"Real Estate Operator",
            "type":"Services"
        }
    ],
    "sg:phone":"+1 334 358 6001",
    "sg:postcode":"36066",
    "sg:province":"AL",
    "sg:tags":[
        "apartment"
    ],
    "wof:name":"Summit Terrace Apartments",
    "wof:placetype":"venue"
},
  "geometry": {"coordinates":[-86.417968,32.480018],"type":"Point"}
}