{
  "type": "Feature",
  "properties": {
    "iso:country":"US",
    "sg:address":"2304 Perch Point Ct",
    "sg:city":"Mobile",
    "sg:classifiers":[
        {
            "category":"Mining & Drilling",
            "type":"Manufacturing & Wholesale Goods"
        }
    ],
    "sg:phone":"+1 251 479 6210",
    "sg:postcode":"36605",
    "sg:province":"AL",
    "sg:tags":[
        "well"
    ],
    "wof:name":"Double H Contracting Inc",
    "wof:placetype":"venue"
},
  "geometry": {"coordinates":[-88.09910000000001,30.586228],"type":"Point"}
}