{
  "type": "Feature",
  "properties": {
    "addr:full":"3488 Springhill Ave Mobile AL 36608",
    "addr:housenumber":"3488",
    "addr:postcode":"36608",
    "addr:street":"Springhill Ave",
    "iso:country":"US",
    "sg:address":"3488 Springhill Ave",
    "sg:city":"Mobile",
    "sg:classifiers":[
        {
            "category":"Personal",
            "subcategory":"Beauty Salon",
            "type":"Services"
        }
    ],
    "sg:phone":"+1 251 343 8138",
    "sg:postcode":"36608",
    "sg:province":"AL",
    "wof:name":"African Village",
    "wof:placetype":"venue"
},
  "geometry": {"coordinates":[-88.12607199999999,30.703894],"type":"Point"}
}