{
  "type": "Feature",
  "properties": {
    "iso:country":"US",
    "sg:address":"4 Office Park Cir Ste 116",
    "sg:city":"Birmingham",
    "sg:classifiers":[
        {
            "category":"Personal",
            "type":"Services"
        },
        {
            "category":"Professional",
            "subcategory":"Art Services",
            "type":"Services"
        }
    ],
    "sg:phone":"+1 205 937 2531",
    "sg:postcode":"35223",
    "sg:province":"AL",
    "sg:tags":[
        "photography",
        "videography",
        "wedding"
    ],
    "wof:name":"Aes Photographic Arts",
    "wof:placetype":"venue"
},
  "geometry": {"coordinates":[-86.771378,33.47961],"type":"Point"}
}