{
  "type": "Feature",
  "properties": {
    "addr:full":"24359 Co Rd 222 Bremen AL 35033",
    "addr:housenumber":"24359;222",
    "addr:postcode":"35033",
    "addr:street":"Co Rd",
    "iso:country":"US",
    "sg:address":"24359 Co Rd 222",
    "sg:city":"Bremen",
    "sg:classifiers":[
        {
            "category":"Professional",
            "subcategory":"Business Services",
            "type":"Services"
        }
    ],
    "sg:phone":"+1 256 287 1001",
    "sg:postcode":"35033",
    "sg:province":"AL",
    "wof:name":"Alabama Real Estate Enterprise",
    "wof:placetype":"venue"
},
  "geometry": {"coordinates":[-87.02401999999999,34.023892],"type":"Point"}
}