{
  "type": "Feature",
  "properties": {
    "iso:country":"US",
    "sg:address":"24359 Co Rd 222",
    "sg:city":"Bremen",
    "sg:classifiers":[
        {
            "category":"Professional",
            "subcategory":"Business Services",
            "type":"Services"
        }
    ],
    "sg:phone":"+1 256 287 1001",
    "sg:postcode":"35033",
    "sg:province":"AL",
    "wof:name":"Alabama Real Estate Enterprise",
    "wof:placetype":"venue"
},
  "geometry": {"coordinates":[-87.02402,34.023892],"type":"Point"}
}