{
  "type": "Feature",
  "properties": {
    "iso:country":"US",
    "sg:address":"110 Gusmus Ave",
    "sg:city":"Muscle Shoals",
    "sg:classifiers":[
        {
            "category":"Retail",
            "subcategory":"Auto Repair",
            "type":"Services"
        }
    ],
    "sg:phone":"+1 256 389 8350",
    "sg:postcode":"35661",
    "sg:province":"AL",
    "sg:tags":[
        "truck",
        "general"
    ],
    "wof:name":"Shoals Diesel Inc",
    "wof:placetype":"venue"
},
  "geometry": {"coordinates":[-87.65656799999999,34.757606],"type":"Point"}
}