{
  "type": "Feature",
  "properties": {
    "iso:country":"US",
    "sg:address":"308 19th St",
    "sg:city":"Birmingham",
    "sg:classifiers":[
        {
            "category":"Bars & Pubs",
            "type":"Food & Drink"
        }
    ],
    "sg:phone":"+1 205 780 9451",
    "sg:postcode":"35218",
    "sg:province":"AL",
    "sg:tags":[
        "bar"
    ],
    "wof:name":"Wallace Lounge",
    "wof:placetype":"venue"
},
  "geometry": {"coordinates":[-86.898528,33.514104],"type":"Point"}
}