{
  "type": "Feature",
  "properties": {
    "iso:country":"US",
    "sg:address":"5629 Co Rd 1763",
    "sg:city":"Arab",
    "sg:classifiers":[
        {
            "category":"Retail",
            "subcategory":"Auto Repair",
            "type":"Services"
        }
    ],
    "sg:phone":"+1 256 586 8564",
    "sg:postcode":"35016",
    "sg:province":"AL",
    "sg:tags":[
        "body"
    ],
    "wof:name":"Bill & Sons",
    "wof:placetype":"venue"
},
  "geometry": {"coordinates":[-86.513993,34.279041],"type":"Point"}
}