{
  "type": "Feature",
  "properties": {
    "iso:country":"US",
    "sg:address":"205 S Seminary St",
    "sg:city":"Florence",
    "sg:classifiers":[
        {
            "category":"Professional",
            "subcategory":"Lawyer & Legal Services",
            "type":"Services"
        }
    ],
    "sg:phone":"+1 256 766 1649",
    "sg:postcode":"35630",
    "sg:province":"AL",
    "wof:name":"Tipper Donald G Atty",
    "wof:placetype":"venue"
},
  "geometry": {"coordinates":[-87.673528,34.798932],"type":"Point"}
}