{
  "type": "Feature",
  "properties": {
    "iso:country":"US",
    "sg:address":"520 George Wallace Dr",
    "sg:city":"Gadsden",
    "sg:classifiers":[
        {
            "category":"Food & Beverages",
            "subcategory":"Groceries & Convenience Stores",
            "type":"Retail Goods"
        }
    ],
    "sg:phone":"+1 256 543 3340",
    "sg:postcode":"35903",
    "sg:province":"AL",
    "wof:name":"Rainbow Food Mart",
    "wof:placetype":"venue"
},
  "geometry": {"coordinates":[-85.995584,34.0017],"type":"Point"}
}