{
  "type": "Feature",
  "properties": {
    "addr:full":"703 N Main St Tuskegee AL 36083",
    "addr:housenumber":"703",
    "addr:postcode":"36083",
    "addr:street":"N Main St",
    "iso:country":"US",
    "sg:address":"703 N Main St",
    "sg:city":"Tuskegee",
    "sg:classifiers":[
        {
            "category":"Personal",
            "subcategory":"Beauty Salon",
            "type":"Services"
        }
    ],
    "sg:phone":"+1 334 724 0109",
    "sg:postcode":"36083",
    "sg:province":"AL",
    "sg:tags":[
        "shop"
    ],
    "wof:name":"New You",
    "wof:placetype":"venue"
},
  "geometry": {"coordinates":[-85.69479200000001,32.428498],"type":"Point"}
}