{
  "type": "Feature",
  "properties": {
    "iso:country":"US",
    "sg:address":"129 Clark St",
    "sg:city":"Grove Hill",
    "sg:classifiers":[
        {
            "category":"Health Services",
            "subcategory":"Hospital",
            "type":"Services"
        }
    ],
    "sg:phone":"+1 251 275 4165",
    "sg:postcode":"36451",
    "sg:province":"AL",
    "sg:tags":[
        "mental"
    ],
    "wof:name":"Southwest Alabama Mental Hlth",
    "wof:placetype":"venue"
},
  "geometry": {"coordinates":[-87.777718,31.707751],"type":"Point"}
}