{
  "type": "Feature",
  "properties": {
    "iso:country":"US",
    "sg:address":"80044 Tallassee Hwy",
    "sg:city":"Eclectic",
    "sg:classifiers":[
        {
            "category":"Food & Beverages",
            "subcategory":"Groceries & Convenience Stores",
            "type":"Retail Goods"
        }
    ],
    "sg:phone":"+1 334 541 2488",
    "sg:postcode":"36024",
    "sg:province":"AL",
    "sg:tags":[
        "grocer"
    ],
    "wof:name":"R & J Grocery",
    "wof:placetype":"venue"
},
  "geometry": {"coordinates":[-86.089369,32.580249],"type":"Point"}
}