{
  "type": "Feature",
  "properties": {
    "addr:full":"574 Azalea Rd Mobile AL 36609",
    "addr:housenumber":"574",
    "addr:postcode":"36609",
    "addr:street":"Azalea Rd",
    "iso:country":"US",
    "sg:address":"574 Azalea Rd",
    "sg:city":"Mobile",
    "sg:classifiers":[
        {
            "category":"Building & Trades",
            "subcategory":"Construction",
            "type":"Services"
        }
    ],
    "sg:phone":"+1 251 666 1500",
    "sg:postcode":"36609",
    "sg:province":"AL",
    "sg:tags":[
        "contractor"
    ],
    "wof:name":"Comcast",
    "wof:placetype":"venue"
},
  "geometry": {"coordinates":[-88.148629,30.657598],"type":"Point"}
}