{
  "type": "Feature",
  "properties": {
    "iso:country":"US",
    "sg:address":"1636 Gadsden Hwy",
    "sg:city":"Birmingham",
    "sg:classifiers":[
        {
            "category":"Shopping",
            "subcategory":"Shoes",
            "type":"Retail Goods"
        }
    ],
    "sg:phone":"+1 205 655 4243",
    "sg:postcode":"35235",
    "sg:province":"AL",
    "sg:tags":[
        "store"
    ],
    "sg:website":"www.rackroomshoes.com",
    "wof:name":"Rack Room Shoes",
    "wof:placetype":"venue"
},
  "geometry": {"coordinates":[-86.63829800000001,33.601799],"type":"Point"}
}