{
  "type": "Feature",
  "properties": {
    "addr:full":"927 Ventura Dr Mc Calla AL 35111",
    "addr:housenumber":"927",
    "addr:postcode":"35111",
    "addr:street":"Ventura Dr",
    "iso:country":"US",
    "sg:address":"927 Ventura Dr",
    "sg:city":"Mc Calla",
    "sg:classifiers":[
        {
            "category":"Professional",
            "type":"Services"
        }
    ],
    "sg:phone":"+1 205 425 1725",
    "sg:postcode":"35111",
    "sg:province":"AL",
    "wof:name":"J&J Racing LLC",
    "wof:placetype":"venue"
},
  "geometry": {"coordinates":[-87.052964,33.321414],"type":"Point"}
}