{
  "type": "Feature",
  "properties": {
    "addr:full":"139 S Court St Prattville AL 36067",
    "addr:housenumber":"139",
    "addr:postcode":"36067",
    "addr:street":"S Court St",
    "iso:country":"US",
    "sg:address":"139 S Court St",
    "sg:city":"Prattville",
    "sg:classifiers":[
        {
            "category":"Retail",
            "subcategory":"Animal Services",
            "type":"Services"
        }
    ],
    "sg:phone":"+1 334 361 6007",
    "sg:postcode":"36067",
    "sg:province":"AL",
    "wof:name":"Pampered Pets",
    "wof:placetype":"venue"
},
  "geometry": {"coordinates":[-86.475376,32.461822],"type":"Point"}
}