{
  "type": "Feature",
  "properties": {
    "iso:country":"US",
    "sg:address":"700 Main Ave",
    "sg:city":"Northport",
    "sg:classifiers":[
        {
            "category":"Organizations",
            "subcategory":"Religious Organization",
            "type":"Services"
        }
    ],
    "sg:phone":"+1 205 758 4703",
    "sg:postcode":"35476",
    "sg:province":"AL",
    "sg:tags":[
        "church"
    ],
    "wof:name":"Northport First United Church",
    "wof:placetype":"venue"
},
  "geometry": {"coordinates":[-87.578886,33.219805],"type":"Point"}
}