{
  "type": "Feature",
  "properties": {
    "iso:country":"US",
    "sg:address":"2416 Thornmor Dr SW",
    "sg:city":"Huntsville",
    "sg:classifiers":[
        {
            "category":"Retail",
            "subcategory":"Veterinary Services",
            "type":"Services"
        }
    ],
    "sg:phone":"+1 256 880 5817",
    "sg:postcode":"35803",
    "sg:province":"AL",
    "wof:name":"Hampton Cove Animal Hospi",
    "wof:placetype":"venue"
},
  "geometry": {"coordinates":[-86.583648,34.62141],"type":"Point"}
}