{
  "type": "Feature",
  "properties": {
    "iso:country":"US",
    "sg:address":"469 Co Rd 262",
    "sg:city":"Hanceville",
    "sg:classifiers":[
        {
            "category":"Professional",
            "subcategory":"Management & Consulting",
            "type":"Services"
        }
    ],
    "sg:phone":"+1 256 287 0917",
    "sg:postcode":"35077",
    "sg:province":"AL",
    "wof:name":"R M Industrial Products Inc",
    "wof:placetype":"venue"
},
  "geometry": {"coordinates":[-86.874618,34.049449],"type":"Point"}
}