{
  "type": "Feature",
  "properties": {
    "iso:country":"US",
    "sg:address":"1100 Sparks Gap Rd",
    "sg:city":"Bessemer",
    "sg:classifiers":[
        {
            "category":"Organizations",
            "subcategory":"Religious Organization",
            "type":"Services"
        }
    ],
    "sg:phone":"+1 205 428 4466",
    "sg:postcode":"35020",
    "sg:province":"AL",
    "wof:name":"New Life Community Church",
    "wof:placetype":"venue"
},
  "geometry": {"coordinates":[-86.97335099999999,33.355458],"type":"Point"}
}