{
  "type": "Feature",
  "properties": {
    "iso:country":"US",
    "sg:address":"845 Adams Ave",
    "sg:city":"Montgomery",
    "sg:classifiers":[
        {
            "category":"Shopping",
            "subcategory":"Florist",
            "type":"Retail Goods"
        }
    ],
    "sg:phone":"+1 334 264 5080",
    "sg:postcode":"36104",
    "sg:province":"AL",
    "wof:name":"Citizen Florist",
    "wof:placetype":"venue"
},
  "geometry": {"coordinates":[-86.297096,32.375555],"type":"Point"}
}