{
  "type": "Feature",
  "properties": {
    "iso:country":"US",
    "sg:address":"2917 Linden Ave",
    "sg:city":"Birmingham",
    "sg:classifiers":[
        {
            "category":"Professional",
            "subcategory":"Business Services",
            "type":"Services"
        }
    ],
    "sg:phone":"+1 205 870 5825",
    "sg:postcode":"35209",
    "sg:province":"AL",
    "wof:name":"Interiors Revisited Inc",
    "wof:placetype":"venue"
},
  "geometry": {"coordinates":[-86.79265599999999,33.478238],"type":"Point"}
}