{
  "type": "Feature",
  "properties": {
    "iso:country":"US",
    "sg:address":"1318 Commercial St SE",
    "sg:city":"Hanceville",
    "sg:classifiers":[
        {
            "category":"Shopping",
            "subcategory":"Clothing, Apparel, & Fashions",
            "type":"Retail Goods"
        }
    ],
    "sg:phone":"+1 256 352 4067",
    "sg:postcode":"35077",
    "sg:province":"AL",
    "wof:name":"Kasey D's Gifts & More",
    "wof:placetype":"venue"
},
  "geometry": {"coordinates":[-86.753361,34.063443],"type":"Point"}
}