{
  "type": "Feature",
  "properties": {
    "iso:country":"US",
    "sg:address":"900 Anna Ave",
    "sg:city":"Tuscaloosa",
    "sg:classifiers":[
        {
            "category":"Health Services",
            "subcategory":"Doctor",
            "type":"Services"
        }
    ],
    "sg:phone":"+1 205 758 6611",
    "sg:postcode":"35401",
    "sg:province":"AL",
    "sg:tags":[
        "physician",
        "surgeon"
    ],
    "wof:name":"Hillard & King",
    "wof:placetype":"venue"
},
  "geometry": {"coordinates":[-87.534157,33.205598],"type":"Point"}
}