{
  "type": "Feature",
  "properties": {
    "iso:country":"US",
    "sg:address":"530 S Union St",
    "sg:city":"Montgomery",
    "sg:classifiers":[
        {
            "category":"Personal",
            "subcategory":"Beauty Salon",
            "type":"Services"
        }
    ],
    "sg:phone":"+1 334 834 0002",
    "sg:postcode":"36104",
    "sg:province":"AL",
    "sg:tags":[
        "shop",
        "barber"
    ],
    "wof:name":"Ronald's Creative Hair Designs",
    "wof:placetype":"venue"
},
  "geometry": {"coordinates":[-86.299794,32.370788],"type":"Point"}
}