{
  "type": "Feature",
  "properties": {
    "iso:country":"US",
    "sg:address":"888 US Hwy 431",
    "sg:city":"Boaz",
    "sg:classifiers":[
        {
            "category":"Banks & Credit Unions",
            "subcategory":"Bank",
            "type":"Services"
        }
    ],
    "sg:phone":"+1 256 840 9525",
    "sg:postcode":"35957",
    "sg:province":"AL",
    "sg:tags":[
        "loan",
        "real estate"
    ],
    "wof:name":"Southern Home Mortgage Corp",
    "wof:placetype":"venue"
},
  "geometry": {"coordinates":[-86.150534,34.199424],"type":"Point"}
}