{
  "type": "Feature",
  "properties": {
    "iso:country":"US",
    "sg:address":"11775 County Line Rd",
    "sg:city":"Madison",
    "sg:classifiers":[
        {
            "category":"Education",
            "subcategory":"School",
            "type":"Public Place"
        }
    ],
    "sg:phone":"+1 256 772 2075",
    "sg:postcode":"35758",
    "sg:province":"AL",
    "sg:tags":[
        "executive"
    ],
    "sg:website":"www.madisoncity.k12.al.us",
    "wof:name":"Heritage Elementary School",
    "wof:placetype":"venue"
},
  "geometry": {"coordinates":[-86.78628500000001,34.728918],"type":"Point"}
}