{
  "type": "Feature",
  "properties": {
    "addr:full":"7208 Honor Keith Rd Trussville AL 35173",
    "addr:housenumber":"7208",
    "addr:postcode":"35173",
    "addr:street":"Honor Keith Rd",
    "iso:country":"US",
    "sg:address":"7208 Honor Keith Rd",
    "sg:city":"Trussville",
    "sg:classifiers":[
        {
            "category":"Freight",
            "type":"Transportation"
        }
    ],
    "sg:phone":"+1 205 655 7009",
    "sg:postcode":"35173",
    "sg:province":"AL",
    "sg:tags":[
        "operator",
        "local",
        "trucking"
    ],
    "wof:name":"Goulds Truck Service & E",
    "wof:placetype":"venue"
},
  "geometry": {"coordinates":[-86.527692,33.712277],"type":"Point"}
}