{
  "type": "Feature",
  "properties": {
    "iso:country":"US",
    "sg:address":"3020 Morgan Rd",
    "sg:city":"Bessemer",
    "sg:classifiers":[
        {
            "category":"Professional",
            "subcategory":"Employment Agencies",
            "type":"Services"
        }
    ],
    "sg:phone":"+1 205 425 8788",
    "sg:postcode":"35022",
    "sg:province":"AL",
    "wof:name":"Nannies Plus Inc",
    "wof:placetype":"venue"
},
  "geometry": {"coordinates":[-86.914297,33.332228],"type":"Point"}
}