{
  "type": "Feature",
  "properties": {
    "iso:country":"US",
    "sg:address":"18630 Bart Brown Rd",
    "sg:city":"Berry",
    "sg:classifiers":[
        {
            "category":"Professional",
            "type":"Services"
        }
    ],
    "sg:phone":"+1 205 330 2527",
    "sg:postcode":"35546",
    "sg:province":"AL",
    "wof:name":"Terry Long",
    "wof:placetype":"venue"
},
  "geometry": {"coordinates":[-87.64329600000001,33.455063],"type":"Point"}
}