{
  "type": "Feature",
  "properties": {
    "addr:full":"601 Park Rd Pleasant Grove AL 35127",
    "addr:housenumber":"601",
    "addr:postcode":"35127",
    "addr:street":"Park Rd",
    "iso:country":"US",
    "sg:address":"601 Park Rd",
    "sg:city":"Pleasant Grove",
    "sg:classifiers":[
        {
            "category":"Organizations",
            "subcategory":"Community Association",
            "type":"Services"
        }
    ],
    "sg:phone":"+1 205 379 5200",
    "sg:postcode":"35127",
    "sg:province":"AL",
    "wof:name":"Pleasant Grove Elementary",
    "wof:placetype":"venue"
},
  "geometry": {"coordinates":[-86.972103,33.491739],"type":"Point"}
}