{
  "type": "Feature",
  "properties": {
    "iso:country":"US",
    "sg:address":"2016 Airport Blvd",
    "sg:city":"Mobile",
    "sg:classifiers":[
        {
            "category":"Home & Garden",
            "subcategory":"Building Materials",
            "type":"Retail Goods"
        },
        {
            "category":"Manufacturing",
            "subcategory":"Glass & Minerals",
            "type":"Manufacturing & Wholesale Goods"
        }
    ],
    "sg:phone":"+1 251 473 6860",
    "sg:postcode":"36606",
    "sg:province":"AL",
    "sg:tags":[
        "leaded",
        "door",
        "mfg",
        "windows",
        "stained",
        "beveled"
    ],
    "wof:name":"Bell Stained Glass & Doors",
    "wof:placetype":"venue"
},
  "geometry": {"coordinates":[-88.087115,30.676616],"type":"Point"}
}