{
  "type": "Feature",
  "properties": {
    "iso:country":"US",
    "sg:address":"3925 2nd Ave S",
    "sg:city":"Birmingham",
    "sg:classifiers":[
        {
            "category":"Autos & Motor Vehicles",
            "subcategory":"Auto Supplies",
            "type":"Retail Goods"
        }
    ],
    "sg:phone":"+1 205 251 2194",
    "sg:postcode":"35222",
    "sg:province":"AL",
    "sg:tags":[
        "automotive",
        "parts"
    ],
    "wof:name":"Dacco Detroit",
    "wof:placetype":"venue"
},
  "geometry": {"coordinates":[-86.776096,33.523716],"type":"Point"}
}