{
  "type": "Feature",
  "properties": {
    "iso:country":"US",
    "sg:address":"3502 Veterans Memorial Pkwy",
    "sg:city":"Lanett",
    "sg:classifiers":[
        {
            "category":"Professional",
            "subcategory":"Business Services",
            "type":"Services"
        }
    ],
    "sg:phone":"+1 334 576 4677",
    "sg:postcode":"36863",
    "sg:province":"AL",
    "sg:tags":[
        "building",
        "inspection"
    ],
    "wof:name":"Perry's Building Inspection",
    "wof:placetype":"venue"
},
  "geometry": {"coordinates":[-85.230217,32.846667],"type":"Point"}
}