{
  "type": "Feature",
  "properties": {
    "iso:country":"US",
    "sg:address":"2505 W Clinton Ave",
    "sg:city":"Huntsville",
    "sg:classifiers":[
        {
            "category":"Organizations",
            "subcategory":"Labor Organization",
            "type":"Services"
        }
    ],
    "sg:phone":"+1 256 534 6951",
    "sg:postcode":"35805",
    "sg:province":"AL",
    "wof:name":"Electrical Local No 558 IBEW",
    "wof:placetype":"venue"
},
  "geometry": {"coordinates":[-86.60463900000001,34.721674],"type":"Point"}
}