{
  "type": "Feature",
  "properties": {
    "iso:country":"US",
    "sg:address":"1294 E Main St",
    "sg:city":"Prattville",
    "sg:classifiers":[
        {
            "category":"Wholesale",
            "subcategory":"Groceries",
            "type":"Manufacturing & Wholesale Goods"
        }
    ],
    "sg:phone":"+1 334 365 5695",
    "sg:postcode":"36066",
    "sg:province":"AL",
    "sg:tags":[
        "general"
    ],
    "wof:name":"Food Sales of Alabama",
    "wof:placetype":"venue"
},
  "geometry": {"coordinates":[-86.436315,32.460381],"type":"Point"}
}