{
  "type": "Feature",
  "properties": {
    "iso:country":"US",
    "sg:address":"303 2nd Ave SE",
    "sg:city":"Decatur",
    "sg:classifiers":[
        {
            "category":"Personal",
            "subcategory":"Barber",
            "type":"Services"
        }
    ],
    "sg:phone":"+1 256 355 1888",
    "sg:postcode":"35601",
    "sg:province":"AL",
    "wof:name":"Genesis",
    "wof:placetype":"venue"
},
  "geometry": {"coordinates":[-86.985174,34.601314],"type":"Point"}
}