{
  "type": "Feature",
  "properties": {
    "iso:country":"US",
    "sg:address":"1816 Ave F",
    "sg:city":"Birmingham",
    "sg:classifiers":[
        {
            "category":"Organizations",
            "subcategory":"Religious Organization",
            "type":"Services"
        }
    ],
    "sg:phone":"+1 205 781 8733",
    "sg:postcode":"35218",
    "sg:province":"AL",
    "wof:name":"Tree of Life Christian Church",
    "wof:placetype":"venue"
},
  "geometry": {"coordinates":[-86.895463,33.513144],"type":"Point"}
}