{
  "type": "Feature",
  "properties": {
    "iso:country":"US",
    "sg:address":"3036 Sterling Rd",
    "sg:city":"Birmingham",
    "sg:classifiers":[
        {
            "category":"Professional",
            "type":"Services"
        }
    ],
    "sg:phone":"+1 205 879 5441",
    "sg:postcode":"35213",
    "sg:province":"AL",
    "wof:name":"Rick & Terri Ferguson",
    "wof:placetype":"venue"
},
  "geometry": {"coordinates":[-86.774837,33.498715],"type":"Point"}
}