{
  "type": "Feature",
  "properties": {
    "addr:full":"118 6th Ave SW Childersburg AL 35044",
    "addr:housenumber":"118",
    "addr:postcode":"35044",
    "addr:street":"6Th Ave Sw",
    "iso:country":"US",
    "sg:address":"118 6th Ave SW",
    "sg:city":"Childersburg",
    "sg:classifiers":[
        {
            "category":"Government",
            "subcategory":"Court House",
            "type":"Public Place"
        }
    ],
    "sg:phone":"+1 256 378 7282",
    "sg:postcode":"35044",
    "sg:province":"AL",
    "sg:tags":[
        "city"
    ],
    "wof:name":"Childersburg Magistrate",
    "wof:placetype":"venue"
},
  "geometry": {"coordinates":[-86.353606,33.27862],"type":"Point"}
}