{
  "type": "Feature",
  "properties": {
    "addr:full":"21582 State Rte 79 Pinson AL 35126",
    "addr:housenumber":"21582",
    "addr:postcode":"35126",
    "addr:street":"State Rte 79",
    "iso:country":"US",
    "sg:address":"21582 State Rte 79",
    "sg:city":"Pinson",
    "sg:classifiers":[
        {
            "category":"Manufacturing",
            "subcategory":"Printing",
            "type":"Manufacturing & Wholesale Goods"
        }
    ],
    "sg:phone":"+1 205 681 2260",
    "sg:postcode":"35126",
    "sg:province":"AL",
    "sg:tags":[
        "lithographic",
        "commercial"
    ],
    "wof:name":"Beaver Printing",
    "wof:placetype":"venue"
},
  "geometry": {"coordinates":[-86.680251,33.803991],"type":"Point"}
}