{
  "type": "Feature",
  "properties": {
    "iso:country":"US",
    "sg:address":"5525 Hampton Heights Dr",
    "sg:city":"Birmingham",
    "sg:classifiers":[
        {
            "category":"Building & Trades",
            "subcategory":"Construction",
            "type":"Services"
        }
    ],
    "sg:phone":"+1 205 942 3165",
    "sg:postcode":"35209",
    "sg:province":"AL",
    "sg:tags":[
        "house"
    ],
    "wof:name":"Scott Gilchrist Designs",
    "wof:placetype":"venue"
},
  "geometry": {"coordinates":[-86.829487,33.470292],"type":"Point"}
}