{
  "type": "Feature",
  "properties": {
    "iso:country":"US",
    "sg:address":"2222 W Clinton Ave",
    "sg:city":"Huntsville",
    "sg:classifiers":[
        {
            "category":"Retail",
            "subcategory":"Auto Repair",
            "type":"Services"
        }
    ],
    "sg:phone":"+1 256 536 8268",
    "sg:postcode":"35805",
    "sg:province":"AL",
    "sg:tags":[
        "repairing",
        "automobile",
        "general"
    ],
    "wof:name":"Fernando's Auto Repair",
    "wof:placetype":"venue"
},
  "geometry": {"coordinates":[-86.601177,34.723677],"type":"Point"}
}