{
  "type": "Feature",
  "properties": {
    "addr:city":"Bessemer",
    "addr:full":"1905 Alabama Ave Bessemer, Al 35020-5009",
    "addr:house_number":"1905",
    "addr:housenumber":"1905",
    "addr:phone":"+1 205-426-1633",
    "addr:postcode":"35020-5009",
    "addr:road":"Alabama Ave",
    "addr:state":"AL",
    "addr:street":"Alabama Ave",
    "iso:country":"US",
    "sg:address":"1905 Alabama Ave",
    "sg:city":"Bessemer",
    "sg:classifiers":[
        {
            "category":"Museum",
            "type":"Entertainment"
        }
    ],
    "sg:phone":"+1 205 426 1633",
    "sg:postcode":"35020",
    "sg:province":"AL",
    "sg:tags":[
        "gallery"
    ],
    "wof:name":"Bessemer Hall Of History",
    "wof:placetype":"venue"
},
  "geometry": {"coordinates":[-86.95050999999999,33.40094],"type":"Point"}
}