{
  "type": "Feature",
  "properties": {
    "iso:country":"US",
    "sg:address":"1905 Alabama Ave",
    "sg:city":"Bessemer",
    "sg:classifiers":[
        {
            "category":"Museum",
            "type":"Entertainment"
        }
    ],
    "sg:phone":"+1 205 426 1633",
    "sg:postcode":"35020",
    "sg:province":"AL",
    "sg:tags":[
        "gallery"
    ],
    "wof:name":"Bessemer Hall Of History",
    "wof:placetype":"venue"
},
  "geometry": {"coordinates":[-86.94968,33.401991],"type":"Point"}
}