{
  "type": "Feature",
  "properties": {
    "iso:country":"US",
    "sg:address":"1250 Inverness Lndg",
    "sg:city":"Birmingham",
    "sg:classifiers":[
        {
            "category":"Health Services",
            "subcategory":"Doctor",
            "type":"Services"
        }
    ],
    "sg:phone":"+1 205 980 0035",
    "sg:postcode":"35242",
    "sg:province":"AL",
    "sg:tags":[
        "physician"
    ],
    "wof:name":"Donna M Bearden",
    "wof:placetype":"venue"
},
  "geometry": {"coordinates":[-86.704179,33.40894],"type":"Point"}
}