{
  "type": "Feature",
  "properties": {
    "iso:country":"US",
    "sg:address":"21833 Co Rd 12 S",
    "sg:city":"Foley",
    "sg:classifiers":[
        {
            "category":"Farming",
            "subcategory":"Nursery",
            "type":"Manufacturing & Wholesale Goods"
        },
        {
            "category":"Building & Trades",
            "subcategory":"Landscaping Services",
            "type":"Services"
        }
    ],
    "sg:phone":"+1 251 955 2000",
    "sg:postcode":"36535",
    "sg:province":"AL",
    "sg:tags":[
        "ornamental",
        "sod",
        "sodding"
    ],
    "wof:name":"Craft Turf Farms",
    "wof:placetype":"venue"
},
  "geometry": {"coordinates":[-87.65246399999999,30.35585],"type":"Point"}
}