{
  "type": "Feature",
  "properties": {
    "addr:full":"1177 Harris Rd Ozark AL 36360",
    "addr:housenumber":"1177",
    "addr:postcode":"36360",
    "addr:street":"Harris Rd",
    "iso:country":"US",
    "sg:address":"1177 Harris Rd",
    "sg:city":"Ozark",
    "sg:classifiers":[
        {
            "category":"Real Estate",
            "subcategory":"Real Estate Operator",
            "type":"Services"
        }
    ],
    "sg:phone":"+1 334 774 0707",
    "sg:postcode":"36360",
    "sg:province":"AL",
    "sg:tags":[
        "apartment"
    ],
    "wof:name":"Harris Hill Apartments",
    "wof:placetype":"venue"
},
  "geometry": {"coordinates":[-85.667055,31.447738],"type":"Point"}
}