{
  "type": "Feature",
  "properties": {
    "iso:country":"US",
    "sg:address":"1408 3rd Ave W",
    "sg:city":"Birmingham",
    "sg:classifiers":[
        {
            "category":"Organizations",
            "subcategory":"Religious Organization",
            "type":"Services"
        },
        {
            "category":"Shopping",
            "subcategory":"Music",
            "type":"Retail Goods"
        }
    ],
    "sg:phone":"+1 205 780 8004",
    "sg:postcode":"35208",
    "sg:province":"AL",
    "sg:tags":[
        "compact",
        "record",
        "disc",
        "tape"
    ],
    "wof:name":"Johnson's Gospel Shop",
    "wof:placetype":"venue"
},
  "geometry": {"coordinates":[-86.861193,33.50519],"type":"Point"}
}