{
  "type": "Feature",
  "properties": {
    "addr:full":"963 Langford Ct Prattville AL 36067",
    "addr:housenumber":"963",
    "addr:postcode":"36067",
    "addr:street":"Langford Ct",
    "iso:country":"US",
    "sg:address":"963 Langford Ct",
    "sg:city":"Prattville",
    "sg:classifiers":[
        {
            "category":"Retail",
            "subcategory":"Auto Repair",
            "type":"Services"
        }
    ],
    "sg:phone":"+1 334 361 1566",
    "sg:postcode":"36067",
    "sg:province":"AL",
    "sg:tags":[
        "body"
    ],
    "wof:name":"All American Auto Body",
    "wof:placetype":"venue"
},
  "geometry": {"coordinates":[-86.45888600000001,32.429142],"type":"Point"}
}