{
  "type": "Feature",
  "properties": {
    "iso:country":"US",
    "sg:address":"918 E 2nd St",
    "sg:city":"Sheffield",
    "sg:classifiers":[
        {
            "category":"Home & Garden",
            "subcategory":"Building Materials",
            "type":"Retail Goods"
        }
    ],
    "sg:phone":"+1 256 383 4586",
    "sg:postcode":"35660",
    "sg:province":"AL",
    "sg:tags":[
        "door"
    ],
    "wof:name":"Shoals Overhead Door LLC",
    "wof:placetype":"venue"
},
  "geometry": {"coordinates":[-87.684264,34.759557],"type":"Point"}
}