{
  "type": "Feature",
  "properties": {
    "addr:full":"1511 E Broad St Gadsden AL 35903",
    "addr:housenumber":"1511",
    "addr:postcode":"35903",
    "addr:street":"E Broad St",
    "iso:country":"US",
    "sg:address":"1511 E Broad St",
    "sg:city":"Gadsden",
    "sg:classifiers":[
        {
            "category":"Autos & Motor Vehicles",
            "subcategory":"Fuel & Gas Station",
            "type":"Retail Goods"
        },
        {
            "category":"Retail",
            "subcategory":"Auto Repair",
            "type":"Services"
        }
    ],
    "sg:phone":"+1 256 492 9321",
    "sg:postcode":"35903",
    "sg:province":"AL",
    "sg:tags":[
        "oil",
        "gasoline"
    ],
    "wof:name":"De Ramus Exxon",
    "wof:placetype":"venue"
},
  "geometry": {"coordinates":[-85.97729699999999,33.99471],"type":"Point"}
}