{
  "type": "Feature",
  "properties": {
    "iso:country":"US",
    "sg:address":"409 Alabama St",
    "sg:city":"Wetumpka",
    "sg:classifiers":[
        {
            "category":"Education",
            "subcategory":"School",
            "type":"Public Place"
        }
    ],
    "sg:phone":"+1 334 567 1248",
    "sg:postcode":"36092",
    "sg:province":"AL",
    "wof:name":"Wetumpka Junior High School",
    "wof:placetype":"venue"
},
  "geometry": {"coordinates":[-86.210664,32.543816],"type":"Point"}
}