{
  "type": "Feature",
  "properties": {
    "addr:full":"27560 State Rte 69 Jasper AL 35504",
    "addr:housenumber":"27560",
    "addr:postcode":"35504",
    "addr:street":"State Rte 69",
    "iso:country":"US",
    "sg:address":"27560 State Rte 69",
    "sg:city":"Jasper",
    "sg:classifiers":[
        {
            "category":"Autos & Motor Vehicles",
            "subcategory":"Auto Supplies",
            "type":"Retail Goods"
        }
    ],
    "sg:phone":"+1 205 384 6629",
    "sg:postcode":"35504",
    "sg:province":"AL",
    "sg:tags":[
        "tire"
    ],
    "wof:name":"Beasley Tires",
    "wof:placetype":"venue"
},
  "geometry": {"coordinates":[-87.18489,33.85217],"type":"Point"}
}