{
  "type": "Feature",
  "properties": {
    "iso:country":"US",
    "sg:address":"2831 Sun Valley Dr",
    "sg:city":"Mobile",
    "sg:classifiers":[
        {
            "category":"Organizations",
            "subcategory":"Religious Organization",
            "type":"Services"
        }
    ],
    "sg:phone":"+1 251 649 4620",
    "sg:postcode":"36618",
    "sg:province":"AL",
    "sg:tags":[
        "church"
    ],
    "wof:name":"Crawford Assembly Of God Chr",
    "wof:placetype":"venue"
},
  "geometry": {"coordinates":[-88.216223,30.754731],"type":"Point"}
}