{
  "type": "Feature",
  "properties": {
    "addr:full":"4900 Hatch Blvd Sheffield AL 35660",
    "addr:postcode":"4900;35660",
    "addr:street":"Hatch Blvd",
    "iso:country":"US",
    "sg:address":"4900 Hatch Blvd",
    "sg:city":"Sheffield",
    "sg:classifiers":[
        {
            "category":"Restaurant",
            "type":"Food & Drink"
        }
    ],
    "sg:phone":"+1 256 381 2736",
    "sg:postcode":"35660",
    "sg:province":"AL",
    "sg:tags":[
        "eating"
    ],
    "wof:name":"Great Southern Mining Co",
    "wof:placetype":"venue"
},
  "geometry": {"coordinates":[-87.66986199999999,34.772557],"type":"Point"}
}