{
  "type": "Feature",
  "properties": {
    "iso:country":"US",
    "sg:address":"3295 Bel Air Mall",
    "sg:city":"Mobile",
    "sg:classifiers":[
        {
            "category":"Restaurant",
            "type":"Food & Drink"
        }
    ],
    "sg:phone":"+1 251 478 5544",
    "sg:postcode":"36606",
    "sg:province":"AL",
    "sg:tags":[
        "eating"
    ],
    "wof:name":"Dibellas Pizza",
    "wof:placetype":"venue"
},
  "geometry": {"coordinates":[-88.123355,30.67333],"type":"Point"}
}