{
  "type": "Feature",
  "properties": {
    "addr:full":"1104 N Pine St Foley AL 36535",
    "addr:housenumber":"1104",
    "addr:postcode":"36535",
    "addr:street":"N Pine St",
    "iso:country":"US",
    "sg:address":"1104 N Pine St",
    "sg:city":"Foley",
    "sg:classifiers":[
        {
            "category":"Personal",
            "subcategory":"Beauty Salon",
            "type":"Services"
        }
    ],
    "sg:phone":"+1 251 943 4961",
    "sg:postcode":"36535",
    "sg:province":"AL",
    "sg:tags":[
        "shop"
    ],
    "wof:name":"Zades Beauty Shop",
    "wof:placetype":"venue"
},
  "geometry": {"coordinates":[-87.687178,30.41975],"type":"Point"}
}