{
  "type": "Feature",
  "properties": {
    "addr:full":"1487 McCurdy Ave S Rainsville AL 35986",
    "addr:housenumber":"1487",
    "addr:postcode":"35986",
    "addr:street":"Mccurdy Ave S Rainsville",
    "iso:country":"US",
    "sg:address":"1487 McCurdy Ave S",
    "sg:city":"Rainsville",
    "sg:classifiers":[
        {
            "category":"Personal",
            "subcategory":"Beauty Salon",
            "type":"Services"
        }
    ],
    "sg:phone":"+1 256 638 6688",
    "sg:postcode":"35986",
    "sg:province":"AL",
    "sg:tags":[
        "shop"
    ],
    "wof:name":"Tracys Salon",
    "wof:placetype":"venue"
},
  "geometry": {"coordinates":[-85.858977,34.476368],"type":"Point"}
}