{
  "type": "Feature",
  "properties": {
    "iso:country":"US",
    "sg:address":"432 Rainbow Dr",
    "sg:city":"Madison",
    "sg:classifiers":[
        {
            "category":"Professional",
            "type":"Services"
        }
    ],
    "sg:phone":"+1 256 721 9404",
    "sg:postcode":"35758",
    "sg:province":"AL",
    "wof:name":"James R Malcolm",
    "wof:placetype":"venue"
},
  "geometry": {"coordinates":[-86.726393,34.748911],"type":"Point"}
}