{
  "type": "Feature",
  "properties": {
    "iso:country":"US",
    "sg:address":"50 Commerce Dr",
    "sg:city":"Pelham",
    "sg:classifiers":[
        {
            "category":"Wholesale",
            "subcategory":"Hardware",
            "type":"Manufacturing & Wholesale Goods"
        }
    ],
    "sg:phone":"+1 205 664 9683",
    "sg:postcode":"35124",
    "sg:province":"AL",
    "wof:name":"Alabama Wholesale Controls",
    "wof:placetype":"venue"
},
  "geometry": {"coordinates":[-86.80163,33.291787],"type":"Point"}
}