{
  "type": "Feature",
  "properties": {
    "iso:country":"US",
    "sg:address":"14391 US Hwy 431",
    "sg:city":"Wedowee",
    "sg:classifiers":[
        {
            "category":"Home & Garden",
            "subcategory":"Carpets & Floor Coverings",
            "type":"Retail Goods"
        }
    ],
    "sg:phone":"+1 256 357 9233",
    "sg:postcode":"36278",
    "sg:province":"AL",
    "wof:name":"Nortons Carpet Shop",
    "wof:placetype":"venue"
},
  "geometry": {"coordinates":[-85.476688,33.292327],"type":"Point"}
}