{
  "type": "Feature",
  "properties": {
    "iso:country":"US",
    "sg:address":"815 Jackson Trace Rd",
    "sg:city":"Wetumpka",
    "sg:classifiers":[
        {
            "category":"Health Services",
            "subcategory":"Doctor",
            "type":"Services"
        }
    ],
    "sg:phone":"+1 334 567 2882",
    "sg:postcode":"36092",
    "sg:province":"AL",
    "sg:tags":[
        "physician",
        "surgeon"
    ],
    "wof:name":"Wetumpka Pediatric Clinic",
    "wof:placetype":"venue"
},
  "geometry": {"coordinates":[-86.190694,32.552677],"type":"Point"}
}