{
  "type": "Feature",
  "properties": {
    "iso:country":"US",
    "sg:address":"4016 Ave I",
    "sg:city":"Birmingham",
    "sg:classifiers":[
        {
            "category":"Recreation",
            "type":"Entertainment"
        }
    ],
    "sg:phone":"+1 205 785 0474",
    "sg:postcode":"35218",
    "sg:province":"AL",
    "wof:name":"Entertainment Center 2000",
    "wof:placetype":"venue"
},
  "geometry": {"coordinates":[-86.903654,33.493479],"type":"Point"}
}