{
  "type": "Feature",
  "properties": {
    "iso:country":"US",
    "sg:address":"409 6th St S",
    "sg:city":"Oneonta",
    "sg:classifiers":[
        {
            "category":"Retail",
            "subcategory":"Auto Repair",
            "type":"Services"
        }
    ],
    "sg:phone":"+1 205 274 2847",
    "sg:postcode":"35121",
    "sg:province":"AL",
    "sg:tags":[
        "automotive",
        "industrial",
        "mfg"
    ],
    "wof:name":"Automotive Machine Co",
    "wof:placetype":"venue"
},
  "geometry": {"coordinates":[-86.462675,33.941692],"type":"Point"}
}