{
  "type": "Feature",
  "properties": {
    "iso:country":"US",
    "sg:address":"5749 Narrow Lane Rd",
    "sg:city":"Montgomery",
    "sg:classifiers":[
        {
            "category":"Organizations",
            "subcategory":"Religious Organization",
            "type":"Services"
        }
    ],
    "sg:phone":"+1 334 612 2200",
    "sg:postcode":"36116",
    "sg:province":"AL",
    "sg:tags":[
        "church"
    ],
    "wof:name":"Apostolic Church Of Christ",
    "wof:placetype":"venue"
},
  "geometry": {"coordinates":[-86.27327,32.297624],"type":"Point"}
}