{
  "type": "Feature",
  "properties": {
    "iso:country":"US",
    "sg:address":"7430 Airport Blvd",
    "sg:city":"Mobile",
    "sg:classifiers":[
        {
            "category":"Autos & Motor Vehicles",
            "subcategory":"Automobile Sales",
            "type":"Retail Goods"
        }
    ],
    "sg:phone":"+1 251 633 2886",
    "sg:postcode":"36608",
    "sg:province":"AL",
    "sg:tags":[
        "car",
        "used",
        "dealer"
    ],
    "wof:name":"M & M Automotive",
    "wof:placetype":"venue"
},
  "geometry": {"coordinates":[-88.21652899999999,30.686715],"type":"Point"}
}