{
  "type": "Feature",
  "properties": {
    "addr:full":"608 8th St S Birmingham AL 35205",
    "addr:housenumber":"608",
    "addr:postcode":"35205",
    "addr:street":"8Th St S",
    "iso:country":"US",
    "sg:address":"608 8th St S",
    "sg:city":"Birmingham",
    "sg:classifiers":[
        {
            "category":"Education",
            "subcategory":"College",
            "type":"Public Place"
        }
    ],
    "sg:phone":"+1 205 934 3447",
    "sg:postcode":"35205",
    "sg:province":"AL",
    "wof:name":"Campus Maintenance",
    "wof:placetype":"venue"
},
  "geometry": {"coordinates":[-86.81690500000001,33.498573],"type":"Point"}
}