{
  "type": "Feature",
  "properties": {
    "iso:country":"US",
    "sg:address":"620 Parkview Dr",
    "sg:city":"Tuscaloosa",
    "sg:classifiers":[
        {
            "category":"Shopping",
            "subcategory":"Computers & Home Electronics",
            "type":"Retail Goods"
        }
    ],
    "sg:phone":"+1 205 752 5511",
    "sg:postcode":"35401",
    "sg:province":"AL",
    "sg:tags":[
        "repair",
        "electrical"
    ],
    "wof:name":"Kincaid TV Stereo Inc",
    "wof:placetype":"venue"
},
  "geometry": {"coordinates":[-87.54815000000001,33.199146],"type":"Point"}
}