{
  "type": "Feature",
  "properties": {
    "iso:country":"US",
    "sg:address":"1118 Saddlebrook Rd",
    "sg:city":"Birmingham",
    "sg:classifiers":[
        {
            "category":"Communications",
            "subcategory":"Film & Video Production",
            "type":"Services"
        }
    ],
    "sg:phone":"+1 205 901 9988",
    "sg:postcode":"35210",
    "sg:province":"AL",
    "sg:tags":[
        "motion"
    ],
    "wof:name":"R C M Production Inc",
    "wof:placetype":"venue"
},
  "geometry": {"coordinates":[-86.656094,33.537432],"type":"Point"}
}