{
  "type": "Feature",
  "properties": {
    "addr:full":"1556 Gulf Shores Pkwy Gulf Shores AL 36542",
    "addr:housenumber":"1556",
    "addr:postcode":"36542",
    "addr:street":"Gulf Shores Pkwy",
    "iso:country":"US",
    "sg:address":"1556 Gulf Shores Pkwy",
    "sg:city":"Gulf Shores",
    "sg:classifiers":[
        {
            "category":"Personal",
            "type":"Services"
        }
    ],
    "sg:phone":"+1 251 968 4637",
    "sg:postcode":"36542",
    "sg:province":"AL",
    "sg:tags":[
        "therapist",
        "massage"
    ],
    "wof:name":"Good Hands Massage Therapy",
    "wof:placetype":"venue"
},
  "geometry": {"coordinates":[-87.68821800000001,30.26984],"type":"Point"}
}