{
  "type": "Feature",
  "properties": {
    "iso:country":"US",
    "sg:address":"212 Mona Dr",
    "sg:city":"Dothan",
    "sg:classifiers":[
        {
            "category":"Freight",
            "type":"Transportation"
        }
    ],
    "sg:phone":"+1 334 793 1196",
    "sg:postcode":"36303",
    "sg:province":"AL",
    "sg:tags":[
        "operator",
        "trucking"
    ],
    "wof:name":"Hammmer Trucking",
    "wof:placetype":"venue"
},
  "geometry": {"coordinates":[-85.409594,31.265035],"type":"Point"}
}