{
  "type": "Feature",
  "properties": {
    "iso:country":"US",
    "sg:address":"222 Green Springs Hwy",
    "sg:city":"Birmingham",
    "sg:classifiers":[
        {
            "category":"Shopping",
            "subcategory":"Crafts & Fabrics",
            "type":"Retail Goods"
        }
    ],
    "sg:phone":"+1 205 942 4545",
    "sg:postcode":"35209",
    "sg:province":"AL",
    "wof:name":"Jo-Ann Fabrics & Crafts",
    "wof:placetype":"venue"
},
  "geometry": {"coordinates":[-86.82248800000001,33.467174],"type":"Point"}
}