{
  "type": "Feature",
  "properties": {
    "iso:country":"US",
    "sg:address":"205 20th St N",
    "sg:city":"Birmingham",
    "sg:classifiers":[
        {
            "category":"Professional",
            "subcategory":"Lawyer & Legal Services",
            "type":"Services"
        },
        {
            "category":"Professional",
            "subcategory":"Accounting & Tax Preparation",
            "type":"Services"
        }
    ],
    "sg:phone":"+1 205 322 2260",
    "sg:postcode":"35203",
    "sg:province":"AL",
    "sg:tags":[
        "attorney",
        "accountant",
        "certified",
        "public"
    ],
    "wof:name":"Hammond Firm",
    "wof:placetype":"venue"
},
  "geometry": {"coordinates":[-86.806487,33.515851],"type":"Point"}
}