{
  "type": "Feature",
  "properties": {
    "addr:full":"3848 State Rte 69 Guntersville AL 35976",
    "addr:housenumber":"3848",
    "addr:postcode":"35976",
    "addr:street":"State Rte 69",
    "iso:country":"US",
    "sg:address":"3848 State Rte 69",
    "sg:city":"Guntersville",
    "sg:classifiers":[
        {
            "category":"Restaurant",
            "type":"Food & Drink"
        }
    ],
    "sg:phone":"+1 256 582 3502",
    "sg:postcode":"35976",
    "sg:province":"AL",
    "sg:tags":[
        "eating"
    ],
    "wof:name":"3 Guys Char Burger",
    "wof:placetype":"venue"
},
  "geometry": {"coordinates":[-86.353031,34.363381],"type":"Point"}
}