{
  "type": "Feature",
  "properties": {
    "iso:country":"US",
    "sg:address":"950 Nova Chemical Blvd",
    "sg:city":"Decatur",
    "sg:classifiers":[
        {
            "category":"Wholesale",
            "subcategory":"Chemicals & Plastics",
            "type":"Manufacturing & Wholesale Goods"
        }
    ],
    "sg:phone":"+1 256 301 9334",
    "sg:postcode":"35601",
    "sg:province":"AL",
    "wof:name":"Novacor Chemical Inc",
    "wof:placetype":"venue"
},
  "geometry": {"coordinates":[-87.016379,34.622301],"type":"Point"}
}