{
  "type": "Feature",
  "properties": {
    "iso:country":"US",
    "sg:address":"369 12th St",
    "sg:city":"Pleasant Grove",
    "sg:classifiers":[
        {
            "category":"Shopping",
            "subcategory":"Jewelry",
            "type":"Retail Goods"
        }
    ],
    "sg:phone":"+1 205 744 4988",
    "sg:postcode":"35127",
    "sg:province":"AL",
    "wof:name":"Time Design",
    "wof:placetype":"venue"
},
  "geometry": {"coordinates":[-86.96692,33.480172],"type":"Point"}
}