{
  "type": "Feature",
  "properties": {
    "iso:country":"US",
    "sg:address":"260 Commerce St",
    "sg:city":"Montgomery",
    "sg:classifiers":[
        {
            "category":"Professional",
            "subcategory":"Management & Consulting",
            "type":"Services"
        }
    ],
    "sg:phone":"+1 334 387 3125",
    "sg:postcode":"36104",
    "sg:province":"AL",
    "sg:tags":[
        "lobbyist",
        "public",
        "relations"
    ],
    "wof:name":"Strategic Consulting Group",
    "wof:placetype":"venue"
},
  "geometry": {"coordinates":[-86.312195,32.380539],"type":"Point"}
}