{
  "type": "Feature",
  "properties": {
    "iso:country":"US",
    "sg:address":"1120 Forest Ave",
    "sg:city":"Jackson",
    "sg:classifiers":[
        {
            "category":"Organizations",
            "subcategory":"Religious Organization",
            "type":"Services"
        }
    ],
    "sg:phone":"+1 251 246 3541",
    "sg:postcode":"36545",
    "sg:province":"AL",
    "sg:tags":[
        "church"
    ],
    "wof:name":"Forest Avenue Baptist Church",
    "wof:placetype":"venue"
},
  "geometry": {"coordinates":[-87.891543,31.523463],"type":"Point"}
}