{
  "type": "Feature",
  "properties": {
    "iso:country":"US",
    "sg:address":"2300 Cedar Key",
    "sg:city":"Mobile",
    "sg:classifiers":[
        {
            "category":"Wholesale",
            "subcategory":"Meat",
            "type":"Manufacturing & Wholesale Goods"
        }
    ],
    "sg:phone":"+1 251 635 1610",
    "sg:postcode":"36695",
    "sg:province":"AL",
    "sg:tags":[
        "representative",
        "mfg"
    ],
    "wof:name":"Harper & Weiskopf Food Mktg",
    "wof:placetype":"venue"
},
  "geometry": {"coordinates":[-88.20568900000001,30.641789],"type":"Point"}
}