{
  "type": "Feature",
  "properties": {
    "addr:full":"1176 Jordan Rd Huntsville AL 35811",
    "addr:housenumber":"1176",
    "addr:postcode":"35811",
    "addr:street":"Jordan Rd",
    "iso:country":"US",
    "sg:address":"1176 Jordan Rd",
    "sg:city":"Huntsville",
    "sg:classifiers":[
        {
            "category":"Wholesale",
            "subcategory":"Chemicals & Plastics",
            "type":"Manufacturing & Wholesale Goods"
        }
    ],
    "sg:phone":"+1 256 851 9170",
    "sg:postcode":"35811",
    "sg:province":"AL",
    "wof:name":"Univar Usa Inc",
    "wof:placetype":"venue"
},
  "geometry": {"coordinates":[-86.531148,34.784976],"type":"Point"}
}