{
  "type": "Feature",
  "properties": {
    "addr:full":"1165 Snow Hinton Dr Tuscaloosa AL 35405",
    "addr:housenumber":"1165",
    "addr:postcode":"35405",
    "addr:street":"Snow Hinton Dr",
    "iso:country":"US",
    "sg:address":"1165 Snow Hinton Dr",
    "sg:city":"Tuscaloosa",
    "sg:classifiers":[
        {
            "category":"Building & Trades",
            "subcategory":"Construction",
            "type":"Services"
        }
    ],
    "sg:phone":"+1 205 758 7753",
    "sg:postcode":"35405",
    "sg:province":"AL",
    "sg:tags":[
        "house"
    ],
    "wof:name":"Jones Construction",
    "wof:placetype":"venue"
},
  "geometry": {"coordinates":[-87.555116,33.129448],"type":"Point"}
}