{
  "type": "Feature",
  "properties": {
    "iso:country":"US",
    "sg:address":"2945 15th St",
    "sg:city":"Tuscaloosa",
    "sg:classifiers":[
        {
            "category":"Retail",
            "subcategory":"Auto Repair",
            "type":"Services"
        }
    ],
    "sg:phone":"+1 205 345 2364",
    "sg:postcode":"35401",
    "sg:province":"AL",
    "sg:tags":[
        "repairing",
        "automobile"
    ],
    "wof:name":"Mitchell Auto Svc",
    "wof:placetype":"venue"
},
  "geometry": {"coordinates":[-87.57288,33.199994],"type":"Point"}
}