{
  "type": "Feature",
  "properties": {
    "iso:country":"US",
    "sg:address":"1708 Main St",
    "sg:city":"Daphne",
    "sg:classifiers":[
        {
            "category":"Professional",
            "subcategory":"Lawyer & Legal Services",
            "type":"Services"
        }
    ],
    "sg:phone":"+1 251 626 1573",
    "sg:postcode":"36526",
    "sg:province":"AL",
    "sg:tags":[
        "attorney"
    ],
    "wof:name":"Crabtree & Sweet PC",
    "wof:placetype":"venue"
},
  "geometry": {"coordinates":[-87.902664,30.603069],"type":"Point"}
}