{
  "type": "Feature",
  "properties": {
    "addr:full":"1 Public Sq E Jacksonville AL 36265",
    "addr:housenumber":"1",
    "addr:postcode":"36265",
    "addr:street":"Public Sq E",
    "iso:country":"US",
    "sg:address":"1 Public Sq E",
    "sg:city":"Jacksonville",
    "sg:classifiers":[
        {
            "category":"Restaurant",
            "type":"Food & Drink"
        }
    ],
    "sg:phone":"+1 256 435 3080",
    "sg:postcode":"36265",
    "sg:province":"AL",
    "wof:name":"Roma's Pizza & Steak House",
    "wof:placetype":"venue"
},
  "geometry": {"coordinates":[-85.76113599999999,33.813452],"type":"Point"}
}