{
  "type": "Feature",
  "properties": {
    "addr:full":"150 N George Wallace Dr Troy AL 36081",
    "addr:housenumber":"150",
    "addr:postcode":"36081",
    "addr:street":"N George Wallace Dr",
    "iso:country":"US",
    "sg:address":"150 N George Wallace Dr",
    "sg:city":"Troy",
    "sg:classifiers":[
        {
            "category":"Education",
            "subcategory":"School",
            "type":"Public Place"
        }
    ],
    "sg:phone":"+1 334 566 3510",
    "sg:postcode":"36081",
    "sg:province":"AL",
    "sg:website":"www.troyschools.net",
    "wof:name":"Charles Henderson High School",
    "wof:placetype":"venue"
},
  "geometry": {"coordinates":[-85.94913,31.807937],"type":"Point"}
}