{
  "type": "Feature",
  "properties": {
    "iso:country":"US",
    "sg:address":"2042 Harmon St",
    "sg:city":"Montgomery",
    "sg:classifiers":[
        {
            "category":"Building & Trades",
            "subcategory":"Construction",
            "type":"Services"
        }
    ],
    "sg:phone":"+1 334 264 5316",
    "sg:postcode":"36107",
    "sg:province":"AL",
    "sg:tags":[
        "house",
        "concrete",
        "contractor"
    ],
    "wof:name":"Rountree Construction",
    "wof:placetype":"venue"
},
  "geometry": {"coordinates":[-86.276224,32.394992],"type":"Point"}
}