{
  "type": "Feature",
  "properties": {
    "iso:country":"US",
    "sg:address":"121 S Court St",
    "sg:city":"Florence",
    "sg:classifiers":[
        {
            "category":"Banks & Credit Unions",
            "subcategory":"Bank",
            "type":"Services"
        }
    ],
    "sg:phone":"+1 256 760 1591",
    "sg:postcode":"35631",
    "sg:province":"AL",
    "sg:tags":[
        "loan",
        "real estate"
    ],
    "wof:name":"Brokers Preferred Home Mtg",
    "wof:placetype":"venue"
},
  "geometry": {"coordinates":[-87.675369,34.799476],"type":"Point"}
}