{
  "type": "Feature",
  "properties": {
    "iso:country":"US",
    "sg:address":"204 Temple Ave S",
    "sg:city":"Fayette",
    "sg:classifiers":[
        {
            "category":"Manufacturing",
            "subcategory":"Printing",
            "type":"Manufacturing & Wholesale Goods"
        }
    ],
    "sg:phone":"+1 205 932 8000",
    "sg:postcode":"35555",
    "sg:province":"AL",
    "sg:tags":[
        "newspaper"
    ],
    "sg:website":"www.cattletoday.com",
    "wof:name":"Cattle Today",
    "wof:placetype":"venue"
},
  "geometry": {"coordinates":[-87.830952,33.683763],"type":"Point"}
}