{
  "type": "Feature",
  "properties": {
    "iso:country":"US",
    "sg:address":"512 S Wilmer Ave",
    "sg:city":"Anniston",
    "sg:classifiers":[
        {
            "category":"Professional",
            "type":"Services"
        }
    ],
    "sg:phone":"+1 256 237 4694",
    "sg:postcode":"36201",
    "sg:province":"AL",
    "sg:tags":[
        "establishment"
    ],
    "wof:name":"Anniston Transit Co",
    "wof:placetype":"venue"
},
  "geometry": {"coordinates":[-85.827307,33.639712],"type":"Point"}
}