{
  "type": "Feature",
  "properties": {
    "addr:full":"2809 Dartmouth Ave Bessemer AL 35020",
    "addr:housenumber":"2809",
    "addr:postcode":"35020",
    "addr:street":"Dartmouth Ave",
    "iso:country":"US",
    "sg:address":"2809 Dartmouth Ave",
    "sg:city":"Bessemer",
    "sg:classifiers":[
        {
            "category":"Shopping",
            "type":"Retail Goods"
        }
    ],
    "sg:phone":"+1 205 481 9293",
    "sg:postcode":"35020",
    "sg:province":"AL",
    "sg:tags":[
        "cosmetic",
        "perfume"
    ],
    "wof:name":"Beauty Masters",
    "wof:placetype":"venue"
},
  "geometry": {"coordinates":[-86.93568999999999,33.409984],"type":"Point"}
}