{
  "type": "Feature",
  "properties": {
    "iso:country":"US",
    "sg:address":"255 Medical Dr",
    "sg:city":"Winfield",
    "sg:classifiers":[
        {
            "category":"Health Services",
            "subcategory":"Doctor",
            "type":"Services"
        }
    ],
    "sg:phone":"+1 205 487 4535",
    "sg:postcode":"35594",
    "sg:province":"AL",
    "sg:tags":[
        "physician",
        "surgeon"
    ],
    "wof:name":"Winfield Neurology & Family",
    "wof:placetype":"venue"
},
  "geometry": {"coordinates":[-87.824067,33.932915],"type":"Point"}
}