{
  "type": "Feature",
  "properties": {
    "iso:country":"US",
    "sg:address":"1104 Gleneagles Dr SW",
    "sg:city":"Huntsville",
    "sg:classifiers":[
        {
            "category":"Social Services",
            "type":"Services"
        }
    ],
    "sg:phone":"+1 256 880 8202",
    "sg:postcode":"35801",
    "sg:province":"AL",
    "sg:tags":[
        "professional",
        "counselor"
    ],
    "wof:name":"Hearth Psychology & Counseling",
    "wof:placetype":"venue"
},
  "geometry": {"coordinates":[-86.580067,34.693775],"type":"Point"}
}