{
  "type": "Feature",
  "properties": {
    "iso:country":"US",
    "sg:address":"516 Quintard Ave",
    "sg:city":"Anniston",
    "sg:classifiers":[
        {
            "category":"Health Services",
            "subcategory":"Doctor",
            "type":"Services"
        }
    ],
    "sg:phone":"+1 256 741 9799",
    "sg:postcode":"36201",
    "sg:province":"AL",
    "sg:tags":[
        "clinic"
    ],
    "wof:name":"Purohit Pediatric Clinic",
    "wof:placetype":"venue"
},
  "geometry": {"coordinates":[-85.826867,33.65093],"type":"Point"}
}