{
  "type": "Feature",
  "properties": {
    "iso:country":"US",
    "sg:address":"4005 Offutt Ct NW",
    "sg:city":"Huntsville",
    "sg:classifiers":[
        {
            "category":"Retail",
            "subcategory":"Repair Shop",
            "type":"Services"
        }
    ],
    "sg:phone":"+1 256 746 0440",
    "sg:postcode":"35810",
    "sg:province":"AL",
    "sg:tags":[
        "appliance"
    ],
    "wof:name":"Jones & Horton Appl Repair",
    "wof:placetype":"venue"
},
  "geometry": {"coordinates":[-86.608636,34.779959],"type":"Point"}
}