{
  "type": "Feature",
  "properties": {
    "iso:country":"US",
    "sg:address":"205 State Hwy 160",
    "sg:city":"Warrior",
    "sg:classifiers":[
        {
            "category":"Utilities",
            "subcategory":"Water",
            "type":"Services"
        }
    ],
    "sg:phone":"+1 205 647 5525",
    "sg:postcode":"35180",
    "sg:province":"AL",
    "sg:tags":[
        "public"
    ],
    "wof:name":"Blount County Water Authority",
    "wof:placetype":"venue"
},
  "geometry": {"coordinates":[-86.824612,33.849125],"type":"Point"}
}