{
  "type": "Feature",
  "properties": {
    "iso:country":"US",
    "sg:address":"1001 Pelham Rd S",
    "sg:city":"Jacksonville",
    "sg:classifiers":[
        {
            "category":"Professional",
            "type":"Services"
        }
    ],
    "sg:phone":"+1 256 435 5005",
    "sg:postcode":"36265",
    "sg:province":"AL",
    "wof:name":"John S Clark Inc",
    "wof:placetype":"venue"
},
  "geometry": {"coordinates":[-85.76106799999999,33.794769],"type":"Point"}
}