{
  "type": "Feature",
  "properties": {
    "iso:country":"US",
    "sg:address":"2201 Pelham Pkwy",
    "sg:city":"Pelham",
    "sg:classifiers":[
        {
            "category":"Wholesale",
            "subcategory":"Hardware",
            "type":"Manufacturing & Wholesale Goods"
        }
    ],
    "sg:phone":"+1 205 988 5505",
    "sg:postcode":"35124",
    "sg:province":"AL",
    "sg:tags":[
        "air",
        "parts",
        "conditioning",
        "supply"
    ],
    "wof:name":"Wittichen Supply Co",
    "wof:placetype":"venue"
},
  "geometry": {"coordinates":[-86.791686,33.333484],"type":"Point"}
}