{
  "type": "Feature",
  "properties": {
    "iso:country":"US",
    "sg:address":"556 S Saint Andrews Str",
    "sg:city":"Dothan",
    "sg:classifiers":[
        {
            "category":"Banks & Credit Unions",
            "subcategory":"Investment Brokerage",
            "type":"Services"
        }
    ],
    "sg:phone":"+1 334 794 2245",
    "sg:postcode":"36301",
    "sg:province":"AL",
    "sg:tags":[
        "corporate",
        "bond"
    ],
    "wof:name":"Herring Bonding Co",
    "wof:placetype":"venue"
},
  "geometry": {"coordinates":[-85.389818,31.217573],"type":"Point"}
}