{
  "type": "Feature",
  "properties": {
    "addr:full":"10 Marlette Dr Selma AL 36701",
    "addr:housenumber":"10",
    "addr:postcode":"36701",
    "addr:street":"Marlette Dr",
    "iso:country":"US",
    "sg:address":"10 Marlette Dr",
    "sg:city":"Selma",
    "sg:classifiers":[
        {
            "category":"Personal",
            "subcategory":"Beauty Salon",
            "type":"Services"
        }
    ],
    "sg:phone":"+1 334 875 4976",
    "sg:postcode":"36701",
    "sg:province":"AL",
    "wof:name":"Naomi's Masterpiece",
    "wof:placetype":"venue"
},
  "geometry": {"coordinates":[-87.01023499999999,32.377902],"type":"Point"}
}