{
  "type": "Feature",
  "properties": {
    "iso:country":"US",
    "sg:address":"43 Hunters Trce",
    "sg:city":"Pelham",
    "sg:classifiers":[
        {
            "category":"Building & Trades",
            "subcategory":"Construction",
            "type":"Services"
        }
    ],
    "sg:phone":"+1 205 664 8220",
    "sg:postcode":"35124",
    "sg:province":"AL",
    "sg:tags":[
        "contractor"
    ],
    "wof:name":"Dan Williams Tile Co",
    "wof:placetype":"venue"
},
  "geometry": {"coordinates":[-86.786144,33.291652],"type":"Point"}
}