{
  "type": "Feature",
  "properties": {
    "addr:full":"236 Distribution Dr Birmingham AL 35209",
    "addr:housenumber":"236",
    "addr:postcode":"35209",
    "addr:street":"Distribution Dr",
    "iso:country":"US",
    "sg:address":"236 Distribution Dr",
    "sg:city":"Birmingham",
    "sg:classifiers":[
        {
            "category":"Freight",
            "type":"Transportation"
        }
    ],
    "sg:phone":"+1 205 943 2000",
    "sg:postcode":"35209",
    "sg:province":"AL",
    "sg:tags":[
        "operator",
        "local",
        "trucking"
    ],
    "wof:name":"Orbis Logistics",
    "wof:placetype":"venue"
},
  "geometry": {"coordinates":[-86.843362,33.444761],"type":"Point"}
}