{
  "type": "Feature",
  "properties": {
    "iso:country":"US",
    "sg:address":"1410 US Hwy 98",
    "sg:city":"Daphne",
    "sg:classifiers":[
        {
            "category":"Professional",
            "subcategory":"Advertising",
            "type":"Services"
        }
    ],
    "sg:phone":"+1 251 694 6780",
    "sg:postcode":"36526",
    "sg:province":"AL",
    "sg:tags":[
        "representative"
    ],
    "wof:name":"The Mobile Press Register",
    "wof:placetype":"venue"
},
  "geometry": {"coordinates":[-87.89805800000001,30.596121],"type":"Point"}
}