{
  "type": "Feature",
  "properties": {
    "iso:country":"US",
    "sg:address":"9095 Ashley Ct",
    "sg:city":"Daphne",
    "sg:classifiers":[
        {
            "category":"Retail",
            "subcategory":"Repair Shop",
            "type":"Services"
        }
    ],
    "sg:phone":"+1 251 621 6708",
    "sg:postcode":"36526",
    "sg:province":"AL",
    "wof:name":"Pro Master Pressure Cleaning",
    "wof:placetype":"venue"
},
  "geometry": {"coordinates":[-87.868713,30.613972],"type":"Point"}
}