{
  "type": "Feature",
  "properties": {
    "addr:full":"1538 Sommerville Rd SE Decatur AL 35601",
    "addr:housenumber":"1538",
    "addr:postcode":"35601",
    "addr:street":"Sommerville Rd Se",
    "iso:country":"US",
    "sg:address":"1538 Sommerville Rd SE",
    "sg:city":"Decatur",
    "sg:classifiers":[
        {
            "category":"Retail",
            "subcategory":"Repair Shop",
            "type":"Services"
        }
    ],
    "sg:phone":"+1 256 810 1958",
    "sg:postcode":"35601",
    "sg:province":"AL",
    "wof:name":"Perfection Cleaners",
    "wof:placetype":"venue"
},
  "geometry": {"coordinates":[-86.972703,34.581322],"type":"Point"}
}