{
  "type": "Feature",
  "properties": {
    "iso:country":"US",
    "sg:address":"3014 Governors Dr SE",
    "sg:city":"Huntsville",
    "sg:classifiers":[
        {
            "category":"Professional",
            "subcategory":"Advertising",
            "type":"Services"
        }
    ],
    "sg:phone":"+1 256 536 2273",
    "sg:postcode":"35801",
    "sg:province":"AL",
    "sg:tags":[
        "mailing",
        "shipping"
    ],
    "wof:name":"Hammett Enterprises",
    "wof:placetype":"venue"
},
  "geometry": {"coordinates":[-86.538886,34.711557],"type":"Point"}
}