{
  "type": "Feature",
  "properties": {
    "iso:country":"US",
    "sg:address":"7755 McKinley Ave",
    "sg:city":"Mobile",
    "sg:classifiers":[
        {
            "category":"Personal",
            "type":"Services"
        }
    ],
    "sg:phone":"+1 251 607 7272",
    "sg:postcode":"36608",
    "sg:province":"AL",
    "wof:name":"Tropical Tattoo",
    "wof:placetype":"venue"
},
  "geometry": {"coordinates":[-88.22489400000001,30.697174],"type":"Point"}
}