{
  "type": "Feature",
  "properties": {
    "addr:full":"415 Old Hwy 31 Warrior AL 35180",
    "addr:housenumber":"415",
    "addr:postcode":"35180",
    "addr:street":"Old Hwy 31 Warrior",
    "iso:country":"US",
    "sg:address":"415 Old Hwy 31",
    "sg:city":"Warrior",
    "sg:classifiers":[
        {
            "category":"Shopping",
            "subcategory":"Discount & Variety Stores",
            "type":"Retail Goods"
        }
    ],
    "sg:phone":"+1 205 590 0092",
    "sg:postcode":"35180",
    "sg:province":"AL",
    "wof:name":"Dollar General",
    "wof:placetype":"venue"
},
  "geometry": {"coordinates":[-86.825412,33.79643],"type":"Point"}
}