{
  "type": "Feature",
  "properties": {
    "iso:country":"US",
    "sg:address":"5117 Post Oak Rd",
    "sg:city":"Anniston",
    "sg:classifiers":[
        {
            "category":"Organizations",
            "subcategory":"Religious Organization",
            "type":"Services"
        }
    ],
    "sg:phone":"+1 256 236 1464",
    "sg:postcode":"36206",
    "sg:province":"AL",
    "sg:tags":[
        "church"
    ],
    "sg:website":"www.hcministries.org",
    "wof:name":"Hill Crest Baptist Church Inc",
    "wof:placetype":"venue"
},
  "geometry": {"coordinates":[-85.851596,33.712745],"type":"Point"}
}