{
  "type": "Feature",
  "properties": {
    "iso:country":"US",
    "sg:address":"426 15th Ter NW",
    "sg:city":"Center Point",
    "sg:classifiers":[
        {
            "category":"Autos & Motor Vehicles",
            "subcategory":"Auto Supplies",
            "type":"Retail Goods"
        },
        {
            "category":"Personal",
            "type":"Services"
        },
        {
            "category":"Retail",
            "subcategory":"Auto Repair",
            "type":"Services"
        }
    ],
    "sg:phone":"+1 205 853 6185",
    "sg:postcode":"35215",
    "sg:province":"AL",
    "sg:tags":[
        "towing",
        "tire"
    ],
    "wof:name":"Center Point Auto Service & Wrecker",
    "wof:placetype":"venue"
},
  "geometry": {"coordinates":[-86.693867,33.627334],"type":"Point"}
}