{
  "type": "Feature",
  "properties": {
    "iso:country":"US",
    "sg:address":"300 Magnolia Ave",
    "sg:city":"Fairhope",
    "sg:classifiers":[
        {
            "category":"Health Services",
            "subcategory":"Health Practitioner",
            "type":"Services"
        }
    ],
    "sg:phone":"+1 251 990 4770",
    "sg:postcode":"36532",
    "sg:province":"AL",
    "wof:name":"Two Hands Massage Therapy",
    "wof:placetype":"venue"
},
  "geometry": {"coordinates":[-87.902998,30.524434],"type":"Point"}
}