{
  "type": "Feature",
  "properties": {
    "iso:country":"US",
    "sg:address":"1610 Hartford Hwy",
    "sg:city":"Dothan",
    "sg:classifiers":[
        {
            "category":"Retail",
            "subcategory":"Repair Shop",
            "type":"Services"
        }
    ],
    "sg:phone":"+1 334 792 0551",
    "sg:postcode":"36301",
    "sg:province":"AL",
    "wof:name":"Dothan Electronic Svc",
    "wof:placetype":"venue"
},
  "geometry": {"coordinates":[-85.419166,31.211129],"type":"Point"}
}