{
  "type": "Feature",
  "properties": {
    "iso:country":"US",
    "sg:address":"108 Lancaster Ct",
    "sg:city":"Dothan",
    "sg:classifiers":[
        {
            "category":"Shopping",
            "subcategory":"Florist",
            "type":"Retail Goods"
        }
    ],
    "sg:phone":"+1 334 702 8191",
    "sg:postcode":"36305",
    "sg:province":"AL",
    "wof:name":"Heart 'N' Home",
    "wof:placetype":"venue"
},
  "geometry": {"coordinates":[-85.461653,31.224007],"type":"Point"}
}