{
  "type": "Feature",
  "properties": {
    "iso:country":"US",
    "sg:address":"3206 6th Ave SW",
    "sg:city":"Huntsville",
    "sg:classifiers":[
        {
            "category":"Retail",
            "subcategory":"Auto Repair",
            "type":"Services"
        }
    ],
    "sg:phone":"+1 256 533 0470",
    "sg:postcode":"35805",
    "sg:province":"AL",
    "sg:tags":[
        "repairing",
        "automobile"
    ],
    "wof:name":"D & R Auto",
    "wof:placetype":"venue"
},
  "geometry": {"coordinates":[-86.610424,34.719077],"type":"Point"}
}