{
  "type": "Feature",
  "properties": {
    "iso:country":"US",
    "sg:address":"122 7th Ave NE",
    "sg:city":"Alabaster",
    "sg:classifiers":[
        {
            "category":"Professional",
            "subcategory":"Accounting & Tax Preparation",
            "type":"Services"
        }
    ],
    "sg:phone":"+1 205 621 2758",
    "sg:postcode":"35007",
    "sg:province":"AL",
    "sg:tags":[
        "accountant"
    ],
    "wof:name":"Cameron & Co",
    "wof:placetype":"venue"
},
  "geometry": {"coordinates":[-86.81356700000001,33.251165],"type":"Point"}
}