{
  "type": "Feature",
  "properties": {
    "addr:full":"2000 Highland Ave S Birmingham AL 35205",
    "addr:housenumber":"2000",
    "addr:postcode":"35205",
    "addr:street":"Highland Ave S",
    "iso:country":"US",
    "sg:address":"2000 Highland Ave S",
    "sg:city":"Birmingham",
    "sg:classifiers":[
        {
            "category":"Restaurant",
            "type":"Food & Drink"
        }
    ],
    "sg:menulink":"http://www.allmenus.com/al/birmingham/103421-ruby-tuesdays/menu/",
    "sg:phone":"+1 205 939 1566",
    "sg:postcode":"35205",
    "sg:province":"AL",
    "sg:tags":[
        "burger",
        "american"
    ],
    "wof:name":"Ruby Tuesdays",
    "wof:placetype":"venue"
},
  "geometry": {"coordinates":[-86.794837,33.499697],"type":"Point"}
}