{
  "type": "Feature",
  "properties": {
    "iso:country":"US",
    "sg:address":"120 Collier Dr",
    "sg:city":"Albertville",
    "sg:classifiers":[
        {
            "category":"Organizations",
            "subcategory":"Religious Organization",
            "type":"Services"
        }
    ],
    "sg:phone":"+1 256 878 2240",
    "sg:postcode":"35951",
    "sg:province":"AL",
    "wof:name":"Chapel Weddings",
    "wof:placetype":"venue"
},
  "geometry": {"coordinates":[-86.19691,34.287576],"type":"Point"}
}