{
  "type": "Feature",
  "properties": {
    "iso:country":"US",
    "sg:address":"1240 9th Ave N",
    "sg:city":"Bessemer",
    "sg:classifiers":[
        {
            "category":"Autos & Motor Vehicles",
            "subcategory":"Automobile Sales",
            "type":"Retail Goods"
        }
    ],
    "sg:phone":"+1 205 428 1411",
    "sg:postcode":"35020",
    "sg:province":"AL",
    "sg:tags":[
        "wholesale",
        "used",
        "dealer",
        "car"
    ],
    "wof:name":"Dawson's Auto & Truck Sales",
    "wof:placetype":"venue"
},
  "geometry": {"coordinates":[-86.967204,33.399022],"type":"Point"}
}