{
  "type": "Feature",
  "properties": {
    "iso:country":"US",
    "sg:address":"1115 Bright Star Rd",
    "sg:city":"Horton",
    "sg:classifiers":[
        {
            "category":"Building & Trades",
            "subcategory":"Plumbing",
            "type":"Services"
        }
    ],
    "sg:phone":"+1 205 466 7520",
    "sg:postcode":"35980",
    "sg:province":"AL",
    "sg:tags":[
        "air",
        "heating",
        "conditioning",
        "contractor"
    ],
    "wof:name":"Copeland Heating & AC",
    "wof:placetype":"venue"
},
  "geometry": {"coordinates":[-86.428915,34.15698],"type":"Point"}
}