{
  "type": "Feature",
  "properties": {
    "addr:full":"475 Spring Valley Rd Tuscumbia AL 35674",
    "addr:housenumber":"475",
    "addr:postcode":"35674",
    "addr:street":"Spring Valley Rd",
    "iso:country":"US",
    "sg:address":"475 Spring Valley Rd",
    "sg:city":"Tuscumbia",
    "sg:classifiers":[
        {
            "category":"Manufacturing",
            "subcategory":"Tools & Machinery",
            "type":"Manufacturing & Wholesale Goods"
        }
    ],
    "sg:phone":"+1 256 381 8999",
    "sg:postcode":"35674",
    "sg:province":"AL",
    "sg:tags":[
        "melting",
        "furnace",
        "aluminum",
        "mfg"
    ],
    "wof:name":"Melt-Tech Inc",
    "wof:placetype":"venue"
},
  "geometry": {"coordinates":[-87.65775499999999,34.660672],"type":"Point"}
}