{
  "type": "Feature",
  "properties": {
    "addr:full":"606 Kimberly Dr SW Hartselle AL 35640",
    "addr:housenumber":"606",
    "addr:postcode":"35640",
    "addr:street":"Kimberly Dr Sw",
    "iso:country":"US",
    "sg:address":"606 Kimberly Dr SW",
    "sg:city":"Hartselle",
    "sg:classifiers":[
        {
            "category":"Building & Trades",
            "subcategory":"Construction",
            "type":"Services"
        }
    ],
    "sg:phone":"+1 256 773 3012",
    "sg:postcode":"35640",
    "sg:province":"AL",
    "sg:tags":[
        "house"
    ],
    "wof:name":"Pham Construction LLC",
    "wof:placetype":"venue"
},
  "geometry": {"coordinates":[-86.940209,34.418241],"type":"Point"}
}