{
  "type": "Feature",
  "properties": {
    "iso:country":"US",
    "sg:address":"109 Brookshire Ln",
    "sg:city":"Pelham",
    "sg:classifiers":[
        {
            "category":"Professional",
            "subcategory":"Business Services",
            "type":"Services"
        }
    ],
    "sg:phone":"+1 205 620 0491",
    "sg:postcode":"35124",
    "sg:province":"AL",
    "wof:name":"Services In Chars Special",
    "wof:placetype":"venue"
},
  "geometry": {"coordinates":[-86.794122,33.28533],"type":"Point"}
}