{
  "type": "Feature",
  "properties": {
    "iso:country":"US",
    "sg:address":"38 US Hwy 431",
    "sg:city":"Boaz",
    "sg:classifiers":[
        {
            "category":"Autos & Motor Vehicles",
            "subcategory":"Motorcycle Sales",
            "type":"Retail Goods"
        }
    ],
    "sg:phone":"+1 256 840 9005",
    "sg:postcode":"35957",
    "sg:province":"AL",
    "sg:tags":[
        "scooter"
    ],
    "wof:name":"DMC Fast Bikes",
    "wof:placetype":"venue"
},
  "geometry": {"coordinates":[-86.14723499999999,34.190742],"type":"Point"}
}