{
  "type": "Feature",
  "properties": {
    "iso:country":"US",
    "sg:address":"27366 US Hwy 278",
    "sg:city":"Addison",
    "sg:classifiers":[
        {
            "category":"Retail",
            "subcategory":"Auto Repair",
            "type":"Services"
        }
    ],
    "sg:phone":"+1 205 489 8033",
    "sg:postcode":"35540",
    "sg:province":"AL",
    "sg:tags":[
        "general"
    ],
    "wof:name":"Bakers Garage",
    "wof:placetype":"venue"
},
  "geometry": {"coordinates":[-87.222481,34.187054],"type":"Point"}
}