{
  "type": "Feature",
  "properties": {
    "iso:country":"US",
    "sg:address":"908 31st Ave",
    "sg:city":"Tuscaloosa",
    "sg:classifiers":[
        {
            "category":"Retail",
            "subcategory":"Auto Repair",
            "type":"Services"
        }
    ],
    "sg:phone":"+1 205 752 5523",
    "sg:postcode":"35401",
    "sg:province":"AL",
    "sg:tags":[
        "alternator",
        "generator"
    ],
    "wof:name":"H-C Auto Electric Co",
    "wof:placetype":"venue"
},
  "geometry": {"coordinates":[-87.575893,33.202553],"type":"Point"}
}