{
  "type": "Feature",
  "properties": {
    "iso:country":"US",
    "sg:address":"2326 3rd St SW",
    "sg:city":"Attalla",
    "sg:classifiers":[
        {
            "category":"Manufacturing",
            "subcategory":"Metals",
            "type":"Manufacturing & Wholesale Goods"
        }
    ],
    "sg:phone":"+1 256 538 6851",
    "sg:postcode":"35954",
    "sg:province":"AL",
    "sg:tags":[
        "fabricator",
        "aluminum"
    ],
    "wof:name":"Powell's Custom Curving",
    "wof:placetype":"venue"
},
  "geometry": {"coordinates":[-86.126423,33.996778],"type":"Point"}
}