{
  "type": "Feature",
  "properties": {
    "iso:country":"US",
    "sg:address":"2875 Woodley Rd",
    "sg:city":"Montgomery",
    "sg:classifiers":[
        {
            "category":"Recreation",
            "type":"Entertainment"
        }
    ],
    "sg:phone":"+1 334 281 2423",
    "sg:postcode":"36111",
    "sg:province":"AL",
    "sg:tags":[
        "instruction",
        "yoga"
    ],
    "wof:name":"Dee Morris & Co",
    "wof:placetype":"venue"
},
  "geometry": {"coordinates":[-86.268132,32.332172],"type":"Point"}
}