{
  "type": "Feature",
  "properties": {
    "addr:full":"2303 Dobbs Dr Phenix City AL 36870",
    "addr:housenumber":"2303",
    "addr:postcode":"36870",
    "addr:street":"Dobbs Dr Phenix",
    "iso:country":"US",
    "sg:address":"2303 Dobbs Dr",
    "sg:city":"Phenix City",
    "sg:classifiers":[
        {
            "category":"Professional",
            "subcategory":"Business Services",
            "type":"Services"
        }
    ],
    "sg:phone":"+1 334 480 0367",
    "sg:postcode":"36870",
    "sg:province":"AL",
    "wof:name":"Hallam Enterprises",
    "wof:placetype":"venue"
},
  "geometry": {"coordinates":[-85.044337,32.483413],"type":"Point"}
}