{
  "type": "Feature",
  "properties": {
    "iso:country":"US",
    "sg:address":"152 Edwards Ln",
    "sg:city":"Grant",
    "sg:classifiers":[
        {
            "category":"Farming",
            "subcategory":"Farm",
            "type":"Manufacturing & Wholesale Goods"
        }
    ],
    "sg:phone":"+1 256 728 4673",
    "sg:postcode":"35747",
    "sg:province":"AL",
    "sg:tags":[
        "crop",
        "general"
    ],
    "wof:name":"Double E Farms",
    "wof:placetype":"venue"
},
  "geometry": {"coordinates":[-86.218737,34.512626],"type":"Point"}
}