{
  "type": "Feature",
  "properties": {
    "iso:country":"US",
    "sg:address":"1875 Co Rd 213",
    "sg:city":"Hollywood",
    "sg:classifiers":[
        {
            "category":"Organizations",
            "subcategory":"Religious Organization",
            "type":"Services"
        }
    ],
    "sg:phone":"+1 256 437 1010",
    "sg:postcode":"35752",
    "sg:province":"AL",
    "wof:name":"Lakeview Baptist Church",
    "wof:placetype":"venue"
},
  "geometry": {"coordinates":[-85.89703,34.758817],"type":"Point"}
}