{
  "type": "Feature",
  "properties": {
    "addr:full":"1569 Cooper Hill Rd Birmingham AL 35210",
    "addr:housenumber":"1569",
    "addr:postcode":"35210",
    "addr:street":"Cooper Hill Rd",
    "iso:country":"US",
    "sg:address":"1569 Cooper Hill Rd",
    "sg:city":"Birmingham",
    "sg:classifiers":[
        {
            "category":"Shopping",
            "subcategory":"Used Merchandise",
            "type":"Retail Goods"
        }
    ],
    "sg:phone":"+1 205 956 5658",
    "sg:postcode":"35210",
    "sg:province":"AL",
    "wof:name":"Mission Possible Bargain Ctr",
    "wof:placetype":"venue"
},
  "geometry": {"coordinates":[-86.725872,33.525926],"type":"Point"}
}