{
  "type": "Feature",
  "properties": {
    "iso:country":"US",
    "sg:address":"1117 Richmond St",
    "sg:city":"Birmingham",
    "sg:classifiers":[
        {
            "category":"Organizations",
            "subcategory":"Religious Organization",
            "type":"Services"
        }
    ],
    "sg:phone":"+1 205 785 1712",
    "sg:postcode":"35224",
    "sg:province":"AL",
    "wof:name":"Whole Truth Chrch God In Chrst",
    "wof:placetype":"venue"
},
  "geometry": {"coordinates":[-86.932529,33.501366],"type":"Point"}
}