{
  "type": "Feature",
  "properties": {
    "iso:country":"US",
    "sg:address":"413 Kimberly Dr",
    "sg:city":"Auburn",
    "sg:classifiers":[
        {
            "category":"Professional",
            "subcategory":"Engineering",
            "type":"Services"
        }
    ],
    "sg:phone":"+1 334 821 1491",
    "sg:postcode":"36832",
    "sg:province":"AL",
    "wof:name":"Harper Engineering",
    "wof:placetype":"venue"
},
  "geometry": {"coordinates":[-85.482181,32.580352],"type":"Point"}
}