{
  "type": "Feature",
  "properties": {
    "addr:full":"2461 Old Shell Rd Mobile AL 36607",
    "addr:housenumber":"2461",
    "addr:postcode":"36607",
    "addr:street":"Old Shell Rd",
    "iso:country":"US",
    "sg:address":"2461 Old Shell Rd",
    "sg:city":"Mobile",
    "sg:classifiers":[
        {
            "category":"Retail",
            "subcategory":"Laundry & Dry Cleaning",
            "type":"Services"
        }
    ],
    "sg:phone":"+1 251 473 4984",
    "sg:postcode":"36607",
    "sg:province":"AL",
    "sg:tags":[
        "cleaners"
    ],
    "wof:name":"Waite's Cleaners",
    "wof:placetype":"venue"
},
  "geometry": {"coordinates":[-88.098759,30.690302],"type":"Point"}
}