{
  "type": "Feature",
  "properties": {
    "iso:country":"US",
    "sg:address":"1606 Laurel Wood Ln",
    "sg:city":"Montgomery",
    "sg:classifiers":[
        {
            "category":"Shopping",
            "type":"Retail Goods"
        }
    ],
    "sg:phone":"+1 334 272 3105",
    "sg:postcode":"36117",
    "sg:province":"AL",
    "sg:tags":[
        "cosmetic",
        "perfume"
    ],
    "wof:name":"Mary Kay Cosmetics",
    "wof:placetype":"venue"
},
  "geometry": {"coordinates":[-86.18414300000001,32.341803],"type":"Point"}
}