{
  "type": "Feature",
  "properties": {
    "iso:country":"US",
    "sg:address":"2109 Marvyn Pkwy",
    "sg:city":"Opelika",
    "sg:classifiers":[
        {
            "category":"Retail",
            "subcategory":"Auto Rental",
            "type":"Services"
        }
    ],
    "sg:phone":"+1 334 749 1413",
    "sg:postcode":"36804",
    "sg:province":"AL",
    "sg:tags":[
        "renting",
        "truck",
        "leasing"
    ],
    "wof:name":"Budget Truck Rental",
    "wof:placetype":"venue"
},
  "geometry": {"coordinates":[-85.371358,32.625648],"type":"Point"}
}