{
  "type": "Feature",
  "properties": {
    "iso:country":"US",
    "sg:address":"1516 W Highland Ave",
    "sg:city":"Selma",
    "sg:classifiers":[
        {
            "category":"Restaurant",
            "type":"Food & Drink"
        }
    ],
    "sg:menulink":"http://www.allmenus.com/al/selma/100559-captain-ds-seafood/menu/",
    "sg:phone":"+1 334 872 7000",
    "sg:postcode":"36701",
    "sg:province":"AL",
    "sg:tags":[
        "seafood",
        "american"
    ],
    "wof:name":"Captain D's Seafood",
    "wof:placetype":"venue"
},
  "geometry": {"coordinates":[-87.043857,32.432371],"type":"Point"}
}