{
  "type": "Feature",
  "properties": {
    "iso:country":"US",
    "sg:address":"2529 Moody Pkwy",
    "sg:city":"Moody",
    "sg:classifiers":[
        {
            "category":"Personal",
            "subcategory":"Barber",
            "type":"Services"
        }
    ],
    "sg:phone":"+1 205 640 7361",
    "sg:postcode":"35004",
    "sg:province":"AL",
    "wof:name":"Gaye Austin Barber & Style",
    "wof:placetype":"venue"
},
  "geometry": {"coordinates":[-86.514628,33.576904],"type":"Point"}
}