{
  "type": "Feature",
  "properties": {
    "iso:country":"US",
    "sg:address":"781 Alabama Ave",
    "sg:city":"Monroeville",
    "sg:classifiers":[
        {
            "category":"Real Estate",
            "subcategory":"Real Estate Agent",
            "type":"Services"
        }
    ],
    "sg:phone":"+1 251 575 4291",
    "sg:postcode":"36460",
    "sg:province":"AL",
    "wof:name":"Farish Agency",
    "wof:placetype":"venue"
},
  "geometry": {"coordinates":[-87.322304,31.517393],"type":"Point"}
}