{
  "type": "Feature",
  "properties": {
    "addr:full":"701 W Fort Williams St Sylacauga AL 35150",
    "addr:housenumber":"701",
    "addr:postcode":"35150",
    "addr:street":"W Fort Williams St",
    "iso:country":"US",
    "sg:address":"701 W Fort Williams St",
    "sg:city":"Sylacauga",
    "sg:classifiers":[
        {
            "category":"Restaurant",
            "type":"Food & Drink"
        }
    ],
    "sg:phone":"+1 256 249 4611",
    "sg:postcode":"35150",
    "sg:province":"AL",
    "wof:name":"Mc Donald's",
    "wof:placetype":"venue"
},
  "geometry": {"coordinates":[-86.260312,33.167283],"type":"Point"}
}