{
  "type": "Feature",
  "properties": {
    "addr:full":"29 Sweet Ave Birmingham AL 35217",
    "addr:housenumber":"29",
    "addr:postcode":"35217",
    "addr:street":"Sweet Ave",
    "iso:country":"US",
    "sg:address":"29 Sweet Ave",
    "sg:city":"Birmingham",
    "sg:classifiers":[
        {
            "category":"Personal",
            "subcategory":"Beauty Salon",
            "type":"Services"
        }
    ],
    "sg:phone":"+1 205 841 8871",
    "sg:postcode":"35217",
    "sg:province":"AL",
    "sg:tags":[
        "shop"
    ],
    "wof:name":"Mary BS Beauty Salon",
    "wof:placetype":"venue"
},
  "geometry": {"coordinates":[-86.77847,33.585868],"type":"Point"}
}