{
  "type": "Feature",
  "properties": {
    "iso:country":"US",
    "sg:address":"814 16th St",
    "sg:city":"Phenix City",
    "sg:classifiers":[
        {
            "category":"Insurance",
            "subcategory":"Hazard Insurance",
            "type":"Services"
        },
        {
            "category":"Professional",
            "subcategory":"Business Services",
            "type":"Services"
        }
    ],
    "sg:phone":"+1 334 297 9893",
    "sg:postcode":"36867",
    "sg:province":"AL",
    "sg:tags":[
        "bond"
    ],
    "wof:name":"Weeks Bonding Company",
    "wof:placetype":"venue"
},
  "geometry": {"coordinates":[-85.003923,32.475273],"type":"Point"}
}