{
  "type": "Feature",
  "properties": {
    "addr:full":"200 Mastin Lake Rd NW Huntsville AL 35811",
    "addr:housenumber":"200",
    "addr:postcode":"35811",
    "addr:street":"Mastin Lake Rd Nw",
    "iso:country":"US",
    "sg:address":"200 Mastin Lake Rd NW",
    "sg:city":"Huntsville",
    "sg:classifiers":[
        {
            "category":"Building & Trades",
            "subcategory":"Cleaning & Sanitation",
            "type":"Services"
        }
    ],
    "sg:phone":"+1 256 852 4743",
    "sg:postcode":"35811",
    "sg:province":"AL",
    "sg:tags":[
        "janitor"
    ],
    "wof:name":"Perez & White General Cleaning",
    "wof:placetype":"venue"
},
  "geometry": {"coordinates":[-86.577119,34.762155],"type":"Point"}
}