{
  "type": "Feature",
  "properties": {
    "iso:country":"US",
    "sg:address":"269 S Garland Rd",
    "sg:city":"Mc Kenzie",
    "sg:classifiers":[
        {
            "category":"Home & Garden",
            "subcategory":"Building Materials",
            "type":"Retail Goods"
        }
    ],
    "sg:phone":"+1 334 374 2004",
    "sg:postcode":"36456",
    "sg:province":"AL",
    "sg:tags":[
        "lumber",
        "plywood"
    ],
    "wof:name":"Lees Hardware Co",
    "wof:placetype":"venue"
},
  "geometry": {"coordinates":[-86.717861,31.542178],"type":"Point"}
}