{
  "type": "Feature",
  "properties": {
    "iso:country":"US",
    "sg:address":"300 Logan St",
    "sg:city":"Albertville",
    "sg:classifiers":[
        {
            "category":"Building & Trades",
            "subcategory":"Landscaping Services",
            "type":"Services"
        }
    ],
    "sg:phone":"+1 256 878 8969",
    "sg:postcode":"35950",
    "sg:province":"AL",
    "wof:name":"Kens Lawn & Landscaping",
    "wof:placetype":"venue"
},
  "geometry": {"coordinates":[-86.21396,34.265966],"type":"Point"}
}