{
  "type": "Feature",
  "properties": {
    "iso:country":"US",
    "sg:address":"4 Concours Ct",
    "sg:city":"Kinsey",
    "sg:classifiers":[
        {
            "category":"Professional",
            "type":"Services"
        }
    ],
    "sg:phone":"+1 334 792 3814",
    "sg:postcode":"36303",
    "sg:province":"AL",
    "sg:tags":[
        "establishment"
    ],
    "wof:name":"Rhodes & Rhodes",
    "wof:placetype":"venue"
},
  "geometry": {"coordinates":[-85.346976,31.283208],"type":"Point"}
}