{
  "type": "Feature",
  "properties": {
    "iso:country":"US",
    "sg:address":"101 N 3rd St",
    "sg:city":"Citronelle",
    "sg:classifiers":[
        {
            "category":"Food & Beverages",
            "subcategory":"Groceries & Convenience Stores",
            "type":"Retail Goods"
        }
    ],
    "sg:phone":"+1 251 866 5938",
    "sg:postcode":"36522",
    "sg:province":"AL",
    "wof:name":"Jr Food Mart",
    "wof:placetype":"venue"
},
  "geometry": {"coordinates":[-88.238089,31.092191],"type":"Point"}
}