{
  "type": "Feature",
  "properties": {
    "iso:country":"US",
    "sg:address":"104 E Laurel Ave",
    "sg:city":"Foley",
    "sg:classifiers":[
        {
            "category":"Professional",
            "subcategory":"Accounting & Tax Preparation",
            "type":"Services"
        }
    ],
    "sg:phone":"+1 251 970 1647",
    "sg:postcode":"36535",
    "sg:province":"AL",
    "sg:tags":[
        "billing"
    ],
    "wof:name":"Emerald Healthcare Group",
    "wof:placetype":"venue"
},
  "geometry": {"coordinates":[-87.683725,30.406351],"type":"Point"}
}