{
  "type": "Feature",
  "properties": {
    "addr:full":"1571 Montgomery Hwy Dothan AL 36303",
    "addr:housenumber":"1571",
    "addr:postcode":"36303",
    "addr:street":"Montgomery Hwy",
    "iso:country":"US",
    "sg:address":"1571 Montgomery Hwy",
    "sg:city":"Dothan",
    "sg:classifiers":[
        {
            "category":"Shopping",
            "subcategory":"Clothing, Apparel, & Fashions",
            "type":"Retail Goods"
        }
    ],
    "sg:phone":"+1 334 678 8833",
    "sg:postcode":"36303",
    "sg:province":"AL",
    "wof:name":"Ladies Fashion & Beauty Supply",
    "wof:placetype":"venue"
},
  "geometry": {"coordinates":[-85.40495900000001,31.238912],"type":"Point"}
}