{
  "type": "Feature",
  "properties": {
    "iso:country":"US",
    "sg:address":"5966 Hobbie Rd",
    "sg:city":"Montgomery",
    "sg:classifiers":[
        {
            "category":"Organizations",
            "subcategory":"Professional Association",
            "type":"Services"
        }
    ],
    "sg:phone":"+1 334 288 4103",
    "sg:postcode":"36105",
    "sg:province":"AL",
    "sg:tags":[
        "business"
    ],
    "wof:name":"Alabama Petroleum Eqp Contrs",
    "wof:placetype":"venue"
},
  "geometry": {"coordinates":[-86.237192,32.171491],"type":"Point"}
}