{
  "type": "Feature",
  "properties": {
    "iso:country":"US",
    "sg:address":"3191 Co Rd 388",
    "sg:city":"Valley",
    "sg:classifiers":[
        {
            "category":"Home & Garden",
            "subcategory":"Garden Supply",
            "type":"Retail Goods"
        }
    ],
    "sg:phone":"+1 334 756 6069",
    "sg:postcode":"36854",
    "sg:province":"AL",
    "sg:tags":[
        "engine"
    ],
    "wof:name":"Dave's Small Engine Repair",
    "wof:placetype":"venue"
},
  "geometry": {"coordinates":[-85.236921,32.751881],"type":"Point"}
}