{
  "type": "Feature",
  "properties": {
    "iso:country":"US",
    "sg:address":"3075 Wetumpka Hwy",
    "sg:city":"Montgomery",
    "sg:classifiers":[
        {
            "category":"Building & Trades",
            "subcategory":"Construction",
            "type":"Services"
        }
    ],
    "sg:phone":"+1 334 272 6436",
    "sg:postcode":"36110",
    "sg:province":"AL",
    "sg:tags":[
        "house"
    ],
    "wof:name":"Diversified Builders",
    "wof:placetype":"venue"
},
  "geometry": {"coordinates":[-86.220746,32.431019],"type":"Point"}
}