{
  "type": "Feature",
  "properties": {
    "iso:country":"US",
    "sg:address":"6520 University Dr NW",
    "sg:city":"Huntsville",
    "sg:classifiers":[
        {
            "category":"Autos & Motor Vehicles",
            "subcategory":"Automobile Sales",
            "type":"Retail Goods"
        },
        {
            "category":"Retail",
            "subcategory":"Auto Repair",
            "type":"Services"
        }
    ],
    "sg:phone":"+1 256 529 7537",
    "sg:postcode":"35806",
    "sg:province":"AL",
    "sg:tags":[
        "used",
        "leasing",
        "car",
        "truck",
        "new"
    ],
    "sg:website":"http://www.regalautoplaza.com/",
    "wof:name":"Landers Mclarty Nissan",
    "wof:placetype":"venue"
},
  "geometry": {"coordinates":[-86.69122299999999,34.74828],"type":"Point"}
}