{
  "type": "Feature",
  "properties": {
    "iso:country":"US",
    "sg:address":"303 Rebecca Rd",
    "sg:city":"Headland",
    "sg:classifiers":[
        {
            "category":"Farming",
            "subcategory":"Farm",
            "type":"Manufacturing & Wholesale Goods"
        }
    ],
    "sg:phone":"+1 334 693 5549",
    "sg:postcode":"36345",
    "sg:province":"AL",
    "sg:tags":[
        "crop",
        "general"
    ],
    "wof:name":"Jimmy Hicks",
    "wof:placetype":"venue"
},
  "geometry": {"coordinates":[-85.325621,31.343455],"type":"Point"}
}