{
  "type": "Feature",
  "properties": {
    "iso:country":"US",
    "sg:address":"2225 Drake Ave SW",
    "sg:city":"Huntsville",
    "sg:classifiers":[
        {
            "category":"Social Services",
            "type":"Services"
        }
    ],
    "sg:phone":"+1 256 882 8998",
    "sg:postcode":"35805",
    "sg:province":"AL",
    "wof:name":"Donna J Lowe MA LPC",
    "wof:placetype":"venue"
},
  "geometry": {"coordinates":[-86.600515,34.701909],"type":"Point"}
}