{
  "type": "Feature",
  "properties": {
    "iso:country":"US",
    "sg:address":"16336 Co Rd 87",
    "sg:city":"Elberta",
    "sg:classifiers":[
        {
            "category":"Farming",
            "subcategory":"Farm & Veterinary Services",
            "type":"Manufacturing & Wholesale Goods"
        }
    ],
    "sg:phone":"+1 251 986 5145",
    "sg:postcode":"36530",
    "sg:province":"AL",
    "sg:tags":[
        "livestock"
    ],
    "wof:name":"J & R Kichler Farms",
    "wof:placetype":"venue"
},
  "geometry": {"coordinates":[-87.581343,30.458755],"type":"Point"}
}