{
  "type": "Feature",
  "properties": {
    "addr:full":"3319 Summerville Rd Boaz AL 35957",
    "addr:housenumber":"3319",
    "addr:postcode":"35957",
    "addr:street":"Summerville Rd",
    "iso:country":"US",
    "sg:address":"3319 Summerville Rd",
    "sg:city":"Boaz",
    "sg:classifiers":[
        {
            "category":"Wholesale",
            "subcategory":"Poultry",
            "type":"Manufacturing & Wholesale Goods"
        }
    ],
    "sg:phone":"+1 256 593 2101",
    "sg:postcode":"35957",
    "sg:province":"AL",
    "wof:name":"Hilley Farms",
    "wof:placetype":"venue"
},
  "geometry": {"coordinates":[-86.214412,34.17993],"type":"Point"}
}