{
  "type": "Feature",
  "properties": {
    "iso:country":"US",
    "sg:address":"700 W 20th Ave",
    "sg:city":"Sheffield",
    "sg:classifiers":[
        {
            "category":"Wholesale",
            "subcategory":"Metals & Minerals",
            "type":"Manufacturing & Wholesale Goods"
        }
    ],
    "sg:phone":"+1 256 381 1000",
    "sg:postcode":"35660",
    "sg:province":"AL",
    "sg:tags":[
        "aluminum"
    ],
    "wof:name":"Alabama Aluminum Alloys Inc",
    "wof:placetype":"venue"
},
  "geometry": {"coordinates":[-87.712338,34.756288],"type":"Point"}
}