{
  "type": "Feature",
  "properties": {
    "addr:full":"2451 2nd Ave E Oneonta AL 35121",
    "addr:housenumber":"2451",
    "addr:postcode":"35121",
    "addr:street":"2Nd Ave E",
    "iso:country":"US",
    "sg:address":"2451 2nd Ave E",
    "sg:city":"Oneonta",
    "sg:classifiers":[
        {
            "category":"Personal",
            "subcategory":"Beauty Salon",
            "type":"Services"
        }
    ],
    "sg:phone":"+1 205 274 8289",
    "sg:postcode":"35121",
    "sg:province":"AL",
    "wof:name":"Prestige Beauty Salon",
    "wof:placetype":"venue"
},
  "geometry": {"coordinates":[-86.451139,33.970405],"type":"Point"}
}