{
  "type": "Feature",
  "properties": {
    "iso:country":"US",
    "sg:address":"4322 Saks Rd",
    "sg:city":"Anniston",
    "sg:classifiers":[
        {
            "category":"Autos & Motor Vehicles",
            "subcategory":"Auto Supplies",
            "type":"Retail Goods"
        }
    ],
    "sg:phone":"+1 256 236 4231",
    "sg:postcode":"36206",
    "sg:province":"AL",
    "sg:tags":[
        "repair",
        "tire"
    ],
    "wof:name":"Brooks Tire Service",
    "wof:placetype":"venue"
},
  "geometry": {"coordinates":[-85.83774099999999,33.7017],"type":"Point"}
}