{
  "type": "Feature",
  "properties": {
    "iso:country":"US",
    "sg:address":"5685 Co Rd 59",
    "sg:city":"Moulton",
    "sg:classifiers":[
        {
            "category":"Farming",
            "subcategory":"Poultry Farm",
            "type":"Manufacturing & Wholesale Goods"
        }
    ],
    "sg:phone":"+1 256 974 0618",
    "sg:postcode":"35650",
    "sg:province":"AL",
    "sg:tags":[
        "hatchery"
    ],
    "wof:name":"Terrys Egg Farm",
    "wof:placetype":"venue"
},
  "geometry": {"coordinates":[-87.34683200000001,34.437398],"type":"Point"}
}