{
  "type": "Feature",
  "properties": {
    "iso:country":"US",
    "sg:address":"4865 US Hwy 80",
    "sg:city":"Selma",
    "sg:classifiers":[
        {
            "category":"Autos & Motor Vehicles",
            "subcategory":"Fuel & Gas Station",
            "type":"Retail Goods"
        }
    ],
    "sg:phone":"+1 334 874 6914",
    "sg:postcode":"36701",
    "sg:province":"AL",
    "sg:tags":[
        "oil"
    ],
    "wof:name":"Interstate Oil",
    "wof:placetype":"venue"
},
  "geometry": {"coordinates":[-87.102756,32.437154],"type":"Point"}
}