{
  "type": "Feature",
  "properties": {
    "iso:country":"US",
    "sg:address":"200 McKenzie Cir",
    "sg:city":"Munford",
    "sg:classifiers":[
        {
            "category":"Real Estate",
            "subcategory":"Real Estate Operator",
            "type":"Services"
        }
    ],
    "sg:phone":"+1 256 358 9999",
    "sg:postcode":"36268",
    "sg:province":"AL",
    "sg:tags":[
        "apartment"
    ],
    "wof:name":"Munford Village Apartments",
    "wof:placetype":"venue"
},
  "geometry": {"coordinates":[-85.945923,33.532714],"type":"Point"}
}