{
  "type": "Feature",
  "properties": {
    "addr:full":"1510 Pelham Rd S Jacksonville AL 36265",
    "addr:housenumber":"1510",
    "addr:postcode":"36265",
    "addr:street":"Pelham Rd",
    "iso:country":"US",
    "sg:address":"1510 Pelham Rd S",
    "sg:city":"Jacksonville",
    "sg:classifiers":[
        {
            "category":"Autos & Motor Vehicles",
            "subcategory":"Automobile Sales",
            "type":"Retail Goods"
        }
    ],
    "sg:phone":"+1 256 435 7800",
    "sg:postcode":"36265",
    "sg:province":"AL",
    "sg:tags":[
        "car",
        "dealer"
    ],
    "wof:name":"Frank Miles Auto Sales",
    "wof:placetype":"venue"
},
  "geometry": {"coordinates":[-85.760925,33.788114],"type":"Point"}
}