{
  "type": "Feature",
  "properties": {
    "addr:full":"609 Wimbledon Dr Dothan AL 36305",
    "addr:housenumber":"609",
    "addr:postcode":"36305",
    "addr:street":"Wimbledon Dr",
    "iso:country":"US",
    "sg:address":"609 Wimbledon Dr",
    "sg:city":"Dothan",
    "sg:classifiers":[
        {
            "category":"Professional",
            "subcategory":"Detective & Security Services",
            "type":"Services"
        }
    ],
    "sg:phone":"+1 334 618 8713",
    "sg:postcode":"36305",
    "sg:province":"AL",
    "sg:tags":[
        "car"
    ],
    "wof:name":"M & M Investigations",
    "wof:placetype":"venue"
},
  "geometry": {"coordinates":[-85.45561499999999,31.212587],"type":"Point"}
}