{
  "type": "Feature",
  "properties": {
    "iso:country":"US",
    "sg:address":"3037 Citizens Pkwy",
    "sg:city":"Selma",
    "sg:classifiers":[
        {
            "category":"Autos & Motor Vehicles",
            "subcategory":"Fuel & Gas Station",
            "type":"Retail Goods"
        }
    ],
    "sg:phone":"+1 334 874 9418",
    "sg:postcode":"36701",
    "sg:province":"AL",
    "sg:tags":[
        "station",
        "gasoline"
    ],
    "wof:name":"Citizens Parkway Amoco",
    "wof:placetype":"venue"
},
  "geometry": {"coordinates":[-87.014721,32.448957],"type":"Point"}
}