{
  "type": "Feature",
  "properties": {
    "iso:country":"US",
    "sg:address":"3895 Co Rd 1545",
    "sg:city":"Cullman",
    "sg:classifiers":[
        {
            "category":"Building & Trades",
            "subcategory":"Electrical",
            "type":"Services"
        }
    ],
    "sg:phone":"+1 256 739 6265",
    "sg:postcode":"35058",
    "sg:province":"AL",
    "sg:tags":[
        "electric",
        "contractor"
    ],
    "wof:name":"T & S Electric",
    "wof:placetype":"venue"
},
  "geometry": {"coordinates":[-86.764914,34.252248],"type":"Point"}
}