{
  "type": "Feature",
  "properties": {
    "iso:country":"US",
    "sg:address":"770 S Court St",
    "sg:city":"Montgomery",
    "sg:classifiers":[
        {
            "category":"Organizations",
            "subcategory":"Religious Organization",
            "type":"Services"
        }
    ],
    "sg:phone":"+1 334 264 8913",
    "sg:postcode":"36104",
    "sg:province":"AL",
    "sg:tags":[
        "church"
    ],
    "wof:name":"Church Of Jesus Christ Of Lds",
    "wof:placetype":"venue"
},
  "geometry": {"coordinates":[-86.308787,32.36668],"type":"Point"}
}