{
  "type": "Feature",
  "properties": {
    "addr:full":"134 High Bluff Dr Gurley AL 35748",
    "addr:housenumber":"134",
    "addr:postcode":"35748",
    "addr:street":"High Bluff Dr Gurley",
    "iso:country":"US",
    "sg:address":"134 High Bluff Dr",
    "sg:city":"Gurley",
    "sg:classifiers":[
        {
            "category":"Building & Trades",
            "subcategory":"Construction",
            "type":"Services"
        }
    ],
    "sg:phone":"+1 256 776 6008",
    "sg:postcode":"35748",
    "sg:province":"AL",
    "sg:tags":[
        "house"
    ],
    "wof:name":"Johnson Const",
    "wof:placetype":"venue"
},
  "geometry": {"coordinates":[-86.36563099999999,34.672486],"type":"Point"}
}