{
  "type": "Feature",
  "properties": {
    "addr:full":"2899 McKenzie St Foley AL 36535",
    "addr:housenumber":"2899",
    "addr:postcode":"36535",
    "addr:street":"Mckenzie St",
    "iso:country":"US",
    "sg:address":"2899 McKenzie St",
    "sg:city":"Foley",
    "sg:classifiers":[
        {
            "category":"Home & Garden",
            "subcategory":"Building Materials",
            "type":"Retail Goods"
        }
    ],
    "sg:phone":"+1 251 955 2401",
    "sg:postcode":"36535",
    "sg:province":"AL",
    "wof:name":"Home Depot",
    "wof:placetype":"venue"
},
  "geometry": {"coordinates":[-87.68303299999999,30.36724],"type":"Point"}
}