{
  "type": "Feature",
  "properties": {
    "addr:full":"100 Chelsea Corners Way Chelsea AL 35043",
    "addr:housenumber":"100",
    "addr:postcode":"35043",
    "addr:street":"Chelsea Corners Way",
    "iso:country":"US",
    "sg:address":"100 Chelsea Corners Way",
    "sg:city":"Chelsea",
    "sg:classifiers":[
        {
            "category":"Professional",
            "subcategory":"Accounting & Tax Preparation",
            "type":"Services"
        }
    ],
    "sg:phone":"+1 205 678 8033",
    "sg:postcode":"35043",
    "sg:province":"AL",
    "sg:tags":[
        "return",
        "filing"
    ],
    "wof:name":"Shelby Accounting & Tax Svc",
    "wof:placetype":"venue"
},
  "geometry": {"coordinates":[-86.633672,33.346266],"type":"Point"}
}