{
  "type": "Feature",
  "properties": {
    "addr:full":"7268 Cottage Hill Rd Mobile AL 36695",
    "addr:housenumber":"7268",
    "addr:postcode":"36695",
    "addr:street":"Cottage Hill Rd",
    "iso:country":"US",
    "sg:address":"7268 Cottage Hill Rd",
    "sg:city":"Mobile",
    "sg:classifiers":[
        {
            "category":"Wholesale",
            "subcategory":"Medical Equipment & Supplies",
            "type":"Manufacturing & Wholesale Goods"
        }
    ],
    "sg:phone":"+1 251 660 0322",
    "sg:postcode":"36695",
    "sg:province":"AL",
    "sg:tags":[
        "hospital"
    ],
    "wof:name":"Coastal Medical Management LLC",
    "wof:placetype":"venue"
},
  "geometry": {"coordinates":[-88.212028,30.637491],"type":"Point"}
}