{
  "type": "Feature",
  "properties": {
    "iso:country":"US",
    "sg:address":"4019 Medford Dr SE",
    "sg:city":"Huntsville",
    "sg:classifiers":[
        {
            "category":"Professional",
            "subcategory":"Computer Services",
            "type":"Services"
        }
    ],
    "sg:phone":"+1 256 883 1131",
    "sg:postcode":"35802",
    "sg:province":"AL",
    "sg:tags":[
        "programing",
        "custom"
    ],
    "wof:name":"Merchantworks",
    "wof:placetype":"venue"
},
  "geometry": {"coordinates":[-86.550482,34.699817],"type":"Point"}
}