{
  "type": "Feature",
  "properties": {
    "addr:full":"3501 Beaty Rd SW Huntsville AL 35805",
    "addr:housenumber":"3501",
    "addr:postcode":"35805",
    "addr:street":"Beaty Rd Sw",
    "iso:country":"US",
    "sg:address":"3501 Beaty Rd SW",
    "sg:city":"Huntsville",
    "sg:classifiers":[
        {
            "category":"Building & Trades",
            "subcategory":"Construction",
            "type":"Services"
        }
    ],
    "sg:phone":"+1 256 797 7902",
    "sg:postcode":"35805",
    "sg:province":"AL",
    "sg:tags":[
        "contractor"
    ],
    "wof:name":"LA Masonry",
    "wof:placetype":"venue"
},
  "geometry": {"coordinates":[-86.62022399999999,34.699197],"type":"Point"}
}