{
  "type": "Feature",
  "properties": {
    "iso:country":"US",
    "sg:address":"811 Co Rd 229",
    "sg:city":"Smiths",
    "sg:classifiers":[
        {
            "category":"Recreation",
            "subcategory":"Arcade",
            "type":"Entertainment"
        }
    ],
    "sg:phone":"+1 334 297 1724",
    "sg:postcode":"36877",
    "sg:province":"AL",
    "sg:tags":[
        "device",
        "operator",
        "amusement"
    ],
    "wof:name":"Moon Road Game Room",
    "wof:placetype":"venue"
},
  "geometry": {"coordinates":[-85.075221,32.50588],"type":"Point"}
}