{
  "type": "Feature",
  "properties": {
    "iso:country":"US",
    "sg:address":"459 Main St",
    "sg:city":"Trussville",
    "sg:classifiers":[
        {
            "category":"Home & Garden",
            "subcategory":"Carpets & Floor Coverings",
            "type":"Retail Goods"
        }
    ],
    "sg:phone":"+1 205 661 6200",
    "sg:postcode":"35173",
    "sg:province":"AL",
    "sg:tags":[
        "mattress"
    ],
    "wof:name":"Bedzzz Express",
    "wof:placetype":"venue"
},
  "geometry": {"coordinates":[-86.614895,33.617625],"type":"Point"}
}