{
  "type": "Feature",
  "properties": {
    "addr:full":"2143 Quail Run Rd Munford AL 36268",
    "addr:housenumber":"2143",
    "addr:postcode":"36268",
    "addr:street":"Quail Run Rd",
    "iso:country":"US",
    "sg:address":"2143 Quail Run Rd",
    "sg:city":"Munford",
    "sg:classifiers":[
        {
            "category":"Government",
            "subcategory":"Office",
            "type":"Public Place"
        }
    ],
    "sg:phone":"+1 256 362 9815",
    "sg:postcode":"36268",
    "sg:province":"AL",
    "sg:tags":[
        "contracting"
    ],
    "wof:name":"World Wide Defense Tech LLC",
    "wof:placetype":"venue"
},
  "geometry": {"coordinates":[-85.98866099999999,33.474078],"type":"Point"}
}