{
  "type": "Feature",
  "properties": {
    "iso:country":"US",
    "sg:address":"2160 14th Ave S",
    "sg:city":"Birmingham",
    "sg:classifiers":[
        {
            "category":"Professional",
            "subcategory":"Lawyer & Legal Services",
            "type":"Services"
        }
    ],
    "sg:phone":"+1 205 933 7533",
    "sg:postcode":"35205",
    "sg:province":"AL",
    "sg:tags":[
        "attorney"
    ],
    "wof:name":"Frank S Buck",
    "wof:placetype":"venue"
},
  "geometry": {"coordinates":[-86.791617,33.498809],"type":"Point"}
}