{
  "type": "Feature",
  "properties": {
    "iso:country":"US",
    "sg:address":"630 Co Rd 113",
    "sg:city":"Montevallo",
    "sg:classifiers":[
        {
            "category":"Utilities",
            "subcategory":"Water",
            "type":"Services"
        }
    ],
    "sg:phone":"+1 205 665 1221",
    "sg:postcode":"35115",
    "sg:province":"AL",
    "sg:tags":[
        "company",
        "sewage"
    ],
    "wof:name":"Chilton Water Authority",
    "wof:placetype":"venue"
},
  "geometry": {"coordinates":[-86.844819,33.029153],"type":"Point"}
}