{
  "type": "Feature",
  "properties": {
    "iso:country":"US",
    "sg:address":"118 Choccolocco St",
    "sg:city":"Oxford",
    "sg:classifiers":[
        {
            "category":"Health Services",
            "subcategory":"Hospital",
            "type":"Services"
        }
    ],
    "sg:phone":"+1 256 831 4601",
    "sg:postcode":"36203",
    "sg:province":"AL",
    "sg:tags":[
        "clinic",
        "specialty"
    ],
    "wof:name":"Calhoun Treatment Center Inc",
    "wof:placetype":"venue"
},
  "geometry": {"coordinates":[-85.834001,33.615023],"type":"Point"}
}