{
  "type": "Feature",
  "properties": {
    "iso:country":"US",
    "sg:address":"5333 Messer Airport Hwy",
    "sg:city":"Birmingham",
    "sg:classifiers":[
        {
            "category":"Autos & Motor Vehicles",
            "subcategory":"Automobile Sales",
            "type":"Retail Goods"
        }
    ],
    "sg:phone":"+1 205 978 2315",
    "sg:postcode":"35212",
    "sg:province":"AL",
    "sg:tags":[
        "car",
        "dealer"
    ],
    "wof:name":"Alabama Car Rental",
    "wof:placetype":"venue"
},
  "geometry": {"coordinates":[-86.754678,33.551424],"type":"Point"}
}