{
  "type": "Feature",
  "properties": {
    "addr:full":"303 Parks Ave Scottsboro AL 35768",
    "addr:housenumber":"303",
    "addr:postcode":"35768",
    "addr:street":"Parks Ave",
    "iso:country":"US",
    "sg:address":"303 Parks Ave",
    "sg:city":"Scottsboro",
    "sg:classifiers":[
        {
            "category":"Health Services",
            "subcategory":"Doctor",
            "type":"Services"
        }
    ],
    "sg:phone":"+1 256 574 3623",
    "sg:postcode":"35768",
    "sg:province":"AL",
    "sg:tags":[
        "physician",
        "surgeon"
    ],
    "wof:name":"Larry T Bolton MD",
    "wof:placetype":"venue"
},
  "geometry": {"coordinates":[-86.04057400000001,34.665999],"type":"Point"}
}