{
  "type": "Feature",
  "properties": {
    "addr:full":"1107 Florence Blvd Florence AL 35634",
    "addr:housenumber":"1107",
    "addr:postcode":"35634",
    "addr:street":"Florence Blvd",
    "iso:country":"US",
    "sg:address":"1107 Florence Blvd",
    "sg:city":"Florence",
    "sg:classifiers":[
        {
            "category":"Retail",
            "subcategory":"Repair Shop",
            "type":"Services"
        }
    ],
    "sg:phone":"+1 256 767 0057",
    "sg:postcode":"35634",
    "sg:province":"AL",
    "sg:tags":[
        "radio",
        "television",
        "electrical"
    ],
    "wof:name":"Shoals Electronic Service",
    "wof:placetype":"venue"
},
  "geometry": {"coordinates":[-87.66332199999999,34.815889],"type":"Point"}
}