{
  "type": "Feature",
  "properties": {
    "iso:country":"US",
    "sg:address":"2211 Woodward Ave",
    "sg:city":"Muscle Shoals",
    "sg:classifiers":[
        {
            "category":"Personal",
            "subcategory":"Tattoo Parlor",
            "type":"Services"
        }
    ],
    "sg:phone":"+1 256 314 4467",
    "sg:postcode":"35661",
    "sg:province":"AL",
    "sg:tags":[
        "tattooing"
    ],
    "wof:name":"West Coast Tattoos",
    "wof:placetype":"venue"
},
  "geometry": {"coordinates":[-87.667808,34.740327],"type":"Point"}
}