{
  "type": "Feature",
  "properties": {
    "addr:full":"976 Ronnie McDowell Ave Russellville AL 35654",
    "addr:housenumber":"976",
    "addr:postcode":"35654",
    "addr:street":"Ronnie Mcdowell Ave",
    "iso:country":"US",
    "sg:address":"976 Ronnie McDowell Ave",
    "sg:city":"Russellville",
    "sg:classifiers":[
        {
            "category":"Health Services",
            "subcategory":"Clinic",
            "type":"Services"
        }
    ],
    "sg:phone":"+1 256 332 3222",
    "sg:postcode":"35654",
    "sg:province":"AL",
    "sg:tags":[
        "home"
    ],
    "wof:name":"Respi-Care",
    "wof:placetype":"venue"
},
  "geometry": {"coordinates":[-87.727814,34.490409],"type":"Point"}
}