{
  "type": "Feature",
  "properties": {
    "iso:country":"US",
    "sg:address":"365 Grand Ave",
    "sg:city":"Fairhope",
    "sg:classifiers":[
        {
            "category":"Freight",
            "type":"Transportation"
        }
    ],
    "sg:phone":"+1 251 929 2133",
    "sg:postcode":"36532",
    "sg:province":"AL",
    "sg:tags":[
        "hauling",
        "trucking"
    ],
    "wof:name":"Easy Haul Inc",
    "wof:placetype":"venue"
},
  "geometry": {"coordinates":[-87.901918,30.533966],"type":"Point"}
}