{
  "type": "Feature",
  "properties": {
    "iso:country":"US",
    "sg:address":"10144 Franklin St",
    "sg:city":"Thorsby",
    "sg:classifiers":[
        {
            "category":"Manufacturing",
            "subcategory":"Tools & Machinery",
            "type":"Manufacturing & Wholesale Goods"
        }
    ],
    "sg:phone":"+1 205 646 3033",
    "sg:postcode":"35171",
    "sg:province":"AL",
    "sg:tags":[
        "farm",
        "mfg"
    ],
    "wof:name":"Parker Equipment Co",
    "wof:placetype":"venue"
},
  "geometry": {"coordinates":[-86.696533,32.913515],"type":"Point"}
}