{
  "type": "Feature",
  "properties": {
    "iso:country":"US",
    "sg:address":"600 Interstate Park Dr",
    "sg:city":"Montgomery",
    "sg:classifiers":[
        {
            "category":"Organizations",
            "subcategory":"Professional Association",
            "type":"Services"
        }
    ],
    "sg:phone":"+1 334 213 2432",
    "sg:postcode":"36109",
    "sg:province":"AL",
    "wof:name":"Alabama Independent Drugstore",
    "wof:placetype":"venue"
},
  "geometry": {"coordinates":[-86.241107,32.361483],"type":"Point"}
}