{
  "type": "Feature",
  "properties": {
    "iso:country":"US",
    "sg:address":"78 Powell Dr",
    "sg:city":"Seale",
    "sg:classifiers":[
        {
            "category":"Building & Trades",
            "subcategory":"Construction",
            "type":"Services"
        }
    ],
    "sg:phone":"+1 334 855 9249",
    "sg:postcode":"36875",
    "sg:province":"AL",
    "sg:tags":[
        "maker",
        "cabinet"
    ],
    "wof:name":"Silver Hammer",
    "wof:placetype":"venue"
},
  "geometry": {"coordinates":[-85.082468,32.308685],"type":"Point"}
}