{
  "type": "Feature",
  "properties": {
    "iso:country":"US",
    "sg:address":"2 West Blvd",
    "sg:city":"Montgomery",
    "sg:classifiers":[
        {
            "category":"Manufacturing",
            "subcategory":"Metals",
            "type":"Manufacturing & Wholesale Goods"
        }
    ],
    "sg:phone":"+1 334 834 1505",
    "sg:postcode":"36108",
    "sg:province":"AL",
    "sg:tags":[
        "fabricator",
        "sheet"
    ],
    "sg:website":"www.alabamasteel.com",
    "wof:name":"Alabama Steel Supply Inc",
    "wof:placetype":"venue"
},
  "geometry": {"coordinates":[-86.379537,32.365245],"type":"Point"}
}