{
  "type": "Feature",
  "properties": {
    "iso:country":"US",
    "sg:address":"165 Linger Ln",
    "sg:city":"Talladega",
    "sg:classifiers":[
        {
            "category":"Building & Trades",
            "subcategory":"Construction",
            "type":"Services"
        }
    ],
    "sg:phone":"+1 256 268 0773",
    "sg:postcode":"35160",
    "sg:province":"AL",
    "sg:tags":[
        "contractor"
    ],
    "wof:name":"Jones Drywall",
    "wof:placetype":"venue"
},
  "geometry": {"coordinates":[-86.200587,33.486409],"type":"Point"}
}