{
  "type": "Feature",
  "properties": {
    "addr:full":"2409 Commerce Ct SW Huntsville AL 35801",
    "addr:housenumber":"2409",
    "addr:postcode":"35801",
    "addr:street":"Commerce Ct Sw",
    "iso:country":"US",
    "sg:address":"2409 Commerce Ct SW",
    "sg:city":"Huntsville",
    "sg:classifiers":[
        {
            "category":"Banks & Credit Unions",
            "subcategory":"Bank",
            "type":"Services"
        }
    ],
    "sg:phone":"+1 256 519 3100",
    "sg:postcode":"35801",
    "sg:province":"AL",
    "sg:tags":[
        "loan",
        "real estate"
    ],
    "wof:name":"Countrywide Home Loans",
    "wof:placetype":"venue"
},
  "geometry": {"coordinates":[-86.588561,34.712777],"type":"Point"}
}