{
  "type": "Feature",
  "properties": {
    "iso:country":"US",
    "sg:address":"13840 Oak Lake Rd",
    "sg:city":"Wilmer",
    "sg:classifiers":[
        {
            "category":"Farming",
            "subcategory":"Farm",
            "type":"Manufacturing & Wholesale Goods"
        }
    ],
    "sg:phone":"+1 251 649 8799",
    "sg:postcode":"36587",
    "sg:province":"AL",
    "sg:tags":[
        "crop",
        "general"
    ],
    "wof:name":"Oak Lake Farms Inc",
    "wof:placetype":"venue"
},
  "geometry": {"coordinates":[-88.374648,30.813596],"type":"Point"}
}