{
  "type": "Feature",
  "properties": {
    "iso:country":"US",
    "sg:address":"347 W Carroll St",
    "sg:city":"Dothan",
    "sg:classifiers":[
        {
            "category":"Retail",
            "subcategory":"Repair Shop",
            "type":"Services"
        }
    ],
    "sg:phone":"+1 334 794 9547",
    "sg:postcode":"36301",
    "sg:province":"AL",
    "wof:name":"Sams Small Engine",
    "wof:placetype":"venue"
},
  "geometry": {"coordinates":[-85.40168799999999,31.199001],"type":"Point"}
}