{
  "type": "Feature",
  "properties": {
    "iso:country":"US",
    "sg:address":"770 Oak Dr E",
    "sg:city":"Trussville",
    "sg:classifiers":[
        {
            "category":"Building & Trades",
            "subcategory":"Plumbing",
            "type":"Services"
        }
    ],
    "sg:phone":"+1 205 655 7909",
    "sg:postcode":"35173",
    "sg:province":"AL",
    "wof:name":"G & H Plumbing",
    "wof:placetype":"venue"
},
  "geometry": {"coordinates":[-86.590667,33.620782],"type":"Point"}
}