{
  "type": "Feature",
  "properties": {
    "addr:full":"11011 US Hwy 431 Albertville AL 35950",
    "addr:housenumber":"11011",
    "addr:postcode":"35950",
    "addr:street":"Us Hwy 431",
    "iso:country":"US",
    "sg:address":"11011 US Hwy 431",
    "sg:city":"Albertville",
    "sg:classifiers":[
        {
            "category":"Retail",
            "subcategory":"Auto Rental",
            "type":"Services"
        }
    ],
    "sg:phone":"+1 256 894 0171",
    "sg:postcode":"35950",
    "sg:province":"AL",
    "sg:tags":[
        "renting",
        "truck",
        "leasing"
    ],
    "wof:name":"U-Haul Co",
    "wof:placetype":"venue"
},
  "geometry": {"coordinates":[-86.26571,34.297386],"type":"Point"}
}