{
  "type": "Feature",
  "properties": {
    "addr:full":"5268 Highland Trace Cir Birmingham AL 35215",
    "addr:housenumber":"5268",
    "addr:postcode":"35215",
    "addr:street":"Highland Trace Cir",
    "iso:country":"US",
    "sg:address":"5268 Highland Trace Cir",
    "sg:city":"Birmingham",
    "sg:classifiers":[
        {
            "category":"Autos & Motor Vehicles",
            "subcategory":"Automobile Sales",
            "type":"Retail Goods"
        }
    ],
    "sg:phone":"+1 205 856 3333",
    "sg:postcode":"35215",
    "sg:province":"AL",
    "sg:tags":[
        "used"
    ],
    "wof:name":"Nelson Auto LLC",
    "wof:placetype":"venue"
},
  "geometry": {"coordinates":[-86.66375499999999,33.656272],"type":"Point"}
}