{
  "type": "Feature",
  "properties": {
    "iso:country":"US",
    "sg:address":"2007 Autumn Wood Dr",
    "sg:city":"Birmingham",
    "sg:classifiers":[
        {
            "category":"Professional",
            "type":"Services"
        }
    ],
    "sg:phone":"+1 205 402 0047",
    "sg:postcode":"35216",
    "sg:province":"AL",
    "wof:name":"Donna M Wood",
    "wof:placetype":"venue"
},
  "geometry": {"coordinates":[-86.790457,33.389998],"type":"Point"}
}