{
  "type": "Feature",
  "properties": {
    "iso:country":"US",
    "sg:address":"1198 7th Ave",
    "sg:city":"Pleasant Grove",
    "sg:classifiers":[
        {
            "category":"Building & Trades",
            "subcategory":"Construction",
            "type":"Services"
        }
    ],
    "sg:phone":"+1 205 744 6472",
    "sg:postcode":"35127",
    "sg:province":"AL",
    "sg:tags":[
        "contractor"
    ],
    "wof:name":"Naborhood Contracting Inc",
    "wof:placetype":"venue"
},
  "geometry": {"coordinates":[-86.97533799999999,33.482966],"type":"Point"}
}