{
  "type": "Feature",
  "properties": {
    "iso:country":"US",
    "sg:address":"1951 Hoover Ct",
    "sg:city":"Birmingham",
    "sg:classifiers":[
        {
            "category":"Real Estate",
            "subcategory":"Real Estate Agent",
            "type":"Services"
        }
    ],
    "sg:phone":"+1 205 981 8973",
    "sg:postcode":"35226",
    "sg:province":"AL",
    "wof:name":"Lorna Road Properties",
    "wof:placetype":"venue"
},
  "geometry": {"coordinates":[-86.806686,33.401812],"type":"Point"}
}