{
  "type": "Feature",
  "properties": {
    "iso:country":"US",
    "sg:address":"3378 Cloverdale Rd",
    "sg:city":"Florence",
    "sg:classifiers":[
        {
            "category":"Restaurant",
            "type":"Food & Drink"
        }
    ],
    "sg:menulink":"http://www.allmenus.com/al/florence/67776-foxs-pizza-den/menu/",
    "sg:phone":"+1 256 767 2332",
    "sg:postcode":"35633",
    "sg:province":"AL",
    "sg:tags":[
        "american",
        "pizza"
    ],
    "wof:name":"Fox's Pizza Den",
    "wof:placetype":"venue"
},
  "geometry": {"coordinates":[-87.69069399999999,34.851203],"type":"Point"}
}