{
  "type": "Feature",
  "properties": {
    "iso:country":"US",
    "sg:address":"163 W Main St",
    "sg:city":"Dothan",
    "sg:classifiers":[
        {
            "category":"Professional",
            "subcategory":"Lawyer & Legal Services",
            "type":"Services"
        }
    ],
    "sg:phone":"+1 334 793 1555",
    "sg:postcode":"36301",
    "sg:province":"AL",
    "sg:tags":[
        "attorney"
    ],
    "sg:website":"www.cochranfirm.com",
    "wof:name":"Cochran Cherry Givens & Smith",
    "wof:placetype":"venue"
},
  "geometry": {"coordinates":[-85.392707,31.223547],"type":"Point"}
}