{
  "type": "Feature",
  "properties": {
    "iso:country":"US",
    "sg:address":"620 15th St E",
    "sg:city":"Tuscaloosa",
    "sg:classifiers":[
        {
            "category":"Personal",
            "subcategory":"Beauty Salon",
            "type":"Services"
        }
    ],
    "sg:phone":"+1 205 343 1773",
    "sg:postcode":"35401",
    "sg:province":"AL",
    "sg:tags":[
        "shop"
    ],
    "wof:name":"Nails Unlimited",
    "wof:placetype":"venue"
},
  "geometry": {"coordinates":[-87.5278,33.197431],"type":"Point"}
}