{
  "type": "Feature",
  "properties": {
    "iso:country":"US",
    "sg:address":"309 Main St",
    "sg:city":"Trussville",
    "sg:classifiers":[
        {
            "category":"Food & Beverages",
            "subcategory":"Groceries & Convenience Stores",
            "type":"Retail Goods"
        }
    ],
    "sg:phone":"+1 205 655 8555",
    "sg:postcode":"35173",
    "sg:province":"AL",
    "sg:tags":[
        "grocer"
    ],
    "sg:website":"www.lowpriceplace.com",
    "wof:name":"Food World",
    "wof:placetype":"venue"
},
  "geometry": {"coordinates":[-86.612505,33.618238],"type":"Point"}
}