{
  "type": "Feature",
  "properties": {
    "addr:full":"26469 Nick Davis Rd Athens AL 35613",
    "addr:housenumber":"26469",
    "addr:postcode":"35613",
    "addr:street":"Nick Davis Rd",
    "iso:country":"US",
    "sg:address":"26469 Nick Davis Rd",
    "sg:city":"Athens",
    "sg:classifiers":[
        {
            "category":"Building & Trades",
            "subcategory":"Construction",
            "type":"Services"
        }
    ],
    "sg:phone":"+1 256 232 5554",
    "sg:postcode":"35613",
    "sg:province":"AL",
    "sg:tags":[
        "mfg",
        "kitchen",
        "cabinet",
        "wood",
        "contractor",
        "carpentry"
    ],
    "sg:website":"www.peekwoodworks.com",
    "wof:name":"Peek Woodworks Inc",
    "wof:placetype":"venue"
},
  "geometry": {"coordinates":[-86.858357,34.802966],"type":"Point"}
}