{
  "type": "Feature",
  "properties": {
    "iso:country":"US",
    "sg:address":"64 Church St",
    "sg:city":"Woodville",
    "sg:classifiers":[
        {
            "category":"Building & Trades",
            "subcategory":"Landscaping Services",
            "type":"Services"
        }
    ],
    "sg:phone":"+1 256 776 0064",
    "sg:postcode":"35776",
    "sg:province":"AL",
    "wof:name":"Michael Carney Lawn Care LLC",
    "wof:placetype":"venue"
},
  "geometry": {"coordinates":[-86.274782,34.627867],"type":"Point"}
}