{
  "type": "Feature",
  "properties": {
    "iso:country":"US",
    "sg:address":"109 S 8th St",
    "sg:city":"Gadsden",
    "sg:classifiers":[
        {
            "category":"Government",
            "subcategory":"Office",
            "type":"Public Place"
        }
    ],
    "sg:phone":"+1 256 547 6311",
    "sg:postcode":"35901",
    "sg:province":"AL",
    "sg:tags":[
        "county",
        "program",
        "health"
    ],
    "wof:name":"Etowah County Home Health Care",
    "wof:placetype":"venue"
},
  "geometry": {"coordinates":[-86.011844,34.014212],"type":"Point"}
}