{
  "type": "Feature",
  "properties": {
    "iso:country":"US",
    "sg:address":"397 Boll Weevil Ln",
    "sg:city":"Toney",
    "sg:classifiers":[
        {
            "category":"Building & Trades",
            "subcategory":"Construction",
            "type":"Services"
        }
    ],
    "sg:phone":"+1 256 651 6375",
    "sg:postcode":"35773",
    "sg:province":"AL",
    "sg:tags":[
        "painter"
    ],
    "wof:name":"Passavant Home Repairs Inc",
    "wof:placetype":"venue"
},
  "geometry": {"coordinates":[-86.687042,34.858932],"type":"Point"}
}