{
  "type": "Feature",
  "properties": {
    "iso:country":"US",
    "sg:address":"620 27th St S",
    "sg:city":"Birmingham",
    "sg:classifiers":[
        {
            "category":"Professional",
            "type":"Services"
        }
    ],
    "sg:phone":"+1 205 731 9952",
    "sg:postcode":"35233",
    "sg:province":"AL",
    "wof:name":"Cabbages & Kings",
    "wof:placetype":"venue"
},
  "geometry": {"coordinates":[-86.79085,33.511231],"type":"Point"}
}