{
  "type": "Feature",
  "properties": {
    "addr:full":"333 Walnut St Prattville AL 36067",
    "addr:housenumber":"333",
    "addr:postcode":"36067",
    "addr:street":"Walnut St",
    "iso:country":"US",
    "sg:address":"333 Walnut St",
    "sg:city":"Prattville",
    "sg:classifiers":[
        {
            "category":"Farming",
            "subcategory":"Farm & Veterinary Services",
            "type":"Manufacturing & Wholesale Goods"
        }
    ],
    "sg:phone":"+1 334 365 8081",
    "sg:postcode":"36067",
    "sg:province":"AL",
    "sg:tags":[
        "seed"
    ],
    "wof:name":"Central Alabama Certified Seed",
    "wof:placetype":"venue"
},
  "geometry": {"coordinates":[-86.47803999999999,32.466521],"type":"Point"}
}