{
  "type": "Feature",
  "properties": {
    "iso:country":"US",
    "sg:address":"330 School St",
    "sg:city":"Frisco City",
    "sg:classifiers":[
        {
            "category":"Building & Trades",
            "subcategory":"Construction",
            "type":"Services"
        }
    ],
    "sg:phone":"+1 251 267 3217",
    "sg:postcode":"36445",
    "sg:province":"AL",
    "sg:tags":[
        "general",
        "contractor"
    ],
    "wof:name":"Oak Ridge Office",
    "wof:placetype":"venue"
},
  "geometry": {"coordinates":[-87.408272,31.43376],"type":"Point"}
}