{
  "type": "Feature",
  "properties": {
    "iso:country":"US",
    "sg:address":"3025 Crescent Cir SE",
    "sg:city":"Huntsville",
    "sg:classifiers":[
        {
            "category":"Building & Trades",
            "subcategory":"Cleaning & Sanitation",
            "type":"Services"
        }
    ],
    "sg:phone":"+1 256 539 3506",
    "sg:postcode":"35801",
    "sg:province":"AL",
    "sg:tags":[
        "janitor"
    ],
    "wof:name":"Spring Cleaning",
    "wof:placetype":"venue"
},
  "geometry": {"coordinates":[-86.536976,34.731476],"type":"Point"}
}