{
  "type": "Feature",
  "properties": {
    "addr:full":"1100 S Montgomery Ave Sheffield AL 35660",
    "addr:housenumber":"1100",
    "addr:postcode":"35660",
    "addr:street":"S Montgomery Ave",
    "iso:country":"US",
    "sg:address":"1100 S Montgomery Ave",
    "sg:city":"Sheffield",
    "sg:classifiers":[
        {
            "category":"Health Services",
            "subcategory":"Doctor",
            "type":"Services"
        }
    ],
    "sg:phone":"+1 256 381 8200",
    "sg:postcode":"35660",
    "sg:province":"AL",
    "sg:tags":[
        "physician",
        "surgeon"
    ],
    "wof:name":"Andre Taylor MD",
    "wof:placetype":"venue"
},
  "geometry": {"coordinates":[-87.69891,34.747507],"type":"Point"}
}