{
  "type": "Feature",
  "properties": {
    "addr:full":"2100 Gaylewood Dr Bessemer AL 35022",
    "addr:housenumber":"2100",
    "addr:postcode":"35022",
    "addr:street":"Gaylewood Dr",
    "iso:country":"US",
    "sg:address":"2100 Gaylewood Dr",
    "sg:city":"Bessemer",
    "sg:classifiers":[
        {
            "category":"Professional",
            "type":"Services"
        }
    ],
    "sg:phone":"+1 205 296 4003",
    "sg:postcode":"35022",
    "sg:province":"AL",
    "wof:name":"Imageinc",
    "wof:placetype":"venue"
},
  "geometry": {"coordinates":[-86.94729100000001,33.348476],"type":"Point"}
}