{
  "type": "Feature",
  "properties": {
    "iso:country":"US",
    "sg:address":"2496 Government St",
    "sg:city":"Mobile",
    "sg:classifiers":[
        {
            "category":"Real Estate",
            "subcategory":"Real Estate Services",
            "type":"Services"
        }
    ],
    "sg:phone":"+1 251 476 1270",
    "sg:postcode":"36606",
    "sg:province":"AL",
    "sg:tags":[
        "company",
        "title"
    ],
    "wof:name":"Title Guaranty & Abstract Co",
    "wof:placetype":"venue"
},
  "geometry": {"coordinates":[-88.097971,30.673065],"type":"Point"}
}