{
  "type": "Feature",
  "properties": {
    "addr:full":"21325 Kimberly Dr Mc Calla AL 35111",
    "addr:housenumber":"21325",
    "addr:postcode":"35111",
    "addr:street":"Kimberly Dr",
    "iso:country":"US",
    "sg:address":"21325 Kimberly Dr",
    "sg:city":"Mc Calla",
    "sg:classifiers":[
        {
            "category":"Shopping",
            "subcategory":"Gifts & Souvenirs",
            "type":"Retail Goods"
        }
    ],
    "sg:phone":"+1 205 477 9613",
    "sg:postcode":"35111",
    "sg:province":"AL",
    "wof:name":"Dlite Em Gifts",
    "wof:placetype":"venue"
},
  "geometry": {"coordinates":[-87.13466699999999,33.294151],"type":"Point"}
}