{
  "type": "Feature",
  "properties": {
    "iso:country":"US",
    "sg:address":"101 Old Montgomery Rd",
    "sg:city":"Selma",
    "sg:classifiers":[
        {
            "category":"Wholesale",
            "subcategory":"Machinery & Supplies",
            "type":"Manufacturing & Wholesale Goods"
        }
    ],
    "sg:phone":"+1 334 872 7552",
    "sg:postcode":"36703",
    "sg:province":"AL",
    "sg:tags":[
        "industrial"
    ],
    "wof:name":"Fastenal Company",
    "wof:placetype":"venue"
},
  "geometry": {"coordinates":[-87.014185,32.400321],"type":"Point"}
}