{
  "type": "Feature",
  "properties": {
    "iso:country":"US",
    "sg:address":"1112 Francis St W",
    "sg:city":"Jacksonville",
    "sg:classifiers":[
        {
            "category":"Building & Trades",
            "subcategory":"Cleaning & Sanitation",
            "type":"Services"
        }
    ],
    "sg:phone":"+1 256 435 3560",
    "sg:postcode":"36265",
    "sg:province":"AL",
    "sg:tags":[
        "department",
        "maintenance"
    ],
    "wof:name":"Maintenance Department",
    "wof:placetype":"venue"
},
  "geometry": {"coordinates":[-85.777018,33.81666],"type":"Point"}
}