{
  "type": "Feature",
  "properties": {
    "iso:country":"US",
    "sg:address":"4831 Pinedale Way",
    "sg:city":"Birmingham",
    "sg:classifiers":[
        {
            "category":"Professional",
            "subcategory":"Accounting & Tax Preparation",
            "type":"Services"
        }
    ],
    "sg:phone":"+1 205 823 6722",
    "sg:postcode":"35226",
    "sg:province":"AL",
    "sg:tags":[
        "auditing",
        "bookkeeping"
    ],
    "wof:name":"Robbie L Howard Pub Accountant",
    "wof:placetype":"venue"
},
  "geometry": {"coordinates":[-86.845982,33.365806],"type":"Point"}
}