{
  "type": "Feature",
  "properties": {
    "iso:country":"US",
    "sg:address":"2107 Marlboro St",
    "sg:city":"Birmingham",
    "sg:classifiers":[
        {
            "category":"Retail",
            "subcategory":"Animal Services",
            "type":"Services"
        }
    ],
    "sg:phone":"+1 205 979 9878",
    "sg:postcode":"35226",
    "sg:province":"AL",
    "sg:tags":[
        "pet",
        "grooming",
        "washing"
    ],
    "wof:name":"J R's Pet Grooming",
    "wof:placetype":"venue"
},
  "geometry": {"coordinates":[-86.822275,33.431686],"type":"Point"}
}