{
  "type": "Feature",
  "properties": {
    "iso:country":"US",
    "sg:address":"1825 Mount Meigs Rd",
    "sg:city":"Montgomery",
    "sg:classifiers":[
        {
            "category":"Insurance",
            "subcategory":"Insurance Agent",
            "type":"Services"
        }
    ],
    "sg:phone":"+1 334 262 1112",
    "sg:postcode":"36107",
    "sg:province":"AL",
    "wof:name":"Moore Insurance",
    "wof:placetype":"venue"
},
  "geometry": {"coordinates":[-86.282572,32.376489],"type":"Point"}
}