{
  "type": "Feature",
  "properties": {
    "iso:country":"US",
    "sg:address":"3130 Ching Dairy Rd",
    "sg:city":"Mobile",
    "sg:classifiers":[
        {
            "category":"Wholesale",
            "subcategory":"Machinery & Supplies",
            "type":"Manufacturing & Wholesale Goods"
        }
    ],
    "sg:phone":"+1 251 476 8774",
    "sg:postcode":"36618",
    "sg:province":"AL",
    "sg:tags":[
        "printing"
    ],
    "wof:name":"A B Dick Co",
    "wof:placetype":"venue"
},
  "geometry": {"coordinates":[-88.208542,30.755732],"type":"Point"}
}