{
  "type": "Feature",
  "properties": {
    "addr:full":"2230 Sumpter St Birmingham AL 35226",
    "addr:housenumber":"2230",
    "addr:postcode":"35226",
    "addr:street":"Sumpter St",
    "iso:country":"US",
    "sg:address":"2230 Sumpter St",
    "sg:city":"Birmingham",
    "sg:classifiers":[
        {
            "category":"Place Of Worship",
            "subcategory":"Church",
            "type":"Public Place"
        },
        {
            "category":"Place Of Worship",
            "type":"Public Place"
        }
    ],
    "sg:phone":"+1 205 822 3117",
    "sg:postcode":"35226",
    "sg:province":"AL",
    "sg:tags":[
        "churches-independent"
    ],
    "wof:name":"Shades Mountain Bible Church",
    "wof:placetype":"venue"
},
  "geometry": {"coordinates":[-86.823776,33.428139],"type":"Point"}
}