{
  "type": "Feature",
  "properties": {
    "iso:country":"US",
    "sg:address":"1532 Saulter View Rd",
    "sg:city":"Birmingham",
    "sg:classifiers":[
        {
            "category":"Professional",
            "subcategory":"Business Services",
            "type":"Services"
        }
    ],
    "sg:phone":"+1 205 223 6688",
    "sg:postcode":"35209",
    "sg:province":"AL",
    "sg:tags":[
        "fund",
        "raising",
        "organization"
    ],
    "wof:name":"P F B Consulting Inc",
    "wof:placetype":"venue"
},
  "geometry": {"coordinates":[-86.79937,33.466326],"type":"Point"}
}