{
  "type": "Feature",
  "properties": {
    "iso:country":"US",
    "sg:address":"1010 S Park Ave",
    "sg:city":"Dothan",
    "sg:classifiers":[
        {
            "category":"Restaurant",
            "type":"Food & Drink"
        }
    ],
    "sg:phone":"+1 334 792 6558",
    "sg:postcode":"36301",
    "sg:province":"AL",
    "sg:tags":[
        "delicatessen"
    ],
    "wof:name":"Pa's Place",
    "wof:placetype":"venue"
},
  "geometry": {"coordinates":[-85.409264,31.214428],"type":"Point"}
}