{
  "type": "Feature",
  "properties": {
    "iso:country":"US",
    "sg:address":"1214 Co Rd 50",
    "sg:city":"Collinsville",
    "sg:classifiers":[
        {
            "category":"Manufacturing",
            "subcategory":"Building Materials",
            "type":"Manufacturing & Wholesale Goods"
        }
    ],
    "sg:phone":"+1 256 623 3553",
    "sg:postcode":"35961",
    "sg:province":"AL",
    "sg:tags":[
        "mfg",
        "metal",
        "carpentry"
    ],
    "wof:name":"Custom Door & Trim Inc",
    "wof:placetype":"venue"
},
  "geometry": {"coordinates":[-85.873409,34.399117],"type":"Point"}
}