{
  "type": "Feature",
  "properties": {
    "addr:full":"15024 E Limestone Rd Harvest AL 35749",
    "addr:housenumber":"15024",
    "addr:postcode":"35749",
    "addr:street":"E Limestone Rd",
    "iso:country":"US",
    "sg:address":"15024 E Limestone Rd",
    "sg:city":"Harvest",
    "sg:classifiers":[
        {
            "category":"Shopping",
            "subcategory":"Music",
            "type":"Retail Goods"
        }
    ],
    "sg:phone":"+1 256 230 9510",
    "sg:postcode":"35749",
    "sg:province":"AL",
    "sg:tags":[
        "video",
        "disc",
        "tape",
        "cassette"
    ],
    "wof:name":"Movie Gallery",
    "wof:placetype":"venue"
},
  "geometry": {"coordinates":[-86.832447,34.773996],"type":"Point"}
}