{
  "type": "Feature",
  "properties": {
    "iso:country":"US",
    "sg:address":"209 Lugenia Dr",
    "sg:city":"Gadsden",
    "sg:classifiers":[
        {
            "category":"Professional",
            "subcategory":"Printing & Photocopies",
            "type":"Services"
        }
    ],
    "sg:phone":"+1 256 546 2590",
    "sg:postcode":"35904",
    "sg:province":"AL",
    "sg:tags":[
        "photocopying",
        "business"
    ],
    "wof:name":"Mitchell Blueprinting",
    "wof:placetype":"venue"
},
  "geometry": {"coordinates":[-86.009333,34.035394],"type":"Point"}
}