{
  "type": "Feature",
  "properties": {
    "iso:country":"US",
    "sg:address":"1550 Tara Dr",
    "sg:city":"Columbiana",
    "sg:classifiers":[
        {
            "category":"Sports & Exercise",
            "subcategory":"Gym",
            "type":"Entertainment"
        }
    ],
    "sg:phone":"+1 205 678 2676",
    "sg:postcode":"35051",
    "sg:province":"AL",
    "sg:tags":[
        "fitness",
        "physical",
        "facility"
    ],
    "wof:name":"Gym Dandies Gymnastics",
    "wof:placetype":"venue"
},
  "geometry": {"coordinates":[-86.637841,33.300048],"type":"Point"}
}