{
  "type": "Feature",
  "properties": {
    "iso:country":"US",
    "sg:address":"1725 Pine St",
    "sg:city":"Montgomery",
    "sg:classifiers":[
        {
            "category":"Shopping",
            "subcategory":"Gifts & Souvenirs",
            "type":"Retail Goods"
        }
    ],
    "sg:phone":"+1 334 293 8821",
    "sg:postcode":"36106",
    "sg:province":"AL",
    "wof:name":"Flowers Gifts",
    "wof:placetype":"venue"
},
  "geometry": {"coordinates":[-86.285858,32.366622],"type":"Point"}
}