{
  "type": "Feature",
  "properties": {
    "iso:country":"US",
    "sg:address":"2100 Blue Spring Rd NW",
    "sg:city":"Huntsville",
    "sg:classifiers":[
        {
            "category":"Banks & Credit Unions",
            "subcategory":"Bank",
            "type":"Services"
        }
    ],
    "sg:phone":"+1 256 851 8388",
    "sg:postcode":"35810",
    "sg:province":"AL",
    "sg:tags":[
        "cashing",
        "check"
    ],
    "wof:name":"Cash N/A Jiffy",
    "wof:placetype":"venue"
},
  "geometry": {"coordinates":[-86.603393,34.749418],"type":"Point"}
}