{
  "type": "Feature",
  "properties": {
    "addr:full":"86 Reid Cir Deatsville AL 36022",
    "addr:housenumber":"86",
    "addr:postcode":"36022",
    "addr:street":"Reid Cir",
    "iso:country":"US",
    "sg:address":"86 Reid Cir",
    "sg:city":"Deatsville",
    "sg:classifiers":[
        {
            "category":"Professional",
            "subcategory":"Business Services",
            "type":"Services"
        }
    ],
    "sg:phone":"+1 334 365 2811",
    "sg:postcode":"36022",
    "sg:province":"AL",
    "wof:name":"Ebert Enterprises LLC",
    "wof:placetype":"venue"
},
  "geometry": {"coordinates":[-86.406633,32.5415],"type":"Point"}
}