{
  "type": "Feature",
  "properties": {
    "addr:full":"810 Beltline Rd SW Decatur AL 35601",
    "addr:housenumber":"810",
    "addr:postcode":"35601",
    "addr:street":"Beltline Rd Sw",
    "iso:country":"US",
    "sg:address":"810 Beltline Rd SW",
    "sg:city":"Decatur",
    "sg:classifiers":[
        {
            "category":"Retail",
            "subcategory":"Car Wash",
            "type":"Services"
        }
    ],
    "sg:phone":"+1 256 350 6202",
    "sg:postcode":"35601",
    "sg:province":"AL",
    "sg:tags":[
        "polishing",
        "washing"
    ],
    "wof:name":"Beltline Car Wash & Lube Inc",
    "wof:placetype":"venue"
},
  "geometry": {"coordinates":[-86.99970500000001,34.560188],"type":"Point"}
}