{
  "type": "Feature",
  "properties": {
    "addr:full":"1399 Nature Trl Jacksonville AL 36265",
    "addr:housenumber":"1399",
    "addr:postcode":"36265",
    "addr:street":"Nature Trl",
    "iso:country":"US",
    "sg:address":"1399 Nature Trl",
    "sg:city":"Jacksonville",
    "sg:classifiers":[
        {
            "category":"Food & Beverages",
            "subcategory":"Groceries & Convenience Stores",
            "type":"Retail Goods"
        }
    ],
    "sg:phone":"+1 256 231 0070",
    "sg:postcode":"36265",
    "sg:province":"AL",
    "wof:name":"White Plains Snack & Save",
    "wof:placetype":"venue"
},
  "geometry": {"coordinates":[-85.684425,33.81822],"type":"Point"}
}