{
  "type": "Feature",
  "properties": {
    "iso:country":"US",
    "sg:address":"1914 13th Ave S",
    "sg:city":"Birmingham",
    "sg:classifiers":[
        {
            "category":"Health Services",
            "subcategory":"Doctor",
            "type":"Services"
        }
    ],
    "sg:phone":"+1 205 933 1392",
    "sg:postcode":"35205",
    "sg:province":"AL",
    "sg:tags":[
        "dentist"
    ],
    "wof:name":"William M Lawson DMD",
    "wof:placetype":"venue"
},
  "geometry": {"coordinates":[-86.795943,33.498297],"type":"Point"}
}