{
  "type": "Feature",
  "properties": {
    "iso:country":"US",
    "sg:address":"1819 29th Ave S",
    "sg:city":"Birmingham",
    "sg:phone":"+1 205 871 3283",
    "sg:postcode":"35209",
    "sg:province":"AL",
    "wof:name":"Dave's Pizza",
    "wof:placetype":"venue"
},
  "geometry": {"coordinates":[-86.79074900000001,33.47961],"type":"Point"}
}