{
  "type": "Feature",
  "properties": {
    "iso:country":"US",
    "sg:address":"11250 US Hwy 431",
    "sg:city":"Wellington",
    "sg:classifiers":[
        {
            "category":"Retail",
            "subcategory":"Repair Shop",
            "type":"Services"
        }
    ],
    "sg:phone":"+1 256 892 9097",
    "sg:postcode":"36279",
    "sg:province":"AL",
    "sg:tags":[
        "welding"
    ],
    "wof:name":"Turner Welding",
    "wof:placetype":"venue"
},
  "geometry": {"coordinates":[-85.914278,33.837918],"type":"Point"}
}