{
  "type": "Feature",
  "properties": {
    "iso:country":"US",
    "sg:address":"3305 Lorna Rd",
    "sg:city":"Birmingham",
    "sg:classifiers":[
        {
            "category":"Restaurant",
            "type":"Food & Drink"
        }
    ],
    "sg:phone":"+1 205 824 2955",
    "sg:postcode":"35216",
    "sg:province":"AL",
    "sg:tags":[
        "cafe"
    ],
    "wof:name":"Tropical Smoothie Cafe",
    "wof:placetype":"venue"
},
  "geometry": {"coordinates":[-86.79819,33.393568],"type":"Point"}
}