{
  "type": "Feature",
  "properties": {
    "iso:country":"US",
    "sg:address":"740 Schillinger Rd S",
    "sg:city":"Mobile",
    "sg:classifiers":[
        {
            "category":"Restaurant",
            "type":"Food & Drink"
        }
    ],
    "sg:phone":"+1 251 633 4870",
    "sg:postcode":"36608",
    "sg:province":"AL",
    "sg:tags":[
        "eating"
    ],
    "wof:name":"China Ocean and Seafood Buffet",
    "wof:placetype":"venue"
},
  "geometry": {"coordinates":[-88.225389,30.67062],"type":"Point"}
}