{
  "type": "Feature",
  "properties": {
    "iso:country":"US",
    "sg:address":"16 Office Park Cir",
    "sg:city":"Birmingham",
    "sg:classifiers":[
        {
            "category":"Retail",
            "subcategory":"Portrait Studio",
            "type":"Services"
        },
        {
            "category":"Professional",
            "subcategory":"Art Services",
            "type":"Services"
        }
    ],
    "sg:phone":"+1 205 870 1883",
    "sg:postcode":"35223",
    "sg:province":"AL",
    "sg:tags":[
        "photo",
        "photography",
        "commercial",
        "photographer"
    ],
    "sg:website":"www.altmarkphoto.com",
    "wof:name":"Barry C Altmark Photography",
    "wof:placetype":"venue"
},
  "geometry": {"coordinates":[-86.769521,33.478926],"type":"Point"}
}