{
  "type": "Feature",
  "properties": {
    "addr:full":"3333 35th Ave N Birmingham AL 35207",
    "addr:housenumber":"3333",
    "addr:postcode":"35207",
    "addr:street":"35Th Ave N",
    "iso:country":"US",
    "sg:address":"3333 35th Ave N",
    "sg:city":"Birmingham",
    "sg:classifiers":[
        {
            "category":"Manufacturing",
            "subcategory":"Metals",
            "type":"Manufacturing & Wholesale Goods"
        }
    ],
    "sg:phone":"+1 205 841 8725",
    "sg:postcode":"35207",
    "sg:province":"AL",
    "sg:tags":[
        "die",
        "ar",
        "iron",
        "aluminum",
        "mfg"
    ],
    "wof:name":"Barry-Craft",
    "wof:placetype":"venue"
},
  "geometry": {"coordinates":[-86.80555,33.560769],"type":"Point"}
}