{
  "type": "Feature",
  "properties": {
    "addr:full":"15801 E Limestone Rd Athens AL 35613",
    "addr:housenumber":"15801",
    "addr:postcode":"35613",
    "addr:street":"E Limestone Rd",
    "iso:country":"US",
    "sg:address":"15801 E Limestone Rd",
    "sg:city":"Athens",
    "sg:classifiers":[
        {
            "category":"Government",
            "subcategory":"Fire Station",
            "type":"Public Place"
        }
    ],
    "sg:phone":"+1 256 232 5795",
    "sg:postcode":"35613",
    "sg:province":"AL",
    "sg:tags":[
        "department"
    ],
    "wof:name":"East Limestone Volunteer Fire",
    "wof:placetype":"venue"
},
  "geometry": {"coordinates":[-86.83264,34.7852],"type":"Point"}
}