{
  "type": "Feature",
  "properties": {
    "addr:full":"101 E Appletree St Scottsboro AL 35768",
    "addr:housenumber":"101",
    "addr:postcode":"35768",
    "addr:street":"E Appletree St",
    "iso:country":"US",
    "sg:address":"101 E Appletree St",
    "sg:city":"Scottsboro",
    "sg:classifiers":[
        {
            "category":"Health Services",
            "subcategory":"Chiropractor",
            "type":"Services"
        }
    ],
    "sg:phone":"+1 256 259 0333",
    "sg:postcode":"35768",
    "sg:province":"AL",
    "wof:name":"Siniard Family Chiropractic",
    "wof:placetype":"venue"
},
  "geometry": {"coordinates":[-86.03480999999999,34.67093],"type":"Point"}
}