{
  "type": "Feature",
  "properties": {
    "addr:full":"3181 Dolly Ridge Dr Birmingham AL 35243",
    "addr:housenumber":"3181",
    "addr:postcode":"35243",
    "addr:street":"Dolly Ridge Dr",
    "iso:country":"US",
    "sg:address":"3181 Dolly Ridge Dr",
    "sg:city":"Birmingham",
    "sg:classifiers":[
        {
            "category":"Organizations",
            "subcategory":"Religious Organization",
            "type":"Services"
        }
    ],
    "sg:phone":"+1 205 967 1634",
    "sg:postcode":"35243",
    "sg:province":"AL",
    "wof:name":"Briarwood Presbyterian",
    "wof:placetype":"venue"
},
  "geometry": {"coordinates":[-86.73604,33.448246],"type":"Point"}
}