{
  "type": "Feature",
  "properties": {
    "iso:country":"US",
    "sg:address":"377 Red Stick Rd",
    "sg:city":"Pelham",
    "sg:classifiers":[
        {
            "category":"Professional",
            "subcategory":"Advertising",
            "type":"Services"
        }
    ],
    "sg:phone":"+1 205 408 7150",
    "sg:postcode":"35124",
    "sg:province":"AL",
    "sg:tags":[
        "representative"
    ],
    "wof:name":"Birmingham Christian Family",
    "wof:placetype":"venue"
},
  "geometry": {"coordinates":[-86.737235,33.370512],"type":"Point"}
}