{
  "type": "Feature",
  "properties": {
    "addr:full":"13675 Remlap Dr Remlap AL 35133",
    "addr:housenumber":"13675",
    "addr:postcode":"35133",
    "addr:street":"Remlap Dr Remlap",
    "iso:country":"US",
    "sg:address":"13675 Remlap Dr",
    "sg:city":"Remlap",
    "sg:classifiers":[
        {
            "category":"Manufacturing",
            "subcategory":"Tools & Machinery",
            "type":"Manufacturing & Wholesale Goods"
        }
    ],
    "sg:phone":"+1 205 680 5340",
    "sg:postcode":"35133",
    "sg:province":"AL",
    "sg:tags":[
        "pattern",
        "maker"
    ],
    "wof:name":"Ling Pattern Works",
    "wof:placetype":"venue"
},
  "geometry": {"coordinates":[-86.63299499999999,33.770207],"type":"Point"}
}