{
  "type": "Feature",
  "properties": {
    "addr:full":"5051 Cardinal St Trussville AL 35173",
    "addr:housenumber":"5051",
    "addr:postcode":"35173",
    "addr:street":"Cardinal St",
    "iso:country":"US",
    "sg:address":"5051 Cardinal St",
    "sg:city":"Trussville",
    "sg:classifiers":[
        {
            "category":"Wholesale",
            "subcategory":"Petroleum",
            "type":"Manufacturing & Wholesale Goods"
        }
    ],
    "sg:phone":"+1 205 661 2799",
    "sg:postcode":"35173",
    "sg:province":"AL",
    "sg:tags":[
        "bulk",
        "grocery",
        "station"
    ],
    "wof:name":"Mc Pherson Oil Company Inc",
    "wof:placetype":"venue"
},
  "geometry": {"coordinates":[-86.566717,33.646241],"type":"Point"}
}