{
  "type": "Feature",
  "properties": {
    "iso:country":"US",
    "sg:address":"5817 Old Leeds Rd",
    "sg:city":"Birmingham",
    "sg:classifiers":[
        {
            "category":"Communications",
            "subcategory":"Television Station",
            "type":"Services"
        }
    ],
    "sg:phone":"+1 205 956 0015",
    "sg:postcode":"35210",
    "sg:province":"AL",
    "sg:tags":[
        "broadcast",
        "representative"
    ],
    "wof:name":"Immaculate Heart Educational Broadcasting",
    "wof:placetype":"venue"
},
  "geometry": {"coordinates":[-86.67604,33.533955],"type":"Point"}
}