{
  "type": "Feature",
  "properties": {
    "iso:country":"US",
    "sg:address":"5176 Lancelot Dr E",
    "sg:city":"Mobile",
    "sg:classifiers":[
        {
            "category":"Wholesale",
            "subcategory":"Hardware",
            "type":"Manufacturing & Wholesale Goods"
        }
    ],
    "sg:phone":"+1 251 661 7648",
    "sg:postcode":"36619",
    "sg:province":"AL",
    "wof:name":"Vise Air Systems",
    "wof:placetype":"venue"
},
  "geometry": {"coordinates":[-88.19831,30.582652],"type":"Point"}
}