{
  "type": "Feature",
  "properties": {
    "iso:country":"US",
    "sg:address":"4970 Corporate Dr NW",
    "sg:city":"Huntsville",
    "sg:classifiers":[
        {
            "category":"Wholesale",
            "subcategory":"Electrical",
            "type":"Manufacturing & Wholesale Goods"
        }
    ],
    "sg:phone":"+1 256 430 0114",
    "sg:postcode":"35805",
    "sg:province":"AL",
    "sg:tags":[
        "electronic",
        "public",
        "relations"
    ],
    "wof:name":"Texas Instruments",
    "wof:placetype":"venue"
},
  "geometry": {"coordinates":[-86.656972,34.733154],"type":"Point"}
}