{
  "type": "Feature",
  "properties": {
    "addr:full":"126 S Alice St Dothan AL 36301",
    "addr:housenumber":"126",
    "addr:postcode":"36301",
    "addr:street":"S Alice St",
    "iso:country":"US",
    "sg:address":"126 S Alice St",
    "sg:city":"Dothan",
    "sg:classifiers":[
        {
            "category":"Personal",
            "subcategory":"Beauty Salon",
            "type":"Services"
        }
    ],
    "sg:phone":"+1 334 702 7333",
    "sg:postcode":"36301",
    "sg:province":"AL",
    "wof:name":"Styles By Bernard",
    "wof:placetype":"venue"
},
  "geometry": {"coordinates":[-85.397317,31.223515],"type":"Point"}
}