{
  "type": "Feature",
  "properties": {
    "iso:country":"US",
    "sg:address":"319 College Dr NE",
    "sg:city":"Hanceville",
    "sg:classifiers":[
        {
            "category":"Organizations",
            "subcategory":"Religious Organization",
            "type":"Services"
        }
    ],
    "sg:phone":"+1 256 352 4000",
    "sg:postcode":"35077",
    "sg:province":"AL",
    "sg:tags":[
        "church"
    ],
    "wof:name":"Faith Restoration",
    "wof:placetype":"venue"
},
  "geometry": {"coordinates":[-86.775578,34.070224],"type":"Point"}
}