{
  "type": "Feature",
  "properties": {
    "iso:country":"US",
    "sg:address":"3302 McFarland Blvd E",
    "sg:city":"Tuscaloosa",
    "sg:classifiers":[
        {
            "category":"Bus Charters",
            "type":"Transportation"
        }
    ],
    "sg:phone":"+1 205 556 5757",
    "sg:postcode":"35405",
    "sg:province":"AL",
    "sg:tags":[
        "rental"
    ],
    "wof:name":"Tuscaloosa Charter Svc",
    "wof:placetype":"venue"
},
  "geometry": {"coordinates":[-87.525019,33.17846],"type":"Point"}
}