{
  "type": "Feature",
  "properties": {
    "addr:full":"6448 Telia Dr Pinson AL 35126",
    "addr:housenumber":"6448",
    "addr:postcode":"35126",
    "addr:street":"Telia Dr",
    "iso:country":"US",
    "sg:address":"6448 Telia Dr",
    "sg:city":"Pinson",
    "sg:classifiers":[
        {
            "category":"Professional",
            "type":"Services"
        }
    ],
    "sg:phone":"+1 205 283 6456",
    "sg:postcode":"35126",
    "sg:province":"AL",
    "wof:name":"X Scape",
    "wof:placetype":"venue"
},
  "geometry": {"coordinates":[-86.636988,33.692911],"type":"Point"}
}