{
  "type": "Feature",
  "properties": {
    "iso:country":"US",
    "sg:address":"2240 Rocky Ridge Rd",
    "sg:city":"Birmingham",
    "sg:classifiers":[
        {
            "category":"Organizations",
            "subcategory":"Religious Organization",
            "type":"Services"
        }
    ],
    "sg:phone":"+1 205 823 0288",
    "sg:postcode":"35216",
    "sg:province":"AL",
    "wof:name":"Disciples Fellowship",
    "wof:placetype":"venue"
},
  "geometry": {"coordinates":[-86.787975,33.401734],"type":"Point"}
}