{
  "type": "Feature",
  "properties": {
    "iso:country":"US",
    "sg:address":"1414 2nd Ave N",
    "sg:city":"Bessemer",
    "sg:classifiers":[
        {
            "category":"Organizations",
            "subcategory":"Religious Organization",
            "type":"Services"
        }
    ],
    "sg:phone":"+1 205 424 8181",
    "sg:postcode":"35020",
    "sg:province":"AL",
    "sg:tags":[
        "church"
    ],
    "wof:name":"Jehovah's Witnesses",
    "wof:placetype":"venue"
},
  "geometry": {"coordinates":[-86.956225,33.397487],"type":"Point"}
}