{
  "type": "Feature",
  "properties": {
    "iso:country":"US",
    "sg:address":"4518 Valleydale Rd",
    "sg:city":"Birmingham",
    "sg:classifiers":[
        {
            "category":"Home & Garden",
            "subcategory":"Building Materials",
            "type":"Retail Goods"
        },
        {
            "category":"Manufacturing",
            "subcategory":"Lumber",
            "type":"Manufacturing & Wholesale Goods"
        }
    ],
    "sg:phone":"+1 205 437 2020",
    "sg:postcode":"35242",
    "sg:province":"AL",
    "sg:tags":[
        "timberland",
        "lumber-wholesale",
        "lumber-used",
        "timber"
    ],
    "wof:name":"Pine Forest Products Inc",
    "wof:placetype":"venue"
},
  "geometry": {"coordinates":[-86.736121,33.384615],"type":"Point"}
}