{
  "type": "Feature",
  "properties": {
    "addr:full":"6995 Atlanta Hwy Montgomery AL 36117",
    "addr:housenumber":"6995",
    "addr:postcode":"36117",
    "addr:street":"Atlanta Hwy",
    "iso:country":"US",
    "sg:address":"6995 Atlanta Hwy",
    "sg:city":"Montgomery",
    "sg:classifiers":[
        {
            "category":"Shopping",
            "subcategory":"Pharmacy",
            "type":"Retail Goods"
        }
    ],
    "sg:phone":"+1 334 277 8253",
    "sg:postcode":"36117",
    "sg:province":"AL",
    "wof:name":"Rite Aid",
    "wof:placetype":"venue"
},
  "geometry": {"coordinates":[-86.17603800000001,32.382556],"type":"Point"}
}