{
  "type": "Feature",
  "properties": {
    "iso:country":"US",
    "sg:address":"186 Alto Shipman Rd",
    "sg:city":"Ariton",
    "sg:classifiers":[
        {
            "category":"Organizations",
            "subcategory":"Religious Organization",
            "type":"Services"
        }
    ],
    "sg:phone":"+1 334 397 2942",
    "sg:postcode":"36311",
    "sg:province":"AL",
    "wof:name":"Elamville House Of Prayer",
    "wof:placetype":"venue"
},
  "geometry": {"coordinates":[-85.681696,31.665111],"type":"Point"}
}