{
  "type": "Feature",
  "properties": {
    "iso:country":"US",
    "sg:address":"1455 Montlimar Dr",
    "sg:city":"Mobile",
    "sg:classifiers":[
        {
            "category":"Professional",
            "subcategory":"Business Services",
            "type":"Services"
        }
    ],
    "sg:phone":"+1 251 344 4471",
    "sg:postcode":"36609",
    "sg:province":"AL",
    "sg:tags":[
        "equipment",
        "microfilming"
    ],
    "wof:name":"J H Rich Co",
    "wof:placetype":"venue"
},
  "geometry": {"coordinates":[-88.135003,30.674826],"type":"Point"}
}