{
  "type": "Feature",
  "properties": {
    "addr:full":"638 Signal Point Rd Guntersville AL 35976",
    "addr:housenumber":"638",
    "addr:postcode":"35976",
    "addr:street":"Signal Point Rd",
    "iso:country":"US",
    "sg:address":"638 Signal Point Rd",
    "sg:city":"Guntersville",
    "sg:classifiers":[
        {
            "category":"Wholesale",
            "subcategory":"Construction Materials",
            "type":"Manufacturing & Wholesale Goods"
        }
    ],
    "sg:phone":"+1 256 582 9299",
    "sg:postcode":"35976",
    "sg:province":"AL",
    "sg:tags":[
        "timberland",
        "company",
        "timber"
    ],
    "wof:name":"Southern Timberwrights",
    "wof:placetype":"venue"
},
  "geometry": {"coordinates":[-86.272392,34.350482],"type":"Point"}
}