{
  "type": "Feature",
  "properties": {
    "addr:full":"1331 US-72 E Athens AL 35611",
    "addr:housenumber":"1331",
    "addr:postcode":"35611",
    "addr:street":"Us-72 E",
    "iso:country":"US",
    "sg:address":"1331 US-72 E",
    "sg:city":"Athens",
    "sg:classifiers":[
        {
            "category":"Restaurant",
            "type":"Food & Drink"
        }
    ],
    "sg:menulink":"http://www.allmenus.com/al/athens/56253-applebees/menu/",
    "sg:phone":"+1 256 233 4430",
    "sg:postcode":"35611",
    "sg:province":"AL",
    "sg:tags":[
        "burger",
        "american",
        "sandwich",
        "soup"
    ],
    "wof:name":"Applebee's",
    "wof:placetype":"venue"
},
  "geometry": {"coordinates":[-86.98631899999999,34.790374],"type":"Point"}
}