{
  "type": "Feature",
  "properties": {
    "iso:country":"US",
    "sg:address":"206 Spring Valley Ct",
    "sg:city":"Huntsville",
    "sg:classifiers":[
        {
            "category":"Professional",
            "subcategory":"Business Services",
            "type":"Services"
        }
    ],
    "sg:phone":"+1 256 882 9544",
    "sg:postcode":"35802",
    "sg:province":"AL",
    "wof:name":"J T Decor",
    "wof:placetype":"venue"
},
  "geometry": {"coordinates":[-86.572486,34.684746],"type":"Point"}
}