{
  "type": "Feature",
  "properties": {
    "addr:full":"4615 14th Ave N Birmingham AL 35212",
    "addr:housenumber":"4615",
    "addr:postcode":"35212",
    "addr:street":"14Th Ave N",
    "iso:country":"US",
    "sg:address":"4615 14th Ave N",
    "sg:city":"Birmingham",
    "sg:classifiers":[
        {
            "category":"Professional",
            "subcategory":"Business Services",
            "type":"Services"
        }
    ],
    "sg:phone":"+1 205 591 4694",
    "sg:postcode":"35212",
    "sg:province":"AL",
    "wof:name":"Living In Style",
    "wof:placetype":"venue"
},
  "geometry": {"coordinates":[-86.76969200000001,33.547562],"type":"Point"}
}