{
  "type": "Feature",
  "properties": {
    "addr:full":"380 Co Rd 489 Woodland AL 36280",
    "addr:housenumber":"380;489",
    "addr:postcode":"36280",
    "addr:street":"Co Rd;Woodland",
    "iso:country":"US",
    "sg:address":"380 Co Rd 489",
    "sg:city":"Woodland",
    "sg:classifiers":[
        {
            "category":"Freight",
            "type":"Transportation"
        }
    ],
    "sg:phone":"+1 256 449 2485",
    "sg:postcode":"36280",
    "sg:province":"AL",
    "sg:tags":[
        "local",
        "storage",
        "trucking"
    ],
    "wof:name":"Herdan Inc",
    "wof:placetype":"venue"
},
  "geometry": {"coordinates":[-85.354733,33.350541],"type":"Point"}
}