{
  "type": "Feature",
  "properties": {
    "iso:country":"US",
    "sg:address":"900 Commons Dr",
    "sg:city":"Dothan",
    "sg:classifiers":[
        {
            "category":"Shopping",
            "subcategory":"Clothing, Apparel, & Fashions",
            "type":"Retail Goods"
        }
    ],
    "sg:phone":"+1 334 718 6289",
    "sg:postcode":"36303",
    "sg:province":"AL",
    "sg:tags":[
        "family"
    ],
    "wof:name":"Photos Etc",
    "wof:placetype":"venue"
},
  "geometry": {"coordinates":[-85.427883,31.255077],"type":"Point"}
}