{
  "type": "Feature",
  "properties": {
    "iso:country":"US",
    "sg:address":"156 McGregor Ave",
    "sg:city":"Mobile",
    "sg:classifiers":[
        {
            "category":"Restaurant",
            "type":"Food & Drink"
        }
    ],
    "sg:phone":"+1 251 343 0003",
    "sg:postcode":"36608",
    "sg:province":"AL",
    "sg:tags":[
        "eating"
    ],
    "wof:name":"Papa's Place Pizza",
    "wof:placetype":"venue"
},
  "geometry": {"coordinates":[-88.145674,30.689407],"type":"Point"}
}