{
  "type": "Feature",
  "properties": {
    "iso:country":"US",
    "sg:address":"2380 Pepperell Pkwy",
    "sg:city":"Opelika",
    "sg:classifiers":[
        {
            "category":"Shopping",
            "subcategory":"Clothing, Apparel, & Fashions",
            "type":"Retail Goods"
        }
    ],
    "sg:phone":"+1 334 749 6311",
    "sg:postcode":"36801",
    "sg:province":"AL",
    "wof:name":"Cato",
    "wof:placetype":"venue"
},
  "geometry": {"coordinates":[-85.413738,32.637587],"type":"Point"}
}