{
  "type": "Feature",
  "properties": {
    "iso:country":"US",
    "sg:address":"112 Stonehaven Way",
    "sg:city":"Pelham",
    "sg:classifiers":[
        {
            "category":"Professional",
            "subcategory":"Business Services",
            "type":"Services"
        }
    ],
    "sg:phone":"+1 205 620 9618",
    "sg:postcode":"35124",
    "sg:province":"AL",
    "wof:name":"Netuition Technologies LLC",
    "wof:placetype":"venue"
},
  "geometry": {"coordinates":[-86.819485,33.272434],"type":"Point"}
}