{
  "type": "Feature",
  "properties": {
    "iso:country":"US",
    "sg:address":"962 Dr Martin L King Jr Ave",
    "sg:city":"Mobile",
    "sg:classifiers":[
        {
            "category":"Shopping",
            "subcategory":"Discount & Variety Stores",
            "type":"Retail Goods"
        },
        {
            "category":"Restaurant",
            "type":"Food & Drink"
        }
    ],
    "sg:phone":"+1 251 433 3222",
    "sg:postcode":"36603",
    "sg:province":"AL",
    "sg:tags":[
        "delivery"
    ],
    "wof:name":"Mlk Variety Shop",
    "wof:placetype":"venue"
},
  "geometry": {"coordinates":[-88.05779099999999,30.697458],"type":"Point"}
}