{
  "type": "Feature",
  "properties": {
    "iso:country":"US",
    "sg:address":"13309 Co Rd 32",
    "sg:city":"Summerdale",
    "sg:classifiers":[
        {
            "category":"Autos & Motor Vehicles",
            "subcategory":"Automobile Sales",
            "type":"Retail Goods"
        },
        {
            "category":"Professional",
            "type":"Services"
        }
    ],
    "sg:phone":"+1 251 988 1905",
    "sg:postcode":"36580",
    "sg:province":"AL",
    "sg:tags":[
        "used",
        "establishment"
    ],
    "wof:name":"Fish River Autos",
    "wof:placetype":"venue"
},
  "geometry": {"coordinates":[-87.795798,30.474997],"type":"Point"}
}