{
  "type": "Feature",
  "properties": {
    "addr:full":"4170 Spinnaker Dr Gulf Shores AL 36542",
    "addr:housenumber":"4170",
    "addr:postcode":"36542",
    "addr:street":"Spinnaker Dr",
    "iso:country":"US",
    "sg:address":"4170 Spinnaker Dr",
    "sg:city":"Gulf Shores",
    "sg:classifiers":[
        {
            "category":"Building & Trades",
            "subcategory":"Construction",
            "type":"Services"
        }
    ],
    "sg:phone":"+1 251 967 5438",
    "sg:postcode":"36542",
    "sg:province":"AL",
    "sg:tags":[
        "dock"
    ],
    "wof:name":"Simco Marine Products Inc",
    "wof:placetype":"venue"
},
  "geometry": {"coordinates":[-87.744461,30.284306],"type":"Point"}
}