{
  "type": "Feature",
  "properties": {
    "iso:country":"US",
    "sg:address":"604 W 3rd St",
    "sg:city":"Bay Minette",
    "sg:classifiers":[
        {
            "category":"Professional",
            "subcategory":"Business Services",
            "type":"Services"
        }
    ],
    "sg:phone":"+1 251 937 4268",
    "sg:postcode":"36507",
    "sg:province":"AL",
    "wof:name":"Big L Auctions",
    "wof:placetype":"venue"
},
  "geometry": {"coordinates":[-87.781853,30.881948],"type":"Point"}
}