{
  "type": "Feature",
  "properties": {
    "iso:country":"US",
    "sg:address":"241 Big Springs Dr",
    "sg:city":"Birmingham",
    "sg:classifiers":[
        {
            "category":"Professional",
            "subcategory":"Management & Consulting",
            "type":"Services"
        }
    ],
    "sg:phone":"+1 205 978 0524",
    "sg:postcode":"35216",
    "sg:province":"AL",
    "wof:name":"Rogan Hr Services LLC",
    "wof:placetype":"venue"
},
  "geometry": {"coordinates":[-86.764896,33.458315],"type":"Point"}
}