{
  "type": "Feature",
  "properties": {
    "addr:full":"189 Glaze Ferry Rd Harpersville AL 35078",
    "addr:housenumber":"189",
    "addr:postcode":"35078",
    "addr:street":"Glaze Ferry Rd",
    "iso:country":"US",
    "sg:address":"189 Glaze Ferry Rd",
    "sg:city":"Harpersville",
    "sg:classifiers":[
        {
            "category":"Shopping",
            "type":"Retail Goods"
        }
    ],
    "sg:phone":"+1 205 672 8575",
    "sg:postcode":"35078",
    "sg:province":"AL",
    "sg:tags":[
        "wedding",
        "supply"
    ],
    "wof:name":"Accurate Restoration Photo Svc",
    "wof:placetype":"venue"
},
  "geometry": {"coordinates":[-86.39612,33.345789],"type":"Point"}
}