{
  "type": "Feature",
  "properties": {
    "iso:country":"US",
    "sg:address":"7101 Moffett Rd",
    "sg:city":"Mobile",
    "sg:classifiers":[
        {
            "category":"Home & Garden",
            "subcategory":"Mobile Homes",
            "type":"Retail Goods"
        },
        {
            "category":"Manufacturing",
            "subcategory":"Buildings",
            "type":"Manufacturing & Wholesale Goods"
        }
    ],
    "sg:phone":"+1 251 645 1502",
    "sg:postcode":"36618",
    "sg:province":"AL",
    "sg:tags":[
        "mfg"
    ],
    "wof:name":"Clayton Homes Inc",
    "wof:placetype":"venue"
},
  "geometry": {"coordinates":[-88.216301,30.755637],"type":"Point"}
}