{
  "type": "Feature",
  "properties": {
    "iso:country":"US",
    "sg:address":"299 Chevrolet St",
    "sg:city":"Kinsey",
    "sg:classifiers":[
        {
            "category":"Personal",
            "type":"Services"
        }
    ],
    "sg:phone":"+1 334 673 3613",
    "sg:postcode":"36303",
    "sg:province":"AL",
    "sg:tags":[
        "credit",
        "debt",
        "counseling"
    ],
    "wof:name":"Financial One Credit Svc",
    "wof:placetype":"venue"
},
  "geometry": {"coordinates":[-85.345672,31.285163],"type":"Point"}
}