{
  "type": "Feature",
  "properties": {
    "addr:full":"1800 Gault Ave N Fort Payne AL 35967",
    "addr:housenumber":"1800",
    "addr:postcode":"35967",
    "addr:street":"Gault Ave N",
    "iso:country":"US",
    "sg:address":"1800 Gault Ave N",
    "sg:city":"Fort Payne",
    "sg:classifiers":[
        {
            "category":"Food & Beverages",
            "subcategory":"Groceries & Convenience Stores",
            "type":"Retail Goods"
        }
    ],
    "sg:phone":"+1 256 845 1676",
    "sg:postcode":"35967",
    "sg:province":"AL",
    "wof:name":"Discount Food Mart",
    "wof:placetype":"venue"
},
  "geometry": {"coordinates":[-85.706704,34.459159],"type":"Point"}
}