{
  "type": "Feature",
  "properties": {
    "iso:country":"US",
    "sg:address":"3367 Co Rd 13",
    "sg:city":"Helena",
    "sg:classifiers":[
        {
            "category":"Building & Trades",
            "subcategory":"Construction",
            "type":"Services"
        }
    ],
    "sg:phone":"+1 205 426 3606",
    "sg:postcode":"35080",
    "sg:province":"AL",
    "sg:tags":[
        "water",
        "well",
        "drilling"
    ],
    "wof:name":"Peel Drilling",
    "wof:placetype":"venue"
},
  "geometry": {"coordinates":[-86.959147,33.243857],"type":"Point"}
}