{
  "type": "Feature",
  "properties": {
    "iso:country":"US",
    "sg:address":"3200 Co Rd 83",
    "sg:city":"Cusseta",
    "sg:classifiers":[
        {
            "category":"Government",
            "subcategory":"Post Office",
            "type":"Public Place"
        }
    ],
    "sg:phone":"+1 334 745 3069",
    "sg:postcode":"36852",
    "sg:province":"AL",
    "sg:tags":[
        "postal",
        "us"
    ],
    "wof:name":"US Post Office",
    "wof:placetype":"venue"
},
  "geometry": {"coordinates":[-85.306556,32.786747],"type":"Point"}
}