{
  "type": "Feature",
  "properties": {
    "addr:full":"6500 Zeigler Blvd Mobile AL 36608",
    "addr:postcode":"6500;36608",
    "addr:street":"Zeigler Blvd",
    "iso:country":"US",
    "sg:address":"6500 Zeigler Blvd",
    "sg:city":"Mobile",
    "sg:classifiers":[
        {
            "category":"Organizations",
            "subcategory":"Religious Organization",
            "type":"Services"
        }
    ],
    "sg:phone":"+1 251 343 7300",
    "sg:postcode":"36608",
    "sg:province":"AL",
    "sg:tags":[
        "church"
    ],
    "wof:name":"Gulf Coast Christian Ctr",
    "wof:placetype":"venue"
},
  "geometry": {"coordinates":[-88.191971,30.708753],"type":"Point"}
}