{
  "type": "Feature",
  "properties": {
    "iso:country":"US",
    "sg:address":"10 55th St S",
    "sg:city":"Birmingham",
    "sg:classifiers":[
        {
            "category":"Building & Trades",
            "subcategory":"Plumbing",
            "type":"Services"
        }
    ],
    "sg:phone":"+1 205 595 4846",
    "sg:postcode":"35212",
    "sg:province":"AL",
    "sg:tags":[
        "plumbing",
        "contractor"
    ],
    "wof:name":"Guin Service Inc",
    "wof:placetype":"venue"
},
  "geometry": {"coordinates":[-86.751533,33.537849],"type":"Point"}
}