{
  "type": "Feature",
  "properties": {
    "addr:full":"890 W Main St Dothan AL 36301",
    "addr:housenumber":"890",
    "addr:postcode":"36301",
    "addr:street":"W Main St",
    "iso:country":"US",
    "sg:address":"890 W Main St",
    "sg:city":"Dothan",
    "sg:classifiers":[
        {
            "category":"Food & Beverages",
            "subcategory":"Bakery",
            "type":"Retail Goods"
        }
    ],
    "sg:phone":"+1 334 702 1001",
    "sg:postcode":"36301",
    "sg:province":"AL",
    "wof:name":"Dolly Madison Cake Company",
    "wof:placetype":"venue"
},
  "geometry": {"coordinates":[-85.402497,31.225833],"type":"Point"}
}