{
  "type": "Feature",
  "properties": {
    "iso:country":"US",
    "sg:address":"2009 Rose Rd",
    "sg:city":"Albertville",
    "sg:classifiers":[
        {
            "category":"Building & Trades",
            "subcategory":"Construction",
            "type":"Services"
        }
    ],
    "sg:phone":"+1 256 891 9777",
    "sg:postcode":"35950",
    "sg:province":"AL",
    "sg:tags":[
        "concrete",
        "contractor"
    ],
    "wof:name":"Shell Concrete Finishers",
    "wof:placetype":"venue"
},
  "geometry": {"coordinates":[-86.227863,34.302147],"type":"Point"}
}