{
  "type": "Feature",
  "properties": {
    "iso:country":"US",
    "sg:address":"900 Western American Cir",
    "sg:city":"Mobile",
    "sg:classifiers":[
        {
            "category":"Organizations",
            "subcategory":"Non-profit Organization",
            "type":"Services"
        }
    ],
    "sg:phone":"+1 251 343 5982",
    "sg:postcode":"36609",
    "sg:province":"AL",
    "sg:tags":[
        "social"
    ],
    "wof:name":"Alabama Gulf Regional Office",
    "wof:placetype":"venue"
},
  "geometry": {"coordinates":[-88.130806,30.673327],"type":"Point"}
}