{
  "type": "Feature",
  "properties": {
    "addr:full":"21192 US Hwy 431 Guntersville AL 35976",
    "addr:housenumber":"21192",
    "addr:postcode":"35976",
    "addr:street":"Us Hwy 431",
    "iso:country":"US",
    "sg:address":"21192 US Hwy 431",
    "sg:city":"Guntersville",
    "sg:classifiers":[
        {
            "category":"Restaurant",
            "type":"Food & Drink"
        }
    ],
    "sg:phone":"+1 256 582 4336",
    "sg:postcode":"35976",
    "sg:province":"AL",
    "sg:tags":[
        "eating"
    ],
    "wof:name":"Claysville Snack Bar",
    "wof:placetype":"venue"
},
  "geometry": {"coordinates":[-86.26343799999999,34.422634],"type":"Point"}
}