{
  "type": "Feature",
  "properties": {
    "iso:country":"US",
    "sg:address":"6791 US Hwy 431",
    "sg:city":"Albertville",
    "sg:classifiers":[
        {
            "category":"Cinema",
            "subcategory":"Movie Rental",
            "type":"Entertainment"
        }
    ],
    "sg:phone":"+1 256 878 5925",
    "sg:postcode":"35950",
    "sg:province":"AL",
    "sg:tags":[
        "leasing",
        "video",
        "disc",
        "tape"
    ],
    "wof:name":"Movie Magic",
    "wof:placetype":"venue"
},
  "geometry": {"coordinates":[-86.199028,34.273044],"type":"Point"}
}