{
  "type": "Feature",
  "properties": {
    "addr:full":"323 Airport Rd Auburn AL 36830",
    "addr:housenumber":"323",
    "addr:postcode":"36830",
    "addr:street":"Airport Rd",
    "iso:country":"US",
    "sg:address":"323 Airport Rd",
    "sg:city":"Auburn",
    "sg:classifiers":[
        {
            "category":"Recreation",
            "type":"Entertainment"
        }
    ],
    "sg:phone":"+1 334 502 7221",
    "sg:postcode":"36830",
    "sg:province":"AL",
    "sg:tags":[
        "martial",
        "arts",
        "instruction"
    ],
    "wof:name":"Auburn Academy Of Martial Arts",
    "wof:placetype":"venue"
},
  "geometry": {"coordinates":[-85.440005,32.613346],"type":"Point"}
}