{
  "type": "Feature",
  "properties": {
    "addr:full":"6521 State Rte 69 Tuscaloosa AL 35405",
    "addr:housenumber":"6521",
    "addr:postcode":"35405",
    "addr:street":"State Rte 69",
    "iso:country":"US",
    "sg:address":"6521 State Rte 69",
    "sg:city":"Tuscaloosa",
    "sg:classifiers":[
        {
            "category":"Professional",
            "subcategory":"Accounting & Tax Preparation",
            "type":"Services"
        }
    ],
    "sg:phone":"+1 205 349 3334",
    "sg:postcode":"35405",
    "sg:province":"AL",
    "wof:name":"Anderson Accounting & Tax Svc",
    "wof:placetype":"venue"
},
  "geometry": {"coordinates":[-87.54512,33.148524],"type":"Point"}
}