{
  "type": "Feature",
  "properties": {
    "iso:country":"US",
    "sg:address":"855 Market Pl",
    "sg:city":"Alexander City",
    "sg:classifiers":[
        {
            "category":"Restaurant",
            "type":"Food & Drink"
        }
    ],
    "sg:phone":"+1 256 329 2236",
    "sg:postcode":"35010",
    "sg:province":"AL",
    "sg:tags":[
        "eating"
    ],
    "wof:name":"Domino's Pizza",
    "wof:placetype":"venue"
},
  "geometry": {"coordinates":[-85.962779,32.922728],"type":"Point"}
}