{
  "type": "Feature",
  "properties": {
    "iso:country":"US",
    "sg:address":"5428 Challenger Ln",
    "sg:city":"Bessemer",
    "sg:classifiers":[
        {
            "category":"Organizations",
            "subcategory":"Religious Organization",
            "type":"Services"
        }
    ],
    "sg:phone":"+1 205 426 2931",
    "sg:postcode":"35022",
    "sg:province":"AL",
    "wof:name":"Charlie Pippen Rev",
    "wof:placetype":"venue"
},
  "geometry": {"coordinates":[-87.028216,33.349491],"type":"Point"}
}