{
  "type": "Feature",
  "properties": {
    "iso:country":"US",
    "sg:address":"5880 Wall Triana Hwy",
    "sg:city":"Madison",
    "sg:classifiers":[
        {
            "category":"Retail",
            "subcategory":"Car Wash",
            "type":"Services"
        }
    ],
    "sg:phone":"+1 256 721 3926",
    "sg:postcode":"35758",
    "sg:province":"AL",
    "sg:tags":[
        "carwash"
    ],
    "wof:name":"Wash Master Car Wash",
    "wof:placetype":"venue"
},
  "geometry": {"coordinates":[-86.74986800000001,34.751696],"type":"Point"}
}