{
  "type": "Feature",
  "properties": {
    "iso:country":"US",
    "sg:address":"20 Kohn Dr",
    "sg:city":"Ramer",
    "sg:classifiers":[
        {
            "category":"Education",
            "subcategory":"Library",
            "type":"Public Place"
        }
    ],
    "sg:phone":"+1 334 584 7144",
    "sg:postcode":"36069",
    "sg:province":"AL",
    "wof:name":"Pine Level Library",
    "wof:placetype":"venue"
},
  "geometry": {"coordinates":[-86.059986,32.064496],"type":"Point"}
}