{
  "type": "Feature",
  "properties": {
    "addr:full":"6972 Eastern Shore Rd Montgomery AL 36117",
    "addr:housenumber":"6972",
    "addr:postcode":"36117",
    "addr:street":"Eastern Shore Rd",
    "iso:country":"US",
    "sg:address":"6972 Eastern Shore Rd",
    "sg:city":"Montgomery",
    "sg:classifiers":[
        {
            "category":"Utilities",
            "subcategory":"Mobile Phone",
            "type":"Services"
        }
    ],
    "sg:phone":"+1 800 961 6628",
    "sg:postcode":"36117",
    "sg:province":"AL",
    "sg:tags":[
        "telecommunication"
    ],
    "wof:name":"Southern Communications Svcs",
    "wof:placetype":"venue"
},
  "geometry": {"coordinates":[-86.178782,32.405396],"type":"Point"}
}