{
  "type": "Feature",
  "properties": {
    "iso:country":"US",
    "sg:address":"35905 US Hwy 280",
    "sg:city":"Sylacauga",
    "sg:classifiers":[
        {
            "category":"Manufacturing",
            "subcategory":"Jewelry",
            "type":"Manufacturing & Wholesale Goods"
        }
    ],
    "sg:phone":"+1 256 378 7998",
    "sg:postcode":"35150",
    "sg:province":"AL",
    "sg:tags":[
        "costume",
        "mfg"
    ],
    "wof:name":"Wired Up Inc",
    "wof:placetype":"venue"
},
  "geometry": {"coordinates":[-86.331833,33.238009],"type":"Point"}
}