{
  "type": "Feature",
  "properties": {
    "addr:full":"2941 Ray Ave SW Decatur AL 35603",
    "addr:housenumber":"2941",
    "addr:postcode":"35603",
    "addr:street":"Ray Ave Sw",
    "iso:country":"US",
    "sg:address":"2941 Ray Ave SW",
    "sg:city":"Decatur",
    "sg:classifiers":[
        {
            "category":"Wholesale",
            "subcategory":"Electrical",
            "type":"Manufacturing & Wholesale Goods"
        },
        {
            "category":"Professional",
            "subcategory":"Computer Services",
            "type":"Services"
        }
    ],
    "sg:phone":"+1 256 355 5313",
    "sg:postcode":"35603",
    "sg:province":"AL",
    "sg:tags":[
        "equipment",
        "satellite",
        "system"
    ],
    "wof:name":"Direct Connection LLC",
    "wof:placetype":"venue"
},
  "geometry": {"coordinates":[-86.980576,34.553647],"type":"Point"}
}