{
  "type": "Feature",
  "properties": {
    "addr:full":"1680 19th Pl SW Birmingham AL 35211",
    "addr:housenumber":"1680",
    "addr:postcode":"35211",
    "addr:street":"19Th Pl Sw",
    "iso:country":"US",
    "sg:address":"1680 19th Pl SW",
    "sg:city":"Birmingham",
    "sg:classifiers":[
        {
            "category":"Organizations",
            "subcategory":"Religious Organization",
            "type":"Services"
        }
    ],
    "sg:phone":"+1 205 923 5347",
    "sg:postcode":"35211",
    "sg:province":"AL",
    "wof:name":"West End Hl Miss Baptst Church",
    "wof:placetype":"venue"
},
  "geometry": {"coordinates":[-86.869477,33.467884],"type":"Point"}
}