{
  "type": "Feature",
  "properties": {
    "addr:full":"3376 Cloverdale Rd Florence AL 35633",
    "addr:housenumber":"3376",
    "addr:postcode":"35633",
    "addr:street":"Cloverdale Rd",
    "iso:country":"US",
    "sg:address":"3376 Cloverdale Rd",
    "sg:city":"Florence",
    "sg:classifiers":[
        {
            "category":"Food & Beverages",
            "subcategory":"Liquor & Beverages",
            "type":"Retail Goods"
        },
        {
            "category":"Shopping",
            "subcategory":"Bicycles & Sporting Goods",
            "type":"Retail Goods"
        }
    ],
    "sg:phone":"+1 256 767 7262",
    "sg:postcode":"35633",
    "sg:province":"AL",
    "sg:tags":[
        "a",
        "shop",
        "as",
        "operates"
    ],
    "wof:name":"K C's Discount Package Store",
    "wof:placetype":"venue"
},
  "geometry": {"coordinates":[-87.690319,34.849717],"type":"Point"}
}