{
  "type": "Feature",
  "properties": {
    "addr:full":"505 Nelson St SW Hartselle AL 35640",
    "addr:housenumber":"505",
    "addr:postcode":"35640",
    "addr:street":"Nelson St Sw",
    "iso:country":"US",
    "sg:address":"505 Nelson St SW",
    "sg:city":"Hartselle",
    "sg:classifiers":[
        {
            "category":"Retail",
            "subcategory":"Car Wash",
            "type":"Services"
        }
    ],
    "sg:phone":"+1 256 773 7413",
    "sg:postcode":"35640",
    "sg:province":"AL",
    "sg:tags":[
        "carwash"
    ],
    "wof:name":"Billy Clemons Car Wash",
    "wof:placetype":"venue"
},
  "geometry": {"coordinates":[-86.94571500000001,34.438496],"type":"Point"}
}