{
  "type": "Feature",
  "properties": {
    "iso:country":"US",
    "sg:address":"2805 Southwest St",
    "sg:city":"Montgomery",
    "sg:classifiers":[
        {
            "category":"Retail",
            "subcategory":"Auto Repair",
            "type":"Services"
        }
    ],
    "sg:phone":"+1 334 613 2087",
    "sg:postcode":"36108",
    "sg:province":"AL",
    "sg:tags":[
        "body",
        "automobile",
        "painting"
    ],
    "wof:name":"Auto Warehouse",
    "wof:placetype":"venue"
},
  "geometry": {"coordinates":[-86.345598,32.331619],"type":"Point"}
}