{
  "type": "Feature",
  "properties": {
    "iso:country":"US",
    "sg:address":"1142 Burnwell Rd",
    "sg:city":"Quinton",
    "sg:classifiers":[
        {
            "category":"Health Services",
            "subcategory":"Medical Lab",
            "type":"Services"
        }
    ],
    "sg:phone":"+1 205 648 0412",
    "sg:postcode":"35130",
    "sg:province":"AL",
    "sg:tags":[
        "laboratory",
        "dental"
    ],
    "wof:name":"Tubbs Dental Lab",
    "wof:placetype":"venue"
},
  "geometry": {"coordinates":[-87.108699,33.700793],"type":"Point"}
}