{
  "type": "Feature",
  "properties": {
    "iso:country":"US",
    "sg:address":"110 Buttercup Ln",
    "sg:city":"Madison",
    "sg:classifiers":[
        {
            "category":"Recreation",
            "type":"Entertainment"
        }
    ],
    "sg:phone":"+1 256 461 9553",
    "sg:postcode":"35758",
    "sg:province":"AL",
    "sg:tags":[
        "rubber",
        "pro",
        "mfg",
        "balloon",
        "fabricated"
    ],
    "wof:name":"Gone With Wind Balloon Company",
    "wof:placetype":"venue"
},
  "geometry": {"coordinates":[-86.730931,34.696064],"type":"Point"}
}