{
  "type": "Feature",
  "properties": {
    "addr:full":"12444 Pine Grove Rd Carrollton AL 35447",
    "addr:housenumber":"12444",
    "addr:postcode":"35447",
    "addr:street":"Pine Grove Rd",
    "iso:country":"US",
    "sg:address":"12444 Pine Grove Rd",
    "sg:city":"Carrollton",
    "sg:classifiers":[
        {
            "category":"Wholesale",
            "subcategory":"Farm Supplies",
            "type":"Manufacturing & Wholesale Goods"
        }
    ],
    "sg:phone":"+1 205 367 8441",
    "sg:postcode":"35447",
    "sg:province":"AL",
    "wof:name":"Feed Dealer",
    "wof:placetype":"venue"
},
  "geometry": {"coordinates":[-88.12569499999999,33.285382],"type":"Point"}
}