{
  "type": "Feature",
  "properties": {
    "addr:full":"4112 White Acres Rd Montgomery AL 36106",
    "addr:housenumber":"4112",
    "addr:postcode":"36106",
    "addr:street":"White Acres Rd",
    "iso:country":"US",
    "sg:address":"4112 White Acres Rd",
    "sg:city":"Montgomery",
    "sg:classifiers":[
        {
            "category":"Shopping",
            "type":"Retail Goods"
        }
    ],
    "sg:phone":"+1 334 396 0101",
    "sg:postcode":"36106",
    "sg:province":"AL",
    "sg:tags":[
        "merchandise"
    ],
    "wof:name":"AAA Tel Communications Inc",
    "wof:placetype":"venue"
},
  "geometry": {"coordinates":[-86.239349,32.349471],"type":"Point"}
}