{
  "type": "Feature",
  "properties": {
    "iso:country":"US",
    "sg:address":"1556 8th Ave W",
    "sg:city":"Birmingham",
    "sg:classifiers":[
        {
            "category":"Shopping",
            "subcategory":"Discount & Variety Stores",
            "type":"Retail Goods"
        }
    ],
    "sg:phone":"+1 205 788 3903",
    "sg:postcode":"35208",
    "sg:province":"AL",
    "sg:tags":[
        "merchandise",
        "general"
    ],
    "wof:name":"Dorothys Fashions",
    "wof:placetype":"venue"
},
  "geometry": {"coordinates":[-86.862588,33.512088],"type":"Point"}
}