{
  "type": "Feature",
  "properties": {
    "iso:country":"US",
    "sg:address":"5671 Meadow Tate Dr",
    "sg:city":"Mount Olive",
    "sg:classifiers":[
        {
            "category":"Building & Trades",
            "subcategory":"Construction",
            "type":"Services"
        }
    ],
    "sg:phone":"+1 205 631 4549",
    "sg:postcode":"35117",
    "sg:province":"AL",
    "sg:tags":[
        "house"
    ],
    "wof:name":"M&W Home Construction & Deve",
    "wof:placetype":"venue"
},
  "geometry": {"coordinates":[-86.861726,33.67035],"type":"Point"}
}