{
  "type": "Feature",
  "properties": {
    "iso:country":"US",
    "sg:address":"805 McKenzie St",
    "sg:city":"Foley",
    "sg:classifiers":[
        {
            "category":"Health Services",
            "subcategory":"Hospital",
            "type":"Services"
        }
    ],
    "sg:phone":"+1 251 970 5902",
    "sg:postcode":"36535",
    "sg:province":"AL",
    "sg:tags":[
        "mental"
    ],
    "wof:name":"Gulf Coast Counseling Svc",
    "wof:placetype":"venue"
},
  "geometry": {"coordinates":[-87.683813,30.414626],"type":"Point"}
}