{
  "type": "Feature",
  "properties": {
    "addr:full":"1632 Abbeywood Dr Mobile AL 36695",
    "addr:housenumber":"1632",
    "addr:postcode":"36695",
    "addr:street":"Abbeywood Dr",
    "iso:country":"US",
    "sg:address":"1632 Abbeywood Dr",
    "sg:city":"Mobile",
    "sg:classifiers":[
        {
            "category":"Professional",
            "type":"Services"
        }
    ],
    "sg:phone":"+1 251 633 7800",
    "sg:postcode":"36695",
    "sg:province":"AL",
    "wof:name":"Phil Feldman Dr",
    "wof:placetype":"venue"
},
  "geometry": {"coordinates":[-88.196268,30.656186],"type":"Point"}
}