{
  "type": "Feature",
  "properties": {
    "addr:full":"1114 Eagle Dr Maylene AL 35114",
    "addr:housenumber":"1114",
    "addr:postcode":"35114",
    "addr:street":"Eagle Dr Maylene",
    "iso:country":"US",
    "sg:address":"1114 Eagle Dr",
    "sg:city":"Maylene",
    "sg:classifiers":[
        {
            "category":"Manufacturing",
            "subcategory":"Tools & Machinery",
            "type":"Manufacturing & Wholesale Goods"
        }
    ],
    "sg:phone":"+1 205 621 6405",
    "sg:postcode":"35114",
    "sg:province":"AL",
    "sg:tags":[
        "electric",
        "mfg"
    ],
    "wof:name":"Cooper Wiring Devices Inc",
    "wof:placetype":"venue"
},
  "geometry": {"coordinates":[-86.85979399999999,33.224411],"type":"Point"}
}