{
  "type": "Feature",
  "properties": {
    "iso:country":"US",
    "sg:address":"22270 US Hwy 72",
    "sg:city":"Athens",
    "sg:classifiers":[
        {
            "category":"Health Services",
            "subcategory":"Clinic",
            "type":"Services"
        }
    ],
    "sg:phone":"+1 256 771 0066",
    "sg:postcode":"35613",
    "sg:province":"AL",
    "sg:tags":[
        "specialty",
        "outpatient"
    ],
    "wof:name":"HealthSouth",
    "wof:placetype":"venue"
},
  "geometry": {"coordinates":[-86.92168100000001,34.779274],"type":"Point"}
}