{
  "type": "Feature",
  "properties": {
    "addr:full":"1830 Cherokee Ave SW Cullman AL 35055",
    "addr:housenumber":"1830",
    "addr:postcode":"35055",
    "addr:street":"Cherokee Ave Sw",
    "iso:country":"US",
    "sg:address":"1830 Cherokee Ave SW",
    "sg:city":"Cullman",
    "sg:classifiers":[
        {
            "category":"Restaurant",
            "type":"Food & Drink"
        }
    ],
    "sg:menulink":"http://www.allmenus.com/al/cullman/179541-chick-fil-a/menu/",
    "sg:phone":"+1 256 735 1650",
    "sg:postcode":"35055",
    "sg:province":"AL",
    "sg:tags":[
        "wrap",
        "soup",
        "american",
        "sandwich",
        "salad"
    ],
    "wof:name":"Chick-fil-A",
    "wof:placetype":"venue"
},
  "geometry": {"coordinates":[-86.841121,34.15347],"type":"Point"}
}