{
  "type": "Feature",
  "properties": {
    "iso:country":"US",
    "sg:address":"3314 26th St N",
    "sg:city":"Birmingham",
    "sg:classifiers":[
        {
            "category":"Organizations",
            "subcategory":"Religious Organization",
            "type":"Services"
        }
    ],
    "sg:phone":"+1 205 252 0078",
    "sg:postcode":"35207",
    "sg:province":"AL",
    "wof:name":"Olivet Mnumental Baptst Church",
    "wof:placetype":"venue"
},
  "geometry": {"coordinates":[-86.81947099999999,33.555045],"type":"Point"}
}