{
  "type": "Feature",
  "properties": {
    "addr:full":"1110 Buck Island Dr Guntersville AL 35976",
    "addr:housenumber":"1110",
    "addr:postcode":"35976",
    "addr:street":"Buck Island Dr",
    "iso:country":"US",
    "sg:address":"1110 Buck Island Dr",
    "sg:city":"Guntersville",
    "sg:classifiers":[
        {
            "category":"Restaurant",
            "type":"Food & Drink"
        }
    ],
    "sg:phone":"+1 256 505 0025",
    "sg:postcode":"35976",
    "sg:province":"AL",
    "sg:tags":[
        "eating"
    ],
    "wof:name":"McDonalds",
    "wof:placetype":"venue"
},
  "geometry": {"coordinates":[-86.25121,34.388063],"type":"Point"}
}