{
  "type": "Feature",
  "properties": {
    "iso:country":"US",
    "sg:address":"136 Plaza Blvd",
    "sg:city":"Madison",
    "sg:classifiers":[
        {
            "category":"Health Services",
            "subcategory":"Dentist",
            "type":"Services"
        }
    ],
    "sg:phone":"+1 256 464 3556",
    "sg:postcode":"35758",
    "sg:province":"AL",
    "wof:name":"Rousseau, C Morgan",
    "wof:placetype":"venue"
},
  "geometry": {"coordinates":[-86.745001,34.710281],"type":"Point"}
}