{
  "type": "Feature",
  "properties": {
    "iso:country":"US",
    "sg:address":"1410 Drake Ave SE",
    "sg:city":"Huntsville",
    "sg:classifiers":[
        {
            "category":"Organizations",
            "subcategory":"Religious Organization",
            "type":"Services"
        }
    ],
    "sg:phone":"+1 256 883 0690",
    "sg:postcode":"35802",
    "sg:province":"AL",
    "wof:name":"Valley United Methodist Church",
    "wof:placetype":"venue"
},
  "geometry": {"coordinates":[-86.548754,34.704883],"type":"Point"}
}