{
  "type": "Feature",
  "properties": {
    "iso:country":"US",
    "sg:address":"405 S Hull St",
    "sg:city":"Montgomery",
    "sg:classifiers":[
        {
            "category":"Professional",
            "subcategory":"Lawyer & Legal Services",
            "type":"Services"
        }
    ],
    "sg:phone":"+1 334 265 1500",
    "sg:postcode":"36104",
    "sg:province":"AL",
    "sg:tags":[
        "attorney"
    ],
    "wof:name":"Wilkerson & Bryan",
    "wof:placetype":"venue"
},
  "geometry": {"coordinates":[-86.30351,32.371916],"type":"Point"}
}