{
  "type": "Feature",
  "properties": {
    "iso:country":"US",
    "sg:address":"20 Center St",
    "sg:city":"Bessemer",
    "sg:classifiers":[
        {
            "category":"Organizations",
            "subcategory":"Religious Organization",
            "type":"Services"
        }
    ],
    "sg:phone":"+1 205 424 8156",
    "sg:postcode":"35020",
    "sg:province":"AL",
    "wof:name":"St Matthews Church of God",
    "wof:placetype":"venue"
},
  "geometry": {"coordinates":[-86.963618,33.380876],"type":"Point"}
}