{
  "type": "Feature",
  "properties": {
    "addr:full":"2030 Chestnut St Montgomery AL 36106",
    "addr:housenumber":"2030",
    "addr:postcode":"36106",
    "addr:street":"Chestnut St",
    "iso:country":"US",
    "sg:address":"2030 Chestnut St",
    "sg:city":"Montgomery",
    "sg:classifiers":[
        {
            "category":"Wholesale",
            "subcategory":"Medical Equipment & Supplies",
            "type":"Manufacturing & Wholesale Goods"
        }
    ],
    "sg:phone":"+1 334 240 0055",
    "sg:postcode":"36106",
    "sg:province":"AL",
    "wof:name":"Logimedix",
    "wof:placetype":"venue"
},
  "geometry": {"coordinates":[-86.282078,32.366922],"type":"Point"}
}