{
  "type": "Feature",
  "properties": {
    "iso:country":"US",
    "sg:address":"1034 23rd St S",
    "sg:city":"Birmingham",
    "sg:classifiers":[
        {
            "category":"Social Services",
            "type":"Services"
        }
    ],
    "sg:phone":"+1 205 807 1850",
    "sg:postcode":"35205",
    "sg:province":"AL",
    "sg:tags":[
        "counselor",
        "marriage",
        "family"
    ],
    "wof:name":"Anita Neuer",
    "wof:placetype":"venue"
},
  "geometry": {"coordinates":[-86.791571,33.503641],"type":"Point"}
}