{
  "type": "Feature",
  "properties": {
    "iso:country":"US",
    "sg:address":"131 Michael Loop",
    "sg:city":"Daphne",
    "sg:classifiers":[
        {
            "category":"Travel",
            "subcategory":"Hotels & Motels",
            "type":"Entertainment"
        }
    ],
    "sg:phone":"+1 251 626 7055",
    "sg:postcode":"36526",
    "sg:province":"AL",
    "sg:tags":[
        "operation"
    ],
    "wof:name":"Ramada Inn",
    "wof:placetype":"venue"
},
  "geometry": {"coordinates":[-87.902475,30.63825],"type":"Point"}
}