{
  "type": "Feature",
  "properties": {
    "iso:country":"US",
    "sg:address":"71 Gladden Ln E",
    "sg:city":"Alexandria",
    "sg:classifiers":[
        {
            "category":"Health Services",
            "subcategory":"Hospital",
            "type":"Services"
        }
    ],
    "sg:phone":"+1 256 435 2262",
    "sg:postcode":"36250",
    "sg:province":"AL",
    "sg:tags":[
        "general"
    ],
    "wof:name":"QHG",
    "wof:placetype":"venue"
},
  "geometry": {"coordinates":[-85.892254,33.768057],"type":"Point"}
}