{
  "type": "Feature",
  "properties": {
    "iso:country":"US",
    "sg:address":"87656 US Hwy 278",
    "sg:city":"Snead",
    "sg:classifiers":[
        {
            "category":"Government",
            "subcategory":"Office",
            "type":"Public Place"
        }
    ],
    "sg:phone":"+1 205 466 7930",
    "sg:postcode":"35952",
    "sg:province":"AL",
    "sg:tags":[
        "city"
    ],
    "wof:name":"Town Hall",
    "wof:placetype":"venue"
},
  "geometry": {"coordinates":[-86.387862,34.114741],"type":"Point"}
}