{
  "type": "Feature",
  "properties": {
    "iso:country":"US",
    "sg:address":"2135 Co Rd 115",
    "sg:city":"Cedar Bluff",
    "sg:classifiers":[
        {
            "category":"Building & Trades",
            "subcategory":"Construction",
            "type":"Services"
        }
    ],
    "sg:phone":"+1 256 422 3503",
    "sg:postcode":"35959",
    "sg:province":"AL",
    "sg:tags":[
        "excavation",
        "house",
        "contractor",
        "general"
    ],
    "wof:name":"Mc Elroy Construction Inc",
    "wof:placetype":"venue"
},
  "geometry": {"coordinates":[-85.504778,34.229026],"type":"Point"}
}