{
  "type": "Feature",
  "properties": {
    "iso:country":"US",
    "sg:address":"9709 Parkway E",
    "sg:city":"Birmingham",
    "sg:classifiers":[
        {
            "category":"Health Services",
            "subcategory":"Doctor",
            "type":"Services"
        }
    ],
    "sg:phone":"+1 205 836 1199",
    "sg:postcode":"35215",
    "sg:province":"AL",
    "sg:tags":[
        "practice",
        "family"
    ],
    "wof:name":"Shaffer Calvin R MD",
    "wof:placetype":"venue"
},
  "geometry": {"coordinates":[-86.692001,33.600399],"type":"Point"}
}