{
  "type": "Feature",
  "properties": {
    "addr:full":"6001 Pulaski Pike NW Huntsville AL 35810",
    "addr:housenumber":"6001",
    "addr:postcode":"35810",
    "addr:street":"Pulaski Pike Nw",
    "iso:country":"US",
    "sg:address":"6001 Pulaski Pike NW",
    "sg:city":"Huntsville",
    "sg:classifiers":[
        {
            "category":"Organizations",
            "subcategory":"Community Association",
            "type":"Services"
        }
    ],
    "sg:phone":"+1 256 859 4470",
    "sg:postcode":"35810",
    "sg:province":"AL",
    "sg:tags":[
        "fraternal"
    ],
    "wof:name":"Cahaba Temple",
    "wof:placetype":"venue"
},
  "geometry": {"coordinates":[-86.616153,34.793571],"type":"Point"}
}