{
  "type": "Feature",
  "properties": {
    "iso:country":"US",
    "sg:address":"221 Cove Creek Rd",
    "sg:city":"Gadsden",
    "sg:classifiers":[
        {
            "category":"Wholesale",
            "subcategory":"Non-durable Goods",
            "type":"Manufacturing & Wholesale Goods"
        }
    ],
    "sg:phone":"+1 256 492 7763",
    "sg:postcode":"35903",
    "sg:province":"AL",
    "wof:name":"Party Central",
    "wof:placetype":"venue"
},
  "geometry": {"coordinates":[-85.933559,34.00653],"type":"Point"}
}