{
  "type": "Feature",
  "properties": {
    "iso:country":"US",
    "sg:address":"1701 Tolbert Cir",
    "sg:city":"Tuskegee",
    "sg:classifiers":[
        {
            "category":"Organizations",
            "subcategory":"Religious Organization",
            "type":"Services"
        }
    ],
    "sg:phone":"+1 334 727 9069",
    "sg:postcode":"36083",
    "sg:province":"AL",
    "sg:tags":[
        "church"
    ],
    "wof:name":"Tuskegee A O H Church of God",
    "wof:placetype":"venue"
},
  "geometry": {"coordinates":[-85.697084,32.442739],"type":"Point"}
}