{
  "type": "Feature",
  "properties": {
    "addr:full":"201 Pin Oak Dr Madison AL 35758",
    "addr:housenumber":"201",
    "addr:postcode":"35758",
    "addr:street":"Pin Oak Dr",
    "iso:country":"US",
    "sg:address":"201 Pin Oak Dr",
    "sg:city":"Madison",
    "sg:classifiers":[
        {
            "category":"Building & Trades",
            "subcategory":"Construction",
            "type":"Services"
        }
    ],
    "sg:phone":"+1 256 617 0327",
    "sg:postcode":"35758",
    "sg:province":"AL",
    "sg:tags":[
        "resurfacing",
        "laying",
        "refinishing",
        "floor"
    ],
    "wof:name":"Hardwood Floors By Sanders",
    "wof:placetype":"venue"
},
  "geometry": {"coordinates":[-86.74632,34.731706],"type":"Point"}
}