{
  "type": "Feature",
  "properties": {
    "iso:country":"US",
    "sg:address":"1421 Hillyer Robinson Pkwy",
    "sg:city":"Anniston",
    "sg:classifiers":[
        {
            "category":"Home & Garden",
            "subcategory":"Garden Supply",
            "type":"Retail Goods"
        }
    ],
    "sg:phone":"+1 256 835 0854",
    "sg:postcode":"36207",
    "sg:province":"AL",
    "sg:tags":[
        "nurseryman"
    ],
    "wof:name":"Sedmak Nursery & Landscape",
    "wof:placetype":"venue"
},
  "geometry": {"coordinates":[-85.808982,33.629482],"type":"Point"}
}