{
  "type": "Feature",
  "properties": {
    "addr:full":"3269 Monte Doro Dr Birmingham AL 35216",
    "addr:housenumber":"3269",
    "addr:postcode":"35216",
    "addr:street":"Monte Doro Dr",
    "iso:country":"US",
    "sg:address":"3269 Monte Doro Dr",
    "sg:city":"Birmingham",
    "sg:classifiers":[
        {
            "category":"Wholesale",
            "subcategory":"Vending Machines",
            "type":"Manufacturing & Wholesale Goods"
        }
    ],
    "sg:phone":"+1 205 822 9333",
    "sg:postcode":"35216",
    "sg:province":"AL",
    "sg:tags":[
        "retail"
    ],
    "wof:name":"W & W Services",
    "wof:placetype":"venue"
},
  "geometry": {"coordinates":[-86.80057499999999,33.40435],"type":"Point"}
}