{
  "type": "Feature",
  "properties": {
    "addr:full":"658 Bert Stinson Rd Falkville AL 35622",
    "addr:housenumber":"658",
    "addr:postcode":"35622",
    "addr:street":"Bert Stinson Rd",
    "iso:country":"US",
    "sg:address":"658 Bert Stinson Rd",
    "sg:city":"Falkville",
    "sg:classifiers":[
        {
            "category":"Shopping",
            "subcategory":"Discount & Variety Stores",
            "type":"Retail Goods"
        }
    ],
    "sg:phone":"+1 256 482 2504",
    "sg:postcode":"35622",
    "sg:province":"AL",
    "wof:name":"Michaels Variety Mall",
    "wof:placetype":"venue"
},
  "geometry": {"coordinates":[-86.823545,34.395371],"type":"Point"}
}