{
  "type": "Feature",
  "properties": {
    "addr:full":"1026 Goodyear Ave Gadsden AL 35903",
    "addr:housenumber":"1026",
    "addr:postcode":"35903",
    "addr:street":"Goodyear Ave",
    "iso:country":"US",
    "sg:address":"1026 Goodyear Ave",
    "sg:city":"Gadsden",
    "sg:classifiers":[
        {
            "category":"Health Services",
            "subcategory":"Doctor",
            "type":"Services"
        }
    ],
    "sg:phone":"+1 256 492 9924",
    "sg:postcode":"35903",
    "sg:province":"AL",
    "sg:tags":[
        "physician",
        "surgeon"
    ],
    "wof:name":"Southern Cardiovascular Assoc",
    "wof:placetype":"venue"
},
  "geometry": {"coordinates":[-85.97156699999999,34.009518],"type":"Point"}
}