{
  "type": "Feature",
  "properties": {
    "addr:full":"1600 17th St N Birmingham AL 35204",
    "addr:housenumber":"1600",
    "addr:postcode":"35204",
    "addr:street":"17Th St N",
    "iso:country":"US",
    "sg:address":"1600 17th St N",
    "sg:city":"Birmingham",
    "sg:classifiers":[
        {
            "category":"Freight",
            "type":"Transportation"
        }
    ],
    "sg:phone":"+1 205 328 0205",
    "sg:postcode":"35204",
    "sg:province":"AL",
    "sg:tags":[
        "operator",
        "local",
        "trucking"
    ],
    "wof:name":"Ground Zero Deliveries",
    "wof:placetype":"venue"
},
  "geometry": {"coordinates":[-86.822333,33.531492],"type":"Point"}
}