{
  "type": "Feature",
  "properties": {
    "iso:country":"US",
    "sg:address":"6337 Yellowhammer Dr",
    "sg:city":"Pinson",
    "sg:classifiers":[
        {
            "category":"Personal",
            "type":"Services"
        }
    ],
    "sg:phone":"+1 205 680 4858",
    "sg:postcode":"35126",
    "sg:province":"AL",
    "wof:name":"Nutritional Medicine Inc",
    "wof:placetype":"venue"
},
  "geometry": {"coordinates":[-86.626192,33.689047],"type":"Point"}
}