{
  "type": "Feature",
  "properties": {
    "iso:country":"US",
    "sg:address":"3363 Holland Rd",
    "sg:city":"Newton",
    "sg:classifiers":[
        {
            "category":"Organizations",
            "subcategory":"Religious Organization",
            "type":"Services"
        }
    ],
    "sg:phone":"+1 334 692 3475",
    "sg:postcode":"36352",
    "sg:province":"AL",
    "wof:name":"Pilgrim Home Baptist Pastorium",
    "wof:placetype":"venue"
},
  "geometry": {"coordinates":[-85.61669999999999,31.243083],"type":"Point"}
}