{
  "type": "Feature",
  "properties": {
    "iso:country":"US",
    "sg:address":"105 S Marion St",
    "sg:city":"Athens",
    "sg:classifiers":[
        {
            "category":"Professional",
            "subcategory":"Business Services",
            "type":"Services"
        }
    ],
    "sg:phone":"+1 256 230 9144",
    "sg:postcode":"35611",
    "sg:province":"AL",
    "sg:tags":[
        "chemical"
    ],
    "wof:name":"Elk River Technologies Inc",
    "wof:placetype":"venue"
},
  "geometry": {"coordinates":[-86.970981,34.80326],"type":"Point"}
}