{
  "type": "Feature",
  "properties": {
    "addr:full":"3 Ragan Dr Dothan AL 36303",
    "addr:housenumber":"3",
    "addr:postcode":"36303",
    "addr:street":"Ragan Dr",
    "iso:country":"US",
    "sg:address":"3 Ragan Dr",
    "sg:city":"Dothan",
    "sg:classifiers":[
        {
            "category":"Real Estate",
            "subcategory":"Real Estate Agent",
            "type":"Services"
        }
    ],
    "sg:phone":"+1 334 792 6307",
    "sg:postcode":"36303",
    "sg:province":"AL",
    "sg:tags":[
        "consulting",
        "business"
    ],
    "wof:name":"Gene Ragan",
    "wof:placetype":"venue"
},
  "geometry": {"coordinates":[-85.318951,31.22259],"type":"Point"}
}