{
  "type": "Feature",
  "properties": {
    "iso:country":"US",
    "sg:address":"2576 US Hwy 231",
    "sg:city":"Wetumpka",
    "sg:classifiers":[
        {
            "category":"Professional",
            "type":"Services"
        }
    ],
    "sg:phone":"+1 334 514 2274",
    "sg:postcode":"36093",
    "sg:province":"AL",
    "wof:name":"Quick Cash of America LLC",
    "wof:placetype":"venue"
},
  "geometry": {"coordinates":[-86.203818,32.483826],"type":"Point"}
}