{
  "type": "Feature",
  "properties": {
    "addr:full":"107 N Rawls St Enterprise AL 36330",
    "addr:housenumber":"107",
    "addr:postcode":"36330",
    "addr:street":"N Rawls St",
    "iso:country":"US",
    "sg:address":"107 N Rawls St",
    "sg:city":"Enterprise",
    "sg:classifiers":[
        {
            "category":"Restaurant",
            "type":"Food & Drink"
        }
    ],
    "sg:phone":"+1 334 393 4798",
    "sg:postcode":"36330",
    "sg:province":"AL",
    "sg:tags":[
        "caterer"
    ],
    "wof:name":"Charleston House",
    "wof:placetype":"venue"
},
  "geometry": {"coordinates":[-85.857158,31.313769],"type":"Point"}
}