{
  "type": "Feature",
  "properties": {
    "addr:full":"703 Joryne Dr Montgomery AL 36109",
    "addr:housenumber":"703",
    "addr:postcode":"36109",
    "addr:street":"Joryne Dr",
    "iso:country":"US",
    "sg:address":"703 Joryne Dr",
    "sg:city":"Montgomery",
    "sg:classifiers":[
        {
            "category":"Building & Trades",
            "subcategory":"Construction",
            "type":"Services"
        }
    ],
    "sg:phone":"+1 334 277 2811",
    "sg:postcode":"36109",
    "sg:province":"AL",
    "sg:tags":[
        "floor",
        "laying",
        "contractor"
    ],
    "wof:name":"Jefferson Ralph Floor Covering",
    "wof:placetype":"venue"
},
  "geometry": {"coordinates":[-86.249916,32.371137],"type":"Point"}
}