{
  "type": "Feature",
  "properties": {
    "addr:full":"108 Morphy Ave Fairhope AL 36532",
    "addr:housenumber":"108",
    "addr:postcode":"36532",
    "addr:street":"Morphy Ave",
    "iso:country":"US",
    "sg:address":"108 Morphy Ave",
    "sg:city":"Fairhope",
    "sg:classifiers":[
        {
            "category":"Professional",
            "subcategory":"Management & Consulting",
            "type":"Services"
        }
    ],
    "sg:phone":"+1 251 928 6321",
    "sg:postcode":"36532",
    "sg:province":"AL",
    "sg:tags":[
        "financial"
    ],
    "wof:name":"Equisource",
    "wof:placetype":"venue"
},
  "geometry": {"coordinates":[-87.90857200000001,30.520271],"type":"Point"}
}