{
  "type": "Feature",
  "properties": {
    "iso:country":"US",
    "sg:address":"9433 US Hwy 431",
    "sg:city":"Owens Cross Roads",
    "sg:classifiers":[
        {
            "category":"Cinema",
            "subcategory":"Movie Rental",
            "type":"Entertainment"
        }
    ],
    "sg:phone":"+1 256 725 8266",
    "sg:postcode":"35763",
    "sg:province":"AL",
    "sg:tags":[
        "personal",
        "video",
        "tape"
    ],
    "wof:name":"Lilah CS Video",
    "wof:placetype":"venue"
},
  "geometry": {"coordinates":[-86.447468,34.568256],"type":"Point"}
}