{
  "type": "Feature",
  "properties": {
    "addr:full":"2100 Brandon St SW Huntsville AL 35801",
    "addr:housenumber":"2100",
    "addr:postcode":"35801",
    "addr:street":"Brandon St Sw",
    "iso:country":"US",
    "sg:address":"2100 Brandon St SW",
    "sg:city":"Huntsville",
    "sg:classifiers":[
        {
            "category":"Shopping",
            "subcategory":"Pharmacy",
            "type":"Retail Goods"
        }
    ],
    "sg:phone":"+1 256 512 0951",
    "sg:postcode":"35801",
    "sg:province":"AL",
    "sg:tags":[
        "photofinishing",
        "laboratory"
    ],
    "wof:name":"Walgreens",
    "wof:placetype":"venue"
},
  "geometry": {"coordinates":[-86.5787,34.717798],"type":"Point"}
}