{
  "type": "Feature",
  "properties": {
    "iso:country":"US",
    "sg:address":"1009 17th Way SW",
    "sg:city":"Birmingham",
    "sg:classifiers":[
        {
            "category":"Building & Trades",
            "subcategory":"Construction",
            "type":"Services"
        }
    ],
    "sg:phone":"+1 205 925 5845",
    "sg:postcode":"35211",
    "sg:province":"AL",
    "sg:tags":[
        "concrete",
        "contractor"
    ],
    "wof:name":"King Concrete Finishing Inc",
    "wof:placetype":"venue"
},
  "geometry": {"coordinates":[-86.863943,33.481512],"type":"Point"}
}