{
  "type": "Feature",
  "properties": {
    "iso:country":"US",
    "sg:address":"115 E 18th St",
    "sg:city":"Anniston",
    "sg:classifiers":[
        {
            "category":"Shopping",
            "subcategory":"Jewelry",
            "type":"Retail Goods"
        }
    ],
    "sg:phone":"+1 256 236 2480",
    "sg:postcode":"36201",
    "sg:province":"AL",
    "sg:tags":[
        "jeweler"
    ],
    "wof:name":"Lam Yung Jewelers",
    "wof:placetype":"venue"
},
  "geometry": {"coordinates":[-85.826976,33.667765],"type":"Point"}
}