{
  "type": "Feature",
  "properties": {
    "iso:country":"US",
    "sg:address":"368 Five Acre Rd",
    "sg:city":"Bessemer",
    "sg:classifiers":[
        {
            "category":"Communications",
            "type":"Services"
        }
    ],
    "sg:phone":"+1 205 744 5827",
    "sg:postcode":"35023",
    "sg:province":"AL",
    "sg:tags":[
        "communication"
    ],
    "wof:name":"One Stop Communications Inc",
    "wof:placetype":"venue"
},
  "geometry": {"coordinates":[-86.972881,33.468238],"type":"Point"}
}