{
  "type": "Feature",
  "properties": {
    "iso:country":"US",
    "sg:address":"402 Whippoorwill Rd",
    "sg:city":"Luverne",
    "sg:classifiers":[
        {
            "category":"Manufacturing",
            "subcategory":"Lumber",
            "type":"Manufacturing & Wholesale Goods"
        }
    ],
    "sg:phone":"+1 334 335 5392",
    "sg:postcode":"36049",
    "sg:province":"AL",
    "sg:tags":[
        "mill"
    ],
    "wof:name":"H & L Sawmill",
    "wof:placetype":"venue"
},
  "geometry": {"coordinates":[-86.173761,31.787423],"type":"Point"}
}