{
  "type": "Feature",
  "properties": {
    "addr:full":"34 Taylor Rd N Montgomery AL 36117",
    "addr:housenumber":"34",
    "addr:postcode":"36117",
    "addr:street":"Taylor Rd N",
    "iso:country":"US",
    "sg:address":"34 Taylor Rd N",
    "sg:city":"Montgomery",
    "sg:classifiers":[
        {
            "category":"Health Services",
            "subcategory":"Doctor",
            "type":"Services"
        }
    ],
    "sg:phone":"+1 334 272 7639",
    "sg:postcode":"36117",
    "sg:province":"AL",
    "sg:tags":[
        "medical"
    ],
    "wof:name":"Pri Med",
    "wof:placetype":"venue"
},
  "geometry": {"coordinates":[-86.17331,32.383467],"type":"Point"}
}