{
  "type": "Feature",
  "properties": {
    "addr:full":"2796 Eastern Blvd Montgomery AL 36117",
    "addr:housenumber":"2796",
    "addr:postcode":"36117",
    "addr:street":"Eastern Blvd",
    "iso:country":"US",
    "sg:address":"2796 Eastern Blvd",
    "sg:city":"Montgomery",
    "sg:classifiers":[
        {
            "category":"Restaurant",
            "type":"Food & Drink"
        }
    ],
    "sg:phone":"+1 334 270 3352",
    "sg:postcode":"36117",
    "sg:province":"AL",
    "wof:name":"Arby's",
    "wof:placetype":"venue"
},
  "geometry": {"coordinates":[-86.223586,32.345182],"type":"Point"}
}