{
  "type": "Feature",
  "properties": {
    "addr:full":"4322 Marquette Dr Mobile AL 36608",
    "addr:housenumber":"4322",
    "addr:postcode":"36608",
    "addr:street":"Marquette Dr",
    "iso:country":"US",
    "sg:address":"4322 Marquette Dr",
    "sg:city":"Mobile",
    "sg:classifiers":[
        {
            "category":"Professional",
            "type":"Services"
        }
    ],
    "sg:phone":"+1 251 344 2008",
    "sg:postcode":"36608",
    "sg:province":"AL",
    "wof:name":"Jon Botts AMA",
    "wof:placetype":"venue"
},
  "geometry": {"coordinates":[-88.14109999999999,30.686294],"type":"Point"}
}