{
  "type": "Feature",
  "properties": {
    "addr:full":"5304 Overlook Rd Mobile AL 36618",
    "addr:housenumber":"5304",
    "addr:postcode":"36618",
    "addr:street":"Overlook Rd",
    "iso:country":"US",
    "sg:address":"5304 Overlook Rd",
    "sg:city":"Mobile",
    "sg:classifiers":[
        {
            "category":"Social Services",
            "type":"Services"
        }
    ],
    "sg:phone":"+1 251 460 0301",
    "sg:postcode":"36618",
    "sg:province":"AL",
    "sg:tags":[
        "agency"
    ],
    "wof:name":"Indenpendent Living Center",
    "wof:placetype":"venue"
},
  "geometry": {"coordinates":[-88.16386,30.71963],"type":"Point"}
}