{
  "type": "Feature",
  "properties": {
    "addr:full":"214 Cahaba Valley Rd Pelham AL 35124",
    "addr:housenumber":"214",
    "addr:postcode":"35124",
    "addr:street":"Cahaba Valley Rd",
    "iso:country":"US",
    "sg:address":"214 Cahaba Valley Rd",
    "sg:city":"Pelham",
    "sg:classifiers":[
        {
            "category":"Personal",
            "subcategory":"Beauty Salon",
            "type":"Services"
        }
    ],
    "sg:phone":"+1 205 444 0095",
    "sg:postcode":"35124",
    "sg:province":"AL",
    "sg:tags":[
        "shop"
    ],
    "wof:name":"Kemp Hair Studio",
    "wof:placetype":"venue"
},
  "geometry": {"coordinates":[-86.78949299999999,33.332476],"type":"Point"}
}