{
  "type": "Feature",
  "properties": {
    "iso:country":"US",
    "sg:address":"94 Iron Man Rd",
    "sg:city":"Hartselle",
    "sg:classifiers":[
        {
            "category":"Manufacturing",
            "subcategory":"Toys & Sporting Goods",
            "type":"Manufacturing & Wholesale Goods"
        }
    ],
    "sg:phone":"+1 256 773 2467",
    "sg:postcode":"35640",
    "sg:province":"AL",
    "sg:tags":[
        "athletic"
    ],
    "sg:website":"www.byronferguson.com",
    "wof:name":"Byron Ferguson Productions",
    "wof:placetype":"venue"
},
  "geometry": {"coordinates":[-87.006219,34.444578],"type":"Point"}
}