{
  "type": "Feature",
  "properties": {
    "iso:country":"US",
    "sg:address":"353 Jamestown Manor Dr",
    "sg:city":"Gardendale",
    "sg:classifiers":[
        {
            "category":"Food & Beverages",
            "subcategory":"Groceries & Convenience Stores",
            "type":"Retail Goods"
        }
    ],
    "sg:phone":"+1 205 631 8414",
    "sg:postcode":"35071",
    "sg:province":"AL",
    "wof:name":"Chek Fax Inc",
    "wof:placetype":"venue"
},
  "geometry": {"coordinates":[-86.807513,33.634811],"type":"Point"}
}