{
  "type": "Feature",
  "properties": {
    "iso:country":"US",
    "sg:address":"109 Vixen Ct",
    "sg:city":"Dothan",
    "sg:classifiers":[
        {
            "category":"Restaurant",
            "type":"Food & Drink"
        }
    ],
    "sg:phone":"+1 334 712 1355",
    "sg:postcode":"36305",
    "sg:province":"AL",
    "sg:tags":[
        "eating"
    ],
    "wof:name":"Pig Out Inc",
    "wof:placetype":"venue"
},
  "geometry": {"coordinates":[-85.458709,31.219443],"type":"Point"}
}