{
  "type": "Feature",
  "properties": {
    "iso:country":"US",
    "sg:address":"150 Greene St",
    "sg:city":"Alexander City",
    "sg:classifiers":[
        {
            "category":"Autos & Motor Vehicles",
            "subcategory":"Auto Supplies",
            "type":"Retail Goods"
        }
    ],
    "sg:phone":"+1 256 234 5023",
    "sg:postcode":"35010",
    "sg:province":"AL",
    "sg:tags":[
        "automobile",
        "parts"
    ],
    "wof:name":"Thomas Auto Parts Inc",
    "wof:placetype":"venue"
},
  "geometry": {"coordinates":[-85.953239,32.94527],"type":"Point"}
}