{
  "type": "Feature",
  "properties": {
    "iso:country":"US",
    "sg:address":"5875 Mockingbird Ln",
    "sg:city":"Pinson",
    "sg:classifiers":[
        {
            "category":"Building & Trades",
            "subcategory":"Electrical",
            "type":"Services"
        }
    ],
    "sg:phone":"+1 205 213 8221",
    "sg:postcode":"35126",
    "sg:province":"AL",
    "sg:tags":[
        "electrical",
        "contractor"
    ],
    "wof:name":"Reymann Elec Contract Door",
    "wof:placetype":"venue"
},
  "geometry": {"coordinates":[-86.630971,33.687557],"type":"Point"}
}