{
  "type": "Feature",
  "properties": {
    "iso:country":"US",
    "sg:address":"275 J Dr",
    "sg:city":"Vernon",
    "sg:classifiers":[
        {
            "category":"Building & Trades",
            "subcategory":"Construction",
            "type":"Services"
        }
    ],
    "sg:phone":"+1 205 695 7904",
    "sg:postcode":"35592",
    "sg:province":"AL",
    "sg:tags":[
        "house",
        "industrial",
        "co"
    ],
    "wof:name":"Larry Moore",
    "wof:placetype":"venue"
},
  "geometry": {"coordinates":[-88.154528,33.746998],"type":"Point"}
}