{
  "type": "Feature",
  "properties": {
    "iso:country":"US",
    "sg:address":"100 Rice Mine Rd NE",
    "sg:city":"Tuscaloosa",
    "sg:classifiers":[
        {
            "category":"Health Services",
            "subcategory":"Doctor",
            "type":"Services"
        }
    ],
    "sg:phone":"+1 205 248 9077",
    "sg:postcode":"35406",
    "sg:province":"AL",
    "sg:tags":[
        "dentist"
    ],
    "wof:name":"Capstone Dental Care",
    "wof:placetype":"venue"
},
  "geometry": {"coordinates":[-87.53255900000001,33.228446],"type":"Point"}
}