{
  "type": "Feature",
  "properties": {
    "iso:country":"US",
    "sg:address":"4210 Oakwood Ave NW",
    "sg:city":"Huntsville",
    "sg:classifiers":[
        {
            "category":"Bars & Pubs",
            "type":"Food & Drink"
        }
    ],
    "sg:phone":"+1 256 489 0625",
    "sg:postcode":"35810",
    "sg:province":"AL",
    "wof:name":"Apex Bar & Lounge",
    "wof:placetype":"venue"
},
  "geometry": {"coordinates":[-86.63121099999999,34.749608],"type":"Point"}
}