{
  "type": "Feature",
  "properties": {
    "iso:country":"US",
    "sg:address":"6130 Graham Rd",
    "sg:city":"Mount Olive",
    "sg:classifiers":[
        {
            "category":"Building & Trades",
            "subcategory":"Construction",
            "type":"Services"
        }
    ],
    "sg:phone":"+1 205 631 5277",
    "sg:postcode":"35117",
    "sg:province":"AL",
    "sg:tags":[
        "house"
    ],
    "wof:name":"Bjs Remodeling Custom",
    "wof:placetype":"venue"
},
  "geometry": {"coordinates":[-86.861203,33.6869],"type":"Point"}
}