{
  "type": "Feature",
  "properties": {
    "addr:full":"540 Lilac Dr Birmingham AL 35215",
    "addr:housenumber":"540",
    "addr:postcode":"35215",
    "addr:street":"Lilac Dr",
    "iso:country":"US",
    "sg:address":"540 Lilac Dr",
    "sg:city":"Birmingham",
    "sg:classifiers":[
        {
            "category":"Retail",
            "subcategory":"Animal Services",
            "type":"Services"
        }
    ],
    "sg:phone":"+1 205 836 8709",
    "sg:postcode":"35215",
    "sg:province":"AL",
    "sg:tags":[
        "breeder",
        "rottweiler"
    ],
    "wof:name":"Apache Hill Rottweilers",
    "wof:placetype":"venue"
},
  "geometry": {"coordinates":[-86.692753,33.607148],"type":"Point"}
}