{
  "type": "Feature",
  "properties": {
    "iso:country":"US",
    "sg:address":"4559 Co Rd 75",
    "sg:city":"Pansey",
    "sg:classifiers":[
        {
            "category":"Autos & Motor Vehicles",
            "subcategory":"Fuel & Gas Station",
            "type":"Retail Goods"
        }
    ],
    "sg:phone":"+1 334 522 4334",
    "sg:postcode":"36370",
    "sg:province":"AL",
    "sg:tags":[
        "oil"
    ],
    "wof:name":"Brunson's Service Ctr",
    "wof:placetype":"venue"
},
  "geometry": {"coordinates":[-85.177678,31.089281],"type":"Point"}
}