{
  "type": "Feature",
  "properties": {
    "iso:country":"US",
    "sg:address":"810 Co Rd 265",
    "sg:city":"Centre",
    "sg:classifiers":[
        {
            "category":"Organizations",
            "subcategory":"Religious Organization",
            "type":"Services"
        }
    ],
    "sg:phone":"+1 256 927 5430",
    "sg:postcode":"35960",
    "sg:province":"AL",
    "sg:tags":[
        "clergy"
    ],
    "wof:name":"Fairview Methodist Church",
    "wof:placetype":"venue"
},
  "geometry": {"coordinates":[-85.724417,34.161871],"type":"Point"}
}