{
  "type": "Feature",
  "properties": {
    "iso:country":"US",
    "sg:address":"2105 Greensboro Ave",
    "sg:city":"Tuscaloosa",
    "sg:classifiers":[
        {
            "category":"Railroad",
            "type":"Transportation"
        }
    ],
    "sg:phone":"+1 205 758 5496",
    "sg:postcode":"35401",
    "sg:province":"AL",
    "sg:tags":[
        "operator",
        "line"
    ],
    "wof:name":"Norfolk Southern Corporation",
    "wof:placetype":"venue"
},
  "geometry": {"coordinates":[-87.559575,33.191595],"type":"Point"}
}