{
  "type": "Feature",
  "properties": {
    "addr:full":"136 Mill Creek Xing Madison AL 35758",
    "addr:housenumber":"136",
    "addr:postcode":"35758",
    "addr:street":"Mill Creek Xing",
    "iso:country":"US",
    "sg:address":"136 Mill Creek Xing",
    "sg:city":"Madison",
    "sg:classifiers":[
        {
            "category":"Professional",
            "subcategory":"Business Services",
            "type":"Services"
        }
    ],
    "sg:phone":"+1 256 772 0022",
    "sg:postcode":"35758",
    "sg:province":"AL",
    "sg:tags":[
        "cartography"
    ],
    "wof:name":"Cartagram LLC",
    "wof:placetype":"venue"
},
  "geometry": {"coordinates":[-86.75172999999999,34.717146],"type":"Point"}
}