{
  "type": "Feature",
  "properties": {
    "iso:country":"US",
    "sg:address":"700 University Blvd S",
    "sg:city":"Mobile",
    "sg:classifiers":[
        {
            "category":"Social Services",
            "type":"Services"
        }
    ],
    "sg:phone":"+1 251 666 2745",
    "sg:postcode":"36609",
    "sg:province":"AL",
    "wof:name":"Red Cross",
    "wof:placetype":"venue"
},
  "geometry": {"coordinates":[-88.164005,30.662157],"type":"Point"}
}