{
  "type": "Feature",
  "properties": {
    "iso:country":"US",
    "sg:address":"615 Woodward Ave",
    "sg:city":"Muscle Shoals",
    "sg:classifiers":[
        {
            "category":"Shopping",
            "subcategory":"Used Merchandise",
            "type":"Retail Goods"
        }
    ],
    "sg:phone":"+1 256 386 7671",
    "sg:postcode":"35661",
    "sg:province":"AL",
    "sg:tags":[
        "shop",
        "thrift"
    ],
    "wof:name":"From Me To You Thrift Store",
    "wof:placetype":"venue"
},
  "geometry": {"coordinates":[-87.667523,34.754451],"type":"Point"}
}