{
  "type": "Feature",
  "properties": {
    "iso:country":"US",
    "sg:address":"3103 Knights Bridge Curve",
    "sg:city":"Montgomery",
    "sg:classifiers":[
        {
            "category":"Wholesale",
            "subcategory":"Apparel",
            "type":"Manufacturing & Wholesale Goods"
        }
    ],
    "sg:phone":"+1 334 269 1008",
    "sg:postcode":"36111",
    "sg:province":"AL",
    "sg:tags":[
        "piece"
    ],
    "wof:name":"Leatherwood Cramer",
    "wof:placetype":"venue"
},
  "geometry": {"coordinates":[-86.26108600000001,32.349297],"type":"Point"}
}