{
  "type": "Feature",
  "properties": {
    "addr:full":"717 Pratt Ave NE Huntsville AL 35801",
    "addr:housenumber":"717",
    "addr:postcode":"35801",
    "addr:street":"Pratt Ave Ne",
    "iso:country":"US",
    "sg:address":"717 Pratt Ave NE",
    "sg:city":"Huntsville",
    "sg:classifiers":[
        {
            "category":"Utilities",
            "subcategory":"Telephone",
            "type":"Services"
        }
    ],
    "sg:phone":"+1 256 534 2512",
    "sg:postcode":"35801",
    "sg:province":"AL",
    "sg:tags":[
        "communications"
    ],
    "wof:name":"Lucent Technologies Inc",
    "wof:placetype":"venue"
},
  "geometry": {"coordinates":[-86.57567,34.738835],"type":"Point"}
}