{
  "type": "Feature",
  "properties": {
    "iso:country":"US",
    "sg:address":"3641 Northcote Dr",
    "sg:city":"Birmingham",
    "sg:classifiers":[
        {
            "category":"Wholesale",
            "subcategory":"Auto Parts",
            "type":"Manufacturing & Wholesale Goods"
        }
    ],
    "sg:phone":"+1 205 967 9700",
    "sg:postcode":"35223",
    "sg:province":"AL",
    "wof:name":"Ranger Automotive Equipment Co",
    "wof:placetype":"venue"
},
  "geometry": {"coordinates":[-86.72956000000001,33.475114],"type":"Point"}
}