{
  "type": "Feature",
  "properties": {
    "iso:country":"US",
    "sg:address":"605 Hagood St",
    "sg:city":"Birmingham",
    "sg:classifiers":[
        {
            "category":"Organizations",
            "subcategory":"Religious Organization",
            "type":"Services"
        }
    ],
    "sg:phone":"+1 205 879 6001",
    "sg:postcode":"35213",
    "sg:province":"AL",
    "wof:name":"Crest Line Cumberland Prsbytrn",
    "wof:placetype":"venue"
},
  "geometry": {"coordinates":[-86.737053,33.515443],"type":"Point"}
}