{
  "type": "Feature",
  "properties": {
    "iso:country":"US",
    "sg:address":"223 Russet Woods Dr",
    "sg:city":"Birmingham",
    "sg:classifiers":[
        {
            "category":"Wholesale",
            "subcategory":"Non-durable Goods",
            "type":"Manufacturing & Wholesale Goods"
        }
    ],
    "sg:phone":"+1 205 424 5450",
    "sg:postcode":"35244",
    "sg:province":"AL",
    "wof:name":"Euler Distribution Corp",
    "wof:placetype":"venue"
},
  "geometry": {"coordinates":[-86.88709,33.330735],"type":"Point"}
}