{
  "type": "Feature",
  "properties": {
    "addr:full":"614 Draper St Piedmont AL 36272",
    "addr:housenumber":"614",
    "addr:postcode":"36272",
    "addr:street":"Draper St",
    "iso:country":"US",
    "sg:address":"614 Draper St",
    "sg:city":"Piedmont",
    "sg:classifiers":[
        {
            "category":"Organizations",
            "subcategory":"Religious Organization",
            "type":"Services"
        }
    ],
    "sg:phone":"+1 256 447 1990",
    "sg:postcode":"36272",
    "sg:province":"AL",
    "wof:name":"Saint Luke F B H",
    "wof:placetype":"venue"
},
  "geometry": {"coordinates":[-85.60871400000001,33.93069],"type":"Point"}
}