{
  "type": "Feature",
  "properties": {
    "iso:country":"US",
    "sg:address":"614 Draper St",
    "sg:city":"Piedmont",
    "sg:classifiers":[
        {
            "category":"Organizations",
            "subcategory":"Religious Organization",
            "type":"Services"
        }
    ],
    "sg:phone":"+1 256 447 1990",
    "sg:postcode":"36272",
    "sg:province":"AL",
    "wof:name":"Saint Luke F B H",
    "wof:placetype":"venue"
},
  "geometry": {"coordinates":[-85.608714,33.93069],"type":"Point"}
}