{
  "type": "Feature",
  "properties": {
    "addr:full":"303 Raymond Muscle Shoals AL 35661",
    "addr:housenumber":"303",
    "addr:postcode":"35661",
    "addr:street":"Raymond Muscle Shoals",
    "iso:country":"US",
    "sg:address":"303 Raymond",
    "sg:city":"Muscle Shoals",
    "sg:classifiers":[
        {
            "category":"Retail",
            "subcategory":"Auto Repair",
            "type":"Services"
        }
    ],
    "sg:phone":"+1 256 383 7533",
    "sg:postcode":"35661",
    "sg:province":"AL",
    "sg:tags":[
        "torque",
        "converter"
    ],
    "wof:name":"Shoals Torque Converters",
    "wof:placetype":"venue"
},
  "geometry": {"coordinates":[-87.62897700000001,34.762029],"type":"Point"}
}