{
  "type": "Feature",
  "properties": {
    "iso:country":"US",
    "sg:address":"300 E Tennessee St",
    "sg:city":"Florence",
    "sg:classifiers":[
        {
            "category":"Home & Garden",
            "subcategory":"Building Materials",
            "type":"Retail Goods"
        },
        {
            "category":"Manufacturing",
            "subcategory":"Metals",
            "type":"Manufacturing & Wholesale Goods"
        }
    ],
    "sg:phone":"+1 256 767 2568",
    "sg:postcode":"35630",
    "sg:province":"AL",
    "sg:tags":[
        "window",
        "door",
        "sales",
        "install",
        "mfg"
    ],
    "wof:name":"McDaniel  Window & Door Co",
    "wof:placetype":"venue"
},
  "geometry": {"coordinates":[-87.67197,34.80184],"type":"Point"}
}