{
  "type": "Feature",
  "properties": {
    "iso:country":"US",
    "sg:address":"2595 Co Rd 80",
    "sg:city":"Russellville",
    "sg:phone":"+1 256 332 1031",
    "sg:postcode":"35654",
    "sg:province":"AL",
    "sg:tags":[
        "farm",
        "soybean"
    ],
    "wof:name":"William Hovater",
    "wof:placetype":"venue"
},
  "geometry": {"coordinates":[-87.574704,34.52377],"type":"Point"}
}