{
  "type": "Feature",
  "properties": {
    "addr:full":"705 Holcombe Ave Mobile AL 36606",
    "addr:housenumber":"705",
    "addr:postcode":"36606",
    "addr:street":"Holcombe Ave",
    "iso:country":"US",
    "sg:address":"705 Holcombe Ave",
    "sg:city":"Mobile",
    "sg:classifiers":[
        {
            "category":"Restaurant",
            "type":"Food & Drink"
        }
    ],
    "sg:phone":"+1 251 473 3011",
    "sg:postcode":"36606",
    "sg:province":"AL",
    "wof:name":"Taste Of Chicago",
    "wof:placetype":"venue"
},
  "geometry": {"coordinates":[-88.090354,30.665694],"type":"Point"}
}