{
  "type": "Feature",
  "properties": {
    "iso:country":"US",
    "sg:address":"445 Co Rd 374",
    "sg:city":"Valley",
    "sg:classifiers":[
        {
            "category":"Professional",
            "type":"Services"
        }
    ],
    "sg:phone":"+1 334 742 2652",
    "sg:postcode":"36854",
    "sg:province":"AL",
    "wof:name":"Kristys Craft",
    "wof:placetype":"venue"
},
  "geometry": {"coordinates":[-85.184557,32.725989],"type":"Point"}
}