{
  "type": "Feature",
  "properties": {
    "addr:full":"2601 Artie St SW Huntsville AL 35805",
    "addr:housenumber":"2601",
    "addr:postcode":"35805",
    "addr:street":"Artie St Sw",
    "iso:country":"US",
    "sg:address":"2601 Artie St SW",
    "sg:city":"Huntsville",
    "sg:classifiers":[
        {
            "category":"Wholesale",
            "subcategory":"Painting Supplies",
            "type":"Manufacturing & Wholesale Goods"
        }
    ],
    "sg:phone":"+1 256 539 0081",
    "sg:postcode":"35805",
    "sg:province":"AL",
    "sg:tags":[
        "paint",
        "varnish",
        "lacquer"
    ],
    "wof:name":"Thompson Lacquer 02",
    "wof:placetype":"venue"
},
  "geometry": {"coordinates":[-86.59285199999999,34.708481],"type":"Point"}
}