{
  "type": "Feature",
  "properties": {
    "iso:country":"US",
    "sg:address":"7839 Red Hill Rd",
    "sg:city":"Tallassee",
    "sg:classifiers":[
        {
            "category":"Professional",
            "subcategory":"Management & Consulting",
            "type":"Services"
        }
    ],
    "sg:phone":"+1 334 541 5941",
    "sg:postcode":"36078",
    "sg:province":"AL",
    "wof:name":"Gym Brokers Inc",
    "wof:placetype":"venue"
},
  "geometry": {"coordinates":[-85.94807,32.618875],"type":"Point"}
}