{
  "type": "Feature",
  "properties": {
    "addr:full":"2209 9th St Tuscaloosa AL 35401",
    "addr:housenumber":"2209",
    "addr:postcode":"35401",
    "addr:street":"9Th St",
    "iso:country":"US",
    "sg:address":"2209 9th St",
    "sg:city":"Tuscaloosa",
    "sg:classifiers":[
        {
            "category":"Professional",
            "subcategory":"Lawyer & Legal Services",
            "type":"Services"
        }
    ],
    "sg:phone":"+1 205 366 0287",
    "sg:postcode":"35401",
    "sg:province":"AL",
    "sg:tags":[
        "attorney"
    ],
    "wof:name":"James O Standridge",
    "wof:placetype":"venue"
},
  "geometry": {"coordinates":[-87.565303,33.206384],"type":"Point"}
}