{
  "type": "Feature",
  "properties": {
    "addr:full":"3000 Spring Hill Ave Mobile AL 36607",
    "addr:housenumber":"3000",
    "addr:postcode":"36607",
    "addr:street":"Spring Hill Ave",
    "iso:country":"US",
    "sg:address":"3000 Spring Hill Ave",
    "sg:city":"Mobile",
    "sg:classifiers":[
        {
            "category":"Retail",
            "subcategory":"Self-service Laundry",
            "type":"Services"
        }
    ],
    "sg:phone":"+1 251 471 9425",
    "sg:postcode":"36607",
    "sg:province":"AL",
    "wof:name":"Washland Inc",
    "wof:placetype":"venue"
},
  "geometry": {"coordinates":[-88.11104899999999,30.699716],"type":"Point"}
}