{
  "type": "Feature",
  "properties": {
    "iso:country":"US",
    "sg:address":"126 Broadway Ave",
    "sg:city":"Sylacauga",
    "sg:classifiers":[
        {
            "category":"Banks & Credit Unions",
            "subcategory":"Bank",
            "type":"Services"
        }
    ],
    "sg:phone":"+1 256 245 2281",
    "sg:postcode":"35150",
    "sg:province":"AL",
    "sg:website":"www.thebankmybank.com",
    "wof:name":"Bank",
    "wof:placetype":"venue"
},
  "geometry": {"coordinates":[-86.250757,33.164487],"type":"Point"}
}