{
  "type": "Feature",
  "properties": {
    "addr:full":"426 Main St Roanoke AL 36274",
    "addr:housenumber":"426",
    "addr:postcode":"36274",
    "addr:street":"Main St",
    "iso:country":"US",
    "sg:address":"426 Main St",
    "sg:city":"Roanoke",
    "sg:classifiers":[
        {
            "category":"Personal",
            "subcategory":"Beauty Salon",
            "type":"Services"
        }
    ],
    "sg:phone":"+1 334 863 2788",
    "sg:postcode":"36274",
    "sg:province":"AL",
    "sg:tags":[
        "shop"
    ],
    "wof:name":"Tommie Sue's Styles",
    "wof:placetype":"venue"
},
  "geometry": {"coordinates":[-85.36614899999999,33.150664],"type":"Point"}
}