{
  "type": "Feature",
  "properties": {
    "addr:full":"173 Co Rd 31 Ashland AL 36251",
    "addr:housenumber":"173;31",
    "addr:postcode":"36251",
    "addr:street":"Co Rd",
    "iso:country":"US",
    "sg:address":"173 Co Rd 31",
    "sg:city":"Ashland",
    "sg:classifiers":[
        {
            "category":"Professional",
            "subcategory":"Lawyer & Legal Services",
            "type":"Services"
        }
    ],
    "sg:phone":"+1 256 354 3578",
    "sg:postcode":"36251",
    "sg:province":"AL",
    "sg:tags":[
        "attorney"
    ],
    "wof:name":"District Attorney Of Al",
    "wof:placetype":"venue"
},
  "geometry": {"coordinates":[-85.84807499999999,33.2384],"type":"Point"}
}