{
  "type": "Feature",
  "properties": {
    "iso:country":"US",
    "sg:address":"1408 6th St",
    "sg:city":"Northport",
    "sg:classifiers":[
        {
            "category":"Organizations",
            "subcategory":"Religious Organization",
            "type":"Services"
        }
    ],
    "sg:phone":"+1 205 349 2123",
    "sg:postcode":"35476",
    "sg:province":"AL",
    "wof:name":"Solid Rock Prmtive Bptst Chrch",
    "wof:placetype":"venue"
},
  "geometry": {"coordinates":[-87.573169,33.220187],"type":"Point"}
}