{
  "type": "Feature",
  "properties": {
    "iso:country":"US",
    "sg:address":"2511 Paul St",
    "sg:city":"Anniston",
    "sg:classifiers":[
        {
            "category":"Building & Trades",
            "subcategory":"Cleaning & Sanitation",
            "type":"Services"
        }
    ],
    "sg:phone":"+1 256 237 1256",
    "sg:postcode":"36201",
    "sg:province":"AL",
    "sg:tags":[
        "maintenance"
    ],
    "wof:name":"Clearview Window Washing",
    "wof:placetype":"venue"
},
  "geometry": {"coordinates":[-85.855133,33.676934],"type":"Point"}
}