{
  "type": "Feature",
  "properties": {
    "iso:country":"US",
    "sg:address":"2053 US Hwy 78",
    "sg:city":"Oxford",
    "sg:classifiers":[
        {
            "category":"Building & Trades",
            "subcategory":"Plumbing",
            "type":"Services"
        }
    ],
    "sg:phone":"+1 256 835 0544",
    "sg:postcode":"36203",
    "sg:province":"AL",
    "sg:tags":[
        "sheet",
        "work",
        "metal",
        "contractor"
    ],
    "wof:name":"Seals Welding & Fabricating",
    "wof:placetype":"venue"
},
  "geometry": {"coordinates":[-85.879538,33.593298],"type":"Point"}
}