{
  "type": "Feature",
  "properties": {
    "addr:full":"1020 Hampton Pl Birmingham AL 35242",
    "addr:housenumber":"1020",
    "addr:postcode":"35242",
    "addr:street":"Hampton Pl",
    "iso:country":"US",
    "sg:address":"1020 Hampton Pl",
    "sg:city":"Birmingham",
    "sg:classifiers":[
        {
            "category":"Building & Trades",
            "subcategory":"Construction",
            "type":"Services"
        }
    ],
    "sg:phone":"+1 205 995 8573",
    "sg:postcode":"35242",
    "sg:province":"AL",
    "sg:tags":[
        "house"
    ],
    "wof:name":"F & B Builders LLC",
    "wof:placetype":"venue"
},
  "geometry": {"coordinates":[-86.67822200000001,33.431962],"type":"Point"}
}