{
  "type": "Feature",
  "properties": {
    "iso:country":"US",
    "sg:address":"1060 Government St",
    "sg:city":"Mobile",
    "sg:classifiers":[
        {
            "category":"Education",
            "subcategory":"School",
            "type":"Public Place"
        }
    ],
    "sg:phone":"+1 251 438 6008",
    "sg:postcode":"36604",
    "sg:province":"AL",
    "wof:name":"Kingdom Life Center",
    "wof:placetype":"venue"
},
  "geometry": {"coordinates":[-88.058553,30.684883],"type":"Point"}
}