{
  "type": "Feature",
  "properties": {
    "addr:full":"425 Popular Cir Gardendale AL 35071",
    "addr:housenumber":"425",
    "addr:postcode":"35071",
    "addr:street":"Popular Cir",
    "iso:country":"US",
    "sg:address":"425 Popular Cir",
    "sg:city":"Gardendale",
    "sg:classifiers":[
        {
            "category":"Professional",
            "subcategory":"Management & Consulting",
            "type":"Services"
        }
    ],
    "sg:phone":"+1 205 631 9661",
    "sg:postcode":"35071",
    "sg:province":"AL",
    "sg:tags":[
        "business"
    ],
    "wof:name":"Skyline Development Co",
    "wof:placetype":"venue"
},
  "geometry": {"coordinates":[-86.815332,33.657506],"type":"Point"}
}