{
  "type": "Feature",
  "properties": {
    "addr:full":"3290 Dauphin St Mobile AL 36606",
    "addr:housenumber":"3290",
    "addr:postcode":"36606",
    "addr:street":"Dauphin St",
    "iso:country":"US",
    "sg:address":"3290 Dauphin St",
    "sg:city":"Mobile",
    "sg:classifiers":[
        {
            "category":"Health Services",
            "subcategory":"Doctor",
            "type":"Services"
        }
    ],
    "sg:phone":"+1 251 471 3309",
    "sg:postcode":"36606",
    "sg:province":"AL",
    "sg:tags":[
        "physician",
        "surgeon"
    ],
    "wof:name":"Vision America Of Mobile",
    "wof:placetype":"venue"
},
  "geometry": {"coordinates":[-88.121084,30.689273],"type":"Point"}
}