{
  "type": "Feature",
  "properties": {
    "addr:full":"23536 State Rte 79 Trafford AL 35172",
    "addr:housenumber":"23536",
    "addr:postcode":"35172",
    "addr:street":"State Rte 79",
    "iso:country":"US",
    "sg:address":"23536 State Rte 79",
    "sg:city":"Trafford",
    "sg:classifiers":[
        {
            "category":"Restaurant",
            "type":"Food & Drink"
        }
    ],
    "sg:phone":"+1 205 681 9108",
    "sg:postcode":"35172",
    "sg:province":"AL",
    "sg:tags":[
        "eating"
    ],
    "wof:name":"Mr Willies",
    "wof:placetype":"venue"
},
  "geometry": {"coordinates":[-86.668312,33.824573],"type":"Point"}
}