{
  "type": "Feature",
  "properties": {
    "addr:full":"140 Dogwood Cir Birmingham AL 35244",
    "addr:housenumber":"140",
    "addr:postcode":"35244",
    "addr:street":"Dogwood Cir",
    "iso:country":"US",
    "sg:address":"140 Dogwood Cir",
    "sg:city":"Birmingham",
    "sg:classifiers":[
        {
            "category":"Education",
            "subcategory":"Dance Studio",
            "type":"Public Place"
        }
    ],
    "sg:phone":"+1 205 981 9080",
    "sg:postcode":"35244",
    "sg:province":"AL",
    "wof:name":"Tiffanys Dance Studio",
    "wof:placetype":"venue"
},
  "geometry": {"coordinates":[-86.751667,33.372097],"type":"Point"}
}