{
  "type": "Feature",
  "properties": {
    "addr:full":"601 George Wallace Dr Gadsden AL 35903",
    "addr:housenumber":"601",
    "addr:postcode":"35903",
    "addr:street":"George Wallace Dr",
    "iso:country":"US",
    "sg:address":"601 George Wallace Dr",
    "sg:city":"Gadsden",
    "sg:classifiers":[
        {
            "category":"Home & Garden",
            "subcategory":"Building Materials",
            "type":"Retail Goods"
        }
    ],
    "sg:phone":"+1 256 543 9110",
    "sg:postcode":"35903",
    "sg:province":"AL",
    "wof:name":"Lowes",
    "wof:placetype":"venue"
},
  "geometry": {"coordinates":[-85.994221,34.000764],"type":"Point"}
}