{
  "type": "Feature",
  "properties": {
    "iso:country":"US",
    "sg:address":"11025 Co Rd 15",
    "sg:city":"Florence",
    "sg:classifiers":[
        {
            "category":"Organizations",
            "subcategory":"Religious Organization",
            "type":"Services"
        }
    ],
    "sg:phone":"+1 256 767 0017",
    "sg:postcode":"35633",
    "sg:province":"AL",
    "sg:tags":[
        "church"
    ],
    "wof:name":"Wesley Chapel United Methodist",
    "wof:placetype":"venue"
},
  "geometry": {"coordinates":[-87.788786,34.906896],"type":"Point"}
}