{
  "type": "Feature",
  "properties": {
    "iso:country":"US",
    "sg:address":"2506 Danville Rd SW",
    "sg:city":"Decatur",
    "sg:classifiers":[
        {
            "category":"Health Services",
            "subcategory":"Dentist",
            "type":"Services"
        }
    ],
    "sg:phone":"+1 256 353 3462",
    "sg:postcode":"35603",
    "sg:province":"AL",
    "wof:name":"Throneberry, Richard DMD",
    "wof:placetype":"venue"
},
  "geometry": {"coordinates":[-87.01775000000001,34.564362],"type":"Point"}
}