{
  "type": "Feature",
  "properties": {
    "iso:country":"US",
    "sg:address":"1320 Impala Dr",
    "sg:city":"Birmingham",
    "sg:classifiers":[
        {
            "category":"Professional",
            "subcategory":"Business Services",
            "type":"Services"
        }
    ],
    "sg:phone":"+1 205 815 3915",
    "sg:postcode":"35235",
    "sg:province":"AL",
    "wof:name":"Tracy Chang",
    "wof:placetype":"venue"
},
  "geometry": {"coordinates":[-86.671001,33.611195],"type":"Point"}
}