{
  "type": "Feature",
  "properties": {
    "addr:full":"1632 8th Ave W Birmingham AL 35208",
    "addr:housenumber":"1632",
    "addr:postcode":"35208",
    "addr:street":"8Th Ave W",
    "iso:country":"US",
    "sg:address":"1632 8th Ave W",
    "sg:city":"Birmingham",
    "sg:classifiers":[
        {
            "category":"Shopping",
            "subcategory":"Gifts & Souvenirs",
            "type":"Retail Goods"
        }
    ],
    "sg:phone":"+1 205 787 1553",
    "sg:postcode":"35208",
    "sg:province":"AL",
    "wof:name":"Naughty But Nice",
    "wof:placetype":"venue"
},
  "geometry": {"coordinates":[-86.864071,33.512093],"type":"Point"}
}