{
  "type": "Feature",
  "properties": {
    "iso:country":"US",
    "sg:address":"301 Co Rd 1770",
    "sg:city":"Joppa",
    "sg:classifiers":[
        {
            "category":"Freight",
            "type":"Transportation"
        }
    ],
    "sg:phone":"+1 256 796 2795",
    "sg:postcode":"35087",
    "sg:province":"AL",
    "sg:tags":[
        "hauling",
        "trucking"
    ],
    "wof:name":"T M Gorham Shop",
    "wof:placetype":"venue"
},
  "geometry": {"coordinates":[-86.587597,34.304842],"type":"Point"}
}