{
  "type": "Feature",
  "properties": {
    "iso:country":"US",
    "sg:address":"1217 S Lawrence St",
    "sg:city":"Montgomery",
    "sg:classifiers":[
        {
            "category":"Wholesale",
            "subcategory":"Stationery",
            "type":"Manufacturing & Wholesale Goods"
        }
    ],
    "sg:phone":"+1 334 356 7859",
    "sg:postcode":"36104",
    "sg:province":"AL",
    "sg:tags":[
        "product",
        "paper"
    ],
    "wof:name":"Paper Petalz",
    "wof:placetype":"venue"
},
  "geometry": {"coordinates":[-86.30553999999999,32.359472],"type":"Point"}
}