{
  "type": "Feature",
  "properties": {
    "iso:country":"US",
    "sg:address":"4560 Co Rd 137",
    "sg:city":"Florence",
    "sg:classifiers":[
        {
            "category":"Retail",
            "subcategory":"Auto Repair",
            "type":"Services"
        }
    ],
    "sg:phone":"+1 256 766 6346",
    "sg:postcode":"35633",
    "sg:province":"AL",
    "sg:tags":[
        "body",
        "automobile",
        "painting"
    ],
    "wof:name":"Miller's Body Shop",
    "wof:placetype":"venue"
},
  "geometry": {"coordinates":[-87.780269,34.865032],"type":"Point"}
}