{
  "type": "Feature",
  "properties": {
    "iso:country":"US",
    "sg:address":"13431 Sea Breeze Blvd",
    "sg:city":"Fairhope",
    "sg:classifiers":[
        {
            "category":"Building & Trades",
            "subcategory":"Cleaning & Sanitation",
            "type":"Services"
        }
    ],
    "sg:phone":"+1 251 929 7769",
    "sg:postcode":"36532",
    "sg:province":"AL",
    "sg:tags":[
        "maintenance"
    ],
    "wof:name":"Pioneer Janitorial Service",
    "wof:placetype":"venue"
},
  "geometry": {"coordinates":[-87.860488,30.420321],"type":"Point"}
}