{
  "type": "Feature",
  "properties": {
    "iso:country":"US",
    "sg:address":"4456 Highway 55 E",
    "sg:city":"Eva",
    "sg:classifiers":[
        {
            "category":"Professional",
            "subcategory":"Business Services",
            "type":"Services"
        },
        {
            "category":"Government",
            "subcategory":"Post Office",
            "type":"Public Place"
        }
    ],
    "sg:phone":"+1 800 275 8777",
    "sg:postcode":"35621",
    "sg:province":"AL",
    "sg:tags":[
        "mail",
        "shipping"
    ],
    "sg:website":"http://www.usps.com",
    "wof:name":"USPS - United States Post Office - Eva Main Office",
    "wof:placetype":"venue"
},
  "geometry": {"coordinates":[-86.77478600000001,34.333143],"type":"Point"}
}