{
  "type": "Feature",
  "properties": {
    "iso:country":"US",
    "sg:address":"8210 Stephanie Dr SW",
    "sg:city":"Huntsville",
    "sg:classifiers":[
        {
            "category":"Professional",
            "subcategory":"Business Services",
            "type":"Services"
        }
    ],
    "sg:phone":"+1 256 880 6073",
    "sg:postcode":"35802",
    "sg:province":"AL",
    "sg:tags":[
        "recording",
        "studio"
    ],
    "wof:name":"Grace Note Productions",
    "wof:placetype":"venue"
},
  "geometry": {"coordinates":[-86.568009,34.657481],"type":"Point"}
}