{
  "type": "Feature",
  "properties": {
    "iso:country":"US",
    "sg:address":"132 E Peachtree St",
    "sg:city":"Scottsboro",
    "sg:classifiers":[
        {
            "category":"Social Services",
            "type":"Services"
        }
    ],
    "sg:phone":"+1 256 574 5826",
    "sg:postcode":"35768",
    "sg:province":"AL",
    "wof:name":"Crisis Service of North Ala",
    "wof:placetype":"venue"
},
  "geometry": {"coordinates":[-86.033716,34.671589],"type":"Point"}
}