{
  "type": "Feature",
  "properties": {
    "addr:full":"60 Moon Rd Bradford AL 35089",
    "addr:housenumber":"60",
    "addr:postcode":"35089",
    "addr:street":"Moon Rd",
    "iso:country":"US",
    "sg:address":"60 Moon Rd",
    "sg:city":"Bradford",
    "sg:classifiers":[
        {
            "category":"Food & Beverages",
            "subcategory":"Bakery",
            "type":"Retail Goods"
        }
    ],
    "sg:phone":"+1 401 377 3059",
    "sg:postcode":"35089",
    "sg:province":"AL",
    "sg:tags":[
        "doughnut"
    ],
    "wof:name":"Bess Eaton Donut",
    "wof:placetype":"venue"
},
  "geometry": {"coordinates":[-86.00578899999999,32.985048],"type":"Point"}
}