{
  "type": "Feature",
  "properties": {
    "addr:full":"940 Calvert Rd Cullman AL 35057",
    "addr:housenumber":"940",
    "addr:postcode":"35057",
    "addr:street":"Calvert Rd",
    "iso:country":"US",
    "sg:address":"940 Calvert Rd",
    "sg:city":"Cullman",
    "sg:classifiers":[
        {
            "category":"Health Services",
            "subcategory":"Clinic",
            "type":"Services"
        }
    ],
    "sg:phone":"+1 256 739 5336",
    "sg:postcode":"35057",
    "sg:province":"AL",
    "sg:tags":[
        "home"
    ],
    "wof:name":"Amway Home Care Products",
    "wof:placetype":"venue"
},
  "geometry": {"coordinates":[-86.878389,34.112131],"type":"Point"}
}