{
  "type": "Feature",
  "properties": {
    "iso:country":"US",
    "sg:address":"5801 Eastdale Dr",
    "sg:city":"Montgomery",
    "sg:classifiers":[
        {
            "category":"Health Services",
            "subcategory":"Nursing And Care Facility",
            "type":"Services"
        }
    ],
    "sg:phone":"+1 334 260 8911",
    "sg:postcode":"36117",
    "sg:province":"AL",
    "sg:tags":[
        "home",
        "retirement",
        "community"
    ],
    "wof:name":"Eastdale Estates",
    "wof:placetype":"venue"
},
  "geometry": {"coordinates":[-86.200953,32.38657],"type":"Point"}
}