{
  "type": "Feature",
  "properties": {
    "addr:full":"24 Saraland Ave Saraland AL 36571",
    "addr:housenumber":"24",
    "addr:postcode":"36571",
    "addr:street":"Saraland Ave Saraland",
    "iso:country":"US",
    "sg:address":"24 Saraland Ave",
    "sg:city":"Saraland",
    "sg:classifiers":[
        {
            "category":"Building & Trades",
            "subcategory":"Landscaping Services",
            "type":"Services"
        }
    ],
    "sg:phone":"+1 251 679 6058",
    "sg:postcode":"36571",
    "sg:province":"AL",
    "wof:name":"Lamberts Lawn Care",
    "wof:placetype":"venue"
},
  "geometry": {"coordinates":[-88.069604,30.827285],"type":"Point"}
}