{
  "type": "Feature",
  "properties": {
    "addr:full":"160 Twitchell Rd Dothan AL 36303",
    "addr:housenumber":"160",
    "addr:postcode":"36303",
    "addr:street":"Twitchell Rd",
    "iso:country":"US",
    "sg:address":"160 Twitchell Rd",
    "sg:city":"Dothan",
    "sg:classifiers":[
        {
            "category":"Utilities",
            "subcategory":"Fuel Oil & Lpg",
            "type":"Services"
        }
    ],
    "sg:phone":"+1 334 792 3136",
    "sg:postcode":"36303",
    "sg:province":"AL",
    "wof:name":"Shell",
    "wof:placetype":"venue"
},
  "geometry": {"coordinates":[-85.397325,31.243145],"type":"Point"}
}