{
  "type": "Feature",
  "properties": {
    "addr:full":"201 W Main St Hartford AL 36344",
    "addr:housenumber":"201",
    "addr:postcode":"36344",
    "addr:street":"W Main St",
    "iso:country":"US",
    "sg:address":"201 W Main St",
    "sg:city":"Hartford",
    "sg:classifiers":[
        {
            "category":"Government",
            "subcategory":"Post Office",
            "type":"Public Place"
        }
    ],
    "sg:phone":"+1 334 588 2952",
    "sg:postcode":"36344",
    "sg:province":"AL",
    "sg:tags":[
        "postal",
        "us"
    ],
    "wof:name":"US Post Office",
    "wof:placetype":"venue"
},
  "geometry": {"coordinates":[-85.697593,31.102221],"type":"Point"}
}