{
  "type": "Feature",
  "properties": {
    "iso:country":"US",
    "sg:address":"494 Nick Fitcheard Rd NW",
    "sg:city":"Huntsville",
    "sg:classifiers":[
        {
            "category":"Freight",
            "type":"Transportation"
        }
    ],
    "sg:phone":"+1 256 859 9802",
    "sg:postcode":"35806",
    "sg:province":"AL",
    "sg:tags":[
        "operator",
        "trucking"
    ],
    "wof:name":"T & M Trucking",
    "wof:placetype":"venue"
},
  "geometry": {"coordinates":[-86.669725,34.783807],"type":"Point"}
}