{
  "type": "Feature",
  "properties": {
    "iso:country":"US",
    "sg:address":"205 New Bethel Rd",
    "sg:city":"Jasper",
    "sg:classifiers":[
        {
            "category":"Organizations",
            "subcategory":"Religious Organization",
            "type":"Services"
        }
    ],
    "sg:phone":"+1 205 483 0815",
    "sg:postcode":"35501",
    "sg:province":"AL",
    "wof:name":"New Bethel Baptist Church",
    "wof:placetype":"venue"
},
  "geometry": {"coordinates":[-87.163654,33.821328],"type":"Point"}
}