{
  "type": "Feature",
  "properties": {
    "iso:country":"US",
    "sg:address":"3021 University Dr NW",
    "sg:city":"Huntsville",
    "sg:classifiers":[
        {
            "category":"Organizations",
            "subcategory":"Religious Organization",
            "type":"Services"
        }
    ],
    "sg:phone":"+1 256 534 4221",
    "sg:postcode":"35816",
    "sg:province":"AL",
    "wof:name":"Holy Cross Saints Constantn An",
    "wof:placetype":"venue"
},
  "geometry": {"coordinates":[-86.61707199999999,34.735103],"type":"Point"}
}