{
  "type": "Feature",
  "properties": {
    "addr:full":"5830 University Dr NW Huntsville AL 35806",
    "addr:housenumber":"5830",
    "addr:postcode":"35806",
    "addr:street":"University Dr Nw",
    "iso:country":"US",
    "sg:address":"5830 University Dr NW",
    "sg:city":"Huntsville",
    "sg:classifiers":[
        {
            "category":"Autos & Motor Vehicles",
            "subcategory":"Fuel & Gas Station",
            "type":"Retail Goods"
        },
        {
            "category":"Food & Beverages",
            "subcategory":"Groceries & Convenience Stores",
            "type":"Retail Goods"
        }
    ],
    "sg:phone":"+1 256 217 1999",
    "sg:postcode":"35806",
    "sg:province":"AL",
    "sg:website":"http://www.chevron.com/products/",
    "wof:name":"Chevron",
    "wof:placetype":"venue"
},
  "geometry": {"coordinates":[-86.662178,34.739841],"type":"Point"}
}