{
  "type": "Feature",
  "properties": {
    "addr:full":"1903 Bruin Dr Florence AL 35630",
    "addr:housenumber":"1903",
    "addr:postcode":"35630",
    "addr:street":"Bruin Dr",
    "iso:country":"US",
    "sg:address":"1903 Bruin Dr",
    "sg:city":"Florence",
    "sg:classifiers":[
        {
            "category":"Health Services",
            "subcategory":"Doctor",
            "type":"Services"
        }
    ],
    "sg:phone":"+1 256 764 1858",
    "sg:postcode":"35630",
    "sg:province":"AL",
    "sg:tags":[
        "physician",
        "surgeon"
    ],
    "wof:name":"Christine B Myers MD",
    "wof:placetype":"venue"
},
  "geometry": {"coordinates":[-87.66523599999999,34.830777],"type":"Point"}
}