{
  "type": "Feature",
  "properties": {
    "iso:country":"US",
    "sg:address":"450 Hackel Dr",
    "sg:city":"Montgomery",
    "sg:classifiers":[
        {
            "category":"Professional",
            "subcategory":"Business Services",
            "type":"Services"
        }
    ],
    "sg:phone":"+1 334 273 8987",
    "sg:postcode":"36117",
    "sg:province":"AL",
    "wof:name":"Culligan Water Technologies De",
    "wof:placetype":"venue"
},
  "geometry": {"coordinates":[-86.208928,32.39709],"type":"Point"}
}