{
  "type": "Feature",
  "properties": {
    "iso:country":"US",
    "sg:address":"3125 Pinson Valley Pkwy",
    "sg:city":"Birmingham",
    "sg:classifiers":[
        {
            "category":"Manufacturing",
            "subcategory":"Tools & Machinery",
            "type":"Manufacturing & Wholesale Goods"
        }
    ],
    "sg:phone":"+1 205 520 5111",
    "sg:postcode":"35217",
    "sg:province":"AL",
    "sg:tags":[
        "conductive",
        "wiring",
        "devices",
        "mfg"
    ],
    "wof:name":"Schneider Electric",
    "wof:placetype":"venue"
},
  "geometry": {"coordinates":[-86.734467,33.623268],"type":"Point"}
}