{
  "type": "Feature",
  "properties": {
    "addr:full":"133 E Grandview Dr Muscle Shoals AL 35661",
    "addr:housenumber":"133",
    "addr:postcode":"35661",
    "addr:street":"E Grandview Dr",
    "iso:country":"US",
    "sg:address":"133 E Grandview Dr",
    "sg:city":"Muscle Shoals",
    "sg:classifiers":[
        {
            "category":"Professional",
            "subcategory":"Lawyer & Legal Services",
            "type":"Services"
        }
    ],
    "sg:phone":"+1 256 383 6128",
    "sg:postcode":"35661",
    "sg:province":"AL",
    "wof:name":"John D Clement Jr",
    "wof:placetype":"venue"
},
  "geometry": {"coordinates":[-87.607061,34.792911],"type":"Point"}
}