{
  "type": "Feature",
  "properties": {
    "iso:country":"US",
    "sg:address":"1026 Stanton Rd",
    "sg:city":"Daphne",
    "sg:classifiers":[
        {
            "category":"Wholesale",
            "subcategory":"Machinery & Supplies",
            "type":"Manufacturing & Wholesale Goods"
        }
    ],
    "sg:phone":"+1 251 626 5470",
    "sg:postcode":"36526",
    "sg:province":"AL",
    "sg:tags":[
        "equipment",
        "irrigation",
        "system"
    ],
    "wof:name":"Irrigation Components",
    "wof:placetype":"venue"
},
  "geometry": {"coordinates":[-87.894064,30.596118],"type":"Point"}
}