{
  "type": "Feature",
  "properties": {
    "addr:full":"129 Gooch Ln Madison AL 35758",
    "addr:housenumber":"129",
    "addr:postcode":"35758",
    "addr:street":"Gooch Ln",
    "iso:country":"US",
    "sg:address":"129 Gooch Ln",
    "sg:city":"Madison",
    "sg:classifiers":[
        {
            "category":"Organizations",
            "subcategory":"Religious Organization",
            "type":"Services"
        }
    ],
    "sg:phone":"+1 256 864 2829",
    "sg:postcode":"35758",
    "sg:province":"AL",
    "sg:tags":[
        "church"
    ],
    "wof:name":"Grady Madison AME Church",
    "wof:placetype":"venue"
},
  "geometry": {"coordinates":[-86.742493,34.750234],"type":"Point"}
}