{
  "type": "Feature",
  "properties": {
    "iso:country":"US",
    "sg:address":"227 New Searcy Rd",
    "sg:city":"Greenville",
    "sg:classifiers":[
        {
            "category":"Building & Trades",
            "subcategory":"Construction",
            "type":"Services"
        }
    ],
    "sg:phone":"+1 334 382 5180",
    "sg:postcode":"36037",
    "sg:province":"AL",
    "sg:tags":[
        "general",
        "contractor"
    ],
    "wof:name":"Allen Tillery Builder",
    "wof:placetype":"venue"
},
  "geometry": {"coordinates":[-86.630039,31.85478],"type":"Point"}
}