{
  "type": "Feature",
  "properties": {
    "addr:full":"5402 US Hwy 431 Albertville AL 35950",
    "addr:housenumber":"5402",
    "addr:postcode":"35950",
    "addr:street":"Us Hwy 431",
    "iso:country":"US",
    "sg:address":"5402 US Hwy 431",
    "sg:city":"Albertville",
    "sg:classifiers":[
        {
            "category":"Retail",
            "subcategory":"Car Wash",
            "type":"Services"
        }
    ],
    "sg:phone":"+1 256 878 5606",
    "sg:postcode":"35950",
    "sg:province":"AL",
    "sg:tags":[
        "automobile",
        "detail",
        "clean"
    ],
    "wof:name":"B & B Automotive Detail",
    "wof:placetype":"venue"
},
  "geometry": {"coordinates":[-86.184112,34.25672],"type":"Point"}
}