{
  "type": "Feature",
  "properties": {
    "iso:country":"US",
    "sg:address":"510 E Laurel St",
    "sg:city":"Scottsboro",
    "sg:classifiers":[
        {
            "category":"Banks & Credit Unions",
            "subcategory":"Bank",
            "type":"Services"
        }
    ],
    "sg:phone":"+1 256 259 1516",
    "sg:postcode":"35768",
    "sg:province":"AL",
    "sg:website":"www.regions.com",
    "wof:name":"Regions",
    "wof:placetype":"venue"
},
  "geometry": {"coordinates":[-86.029504,34.672716],"type":"Point"}
}