{
  "type": "Feature",
  "properties": {
    "iso:country":"US",
    "sg:address":"4220 Co Rd 76",
    "sg:city":"Rogersville",
    "sg:classifiers":[
        {
            "category":"Wholesale",
            "subcategory":"Poultry",
            "type":"Manufacturing & Wholesale Goods"
        }
    ],
    "sg:phone":"+1 256 247 5993",
    "sg:postcode":"35652",
    "sg:province":"AL",
    "wof:name":"Tim Newton Poultry",
    "wof:placetype":"venue"
},
  "geometry": {"coordinates":[-87.355337,34.891143],"type":"Point"}
}