{
  "type": "Feature",
  "properties": {
    "iso:country":"US",
    "sg:address":"195 Oxmoor Rd",
    "sg:city":"Homewood",
    "sg:classifiers":[
        {
            "category":"Travel",
            "subcategory":"Hotels & Motels",
            "type":"Entertainment"
        }
    ],
    "sg:phone":"+1 205 941 0990",
    "sg:postcode":"35209",
    "sg:province":"AL",
    "sg:website":"www.choicehotels.com",
    "wof:name":"Comfort Inn",
    "wof:placetype":"venue"
},
  "geometry": {"coordinates":[-86.828647,33.461051],"type":"Point"}
}