{
  "type": "Feature",
  "properties": {
    "iso:country":"US",
    "sg:address":"3115 Northington Ct",
    "sg:city":"Florence",
    "sg:classifiers":[
        {
            "category":"Professional",
            "subcategory":"Computer Services",
            "type":"Services"
        }
    ],
    "sg:phone":"+1 256 740 5644",
    "sg:postcode":"35630",
    "sg:province":"AL",
    "sg:tags":[
        "home",
        "consulting",
        "page",
        "dev",
        "internet"
    ],
    "wof:name":"Shoals Web",
    "wof:placetype":"venue"
},
  "geometry": {"coordinates":[-87.665851,34.875548],"type":"Point"}
}