{
  "type": "Feature",
  "properties": {
    "iso:country":"US",
    "sg:address":"112 Deer Run Ln",
    "sg:city":"Harvest",
    "sg:classifiers":[
        {
            "category":"Building & Trades",
            "subcategory":"Construction",
            "type":"Services"
        }
    ],
    "sg:phone":"+1 256 325 7233",
    "sg:postcode":"35749",
    "sg:province":"AL",
    "sg:tags":[
        "contractor"
    ],
    "wof:name":"Petsafe of North Alabama",
    "wof:placetype":"venue"
},
  "geometry": {"coordinates":[-86.690983,34.823771],"type":"Point"}
}