{
  "type": "Feature",
  "properties": {
    "iso:country":"US",
    "sg:address":"125 Colonial Promenade Pkwy",
    "sg:city":"Alabaster",
    "sg:classifiers":[
        {
            "category":"Restaurant",
            "type":"Food & Drink"
        }
    ],
    "sg:menulink":"http://www.allmenus.com/al/alabaster-helena/179527-chick-fil-a/menu/",
    "sg:phone":"+1 205 685 1190",
    "sg:postcode":"35007",
    "sg:province":"AL",
    "sg:tags":[
        "wrap",
        "soup",
        "american",
        "sandwich",
        "salad"
    ],
    "wof:name":"Chick-fil-A",
    "wof:placetype":"venue"
},
  "geometry": {"coordinates":[-86.804722,33.229531],"type":"Point"}
}