{
  "type": "Feature",
  "properties": {
    "addr:full":"102 Madison Ave Madison AL 35758",
    "addr:housenumber":"102",
    "addr:postcode":"35758",
    "addr:street":"Madison Ave",
    "iso:country":"US",
    "sg:address":"102 Madison Ave",
    "sg:city":"Madison",
    "sg:classifiers":[
        {
            "category":"Real Estate",
            "subcategory":"Real Estate Agent",
            "type":"Services"
        }
    ],
    "sg:phone":"+1 256 461 0275",
    "sg:postcode":"35758",
    "sg:province":"AL",
    "wof:name":"Villas Of Madison Sales Ctr",
    "wof:placetype":"venue"
},
  "geometry": {"coordinates":[-86.739344,34.714595],"type":"Point"}
}