{
  "type": "Feature",
  "properties": {
    "iso:country":"US",
    "sg:address":"4101 Coalburg Rd",
    "sg:city":"Birmingham",
    "sg:classifiers":[
        {
            "category":"Wholesale",
            "subcategory":"Office Equipment",
            "type":"Manufacturing & Wholesale Goods"
        },
        {
            "category":"Shopping",
            "subcategory":"Stationery & Office Supplies",
            "type":"Retail Goods"
        },
        {
            "category":"Professional",
            "subcategory":"Printing & Photocopies",
            "type":"Services"
        }
    ],
    "sg:phone":"+1 205 631 4048",
    "sg:postcode":"35207",
    "sg:province":"AL",
    "sg:tags":[
        "autographic",
        "register",
        "services-commercial"
    ],
    "wof:name":"T R M Services",
    "wof:placetype":"venue"
},
  "geometry": {"coordinates":[-86.841942,33.56181],"type":"Point"}
}