{
  "type": "Feature",
  "properties": {
    "iso:country":"US",
    "sg:address":"134 Lecroy Cir",
    "sg:city":"Brent",
    "sg:classifiers":[
        {
            "category":"Farming",
            "subcategory":"Livestock Farm",
            "type":"Manufacturing & Wholesale Goods"
        }
    ],
    "sg:phone":"+1 205 926 9274",
    "sg:postcode":"35034",
    "sg:province":"AL",
    "sg:tags":[
        "beef",
        "feedlot",
        "cattle"
    ],
    "wof:name":"Dowdle Farms",
    "wof:placetype":"venue"
},
  "geometry": {"coordinates":[-87.183374,32.926566],"type":"Point"}
}