{
  "type": "Feature",
  "properties": {
    "iso:country":"US",
    "sg:address":"16914 State Rte 216",
    "sg:city":"Brookwood",
    "sg:classifiers":[
        {
            "category":"Organizations",
            "subcategory":"Religious Organization",
            "type":"Services"
        }
    ],
    "sg:phone":"+1 205 554 1595",
    "sg:postcode":"35444",
    "sg:province":"AL",
    "sg:tags":[
        "church"
    ],
    "wof:name":"East Brookwood Missionary Bapt",
    "wof:placetype":"venue"
},
  "geometry": {"coordinates":[-87.286574,33.27803],"type":"Point"}
}