{
  "type": "Feature",
  "properties": {
    "iso:country":"US",
    "sg:address":"2966 Spring Hill Ave",
    "sg:city":"Mobile",
    "sg:classifiers":[
        {
            "category":"Personal",
            "subcategory":"Barber",
            "type":"Services"
        }
    ],
    "sg:phone":"+1 251 478 0152",
    "sg:postcode":"36607",
    "sg:province":"AL",
    "sg:tags":[
        "shop"
    ],
    "wof:name":"Exclusive Cuts Barber Shop",
    "wof:placetype":"venue"
},
  "geometry": {"coordinates":[-88.110327,30.699525],"type":"Point"}
}