{
  "type": "Feature",
  "properties": {
    "iso:country":"US",
    "sg:address":"35161 US Hwy 280",
    "sg:city":"Sylacauga",
    "sg:classifiers":[
        {
            "category":"Social Services",
            "subcategory":"Child Care",
            "type":"Services"
        }
    ],
    "sg:phone":"+1 256 378 6747",
    "sg:postcode":"35150",
    "sg:province":"AL",
    "sg:tags":[
        "day"
    ],
    "wof:name":"Elite Care",
    "wof:placetype":"venue"
},
  "geometry": {"coordinates":[-86.33651999999999,33.244373],"type":"Point"}
}