{
  "type": "Feature",
  "properties": {
    "addr:full":"4851 Whitesburg Dr S Huntsville AL 35802",
    "addr:housenumber":"4851",
    "addr:postcode":"35802",
    "addr:street":"Whitesburg Dr S",
    "iso:country":"US",
    "sg:address":"4851 Whitesburg Dr S",
    "sg:city":"Huntsville",
    "sg:classifiers":[
        {
            "category":"Food & Beverages",
            "subcategory":"Groceries & Convenience Stores",
            "type":"Retail Goods"
        }
    ],
    "sg:phone":"+1 256 650 2390",
    "sg:postcode":"35802",
    "sg:province":"AL",
    "sg:tags":[
        "supermarket"
    ],
    "wof:name":"Publix",
    "wof:placetype":"venue"
},
  "geometry": {"coordinates":[-86.568175,34.69415],"type":"Point"}
}