{
  "type": "Feature",
  "properties": {
    "iso:country":"US",
    "sg:address":"576 Martin Luther King Dr",
    "sg:city":"Auburn",
    "sg:classifiers":[
        {
            "category":"Organizations",
            "subcategory":"Religious Organization",
            "type":"Services"
        }
    ],
    "sg:phone":"+1 334 821 1802",
    "sg:postcode":"36832",
    "sg:province":"AL",
    "wof:name":"Auburn AME Zion Church",
    "wof:placetype":"venue"
},
  "geometry": {"coordinates":[-85.491189,32.610233],"type":"Point"}
}