{
  "type": "Feature",
  "properties": {
    "iso:country":"US",
    "sg:address":"2090 Columbiana Rd",
    "sg:city":"Birmingham",
    "sg:classifiers":[
        {
            "category":"Health Services",
            "subcategory":"Doctor",
            "type":"Services"
        }
    ],
    "sg:phone":"+1 205 443 0307",
    "sg:postcode":"35216",
    "sg:province":"AL",
    "sg:tags":[
        "medical"
    ],
    "wof:name":"Care Now Clinics",
    "wof:placetype":"venue"
},
  "geometry": {"coordinates":[-86.808404,33.437962],"type":"Point"}
}