{
  "type": "Feature",
  "properties": {
    "addr:full":"1971 S Brannon Stand Rd Dothan AL 36305",
    "addr:housenumber":"1971",
    "addr:postcode":"36305",
    "addr:street":"S Brannon Stand Rd",
    "iso:country":"US",
    "sg:address":"1971 S Brannon Stand Rd",
    "sg:city":"Dothan",
    "sg:classifiers":[
        {
            "category":"Real Estate",
            "subcategory":"Real Estate Agent",
            "type":"Services"
        }
    ],
    "sg:phone":"+1 334 793 8279",
    "sg:postcode":"36305",
    "sg:province":"AL",
    "sg:tags":[
        "management"
    ],
    "wof:name":"Dothan Real Estate",
    "wof:placetype":"venue"
},
  "geometry": {"coordinates":[-85.485347,31.212829],"type":"Point"}
}