{
  "type": "Feature",
  "properties": {
    "addr:full":"2710 Treyburne Ln Owens Cross Roads AL 35763",
    "addr:housenumber":"2710",
    "addr:postcode":"35763",
    "addr:street":"Treyburne Ln",
    "iso:country":"US",
    "sg:address":"2710 Treyburne Ln",
    "sg:city":"Owens Cross Roads",
    "sg:classifiers":[
        {
            "category":"Professional",
            "type":"Services"
        }
    ],
    "sg:phone":"+1 256 564 9825",
    "sg:postcode":"35763",
    "sg:province":"AL",
    "wof:name":"Lennys of Huntsville LLC",
    "wof:placetype":"venue"
},
  "geometry": {"coordinates":[-86.471293,34.669762],"type":"Point"}
}