{
  "type": "Feature",
  "properties": {
    "iso:country":"US",
    "sg:address":"1000 Riverchase Galleria",
    "sg:city":"Birmingham",
    "sg:classifiers":[
        {
            "category":"Restaurant",
            "type":"Food & Drink"
        }
    ],
    "sg:menulink":"http://www.allmenus.com/al/hoover/255158-shulas-american-steakhouse/menu/",
    "sg:phone":"+1 205 444 5750",
    "sg:postcode":"35244",
    "sg:province":"AL",
    "sg:tags":[
        "american",
        "steakhouse"
    ],
    "wof:name":"Shula's American Steakhouse",
    "wof:placetype":"venue"
},
  "geometry": {"coordinates":[-86.80532599999999,33.379586],"type":"Point"}
}