{
  "type": "Feature",
  "properties": {
    "iso:country":"US",
    "sg:address":"116 Bush Ave",
    "sg:city":"Mobile",
    "sg:classifiers":[
        {
            "category":"Professional",
            "type":"Services"
        }
    ],
    "sg:phone":"+1 251 432 0253",
    "sg:postcode":"36604",
    "sg:province":"AL",
    "wof:name":"Meyer Motor Comp",
    "wof:placetype":"venue"
},
  "geometry": {"coordinates":[-88.066748,30.691972],"type":"Point"}
}