{
  "type": "Feature",
  "properties": {
    "iso:country":"US",
    "sg:address":"3506 29th St",
    "sg:city":"Tuscaloosa",
    "sg:classifiers":[
        {
            "category":"Food & Beverages",
            "subcategory":"Groceries & Convenience Stores",
            "type":"Retail Goods"
        }
    ],
    "sg:phone":"+1 205 752 5158",
    "sg:postcode":"35401",
    "sg:province":"AL",
    "sg:tags":[
        "grocer"
    ],
    "wof:name":"Stacy's Food Market",
    "wof:placetype":"venue"
},
  "geometry": {"coordinates":[-87.582452,33.186273],"type":"Point"}
}