{
  "type": "Feature",
  "properties": {
    "iso:country":"US",
    "sg:address":"907 S Memorial Dr",
    "sg:city":"Prattville",
    "sg:classifiers":[
        {
            "category":"Manufacturing",
            "subcategory":"Apparel",
            "type":"Manufacturing & Wholesale Goods"
        }
    ],
    "sg:phone":"+1 334 361 2133",
    "sg:postcode":"36067",
    "sg:province":"AL",
    "sg:tags":[
        "embroidery"
    ],
    "sg:website":"www.artstitch.com",
    "wof:name":"Art Stitch Embroidery",
    "wof:placetype":"venue"
},
  "geometry": {"coordinates":[-86.446538,32.455261],"type":"Point"}
}