{
  "type": "Feature",
  "properties": {
    "iso:country":"US",
    "sg:address":"260 Old Anniston-Gadsden Hwy",
    "sg:city":"Ohatchee",
    "sg:classifiers":[
        {
            "category":"Wholesale",
            "subcategory":"Durable Goods & Equipment",
            "type":"Manufacturing & Wholesale Goods"
        },
        {
            "category":"Shopping",
            "subcategory":"Gifts & Souvenirs",
            "type":"Retail Goods"
        }
    ],
    "sg:phone":"+1 256 892 1374",
    "sg:postcode":"36271",
    "sg:province":"AL",
    "sg:tags":[
        "novelty"
    ],
    "wof:name":"C-S Wholesale",
    "wof:placetype":"venue"
},
  "geometry": {"coordinates":[-85.917875,33.856792],"type":"Point"}
}