{
  "type": "Feature",
  "properties": {
    "addr:full":"3296 Shallowford Cir Birmingham AL 35216",
    "addr:housenumber":"3296",
    "addr:postcode":"35216",
    "addr:street":"Shallowford Cir",
    "iso:country":"US",
    "sg:address":"3296 Shallowford Cir",
    "sg:city":"Birmingham",
    "sg:classifiers":[
        {
            "category":"Shopping",
            "subcategory":"Beauty & Cosmetics",
            "type":"Retail Goods"
        }
    ],
    "sg:phone":"+1 205 979 9908",
    "sg:postcode":"35216",
    "sg:province":"AL",
    "sg:tags":[
        "merchandise"
    ],
    "wof:name":"Mary Kay Cosmetics",
    "wof:placetype":"venue"
},
  "geometry": {"coordinates":[-86.78663899999999,33.406448],"type":"Point"}
}