{
  "type": "Feature",
  "properties": {
    "iso:country":"US",
    "sg:address":"10720 Magnolia Rd",
    "sg:city":"Irvington",
    "sg:classifiers":[
        {
            "category":"Building & Trades",
            "subcategory":"Electrical",
            "type":"Services"
        }
    ],
    "sg:phone":"+1 251 957 3539",
    "sg:postcode":"36544",
    "sg:province":"AL",
    "sg:tags":[
        "electrical",
        "contractor"
    ],
    "wof:name":"Holt Electric",
    "wof:placetype":"venue"
},
  "geometry": {"coordinates":[-88.225552,30.471377],"type":"Point"}
}