{
  "type": "Feature",
  "properties": {
    "addr:full":"96 State Rte 134 Daleville AL 36322",
    "addr:housenumber":"96",
    "addr:postcode":"36322",
    "addr:street":"State Rte 134",
    "iso:country":"US",
    "sg:address":"96 State Rte 134",
    "sg:city":"Daleville",
    "sg:classifiers":[
        {
            "category":"Restaurant",
            "type":"Food & Drink"
        }
    ],
    "sg:phone":"+1 334 598 1161",
    "sg:postcode":"36322",
    "sg:province":"AL",
    "wof:name":"Myong's Restaurant",
    "wof:placetype":"venue"
},
  "geometry": {"coordinates":[-85.710802,31.307213],"type":"Point"}
}