{
  "type": "Feature",
  "properties": {
    "addr:full":"1573 State Rte 36 Hartselle AL 35640",
    "addr:housenumber":"1573",
    "addr:postcode":"35640",
    "addr:street":"State Rte 36",
    "iso:country":"US",
    "sg:address":"1573 State Rte 36",
    "sg:city":"Hartselle",
    "sg:classifiers":[
        {
            "category":"Shopping",
            "type":"Retail Goods"
        },
        {
            "category":"Retail",
            "subcategory":"Repair Shop",
            "type":"Services"
        }
    ],
    "sg:phone":"+1 256 773 7026",
    "sg:postcode":"35640",
    "sg:province":"AL",
    "sg:tags":[
        "television",
        "cut",
        "radio",
        "merchandise",
        "mfg"
    ],
    "wof:name":"T V Medics",
    "wof:placetype":"venue"
},
  "geometry": {"coordinates":[-86.90790200000001,34.449275],"type":"Point"}
}