{
  "type": "Feature",
  "properties": {
    "iso:country":"US",
    "sg:address":"9 Public Sq E",
    "sg:city":"Jacksonville",
    "sg:classifiers":[
        {
            "category":"Banks & Credit Unions",
            "subcategory":"Bank",
            "type":"Services"
        }
    ],
    "sg:phone":"+1 256 435 0804",
    "sg:postcode":"36265",
    "sg:province":"AL",
    "sg:tags":[
        "loan",
        "real estate"
    ],
    "wof:name":"Jacksonville Mortgage Svc Inc",
    "wof:placetype":"venue"
},
  "geometry": {"coordinates":[-85.761162,33.813548],"type":"Point"}
}