{
  "type": "Feature",
  "properties": {
    "iso:country":"US",
    "sg:address":"267 Metcalf St",
    "sg:city":"Cottonwood",
    "sg:classifiers":[
        {
            "category":"Organizations",
            "subcategory":"Religious Organization",
            "type":"Services"
        }
    ],
    "sg:phone":"+1 334 691 2398",
    "sg:postcode":"36320",
    "sg:province":"AL",
    "wof:name":"Calvary Baptist Church",
    "wof:placetype":"venue"
},
  "geometry": {"coordinates":[-85.309984,31.06469],"type":"Point"}
}