{
  "type": "Feature",
  "properties": {
    "iso:country":"US",
    "sg:address":"108 W Elm St",
    "sg:city":"Athens",
    "sg:classifiers":[
        {
            "category":"Retail",
            "subcategory":"Repair Shop",
            "type":"Services"
        }
    ],
    "sg:phone":"+1 256 232 7111",
    "sg:postcode":"35611",
    "sg:province":"AL",
    "wof:name":"South Television Repair",
    "wof:placetype":"venue"
},
  "geometry": {"coordinates":[-86.969176,34.819523],"type":"Point"}
}