{
  "type": "Feature",
  "properties": {
    "iso:country":"US",
    "sg:address":"1931 Central Pkwy SW",
    "sg:city":"Decatur",
    "sg:classifiers":[
        {
            "category":"Professional",
            "subcategory":"Business Services",
            "type":"Services"
        }
    ],
    "sg:phone":"+1 256 350 1753",
    "sg:postcode":"35601",
    "sg:province":"AL",
    "wof:name":"Classic Designs By Nina",
    "wof:placetype":"venue"
},
  "geometry": {"coordinates":[-86.985513,34.578055],"type":"Point"}
}