{
  "type": "Feature",
  "properties": {
    "addr:full":"1074 Rock Creek Rd Bessemer AL 35023",
    "addr:housenumber":"1074",
    "addr:postcode":"35023",
    "addr:street":"Rock Creek Rd",
    "iso:country":"US",
    "sg:address":"1074 Rock Creek Rd",
    "sg:city":"Bessemer",
    "sg:classifiers":[
        {
            "category":"Building & Trades",
            "subcategory":"Plumbing",
            "type":"Services"
        }
    ],
    "sg:phone":"+1 205 497 3548",
    "sg:postcode":"35023",
    "sg:province":"AL",
    "sg:tags":[
        "contractor"
    ],
    "wof:name":"Artjess Inc",
    "wof:placetype":"venue"
},
  "geometry": {"coordinates":[-87.02917600000001,33.481297],"type":"Point"}
}