{
  "type": "Feature",
  "properties": {
    "iso:country":"US",
    "sg:address":"1209 Central Pkwy SW",
    "sg:city":"Decatur",
    "sg:classifiers":[
        {
            "category":"Wholesale",
            "subcategory":"Chemicals & Plastics",
            "type":"Manufacturing & Wholesale Goods"
        }
    ],
    "sg:phone":"+1 256 355 7822",
    "sg:postcode":"35601",
    "sg:province":"AL",
    "wof:name":"Express Detail & Truck Access",
    "wof:placetype":"venue"
},
  "geometry": {"coordinates":[-86.985962,34.5862],"type":"Point"}
}