{
  "type": "Feature",
  "properties": {
    "addr:full":"486 Co Rd 398 Dutton AL 35744",
    "addr:housenumber":"486;398",
    "addr:postcode":"35744",
    "addr:street":"Co Rd",
    "iso:country":"US",
    "sg:address":"486 Co Rd 398",
    "sg:city":"Dutton",
    "sg:classifiers":[
        {
            "category":"Farming",
            "subcategory":"Poultry Farm",
            "type":"Manufacturing & Wholesale Goods"
        }
    ],
    "sg:phone":"+1 256 657 3059",
    "sg:postcode":"35744",
    "sg:province":"AL",
    "sg:tags":[
        "hatchery"
    ],
    "wof:name":"Gilbert Poultry Farm",
    "wof:placetype":"venue"
},
  "geometry": {"coordinates":[-85.891789,34.601108],"type":"Point"}
}