{
  "type": "Feature",
  "properties": {
    "iso:country":"US",
    "sg:address":"1624 7th Ave W",
    "sg:city":"Birmingham",
    "sg:classifiers":[
        {
            "category":"Personal",
            "type":"Services"
        }
    ],
    "sg:phone":"+1 205 787 1926",
    "sg:postcode":"35208",
    "sg:province":"AL",
    "wof:name":"CK & K Wedding Coordinators",
    "wof:placetype":"venue"
},
  "geometry": {"coordinates":[-86.864796,33.510971],"type":"Point"}
}