{
  "type": "Feature",
  "properties": {
    "iso:country":"US",
    "sg:address":"1044 Valley Dr",
    "sg:city":"Attalla",
    "sg:classifiers":[
        {
            "category":"Organizations",
            "subcategory":"Religious Organization",
            "type":"Services"
        }
    ],
    "sg:phone":"+1 256 538 3130",
    "sg:postcode":"35954",
    "sg:province":"AL",
    "wof:name":"Bethany Bapt Church",
    "wof:placetype":"venue"
},
  "geometry": {"coordinates":[-86.053632,34.052587],"type":"Point"}
}