{
  "type": "Feature",
  "properties": {
    "addr:full":"162 Noel Ave Mobile AL 36607",
    "addr:housenumber":"162",
    "addr:postcode":"36607",
    "addr:street":"Noel Ave",
    "iso:country":"US",
    "sg:address":"162 Noel Ave",
    "sg:city":"Mobile",
    "sg:classifiers":[
        {
            "category":"Building & Trades",
            "subcategory":"Landscaping Services",
            "type":"Services"
        }
    ],
    "sg:phone":"+1 251 209 3593",
    "sg:postcode":"36607",
    "sg:province":"AL",
    "wof:name":"Chadwells Landscape & Irrigat",
    "wof:placetype":"venue"
},
  "geometry": {"coordinates":[-88.123907,30.697594],"type":"Point"}
}