{
  "type": "Feature",
  "properties": {
    "addr:full":"6425 US Hwy 431 Owens Cross Rds AL 35763",
    "addr:housenumber":"6425",
    "addr:postcode":"35763",
    "addr:street":"Us Hwy 431 Owens Cross Rds",
    "iso:country":"US",
    "sg:address":"6425 US Hwy 431",
    "sg:city":"Owens Cross Rds",
    "sg:classifiers":[
        {
            "category":"Retail",
            "subcategory":"Veterinary Services",
            "type":"Services"
        }
    ],
    "sg:phone":"+1 256 533 3385",
    "sg:postcode":"35763",
    "sg:province":"AL",
    "sg:tags":[
        "veterinarian"
    ],
    "wof:name":"Hampton Cove Animal Hospital",
    "wof:placetype":"venue"
},
  "geometry": {"coordinates":[-86.48670199999999,34.665786],"type":"Point"}
}