{
  "type": "Feature",
  "properties": {
    "iso:country":"US",
    "sg:address":"344 Jernigan Rd",
    "sg:city":"Brewton",
    "sg:classifiers":[
        {
            "category":"Travel",
            "subcategory":"Campground",
            "type":"Entertainment"
        }
    ],
    "sg:phone":"+1 251 867 3536",
    "sg:postcode":"36426",
    "sg:province":"AL",
    "sg:tags":[
        "trailer"
    ],
    "wof:name":"Alice's Rv Park",
    "wof:placetype":"venue"
},
  "geometry": {"coordinates":[-87.144216,31.086981],"type":"Point"}
}