{
  "type": "Feature",
  "properties": {
    "iso:country":"US",
    "sg:address":"6715 Old Shell Rd",
    "sg:city":"Mobile",
    "sg:classifiers":[
        {
            "category":"Freight",
            "type":"Transportation"
        }
    ],
    "sg:phone":"+1 251 344 0947",
    "sg:postcode":"36608",
    "sg:province":"AL",
    "sg:tags":[
        "general"
    ],
    "wof:name":"EZ Stor Alls Inc",
    "wof:placetype":"venue"
},
  "geometry": {"coordinates":[-88.197836,30.69072],"type":"Point"}
}