{
  "type": "Feature",
  "properties": {
    "iso:country":"US",
    "sg:address":"521 Pitts St",
    "sg:city":"Auburn",
    "sg:classifiers":[
        {
            "category":"Professional",
            "subcategory":"Secretarial Services",
            "type":"Services"
        }
    ],
    "sg:phone":"+1 334 887 9565",
    "sg:postcode":"36830",
    "sg:province":"AL",
    "sg:tags":[
        "reporting"
    ],
    "wof:name":"Tinicas",
    "wof:placetype":"venue"
},
  "geometry": {"coordinates":[-85.471642,32.613803],"type":"Point"}
}