{
  "type": "Feature",
  "properties": {
    "iso:country":"US",
    "sg:address":"4502 Englewood Rd",
    "sg:city":"Helena",
    "sg:classifiers":[
        {
            "category":"Manufacturing",
            "subcategory":"Printing",
            "type":"Manufacturing & Wholesale Goods"
        }
    ],
    "sg:phone":"+1 205 664 0276",
    "sg:postcode":"35080",
    "sg:province":"AL",
    "sg:tags":[
        "typesetting"
    ],
    "wof:name":"Stacies Typesetting & Graphics",
    "wof:placetype":"venue"
},
  "geometry": {"coordinates":[-86.83846800000001,33.28519],"type":"Point"}
}