{
  "type": "Feature",
  "properties": {
    "addr:full":"1423 Gadsden Hwy Trussville AL 35173",
    "addr:housenumber":"1423",
    "addr:postcode":"35173",
    "addr:street":"Gadsden Hwy",
    "iso:country":"US",
    "sg:address":"1423 Gadsden Hwy",
    "sg:city":"Trussville",
    "sg:classifiers":[
        {
            "category":"Shopping",
            "type":"Retail Goods"
        }
    ],
    "sg:phone":"+1 205 661 1335",
    "sg:postcode":"35173",
    "sg:province":"AL",
    "sg:tags":[
        "merchandise"
    ],
    "wof:name":"T-Mobile USA Inc",
    "wof:placetype":"venue"
},
  "geometry": {"coordinates":[-86.615275,33.617567],"type":"Point"}
}