{
  "type": "Feature",
  "properties": {
    "addr:full":"210 E Main St Albertville AL 35950",
    "addr:housenumber":"210",
    "addr:postcode":"35950",
    "addr:street":"E Main St",
    "iso:country":"US",
    "sg:address":"210 E Main St",
    "sg:city":"Albertville",
    "sg:classifiers":[
        {
            "category":"Shopping",
            "subcategory":"Gifts & Souvenirs",
            "type":"Retail Goods"
        }
    ],
    "sg:phone":"+1 256 878 1730",
    "sg:postcode":"35950",
    "sg:province":"AL",
    "wof:name":"Southern Lights Candle Factory",
    "wof:placetype":"venue"
},
  "geometry": {"coordinates":[-86.20714,34.267171],"type":"Point"}
}