{
  "type": "Feature",
  "properties": {
    "iso:country":"US",
    "sg:address":"1410 Gilmer Ave",
    "sg:city":"Tallassee",
    "sg:classifiers":[
        {
            "category":"Restaurant",
            "type":"Food & Drink"
        }
    ],
    "sg:phone":"+1 334 283 3062",
    "sg:postcode":"36078",
    "sg:province":"AL",
    "wof:name":"KFC",
    "wof:placetype":"venue"
},
  "geometry": {"coordinates":[-85.917,32.550472],"type":"Point"}
}