{
  "type": "Feature",
  "properties": {
    "iso:country":"US",
    "sg:address":"1219 N Main Ave",
    "sg:city":"Sylacauga",
    "sg:classifiers":[
        {
            "category":"Manufacturing",
            "subcategory":"Printing",
            "type":"Manufacturing & Wholesale Goods"
        }
    ],
    "sg:phone":"+1 256 245 9201",
    "sg:postcode":"35150",
    "sg:province":"AL",
    "sg:tags":[
        "screen"
    ],
    "wof:name":"21st Century Signs",
    "wof:placetype":"venue"
},
  "geometry": {"coordinates":[-86.247272,33.183616],"type":"Point"}
}