{
  "type": "Feature",
  "properties": {
    "addr:full":"2700 Snow Rd N Semmes AL 36575",
    "addr:housenumber":"2700",
    "addr:postcode":"36575",
    "addr:street":"Snow Rd N",
    "iso:country":"US",
    "sg:address":"2700 Snow Rd N",
    "sg:city":"Semmes",
    "sg:classifiers":[
        {
            "category":"Home & Garden",
            "subcategory":"Garden Supply",
            "type":"Retail Goods"
        }
    ],
    "sg:phone":"+1 251 649 0104",
    "sg:postcode":"36575",
    "sg:province":"AL",
    "sg:tags":[
        "nurseryman"
    ],
    "sg:website":"www.martinsnursery.com",
    "wof:name":"Martin's Nursery",
    "wof:placetype":"venue"
},
  "geometry": {"coordinates":[-88.276444,30.74477],"type":"Point"}
}