{
  "type": "Feature",
  "properties": {
    "iso:country":"US",
    "sg:address":"1705 State Rte 165",
    "sg:city":"Pittsview",
    "sg:classifiers":[
        {
            "category":"Shopping",
            "subcategory":"Bicycles & Sporting Goods",
            "type":"Retail Goods"
        }
    ],
    "sg:phone":"+1 334 855 4945",
    "sg:postcode":"36871",
    "sg:province":"AL",
    "sg:tags":[
        "convenient",
        "store"
    ],
    "wof:name":"Bluff Creek Bait & Tackle",
    "wof:placetype":"venue"
},
  "geometry": {"coordinates":[-85.034692,32.196563],"type":"Point"}
}