{
  "type": "Feature",
  "properties": {
    "iso:country":"US",
    "sg:address":"50 Fowler St",
    "sg:city":"Montgomery",
    "sg:classifiers":[
        {
            "category":"Retail",
            "subcategory":"Auto Repair",
            "type":"Services"
        }
    ],
    "sg:phone":"+1 334 263 6625",
    "sg:postcode":"36104",
    "sg:province":"AL",
    "sg:tags":[
        "truck"
    ],
    "wof:name":"Southern States Truck Tire",
    "wof:placetype":"venue"
},
  "geometry": {"coordinates":[-86.310601,32.39778],"type":"Point"}
}