{
  "type": "Feature",
  "properties": {
    "addr:full":"1605 Ross Clark Cir Dothan AL 36301",
    "addr:housenumber":"1605",
    "addr:postcode":"36301",
    "addr:street":"Ross Clark Cir",
    "iso:country":"US",
    "sg:address":"1605 Ross Clark Cir",
    "sg:city":"Dothan",
    "sg:classifiers":[
        {
            "category":"Banks & Credit Unions",
            "subcategory":"Financial Services",
            "type":"Services"
        },
        {
            "category":"Insurance",
            "subcategory":"Health Insurance",
            "type":"Services"
        }
    ],
    "sg:phone":"+1 334 677 0475",
    "sg:postcode":"36301",
    "sg:province":"AL",
    "sg:tags":[
        "sharing",
        "profit",
        "annuity",
        "benefit",
        "retirement",
        "plan",
        "employee",
        "pension"
    ],
    "sg:website":"http://www.medicaid.alabama.gov",
    "wof:name":"Food Stamps",
    "wof:placetype":"venue"
},
  "geometry": {"coordinates":[-85.37326,31.196166],"type":"Point"}
}