{
  "type": "Feature",
  "properties": {
    "iso:country":"US",
    "sg:address":"1159 S Broad St",
    "sg:city":"Mobile",
    "sg:classifiers":[
        {
            "category":"Wholesale",
            "subcategory":"Auto Parts",
            "type":"Manufacturing & Wholesale Goods"
        }
    ],
    "sg:phone":"+1 251 433 3696",
    "sg:postcode":"36603",
    "sg:province":"AL",
    "sg:tags":[
        "automobile",
        "supply"
    ],
    "wof:name":"Clutch & Powertrain",
    "wof:placetype":"venue"
},
  "geometry": {"coordinates":[-88.05653599999999,30.663975],"type":"Point"}
}