{
  "type": "Feature",
  "properties": {
    "iso:country":"US",
    "sg:address":"5575 US Hwy 431",
    "sg:city":"Opelika",
    "sg:classifiers":[
        {
            "category":"Retail",
            "subcategory":"Repair Shop",
            "type":"Services"
        }
    ],
    "sg:phone":"+1 334 749 6539",
    "sg:postcode":"36801",
    "sg:province":"AL",
    "sg:tags":[
        "truck"
    ],
    "wof:name":"Big Trucks Repair Svc",
    "wof:placetype":"venue"
},
  "geometry": {"coordinates":[-85.382251,32.719102],"type":"Point"}
}