{
  "type": "Feature",
  "properties": {
    "addr:full":"2614 Artie St SW Huntsville AL 35805",
    "addr:postcode":"2614;35805",
    "addr:street":"Artie St Sw",
    "iso:country":"US",
    "sg:address":"2614 Artie St SW",
    "sg:city":"Huntsville",
    "sg:classifiers":[
        {
            "category":"Insurance",
            "subcategory":"Insurance Agent",
            "type":"Services"
        }
    ],
    "sg:phone":"+1 256 533 1940",
    "sg:postcode":"35805",
    "sg:province":"AL",
    "wof:name":"Colonial Supplemental Ins",
    "wof:placetype":"venue"
},
  "geometry": {"coordinates":[-86.59291,34.708871],"type":"Point"}
}