{
  "type": "Feature",
  "properties": {
    "iso:country":"US",
    "sg:address":"420 20th St N",
    "sg:city":"Birmingham",
    "sg:classifiers":[
        {
            "category":"Professional",
            "subcategory":"Accounting & Tax Preparation",
            "type":"Services"
        }
    ],
    "sg:phone":"+1 205 252 8600",
    "sg:postcode":"35203",
    "sg:province":"AL",
    "wof:name":"Arthur Andersen LLP",
    "wof:placetype":"venue"
},
  "geometry": {"coordinates":[-86.80775199999999,33.517424],"type":"Point"}
}