{
  "type": "Feature",
  "properties": {
    "iso:country":"US",
    "sg:address":"14900 Co Rd 3",
    "sg:city":"Fairhope",
    "sg:classifiers":[
        {
            "category":"Manufacturing",
            "subcategory":"Signs",
            "type":"Manufacturing & Wholesale Goods"
        }
    ],
    "sg:phone":"+1 251 928 7897",
    "sg:postcode":"36532",
    "sg:province":"AL",
    "sg:tags":[
        "specialty",
        "business",
        "mfg"
    ],
    "wof:name":"Moore Sign Design",
    "wof:placetype":"venue"
},
  "geometry": {"coordinates":[-87.898842,30.443943],"type":"Point"}
}