{
  "type": "Feature",
  "properties": {
    "iso:country":"US",
    "sg:address":"3902 Pepperell Pkwy",
    "sg:city":"Opelika",
    "sg:classifiers":[
        {
            "category":"Food & Beverages",
            "subcategory":"Groceries & Convenience Stores",
            "type":"Retail Goods"
        }
    ],
    "sg:phone":"+1 334 745 7457",
    "sg:postcode":"36801",
    "sg:province":"AL",
    "wof:name":"Cowboys Food Mart",
    "wof:placetype":"venue"
},
  "geometry": {"coordinates":[-85.437574,32.630203],"type":"Point"}
}