{
  "type": "Feature",
  "properties": {
    "iso:country":"US",
    "sg:address":"1800 Wilmer Ave",
    "sg:city":"Anniston",
    "sg:classifiers":[
        {
            "category":"Wholesale",
            "subcategory":"Painting Supplies",
            "type":"Manufacturing & Wholesale Goods"
        }
    ],
    "sg:phone":"+1 256 236 5601",
    "sg:postcode":"36201",
    "sg:province":"AL",
    "sg:tags":[
        "floor"
    ],
    "wof:name":"Triplett Paint & Dctg Ctr",
    "wof:placetype":"venue"
},
  "geometry": {"coordinates":[-85.828491,33.669008],"type":"Point"}
}