{
  "type": "Feature",
  "properties": {
    "addr:full":"103 Creed Rd Ashland AL 36251",
    "addr:housenumber":"103",
    "addr:postcode":"36251",
    "addr:street":"Creed Rd",
    "iso:country":"US",
    "sg:address":"103 Creed Rd",
    "sg:city":"Ashland",
    "sg:classifiers":[
        {
            "category":"Home & Garden",
            "subcategory":"Furniture",
            "type":"Retail Goods"
        }
    ],
    "sg:phone":"+1 256 354 3221",
    "sg:postcode":"36251",
    "sg:province":"AL",
    "sg:tags":[
        "repair"
    ],
    "wof:name":"Williams Fred Uphl & Intr Des",
    "wof:placetype":"venue"
},
  "geometry": {"coordinates":[-85.88525799999999,33.29749],"type":"Point"}
}