{
  "type": "Feature",
  "properties": {
    "addr:full":"2539 Eddins Rd Dothan AL 36301",
    "addr:housenumber":"2539",
    "addr:postcode":"36301",
    "addr:street":"Eddins Rd",
    "iso:country":"US",
    "sg:address":"2539 Eddins Rd",
    "sg:city":"Dothan",
    "sg:classifiers":[
        {
            "category":"Building & Trades",
            "subcategory":"Construction",
            "type":"Services"
        }
    ],
    "sg:phone":"+1 334 673 3518",
    "sg:postcode":"36301",
    "sg:province":"AL",
    "sg:tags":[
        "house"
    ],
    "wof:name":"Southern Home Builders LLC",
    "wof:placetype":"venue"
},
  "geometry": {"coordinates":[-85.34334800000001,31.162094],"type":"Point"}
}