{
  "type": "Feature",
  "properties": {
    "addr:full":"9067 Co Rd 64 Daphne AL 36526",
    "addr:housenumber":"9067;64",
    "addr:postcode":"36526",
    "addr:street":"Co Rd",
    "iso:country":"US",
    "sg:address":"9067 Co Rd 64",
    "sg:city":"Daphne",
    "sg:classifiers":[
        {
            "category":"Organizations",
            "subcategory":"Religious Organization",
            "type":"Services"
        }
    ],
    "sg:phone":"+1 251 626 2620",
    "sg:postcode":"36526",
    "sg:province":"AL",
    "sg:tags":[
        "church"
    ],
    "wof:name":"Belforest Church God In Chrst",
    "wof:placetype":"venue"
},
  "geometry": {"coordinates":[-87.866285,30.60391],"type":"Point"}
}