{
  "type": "Feature",
  "properties": {
    "iso:country":"US",
    "sg:address":"900 S Quintard Ave",
    "sg:city":"Oxford",
    "sg:classifiers":[
        {
            "category":"Shopping",
            "subcategory":"Shoes",
            "type":"Retail Goods"
        }
    ],
    "sg:phone":"+1 256 235 3765",
    "sg:postcode":"36203",
    "sg:province":"AL",
    "wof:name":"Martins 5",
    "wof:placetype":"venue"
},
  "geometry": {"coordinates":[-85.827565,33.611994],"type":"Point"}
}