{
  "type": "Feature",
  "properties": {
    "addr:full":"619 9th Ave N Bessemer AL 35020",
    "addr:housenumber":"619",
    "addr:postcode":"35020",
    "addr:street":"9Th Ave N",
    "iso:country":"US",
    "sg:address":"619 9th Ave N",
    "sg:city":"Bessemer",
    "sg:classifiers":[
        {
            "category":"Shopping",
            "subcategory":"Pharmacy",
            "type":"Retail Goods"
        }
    ],
    "sg:phone":"+1 205 425 3039",
    "sg:postcode":"35020",
    "sg:province":"AL",
    "sg:tags":[
        "drug",
        "store"
    ],
    "wof:name":"Medicine Shoppe The",
    "wof:placetype":"venue"
},
  "geometry": {"coordinates":[-86.97207899999999,33.393216],"type":"Point"}
}