{
  "type": "Feature",
  "properties": {
    "addr:full":"1613 Prairie Ave Mobile AL 36605",
    "addr:housenumber":"1613",
    "addr:postcode":"36605",
    "addr:street":"Prairie Ave",
    "iso:country":"US",
    "sg:address":"1613 Prairie Ave",
    "sg:city":"Mobile",
    "sg:classifiers":[
        {
            "category":"Retail",
            "subcategory":"Auto Repair",
            "type":"Services"
        }
    ],
    "sg:phone":"+1 251 476 2995",
    "sg:postcode":"36605",
    "sg:province":"AL",
    "sg:tags":[
        "mobile",
        "home",
        "transport"
    ],
    "wof:name":"Atlas Mobile Home Service",
    "wof:placetype":"venue"
},
  "geometry": {"coordinates":[-88.082815,30.655352],"type":"Point"}
}