{
  "type": "Feature",
  "properties": {
    "iso:country":"US",
    "sg:address":"809 Crawford Rd",
    "sg:city":"Opelika",
    "sg:classifiers":[
        {
            "category":"Manufacturing",
            "subcategory":"Signs",
            "type":"Manufacturing & Wholesale Goods"
        }
    ],
    "sg:phone":"+1 334 704 0361",
    "sg:postcode":"36804",
    "sg:province":"AL",
    "wof:name":"A & O Signs",
    "wof:placetype":"venue"
},
  "geometry": {"coordinates":[-85.361853,32.616157],"type":"Point"}
}