{
  "type": "Feature",
  "properties": {
    "addr:full":"1900 20th Ave S Homewood AL 35209",
    "addr:housenumber":"1900",
    "addr:postcode":"35209",
    "addr:street":"20Th Ave S Homewood",
    "iso:country":"US",
    "sg:address":"1900 20th Ave S",
    "sg:city":"Homewood",
    "sg:classifiers":[
        {
            "category":"Real Estate",
            "subcategory":"Real Estate Agent",
            "type":"Services"
        }
    ],
    "sg:phone":"+1 205 933 0300",
    "sg:postcode":"35209",
    "sg:province":"AL",
    "wof:name":"Leader Realty Co",
    "wof:placetype":"venue"
},
  "geometry": {"coordinates":[-86.791011,33.490749],"type":"Point"}
}