{
  "type": "Feature",
  "properties": {
    "iso:country":"US",
    "sg:address":"724 N Walnut Ave",
    "sg:city":"Demopolis",
    "sg:classifiers":[
        {
            "category":"Personal",
            "subcategory":"Beauty Salon",
            "type":"Services"
        }
    ],
    "sg:phone":"+1 334 289 1942",
    "sg:postcode":"36732",
    "sg:province":"AL",
    "sg:tags":[
        "shop"
    ],
    "wof:name":"Designer S Hair",
    "wof:placetype":"venue"
},
  "geometry": {"coordinates":[-87.837572,32.522997],"type":"Point"}
}