{
  "type": "Feature",
  "properties": {
    "iso:country":"US",
    "sg:address":"24982 US Hwy 31",
    "sg:city":"Jemison",
    "sg:classifiers":[
        {
            "category":"Health Services",
            "subcategory":"Chiropractor",
            "type":"Services"
        },
        {
            "category":"Professional",
            "type":"Services"
        }
    ],
    "sg:phone":"+1 205 688 3303",
    "sg:postcode":"35085",
    "sg:province":"AL",
    "wof:name":"Jemison Family Chiropractic",
    "wof:placetype":"venue"
},
  "geometry": {"coordinates":[-86.745532,32.962266],"type":"Point"}
}