{
  "type": "Feature",
  "properties": {
    "addr:full":"195 S Foster St Dothan AL 36301",
    "addr:housenumber":"195",
    "addr:postcode":"36301",
    "addr:street":"S Foster St",
    "iso:country":"US",
    "sg:address":"195 S Foster St",
    "sg:city":"Dothan",
    "sg:classifiers":[
        {
            "category":"Home & Garden",
            "subcategory":"Hardware",
            "type":"Retail Goods"
        }
    ],
    "sg:phone":"+1 334 792 7812",
    "sg:postcode":"36301",
    "sg:province":"AL",
    "wof:name":"T R Frith Seed & Hardware",
    "wof:placetype":"venue"
},
  "geometry": {"coordinates":[-85.39189500000001,31.222758],"type":"Point"}
}