{
  "type": "Feature",
  "properties": {
    "iso:country":"US",
    "sg:address":"311 Columbus St E",
    "sg:city":"Fayette",
    "sg:classifiers":[
        {
            "category":"Home & Garden",
            "subcategory":"Furniture",
            "type":"Retail Goods"
        }
    ],
    "sg:phone":"+1 205 932 4233",
    "sg:postcode":"35555",
    "sg:province":"AL",
    "wof:name":"Furniture Depot",
    "wof:placetype":"venue"
},
  "geometry": {"coordinates":[-87.82864,33.68458],"type":"Point"}
}