{
  "type": "Feature",
  "properties": {
    "iso:country":"US",
    "sg:address":"1415 Hillyer Robinson Pkwy",
    "sg:city":"Anniston",
    "sg:classifiers":[
        {
            "category":"Government",
            "subcategory":"Office",
            "type":"Public Place"
        }
    ],
    "sg:phone":"+1 256 831 3067",
    "sg:postcode":"36207",
    "sg:province":"AL",
    "sg:tags":[
        "federal",
        "planning",
        "dev"
    ],
    "wof:name":"USDA Rural Development",
    "wof:placetype":"venue"
},
  "geometry": {"coordinates":[-85.808922,33.629641],"type":"Point"}
}