{
  "type": "Feature",
  "properties": {
    "iso:country":"US",
    "sg:address":"22 Co Rd 892",
    "sg:city":"Valley",
    "sg:classifiers":[
        {
            "category":"Professional",
            "type":"Services"
        }
    ],
    "sg:phone":"+1 334 741 0953",
    "sg:postcode":"36854",
    "sg:province":"AL",
    "wof:name":"Netsigns",
    "wof:placetype":"venue"
},
  "geometry": {"coordinates":[-85.176859,32.687732],"type":"Point"}
}