{
  "type": "Feature",
  "properties": {
    "iso:country":"US",
    "sg:address":"113 McDermotts Way",
    "sg:city":"Madison",
    "sg:classifiers":[
        {
            "category":"Health Services",
            "subcategory":"Health Practitioner",
            "type":"Services"
        }
    ],
    "sg:phone":"+1 256 721 9308",
    "sg:postcode":"35758",
    "sg:province":"AL",
    "sg:tags":[
        "dental",
        "hygienist"
    ],
    "wof:name":"Deborah J Patterson",
    "wof:placetype":"venue"
},
  "geometry": {"coordinates":[-86.756452,34.725462],"type":"Point"}
}