{
  "type": "Feature",
  "properties": {
    "addr:full":"1246 Greystone Crst Birmingham AL 35242",
    "addr:housenumber":"1246",
    "addr:postcode":"35242",
    "addr:street":"Greystone Crst",
    "iso:country":"US",
    "sg:address":"1246 Greystone Crst",
    "sg:city":"Birmingham",
    "sg:classifiers":[
        {
            "category":"Building & Trades",
            "subcategory":"Construction",
            "type":"Services"
        }
    ],
    "sg:phone":"+1 205 991 5464",
    "sg:postcode":"35242",
    "sg:province":"AL",
    "sg:tags":[
        "residential",
        "commercial",
        "contractor"
    ],
    "wof:name":"Steve Shirley General Contr",
    "wof:placetype":"venue"
},
  "geometry": {"coordinates":[-86.634685,33.43262],"type":"Point"}
}