{
  "type": "Feature",
  "properties": {
    "addr:full":"4823 Overlook Rd Mobile AL 36618",
    "addr:housenumber":"4823",
    "addr:postcode":"36618",
    "addr:street":"Overlook Rd",
    "iso:country":"US",
    "sg:address":"4823 Overlook Rd",
    "sg:city":"Mobile",
    "sg:classifiers":[
        {
            "category":"Banks & Credit Unions",
            "subcategory":"Bank",
            "type":"Services"
        }
    ],
    "sg:phone":"+1 251 470 7520",
    "sg:postcode":"36618",
    "sg:province":"AL",
    "wof:name":"Compass Bank",
    "wof:placetype":"venue"
},
  "geometry": {"coordinates":[-88.156924,30.719666],"type":"Point"}
}