{
  "type": "Feature",
  "properties": {
    "addr:full":"6996 Heather Ln Pinson AL 35126",
    "addr:housenumber":"6996",
    "addr:postcode":"35126",
    "addr:street":"Heather Ln",
    "iso:country":"US",
    "sg:address":"6996 Heather Ln",
    "sg:city":"Pinson",
    "sg:classifiers":[
        {
            "category":"Professional",
            "subcategory":"Business Services",
            "type":"Services"
        }
    ],
    "sg:phone":"+1 205 680 6070",
    "sg:postcode":"35126",
    "sg:province":"AL",
    "wof:name":"Air Bags Express",
    "wof:placetype":"venue"
},
  "geometry": {"coordinates":[-86.64393699999999,33.706619],"type":"Point"}
}