{
  "type": "Feature",
  "properties": {
    "iso:country":"US",
    "sg:address":"2200 Briarwood Way",
    "sg:city":"Birmingham",
    "sg:classifiers":[
        {
            "category":"Professional",
            "type":"Services"
        }
    ],
    "sg:phone":"+1 205 776 5349",
    "sg:postcode":"35243",
    "sg:province":"AL",
    "sg:tags":[
        "establishment"
    ],
    "wof:name":"Carolyn House",
    "wof:placetype":"venue"
},
  "geometry": {"coordinates":[-86.760133,33.41534],"type":"Point"}
}