{
  "type": "Feature",
  "properties": {
    "addr:full":"6449 Moffett Rd Mobile AL 36618",
    "addr:housenumber":"6449",
    "addr:postcode":"36618",
    "addr:street":"Moffett Rd",
    "iso:country":"US",
    "sg:address":"6449 Moffett Rd",
    "sg:city":"Mobile",
    "sg:classifiers":[
        {
            "category":"Government",
            "subcategory":"Police Station",
            "type":"Public Place"
        }
    ],
    "sg:phone":"+1 251 574 6298",
    "sg:postcode":"36618",
    "sg:province":"AL",
    "sg:tags":[
        "sheriff"
    ],
    "wof:name":"Mobile County Sheriff Training",
    "wof:placetype":"venue"
},
  "geometry": {"coordinates":[-88.193304,30.750592],"type":"Point"}
}