{
  "type": "Feature",
  "properties": {
    "iso:country":"US",
    "sg:address":"2098 Co Rd 55",
    "sg:city":"Hartselle",
    "sg:classifiers":[
        {
            "category":"Wholesale",
            "subcategory":"Meat",
            "type":"Manufacturing & Wholesale Goods"
        }
    ],
    "sg:phone":"+1 256 462 1034",
    "sg:postcode":"35640",
    "sg:province":"AL",
    "wof:name":"Weaver Meat Processing",
    "wof:placetype":"venue"
},
  "geometry": {"coordinates":[-86.997663,34.370582],"type":"Point"}
}