{
  "type": "Feature",
  "properties": {
    "iso:country":"US",
    "sg:address":"102 Francis Ave",
    "sg:city":"Muscle Shoals",
    "sg:classifiers":[
        {
            "category":"Retail",
            "subcategory":"Auto Repair",
            "type":"Services"
        }
    ],
    "sg:phone":"+1 256 386 0085",
    "sg:postcode":"35661",
    "sg:province":"AL",
    "sg:tags":[
        "repairing",
        "automobile"
    ],
    "wof:name":"Central Bug & Buggy Shop",
    "wof:placetype":"venue"
},
  "geometry": {"coordinates":[-87.631216,34.748899],"type":"Point"}
}