{
  "type": "Feature",
  "properties": {
    "iso:country":"US",
    "sg:address":"686 Dover Rd",
    "sg:city":"Kinsey",
    "sg:classifiers":[
        {
            "category":"Shopping",
            "type":"Retail Goods"
        }
    ],
    "sg:phone":"+1 334 702 0010",
    "sg:postcode":"36303",
    "sg:province":"AL",
    "sg:tags":[
        "awning",
        "canopy"
    ],
    "wof:name":"Awniings & More",
    "wof:placetype":"venue"
},
  "geometry": {"coordinates":[-85.328239,31.3022],"type":"Point"}
}