{
  "type": "Feature",
  "properties": {
    "iso:country":"US",
    "sg:address":"4061 Independence Dr NW",
    "sg:city":"Huntsville",
    "sg:classifiers":[
        {
            "category":"Restaurant",
            "type":"Food & Drink"
        }
    ],
    "sg:phone":"+1 256 830 1700",
    "sg:postcode":"35816",
    "sg:province":"AL",
    "sg:tags":[
        "eating"
    ],
    "wof:name":"Mikato Japanese Steak House",
    "wof:placetype":"venue"
},
  "geometry": {"coordinates":[-86.630249,34.73648],"type":"Point"}
}