{
  "type": "Feature",
  "properties": {
    "iso:country":"US",
    "sg:address":"428 Palisades Blvd",
    "sg:city":"Birmingham",
    "sg:classifiers":[
        {
            "category":"Restaurant",
            "type":"Food & Drink"
        }
    ],
    "sg:menulink":"http://www.allmenus.com/al/birmingham/56176-cicis-pizza-buffet/menu/",
    "sg:phone":"+1 205 870 0005",
    "sg:postcode":"35209",
    "sg:province":"AL",
    "sg:tags":[
        "american",
        "pizza"
    ],
    "wof:name":"CiCi's Pizza Buffet",
    "wof:placetype":"venue"
},
  "geometry": {"coordinates":[-86.819141,33.46861],"type":"Point"}
}