{
  "type": "Feature",
  "properties": {
    "iso:country":"US",
    "sg:address":"121 Stevens Hill Cir",
    "sg:city":"Birmingham",
    "sg:classifiers":[
        {
            "category":"Professional",
            "subcategory":"Management & Consulting",
            "type":"Services"
        }
    ],
    "sg:phone":"+1 205 980 4811",
    "sg:postcode":"35244",
    "sg:province":"AL",
    "wof:name":"Mark C Rogers",
    "wof:placetype":"venue"
},
  "geometry": {"coordinates":[-86.748507,33.385351],"type":"Point"}
}