{
  "type": "Feature",
  "properties": {
    "addr:full":"275 6th Ave Ashville AL 35953",
    "addr:housenumber":"275",
    "addr:postcode":"35953",
    "addr:street":"6Th Ave",
    "iso:country":"US",
    "sg:address":"275 6th Ave",
    "sg:city":"Ashville",
    "sg:classifiers":[
        {
            "category":"Manufacturing",
            "subcategory":"Tools & Machinery",
            "type":"Manufacturing & Wholesale Goods"
        }
    ],
    "sg:phone":"+1 205 594 4131",
    "sg:postcode":"35953",
    "sg:province":"AL",
    "sg:tags":[
        "farm",
        "equipment"
    ],
    "wof:name":"Fouts Tractor Co",
    "wof:placetype":"venue"
},
  "geometry": {"coordinates":[-86.250795,33.836413],"type":"Point"}
}