{
  "type": "Feature",
  "properties": {
    "iso:country":"US",
    "sg:address":"1718 Quintard Ave",
    "sg:city":"Anniston",
    "sg:classifiers":[
        {
            "category":"Building & Trades",
            "subcategory":"Equipment Rental",
            "type":"Services"
        }
    ],
    "sg:phone":"+1 256 237 8101",
    "sg:postcode":"36201",
    "sg:province":"AL",
    "wof:name":"Rent-A-Center",
    "wof:placetype":"venue"
},
  "geometry": {"coordinates":[-85.826928,33.667474],"type":"Point"}
}