{
  "type": "Feature",
  "properties": {
    "iso:country":"US",
    "sg:address":"209 Oakwood Ave NW",
    "sg:city":"Huntsville",
    "sg:classifiers":[
        {
            "category":"Building & Trades",
            "subcategory":"Landscaping Services",
            "type":"Services"
        }
    ],
    "sg:phone":"+1 256 534 9794",
    "sg:postcode":"35811",
    "sg:province":"AL",
    "wof:name":"Awesome Cutt Lawn Maintenance",
    "wof:placetype":"venue"
},
  "geometry": {"coordinates":[-86.585454,34.749124],"type":"Point"}
}