{
  "type": "Feature",
  "properties": {
    "addr:full":"357 Lucerne Blvd Birmingham AL 35209",
    "addr:housenumber":"357",
    "addr:postcode":"35209",
    "addr:street":"Lucerne Blvd",
    "iso:country":"US",
    "sg:address":"357 Lucerne Blvd",
    "sg:city":"Birmingham",
    "sg:classifiers":[
        {
            "category":"Professional",
            "subcategory":"Management & Consulting",
            "type":"Services"
        }
    ],
    "sg:phone":"+1 205 414 0064",
    "sg:postcode":"35209",
    "sg:province":"AL",
    "sg:tags":[
        "business"
    ],
    "wof:name":"Shades Valley Forestry Inc",
    "wof:placetype":"venue"
},
  "geometry": {"coordinates":[-86.803355,33.46061],"type":"Point"}
}