{
  "type": "Feature",
  "properties": {
    "iso:country":"US",
    "sg:address":"608 40th St S",
    "sg:city":"Birmingham",
    "sg:classifiers":[
        {
            "category":"Shopping",
            "subcategory":"Clothing, Apparel, & Fashions",
            "type":"Retail Goods"
        }
    ],
    "sg:phone":"+1 205 595 7382",
    "sg:postcode":"35222",
    "sg:province":"AL",
    "wof:name":"Cory Amos & Associates",
    "wof:placetype":"venue"
},
  "geometry": {"coordinates":[-86.77258,33.518906],"type":"Point"}
}