{
  "type": "Feature",
  "properties": {
    "iso:country":"US",
    "sg:address":"2030 Country Ridge Pl",
    "sg:city":"Birmingham",
    "sg:classifiers":[
        {
            "category":"Professional",
            "subcategory":"Management & Consulting",
            "type":"Services"
        }
    ],
    "sg:phone":"+1 205 967 0464",
    "sg:postcode":"35243",
    "sg:province":"AL",
    "wof:name":"John R Durant",
    "wof:placetype":"venue"
},
  "geometry": {"coordinates":[-86.762359,33.434738],"type":"Point"}
}