{
  "type": "Feature",
  "properties": {
    "addr:full":"311 Panoramic Trl Warrior AL 35180",
    "addr:housenumber":"311",
    "addr:postcode":"35180",
    "addr:street":"Panoramic Trl",
    "iso:country":"US",
    "sg:address":"311 Panoramic Trl",
    "sg:city":"Warrior",
    "sg:classifiers":[
        {
            "category":"Wholesale",
            "subcategory":"Furniture",
            "type":"Manufacturing & Wholesale Goods"
        }
    ],
    "sg:phone":"+1 205 647 1148",
    "sg:postcode":"35180",
    "sg:province":"AL",
    "sg:tags":[
        "durable"
    ],
    "wof:name":"Security Services America LLC",
    "wof:placetype":"venue"
},
  "geometry": {"coordinates":[-86.780422,33.858046],"type":"Point"}
}