{
  "type": "Feature",
  "properties": {
    "addr:full":"517 Cahaba Park Cir Birmingham AL 35242",
    "addr:housenumber":"517",
    "addr:postcode":"35242",
    "addr:street":"Cahaba Park Cir",
    "iso:country":"US",
    "sg:address":"517 Cahaba Park Cir",
    "sg:city":"Birmingham",
    "sg:classifiers":[
        {
            "category":"Restaurant",
            "type":"Food & Drink"
        }
    ],
    "sg:menulink":"http://www.allmenus.com/al/chelsea/166776-burger-king/menu/",
    "sg:phone":"+1 205 995 1241",
    "sg:postcode":"35242",
    "sg:province":"AL",
    "sg:tags":[
        "burger",
        "american"
    ],
    "wof:name":"Burger King",
    "wof:placetype":"venue"
},
  "geometry": {"coordinates":[-86.706717,33.428873],"type":"Point"}
}