{
  "type": "Feature",
  "properties": {
    "iso:country":"US",
    "sg:address":"9000 US Hwy 78",
    "sg:city":"Heflin",
    "sg:classifiers":[
        {
            "category":"Building & Trades",
            "subcategory":"Construction",
            "type":"Services"
        }
    ],
    "sg:phone":"+1 256 463 5576",
    "sg:postcode":"36264",
    "sg:province":"AL",
    "sg:tags":[
        "home",
        "builder"
    ],
    "wof:name":"Cypress Log Home",
    "wof:placetype":"venue"
},
  "geometry": {"coordinates":[-85.524766,33.68856],"type":"Point"}
}