{
  "type": "Feature",
  "properties": {
    "iso:country":"US",
    "sg:address":"3414 Blue Spring Rd NW",
    "sg:city":"Huntsville",
    "sg:classifiers":[
        {
            "category":"Professional",
            "type":"Services"
        }
    ],
    "sg:phone":"+1 256 859 0850",
    "sg:postcode":"35810",
    "sg:province":"AL",
    "wof:name":"Elite Images",
    "wof:placetype":"venue"
},
  "geometry": {"coordinates":[-86.598973,34.767029],"type":"Point"}
}