{
  "type": "Feature",
  "properties": {
    "iso:country":"US",
    "sg:address":"161 Tidwell Rd",
    "sg:city":"Winfield",
    "sg:classifiers":[
        {
            "category":"Building & Trades",
            "subcategory":"Construction",
            "type":"Services"
        }
    ],
    "sg:phone":"+1 205 412 0596",
    "sg:postcode":"35594",
    "sg:province":"AL",
    "sg:tags":[
        "fence",
        "contractor"
    ],
    "wof:name":"Crumpton Fence Co",
    "wof:placetype":"venue"
},
  "geometry": {"coordinates":[-87.754522,33.850138],"type":"Point"}
}