{
  "type": "Feature",
  "properties": {
    "iso:country":"US",
    "sg:address":"112 Colby Dr NE",
    "sg:city":"Huntsville",
    "sg:classifiers":[
        {
            "category":"Building & Trades",
            "subcategory":"Landscaping Services",
            "type":"Services"
        }
    ],
    "sg:phone":"+1 256 326 9095",
    "sg:postcode":"35810",
    "sg:province":"AL",
    "wof:name":"Affordable Tree Care",
    "wof:placetype":"venue"
},
  "geometry": {"coordinates":[-86.54829599999999,34.824534],"type":"Point"}
}