{
  "type": "Feature",
  "properties": {
    "iso:country":"US",
    "sg:address":"4656 US Hwy 231",
    "sg:city":"Wetumpka",
    "sg:classifiers":[
        {
            "category":"Utilities",
            "subcategory":"Mobile Phone",
            "type":"Services"
        }
    ],
    "sg:phone":"+1 334 567 3431",
    "sg:postcode":"36092",
    "sg:province":"AL",
    "sg:tags":[
        "communication",
        "radiotelephone"
    ],
    "wof:name":"Alltel",
    "wof:placetype":"venue"
},
  "geometry": {"coordinates":[-86.213579,32.510637],"type":"Point"}
}