{
  "type": "Feature",
  "properties": {
    "addr:full":"1571 S Eufaula Ave Eufaula AL 36027",
    "addr:housenumber":"1571",
    "addr:postcode":"36027",
    "addr:street":"S Eufaula Ave",
    "iso:country":"US",
    "sg:address":"1571 S Eufaula Ave",
    "sg:city":"Eufaula",
    "sg:classifiers":[
        {
            "category":"Shopping",
            "subcategory":"Pharmacy",
            "type":"Retail Goods"
        }
    ],
    "sg:phone":"+1 334 687 0602",
    "sg:postcode":"36027",
    "sg:province":"AL",
    "wof:name":"Rite Aid",
    "wof:placetype":"venue"
},
  "geometry": {"coordinates":[-85.15619100000001,31.870956],"type":"Point"}
}