{
  "type": "Feature",
  "properties": {
    "iso:country":"US",
    "sg:address":"1405 Thompson Cir",
    "sg:city":"Gardendale",
    "sg:classifiers":[
        {
            "category":"Wholesale",
            "subcategory":"Stationery",
            "type":"Manufacturing & Wholesale Goods"
        }
    ],
    "sg:phone":"+1 205 631 5604",
    "sg:postcode":"35071",
    "sg:province":"AL",
    "sg:tags":[
        "business",
        "form",
        "system"
    ],
    "wof:name":"Delta Business Systems",
    "wof:placetype":"venue"
},
  "geometry": {"coordinates":[-86.810922,33.659934],"type":"Point"}
}