{
  "type": "Feature",
  "properties": {
    "iso:country":"US",
    "sg:address":"23678 US Hwy 98",
    "sg:city":"Fairhope",
    "sg:classifiers":[
        {
            "category":"Health Services",
            "subcategory":"Doctor",
            "type":"Services"
        }
    ],
    "sg:phone":"+1 251 928 8770",
    "sg:postcode":"36532",
    "sg:province":"AL",
    "sg:tags":[
        "dentist"
    ],
    "sg:website":"www.northcuttdental.com",
    "wof:name":"Northcutt Dental Practice",
    "wof:placetype":"venue"
},
  "geometry": {"coordinates":[-87.895195,30.569919],"type":"Point"}
}