{
  "type": "Feature",
  "properties": {
    "iso:country":"US",
    "sg:address":"2205 9th Ave",
    "sg:city":"Northport",
    "sg:classifiers":[
        {
            "category":"Building & Trades",
            "subcategory":"Construction",
            "type":"Services"
        }
    ],
    "sg:phone":"+1 205 349 8886",
    "sg:postcode":"35476",
    "sg:province":"AL",
    "sg:tags":[
        "home",
        "builder"
    ],
    "wof:name":"Clay Kilgore Construction Inc",
    "wof:placetype":"venue"
},
  "geometry": {"coordinates":[-87.566941,33.230862],"type":"Point"}
}