{
  "type": "Feature",
  "properties": {
    "iso:country":"US",
    "sg:address":"3001 Woodward Ave",
    "sg:city":"Muscle Shoals",
    "sg:classifiers":[
        {
            "category":"Food & Beverages",
            "subcategory":"Groceries & Convenience Stores",
            "type":"Retail Goods"
        }
    ],
    "sg:phone":"+1 256 381 7277",
    "sg:postcode":"35661",
    "sg:province":"AL",
    "sg:tags":[
        "grocer"
    ],
    "wof:name":"Shop Rite",
    "wof:placetype":"venue"
},
  "geometry": {"coordinates":[-87.66788,34.732945],"type":"Point"}
}