{
  "type": "Feature",
  "properties": {
    "addr:full":"312 Arrowhead Dr Enterprise AL 36330",
    "addr:housenumber":"312",
    "addr:postcode":"36330",
    "addr:street":"Arrowhead Dr",
    "iso:country":"US",
    "sg:address":"312 Arrowhead Dr",
    "sg:city":"Enterprise",
    "sg:classifiers":[
        {
            "category":"Personal",
            "type":"Services"
        }
    ],
    "sg:phone":"+1 334 393 2922",
    "sg:postcode":"36330",
    "sg:province":"AL",
    "wof:name":"Hudgens Construction",
    "wof:placetype":"venue"
},
  "geometry": {"coordinates":[-85.859139,31.384558],"type":"Point"}
}