{
  "type": "Feature",
  "properties": {
    "addr:full":"605 37th St S Birmingham AL 35222",
    "addr:housenumber":"605",
    "addr:postcode":"35222",
    "addr:street":"37Th St S",
    "iso:country":"US",
    "sg:address":"605 37th St S",
    "sg:city":"Birmingham",
    "sg:classifiers":[
        {
            "category":"Professional",
            "subcategory":"Management & Consulting",
            "type":"Services"
        }
    ],
    "sg:phone":"+1 205 323 5080",
    "sg:postcode":"35222",
    "sg:province":"AL",
    "sg:tags":[
        "construction"
    ],
    "wof:name":"Jefferson Management LLC",
    "wof:placetype":"venue"
},
  "geometry": {"coordinates":[-86.776701,33.517347],"type":"Point"}
}