{
  "type": "Feature",
  "properties": {
    "addr:full":"3046 Fairwest Pl Montgomery AL 36108",
    "addr:housenumber":"3046",
    "addr:postcode":"36108",
    "addr:street":"Fairwest Pl",
    "iso:country":"US",
    "sg:address":"3046 Fairwest Pl",
    "sg:city":"Montgomery",
    "sg:classifiers":[
        {
            "category":"Government",
            "subcategory":"Police Station",
            "type":"Public Place"
        }
    ],
    "sg:phone":"+1 334 240 4524",
    "sg:postcode":"36108",
    "sg:province":"AL",
    "sg:tags":[
        "protection"
    ],
    "wof:name":"Montgomery Montgomery Police",
    "wof:placetype":"venue"
},
  "geometry": {"coordinates":[-86.336906,32.349256],"type":"Point"}
}