{
  "type": "Feature",
  "properties": {
    "addr:full":"3816 Triana Blvd SW Huntsville AL 35805",
    "addr:housenumber":"3816",
    "addr:postcode":"35805",
    "addr:street":"Triana Blvd Sw",
    "iso:country":"US",
    "sg:address":"3816 Triana Blvd SW",
    "sg:city":"Huntsville",
    "sg:classifiers":[
        {
            "category":"Insurance",
            "subcategory":"Insurance Agent",
            "type":"Services"
        }
    ],
    "sg:phone":"+1 256 880 1720",
    "sg:postcode":"35805",
    "sg:province":"AL",
    "wof:name":"Woody Duncan Insurance",
    "wof:placetype":"venue"
},
  "geometry": {"coordinates":[-86.609522,34.698087],"type":"Point"}
}