{
  "type": "Feature",
  "properties": {
    "iso:country":"US",
    "sg:address":"211 Deerfoot Dr",
    "sg:city":"Madison",
    "sg:classifiers":[
        {
            "category":"Professional",
            "type":"Services"
        }
    ],
    "sg:phone":"+1 256 722 2706",
    "sg:postcode":"35757",
    "sg:province":"AL",
    "wof:name":"David Flaugher",
    "wof:placetype":"venue"
},
  "geometry": {"coordinates":[-86.74229699999999,34.805738],"type":"Point"}
}