{
  "type": "Feature",
  "properties": {
    "iso:country":"US",
    "sg:address":"4109 Riverview Cove",
    "sg:city":"Cahaba Heights",
    "sg:classifiers":[
        {
            "category":"Shopping",
            "subcategory":"Florist",
            "type":"Retail Goods"
        }
    ],
    "sg:phone":"+1 205 967 9759",
    "sg:postcode":"35243",
    "sg:province":"AL",
    "wof:name":"Irene Pate Flowers & Gifts",
    "wof:placetype":"venue"
},
  "geometry": {"coordinates":[-86.723276,33.452764],"type":"Point"}
}