{
  "type": "Feature",
  "properties": {
    "iso:country":"US",
    "sg:address":"3415 Buckboard Rd",
    "sg:city":"Montgomery",
    "sg:classifiers":[
        {
            "category":"Professional",
            "subcategory":"Business Services",
            "type":"Services"
        }
    ],
    "sg:phone":"+1 334 354 0222",
    "sg:postcode":"36116",
    "sg:province":"AL",
    "wof:name":"Charles E Lewis & Associates",
    "wof:placetype":"venue"
},
  "geometry": {"coordinates":[-86.225924,32.330042],"type":"Point"}
}