{
  "type": "Feature",
  "properties": {
    "iso:country":"US",
    "sg:address":"2 N Jackson St",
    "sg:city":"Montgomery",
    "sg:classifiers":[
        {
            "category":"Professional",
            "subcategory":"Management & Consulting",
            "type":"Services"
        }
    ],
    "sg:phone":"+1 334 264 3014",
    "sg:postcode":"36104",
    "sg:province":"AL",
    "sg:tags":[
        "consultant",
        "business"
    ],
    "wof:name":"Regency Worldwide Partners",
    "wof:placetype":"venue"
},
  "geometry": {"coordinates":[-86.296615,32.378214],"type":"Point"}
}