{
  "type": "Feature",
  "properties": {
    "iso:country":"US",
    "sg:address":"27200 Perdido Beach Blvd",
    "sg:city":"Orange Beach",
    "sg:classifiers":[
        {
            "category":"Recreation",
            "type":"Entertainment"
        }
    ],
    "sg:phone":"+1 251 981 8241",
    "sg:postcode":"36561",
    "sg:province":"AL",
    "sg:tags":[
        "charter",
        "boat"
    ],
    "wof:name":"Grampa Woo Excursions",
    "wof:placetype":"venue"
},
  "geometry": {"coordinates":[-87.580817,30.270721],"type":"Point"}
}