{
  "type": "Feature",
  "properties": {
    "addr:full":"3404 6th Ave S Birmingham AL 35222",
    "addr:housenumber":"3404",
    "addr:postcode":"35222",
    "addr:street":"6Th Ave S",
    "iso:country":"US",
    "sg:address":"3404 6th Ave S",
    "sg:city":"Birmingham",
    "sg:classifiers":[
        {
            "category":"Manufacturing",
            "subcategory":"Printing",
            "type":"Manufacturing & Wholesale Goods"
        }
    ],
    "sg:phone":"+1 205 322 3131",
    "sg:postcode":"35222",
    "sg:province":"AL",
    "sg:tags":[
        "print",
        "lithographic",
        "typesetting"
    ],
    "wof:name":"Prantl Printing Company",
    "wof:placetype":"venue"
},
  "geometry": {"coordinates":[-86.780394,33.517195],"type":"Point"}
}