{
  "type": "Feature",
  "properties": {
    "addr:full":"7170 6th Ave Altoona AL 35952",
    "addr:housenumber":"7170",
    "addr:postcode":"35952",
    "addr:street":"6Th Ave",
    "iso:country":"US",
    "sg:address":"7170 6th Ave",
    "sg:city":"Altoona",
    "sg:classifiers":[
        {
            "category":"Banks & Credit Unions",
            "subcategory":"Bank",
            "type":"Services"
        }
    ],
    "sg:phone":"+1 205 589 6334",
    "sg:postcode":"35952",
    "sg:province":"AL",
    "sg:website":"www.exba.com",
    "wof:name":"Exchange Bank Of Alabama",
    "wof:placetype":"venue"
},
  "geometry": {"coordinates":[-86.32575,34.025035],"type":"Point"}
}