{
  "type": "Feature",
  "properties": {
    "iso:country":"US",
    "sg:address":"215 1st Ave E",
    "sg:city":"Oneonta",
    "sg:classifiers":[
        {
            "category":"Shopping",
            "subcategory":"Jewelry",
            "type":"Retail Goods"
        }
    ],
    "sg:phone":"+1 205 274 9468",
    "sg:postcode":"35121",
    "sg:province":"AL",
    "sg:tags":[
        "jeweler"
    ],
    "wof:name":"Howard's Jewelry & Diamond",
    "wof:placetype":"venue"
},
  "geometry": {"coordinates":[-86.474838,33.945577],"type":"Point"}
}