{
  "type": "Feature",
  "properties": {
    "iso:country":"US",
    "sg:address":"603 Main St",
    "sg:city":"Greensboro",
    "sg:classifiers":[
        {
            "category":"Manufacturing",
            "subcategory":"Paper Products",
            "type":"Manufacturing & Wholesale Goods"
        }
    ],
    "sg:phone":"+1 334 624 1427",
    "sg:postcode":"36744",
    "sg:province":"AL",
    "wof:name":"Bailey Paper Co Inc",
    "wof:placetype":"venue"
},
  "geometry": {"coordinates":[-87.588828,32.703303],"type":"Point"}
}