{
  "type": "Feature",
  "properties": {
    "addr:full":"4190 Highway 41 Brewton AL 36426",
    "addr:housenumber":"4190",
    "addr:postcode":"36426",
    "addr:street":"Highway 41",
    "iso:country":"US",
    "sg:address":"4190 Highway 41",
    "sg:city":"Brewton",
    "sg:classifiers":[
        {
            "category":"Government",
            "subcategory":"City Hall",
            "type":"Public Place"
        },
        {
            "category":"Government",
            "subcategory":"Office",
            "type":"Public Place"
        }
    ],
    "sg:phone":"+1 251 867 5378",
    "sg:postcode":"36426",
    "sg:province":"AL",
    "sg:tags":[
        "town",
        "township",
        "planner",
        "government-city",
        "village"
    ],
    "wof:name":"Riverview Town Of Town Hall",
    "wof:placetype":"venue"
},
  "geometry": {"coordinates":[-87.059764,31.059347],"type":"Point"}
}