{
  "type": "Feature",
  "properties": {
    "iso:country":"US",
    "sg:address":"PO Box 3",
    "sg:city":"Mount Olive",
    "sg:classifiers":[
        {
            "category":"Retail",
            "subcategory":"Auto Repair",
            "type":"Services"
        }
    ],
    "sg:phone":"+1 205 647 4630",
    "sg:postcode":"35117",
    "sg:province":"AL",
    "wof:name":"Welch's Radiator & Muffler Shop",
    "wof:placetype":"venue"
},
  "geometry": {"coordinates":[-86.873901,33.663399],"type":"Point"}
}