{
  "type": "Feature",
  "properties": {
    "iso:country":"US",
    "sg:address":"11555 Jack Hamilton Rd",
    "sg:city":"Mobile",
    "sg:phone":"+1 251 633 2764",
    "sg:postcode":"36695",
    "sg:province":"AL",
    "sg:tags":[
        "farm",
        "cotton"
    ],
    "wof:name":"Dorland Farms",
    "wof:placetype":"venue"
},
  "geometry": {"coordinates":[-88.315954,30.603433],"type":"Point"}
}