{
  "type": "Feature",
  "properties": {
    "iso:country":"US",
    "sg:address":"297 Lenlock Ln",
    "sg:city":"Anniston",
    "sg:classifiers":[
        {
            "category":"Retail",
            "subcategory":"Auto Repair",
            "type":"Services"
        }
    ],
    "sg:phone":"+1 256 847 1174",
    "sg:postcode":"36206",
    "sg:province":"AL",
    "sg:tags":[
        "repairing",
        "automobile"
    ],
    "wof:name":"Automotive Repair",
    "wof:placetype":"venue"
},
  "geometry": {"coordinates":[-85.832339,33.723133],"type":"Point"}
}