{
  "type": "Feature",
  "properties": {
    "iso:country":"US",
    "sg:address":"2114 Airport Rd",
    "sg:city":"Haleyville",
    "sg:classifiers":[
        {
            "category":"Retail",
            "subcategory":"Laundry & Dry Cleaning",
            "type":"Services"
        }
    ],
    "sg:phone":"+1 205 486 5144",
    "sg:postcode":"35565",
    "sg:province":"AL",
    "sg:tags":[
        "cleaners",
        "rug",
        "carpet"
    ],
    "wof:name":"Southeast Carpet Cleaning",
    "wof:placetype":"venue"
},
  "geometry": {"coordinates":[-87.61186600000001,34.298667],"type":"Point"}
}