{
  "type": "Feature",
  "properties": {
    "addr:full":"2 The Falls Dr Birmingham AL 35216",
    "addr:housenumber":"2",
    "addr:postcode":"35216",
    "addr:street":"The Falls Dr",
    "iso:country":"US",
    "sg:address":"2 The Falls Dr",
    "sg:city":"Birmingham",
    "sg:classifiers":[
        {
            "category":"Professional",
            "subcategory":"Management & Consulting",
            "type":"Services"
        }
    ],
    "sg:phone":"+1 205 966 0470",
    "sg:postcode":"35216",
    "sg:province":"AL",
    "wof:name":"J&B Partnership",
    "wof:placetype":"venue"
},
  "geometry": {"coordinates":[-86.799657,33.423414],"type":"Point"}
}