{
  "type": "Feature",
  "properties": {
    "iso:country":"US",
    "sg:address":"12051 Ballard Rd",
    "sg:city":"Grand Bay",
    "sg:classifiers":[
        {
            "category":"Home & Garden",
            "subcategory":"Home Furnishings",
            "type":"Retail Goods"
        }
    ],
    "sg:phone":"+1 251 865 6637",
    "sg:postcode":"36541",
    "sg:province":"AL",
    "wof:name":"Jubilee Pottery",
    "wof:placetype":"venue"
},
  "geometry": {"coordinates":[-88.341022,30.552244],"type":"Point"}
}