{
  "type": "Feature",
  "properties": {
    "iso:country":"US",
    "sg:address":"120 S Anniston Ave",
    "sg:city":"Sylacauga",
    "sg:classifiers":[
        {
            "category":"Health Services",
            "subcategory":"Doctor",
            "type":"Services"
        }
    ],
    "sg:phone":"+1 256 249 5500",
    "sg:postcode":"35150",
    "sg:province":"AL",
    "sg:tags":[
        "physician",
        "surgeon"
    ],
    "wof:name":"Graystone Neurology",
    "wof:placetype":"venue"
},
  "geometry": {"coordinates":[-86.253327,33.164529],"type":"Point"}
}