{
  "type": "Feature",
  "properties": {
    "iso:country":"US",
    "sg:address":"14445 State Hwy 75",
    "sg:city":"Remlap",
    "sg:classifiers":[
        {
            "category":"Building & Trades",
            "subcategory":"Construction",
            "type":"Services"
        }
    ],
    "sg:phone":"+1 205 681 5442",
    "sg:postcode":"35133",
    "sg:province":"AL",
    "sg:tags":[
        "floor",
        "laying",
        "contractor"
    ],
    "wof:name":"Century Specialties",
    "wof:placetype":"venue"
},
  "geometry": {"coordinates":[-86.628692,33.775495],"type":"Point"}
}