{
  "type": "Feature",
  "properties": {
    "iso:country":"US",
    "sg:address":"3400 Whitesburg Dr S",
    "sg:city":"Huntsville",
    "sg:classifiers":[
        {
            "category":"Organizations",
            "subcategory":"Community Association",
            "type":"Services"
        }
    ],
    "sg:phone":"+1 256 881 0726",
    "sg:postcode":"35802",
    "sg:province":"AL",
    "sg:tags":[
        "club"
    ],
    "wof:name":"For Being Awareness Assoc",
    "wof:placetype":"venue"
},
  "geometry": {"coordinates":[-86.56841300000001,34.69878],"type":"Point"}
}