{
  "type": "Feature",
  "properties": {
    "addr:full":"1617 Darby Dr Florence AL 35630",
    "addr:housenumber":"1617",
    "addr:postcode":"35630",
    "addr:street":"Darby Dr",
    "iso:country":"US",
    "sg:address":"1617 Darby Dr",
    "sg:city":"Florence",
    "sg:classifiers":[
        {
            "category":"Shopping",
            "subcategory":"Gifts & Souvenirs",
            "type":"Retail Goods"
        }
    ],
    "sg:phone":"+1 256 766 6950",
    "sg:postcode":"35630",
    "sg:province":"AL",
    "wof:name":"Yellow Door",
    "wof:placetype":"venue"
},
  "geometry": {"coordinates":[-87.656807,34.819832],"type":"Point"}
}