{
  "type": "Feature",
  "properties": {
    "iso:country":"US",
    "sg:address":"36 Church St",
    "sg:city":"Birmingham",
    "sg:classifiers":[
        {
            "category":"Shopping",
            "type":"Retail Goods"
        }
    ],
    "sg:phone":"+1 205 803 5252",
    "sg:postcode":"35213",
    "sg:province":"AL",
    "sg:tags":[
        "art",
        "gallery",
        "dealer"
    ],
    "wof:name":"Beverly Mc Neil Gallery",
    "wof:placetype":"venue"
},
  "geometry": {"coordinates":[-86.754954,33.501516],"type":"Point"}
}