{
  "type": "Feature",
  "properties": {
    "iso:country":"US",
    "sg:address":"2034 Chestnut St",
    "sg:city":"Montgomery",
    "sg:classifiers":[
        {
            "category":"Health Services",
            "subcategory":"Doctor",
            "type":"Services"
        }
    ],
    "sg:phone":"+1 334 269 0212",
    "sg:postcode":"36106",
    "sg:province":"AL",
    "sg:tags":[
        "physician",
        "medical",
        "surgeon"
    ],
    "wof:name":"Montgomery Kidney Specialists",
    "wof:placetype":"venue"
},
  "geometry": {"coordinates":[-86.28213,32.366921],"type":"Point"}
}