{
  "type": "Feature",
  "properties": {
    "addr:full":"1001 Park Rd Bessemer AL 35023",
    "addr:housenumber":"1001",
    "addr:postcode":"35023",
    "addr:street":"Park Rd",
    "iso:country":"US",
    "sg:address":"1001 Park Rd",
    "sg:city":"Bessemer",
    "sg:classifiers":[
        {
            "category":"Organizations",
            "subcategory":"Religious Organization",
            "type":"Services"
        }
    ],
    "sg:phone":"+1 205 491 3864",
    "sg:postcode":"35023",
    "sg:province":"AL",
    "wof:name":"Church of God",
    "wof:placetype":"venue"
},
  "geometry": {"coordinates":[-87.08339100000001,33.478845],"type":"Point"}
}