{
  "type": "Feature",
  "properties": {
    "iso:country":"US",
    "sg:address":"5200 Old Birmingham Hwy",
    "sg:city":"Jasper",
    "sg:classifiers":[
        {
            "category":"Retail",
            "subcategory":"Auto Repair",
            "type":"Services"
        }
    ],
    "sg:phone":"+1 205 483 9204",
    "sg:postcode":"35501",
    "sg:province":"AL",
    "sg:tags":[
        "wheel",
        "axle",
        "alignment"
    ],
    "wof:name":"78 Alignment Svc",
    "wof:placetype":"venue"
},
  "geometry": {"coordinates":[-87.210026,33.817334],"type":"Point"}
}