{
  "type": "Feature",
  "properties": {
    "iso:country":"US",
    "sg:address":"403 Lawrence St E",
    "sg:city":"Russellville",
    "sg:classifiers":[
        {
            "category":"Shopping",
            "type":"Retail Goods"
        }
    ],
    "sg:phone":"+1 256 332 2332",
    "sg:postcode":"35653",
    "sg:province":"AL",
    "sg:tags":[
        "monument"
    ],
    "wof:name":"Atkins Marble & Granite Works",
    "wof:placetype":"venue"
},
  "geometry": {"coordinates":[-87.726966,34.503644],"type":"Point"}
}