{
  "type": "Feature",
  "properties": {
    "iso:country":"US",
    "sg:address":"9070 Ponderosa Dr S",
    "sg:city":"Semmes",
    "sg:classifiers":[
        {
            "category":"Building & Trades",
            "subcategory":"Construction",
            "type":"Services"
        }
    ],
    "sg:phone":"+1 251 533 8657",
    "sg:postcode":"36575",
    "sg:province":"AL",
    "sg:tags":[
        "residential"
    ],
    "wof:name":"Jason Pharez Construction",
    "wof:placetype":"venue"
},
  "geometry": {"coordinates":[-88.261944,30.727483],"type":"Point"}
}