{
  "type": "Feature",
  "properties": {
    "iso:country":"US",
    "sg:address":"3875 Greensboro Ave",
    "sg:city":"Tuscaloosa",
    "sg:classifiers":[
        {
            "category":"Retail",
            "subcategory":"Repair Shop",
            "type":"Services"
        }
    ],
    "sg:phone":"+1 205 345 2665",
    "sg:postcode":"35405",
    "sg:province":"AL",
    "sg:tags":[
        "refrigeration"
    ],
    "wof:name":"Hughes & Mullenix Heating",
    "wof:placetype":"venue"
},
  "geometry": {"coordinates":[-87.54709800000001,33.173894],"type":"Point"}
}