{
  "type": "Feature",
  "properties": {
    "addr:full":"569 McCurdy Ave N Rainsville AL 35986",
    "addr:housenumber":"569",
    "addr:postcode":"35986",
    "addr:street":"Mccurdy Ave N",
    "iso:country":"US",
    "sg:address":"569 McCurdy Ave N",
    "sg:city":"Rainsville",
    "sg:classifiers":[
        {
            "category":"Health Services",
            "subcategory":"Doctor",
            "type":"Services"
        }
    ],
    "sg:phone":"+1 256 638 7272",
    "sg:postcode":"35986",
    "sg:province":"AL",
    "sg:tags":[
        "dentist"
    ],
    "wof:name":"Phillip L Fortner DDS",
    "wof:placetype":"venue"
},
  "geometry": {"coordinates":[-85.842478,34.500965],"type":"Point"}
}