{
  "type": "Feature",
  "properties": {
    "iso:country":"US",
    "sg:address":"209 W Grand Ave",
    "sg:city":"Rainbow City",
    "sg:classifiers":[
        {
            "category":"Restaurant",
            "type":"Food & Drink"
        }
    ],
    "sg:menulink":"http://www.allmenus.com/al/gadsden/94084-western-sizzlin/menu/",
    "sg:phone":"+1 256 442 5061",
    "sg:postcode":"35906",
    "sg:province":"AL",
    "sg:tags":[
        "american",
        "steakhouse"
    ],
    "wof:name":"Western Sizzlin",
    "wof:placetype":"venue"
},
  "geometry": {"coordinates":[-86.044057,33.958661],"type":"Point"}
}