{
  "type": "Feature",
  "properties": {
    "addr:full":"106 E Washington St Abbeville AL 36310",
    "addr:housenumber":"106",
    "addr:postcode":"36310",
    "addr:street":"E Washington St",
    "iso:country":"US",
    "sg:address":"106 E Washington St",
    "sg:city":"Abbeville",
    "sg:classifiers":[
        {
            "category":"Shopping",
            "subcategory":"Florist",
            "type":"Retail Goods"
        }
    ],
    "sg:phone":"+1 334 585 4010",
    "sg:postcode":"36310",
    "sg:province":"AL",
    "wof:name":"Flower Pot",
    "wof:placetype":"venue"
},
  "geometry": {"coordinates":[-85.23684799999999,31.569902],"type":"Point"}
}