{
  "type": "Feature",
  "properties": {
    "iso:country":"US",
    "sg:address":"302 Megan Ave",
    "sg:city":"Muscle Shoals",
    "sg:classifiers":[
        {
            "category":"Shopping",
            "subcategory":"Discount & Variety Stores",
            "type":"Retail Goods"
        }
    ],
    "sg:phone":"+1 256 386 7654",
    "sg:postcode":"35661",
    "sg:province":"AL",
    "sg:tags":[
        "merchandise",
        "general"
    ],
    "wof:name":"Hurst Specialty Retail Inc",
    "wof:placetype":"venue"
},
  "geometry": {"coordinates":[-87.64148400000001,34.73222],"type":"Point"}
}