{
  "type": "Feature",
  "properties": {
    "iso:country":"US",
    "sg:address":"208 Hangar Rd",
    "sg:city":"Gadsden",
    "sg:classifiers":[
        {
            "category":"Professional",
            "subcategory":"Employment Agencies",
            "type":"Services"
        }
    ],
    "sg:phone":"+1 256 413 1961",
    "sg:postcode":"35904",
    "sg:province":"AL",
    "sg:tags":[
        "help",
        "supply"
    ],
    "wof:name":"Lan Jet Inc",
    "wof:placetype":"venue"
},
  "geometry": {"coordinates":[-86.08843,33.964596],"type":"Point"}
}