{
  "type": "Feature",
  "properties": {
    "addr:full":"1087 Downtowner Blvd Mobile AL 36609",
    "addr:housenumber":"1087",
    "addr:postcode":"36609",
    "addr:street":"Downtowner Blvd",
    "iso:country":"US",
    "sg:address":"1087 Downtowner Blvd",
    "sg:city":"Mobile",
    "sg:classifiers":[
        {
            "category":"Railroad",
            "type":"Transportation"
        },
        {
            "category":"Airline",
            "type":"Transportation"
        },
        {
            "category":"Travel",
            "subcategory":"Travel Agent",
            "type":"Entertainment"
        },
        {
            "category":"Marine",
            "type":"Transportation"
        },
        {
            "category":"Landmark",
            "subcategory":"Tourist Information",
            "type":"Public Place"
        }
    ],
    "sg:phone":"+1 251 650 0442",
    "sg:postcode":"36609",
    "sg:province":"AL",
    "sg:tags":[
        "railroads-ticket",
        "agency",
        "services-commercial",
        "promoter",
        "tours-operators",
        "cruise",
        "ticket"
    ],
    "wof:name":"Springdale Travel",
    "wof:placetype":"venue"
},
  "geometry": {"coordinates":[-88.144122,30.665305],"type":"Point"}
}