{
  "type": "Feature",
  "properties": {
    "iso:country":"US",
    "sg:address":"111 Moulton St W",
    "sg:city":"Decatur",
    "sg:classifiers":[
        {
            "category":"Shopping",
            "type":"Retail Goods"
        }
    ],
    "sg:phone":"+1 256 353 4624",
    "sg:postcode":"35601",
    "sg:province":"AL",
    "sg:tags":[
        "monument"
    ],
    "wof:name":"Decatur Marble & Granite Works",
    "wof:placetype":"venue"
},
  "geometry": {"coordinates":[-86.98994999999999,34.60394],"type":"Point"}
}