{
  "type": "Feature",
  "properties": {
    "addr:full":"803 Rainbow Dr Gadsden AL 35901",
    "addr:housenumber":"803",
    "addr:postcode":"35901",
    "addr:street":"Rainbow Dr",
    "iso:country":"US",
    "sg:address":"803 Rainbow Dr",
    "sg:city":"Gadsden",
    "sg:classifiers":[
        {
            "category":"Real Estate",
            "subcategory":"Real Estate Agent",
            "type":"Services"
        },
        {
            "category":"Professional",
            "subcategory":"Business Services",
            "type":"Services"
        }
    ],
    "sg:phone":"+1 256 547 9039",
    "sg:postcode":"35901",
    "sg:province":"AL",
    "wof:name":"Freeman Land & Development Inc",
    "wof:placetype":"venue"
},
  "geometry": {"coordinates":[-86.00441600000001,34.000788],"type":"Point"}
}