{
  "type": "Feature",
  "properties": {
    "addr:full":"719 N Broad St Scottsboro AL 35768",
    "addr:housenumber":"719",
    "addr:postcode":"35768",
    "addr:street":"N Broad St",
    "iso:country":"US",
    "sg:address":"719 N Broad St",
    "sg:city":"Scottsboro",
    "sg:classifiers":[
        {
            "category":"Real Estate",
            "subcategory":"Real Estate Services",
            "type":"Services"
        }
    ],
    "sg:phone":"+1 256 259 8674",
    "sg:postcode":"35768",
    "sg:province":"AL",
    "sg:tags":[
        "company",
        "title"
    ],
    "wof:name":"Reeves Title",
    "wof:placetype":"venue"
},
  "geometry": {"coordinates":[-86.034829,34.667523],"type":"Point"}
}