{
  "type": "Feature",
  "properties": {
    "iso:country":"US",
    "sg:address":"9833 Parkway E",
    "sg:city":"Birmingham",
    "sg:classifiers":[
        {
            "category":"Retail",
            "subcategory":"Auto Repair",
            "type":"Services"
        }
    ],
    "sg:phone":"+1 205 815 3333",
    "sg:postcode":"35215",
    "sg:province":"AL",
    "wof:name":"Adam's Car Clinic",
    "wof:placetype":"venue"
},
  "geometry": {"coordinates":[-86.689941,33.605577],"type":"Point"}
}