{
  "type": "Feature",
  "properties": {
    "iso:country":"US",
    "sg:address":"2915 10th Ct S",
    "sg:city":"Birmingham",
    "sg:classifiers":[
        {
            "category":"Real Estate",
            "subcategory":"Architect",
            "type":"Services"
        }
    ],
    "sg:phone":"+1 205 933 6358",
    "sg:postcode":"35205",
    "sg:province":"AL",
    "sg:tags":[
        "architectural"
    ],
    "wof:name":"Architect Design Group",
    "wof:placetype":"venue"
},
  "geometry": {"coordinates":[-86.78312200000001,33.509138],"type":"Point"}
}