{
  "type": "Feature",
  "properties": {
    "addr:full":"3000 Mc Gehee Rd Montgomery AL 36111",
    "addr:housenumber":"3000",
    "addr:postcode":"36111",
    "addr:street":"Mc Gehee Rd",
    "iso:country":"US",
    "sg:address":"3000 Mc Gehee Rd",
    "sg:city":"Montgomery",
    "sg:classifiers":[
        {
            "category":"Retail",
            "subcategory":"Laundry & Dry Cleaning",
            "type":"Services"
        }
    ],
    "sg:phone":"+1 334 281 2848",
    "sg:postcode":"36111",
    "sg:province":"AL",
    "sg:tags":[
        "drycleaning",
        "plant"
    ],
    "wof:name":"Jim Massey Cleaners & Laundry",
    "wof:placetype":"venue"
},
  "geometry": {"coordinates":[-86.258703,32.337722],"type":"Point"}
}