{
  "type": "Feature",
  "properties": {
    "addr:full":"1926 State Rte 17 Hamilton AL 35570",
    "addr:housenumber":"1926",
    "addr:postcode":"35570",
    "addr:street":"State Rte 17",
    "iso:country":"US",
    "sg:address":"1926 State Rte 17",
    "sg:city":"Hamilton",
    "sg:classifiers":[
        {
            "category":"Retail",
            "subcategory":"Auto Repair",
            "type":"Services"
        }
    ],
    "sg:phone":"+1 205 921 7669",
    "sg:postcode":"35570",
    "sg:province":"AL",
    "sg:tags":[
        "repairing",
        "automobile"
    ],
    "wof:name":"A & T Distributors",
    "wof:placetype":"venue"
},
  "geometry": {"coordinates":[-88.020528,34.134481],"type":"Point"}
}