{
  "type": "Feature",
  "properties": {
    "iso:country":"US",
    "sg:address":"301 Coliseum Blvd",
    "sg:city":"Montgomery",
    "sg:classifiers":[
        {
            "category":"Banks & Credit Unions",
            "subcategory":"Bank",
            "type":"Services"
        }
    ],
    "sg:phone":"+1 334 000 1111",
    "sg:postcode":"36109",
    "sg:province":"AL",
    "wof:name":"Regions",
    "wof:placetype":"venue"
},
  "geometry": {"coordinates":[-86.25779,32.39288],"type":"Point"}
}