{
  "type": "Feature",
  "properties": {
    "iso:country":"US",
    "sg:address":"500 2nd Ave N",
    "sg:city":"Clanton",
    "sg:classifiers":[
        {
            "category":"Government",
            "subcategory":"Court House",
            "type":"Public Place"
        }
    ],
    "sg:phone":"+1 205 755 1558",
    "sg:postcode":"35045",
    "sg:province":"AL",
    "sg:tags":[
        "county"
    ],
    "wof:name":"Chilton District Court Judge",
    "wof:placetype":"venue"
},
  "geometry": {"coordinates":[-86.62899299999999,32.840058],"type":"Point"}
}