{
  "type": "Feature",
  "properties": {
    "addr:full":"45680 Oak Ln Bay Minette AL 36507",
    "addr:housenumber":"45680",
    "addr:postcode":"36507",
    "addr:street":"Oak Ln",
    "iso:country":"US",
    "sg:address":"45680 Oak Ln",
    "sg:city":"Bay Minette",
    "sg:classifiers":[
        {
            "category":"Building & Trades",
            "subcategory":"Plumbing",
            "type":"Services"
        }
    ],
    "sg:phone":"+1 251 937 0063",
    "sg:postcode":"36507",
    "sg:province":"AL",
    "sg:tags":[
        "conditioning",
        "air",
        "system",
        "contractor"
    ],
    "wof:name":"Boeschen's Heating & Cooling",
    "wof:placetype":"venue"
},
  "geometry": {"coordinates":[-87.744665,30.888799],"type":"Point"}
}