{
  "type": "Feature",
  "properties": {
    "iso:country":"US",
    "sg:address":"235 McCurdy Ave S",
    "sg:city":"Rainsville",
    "sg:classifiers":[
        {
            "category":"Organizations",
            "subcategory":"Religious Organization",
            "type":"Services"
        }
    ],
    "sg:phone":"+1 256 638 7733",
    "sg:postcode":"35986",
    "sg:province":"AL",
    "wof:name":"Rainsville Community Church",
    "wof:placetype":"venue"
},
  "geometry": {"coordinates":[-85.849135,34.491069],"type":"Point"}
}