{
  "type": "Feature",
  "properties": {
    "addr:full":"2405 22nd St N Birmingham AL 35234",
    "addr:housenumber":"2405",
    "addr:postcode":"35234",
    "addr:street":"22Nd St N",
    "iso:country":"US",
    "sg:address":"2405 22nd St N",
    "sg:city":"Birmingham",
    "sg:classifiers":[
        {
            "category":"Retail",
            "subcategory":"Photofinishing",
            "type":"Services"
        }
    ],
    "sg:phone":"+1 205 250 0087",
    "sg:postcode":"35234",
    "sg:province":"AL",
    "sg:tags":[
        "laboratory"
    ],
    "wof:name":"Rons Photography",
    "wof:placetype":"venue"
},
  "geometry": {"coordinates":[-86.820978,33.543622],"type":"Point"}
}