{
  "type": "Feature",
  "properties": {
    "iso:country":"US",
    "sg:address":"601 Sweeneys Ln",
    "sg:city":"Mobile",
    "sg:classifiers":[
        {
            "category":"Organizations",
            "subcategory":"Membership Organization",
            "type":"Services"
        }
    ],
    "sg:phone":"+1 251 452 4074",
    "sg:postcode":"36617",
    "sg:province":"AL",
    "wof:name":"Tommy Boykin",
    "wof:placetype":"venue"
},
  "geometry": {"coordinates":[-88.08777,30.723782],"type":"Point"}
}