{
  "type": "Feature",
  "properties": {
    "iso:country":"US",
    "sg:address":"11562 Fairway Dr",
    "sg:city":"Irvington",
    "sg:classifiers":[
        {
            "category":"Airport",
            "type":"Transportation"
        }
    ],
    "sg:phone":"+1 251 824 2831",
    "sg:postcode":"36544",
    "sg:province":"AL",
    "wof:name":"Dauphin Island Airport",
    "wof:placetype":"venue"
},
  "geometry": {"coordinates":[-88.22134,30.450125],"type":"Point"}
}