{
  "type": "Feature",
  "properties": {
    "iso:country":"US",
    "sg:address":"1408 Golden Springs Rd",
    "sg:city":"Anniston",
    "sg:classifiers":[
        {
            "category":"Utilities",
            "subcategory":"Mobile Phone",
            "type":"Services"
        }
    ],
    "sg:phone":"+1 256 835 9616",
    "sg:postcode":"36207",
    "sg:province":"AL",
    "sg:tags":[
        "telephone",
        "cellular"
    ],
    "wof:name":"TCI Wireless Super Ctr Store",
    "wof:placetype":"venue"
},
  "geometry": {"coordinates":[-85.786197,33.628325],"type":"Point"}
}