{
  "type": "Feature",
  "properties": {
    "addr:full":"6388 US Hwy 431 Owens Cross Rds AL 35763",
    "addr:housenumber":"6388",
    "addr:postcode":"35763",
    "addr:street":"Us Hwy 431 Owens Cross Rds",
    "iso:country":"US",
    "sg:address":"6388 US Hwy 431",
    "sg:city":"Owens Cross Rds",
    "sg:classifiers":[
        {
            "category":"Banks & Credit Unions",
            "subcategory":"Bank",
            "type":"Services"
        }
    ],
    "sg:phone":"+1 256 551 7150",
    "sg:postcode":"35763",
    "sg:province":"AL",
    "wof:name":"Union Planters Bank",
    "wof:placetype":"venue"
},
  "geometry": {"coordinates":[-86.487869,34.667183],"type":"Point"}
}