{
  "type": "Feature",
  "properties": {
    "iso:country":"US",
    "sg:address":"3651 Traveler Dr",
    "sg:city":"Saraland",
    "sg:classifiers":[
        {
            "category":"Building & Trades",
            "subcategory":"Pest Control",
            "type":"Services"
        }
    ],
    "sg:phone":"+1 251 675 8037",
    "sg:postcode":"36571",
    "sg:province":"AL",
    "wof:name":"Ward Exterminating Co",
    "wof:placetype":"venue"
},
  "geometry": {"coordinates":[-88.128276,30.834581],"type":"Point"}
}