{
  "type": "Feature",
  "properties": {
    "iso:country":"US",
    "sg:address":"2218 Executive Park Dr",
    "sg:city":"Opelika",
    "sg:classifiers":[
        {
            "category":"Insurance",
            "subcategory":"Insurance Agent",
            "type":"Services"
        }
    ],
    "sg:phone":"+1 334 745 9310",
    "sg:postcode":"36801",
    "sg:province":"AL",
    "wof:name":"Blue Cross & Blue Shield",
    "wof:placetype":"venue"
},
  "geometry": {"coordinates":[-85.438463,32.629283],"type":"Point"}
}