{
  "type": "Feature",
  "properties": {
    "addr:full":"3495 Plantersville Rd Alpine AL 35014",
    "addr:housenumber":"3495",
    "addr:postcode":"35014",
    "addr:street":"Plantersville Rd",
    "iso:country":"US",
    "sg:address":"3495 Plantersville Rd",
    "sg:city":"Alpine",
    "sg:phone":"+1 256 268 0753",
    "sg:postcode":"35014",
    "sg:province":"AL",
    "sg:tags":[
        "farm",
        "cotton"
    ],
    "wof:name":"Vincent Allen",
    "wof:placetype":"venue"
},
  "geometry": {"coordinates":[-86.23867799999999,33.398542],"type":"Point"}
}