{
  "type": "Feature",
  "properties": {
    "iso:country":"US",
    "sg:address":"260 Big Springs Dr",
    "sg:city":"Birmingham",
    "sg:classifiers":[
        {
            "category":"Health Services",
            "subcategory":"Doctor",
            "type":"Services"
        }
    ],
    "sg:phone":"+1 205 979 8318",
    "sg:postcode":"35216",
    "sg:province":"AL",
    "sg:tags":[
        "medical"
    ],
    "wof:name":"W Glen Wells Dr",
    "wof:placetype":"venue"
},
  "geometry": {"coordinates":[-86.764708,33.459114],"type":"Point"}
}