{
  "type": "Feature",
  "properties": {
    "addr:full":"4204 Rolling Ridge Way Pleasant Grove AL 35127",
    "addr:housenumber":"4204",
    "addr:postcode":"35127",
    "addr:street":"Rolling Ridge Way",
    "iso:country":"US",
    "sg:address":"4204 Rolling Ridge Way",
    "sg:city":"Pleasant Grove",
    "sg:classifiers":[
        {
            "category":"Arts & Performance",
            "subcategory":"Theater",
            "type":"Entertainment"
        }
    ],
    "sg:phone":"+1 205 744 7825",
    "sg:postcode":"35127",
    "sg:province":"AL",
    "wof:name":"The Three Horsemen",
    "wof:placetype":"venue"
},
  "geometry": {"coordinates":[-86.985439,33.469387],"type":"Point"}
}