{
  "type": "Feature",
  "properties": {
    "addr:full":"5735 Carmichael Pkwy Montgomery AL 36117",
    "addr:housenumber":"5735",
    "addr:postcode":"36117",
    "addr:street":"Carmichael Pkwy",
    "iso:country":"US",
    "sg:address":"5735 Carmichael Pkwy",
    "sg:city":"Montgomery",
    "sg:classifiers":[
        {
            "category":"Organizations",
            "subcategory":"Non-profit Organization",
            "type":"Services"
        }
    ],
    "sg:phone":"+1 334 396 9870",
    "sg:postcode":"36117",
    "sg:province":"AL",
    "wof:name":"National Kidney Foundation",
    "wof:placetype":"venue"
},
  "geometry": {"coordinates":[-86.20656200000001,32.361159],"type":"Point"}
}