{
  "type": "Feature",
  "properties": {
    "iso:country":"US",
    "sg:address":"1006 Windham St NE",
    "sg:city":"Huntsville",
    "sg:classifiers":[
        {
            "category":"Professional",
            "subcategory":"Computer Services",
            "type":"Services"
        }
    ],
    "sg:phone":"+1 256 519 6366",
    "sg:postcode":"35801",
    "sg:province":"AL",
    "sg:tags":[
        "internet"
    ],
    "wof:name":"Neon City Web Svc",
    "wof:placetype":"venue"
},
  "geometry": {"coordinates":[-86.567443,34.746568],"type":"Point"}
}