{
  "type": "Feature",
  "properties": {
    "iso:country":"US",
    "sg:address":"251 Ervin Ln",
    "sg:city":"Madison",
    "sg:classifiers":[
        {
            "category":"Organizations",
            "subcategory":"Religious Organization",
            "type":"Services"
        }
    ],
    "sg:phone":"+1 256 772 3099",
    "sg:postcode":"35756",
    "sg:province":"AL",
    "sg:tags":[
        "church"
    ],
    "wof:name":"Triana Seventh Day Adventist",
    "wof:placetype":"venue"
},
  "geometry": {"coordinates":[-86.75044,34.596083],"type":"Point"}
}