{
  "type": "Feature",
  "properties": {
    "addr:full":"2516 US Hwy 98 Daphne AL 36526",
    "addr:housenumber":"2516",
    "addr:postcode":"36526",
    "addr:street":"Us Hwy 98",
    "iso:country":"US",
    "sg:address":"2516 US Hwy 98",
    "sg:city":"Daphne",
    "sg:classifiers":[
        {
            "category":"Autos & Motor Vehicles",
            "subcategory":"Auto Supplies",
            "type":"Retail Goods"
        }
    ],
    "sg:phone":"+1 251 626 6215",
    "sg:postcode":"36526",
    "sg:province":"AL",
    "sg:tags":[
        "tire"
    ],
    "wof:name":"Fausak Tire Ctr",
    "wof:placetype":"venue"
},
  "geometry": {"coordinates":[-87.891251,30.5505],"type":"Point"}
}