{
  "type": "Feature",
  "properties": {
    "iso:country":"US",
    "sg:address":"2457 Co Rd 180",
    "sg:city":"Rainsville",
    "sg:classifiers":[
        {
            "category":"Building & Trades",
            "subcategory":"Plumbing",
            "type":"Services"
        }
    ],
    "sg:phone":"+1 256 638 9675",
    "sg:postcode":"35986",
    "sg:province":"AL",
    "sg:tags":[
        "contractor"
    ],
    "wof:name":"Herrens Heating & Cooling LLC",
    "wof:placetype":"venue"
},
  "geometry": {"coordinates":[-85.80321,34.509713],"type":"Point"}
}