{
  "type": "Feature",
  "properties": {
    "iso:country":"US",
    "sg:address":"445 S Hull St",
    "sg:city":"Montgomery",
    "sg:classifiers":[
        {
            "category":"Professional",
            "subcategory":"Computer Services",
            "type":"Services"
        }
    ],
    "sg:phone":"+1 334 265 7311",
    "sg:postcode":"36104",
    "sg:province":"AL",
    "sg:tags":[
        "system",
        "integration"
    ],
    "wof:name":"Applied Computer & Consulting",
    "wof:placetype":"venue"
},
  "geometry": {"coordinates":[-86.30351,32.371916],"type":"Point"}
}