{
  "type": "Feature",
  "properties": {
    "iso:country":"US",
    "sg:address":"1027 Opelika Rd",
    "sg:city":"Auburn",
    "sg:classifiers":[
        {
            "category":"Autos & Motor Vehicles",
            "subcategory":"Auto Supplies",
            "type":"Retail Goods"
        },
        {
            "category":"Retail",
            "subcategory":"Auto Repair",
            "type":"Services"
        }
    ],
    "sg:phone":"+1 334 887 9876",
    "sg:postcode":"36830",
    "sg:province":"AL",
    "sg:tags":[
        "automobile",
        "parts",
        "tire",
        "general"
    ],
    "wof:name":"Eagle Tire",
    "wof:placetype":"venue"
},
  "geometry": {"coordinates":[-85.463041,32.6174],"type":"Point"}
}