{
  "type": "Feature",
  "properties": {
    "iso:country":"US",
    "sg:address":"28133 Falcon Ln",
    "sg:city":"Elkmont",
    "sg:classifiers":[
        {
            "category":"Building & Trades",
            "subcategory":"Construction",
            "type":"Services"
        }
    ],
    "sg:phone":"+1 256 423 8914",
    "sg:postcode":"35620",
    "sg:province":"AL",
    "sg:tags":[
        "concrete",
        "contractor"
    ],
    "wof:name":"Scotts Concrete",
    "wof:placetype":"venue"
},
  "geometry": {"coordinates":[-86.919502,34.965123],"type":"Point"}
}