{
  "type": "Feature",
  "properties": {
    "addr:full":"4371 Narrow Lane Rd Montgomery AL 36116",
    "addr:housenumber":"4371",
    "addr:postcode":"36116",
    "addr:street":"Narrow Lane Rd",
    "iso:country":"US",
    "sg:address":"4371 Narrow Lane Rd",
    "sg:city":"Montgomery",
    "sg:classifiers":[
        {
            "category":"Health Services",
            "subcategory":"Doctor",
            "type":"Services"
        }
    ],
    "sg:phone":"+1 334 284 5211",
    "sg:postcode":"36116",
    "sg:province":"AL",
    "sg:tags":[
        "medical"
    ],
    "wof:name":"Bryan Strickland MD",
    "wof:placetype":"venue"
},
  "geometry": {"coordinates":[-86.28198999999999,32.323413],"type":"Point"}
}