{
  "type": "Feature",
  "properties": {
    "iso:country":"US",
    "sg:address":"20688 Honeysuckle Ln",
    "sg:city":"Mc Calla",
    "sg:classifiers":[
        {
            "category":"Building & Trades",
            "subcategory":"Electrical",
            "type":"Services"
        }
    ],
    "sg:phone":"+1 205 477 4664",
    "sg:postcode":"35111",
    "sg:province":"AL",
    "sg:tags":[
        "electrical",
        "contractor"
    ],
    "wof:name":"Accurate Electric",
    "wof:placetype":"venue"
},
  "geometry": {"coordinates":[-87.154431,33.253034],"type":"Point"}
}