{
  "type": "Feature",
  "properties": {
    "addr:full":"2340 Woodcrest Pl Birmingham AL 35209",
    "addr:housenumber":"2340",
    "addr:postcode":"35209",
    "addr:street":"Woodcrest Pl",
    "iso:country":"US",
    "sg:address":"2340 Woodcrest Pl",
    "sg:city":"Birmingham",
    "sg:classifiers":[
        {
            "category":"Banks & Credit Unions",
            "subcategory":"Bank",
            "type":"Services"
        }
    ],
    "sg:phone":"+1 205 870 1939",
    "sg:postcode":"35209",
    "sg:province":"AL",
    "sg:website":"http://www.iberiabank.com",
    "wof:name":"Iberia Bank",
    "wof:placetype":"venue"
},
  "geometry": {"coordinates":[-86.787216,33.488319],"type":"Point"}
}