{
  "type": "Feature",
  "properties": {
    "iso:country":"US",
    "sg:address":"10645 US Hwy 278",
    "sg:city":"Holly Pond",
    "sg:classifiers":[
        {
            "category":"Restaurant",
            "type":"Food & Drink"
        }
    ],
    "sg:phone":"+1 256 796 1400",
    "sg:postcode":"35083",
    "sg:province":"AL",
    "wof:name":"Water Brook Restaurant",
    "wof:placetype":"venue"
},
  "geometry": {"coordinates":[-86.605134,34.174257],"type":"Point"}
}