{
  "type": "Feature",
  "properties": {
    "iso:country":"US",
    "sg:address":"2108 Sharon Ln",
    "sg:city":"Birmingham",
    "sg:classifiers":[
        {
            "category":"Professional",
            "subcategory":"Management & Consulting",
            "type":"Services"
        }
    ],
    "sg:phone":"+1 205 822 9459",
    "sg:postcode":"35226",
    "sg:province":"AL",
    "sg:tags":[
        "consultant",
        "machinery",
        "alignment",
        "vibration"
    ],
    "wof:name":"Vibalign Inc",
    "wof:placetype":"venue"
},
  "geometry": {"coordinates":[-86.853561,33.39355],"type":"Point"}
}