{
  "type": "Feature",
  "properties": {
    "iso:country":"US",
    "sg:address":"112 Redland Bluff Rd",
    "sg:city":"Wetumpka",
    "sg:classifiers":[
        {
            "category":"Food & Beverages",
            "subcategory":"Groceries & Convenience Stores",
            "type":"Retail Goods"
        }
    ],
    "sg:phone":"+1 334 514 6004",
    "sg:postcode":"36093",
    "sg:province":"AL",
    "wof:name":"Allens One Stop",
    "wof:placetype":"venue"
},
  "geometry": {"coordinates":[-86.16932300000001,32.466792],"type":"Point"}
}