{
  "type": "Feature",
  "properties": {
    "iso:country":"US",
    "sg:address":"707 S Railroad St",
    "sg:city":"Phenix City",
    "sg:classifiers":[
        {
            "category":"Real Estate",
            "subcategory":"Real Estate Agent",
            "type":"Services"
        }
    ],
    "sg:phone":"+1 334 297 6698",
    "sg:postcode":"36867",
    "sg:province":"AL",
    "wof:name":"Home Express Inc",
    "wof:placetype":"venue"
},
  "geometry": {"coordinates":[-85.005354,32.476993],"type":"Point"}
}