{
  "type": "Feature",
  "properties": {
    "addr:full":"461 Cahaba Valley Rd Pelham AL 35124",
    "addr:housenumber":"461",
    "addr:postcode":"35124",
    "addr:street":"Cahaba Valley Rd",
    "iso:country":"US",
    "sg:address":"461 Cahaba Valley Rd",
    "sg:city":"Pelham",
    "sg:classifiers":[
        {
            "category":"Retail",
            "subcategory":"Auto Repair",
            "type":"Services"
        }
    ],
    "sg:phone":"+1 205 682 1054",
    "sg:postcode":"35124",
    "sg:province":"AL",
    "sg:tags":[
        "glass",
        "replacement"
    ],
    "wof:name":"Atlantic Windshield Repair",
    "wof:placetype":"venue"
},
  "geometry": {"coordinates":[-86.784271,33.334776],"type":"Point"}
}