{
  "type": "Feature",
  "properties": {
    "iso:country":"US",
    "sg:address":"2 Phillip St",
    "sg:city":"Montgomery",
    "sg:classifiers":[
        {
            "category":"Organizations",
            "subcategory":"Religious Organization",
            "type":"Services"
        }
    ],
    "sg:phone":"+1 334 269 5326",
    "sg:postcode":"36108",
    "sg:province":"AL",
    "sg:tags":[
        "church"
    ],
    "wof:name":"Mount Pleasant AME Zion Church",
    "wof:placetype":"venue"
},
  "geometry": {"coordinates":[-86.392906,32.39398],"type":"Point"}
}