{
  "type": "Feature",
  "properties": {
    "iso:country":"US",
    "sg:address":"4320 High Point Rd",
    "sg:city":"Albertville",
    "sg:classifiers":[
        {
            "category":"Farming",
            "subcategory":"Poultry Farm",
            "type":"Manufacturing & Wholesale Goods"
        }
    ],
    "sg:phone":"+1 256 891 0971",
    "sg:postcode":"35950",
    "sg:province":"AL",
    "sg:tags":[
        "hatchery"
    ],
    "wof:name":"Martin Kenneth",
    "wof:placetype":"venue"
},
  "geometry": {"coordinates":[-86.279393,34.241759],"type":"Point"}
}