{
  "type": "Feature",
  "properties": {
    "addr:full":"1121 Carter Hill Rd Montgomery AL 36106",
    "addr:housenumber":"1121",
    "addr:postcode":"36106",
    "addr:street":"Carter Hill Rd",
    "iso:country":"US",
    "sg:address":"1121 Carter Hill Rd",
    "sg:city":"Montgomery",
    "sg:classifiers":[
        {
            "category":"Autos & Motor Vehicles",
            "subcategory":"Fuel & Gas Station",
            "type":"Retail Goods"
        }
    ],
    "sg:phone":"+1 334 834 6362",
    "sg:postcode":"36106",
    "sg:province":"AL",
    "sg:tags":[
        "oil"
    ],
    "wof:name":"Amoco Gasoline & Food Shop",
    "wof:placetype":"venue"
},
  "geometry": {"coordinates":[-86.291856,32.360604],"type":"Point"}
}