{
  "type": "Feature",
  "properties": {
    "iso:country":"US",
    "sg:address":"11460 Co Rd 14",
    "sg:city":"Waterloo",
    "sg:classifiers":[
        {
            "category":"Food & Beverages",
            "subcategory":"Groceries & Convenience Stores",
            "type":"Retail Goods"
        }
    ],
    "sg:phone":"+1 256 767 3324",
    "sg:postcode":"35677",
    "sg:province":"AL",
    "wof:name":"Carols Bent Dent Groceries &",
    "wof:placetype":"venue"
},
  "geometry": {"coordinates":[-87.9984,34.904906],"type":"Point"}
}