{
  "type": "Feature",
  "properties": {
    "iso:country":"US",
    "sg:address":"1843 Montgomery Hwy",
    "sg:city":"Birmingham",
    "sg:classifiers":[
        {
            "category":"Restaurant",
            "type":"Food & Drink"
        }
    ],
    "sg:phone":"+1 205 985 0051",
    "sg:postcode":"35244",
    "sg:province":"AL",
    "sg:tags":[
        "eating"
    ],
    "wof:name":"Cafe Saigon",
    "wof:placetype":"venue"
},
  "geometry": {"coordinates":[-86.79511100000001,33.350572],"type":"Point"}
}