{
  "type": "Feature",
  "properties": {
    "iso:country":"US",
    "sg:address":"2202 E 6th St",
    "sg:city":"Muscle Shoals",
    "sg:classifiers":[
        {
            "category":"Autos & Motor Vehicles",
            "subcategory":"Automobile Sales",
            "type":"Retail Goods"
        }
    ],
    "sg:phone":"+1 256 383 5507",
    "sg:postcode":"35661",
    "sg:province":"AL",
    "sg:tags":[
        "used"
    ],
    "wof:name":"Wayne Motors Inc",
    "wof:placetype":"venue"
},
  "geometry": {"coordinates":[-87.630731,34.729706],"type":"Point"}
}