{
  "type": "Feature",
  "properties": {
    "iso:country":"US",
    "sg:address":"300 Red Eagle Dr",
    "sg:city":"Wetumpka",
    "sg:classifiers":[
        {
            "category":"Social Services",
            "subcategory":"Adult Care",
            "type":"Services"
        },
        {
            "category":"Government",
            "subcategory":"Office",
            "type":"Public Place"
        }
    ],
    "sg:phone":"+1 334 567 7034",
    "sg:postcode":"36092",
    "sg:province":"AL",
    "sg:tags":[
        "residential"
    ],
    "wof:name":"Alabama Youth Homes",
    "wof:placetype":"venue"
},
  "geometry": {"coordinates":[-86.189187,32.556194],"type":"Point"}
}