{
  "type": "Feature",
  "properties": {
    "iso:country":"US",
    "sg:address":"2001 Country Ridge Pl",
    "sg:city":"Birmingham",
    "sg:classifiers":[
        {
            "category":"Professional",
            "subcategory":"Business Services",
            "type":"Services"
        }
    ],
    "sg:phone":"+1 205 967 5464",
    "sg:postcode":"35243",
    "sg:province":"AL",
    "sg:tags":[
        "water",
        "treatment"
    ],
    "wof:name":"Hercules Inc",
    "wof:placetype":"venue"
},
  "geometry": {"coordinates":[-86.763288,33.43425],"type":"Point"}
}