{
  "type": "Feature",
  "properties": {
    "iso:country":"US",
    "sg:address":"37017 State Rte 79",
    "sg:city":"Cleveland",
    "sg:classifiers":[
        {
            "category":"Manufacturing",
            "subcategory":"Tools & Machinery",
            "type":"Manufacturing & Wholesale Goods"
        }
    ],
    "sg:phone":"+1 205 274 7137",
    "sg:postcode":"35049",
    "sg:province":"AL",
    "sg:tags":[
        "physician",
        "surgeon"
    ],
    "wof:name":"American Orthopedic Supply",
    "wof:placetype":"venue"
},
  "geometry": {"coordinates":[-86.585992,33.994224],"type":"Point"}
}