{
  "type": "Feature",
  "properties": {
    "addr:full":"2121 Montevallo Rd SW Birmingham AL 35211",
    "addr:housenumber":"2121",
    "addr:postcode":"35211",
    "addr:street":"Montevallo Rd Sw",
    "iso:country":"US",
    "sg:address":"2121 Montevallo Rd SW",
    "sg:city":"Birmingham",
    "sg:classifiers":[
        {
            "category":"Community Center",
            "subcategory":"Youth",
            "type":"Public Place"
        }
    ],
    "sg:phone":"+1 205 916 0150",
    "sg:postcode":"35211",
    "sg:province":"AL",
    "wof:name":"Urban Young Life Of Birmingham",
    "wof:placetype":"venue"
},
  "geometry": {"coordinates":[-86.84204099999999,33.468003],"type":"Point"}
}