{
  "type": "Feature",
  "properties": {
    "addr:full":"1872 W Beach Blvd Gulf Shores AL 36542",
    "addr:housenumber":"1872",
    "addr:postcode":"36542",
    "addr:street":"W Beach Blvd",
    "iso:country":"US",
    "sg:address":"1872 W Beach Blvd",
    "sg:city":"Gulf Shores",
    "sg:classifiers":[
        {
            "category":"Food & Beverages",
            "subcategory":"Fruits & Vegetables",
            "type":"Retail Goods"
        }
    ],
    "sg:phone":"+1 251 948 4873",
    "sg:postcode":"36542",
    "sg:province":"AL",
    "wof:name":"United Produce Co",
    "wof:placetype":"venue"
},
  "geometry": {"coordinates":[-87.74067599999999,30.241138],"type":"Point"}
}