{
  "type": "Feature",
  "properties": {
    "iso:country":"US",
    "sg:address":"3703 Dunbarton Dr",
    "sg:city":"Birmingham",
    "sg:classifiers":[
        {
            "category":"Building & Trades",
            "subcategory":"Cleaning & Sanitation",
            "type":"Services"
        }
    ],
    "sg:phone":"+1 205 967 3703",
    "sg:postcode":"35223",
    "sg:province":"AL",
    "sg:tags":[
        "refrigeration",
        "maintenance"
    ],
    "wof:name":"Western Management Systems",
    "wof:placetype":"venue"
},
  "geometry": {"coordinates":[-86.73495699999999,33.473404],"type":"Point"}
}