{
  "type": "Feature",
  "properties": {
    "iso:country":"US",
    "sg:address":"413 Chickasaw Ln",
    "sg:city":"Trussville",
    "sg:classifiers":[
        {
            "category":"Communications",
            "subcategory":"Film & Video Production",
            "type":"Services"
        },
        {
            "category":"Professional",
            "subcategory":"Advertising",
            "type":"Services"
        }
    ],
    "sg:phone":"+1 205 655 8585",
    "sg:postcode":"35173",
    "sg:province":"AL",
    "sg:tags":[
        "radio",
        "television",
        "counselor",
        "commercial"
    ],
    "wof:name":"Aztec Productions Inc",
    "wof:placetype":"venue"
},
  "geometry": {"coordinates":[-86.599733,33.629372],"type":"Point"}
}