{
  "type": "Feature",
  "properties": {
    "iso:country":"US",
    "sg:address":"173 Four Mile Exd",
    "sg:city":"Anniston",
    "sg:classifiers":[
        {
            "category":"Professional",
            "subcategory":"Engineering",
            "type":"Services"
        }
    ],
    "sg:phone":"+1 256 435 4778",
    "sg:postcode":"36206",
    "sg:province":"AL",
    "wof:name":"Refrigeration Service Eng",
    "wof:placetype":"venue"
},
  "geometry": {"coordinates":[-85.77729,33.752594],"type":"Point"}
}