{
  "type": "Feature",
  "properties": {
    "addr:full":"1130 Co Rd 47 Columbiana AL 35051",
    "addr:housenumber":"1130;47",
    "addr:postcode":"35051",
    "addr:street":"Co Rd",
    "iso:country":"US",
    "sg:address":"1130 Co Rd 47",
    "sg:city":"Columbiana",
    "sg:classifiers":[
        {
            "category":"Organizations",
            "subcategory":"Religious Organization",
            "type":"Services"
        }
    ],
    "sg:phone":"+1 205 669 9311",
    "sg:postcode":"35051",
    "sg:province":"AL",
    "wof:name":"Love In Action Ministry",
    "wof:placetype":"venue"
},
  "geometry": {"coordinates":[-86.613067,33.201346],"type":"Point"}
}