{
  "type": "Feature",
  "properties": {
    "addr:full":"679 E Michigan Ave Foley AL 36535",
    "addr:housenumber":"679",
    "addr:postcode":"36535",
    "addr:street":"E Michigan Ave",
    "iso:country":"US",
    "sg:address":"679 E Michigan Ave",
    "sg:city":"Foley",
    "sg:classifiers":[
        {
            "category":"Real Estate",
            "subcategory":"Real Estate Operator",
            "type":"Services"
        }
    ],
    "sg:phone":"+1 251 971 3800",
    "sg:postcode":"36535",
    "sg:province":"AL",
    "sg:tags":[
        "apartment"
    ],
    "wof:name":"South Pointe Apartment Homes",
    "wof:placetype":"venue"
},
  "geometry": {"coordinates":[-87.673249,30.392285],"type":"Point"}
}