{
  "type": "Feature",
  "properties": {
    "iso:country":"US",
    "sg:address":"6530 Quail Run Dr",
    "sg:city":"Pelham",
    "sg:classifiers":[
        {
            "category":"Wholesale",
            "subcategory":"Machinery & Supplies",
            "type":"Manufacturing & Wholesale Goods"
        }
    ],
    "sg:phone":"+1 205 987 0207",
    "sg:postcode":"35124",
    "sg:province":"AL",
    "sg:tags":[
        "sprinkler"
    ],
    "wof:name":"Premier Fire Svc Inc",
    "wof:placetype":"venue"
},
  "geometry": {"coordinates":[-86.772117,33.351559],"type":"Point"}
}