{
  "type": "Feature",
  "properties": {
    "iso:country":"US",
    "sg:address":"21 W 16th St",
    "sg:city":"Anniston",
    "sg:classifiers":[
        {
            "category":"Professional",
            "subcategory":"Employment Agencies",
            "type":"Services"
        }
    ],
    "sg:phone":"+1 256 237 3591",
    "sg:postcode":"36201",
    "sg:province":"AL",
    "sg:tags":[
        "consultant",
        "outplacement"
    ],
    "wof:name":"Employment Service",
    "wof:placetype":"venue"
},
  "geometry": {"coordinates":[-85.830445,33.66513],"type":"Point"}
}