{
  "type": "Feature",
  "properties": {
    "iso:country":"US",
    "sg:address":"9450 Alderway St",
    "sg:city":"Mobile",
    "sg:classifiers":[
        {
            "category":"Wholesale",
            "subcategory":"Medical Equipment & Supplies",
            "type":"Manufacturing & Wholesale Goods"
        }
    ],
    "sg:phone":"+1 251 639 5049",
    "sg:postcode":"36695",
    "sg:province":"AL",
    "sg:tags":[
        "used"
    ],
    "wof:name":"Southern Diagnostics Inc",
    "wof:placetype":"venue"
},
  "geometry": {"coordinates":[-88.276646,30.64796],"type":"Point"}
}