{
  "type": "Feature",
  "properties": {
    "iso:country":"US",
    "sg:address":"10655 US Hwy 43",
    "sg:city":"Russellville",
    "sg:classifiers":[
        {
            "category":"Wholesale",
            "subcategory":"Construction Materials",
            "type":"Manufacturing & Wholesale Goods"
        },
        {
            "category":"Manufacturing",
            "subcategory":"Buildings",
            "type":"Manufacturing & Wholesale Goods"
        }
    ],
    "sg:phone":"+1 256 332 4510",
    "sg:postcode":"35653",
    "sg:province":"AL",
    "sg:tags":[
        "mobile",
        "home",
        "mfg"
    ],
    "sg:website":"www.franklinhomesusa.com",
    "wof:name":"Franklin Homes Inc",
    "wof:placetype":"venue"
},
  "geometry": {"coordinates":[-87.753639,34.4562],"type":"Point"}
}