{
  "type": "Feature",
  "properties": {
    "addr:full":"3275 Harrison Rd Montgomery AL 36109",
    "addr:housenumber":"3275",
    "addr:postcode":"36109",
    "addr:street":"Harrison Rd",
    "iso:country":"US",
    "sg:address":"3275 Harrison Rd",
    "sg:city":"Montgomery",
    "sg:classifiers":[
        {
            "category":"Manufacturing",
            "subcategory":"Glass & Minerals",
            "type":"Manufacturing & Wholesale Goods"
        }
    ],
    "sg:phone":"+1 334 394 9996",
    "sg:postcode":"36109",
    "sg:province":"AL",
    "sg:tags":[
        "cement"
    ],
    "wof:name":"Greenwood Cementary",
    "wof:placetype":"venue"
},
  "geometry": {"coordinates":[-86.261905,32.367029],"type":"Point"}
}