{
  "type": "Feature",
  "properties": {
    "iso:country":"US",
    "sg:address":"1000 Quintard Ave",
    "sg:city":"Anniston",
    "sg:classifiers":[
        {
            "category":"Professional",
            "subcategory":"Lawyer & Legal Services",
            "type":"Services"
        }
    ],
    "sg:phone":"+1 256 236 1035",
    "sg:postcode":"36201",
    "sg:province":"AL",
    "wof:name":"Theresa Kisor",
    "wof:placetype":"venue"
},
  "geometry": {"coordinates":[-85.82685600000001,33.65842],"type":"Point"}
}