{
  "type": "Feature",
  "properties": {
    "iso:country":"US",
    "sg:address":"202 S Memorial Dr",
    "sg:city":"Prattville",
    "sg:classifiers":[
        {
            "category":"Banks & Credit Unions",
            "subcategory":"Investment Brokerage",
            "type":"Services"
        }
    ],
    "sg:phone":"+1 334 358 5550",
    "sg:postcode":"36067",
    "sg:province":"AL",
    "sg:tags":[
        "advisory",
        "financial"
    ],
    "wof:name":"PLS Financial Svc",
    "wof:placetype":"venue"
},
  "geometry": {"coordinates":[-86.45100499999999,32.463713],"type":"Point"}
}