{
  "type": "Feature",
  "properties": {
    "iso:country":"US",
    "sg:address":"464 Pinecrest Rd",
    "sg:city":"Prattville",
    "sg:classifiers":[
        {
            "category":"Retail",
            "subcategory":"Repair Shop",
            "type":"Services"
        }
    ],
    "sg:phone":"+1 334 358 2776",
    "sg:postcode":"36067",
    "sg:province":"AL",
    "wof:name":"To Z A Refrigeration",
    "wof:placetype":"venue"
},
  "geometry": {"coordinates":[-86.457359,32.463391],"type":"Point"}
}