{
  "type": "Feature",
  "properties": {
    "iso:country":"US",
    "sg:address":"1216 15th St S",
    "sg:city":"Birmingham",
    "sg:classifiers":[
        {
            "category":"Building & Trades",
            "subcategory":"Construction",
            "type":"Services"
        }
    ],
    "sg:phone":"+1 205 933 0990",
    "sg:postcode":"35205",
    "sg:province":"AL",
    "sg:tags":[
        "residential"
    ],
    "wof:name":"Liberty Design & Construction",
    "wof:placetype":"venue"
},
  "geometry": {"coordinates":[-86.802954,33.495571],"type":"Point"}
}