{
  "type": "Feature",
  "properties": {
    "addr:full":"220 Williamsburg Office Park Birmingham AL 35216",
    "addr:housenumber":"220",
    "addr:postcode":"35216",
    "addr:street":"Office Park",
    "iso:country":"US",
    "sg:address":"220 Williamsburg Office Park",
    "sg:city":"Birmingham",
    "sg:classifiers":[
        {
            "category":"Professional",
            "subcategory":"Accounting & Tax Preparation",
            "type":"Services"
        }
    ],
    "sg:phone":"+1 205 979 8998",
    "sg:postcode":"35216",
    "sg:province":"AL",
    "sg:tags":[
        "accountant"
    ],
    "wof:name":"Elliott George CPA",
    "wof:placetype":"venue"
},
  "geometry": {"coordinates":[-86.713183,33.591588],"type":"Point"}
}