{
  "type": "Feature",
  "properties": {
    "iso:country":"US",
    "sg:address":"27290 Cove Dr",
    "sg:city":"Orange Beach",
    "sg:classifiers":[
        {
            "category":"Manufacturing",
            "subcategory":"Printing",
            "type":"Manufacturing & Wholesale Goods"
        }
    ],
    "sg:phone":"+1 251 981 9277",
    "sg:postcode":"36561",
    "sg:province":"AL",
    "sg:tags":[
        "lithographic",
        "commercial"
    ],
    "wof:name":"Mike Adcock Printing Equipment",
    "wof:placetype":"venue"
},
  "geometry": {"coordinates":[-87.562219,30.284737],"type":"Point"}
}