{
  "type": "Feature",
  "properties": {
    "iso:country":"US",
    "sg:address":"2714 Cahaba Rd",
    "sg:city":"Birmingham",
    "sg:classifiers":[
        {
            "category":"Shopping",
            "subcategory":"Pharmacy",
            "type":"Retail Goods"
        }
    ],
    "sg:phone":"+1 205 871 1141",
    "sg:postcode":"35223",
    "sg:province":"AL",
    "wof:name":"Ritchs Pharmacy",
    "wof:placetype":"venue"
},
  "geometry": {"coordinates":[-86.773646,33.483622],"type":"Point"}
}