{
  "type": "Feature",
  "properties": {
    "iso:country":"US",
    "sg:address":"109 N Market St",
    "sg:city":"Troy",
    "sg:classifiers":[
        {
            "category":"Shopping",
            "subcategory":"Clothing, Apparel, & Fashions",
            "type":"Retail Goods"
        }
    ],
    "sg:phone":"+1 334 566 0950",
    "sg:postcode":"36081",
    "sg:province":"AL",
    "wof:name":"Mattie's Fashion Boutique",
    "wof:placetype":"venue"
},
  "geometry": {"coordinates":[-85.970573,31.80796],"type":"Point"}
}