{
  "type": "Feature",
  "properties": {
    "iso:country":"US",
    "sg:address":"613 State Rte 52",
    "sg:city":"Kinston",
    "sg:classifiers":[
        {
            "category":"Restaurant",
            "type":"Food & Drink"
        }
    ],
    "sg:phone":"+1 334 565 3544",
    "sg:postcode":"36453",
    "sg:province":"AL",
    "wof:name":"Country Corner Cafe",
    "wof:placetype":"venue"
},
  "geometry": {"coordinates":[-86.172846,31.219199],"type":"Point"}
}