{
  "type": "Feature",
  "properties": {
    "iso:country":"US",
    "sg:address":"3313 Bob Wallace Ave SW",
    "sg:city":"Huntsville",
    "sg:classifiers":[
        {
            "category":"Health Services",
            "subcategory":"Health Practitioner",
            "type":"Services"
        }
    ],
    "sg:phone":"+1 256 535 9545",
    "sg:postcode":"35805",
    "sg:province":"AL",
    "sg:tags":[
        "psychologist"
    ],
    "wof:name":"Donald K Watters PHD",
    "wof:placetype":"venue"
},
  "geometry": {"coordinates":[-86.612359,34.712108],"type":"Point"}
}