{
  "type": "Feature",
  "properties": {
    "addr:full":"440 N Daleville Ave Daleville AL 36322",
    "addr:housenumber":"440",
    "addr:postcode":"36322",
    "addr:street":"N Daleville Ave",
    "iso:country":"US",
    "sg:address":"440 N Daleville Ave",
    "sg:city":"Daleville",
    "sg:classifiers":[
        {
            "category":"Restaurant",
            "type":"Food & Drink"
        }
    ],
    "sg:menulink":"http://www.allmenus.com/al/daleville/87586-little-caesars-pizza/menu/",
    "sg:phone":"+1 334 598 6429",
    "sg:postcode":"36322",
    "sg:province":"AL",
    "sg:tags":[
        "american",
        "pizza"
    ],
    "wof:name":"Little Caesar's Pizza",
    "wof:placetype":"venue"
},
  "geometry": {"coordinates":[-85.711769,31.312379],"type":"Point"}
}