{
  "type": "Feature",
  "properties": {
    "iso:country":"US",
    "sg:address":"100 Riverchase Pkwy E",
    "sg:city":"Birmingham",
    "sg:classifiers":[
        {
            "category":"Food & Beverages",
            "subcategory":"Groceries & Convenience Stores",
            "type":"Retail Goods"
        }
    ],
    "sg:phone":"+1 205 987 7701",
    "sg:postcode":"35244",
    "sg:province":"AL",
    "wof:name":"Sunny Foods 21",
    "wof:placetype":"venue"
},
  "geometry": {"coordinates":[-86.790918,33.365601],"type":"Point"}
}