{
  "type": "Feature",
  "properties": {
    "iso:country":"US",
    "sg:address":"133 Lakeshore Dr",
    "sg:city":"Daphne",
    "sg:classifiers":[
        {
            "category":"Professional",
            "subcategory":"Advertising",
            "type":"Services"
        }
    ],
    "sg:phone":"+1 251 625 4150",
    "sg:postcode":"36526",
    "sg:province":"AL",
    "wof:name":"Scott & Assoc",
    "wof:placetype":"venue"
},
  "geometry": {"coordinates":[-87.903049,30.646964],"type":"Point"}
}