{
  "type": "Feature",
  "properties": {
    "iso:country":"US",
    "sg:address":"1702 W Clark Ave",
    "sg:city":"Prichard",
    "sg:classifiers":[
        {
            "category":"Organizations",
            "subcategory":"Religious Organization",
            "type":"Services"
        }
    ],
    "sg:phone":"+1 251 456 4717",
    "sg:postcode":"36610",
    "sg:province":"AL",
    "sg:tags":[
        "church"
    ],
    "wof:name":"Crockett Memorial AME Zion",
    "wof:placetype":"venue"
},
  "geometry": {"coordinates":[-88.09768099999999,30.729062],"type":"Point"}
}