{
  "type": "Feature",
  "properties": {
    "iso:country":"US",
    "sg:address":"19154 Co Rd 27",
    "sg:city":"Fairhope",
    "sg:classifiers":[
        {
            "category":"Retail",
            "subcategory":"Repair Shop",
            "type":"Services"
        }
    ],
    "sg:phone":"+1 251 928 5937",
    "sg:postcode":"36532",
    "sg:province":"AL",
    "sg:tags":[
        "lock",
        "locksmith"
    ],
    "wof:name":"Baker's Locksmith",
    "wof:placetype":"venue"
},
  "geometry": {"coordinates":[-87.852572,30.505464],"type":"Point"}
}