{
  "type": "Feature",
  "properties": {
    "addr:full":"215 Richard Arrington Jr Blvd N Birmingham AL 35203",
    "addr:housenumber":"215",
    "addr:postcode":"35203",
    "addr:street":"Richard Arrington Jr Blvd N",
    "iso:country":"US",
    "sg:address":"215 Richard Arrington Jr Blvd N",
    "sg:city":"Birmingham",
    "sg:classifiers":[
        {
            "category":"Professional",
            "subcategory":"Lawyer & Legal Services",
            "type":"Services"
        }
    ],
    "sg:phone":"+1 205 323 1234",
    "sg:postcode":"35203",
    "sg:province":"AL",
    "wof:name":"Law Office of Duncan W Casey",
    "wof:placetype":"venue"
},
  "geometry": {"coordinates":[-86.80550599999999,33.516769],"type":"Point"}
}