{
  "type": "Feature",
  "properties": {
    "addr:full":"1017 Ave C Opelika AL 36801",
    "addr:postcode":"36801",
    "addr:street":"1017 Ave C Opelika",
    "iso:country":"US",
    "sg:address":"1017 Ave C",
    "sg:city":"Opelika",
    "sg:classifiers":[
        {
            "category":"Building & Trades",
            "subcategory":"Construction",
            "type":"Services"
        }
    ],
    "sg:phone":"+1 334 749 8880",
    "sg:postcode":"36801",
    "sg:province":"AL",
    "sg:tags":[
        "carpentry",
        "material",
        "contractor"
    ],
    "wof:name":"Witt Custom Repairs",
    "wof:placetype":"venue"
},
  "geometry": {"coordinates":[-85.37853,32.643803],"type":"Point"}
}