{
  "type": "Feature",
  "properties": {
    "iso:country":"US",
    "sg:address":"6323 Maywick Dr NW",
    "sg:city":"Huntsville",
    "sg:classifiers":[
        {
            "category":"Building & Trades",
            "subcategory":"Construction",
            "type":"Services"
        }
    ],
    "sg:phone":"+1 256 746 0646",
    "sg:postcode":"35810",
    "sg:province":"AL",
    "sg:tags":[
        "painter"
    ],
    "wof:name":"Universal Painting & Restor",
    "wof:placetype":"venue"
},
  "geometry": {"coordinates":[-86.594534,34.804542],"type":"Point"}
}