{
  "type": "Feature",
  "properties": {
    "iso:country":"US",
    "sg:address":"370 McKeithen Pl",
    "sg:city":"Millbrook",
    "sg:classifiers":[
        {
            "category":"Real Estate",
            "subcategory":"Real Estate Agent",
            "type":"Services"
        }
    ],
    "sg:phone":"+1 334 285 1995",
    "sg:postcode":"36054",
    "sg:province":"AL",
    "wof:name":"Columns",
    "wof:placetype":"venue"
},
  "geometry": {"coordinates":[-86.36935699999999,32.513563],"type":"Point"}
}