{
  "type": "Feature",
  "properties": {
    "iso:country":"US",
    "sg:address":"5651 Holmes Ave NW",
    "sg:city":"Huntsville",
    "sg:classifiers":[
        {
            "category":"Shopping",
            "subcategory":"Department Store",
            "type":"Retail Goods"
        }
    ],
    "sg:phone":"+1 256 837 7323",
    "sg:postcode":"35816",
    "sg:province":"AL",
    "sg:website":"www.samsclub.com",
    "wof:name":"Sam's Club",
    "wof:placetype":"venue"
},
  "geometry": {"coordinates":[-86.656696,34.736115],"type":"Point"}
}