{
  "type": "Feature",
  "properties": {
    "iso:country":"US",
    "sg:address":"3641 Lorna Rd",
    "sg:city":"Birmingham",
    "sg:classifiers":[
        {
            "category":"Restaurant",
            "type":"Food & Drink"
        }
    ],
    "sg:phone":"+1 205 989 6656",
    "sg:postcode":"35216",
    "sg:province":"AL",
    "sg:tags":[
        "delivery"
    ],
    "wof:name":"El Paisano",
    "wof:placetype":"venue"
},
  "geometry": {"coordinates":[-86.797298,33.381051],"type":"Point"}
}