{
  "type": "Feature",
  "properties": {
    "addr:full":"409 Half Moon Bend Birmingham AL 35206",
    "addr:housenumber":"409",
    "addr:postcode":"35206",
    "addr:street":"Half Moon Bend",
    "iso:country":"US",
    "sg:address":"409 Half Moon Bend",
    "sg:city":"Birmingham",
    "sg:classifiers":[
        {
            "category":"Professional",
            "type":"Services"
        }
    ],
    "sg:phone":"+1 205 833 8776",
    "sg:postcode":"35206",
    "sg:province":"AL",
    "wof:name":"Ferrier Rene",
    "wof:placetype":"venue"
},
  "geometry": {"coordinates":[-86.68783000000001,33.571965],"type":"Point"}
}