{
  "type": "Feature",
  "properties": {
    "iso:country":"US",
    "sg:address":"28691 US Hwy 98",
    "sg:city":"Daphne",
    "sg:classifiers":[
        {
            "category":"Shopping",
            "subcategory":"Florist",
            "type":"Retail Goods"
        }
    ],
    "sg:phone":"+1 251 626 0119",
    "sg:postcode":"36526",
    "sg:province":"AL",
    "wof:name":"Windsor Florist",
    "wof:placetype":"venue"
},
  "geometry": {"coordinates":[-87.91284400000001,30.642245],"type":"Point"}
}