{
  "type": "Feature",
  "properties": {
    "iso:country":"US",
    "sg:address":"119 University Blvd S",
    "sg:city":"Mobile",
    "sg:classifiers":[
        {
            "category":"Building & Trades",
            "subcategory":"Construction",
            "type":"Services"
        }
    ],
    "sg:phone":"+1 251 342 6641",
    "sg:postcode":"36608",
    "sg:province":"AL",
    "sg:tags":[
        "house",
        "business"
    ],
    "wof:name":"Barr Designs",
    "wof:placetype":"venue"
},
  "geometry": {"coordinates":[-88.173428,30.687843],"type":"Point"}
}