{
  "type": "Feature",
  "properties": {
    "iso:country":"US",
    "sg:address":"1559 State Rte 123",
    "sg:city":"Hartford",
    "sg:classifiers":[
        {
            "category":"Shopping",
            "subcategory":"Gifts & Souvenirs",
            "type":"Retail Goods"
        }
    ],
    "sg:phone":"+1 334 588 2839",
    "sg:postcode":"36344",
    "sg:province":"AL",
    "wof:name":"Pams Things",
    "wof:placetype":"venue"
},
  "geometry": {"coordinates":[-85.679751,31.113073],"type":"Point"}
}