{
  "type": "Feature",
  "properties": {
    "addr:full":"434 Ozark Rd Abbeville AL 36310",
    "addr:housenumber":"434",
    "addr:postcode":"36310",
    "addr:street":"Ozark Rd",
    "iso:country":"US",
    "sg:address":"434 Ozark Rd",
    "sg:city":"Abbeville",
    "sg:classifiers":[
        {
            "category":"Retail",
            "subcategory":"Funeral Services",
            "type":"Services"
        }
    ],
    "sg:phone":"+1 334 585 5261",
    "sg:postcode":"36310",
    "sg:province":"AL",
    "sg:tags":[
        "director"
    ],
    "wof:name":"Holman-Abbeville Mortuary",
    "wof:placetype":"venue"
},
  "geometry": {"coordinates":[-85.263386,31.555869],"type":"Point"}
}