{
  "type": "Feature",
  "properties": {
    "iso:country":"US",
    "sg:address":"1510 Gospel Rd",
    "sg:city":"Sheffield",
    "sg:classifiers":[
        {
            "category":"Retail",
            "subcategory":"Auto Repair",
            "type":"Services"
        }
    ],
    "sg:phone":"+1 256 381 5253",
    "sg:postcode":"35660",
    "sg:province":"AL",
    "sg:tags":[
        "trailer"
    ],
    "wof:name":"Jake Enterprises",
    "wof:placetype":"venue"
},
  "geometry": {"coordinates":[-87.670472,34.77375],"type":"Point"}
}