{
  "type": "Feature",
  "properties": {
    "iso:country":"US",
    "sg:address":"1117 23rd Ave",
    "sg:city":"Tuscaloosa",
    "sg:classifiers":[
        {
            "category":"Organizations",
            "subcategory":"Religious Organization",
            "type":"Services"
        }
    ],
    "sg:phone":"+1 205 758 7405",
    "sg:postcode":"35401",
    "sg:province":"AL",
    "sg:tags":[
        "church"
    ],
    "wof:name":"Bailey Tabernacle CME",
    "wof:placetype":"venue"
},
  "geometry": {"coordinates":[-87.56424,33.203756],"type":"Point"}
}