{
  "type": "Feature",
  "properties": {
    "addr:full":"222 Saddle Rock Ct Harvest AL 35749",
    "addr:housenumber":"222",
    "addr:postcode":"35749",
    "addr:street":"Saddle Rock Ct",
    "iso:country":"US",
    "sg:address":"222 Saddle Rock Ct",
    "sg:city":"Harvest",
    "sg:classifiers":[
        {
            "category":"Building & Trades",
            "subcategory":"Construction",
            "type":"Services"
        }
    ],
    "sg:phone":"+1 256 726 9899",
    "sg:postcode":"35749",
    "sg:province":"AL",
    "sg:tags":[
        "house"
    ],
    "wof:name":"Eagle Home Improvement",
    "wof:placetype":"venue"
},
  "geometry": {"coordinates":[-86.75973500000001,34.798175],"type":"Point"}
}