{
  "type": "Feature",
  "properties": {
    "addr:full":"150 W Park Loop NW Huntsville AL 35806",
    "addr:housenumber":"150",
    "addr:postcode":"35806",
    "addr:street":"W Park Loop Nw",
    "iso:country":"US",
    "sg:address":"150 W Park Loop NW",
    "sg:city":"Huntsville",
    "sg:classifiers":[
        {
            "category":"Health Services",
            "subcategory":"Medical Lab",
            "type":"Services"
        }
    ],
    "sg:phone":"+1 256 721 1139",
    "sg:postcode":"35806",
    "sg:province":"AL",
    "sg:tags":[
        "laboratory"
    ],
    "wof:name":"Laboratory Corp Of America",
    "wof:placetype":"venue"
},
  "geometry": {"coordinates":[-86.68997299999999,34.745528],"type":"Point"}
}