{
  "type": "Feature",
  "properties": {
    "addr:full":"4664 Nelson Dr Bessemer AL 35022",
    "addr:housenumber":"4664",
    "addr:postcode":"35022",
    "addr:street":"Nelson Dr",
    "iso:country":"US",
    "sg:address":"4664 Nelson Dr",
    "sg:city":"Bessemer",
    "sg:classifiers":[
        {
            "category":"Building & Trades",
            "subcategory":"Construction",
            "type":"Services"
        }
    ],
    "sg:phone":"+1 205 428 0500",
    "sg:postcode":"35022",
    "sg:province":"AL",
    "sg:tags":[
        "specializing",
        "paving",
        "asphalt",
        "contractor"
    ],
    "wof:name":"Murray Asphalt & Paving",
    "wof:placetype":"venue"
},
  "geometry": {"coordinates":[-86.91913700000001,33.375933],"type":"Point"}
}