{
  "type": "Feature",
  "properties": {
    "iso:country":"US",
    "sg:address":"12836 US Hwy 431",
    "sg:city":"Wedowee",
    "sg:classifiers":[
        {
            "category":"Shopping",
            "subcategory":"Used Merchandise",
            "type":"Retail Goods"
        }
    ],
    "sg:phone":"+1 256 357 2777",
    "sg:postcode":"36278",
    "sg:province":"AL",
    "wof:name":"Now & Then Curiosity Shop",
    "wof:placetype":"venue"
},
  "geometry": {"coordinates":[-85.57215100000001,33.45267],"type":"Point"}
}