{
  "type": "Feature",
  "properties": {
    "addr:full":"4087 Cottage Hill Rd Mobile AL 36609",
    "addr:housenumber":"4087",
    "addr:postcode":"36609",
    "addr:street":"Cottage Hill Rd",
    "iso:country":"US",
    "sg:address":"4087 Cottage Hill Rd",
    "sg:city":"Mobile",
    "sg:classifiers":[
        {
            "category":"Professional",
            "subcategory":"Lawyer & Legal Services",
            "type":"Services"
        }
    ],
    "sg:phone":"+1 251 661 9399",
    "sg:postcode":"36609",
    "sg:province":"AL",
    "sg:tags":[
        "attorney"
    ],
    "wof:name":"Gregory B Mc Atee",
    "wof:placetype":"venue"
},
  "geometry": {"coordinates":[-88.14743799999999,30.652341],"type":"Point"}
}