{
  "type": "Feature",
  "properties": {
    "iso:country":"US",
    "sg:address":"2032 Valleydale Rd",
    "sg:city":"Birmingham",
    "sg:classifiers":[
        {
            "category":"Retail",
            "subcategory":"Portrait Studio",
            "type":"Services"
        }
    ],
    "sg:phone":"+1 205 987 6226",
    "sg:postcode":"35244",
    "sg:province":"AL",
    "sg:tags":[
        "personal",
        "photo",
        "m"
    ],
    "wof:name":"David J Dern Photography Inc",
    "wof:placetype":"venue"
},
  "geometry": {"coordinates":[-86.79045000000001,33.347806],"type":"Point"}
}