{
  "type": "Feature",
  "properties": {
    "iso:country":"US",
    "sg:address":"2690 McKenzie St",
    "sg:city":"Foley",
    "sg:classifiers":[
        {
            "category":"Real Estate",
            "subcategory":"Real Estate Services",
            "type":"Services"
        }
    ],
    "sg:phone":"+1 251 943 1551",
    "sg:postcode":"36535",
    "sg:province":"AL",
    "sg:tags":[
        "company",
        "title"
    ],
    "wof:name":"Alabama Land Title",
    "wof:placetype":"venue"
},
  "geometry": {"coordinates":[-87.683378,30.370387],"type":"Point"}
}