{
  "type": "Feature",
  "properties": {
    "addr:full":"3010 Armstrong Rd Cedar Bluff AL 35959",
    "addr:housenumber":"3010",
    "addr:postcode":"35959",
    "addr:street":"Armstrong Rd",
    "iso:country":"US",
    "sg:address":"3010 Armstrong Rd",
    "sg:city":"Cedar Bluff",
    "sg:classifiers":[
        {
            "category":"Real Estate",
            "subcategory":"Real Estate Agent",
            "type":"Services"
        }
    ],
    "sg:phone":"+1 256 779 3377",
    "sg:postcode":"35959",
    "sg:province":"AL",
    "wof:name":"Nabers Realty",
    "wof:placetype":"venue"
},
  "geometry": {"coordinates":[-85.614355,34.232462],"type":"Point"}
}