{
  "type": "Feature",
  "properties": {
    "iso:country":"US",
    "sg:address":"1456 Co Rd 33",
    "sg:city":"Louisville",
    "sg:classifiers":[
        {
            "category":"Home & Garden",
            "subcategory":"Building Materials",
            "type":"Retail Goods"
        }
    ],
    "sg:phone":"+1 334 266 6077",
    "sg:postcode":"36048",
    "sg:province":"AL",
    "wof:name":"Southeast Wood Trigging",
    "wof:placetype":"venue"
},
  "geometry": {"coordinates":[-85.522378,31.688214],"type":"Point"}
}