{
  "type": "Feature",
  "properties": {
    "iso:country":"US",
    "sg:address":"108 Spinnaker Ln",
    "sg:city":"Alabaster",
    "sg:classifiers":[
        {
            "category":"Manufacturing",
            "subcategory":"Apparel",
            "type":"Manufacturing & Wholesale Goods"
        }
    ],
    "sg:phone":"+1 205 664 4024",
    "sg:postcode":"35007",
    "sg:province":"AL",
    "sg:tags":[
        "household",
        "furnishing",
        "mfg"
    ],
    "wof:name":"Got Pillows",
    "wof:placetype":"venue"
},
  "geometry": {"coordinates":[-86.82995699999999,33.268442],"type":"Point"}
}