{
  "type": "Feature",
  "properties": {
    "addr:full":"1000 S Beltline Hwy Mobile AL 36609",
    "addr:housenumber":"1000",
    "addr:postcode":"36609",
    "addr:street":"S Beltline Hwy",
    "iso:country":"US",
    "sg:address":"1000 S Beltline Hwy",
    "sg:city":"Mobile",
    "sg:classifiers":[
        {
            "category":"Travel",
            "subcategory":"Hotels & Motels",
            "type":"Entertainment"
        }
    ],
    "sg:phone":"+1 251 344 5200",
    "sg:postcode":"36609",
    "sg:province":"AL",
    "sg:tags":[
        "operation",
        "eating"
    ],
    "wof:name":"Courtyard By Marriott",
    "wof:placetype":"venue"
},
  "geometry": {"coordinates":[-88.12767599999999,30.67168],"type":"Point"}
}