{
  "type": "Feature",
  "properties": {
    "iso:country":"US",
    "sg:address":"1053 Stones Throw Dr NW",
    "sg:city":"Huntsville",
    "sg:classifiers":[
        {
            "category":"Professional",
            "type":"Services"
        }
    ],
    "sg:phone":"+1 256 830 6698",
    "sg:postcode":"35806",
    "sg:province":"AL",
    "wof:name":"RMS Services Inc",
    "wof:placetype":"venue"
},
  "geometry": {"coordinates":[-86.668002,34.744536],"type":"Point"}
}