{
  "type": "Feature",
  "properties": {
    "iso:country":"US",
    "sg:address":"3716 Moffett Rd",
    "sg:city":"Mobile",
    "sg:classifiers":[
        {
            "category":"Shopping",
            "subcategory":"Used Merchandise",
            "type":"Retail Goods"
        }
    ],
    "sg:phone":"+1 251 344 2401",
    "sg:postcode":"36618",
    "sg:province":"AL",
    "sg:tags":[
        "pawnbroker"
    ],
    "wof:name":"Alabama Title Loans Inc",
    "wof:placetype":"venue"
},
  "geometry": {"coordinates":[-88.128085,30.710851],"type":"Point"}
}