{
  "type": "Feature",
  "properties": {
    "iso:country":"US",
    "sg:address":"1423 Upper Kingston Rd",
    "sg:city":"Prattville",
    "sg:classifiers":[
        {
            "category":"Organizations",
            "subcategory":"Community Association",
            "type":"Services"
        }
    ],
    "sg:phone":"+1 334 358 9025",
    "sg:postcode":"36067",
    "sg:province":"AL",
    "sg:tags":[
        "fraternal"
    ],
    "wof:name":"Grand Chapter OES Of Al",
    "wof:placetype":"venue"
},
  "geometry": {"coordinates":[-86.467655,32.503121],"type":"Point"}
}