{
  "type": "Feature",
  "properties": {
    "iso:country":"US",
    "sg:address":"215 E Air Depot Rd",
    "sg:city":"Gadsden",
    "sg:classifiers":[
        {
            "category":"Freight",
            "type":"Transportation"
        }
    ],
    "sg:phone":"+1 256 492 1400",
    "sg:postcode":"35905",
    "sg:province":"AL",
    "sg:tags":[
        "warehouse",
        "storage",
        "refrigeration",
        "facility"
    ],
    "wof:name":"Ameri Cold Logistics",
    "wof:placetype":"venue"
},
  "geometry": {"coordinates":[-85.93909499999999,33.964956],"type":"Point"}
}