{
  "type": "Feature",
  "properties": {
    "iso:country":"US",
    "sg:address":"237 Oxmoor Cir",
    "sg:city":"Birmingham",
    "sg:classifiers":[
        {
            "category":"Wholesale",
            "subcategory":"Books, Periodicals, & Newspapers",
            "type":"Manufacturing & Wholesale Goods"
        },
        {
            "category":"Cinema",
            "subcategory":"Movie Rental",
            "type":"Entertainment"
        }
    ],
    "sg:phone":"+1 205 916 0062",
    "sg:postcode":"35209",
    "sg:province":"AL",
    "sg:tags":[
        "magazine",
        "game",
        "video",
        "comic"
    ],
    "wof:name":"An Adult Book & Video Exchange",
    "wof:placetype":"venue"
},
  "geometry": {"coordinates":[-86.837164,33.453228],"type":"Point"}
}