{
  "type": "Feature",
  "properties": {
    "iso:country":"US",
    "sg:address":"11085 Douglas Rd",
    "sg:city":"Grand Bay",
    "sg:classifiers":[
        {
            "category":"Manufacturing",
            "subcategory":"Signs",
            "type":"Manufacturing & Wholesale Goods"
        }
    ],
    "sg:phone":"+1 251 865 1447",
    "sg:postcode":"36541",
    "sg:province":"AL",
    "sg:tags":[
        "specialty",
        "mfg"
    ],
    "wof:name":"Courtney Neon Company",
    "wof:placetype":"venue"
},
  "geometry": {"coordinates":[-88.335055,30.462176],"type":"Point"}
}