{
  "type": "Feature",
  "properties": {
    "iso:country":"US",
    "sg:address":"107 Highland Ave",
    "sg:city":"Union Springs",
    "sg:classifiers":[
        {
            "category":"Building & Trades",
            "subcategory":"Construction",
            "type":"Services"
        }
    ],
    "sg:phone":"+1 334 738 5175",
    "sg:postcode":"36089",
    "sg:province":"AL",
    "sg:tags":[
        "nonresidential"
    ],
    "wof:name":"Wayne Green Contract Inc",
    "wof:placetype":"venue"
},
  "geometry": {"coordinates":[-85.71247700000001,32.1518],"type":"Point"}
}