{
  "type": "Feature",
  "properties": {
    "iso:country":"US",
    "sg:address":"16176 State Rte 22",
    "sg:city":"Clanton",
    "sg:classifiers":[
        {
            "category":"Manufacturing",
            "subcategory":"Tools & Machinery",
            "type":"Manufacturing & Wholesale Goods"
        }
    ],
    "sg:phone":"+1 205 979 9593",
    "sg:postcode":"35045",
    "sg:province":"AL",
    "sg:tags":[
        "equipment",
        "laboratory",
        "supply"
    ],
    "wof:name":"Tri State Balance",
    "wof:placetype":"venue"
},
  "geometry": {"coordinates":[-86.765622,32.81133],"type":"Point"}
}