{
  "type": "Feature",
  "properties": {
    "iso:country":"US",
    "sg:address":"872 Main St W",
    "sg:city":"Rainsville",
    "sg:classifiers":[
        {
            "category":"Autos & Motor Vehicles",
            "subcategory":"Automobile Sales",
            "type":"Retail Goods"
        }
    ],
    "sg:phone":"+1 256 638 3597",
    "sg:postcode":"35986",
    "sg:province":"AL",
    "sg:tags":[
        "used"
    ],
    "wof:name":"Loves Auto Sales",
    "wof:placetype":"venue"
},
  "geometry": {"coordinates":[-85.858755,34.501866],"type":"Point"}
}