{
  "type": "Feature",
  "properties": {
    "iso:country":"US",
    "sg:address":"221 1st Ave E",
    "sg:city":"Oneonta",
    "sg:classifiers":[
        {
            "category":"Wholesale",
            "subcategory":"Medical Equipment & Supplies",
            "type":"Manufacturing & Wholesale Goods"
        }
    ],
    "sg:phone":"+1 205 625 6334",
    "sg:postcode":"35121",
    "sg:province":"AL",
    "sg:tags":[
        "physician",
        "surgeon"
    ],
    "wof:name":"Hyde Medical Supply",
    "wof:placetype":"venue"
},
  "geometry": {"coordinates":[-86.474905,33.945526],"type":"Point"}
}