{
  "type": "Feature",
  "properties": {
    "iso:country":"US",
    "sg:address":"575 Pebble Rd",
    "sg:city":"Montevallo",
    "sg:classifiers":[
        {
            "category":"Building & Trades",
            "subcategory":"Construction",
            "type":"Services"
        }
    ],
    "sg:phone":"+1 205 665 9446",
    "sg:postcode":"35115",
    "sg:province":"AL",
    "sg:tags":[
        "house"
    ],
    "wof:name":"Plus One Construction Inc",
    "wof:placetype":"venue"
},
  "geometry": {"coordinates":[-86.891487,33.117523],"type":"Point"}
}