{
  "type": "Feature",
  "properties": {
    "iso:country":"US",
    "sg:address":"131 Rice Rd",
    "sg:city":"Taylor",
    "sg:classifiers":[
        {
            "category":"Organizations",
            "subcategory":"Religious Organization",
            "type":"Services"
        }
    ],
    "sg:phone":"+1 334 677 5257",
    "sg:postcode":"36301",
    "sg:province":"AL",
    "sg:tags":[
        "church"
    ],
    "wof:name":"Taylor Assembly Of God Church",
    "wof:placetype":"venue"
},
  "geometry": {"coordinates":[-85.46278,31.145665],"type":"Point"}
}