{
  "type": "Feature",
  "properties": {
    "iso:country":"US",
    "sg:address":"2000 Pepperell Pkwy",
    "sg:city":"Opelika",
    "sg:classifiers":[
        {
            "category":"Local Transit",
            "type":"Transportation"
        }
    ],
    "sg:phone":"+1 334 749 1553",
    "sg:postcode":"36801",
    "sg:province":"AL",
    "sg:tags":[
        "passenger"
    ],
    "wof:name":"Emergency Transport System",
    "wof:placetype":"venue"
},
  "geometry": {"coordinates":[-85.40585,32.637955],"type":"Point"}
}