{
  "type": "Feature",
  "properties": {
    "addr:full":"202 E Boundary St Eufaula AL 36027",
    "addr:housenumber":"202",
    "addr:postcode":"36027",
    "addr:street":"E Boundary St",
    "iso:country":"US",
    "sg:address":"202 E Boundary St",
    "sg:city":"Eufaula",
    "sg:classifiers":[
        {
            "category":"Social Services",
            "subcategory":"Job Training",
            "type":"Services"
        }
    ],
    "sg:phone":"+1 334 687 9889",
    "sg:postcode":"36027",
    "sg:province":"AL",
    "sg:tags":[
        "retardation",
        "disabled",
        "mental",
        "dev"
    ],
    "wof:name":"Charles Parramore Work Ctr",
    "wof:placetype":"venue"
},
  "geometry": {"coordinates":[-85.14575600000001,31.880851],"type":"Point"}
}