{
  "type": "Feature",
  "properties": {
    "iso:country":"US",
    "sg:address":"3544 Lorna Ridge Dr",
    "sg:city":"Birmingham",
    "sg:classifiers":[
        {
            "category":"Wholesale",
            "subcategory":"Medical Equipment & Supplies",
            "type":"Manufacturing & Wholesale Goods"
        }
    ],
    "sg:phone":"+1 205 978 8819",
    "sg:postcode":"35216",
    "sg:province":"AL",
    "sg:tags":[
        "physician",
        "surgeon"
    ],
    "wof:name":"Capital Medical Systems LLC",
    "wof:placetype":"venue"
},
  "geometry": {"coordinates":[-86.79421600000001,33.390928],"type":"Point"}
}