{
  "type": "Feature",
  "properties": {
    "iso:country":"US",
    "sg:address":"2141 Fox Ridge Rd",
    "sg:city":"Tuscaloosa",
    "sg:classifiers":[
        {
            "category":"Building & Trades",
            "subcategory":"Landscaping Services",
            "type":"Services"
        }
    ],
    "sg:phone":"+1 205 752 8816",
    "sg:postcode":"35406",
    "sg:province":"AL",
    "wof:name":"Philip Henderson Lawncare & Co",
    "wof:placetype":"venue"
},
  "geometry": {"coordinates":[-87.563225,33.227627],"type":"Point"}
}