{
  "type": "Feature",
  "properties": {
    "iso:country":"US",
    "sg:address":"405 Eastern Blvd",
    "sg:city":"Montgomery",
    "sg:classifiers":[
        {
            "category":"Autos & Motor Vehicles",
            "subcategory":"Automobile Sales",
            "type":"Retail Goods"
        }
    ],
    "sg:phone":"+1 334 271 1730",
    "sg:postcode":"36117",
    "sg:province":"AL",
    "sg:tags":[
        "car",
        "dealer"
    ],
    "sg:website":"www.mcgoughmotors.com",
    "wof:name":"Mc Gough Mazda",
    "wof:placetype":"venue"
},
  "geometry": {"coordinates":[-86.209254,32.371808],"type":"Point"}
}