{
  "type": "Feature",
  "properties": {
    "addr:full":"5516 Winchester Rd New Market AL 35761",
    "addr:housenumber":"5516",
    "addr:postcode":"35761",
    "addr:street":"Winchester Rd",
    "iso:country":"US",
    "sg:address":"5516 Winchester Rd",
    "sg:city":"New Market",
    "sg:classifiers":[
        {
            "category":"Government",
            "subcategory":"Post Office",
            "type":"Public Place"
        }
    ],
    "sg:phone":"+1 256 379 2997",
    "sg:postcode":"35761",
    "sg:province":"AL",
    "sg:tags":[
        "postal",
        "us"
    ],
    "wof:name":"New Market Main Office",
    "wof:placetype":"venue"
},
  "geometry": {"coordinates":[-86.42775899999999,34.911699],"type":"Point"}
}