{
  "type": "Feature",
  "properties": {
    "addr:full":"7405 Berneys Station Rd Talladega AL 35160",
    "addr:housenumber":"7405",
    "addr:postcode":"35160",
    "addr:street":"Berneys Station Rd",
    "iso:country":"US",
    "sg:address":"7405 Berneys Station Rd",
    "sg:city":"Talladega",
    "sg:classifiers":[
        {
            "category":"Retail",
            "subcategory":"Repair Shop",
            "type":"Services"
        }
    ],
    "sg:phone":"+1 256 362 9282",
    "sg:postcode":"35160",
    "sg:province":"AL",
    "sg:tags":[
        "machine",
        "washing"
    ],
    "wof:name":"Mowery Refrigeration & Appl",
    "wof:placetype":"venue"
},
  "geometry": {"coordinates":[-86.134208,33.346756],"type":"Point"}
}