{
  "type": "Feature",
  "properties": {
    "iso:country":"US",
    "sg:address":"303 1st St S",
    "sg:city":"Clanton",
    "sg:classifiers":[
        {
            "category":"Utilities",
            "subcategory":"Natural Gas",
            "type":"Services"
        }
    ],
    "sg:phone":"+1 205 755 5162",
    "sg:postcode":"35045",
    "sg:province":"AL",
    "sg:tags":[
        "distribution"
    ],
    "wof:name":"Alagasco",
    "wof:placetype":"venue"
},
  "geometry": {"coordinates":[-86.623373,32.83886],"type":"Point"}
}