{
  "type": "Feature",
  "properties": {
    "addr:full":"100 19th St N Birmingham AL 35210",
    "addr:housenumber":"100",
    "addr:postcode":"35210",
    "addr:street":"19Th St N",
    "iso:country":"US",
    "sg:address":"100 19th St N",
    "sg:city":"Birmingham",
    "sg:classifiers":[
        {
            "category":"Building & Trades",
            "subcategory":"Electrical",
            "type":"Services"
        }
    ],
    "sg:phone":"+1 205 956 3332",
    "sg:postcode":"35210",
    "sg:province":"AL",
    "sg:tags":[
        "refrigeration"
    ],
    "wof:name":"Scientific Refrigeration Svcs",
    "wof:placetype":"venue"
},
  "geometry": {"coordinates":[-86.70874499999999,33.538835],"type":"Point"}
}