{
  "type": "Feature",
  "properties": {
    "iso:country":"US",
    "sg:address":"100 19th St N",
    "sg:city":"Birmingham",
    "sg:classifiers":[
        {
            "category":"Building & Trades",
            "subcategory":"Electrical",
            "type":"Services"
        }
    ],
    "sg:phone":"+1 205 956 3332",
    "sg:postcode":"35210",
    "sg:province":"AL",
    "sg:tags":[
        "refrigeration"
    ],
    "wof:name":"Scientific Refrigeration Svcs",
    "wof:placetype":"venue"
},
  "geometry": {"coordinates":[-86.708745,33.538835],"type":"Point"}
}