{
  "type": "Feature",
  "properties": {
    "iso:country":"US",
    "sg:address":"11 85th St N",
    "sg:city":"Birmingham",
    "sg:classifiers":[
        {
            "category":"Professional",
            "subcategory":"Accounting & Tax Preparation",
            "type":"Services"
        }
    ],
    "sg:phone":"+1 205 833 1897",
    "sg:postcode":"35206",
    "sg:province":"AL",
    "sg:tags":[
        "accountant",
        "bookkeeping"
    ],
    "wof:name":"Prickett Charles T & Assoc",
    "wof:placetype":"venue"
},
  "geometry": {"coordinates":[-86.719803,33.573799],"type":"Point"}
}