{
  "type": "Feature",
  "properties": {
    "iso:country":"US",
    "sg:address":"701 E 6th St",
    "sg:city":"Prattville",
    "sg:classifiers":[
        {
            "category":"Real Estate",
            "subcategory":"Real Estate Operator",
            "type":"Services"
        }
    ],
    "sg:phone":"+1 334 365 3442",
    "sg:postcode":"36067",
    "sg:province":"AL",
    "sg:tags":[
        "apartment"
    ],
    "wof:name":"Prattwood Apartments",
    "wof:placetype":"venue"
},
  "geometry": {"coordinates":[-86.452624,32.469394],"type":"Point"}
}