{
  "type": "Feature",
  "properties": {
    "addr:full":"1108 Rucker Blvd Enterprise AL 36330",
    "addr:housenumber":"1108",
    "addr:postcode":"36330",
    "addr:street":"Rucker Blvd",
    "iso:country":"US",
    "sg:address":"1108 Rucker Blvd",
    "sg:city":"Enterprise",
    "sg:classifiers":[
        {
            "category":"Retail",
            "subcategory":"Repair Shop",
            "type":"Services"
        }
    ],
    "sg:phone":"+1 334 347 7800",
    "sg:postcode":"36330",
    "sg:province":"AL",
    "sg:website":"www.framery.com",
    "wof:name":"Framery",
    "wof:placetype":"venue"
},
  "geometry": {"coordinates":[-85.821073,31.326302],"type":"Point"}
}