{
  "type": "Feature",
  "properties": {
    "iso:country":"US",
    "sg:address":"124 Co Rd 316",
    "sg:city":"Bryant",
    "sg:classifiers":[
        {
            "category":"Restaurant",
            "type":"Food & Drink"
        }
    ],
    "sg:phone":"+1 256 597 2510",
    "sg:postcode":"35958",
    "sg:province":"AL",
    "sg:tags":[
        "eating"
    ],
    "wof:name":"Terry Romans",
    "wof:placetype":"venue"
},
  "geometry": {"coordinates":[-85.621144,34.856407],"type":"Point"}
}