{
  "type": "Feature",
  "properties": {
    "iso:country":"US",
    "sg:address":"313 Fieldstown Rd",
    "sg:city":"Gardendale",
    "sg:classifiers":[
        {
            "category":"Shopping",
            "subcategory":"Pharmacy",
            "type":"Retail Goods"
        }
    ],
    "sg:phone":"+1 205 631 5506",
    "sg:postcode":"35071",
    "sg:province":"AL",
    "wof:name":"William & Mary Pharmacy Inc",
    "wof:placetype":"venue"
},
  "geometry": {"coordinates":[-86.81411,33.651719],"type":"Point"}
}