{
  "type": "Feature",
  "properties": {
    "iso:country":"US",
    "sg:address":"108 N Court St",
    "sg:city":"Florence",
    "sg:classifiers":[
        {
            "category":"Home & Garden",
            "subcategory":"Furniture",
            "type":"Retail Goods"
        }
    ],
    "sg:phone":"+1 256 389 8882",
    "sg:postcode":"35630",
    "sg:province":"AL",
    "wof:name":"High Cotton",
    "wof:placetype":"venue"
},
  "geometry": {"coordinates":[-87.676358,34.800999],"type":"Point"}
}