{
  "type": "Feature",
  "properties": {
    "iso:country":"US",
    "sg:address":"2051 Canyon Rd",
    "sg:city":"Birmingham",
    "sg:classifiers":[
        {
            "category":"Manufacturing",
            "subcategory":"Printing",
            "type":"Manufacturing & Wholesale Goods"
        }
    ],
    "sg:phone":"+1 205 979 5247",
    "sg:postcode":"35216",
    "sg:province":"AL",
    "sg:tags":[
        "lithographic",
        "commercial",
        "photocopying"
    ],
    "wof:name":"KWIK KOPY Printing",
    "wof:placetype":"venue"
},
  "geometry": {"coordinates":[-86.78967,33.445175],"type":"Point"}
}