{
  "type": "Feature",
  "properties": {
    "iso:country":"US",
    "sg:address":"137 W Oxmoor Rd",
    "sg:city":"Birmingham",
    "sg:classifiers":[
        {
            "category":"Retail",
            "subcategory":"Auto Repair",
            "type":"Services"
        }
    ],
    "sg:phone":"+1 205 942 9779",
    "sg:postcode":"35209",
    "sg:province":"AL",
    "sg:tags":[
        "general"
    ],
    "wof:name":"Alafleet LLC",
    "wof:placetype":"venue"
},
  "geometry": {"coordinates":[-86.841077,33.445025],"type":"Point"}
}