{
  "type": "Feature",
  "properties": {
    "iso:country":"US",
    "sg:address":"3813 Huntsville Ave",
    "sg:city":"Brighton",
    "sg:classifiers":[
        {
            "category":"Home & Garden",
            "subcategory":"Furniture",
            "type":"Retail Goods"
        }
    ],
    "sg:phone":"+1 205 425 2512",
    "sg:postcode":"35020",
    "sg:province":"AL",
    "sg:tags":[
        "household"
    ],
    "wof:name":"Brighton House Furniture Co",
    "wof:placetype":"venue"
},
  "geometry": {"coordinates":[-86.95053799999999,33.431233],"type":"Point"}
}