{
  "type": "Feature",
  "properties": {
    "addr:full":"3816 Pepperell Pkwy Opelika AL 36801",
    "addr:housenumber":"3816",
    "addr:postcode":"36801",
    "addr:street":"Pepperell Pkwy Opelika",
    "iso:country":"US",
    "sg:address":"3816 Pepperell Pkwy",
    "sg:city":"Opelika",
    "sg:classifiers":[
        {
            "category":"Food & Beverages",
            "subcategory":"Bakery",
            "type":"Retail Goods"
        }
    ],
    "sg:phone":"+1 334 737 0362",
    "sg:postcode":"36801",
    "sg:province":"AL",
    "sg:tags":[
        "baker"
    ],
    "wof:name":"Merita Thrift Store",
    "wof:placetype":"venue"
},
  "geometry": {"coordinates":[-85.432807,32.633024],"type":"Point"}
}