{
  "type": "Feature",
  "properties": {
    "addr:full":"225 J C Mauldin Hwy Killen AL 35645",
    "addr:housenumber":"225",
    "addr:postcode":"35645",
    "addr:street":"J C Mauldin Hwy",
    "iso:country":"US",
    "sg:address":"225 J C Mauldin Hwy",
    "sg:city":"Killen",
    "sg:classifiers":[
        {
            "category":"Recreation",
            "type":"Entertainment"
        }
    ],
    "sg:phone":"+1 256 757 6583",
    "sg:postcode":"35645",
    "sg:province":"AL",
    "sg:tags":[
        "parks"
    ],
    "wof:name":"Killen Recreation Director",
    "wof:placetype":"venue"
},
  "geometry": {"coordinates":[-87.542074,34.858863],"type":"Point"}
}