{
  "type": "Feature",
  "properties": {
    "iso:country":"US",
    "sg:address":"510 Bodine Rd",
    "sg:city":"Oneonta",
    "sg:classifiers":[
        {
            "category":"Building & Trades",
            "subcategory":"Construction",
            "type":"Services"
        }
    ],
    "sg:phone":"+1 205 625 4409",
    "sg:postcode":"35121",
    "sg:province":"AL",
    "sg:tags":[
        "concrete",
        "contractor"
    ],
    "wof:name":"John A Bodine Construction",
    "wof:placetype":"venue"
},
  "geometry": {"coordinates":[-86.451093,34.02745],"type":"Point"}
}