{
  "type": "Feature",
  "properties": {
    "addr:full":"102 1st St S Clanton AL 35045",
    "addr:housenumber":"102",
    "addr:postcode":"35045",
    "addr:street":"1St St S",
    "iso:country":"US",
    "sg:address":"102 1st St S",
    "sg:city":"Clanton",
    "sg:classifiers":[
        {
            "category":"Education",
            "subcategory":"School",
            "type":"Public Place"
        }
    ],
    "sg:phone":"+1 205 280 2750",
    "sg:postcode":"35045",
    "sg:province":"AL",
    "wof:name":"Henry M Adair Middle School",
    "wof:placetype":"venue"
},
  "geometry": {"coordinates":[-86.62549199999999,32.842636],"type":"Point"}
}