{
  "type": "Feature",
  "properties": {
    "iso:country":"US",
    "sg:address":"555 Adams Creek Rd",
    "sg:city":"Chancellor",
    "sg:classifiers":[
        {
            "category":"Farming",
            "subcategory":"Livestock Farm",
            "type":"Manufacturing & Wholesale Goods"
        }
    ],
    "sg:phone":"+1 334 684 2094",
    "sg:postcode":"36316",
    "sg:province":"AL",
    "sg:tags":[
        "beef",
        "feedlot",
        "cattle"
    ],
    "wof:name":"Daniel Cotton",
    "wof:placetype":"venue"
},
  "geometry": {"coordinates":[-85.836826,31.108857],"type":"Point"}
}