{
  "type": "Feature",
  "properties": {
    "addr:full":"219 Haynes St Talladega AL 35160",
    "addr:housenumber":"219",
    "addr:postcode":"35160",
    "addr:street":"Haynes St",
    "iso:country":"US",
    "sg:address":"219 Haynes St",
    "sg:city":"Talladega",
    "sg:classifiers":[
        {
            "category":"Restaurant",
            "type":"Food & Drink"
        }
    ],
    "sg:menulink":"http://www.allmenus.com/al/talladega/198632-kfc---kentucky-fried-chicken/menu/",
    "sg:phone":"+1 256 362 5681",
    "sg:postcode":"35160",
    "sg:province":"AL",
    "sg:tags":[
        "american",
        "chicken"
    ],
    "wof:name":"KFC - Kentucky Fried Chicken",
    "wof:placetype":"venue"
},
  "geometry": {"coordinates":[-86.081346,33.435016],"type":"Point"}
}