{
  "type": "Feature",
  "properties": {
    "addr:full":"11335 Cardinal Dr Madison AL 35756",
    "addr:housenumber":"11335",
    "addr:postcode":"35756",
    "addr:street":"Cardinal Dr",
    "iso:country":"US",
    "sg:address":"11335 Cardinal Dr",
    "sg:city":"Madison",
    "sg:classifiers":[
        {
            "category":"Professional",
            "subcategory":"Accounting & Tax Preparation",
            "type":"Services"
        }
    ],
    "sg:phone":"+1 256 232 6398",
    "sg:postcode":"35756",
    "sg:province":"AL",
    "sg:tags":[
        "return",
        "filing"
    ],
    "wof:name":"1 Day Tax Prep & Bookkeeping",
    "wof:placetype":"venue"
},
  "geometry": {"coordinates":[-86.803332,34.717218],"type":"Point"}
}