{
  "type": "Feature",
  "properties": {
    "iso:country":"US",
    "sg:address":"7662 William Howton Rd",
    "sg:city":"Mulga",
    "sg:classifiers":[
        {
            "category":"Manufacturing",
            "subcategory":"Tools & Machinery",
            "type":"Manufacturing & Wholesale Goods"
        }
    ],
    "sg:phone":"+1 205 436 4260",
    "sg:postcode":"35118",
    "sg:province":"AL",
    "sg:tags":[
        "industry",
        "mfg"
    ],
    "wof:name":"White Equipment Co",
    "wof:placetype":"venue"
},
  "geometry": {"coordinates":[-87.08976,33.523677],"type":"Point"}
}