{
  "type": "Feature",
  "properties": {
    "iso:country":"US",
    "sg:address":"9491 State Rte 168",
    "sg:city":"Boaz",
    "sg:classifiers":[
        {
            "category":"Retail",
            "subcategory":"Auto Repair",
            "type":"Services"
        }
    ],
    "sg:phone":"+1 256 593 0777",
    "sg:postcode":"35957",
    "sg:province":"AL",
    "sg:tags":[
        "general"
    ],
    "wof:name":"GLA Automotive",
    "wof:placetype":"venue"
},
  "geometry": {"coordinates":[-86.1752,34.198338],"type":"Point"}
}