{
  "type": "Feature",
  "properties": {
    "iso:country":"US",
    "sg:address":"113 Railroad St SW",
    "sg:city":"Hartselle",
    "sg:classifiers":[
        {
            "category":"Personal",
            "subcategory":"Beauty Salon",
            "type":"Services"
        }
    ],
    "sg:phone":"+1 256 773 8953",
    "sg:postcode":"35640",
    "sg:province":"AL",
    "wof:name":"Kama Salon",
    "wof:placetype":"venue"
},
  "geometry": {"coordinates":[-86.93347799999999,34.443839],"type":"Point"}
}