{
  "type": "Feature",
  "properties": {
    "iso:country":"US",
    "sg:address":"1520 Montclair Rd",
    "sg:city":"Birmingham",
    "sg:classifiers":[
        {
            "category":"Professional",
            "subcategory":"Accounting & Tax Preparation",
            "type":"Services"
        }
    ],
    "sg:phone":"+1 205 956 6625",
    "sg:postcode":"35210",
    "sg:province":"AL",
    "sg:tags":[
        "return"
    ],
    "wof:name":"Jackson Hewitt Tax Service",
    "wof:placetype":"venue"
},
  "geometry": {"coordinates":[-86.72631199999999,33.523701],"type":"Point"}
}