{
  "type": "Feature",
  "properties": {
    "addr:full":"8583 State Rte 59 Foley AL 36535",
    "addr:housenumber":"8583",
    "addr:postcode":"36535",
    "addr:street":"State Rte 59",
    "iso:country":"US",
    "sg:address":"8583 State Rte 59",
    "sg:city":"Foley",
    "sg:classifiers":[
        {
            "category":"Retail",
            "subcategory":"Auto Repair",
            "type":"Services"
        }
    ],
    "sg:phone":"+1 800 800 2727",
    "sg:postcode":"36535",
    "sg:province":"AL",
    "sg:tags":[
        "glass",
        "replacement"
    ],
    "wof:name":"Safelite Autoglass",
    "wof:placetype":"venue"
},
  "geometry": {"coordinates":[-87.682976,30.345384],"type":"Point"}
}