{
  "type": "Feature",
  "properties": {
    "iso:country":"US",
    "sg:address":"720 Ewing Ave",
    "sg:city":"Gadsden",
    "sg:classifiers":[
        {
            "category":"Professional",
            "type":"Services"
        }
    ],
    "sg:phone":"+1 256 547 2912",
    "sg:postcode":"35901",
    "sg:province":"AL",
    "sg:tags":[
        "establishment"
    ],
    "wof:name":"Riverhill Estates",
    "wof:placetype":"venue"
},
  "geometry": {"coordinates":[-85.987916,34.026171],"type":"Point"}
}