{
  "type": "Feature",
  "properties": {
    "iso:country":"US",
    "sg:address":"2620 Centron Dr SW",
    "sg:city":"Decatur",
    "sg:classifiers":[
        {
            "category":"Shopping",
            "subcategory":"Optical Goods",
            "type":"Retail Goods"
        }
    ],
    "sg:phone":"+1 256 350 2020",
    "sg:postcode":"35603",
    "sg:province":"AL",
    "wof:name":"Marx Optical",
    "wof:placetype":"venue"
},
  "geometry": {"coordinates":[-87.008797,34.562872],"type":"Point"}
}