{
  "type": "Feature",
  "properties": {
    "iso:country":"US",
    "sg:address":"2917 Ashville Dr SW",
    "sg:city":"Decatur",
    "sg:classifiers":[
        {
            "category":"Shopping",
            "subcategory":"Computers & Home Electronics",
            "type":"Retail Goods"
        }
    ],
    "sg:phone":"+1 256 341 5822",
    "sg:postcode":"35603",
    "sg:province":"AL",
    "wof:name":"Bull Information Systems",
    "wof:placetype":"venue"
},
  "geometry": {"coordinates":[-87.03500099999999,34.557795],"type":"Point"}
}