{
  "type": "Feature",
  "properties": {
    "iso:country":"US",
    "sg:address":"10578 Co Rd 55",
    "sg:city":"Sterrett",
    "sg:classifiers":[
        {
            "category":"Manufacturing",
            "subcategory":"Tools & Machinery",
            "type":"Manufacturing & Wholesale Goods"
        }
    ],
    "sg:phone":"+1 205 678 0310",
    "sg:postcode":"35186",
    "sg:province":"AL",
    "sg:tags":[
        "process",
        "control",
        "mfg",
        "instrument"
    ],
    "wof:name":"Druck Inc",
    "wof:placetype":"venue"
},
  "geometry": {"coordinates":[-86.533602,33.3644],"type":"Point"}
}