{
  "type": "Feature",
  "properties": {
    "iso:country":"US",
    "sg:address":"6507 Foxleigh Ct",
    "sg:city":"Montgomery",
    "sg:classifiers":[
        {
            "category":"Building & Trades",
            "subcategory":"Plumbing",
            "type":"Services"
        }
    ],
    "sg:phone":"+1 334 546 6936",
    "sg:postcode":"36116",
    "sg:province":"AL",
    "sg:tags":[
        "contractor"
    ],
    "wof:name":"Four Seasons Htg A Conditionin",
    "wof:placetype":"venue"
},
  "geometry": {"coordinates":[-86.210333,32.321199],"type":"Point"}
}