{
  "type": "Feature",
  "properties": {
    "iso:country":"US",
    "sg:address":"523 State Rte 1",
    "sg:city":"Dothan",
    "sg:classifiers":[
        {
            "category":"Professional",
            "type":"Services"
        }
    ],
    "sg:phone":"+1 334 702 3380",
    "sg:postcode":"36301",
    "sg:province":"AL",
    "sg:tags":[
        "establishment"
    ],
    "wof:name":"Mccray Ulysesse",
    "wof:placetype":"venue"
},
  "geometry": {"coordinates":[-85.392971,31.217227],"type":"Point"}
}