{
  "type": "Feature",
  "properties": {
    "iso:country":"US",
    "sg:address":"117 Malaga Ave",
    "sg:city":"Birmingham",
    "sg:classifiers":[
        {
            "category":"Professional",
            "type":"Services"
        }
    ],
    "sg:phone":"+1 205 879 7838",
    "sg:postcode":"35209",
    "sg:province":"AL",
    "wof:name":"Softrock LLC",
    "wof:placetype":"venue"
},
  "geometry": {"coordinates":[-86.781071,33.481305],"type":"Point"}
}