{
  "type": "Feature",
  "properties": {
    "iso:country":"US",
    "sg:address":"3054 State Rte 143",
    "sg:city":"Marbury",
    "sg:classifiers":[
        {
            "category":"Restaurant",
            "type":"Food & Drink"
        }
    ],
    "sg:phone":"+1 205 755 3768",
    "sg:postcode":"36051",
    "sg:province":"AL",
    "wof:name":"Patsy's Kitchen",
    "wof:placetype":"venue"
},
  "geometry": {"coordinates":[-86.473483,32.703185],"type":"Point"}
}