{
  "type": "Feature",
  "properties": {
    "addr:full":"801 Princeton Ave SW Birmingham AL 35211",
    "addr:housenumber":"801",
    "addr:postcode":"35211",
    "addr:street":"Princeton Ave Sw",
    "iso:country":"US",
    "sg:address":"801 Princeton Ave SW",
    "sg:city":"Birmingham",
    "sg:classifiers":[
        {
            "category":"Health Services",
            "subcategory":"Doctor",
            "type":"Services"
        }
    ],
    "sg:phone":"+1 205 786 5527",
    "sg:postcode":"35211",
    "sg:province":"AL",
    "sg:tags":[
        "physician",
        "surgeon"
    ],
    "wof:name":"Gastroenterology Associates",
    "wof:placetype":"venue"
},
  "geometry": {"coordinates":[-86.849215,33.497231],"type":"Point"}
}