{
  "type": "Feature",
  "properties": {
    "iso:country":"US",
    "sg:address":"641 Co Rd 691",
    "sg:city":"Holly Pond",
    "sg:classifiers":[
        {
            "category":"Farming",
            "subcategory":"Farm & Veterinary Services",
            "type":"Manufacturing & Wholesale Goods"
        }
    ],
    "sg:phone":"+1 256 796 2934",
    "sg:postcode":"35083",
    "sg:province":"AL",
    "sg:tags":[
        "livestock"
    ],
    "wof:name":"Inez Sams Poultry Farm",
    "wof:placetype":"venue"
},
  "geometry": {"coordinates":[-86.58846800000001,34.14813],"type":"Point"}
}