{
  "type": "Feature",
  "properties": {
    "addr:full":"330 Sutton Rd Owens Cross Rds AL 35763",
    "addr:housenumber":"330",
    "addr:postcode":"35763",
    "addr:street":"Sutton Rd",
    "iso:country":"US",
    "sg:address":"330 Sutton Rd",
    "sg:city":"Owens Cross Rds",
    "sg:classifiers":[
        {
            "category":"Personal",
            "subcategory":"Beauty Salon",
            "type":"Services"
        }
    ],
    "sg:phone":"+1 256 539 2237",
    "sg:postcode":"35763",
    "sg:province":"AL",
    "wof:name":"Smart Style Family Hair Salon",
    "wof:placetype":"venue"
},
  "geometry": {"coordinates":[-86.487691,34.660101],"type":"Point"}
}