{
  "type": "Feature",
  "properties": {
    "iso:country":"US",
    "sg:address":"124 Hamric Dr E",
    "sg:city":"Oxford",
    "sg:classifiers":[
        {
            "category":"Retail",
            "subcategory":"Auto Repair",
            "type":"Services"
        }
    ],
    "sg:phone":"+1 256 831 4392",
    "sg:postcode":"36203",
    "sg:province":"AL",
    "sg:tags":[
        "muffler",
        "exhaust",
        "system"
    ],
    "wof:name":"Oxford Muffler & Automotive",
    "wof:placetype":"venue"
},
  "geometry": {"coordinates":[-85.833584,33.607139],"type":"Point"}
}