{
  "type": "Feature",
  "properties": {
    "iso:country":"US",
    "sg:address":"1480 Montgomery Hwy",
    "sg:city":"Birmingham",
    "sg:classifiers":[
        {
            "category":"Professional",
            "subcategory":"Lawyer & Legal Services",
            "type":"Services"
        }
    ],
    "sg:phone":"+1 205 823 8393",
    "sg:postcode":"35216",
    "sg:province":"AL",
    "wof:name":"James T Collins",
    "wof:placetype":"venue"
},
  "geometry": {"coordinates":[-86.80381,33.415762],"type":"Point"}
}