{
  "type": "Feature",
  "properties": {
    "iso:country":"US",
    "sg:address":"20 Bealle Cir",
    "sg:city":"Tuscaloosa",
    "sg:classifiers":[
        {
            "category":"Education",
            "subcategory":"School",
            "type":"Public Place"
        }
    ],
    "sg:phone":"+1 205 554 0565",
    "sg:postcode":"35404",
    "sg:province":"AL",
    "wof:name":"City Programs-Tuscaloosa Cnty",
    "wof:placetype":"venue"
},
  "geometry": {"coordinates":[-87.497417,33.241052],"type":"Point"}
}