{
  "type": "Feature",
  "properties": {
    "iso:country":"US",
    "sg:address":"2109 33rd Ave N",
    "sg:city":"Birmingham",
    "sg:classifiers":[
        {
            "category":"Retail",
            "subcategory":"Auto Repair",
            "type":"Services"
        }
    ],
    "sg:phone":"+1 205 322 7946",
    "sg:postcode":"35207",
    "sg:province":"AL",
    "sg:tags":[
        "general"
    ],
    "wof:name":"Rays Auto Repair",
    "wof:placetype":"venue"
},
  "geometry": {"coordinates":[-86.825074,33.552923],"type":"Point"}
}