{
  "type": "Feature",
  "properties": {
    "iso:country":"US",
    "sg:address":"308 Bus Center Dr",
    "sg:city":"Birmingham",
    "sg:classifiers":[
        {
            "category":"Professional",
            "subcategory":"Engineering",
            "type":"Services"
        },
        {
            "category":"Manufacturing",
            "subcategory":"Electronics",
            "type":"Manufacturing & Wholesale Goods"
        }
    ],
    "sg:phone":"+1 205 987 7717",
    "sg:postcode":"35244",
    "sg:province":"AL",
    "sg:tags":[
        "engineer"
    ],
    "sg:website":"www.epic-solutions.com",
    "wof:name":"Epic Solutions Inc",
    "wof:placetype":"venue"
},
  "geometry": {"coordinates":[-86.790442,33.349488],"type":"Point"}
}