{
  "type": "Feature",
  "properties": {
    "iso:country":"US",
    "sg:address":"218 Co Rd 1450",
    "sg:city":"Cullman",
    "sg:classifiers":[
        {
            "category":"Farming",
            "subcategory":"Livestock Farm",
            "type":"Manufacturing & Wholesale Goods"
        }
    ],
    "sg:phone":"+1 256 734 3277",
    "sg:postcode":"35058",
    "sg:province":"AL",
    "sg:tags":[
        "beef",
        "feedlot",
        "cattle"
    ],
    "wof:name":"B Nobinger",
    "wof:placetype":"venue"
},
  "geometry": {"coordinates":[-86.791117,34.245558],"type":"Point"}
}