{
  "type": "Feature",
  "properties": {
    "iso:country":"US",
    "sg:address":"75 River St",
    "sg:city":"Coffeeville",
    "sg:classifiers":[
        {
            "category":"Autos & Motor Vehicles",
            "subcategory":"Fuel & Gas Station",
            "type":"Retail Goods"
        }
    ],
    "sg:phone":"+1 251 276 3633",
    "sg:postcode":"36524",
    "sg:province":"AL",
    "sg:tags":[
        "oil"
    ],
    "wof:name":"Walker's BP",
    "wof:placetype":"venue"
},
  "geometry": {"coordinates":[-88.09030799999999,31.75824],"type":"Point"}
}