{
  "type": "Feature",
  "properties": {
    "iso:country":"US",
    "sg:address":"7001 Bellingrath Rd",
    "sg:city":"Theodore",
    "sg:classifiers":[
        {
            "category":"Freight",
            "type":"Transportation"
        }
    ],
    "sg:phone":"+1 251 653 5585",
    "sg:postcode":"36582",
    "sg:province":"AL",
    "wof:name":"Fleet Transportation Services",
    "wof:placetype":"venue"
},
  "geometry": {"coordinates":[-88.172817,30.546039],"type":"Point"}
}