{
  "type": "Feature",
  "properties": {
    "addr:full":"1813 Westend Ct Opelika AL 36801",
    "addr:housenumber":"1813",
    "addr:postcode":"36801",
    "addr:street":"Westend Ct",
    "iso:country":"US",
    "sg:address":"1813 Westend Ct",
    "sg:city":"Opelika",
    "sg:classifiers":[
        {
            "category":"Personal",
            "subcategory":"Beauty Salon",
            "type":"Services"
        }
    ],
    "sg:phone":"+1 334 745 0603",
    "sg:postcode":"36801",
    "sg:province":"AL",
    "sg:tags":[
        "shop"
    ],
    "wof:name":"New Birth Hair Designs",
    "wof:placetype":"venue"
},
  "geometry": {"coordinates":[-85.397914,32.638348],"type":"Point"}
}