{
  "type": "Feature",
  "properties": {
    "iso:country":"US",
    "sg:address":"2413 19th St N",
    "sg:city":"Bessemer",
    "sg:classifiers":[
        {
            "category":"Building & Trades",
            "subcategory":"Construction",
            "type":"Services"
        }
    ],
    "sg:phone":"+1 205 664 3751",
    "sg:postcode":"35020",
    "sg:province":"AL",
    "sg:tags":[
        "fence",
        "contractor"
    ],
    "wof:name":"Metro Fence Inc",
    "wof:placetype":"venue"
},
  "geometry": {"coordinates":[-86.98186699999999,33.418911],"type":"Point"}
}