{
  "type": "Feature",
  "properties": {
    "iso:country":"US",
    "sg:address":"1151 Springhill Ave",
    "sg:city":"Mobile",
    "sg:classifiers":[
        {
            "category":"Recreation",
            "type":"Entertainment"
        }
    ],
    "sg:phone":"+1 251 438 7415",
    "sg:postcode":"36604",
    "sg:province":"AL",
    "sg:tags":[
        "hall",
        "auditorium"
    ],
    "wof:name":"Springhill Community Ctr",
    "wof:placetype":"venue"
},
  "geometry": {"coordinates":[-88.063108,30.692103],"type":"Point"}
}