{
  "type": "Feature",
  "properties": {
    "addr:full":"2520 McKenzie St Foley AL 36535",
    "addr:housenumber":"2520",
    "addr:postcode":"36535",
    "addr:street":"Mckenzie St",
    "iso:country":"US",
    "sg:address":"2520 McKenzie St",
    "sg:city":"Foley",
    "sg:classifiers":[
        {
            "category":"Travel",
            "subcategory":"Hotels & Motels",
            "type":"Entertainment"
        }
    ],
    "sg:phone":"+1 251 943 1241",
    "sg:postcode":"36535",
    "sg:province":"AL",
    "sg:tags":[
        "operation"
    ],
    "wof:name":"Key West Inn Foley",
    "wof:placetype":"venue"
},
  "geometry": {"coordinates":[-87.683379,30.373556],"type":"Point"}
}