{
  "type": "Feature",
  "properties": {
    "iso:country":"US",
    "sg:address":"794 Berry Mountain Loop",
    "sg:city":"Blountsville",
    "sg:classifiers":[
        {
            "category":"Building & Trades",
            "subcategory":"Construction",
            "type":"Services"
        }
    ],
    "sg:phone":"+1 205 274 7761",
    "sg:postcode":"35031",
    "sg:province":"AL",
    "sg:tags":[
        "house"
    ],
    "wof:name":"Teal Construction LLC",
    "wof:placetype":"venue"
},
  "geometry": {"coordinates":[-86.495762,34.008936],"type":"Point"}
}