{
  "type": "Feature",
  "properties": {
    "iso:country":"US",
    "sg:address":"336 N Court St",
    "sg:city":"Montgomery",
    "sg:classifiers":[
        {
            "category":"Wholesale",
            "subcategory":"Electrical",
            "type":"Manufacturing & Wholesale Goods"
        }
    ],
    "sg:phone":"+1 334 262 4885",
    "sg:postcode":"36104",
    "sg:province":"AL",
    "sg:tags":[
        "equipment",
        "electronic",
        "supply"
    ],
    "wof:name":"Handey's Electronic Ctr",
    "wof:placetype":"venue"
},
  "geometry": {"coordinates":[-86.308953,32.381626],"type":"Point"}
}