{
  "type": "Feature",
  "properties": {
    "addr:full":"214 Nassau St Brundidge AL 36010",
    "addr:housenumber":"214",
    "addr:postcode":"36010",
    "addr:street":"Nassau St",
    "iso:country":"US",
    "sg:address":"214 Nassau St",
    "sg:city":"Brundidge",
    "sg:classifiers":[
        {
            "category":"Manufacturing",
            "subcategory":"Electronics",
            "type":"Manufacturing & Wholesale Goods"
        }
    ],
    "sg:phone":"+1 334 735 3030",
    "sg:postcode":"36010",
    "sg:province":"AL",
    "sg:tags":[
        "equipment",
        "electronic",
        "supply"
    ],
    "sg:website":"www.becelectronics.com",
    "wof:name":"BEC",
    "wof:placetype":"venue"
},
  "geometry": {"coordinates":[-85.81209699999999,31.723385],"type":"Point"}
}