{
  "type": "Feature",
  "properties": {
    "iso:country":"US",
    "sg:address":"8122 Woodley Rd",
    "sg:city":"Montgomery",
    "sg:classifiers":[
        {
            "category":"Retail",
            "subcategory":"Auto Repair",
            "type":"Services"
        }
    ],
    "sg:phone":"+1 334 284 0700",
    "sg:postcode":"36116",
    "sg:province":"AL",
    "sg:tags":[
        "repairing",
        "automobile"
    ],
    "wof:name":"Menefee Garage",
    "wof:placetype":"venue"
},
  "geometry": {"coordinates":[-86.206937,32.252598],"type":"Point"}
}