{
  "type": "Feature",
  "properties": {
    "iso:country":"US",
    "sg:address":"1940 S Oates St",
    "sg:city":"Dothan",
    "sg:classifiers":[
        {
            "category":"Personal",
            "subcategory":"Tanning Parlor",
            "type":"Services"
        },
        {
            "category":"Personal",
            "type":"Services"
        }
    ],
    "sg:phone":"+1 334 792 4000",
    "sg:postcode":"36301",
    "sg:province":"AL",
    "sg:tags":[
        "salon"
    ],
    "wof:name":"Guys & Gals Tanning Boutique",
    "wof:placetype":"venue"
},
  "geometry": {"coordinates":[-85.398649,31.196713],"type":"Point"}
}