{
  "type": "Feature",
  "properties": {
    "addr:full":"5451 Chalkville Rd Birmingham AL 35235",
    "addr:housenumber":"5451",
    "addr:postcode":"35235",
    "addr:street":"Chalkville Rd",
    "iso:country":"US",
    "sg:address":"5451 Chalkville Rd",
    "sg:city":"Birmingham",
    "sg:classifiers":[
        {
            "category":"Insurance",
            "subcategory":"Insurance Agent",
            "type":"Services"
        },
        {
            "category":"Insurance",
            "subcategory":"Hazard Insurance",
            "type":"Services"
        },
        {
            "category":"Insurance",
            "subcategory":"Title Insurance",
            "type":"Services"
        },
        {
            "category":"Insurance",
            "subcategory":"Life Insurance",
            "type":"Services"
        }
    ],
    "sg:phone":"+1 205 856 9022",
    "sg:postcode":"35235",
    "sg:province":"AL",
    "sg:tags":[
        "business",
        "auto",
        "commercial",
        "homeowner",
        "motorcycle",
        "renter"
    ],
    "wof:name":"Allstate Insurance Company - Charles Burns",
    "wof:placetype":"venue"
},
  "geometry": {"coordinates":[-86.640766,33.65405],"type":"Point"}
}