{
  "type": "Feature",
  "properties": {
    "iso:country":"US",
    "sg:address":"2021 Camp Tukabatchee Rd",
    "sg:city":"Prattville",
    "sg:classifiers":[
        {
            "category":"Social Services",
            "type":"Services"
        }
    ],
    "sg:phone":"+1 334 365 8129",
    "sg:postcode":"36067",
    "sg:province":"AL",
    "wof:name":"Camp Hobbs",
    "wof:placetype":"venue"
},
  "geometry": {"coordinates":[-86.517898,32.570786],"type":"Point"}
}