{
  "type": "Feature",
  "properties": {
    "iso:country":"US",
    "sg:address":"1905 Cahaba Rd",
    "sg:city":"Birmingham",
    "sg:classifiers":[
        {
            "category":"Shopping",
            "subcategory":"Used Merchandise",
            "type":"Retail Goods"
        }
    ],
    "sg:phone":"+1 205 423 9200",
    "sg:postcode":"35223",
    "sg:province":"AL",
    "wof:name":"Macassar LLC",
    "wof:placetype":"venue"
},
  "geometry": {"coordinates":[-86.78142800000001,33.495788],"type":"Point"}
}