{
  "type": "Feature",
  "properties": {
    "iso:country":"US",
    "sg:address":"8566 Madison Blvd",
    "sg:city":"Madison",
    "sg:classifiers":[
        {
            "category":"Autos & Motor Vehicles",
            "subcategory":"Automobile Sales",
            "type":"Retail Goods"
        }
    ],
    "sg:phone":"+1 256 319 2002",
    "sg:postcode":"35758",
    "sg:province":"AL",
    "sg:tags":[
        "car",
        "dealer"
    ],
    "wof:name":"Driving2000.Com-Madison",
    "wof:placetype":"venue"
},
  "geometry": {"coordinates":[-86.738764,34.681997],"type":"Point"}
}