{
  "type": "Feature",
  "properties": {
    "addr:full":"5350 Vaughn Rd Montgomery AL 36116",
    "addr:housenumber":"5350",
    "addr:postcode":"36116",
    "addr:street":"Vaughn Rd",
    "iso:country":"US",
    "sg:address":"5350 Vaughn Rd",
    "sg:city":"Montgomery",
    "sg:classifiers":[
        {
            "category":"Education",
            "subcategory":"School",
            "type":"Public Place"
        }
    ],
    "sg:phone":"+1 334 272 7220",
    "sg:postcode":"36116",
    "sg:province":"AL",
    "sg:website":"www.knights.pvt.k12.al.us",
    "wof:name":"Catholic High School",
    "wof:placetype":"venue"
},
  "geometry": {"coordinates":[-86.215667,32.342024],"type":"Point"}
}