{
  "type": "Feature",
  "properties": {
    "iso:country":"US",
    "sg:address":"401 Canyon Park Dr",
    "sg:city":"Pelham",
    "sg:classifiers":[
        {
            "category":"Professional",
            "subcategory":"Art Services",
            "type":"Services"
        }
    ],
    "sg:phone":"+1 205 621 1311",
    "sg:postcode":"35124",
    "sg:province":"AL",
    "sg:tags":[
        "arts",
        "graphic",
        "photography"
    ],
    "wof:name":"Smartart South Inc",
    "wof:placetype":"venue"
},
  "geometry": {"coordinates":[-86.807172,33.299357],"type":"Point"}
}