{
  "type": "Feature",
  "properties": {
    "iso:country":"US",
    "sg:address":"5321 Frankford Dr SE",
    "sg:city":"Owens Cross Roads",
    "sg:classifiers":[
        {
            "category":"Freight",
            "type":"Transportation"
        }
    ],
    "sg:phone":"+1 256 536 0376",
    "sg:postcode":"35763",
    "sg:province":"AL",
    "sg:tags":[
        "operator",
        "local",
        "trucking"
    ],
    "wof:name":"EZ Delivery Inc",
    "wof:placetype":"venue"
},
  "geometry": {"coordinates":[-86.484101,34.646532],"type":"Point"}
}