{
  "type": "Feature",
  "properties": {
    "iso:country":"US",
    "sg:address":"26175 US Hwy 90",
    "sg:city":"Robertsdale",
    "sg:classifiers":[
        {
            "category":"Autos & Motor Vehicles",
            "subcategory":"Boat Sales",
            "type":"Retail Goods"
        }
    ],
    "sg:phone":"+1 251 942 1807",
    "sg:postcode":"36567",
    "sg:province":"AL",
    "sg:tags":[
        "canoe"
    ],
    "wof:name":"Kicks On The Styx Canoeing",
    "wof:placetype":"venue"
},
  "geometry": {"coordinates":[-87.579488,30.546964],"type":"Point"}
}