{
  "type": "Feature",
  "properties": {
    "addr:full":"1636 Mill Sq Alexander City AL 35010",
    "addr:housenumber":"1636",
    "addr:postcode":"35010",
    "addr:street":"Mill Sq",
    "iso:country":"US",
    "sg:address":"1636 Mill Sq",
    "sg:city":"Alexander City",
    "sg:classifiers":[
        {
            "category":"Building & Trades",
            "subcategory":"Equipment Rental",
            "type":"Services"
        }
    ],
    "sg:phone":"+1 256 234 2080",
    "sg:postcode":"35010",
    "sg:province":"AL",
    "sg:tags":[
        "electronics",
        "consumer",
        "television"
    ],
    "wof:name":"Bestway Rent To Own",
    "wof:placetype":"venue"
},
  "geometry": {"coordinates":[-85.970916,32.936016],"type":"Point"}
}