{
  "type": "Feature",
  "properties": {
    "iso:country":"US",
    "sg:address":"621 E Broad St",
    "sg:city":"Gadsden",
    "sg:classifiers":[
        {
            "category":"Personal",
            "subcategory":"Beauty Salon",
            "type":"Services"
        }
    ],
    "sg:phone":"+1 256 547 8541",
    "sg:postcode":"35903",
    "sg:province":"AL",
    "sg:tags":[
        "shop"
    ],
    "wof:name":"Hairloom",
    "wof:placetype":"venue"
},
  "geometry": {"coordinates":[-85.985838,34.003822],"type":"Point"}
}