{
  "type": "Feature",
  "properties": {
    "iso:country":"US",
    "sg:address":"316 Brown St",
    "sg:city":"Opp",
    "sg:classifiers":[
        {
            "category":"Real Estate",
            "subcategory":"Real Estate Operator",
            "type":"Services"
        }
    ],
    "sg:phone":"+1 334 493 4268",
    "sg:postcode":"36467",
    "sg:province":"AL",
    "sg:tags":[
        "apartment"
    ],
    "wof:name":"Rogers Apartments",
    "wof:placetype":"venue"
},
  "geometry": {"coordinates":[-86.260262,31.279469],"type":"Point"}
}