{
  "type": "Feature",
  "properties": {
    "addr:full":"209 Parkway Dr NW Huntsville AL 35801",
    "addr:housenumber":"209",
    "addr:postcode":"35801",
    "addr:street":"Parkway Dr Nw",
    "iso:country":"US",
    "sg:address":"209 Parkway Dr NW",
    "sg:city":"Huntsville",
    "sg:classifiers":[
        {
            "category":"Building & Trades",
            "subcategory":"Cleaning & Sanitation",
            "type":"Services"
        },
        {
            "category":"Building & Trades",
            "subcategory":"Equipment Rental",
            "type":"Services"
        },
        {
            "category":"Retail",
            "subcategory":"Laundry & Dry Cleaning",
            "type":"Services"
        },
        {
            "category":"Building & Trades",
            "subcategory":"Construction",
            "type":"Services"
        }
    ],
    "sg:phone":"+1 256 533 7163",
    "sg:postcode":"35801",
    "sg:province":"AL",
    "sg:tags":[
        "cleaner",
        "yard",
        "fire",
        "damage",
        "rug",
        "water",
        "restoration",
        "contractor",
        "store",
        "carpet"
    ],
    "sg:website":"http://www.united-specialist.com",
    "wof:name":"United Fire Smoke & Water Restoration",
    "wof:placetype":"venue"
},
  "geometry": {"coordinates":[-86.584777,34.747923],"type":"Point"}
}