{
  "type": "Feature",
  "properties": {
    "iso:country":"US",
    "sg:address":"1030 5th Ave SE",
    "sg:city":"Decatur",
    "sg:classifiers":[
        {
            "category":"Retail",
            "subcategory":"Repair Shop",
            "type":"Services"
        }
    ],
    "sg:phone":"+1 256 355 5580",
    "sg:postcode":"35601",
    "sg:province":"AL",
    "sg:tags":[
        "lock",
        "locksmith"
    ],
    "wof:name":"Busy Bee Lock & Key",
    "wof:placetype":"venue"
},
  "geometry": {"coordinates":[-86.98161899999999,34.589546],"type":"Point"}
}