{
  "type": "Feature",
  "properties": {
    "iso:country":"US",
    "sg:address":"125 Interstate Park Dr",
    "sg:city":"Montgomery",
    "sg:classifiers":[
        {
            "category":"Real Estate",
            "subcategory":"Architect",
            "type":"Services"
        }
    ],
    "sg:phone":"+1 334 271 3200",
    "sg:postcode":"36109",
    "sg:province":"AL",
    "sg:website":"www.gmcnetwork.com",
    "wof:name":"Goodwyn Mills & Cawood Inc",
    "wof:placetype":"venue"
},
  "geometry": {"coordinates":[-86.240178,32.362133],"type":"Point"}
}