{
  "type": "Feature",
  "properties": {
    "iso:country":"US",
    "sg:address":"19521 Huber Rd",
    "sg:city":"Elkmont",
    "sg:classifiers":[
        {
            "category":"Manufacturing",
            "subcategory":"Tools & Machinery",
            "type":"Manufacturing & Wholesale Goods"
        }
    ],
    "sg:phone":"+1 256 232 6586",
    "sg:postcode":"35620",
    "sg:province":"AL",
    "sg:tags":[
        "mfg"
    ],
    "wof:name":"Wc Die Repair Shop",
    "wof:placetype":"venue"
},
  "geometry": {"coordinates":[-86.97321100000001,34.870226],"type":"Point"}
}