{
  "type": "Feature",
  "properties": {
    "iso:country":"US",
    "sg:address":"2821 Smith Sims Rd",
    "sg:city":"Trussville",
    "sg:classifiers":[
        {
            "category":"Building & Trades",
            "subcategory":"Landscaping Services",
            "type":"Services"
        }
    ],
    "sg:phone":"+1 205 655 0378",
    "sg:postcode":"35173",
    "sg:province":"AL",
    "wof:name":"Tracy Ervin",
    "wof:placetype":"venue"
},
  "geometry": {"coordinates":[-86.598603,33.591238],"type":"Point"}
}