{
  "type": "Feature",
  "properties": {
    "iso:country":"US",
    "sg:address":"12942 US Hwy 90",
    "sg:city":"Grand Bay",
    "sg:classifiers":[
        {
            "category":"Autos & Motor Vehicles",
            "subcategory":"Auto Supplies",
            "type":"Retail Goods"
        }
    ],
    "sg:phone":"+1 251 865 6803",
    "sg:postcode":"36541",
    "sg:province":"AL",
    "sg:tags":[
        "automobile",
        "parts"
    ],
    "wof:name":"Bay Auto Supply",
    "wof:placetype":"venue"
},
  "geometry": {"coordinates":[-88.348947,30.475487],"type":"Point"}
}