{
  "type": "Feature",
  "properties": {
    "addr:full":"131 Cain Ln Brewton AL 36426",
    "addr:housenumber":"131",
    "addr:postcode":"36426",
    "addr:street":"Cain Ln",
    "iso:country":"US",
    "sg:address":"131 Cain Ln",
    "sg:city":"Brewton",
    "sg:classifiers":[
        {
            "category":"Building & Trades",
            "subcategory":"Construction",
            "type":"Services"
        }
    ],
    "sg:phone":"+1 251 809 0119",
    "sg:postcode":"36426",
    "sg:province":"AL",
    "sg:tags":[
        "house"
    ],
    "wof:name":"Robert Lee Jernigan Construct",
    "wof:placetype":"venue"
},
  "geometry": {"coordinates":[-87.041434,31.180844],"type":"Point"}
}