{
  "type": "Feature",
  "properties": {
    "iso:country":"US",
    "sg:address":"3009 Hand Ave",
    "sg:city":"Mobile",
    "sg:classifiers":[
        {
            "category":"Wholesale",
            "subcategory":"Metals & Minerals",
            "type":"Manufacturing & Wholesale Goods"
        }
    ],
    "sg:phone":"+1 251 457 1143",
    "sg:postcode":"36612",
    "sg:province":"AL",
    "wof:name":"Mobile M G C Div 9107",
    "wof:placetype":"venue"
},
  "geometry": {"coordinates":[-88.11715599999999,30.74434],"type":"Point"}
}