{
  "type": "Feature",
  "properties": {
    "addr:full":"2112 Lake Heather Way Birmingham AL 35242",
    "addr:housenumber":"2112",
    "addr:postcode":"35242",
    "addr:street":"Lake Heather Way",
    "iso:country":"US",
    "sg:address":"2112 Lake Heather Way",
    "sg:city":"Birmingham",
    "sg:classifiers":[
        {
            "category":"Professional",
            "subcategory":"Business Services",
            "type":"Services"
        }
    ],
    "sg:phone":"+1 205 437 1051",
    "sg:postcode":"35242",
    "sg:province":"AL",
    "wof:name":"Drh Group",
    "wof:placetype":"venue"
},
  "geometry": {"coordinates":[-86.706155,33.41719],"type":"Point"}
}