{
  "type": "Feature",
  "properties": {
    "iso:country":"US",
    "sg:address":"517 9th St N",
    "sg:city":"Birmingham",
    "sg:classifiers":[
        {
            "category":"Autos & Motor Vehicles",
            "subcategory":"Motorcycle Sales",
            "type":"Retail Goods"
        }
    ],
    "sg:phone":"+1 205 326 1031",
    "sg:postcode":"35203",
    "sg:province":"AL",
    "wof:name":"PBR Club House",
    "wof:placetype":"venue"
},
  "geometry": {"coordinates":[-86.82405300000001,33.512102],"type":"Point"}
}