{
  "type": "Feature",
  "properties": {
    "iso:country":"US",
    "sg:address":"805 Royal Ter",
    "sg:city":"Shoal Creek",
    "sg:classifiers":[
        {
            "category":"Manufacturing",
            "subcategory":"Tools & Machinery",
            "type":"Manufacturing & Wholesale Goods"
        }
    ],
    "sg:phone":"+1 205 408 7888",
    "sg:postcode":"35242",
    "sg:province":"AL",
    "sg:tags":[
        "equipment",
        "electric"
    ],
    "wof:name":"Handlin/Schwarz Assoc",
    "wof:placetype":"venue"
},
  "geometry": {"coordinates":[-86.64463,33.433495],"type":"Point"}
}