{
  "type": "Feature",
  "properties": {
    "iso:country":"US",
    "sg:address":"5235 Pinson Valley Pkwy",
    "sg:city":"Birmingham",
    "sg:classifiers":[
        {
            "category":"Retail",
            "subcategory":"Auto Repair",
            "type":"Services"
        }
    ],
    "sg:phone":"+1 205 681 2900",
    "sg:postcode":"35215",
    "sg:province":"AL",
    "sg:tags":[
        "bus"
    ],
    "wof:name":"Houston EAGLE Svc",
    "wof:placetype":"venue"
},
  "geometry": {"coordinates":[-86.693055,33.678457],"type":"Point"}
}