{
  "type": "Feature",
  "properties": {
    "iso:country":"US",
    "sg:address":"313 S 5th St",
    "sg:city":"Gadsden",
    "sg:classifiers":[
        {
            "category":"Health Services",
            "subcategory":"Doctor",
            "type":"Services"
        }
    ],
    "sg:phone":"+1 256 547 2844",
    "sg:postcode":"35901",
    "sg:province":"AL",
    "sg:tags":[
        "dentist"
    ],
    "wof:name":"E M Lindsey DMD",
    "wof:placetype":"venue"
},
  "geometry": {"coordinates":[-86.007662,34.009194],"type":"Point"}
}