{
  "type": "Feature",
  "properties": {
    "addr:full":"310 Shelia St Florence AL 35633",
    "addr:housenumber":"310",
    "addr:postcode":"35633",
    "addr:street":"Shelia St",
    "iso:country":"US",
    "sg:address":"310 Shelia St",
    "sg:city":"Florence",
    "sg:classifiers":[
        {
            "category":"Education",
            "subcategory":"Library",
            "type":"Public Place"
        }
    ],
    "sg:phone":"+1 256 766 7528",
    "sg:postcode":"35633",
    "sg:province":"AL",
    "wof:name":"Chisholm Branch",
    "wof:placetype":"venue"
},
  "geometry": {"coordinates":[-87.683145,34.893034],"type":"Point"}
}