{
  "type": "Feature",
  "properties": {
    "iso:country":"US",
    "sg:address":"4171 Lomac St",
    "sg:city":"Montgomery",
    "sg:classifiers":[
        {
            "category":"Health Services",
            "subcategory":"Chiropractor",
            "type":"Services"
        }
    ],
    "sg:phone":"+1 334 272 3030",
    "sg:postcode":"36106",
    "sg:province":"AL",
    "wof:name":"Hogan J Dan III Dr",
    "wof:placetype":"venue"
},
  "geometry": {"coordinates":[-86.234711,32.357541],"type":"Point"}
}