{
  "type": "Feature",
  "properties": {
    "iso:country":"US",
    "sg:address":"3300 River Rd",
    "sg:city":"Theodore",
    "sg:classifiers":[
        {
            "category":"Restaurant",
            "type":"Food & Drink"
        }
    ],
    "sg:phone":"+1 251 973 9070",
    "sg:postcode":"36582",
    "sg:province":"AL",
    "sg:tags":[
        "eating"
    ],
    "wof:name":"Baudean's",
    "wof:placetype":"venue"
},
  "geometry": {"coordinates":[-88.117222,30.457625],"type":"Point"}
}