{
  "type": "Feature",
  "properties": {
    "iso:country":"US",
    "sg:address":"7611 State Rte 69",
    "sg:city":"Cullman",
    "sg:classifiers":[
        {
            "category":"Organizations",
            "subcategory":"Religious Organization",
            "type":"Services"
        }
    ],
    "sg:phone":"+1 256 287 0510",
    "sg:postcode":"35057",
    "sg:province":"AL",
    "sg:tags":[
        "church"
    ],
    "wof:name":"Bremen Missionary Baptist Chr",
    "wof:placetype":"venue"
},
  "geometry": {"coordinates":[-86.96875,33.995337],"type":"Point"}
}