{
  "type": "Feature",
  "properties": {
    "addr:full":"6720 Iceland Ave Birmingham AL 35224",
    "addr:postcode":"6720;35224",
    "addr:street":"Iceland Ave",
    "iso:country":"US",
    "sg:address":"6720 Iceland Ave",
    "sg:city":"Birmingham",
    "sg:classifiers":[
        {
            "category":"Shopping",
            "subcategory":"Computers & Home Electronics",
            "type":"Retail Goods"
        }
    ],
    "sg:phone":"+1 205 787 7168",
    "sg:postcode":"35224",
    "sg:province":"AL",
    "wof:name":"Multimedia Country Inc",
    "wof:placetype":"venue"
},
  "geometry": {"coordinates":[-86.948666,33.522814],"type":"Point"}
}