{
  "type": "Feature",
  "properties": {
    "iso:country":"US",
    "sg:address":"2403 Briarwood Ave SW",
    "sg:city":"Fort Payne",
    "sg:classifiers":[
        {
            "category":"Manufacturing",
            "subcategory":"Textiles",
            "type":"Manufacturing & Wholesale Goods"
        }
    ],
    "sg:phone":"+1 256 845 2721",
    "sg:postcode":"35967",
    "sg:province":"AL",
    "sg:tags":[
        "hosiery"
    ],
    "wof:name":"Isbell Manufacturing Co",
    "wof:placetype":"venue"
},
  "geometry": {"coordinates":[-85.76477300000001,34.422375],"type":"Point"}
}