{
  "type": "Feature",
  "properties": {
    "addr:full":"230 4th Ave N Bessemer AL 35020",
    "addr:housenumber":"230",
    "addr:postcode":"35020",
    "addr:street":"4Th Ave N",
    "iso:country":"US",
    "sg:address":"230 4th Ave N",
    "sg:city":"Bessemer",
    "sg:classifiers":[
        {
            "category":"Building & Trades",
            "subcategory":"Plumbing",
            "type":"Services"
        }
    ],
    "sg:phone":"+1 205 424 4166",
    "sg:postcode":"35020",
    "sg:province":"AL",
    "sg:tags":[
        "conditioning",
        "air",
        "system",
        "contractor"
    ],
    "wof:name":"Irvin Heating Cooling & Insltn",
    "wof:placetype":"venue"
},
  "geometry": {"coordinates":[-86.96890500000001,33.385527],"type":"Point"}
}