{
  "type": "Feature",
  "properties": {
    "addr:full":"6650 Old Hwy 31 N Gardendale AL 35071",
    "addr:housenumber":"6650",
    "addr:postcode":"35071",
    "addr:street":"Old Hwy 31 N",
    "iso:country":"US",
    "sg:address":"6650 Old Hwy 31 N",
    "sg:city":"Gardendale",
    "sg:classifiers":[
        {
            "category":"Education",
            "subcategory":"Special Training",
            "type":"Public Place"
        }
    ],
    "sg:phone":"+1 205 681 9797",
    "sg:postcode":"35071",
    "sg:province":"AL",
    "sg:tags":[
        "educational"
    ],
    "wof:name":"Jefferson Shelby Wildland Urba",
    "wof:placetype":"venue"
},
  "geometry": {"coordinates":[-86.817993,33.701141],"type":"Point"}
}