{
  "type": "Feature",
  "properties": {
    "iso:country":"US",
    "sg:address":"241 Baldwin Rd",
    "sg:city":"Saraland",
    "sg:classifiers":[
        {
            "category":"Organizations",
            "subcategory":"Religious Organization",
            "type":"Services"
        }
    ],
    "sg:phone":"+1 251 675 5064",
    "sg:postcode":"36571",
    "sg:province":"AL",
    "wof:name":"Saraland Aoh Church God",
    "wof:placetype":"venue"
},
  "geometry": {"coordinates":[-88.065103,30.828304],"type":"Point"}
}