{
  "type": "Feature",
  "properties": {
    "iso:country":"US",
    "sg:address":"11220 Memorial Pkwy SW",
    "sg:city":"Huntsville",
    "sg:classifiers":[
        {
            "category":"Cafe",
            "type":"Food & Drink"
        }
    ],
    "sg:menulink":"http://www.allmenus.com/al/huntsville/55331-south-park-cafe/menu/",
    "sg:phone":"+1 256 489 7275",
    "sg:postcode":"35803",
    "sg:province":"AL",
    "sg:tags":[
        "american"
    ],
    "wof:name":"South Park Cafe",
    "wof:placetype":"venue"
},
  "geometry": {"coordinates":[-86.56702,34.636585],"type":"Point"}
}