{
  "type": "Feature",
  "properties": {
    "iso:country":"US",
    "sg:address":"420 Lurleen Dr",
    "sg:city":"Altoona",
    "sg:classifiers":[
        {
            "category":"Retail",
            "subcategory":"Repair Shop",
            "type":"Services"
        }
    ],
    "sg:phone":"+1 205 466 7969",
    "sg:postcode":"35952",
    "sg:province":"AL",
    "sg:tags":[
        "welding"
    ],
    "wof:name":"Blackmon Enterprise",
    "wof:placetype":"venue"
},
  "geometry": {"coordinates":[-86.385361,34.111258],"type":"Point"}
}