{
  "type": "Feature",
  "properties": {
    "addr:full":"1506 Coalesway Dr Mobile AL 36693",
    "addr:housenumber":"1506",
    "addr:postcode":"36693",
    "addr:street":"Coalesway Dr",
    "iso:country":"US",
    "sg:address":"1506 Coalesway Dr",
    "sg:city":"Mobile",
    "sg:classifiers":[
        {
            "category":"Shopping",
            "subcategory":"Computers & Home Electronics",
            "type":"Retail Goods"
        }
    ],
    "sg:phone":"+1 251 661 3584",
    "sg:postcode":"36693",
    "sg:province":"AL",
    "wof:name":"Medclinicnet Inc",
    "wof:placetype":"venue"
},
  "geometry": {"coordinates":[-88.145725,30.624849],"type":"Point"}
}