{
  "type": "Feature",
  "properties": {
    "addr:full":"300 S 7th St Opelika AL 36801",
    "addr:housenumber":"300",
    "addr:postcode":"36801",
    "addr:street":"S 7Th St",
    "iso:country":"US",
    "sg:address":"300 S 7th St",
    "sg:city":"Opelika",
    "sg:classifiers":[
        {
            "category":"Autos & Motor Vehicles",
            "subcategory":"Automobile Sales",
            "type":"Retail Goods"
        }
    ],
    "sg:phone":"+1 334 749 2090",
    "sg:postcode":"36801",
    "sg:province":"AL",
    "sg:tags":[
        "used"
    ],
    "wof:name":"Puckett Motors",
    "wof:placetype":"venue"
},
  "geometry": {"coordinates":[-85.375231,32.646363],"type":"Point"}
}