{
  "type": "Feature",
  "properties": {
    "iso:country":"US",
    "sg:address":"624 Douglas Ave",
    "sg:city":"Brewton",
    "sg:classifiers":[
        {
            "category":"Professional",
            "subcategory":"Accounting & Tax Preparation",
            "type":"Services"
        }
    ],
    "sg:phone":"+1 251 867 5300",
    "sg:postcode":"36426",
    "sg:province":"AL",
    "wof:name":"Deep South Inc",
    "wof:placetype":"venue"
},
  "geometry": {"coordinates":[-87.06217599999999,31.13847],"type":"Point"}
}