{
  "type": "Feature",
  "properties": {
    "addr:full":"2101 Florence Blvd Florence AL 35634",
    "addr:housenumber":"2101",
    "addr:postcode":"35634",
    "addr:street":"Florence Blvd",
    "iso:country":"US",
    "sg:address":"2101 Florence Blvd",
    "sg:city":"Florence",
    "sg:classifiers":[
        {
            "category":"Professional",
            "subcategory":"Accounting & Tax Preparation",
            "type":"Services"
        }
    ],
    "sg:phone":"+1 256 760 9502",
    "sg:postcode":"35634",
    "sg:province":"AL",
    "sg:tags":[
        "accountant"
    ],
    "sg:website":"www.frankspirescpa.com",
    "wof:name":"Spires & Assoc",
    "wof:placetype":"venue"
},
  "geometry": {"coordinates":[-87.644492,34.825526],"type":"Point"}
}