{
  "type": "Feature",
  "properties": {
    "addr:full":"126 Shiraz St Montevallo AL 35115",
    "addr:housenumber":"126",
    "addr:postcode":"35115",
    "addr:street":"Shiraz St",
    "iso:country":"US",
    "sg:address":"126 Shiraz St",
    "sg:city":"Montevallo",
    "sg:classifiers":[
        {
            "category":"Building & Trades",
            "subcategory":"Construction",
            "type":"Services"
        }
    ],
    "sg:phone":"+1 205 664 0706",
    "sg:postcode":"35115",
    "sg:province":"AL",
    "sg:tags":[
        "house"
    ],
    "wof:name":"Upchurch Enterprises Inc",
    "wof:placetype":"venue"
},
  "geometry": {"coordinates":[-86.836254,33.186121],"type":"Point"}
}