{
  "type": "Feature",
  "properties": {
    "iso:country":"US",
    "sg:address":"7377 Co Rd 747",
    "sg:city":"Cullman",
    "sg:classifiers":[
        {
            "category":"Building & Trades",
            "subcategory":"Plumbing",
            "type":"Services"
        }
    ],
    "sg:phone":"+1 256 236 6450",
    "sg:postcode":"35055",
    "sg:province":"AL",
    "sg:tags":[
        "contractor"
    ],
    "wof:name":"Lynn Dulaney Plumbing",
    "wof:placetype":"venue"
},
  "geometry": {"coordinates":[-86.743624,34.159003],"type":"Point"}
}