{
  "type": "Feature",
  "properties": {
    "addr:full":"9028 Golden Cir Adger AL 35006",
    "addr:housenumber":"9028",
    "addr:postcode":"35006",
    "addr:street":"Golden Cir",
    "iso:country":"US",
    "sg:address":"9028 Golden Cir",
    "sg:city":"Adger",
    "sg:classifiers":[
        {
            "category":"Professional",
            "type":"Services"
        }
    ],
    "sg:phone":"+1 205 491 4958",
    "sg:postcode":"35006",
    "sg:province":"AL",
    "wof:name":"Steve Thomas",
    "wof:placetype":"venue"
},
  "geometry": {"coordinates":[-87.14654899999999,33.449531],"type":"Point"}
}