{
  "type": "Feature",
  "properties": {
    "iso:country":"US",
    "sg:address":"1872 Collier Dr",
    "sg:city":"Birmingham",
    "sg:classifiers":[
        {
            "category":"Organizations",
            "subcategory":"Religious Organization",
            "type":"Services"
        }
    ],
    "sg:phone":"+1 205 923 3368",
    "sg:postcode":"35228",
    "sg:province":"AL",
    "wof:name":"Zion Travelers Primitive",
    "wof:placetype":"venue"
},
  "geometry": {"coordinates":[-86.915089,33.454025],"type":"Point"}
}