{
  "type": "Feature",
  "properties": {
    "addr:full":"1872 Collier Dr Birmingham AL 35228",
    "addr:housenumber":"1872",
    "addr:postcode":"35228",
    "addr:street":"Collier Dr",
    "iso:country":"US",
    "sg:address":"1872 Collier Dr",
    "sg:city":"Birmingham",
    "sg:classifiers":[
        {
            "category":"Organizations",
            "subcategory":"Religious Organization",
            "type":"Services"
        }
    ],
    "sg:phone":"+1 205 923 3368",
    "sg:postcode":"35228",
    "sg:province":"AL",
    "wof:name":"Zion Travelers Primitive",
    "wof:placetype":"venue"
},
  "geometry": {"coordinates":[-86.91508899999999,33.454025],"type":"Point"}
}