{
  "type": "Feature",
  "properties": {
    "addr:full":"1597 Montgomery Hwy Dothan AL 36303",
    "addr:housenumber":"1597",
    "addr:postcode":"36303",
    "addr:street":"Montgomery Hwy",
    "iso:country":"US",
    "sg:address":"1597 Montgomery Hwy",
    "sg:city":"Dothan",
    "sg:classifiers":[
        {
            "category":"Personal",
            "subcategory":"Beauty Salon",
            "type":"Services"
        }
    ],
    "sg:phone":"+1 334 792 0904",
    "sg:postcode":"36303",
    "sg:province":"AL",
    "wof:name":"Beauty Bazaar",
    "wof:placetype":"venue"
},
  "geometry": {"coordinates":[-85.404838,31.238909],"type":"Point"}
}