{
  "type": "Feature",
  "properties": {
    "addr:full":"2306 S Wilson Dam Hwy Muscle Shoals AL 35661",
    "addr:housenumber":"2306",
    "addr:postcode":"35661",
    "addr:street":"S Wilson Dam Hwy",
    "iso:country":"US",
    "sg:address":"2306 S Wilson Dam Hwy",
    "sg:city":"Muscle Shoals",
    "sg:classifiers":[
        {
            "category":"Social Services",
            "subcategory":"Job Training",
            "type":"Services"
        }
    ],
    "sg:phone":"+1 256 381 4088",
    "sg:postcode":"35661",
    "sg:province":"AL",
    "sg:tags":[
        "rehabilitation"
    ],
    "wof:name":"Directions Management Svc",
    "wof:placetype":"venue"
},
  "geometry": {"coordinates":[-87.635319,34.737091],"type":"Point"}
}