{
  "type": "Feature",
  "properties": {
    "iso:country":"US",
    "sg:address":"1735 E University Dr",
    "sg:city":"Auburn",
    "sg:classifiers":[
        {
            "category":"Retail",
            "subcategory":"Portrait Studio",
            "type":"Services"
        }
    ],
    "sg:phone":"+1 334 826 7502",
    "sg:postcode":"36830",
    "sg:province":"AL",
    "sg:tags":[
        "photographer",
        "photo"
    ],
    "sg:website":"www.moore-studios.com",
    "wof:name":"Moore Studios",
    "wof:placetype":"venue"
},
  "geometry": {"coordinates":[-85.447745,32.621192],"type":"Point"}
}