{
  "type": "Feature",
  "properties": {
    "addr:full":"1036 Parkway Dr SE Leeds AL 35094",
    "addr:housenumber":"1036",
    "addr:postcode":"35094",
    "addr:street":"Parkway Dr Se",
    "iso:country":"US",
    "sg:address":"1036 Parkway Dr SE",
    "sg:city":"Leeds",
    "sg:classifiers":[
        {
            "category":"Home & Garden",
            "subcategory":"Building Materials",
            "type":"Retail Goods"
        }
    ],
    "sg:phone":"+1 205 702 4242",
    "sg:postcode":"35094",
    "sg:province":"AL",
    "wof:name":"Mullins Building Products Inc",
    "wof:placetype":"venue"
},
  "geometry": {"coordinates":[-86.538133,33.541979],"type":"Point"}
}