{
  "type": "Feature",
  "properties": {
    "addr:full":"1953 US Hwy 31 Birmingham AL 35244",
    "addr:housenumber":"1953",
    "addr:postcode":"35244",
    "addr:street":"Us Hwy 31",
    "iso:country":"US",
    "sg:address":"1953 US Hwy 31",
    "sg:city":"Birmingham",
    "sg:classifiers":[
        {
            "category":"Organizations",
            "subcategory":"Religious Organization",
            "type":"Services"
        }
    ],
    "sg:phone":"+1 205 987 4030",
    "sg:postcode":"35244",
    "sg:province":"AL",
    "sg:tags":[
        "methodist",
        "church"
    ],
    "wof:name":"Riverchase Untd Methdst Church",
    "wof:placetype":"venue"
},
  "geometry": {"coordinates":[-86.795529,33.346917],"type":"Point"}
}