{
  "type": "Feature",
  "properties": {
    "addr:full":"10023 Springfield Ct Mobile AL 36695",
    "addr:housenumber":"10023",
    "addr:postcode":"36695",
    "addr:street":"Springfield Ct",
    "iso:country":"US",
    "sg:address":"10023 Springfield Ct",
    "sg:city":"Mobile",
    "sg:classifiers":[
        {
            "category":"Real Estate",
            "subcategory":"Real Estate Agent",
            "type":"Services"
        }
    ],
    "sg:phone":"+1 251 633 4742",
    "sg:postcode":"36695",
    "sg:province":"AL",
    "sg:tags":[
        "inspection"
    ],
    "wof:name":"All Angels Pro Hm Inspctn Inc",
    "wof:placetype":"venue"
},
  "geometry": {"coordinates":[-88.281648,30.665288],"type":"Point"}
}