{
  "type": "Feature",
  "properties": {
    "addr:full":"13340 Memorial Pkwy SW Huntsville AL 35803",
    "addr:housenumber":"13340",
    "addr:postcode":"35803",
    "addr:street":"Memorial Pkwy Sw",
    "iso:country":"US",
    "sg:address":"13340 Memorial Pkwy SW",
    "sg:city":"Huntsville",
    "sg:classifiers":[
        {
            "category":"Freight",
            "type":"Transportation"
        }
    ],
    "sg:phone":"+1 256 881 9239",
    "sg:postcode":"35803",
    "sg:province":"AL",
    "sg:tags":[
        "company",
        "hauling",
        "contract"
    ],
    "wof:name":"Beaty Trucking Company Inc",
    "wof:placetype":"venue"
},
  "geometry": {"coordinates":[-86.563672,34.58666],"type":"Point"}
}