{
  "type": "Feature",
  "properties": {
    "iso:country":"US",
    "sg:address":"27 Co Rd 7",
    "sg:city":"Tyler",
    "sg:classifiers":[
        {
            "category":"Manufacturing",
            "subcategory":"Textiles",
            "type":"Manufacturing & Wholesale Goods"
        }
    ],
    "sg:phone":"+1 334 874 7982",
    "sg:postcode":"36785",
    "sg:province":"AL",
    "sg:tags":[
        "cotton"
    ],
    "wof:name":"J A Minter & Son Cotton Gin",
    "wof:placetype":"venue"
},
  "geometry": {"coordinates":[-86.879708,32.342416],"type":"Point"}
}