{
  "type": "Feature",
  "properties": {
    "iso:country":"US",
    "sg:address":"376 Southwood Dr",
    "sg:city":"Oxford",
    "sg:classifiers":[
        {
            "category":"Manufacturing",
            "subcategory":"Textiles",
            "type":"Manufacturing & Wholesale Goods"
        }
    ],
    "sg:phone":"+1 256 835 1323",
    "sg:postcode":"36203",
    "sg:province":"AL",
    "sg:tags":[
        "mill",
        "fabric",
        "cotton"
    ],
    "wof:name":"K & K Babies & Bows",
    "wof:placetype":"venue"
},
  "geometry": {"coordinates":[-85.846069,33.56524],"type":"Point"}
}