{
  "type": "Feature",
  "properties": {
    "iso:country":"US",
    "sg:address":"2310 Lynn Rd NW",
    "sg:city":"Huntsville",
    "sg:classifiers":[
        {
            "category":"Professional",
            "subcategory":"Management & Consulting",
            "type":"Services"
        }
    ],
    "sg:phone":"+1 256 859 7936",
    "sg:postcode":"35810",
    "sg:province":"AL",
    "sg:tags":[
        "consultant",
        "business"
    ],
    "wof:name":"Administrative Consultants",
    "wof:placetype":"venue"
},
  "geometry": {"coordinates":[-86.59266100000001,34.780469],"type":"Point"}
}