{
  "type": "Feature",
  "properties": {
    "iso:country":"US",
    "sg:address":"1031 Delta St",
    "sg:city":"Bessemer",
    "sg:classifiers":[
        {
            "category":"Organizations",
            "subcategory":"Membership Organization",
            "type":"Services"
        }
    ],
    "sg:phone":"+1 205 425 2309",
    "sg:postcode":"35020",
    "sg:province":"AL",
    "wof:name":"Carmans Camp Inc",
    "wof:placetype":"venue"
},
  "geometry": {"coordinates":[-86.97093599999999,33.361306],"type":"Point"}
}