{
  "type": "Feature",
  "properties": {
    "addr:full":"806 W Mobile St Florence AL 35630",
    "addr:housenumber":"806",
    "addr:postcode":"35630",
    "addr:street":"W Mobile St",
    "iso:country":"US",
    "sg:address":"806 W Mobile St",
    "sg:city":"Florence",
    "sg:classifiers":[
        {
            "category":"Personal",
            "subcategory":"Beauty Salon",
            "type":"Services"
        },
        {
            "category":"Personal",
            "subcategory":"Barber",
            "type":"Services"
        }
    ],
    "sg:phone":"+1 256 767 4980",
    "sg:postcode":"35630",
    "sg:province":"AL",
    "sg:tags":[
        "hair"
    ],
    "wof:name":"Herman's Cut & Style Shop Inc",
    "wof:placetype":"venue"
},
  "geometry": {"coordinates":[-87.686922,34.798013],"type":"Point"}
}