{
  "type": "Feature",
  "properties": {
    "iso:country":"US",
    "sg:address":"3739 Alford Bend Rd",
    "sg:city":"Hokes Bluff",
    "sg:classifiers":[
        {
            "category":"Food & Beverages",
            "subcategory":"Bakery",
            "type":"Retail Goods"
        }
    ],
    "sg:phone":"+1 256 494 9401",
    "sg:postcode":"35903",
    "sg:province":"AL",
    "sg:tags":[
        "baker"
    ],
    "wof:name":"Cothran's Bakery",
    "wof:placetype":"venue"
},
  "geometry": {"coordinates":[-85.865297,33.987059],"type":"Point"}
}