{
  "type": "Feature",
  "properties": {
    "addr:full":"1275 Hillcrest Rd Mobile AL 36695",
    "addr:housenumber":"1275",
    "addr:postcode":"36695",
    "addr:street":"Hillcrest Rd",
    "iso:country":"US",
    "sg:address":"1275 Hillcrest Rd",
    "sg:city":"Mobile",
    "sg:classifiers":[
        {
            "category":"Restaurant",
            "type":"Food & Drink"
        }
    ],
    "sg:menulink":"http://www.allmenus.com/al/tanner-williams/173898-wendys/menu/",
    "sg:phone":"+1 251 633 9400",
    "sg:postcode":"36695",
    "sg:province":"AL",
    "sg:tags":[
        "burger",
        "american",
        "soup"
    ],
    "wof:name":"Wendy's",
    "wof:placetype":"venue"
},
  "geometry": {"coordinates":[-88.190566,30.66277],"type":"Point"}
}