{
  "type": "Feature",
  "properties": {
    "addr:full":"915 E Glenn Ave Auburn AL 36830",
    "addr:housenumber":"915",
    "addr:postcode":"36830",
    "addr:street":"E Glenn Ave",
    "iso:country":"US",
    "sg:address":"915 E Glenn Ave",
    "sg:city":"Auburn",
    "sg:classifiers":[
        {
            "category":"Social Services",
            "type":"Services"
        }
    ],
    "sg:phone":"+1 334 821 4512",
    "sg:postcode":"36830",
    "sg:province":"AL",
    "sg:tags":[
        "counselor",
        "marriage",
        "family"
    ],
    "wof:name":"Professional Counseling Svc",
    "wof:placetype":"venue"
},
  "geometry": {"coordinates":[-85.462481,32.609062],"type":"Point"}
}