{
  "type": "Feature",
  "properties": {
    "addr:full":"1109 30th Ave Northport AL 35476",
    "addr:housenumber":"1109",
    "addr:postcode":"35476",
    "addr:street":"30Th Ave",
    "iso:country":"US",
    "sg:address":"1109 30th Ave",
    "sg:city":"Northport",
    "sg:classifiers":[
        {
            "category":"Retail",
            "subcategory":"Auto Repair",
            "type":"Services"
        }
    ],
    "sg:phone":"+1 205 366 0510",
    "sg:postcode":"35476",
    "sg:province":"AL",
    "sg:tags":[
        "general"
    ],
    "wof:name":"Northport Auto Machine Shop",
    "wof:placetype":"venue"
},
  "geometry": {"coordinates":[-87.58583,33.224054],"type":"Point"}
}