{
  "type": "Feature",
  "properties": {
    "iso:country":"US",
    "sg:address":"1807 Glenn Blvd SW",
    "sg:city":"Fort Payne",
    "sg:classifiers":[
        {
            "category":"Shopping",
            "subcategory":"Bicycles & Sporting Goods",
            "type":"Retail Goods"
        }
    ],
    "sg:phone":"+1 256 997 0622",
    "sg:postcode":"35967",
    "sg:province":"AL",
    "wof:name":"Hibbett Sporting Goods Inc",
    "wof:placetype":"venue"
},
  "geometry": {"coordinates":[-85.75722399999999,34.438409],"type":"Point"}
}