{
  "type": "Feature",
  "properties": {
    "iso:country":"US",
    "sg:address":"3595 Grandview Pkwy Ste 1",
    "sg:city":"Birmingham",
    "sg:classifiers":[
        {
            "category":"Insurance",
            "subcategory":"Hazard Insurance",
            "type":"Services"
        },
        {
            "category":"Insurance",
            "subcategory":"Life Insurance",
            "type":"Services"
        },
        {
            "category":"Insurance",
            "subcategory":"Health Insurance",
            "type":"Services"
        }
    ],
    "sg:phone":"+1 205 909 6000",
    "sg:postcode":"35243",
    "sg:province":"AL",
    "sg:website":"http://www.assurantemployeebenefits.com",
    "wof:name":"Assurant Employee Benefits",
    "wof:placetype":"venue"
},
  "geometry": {"coordinates":[-86.71919699999999,33.436015],"type":"Point"}
}