{
  "type": "Feature",
  "properties": {
    "addr:full":"619 19th St SW Birmingham AL 35211",
    "addr:housenumber":"619",
    "addr:postcode":"35211",
    "addr:street":"19Th St Sw",
    "iso:country":"US",
    "sg:address":"619 19th St SW",
    "sg:city":"Birmingham",
    "sg:classifiers":[
        {
            "category":"Utilities",
            "subcategory":"Mobile Phone",
            "type":"Services"
        },
        {
            "category":"Coffee & Tea",
            "type":"Food & Drink"
        }
    ],
    "sg:phone":"+1 205 996 9892",
    "sg:postcode":"35211",
    "sg:province":"AL",
    "sg:tags":[
        "shop",
        "wi-fi",
        "espresso",
        "hotspot",
        "restaurant"
    ],
    "sg:website":"http://www.starbuckscoffee.com",
    "wof:name":"Starbucks Coffee",
    "wof:placetype":"venue"
},
  "geometry": {"coordinates":[-86.869472,33.483793],"type":"Point"}
}