{
  "type": "Feature",
  "properties": {
    "iso:country":"US",
    "sg:address":"107 Mount Vernon Homes",
    "sg:city":"Boaz",
    "sg:classifiers":[
        {
            "category":"Retail",
            "subcategory":"Photofinishing",
            "type":"Services"
        }
    ],
    "sg:phone":"+1 256 840 5887",
    "sg:postcode":"35957",
    "sg:province":"AL",
    "sg:tags":[
        "laboratory"
    ],
    "wof:name":"Angels Attic",
    "wof:placetype":"venue"
},
  "geometry": {"coordinates":[-86.172763,34.207487],"type":"Point"}
}