{
  "type": "Feature",
  "properties": {
    "iso:country":"US",
    "sg:address":"2101 6th St",
    "sg:city":"Tuscaloosa",
    "sg:classifiers":[
        {
            "category":"Retail",
            "subcategory":"Auto Repair",
            "type":"Services"
        }
    ],
    "sg:phone":"+1 205 758 1630",
    "sg:postcode":"35401",
    "sg:province":"AL",
    "sg:tags":[
        "body",
        "shop",
        "automobile",
        "paint",
        "automotive",
        "painting"
    ],
    "wof:name":"Campbell Body Shop Inc",
    "wof:placetype":"venue"
},
  "geometry": {"coordinates":[-87.565219,33.209623],"type":"Point"}
}