{
  "type": "Feature",
  "properties": {
    "iso:country":"US",
    "sg:address":"238 Bluesprings Cir",
    "sg:city":"Jackson",
    "sg:classifiers":[
        {
            "category":"Professional",
            "subcategory":"Engineering",
            "type":"Services"
        }
    ],
    "sg:phone":"+1 251 246 7113",
    "sg:postcode":"36545",
    "sg:province":"AL",
    "sg:tags":[
        "engineer"
    ],
    "wof:name":"Metso Automation",
    "wof:placetype":"venue"
},
  "geometry": {"coordinates":[-87.885149,31.506833],"type":"Point"}
}