{
  "type": "Feature",
  "properties": {
    "iso:country":"US",
    "sg:address":"767 Co Rd 394",
    "sg:city":"Groveoak",
    "sg:classifiers":[
        {
            "category":"Home & Garden",
            "subcategory":"Carpets & Floor Coverings",
            "type":"Retail Goods"
        }
    ],
    "sg:phone":"+1 256 659 4653",
    "sg:postcode":"35975",
    "sg:province":"AL",
    "wof:name":"Rogers Hardwood Floors",
    "wof:placetype":"venue"
},
  "geometry": {"coordinates":[-86.05839,34.403364],"type":"Point"}
}