{
  "type": "Feature",
  "properties": {
    "iso:country":"US",
    "sg:address":"794 Co Rd 70",
    "sg:city":"Fyffe",
    "sg:classifiers":[
        {
            "category":"Wholesale",
            "subcategory":"Machinery & Supplies",
            "type":"Manufacturing & Wholesale Goods"
        }
    ],
    "sg:phone":"+1 256 659 2282",
    "sg:postcode":"35971",
    "sg:province":"AL",
    "sg:tags":[
        "equipment",
        "industrial"
    ],
    "wof:name":"Jeromes Small Engine Center",
    "wof:placetype":"venue"
},
  "geometry": {"coordinates":[-86.014996,34.400434],"type":"Point"}
}