{
  "type": "Feature",
  "properties": {
    "addr:full":"120 E 2nd St Falkville AL 35622",
    "addr:housenumber":"120",
    "addr:postcode":"35622",
    "addr:street":"E 2Nd St",
    "iso:country":"US",
    "sg:address":"120 E 2nd St",
    "sg:city":"Falkville",
    "sg:classifiers":[
        {
            "category":"Manufacturing",
            "subcategory":"Electronics",
            "type":"Manufacturing & Wholesale Goods"
        }
    ],
    "sg:phone":"+1 256 784 9522",
    "sg:postcode":"35622",
    "sg:province":"AL",
    "sg:tags":[
        "equipment",
        "mfg",
        "communications"
    ],
    "wof:name":"Advanced Sign Fabricators Inc",
    "wof:placetype":"venue"
},
  "geometry": {"coordinates":[-86.906143,34.367995],"type":"Point"}
}