{
  "type": "Feature",
  "properties": {
    "addr:full":"1841 Montgomery Hwy Birmingham AL 35244",
    "addr:housenumber":"1841",
    "addr:postcode":"35244",
    "addr:street":"Montgomery Hwy",
    "iso:country":"US",
    "sg:address":"1841 Montgomery Hwy",
    "sg:city":"Birmingham",
    "sg:classifiers":[
        {
            "category":"Sports & Exercise",
            "subcategory":"Gym",
            "type":"Entertainment"
        }
    ],
    "sg:phone":"+1 205 989 5673",
    "sg:postcode":"35244",
    "sg:province":"AL",
    "sg:tags":[
        "club",
        "health",
        "studio",
        "gymnasium"
    ],
    "wof:name":"Lord's Gym",
    "wof:placetype":"venue"
},
  "geometry": {"coordinates":[-86.795109,33.350507],"type":"Point"}
}