{
  "type": "Feature",
  "properties": {
    "addr:full":"27625 US Hwy 98 Daphne AL 36526",
    "addr:postcode":"27625;36526",
    "addr:street":"Us Hwy 98",
    "iso:country":"US",
    "sg:address":"27625 US Hwy 98",
    "sg:city":"Daphne",
    "sg:classifiers":[
        {
            "category":"Social Services",
            "type":"Services"
        }
    ],
    "sg:phone":"+1 251 626 7959",
    "sg:postcode":"36526",
    "sg:province":"AL",
    "sg:tags":[
        "professional",
        "clinic",
        "counselor",
        "specialty",
        "outpatient"
    ],
    "wof:name":"Crossway Counseling Center",
    "wof:placetype":"venue"
},
  "geometry": {"coordinates":[-87.90881,30.626223],"type":"Point"}
}