{
  "type": "Feature",
  "properties": {
    "addr:full":"745 Rocky Branch Dr Guntersville AL 35976",
    "addr:housenumber":"745",
    "addr:postcode":"35976",
    "addr:street":"Rocky Branch Dr",
    "iso:country":"US",
    "sg:address":"745 Rocky Branch Dr",
    "sg:city":"Guntersville",
    "sg:classifiers":[
        {
            "category":"Building & Trades",
            "subcategory":"Construction",
            "type":"Services"
        }
    ],
    "sg:phone":"+1 256 878 3400",
    "sg:postcode":"35976",
    "sg:province":"AL",
    "sg:tags":[
        "resurfacing",
        "laying",
        "refinishing",
        "floor"
    ],
    "wof:name":"Jeff Rice Flooring Instltn",
    "wof:placetype":"venue"
},
  "geometry": {"coordinates":[-86.35816800000001,34.250108],"type":"Point"}
}