{
  "type": "Feature",
  "properties": {
    "iso:country":"US",
    "sg:address":"23701 Redtown Rd",
    "sg:city":"Atmore",
    "sg:classifiers":[
        {
            "category":"Food & Beverages",
            "subcategory":"Groceries & Convenience Stores",
            "type":"Retail Goods"
        }
    ],
    "sg:phone":"+1 251 577 6484",
    "sg:postcode":"36502",
    "sg:province":"AL",
    "wof:name":"Lottie Grocery",
    "wof:placetype":"venue"
},
  "geometry": {"coordinates":[-87.61707199999999,31.128617],"type":"Point"}
}