{
  "type": "Feature",
  "properties": {
    "iso:country":"US",
    "sg:address":"600 Oakwood Ave NE",
    "sg:city":"Huntsville",
    "sg:classifiers":[
        {
            "category":"Retail",
            "subcategory":"Auto Repair",
            "type":"Services"
        }
    ],
    "sg:phone":"+1 256 536 6471",
    "sg:postcode":"35811",
    "sg:province":"AL",
    "sg:tags":[
        "repairing",
        "automobile"
    ],
    "wof:name":"Paul's Auto Repair",
    "wof:placetype":"venue"
},
  "geometry": {"coordinates":[-86.576065,34.749078],"type":"Point"}
}