{
  "type": "Feature",
  "properties": {
    "iso:country":"US",
    "sg:address":"2600 Abbott Dr",
    "sg:city":"Pell City",
    "sg:classifiers":[
        {
            "category":"Health Services",
            "subcategory":"Doctor",
            "type":"Services"
        }
    ],
    "sg:phone":"+1 205 338 9837",
    "sg:postcode":"35128",
    "sg:province":"AL",
    "sg:tags":[
        "physician",
        "surgeon"
    ],
    "wof:name":"Wade M Cline MD",
    "wof:placetype":"venue"
},
  "geometry": {"coordinates":[-86.273377,33.519051],"type":"Point"}
}