{
  "type": "Feature",
  "properties": {
    "iso:country":"US",
    "sg:address":"920 3rd Ave SW",
    "sg:city":"Alabaster",
    "sg:classifiers":[
        {
            "category":"Manufacturing",
            "subcategory":"Paper Products",
            "type":"Manufacturing & Wholesale Goods"
        }
    ],
    "sg:phone":"+1 205 620 6967",
    "sg:postcode":"35007",
    "sg:province":"AL",
    "sg:tags":[
        "stationery",
        "mfg",
        "supply"
    ],
    "wof:name":"Sticker There",
    "wof:placetype":"venue"
},
  "geometry": {"coordinates":[-86.828565,33.242504],"type":"Point"}
}