{
  "type": "Feature",
  "properties": {
    "addr:full":"2534 Old Shell Rd Mobile AL 36607",
    "addr:housenumber":"2534",
    "addr:postcode":"36607",
    "addr:street":"Old Shell Rd",
    "iso:country":"US",
    "sg:address":"2534 Old Shell Rd",
    "sg:city":"Mobile",
    "sg:classifiers":[
        {
            "category":"Autos & Motor Vehicles",
            "subcategory":"Auto Supplies",
            "type":"Retail Goods"
        },
        {
            "category":"Wholesale",
            "subcategory":"Auto Parts",
            "type":"Manufacturing & Wholesale Goods"
        }
    ],
    "sg:phone":"+1 251 471 5846",
    "sg:postcode":"36607",
    "sg:province":"AL",
    "sg:tags":[
        "automobile"
    ],
    "wof:name":"USA Matic Inc",
    "wof:placetype":"venue"
},
  "geometry": {"coordinates":[-88.09875599999999,30.690392],"type":"Point"}
}