{
  "type": "Feature",
  "properties": {
    "addr:full":"7857 Old Sylacauga Hwy Childersburg AL 35044",
    "addr:housenumber":"7857",
    "addr:postcode":"35044",
    "addr:street":"Old Sylacauga Hwy",
    "iso:country":"US",
    "sg:address":"7857 Old Sylacauga Hwy",
    "sg:city":"Childersburg",
    "sg:classifiers":[
        {
            "category":"Organizations",
            "subcategory":"Religious Organization",
            "type":"Services"
        }
    ],
    "sg:phone":"+1 256 378 5515",
    "sg:postcode":"35044",
    "sg:province":"AL",
    "sg:tags":[
        "church"
    ],
    "wof:name":"Victory Baptist Church",
    "wof:placetype":"venue"
},
  "geometry": {"coordinates":[-86.348162,33.257855],"type":"Point"}
}