{
  "type": "Feature",
  "properties": {
    "iso:country":"US",
    "sg:address":"127 Textile Ave",
    "sg:city":"Albertville",
    "sg:classifiers":[
        {
            "category":"Manufacturing",
            "subcategory":"Textiles",
            "type":"Manufacturing & Wholesale Goods"
        }
    ],
    "sg:phone":"+1 256 878 4401",
    "sg:postcode":"35950",
    "sg:province":"AL",
    "sg:tags":[
        "surgical",
        "fabric",
        "cotton",
        "mill",
        "mfg"
    ],
    "wof:name":"Kendall Healthcare Products",
    "wof:placetype":"venue"
},
  "geometry": {"coordinates":[-86.189959,34.24813],"type":"Point"}
}