{
  "type": "Feature",
  "properties": {
    "iso:country":"US",
    "sg:address":"8880 Co Rd 65",
    "sg:city":"Foley",
    "sg:classifiers":[
        {
            "category":"Professional",
            "type":"Services"
        }
    ],
    "sg:phone":"+1 251 971 1205",
    "sg:postcode":"36535",
    "sg:province":"AL",
    "sg:tags":[
        "establishment"
    ],
    "wof:name":"Marterra Dolphins",
    "wof:placetype":"venue"
},
  "geometry": {"coordinates":[-87.71708,30.355225],"type":"Point"}
}