{
  "type": "Feature",
  "properties": {
    "addr:full":"3750 Co Rd 1 Collinsville AL 35961",
    "addr:housenumber":"3750",
    "addr:postcode":"35961",
    "addr:street":"Co Rd 1",
    "iso:country":"US",
    "sg:address":"3750 Co Rd 1",
    "sg:city":"Collinsville",
    "sg:classifiers":[
        {
            "category":"Farming",
            "subcategory":"Livestock Farm",
            "type":"Manufacturing & Wholesale Goods"
        }
    ],
    "sg:phone":"+1 256 523 3346",
    "sg:postcode":"35961",
    "sg:province":"AL",
    "sg:tags":[
        "beef",
        "feedlot",
        "cattle"
    ],
    "wof:name":"Miller Wilson",
    "wof:placetype":"venue"
},
  "geometry": {"coordinates":[-85.83062200000001,34.231674],"type":"Point"}
}