{
  "type": "Feature",
  "properties": {
    "addr:full":"520 Cleveland Ave Attalla AL 35954",
    "addr:housenumber":"520",
    "addr:postcode":"35954",
    "addr:street":"Cleveland Ave",
    "iso:country":"US",
    "sg:address":"520 Cleveland Ave",
    "sg:city":"Attalla",
    "sg:classifiers":[
        {
            "category":"Organizations",
            "subcategory":"Religious Organization",
            "type":"Services"
        }
    ],
    "sg:phone":"+1 256 538 7641",
    "sg:postcode":"35954",
    "sg:province":"AL",
    "wof:name":"Cherry Street Baptist Church",
    "wof:placetype":"venue"
},
  "geometry": {"coordinates":[-86.078335,34.018021],"type":"Point"}
}