{
  "type": "Feature",
  "properties": {
    "iso:country":"US",
    "sg:address":"4007 Patton Rd SW",
    "sg:city":"Huntsville",
    "sg:classifiers":[
        {
            "category":"Building & Trades",
            "subcategory":"Construction",
            "type":"Services"
        }
    ],
    "sg:phone":"+1 256 519 8069",
    "sg:postcode":"35805",
    "sg:province":"AL",
    "sg:tags":[
        "painter"
    ],
    "wof:name":"Headrick & Son Painting",
    "wof:placetype":"venue"
},
  "geometry": {"coordinates":[-86.627282,34.697592],"type":"Point"}
}