{
  "type": "Feature",
  "properties": {
    "addr:full":"6281 US Hwy 431 Owens Cross Rds AL 35763",
    "addr:housenumber":"6281",
    "addr:postcode":"35763",
    "addr:street":"Us Hwy 431 Owens Cross Rds",
    "iso:country":"US",
    "sg:address":"6281 US Hwy 431",
    "sg:city":"Owens Cross Rds",
    "sg:classifiers":[
        {
            "category":"Real Estate",
            "subcategory":"Real Estate Agent",
            "type":"Services"
        }
    ],
    "sg:phone":"+1 256 650 0883",
    "sg:postcode":"35763",
    "sg:province":"AL",
    "wof:name":"Coldwell Banker Premier",
    "wof:placetype":"venue"
},
  "geometry": {"coordinates":[-86.48923000000001,34.670308],"type":"Point"}
}