{
  "type": "Feature",
  "properties": {
    "iso:country":"US",
    "sg:address":"300 Vestavia Pkwy",
    "sg:city":"Birmingham",
    "sg:classifiers":[
        {
            "category":"Shopping",
            "subcategory":"Computers & Home Electronics",
            "type":"Retail Goods"
        }
    ],
    "sg:phone":"+1 205 823 1084",
    "sg:postcode":"35216",
    "sg:province":"AL",
    "wof:name":"Radio Shack",
    "wof:placetype":"venue"
},
  "geometry": {"coordinates":[-86.798222,33.417098],"type":"Point"}
}