{
  "type": "Feature",
  "properties": {
    "iso:country":"US",
    "sg:address":"4022 Dunsmore St SE",
    "sg:city":"Huntsville",
    "sg:classifiers":[
        {
            "category":"Professional",
            "subcategory":"Business Services",
            "type":"Services"
        },
        {
            "category":"Manufacturing",
            "subcategory":"Printing",
            "type":"Manufacturing & Wholesale Goods"
        }
    ],
    "sg:phone":"+1 256 650 0114",
    "sg:postcode":"35802",
    "sg:province":"AL",
    "sg:tags":[
        "commercial",
        "embroidery"
    ],
    "wof:name":"Express Embroidery & Screen PR",
    "wof:placetype":"venue"
},
  "geometry": {"coordinates":[-86.552385,34.699892],"type":"Point"}
}