{
  "type": "Feature",
  "properties": {
    "addr:full":"1377 Paula St Prattville AL 36067",
    "addr:housenumber":"1377",
    "addr:postcode":"36067",
    "addr:street":"Paula St",
    "iso:country":"US",
    "sg:address":"1377 Paula St",
    "sg:city":"Prattville",
    "sg:classifiers":[
        {
            "category":"Building & Trades",
            "subcategory":"Plumbing",
            "type":"Services"
        }
    ],
    "sg:phone":"+1 334 361 0807",
    "sg:postcode":"36067",
    "sg:province":"AL",
    "sg:tags":[
        "contractor"
    ],
    "wof:name":"GA Plumbing Inc",
    "wof:placetype":"venue"
},
  "geometry": {"coordinates":[-86.458242,32.51116],"type":"Point"}
}