{
  "type": "Feature",
  "properties": {
    "iso:country":"US",
    "sg:address":"630 Noble St",
    "sg:city":"Anniston",
    "sg:classifiers":[
        {
            "category":"Wholesale",
            "subcategory":"Machinery & Supplies",
            "type":"Manufacturing & Wholesale Goods"
        }
    ],
    "sg:phone":"+1 256 236 0127",
    "sg:postcode":"36201",
    "sg:province":"AL",
    "sg:tags":[
        "equipment",
        "industrial"
    ],
    "sg:website":"www.newmanindustrial.com",
    "wof:name":"Newman Industrial Supply Inc",
    "wof:placetype":"venue"
},
  "geometry": {"coordinates":[-85.829796,33.651648],"type":"Point"}
}