{
  "type": "Feature",
  "properties": {
    "addr:full":"1215 Lake Forest Cir Birmingham AL 35244",
    "addr:housenumber":"1215",
    "addr:postcode":"35244",
    "addr:street":"Lake Forest Cir",
    "iso:country":"US",
    "sg:address":"1215 Lake Forest Cir",
    "sg:city":"Birmingham",
    "sg:classifiers":[
        {
            "category":"Building & Trades",
            "subcategory":"Construction",
            "type":"Services"
        }
    ],
    "sg:phone":"+1 205 733 9583",
    "sg:postcode":"35244",
    "sg:province":"AL",
    "sg:tags":[
        "house"
    ],
    "wof:name":"Precision Home Crafters LLC",
    "wof:placetype":"venue"
},
  "geometry": {"coordinates":[-86.830794,33.341276],"type":"Point"}
}