{
  "type": "Feature",
  "properties": {
    "iso:country":"US",
    "sg:address":"2809 Crescent Ave",
    "sg:city":"Birmingham",
    "sg:classifiers":[
        {
            "category":"Manufacturing",
            "subcategory":"Metals",
            "type":"Manufacturing & Wholesale Goods"
        }
    ],
    "sg:phone":"+1 205 870 4422",
    "sg:postcode":"35209",
    "sg:province":"AL",
    "sg:tags":[
        "glass",
        "product",
        "mfg"
    ],
    "wof:name":"Bob Rosser Hand Engraver",
    "wof:placetype":"venue"
},
  "geometry": {"coordinates":[-86.793788,33.479157],"type":"Point"}
}