{
  "type": "Feature",
  "properties": {
    "iso:country":"US",
    "sg:address":"2800 Dauphin Island Pkwy",
    "sg:city":"Mobile",
    "sg:classifiers":[
        {
            "category":"Health Services",
            "subcategory":"Chiropractor",
            "type":"Services"
        }
    ],
    "sg:phone":"+1 251 473 7246",
    "sg:postcode":"36605",
    "sg:province":"AL",
    "wof:name":"Walker Scott DC Dr",
    "wof:placetype":"venue"
},
  "geometry": {"coordinates":[-88.0732,30.613878],"type":"Point"}
}