{
  "type": "Feature",
  "properties": {
    "addr:full":"3202 State Rte 75 Flat Rock AL 35966",
    "addr:housenumber":"3202",
    "addr:postcode":"35966",
    "addr:street":"State Rte 75",
    "iso:country":"US",
    "sg:address":"3202 State Rte 75",
    "sg:city":"Flat Rock",
    "sg:classifiers":[
        {
            "category":"Shopping",
            "subcategory":"Bicycles & Sporting Goods",
            "type":"Retail Goods"
        }
    ],
    "sg:phone":"+1 256 632 3790",
    "sg:postcode":"35966",
    "sg:province":"AL",
    "wof:name":"A1 Saddlery",
    "wof:placetype":"venue"
},
  "geometry": {"coordinates":[-85.59834499999999,34.781657],"type":"Point"}
}