{
  "type": "Feature",
  "properties": {
    "addr:full":"433 Valley Ave Birmingham AL 35209",
    "addr:housenumber":"433",
    "addr:postcode":"35209",
    "addr:street":"Valley Ave",
    "iso:country":"US",
    "sg:address":"433 Valley Ave",
    "sg:city":"Birmingham",
    "sg:classifiers":[
        {
            "category":"Food & Beverages",
            "subcategory":"Groceries & Convenience Stores",
            "type":"Retail Goods"
        }
    ],
    "sg:phone":"+1 205 916 0707",
    "sg:postcode":"35209",
    "sg:province":"AL",
    "wof:name":"Gordos Market Inc",
    "wof:placetype":"venue"
},
  "geometry": {"coordinates":[-86.818641,33.473279],"type":"Point"}
}