{
  "type": "Feature",
  "properties": {
    "iso:country":"US",
    "sg:address":"201 20th St N",
    "sg:city":"Pell City",
    "sg:classifiers":[
        {
            "category":"Shopping",
            "subcategory":"Computers & Home Electronics",
            "type":"Retail Goods"
        }
    ],
    "sg:phone":"+1 205 338 3890",
    "sg:postcode":"35125",
    "sg:province":"AL",
    "sg:tags":[
        "equipment",
        "dealer"
    ],
    "wof:name":"Netland Systems",
    "wof:placetype":"venue"
},
  "geometry": {"coordinates":[-86.285621,33.588322],"type":"Point"}
}