{
  "type": "Feature",
  "properties": {
    "addr:full":"511 Vanity Fair Ave Butler AL 36904",
    "addr:housenumber":"511",
    "addr:postcode":"36904",
    "addr:street":"Vanity Fair Ave",
    "iso:country":"US",
    "sg:address":"511 Vanity Fair Ave",
    "sg:city":"Butler",
    "sg:classifiers":[
        {
            "category":"Real Estate",
            "subcategory":"Real Estate Operator",
            "type":"Services"
        }
    ],
    "sg:phone":"+1 205 459 4642",
    "sg:postcode":"36904",
    "sg:province":"AL",
    "sg:tags":[
        "apartment"
    ],
    "wof:name":"Sherwood Manor Apartments",
    "wof:placetype":"venue"
},
  "geometry": {"coordinates":[-88.208378,32.09206],"type":"Point"}
}