{
  "type": "Feature",
  "properties": {
    "addr:full":"501 New Market Rd New Market AL 35761",
    "addr:housenumber":"501",
    "addr:postcode":"35761",
    "addr:street":"New Market Rd",
    "iso:country":"US",
    "sg:address":"501 New Market Rd",
    "sg:city":"New Market",
    "sg:classifiers":[
        {
            "category":"Real Estate",
            "subcategory":"Real Estate Agent",
            "type":"Services"
        }
    ],
    "sg:phone":"+1 256 379 3040",
    "sg:postcode":"35761",
    "sg:province":"AL",
    "sg:tags":[
        "cooperative"
    ],
    "wof:name":"Madison County Coop",
    "wof:placetype":"venue"
},
  "geometry": {"coordinates":[-86.465817,34.924653],"type":"Point"}
}