{
  "type": "Feature",
  "properties": {
    "iso:country":"US",
    "sg:address":"15158 Bethabara Rd",
    "sg:city":"Northport",
    "sg:classifiers":[
        {
            "category":"Organizations",
            "subcategory":"Religious Organization",
            "type":"Services"
        }
    ],
    "sg:phone":"+1 205 339 8817",
    "sg:postcode":"35475",
    "sg:province":"AL",
    "sg:tags":[
        "church"
    ],
    "wof:name":"Bethabara Baptist",
    "wof:placetype":"venue"
},
  "geometry": {"coordinates":[-87.70922299999999,33.37747],"type":"Point"}
}