{
  "type": "Feature",
  "properties": {
    "addr:full":"2891 Allison-Bonnett Memorial Dr Hueytown AL 35023",
    "addr:housenumber":"2891",
    "addr:postcode":"35023",
    "addr:street":"Allison-Bonnett Memorial Dr",
    "iso:country":"US",
    "sg:address":"2891 Allison-Bonnett Memorial Dr",
    "sg:city":"Hueytown",
    "sg:classifiers":[
        {
            "category":"Food & Beverages",
            "subcategory":"Groceries & Convenience Stores",
            "type":"Retail Goods"
        }
    ],
    "sg:phone":"+1 205 744 0482",
    "sg:postcode":"35023",
    "sg:province":"AL",
    "sg:tags":[
        "grocer"
    ],
    "wof:name":"Food World",
    "wof:placetype":"venue"
},
  "geometry": {"coordinates":[-86.965881,33.456438],"type":"Point"}
}