{
  "type": "Feature",
  "properties": {
    "iso:country":"US",
    "sg:address":"6741 Taylor Cir",
    "sg:city":"Montgomery",
    "sg:classifiers":[
        {
            "category":"Personal",
            "subcategory":"Beauty Salon",
            "type":"Services"
        }
    ],
    "sg:phone":"+1 334 244 6421",
    "sg:postcode":"36117",
    "sg:province":"AL",
    "sg:tags":[
        "shop"
    ],
    "wof:name":"Ahead of Time Hair Studio",
    "wof:placetype":"venue"
},
  "geometry": {"coordinates":[-86.175617,32.346595],"type":"Point"}
}