{
  "type": "Feature",
  "properties": {
    "addr:full":"750 Co Rd 49 Hamilton AL 35570",
    "addr:housenumber":"750;49",
    "addr:postcode":"35570",
    "addr:street":"Co Rd",
    "iso:country":"US",
    "sg:address":"750 Co Rd 49",
    "sg:city":"Hamilton",
    "sg:classifiers":[
        {
            "category":"Building & Trades",
            "subcategory":"Construction",
            "type":"Services"
        }
    ],
    "sg:phone":"+1 205 921 3729",
    "sg:postcode":"35570",
    "sg:province":"AL",
    "sg:tags":[
        "gutter",
        "contractor"
    ],
    "wof:name":"Southland Gutter & Siding",
    "wof:placetype":"venue"
},
  "geometry": {"coordinates":[-87.901003,34.148595],"type":"Point"}
}