{
  "type": "Feature",
  "properties": {
    "addr:full":"1345 Steiner Ave SW Birmingham AL 35211",
    "addr:housenumber":"1345",
    "addr:postcode":"35211",
    "addr:street":"Steiner Ave Sw",
    "iso:country":"US",
    "sg:address":"1345 Steiner Ave SW",
    "sg:city":"Birmingham",
    "sg:classifiers":[
        {
            "category":"Social Services",
            "type":"Services"
        }
    ],
    "sg:phone":"+1 205 780 7464",
    "sg:postcode":"35211",
    "sg:province":"AL",
    "wof:name":"Ping",
    "wof:placetype":"venue"
},
  "geometry": {"coordinates":[-86.85263500000001,33.491394],"type":"Point"}
}