{
  "type": "Feature",
  "properties": {
    "iso:country":"US",
    "sg:address":"1616 S Eufaula Ave",
    "sg:city":"Eufaula",
    "sg:classifiers":[
        {
            "category":"Utilities",
            "subcategory":"Refuse",
            "type":"Services"
        }
    ],
    "sg:phone":"+1 334 687 9331",
    "sg:postcode":"36027",
    "sg:province":"AL",
    "sg:tags":[
        "garbage",
        "collection"
    ],
    "wof:name":"Taylor's Of Eufaula Inc",
    "wof:placetype":"venue"
},
  "geometry": {"coordinates":[-85.153719,31.87362],"type":"Point"}
}