{
  "type": "Feature",
  "properties": {
    "iso:country":"US",
    "sg:address":"1612 Hurtel St",
    "sg:city":"Mobile",
    "sg:classifiers":[
        {
            "category":"Utilities",
            "subcategory":"Refuse",
            "type":"Services"
        }
    ],
    "sg:phone":"+1 251 457 8298",
    "sg:postcode":"36605",
    "sg:province":"AL",
    "sg:tags":[
        "system"
    ],
    "wof:name":"Robinson Sanitation",
    "wof:placetype":"venue"
},
  "geometry": {"coordinates":[-88.077997,30.656882],"type":"Point"}
}