{
  "type": "Feature",
  "properties": {
    "addr:full":"6112 Roosevelt Cir NW Huntsville AL 35810",
    "addr:housenumber":"6112",
    "addr:postcode":"35810",
    "addr:street":"Roosevelt Cir Nw",
    "iso:country":"US",
    "sg:address":"6112 Roosevelt Cir NW",
    "sg:city":"Huntsville",
    "sg:classifiers":[
        {
            "category":"Personal",
            "subcategory":"Beauty Salon",
            "type":"Services"
        }
    ],
    "sg:phone":"+1 256 859 6670",
    "sg:postcode":"35810",
    "sg:province":"AL",
    "sg:tags":[
        "shop"
    ],
    "wof:name":"Gordon's Beauty Shop",
    "wof:placetype":"venue"
},
  "geometry": {"coordinates":[-86.587914,34.799019],"type":"Point"}
}