{
  "type": "Feature",
  "properties": {
    "iso:country":"US",
    "sg:address":"7565 Heaton Dr",
    "sg:city":"Theodore",
    "sg:classifiers":[
        {
            "category":"Building & Trades",
            "subcategory":"Construction",
            "type":"Services"
        },
        {
            "category":"Home & Garden",
            "subcategory":"Home Furnishings",
            "type":"Retail Goods"
        }
    ],
    "sg:phone":"+1 251 653 2362",
    "sg:postcode":"36582",
    "sg:province":"AL",
    "sg:tags":[
        "fireplace",
        "contractor"
    ],
    "wof:name":"Builder's Choice",
    "wof:placetype":"venue"
},
  "geometry": {"coordinates":[-88.166761,30.532683],"type":"Point"}
}