{
  "type": "Feature",
  "properties": {
    "iso:country":"US",
    "sg:address":"3919 Veterans Memorial Dr",
    "sg:city":"Adamsville",
    "sg:classifiers":[
        {
            "category":"Autos & Motor Vehicles",
            "subcategory":"Boat Sales",
            "type":"Retail Goods"
        },
        {
            "category":"Autos & Motor Vehicles",
            "subcategory":"Motorcycle Sales",
            "type":"Retail Goods"
        }
    ],
    "sg:phone":"+1 205 674 5511",
    "sg:postcode":"35005",
    "sg:province":"AL",
    "sg:tags":[
        "repair",
        "all",
        "terrain"
    ],
    "wof:name":"Competition Motor Sports Inc",
    "wof:placetype":"venue"
},
  "geometry": {"coordinates":[-86.931604,33.586356],"type":"Point"}
}