{
  "type": "Feature",
  "properties": {
    "iso:country":"US",
    "sg:address":"181 Columbus St E",
    "sg:city":"Cordova",
    "sg:classifiers":[
        {
            "category":"Organizations",
            "subcategory":"Religious Organization",
            "type":"Services"
        }
    ],
    "sg:phone":"+1 205 483 9991",
    "sg:postcode":"35550",
    "sg:province":"AL",
    "sg:tags":[
        "church"
    ],
    "wof:name":"St James CME",
    "wof:placetype":"venue"
},
  "geometry": {"coordinates":[-87.18156,33.752899],"type":"Point"}
}