{
  "type": "Feature",
  "properties": {
    "iso:country":"US",
    "sg:address":"2701 Opelika Rd",
    "sg:city":"Phenix City",
    "sg:classifiers":[
        {
            "category":"Freight",
            "type":"Transportation"
        }
    ],
    "sg:phone":"+1 334 448 6003",
    "sg:postcode":"36870",
    "sg:province":"AL",
    "sg:tags":[
        "trucking"
    ],
    "wof:name":"Burditt Trucking Inc",
    "wof:placetype":"venue"
},
  "geometry": {"coordinates":[-85.03369000000001,32.486525],"type":"Point"}
}