{
  "type": "Feature",
  "properties": {
    "iso:country":"US",
    "sg:address":"904 Gilmer Ave",
    "sg:city":"Tallassee",
    "sg:classifiers":[
        {
            "category":"Shopping",
            "subcategory":"Tobacco",
            "type":"Retail Goods"
        }
    ],
    "sg:phone":"+1 334 252 0050",
    "sg:postcode":"36078",
    "sg:province":"AL",
    "sg:tags":[
        "cigarette",
        "cigar",
        "dealer"
    ],
    "wof:name":"D J's Tobacco & More",
    "wof:placetype":"venue"
},
  "geometry": {"coordinates":[-85.90989,32.544595],"type":"Point"}
}