{
  "type": "Feature",
  "properties": {
    "addr:full":"220 Distribution Dr Birmingham AL 35209",
    "addr:housenumber":"220",
    "addr:postcode":"35209",
    "addr:street":"Distribution Dr",
    "iso:country":"US",
    "sg:address":"220 Distribution Dr",
    "sg:city":"Birmingham",
    "sg:classifiers":[
        {
            "category":"Freight",
            "type":"Transportation"
        }
    ],
    "sg:phone":"+1 205 290 2767",
    "sg:postcode":"35209",
    "sg:province":"AL",
    "sg:tags":[
        "warehouse"
    ],
    "wof:name":"Southern Progress Corporation",
    "wof:placetype":"venue"
},
  "geometry": {"coordinates":[-86.843772,33.44477],"type":"Point"}
}