{
  "type": "Feature",
  "properties": {
    "iso:country":"US",
    "sg:address":"5765 Co Rd 200",
    "sg:city":"Florence",
    "sg:classifiers":[
        {
            "category":"Food & Beverages",
            "subcategory":"Specialty",
            "type":"Retail Goods"
        }
    ],
    "sg:phone":"+1 256 760 0020",
    "sg:postcode":"35633",
    "sg:province":"AL",
    "wof:name":"L & H Spring Water Distrs",
    "wof:placetype":"venue"
},
  "geometry": {"coordinates":[-87.769368,34.875845],"type":"Point"}
}