{
  "type": "Feature",
  "properties": {
    "iso:country":"US",
    "sg:address":"63 S Royal St",
    "sg:city":"Mobile",
    "sg:classifiers":[
        {
            "category":"Professional",
            "subcategory":"Lawyer & Legal Services",
            "type":"Services"
        }
    ],
    "sg:phone":"+1 251 431 8832",
    "sg:postcode":"36602",
    "sg:province":"AL",
    "sg:tags":[
        "attorney"
    ],
    "wof:name":"Karen T Luce",
    "wof:placetype":"venue"
},
  "geometry": {"coordinates":[-88.040274,30.690655],"type":"Point"}
}