{
  "type": "Feature",
  "properties": {
    "addr:full":"25 Bussey Rd Dora AL 35062",
    "addr:housenumber":"25",
    "addr:postcode":"35062",
    "addr:street":"Bussey Rd",
    "iso:country":"US",
    "sg:address":"25 Bussey Rd",
    "sg:city":"Dora",
    "sg:classifiers":[
        {
            "category":"Building & Trades",
            "subcategory":"Construction",
            "type":"Services"
        }
    ],
    "sg:phone":"+1 205 648 6464",
    "sg:postcode":"35062",
    "sg:province":"AL",
    "sg:tags":[
        "contractor"
    ],
    "wof:name":"D & D Construction",
    "wof:placetype":"venue"
},
  "geometry": {"coordinates":[-87.072035,33.745156],"type":"Point"}
}