{
  "type": "Feature",
  "properties": {
    "addr:full":"618 Montgomery Hwy Birmingham AL 35216",
    "addr:housenumber":"618",
    "addr:postcode":"35216",
    "addr:street":"Montgomery Hwy",
    "iso:country":"US",
    "sg:address":"618 Montgomery Hwy",
    "sg:city":"Birmingham",
    "sg:classifiers":[
        {
            "category":"Shopping",
            "subcategory":"Photographic Equipment",
            "type":"Retail Goods"
        }
    ],
    "sg:phone":"+1 205 823 8361",
    "sg:postcode":"35216",
    "sg:province":"AL",
    "sg:tags":[
        "supply"
    ],
    "wof:name":"Ritz Camera",
    "wof:placetype":"venue"
},
  "geometry": {"coordinates":[-86.78975,33.448994],"type":"Point"}
}