{
  "type": "Feature",
  "properties": {
    "addr:full":"316 Cole Dr Guin AL 35563",
    "addr:housenumber":"316",
    "addr:postcode":"35563",
    "addr:street":"Cole Dr Guin",
    "iso:country":"US",
    "sg:address":"316 Cole Dr",
    "sg:city":"Guin",
    "sg:classifiers":[
        {
            "category":"Organizations",
            "subcategory":"Community Association",
            "type":"Services"
        }
    ],
    "sg:phone":"+1 205 468 3580",
    "sg:postcode":"35563",
    "sg:province":"AL",
    "sg:tags":[
        "club"
    ],
    "wof:name":"B & B Hunting Club",
    "wof:placetype":"venue"
},
  "geometry": {"coordinates":[-87.96351300000001,33.951768],"type":"Point"}
}