{
  "type": "Feature",
  "properties": {
    "iso:country":"US",
    "sg:address":"316 Cole Dr",
    "sg:city":"Guin",
    "sg:classifiers":[
        {
            "category":"Organizations",
            "subcategory":"Community Association",
            "type":"Services"
        }
    ],
    "sg:phone":"+1 205 468 3580",
    "sg:postcode":"35563",
    "sg:province":"AL",
    "sg:tags":[
        "club"
    ],
    "wof:name":"B & B Hunting Club",
    "wof:placetype":"venue"
},
  "geometry": {"coordinates":[-87.963513,33.951768],"type":"Point"}
}