{
  "type": "Feature",
  "properties": {
    "iso:country":"US",
    "sg:address":"647 East Ln",
    "sg:city":"Auburn",
    "sg:classifiers":[
        {
            "category":"Professional",
            "type":"Services"
        }
    ],
    "sg:phone":"+1 334 502 7965",
    "sg:postcode":"36830",
    "sg:province":"AL",
    "wof:name":"Dbcrouse LLC",
    "wof:placetype":"venue"
},
  "geometry": {"coordinates":[-85.450213,32.617621],"type":"Point"}
}