{
  "type": "Feature",
  "properties": {
    "addr:full":"2910 Main St Millbrook AL 36054",
    "addr:housenumber":"2910",
    "addr:postcode":"36054",
    "addr:street":"Main St",
    "iso:country":"US",
    "sg:address":"2910 Main St",
    "sg:city":"Millbrook",
    "sg:classifiers":[
        {
            "category":"Shopping",
            "subcategory":"Discount & Variety Stores",
            "type":"Retail Goods"
        }
    ],
    "sg:phone":"+1 334 285 3778",
    "sg:postcode":"36054",
    "sg:province":"AL",
    "wof:name":"Family Dollar Stores",
    "wof:placetype":"venue"
},
  "geometry": {"coordinates":[-86.36055399999999,32.471461],"type":"Point"}
}