{
  "type": "Feature",
  "properties": {
    "addr:full":"405 Old School St Spruce Pine AL 35585",
    "addr:housenumber":"405",
    "addr:postcode":"35585",
    "addr:street":"Old School St",
    "iso:country":"US",
    "sg:address":"405 Old School St",
    "sg:city":"Spruce Pine",
    "sg:classifiers":[
        {
            "category":"Building & Trades",
            "subcategory":"Construction",
            "type":"Services"
        }
    ],
    "sg:phone":"+1 256 331 0008",
    "sg:postcode":"35585",
    "sg:province":"AL",
    "sg:tags":[
        "dock"
    ],
    "sg:website":"www.mld.com",
    "wof:name":"M L Docks",
    "wof:placetype":"venue"
},
  "geometry": {"coordinates":[-87.729829,34.394338],"type":"Point"}
}