{
  "type": "Feature",
  "properties": {
    "addr:full":"1300 4th Ave N Bessemer AL 35020",
    "addr:housenumber":"1300",
    "addr:postcode":"35020",
    "addr:street":"4Th Ave N",
    "iso:country":"US",
    "sg:address":"1300 4th Ave N",
    "sg:city":"Bessemer",
    "sg:classifiers":[
        {
            "category":"Retail",
            "subcategory":"Funeral Services",
            "type":"Services"
        }
    ],
    "sg:phone":"+1 205 425 2424",
    "sg:postcode":"35020",
    "sg:province":"AL",
    "sg:tags":[
        "home"
    ],
    "wof:name":"Brown Service Funeral Home",
    "wof:placetype":"venue"
},
  "geometry": {"coordinates":[-86.95899799999999,33.397675],"type":"Point"}
}