{
  "type": "Feature",
  "properties": {
    "iso:country":"US",
    "sg:address":"207 Morgan St",
    "sg:city":"Dothan",
    "sg:classifiers":[
        {
            "category":"Real Estate",
            "subcategory":"Real Estate Agent",
            "type":"Services"
        }
    ],
    "sg:phone":"+1 334 793 9393",
    "sg:postcode":"36301",
    "sg:province":"AL",
    "wof:name":"Bob Hall Co",
    "wof:placetype":"venue"
},
  "geometry": {"coordinates":[-85.401281,31.223357],"type":"Point"}
}