{
  "type": "Feature",
  "properties": {
    "iso:country":"US",
    "sg:address":"19099 State Rte 145",
    "sg:city":"Shelby",
    "sg:classifiers":[
        {
            "category":"Social Services",
            "subcategory":"Child Care",
            "type":"Services"
        }
    ],
    "sg:phone":"+1 205 669 5197",
    "sg:postcode":"35143",
    "sg:province":"AL",
    "sg:tags":[
        "day"
    ],
    "wof:name":"Shelby Head Start Center",
    "wof:placetype":"venue"
},
  "geometry": {"coordinates":[-86.562704,33.084682],"type":"Point"}
}