{
  "type": "Feature",
  "properties": {
    "iso:country":"US",
    "sg:address":"6130 Clay Palmerdale Rd",
    "sg:city":"Pinson",
    "sg:classifiers":[
        {
            "category":"Shopping",
            "subcategory":"Gifts & Souvenirs",
            "type":"Retail Goods"
        }
    ],
    "sg:phone":"+1 205 680 5242",
    "sg:postcode":"35126",
    "sg:province":"AL",
    "sg:tags":[
        "shop"
    ],
    "wof:name":"Back In Time",
    "wof:placetype":"venue"
},
  "geometry": {"coordinates":[-86.621503,33.716964],"type":"Point"}
}