{
  "type": "Feature",
  "properties": {
    "addr:full":"614 W Fairview Ave Montgomery AL 36105",
    "addr:housenumber":"614",
    "addr:postcode":"36105",
    "addr:street":"W Fairview Ave",
    "iso:country":"US",
    "sg:address":"614 W Fairview Ave",
    "sg:city":"Montgomery",
    "sg:classifiers":[
        {
            "category":"Retail",
            "subcategory":"Auto Repair",
            "type":"Services"
        }
    ],
    "sg:phone":"+1 334 262 5270",
    "sg:postcode":"36105",
    "sg:province":"AL",
    "sg:tags":[
        "automotive"
    ],
    "wof:name":"Tonys Tire Service",
    "wof:placetype":"venue"
},
  "geometry": {"coordinates":[-86.318163,32.351681],"type":"Point"}
}