{
  "type": "Feature",
  "properties": {
    "iso:country":"US",
    "sg:address":"5634 Co Rd 43",
    "sg:city":"Clanton",
    "sg:classifiers":[
        {
            "category":"Government",
            "subcategory":"Fire Station",
            "type":"Public Place"
        }
    ],
    "sg:phone":"+1 205 646 2543",
    "sg:postcode":"35045",
    "sg:province":"AL",
    "sg:tags":[
        "protection"
    ],
    "wof:name":"Collins Chapel Vol Fire A",
    "wof:placetype":"venue"
},
  "geometry": {"coordinates":[-86.682954,32.92053],"type":"Point"}
}