{
  "type": "Feature",
  "properties": {
    "iso:country":"US",
    "sg:address":"1935 S College St",
    "sg:city":"Auburn",
    "sg:classifiers":[
        {
            "category":"Retail",
            "subcategory":"Laundry & Dry Cleaning",
            "type":"Services"
        }
    ],
    "sg:phone":"+1 334 501 7110",
    "sg:postcode":"36832",
    "sg:province":"AL",
    "sg:tags":[
        "drycleaning",
        "plant"
    ],
    "wof:name":"Penny Profit",
    "wof:placetype":"venue"
},
  "geometry": {"coordinates":[-85.500267,32.569618],"type":"Point"}
}