{
  "type": "Feature",
  "properties": {
    "iso:country":"US",
    "sg:address":"4680 Winchester Way",
    "sg:city":"Irondale",
    "sg:classifiers":[
        {
            "category":"Shopping",
            "subcategory":"Florist",
            "type":"Retail Goods"
        }
    ],
    "sg:phone":"+1 205 956 5185",
    "sg:postcode":"35210",
    "sg:province":"AL",
    "sg:website":"www.bigelowmotors.com",
    "wof:name":"Evelyn's Flower Cottage",
    "wof:placetype":"venue"
},
  "geometry": {"coordinates":[-86.665041,33.547877],"type":"Point"}
}