{
  "type": "Feature",
  "properties": {
    "addr:full":"3201 Monte Verde Cir Birmingham AL 35216",
    "addr:housenumber":"3201",
    "addr:postcode":"35216",
    "addr:street":"Monte Verde Cir",
    "iso:country":"US",
    "sg:address":"3201 Monte Verde Cir",
    "sg:city":"Birmingham",
    "sg:classifiers":[
        {
            "category":"Shopping",
            "subcategory":"Clothing, Apparel, & Fashions",
            "type":"Retail Goods"
        }
    ],
    "sg:phone":"+1 205 979 4971",
    "sg:postcode":"35216",
    "sg:province":"AL",
    "sg:tags":[
        "infant",
        "wear",
        "store"
    ],
    "wof:name":"Joyces Little People",
    "wof:placetype":"venue"
},
  "geometry": {"coordinates":[-86.80256300000001,33.405986],"type":"Point"}
}