{
  "type": "Feature",
  "properties": {
    "iso:country":"US",
    "sg:address":"17 S Florida St",
    "sg:city":"Mobile",
    "sg:classifiers":[
        {
            "category":"Personal",
            "subcategory":"Beauty Salon",
            "type":"Services"
        }
    ],
    "sg:phone":"+1 251 471 3128",
    "sg:postcode":"36606",
    "sg:province":"AL",
    "sg:tags":[
        "shop"
    ],
    "wof:name":"7 Step Hair Salon",
    "wof:placetype":"venue"
},
  "geometry": {"coordinates":[-88.100278,30.687141],"type":"Point"}
}