{
  "type": "Feature",
  "properties": {
    "iso:country":"US",
    "sg:address":"1404 Gilmer Ave",
    "sg:city":"Tallassee",
    "sg:classifiers":[
        {
            "category":"Autos & Motor Vehicles",
            "subcategory":"Fuel & Gas Station",
            "type":"Retail Goods"
        }
    ],
    "sg:phone":"+1 334 283 3550",
    "sg:postcode":"36078",
    "sg:province":"AL",
    "sg:tags":[
        "oil"
    ],
    "wof:name":"Tallassee Chevron & Food Mart",
    "wof:placetype":"venue"
},
  "geometry": {"coordinates":[-85.91345,32.548608],"type":"Point"}
}