{
  "type": "Feature",
  "properties": {
    "iso:country":"US",
    "sg:address":"1185 Huffman Rd",
    "sg:city":"Birmingham",
    "sg:classifiers":[
        {
            "category":"Shopping",
            "subcategory":"Beauty & Cosmetics",
            "type":"Retail Goods"
        }
    ],
    "sg:phone":"+1 205 853 2518",
    "sg:postcode":"35215",
    "sg:province":"AL",
    "sg:tags":[
        "merchandise"
    ],
    "wof:name":"Merle Norman Cosmetics",
    "wof:placetype":"venue"
},
  "geometry": {"coordinates":[-86.68773899999999,33.613156],"type":"Point"}
}