{
  "type": "Feature",
  "properties": {
    "iso:country":"US",
    "sg:address":"713 19th St",
    "sg:city":"Birmingham",
    "sg:classifiers":[
        {
            "category":"Organizations",
            "subcategory":"Religious Organization",
            "type":"Services"
        }
    ],
    "sg:phone":"+1 205 787 0066",
    "sg:postcode":"35218",
    "sg:province":"AL",
    "sg:tags":[
        "church"
    ],
    "wof:name":"Ebenezer Baptist Church",
    "wof:placetype":"venue"
},
  "geometry": {"coordinates":[-86.89444899999999,33.511691],"type":"Point"}
}