{
  "type": "Feature",
  "properties": {
    "addr:full":"1009 Line St NE Decatur AL 35601",
    "addr:housenumber":"1009",
    "addr:postcode":"35601",
    "addr:street":"Line St Ne",
    "iso:country":"US",
    "sg:address":"1009 Line St NE",
    "sg:city":"Decatur",
    "sg:classifiers":[
        {
            "category":"Health Services",
            "subcategory":"Nursing And Care Facility",
            "type":"Services"
        }
    ],
    "sg:phone":"+1 256 350 4545",
    "sg:postcode":"35601",
    "sg:province":"AL",
    "sg:tags":[
        "building",
        "operator",
        "apartment",
        "inter"
    ],
    "wof:name":"Riverside Senior Living",
    "wof:placetype":"venue"
},
  "geometry": {"coordinates":[-86.979473,34.612698],"type":"Point"}
}