{
  "type": "Feature",
  "properties": {
    "iso:country":"US",
    "sg:address":"850 Eastern Blvd",
    "sg:city":"Montgomery",
    "sg:classifiers":[
        {
            "category":"Restaurant",
            "type":"Food & Drink"
        }
    ],
    "sg:menulink":"http://www.allmenus.com/al/montgomery/91606-shoneys-restaurant/menu/",
    "sg:phone":"+1 334 396 8533",
    "sg:postcode":"36117",
    "sg:province":"AL",
    "sg:tags":[
        "american"
    ],
    "wof:name":"Shoney's Restaurant",
    "wof:placetype":"venue"
},
  "geometry": {"coordinates":[-86.21071000000001,32.368888],"type":"Point"}
}