{
  "type": "Feature",
  "properties": {
    "iso:country":"US",
    "sg:address":"712 Triana Blvd NW",
    "sg:city":"Huntsville",
    "sg:classifiers":[
        {
            "category":"Food & Beverages",
            "subcategory":"Supermarket",
            "type":"Retail Goods"
        },
        {
            "category":"Food & Beverages",
            "subcategory":"Groceries & Convenience Stores",
            "type":"Retail Goods"
        }
    ],
    "sg:phone":"+1 256 534 5151",
    "sg:postcode":"35805",
    "sg:province":"AL",
    "sg:tags":[
        "super"
    ],
    "wof:name":"Alabama Supermarket",
    "wof:placetype":"venue"
},
  "geometry": {"coordinates":[-86.610086,34.727393],"type":"Point"}
}