{
  "type": "Feature",
  "properties": {
    "iso:country":"US",
    "sg:address":"204 Shadowood Dr",
    "sg:city":"Dothan",
    "sg:classifiers":[
        {
            "category":"Building & Trades",
            "subcategory":"Construction",
            "type":"Services"
        }
    ],
    "sg:phone":"+1 334 702 6550",
    "sg:postcode":"36301",
    "sg:province":"AL",
    "sg:tags":[
        "house",
        "improvement",
        "home"
    ],
    "wof:name":"Southern Construction & Rmdlng",
    "wof:placetype":"venue"
},
  "geometry": {"coordinates":[-85.422848,31.174418],"type":"Point"}
}