{
  "type": "Feature",
  "properties": {
    "addr:full":"2029 2nd Ave N Birmingham AL 35203",
    "addr:housenumber":"2029",
    "addr:postcode":"35203",
    "addr:street":"2Nd Ave N",
    "iso:country":"US",
    "sg:address":"2029 2nd Ave N",
    "sg:city":"Birmingham",
    "sg:classifiers":[
        {
            "category":"Professional",
            "subcategory":"Lawyer & Legal Services",
            "type":"Services"
        }
    ],
    "sg:phone":"+1 205 322 0012",
    "sg:postcode":"35203",
    "sg:province":"AL",
    "sg:tags":[
        "attorney"
    ],
    "wof:name":"Smitherman & Smitherman",
    "wof:placetype":"venue"
},
  "geometry": {"coordinates":[-86.80519200000001,33.515793],"type":"Point"}
}