{
  "type": "Feature",
  "properties": {
    "iso:country":"US",
    "sg:address":"116 Lincoln Ave",
    "sg:city":"Muscle Shoals",
    "sg:classifiers":[
        {
            "category":"Professional",
            "subcategory":"Management & Consulting",
            "type":"Services"
        }
    ],
    "sg:phone":"+1 256 383 3309",
    "sg:postcode":"35661",
    "sg:province":"AL",
    "sg:tags":[
        "business"
    ],
    "wof:name":"James W Sewall",
    "wof:placetype":"venue"
},
  "geometry": {"coordinates":[-87.637849,34.739546],"type":"Point"}
}