{
  "type": "Feature",
  "properties": {
    "iso:country":"US",
    "sg:address":"6435 Louina Rd",
    "sg:city":"Roanoke",
    "sg:classifiers":[
        {
            "category":"Professional",
            "subcategory":"Business Services",
            "type":"Services"
        }
    ],
    "sg:phone":"+1 334 863 2389",
    "sg:postcode":"36274",
    "sg:province":"AL",
    "wof:name":"Southern Traditions",
    "wof:placetype":"venue"
},
  "geometry": {"coordinates":[-85.46865099999999,33.116597],"type":"Point"}
}