{
  "type": "Feature",
  "properties": {
    "addr:full":"225 Spragins Ave NW Huntsville AL 35801",
    "addr:housenumber":"225",
    "addr:postcode":"35801",
    "addr:street":"Spragins Ave Nw",
    "iso:country":"US",
    "sg:address":"225 Spragins Ave NW",
    "sg:city":"Huntsville",
    "sg:classifiers":[
        {
            "category":"Professional",
            "subcategory":"Computer Services",
            "type":"Services"
        }
    ],
    "sg:phone":"+1 256 382 4600",
    "sg:postcode":"35801",
    "sg:province":"AL",
    "sg:tags":[
        "design",
        "system",
        "programing",
        "custom"
    ],
    "wof:name":"Systems Development Corp",
    "wof:placetype":"venue"
},
  "geometry": {"coordinates":[-86.588605,34.731987],"type":"Point"}
}