{
  "type": "Feature",
  "properties": {
    "addr:full":"5160 State Rte 180 Gulf Shores AL 36542",
    "addr:housenumber":"5160",
    "addr:postcode":"36542",
    "addr:street":"State Rte 180",
    "iso:country":"US",
    "sg:address":"5160 State Rte 180",
    "sg:city":"Gulf Shores",
    "sg:classifiers":[
        {
            "category":"Food & Beverages",
            "subcategory":"Groceries & Convenience Stores",
            "type":"Retail Goods"
        }
    ],
    "sg:phone":"+1 251 540 2000",
    "sg:postcode":"36542",
    "sg:province":"AL",
    "wof:name":"Plaza West Grocery",
    "wof:placetype":"venue"
},
  "geometry": {"coordinates":[-87.933899,30.234004],"type":"Point"}
}