{
  "type": "Feature",
  "properties": {
    "addr:full":"1901 Co Rd 10 Florence AL 35633",
    "addr:housenumber":"1901;10",
    "addr:postcode":"35633",
    "addr:street":"Co Rd",
    "iso:country":"US",
    "sg:address":"1901 Co Rd 10",
    "sg:city":"Florence",
    "sg:classifiers":[
        {
            "category":"Manufacturing",
            "subcategory":"Toys & Sporting Goods",
            "type":"Manufacturing & Wholesale Goods"
        }
    ],
    "sg:phone":"+1 256 760 8090",
    "sg:postcode":"35633",
    "sg:province":"AL",
    "sg:tags":[
        "mfg"
    ],
    "wof:name":"Pickwick Lakes Smallmouth Svcs",
    "wof:placetype":"venue"
},
  "geometry": {"coordinates":[-87.864372,34.989283],"type":"Point"}
}