{
  "type": "Feature",
  "properties": {
    "addr:full":"824 Lucas St Athens AL 35611",
    "addr:housenumber":"824",
    "addr:postcode":"35611",
    "addr:street":"Lucas St",
    "iso:country":"US",
    "sg:address":"824 Lucas St",
    "sg:city":"Athens",
    "sg:classifiers":[
        {
            "category":"Organizations",
            "subcategory":"Religious Organization",
            "type":"Services"
        }
    ],
    "sg:phone":"+1 256 232 6031",
    "sg:postcode":"35611",
    "sg:province":"AL",
    "sg:tags":[
        "church"
    ],
    "wof:name":"Lucas Street Church of Christ",
    "wof:placetype":"venue"
},
  "geometry": {"coordinates":[-86.979736,34.795051],"type":"Point"}
}