{
  "type": "Feature",
  "properties": {
    "addr:full":"3364 State Rte 205 Albertville AL 35950",
    "addr:housenumber":"3364",
    "addr:postcode":"35950",
    "addr:street":"State Rte 205",
    "iso:country":"US",
    "sg:address":"3364 State Rte 205",
    "sg:city":"Albertville",
    "sg:classifiers":[
        {
            "category":"Real Estate",
            "subcategory":"Developer",
            "type":"Services"
        }
    ],
    "sg:phone":"+1 256 878 6781",
    "sg:postcode":"35950",
    "sg:province":"AL",
    "sg:tags":[
        "cemetery"
    ],
    "wof:name":"Marshall Memorial Gdn",
    "wof:placetype":"venue"
},
  "geometry": {"coordinates":[-86.26680500000001,34.284557],"type":"Point"}
}