{
  "type": "Feature",
  "properties": {
    "addr:full":"319 W College St Columbiana AL 35051",
    "addr:housenumber":"319",
    "addr:postcode":"35051",
    "addr:street":"W College St",
    "iso:country":"US",
    "sg:address":"319 W College St",
    "sg:city":"Columbiana",
    "sg:classifiers":[
        {
            "category":"Autos & Motor Vehicles",
            "subcategory":"Boat Sales",
            "type":"Retail Goods"
        }
    ],
    "sg:phone":"+1 205 669 0859",
    "sg:postcode":"35051",
    "sg:province":"AL",
    "sg:tags":[
        "dealer",
        "hunting",
        "supply"
    ],
    "wof:name":"Dons Marine Mini Storage",
    "wof:placetype":"venue"
},
  "geometry": {"coordinates":[-86.61543399999999,33.17992],"type":"Point"}
}