{
  "type": "Feature",
  "properties": {
    "iso:country":"US",
    "sg:address":"4041 Greystone Dr",
    "sg:city":"Birmingham",
    "sg:classifiers":[
        {
            "category":"Farming",
            "subcategory":"Farm",
            "type":"Manufacturing & Wholesale Goods"
        }
    ],
    "sg:phone":"+1 205 437 9655",
    "sg:postcode":"35242",
    "sg:province":"AL",
    "sg:tags":[
        "crop",
        "general"
    ],
    "wof:name":"Easterling Farms Inc",
    "wof:placetype":"venue"
},
  "geometry": {"coordinates":[-86.654228,33.421566],"type":"Point"}
}