{
  "type": "Feature",
  "properties": {
    "addr:full":"270 Old Locke 3 Rd Demopolis AL 36732",
    "addr:housenumber":"270;3",
    "addr:postcode":"36732",
    "addr:street":"Old Locke;Rd",
    "iso:country":"US",
    "sg:address":"270 Old Locke 3 Rd",
    "sg:city":"Demopolis",
    "sg:classifiers":[
        {
            "category":"Retail",
            "subcategory":"Auto Repair",
            "type":"Services"
        }
    ],
    "sg:phone":"+1 334 289 3843",
    "sg:postcode":"36732",
    "sg:province":"AL",
    "sg:tags":[
        "repairing",
        "automobile",
        "general"
    ],
    "wof:name":"Tucker's Garage",
    "wof:placetype":"venue"
},
  "geometry": {"coordinates":[-87.881306,32.357506],"type":"Point"}
}