{
  "type": "Feature",
  "properties": {
    "iso:country":"US",
    "sg:address":"7335 Airport Blvd",
    "sg:city":"Mobile",
    "sg:classifiers":[
        {
            "category":"Restaurant",
            "type":"Food & Drink"
        }
    ],
    "sg:phone":"+1 251 344 8815",
    "sg:postcode":"36608",
    "sg:province":"AL",
    "wof:name":"China Moon Seafood Restaurant",
    "wof:placetype":"venue"
},
  "geometry": {"coordinates":[-88.215435,30.68702],"type":"Point"}
}