{
  "type": "Feature",
  "properties": {
    "iso:country":"US",
    "sg:address":"2506 Lambert Dr",
    "sg:city":"Opelika",
    "sg:classifiers":[
        {
            "category":"Health Services",
            "subcategory":"Clinic",
            "type":"Services"
        }
    ],
    "sg:phone":"+1 334 742 2700",
    "sg:postcode":"36801",
    "sg:province":"AL",
    "sg:tags":[
        "alcohol",
        "center",
        "drug",
        "abuse",
        "retardation",
        "mental"
    ],
    "sg:website":"www.eastalabamamhc.org",
    "wof:name":"East Alabama Mental Health",
    "wof:placetype":"venue"
},
  "geometry": {"coordinates":[-85.40523399999999,32.621221],"type":"Point"}
}