{
  "type": "Feature",
  "properties": {
    "addr:full":"7877 3 Notch Rd Mobile AL 36619",
    "addr:housenumber":"7877 3",
    "addr:postcode":"36619",
    "addr:street":"Notch Rd",
    "iso:country":"US",
    "sg:address":"7877 3 Notch Rd",
    "sg:city":"Mobile",
    "sg:classifiers":[
        {
            "category":"Manufacturing",
            "subcategory":"Building Materials",
            "type":"Manufacturing & Wholesale Goods"
        },
        {
            "category":"Building & Trades",
            "subcategory":"Construction",
            "type":"Services"
        }
    ],
    "sg:phone":"+1 251 661 9079",
    "sg:postcode":"36619",
    "sg:province":"AL",
    "sg:tags":[
        "mfg",
        "household",
        "cabinet",
        "wood",
        "kitchen",
        "maker",
        "furn"
    ],
    "wof:name":"Quality Cabinets Inc",
    "wof:placetype":"venue"
},
  "geometry": {"coordinates":[-88.170835,30.590193],"type":"Point"}
}