{
  "type": "Feature",
  "properties": {
    "addr:full":"21 Patterson St Alexander City AL 35010",
    "addr:housenumber":"21",
    "addr:postcode":"35010",
    "addr:street":"Patterson St",
    "iso:country":"US",
    "sg:address":"21 Patterson St",
    "sg:city":"Alexander City",
    "sg:classifiers":[
        {
            "category":"Manufacturing",
            "subcategory":"Glass & Minerals",
            "type":"Manufacturing & Wholesale Goods"
        }
    ],
    "sg:phone":"+1 256 329 0798",
    "sg:postcode":"35010",
    "sg:province":"AL",
    "sg:tags":[
        "product",
        "metal",
        "mfg"
    ],
    "wof:name":"Custom Glass",
    "wof:placetype":"venue"
},
  "geometry": {"coordinates":[-85.931883,32.915493],"type":"Point"}
}