{
  "type": "Feature",
  "properties": {
    "iso:country":"US",
    "sg:address":"1430 Fielding St",
    "sg:city":"Brighton",
    "sg:classifiers":[
        {
            "category":"Organizations",
            "subcategory":"Religious Organization",
            "type":"Services"
        }
    ],
    "sg:phone":"+1 205 428 3324",
    "sg:postcode":"35020",
    "sg:province":"AL",
    "sg:tags":[
        "church"
    ],
    "wof:name":"First Baptist Church Brighton",
    "wof:placetype":"venue"
},
  "geometry": {"coordinates":[-86.95194600000001,33.432285],"type":"Point"}
}