{
  "type": "Feature",
  "properties": {
    "iso:country":"US",
    "sg:address":"201 Virginia Dr",
    "sg:city":"Birmingham",
    "sg:classifiers":[
        {
            "category":"Professional",
            "subcategory":"Art Services",
            "type":"Services"
        }
    ],
    "sg:phone":"+1 205 290 0033",
    "sg:postcode":"35209",
    "sg:province":"AL",
    "sg:tags":[
        "commercial",
        "design"
    ],
    "wof:name":"Kathleen Camp Grphic Desgr LLC",
    "wof:placetype":"venue"
},
  "geometry": {"coordinates":[-86.810266,33.472912],"type":"Point"}
}