{
  "type": "Feature",
  "properties": {
    "addr:full":"5051 Co Rd 625 Enterprise AL 36330",
    "addr:housenumber":"5051;625",
    "addr:postcode":"36330",
    "addr:street":"Co Rd;Enterprise",
    "iso:country":"US",
    "sg:address":"5051 Co Rd 625",
    "sg:city":"Enterprise",
    "sg:classifiers":[
        {
            "category":"Retail",
            "subcategory":"Auto Repair",
            "type":"Services"
        }
    ],
    "sg:phone":"+1 334 347 1723",
    "sg:postcode":"36330",
    "sg:province":"AL",
    "sg:tags":[
        "general"
    ],
    "wof:name":"Leon Adkisons Garage",
    "wof:placetype":"venue"
},
  "geometry": {"coordinates":[-85.97868699999999,31.254757],"type":"Point"}
}