{
  "type": "Feature",
  "properties": {
    "addr:full":"3095 Ross Clark Cir Dothan AL 36301",
    "addr:housenumber":"3095",
    "addr:postcode":"36301",
    "addr:street":"Ross Clark Cir",
    "iso:country":"US",
    "sg:address":"3095 Ross Clark Cir",
    "sg:city":"Dothan",
    "sg:classifiers":[
        {
            "category":"Manufacturing",
            "subcategory":"Food",
            "type":"Manufacturing & Wholesale Goods"
        },
        {
            "category":"Bakery",
            "type":"Food & Drink"
        }
    ],
    "sg:menulink":"http://www.allmenus.com/al/dothan/114272-krispy-kreme/menu/",
    "sg:phone":"+1 334 677 0741",
    "sg:postcode":"36301",
    "sg:province":"AL",
    "sg:tags":[
        "american",
        "bakery",
        "pastry"
    ],
    "wof:name":"Krispy Kreme",
    "wof:placetype":"venue"
},
  "geometry": {"coordinates":[-85.432288,31.227597],"type":"Point"}
}