{
  "type": "Feature",
  "properties": {
    "iso:country":"US",
    "sg:address":"5604 Co Rd 55",
    "sg:city":"Eva",
    "sg:classifiers":[
        {
            "category":"Shopping",
            "subcategory":"Discount & Variety Stores",
            "type":"Retail Goods"
        },
        {
            "category":"Shopping",
            "subcategory":"Department Store",
            "type":"Retail Goods"
        }
    ],
    "sg:phone":"+1 256 796 2147",
    "sg:postcode":"35621",
    "sg:province":"AL",
    "sg:tags":[
        "shop"
    ],
    "wof:name":"Dollar General 7550",
    "wof:placetype":"venue"
},
  "geometry": {"coordinates":[-86.733493,34.312134],"type":"Point"}
}