{
  "type": "Feature",
  "properties": {
    "addr:full":"1863 Rosedale Rd Mobile AL 36605",
    "addr:housenumber":"1863",
    "addr:postcode":"36605",
    "addr:street":"Rosedale Rd",
    "iso:country":"US",
    "sg:address":"1863 Rosedale Rd",
    "sg:city":"Mobile",
    "sg:classifiers":[
        {
            "category":"Building & Trades",
            "subcategory":"Construction",
            "type":"Services"
        }
    ],
    "sg:phone":"+1 251 473 3808",
    "sg:postcode":"36605",
    "sg:province":"AL",
    "sg:tags":[
        "hanging",
        "contractor"
    ],
    "wof:name":"Jinson Paint Company",
    "wof:placetype":"venue"
},
  "geometry": {"coordinates":[-88.08113,30.623512],"type":"Point"}
}