{
  "type": "Feature",
  "properties": {
    "iso:country":"US",
    "sg:address":"450 Rose Dr",
    "sg:city":"Florence",
    "sg:classifiers":[
        {
            "category":"Building & Trades",
            "subcategory":"Construction",
            "type":"Services"
        }
    ],
    "sg:phone":"+1 256 766 4560",
    "sg:postcode":"35630",
    "sg:province":"AL",
    "sg:tags":[
        "industrial",
        "commercial",
        "contractor"
    ],
    "wof:name":"Smith General Contractors LLC",
    "wof:placetype":"venue"
},
  "geometry": {"coordinates":[-87.665319,34.858438],"type":"Point"}
}