{
  "type": "Feature",
  "properties": {
    "iso:country":"US",
    "sg:address":"1608 13th Ave S",
    "sg:city":"Birmingham",
    "sg:classifiers":[
        {
            "category":"Social Services",
            "subcategory":"Child Care",
            "type":"Services"
        }
    ],
    "sg:phone":"+1 205 933 1098",
    "sg:postcode":"35205",
    "sg:province":"AL",
    "wof:name":"Child Care Council",
    "wof:placetype":"venue"
},
  "geometry": {"coordinates":[-86.799842,33.496481],"type":"Point"}
}