{
  "type": "Feature",
  "properties": {
    "iso:country":"US",
    "sg:address":"6414 Grelot Rd",
    "sg:city":"Mobile",
    "sg:classifiers":[
        {
            "category":"Social Services",
            "type":"Services"
        }
    ],
    "sg:phone":"+1 251 776 7158",
    "sg:postcode":"36695",
    "sg:province":"AL",
    "sg:tags":[
        "agency",
        "adoption"
    ],
    "wof:name":"Special Beginnings Adoptions",
    "wof:placetype":"venue"
},
  "geometry": {"coordinates":[-88.198323,30.661194],"type":"Point"}
}