{
  "type": "Feature",
  "properties": {
    "iso:country":"US",
    "sg:address":"10740 Lock 17 Rd",
    "sg:city":"Adger",
    "sg:classifiers":[
        {
            "category":"Mining & Drilling",
            "type":"Manufacturing & Wholesale Goods"
        }
    ],
    "sg:phone":"+1 205 491 7234",
    "sg:postcode":"35006",
    "sg:province":"AL",
    "sg:tags":[
        "development",
        "gas",
        "oil",
        "exploration"
    ],
    "wof:name":"Energen Resources Corp",
    "wof:placetype":"venue"
},
  "geometry": {"coordinates":[-87.203877,33.442994],"type":"Point"}
}