{
  "type": "Feature",
  "properties": {
    "iso:country":"US",
    "sg:address":"1201 Montlimar Dr",
    "sg:city":"Mobile",
    "sg:classifiers":[
        {
            "category":"Professional",
            "subcategory":"Management & Consulting",
            "type":"Services"
        }
    ],
    "sg:phone":"+1 251 653 6640",
    "sg:postcode":"36609",
    "sg:province":"AL",
    "wof:name":"Special Event Staffing",
    "wof:placetype":"venue"
},
  "geometry": {"coordinates":[-88.133321,30.668529],"type":"Point"}
}