{
  "type": "Feature",
  "properties": {
    "addr:full":"409 E Walnut St Troy AL 36081",
    "addr:housenumber":"409",
    "addr:postcode":"36081",
    "addr:street":"E Walnut St",
    "iso:country":"US",
    "sg:address":"409 E Walnut St",
    "sg:city":"Troy",
    "sg:classifiers":[
        {
            "category":"Freight",
            "type":"Transportation"
        }
    ],
    "sg:phone":"+1 334 566 9907",
    "sg:postcode":"36081",
    "sg:province":"AL",
    "sg:tags":[
        "commercial",
        "storage"
    ],
    "wof:name":"Star Storage",
    "wof:placetype":"venue"
},
  "geometry": {"coordinates":[-85.968698,31.808421],"type":"Point"}
}