{
  "type": "Feature",
  "properties": {
    "iso:country":"US",
    "sg:address":"310 Hitchitie Rd",
    "sg:city":"Seale",
    "sg:classifiers":[
        {
            "category":"Farming",
            "subcategory":"Livestock Farm",
            "type":"Manufacturing & Wholesale Goods"
        }
    ],
    "sg:phone":"+1 334 855 4426",
    "sg:postcode":"36875",
    "sg:province":"AL",
    "sg:tags":[
        "beef",
        "feedlot",
        "cattle"
    ],
    "wof:name":"Fort Uchee Farms Inc",
    "wof:placetype":"venue"
},
  "geometry": {"coordinates":[-85.230042,32.357644],"type":"Point"}
}