{
  "type": "Feature",
  "properties": {
    "iso:country":"US",
    "sg:address":"2100 Lynngate Dr",
    "sg:city":"Birmingham",
    "sg:classifiers":[
        {
            "category":"Professional",
            "subcategory":"Lawyer & Legal Services",
            "type":"Services"
        }
    ],
    "sg:phone":"+1 205 822 5444",
    "sg:postcode":"35216",
    "sg:province":"AL",
    "sg:tags":[
        "attorney"
    ],
    "wof:name":"Alan C Keith",
    "wof:placetype":"venue"
},
  "geometry": {"coordinates":[-86.79395599999999,33.395691],"type":"Point"}
}