{
  "type": "Feature",
  "properties": {
    "iso:country":"US",
    "sg:address":"1901 Vanderbilt Rd",
    "sg:city":"Birmingham",
    "sg:classifiers":[
        {
            "category":"Retail",
            "subcategory":"Car Wash",
            "type":"Services"
        }
    ],
    "sg:phone":"+1 205 244 1133",
    "sg:postcode":"35234",
    "sg:province":"AL",
    "sg:tags":[
        "carwash"
    ],
    "wof:name":"Billys Car Wash & Detail",
    "wof:placetype":"venue"
},
  "geometry": {"coordinates":[-86.791622,33.549206],"type":"Point"}
}