{
  "type": "Feature",
  "properties": {
    "addr:full":"2400 Hammock Rd Mobile AL 36605",
    "addr:housenumber":"2400",
    "addr:postcode":"36605",
    "addr:street":"Hammock Rd",
    "iso:country":"US",
    "sg:address":"2400 Hammock Rd",
    "sg:city":"Mobile",
    "sg:classifiers":[
        {
            "category":"Education",
            "subcategory":"School",
            "type":"Public Place"
        }
    ],
    "sg:phone":"+1 251 221 1376",
    "sg:postcode":"36605",
    "sg:province":"AL",
    "wof:name":"Hollinger's Island Elementary",
    "wof:placetype":"venue"
},
  "geometry": {"coordinates":[-88.091055,30.542382],"type":"Point"}
}