{
  "type": "Feature",
  "properties": {
    "iso:country":"US",
    "sg:address":"3434 Indian Lake Dr",
    "sg:city":"Pelham",
    "sg:classifiers":[
        {
            "category":"Professional",
            "subcategory":"Business Services",
            "type":"Services"
        }
    ],
    "sg:phone":"+1 205 988 9435",
    "sg:postcode":"35124",
    "sg:province":"AL",
    "wof:name":"Essential Accen",
    "wof:placetype":"venue"
},
  "geometry": {"coordinates":[-86.812215,33.341977],"type":"Point"}
}