{
  "type": "Feature",
  "properties": {
    "iso:country":"US",
    "sg:address":"4668 N Pinewood Dr",
    "sg:city":"Mobile",
    "sg:classifiers":[
        {
            "category":"Organizations",
            "subcategory":"Community Association",
            "type":"Services"
        }
    ],
    "sg:phone":"+1 251 343 7889",
    "sg:postcode":"36618",
    "sg:province":"AL",
    "wof:name":"AF LLC",
    "wof:placetype":"venue"
},
  "geometry": {"coordinates":[-88.15191,30.711133],"type":"Point"}
}