{
  "type": "Feature",
  "properties": {
    "addr:full":"3485 Main St W Fyffe AL 35971",
    "addr:housenumber":"3485",
    "addr:postcode":"35971",
    "addr:street":"Main St W Fyffe",
    "iso:country":"US",
    "sg:address":"3485 Main St W",
    "sg:city":"Fyffe",
    "sg:classifiers":[
        {
            "category":"Wholesale",
            "subcategory":"Metals & Minerals",
            "type":"Manufacturing & Wholesale Goods"
        }
    ],
    "sg:phone":"+1 256 623 4066",
    "sg:postcode":"35971",
    "sg:province":"AL",
    "sg:tags":[
        "steel",
        "equipment",
        "industrial"
    ],
    "wof:name":"Steel & Industrial Supplies",
    "wof:placetype":"venue"
},
  "geometry": {"coordinates":[-85.89260400000001,34.524545],"type":"Point"}
}