{
  "type": "Feature",
  "properties": {
    "addr:full":"329 Business Cir Pelham AL 35124",
    "addr:housenumber":"329",
    "addr:postcode":"35124",
    "addr:street":"Business Cir",
    "iso:country":"US",
    "sg:address":"329 Business Cir",
    "sg:city":"Pelham",
    "sg:classifiers":[
        {
            "category":"Education",
            "subcategory":"Vocational School",
            "type":"Public Place"
        }
    ],
    "sg:phone":"+1 205 621 7745",
    "sg:postcode":"35124",
    "sg:province":"AL",
    "wof:name":"North Alabama Skills Ctr",
    "wof:placetype":"venue"
},
  "geometry": {"coordinates":[-86.810076,33.295634],"type":"Point"}
}