{
  "type": "Feature",
  "properties": {
    "addr:full":"26212 Joe Foley Rd Robertsdale AL 36567",
    "addr:housenumber":"26212",
    "addr:postcode":"36567",
    "addr:street":"Joe Foley Rd",
    "iso:country":"US",
    "sg:address":"26212 Joe Foley Rd",
    "sg:city":"Robertsdale",
    "sg:classifiers":[
        {
            "category":"Professional",
            "type":"Services"
        }
    ],
    "sg:phone":"+1 251 942 1175",
    "sg:postcode":"36567",
    "sg:province":"AL",
    "sg:tags":[
        "establishment"
    ],
    "wof:name":"End Of The Road",
    "wof:placetype":"venue"
},
  "geometry": {"coordinates":[-87.57927599999999,30.545892],"type":"Point"}
}