{
  "type": "Feature",
  "properties": {
    "addr:full":"411 1st St N Alabaster AL 35007",
    "addr:housenumber":"411",
    "addr:postcode":"35007",
    "addr:street":"1St St N",
    "iso:country":"US",
    "sg:address":"411 1st St N",
    "sg:city":"Alabaster",
    "sg:classifiers":[
        {
            "category":"Professional",
            "type":"Services"
        },
        {
            "category":"Restaurant",
            "type":"Food & Drink"
        }
    ],
    "sg:phone":"+1 205 663 6993",
    "sg:postcode":"35007",
    "sg:province":"AL",
    "sg:tags":[
        "barbecue",
        "caterer"
    ],
    "wof:name":"Buddy's Bar-B-Que",
    "wof:placetype":"venue"
},
  "geometry": {"coordinates":[-86.81554800000001,33.247038],"type":"Point"}
}