{
  "type": "Feature",
  "properties": {
    "addr:full":"2122 Hand Ave Mobile AL 36612",
    "addr:housenumber":"2122",
    "addr:postcode":"36612",
    "addr:street":"Hand Ave",
    "iso:country":"US",
    "sg:address":"2122 Hand Ave",
    "sg:city":"Mobile",
    "sg:classifiers":[
        {
            "category":"Building & Trades",
            "subcategory":"Construction",
            "type":"Services"
        }
    ],
    "sg:phone":"+1 251 456 0256",
    "sg:postcode":"36612",
    "sg:province":"AL",
    "sg:tags":[
        "contractor"
    ],
    "wof:name":"Vision Builders LLC",
    "wof:placetype":"venue"
},
  "geometry": {"coordinates":[-88.116151,30.745151],"type":"Point"}
}