{
  "type": "Feature",
  "properties": {
    "iso:country":"US",
    "sg:address":"4317 Fair Oaks Dr",
    "sg:city":"Birmingham",
    "sg:classifiers":[
        {
            "category":"Organizations",
            "subcategory":"Non-profit Organization",
            "type":"Services"
        }
    ],
    "sg:phone":"+1 205 879 2728",
    "sg:postcode":"35213",
    "sg:province":"AL",
    "sg:tags":[
        "social"
    ],
    "wof:name":"Cat Welfare Society Ltd",
    "wof:placetype":"venue"
},
  "geometry": {"coordinates":[-86.717073,33.510492],"type":"Point"}
}