{
  "type": "Feature",
  "properties": {
    "iso:country":"US",
    "sg:address":"2210 Division St",
    "sg:city":"Mobile",
    "sg:classifiers":[
        {
            "category":"Organizations",
            "subcategory":"Religious Organization",
            "type":"Services"
        }
    ],
    "sg:phone":"+1 251 456 9065",
    "sg:postcode":"36617",
    "sg:province":"AL",
    "wof:name":"Ernest A Rouse Rev",
    "wof:placetype":"venue"
},
  "geometry": {"coordinates":[-88.094301,30.723077],"type":"Point"}
}