{
  "type": "Feature",
  "properties": {
    "iso:country":"US",
    "sg:address":"1631 S College St",
    "sg:city":"Auburn",
    "sg:classifiers":[
        {
            "category":"Food & Beverages",
            "subcategory":"Liquor & Beverages",
            "type":"Retail Goods"
        }
    ],
    "sg:phone":"+1 334 821 6499",
    "sg:postcode":"36832",
    "sg:province":"AL",
    "sg:tags":[
        "alcoholic"
    ],
    "wof:name":"Tiger Package",
    "wof:placetype":"venue"
},
  "geometry": {"coordinates":[-85.499144,32.573596],"type":"Point"}
}