{
  "type": "Feature",
  "properties": {
    "iso:country":"US",
    "sg:address":"2227 2nd Ave N",
    "sg:city":"Birmingham",
    "sg:classifiers":[
        {
            "category":"Real Estate",
            "subcategory":"Real Estate Services",
            "type":"Services"
        },
        {
            "category":"Shopping",
            "subcategory":"Used Merchandise",
            "type":"Retail Goods"
        },
        {
            "category":"Home & Garden",
            "subcategory":"Carpets & Floor Coverings",
            "type":"Retail Goods"
        },
        {
            "category":"Home & Garden",
            "subcategory":"Furniture",
            "type":"Retail Goods"
        }
    ],
    "sg:phone":"+1 205 252 2195",
    "sg:postcode":"35203",
    "sg:province":"AL",
    "sg:tags":[
        "renting",
        "staging",
        "mattress",
        "leasing",
        "store"
    ],
    "sg:website":"http://www.haroldfurniture.com",
    "wof:name":"Harold's Furniture Leasing & Sales Company Inc",
    "wof:placetype":"venue"
},
  "geometry": {"coordinates":[-86.803139,33.516851],"type":"Point"}
}