{
  "type": "Feature",
  "properties": {
    "addr:full":"13534 Old Marion Rd Duncanville AL 35456",
    "addr:housenumber":"13534",
    "addr:postcode":"35456",
    "addr:street":"Old Marion Rd",
    "iso:country":"US",
    "sg:address":"13534 Old Marion Rd",
    "sg:city":"Duncanville",
    "sg:classifiers":[
        {
            "category":"Organizations",
            "subcategory":"Religious Organization",
            "type":"Services"
        }
    ],
    "sg:phone":"+1 205 342 9091",
    "sg:postcode":"35456",
    "sg:province":"AL",
    "sg:tags":[
        "church"
    ],
    "wof:name":"Mount Sinai Baptist Church",
    "wof:placetype":"venue"
},
  "geometry": {"coordinates":[-87.518653,33.094938],"type":"Point"}
}