{
  "type": "Feature",
  "properties": {
    "iso:country":"US",
    "sg:address":"3427 Colonnade Pkwy",
    "sg:city":"Birmingham",
    "sg:classifiers":[
        {
            "category":"Personal",
            "subcategory":"Tanning Parlor",
            "type":"Services"
        }
    ],
    "sg:phone":"+1 205 583 4653",
    "sg:postcode":"35243",
    "sg:province":"AL",
    "sg:tags":[
        "salon"
    ],
    "wof:name":"Gold's Gym",
    "wof:placetype":"venue"
},
  "geometry": {"coordinates":[-86.733575,33.434814],"type":"Point"}
}