{
  "type": "Feature",
  "properties": {
    "iso:country":"US",
    "sg:address":"7 Bemiston Ave",
    "sg:city":"Talladega",
    "sg:classifiers":[
        {
            "category":"Government",
            "subcategory":"Office",
            "type":"Public Place"
        }
    ],
    "sg:phone":"+1 256 362 5832",
    "sg:postcode":"35160",
    "sg:province":"AL",
    "wof:name":"Early Intervention/Child Find",
    "wof:placetype":"venue"
},
  "geometry": {"coordinates":[-86.121018,33.418947],"type":"Point"}
}