{
  "type": "Feature",
  "properties": {
    "iso:country":"US",
    "sg:address":"5002 Whitling Dr",
    "sg:city":"Pelham",
    "sg:classifiers":[
        {
            "category":"Professional",
            "subcategory":"Business Services",
            "type":"Services"
        }
    ],
    "sg:phone":"+1 205 620 5555",
    "sg:postcode":"35124",
    "sg:province":"AL",
    "sg:tags":[
        "maintains",
        "pool",
        "swimming"
    ],
    "wof:name":"Professional Pools of Birmingh",
    "wof:placetype":"venue"
},
  "geometry": {"coordinates":[-86.827063,33.289141],"type":"Point"}
}