{
  "type": "Feature",
  "properties": {
    "iso:country":"US",
    "sg:address":"716 Valley Dr",
    "sg:city":"Birmingham",
    "sg:classifiers":[
        {
            "category":"Building & Trades",
            "subcategory":"Cleaning & Sanitation",
            "type":"Services"
        }
    ],
    "sg:phone":"+1 205 833 2369",
    "sg:postcode":"35206",
    "sg:province":"AL",
    "sg:tags":[
        "maintenance"
    ],
    "wof:name":"R & B Cleaning Service Inc",
    "wof:placetype":"venue"
},
  "geometry": {"coordinates":[-86.687263,33.583093],"type":"Point"}
}