{
  "type": "Feature",
  "properties": {
    "iso:country":"US",
    "sg:address":"1331 Metcalf St",
    "sg:city":"Cottonwood",
    "sg:classifiers":[
        {
            "category":"Organizations",
            "subcategory":"Religious Organization",
            "type":"Services"
        }
    ],
    "sg:phone":"+1 334 691 2622",
    "sg:postcode":"36320",
    "sg:province":"AL",
    "sg:tags":[
        "church"
    ],
    "wof:name":"Cottonwood United Methodist Ch",
    "wof:placetype":"venue"
},
  "geometry": {"coordinates":[-85.303204,31.052161],"type":"Point"}
}