{
  "type": "Feature",
  "properties": {
    "addr:full":"6263 Old Cherry Dr E Theodore AL 36582",
    "addr:housenumber":"6263",
    "addr:postcode":"36582",
    "addr:street":"Old Cherry Dr E",
    "iso:country":"US",
    "sg:address":"6263 Old Cherry Dr E",
    "sg:city":"Theodore",
    "sg:classifiers":[
        {
            "category":"Building & Trades",
            "subcategory":"Landscaping Services",
            "type":"Services"
        }
    ],
    "sg:phone":"+1 251 653 9711",
    "sg:postcode":"36582",
    "sg:province":"AL",
    "wof:name":"Mikes Tree Service",
    "wof:placetype":"venue"
},
  "geometry": {"coordinates":[-88.23135000000001,30.56042],"type":"Point"}
}