{
  "type": "Feature",
  "properties": {
    "addr:full":"935 N Daleville Ave Daleville AL 36322",
    "addr:housenumber":"935",
    "addr:postcode":"36322",
    "addr:street":"N Daleville Ave",
    "iso:country":"US",
    "sg:address":"935 N Daleville Ave",
    "sg:city":"Daleville",
    "sg:classifiers":[
        {
            "category":"Restaurant",
            "type":"Food & Drink"
        }
    ],
    "sg:menulink":"http://www.allmenus.com/al/daleville/204734-taco-bell/menu/",
    "sg:postcode":"36322",
    "sg:province":"AL",
    "sg:tags":[
        "mexican"
    ],
    "wof:name":"Taco Bell",
    "wof:placetype":"venue"
},
  "geometry": {"coordinates":[-85.710694,31.319359],"type":"Point"}
}