{
  "type": "Feature",
  "properties": {
    "addr:full":"3801 4th Ter N Birmingham AL 35222",
    "addr:housenumber":"3801",
    "addr:postcode":"35222",
    "addr:street":"4Th Ter N",
    "iso:country":"US",
    "sg:address":"3801 4th Ter N",
    "sg:city":"Birmingham",
    "sg:classifiers":[
        {
            "category":"Wholesale",
            "subcategory":"Durable Goods & Equipment",
            "type":"Manufacturing & Wholesale Goods"
        },
        {
            "category":"Wholesale",
            "subcategory":"Auto Parts",
            "type":"Manufacturing & Wholesale Goods"
        }
    ],
    "sg:phone":"+1 205 591 9660",
    "sg:postcode":"35222",
    "sg:province":"AL",
    "sg:tags":[
        "fire",
        "extinguisher",
        "protective",
        "safety"
    ],
    "wof:name":"Industrial Fire & Safety Equip",
    "wof:placetype":"venue"
},
  "geometry": {"coordinates":[-86.78104999999999,33.528238],"type":"Point"}
}