{
  "type": "Feature",
  "properties": {
    "addr:full":"3621 Winchester Rd New Market AL 35761",
    "addr:housenumber":"3621",
    "addr:postcode":"35761",
    "addr:street":"Winchester Rd",
    "iso:country":"US",
    "sg:address":"3621 Winchester Rd",
    "sg:city":"New Market",
    "sg:classifiers":[
        {
            "category":"Social Services",
            "type":"Services"
        }
    ],
    "sg:phone":"+1 256 379 3020",
    "sg:postcode":"35761",
    "sg:province":"AL",
    "sg:tags":[
        "care",
        "center",
        "day"
    ],
    "wof:name":"New Market Adult Day Senior",
    "wof:placetype":"venue"
},
  "geometry": {"coordinates":[-86.45798000000001,34.854091],"type":"Point"}
}