{
  "type": "Feature",
  "properties": {
    "addr:full":"111 E 1st St Sheffield AL 35660",
    "addr:housenumber":"111",
    "addr:postcode":"35660",
    "addr:street":"E 1St St",
    "iso:country":"US",
    "sg:address":"111 E 1st St",
    "sg:city":"Sheffield",
    "sg:classifiers":[
        {
            "category":"Autos & Motor Vehicles",
            "subcategory":"Auto Supplies",
            "type":"Retail Goods"
        },
        {
            "category":"Wholesale",
            "subcategory":"Auto Parts",
            "type":"Manufacturing & Wholesale Goods"
        }
    ],
    "sg:phone":"+1 256 381 0480",
    "sg:postcode":"35660",
    "sg:province":"AL",
    "sg:tags":[
        "automotive",
        "automobile"
    ],
    "wof:name":"Allied Parts Plus Inc",
    "wof:placetype":"venue"
},
  "geometry": {"coordinates":[-87.698463,34.75886],"type":"Point"}
}