{
  "type": "Feature",
  "properties": {
    "addr:full":"3207 College Ave Jackson AL 36545",
    "addr:housenumber":"3207",
    "addr:postcode":"36545",
    "addr:street":"College Ave",
    "iso:country":"US",
    "sg:address":"3207 College Ave",
    "sg:city":"Jackson",
    "sg:classifiers":[
        {
            "category":"Travel",
            "subcategory":"Hotels & Motels",
            "type":"Entertainment"
        }
    ],
    "sg:phone":"+1 251 246 5741",
    "sg:postcode":"36545",
    "sg:province":"AL",
    "wof:name":"Downtown Inn Motel",
    "wof:placetype":"venue"
},
  "geometry": {"coordinates":[-87.889115,31.534575],"type":"Point"}
}