{
  "type": "Feature",
  "properties": {
    "addr:full":"909 6th Ave SE Decatur AL 35601",
    "addr:housenumber":"909",
    "addr:postcode":"35601",
    "addr:street":"6Th Ave Se",
    "iso:country":"US",
    "sg:address":"909 6th Ave SE",
    "sg:city":"Decatur",
    "sg:classifiers":[
        {
            "category":"Food & Beverages",
            "subcategory":"Groceries & Convenience Stores",
            "type":"Retail Goods"
        }
    ],
    "sg:phone":"+1 256 350 7030",
    "sg:postcode":"35601",
    "sg:province":"AL",
    "wof:name":"Village Pantry",
    "wof:placetype":"venue"
},
  "geometry": {"coordinates":[-86.980339,34.593248],"type":"Point"}
}