{
  "type": "Feature",
  "properties": {
    "addr:full":"3604 Michele Ct Mobile AL 36605",
    "addr:housenumber":"3604",
    "addr:postcode":"36605",
    "addr:street":"Michele Ct",
    "iso:country":"US",
    "sg:address":"3604 Michele Ct",
    "sg:city":"Mobile",
    "sg:classifiers":[
        {
            "category":"Building & Trades",
            "subcategory":"Construction",
            "type":"Services"
        }
    ],
    "sg:phone":"+1 251 479 2911",
    "sg:postcode":"36605",
    "sg:province":"AL",
    "sg:tags":[
        "house"
    ],
    "wof:name":"Howle Construction Co",
    "wof:placetype":"venue"
},
  "geometry": {"coordinates":[-88.108953,30.597495],"type":"Point"}
}