{
  "type": "Feature",
  "properties": {
    "iso:country":"US",
    "sg:address":"2843 County Line Dr",
    "sg:city":"Trafford",
    "sg:classifiers":[
        {
            "category":"Government",
            "subcategory":"Office",
            "type":"Public Place"
        }
    ],
    "sg:phone":"+1 205 590 1649",
    "sg:postcode":"35172",
    "sg:province":"AL",
    "sg:tags":[
        "village"
    ],
    "wof:name":"County Line Town Office",
    "wof:placetype":"venue"
},
  "geometry": {"coordinates":[-86.72882199999999,33.82037],"type":"Point"}
}