{
  "type": "Feature",
  "properties": {
    "addr:full":"2518 Commerce Cir Birmingham AL 35217",
    "addr:housenumber":"2518",
    "addr:postcode":"35217",
    "addr:street":"Commerce Cir",
    "iso:country":"US",
    "sg:address":"2518 Commerce Cir",
    "sg:city":"Birmingham",
    "sg:classifiers":[
        {
            "category":"Freight",
            "type":"Transportation"
        }
    ],
    "sg:phone":"+1 205 808 0888",
    "sg:postcode":"35217",
    "sg:province":"AL",
    "sg:tags":[
        "operator",
        "trucking"
    ],
    "wof:name":"Jlynn Inc",
    "wof:placetype":"venue"
},
  "geometry": {"coordinates":[-86.772431,33.585642],"type":"Point"}
}