{
  "type": "Feature",
  "properties": {
    "addr:full":"2285 Bashi Rd Thomasville AL 36784",
    "addr:housenumber":"2285",
    "addr:postcode":"36784",
    "addr:street":"Bashi Rd",
    "iso:country":"US",
    "sg:address":"2285 Bashi Rd",
    "sg:city":"Thomasville",
    "sg:classifiers":[
        {
            "category":"Wholesale",
            "subcategory":"Construction Materials",
            "type":"Manufacturing & Wholesale Goods"
        }
    ],
    "sg:phone":"+1 334 636 1500",
    "sg:postcode":"36784",
    "sg:province":"AL",
    "sg:tags":[
        "timberland",
        "company",
        "timber"
    ],
    "wof:name":"Lower Dixie Timber Co Inc",
    "wof:placetype":"venue"
},
  "geometry": {"coordinates":[-87.79078,31.960039],"type":"Point"}
}