{
  "type": "Feature",
  "properties": {
    "iso:country":"US",
    "sg:address":"3441 Parkwood Rd",
    "sg:city":"Bessemer",
    "sg:classifiers":[
        {
            "category":"Professional",
            "subcategory":"Business Services",
            "type":"Services"
        }
    ],
    "sg:phone":"+1 205 428 3093",
    "sg:postcode":"35022",
    "sg:province":"AL",
    "wof:name":"Dispatch Yard",
    "wof:placetype":"venue"
},
  "geometry": {"coordinates":[-86.891288,33.354612],"type":"Point"}
}