{
  "type": "Feature",
  "properties": {
    "iso:country":"US",
    "sg:address":"1014 Moore Ave",
    "sg:city":"Anniston",
    "sg:classifiers":[
        {
            "category":"Building & Trades",
            "subcategory":"Plumbing",
            "type":"Services"
        }
    ],
    "sg:phone":"+1 256 236 5088",
    "sg:postcode":"36201",
    "sg:province":"AL",
    "sg:tags":[
        "conditioning",
        "air",
        "system",
        "contractor"
    ],
    "wof:name":"Ford Air Conditioning Co",
    "wof:placetype":"venue"
},
  "geometry": {"coordinates":[-85.833039,33.65739],"type":"Point"}
}