{
  "type": "Feature",
  "properties": {
    "iso:country":"US",
    "sg:address":"139 Beaver Pt",
    "sg:city":"Dadeville",
    "sg:classifiers":[
        {
            "category":"Organizations",
            "subcategory":"Membership Organization",
            "type":"Services"
        }
    ],
    "sg:phone":"+1 256 825 6930",
    "sg:postcode":"36853",
    "sg:province":"AL",
    "wof:name":"Ican Foundation",
    "wof:placetype":"venue"
},
  "geometry": {"coordinates":[-85.808917,32.747699],"type":"Point"}
}