{
  "type": "Feature",
  "properties": {
    "iso:country":"US",
    "sg:address":"7220 4th Ave N",
    "sg:city":"Birmingham",
    "sg:classifiers":[
        {
            "category":"Organizations",
            "subcategory":"Religious Organization",
            "type":"Services"
        }
    ],
    "sg:phone":"+1 205 836 3031",
    "sg:postcode":"35206",
    "sg:province":"AL",
    "sg:tags":[
        "church"
    ],
    "wof:name":"East Lake Full Gospel Baptist",
    "wof:placetype":"venue"
},
  "geometry": {"coordinates":[-86.737086,33.559438],"type":"Point"}
}