{
  "type": "Feature",
  "properties": {
    "iso:country":"US",
    "sg:address":"1806 24th St SW",
    "sg:city":"Birmingham",
    "sg:classifiers":[
        {
            "category":"Food & Beverages",
            "subcategory":"Groceries & Convenience Stores",
            "type":"Retail Goods"
        }
    ],
    "sg:phone":"+1 205 923 1380",
    "sg:postcode":"35211",
    "sg:province":"AL",
    "wof:name":"Triple S Convenience Store Inc",
    "wof:placetype":"venue"
},
  "geometry": {"coordinates":[-86.874168,33.466327],"type":"Point"}
}