{
  "type": "Feature",
  "properties": {
    "iso:country":"US",
    "sg:address":"6346 Gene Terry Rd",
    "sg:city":"Cottonwood",
    "sg:classifiers":[
        {
            "category":"Shopping",
            "subcategory":"Bicycles & Sporting Goods",
            "type":"Retail Goods"
        }
    ],
    "sg:phone":"+1 334 691 7102",
    "sg:postcode":"36320",
    "sg:province":"AL",
    "wof:name":"American Angler Products",
    "wof:placetype":"venue"
},
  "geometry": {"coordinates":[-85.29763199999999,31.066375],"type":"Point"}
}