{
  "type": "Feature",
  "properties": {
    "addr:full":"107 Commercial Ln Dothan AL 36303",
    "addr:housenumber":"107",
    "addr:postcode":"36303",
    "addr:street":"Commercial Ln",
    "iso:country":"US",
    "sg:address":"107 Commercial Ln",
    "sg:city":"Dothan",
    "sg:classifiers":[
        {
            "category":"Home & Garden",
            "subcategory":"Building Materials",
            "type":"Retail Goods"
        }
    ],
    "sg:phone":"+1 334 794 8836",
    "sg:postcode":"36303",
    "sg:province":"AL",
    "wof:name":"A & A Drywall Supply",
    "wof:placetype":"venue"
},
  "geometry": {"coordinates":[-85.389369,31.259731],"type":"Point"}
}