{
  "type": "Feature",
  "properties": {
    "iso:country":"US",
    "sg:address":"1136 Winchester Rd NE",
    "sg:city":"Huntsville",
    "sg:classifiers":[
        {
            "category":"Organizations",
            "subcategory":"Religious Organization",
            "type":"Services"
        }
    ],
    "sg:phone":"+1 256 852 1717",
    "sg:postcode":"35811",
    "sg:province":"AL",
    "sg:tags":[
        "church"
    ],
    "wof:name":"Restoration Reviving Ctr",
    "wof:placetype":"venue"
},
  "geometry": {"coordinates":[-86.533214,34.799694],"type":"Point"}
}