{
  "type": "Feature",
  "properties": {
    "addr:full":"5232 Atlanta Hwy Montgomery AL 36109",
    "addr:housenumber":"5232",
    "addr:postcode":"36109",
    "addr:street":"Atlanta Hwy",
    "iso:country":"US",
    "sg:address":"5232 Atlanta Hwy",
    "sg:city":"Montgomery",
    "sg:classifiers":[
        {
            "category":"Banks & Credit Unions",
            "subcategory":"Bank",
            "type":"Services"
        }
    ],
    "sg:phone":"+1 334 273 7964",
    "sg:postcode":"36109",
    "sg:province":"AL",
    "sg:tags":[
        "cashing",
        "check"
    ],
    "wof:name":"Title Cash",
    "wof:placetype":"venue"
},
  "geometry": {"coordinates":[-86.217443,32.3817],"type":"Point"}
}