{
  "type": "Feature",
  "properties": {
    "iso:country":"US",
    "sg:address":"1700 Pearson Ave SW",
    "sg:city":"Birmingham",
    "sg:classifiers":[
        {
            "category":"Personal",
            "subcategory":"Beauty Salon",
            "type":"Services"
        }
    ],
    "sg:phone":"+1 205 923 5313",
    "sg:postcode":"35211",
    "sg:province":"AL",
    "sg:tags":[
        "shop"
    ],
    "wof:name":"Kandi Hair Salon",
    "wof:placetype":"venue"
},
  "geometry": {"coordinates":[-86.864309,33.485312],"type":"Point"}
}