{
  "type": "Feature",
  "properties": {
    "iso:country":"US",
    "sg:address":"2434 Veterans Memorial Pkwy",
    "sg:city":"Lanett",
    "sg:classifiers":[
        {
            "category":"Autos & Motor Vehicles",
            "subcategory":"Motorcycle Sales",
            "type":"Retail Goods"
        }
    ],
    "sg:phone":"+1 334 576 8383",
    "sg:postcode":"36863",
    "sg:province":"AL",
    "sg:tags":[
        "scooter"
    ],
    "wof:name":"C C Rider Cycles Sales",
    "wof:placetype":"venue"
},
  "geometry": {"coordinates":[-85.219117,32.846892],"type":"Point"}
}