{
  "type": "Feature",
  "properties": {
    "addr:full":"375 Montgomery Ave Thorsby AL 35171",
    "addr:housenumber":"375",
    "addr:postcode":"35171",
    "addr:street":"Montgomery Ave",
    "iso:country":"US",
    "sg:address":"375 Montgomery Ave",
    "sg:city":"Thorsby",
    "sg:classifiers":[
        {
            "category":"Freight",
            "type":"Transportation"
        }
    ],
    "sg:phone":"+1 205 646 0021",
    "sg:postcode":"35171",
    "sg:province":"AL",
    "sg:tags":[
        "commercial",
        "storage"
    ],
    "wof:name":"Thorsby Jemison/Clanton/Cooper",
    "wof:placetype":"venue"
},
  "geometry": {"coordinates":[-86.719432,32.918933],"type":"Point"}
}