{
  "type": "Feature",
  "properties": {
    "addr:full":"1201 Park St Troy AL 36081",
    "addr:housenumber":"1201",
    "addr:postcode":"36081",
    "addr:street":"Park St",
    "iso:country":"US",
    "sg:address":"1201 Park St",
    "sg:city":"Troy",
    "sg:classifiers":[
        {
            "category":"Insurance",
            "subcategory":"Insurance Agent",
            "type":"Services"
        }
    ],
    "sg:phone":"+1 334 566 6064",
    "sg:postcode":"36081",
    "sg:province":"AL",
    "wof:name":"William D Beck Agency",
    "wof:placetype":"venue"
},
  "geometry": {"coordinates":[-85.963593,31.791413],"type":"Point"}
}