{
  "type": "Feature",
  "properties": {
    "iso:country":"US",
    "sg:address":"3175 Alabama Ave",
    "sg:city":"Monroeville",
    "sg:classifiers":[
        {
            "category":"Retail",
            "subcategory":"Auto Repair",
            "type":"Services"
        }
    ],
    "sg:phone":"+1 251 743 4377",
    "sg:postcode":"36460",
    "sg:province":"AL",
    "sg:tags":[
        "body",
        "automobile",
        "painting"
    ],
    "wof:name":"Smith Body Shop LLC",
    "wof:placetype":"venue"
},
  "geometry": {"coordinates":[-87.333043,31.480157],"type":"Point"}
}