{
  "type": "Feature",
  "properties": {
    "addr:full":"114 6th Ave NE Decatur AL 35601",
    "addr:housenumber":"114",
    "addr:postcode":"35601",
    "addr:street":"6Th Ave Ne",
    "iso:country":"US",
    "sg:address":"114 6th Ave NE",
    "sg:city":"Decatur",
    "sg:classifiers":[
        {
            "category":"Autos & Motor Vehicles",
            "subcategory":"Fuel & Gas Station",
            "type":"Retail Goods"
        }
    ],
    "sg:phone":"+1 256 355 3202",
    "sg:postcode":"35601",
    "sg:province":"AL",
    "sg:tags":[
        "grocery",
        "station",
        "gasoline",
        "oil"
    ],
    "wof:name":"Poppie's Place Spur",
    "wof:placetype":"venue"
},
  "geometry": {"coordinates":[-86.979934,34.60423],"type":"Point"}
}