{
  "type": "Feature",
  "properties": {
    "iso:country":"US",
    "sg:address":"22645 Canal Rd",
    "sg:city":"Orange Beach",
    "sg:classifiers":[
        {
            "category":"Professional",
            "subcategory":"Lawyer & Legal Services",
            "type":"Services"
        }
    ],
    "sg:phone":"+1 251 967 1585",
    "sg:postcode":"36561",
    "sg:province":"AL",
    "sg:tags":[
        "attorney"
    ],
    "wof:name":"Lawrence L Jones",
    "wof:placetype":"venue"
},
  "geometry": {"coordinates":[-87.618556,30.290198],"type":"Point"}
}