{
  "type": "Feature",
  "properties": {
    "addr:full":"552 Bessemer Super Hwy Birmingham AL 35228",
    "addr:housenumber":"552",
    "addr:postcode":"35228",
    "addr:street":"Super Hwy",
    "iso:country":"US",
    "sg:address":"552 Bessemer Super Hwy",
    "sg:city":"Birmingham",
    "sg:classifiers":[
        {
            "category":"Health Services",
            "subcategory":"Optometrist",
            "type":"Services"
        },
        {
            "category":"Health Services",
            "subcategory":"Chiropractor",
            "type":"Services"
        }
    ],
    "sg:phone":"+1 205 923 0151",
    "sg:postcode":"35228",
    "sg:province":"AL",
    "sg:tags":[
        "clinic",
        "chiropractic"
    ],
    "wof:name":"Collins Chiropractic",
    "wof:placetype":"venue"
},
  "geometry": {"coordinates":[-86.919546,33.455711],"type":"Point"}
}