{
  "type": "Feature",
  "properties": {
    "iso:country":"US",
    "sg:address":"7805 US Hwy 72",
    "sg:city":"Athens",
    "sg:classifiers":[
        {
            "category":"Organizations",
            "subcategory":"Religious Organization",
            "type":"Services"
        }
    ],
    "sg:phone":"+1 256 729 8343",
    "sg:postcode":"35611",
    "sg:province":"AL",
    "wof:name":"Mt Carmel Church Of Christ",
    "wof:placetype":"venue"
},
  "geometry": {"coordinates":[-87.182211,34.802843],"type":"Point"}
}