{
  "type": "Feature",
  "properties": {
    "iso:country":"US",
    "sg:address":"4401 Florence Blvd",
    "sg:city":"Florence",
    "sg:classifiers":[
        {
            "category":"Professional",
            "type":"Services"
        }
    ],
    "sg:phone":"+1 256 757 9709",
    "sg:postcode":"35634",
    "sg:province":"AL",
    "sg:tags":[
        "establishment"
    ],
    "wof:name":"Guaranteed Credit Approval",
    "wof:placetype":"venue"
},
  "geometry": {"coordinates":[-87.573954,34.849086],"type":"Point"}
}