{
  "type": "Feature",
  "properties": {
    "addr:full":"416 State Rte 165 Phenix City AL 36869",
    "addr:housenumber":"416",
    "addr:postcode":"36869",
    "addr:street":"State Rte 165 Phenix City Al",
    "iso:country":"US",
    "sg:address":"416 State Rte 165",
    "sg:city":"Phenix City",
    "sg:classifiers":[
        {
            "category":"Organizations",
            "subcategory":"Community Association",
            "type":"Services"
        }
    ],
    "sg:phone":"+1 334 855 3698",
    "sg:postcode":"36869",
    "sg:province":"AL",
    "wof:name":"Order of Eastern Star & I",
    "wof:placetype":"venue"
},
  "geometry": {"coordinates":[-85.03450100000001,32.364755],"type":"Point"}
}