{
  "type": "Feature",
  "properties": {
    "iso:country":"US",
    "sg:address":"6534 Co Rd 200",
    "sg:city":"Florence",
    "sg:classifiers":[
        {
            "category":"Professional",
            "type":"Services"
        },
        {
            "category":"Manufacturing",
            "subcategory":"Apparel",
            "type":"Manufacturing & Wholesale Goods"
        }
    ],
    "sg:phone":"+1 256 764 8230",
    "sg:postcode":"35633",
    "sg:province":"AL",
    "sg:tags":[
        "establishment",
        "clothing",
        "mfg"
    ],
    "wof:name":"Project Alabama LLC",
    "wof:placetype":"venue"
},
  "geometry": {"coordinates":[-87.767021,34.873935],"type":"Point"}
}