{
  "type": "Feature",
  "properties": {
    "iso:country":"US",
    "sg:address":"2767 Old Providence Rd",
    "sg:city":"Goodwater",
    "sg:classifiers":[
        {
            "category":"Organizations",
            "subcategory":"Religious Organization",
            "type":"Services"
        }
    ],
    "sg:phone":"+1 256 329 5129",
    "sg:postcode":"35072",
    "sg:province":"AL",
    "sg:tags":[
        "church"
    ],
    "wof:name":"Old Providence Baptist",
    "wof:placetype":"venue"
},
  "geometry": {"coordinates":[-85.920041,33.091909],"type":"Point"}
}