{
  "type": "Feature",
  "properties": {
    "iso:country":"US",
    "sg:address":"2080 Main St",
    "sg:city":"Millbrook",
    "sg:classifiers":[
        {
            "category":"Organizations",
            "subcategory":"Religious Organization",
            "type":"Services"
        }
    ],
    "sg:phone":"+1 334 285 7650",
    "sg:postcode":"36054",
    "sg:province":"AL",
    "sg:tags":[
        "church"
    ],
    "wof:name":"Victory Tabernacle AOH Chr",
    "wof:placetype":"venue"
},
  "geometry": {"coordinates":[-86.3604,32.46075],"type":"Point"}
}