{
  "type": "Feature",
  "properties": {
    "iso:country":"US",
    "sg:address":"1720 Mauvilla Dr",
    "sg:city":"Demopolis",
    "sg:classifiers":[
        {
            "category":"Government",
            "subcategory":"Office",
            "type":"Public Place"
        }
    ],
    "sg:phone":"+1 334 289 3951",
    "sg:postcode":"36732",
    "sg:province":"AL",
    "sg:tags":[
        "city",
        "program"
    ],
    "wof:name":"Demopolis Community Education",
    "wof:placetype":"venue"
},
  "geometry": {"coordinates":[-87.859222,32.505811],"type":"Point"}
}