{
  "type": "Feature",
  "properties": {
    "iso:country":"US",
    "sg:address":"2155 Brittany Dr",
    "sg:city":"Mobile",
    "sg:classifiers":[
        {
            "category":"Professional",
            "subcategory":"Engineering",
            "type":"Services"
        }
    ],
    "sg:phone":"+1 251 607 7033",
    "sg:postcode":"36695",
    "sg:province":"AL",
    "sg:tags":[
        "engineer"
    ],
    "wof:name":"Mobile Electrical Engineering",
    "wof:placetype":"venue"
},
  "geometry": {"coordinates":[-88.238528,30.64489],"type":"Point"}
}