{
  "type": "Feature",
  "properties": {
    "addr:full":"103 Northside Sq Huntsville AL 35801",
    "addr:housenumber":"103",
    "addr:postcode":"35801",
    "addr:street":"Northside Sq",
    "iso:country":"US",
    "sg:address":"103 Northside Sq",
    "sg:city":"Huntsville",
    "sg:classifiers":[
        {
            "category":"Farming",
            "subcategory":"Farm",
            "type":"Manufacturing & Wholesale Goods"
        }
    ],
    "sg:phone":"+1 256 533 1233",
    "sg:postcode":"35801",
    "sg:province":"AL",
    "wof:name":"Ashburn Farms",
    "wof:placetype":"venue"
},
  "geometry": {"coordinates":[-86.585311,34.730554],"type":"Point"}
}