{
  "type": "Feature",
  "properties": {
    "addr:full":"944 Brandy Ln Birmingham AL 35214",
    "addr:housenumber":"944",
    "addr:postcode":"35214",
    "addr:street":"Brandy Ln",
    "iso:country":"US",
    "sg:address":"944 Brandy Ln",
    "sg:city":"Birmingham",
    "sg:classifiers":[
        {
            "category":"Shopping",
            "type":"Retail Goods"
        }
    ],
    "sg:phone":"+1 205 791 3707",
    "sg:postcode":"35214",
    "sg:province":"AL",
    "sg:tags":[
        "merchandise"
    ],
    "wof:name":"Tub O Matic",
    "wof:placetype":"venue"
},
  "geometry": {"coordinates":[-86.87286899999999,33.563049],"type":"Point"}
}