{
  "type": "Feature",
  "properties": {
    "addr:full":"850 Boll Weevil Cir Enterprise AL 36330",
    "addr:housenumber":"850",
    "addr:postcode":"36330",
    "addr:street":"Boll Weevil Cir Enterprise",
    "iso:country":"US",
    "sg:address":"850 Boll Weevil Cir",
    "sg:city":"Enterprise",
    "sg:classifiers":[
        {
            "category":"Autos & Motor Vehicles",
            "subcategory":"Fuel & Gas Station",
            "type":"Retail Goods"
        }
    ],
    "sg:phone":"+1 334 308 2954",
    "sg:postcode":"36330",
    "sg:province":"AL",
    "sg:tags":[
        "oil"
    ],
    "wof:name":"Enterprise Texaco",
    "wof:placetype":"venue"
},
  "geometry": {"coordinates":[-85.854063,31.335104],"type":"Point"}
}