{
  "type": "Feature",
  "properties": {
    "addr:full":"11539 Backbone Church Rd Gordo AL 35466",
    "addr:housenumber":"11539",
    "addr:postcode":"35466",
    "addr:street":"Backbone Church Rd",
    "iso:country":"US",
    "sg:address":"11539 Backbone Church Rd",
    "sg:city":"Gordo",
    "sg:classifiers":[
        {
            "category":"Shopping",
            "type":"Retail Goods"
        }
    ],
    "sg:phone":"+1 205 339 7001",
    "sg:postcode":"35466",
    "sg:province":"AL",
    "sg:tags":[
        "plumbing",
        "heating",
        "supply"
    ],
    "wof:name":"Buhl Supply Co",
    "wof:placetype":"venue"
},
  "geometry": {"coordinates":[-87.811269,33.245893],"type":"Point"}
}