{
  "type": "Feature",
  "properties": {
    "iso:country":"US",
    "sg:address":"1100 S Jackson Hwy",
    "sg:city":"Sheffield",
    "sg:classifiers":[
        {
            "category":"Health Services",
            "subcategory":"Doctor",
            "type":"Services"
        }
    ],
    "sg:phone":"+1 256 718 5900",
    "sg:postcode":"35660",
    "sg:province":"AL",
    "sg:tags":[
        "physician",
        "surgeon"
    ],
    "wof:name":"Obstetrics & Gynecology Assoc",
    "wof:placetype":"venue"
},
  "geometry": {"coordinates":[-87.701681,34.74715],"type":"Point"}
}