{
  "type": "Feature",
  "properties": {
    "iso:country":"US",
    "sg:address":"3504 Spruce Ave SW",
    "sg:city":"Huntsville",
    "sg:classifiers":[
        {
            "category":"Building & Trades",
            "subcategory":"Equipment Rental",
            "type":"Services"
        }
    ],
    "sg:phone":"+1 256 536 4661",
    "sg:postcode":"35805",
    "sg:province":"AL",
    "wof:name":"Reindeer Inc",
    "wof:placetype":"venue"
},
  "geometry": {"coordinates":[-86.613639,34.701294],"type":"Point"}
}