{
  "type": "Feature",
  "properties": {
    "iso:country":"US",
    "sg:address":"75 Co Rd 311",
    "sg:city":"Moulton",
    "sg:classifiers":[
        {
            "category":"Freight",
            "type":"Transportation"
        }
    ],
    "sg:phone":"+1 256 974 2700",
    "sg:postcode":"35650",
    "sg:province":"AL",
    "sg:tags":[
        "operator",
        "trucking"
    ],
    "wof:name":"Still Breathing Freight Lines",
    "wof:placetype":"venue"
},
  "geometry": {"coordinates":[-87.27783599999999,34.547612],"type":"Point"}
}