{
  "type": "Feature",
  "properties": {
    "addr:full":"13965 Sprinkle Ave Bayou La Batre AL 36509",
    "addr:housenumber":"13965",
    "addr:postcode":"36509",
    "addr:street":"Sprinkle Ave Bayou La",
    "iso:country":"US",
    "sg:address":"13965 Sprinkle Ave",
    "sg:city":"Bayou La Batre",
    "sg:classifiers":[
        {
            "category":"Retail",
            "subcategory":"Repair Shop",
            "type":"Services"
        },
        {
            "category":"Home & Garden",
            "subcategory":"Garden Supply",
            "type":"Retail Goods"
        }
    ],
    "sg:phone":"+1 251 824 2165",
    "sg:postcode":"36509",
    "sg:province":"AL",
    "sg:tags":[
        "engine",
        "equipment",
        "industrial"
    ],
    "wof:name":"George's Small Engine & Repair",
    "wof:placetype":"venue"
},
  "geometry": {"coordinates":[-88.23742,30.401432],"type":"Point"}
}