{
  "type": "Feature",
  "properties": {
    "iso:country":"US",
    "sg:address":"658 N Wood Ave",
    "sg:city":"Florence",
    "sg:classifiers":[
        {
            "category":"Travel",
            "subcategory":"Hotels & Motels",
            "type":"Entertainment"
        }
    ],
    "sg:phone":"+1 256 766 8441",
    "sg:postcode":"35630",
    "sg:province":"AL",
    "sg:tags":[
        "operation"
    ],
    "sg:website":"www.woodavenueinn.com",
    "wof:name":"Wood Avenue Inn",
    "wof:placetype":"venue"
},
  "geometry": {"coordinates":[-87.677306,34.807754],"type":"Point"}
}