{
  "type": "Feature",
  "properties": {
    "iso:country":"US",
    "sg:address":"17325 Mormon Rd",
    "sg:city":"Northport",
    "sg:classifiers":[
        {
            "category":"Retail",
            "subcategory":"Repair Shop",
            "type":"Services"
        }
    ],
    "sg:phone":"+1 205 339 6250",
    "sg:postcode":"35475",
    "sg:province":"AL",
    "sg:tags":[
        "electrical"
    ],
    "wof:name":"Appliance Tech",
    "wof:placetype":"venue"
},
  "geometry": {"coordinates":[-87.708071,33.412679],"type":"Point"}
}