{
  "type": "Feature",
  "properties": {
    "iso:country":"US",
    "sg:address":"970 Silver Creek Cir",
    "sg:city":"Prattville",
    "sg:classifiers":[
        {
            "category":"Professional",
            "subcategory":"Business Services",
            "type":"Services"
        }
    ],
    "sg:phone":"+1 334 365 6749",
    "sg:postcode":"36066",
    "sg:province":"AL",
    "wof:name":"Bright Acquisitions",
    "wof:placetype":"venue"
},
  "geometry": {"coordinates":[-86.434203,32.452735],"type":"Point"}
}