{
  "type": "Feature",
  "properties": {
    "iso:country":"US",
    "sg:address":"1820 4th Ave N",
    "sg:city":"Birmingham",
    "sg:classifiers":[
        {
            "category":"Restaurant",
            "type":"Food & Drink"
        }
    ],
    "sg:phone":"+1 205 323 1820",
    "sg:postcode":"35203",
    "sg:province":"AL",
    "sg:website":"www.restaurantg.com",
    "wof:name":"G Restaurant",
    "wof:placetype":"venue"
},
  "geometry": {"coordinates":[-86.809241,33.516454],"type":"Point"}
}