{
  "type": "Feature",
  "properties": {
    "iso:country":"US",
    "sg:address":"100 Alton Lynch Cir",
    "sg:city":"Madison",
    "sg:classifiers":[
        {
            "category":"Real Estate",
            "subcategory":"Real Estate Operator",
            "type":"Services"
        }
    ],
    "sg:phone":"+1 256 837 0461",
    "sg:postcode":"35757",
    "sg:province":"AL",
    "sg:tags":[
        "mobile",
        "home",
        "community"
    ],
    "wof:name":"Crestwood Mobile Home Estates",
    "wof:placetype":"venue"
},
  "geometry": {"coordinates":[-86.730644,34.776655],"type":"Point"}
}