{
  "type": "Feature",
  "properties": {
    "iso:country":"US",
    "sg:address":"6112 Co Rd 10",
    "sg:city":"Hamilton",
    "sg:phone":"+1 205 921 4024",
    "sg:postcode":"35570",
    "sg:province":"AL",
    "sg:tags":[
        "farm",
        "corn"
    ],
    "wof:name":"Carl Lucas",
    "wof:placetype":"venue"
},
  "geometry": {"coordinates":[-88.02426699999999,34.057451],"type":"Point"}
}