{
  "type": "Feature",
  "properties": {
    "iso:country":"US",
    "sg:address":"508 River Falls St",
    "sg:city":"Andalusia",
    "sg:classifiers":[
        {
            "category":"Insurance",
            "subcategory":"Insurance Agent",
            "type":"Services"
        }
    ],
    "sg:phone":"+1 334 222 3831",
    "sg:postcode":"36420",
    "sg:province":"AL",
    "wof:name":"Rex Powell General Insurance",
    "wof:placetype":"venue"
},
  "geometry": {"coordinates":[-86.491008,31.313043],"type":"Point"}
}