{
  "type": "Feature",
  "properties": {
    "iso:country":"US",
    "sg:address":"3501 Kenwood Dr",
    "sg:city":"Huntsville",
    "sg:classifiers":[
        {
            "category":"Education",
            "subcategory":"School",
            "type":"Public Place"
        }
    ],
    "sg:phone":"+1 256 851 4160",
    "sg:postcode":"35810",
    "sg:province":"AL",
    "sg:tags":[
        "executive"
    ],
    "wof:name":"Lakewood Elementary School",
    "wof:placetype":"venue"
},
  "geometry": {"coordinates":[-86.58937,34.772214],"type":"Point"}
}