{
  "type": "Feature",
  "properties": {
    "addr:full":"373 Prevatt Rd Dothan AL 36301",
    "addr:housenumber":"373",
    "addr:postcode":"36301",
    "addr:street":"Prevatt Rd",
    "iso:country":"US",
    "sg:address":"373 Prevatt Rd",
    "sg:city":"Dothan",
    "sg:classifiers":[
        {
            "category":"Professional",
            "type":"Services"
        }
    ],
    "sg:phone":"+1 334 699 8258",
    "sg:postcode":"36301",
    "sg:province":"AL",
    "wof:name":"Doug & Melissa Applin",
    "wof:placetype":"venue"
},
  "geometry": {"coordinates":[-85.363851,31.194364],"type":"Point"}
}