{
  "type": "Feature",
  "properties": {
    "addr:full":"1088 Hughes Rd Madison AL 35758",
    "addr:housenumber":"1088",
    "addr:postcode":"35758",
    "addr:street":"Hughes Rd",
    "iso:country":"US",
    "sg:address":"1088 Hughes Rd",
    "sg:city":"Madison",
    "sg:classifiers":[
        {
            "category":"Organizations",
            "subcategory":"Religious Organization",
            "type":"Services"
        }
    ],
    "sg:phone":"+1 256 837 9737",
    "sg:postcode":"35758",
    "sg:province":"AL",
    "sg:website":"www.trinitymadison.com",
    "wof:name":"Trinity Baptist Church",
    "wof:placetype":"venue"
},
  "geometry": {"coordinates":[-86.741355,34.733632],"type":"Point"}
}