{
  "type": "Feature",
  "properties": {
    "iso:country":"US",
    "sg:address":"1701 Chester St NW",
    "sg:city":"Huntsville",
    "sg:classifiers":[
        {
            "category":"Organizations",
            "subcategory":"Community Association",
            "type":"Services"
        }
    ],
    "sg:phone":"+1 256 533 6326",
    "sg:postcode":"35816",
    "sg:province":"AL",
    "wof:name":"Ancient & Accepted Scotti",
    "wof:placetype":"venue"
},
  "geometry": {"coordinates":[-86.610177,34.745117],"type":"Point"}
}