{
  "type": "Feature",
  "properties": {
    "addr:full":"460 S Foster St Dothan AL 36301",
    "addr:housenumber":"460",
    "addr:postcode":"36301",
    "addr:street":"S Foster St",
    "iso:country":"US",
    "sg:address":"460 S Foster St",
    "sg:city":"Dothan",
    "sg:classifiers":[
        {
            "category":"Health Services",
            "subcategory":"Nursing And Care Facility",
            "type":"Services"
        }
    ],
    "sg:phone":"+1 334 792 9718",
    "sg:postcode":"36301",
    "sg:province":"AL",
    "sg:tags":[
        "home",
        "retirement",
        "community"
    ],
    "wof:name":"Gran's Home",
    "wof:placetype":"venue"
},
  "geometry": {"coordinates":[-85.391789,31.218934],"type":"Point"}
}