{
  "type": "Feature",
  "properties": {
    "iso:country":"US",
    "sg:address":"300 Fairhope Dr NW",
    "sg:city":"Arab",
    "sg:classifiers":[
        {
            "category":"Professional",
            "subcategory":"Management & Consulting",
            "type":"Services"
        }
    ],
    "sg:phone":"+1 256 586 0309",
    "sg:postcode":"35016",
    "sg:province":"AL",
    "sg:tags":[
        "business"
    ],
    "wof:name":"Hcs & Tte",
    "wof:placetype":"venue"
},
  "geometry": {"coordinates":[-86.533563,34.327234],"type":"Point"}
}