{
  "type": "Feature",
  "properties": {
    "iso:country":"US",
    "sg:address":"1001 S Eufaula Ave",
    "sg:city":"Eufaula",
    "sg:classifiers":[
        {
            "category":"Professional",
            "type":"Services"
        }
    ],
    "sg:phone":"+1 334 687 0001",
    "sg:postcode":"36027",
    "sg:province":"AL",
    "wof:name":"Titlemax",
    "wof:placetype":"venue"
},
  "geometry": {"coordinates":[-85.146866,31.880762],"type":"Point"}
}