{
  "type": "Feature",
  "properties": {
    "iso:country":"US",
    "sg:address":"237 S Wilson Ave",
    "sg:city":"Mobile",
    "sg:classifiers":[
        {
            "category":"Shopping",
            "subcategory":"Discount & Variety Stores",
            "type":"Retail Goods"
        }
    ],
    "sg:phone":"+1 251 452 4160",
    "sg:postcode":"36610",
    "sg:province":"AL",
    "sg:tags":[
        "real estate"
    ],
    "wof:name":"Zoghbys Department Store",
    "wof:placetype":"venue"
},
  "geometry": {"coordinates":[-88.082167,30.733269],"type":"Point"}
}