{
  "type": "Feature",
  "properties": {
    "addr:full":"179 Defee Rd Lapine AL 36046",
    "addr:housenumber":"179",
    "addr:postcode":"36046",
    "addr:street":"Defee Rd",
    "iso:country":"US",
    "sg:address":"179 Defee Rd",
    "sg:city":"Lapine",
    "sg:classifiers":[
        {
            "category":"Organizations",
            "subcategory":"Religious Organization",
            "type":"Services"
        }
    ],
    "sg:phone":"+1 334 537 4614",
    "sg:postcode":"36046",
    "sg:province":"AL",
    "sg:tags":[
        "church"
    ],
    "wof:name":"New Ebenezer Baptist Church",
    "wof:placetype":"venue"
},
  "geometry": {"coordinates":[-86.352436,31.950636],"type":"Point"}
}