{
  "type": "Feature",
  "properties": {
    "addr:full":"181 Hughes Rd Madison AL 35758",
    "addr:housenumber":"181",
    "addr:postcode":"35758",
    "addr:street":"Hughes Rd",
    "iso:country":"US",
    "sg:address":"181 Hughes Rd",
    "sg:city":"Madison",
    "sg:classifiers":[
        {
            "category":"Retail",
            "subcategory":"Portrait Studio",
            "type":"Services"
        }
    ],
    "sg:phone":"+1 256 772 9780",
    "sg:postcode":"35758",
    "sg:province":"AL",
    "sg:tags":[
        "photographer"
    ],
    "wof:name":"Commercial Images Inc",
    "wof:placetype":"venue"
},
  "geometry": {"coordinates":[-86.742154,34.702435],"type":"Point"}
}