{
  "type": "Feature",
  "properties": {
    "iso:country":"US",
    "sg:address":"26129 State Rte 25",
    "sg:city":"Wilsonville",
    "sg:classifiers":[
        {
            "category":"Social Services",
            "type":"Services"
        }
    ],
    "sg:phone":"+1 205 669 2014",
    "sg:postcode":"35186",
    "sg:province":"AL",
    "wof:name":"Martin R Counseling",
    "wof:placetype":"venue"
},
  "geometry": {"coordinates":[-86.557689,33.226686],"type":"Point"}
}