{
  "type": "Feature",
  "properties": {
    "iso:country":"US",
    "sg:address":"13016 State Rte 48",
    "sg:city":"Wedowee",
    "sg:classifiers":[
        {
            "category":"Building & Trades",
            "subcategory":"Construction",
            "type":"Services"
        }
    ],
    "sg:phone":"+1 256 357 2676",
    "sg:postcode":"36278",
    "sg:province":"AL",
    "sg:tags":[
        "general",
        "contractor"
    ],
    "wof:name":"Unique Home",
    "wof:placetype":"venue"
},
  "geometry": {"coordinates":[-85.528424,33.302813],"type":"Point"}
}