{
  "type": "Feature",
  "properties": {
    "addr:full":"801 S Eufaula Ave Eufaula AL 36027",
    "addr:housenumber":"801",
    "addr:postcode":"36027",
    "addr:street":"S Eufaula Ave",
    "iso:country":"US",
    "sg:address":"801 S Eufaula Ave",
    "sg:city":"Eufaula",
    "sg:classifiers":[
        {
            "category":"Retail",
            "subcategory":"Auto Repair",
            "type":"Services"
        }
    ],
    "sg:phone":"+1 334 687 3561",
    "sg:postcode":"36027",
    "sg:province":"AL",
    "sg:tags":[
        "repairing",
        "automobile"
    ],
    "wof:name":"Herndon Tire Co",
    "wof:placetype":"venue"
},
  "geometry": {"coordinates":[-85.14575499999999,31.882904],"type":"Point"}
}