{
  "type": "Feature",
  "properties": {
    "iso:country":"US",
    "sg:address":"2118 4th Ave N",
    "sg:city":"Birmingham",
    "sg:classifiers":[
        {
            "category":"Social Services",
            "subcategory":"Child Care",
            "type":"Services"
        }
    ],
    "sg:phone":"+1 205 322 8310",
    "sg:postcode":"35203",
    "sg:province":"AL",
    "sg:tags":[
        "day"
    ],
    "wof:name":"Elizabth Perry Rushtn Chld Dev",
    "wof:placetype":"venue"
},
  "geometry": {"coordinates":[-86.805024,33.518456],"type":"Point"}
}