{
  "type": "Feature",
  "properties": {
    "iso:country":"US",
    "sg:address":"880 Montclair Rd Ste 275",
    "sg:city":"Birmingham",
    "sg:classifiers":[
        {
            "category":"Health Services",
            "subcategory":"Clinic",
            "type":"Services"
        },
        {
            "category":"Health Services",
            "subcategory":"Medical Lab",
            "type":"Services"
        },
        {
            "category":"Professional",
            "subcategory":"Business Services",
            "type":"Services"
        }
    ],
    "sg:phone":"+1 877 312 7311",
    "sg:postcode":"35213",
    "sg:province":"AL",
    "sg:tags":[
        "information",
        "testing",
        "aid",
        "welfare"
    ],
    "sg:website":"http://birmingham.citysearch.com/profile/external/603799162/birmingham_al/std_test_express_birmingham.html?publisher=yellowpages&reference_id=1&placement=ypwebsitemip",
    "wof:name":"STD Test Express Birmingham",
    "wof:placetype":"venue"
},
  "geometry": {"coordinates":[-86.745659,33.515962],"type":"Point"}
}