{
  "type": "Feature",
  "properties": {
    "iso:country":"US",
    "sg:address":"9730 State Rte 69",
    "sg:city":"Tuscaloosa",
    "sg:classifiers":[
        {
            "category":"Sports & Exercise",
            "subcategory":"Gym",
            "type":"Entertainment"
        }
    ],
    "sg:phone":"+1 205 349 4555",
    "sg:postcode":"35405",
    "sg:province":"AL",
    "sg:tags":[
        "club",
        "health",
        "studio",
        "gymnasium"
    ],
    "wof:name":"Curves For Women",
    "wof:placetype":"venue"
},
  "geometry": {"coordinates":[-87.570211,33.068222],"type":"Point"}
}