{
  "type": "Feature",
  "properties": {
    "addr:full":"15024 E Limestone Rd Harvest AL 35749",
    "addr:housenumber":"15024",
    "addr:postcode":"35749",
    "addr:street":"E Limestone Rd",
    "iso:country":"US",
    "sg:address":"15024 E Limestone Rd",
    "sg:city":"Harvest",
    "sg:classifiers":[
        {
            "category":"Restaurant",
            "type":"Food & Drink"
        }
    ],
    "sg:menulink":"http://www.allmenus.com/al/athens/120877-subway/menu/",
    "sg:phone":"+1 256 771 1363",
    "sg:postcode":"35749",
    "sg:province":"AL",
    "sg:tags":[
        "american",
        "sandwich"
    ],
    "wof:name":"Subway",
    "wof:placetype":"venue"
},
  "geometry": {"coordinates":[-86.832542,34.773315],"type":"Point"}
}