{
  "type": "Feature",
  "properties": {
    "iso:country":"US",
    "sg:address":"918 S Randolph Ave",
    "sg:city":"Eufaula",
    "sg:classifiers":[
        {
            "category":"Wholesale",
            "subcategory":"Durable Goods & Equipment",
            "type":"Manufacturing & Wholesale Goods"
        }
    ],
    "sg:phone":"+1 334 616 6930",
    "sg:postcode":"36027",
    "sg:province":"AL",
    "sg:tags":[
        "exporter"
    ],
    "wof:name":"REC Intl",
    "wof:placetype":"venue"
},
  "geometry": {"coordinates":[-85.14425300000001,31.880598],"type":"Point"}
}