{
  "type": "Feature",
  "properties": {
    "iso:country":"US",
    "sg:address":"2920 Lomb Ave",
    "sg:city":"Birmingham",
    "sg:classifiers":[
        {
            "category":"Professional",
            "type":"Services"
        }
    ],
    "sg:phone":"+1 205 788 7737",
    "sg:postcode":"35208",
    "sg:province":"AL",
    "wof:name":"Rev F V Walker",
    "wof:placetype":"venue"
},
  "geometry": {"coordinates":[-86.868104,33.500574],"type":"Point"}
}