{
  "type": "Feature",
  "properties": {
    "iso:country":"US",
    "sg:address":"11441 Rocky Ford Rd",
    "sg:city":"Piedmont",
    "sg:classifiers":[
        {
            "category":"Organizations",
            "subcategory":"Religious Organization",
            "type":"Services"
        }
    ],
    "sg:phone":"+1 256 492 0108",
    "sg:postcode":"36272",
    "sg:province":"AL",
    "wof:name":"Jones Chapel Baptist Church",
    "wof:placetype":"venue"
},
  "geometry": {"coordinates":[-85.768039,34.012273],"type":"Point"}
}