{
  "type": "Feature",
  "properties": {
    "iso:country":"US",
    "sg:address":"2024 State Rte 20",
    "sg:city":"Decatur",
    "sg:classifiers":[
        {
            "category":"Manufacturing",
            "subcategory":"Metals",
            "type":"Manufacturing & Wholesale Goods"
        }
    ],
    "sg:phone":"+1 256 308 1321",
    "sg:postcode":"35601",
    "sg:province":"AL",
    "sg:tags":[
        "treating",
        "heat"
    ],
    "wof:name":"Cooper HEAT-Mqs",
    "wof:placetype":"venue"
},
  "geometry": {"coordinates":[-87.016507,34.619326],"type":"Point"}
}