{
  "type": "Feature",
  "properties": {
    "addr:full":"1779 Plantersville Rd Alpine AL 35014",
    "addr:housenumber":"1779",
    "addr:postcode":"35014",
    "addr:street":"Plantersville Rd",
    "iso:country":"US",
    "sg:address":"1779 Plantersville Rd",
    "sg:city":"Alpine",
    "sg:classifiers":[
        {
            "category":"Food & Beverages",
            "subcategory":"Groceries & Convenience Stores",
            "type":"Retail Goods"
        }
    ],
    "sg:phone":"+1 256 268 0436",
    "sg:postcode":"35014",
    "sg:province":"AL",
    "sg:tags":[
        "station",
        "gasoline"
    ],
    "wof:name":"Bama Service Company II",
    "wof:placetype":"venue"
},
  "geometry": {"coordinates":[-86.24087,33.42313],"type":"Point"}
}