{
  "type": "Feature",
  "properties": {
    "addr:full":"4890 University Sq Huntsville AL 35816",
    "addr:housenumber":"4890",
    "addr:postcode":"35816",
    "addr:street":"University Sq",
    "iso:country":"US",
    "sg:address":"4890 University Sq",
    "sg:city":"Huntsville",
    "sg:classifiers":[
        {
            "category":"Government",
            "subcategory":"Office",
            "type":"Public Place"
        }
    ],
    "sg:phone":"+1 256 544 5795",
    "sg:postcode":"35816",
    "sg:province":"AL",
    "sg:tags":[
        "federal",
        "planning",
        "dev"
    ],
    "wof:name":"USDA Rural Development",
    "wof:placetype":"venue"
},
  "geometry": {"coordinates":[-86.654167,34.741724],"type":"Point"}
}