{
  "type": "Feature",
  "properties": {
    "addr:full":"2101 Richard Arrington Jr Blvd N Birmingham AL 35203",
    "addr:housenumber":"2101",
    "addr:postcode":"35203",
    "addr:street":"Richard Arrington Jr Blvd N",
    "iso:country":"US",
    "sg:address":"2101 Richard Arrington Jr Blvd N",
    "sg:city":"Birmingham",
    "sg:classifiers":[
        {
            "category":"Travel",
            "subcategory":"Hotels & Motels",
            "type":"Entertainment"
        },
        {
            "category":"Travel",
            "subcategory":"Resort",
            "type":"Entertainment"
        },
        {
            "category":"Sports & Exercise",
            "subcategory":"Ski Resort",
            "type":"Entertainment"
        }
    ],
    "sg:phone":"+1 205 324 5000",
    "sg:postcode":"35203",
    "sg:province":"AL",
    "sg:tags":[
        "corporate",
        "lodging"
    ],
    "sg:website":"http://clk.atdmt.com/NYC/go/156799074/direct/01/",
    "wof:name":"Sheraton Birmingham Hotel",
    "wof:placetype":"venue"
},
  "geometry": {"coordinates":[-86.81057,33.524929],"type":"Point"}
}