{
  "type": "Feature",
  "properties": {
    "iso:country":"US",
    "sg:address":"201 Cahaba Valley Pkwy N",
    "sg:city":"Pelham",
    "sg:classifiers":[
        {
            "category":"Building & Trades",
            "subcategory":"Construction",
            "type":"Services"
        }
    ],
    "sg:phone":"+1 205 402 7322",
    "sg:postcode":"35124",
    "sg:province":"AL",
    "sg:tags":[
        "excavating",
        "contractor"
    ],
    "wof:name":"Meredith Environmental Inc",
    "wof:placetype":"venue"
},
  "geometry": {"coordinates":[-86.78484899999999,33.343117],"type":"Point"}
}