{
  "type": "Feature",
  "properties": {
    "addr:full":"530 Plainview St Gadsden AL 35901",
    "addr:housenumber":"530",
    "addr:postcode":"35901",
    "addr:street":"Plainview St",
    "iso:country":"US",
    "sg:address":"530 Plainview St",
    "sg:city":"Gadsden",
    "sg:classifiers":[
        {
            "category":"Retail",
            "subcategory":"Auto Repair",
            "type":"Services"
        }
    ],
    "sg:phone":"+1 256 547 7451",
    "sg:postcode":"35901",
    "sg:province":"AL",
    "sg:tags":[
        "tire"
    ],
    "wof:name":"Sips Tire Repair Ser",
    "wof:placetype":"venue"
},
  "geometry": {"coordinates":[-86.020658,34.028089],"type":"Point"}
}