{
  "type": "Feature",
  "properties": {
    "addr:full":"115 Eastern Blvd Montgomery AL 36117",
    "addr:housenumber":"115",
    "addr:postcode":"36117",
    "addr:street":"Eastern Blvd",
    "iso:country":"US",
    "sg:address":"115 Eastern Blvd",
    "sg:city":"Montgomery",
    "sg:classifiers":[
        {
            "category":"Restaurant",
            "type":"Food & Drink"
        }
    ],
    "sg:phone":"+1 334 260 0795",
    "sg:postcode":"36117",
    "sg:province":"AL",
    "sg:tags":[
        "lunch",
        "brunch",
        "breakfast"
    ],
    "sg:website":"http://www.ihop.com",
    "wof:name":"IHOP",
    "wof:placetype":"venue"
},
  "geometry": {"coordinates":[-86.22357599999999,32.34576],"type":"Point"}
}