{
  "type": "Feature",
  "properties": {
    "addr:full":"260 Deep Hollow Rd Oneonta AL 35121",
    "addr:housenumber":"260",
    "addr:postcode":"35121",
    "addr:street":"Deep Hollow Rd",
    "iso:country":"US",
    "sg:address":"260 Deep Hollow Rd",
    "sg:city":"Oneonta",
    "sg:classifiers":[
        {
            "category":"Building & Trades",
            "subcategory":"Construction",
            "type":"Services"
        }
    ],
    "sg:phone":"+1 205 625 4360",
    "sg:postcode":"35121",
    "sg:province":"AL",
    "sg:tags":[
        "siding",
        "contractor"
    ],
    "wof:name":"H & C Siding",
    "wof:placetype":"venue"
},
  "geometry": {"coordinates":[-86.517945,33.896808],"type":"Point"}
}