{
  "type": "Feature",
  "properties": {
    "iso:country":"US",
    "sg:address":"6655 Zeigler Blvd",
    "sg:city":"Mobile",
    "sg:classifiers":[
        {
            "category":"Real Estate",
            "subcategory":"Real Estate Operator",
            "type":"Services"
        }
    ],
    "sg:phone":"+1 251 342 1011",
    "sg:postcode":"36608",
    "sg:province":"AL",
    "sg:tags":[
        "apartment"
    ],
    "wof:name":"Creekside Apartments",
    "wof:placetype":"venue"
},
  "geometry": {"coordinates":[-88.198152,30.708634],"type":"Point"}
}