{
  "type": "Feature",
  "properties": {
    "addr:full":"12788 Dominion Dr Fairhope AL 36532",
    "addr:housenumber":"12788",
    "addr:postcode":"36532",
    "addr:street":"Dominion Dr",
    "iso:country":"US",
    "sg:address":"12788 Dominion Dr",
    "sg:city":"Fairhope",
    "sg:classifiers":[
        {
            "category":"Building & Trades",
            "subcategory":"Construction",
            "type":"Services"
        }
    ],
    "sg:phone":"+1 251 928 6698",
    "sg:postcode":"36532",
    "sg:province":"AL",
    "sg:tags":[
        "designer",
        "marine",
        "contractor"
    ],
    "wof:name":"Doug Ward Construction",
    "wof:placetype":"venue"
},
  "geometry": {"coordinates":[-87.84230700000001,30.418426],"type":"Point"}
}