{
  "type": "Feature",
  "properties": {
    "iso:country":"US",
    "sg:address":"19560 N 3rd St",
    "sg:city":"Citronelle",
    "sg:classifiers":[
        {
            "category":"Personal",
            "subcategory":"Beauty Salon",
            "type":"Services"
        }
    ],
    "sg:phone":"+1 251 866 0074",
    "sg:postcode":"36522",
    "sg:province":"AL",
    "sg:tags":[
        "shop"
    ],
    "wof:name":"Ladybug",
    "wof:placetype":"venue"
},
  "geometry": {"coordinates":[-88.237987,31.101932],"type":"Point"}
}