{
  "type": "Feature",
  "properties": {
    "iso:country":"US",
    "sg:address":"4135 Dawes Rd",
    "sg:city":"Mobile",
    "sg:classifiers":[
        {
            "category":"Organizations",
            "subcategory":"Religious Organization",
            "type":"Services"
        }
    ],
    "sg:phone":"+1 251 660 0013",
    "sg:postcode":"36695",
    "sg:province":"AL",
    "sg:tags":[
        "church"
    ],
    "wof:name":"River Of Life",
    "wof:placetype":"venue"
},
  "geometry": {"coordinates":[-88.342823,30.565526],"type":"Point"}
}