{
  "type": "Feature",
  "properties": {
    "iso:country":"US",
    "sg:address":"P.O. Box 11586 2129 East South Blvd",
    "sg:city":"Montgomery",
    "sg:classifiers":[
        {
            "category":"Professional",
            "subcategory":"Computer Services",
            "type":"Services"
        }
    ],
    "sg:postcode":"36111-0586",
    "sg:province":"AL",
    "sg:tags":[
        "parenting",
        "childhood-development",
        "children",
        "learning"
    ],
    "sg:website":"http://abbysfunhouse.com",
    "wof:name":"AbbysFunHouse.com",
    "wof:placetype":"venue"
},
  "geometry": {"coordinates":[-86.26731700000001,32.342438],"type":"Point"}
}