{
  "type": "Feature",
  "properties": {
    "addr:full":"3019 Norwood Blvd Birmingham AL 35234",
    "addr:housenumber":"3019",
    "addr:postcode":"35234",
    "addr:street":"Norwood Blvd",
    "iso:country":"US",
    "sg:address":"3019 Norwood Blvd",
    "sg:city":"Birmingham",
    "sg:classifiers":[
        {
            "category":"Freight",
            "type":"Transportation"
        }
    ],
    "sg:phone":"+1 205 323 6102",
    "sg:postcode":"35234",
    "sg:province":"AL",
    "sg:tags":[
        "operator",
        "local",
        "trucking"
    ],
    "wof:name":"B & F Trucking Inc",
    "wof:placetype":"venue"
},
  "geometry": {"coordinates":[-86.804627,33.540762],"type":"Point"}
}