{
  "type": "Feature",
  "properties": {
    "addr:full":"28490 2nd St Daphne AL 36526",
    "addr:housenumber":"28490",
    "addr:postcode":"36526",
    "addr:street":"2Nd St",
    "iso:country":"US",
    "sg:address":"28490 2nd St",
    "sg:city":"Daphne",
    "sg:classifiers":[
        {
            "category":"Health Services",
            "subcategory":"Health Practitioner",
            "type":"Services"
        }
    ],
    "sg:phone":"+1 251 621 2990",
    "sg:postcode":"36526",
    "sg:province":"AL",
    "sg:tags":[
        "psychologist"
    ],
    "wof:name":"C Van Rosen PHD",
    "wof:placetype":"venue"
},
  "geometry": {"coordinates":[-87.91393100000001,30.640071],"type":"Point"}
}