{
  "type": "Feature",
  "properties": {
    "addr:full":"415 Mabry St Selma AL 36701",
    "addr:housenumber":"415",
    "addr:postcode":"36701",
    "addr:street":"Mabry St",
    "iso:country":"US",
    "sg:address":"415 Mabry St",
    "sg:city":"Selma",
    "sg:classifiers":[
        {
            "category":"Shopping",
            "type":"Retail Goods"
        }
    ],
    "sg:phone":"+1 334 872 3368",
    "sg:postcode":"36701",
    "sg:province":"AL",
    "sg:tags":[
        "merchandise"
    ],
    "wof:name":"Shark Bay Aquarium",
    "wof:placetype":"venue"
},
  "geometry": {"coordinates":[-87.02681699999999,32.410502],"type":"Point"}
}