{
  "type": "Feature",
  "properties": {
    "iso:country":"US",
    "sg:address":"3676 Cedar Springs Rd",
    "sg:city":"Jacksonville",
    "sg:classifiers":[
        {
            "category":"Manufacturing",
            "subcategory":"Tools & Machinery",
            "type":"Manufacturing & Wholesale Goods"
        }
    ],
    "sg:phone":"+1 256 435 7869",
    "sg:postcode":"36265",
    "sg:province":"AL",
    "sg:tags":[
        "water",
        "equipment",
        "works",
        "supply"
    ],
    "wof:name":"Calhoun Meter Co",
    "wof:placetype":"venue"
},
  "geometry": {"coordinates":[-85.838724,33.799438],"type":"Point"}
}