{
  "type": "Feature",
  "properties": {
    "iso:country":"US",
    "sg:address":"100 Pinewood Dr",
    "sg:city":"Munford",
    "sg:classifiers":[
        {
            "category":"Building & Trades",
            "subcategory":"Construction",
            "type":"Services"
        }
    ],
    "sg:phone":"+1 256 831 5397",
    "sg:postcode":"36268",
    "sg:province":"AL",
    "sg:tags":[
        "contractor"
    ],
    "wof:name":"Smith & Haynes Specialties",
    "wof:placetype":"venue"
},
  "geometry": {"coordinates":[-85.870158,33.561868],"type":"Point"}
}