{
  "type": "Feature",
  "properties": {
    "addr:full":"2640 McKenzie St Foley AL 36535",
    "addr:housenumber":"2640",
    "addr:postcode":"36535",
    "addr:street":"Mckenzie St",
    "iso:country":"US",
    "sg:address":"2640 McKenzie St",
    "sg:city":"Foley",
    "sg:classifiers":[
        {
            "category":"Home & Garden",
            "subcategory":"Building Materials",
            "type":"Retail Goods"
        },
        {
            "category":"Manufacturing",
            "subcategory":"Glass & Minerals",
            "type":"Manufacturing & Wholesale Goods"
        }
    ],
    "sg:phone":"+1 251 943 2985",
    "sg:postcode":"36535",
    "sg:province":"AL",
    "sg:tags":[
        "ready",
        "concrete",
        "mixed",
        "mfg"
    ],
    "wof:name":"Reynolds Ready Mix LLC",
    "wof:placetype":"venue"
},
  "geometry": {"coordinates":[-87.683379,30.371318],"type":"Point"}
}