{
  "type": "Feature",
  "properties": {
    "iso:country":"US",
    "sg:address":"109 Radford Cir",
    "sg:city":"Dothan",
    "sg:classifiers":[
        {
            "category":"Building & Trades",
            "subcategory":"Plumbing",
            "type":"Services"
        }
    ],
    "sg:phone":"+1 334 794 6971",
    "sg:postcode":"36301",
    "sg:province":"AL",
    "sg:tags":[
        "contractor"
    ],
    "wof:name":"Wood Plumbing",
    "wof:placetype":"venue"
},
  "geometry": {"coordinates":[-85.362062,31.20239],"type":"Point"}
}