{
  "type": "Feature",
  "properties": {
    "iso:country":"US",
    "sg:address":"51 Dexter Ave",
    "sg:city":"Montgomery",
    "sg:classifiers":[
        {
            "category":"Food & Beverages",
            "subcategory":"Groceries & Convenience Stores",
            "type":"Retail Goods"
        }
    ],
    "sg:phone":"+1 334 265 9002",
    "sg:postcode":"36104",
    "sg:province":"AL",
    "sg:tags":[
        "deli"
    ],
    "wof:name":"Dexter Deli Market",
    "wof:placetype":"venue"
},
  "geometry": {"coordinates":[-86.30804999999999,32.377477],"type":"Point"}
}