{
  "type": "Feature",
  "properties": {
    "addr:full":"4620 18th Ave E Tuscaloosa AL 35405",
    "addr:housenumber":"4620",
    "addr:postcode":"35405",
    "addr:street":"18Th Ave E",
    "iso:country":"US",
    "sg:address":"4620 18th Ave E",
    "sg:city":"Tuscaloosa",
    "sg:classifiers":[
        {
            "category":"Wholesale",
            "subcategory":"Durable Goods & Equipment",
            "type":"Manufacturing & Wholesale Goods"
        }
    ],
    "sg:phone":"+1 205 553 1223",
    "sg:postcode":"35405",
    "sg:province":"AL",
    "sg:tags":[
        "exporter"
    ],
    "wof:name":"Mc Connell Hills Apts",
    "wof:placetype":"venue"
},
  "geometry": {"coordinates":[-87.51383,33.167325],"type":"Point"}
}