{
  "type": "Feature",
  "properties": {
    "iso:country":"US",
    "sg:address":"107 N Jackson St",
    "sg:city":"Mobile",
    "sg:classifiers":[
        {
            "category":"Professional",
            "subcategory":"Lawyer & Legal Services",
            "type":"Services"
        }
    ],
    "sg:phone":"+1 251 423 4759",
    "sg:postcode":"36602",
    "sg:province":"AL",
    "wof:name":"Tracie B Lee LLC",
    "wof:placetype":"venue"
},
  "geometry": {"coordinates":[-88.04557200000001,30.692448],"type":"Point"}
}