{
  "type": "Feature",
  "properties": {
    "iso:country":"US",
    "sg:address":"4110 Co Rd 41",
    "sg:city":"Russellville",
    "sg:classifiers":[
        {
            "category":"Manufacturing",
            "subcategory":"Lumber",
            "type":"Manufacturing & Wholesale Goods"
        }
    ],
    "sg:phone":"+1 256 332 6170",
    "sg:postcode":"35653",
    "sg:province":"AL",
    "sg:tags":[
        "logging"
    ],
    "wof:name":"B & B Timber",
    "wof:placetype":"venue"
},
  "geometry": {"coordinates":[-87.847084,34.534839],"type":"Point"}
}