{
  "type": "Feature",
  "properties": {
    "iso:country":"US",
    "sg:address":"602 Main St W",
    "sg:city":"Hartselle",
    "sg:classifiers":[
        {
            "category":"Health Services",
            "subcategory":"Doctor",
            "type":"Services"
        }
    ],
    "sg:phone":"+1 256 773 7250",
    "sg:postcode":"35640",
    "sg:province":"AL",
    "sg:tags":[
        "dentist"
    ],
    "wof:name":"Douglas R Sittason DDS",
    "wof:placetype":"venue"
},
  "geometry": {"coordinates":[-86.940923,34.442519],"type":"Point"}
}