{
  "type": "Feature",
  "properties": {
    "addr:full":"59 Richardson Dr Monroeville AL 36460",
    "addr:housenumber":"59",
    "addr:postcode":"36460",
    "addr:street":"Richardson Dr",
    "iso:country":"US",
    "sg:address":"59 Richardson Dr",
    "sg:city":"Monroeville",
    "sg:classifiers":[
        {
            "category":"Organizations",
            "subcategory":"Religious Organization",
            "type":"Services"
        }
    ],
    "sg:phone":"+1 251 575 7765",
    "sg:postcode":"36460",
    "sg:province":"AL",
    "sg:tags":[
        "church"
    ],
    "wof:name":"Monroeville Church Of Christ",
    "wof:placetype":"venue"
},
  "geometry": {"coordinates":[-87.35514499999999,31.530165],"type":"Point"}
}