{
  "type": "Feature",
  "properties": {
    "addr:full":"11420 Al Highway 75 Henagar AL 35978",
    "addr:housenumber":"11420",
    "addr:postcode":"35978",
    "addr:street":"Al Highway 75",
    "iso:country":"US",
    "sg:address":"11420 Al Highway 75",
    "sg:city":"Henagar",
    "sg:classifiers":[
        {
            "category":"Personal",
            "subcategory":"Beauty Salon",
            "type":"Services"
        },
        {
            "category":"Personal",
            "subcategory":"Nail Salon",
            "type":"Services"
        }
    ],
    "sg:phone":"+1 256 657 1220",
    "sg:postcode":"35978",
    "sg:province":"AL",
    "sg:tags":[
        "hair",
        "stylist"
    ],
    "wof:name":"Nail Shop-Beauty Shop",
    "wof:placetype":"venue"
},
  "geometry": {"coordinates":[-85.699967,34.659742],"type":"Point"}
}