{
  "type": "Feature",
  "properties": {
    "iso:country":"US",
    "sg:address":"25300 Perdido Beach Blvd",
    "sg:city":"Orange Beach",
    "sg:classifiers":[
        {
            "category":"Building & Trades",
            "subcategory":"Construction",
            "type":"Services"
        }
    ],
    "sg:phone":"+1 251 974 3895",
    "sg:postcode":"36561",
    "sg:province":"AL",
    "sg:tags":[
        "residential"
    ],
    "wof:name":"Amason & Associates",
    "wof:placetype":"venue"
},
  "geometry": {"coordinates":[-87.59307200000001,30.268075],"type":"Point"}
}