{
  "type": "Feature",
  "properties": {
    "iso:country":"US",
    "sg:address":"1521 West St",
    "sg:city":"Montgomery",
    "sg:classifiers":[
        {
            "category":"Personal",
            "subcategory":"Beauty Salon",
            "type":"Services"
        }
    ],
    "sg:phone":"+1 334 262 4247",
    "sg:postcode":"36106",
    "sg:province":"AL",
    "sg:tags":[
        "shop"
    ],
    "wof:name":"Beauty Center",
    "wof:placetype":"venue"
},
  "geometry": {"coordinates":[-86.281541,32.364252],"type":"Point"}
}