{
  "type": "Feature",
  "properties": {
    "addr:full":"800 Dogwood Trl Warrior AL 35180",
    "addr:housenumber":"800",
    "addr:postcode":"35180",
    "addr:street":"Dogwood Trl",
    "iso:country":"US",
    "sg:address":"800 Dogwood Trl",
    "sg:city":"Warrior",
    "sg:classifiers":[
        {
            "category":"Retail",
            "subcategory":"Repair Shop",
            "type":"Services"
        }
    ],
    "sg:phone":"+1 205 647 4636",
    "sg:postcode":"35180",
    "sg:province":"AL",
    "sg:tags":[
        "electrical"
    ],
    "wof:name":"Jones Appliance Service",
    "wof:placetype":"venue"
},
  "geometry": {"coordinates":[-86.860534,33.833025],"type":"Point"}
}