{
  "type": "Feature",
  "properties": {
    "addr:full":"1480 Eastern Blvd Montgomery AL 36117",
    "addr:housenumber":"1480",
    "addr:postcode":"36117",
    "addr:street":"Eastern Blvd",
    "iso:country":"US",
    "sg:address":"1480 Eastern Blvd",
    "sg:city":"Montgomery",
    "sg:classifiers":[
        {
            "category":"Bakery",
            "type":"Food & Drink"
        }
    ],
    "sg:menulink":"http://www.allmenus.com/al/montgomery/99927-golden-corral/menu/",
    "sg:phone":"+1 334 532 0020",
    "sg:postcode":"36117",
    "sg:province":"AL",
    "sg:tags":[
        "american",
        "pastry"
    ],
    "wof:name":"Golden Corral",
    "wof:placetype":"venue"
},
  "geometry": {"coordinates":[-86.216735,32.3575],"type":"Point"}
}