{
  "type": "Feature",
  "properties": {
    "iso:country":"US",
    "sg:address":"2407 Montgomery Hwy",
    "sg:city":"Dothan",
    "sg:classifiers":[
        {
            "category":"Banks & Credit Unions",
            "subcategory":"Investment Brokerage",
            "type":"Services"
        }
    ],
    "sg:phone":"+1 334 673 8384",
    "sg:postcode":"36303",
    "sg:province":"AL",
    "sg:tags":[
        "advisory",
        "financial"
    ],
    "wof:name":"Citi Corp",
    "wof:placetype":"venue"
},
  "geometry": {"coordinates":[-85.418444,31.243131],"type":"Point"}
}