{
  "type": "Feature",
  "properties": {
    "iso:country":"US",
    "sg:address":"529 S Perry St",
    "sg:city":"Montgomery",
    "sg:classifiers":[
        {
            "category":"Professional",
            "subcategory":"Secretarial Services",
            "type":"Services"
        }
    ],
    "sg:phone":"+1 334 297 7119",
    "sg:postcode":"36104",
    "sg:province":"AL",
    "sg:tags":[
        "reporting",
        "court"
    ],
    "wof:name":"Pruitt & Davis",
    "wof:placetype":"venue"
},
  "geometry": {"coordinates":[-86.307072,32.370565],"type":"Point"}
}