{
  "type": "Feature",
  "properties": {
    "iso:country":"US",
    "sg:address":"314 Robin Hood Dr",
    "sg:city":"Florence",
    "sg:classifiers":[
        {
            "category":"Retail",
            "subcategory":"Repair Shop",
            "type":"Services"
        }
    ],
    "sg:phone":"+1 256 766 0911",
    "sg:postcode":"35633",
    "sg:province":"AL",
    "sg:tags":[
        "electrical"
    ],
    "wof:name":"Vics Appliance Repair",
    "wof:placetype":"venue"
},
  "geometry": {"coordinates":[-87.678849,34.84093],"type":"Point"}
}