{
  "type": "Feature",
  "properties": {
    "iso:country":"US",
    "sg:address":"1210 Bridge Ave",
    "sg:city":"Northport",
    "sg:classifiers":[
        {
            "category":"Retail",
            "subcategory":"Laundry & Dry Cleaning",
            "type":"Services"
        }
    ],
    "sg:phone":"+1 205 344 9034",
    "sg:postcode":"35476",
    "sg:province":"AL",
    "sg:tags":[
        "cleaners"
    ],
    "wof:name":"Royal Dry Cleaners",
    "wof:placetype":"venue"
},
  "geometry": {"coordinates":[-87.575872,33.224563],"type":"Point"}
}