{
  "type": "Feature",
  "properties": {
    "addr:full":"4134 Government Blvd Mobile AL 36693",
    "addr:housenumber":"4134",
    "addr:postcode":"36693",
    "addr:street":"Government Blvd",
    "iso:country":"US",
    "sg:address":"4134 Government Blvd",
    "sg:city":"Mobile",
    "sg:classifiers":[
        {
            "category":"Wholesale",
            "subcategory":"Hardware",
            "type":"Manufacturing & Wholesale Goods"
        }
    ],
    "sg:phone":"+1 251 666 1188",
    "sg:postcode":"36693",
    "sg:province":"AL",
    "sg:tags":[
        "plumbing",
        "equipment",
        "supply"
    ],
    "wof:name":"Morales J H Sales",
    "wof:placetype":"venue"
},
  "geometry": {"coordinates":[-88.14513100000001,30.633471],"type":"Point"}
}