{
  "type": "Feature",
  "properties": {
    "addr:full":"603 Bert Rosenbush Rd Demopolis AL 36732",
    "addr:housenumber":"603",
    "addr:postcode":"36732",
    "addr:street":"Bert Rosenbush Rd",
    "iso:country":"US",
    "sg:address":"603 Bert Rosenbush Rd",
    "sg:city":"Demopolis",
    "sg:classifiers":[
        {
            "category":"Professional",
            "subcategory":"Computer Services",
            "type":"Services"
        }
    ],
    "sg:phone":"+1 334 289 8166",
    "sg:postcode":"36732",
    "sg:province":"AL",
    "sg:tags":[
        "repair"
    ],
    "wof:name":"C & G Waldrop Computer Repair",
    "wof:placetype":"venue"
},
  "geometry": {"coordinates":[-87.86642999999999,32.420631],"type":"Point"}
}