{
  "type": "Feature",
  "properties": {
    "iso:country":"US",
    "sg:address":"815 Co Rd 53",
    "sg:city":"Clanton",
    "sg:classifiers":[
        {
            "category":"Home & Garden",
            "subcategory":"Garden Supply",
            "type":"Retail Goods"
        }
    ],
    "sg:phone":"+1 205 280 3888",
    "sg:postcode":"35045",
    "sg:province":"AL",
    "sg:tags":[
        "lawn",
        "mower"
    ],
    "wof:name":"Clanton's Small Engine",
    "wof:placetype":"venue"
},
  "geometry": {"coordinates":[-86.665029,32.843381],"type":"Point"}
}