{
  "type": "Feature",
  "properties": {
    "addr:full":"648 Boll Weevil Cir Enterprise AL 36330",
    "addr:housenumber":"648",
    "addr:postcode":"36330",
    "addr:street":"Boll Weevil Cir Enterprise",
    "iso:country":"US",
    "sg:address":"648 Boll Weevil Cir",
    "sg:city":"Enterprise",
    "sg:classifiers":[
        {
            "category":"Insurance",
            "subcategory":"Insurance Agent",
            "type":"Services"
        }
    ],
    "sg:phone":"+1 334 308 0090",
    "sg:postcode":"36330",
    "sg:province":"AL",
    "wof:name":"Geico Insurance",
    "wof:placetype":"venue"
},
  "geometry": {"coordinates":[-85.861327,31.334078],"type":"Point"}
}