{
  "type": "Feature",
  "properties": {
    "addr:full":"4025 Greensboro Ave Tuscaloosa AL 35405",
    "addr:housenumber":"4025",
    "addr:postcode":"35405",
    "addr:street":"Greensboro Ave",
    "iso:country":"US",
    "sg:address":"4025 Greensboro Ave",
    "sg:city":"Tuscaloosa",
    "sg:classifiers":[
        {
            "category":"Organizations",
            "subcategory":"Religious Organization",
            "type":"Services"
        }
    ],
    "sg:phone":"+1 205 750 0084",
    "sg:postcode":"35405",
    "sg:province":"AL",
    "wof:name":"Overcoming Deliverence Church",
    "wof:placetype":"venue"
},
  "geometry": {"coordinates":[-87.52510700000001,33.17187],"type":"Point"}
}