{
  "type": "Feature",
  "properties": {
    "iso:country":"US",
    "sg:address":"511 Hargrove Rd E",
    "sg:city":"Tuscaloosa",
    "sg:classifiers":[
        {
            "category":"Banks & Credit Unions",
            "subcategory":"Bank",
            "type":"Services"
        }
    ],
    "sg:phone":"+1 205 345 0088",
    "sg:postcode":"35401",
    "sg:province":"AL",
    "sg:tags":[
        "cashing",
        "check"
    ],
    "wof:name":"It's All About Cash",
    "wof:placetype":"venue"
},
  "geometry": {"coordinates":[-87.53017,33.1879],"type":"Point"}
}