{
  "type": "Feature",
  "properties": {
    "iso:country":"US",
    "sg:address":"2017 6th Ave N",
    "sg:city":"Birmingham",
    "sg:classifiers":[
        {
            "category":"Organizations",
            "subcategory":"Religious Organization",
            "type":"Services"
        }
    ],
    "sg:phone":"+1 205 251 2324",
    "sg:postcode":"35203",
    "sg:province":"AL",
    "sg:tags":[
        "book",
        "store"
    ],
    "sg:website":"www.adventbirmingham.org",
    "wof:name":"Cathedral Church Of Advent",
    "wof:placetype":"venue"
},
  "geometry": {"coordinates":[-86.807673,33.519748],"type":"Point"}
}