{
  "type": "Feature",
  "properties": {
    "addr:full":"48715 US Hwy 78 Lincoln AL 35096",
    "addr:postcode":"48715;35096",
    "addr:street":"Us Hwy 78",
    "iso:country":"US",
    "sg:address":"48715 US Hwy 78",
    "sg:city":"Lincoln",
    "sg:classifiers":[
        {
            "category":"Autos & Motor Vehicles",
            "subcategory":"Auto Supplies",
            "type":"Retail Goods"
        }
    ],
    "sg:phone":"+1 205 763 7756",
    "sg:postcode":"35096",
    "sg:province":"AL",
    "sg:tags":[
        "automobile",
        "parts"
    ],
    "wof:name":"Midway Auto Parts",
    "wof:placetype":"venue"
},
  "geometry": {"coordinates":[-86.10172300000001,33.604382],"type":"Point"}
}