{
  "type": "Feature",
  "properties": {
    "iso:country":"US",
    "sg:address":"400 S Union St",
    "sg:city":"Montgomery",
    "sg:classifiers":[
        {
            "category":"Health Services",
            "subcategory":"Nursing And Care Facility",
            "type":"Services"
        }
    ],
    "sg:phone":"+1 334 834 2300",
    "sg:postcode":"36104",
    "sg:province":"AL",
    "wof:name":"United Cerebral Palsy",
    "wof:placetype":"venue"
},
  "geometry": {"coordinates":[-86.299448,32.372714],"type":"Point"}
}