{
  "type": "Feature",
  "properties": {
    "addr:full":"110 S Oak St Troy AL 36081",
    "addr:housenumber":"110",
    "addr:postcode":"36081",
    "addr:street":"S Oak St",
    "iso:country":"US",
    "sg:address":"110 S Oak St",
    "sg:city":"Troy",
    "sg:classifiers":[
        {
            "category":"Government",
            "subcategory":"Office",
            "type":"Public Place"
        }
    ],
    "sg:phone":"+1 334 566 0011",
    "sg:postcode":"36081",
    "sg:province":"AL",
    "sg:tags":[
        "federal",
        "human"
    ],
    "wof:name":"US Organized Community Action",
    "wof:placetype":"venue"
},
  "geometry": {"coordinates":[-85.971484,31.807839],"type":"Point"}
}