{
  "type": "Feature",
  "properties": {
    "iso:country":"US",
    "sg:address":"204 College St SW",
    "sg:city":"Jacksonville",
    "sg:classifiers":[
        {
            "category":"Home & Garden",
            "subcategory":"Building Materials",
            "type":"Retail Goods"
        }
    ],
    "sg:phone":"+1 256 494 0790",
    "sg:postcode":"36265",
    "sg:province":"AL",
    "sg:tags":[
        "door"
    ],
    "wof:name":"Valley Overhead Doors",
    "wof:placetype":"venue"
},
  "geometry": {"coordinates":[-85.763301,33.815256],"type":"Point"}
}