{
  "type": "Feature",
  "properties": {
    "iso:country":"US",
    "sg:address":"305 Chase Dr",
    "sg:city":"Saraland",
    "sg:classifiers":[
        {
            "category":"Organizations",
            "subcategory":"Labor Organization",
            "type":"Services"
        }
    ],
    "sg:phone":"+1 251 675 6681",
    "sg:postcode":"36571",
    "sg:province":"AL",
    "wof:name":"Teamsters Local",
    "wof:placetype":"venue"
},
  "geometry": {"coordinates":[-88.123339,30.829738],"type":"Point"}
}