{
  "type": "Feature",
  "properties": {
    "iso:country":"US",
    "sg:address":"720 Parker Rd",
    "sg:city":"Bessemer",
    "sg:classifiers":[
        {
            "category":"Organizations",
            "subcategory":"Religious Organization",
            "type":"Services"
        }
    ],
    "sg:phone":"+1 205 481 9366",
    "sg:postcode":"35022",
    "sg:province":"AL",
    "sg:tags":[
        "church"
    ],
    "wof:name":"Glenn Hills United Meth Chr",
    "wof:placetype":"venue"
},
  "geometry": {"coordinates":[-86.983262,33.378752],"type":"Point"}
}