{
  "type": "Feature",
  "properties": {
    "addr:full":"7471 Theodore Dawes Rd Theodore AL 36582",
    "addr:housenumber":"7471",
    "addr:postcode":"36582",
    "addr:street":"Theodore Dawes Rd",
    "iso:country":"US",
    "sg:address":"7471 Theodore Dawes Rd",
    "sg:city":"Theodore",
    "sg:classifiers":[
        {
            "category":"Wholesale",
            "subcategory":"Durable Goods & Equipment",
            "type":"Manufacturing & Wholesale Goods"
        }
    ],
    "sg:phone":"+1 251 653 0679",
    "sg:postcode":"36582",
    "sg:province":"AL",
    "sg:tags":[
        "importer"
    ],
    "wof:name":"Heba Tala Co",
    "wof:placetype":"venue"
},
  "geometry": {"coordinates":[-88.219191,30.568288],"type":"Point"}
}