{
  "type": "Feature",
  "properties": {
    "iso:country":"US",
    "sg:address":"1406 14th Ave",
    "sg:city":"Phenix City",
    "sg:classifiers":[
        {
            "category":"Building & Trades",
            "subcategory":"Construction",
            "type":"Services"
        }
    ],
    "sg:phone":"+1 334 298 4847",
    "sg:postcode":"36867",
    "sg:province":"AL",
    "sg:tags":[
        "general",
        "contractor"
    ],
    "wof:name":"Watson Dry Wall LLC",
    "wof:placetype":"venue"
},
  "geometry": {"coordinates":[-85.01217200000001,32.47451],"type":"Point"}
}