{
  "type": "Feature",
  "properties": {
    "iso:country":"US",
    "sg:address":"1855 Hickman Ave",
    "sg:city":"Elba",
    "sg:classifiers":[
        {
            "category":"Professional",
            "type":"Services"
        }
    ],
    "sg:phone":"+1 334 897 8900",
    "sg:postcode":"36323",
    "sg:province":"AL",
    "wof:name":"Mary Phillips",
    "wof:placetype":"venue"
},
  "geometry": {"coordinates":[-86.087357,31.41722],"type":"Point"}
}