{
  "type": "Feature",
  "properties": {
    "iso:country":"US",
    "sg:address":"216 North St E",
    "sg:city":"Talladega",
    "sg:classifiers":[
        {
            "category":"Education",
            "subcategory":"Library",
            "type":"Public Place"
        }
    ],
    "sg:phone":"+1 256 362 8033",
    "sg:postcode":"35160",
    "sg:province":"AL",
    "wof:name":"Weaver Library",
    "wof:placetype":"venue"
},
  "geometry": {"coordinates":[-86.09881,33.436018],"type":"Point"}
}