{
  "type": "Feature",
  "properties": {
    "addr:full":"190 Lime Quarry Rd Madison AL 35758",
    "addr:housenumber":"190",
    "addr:postcode":"35758",
    "addr:street":"Lime Quarry Rd",
    "iso:country":"US",
    "sg:address":"190 Lime Quarry Rd",
    "sg:city":"Madison",
    "sg:classifiers":[
        {
            "category":"Wholesale",
            "subcategory":"Office Equipment",
            "type":"Manufacturing & Wholesale Goods"
        },
        {
            "category":"Professional",
            "subcategory":"Employment Agencies",
            "type":"Services"
        }
    ],
    "sg:phone":"+1 256 464 8545",
    "sg:postcode":"35758",
    "sg:province":"AL",
    "sg:tags":[
        "credit",
        "help",
        "supply"
    ],
    "wof:name":"Advanced Payment Solutions",
    "wof:placetype":"venue"
},
  "geometry": {"coordinates":[-86.748589,34.676442],"type":"Point"}
}