{
  "type": "Feature",
  "properties": {
    "iso:country":"US",
    "sg:address":"3240 Woodard Dr",
    "sg:city":"Mobile",
    "sg:classifiers":[
        {
            "category":"Wholesale",
            "subcategory":"Vending Machines",
            "type":"Manufacturing & Wholesale Goods"
        }
    ],
    "sg:phone":"+1 251 649 3559",
    "sg:postcode":"36618",
    "sg:province":"AL",
    "sg:tags":[
        "operator"
    ],
    "wof:name":"Rowell Vending Inc",
    "wof:placetype":"venue"
},
  "geometry": {"coordinates":[-88.21395,30.757179],"type":"Point"}
}