{
  "type": "Feature",
  "properties": {
    "iso:country":"US",
    "sg:address":"803 Willow Oak Dr",
    "sg:city":"Birmingham",
    "sg:classifiers":[
        {
            "category":"Professional",
            "subcategory":"Management & Consulting",
            "type":"Services"
        }
    ],
    "sg:phone":"+1 205 987 7482",
    "sg:postcode":"35244",
    "sg:province":"AL",
    "sg:tags":[
        "environmental",
        "consultant"
    ],
    "wof:name":"Gordon Environmental",
    "wof:placetype":"venue"
},
  "geometry": {"coordinates":[-86.803321,33.34974],"type":"Point"}
}