{
  "type": "Feature",
  "properties": {
    "iso:country":"US",
    "sg:address":"10426 US Hwy 278",
    "sg:city":"Holly Pond",
    "sg:classifiers":[
        {
            "category":"Retail",
            "subcategory":"Auto Repair",
            "type":"Services"
        }
    ],
    "sg:phone":"+1 256 796 3017",
    "sg:postcode":"35055",
    "sg:province":"AL",
    "sg:tags":[
        "repairing",
        "automotive",
        "automobile"
    ],
    "wof:name":"Rays Breaks & Alignment LLC",
    "wof:placetype":"venue"
},
  "geometry": {"coordinates":[-86.62384,34.174387],"type":"Point"}
}