{
  "type": "Feature",
  "properties": {
    "iso:country":"US",
    "sg:address":"3507 Sparkman Dr NW",
    "sg:city":"Huntsville",
    "sg:classifiers":[
        {
            "category":"Building & Trades",
            "subcategory":"Cleaning & Sanitation",
            "type":"Services"
        }
    ],
    "sg:phone":"+1 256 851 9045",
    "sg:postcode":"35810",
    "sg:province":"AL",
    "sg:tags":[
        "janitor"
    ],
    "wof:name":"Hampton & Hampton",
    "wof:placetype":"venue"
},
  "geometry": {"coordinates":[-86.61586,34.76011],"type":"Point"}
}