{
  "type": "Feature",
  "properties": {
    "addr:full":"165 Co Rd 4 Cottonton AL 36871",
    "addr:housenumber":"165",
    "addr:postcode":"36871",
    "addr:street":"Co Rd 4 Cottonton",
    "iso:country":"US",
    "sg:address":"165 Co Rd 4",
    "sg:city":"Cottonton",
    "sg:classifiers":[
        {
            "category":"Shopping",
            "subcategory":"Bicycles & Sporting Goods",
            "type":"Retail Goods"
        }
    ],
    "sg:phone":"+1 334 855 4635",
    "sg:postcode":"36871",
    "sg:province":"AL",
    "sg:tags":[
        "bait",
        "fishing"
    ],
    "wof:name":"Kite's Grocery & Bait Shop",
    "wof:placetype":"venue"
},
  "geometry": {"coordinates":[-85.183685,32.196145],"type":"Point"}
}