{
  "type": "Feature",
  "properties": {
    "addr:full":"1280 Westover Rd Harpersville AL 35147",
    "addr:housenumber":"1280",
    "addr:postcode":"35147",
    "addr:street":"Westover Rd",
    "iso:country":"US",
    "sg:address":"1280 Westover Rd",
    "sg:city":"Harpersville",
    "sg:classifiers":[
        {
            "category":"Manufacturing",
            "subcategory":"Glass & Minerals",
            "type":"Manufacturing & Wholesale Goods"
        }
    ],
    "sg:phone":"+1 205 678 2117",
    "sg:postcode":"35147",
    "sg:province":"AL",
    "sg:tags":[
        "ready",
        "concrete",
        "material",
        "building",
        "mfg"
    ],
    "wof:name":"Kirkpatrick Concrete Inc",
    "wof:placetype":"venue"
},
  "geometry": {"coordinates":[-86.510071,33.362043],"type":"Point"}
}