{
  "type": "Feature",
  "properties": {
    "iso:country":"US",
    "sg:address":"24744 US Hwy 31",
    "sg:city":"Jemison",
    "sg:classifiers":[
        {
            "category":"Shopping",
            "type":"Retail Goods"
        }
    ],
    "sg:phone":"+1 205 688 5222",
    "sg:postcode":"35085",
    "sg:province":"AL",
    "sg:tags":[
        "candle"
    ],
    "wof:name":"Alabaster Candle Supply Inc",
    "wof:placetype":"venue"
},
  "geometry": {"coordinates":[-86.744355,32.960837],"type":"Point"}
}