{
  "type": "Feature",
  "properties": {
    "iso:country":"US",
    "sg:address":"350 E Jeff Davis Ave",
    "sg:city":"Montgomery",
    "sg:classifiers":[
        {
            "category":"Professional",
            "subcategory":"Computer Services",
            "type":"Services"
        }
    ],
    "sg:phone":"+1 334 263 0529",
    "sg:postcode":"36104",
    "sg:province":"AL",
    "sg:tags":[
        "graphics"
    ],
    "wof:name":"Alabama Graphics & Engineering",
    "wof:placetype":"venue"
},
  "geometry": {"coordinates":[-86.303831,32.366314],"type":"Point"}
}