{
  "type": "Feature",
  "properties": {
    "iso:country":"US",
    "sg:address":"1989 Laurel Oak Ct",
    "sg:city":"Mobile",
    "sg:classifiers":[
        {
            "category":"Communications",
            "subcategory":"Film & Video Production",
            "type":"Services"
        },
        {
            "category":"Arts & Performance",
            "subcategory":"Theater",
            "type":"Entertainment"
        }
    ],
    "sg:phone":"+1 251 591 5449",
    "sg:postcode":"36695",
    "sg:province":"AL",
    "sg:tags":[
        "theatrical",
        "taping"
    ],
    "wof:name":"Beaken Productions Inc",
    "wof:placetype":"venue"
},
  "geometry": {"coordinates":[-88.24516,30.648755],"type":"Point"}
}