{
  "type": "Feature",
  "properties": {
    "addr:full":"10085 US Hwy 431 New Hope AL 35760",
    "addr:housenumber":"10085",
    "addr:postcode":"35760",
    "addr:street":"Us Hwy 431",
    "iso:country":"US",
    "sg:address":"10085 US Hwy 431",
    "sg:city":"New Hope",
    "sg:classifiers":[
        {
            "category":"Professional",
            "type":"Services"
        }
    ],
    "sg:phone":"+1 256 723 3515",
    "sg:postcode":"35760",
    "sg:province":"AL",
    "sg:tags":[
        "establishment"
    ],
    "wof:name":"Corner Auto Market",
    "wof:placetype":"venue"
},
  "geometry": {"coordinates":[-86.433958,34.551797],"type":"Point"}
}