{
  "type": "Feature",
  "properties": {
    "iso:country":"US",
    "sg:address":"8461 US Hwy 231",
    "sg:city":"Wetumpka",
    "sg:classifiers":[
        {
            "category":"Food & Beverages",
            "subcategory":"Groceries & Convenience Stores",
            "type":"Retail Goods"
        }
    ],
    "sg:phone":"+1 334 567 7630",
    "sg:postcode":"36092",
    "sg:province":"AL",
    "wof:name":"Conoco",
    "wof:placetype":"venue"
},
  "geometry": {"coordinates":[-86.19071,32.558873],"type":"Point"}
}