{
  "type": "Feature",
  "properties": {
    "iso:country":"US",
    "sg:address":"3498 Bel Air Mall",
    "sg:city":"Mobile",
    "sg:classifiers":[
        {
            "category":"Shopping",
            "subcategory":"Jewelry",
            "type":"Retail Goods"
        }
    ],
    "sg:phone":"+1 251 478 1046",
    "sg:postcode":"36606",
    "sg:province":"AL",
    "sg:tags":[
        "jeweler"
    ],
    "wof:name":"Silver Expressions",
    "wof:placetype":"venue"
},
  "geometry": {"coordinates":[-88.122272,30.670036],"type":"Point"}
}