{
  "type": "Feature",
  "properties": {
    "iso:country":"US",
    "sg:address":"13871 State Rte 216",
    "sg:city":"Cottondale",
    "sg:classifiers":[
        {
            "category":"Retail",
            "subcategory":"Auto Repair",
            "type":"Services"
        }
    ],
    "sg:phone":"+1 205 556 7050",
    "sg:postcode":"35453",
    "sg:province":"AL",
    "sg:tags":[
        "general"
    ],
    "wof:name":"Fleetwood Service Inc",
    "wof:placetype":"venue"
},
  "geometry": {"coordinates":[-87.397431,33.251132],"type":"Point"}
}