{
  "type": "Feature",
  "properties": {
    "iso:country":"US",
    "sg:address":"1615 Darby Dr",
    "sg:city":"Florence",
    "sg:classifiers":[
        {
            "category":"Personal",
            "type":"Services"
        },
        {
            "category":"Shopping",
            "subcategory":"Clothing, Apparel, & Fashions",
            "type":"Retail Goods"
        }
    ],
    "sg:phone":"+1 256 764 1981",
    "sg:postcode":"35630",
    "sg:province":"AL",
    "sg:tags":[
        "rent",
        "formal",
        "wear",
        "furnishing"
    ],
    "wof:name":"Burch & Hatfield Formal Shops",
    "wof:placetype":"venue"
},
  "geometry": {"coordinates":[-87.65679,34.819875],"type":"Point"}
}