{
  "type": "Feature",
  "properties": {
    "iso:country":"US",
    "sg:address":"121 W Ladiga St",
    "sg:city":"Piedmont",
    "sg:classifiers":[
        {
            "category":"Government",
            "subcategory":"Police Station",
            "type":"Public Place"
        }
    ],
    "sg:phone":"+1 256 447 9091",
    "sg:postcode":"36272",
    "sg:province":"AL",
    "sg:tags":[
        "department"
    ],
    "wof:name":"Piedmont Police Dept",
    "wof:placetype":"venue"
},
  "geometry": {"coordinates":[-85.611726,33.923232],"type":"Point"}
}