{
  "type": "Feature",
  "properties": {
    "iso:country":"US",
    "sg:address":"203 Linden St",
    "sg:city":"Trussville",
    "sg:classifiers":[
        {
            "category":"Organizations",
            "subcategory":"Religious Organization",
            "type":"Services"
        }
    ],
    "sg:phone":"+1 205 655 0992",
    "sg:postcode":"35173",
    "sg:province":"AL",
    "wof:name":"Trussville Community Church",
    "wof:placetype":"venue"
},
  "geometry": {"coordinates":[-86.612713,33.619862],"type":"Point"}
}