{
  "type": "Feature",
  "properties": {
    "iso:country":"US",
    "sg:address":"152 Limerick Ct",
    "sg:city":"Muscle Shoals",
    "sg:classifiers":[
        {
            "category":"Professional",
            "subcategory":"Lawyer & Legal Services",
            "type":"Services"
        }
    ],
    "sg:phone":"+1 256 446 5632",
    "sg:postcode":"35661",
    "sg:province":"AL",
    "sg:tags":[
        "attorney"
    ],
    "wof:name":"Steve Graham",
    "wof:placetype":"venue"
},
  "geometry": {"coordinates":[-87.556804,34.805846],"type":"Point"}
}