{
  "type": "Feature",
  "properties": {
    "iso:country":"US",
    "sg:address":"9034 Memorial Pkwy SW",
    "sg:city":"Huntsville",
    "sg:classifiers":[
        {
            "category":"Personal",
            "subcategory":"Barber",
            "type":"Services"
        }
    ],
    "sg:phone":"+1 256 881 9878",
    "sg:postcode":"35802",
    "sg:province":"AL",
    "wof:name":"Haysland Square Barber Shop",
    "wof:placetype":"venue"
},
  "geometry": {"coordinates":[-86.567072,34.649407],"type":"Point"}
}