{
  "type": "Feature",
  "properties": {
    "iso:country":"US",
    "sg:address":"15314 State Rte 14",
    "sg:city":"Sawyerville",
    "sg:classifiers":[
        {
            "category":"Restaurant",
            "type":"Food & Drink"
        }
    ],
    "sg:phone":"+1 334 624 1205",
    "sg:postcode":"36776",
    "sg:province":"AL",
    "wof:name":"Small's Country Kitchen",
    "wof:placetype":"venue"
},
  "geometry": {"coordinates":[-87.695431,32.741552],"type":"Point"}
}