{
  "type": "Feature",
  "properties": {
    "iso:country":"US",
    "sg:address":"2625 3rd St NW",
    "sg:city":"Birmingham",
    "sg:classifiers":[
        {
            "category":"Building & Trades",
            "subcategory":"Plumbing",
            "type":"Services"
        }
    ],
    "sg:phone":"+1 205 856 9540",
    "sg:postcode":"35215",
    "sg:province":"AL",
    "sg:tags":[
        "contractor"
    ],
    "wof:name":"Four Seasons Heating & Air",
    "wof:placetype":"venue"
},
  "geometry": {"coordinates":[-86.692813,33.654971],"type":"Point"}
}