{
  "type": "Feature",
  "properties": {
    "iso:country":"US",
    "sg:address":"2108 Rainbow Dr",
    "sg:city":"Gadsden",
    "sg:classifiers":[
        {
            "category":"Health Services",
            "subcategory":"Doctor",
            "type":"Services"
        }
    ],
    "sg:phone":"+1 256 547 0160",
    "sg:postcode":"35901",
    "sg:province":"AL",
    "sg:tags":[
        "clinic"
    ],
    "wof:name":"Doctors Medcare",
    "wof:placetype":"venue"
},
  "geometry": {"coordinates":[-86.018092,33.97277],"type":"Point"}
}