{
  "type": "Feature",
  "properties": {
    "addr:full":"5008 State Rte 51 Opelika AL 36804",
    "addr:housenumber":"5008",
    "addr:postcode":"36804",
    "addr:street":"State Rte 51 Opelika",
    "iso:country":"US",
    "sg:address":"5008 State Rte 51",
    "sg:city":"Opelika",
    "sg:classifiers":[
        {
            "category":"Freight",
            "type":"Transportation"
        }
    ],
    "sg:phone":"+1 334 705 0073",
    "sg:postcode":"36804",
    "sg:province":"AL",
    "sg:tags":[
        "commercial",
        "storage"
    ],
    "wof:name":"Community Self Storage LLC",
    "wof:placetype":"venue"
},
  "geometry": {"coordinates":[-85.370704,32.585655],"type":"Point"}
}