{
  "type": "Feature",
  "properties": {
    "addr:full":"101 2nd Ave N Clanton AL 35045",
    "addr:housenumber":"101",
    "addr:postcode":"35045",
    "addr:street":"2Nd Ave N",
    "iso:country":"US",
    "sg:address":"101 2nd Ave N",
    "sg:city":"Clanton",
    "sg:classifiers":[
        {
            "category":"Building & Trades",
            "subcategory":"Construction",
            "type":"Services"
        }
    ],
    "sg:phone":"+1 205 755 5932",
    "sg:postcode":"35045",
    "sg:province":"AL",
    "sg:tags":[
        "excavation",
        "contractor"
    ],
    "wof:name":"Gene Dennis Excavating",
    "wof:placetype":"venue"
},
  "geometry": {"coordinates":[-86.62488999999999,32.841761],"type":"Point"}
}