{
  "type": "Feature",
  "properties": {
    "addr:full":"5701 Atlanta Hwy Montgomery AL 36117",
    "addr:housenumber":"5701",
    "addr:postcode":"36117",
    "addr:street":"Atlanta Hwy",
    "iso:country":"US",
    "sg:address":"5701 Atlanta Hwy",
    "sg:city":"Montgomery",
    "sg:classifiers":[
        {
            "category":"Retail",
            "subcategory":"Auto Repair",
            "type":"Services"
        }
    ],
    "sg:phone":"+1 334 271 7187",
    "sg:postcode":"36117",
    "sg:province":"AL",
    "sg:tags":[
        "automobile",
        "lubrication"
    ],
    "wof:name":"American Lube Fast",
    "wof:placetype":"venue"
},
  "geometry": {"coordinates":[-86.20223,32.38214],"type":"Point"}
}