{
  "type": "Feature",
  "properties": {
    "addr:full":"1668 Montgomery Hwy Birmingham AL 35216",
    "addr:housenumber":"1668",
    "addr:postcode":"35216",
    "addr:street":"Montgomery Hwy",
    "iso:country":"US",
    "sg:address":"1668 Montgomery Hwy",
    "sg:city":"Birmingham",
    "sg:classifiers":[
        {
            "category":"Shopping",
            "subcategory":"Department Store",
            "type":"Retail Goods"
        }
    ],
    "sg:phone":"+1 205 822 8281",
    "sg:postcode":"35216",
    "sg:province":"AL",
    "sg:tags":[
        "shop"
    ],
    "wof:name":"Deals Nothing Over A Dollar",
    "wof:placetype":"venue"
},
  "geometry": {"coordinates":[-86.806449,33.39273],"type":"Point"}
}