{
  "type": "Feature",
  "properties": {
    "addr:full":"1132 Penfield Dr Birmingham AL 35217",
    "addr:housenumber":"1132",
    "addr:postcode":"35217",
    "addr:street":"Penfield Dr",
    "iso:country":"US",
    "sg:address":"1132 Penfield Dr",
    "sg:city":"Birmingham",
    "sg:classifiers":[
        {
            "category":"Building & Trades",
            "subcategory":"Construction",
            "type":"Services"
        }
    ],
    "sg:phone":"+1 205 836 5510",
    "sg:postcode":"35217",
    "sg:province":"AL",
    "sg:tags":[
        "heavy"
    ],
    "wof:name":"Naylors Bushhogging",
    "wof:placetype":"venue"
},
  "geometry": {"coordinates":[-86.732321,33.592353],"type":"Point"}
}