{
  "type": "Feature",
  "properties": {
    "addr:full":"801 Commercial St SE Hanceville AL 35077",
    "addr:housenumber":"801",
    "addr:postcode":"35077",
    "addr:street":"Commercial St Se",
    "iso:country":"US",
    "sg:address":"801 Commercial St SE",
    "sg:city":"Hanceville",
    "sg:classifiers":[
        {
            "category":"Government",
            "subcategory":"Office",
            "type":"Public Place"
        }
    ],
    "sg:phone":"+1 256 352 6430",
    "sg:postcode":"35077",
    "sg:province":"AL",
    "sg:tags":[
        "village"
    ],
    "wof:name":"Hanceville Agri-Business",
    "wof:placetype":"venue"
},
  "geometry": {"coordinates":[-86.760188,34.06169],"type":"Point"}
}