{
  "type": "Feature",
  "properties": {
    "iso:country":"US",
    "sg:address":"1120 Pleasant Grove Rd",
    "sg:city":"Pleasant Grove",
    "sg:classifiers":[
        {
            "category":"Organizations",
            "subcategory":"Religious Organization",
            "type":"Services"
        }
    ],
    "sg:phone":"+1 205 744 8521",
    "sg:postcode":"35127",
    "sg:province":"AL",
    "sg:tags":[
        "church"
    ],
    "sg:website":"www.cottagehillbaptist.org",
    "wof:name":"Cottage Hill Baptist Church",
    "wof:placetype":"venue"
},
  "geometry": {"coordinates":[-86.960211,33.48275],"type":"Point"}
}