{
  "type": "Feature",
  "properties": {
    "iso:country":"US",
    "sg:address":"1555 Hartman Industrial Blvd",
    "sg:city":"Birmingham",
    "sg:classifiers":[
        {
            "category":"Manufacturing",
            "subcategory":"Glass & Minerals",
            "type":"Manufacturing & Wholesale Goods"
        }
    ],
    "sg:phone":"+1 205 925 5625",
    "sg:postcode":"35221",
    "sg:province":"AL",
    "sg:tags":[
        "hydraulic",
        "cement",
        "mfg"
    ],
    "wof:name":"Holcim Usa Inc",
    "wof:placetype":"venue"
},
  "geometry": {"coordinates":[-86.902558,33.457846],"type":"Point"}
}