{
  "type": "Feature",
  "properties": {
    "addr:full":"65 Strickland Dr Woodstock AL 35188",
    "addr:housenumber":"65",
    "addr:postcode":"35188",
    "addr:street":"Strickland Dr",
    "iso:country":"US",
    "sg:address":"65 Strickland Dr",
    "sg:city":"Woodstock",
    "sg:classifiers":[
        {
            "category":"Retail",
            "subcategory":"Funeral Services",
            "type":"Services"
        }
    ],
    "sg:phone":"+1 205 938 1001",
    "sg:postcode":"35188",
    "sg:province":"AL",
    "sg:tags":[
        "director"
    ],
    "wof:name":"Patterson Funeral Hm Woodstock",
    "wof:placetype":"venue"
},
  "geometry": {"coordinates":[-87.14909,33.206955],"type":"Point"}
}