{
  "type": "Feature",
  "properties": {
    "iso:country":"US",
    "sg:address":"5915 Carmichael Rd",
    "sg:city":"Montgomery",
    "sg:classifiers":[
        {
            "category":"Insurance",
            "subcategory":"Insurance Agent",
            "type":"Services"
        }
    ],
    "sg:phone":"+1 334 279 0323",
    "sg:postcode":"36117",
    "sg:province":"AL",
    "wof:name":"Auto Owners Inc",
    "wof:placetype":"venue"
},
  "geometry": {"coordinates":[-86.204469,32.359968],"type":"Point"}
}