{
  "type": "Feature",
  "properties": {
    "iso:country":"US",
    "sg:address":"10902 Covered Bridge Rd",
    "sg:city":"Brookwood",
    "sg:classifiers":[
        {
            "category":"Restaurant",
            "type":"Food & Drink"
        }
    ],
    "sg:menulink":"http://www.allmenus.com/al/coaling-vance/120841-subway/menu/",
    "sg:phone":"+1 205 556 5445",
    "sg:postcode":"35444",
    "sg:province":"AL",
    "sg:tags":[
        "american",
        "sandwich"
    ],
    "wof:name":"Subway",
    "wof:placetype":"venue"
},
  "geometry": {"coordinates":[-87.29783999999999,33.198948],"type":"Point"}
}