{
  "type": "Feature",
  "properties": {
    "addr:full":"625 Anderson Rd Montgomery AL 36110",
    "addr:housenumber":"625",
    "addr:postcode":"36110",
    "addr:street":"Anderson Rd",
    "iso:country":"US",
    "sg:address":"625 Anderson Rd",
    "sg:city":"Montgomery",
    "sg:classifiers":[
        {
            "category":"Building & Trades",
            "subcategory":"Construction",
            "type":"Services"
        }
    ],
    "sg:phone":"+1 334 286 8350",
    "sg:postcode":"36110",
    "sg:province":"AL",
    "sg:tags":[
        "marking",
        "maintenance",
        "parking"
    ],
    "wof:name":"A-Plus Sealcoating & Striping",
    "wof:placetype":"venue"
},
  "geometry": {"coordinates":[-86.22898499999999,32.45458],"type":"Point"}
}