{
  "type": "Feature",
  "properties": {
    "iso:country":"US",
    "sg:address":"186 N Midway St",
    "sg:city":"Clayton",
    "sg:classifiers":[
        {
            "category":"Wholesale",
            "subcategory":"Machinery & Supplies",
            "type":"Manufacturing & Wholesale Goods"
        }
    ],
    "sg:phone":"+1 334 775 1504",
    "sg:postcode":"36016",
    "sg:province":"AL",
    "sg:tags":[
        "salon",
        "beauty"
    ],
    "wof:name":"Nu Styles",
    "wof:placetype":"venue"
},
  "geometry": {"coordinates":[-85.457701,31.884376],"type":"Point"}
}