{
  "type": "Feature",
  "properties": {
    "addr:full":"1200 14th St Phenix City AL 36867",
    "addr:housenumber":"1200",
    "addr:postcode":"36867",
    "addr:street":"14Th St Phenix",
    "iso:country":"US",
    "sg:address":"1200 14th St",
    "sg:city":"Phenix City",
    "sg:classifiers":[
        {
            "category":"Shopping",
            "type":"Retail Goods"
        }
    ],
    "sg:phone":"+1 334 297 3535",
    "sg:postcode":"36867",
    "sg:province":"AL",
    "sg:tags":[
        "plaque"
    ],
    "wof:name":"Trophy Hut",
    "wof:placetype":"venue"
},
  "geometry": {"coordinates":[-85.009528,32.472609],"type":"Point"}
}