{
  "type": "Feature",
  "properties": {
    "iso:country":"US",
    "sg:address":"317 E Glenwood Dr",
    "sg:city":"Birmingham",
    "sg:phone":"+1 205 870 5160",
    "sg:postcode":"35209",
    "sg:province":"AL",
    "sg:tags":[
        "product",
        "petroleum"
    ],
    "wof:name":"Cherokee Aviation Inc",
    "wof:placetype":"venue"
},
  "geometry": {"coordinates":[-86.799245,33.469672],"type":"Point"}
}