{
  "type": "Feature",
  "properties": {
    "addr:full":"4100 State Rte 14 Millbrook AL 36054",
    "addr:housenumber":"4100",
    "addr:postcode":"36054",
    "addr:street":"State Rte 14",
    "iso:country":"US",
    "sg:address":"4100 State Rte 14",
    "sg:city":"Millbrook",
    "sg:classifiers":[
        {
            "category":"Recreation",
            "type":"Entertainment"
        }
    ],
    "sg:phone":"+1 334 285 9992",
    "sg:postcode":"36054",
    "sg:province":"AL",
    "sg:tags":[
        "martial",
        "arts",
        "instruction"
    ],
    "wof:name":"Chung's Taekwondo Ctr",
    "wof:placetype":"venue"
},
  "geometry": {"coordinates":[-86.366348,32.521346],"type":"Point"}
}