{
  "type": "Feature",
  "properties": {
    "addr:full":"430 Heatherwood Forest Cir Birmingham AL 35244",
    "addr:housenumber":"430",
    "addr:postcode":"35244",
    "addr:street":"Heatherwood Forest Cir",
    "iso:country":"US",
    "sg:address":"430 Heatherwood Forest Cir",
    "sg:city":"Birmingham",
    "sg:classifiers":[
        {
            "category":"Building & Trades",
            "subcategory":"Plumbing",
            "type":"Services"
        }
    ],
    "sg:phone":"+1 205 981 6640",
    "sg:postcode":"35244",
    "sg:province":"AL",
    "sg:tags":[
        "contractor"
    ],
    "wof:name":"Plb Investments LLC",
    "wof:placetype":"venue"
},
  "geometry": {"coordinates":[-86.750513,33.388318],"type":"Point"}
}