{
  "type": "Feature",
  "properties": {
    "iso:country":"US",
    "sg:address":"675 US Hwy 72",
    "sg:city":"Cherokee",
    "sg:classifiers":[
        {
            "category":"Food & Beverages",
            "subcategory":"Specialty",
            "type":"Retail Goods"
        },
        {
            "category":"Food & Beverages",
            "subcategory":"Liquor & Beverages",
            "type":"Retail Goods"
        }
    ],
    "sg:phone":"+1 256 360 2349",
    "sg:postcode":"35616",
    "sg:province":"AL",
    "wof:name":"B & B Beverages",
    "wof:placetype":"venue"
},
  "geometry": {"coordinates":[-87.69327,34.716422],"type":"Point"}
}