{
  "type": "Feature",
  "properties": {
    "iso:country":"US",
    "sg:address":"220 Moulton St E",
    "sg:city":"Decatur",
    "sg:classifiers":[
        {
            "category":"Shopping",
            "subcategory":"Used Merchandise",
            "type":"Retail Goods"
        }
    ],
    "sg:phone":"+1 256 353 8900",
    "sg:postcode":"35601",
    "sg:province":"AL",
    "sg:tags":[
        "repair",
        "electrical"
    ],
    "wof:name":"Decatur Lamp Co",
    "wof:placetype":"venue"
},
  "geometry": {"coordinates":[-86.982823,34.603979],"type":"Point"}
}