{
  "type": "Feature",
  "properties": {
    "addr:full":"132 Wind Rush Rd Huntsville AL 35811",
    "addr:housenumber":"132",
    "addr:postcode":"35811",
    "addr:street":"Wind Rush Rd",
    "iso:country":"US",
    "sg:address":"132 Wind Rush Rd",
    "sg:city":"Huntsville",
    "sg:classifiers":[
        {
            "category":"Arts & Performance",
            "subcategory":"Theater",
            "type":"Entertainment"
        }
    ],
    "sg:phone":"+1 256 851 0798",
    "sg:postcode":"35811",
    "sg:province":"AL",
    "sg:tags":[
        "group"
    ],
    "wof:name":"Delmore Brothers Music",
    "wof:placetype":"venue"
},
  "geometry": {"coordinates":[-86.506507,34.805698],"type":"Point"}
}