{
  "type": "Feature",
  "properties": {
    "iso:country":"US",
    "sg:address":"305 Oak Trce",
    "sg:city":"Birmingham",
    "sg:classifiers":[
        {
            "category":"Professional",
            "subcategory":"Accounting & Tax Preparation",
            "type":"Services"
        }
    ],
    "sg:phone":"+1 205 988 8258",
    "sg:postcode":"35244",
    "sg:province":"AL",
    "wof:name":"Kennedy CPA P C",
    "wof:placetype":"venue"
},
  "geometry": {"coordinates":[-86.845366,33.344584],"type":"Point"}
}