{
  "type": "Feature",
  "properties": {
    "iso:country":"US",
    "sg:address":"426 Co Rd 5",
    "sg:city":"Bremen",
    "sg:classifiers":[
        {
            "category":"Professional",
            "subcategory":"Management & Consulting",
            "type":"Services"
        }
    ],
    "sg:phone":"+1 256 287 0035",
    "sg:postcode":"35033",
    "sg:province":"AL",
    "wof:name":"Fast Track Marketing LLC",
    "wof:placetype":"venue"
},
  "geometry": {"coordinates":[-86.971242,33.897761],"type":"Point"}
}