{
  "type": "Feature",
  "properties": {
    "iso:country":"US",
    "sg:address":"2091 Blackshear Dr",
    "sg:city":"Montgomery",
    "sg:classifiers":[
        {
            "category":"Manufacturing",
            "subcategory":"Glass & Minerals",
            "type":"Manufacturing & Wholesale Goods"
        }
    ],
    "sg:phone":"+1 334 265 7788",
    "sg:postcode":"36108",
    "sg:province":"AL",
    "sg:tags":[
        "ready",
        "concrete",
        "mfg"
    ],
    "wof:name":"Tuskegee Ready Mix Inc",
    "wof:placetype":"venue"
},
  "geometry": {"coordinates":[-86.34881900000001,32.362344],"type":"Point"}
}