{
  "type": "Feature",
  "properties": {
    "iso:country":"US",
    "sg:address":"6680 Zeigler Blvd",
    "sg:city":"Mobile",
    "sg:classifiers":[
        {
            "category":"Home & Garden",
            "subcategory":"Household Appliances",
            "type":"Retail Goods"
        }
    ],
    "sg:phone":"+1 251 316 0055",
    "sg:postcode":"36608",
    "sg:province":"AL",
    "sg:tags":[
        "pump"
    ],
    "wof:name":"Thompson Pump & Mfg",
    "wof:placetype":"venue"
},
  "geometry": {"coordinates":[-88.19765599999999,30.708709],"type":"Point"}
}