{
  "type": "Feature",
  "properties": {
    "iso:country":"US",
    "sg:address":"3500 West Blvd",
    "sg:city":"Montgomery",
    "sg:classifiers":[
        {
            "category":"Wholesale",
            "subcategory":"Poultry",
            "type":"Manufacturing & Wholesale Goods"
        }
    ],
    "sg:phone":"+1 334 281 0400",
    "sg:postcode":"36108",
    "sg:province":"AL",
    "wof:name":"Sylvest Farms UPS",
    "wof:placetype":"venue"
},
  "geometry": {"coordinates":[-86.353839,32.330798],"type":"Point"}
}