{
  "type": "Feature",
  "properties": {
    "addr:full":"300 N Lawrence St Montgomery AL 36104",
    "addr:housenumber":"300",
    "addr:postcode":"36104",
    "addr:street":"N Lawrence St",
    "iso:country":"US",
    "sg:address":"300 N Lawrence St",
    "sg:city":"Montgomery",
    "sg:classifiers":[
        {
            "category":"Professional",
            "subcategory":"Lawyer & Legal Services",
            "type":"Services"
        }
    ],
    "sg:phone":"+1 334 264 6664",
    "sg:postcode":"36104",
    "sg:province":"AL",
    "sg:tags":[
        "attorney"
    ],
    "wof:name":"Thomas D Simon",
    "wof:placetype":"venue"
},
  "geometry": {"coordinates":[-86.30643499999999,32.382059],"type":"Point"}
}