{
  "type": "Feature",
  "properties": {
    "iso:country":"US",
    "sg:address":"569 S Main St",
    "sg:city":"Wetumpka",
    "sg:classifiers":[
        {
            "category":"Restaurant",
            "type":"Food & Drink"
        }
    ],
    "sg:menulink":"http://www.allmenus.com/al/wetumpka/154263-hardees/menu/",
    "sg:phone":"+1 334 567 7035",
    "sg:postcode":"36092",
    "sg:province":"AL",
    "sg:tags":[
        "burger",
        "american"
    ],
    "wof:name":"Hardee's",
    "wof:placetype":"venue"
},
  "geometry": {"coordinates":[-86.206957,32.528856],"type":"Point"}
}