{
  "type": "Feature",
  "properties": {
    "iso:country":"US",
    "sg:address":"103 S Commerce St",
    "sg:city":"Geneva",
    "sg:classifiers":[
        {
            "category":"Manufacturing",
            "subcategory":"Paper Products",
            "type":"Manufacturing & Wholesale Goods"
        }
    ],
    "sg:phone":"+1 334 684 7130",
    "sg:postcode":"36340",
    "sg:province":"AL",
    "sg:tags":[
        "pulp"
    ],
    "wof:name":"J F Spann Timber Inc",
    "wof:placetype":"venue"
},
  "geometry": {"coordinates":[-85.866216,31.039522],"type":"Point"}
}