{
  "type": "Feature",
  "properties": {
    "iso:country":"US",
    "sg:address":"105 8th Pl",
    "sg:city":"Pleasant Grove",
    "sg:classifiers":[
        {
            "category":"Food & Beverages",
            "subcategory":"Fruits & Vegetables",
            "type":"Retail Goods"
        }
    ],
    "sg:phone":"+1 205 322 6256",
    "sg:postcode":"35127",
    "sg:province":"AL",
    "wof:name":"Tommy Tucker Produce",
    "wof:placetype":"venue"
},
  "geometry": {"coordinates":[-86.959117,33.487753],"type":"Point"}
}