{
  "type": "Feature",
  "properties": {
    "iso:country":"US",
    "sg:address":"272 Co Rd 700",
    "sg:city":"Cullman",
    "sg:classifiers":[
        {
            "category":"Organizations",
            "subcategory":"Religious Organization",
            "type":"Services"
        }
    ],
    "sg:phone":"+1 256 736 5526",
    "sg:postcode":"35055",
    "sg:province":"AL",
    "wof:name":"White Grove Baptist Church",
    "wof:placetype":"venue"
},
  "geometry": {"coordinates":[-86.807447,34.14753],"type":"Point"}
}