{
  "type": "Feature",
  "properties": {
    "iso:country":"US",
    "sg:address":"1096 Co Rd 339",
    "sg:city":"Pisgah",
    "sg:classifiers":[
        {
            "category":"Personal",
            "subcategory":"Beauty Salon",
            "type":"Services"
        }
    ],
    "sg:phone":"+1 256 451 3038",
    "sg:postcode":"35765",
    "sg:province":"AL",
    "sg:tags":[
        "shop"
    ],
    "wof:name":"Mane Attraction",
    "wof:placetype":"venue"
},
  "geometry": {"coordinates":[-85.764923,34.723295],"type":"Point"}
}