{
  "type": "Feature",
  "properties": {
    "iso:country":"US",
    "sg:address":"5650 Old Pascagoula Rd",
    "sg:city":"Mobile",
    "sg:classifiers":[
        {
            "category":"Retail",
            "subcategory":"Auto Rental",
            "type":"Services"
        }
    ],
    "sg:phone":"+1 251 653 1639",
    "sg:postcode":"36619",
    "sg:province":"AL",
    "sg:tags":[
        "car"
    ],
    "wof:name":"Enterprise Rent-A-Car",
    "wof:placetype":"venue"
},
  "geometry": {"coordinates":[-88.177221,30.585457],"type":"Point"}
}