{
  "type": "Feature",
  "properties": {
    "addr:full":"1421 16th Ave S Birmingham AL 35205",
    "addr:housenumber":"1421",
    "addr:postcode":"35205",
    "addr:street":"16Th Ave S",
    "iso:country":"US",
    "sg:address":"1421 16th Ave S",
    "sg:city":"Birmingham",
    "sg:classifiers":[
        {
            "category":"Retail",
            "subcategory":"Portrait Studio",
            "type":"Services"
        }
    ],
    "sg:phone":"+1 205 933 7717",
    "sg:postcode":"35205",
    "sg:province":"AL",
    "sg:tags":[
        "photo"
    ],
    "wof:name":"K P Studio",
    "wof:placetype":"venue"
},
  "geometry": {"coordinates":[-86.801704,33.491483],"type":"Point"}
}