{
  "type": "Feature",
  "properties": {
    "iso:country":"US",
    "sg:address":"1511 Mc Nabb Dr SW",
    "sg:city":"Cullman",
    "sg:classifiers":[
        {
            "category":"Professional",
            "type":"Services"
        }
    ],
    "sg:phone":"+1 256 734 4200",
    "sg:postcode":"35055",
    "sg:province":"AL",
    "sg:tags":[
        "establishment"
    ],
    "wof:name":"Perkins Place",
    "wof:placetype":"venue"
},
  "geometry": {"coordinates":[-86.859025,34.17538],"type":"Point"}
}