{
  "type": "Feature",
  "properties": {
    "addr:full":"901 Glade Rd E Anniston AL 36206",
    "addr:housenumber":"901",
    "addr:postcode":"36206",
    "addr:street":"Glade Rd E",
    "iso:country":"US",
    "sg:address":"901 Glade Rd E",
    "sg:city":"Anniston",
    "sg:classifiers":[
        {
            "category":"Government",
            "subcategory":"Office",
            "type":"Public Place"
        }
    ],
    "sg:phone":"+1 256 820 3888",
    "sg:postcode":"36206",
    "sg:province":"AL",
    "sg:tags":[
        "village"
    ],
    "wof:name":"Anniston Batting Cages",
    "wof:placetype":"venue"
},
  "geometry": {"coordinates":[-85.828513,33.729474],"type":"Point"}
}