{
  "type": "Feature",
  "properties": {
    "iso:country":"US",
    "sg:address":"2401 10th St",
    "sg:city":"Phenix City",
    "sg:classifiers":[
        {
            "category":"Restaurant",
            "type":"Food & Drink"
        }
    ],
    "sg:menulink":"http://www.allmenus.com/al/phenix-city/94193-buffet-city/menu/",
    "sg:phone":"+1 334 291 3228",
    "sg:postcode":"36869",
    "sg:province":"AL",
    "sg:tags":[
        "asian",
        "chinese"
    ],
    "wof:name":"Buffet City",
    "wof:placetype":"venue"
},
  "geometry": {"coordinates":[-85.025541,32.464515],"type":"Point"}
}