{
  "type": "Feature",
  "properties": {
    "iso:country":"US",
    "sg:address":"2700 31st St",
    "sg:city":"Birmingham",
    "sg:classifiers":[
        {
            "category":"Organizations",
            "subcategory":"Religious Organization",
            "type":"Services"
        }
    ],
    "sg:phone":"+1 205 785 2144",
    "sg:postcode":"35208",
    "sg:province":"AL",
    "sg:tags":[
        "church"
    ],
    "wof:name":"Fairview United Methodist C",
    "wof:placetype":"venue"
},
  "geometry": {"coordinates":[-86.870932,33.501652],"type":"Point"}
}