{
  "type": "Feature",
  "properties": {
    "iso:country":"US",
    "sg:address":"2550 Redstone Rd SW",
    "sg:city":"Huntsville",
    "sg:classifiers":[
        {
            "category":"Organizations",
            "subcategory":"Religious Organization",
            "type":"Services"
        }
    ],
    "sg:phone":"+1 256 883 6616",
    "sg:postcode":"35803",
    "sg:province":"AL",
    "wof:name":"Abundant Life Church",
    "wof:placetype":"venue"
},
  "geometry": {"coordinates":[-86.578432,34.617577],"type":"Point"}
}