{
  "type": "Feature",
  "properties": {
    "addr:full":"1203 N Eufaula Ave Eufaula AL 36027",
    "addr:housenumber":"1203",
    "addr:postcode":"36027",
    "addr:street":"N Eufaula Ave",
    "iso:country":"US",
    "sg:address":"1203 N Eufaula Ave",
    "sg:city":"Eufaula",
    "sg:classifiers":[
        {
            "category":"Food & Beverages",
            "subcategory":"Groceries & Convenience Stores",
            "type":"Retail Goods"
        }
    ],
    "sg:phone":"+1 334 687 3200",
    "sg:postcode":"36027",
    "sg:province":"AL",
    "sg:tags":[
        "grocer"
    ],
    "wof:name":"Driftwood General Store",
    "wof:placetype":"venue"
},
  "geometry": {"coordinates":[-85.14786599999999,31.916946],"type":"Point"}
}