{
  "type": "Feature",
  "properties": {
    "addr:full":"1206 Kildare St NW Huntsville AL 35801",
    "addr:housenumber":"1206",
    "addr:postcode":"35801",
    "addr:street":"Kildare St Nw",
    "iso:country":"US",
    "sg:address":"1206 Kildare St NW",
    "sg:city":"Huntsville",
    "sg:classifiers":[
        {
            "category":"Building & Trades",
            "subcategory":"Construction",
            "type":"Services"
        }
    ],
    "sg:phone":"+1 256 536 3910",
    "sg:postcode":"35801",
    "sg:province":"AL",
    "sg:tags":[
        "hanging",
        "contractor"
    ],
    "wof:name":"Matthews Painting",
    "wof:placetype":"venue"
},
  "geometry": {"coordinates":[-86.584706,34.747798],"type":"Point"}
}