{
  "type": "Feature",
  "properties": {
    "iso:country":"US",
    "sg:address":"1735 E University Dr",
    "sg:city":"Auburn",
    "sg:classifiers":[
        {
            "category":"Health Services",
            "subcategory":"Chiropractor",
            "type":"Services"
        }
    ],
    "sg:phone":"+1 334 826 2225",
    "sg:postcode":"36830",
    "sg:province":"AL",
    "wof:name":"Auburn Chiropractic Associates",
    "wof:placetype":"venue"
},
  "geometry": {"coordinates":[-85.447745,32.621192],"type":"Point"}
}