{
  "type": "Feature",
  "properties": {
    "iso:country":"US",
    "sg:address":"2501 Oakwood Ave NW",
    "sg:city":"Huntsville",
    "sg:classifiers":[
        {
            "category":"Professional",
            "subcategory":"Business Services",
            "type":"Services"
        },
        {
            "category":"Shopping",
            "subcategory":"Crafts & Fabrics",
            "type":"Retail Goods"
        }
    ],
    "sg:phone":"+1 256 533 2912",
    "sg:postcode":"35810",
    "sg:province":"AL",
    "sg:tags":[
        "sewing"
    ],
    "wof:name":"Personalize It In Stitches",
    "wof:placetype":"venue"
},
  "geometry": {"coordinates":[-86.609166,34.749452],"type":"Point"}
}