{
  "type": "Feature",
  "properties": {
    "addr:full":"220 Thompson Blvd Chickasaw AL 36611",
    "addr:housenumber":"220",
    "addr:postcode":"36611",
    "addr:street":"Thompson Blvd",
    "iso:country":"US",
    "sg:address":"220 Thompson Blvd",
    "sg:city":"Chickasaw",
    "sg:classifiers":[
        {
            "category":"Building & Trades",
            "subcategory":"Plumbing",
            "type":"Services"
        }
    ],
    "sg:phone":"+1 251 456 9347",
    "sg:postcode":"36611",
    "sg:province":"AL",
    "sg:tags":[
        "plumbing",
        "contractor"
    ],
    "wof:name":"Eddins Plumbing Inc",
    "wof:placetype":"venue"
},
  "geometry": {"coordinates":[-88.08807299999999,30.763415],"type":"Point"}
}