{
  "type": "Feature",
  "properties": {
    "iso:country":"US",
    "sg:address":"19 Oak Ridge Dr",
    "sg:city":"Pelham",
    "sg:classifiers":[
        {
            "category":"Food & Beverages",
            "subcategory":"Groceries & Convenience Stores",
            "type":"Retail Goods"
        }
    ],
    "sg:phone":"+1 205 620 9514",
    "sg:postcode":"35124",
    "sg:province":"AL",
    "wof:name":"Soul Purpose Southbridge Deli",
    "wof:placetype":"venue"
},
  "geometry": {"coordinates":[-86.800383,33.305891],"type":"Point"}
}