{
  "type": "Feature",
  "properties": {
    "iso:country":"US",
    "sg:address":"2741 Gunter Park Dr W",
    "sg:city":"Montgomery",
    "sg:classifiers":[
        {
            "category":"Manufacturing",
            "subcategory":"Tools & Machinery",
            "type":"Manufacturing & Wholesale Goods"
        }
    ],
    "sg:phone":"+1 334 244 2800",
    "sg:postcode":"36109",
    "sg:province":"AL",
    "sg:tags":[
        "terminal",
        "peripheral",
        "computer",
        "mfg",
        "man"
    ],
    "wof:name":"Unisys Corporation",
    "wof:placetype":"venue"
},
  "geometry": {"coordinates":[-86.237444,32.406945],"type":"Point"}
}