{
  "type": "Feature",
  "properties": {
    "addr:full":"2124 Frederick Rd Opelika AL 36801",
    "addr:housenumber":"2124",
    "addr:postcode":"36801",
    "addr:street":"Frederick Rd",
    "iso:country":"US",
    "sg:address":"2124 Frederick Rd",
    "sg:city":"Opelika",
    "sg:classifiers":[
        {
            "category":"Wholesale",
            "subcategory":"Groceries",
            "type":"Manufacturing & Wholesale Goods"
        }
    ],
    "sg:phone":"+1 334 742 9901",
    "sg:postcode":"36801",
    "sg:province":"AL",
    "wof:name":"Frito-Lay",
    "wof:placetype":"venue"
},
  "geometry": {"coordinates":[-85.40862,32.62233],"type":"Point"}
}