{
  "type": "Feature",
  "properties": {
    "iso:country":"US",
    "sg:address":"3401 Whitestone Dr",
    "sg:city":"Semmes",
    "sg:classifiers":[
        {
            "category":"Retail",
            "subcategory":"Repair Shop",
            "type":"Services"
        }
    ],
    "sg:phone":"+1 251 649 3088",
    "sg:postcode":"36575",
    "sg:province":"AL",
    "sg:tags":[
        "water",
        "meter"
    ],
    "wof:name":"Herndon Reed Meter Repair",
    "wof:placetype":"venue"
},
  "geometry": {"coordinates":[-88.240683,30.763046],"type":"Point"}
}