{
  "type": "Feature",
  "properties": {
    "addr:full":"5010 Academy Ln Bessemer AL 35022",
    "addr:housenumber":"5010",
    "addr:postcode":"35022",
    "addr:street":"Academy Ln",
    "iso:country":"US",
    "sg:address":"5010 Academy Ln",
    "sg:city":"Bessemer",
    "sg:classifiers":[
        {
            "category":"Restaurant",
            "type":"Food & Drink"
        }
    ],
    "sg:menulink":"http://www.allmenus.com/al/birmingham/106492-waffle-house/menu/",
    "sg:phone":"+1 205 425 2734",
    "sg:postcode":"35022",
    "sg:province":"AL",
    "sg:tags":[
        "american"
    ],
    "wof:name":"Waffle House",
    "wof:placetype":"venue"
},
  "geometry": {"coordinates":[-87.00431500000001,33.366412],"type":"Point"}
}