{
  "type": "Feature",
  "properties": {
    "iso:country":"US",
    "sg:address":"111 4th Ave",
    "sg:city":"Lincoln",
    "sg:classifiers":[
        {
            "category":"Professional",
            "type":"Services"
        }
    ],
    "sg:phone":"+1 205 763 7470",
    "sg:postcode":"35096",
    "sg:province":"AL",
    "wof:name":"Bingham Shores Inc",
    "wof:placetype":"venue"
},
  "geometry": {"coordinates":[-86.114887,33.608638],"type":"Point"}
}