{
  "type": "Feature",
  "properties": {
    "iso:country":"US",
    "sg:address":"17 Burch Ave",
    "sg:city":"Stevenson",
    "sg:classifiers":[
        {
            "category":"Professional",
            "type":"Services"
        }
    ],
    "sg:phone":"+1 256 437 9553",
    "sg:postcode":"35772",
    "sg:province":"AL",
    "wof:name":"Garrett Goff",
    "wof:placetype":"venue"
},
  "geometry": {"coordinates":[-85.85477400000001,34.871939],"type":"Point"}
}