{
  "type": "Feature",
  "properties": {
    "iso:country":"US",
    "sg:address":"2232 7th St S",
    "sg:city":"Clanton",
    "sg:classifiers":[
        {
            "category":"Food & Beverages",
            "subcategory":"Fruits & Vegetables",
            "type":"Retail Goods"
        }
    ],
    "sg:phone":"+1 205 755 3433",
    "sg:postcode":"35046",
    "sg:province":"AL",
    "sg:tags":[
        "produce"
    ],
    "wof:name":"Todds Produce",
    "wof:placetype":"venue"
},
  "geometry": {"coordinates":[-86.577899,32.801557],"type":"Point"}
}