{
  "type": "Feature",
  "properties": {
    "iso:country":"US",
    "sg:address":"1161 Springfield Rd",
    "sg:city":"Vernon",
    "sg:classifiers":[
        {
            "category":"Freight",
            "type":"Transportation"
        }
    ],
    "sg:phone":"+1 205 695 8829",
    "sg:postcode":"35592",
    "sg:province":"AL",
    "sg:tags":[
        "operator",
        "local",
        "trucking"
    ],
    "wof:name":"Patrick Trucking LLC",
    "wof:placetype":"venue"
},
  "geometry": {"coordinates":[-88.13702,33.756764],"type":"Point"}
}