{
  "type": "Feature",
  "properties": {
    "iso:country":"US",
    "sg:address":"10181 Burgreen Rd",
    "sg:city":"Madison",
    "sg:classifiers":[
        {
            "category":"Building & Trades",
            "subcategory":"Landscaping Services",
            "type":"Services"
        }
    ],
    "sg:phone":"+1 256 772 9645",
    "sg:postcode":"35756",
    "sg:province":"AL",
    "sg:tags":[
        "landscape",
        "contractor"
    ],
    "wof:name":"B & J Landscaping",
    "wof:placetype":"venue"
},
  "geometry": {"coordinates":[-86.796774,34.702574],"type":"Point"}
}