{
  "type": "Feature",
  "properties": {
    "addr:full":"1425 Sunset Dr Guntersville AL 35976",
    "addr:housenumber":"1425",
    "addr:postcode":"35976",
    "addr:street":"Sunset Dr",
    "iso:country":"US",
    "sg:address":"1425 Sunset Dr",
    "sg:city":"Guntersville",
    "sg:classifiers":[
        {
            "category":"Banks & Credit Unions",
            "subcategory":"Bank",
            "type":"Services"
        }
    ],
    "sg:phone":"+1 256 582 9555",
    "sg:postcode":"35976",
    "sg:province":"AL",
    "sg:tags":[
        "loan"
    ],
    "wof:name":"Cash Today",
    "wof:placetype":"venue"
},
  "geometry": {"coordinates":[-86.31531200000001,34.353247],"type":"Point"}
}