{
  "type": "Feature",
  "properties": {
    "iso:country":"US",
    "sg:address":"106 Main St",
    "sg:city":"Selma",
    "sg:classifiers":[
        {
            "category":"Government",
            "subcategory":"Fire Station",
            "type":"Public Place"
        }
    ],
    "sg:phone":"+1 334 872 4600",
    "sg:postcode":"36701",
    "sg:province":"AL",
    "sg:tags":[
        "department",
        "protection"
    ],
    "wof:name":"Summerfield Volunteer Fire",
    "wof:placetype":"venue"
},
  "geometry": {"coordinates":[-87.042118,32.516027],"type":"Point"}
}