{
  "type": "Feature",
  "properties": {
    "iso:country":"US",
    "sg:address":"2031 Holtville Rd",
    "sg:city":"Wetumpka",
    "sg:classifiers":[
        {
            "category":"Insurance",
            "subcategory":"Insurance Agent",
            "type":"Services"
        }
    ],
    "sg:phone":"+1 334 514 3084",
    "sg:postcode":"36092",
    "sg:province":"AL",
    "wof:name":"Liberty National Insurance Co",
    "wof:placetype":"venue"
},
  "geometry": {"coordinates":[-86.226055,32.562132],"type":"Point"}
}