{
  "type": "Feature",
  "properties": {
    "iso:country":"US",
    "sg:address":"7047 Old Madison Pike NW",
    "sg:city":"Huntsville",
    "sg:classifiers":[
        {
            "category":"Health Services",
            "subcategory":"Clinic",
            "type":"Services"
        }
    ],
    "sg:phone":"+1 256 922 9919",
    "sg:postcode":"35806",
    "sg:province":"AL",
    "sg:tags":[
        "home",
        "agency",
        "employment",
        "care"
    ],
    "wof:name":"Amedisys Home Health Care",
    "wof:placetype":"venue"
},
  "geometry": {"coordinates":[-86.683188,34.713249],"type":"Point"}
}