{
  "type": "Feature",
  "properties": {
    "addr:full":"2006 Modaus Rd SW Decatur AL 35603",
    "addr:housenumber":"2006",
    "addr:postcode":"35603",
    "addr:street":"Modaus Rd Sw",
    "iso:country":"US",
    "sg:address":"2006 Modaus Rd SW",
    "sg:city":"Decatur",
    "sg:classifiers":[
        {
            "category":"Organizations",
            "subcategory":"Religious Organization",
            "type":"Services"
        }
    ],
    "sg:phone":"+1 256 350 6586",
    "sg:postcode":"35603",
    "sg:province":"AL",
    "sg:tags":[
        "church"
    ],
    "wof:name":"Church Of Jesus Christ Of Lds",
    "wof:placetype":"venue"
},
  "geometry": {"coordinates":[-87.018162,34.560627],"type":"Point"}
}