{
  "type": "Feature",
  "properties": {
    "iso:country":"US",
    "sg:address":"113 2nd Ave SE",
    "sg:city":"Decatur",
    "sg:classifiers":[
        {
            "category":"Health Services",
            "subcategory":"Health Practitioner",
            "type":"Services"
        }
    ],
    "sg:phone":"+1 256 350 1764",
    "sg:postcode":"35601",
    "sg:province":"AL",
    "sg:tags":[
        "therapist",
        "physical"
    ],
    "sg:website":"www.encorerehab.com",
    "wof:name":"Encore Rehab",
    "wof:placetype":"venue"
},
  "geometry": {"coordinates":[-86.985155,34.603009],"type":"Point"}
}