{
  "type": "Feature",
  "properties": {
    "iso:country":"US",
    "sg:address":"9 Weldon St",
    "sg:city":"Wilsonville",
    "sg:classifiers":[
        {
            "category":"Organizations",
            "subcategory":"Religious Organization",
            "type":"Services"
        }
    ],
    "sg:phone":"+1 205 669 0844",
    "sg:postcode":"35186",
    "sg:province":"AL",
    "wof:name":"Blessed Hope Bible Church",
    "wof:placetype":"venue"
},
  "geometry": {"coordinates":[-86.484635,33.236224],"type":"Point"}
}