{
  "type": "Feature",
  "properties": {
    "iso:country":"US",
    "sg:address":"5901 Crestwood Blvd",
    "sg:city":"Birmingham",
    "sg:classifiers":[
        {
            "category":"Organizations",
            "subcategory":"Religious Organization",
            "type":"Services"
        }
    ],
    "sg:phone":"+1 205 595 7842",
    "sg:postcode":"35212",
    "sg:province":"AL",
    "sg:tags":[
        "church"
    ],
    "wof:name":"Christian Crestwood Church",
    "wof:placetype":"venue"
},
  "geometry": {"coordinates":[-86.740052,33.530735],"type":"Point"}
}