{
  "type": "Feature",
  "properties": {
    "addr:full":"5901 Crestwood Blvd Birmingham AL 35212",
    "addr:housenumber":"5901",
    "addr:postcode":"35212",
    "addr:street":"Crestwood Blvd",
    "iso:country":"US",
    "sg:address":"5901 Crestwood Blvd",
    "sg:city":"Birmingham",
    "sg:classifiers":[
        {
            "category":"Organizations",
            "subcategory":"Religious Organization",
            "type":"Services"
        }
    ],
    "sg:phone":"+1 205 595 7842",
    "sg:postcode":"35212",
    "sg:province":"AL",
    "sg:tags":[
        "church"
    ],
    "wof:name":"Christian Crestwood Church",
    "wof:placetype":"venue"
},
  "geometry": {"coordinates":[-86.74005200000001,33.530735],"type":"Point"}
}