{
  "type": "Feature",
  "properties": {
    "iso:country":"US",
    "sg:address":"926 State Rte 123",
    "sg:city":"Hartford",
    "sg:classifiers":[
        {
            "category":"Manufacturing",
            "subcategory":"Textiles",
            "type":"Manufacturing & Wholesale Goods"
        }
    ],
    "sg:phone":"+1 334 588 0207",
    "sg:postcode":"36344",
    "sg:province":"AL",
    "sg:tags":[
        "processing",
        "cotton"
    ],
    "wof:name":"Brooks Cotton Co",
    "wof:placetype":"venue"
},
  "geometry": {"coordinates":[-85.67865500000001,31.114051],"type":"Point"}
}