{
  "type": "Feature",
  "properties": {
    "iso:country":"US",
    "sg:address":"1873 Highway 77",
    "sg:city":"Southside",
    "sg:classifiers":[
        {
            "category":"Restaurant",
            "type":"Food & Drink"
        }
    ],
    "sg:menulink":"http://www.allmenus.com/al/gadsden/55362-the-fisherman-restaurant/menu/",
    "sg:phone":"+1 256 442 5252",
    "sg:postcode":"35907",
    "sg:province":"AL",
    "sg:tags":[
        "american"
    ],
    "wof:name":"The Fisherman Restaurant",
    "wof:placetype":"venue"
},
  "geometry": {"coordinates":[-86.022538,33.925472],"type":"Point"}
}