{
  "type": "Feature",
  "properties": {
    "addr:full":"7105 Magnolia Springs Hwy Foley AL 36535",
    "addr:housenumber":"7105",
    "addr:postcode":"al 36535",
    "addr:street":"Magnolia Springs Hwy",
    "iso:country":"US",
    "sg:address":"7105 Magnolia Springs Hwy",
    "sg:city":"Foley",
    "sg:classifiers":[
        {
            "category":"Building & Trades",
            "subcategory":"Construction",
            "type":"Services"
        }
    ],
    "sg:phone":"+1 251 988 1202",
    "sg:postcode":"36535",
    "sg:province":"AL",
    "sg:tags":[
        "sandblasting"
    ],
    "wof:name":"Bowman Coatings",
    "wof:placetype":"venue"
},
  "geometry": {"coordinates":[-87.767976,30.331739],"type":"Point"}
}