{
  "type": "Feature",
  "properties": {
    "iso:country":"US",
    "sg:address":"405 S 7th Ave",
    "sg:city":"Hartford",
    "sg:classifiers":[
        {
            "category":"Freight",
            "type":"Transportation"
        }
    ],
    "sg:phone":"+1 334 588 0508",
    "sg:postcode":"36344",
    "sg:province":"AL",
    "wof:name":"Assurance Transport LLC",
    "wof:placetype":"venue"
},
  "geometry": {"coordinates":[-85.702395,31.099277],"type":"Point"}
}