{
  "type": "Feature",
  "properties": {
    "iso:country":"US",
    "sg:address":"413 Murray Rd",
    "sg:city":"Dothan",
    "sg:classifiers":[
        {
            "category":"Building & Trades",
            "subcategory":"Construction",
            "type":"Services"
        }
    ],
    "sg:phone":"+1 334 702 7541",
    "sg:postcode":"36303",
    "sg:province":"AL",
    "sg:tags":[
        "drywall",
        "contractor"
    ],
    "wof:name":"Redmond Drywall Inc",
    "wof:placetype":"venue"
},
  "geometry": {"coordinates":[-85.395983,31.256966],"type":"Point"}
}