{
  "type": "Feature",
  "properties": {
    "iso:country":"US",
    "sg:address":"1863 Coral Ln",
    "sg:city":"Montgomery",
    "sg:classifiers":[
        {
            "category":"Health Services",
            "subcategory":"Nursing And Care Facility",
            "type":"Services"
        }
    ],
    "sg:phone":"+1 334 284 6494",
    "sg:postcode":"36116",
    "sg:province":"AL",
    "sg:tags":[
        "skilled"
    ],
    "wof:name":"Thomas Manor",
    "wof:placetype":"venue"
},
  "geometry": {"coordinates":[-86.295815,32.317419],"type":"Point"}
}