{
  "type": "Feature",
  "properties": {
    "iso:country":"US",
    "sg:address":"25 W Oxmoor Rd",
    "sg:city":"Birmingham",
    "sg:classifiers":[
        {
            "category":"Manufacturing",
            "subcategory":"Glass & Minerals",
            "type":"Manufacturing & Wholesale Goods"
        }
    ],
    "sg:phone":"+1 205 945 1698",
    "sg:postcode":"35209",
    "sg:province":"AL",
    "sg:tags":[
        "plate",
        "window",
        "glass-auto"
    ],
    "sg:website":"http://www.dopm.uab.edu",
    "wof:name":"Southern Auto Glass Inc",
    "wof:placetype":"venue"
},
  "geometry": {"coordinates":[-86.84009399999999,33.457133],"type":"Point"}
}