{
  "type": "Feature",
  "properties": {
    "iso:country":"US",
    "sg:address":"328 5th Ave NW",
    "sg:city":"Attalla",
    "sg:classifiers":[
        {
            "category":"Wholesale",
            "subcategory":"Electrical",
            "type":"Manufacturing & Wholesale Goods"
        }
    ],
    "sg:phone":"+1 256 538 8826",
    "sg:postcode":"35954",
    "sg:province":"AL",
    "sg:tags":[
        "equipment"
    ],
    "wof:name":"Security Entrmt Tlecommunicatn",
    "wof:placetype":"venue"
},
  "geometry": {"coordinates":[-86.089036,34.022508],"type":"Point"}
}