{
  "type": "Feature",
  "properties": {
    "iso:country":"US",
    "sg:address":"586 Slaughter Rd",
    "sg:city":"Madison",
    "sg:classifiers":[
        {
            "category":"Organizations",
            "subcategory":"Religious Organization",
            "type":"Services"
        }
    ],
    "sg:phone":"+1 256 971 0420",
    "sg:postcode":"35758",
    "sg:province":"AL",
    "sg:tags":[
        "church"
    ],
    "wof:name":"Skyline ABA Baptist Church",
    "wof:placetype":"venue"
},
  "geometry": {"coordinates":[-86.706649,34.711159],"type":"Point"}
}