{
  "type": "Feature",
  "properties": {
    "iso:country":"US",
    "sg:address":"1874 Beltline Rd SW",
    "sg:city":"Decatur",
    "sg:classifiers":[
        {
            "category":"Health Services",
            "subcategory":"Doctor",
            "type":"Services"
        }
    ],
    "sg:phone":"+1 256 350 9700",
    "sg:postcode":"35601",
    "sg:province":"AL",
    "sg:tags":[
        "physician",
        "surgeon"
    ],
    "wof:name":"Manifold Ob-Gyn",
    "wof:placetype":"venue"
},
  "geometry": {"coordinates":[-87.01684,34.575904],"type":"Point"}
}