{
  "type": "Feature",
  "properties": {
    "iso:country":"US",
    "sg:address":"4549 Clearview Dr",
    "sg:city":"Mobile",
    "sg:classifiers":[
        {
            "category":"Autos & Motor Vehicles",
            "subcategory":"Boat Sales",
            "type":"Retail Goods"
        }
    ],
    "sg:phone":"+1 251 666 1152",
    "sg:postcode":"36619",
    "sg:province":"AL",
    "sg:tags":[
        "dealer",
        "sales"
    ],
    "wof:name":"Stauter Boat Works",
    "wof:placetype":"venue"
},
  "geometry": {"coordinates":[-88.229236,30.596452],"type":"Point"}
}