{
  "type": "Feature",
  "properties": {
    "iso:country":"US",
    "sg:address":"134 Corporate Way",
    "sg:city":"Pelham",
    "sg:classifiers":[
        {
            "category":"Building & Trades",
            "subcategory":"Construction",
            "type":"Services"
        }
    ],
    "sg:phone":"+1 205 621 0700",
    "sg:postcode":"35124",
    "sg:province":"AL",
    "sg:tags":[
        "contractor"
    ],
    "wof:name":"Classic Contractor Svc Inc",
    "wof:placetype":"venue"
},
  "geometry": {"coordinates":[-86.80291200000001,33.31382],"type":"Point"}
}