{
  "type": "Feature",
  "properties": {
    "addr:full":"2001 Woodward Ave Muscle Shoals AL 35661",
    "addr:housenumber":"2001",
    "addr:postcode":"35661",
    "addr:street":"Woodward Ave",
    "iso:country":"US",
    "sg:address":"2001 Woodward Ave",
    "sg:city":"Muscle Shoals",
    "sg:classifiers":[
        {
            "category":"Restaurant",
            "type":"Food & Drink"
        }
    ],
    "sg:phone":"+1 256 314 1113",
    "sg:postcode":"35661",
    "sg:province":"AL",
    "wof:name":"Arby's",
    "wof:placetype":"venue"
},
  "geometry": {"coordinates":[-87.66771799999999,34.742058],"type":"Point"}
}