{
  "type": "Feature",
  "properties": {
    "iso:country":"US",
    "sg:address":"711 Murray Rd",
    "sg:city":"Dothan",
    "sg:classifiers":[
        {
            "category":"Shopping",
            "type":"Retail Goods"
        }
    ],
    "sg:phone":"+1 334 793 3657",
    "sg:postcode":"36303",
    "sg:province":"AL",
    "sg:tags":[
        "trophy",
        "mfg",
        "specialty",
        "award",
        "medal",
        "merchandise"
    ],
    "wof:name":"Jackson Trophies & Awards Inc",
    "wof:placetype":"venue"
},
  "geometry": {"coordinates":[-85.401429,31.256957],"type":"Point"}
}