{
  "type": "Feature",
  "properties": {
    "iso:country":"US",
    "sg:address":"1102 US Hwy 231 Bus",
    "sg:city":"Dothan",
    "sg:classifiers":[
        {
            "category":"Autos & Motor Vehicles",
            "subcategory":"Automobile Sales",
            "type":"Retail Goods"
        }
    ],
    "sg:phone":"+1 334 673 1221",
    "sg:postcode":"36303",
    "sg:province":"AL",
    "sg:tags":[
        "car",
        "dealer"
    ],
    "wof:name":"Hughes Johnson Chrys-Jeep",
    "wof:placetype":"venue"
},
  "geometry": {"coordinates":[-85.399893,31.238432],"type":"Point"}
}