{
  "type": "Feature",
  "properties": {
    "iso:country":"US",
    "sg:address":"708 Green St",
    "sg:city":"Auburn",
    "sg:classifiers":[
        {
            "category":"Insurance",
            "subcategory":"Insurance Agent",
            "type":"Services"
        }
    ],
    "sg:phone":"+1 334 821 2553",
    "sg:postcode":"36830",
    "sg:province":"AL",
    "wof:name":"A C Huey Agency",
    "wof:placetype":"venue"
},
  "geometry": {"coordinates":[-85.459554,32.592139],"type":"Point"}
}