{
  "type": "Feature",
  "properties": {
    "iso:country":"US",
    "sg:address":"4505 Swallow Pl",
    "sg:city":"Birmingham",
    "sg:classifiers":[
        {
            "category":"Organizations",
            "subcategory":"Religious Organization",
            "type":"Services"
        }
    ],
    "sg:phone":"+1 205 957 6171",
    "sg:postcode":"35213",
    "sg:province":"AL",
    "wof:name":"Christian Public Service",
    "wof:placetype":"venue"
},
  "geometry": {"coordinates":[-86.7251,33.519841],"type":"Point"}
}