{
  "type": "Feature",
  "properties": {
    "addr:full":"135 W Oxmoor Rd Birmingham AL 35209",
    "addr:housenumber":"135",
    "addr:postcode":"35209",
    "addr:street":"W Oxmoor Rd",
    "iso:country":"US",
    "sg:address":"135 W Oxmoor Rd",
    "sg:city":"Birmingham",
    "sg:classifiers":[
        {
            "category":"Freight",
            "type":"Transportation"
        }
    ],
    "sg:phone":"+1 205 942 5333",
    "sg:postcode":"35209",
    "sg:province":"AL",
    "sg:tags":[
        "special"
    ],
    "wof:name":"Urbaco U S A",
    "wof:placetype":"venue"
},
  "geometry": {"coordinates":[-86.841082,33.444949],"type":"Point"}
}