{
  "type": "Feature",
  "properties": {
    "iso:country":"US",
    "sg:address":"380 Ingate Rd",
    "sg:city":"Centreville",
    "sg:classifiers":[
        {
            "category":"Freight",
            "type":"Transportation"
        }
    ],
    "sg:phone":"+1 205 926 6643",
    "sg:postcode":"35042",
    "sg:province":"AL",
    "sg:tags":[
        "operator",
        "local",
        "trucking"
    ],
    "wof:name":"McMillan Trucking Inc",
    "wof:placetype":"venue"
},
  "geometry": {"coordinates":[-87.18364200000001,32.956941],"type":"Point"}
}