{
  "type": "Feature",
  "properties": {
    "iso:country":"US",
    "sg:address":"657 W Claiborne St",
    "sg:city":"Monroeville",
    "sg:classifiers":[
        {
            "category":"Autos & Motor Vehicles",
            "subcategory":"Fuel & Gas Station",
            "type":"Retail Goods"
        }
    ],
    "sg:phone":"+1 251 743 3133",
    "sg:postcode":"36460",
    "sg:province":"AL",
    "sg:tags":[
        "gasoline",
        "product",
        "station",
        "petroleum"
    ],
    "wof:name":"Middleton Oil Co Inc",
    "wof:placetype":"venue"
},
  "geometry": {"coordinates":[-87.336165,31.52653],"type":"Point"}
}