{
  "type": "Feature",
  "properties": {
    "iso:country":"US",
    "sg:address":"1218 S Eufaula Ave",
    "sg:city":"Eufaula",
    "sg:classifiers":[
        {
            "category":"Utilities",
            "subcategory":"Mobile Phone",
            "type":"Services"
        }
    ],
    "sg:phone":"+1 334 687 9696",
    "sg:postcode":"36027",
    "sg:province":"AL",
    "sg:tags":[
        "telephone",
        "cellular"
    ],
    "wof:name":"Alltel Mobile",
    "wof:placetype":"venue"
},
  "geometry": {"coordinates":[-85.149846,31.877589],"type":"Point"}
}