{
  "type": "Feature",
  "properties": {
    "iso:country":"US",
    "sg:address":"959 Huffman Rd",
    "sg:city":"Birmingham",
    "sg:classifiers":[
        {
            "category":"Organizations",
            "subcategory":"Religious Organization",
            "type":"Services"
        }
    ],
    "sg:phone":"+1 205 833 2410",
    "sg:postcode":"35215",
    "sg:province":"AL",
    "wof:name":"Parkway Christian Academy",
    "wof:placetype":"venue"
},
  "geometry": {"coordinates":[-86.688862,33.604586],"type":"Point"}
}