{
  "type": "Feature",
  "properties": {
    "iso:country":"US",
    "sg:address":"11385 State Rte 20",
    "sg:city":"Florence",
    "sg:classifiers":[
        {
            "category":"Wholesale",
            "subcategory":"Auto Parts",
            "type":"Manufacturing & Wholesale Goods"
        }
    ],
    "sg:phone":"+1 256 718 0076",
    "sg:postcode":"35633",
    "sg:province":"AL",
    "sg:tags":[
        "used"
    ],
    "wof:name":"Central Auto Parts",
    "wof:placetype":"venue"
},
  "geometry": {"coordinates":[-87.806768,34.894239],"type":"Point"}
}