{
  "type": "Feature",
  "properties": {
    "iso:country":"US",
    "sg:address":"9350 Dauphin Island Pkwy",
    "sg:city":"Theodore",
    "sg:classifiers":[
        {
            "category":"Manufacturing",
            "subcategory":"Printing",
            "type":"Manufacturing & Wholesale Goods"
        }
    ],
    "sg:phone":"+1 251 408 0239",
    "sg:postcode":"36582",
    "sg:province":"AL",
    "sg:tags":[
        "book"
    ],
    "wof:name":"Genesis Communications In",
    "wof:placetype":"venue"
},
  "geometry": {"coordinates":[-88.110674,30.504053],"type":"Point"}
}