{
  "type": "Feature",
  "properties": {
    "iso:country":"US",
    "sg:address":"1931 Central Pkwy SW",
    "sg:city":"Decatur",
    "sg:classifiers":[
        {
            "category":"Organizations",
            "subcategory":"Professional Association",
            "type":"Services"
        }
    ],
    "sg:phone":"+1 256 350 9944",
    "sg:postcode":"35601",
    "sg:province":"AL",
    "wof:name":"Tvtc",
    "wof:placetype":"venue"
},
  "geometry": {"coordinates":[-86.985513,34.578055],"type":"Point"}
}