{
  "type": "Feature",
  "properties": {
    "iso:country":"US",
    "sg:address":"620 Vine St NW",
    "sg:city":"Decatur",
    "sg:classifiers":[
        {
            "category":"Organizations",
            "subcategory":"Religious Organization",
            "type":"Services"
        }
    ],
    "sg:phone":"+1 256 308 9883",
    "sg:postcode":"35601",
    "sg:province":"AL",
    "sg:tags":[
        "church"
    ],
    "wof:name":"United Christian Bible Church",
    "wof:placetype":"venue"
},
  "geometry": {"coordinates":[-86.992632,34.617176],"type":"Point"}
}