{
  "type": "Feature",
  "properties": {
    "iso:country":"US",
    "sg:address":"7608 52nd St",
    "sg:city":"Tuscaloosa",
    "sg:classifiers":[
        {
            "category":"Wholesale",
            "subcategory":"Vending Machines",
            "type":"Manufacturing & Wholesale Goods"
        }
    ],
    "sg:phone":"+1 205 886 4359",
    "sg:postcode":"35401",
    "sg:province":"AL",
    "sg:tags":[
        "operator"
    ],
    "wof:name":"Pick A Snack Vending",
    "wof:placetype":"venue"
},
  "geometry": {"coordinates":[-87.638727,33.168346],"type":"Point"}
}