{
  "type": "Feature",
  "properties": {
    "iso:country":"US",
    "sg:address":"2138 Co Rd 75",
    "sg:city":"Stevenson",
    "sg:classifiers":[
        {
            "category":"Building & Trades",
            "subcategory":"Construction",
            "type":"Services"
        }
    ],
    "sg:phone":"+1 256 259 1244",
    "sg:postcode":"35772",
    "sg:province":"AL",
    "sg:tags":[
        "downspouts",
        "gutter"
    ],
    "wof:name":"T J's Seamless Gutters",
    "wof:placetype":"venue"
},
  "geometry": {"coordinates":[-85.808159,34.904204],"type":"Point"}
}