{
  "type": "Feature",
  "properties": {
    "iso:country":"US",
    "sg:address":"1624 Upper Wetumpka Rd",
    "sg:city":"Montgomery",
    "sg:phone":"+1 334 265 4611",
    "sg:postcode":"36107",
    "sg:province":"AL",
    "sg:tags":[
        "product",
        "petroleum"
    ],
    "wof:name":"United Stop & Shop",
    "wof:placetype":"venue"
},
  "geometry": {"coordinates":[-86.285768,32.384506],"type":"Point"}
}