{
  "type": "Feature",
  "properties": {
    "iso:country":"US",
    "sg:address":"3049 Steele Station Road",
    "sg:city":"Rainbow City",
    "sg:classifiers":[
        {
            "category":"Professional",
            "subcategory":"Computer Services",
            "type":"Services"
        }
    ],
    "sg:phone":"+1 800 392 0864",
    "sg:postcode":"35906",
    "sg:province":"AL",
    "sg:tags":[
        "internet",
        "software",
        "development",
        "web",
        "design",
        "mobile",
        "application"
    ],
    "sg:website":"http://dynamictechinc.com",
    "wof:name":"Dynamic Technologies Inc",
    "wof:placetype":"venue"
},
  "geometry": {"coordinates":[-86.088509,33.963139],"type":"Point"}
}