{
  "type": "Feature",
  "properties": {
    "addr:full":"422 18th St S Birmingham AL 35294",
    "addr:housenumber":"422",
    "addr:postcode":"35294",
    "addr:street":"18Th St S",
    "iso:country":"US",
    "sg:address":"422 18th St S",
    "sg:city":"Birmingham",
    "sg:classifiers":[
        {
            "category":"Bars & Pubs",
            "type":"Food & Drink"
        }
    ],
    "sg:phone":"+1 205 786 3012",
    "sg:postcode":"35294",
    "sg:province":"AL",
    "sg:tags":[
        "bar"
    ],
    "wof:name":"Jamie O Six Lounge",
    "wof:placetype":"venue"
},
  "geometry": {"coordinates":[-86.804755,33.507429],"type":"Point"}
}