{
  "type": "Feature",
  "properties": {
    "addr:full":"1643 Hartford Hwy Dothan AL 36301",
    "addr:housenumber":"1643",
    "addr:postcode":"36301",
    "addr:street":"Hartford Hwy",
    "iso:country":"US",
    "sg:address":"1643 Hartford Hwy",
    "sg:city":"Dothan",
    "sg:classifiers":[
        {
            "category":"Real Estate",
            "subcategory":"Real Estate Agent",
            "type":"Services"
        }
    ],
    "sg:phone":"+1 334 673 2400",
    "sg:postcode":"36301",
    "sg:province":"AL",
    "wof:name":"Omega Realty",
    "wof:placetype":"venue"
},
  "geometry": {"coordinates":[-85.418753,31.211255],"type":"Point"}
}