{
  "type": "Feature",
  "properties": {
    "iso:country":"US",
    "sg:address":"1001 4th Ave N",
    "sg:city":"Clanton",
    "sg:classifiers":[
        {
            "category":"Professional",
            "subcategory":"Engineering",
            "type":"Services"
        }
    ],
    "sg:phone":"+1 205 755 0811",
    "sg:postcode":"35045",
    "sg:province":"AL",
    "sg:tags":[
        "engineer"
    ],
    "wof:name":"Day Wilburn Assoicates Inc",
    "wof:placetype":"venue"
},
  "geometry": {"coordinates":[-86.635728,32.839532],"type":"Point"}
}