{
  "type": "Feature",
  "properties": {
    "iso:country":"US",
    "sg:address":"80 Broken Arrow Cove",
    "sg:city":"Ohatchee",
    "sg:classifiers":[
        {
            "category":"Professional",
            "subcategory":"Business Services",
            "type":"Services"
        }
    ],
    "sg:phone":"+1 256 892 2828",
    "sg:postcode":"36271",
    "sg:province":"AL",
    "wof:name":"Clark Sales Co LLC",
    "wof:placetype":"venue"
},
  "geometry": {"coordinates":[-86.118271,33.708367],"type":"Point"}
}