{
  "type": "Feature",
  "properties": {
    "iso:country":"US",
    "sg:address":"246 S 5th St",
    "sg:city":"Gadsden",
    "sg:classifiers":[
        {
            "category":"Professional",
            "subcategory":"Lawyer & Legal Services",
            "type":"Services"
        }
    ],
    "sg:phone":"+1 256 543 3080",
    "sg:postcode":"35901",
    "sg:province":"AL",
    "sg:tags":[
        "attorney"
    ],
    "wof:name":"David K Mc Whorter",
    "wof:placetype":"venue"
},
  "geometry": {"coordinates":[-86.006592,34.010757],"type":"Point"}
}