{
  "type": "Feature",
  "properties": {
    "addr:full":"308 E Main St Albertville AL 35950",
    "addr:housenumber":"308",
    "addr:postcode":"35950",
    "addr:street":"E Main St",
    "iso:country":"US",
    "sg:address":"308 E Main St",
    "sg:city":"Albertville",
    "sg:classifiers":[
        {
            "category":"Home & Garden",
            "subcategory":"Household Appliances",
            "type":"Retail Goods"
        }
    ],
    "sg:phone":"+1 256 878 3321",
    "sg:postcode":"35950",
    "sg:province":"AL",
    "wof:name":"Coast Gas",
    "wof:placetype":"venue"
},
  "geometry": {"coordinates":[-86.20531800000001,34.266522],"type":"Point"}
}