{
  "type": "Feature",
  "properties": {
    "iso:country":"US",
    "sg:address":"5394 S Oates St",
    "sg:city":"Dothan",
    "sg:classifiers":[
        {
            "category":"Autos & Motor Vehicles",
            "subcategory":"Auto Supplies",
            "type":"Retail Goods"
        },
        {
            "category":"Retail",
            "subcategory":"Auto Repair",
            "type":"Services"
        }
    ],
    "sg:phone":"+1 334 702 4323",
    "sg:postcode":"36301",
    "sg:province":"AL",
    "sg:tags":[
        "body",
        "automobile",
        "truck",
        "painting",
        "repairing"
    ],
    "wof:name":"Clark's Body Shop",
    "wof:placetype":"venue"
},
  "geometry": {"coordinates":[-85.402641,31.149461],"type":"Point"}
}