{
  "type": "Feature",
  "properties": {
    "addr:full":"11070 US Hwy 278 Holly Pond AL 35083",
    "addr:housenumber":"11070",
    "addr:postcode":"35083",
    "addr:street":"Us Hwy 278 Holly Pond",
    "iso:country":"US",
    "sg:address":"11070 US Hwy 278",
    "sg:city":"Holly Pond",
    "sg:classifiers":[
        {
            "category":"Retail",
            "subcategory":"Veterinary Services",
            "type":"Services"
        }
    ],
    "sg:phone":"+1 256 796 0055",
    "sg:postcode":"35083",
    "sg:province":"AL",
    "wof:name":"Holly Pond Animal Clinic",
    "wof:placetype":"venue"
},
  "geometry": {"coordinates":[-86.604596,34.174093],"type":"Point"}
}