{
  "type": "Feature",
  "properties": {
    "iso:country":"US",
    "sg:address":"7860 Cottage Hill Rd",
    "sg:city":"Mobile",
    "sg:classifiers":[
        {
            "category":"Building & Trades",
            "subcategory":"Pest Control",
            "type":"Services"
        }
    ],
    "sg:phone":"+1 251 660 2700",
    "sg:postcode":"36695",
    "sg:province":"AL",
    "wof:name":"Terminix",
    "wof:placetype":"venue"
},
  "geometry": {"coordinates":[-88.227675,30.640223],"type":"Point"}
}