{
  "type": "Feature",
  "properties": {
    "addr:full":"1303 Memory Ln Andalusia AL 36420",
    "addr:housenumber":"1303",
    "addr:postcode":"36420",
    "addr:street":"Memory Ln",
    "iso:country":"US",
    "sg:address":"1303 Memory Ln",
    "sg:city":"Andalusia",
    "sg:classifiers":[
        {
            "category":"Retail",
            "subcategory":"Animal Services",
            "type":"Services"
        }
    ],
    "sg:phone":"+1 334 222 7790",
    "sg:postcode":"36420",
    "sg:province":"AL",
    "wof:name":"Brendas Pet Grooming",
    "wof:placetype":"venue"
},
  "geometry": {"coordinates":[-86.456446,31.299245],"type":"Point"}
}