{
  "type": "Feature",
  "properties": {
    "iso:country":"US",
    "sg:address":"1301 John R St",
    "sg:city":"Muscle Shoals",
    "sg:classifiers":[
        {
            "category":"Professional",
            "subcategory":"Business Services",
            "type":"Services"
        },
        {
            "category":"Home & Garden",
            "subcategory":"Home Furnishings",
            "type":"Retail Goods"
        }
    ],
    "sg:phone":"+1 256 386 0360",
    "sg:postcode":"35661",
    "sg:province":"AL",
    "sg:tags":[
        "interior",
        "consultant",
        "design",
        "decorator",
        "housewares"
    ],
    "wof:name":"Traditions",
    "wof:placetype":"venue"
},
  "geometry": {"coordinates":[-87.665446,34.748083],"type":"Point"}
}