{
  "type": "Feature",
  "properties": {
    "addr:full":"21027 Co Rd 55 Silverhill AL 36576",
    "addr:housenumber":"21027;55",
    "addr:postcode":"36576",
    "addr:street":"Co Rd",
    "iso:country":"US",
    "sg:address":"21027 Co Rd 55",
    "sg:city":"Silverhill",
    "sg:classifiers":[
        {
            "category":"Retail",
            "subcategory":"Auto Repair",
            "type":"Services"
        }
    ],
    "sg:phone":"+1 251 945 5139",
    "sg:postcode":"36576",
    "sg:province":"AL",
    "sg:tags":[
        "wrecker"
    ],
    "wof:name":"Old Dixie Wrecker Svc",
    "wof:placetype":"venue"
},
  "geometry": {"coordinates":[-87.750833,30.534556],"type":"Point"}
}