{
  "type": "Feature",
  "properties": {
    "addr:full":"446 Co Rd 55 Clanton AL 35046",
    "addr:housenumber":"446;55",
    "addr:postcode":"35046",
    "addr:street":"Co Rd",
    "iso:country":"US",
    "sg:address":"446 Co Rd 55",
    "sg:city":"Clanton",
    "sg:classifiers":[
        {
            "category":"Autos & Motor Vehicles",
            "subcategory":"Fuel & Gas Station",
            "type":"Retail Goods"
        }
    ],
    "sg:phone":"+1 205 755 2394",
    "sg:postcode":"35046",
    "sg:province":"AL",
    "sg:tags":[
        "grocery",
        "station",
        "gasoline"
    ],
    "wof:name":"T & N Bait Shop",
    "wof:placetype":"venue"
},
  "geometry": {"coordinates":[-86.603585,32.913472],"type":"Point"}
}