{
  "type": "Feature",
  "properties": {
    "iso:country":"US",
    "sg:address":"1110 Putman Dr NW",
    "sg:city":"Huntsville",
    "sg:classifiers":[
        {
            "category":"Building & Trades",
            "subcategory":"Construction",
            "type":"Services"
        }
    ],
    "sg:phone":"+1 256 837 8880",
    "sg:postcode":"35816",
    "sg:province":"AL",
    "sg:tags":[
        "roofing",
        "contractor"
    ],
    "sg:website":"www.tiptoproof.com",
    "wof:name":"Tip Top Roofing & Sheet Metal",
    "wof:placetype":"venue"
},
  "geometry": {"coordinates":[-86.635776,34.73924],"type":"Point"}
}