{
  "type": "Feature",
  "properties": {
    "iso:country":"US",
    "sg:address":"261 S Greenway Dr",
    "sg:city":"Trinity",
    "sg:classifiers":[
        {
            "category":"Education",
            "subcategory":"School",
            "type":"Public Place"
        }
    ],
    "sg:phone":"+1 256 353 5214",
    "sg:postcode":"35673",
    "sg:province":"AL",
    "sg:tags":[
        "district"
    ],
    "sg:website":"www.bamakids.com",
    "wof:name":"West Morgan High School",
    "wof:placetype":"venue"
},
  "geometry": {"coordinates":[-87.080251,34.58436],"type":"Point"}
}