{
  "type": "Feature",
  "properties": {
    "iso:country":"US",
    "sg:address":"11802 State Rte 157",
    "sg:city":"Vinemont",
    "sg:classifiers":[
        {
            "category":"Utilities",
            "subcategory":"Water",
            "type":"Services"
        }
    ],
    "sg:phone":"+1 256 734 2413",
    "sg:postcode":"35179",
    "sg:province":"AL",
    "sg:tags":[
        "system",
        "supply"
    ],
    "wof:name":"VAW Water System Inc",
    "wof:placetype":"venue"
},
  "geometry": {"coordinates":[-86.966044,34.248659],"type":"Point"}
}