{
  "type": "Feature",
  "properties": {
    "iso:country":"US",
    "sg:address":"1493 Secretariat Dr",
    "sg:city":"Helena",
    "sg:classifiers":[
        {
            "category":"Manufacturing",
            "subcategory":"Tools & Machinery",
            "type":"Manufacturing & Wholesale Goods"
        }
    ],
    "sg:phone":"+1 205 664 8785",
    "sg:postcode":"35080",
    "sg:province":"AL",
    "sg:tags":[
        "mfg"
    ],
    "wof:name":"T Wayne Mewbourne",
    "wof:placetype":"venue"
},
  "geometry": {"coordinates":[-86.824564,33.27028],"type":"Point"}
}