{
  "type": "Feature",
  "properties": {
    "iso:country":"US",
    "sg:address":"402 Celtic Dr",
    "sg:city":"Madison",
    "sg:classifiers":[
        {
            "category":"Professional",
            "subcategory":"Computer Services",
            "type":"Services"
        },
        {
            "category":"Shopping",
            "subcategory":"Computers & Home Electronics",
            "type":"Retail Goods"
        }
    ],
    "sg:phone":"+1 256 520 4805",
    "sg:postcode":"35758",
    "sg:province":"AL",
    "sg:tags":[
        "consultant",
        "software"
    ],
    "wof:name":"Eye T Solutions Group Inc",
    "wof:placetype":"venue"
},
  "geometry": {"coordinates":[-86.744958,34.682083],"type":"Point"}
}