{
  "type": "Feature",
  "properties": {
    "addr:full":"4315 Holmes Ave NW Huntsville AL 35816",
    "addr:housenumber":"4315",
    "addr:postcode":"35816",
    "addr:street":"Holmes Ave Nw",
    "iso:country":"US",
    "sg:address":"4315 Holmes Ave NW",
    "sg:city":"Huntsville",
    "sg:classifiers":[
        {
            "category":"Organizations",
            "subcategory":"Religious Organization",
            "type":"Services"
        }
    ],
    "sg:phone":"+1 256 837 1211",
    "sg:postcode":"35816",
    "sg:province":"AL",
    "wof:name":"Trinity Presbyterian Church",
    "wof:placetype":"venue"
},
  "geometry": {"coordinates":[-86.635132,34.727478],"type":"Point"}
}