{
  "type": "Feature",
  "properties": {
    "iso:country":"US",
    "sg:address":"10861 Dogwood Dr",
    "sg:city":"Stockton",
    "sg:classifiers":[
        {
            "category":"Wholesale",
            "subcategory":"Plants",
            "type":"Manufacturing & Wholesale Goods"
        }
    ],
    "sg:phone":"+1 251 937 4182",
    "sg:postcode":"36579",
    "sg:province":"AL",
    "sg:tags":[
        "nursery",
        "tree"
    ],
    "wof:name":"Southernwood Nursery",
    "wof:placetype":"venue"
},
  "geometry": {"coordinates":[-87.819383,30.98469],"type":"Point"}
}