{
  "type": "Feature",
  "properties": {
    "iso:country":"US",
    "sg:address":"1433 Crawford Rd",
    "sg:city":"Scottsboro",
    "sg:classifiers":[
        {
            "category":"Professional",
            "type":"Services"
        }
    ],
    "sg:phone":"+1 256 259 7172",
    "sg:postcode":"35769",
    "sg:province":"AL",
    "wof:name":"Julia Nichols",
    "wof:placetype":"venue"
},
  "geometry": {"coordinates":[-86.000377,34.670724],"type":"Point"}
}