{
  "type": "Feature",
  "properties": {
    "iso:country":"US",
    "sg:address":"6150 Omni Park Dr",
    "sg:city":"Mobile",
    "sg:classifiers":[
        {
            "category":"Professional",
            "type":"Services"
        }
    ],
    "sg:phone":"+1 251 639 7800",
    "sg:postcode":"36609",
    "sg:province":"AL",
    "sg:tags":[
        "establishment"
    ],
    "wof:name":"World Omni For Human Resources",
    "wof:placetype":"venue"
},
  "geometry": {"coordinates":[-88.190321,30.662723],"type":"Point"}
}