{
  "type": "Feature",
  "properties": {
    "addr:full":"9412 Valley Ln SE Huntsville AL 35803",
    "addr:housenumber":"9412",
    "addr:postcode":"35803",
    "addr:street":"Valley Ln Se",
    "iso:country":"US",
    "sg:address":"9412 Valley Ln SE",
    "sg:city":"Huntsville",
    "sg:classifiers":[
        {
            "category":"Professional",
            "subcategory":"Computer Services",
            "type":"Services"
        }
    ],
    "sg:phone":"+1 256 882 9746",
    "sg:postcode":"35803",
    "sg:province":"AL",
    "sg:tags":[
        "related"
    ],
    "wof:name":"Diamond Sky Inc",
    "wof:placetype":"venue"
},
  "geometry": {"coordinates":[-86.530804,34.638525],"type":"Point"}
}