{
  "type": "Feature",
  "properties": {
    "iso:country":"US",
    "sg:address":"895 State Rte 69",
    "sg:city":"Cullman",
    "sg:classifiers":[
        {
            "category":"Building & Trades",
            "subcategory":"Construction",
            "type":"Services"
        }
    ],
    "sg:phone":"+1 256 739 8412",
    "sg:postcode":"35058",
    "sg:province":"AL",
    "sg:tags":[
        "general",
        "contractor"
    ],
    "wof:name":"Blackwood Construction Co Inc",
    "wof:placetype":"venue"
},
  "geometry": {"coordinates":[-86.784715,34.194602],"type":"Point"}
}