{
  "type": "Feature",
  "properties": {
    "iso:country":"US",
    "sg:address":"1322 Hargrove Rd",
    "sg:city":"Tuscaloosa",
    "sg:classifiers":[
        {
            "category":"Restaurant",
            "type":"Food & Drink"
        }
    ],
    "sg:phone":"+1 205 759 2924",
    "sg:postcode":"35401",
    "sg:province":"AL",
    "sg:tags":[
        "eating"
    ],
    "wof:name":"Seasoned To Pleeze",
    "wof:placetype":"venue"
},
  "geometry": {"coordinates":[-87.557153,33.193774],"type":"Point"}
}