{
  "type": "Feature",
  "properties": {
    "iso:country":"US",
    "sg:address":"303 Reed St",
    "sg:city":"Tuscaloosa",
    "sg:classifiers":[
        {
            "category":"Professional",
            "type":"Services"
        }
    ],
    "sg:phone":"+1 205 366 9150",
    "sg:postcode":"35401",
    "sg:province":"AL",
    "wof:name":"Team Norris Enterprises",
    "wof:placetype":"venue"
},
  "geometry": {"coordinates":[-87.555155,33.212755],"type":"Point"}
}