{
  "type": "Feature",
  "properties": {
    "addr:full":"200 Mildred St Brewton AL 36426",
    "addr:housenumber":"200",
    "addr:postcode":"36426",
    "addr:street":"Mildred St",
    "iso:country":"US",
    "sg:address":"200 Mildred St",
    "sg:city":"Brewton",
    "sg:classifiers":[
        {
            "category":"Autos & Motor Vehicles",
            "subcategory":"Auto Supplies",
            "type":"Retail Goods"
        },
        {
            "category":"Retail",
            "subcategory":"Auto Repair",
            "type":"Services"
        }
    ],
    "sg:phone":"+1 251 867 7746",
    "sg:postcode":"36426",
    "sg:province":"AL",
    "sg:tags":[
        "shop",
        "automobile",
        "part",
        "machine"
    ],
    "wof:name":"Speed & Machine",
    "wof:placetype":"venue"
},
  "geometry": {"coordinates":[-87.072536,31.103435],"type":"Point"}
}