{
  "type": "Feature",
  "properties": {
    "iso:country":"US",
    "sg:address":"3777 Co Rd 2",
    "sg:city":"Millry",
    "sg:classifiers":[
        {
            "category":"Professional",
            "subcategory":"Testing Lab",
            "type":"Services"
        }
    ],
    "sg:phone":"+1 251 542 9834",
    "sg:postcode":"36558",
    "sg:province":"AL",
    "sg:tags":[
        "engineering",
        "management"
    ],
    "wof:name":"Soils Five Inc",
    "wof:placetype":"venue"
},
  "geometry": {"coordinates":[-88.436537,31.709993],"type":"Point"}
}