{
  "type": "Feature",
  "properties": {
    "addr:full":"1934 Hickey Dr Adger AL 35006",
    "addr:housenumber":"1934",
    "addr:postcode":"35006",
    "addr:street":"Hickey Dr Adger",
    "iso:country":"US",
    "sg:address":"1934 Hickey Dr",
    "sg:city":"Adger",
    "sg:classifiers":[
        {
            "category":"Building & Trades",
            "subcategory":"Construction",
            "type":"Services"
        }
    ],
    "sg:phone":"+1 205 491 4509",
    "sg:postcode":"35006",
    "sg:province":"AL",
    "sg:tags":[
        "contractor"
    ],
    "wof:name":"Gary Hickey Roofing",
    "wof:placetype":"venue"
},
  "geometry": {"coordinates":[-87.147238,33.451574],"type":"Point"}
}