{
  "type": "Feature",
  "properties": {
    "iso:country":"US",
    "sg:address":"2310 Locke Ln",
    "sg:city":"Birmingham",
    "sg:classifiers":[
        {
            "category":"Retail",
            "subcategory":"Auto Repair",
            "type":"Services"
        }
    ],
    "sg:phone":"+1 205 978 1624",
    "sg:postcode":"35226",
    "sg:province":"AL",
    "sg:tags":[
        "general"
    ],
    "wof:name":"Carsmetic",
    "wof:placetype":"venue"
},
  "geometry": {"coordinates":[-86.844099,33.389371],"type":"Point"}
}