{
  "type": "Feature",
  "properties": {
    "addr:full":"6547 Atlanta Hwy Montgomery AL 36117",
    "addr:housenumber":"6547",
    "addr:postcode":"36117",
    "addr:street":"Atlanta Hwy",
    "iso:country":"US",
    "sg:address":"6547 Atlanta Hwy",
    "sg:city":"Montgomery",
    "sg:classifiers":[
        {
            "category":"Shopping",
            "subcategory":"Discount & Variety Stores",
            "type":"Retail Goods"
        }
    ],
    "sg:phone":"+1 334 395 6579",
    "sg:postcode":"36117",
    "sg:province":"AL",
    "wof:name":"Dollar Tree",
    "wof:placetype":"venue"
},
  "geometry": {"coordinates":[-86.18446,32.38236],"type":"Point"}
}