{
  "type": "Feature",
  "properties": {
    "iso:country":"US",
    "sg:address":"43555 Still Rd",
    "sg:city":"Bay Minette",
    "sg:classifiers":[
        {
            "category":"Retail",
            "subcategory":"Repair Shop",
            "type":"Services"
        }
    ],
    "sg:phone":"+1 251 937 9719",
    "sg:postcode":"36507",
    "sg:province":"AL",
    "wof:name":"Home & Office Maint & Repr",
    "wof:placetype":"venue"
},
  "geometry": {"coordinates":[-87.723542,30.859319],"type":"Point"}
}