{
  "type": "Feature",
  "properties": {
    "iso:country":"US",
    "sg:address":"5626 Red Hollow Rd",
    "sg:city":"Birmingham",
    "sg:classifiers":[
        {
            "category":"Building & Trades",
            "subcategory":"Construction",
            "type":"Services"
        }
    ],
    "sg:phone":"+1 205 681 5875",
    "sg:postcode":"35215",
    "sg:province":"AL",
    "sg:tags":[
        "contractor"
    ],
    "wof:name":"Rhodes Roofing",
    "wof:placetype":"venue"
},
  "geometry": {"coordinates":[-86.722703,33.667212],"type":"Point"}
}