{
  "type": "Feature",
  "properties": {
    "iso:country":"US",
    "sg:address":"1430 21st Ave E",
    "sg:city":"Tuscaloosa",
    "sg:classifiers":[
        {
            "category":"Retail",
            "subcategory":"Laundry & Dry Cleaning",
            "type":"Services"
        }
    ],
    "sg:phone":"+1 205 553 1996",
    "sg:postcode":"35404",
    "sg:province":"AL",
    "wof:name":"Acclaimed Home Services",
    "wof:placetype":"venue"
},
  "geometry": {"coordinates":[-87.510626,33.198337],"type":"Point"}
}