{
  "type": "Feature",
  "properties": {
    "addr:full":"595 Sand Valley Rd Oneonta AL 35121",
    "addr:housenumber":"595",
    "addr:postcode":"35121",
    "addr:street":"Sand Valley Rd",
    "iso:country":"US",
    "sg:address":"595 Sand Valley Rd",
    "sg:city":"Oneonta",
    "sg:classifiers":[
        {
            "category":"Restaurant",
            "type":"Food & Drink"
        }
    ],
    "sg:phone":"+1 205 625 4590",
    "sg:postcode":"35121",
    "sg:province":"AL",
    "sg:tags":[
        "banquet",
        "rooms"
    ],
    "wof:name":"O'So Good Snack Shack",
    "wof:placetype":"venue"
},
  "geometry": {"coordinates":[-86.48103399999999,33.957085],"type":"Point"}
}