{
  "type": "Feature",
  "properties": {
    "iso:country":"US",
    "sg:address":"110 Season Ln",
    "sg:city":"Huntsville",
    "sg:classifiers":[
        {
            "category":"Building & Trades",
            "subcategory":"Construction",
            "type":"Services"
        }
    ],
    "sg:phone":"+1 256 859 0905",
    "sg:postcode":"35811",
    "sg:province":"AL",
    "sg:tags":[
        "house"
    ],
    "wof:name":"Southern Traditional Home",
    "wof:placetype":"venue"
},
  "geometry": {"coordinates":[-86.488782,34.77137],"type":"Point"}
}