{
  "type": "Feature",
  "properties": {
    "iso:country":"US",
    "sg:address":"10240 Schoolhouse Rd",
    "sg:city":"Grand Bay",
    "sg:classifiers":[
        {
            "category":"Personal",
            "subcategory":"Beauty Salon",
            "type":"Services"
        }
    ],
    "sg:phone":"+1 251 865 4817",
    "sg:postcode":"36541",
    "sg:province":"AL",
    "wof:name":"Classic Sweep & Swirl",
    "wof:placetype":"venue"
},
  "geometry": {"coordinates":[-88.34343200000001,30.479529],"type":"Point"}
}