{
  "type": "Feature",
  "properties": {
    "iso:country":"US",
    "sg:address":"875 Co Rd 334",
    "sg:city":"Salem",
    "sg:classifiers":[
        {
            "category":"Organizations",
            "subcategory":"Religious Organization",
            "type":"Services"
        }
    ],
    "sg:phone":"+1 334 297 0962",
    "sg:postcode":"36874",
    "sg:province":"AL",
    "sg:tags":[
        "church"
    ],
    "wof:name":"Greater Ebenezer Baptst Church",
    "wof:placetype":"venue"
},
  "geometry": {"coordinates":[-85.140832,32.628364],"type":"Point"}
}