{
  "type": "Feature",
  "properties": {
    "iso:country":"US",
    "sg:address":"798 Piccadilly Sq Dr",
    "sg:city":"Mobile",
    "sg:classifiers":[
        {
            "category":"Health Services",
            "subcategory":"Doctor",
            "type":"Services"
        }
    ],
    "sg:phone":"+1 251 343 1007",
    "sg:postcode":"36609",
    "sg:province":"AL",
    "wof:name":"Kenneth C Lambert DMD",
    "wof:placetype":"venue"
},
  "geometry": {"coordinates":[-88.190637,30.672758],"type":"Point"}
}