{
  "type": "Feature",
  "properties": {
    "addr:full":"357 Co Rd 6 Sardis AL 36775",
    "addr:housenumber":"357",
    "addr:postcode":"36775",
    "addr:street":"Co Rd 6",
    "iso:country":"US",
    "sg:address":"357 Co Rd 6",
    "sg:city":"Sardis",
    "sg:classifiers":[
        {
            "category":"Organizations",
            "subcategory":"Religious Organization",
            "type":"Services"
        }
    ],
    "sg:phone":"+1 334 874 9876",
    "sg:postcode":"36775",
    "sg:province":"AL",
    "wof:name":"Marrietta AME Zion",
    "wof:placetype":"venue"
},
  "geometry": {"coordinates":[-87.020308,32.213987],"type":"Point"}
}