{
  "type": "Feature",
  "properties": {
    "iso:country":"US",
    "sg:address":"1030 Perry Hill Rd",
    "sg:city":"Montgomery",
    "sg:classifiers":[
        {
            "category":"Shopping",
            "subcategory":"Discount & Variety Stores",
            "type":"Retail Goods"
        }
    ],
    "sg:phone":"+1 334 271 4732",
    "sg:postcode":"36109",
    "sg:province":"AL",
    "wof:name":"Dollar General",
    "wof:placetype":"venue"
},
  "geometry": {"coordinates":[-86.244248,32.365926],"type":"Point"}
}