{
  "type": "Feature",
  "properties": {
    "addr:full":"232 McFarland Blvd Northport AL 35476",
    "addr:housenumber":"232",
    "addr:postcode":"35476",
    "addr:street":"Mcfarland Blvd",
    "iso:country":"US",
    "sg:address":"232 McFarland Blvd",
    "sg:city":"Northport",
    "sg:classifiers":[
        {
            "category":"Shopping",
            "type":"Retail Goods"
        }
    ],
    "sg:phone":"+1 205 366 1000",
    "sg:postcode":"35476",
    "sg:province":"AL",
    "sg:tags":[
        "merchandise"
    ],
    "wof:name":"Aquarium Showcase",
    "wof:placetype":"venue"
},
  "geometry": {"coordinates":[-87.55256,33.236261],"type":"Point"}
}