{
  "type": "Feature",
  "properties": {
    "iso:country":"US",
    "sg:address":"3206 34th Ave",
    "sg:city":"Northport",
    "sg:classifiers":[
        {
            "category":"Home & Garden",
            "subcategory":"Hardware",
            "type":"Retail Goods"
        }
    ],
    "sg:phone":"+1 205 339 5255",
    "sg:postcode":"35476",
    "sg:province":"AL",
    "wof:name":"Beasley Gus",
    "wof:placetype":"venue"
},
  "geometry": {"coordinates":[-87.591215,33.238881],"type":"Point"}
}