{
  "type": "Feature",
  "properties": {
    "iso:country":"US",
    "sg:address":"114 Myrtle Dr",
    "sg:city":"Ozark",
    "sg:classifiers":[
        {
            "category":"Personal",
            "subcategory":"Beauty Salon",
            "type":"Services"
        }
    ],
    "sg:phone":"+1 334 445 6310",
    "sg:postcode":"36360",
    "sg:province":"AL",
    "sg:tags":[
        "shop"
    ],
    "wof:name":"Shear Angels Hair Salon",
    "wof:placetype":"venue"
},
  "geometry": {"coordinates":[-85.63456,31.468905],"type":"Point"}
}