{
  "type": "Feature",
  "properties": {
    "iso:country":"US",
    "sg:address":"1316 Bessemer Rd",
    "sg:city":"Birmingham",
    "sg:classifiers":[
        {
            "category":"Professional",
            "subcategory":"Management & Consulting",
            "type":"Services"
        }
    ],
    "sg:phone":"+1 205 923 7305",
    "sg:postcode":"35208",
    "sg:province":"AL",
    "wof:name":"Expert Management",
    "wof:placetype":"venue"
},
  "geometry": {"coordinates":[-86.894581,33.480993],"type":"Point"}
}