{
  "type": "Feature",
  "properties": {
    "iso:country":"US",
    "sg:address":"410 E Laurel Ave",
    "sg:city":"Foley",
    "sg:classifiers":[
        {
            "category":"Health Services",
            "subcategory":"Medical Lab",
            "type":"Services"
        }
    ],
    "sg:phone":"+1 251 460 0013",
    "sg:postcode":"36535",
    "sg:province":"AL",
    "sg:tags":[
        "detection",
        "equipment",
        "drug"
    ],
    "wof:name":"Gulfsouth Resources",
    "wof:placetype":"venue"
},
  "geometry": {"coordinates":[-87.678127,30.406301],"type":"Point"}
}