{
  "type": "Feature",
  "properties": {
    "iso:country":"US",
    "sg:address":"166 Ellenburg Dr",
    "sg:city":"Dothan",
    "sg:classifiers":[
        {
            "category":"Building & Trades",
            "subcategory":"Construction",
            "type":"Services"
        }
    ],
    "sg:phone":"+1 334 794 6884",
    "sg:postcode":"36303",
    "sg:province":"AL",
    "sg:tags":[
        "asphalt",
        "excavation",
        "contractor",
        "paving",
        "general",
        "demolition"
    ],
    "wof:name":"Ellenburg Construction Inc",
    "wof:placetype":"venue"
},
  "geometry": {"coordinates":[-85.374273,31.272439],"type":"Point"}
}