{
  "type": "Feature",
  "properties": {
    "iso:country":"US",
    "sg:address":"5743 Andrews Rd",
    "sg:city":"Mobile",
    "sg:classifiers":[
        {
            "category":"Retail",
            "subcategory":"Auto Repair",
            "type":"Services"
        }
    ],
    "sg:phone":"+1 251 666 6632",
    "sg:postcode":"36619",
    "sg:province":"AL",
    "sg:tags":[
        "general"
    ],
    "wof:name":"R & J Automotive",
    "wof:placetype":"venue"
},
  "geometry": {"coordinates":[-88.174024,30.592834],"type":"Point"}
}