{
  "type": "Feature",
  "properties": {
    "iso:country":"US",
    "sg:address":"700 8th St N",
    "sg:city":"Clanton",
    "sg:classifiers":[
        {
            "category":"Real Estate",
            "subcategory":"Real Estate Operator",
            "type":"Services"
        }
    ],
    "sg:phone":"+1 205 755 6733",
    "sg:postcode":"35045",
    "sg:province":"AL",
    "sg:tags":[
        "apartment"
    ],
    "wof:name":"Rolling Oaks Apartments",
    "wof:placetype":"venue"
},
  "geometry": {"coordinates":[-86.639324,32.844665],"type":"Point"}
}