{
  "type": "Feature",
  "properties": {
    "iso:country":"US",
    "sg:address":"3120 26th St N",
    "sg:city":"Birmingham",
    "sg:classifiers":[
        {
            "category":"Autos & Motor Vehicles",
            "subcategory":"Auto Supplies",
            "type":"Retail Goods"
        }
    ],
    "sg:phone":"+1 205 252 0219",
    "sg:postcode":"35207",
    "sg:province":"AL",
    "sg:tags":[
        "automobile",
        "parts"
    ],
    "wof:name":"Gafford Auto Parts Co",
    "wof:placetype":"venue"
},
  "geometry": {"coordinates":[-86.818618,33.553015],"type":"Point"}
}