{
  "type": "Feature",
  "properties": {
    "iso:country":"US",
    "sg:address":"916 Belmont Ave",
    "sg:city":"Talladega",
    "sg:classifiers":[
        {
            "category":"Organizations",
            "subcategory":"Religious Organization",
            "type":"Services"
        }
    ],
    "sg:phone":"+1 256 761 9656",
    "sg:postcode":"35160",
    "sg:province":"AL",
    "sg:tags":[
        "church"
    ],
    "wof:name":"Brecon Baptist Church",
    "wof:placetype":"venue"
},
  "geometry": {"coordinates":[-86.108611,33.451934],"type":"Point"}
}