{
  "type": "Feature",
  "properties": {
    "addr:full":"1869 Co Rd 400 Fyffe AL 35971",
    "addr:housenumber":"1869",
    "addr:postcode":"35971",
    "addr:street":"Co Rd 400",
    "iso:country":"US",
    "sg:address":"1869 Co Rd 400",
    "sg:city":"Fyffe",
    "sg:classifiers":[
        {
            "category":"Farming",
            "subcategory":"Livestock Farm",
            "type":"Manufacturing & Wholesale Goods"
        }
    ],
    "sg:phone":"+1 256 659 4054",
    "sg:postcode":"35971",
    "sg:province":"AL",
    "sg:tags":[
        "beef",
        "feedlot",
        "cattle"
    ],
    "wof:name":"Nell Williams Farm",
    "wof:placetype":"venue"
},
  "geometry": {"coordinates":[-85.990208,34.414522],"type":"Point"}
}