{
  "type": "Feature",
  "properties": {
    "iso:country":"US",
    "sg:address":"4546 Yellow Jacket Rd",
    "sg:city":"Townley",
    "sg:classifiers":[
        {
            "category":"Manufacturing",
            "subcategory":"Lumber",
            "type":"Manufacturing & Wholesale Goods"
        }
    ],
    "sg:phone":"+1 205 924 4422",
    "sg:postcode":"35587",
    "sg:province":"AL",
    "sg:tags":[
        "logging"
    ],
    "wof:name":"Nesmith Logging",
    "wof:placetype":"venue"
},
  "geometry": {"coordinates":[-87.468719,33.819968],"type":"Point"}
}