{
  "type": "Feature",
  "properties": {
    "iso:country":"US",
    "sg:address":"1510 Levert Ave",
    "sg:city":"Athens",
    "sg:classifiers":[
        {
            "category":"Health Services",
            "subcategory":"Chiropractor",
            "type":"Services"
        }
    ],
    "sg:phone":"+1 256 232 3618",
    "sg:postcode":"35611",
    "sg:province":"AL",
    "wof:name":"Tucker Lrry Chropractic Clinic",
    "wof:placetype":"venue"
},
  "geometry": {"coordinates":[-86.97802,34.792077],"type":"Point"}
}