{
  "type": "Feature",
  "properties": {
    "iso:country":"US",
    "sg:address":"905 10th Ct SW",
    "sg:city":"Alabaster",
    "sg:classifiers":[
        {
            "category":"Building & Trades",
            "subcategory":"Construction",
            "type":"Services"
        }
    ],
    "sg:phone":"+1 205 663 1000",
    "sg:postcode":"35007",
    "sg:province":"AL",
    "sg:tags":[
        "painter"
    ],
    "wof:name":"Prime Painting & Contracting",
    "wof:placetype":"venue"
},
  "geometry": {"coordinates":[-86.829493,33.232082],"type":"Point"}
}