{
  "type": "Feature",
  "properties": {
    "addr:full":"10104 Skylark Dr SE Huntsville AL 35803",
    "addr:housenumber":"10104",
    "addr:postcode":"35803",
    "addr:street":"Skylark Dr Se",
    "iso:country":"US",
    "sg:address":"10104 Skylark Dr SE",
    "sg:city":"Huntsville",
    "sg:classifiers":[
        {
            "category":"Professional",
            "subcategory":"Business Services",
            "type":"Services"
        }
    ],
    "sg:phone":"+1 256 880 3152",
    "sg:postcode":"35803",
    "sg:province":"AL",
    "wof:name":"Werner Stark Design",
    "wof:placetype":"venue"
},
  "geometry": {"coordinates":[-86.55763399999999,34.629],"type":"Point"}
}