{
  "type": "Feature",
  "properties": {
    "iso:country":"US",
    "sg:address":"2168 Denton Rd",
    "sg:city":"Dothan",
    "sg:classifiers":[
        {
            "category":"Professional",
            "type":"Services"
        }
    ],
    "sg:phone":"+1 334 677 1698",
    "sg:postcode":"36303",
    "sg:province":"AL",
    "wof:name":"Gross Sr",
    "wof:placetype":"venue"
},
  "geometry": {"coordinates":[-85.412058,31.258021],"type":"Point"}
}