{
  "type": "Feature",
  "properties": {
    "addr:full":"312 Azalea Rd Mobile AL 36609",
    "addr:housenumber":"312",
    "addr:postcode":"36609",
    "addr:street":"Azalea Rd",
    "iso:country":"US",
    "sg:address":"312 Azalea Rd",
    "sg:city":"Mobile",
    "sg:classifiers":[
        {
            "category":"Personal",
            "subcategory":"Beauty Salon",
            "type":"Services"
        }
    ],
    "sg:phone":"+1 251 343 4005",
    "sg:postcode":"36609",
    "sg:province":"AL",
    "wof:name":"Dezign Elegance",
    "wof:placetype":"venue"
},
  "geometry": {"coordinates":[-88.148785,30.672067],"type":"Point"}
}