{
  "type": "Feature",
  "properties": {
    "iso:country":"US",
    "sg:address":"150 E Fleming Rd",
    "sg:city":"Montgomery",
    "sg:classifiers":[
        {
            "category":"Arts & Performance",
            "subcategory":"Theater",
            "type":"Entertainment"
        }
    ],
    "sg:phone":"+1 334 281 4288",
    "sg:postcode":"36105",
    "sg:province":"AL",
    "sg:tags":[
        "center",
        "community"
    ],
    "wof:name":"Carmichael Center The",
    "wof:placetype":"venue"
},
  "geometry": {"coordinates":[-86.303324,32.322541],"type":"Point"}
}