{
  "type": "Feature",
  "properties": {
    "iso:country":"US",
    "sg:address":"146 Salisbury Ln",
    "sg:city":"Birmingham",
    "sg:classifiers":[
        {
            "category":"Building & Trades",
            "subcategory":"Plumbing",
            "type":"Services"
        }
    ],
    "sg:phone":"+1 205 835 2600",
    "sg:postcode":"35242",
    "sg:province":"AL",
    "sg:tags":[
        "contractor"
    ],
    "wof:name":"Alliance Plumbing Solutions In",
    "wof:placetype":"venue"
},
  "geometry": {"coordinates":[-86.648594,33.394579],"type":"Point"}
}