{
  "type": "Feature",
  "properties": {
    "iso:country":"US",
    "sg:address":"507 Karey Dr",
    "sg:city":"Birmingham",
    "sg:classifiers":[
        {
            "category":"Wholesale",
            "subcategory":"Stationery",
            "type":"Manufacturing & Wholesale Goods"
        }
    ],
    "sg:phone":"+1 205 592 6730",
    "sg:postcode":"35215",
    "sg:province":"AL",
    "sg:tags":[
        "packaging",
        "material"
    ],
    "wof:name":"Crus Packaging & Equipment",
    "wof:placetype":"venue"
},
  "geometry": {"coordinates":[-86.67081399999999,33.628995],"type":"Point"}
}