{
  "type": "Feature",
  "properties": {
    "iso:country":"US",
    "sg:address":"586 E Burdeshaw St",
    "sg:city":"Dothan",
    "sg:classifiers":[
        {
            "category":"Retail",
            "subcategory":"Funeral Services",
            "type":"Services"
        }
    ],
    "sg:phone":"+1 334 792 7913",
    "sg:postcode":"36303",
    "sg:province":"AL",
    "sg:tags":[
        "director"
    ],
    "wof:name":"Hammond & Son Funeral Home",
    "wof:placetype":"venue"
},
  "geometry": {"coordinates":[-85.386416,31.227702],"type":"Point"}
}