{
  "type": "Feature",
  "properties": {
    "addr:full":"5895 Woodmont Dr Tuscumbia AL 35674",
    "addr:housenumber":"5895",
    "addr:postcode":"35674",
    "addr:street":"Woodmont Dr Tuscumbia",
    "iso:country":"US",
    "sg:address":"5895 Woodmont Dr",
    "sg:city":"Tuscumbia",
    "sg:classifiers":[
        {
            "category":"Building & Trades",
            "subcategory":"Construction",
            "type":"Services"
        }
    ],
    "sg:phone":"+1 256 381 1943",
    "sg:postcode":"35674",
    "sg:province":"AL",
    "sg:tags":[
        "excavation",
        "contractor"
    ],
    "wof:name":"Henson Construction",
    "wof:placetype":"venue"
},
  "geometry": {"coordinates":[-87.694468,34.660769],"type":"Point"}
}