{
  "type": "Feature",
  "properties": {
    "iso:country":"US",
    "sg:address":"900 Arkadelphia Rd",
    "sg:city":"Birmingham",
    "sg:classifiers":[
        {
            "category":"Education",
            "subcategory":"College",
            "type":"Public Place"
        }
    ],
    "sg:phone":"+1 205 226 4960",
    "sg:postcode":"35254",
    "sg:province":"AL",
    "sg:tags":[
        "academic",
        "school"
    ],
    "wof:name":"Birmingham-Southern College",
    "wof:placetype":"venue"
},
  "geometry": {"coordinates":[-86.850215,33.516638],"type":"Point"}
}