{
  "type": "Feature",
  "properties": {
    "addr:full":"135 Mint Springs Rd New Market AL 35761",
    "addr:housenumber":"135",
    "addr:postcode":"35761",
    "addr:street":"Mint Springs Rd",
    "iso:country":"US",
    "sg:address":"135 Mint Springs Rd",
    "sg:city":"New Market",
    "sg:classifiers":[
        {
            "category":"Professional",
            "type":"Services"
        }
    ],
    "sg:phone":"+1 256 379 2366",
    "sg:postcode":"35761",
    "sg:province":"AL",
    "wof:name":"Danny W McCord",
    "wof:placetype":"venue"
},
  "geometry": {"coordinates":[-86.452693,34.927066],"type":"Point"}
}