{
  "type": "Feature",
  "properties": {
    "addr:full":"1201 S Quintard Ave Anniston AL 36201",
    "addr:housenumber":"1201",
    "addr:postcode":"36201",
    "addr:street":"S Quintard Ave",
    "iso:country":"US",
    "sg:address":"1201 S Quintard Ave",
    "sg:city":"Anniston",
    "sg:classifiers":[
        {
            "category":"Restaurant",
            "type":"Food & Drink"
        }
    ],
    "sg:menulink":"http://www.allmenus.com/al/anniston/107664-waffle-house/menu/",
    "sg:phone":"+1 256 835 1698",
    "sg:postcode":"36201",
    "sg:province":"AL",
    "sg:tags":[
        "american"
    ],
    "wof:name":"Waffle House",
    "wof:placetype":"venue"
},
  "geometry": {"coordinates":[-85.82560100000001,33.632956],"type":"Point"}
}