{
  "type": "Feature",
  "properties": {
    "addr:full":"803 Randolph Ave SE Huntsville AL 35801",
    "addr:housenumber":"803",
    "addr:postcode":"35801",
    "addr:street":"Randolph Ave Se",
    "iso:country":"US",
    "sg:address":"803 Randolph Ave SE",
    "sg:city":"Huntsville",
    "sg:classifiers":[
        {
            "category":"Organizations",
            "subcategory":"Religious Organization",
            "type":"Services"
        }
    ],
    "sg:phone":"+1 256 851 1507",
    "sg:postcode":"35801",
    "sg:province":"AL",
    "sg:tags":[
        "church"
    ],
    "wof:name":"Spiritual Life Worship Ctr",
    "wof:placetype":"venue"
},
  "geometry": {"coordinates":[-86.564689,34.735526],"type":"Point"}
}