{
  "type": "Feature",
  "properties": {
    "iso:country":"US",
    "sg:address":"303 E Broad St",
    "sg:city":"Eufaula",
    "sg:classifiers":[
        {
            "category":"Government",
            "subcategory":"Office",
            "type":"Public Place"
        }
    ],
    "sg:phone":"+1 334 687 1566",
    "sg:postcode":"36027",
    "sg:province":"AL",
    "wof:name":"County Juvenile Office",
    "wof:placetype":"venue"
},
  "geometry": {"coordinates":[-85.142001,31.89289],"type":"Point"}
}