{
  "type": "Feature",
  "properties": {
    "addr:full":"18135 Robin Ln Sylacauga AL 35150",
    "addr:housenumber":"18135",
    "addr:postcode":"35150",
    "addr:street":"Robin Ln",
    "iso:country":"US",
    "sg:address":"18135 Robin Ln",
    "sg:city":"Sylacauga",
    "sg:classifiers":[
        {
            "category":"Building & Trades",
            "subcategory":"Construction",
            "type":"Services"
        }
    ],
    "sg:phone":"+1 256 245 7329",
    "sg:postcode":"35150",
    "sg:province":"AL",
    "sg:tags":[
        "contractor"
    ],
    "wof:name":"Doyle Kelly Roofing",
    "wof:placetype":"venue"
},
  "geometry": {"coordinates":[-86.275288,33.182856],"type":"Point"}
}