{
  "type": "Feature",
  "properties": {
    "iso:country":"US",
    "sg:address":"2536 Montgomery Hwy",
    "sg:city":"Dothan",
    "sg:classifiers":[
        {
            "category":"Wholesale",
            "subcategory":"Stationery",
            "type":"Manufacturing & Wholesale Goods"
        },
        {
            "category":"Shopping",
            "type":"Retail Goods"
        }
    ],
    "sg:phone":"+1 334 793 5500",
    "sg:postcode":"36303",
    "sg:province":"AL",
    "sg:tags":[
        "school",
        "supply"
    ],
    "wof:name":"Teachers Tools",
    "wof:placetype":"venue"
},
  "geometry": {"coordinates":[-85.420829,31.245642],"type":"Point"}
}