{
  "type": "Feature",
  "properties": {
    "iso:country":"US",
    "sg:address":"158 Kimbrough Ln",
    "sg:city":"Owens Cross Rds",
    "sg:classifiers":[
        {
            "category":"Real Estate",
            "subcategory":"Surveying",
            "type":"Services"
        }
    ],
    "sg:phone":"+1 256 725 5158",
    "sg:postcode":"35763",
    "sg:province":"AL",
    "sg:tags":[
        "surveyor"
    ],
    "wof:name":"Kimbrough & Son Surveying",
    "wof:placetype":"venue"
},
  "geometry": {"coordinates":[-86.423646,34.60407],"type":"Point"}
}