{
  "type": "Feature",
  "properties": {
    "iso:country":"US",
    "sg:address":"3675 Debby Dr",
    "sg:city":"Montgomery",
    "sg:classifiers":[
        {
            "category":"Manufacturing",
            "subcategory":"Printing",
            "type":"Manufacturing & Wholesale Goods"
        }
    ],
    "sg:phone":"+1 334 281 1315",
    "sg:postcode":"36111",
    "sg:province":"AL",
    "sg:tags":[
        "printer"
    ],
    "wof:name":"Creative Printing",
    "wof:placetype":"venue"
},
  "geometry": {"coordinates":[-86.240906,32.329819],"type":"Point"}
}