{
  "type": "Feature",
  "properties": {
    "iso:country":"US",
    "sg:address":"2105 Drake Ave SW",
    "sg:city":"Huntsville",
    "sg:classifiers":[
        {
            "category":"Autos & Motor Vehicles",
            "subcategory":"Recreational Vehicle Sales",
            "type":"Retail Goods"
        },
        {
            "category":"Wholesale",
            "subcategory":"Auto Parts",
            "type":"Manufacturing & Wholesale Goods"
        }
    ],
    "sg:phone":"+1 256 650 5839",
    "sg:postcode":"35805",
    "sg:province":"AL",
    "sg:tags":[
        "automobile",
        "used",
        "general"
    ],
    "sg:website":"www.performancerv.com",
    "wof:name":"Performance Rv",
    "wof:placetype":"venue"
},
  "geometry": {"coordinates":[-86.591672,34.705372],"type":"Point"}
}