{
  "type": "Feature",
  "properties": {
    "iso:country":"US",
    "sg:address":"8162 Magic Brook Way",
    "sg:city":"Athens",
    "sg:classifiers":[
        {
            "category":"Farming",
            "subcategory":"Dairy Farm",
            "type":"Manufacturing & Wholesale Goods"
        }
    ],
    "sg:phone":"+1 256 729 6416",
    "sg:postcode":"35611",
    "sg:province":"AL",
    "wof:name":"Ralph Brooks Dairy",
    "wof:placetype":"venue"
},
  "geometry": {"coordinates":[-87.17637,34.793656],"type":"Point"}
}