{
  "type": "Feature",
  "properties": {
    "addr:full":"1400 S Court St Montgomery AL 36104",
    "addr:housenumber":"1400",
    "addr:postcode":"36104",
    "addr:street":"S Court",
    "iso:country":"US",
    "sg:address":"1400 S Court St",
    "sg:city":"Montgomery",
    "sg:classifiers":[
        {
            "category":"Social Services",
            "subcategory":"Adult Care",
            "type":"Services"
        }
    ],
    "sg:phone":"+1 334 264 4404",
    "sg:postcode":"36104",
    "sg:province":"AL",
    "sg:tags":[
        "home",
        "residential"
    ],
    "wof:name":"Jan Elder Care",
    "wof:placetype":"venue"
},
  "geometry": {"coordinates":[-86.30856199999999,32.359569],"type":"Point"}
}