{
  "type": "Feature",
  "properties": {
    "iso:country":"US",
    "sg:address":"539 Stonecrest Dr",
    "sg:city":"Birmingham",
    "sg:classifiers":[
        {
            "category":"Professional",
            "type":"Services"
        },
        {
            "category":"Airport",
            "type":"Transportation"
        }
    ],
    "sg:phone":"+1 205 980 6877",
    "sg:postcode":"35242",
    "sg:province":"AL",
    "wof:name":"Meteors Airport Shuttle",
    "wof:placetype":"venue"
},
  "geometry": {"coordinates":[-86.65973700000001,33.407071],"type":"Point"}
}