{
  "type": "Feature",
  "properties": {
    "iso:country":"US",
    "sg:address":"401 N Craft Hwy",
    "sg:city":"Chickasaw",
    "sg:classifiers":[
        {
            "category":"Food & Beverages",
            "subcategory":"Groceries & Convenience Stores",
            "type":"Retail Goods"
        },
        {
            "category":"Autos & Motor Vehicles",
            "subcategory":"Auto Supplies",
            "type":"Retail Goods"
        }
    ],
    "sg:phone":"+1 251 452 0898",
    "sg:postcode":"36611",
    "sg:province":"AL",
    "wof:name":"Chickasaw Pride",
    "wof:placetype":"venue"
},
  "geometry": {"coordinates":[-88.075296,30.771939],"type":"Point"}
}