{
  "type": "Feature",
  "properties": {
    "iso:country":"US",
    "sg:address":"602 Boll Weevil Cir",
    "sg:city":"Enterprise",
    "sg:classifiers":[
        {
            "category":"Restaurant",
            "type":"Food & Drink"
        }
    ],
    "sg:menulink":"http://www.allmenus.com/al/enterprise/204732-taco-bell/menu/",
    "sg:postcode":"36330",
    "sg:province":"AL",
    "sg:tags":[
        "mexican"
    ],
    "wof:name":"Taco Bell",
    "wof:placetype":"venue"
},
  "geometry": {"coordinates":[-85.83113899999999,31.323654],"type":"Point"}
}