{
  "type": "Feature",
  "properties": {
    "iso:country":"US",
    "sg:address":"8351 Junior Rd",
    "sg:city":"Mobile",
    "sg:classifiers":[
        {
            "category":"Building & Trades",
            "subcategory":"Cleaning & Sanitation",
            "type":"Services"
        }
    ],
    "sg:phone":"+1 251 639 3149",
    "sg:postcode":"36695",
    "sg:province":"AL",
    "wof:name":"Clean Sweep Cleaning Service",
    "wof:placetype":"venue"
},
  "geometry": {"coordinates":[-88.237547,30.634457],"type":"Point"}
}