{
  "type": "Feature",
  "properties": {
    "iso:country":"US",
    "sg:address":"4565 Co Rd 33",
    "sg:city":"Orrville",
    "sg:classifiers":[
        {
            "category":"Building & Trades",
            "subcategory":"Cleaning & Sanitation",
            "type":"Services"
        }
    ],
    "sg:phone":"+1 334 996 8226",
    "sg:postcode":"36767",
    "sg:province":"AL",
    "sg:tags":[
        "janitor"
    ],
    "wof:name":"R & R Cleaning Svc",
    "wof:placetype":"venue"
},
  "geometry": {"coordinates":[-87.236503,32.280528],"type":"Point"}
}