{
  "type": "Feature",
  "properties": {
    "iso:country":"US",
    "sg:address":"12758 Moore Rd",
    "sg:city":"Duncanville",
    "sg:classifiers":[
        {
            "category":"Recreation",
            "type":"Entertainment"
        }
    ],
    "sg:phone":"+1 205 391 0860",
    "sg:postcode":"35456",
    "sg:province":"AL",
    "sg:tags":[
        "club",
        "membership"
    ],
    "wof:name":"Topadah Hill Hunting Club",
    "wof:placetype":"venue"
},
  "geometry": {"coordinates":[-87.431831,33.080151],"type":"Point"}
}