{
  "type": "Feature",
  "properties": {
    "iso:country":"US",
    "sg:address":"8225 Stephanie Dr SW",
    "sg:city":"Huntsville",
    "sg:classifiers":[
        {
            "category":"Building & Trades",
            "subcategory":"Construction",
            "type":"Services"
        }
    ],
    "sg:phone":"+1 256 883 9443",
    "sg:postcode":"35802",
    "sg:province":"AL",
    "sg:tags":[
        "hanging",
        "help",
        "contractor"
    ],
    "wof:name":"Christian Maids Inc",
    "wof:placetype":"venue"
},
  "geometry": {"coordinates":[-86.567852,34.657783],"type":"Point"}
}