{
  "type": "Feature",
  "properties": {
    "iso:country":"US",
    "sg:address":"3298 Co Rd 427",
    "sg:city":"Elba",
    "sg:classifiers":[
        {
            "category":"Organizations",
            "subcategory":"Religious Organization",
            "type":"Services"
        }
    ],
    "sg:phone":"+1 334 897 3828",
    "sg:postcode":"36323",
    "sg:province":"AL",
    "wof:name":"Basin Baptist Church",
    "wof:placetype":"venue"
},
  "geometry": {"coordinates":[-86.126058,31.333117],"type":"Point"}
}