{
  "type": "Feature",
  "properties": {
    "iso:country":"US",
    "sg:address":"1600 32nd St SW",
    "sg:city":"Birmingham",
    "sg:classifiers":[
        {
            "category":"Retail",
            "subcategory":"Auto Repair",
            "type":"Services"
        }
    ],
    "sg:phone":"+1 205 929 0031",
    "sg:postcode":"35221",
    "sg:province":"AL",
    "sg:tags":[
        "general"
    ],
    "wof:name":"Scoopie Auto Clinic",
    "wof:placetype":"venue"
},
  "geometry": {"coordinates":[-86.884782,33.468564],"type":"Point"}
}