{
  "type": "Feature",
  "properties": {
    "iso:country":"US",
    "sg:address":"340 Bent Tree Dr",
    "sg:city":"Prattville",
    "sg:classifiers":[
        {
            "category":"Professional",
            "subcategory":"Computer Services",
            "type":"Services"
        }
    ],
    "sg:phone":"+1 334 491 4282",
    "sg:postcode":"36067",
    "sg:province":"AL",
    "sg:tags":[
        "programing",
        "custom"
    ],
    "wof:name":"Computer Commuter The",
    "wof:placetype":"venue"
},
  "geometry": {"coordinates":[-86.467576,32.470426],"type":"Point"}
}