{
  "type": "Feature",
  "properties": {
    "addr:full":"102 Main St Anniston AL 36203",
    "addr:housenumber":"102",
    "addr:postcode":"36203",
    "addr:street":"Main St",
    "iso:country":"US",
    "sg:address":"102 Main St",
    "sg:city":"Anniston",
    "sg:classifiers":[
        {
            "category":"Banks & Credit Unions",
            "subcategory":"Bank",
            "type":"Services"
        }
    ],
    "sg:phone":"+1 256 447 6055",
    "sg:postcode":"36203",
    "sg:province":"AL",
    "sg:tags":[
        "cashing",
        "check"
    ],
    "wof:name":"Check Advance",
    "wof:placetype":"venue"
},
  "geometry": {"coordinates":[-85.833742,33.619583],"type":"Point"}
}