{
  "type": "Feature",
  "properties": {
    "addr:full":"701 Martin Luther King Jr Ave Ozark AL 36360",
    "addr:housenumber":"701",
    "addr:postcode":"36360",
    "addr:street":"Martin Luther King Jr Ave",
    "iso:country":"US",
    "sg:address":"701 Martin Luther King Jr Ave",
    "sg:city":"Ozark",
    "sg:classifiers":[
        {
            "category":"Utilities",
            "subcategory":"Refuse",
            "type":"Services"
        }
    ],
    "sg:phone":"+1 334 735 5123",
    "sg:postcode":"36360",
    "sg:province":"AL",
    "sg:tags":[
        "garbage",
        "collection"
    ],
    "wof:name":"Mark Dunning Industries Inc",
    "wof:placetype":"venue"
},
  "geometry": {"coordinates":[-85.65663000000001,31.463165],"type":"Point"}
}