{
  "type": "Feature",
  "properties": {
    "iso:country":"US",
    "sg:address":"365 Head Dr",
    "sg:city":"Cleveland",
    "sg:classifiers":[
        {
            "category":"Real Estate",
            "subcategory":"Real Estate Agent",
            "type":"Services"
        }
    ],
    "sg:phone":"+1 205 625 5070",
    "sg:postcode":"35049",
    "sg:province":"AL",
    "sg:tags":[
        "appraiser"
    ],
    "wof:name":"Real Estate Appraisal Svc",
    "wof:placetype":"venue"
},
  "geometry": {"coordinates":[-86.582558,33.989113],"type":"Point"}
}