{
  "type": "Feature",
  "properties": {
    "addr:full":"195 Rainbow Cir Sylacauga AL 35151",
    "addr:housenumber":"195",
    "addr:postcode":"35151",
    "addr:street":"Rainbow Cir",
    "iso:country":"US",
    "sg:address":"195 Rainbow Cir",
    "sg:city":"Sylacauga",
    "sg:classifiers":[
        {
            "category":"Restaurant",
            "type":"Food & Drink"
        }
    ],
    "sg:phone":"+1 256 245 6531",
    "sg:postcode":"35151",
    "sg:province":"AL",
    "sg:tags":[
        "eating"
    ],
    "wof:name":"Mama Rees Resturant Inc",
    "wof:placetype":"venue"
},
  "geometry": {"coordinates":[-86.33622,33.244016],"type":"Point"}
}