{
  "type": "Feature",
  "properties": {
    "addr:full":"7448 US Hwy 431 Albertville AL 35950",
    "addr:housenumber":"7448",
    "addr:postcode":"35950",
    "addr:street":"Us Hwy 431",
    "iso:country":"US",
    "sg:address":"7448 US Hwy 431",
    "sg:city":"Albertville",
    "sg:classifiers":[
        {
            "category":"Arts & Performance",
            "subcategory":"Theater",
            "type":"Entertainment"
        }
    ],
    "sg:phone":"+1 256 891 1658",
    "sg:postcode":"35950",
    "sg:province":"AL",
    "sg:tags":[
        "group"
    ],
    "wof:name":"Lindseys Karaoke & D J Mus Co",
    "wof:placetype":"venue"
},
  "geometry": {"coordinates":[-86.20654999999999,34.276753],"type":"Point"}
}