{
  "type": "Feature",
  "properties": {
    "addr:full":"4520 Edwards St Brighton AL 35020",
    "addr:housenumber":"4520",
    "addr:postcode":"35020",
    "addr:street":"Edwards St",
    "iso:country":"US",
    "sg:address":"4520 Edwards St",
    "sg:city":"Brighton",
    "sg:classifiers":[
        {
            "category":"Organizations",
            "subcategory":"Religious Organization",
            "type":"Services"
        }
    ],
    "sg:phone":"+1 205 424 4330",
    "sg:postcode":"35020",
    "sg:province":"AL",
    "sg:tags":[
        "church"
    ],
    "wof:name":"First Baptist Church Woodward",
    "wof:placetype":"venue"
},
  "geometry": {"coordinates":[-86.951212,33.439168],"type":"Point"}
}