{
  "type": "Feature",
  "properties": {
    "addr:full":"1600 Carraway Blvd Birmingham AL 35234",
    "addr:housenumber":"1600",
    "addr:postcode":"35234",
    "addr:street":"Carraway Blvd",
    "iso:country":"US",
    "sg:address":"1600 Carraway Blvd",
    "sg:city":"Birmingham",
    "sg:classifiers":[
        {
            "category":"Restaurant",
            "type":"Food & Drink"
        }
    ],
    "sg:menulink":"http://www.allmenus.com/al/birmingham/55606-subway/menu/",
    "sg:phone":"+1 205 502 7827",
    "sg:postcode":"35234",
    "sg:province":"AL",
    "sg:tags":[
        "american",
        "sandwich"
    ],
    "wof:name":"Subway",
    "wof:placetype":"venue"
},
  "geometry": {"coordinates":[-86.809646,33.536391],"type":"Point"}
}