{
  "type": "Feature",
  "properties": {
    "addr:full":"3665 Westgate Pkwy Dothan AL 36303",
    "addr:housenumber":"3665",
    "addr:postcode":"36303",
    "addr:street":"Westgate Pkwy",
    "iso:country":"US",
    "sg:address":"3665 Westgate Pkwy",
    "sg:city":"Dothan",
    "sg:classifiers":[
        {
            "category":"Building & Trades",
            "subcategory":"Construction",
            "type":"Services"
        }
    ],
    "sg:phone":"+1 334 678 0376",
    "sg:postcode":"36303",
    "sg:province":"AL",
    "sg:tags":[
        "nonresidential"
    ],
    "wof:name":"Hugh Peacock Construction",
    "wof:placetype":"venue"
},
  "geometry": {"coordinates":[-85.408388,31.271845],"type":"Point"}
}