{
  "type": "Feature",
  "properties": {
    "iso:country":"US",
    "sg:address":"8720 Old Hwy 31 N",
    "sg:city":"Kimberly",
    "sg:classifiers":[
        {
            "category":"Food & Beverages",
            "subcategory":"Groceries & Convenience Stores",
            "type":"Retail Goods"
        }
    ],
    "sg:phone":"+1 205 590 4000",
    "sg:postcode":"35116",
    "sg:province":"AL",
    "wof:name":"Payless Sav Mor",
    "wof:placetype":"venue"
},
  "geometry": {"coordinates":[-86.81259799999999,33.760649],"type":"Point"}
}