{
  "type": "Feature",
  "properties": {
    "iso:country":"US",
    "sg:address":"2104 Warrior Rd",
    "sg:city":"Birmingham",
    "sg:classifiers":[
        {
            "category":"Building & Trades",
            "subcategory":"Construction",
            "type":"Services"
        }
    ],
    "sg:phone":"+1 205 786 6138",
    "sg:postcode":"35208",
    "sg:province":"AL",
    "sg:tags":[
        "roofing",
        "contractor"
    ],
    "wof:name":"Home Siding & Roofing Co",
    "wof:placetype":"venue"
},
  "geometry": {"coordinates":[-86.878525,33.497442],"type":"Point"}
}