{
  "type": "Feature",
  "properties": {
    "iso:country":"US",
    "sg:address":"219 Cherokee Heights Rd",
    "sg:city":"Tallassee",
    "sg:classifiers":[
        {
            "category":"Building & Trades",
            "subcategory":"Construction",
            "type":"Services"
        }
    ],
    "sg:phone":"+1 334 857 2470",
    "sg:postcode":"36078",
    "sg:province":"AL",
    "sg:tags":[
        "house"
    ],
    "wof:name":"Deep Water Dock Co LLC",
    "wof:placetype":"venue"
},
  "geometry": {"coordinates":[-85.926324,32.676845],"type":"Point"}
}