{
  "type": "Feature",
  "properties": {
    "addr:full":"292 Pin Oak Dr Chelsea AL 35043",
    "addr:housenumber":"292",
    "addr:postcode":"35043",
    "addr:street":"Pin Oak Dr",
    "iso:country":"US",
    "sg:address":"292 Pin Oak Dr",
    "sg:city":"Chelsea",
    "sg:classifiers":[
        {
            "category":"Professional",
            "subcategory":"Management & Consulting",
            "type":"Services"
        }
    ],
    "sg:phone":"+1 205 678 7145",
    "sg:postcode":"35043",
    "sg:province":"AL",
    "wof:name":"Marca Management Systems MMS L",
    "wof:placetype":"venue"
},
  "geometry": {"coordinates":[-86.638972,33.337959],"type":"Point"}
}