{
  "type": "Feature",
  "properties": {
    "addr:full":"8741 Moffett Rd Semmes AL 36575",
    "addr:housenumber":"8741",
    "addr:postcode":"36575",
    "addr:street":"Moffett Rd",
    "iso:country":"US",
    "sg:address":"8741 Moffett Rd",
    "sg:city":"Semmes",
    "sg:classifiers":[
        {
            "category":"Shopping",
            "subcategory":"Bicycles & Sporting Goods",
            "type":"Retail Goods"
        }
    ],
    "sg:phone":"+1 251 649 0703",
    "sg:postcode":"36575",
    "sg:province":"AL",
    "wof:name":"Gb Sportswear",
    "wof:placetype":"venue"
},
  "geometry": {"coordinates":[-88.249797,30.777581],"type":"Point"}
}