{
  "type": "Feature",
  "properties": {
    "iso:country":"US",
    "sg:address":"1361 Lazy Y Rd",
    "sg:city":"Hayden",
    "sg:classifiers":[
        {
            "category":"Freight",
            "type":"Transportation"
        }
    ],
    "sg:phone":"+1 205 590 4425",
    "sg:postcode":"35079",
    "sg:province":"AL",
    "sg:tags":[
        "trucking"
    ],
    "wof:name":"J R Express",
    "wof:placetype":"venue"
},
  "geometry": {"coordinates":[-86.89176500000001,33.879764],"type":"Point"}
}