{
  "type": "Feature",
  "properties": {
    "iso:country":"US",
    "sg:address":"3721 Sullivan St",
    "sg:city":"Madison",
    "sg:classifiers":[
        {
            "category":"Food & Beverages",
            "subcategory":"Groceries & Convenience Stores",
            "type":"Retail Goods"
        }
    ],
    "sg:phone":"+1 256 772 3733",
    "sg:postcode":"35758",
    "sg:province":"AL",
    "wof:name":"Express Food Marts",
    "wof:placetype":"venue"
},
  "geometry": {"coordinates":[-86.751965,34.676847],"type":"Point"}
}