{
  "type": "Feature",
  "properties": {
    "iso:country":"US",
    "sg:address":"4506 6th St E",
    "sg:city":"Tuscaloosa",
    "sg:classifiers":[
        {
            "category":"Professional",
            "type":"Services"
        }
    ],
    "sg:phone":"+1 205 553 1627",
    "sg:postcode":"35404",
    "sg:province":"AL",
    "wof:name":"Edward D Pierce",
    "wof:placetype":"venue"
},
  "geometry": {"coordinates":[-87.477775,33.20937],"type":"Point"}
}