{
  "type": "Feature",
  "properties": {
    "iso:country":"US",
    "sg:address":"119 Mt Rose Rd",
    "sg:city":"Georgiana",
    "sg:classifiers":[
        {
            "category":"Organizations",
            "subcategory":"Religious Organization",
            "type":"Services"
        }
    ],
    "sg:phone":"+1 334 376 9678",
    "sg:postcode":"36033",
    "sg:province":"AL",
    "wof:name":"Mt Rose Baptist Church",
    "wof:placetype":"venue"
},
  "geometry": {"coordinates":[-86.87996099999999,31.659668],"type":"Point"}
}