{
  "type": "Feature",
  "properties": {
    "iso:country":"US",
    "sg:address":"439 S College St",
    "sg:city":"Auburn",
    "sg:classifiers":[
        {
            "category":"Organizations",
            "subcategory":"Religious Organization",
            "type":"Services"
        }
    ],
    "sg:phone":"+1 334 821 1212",
    "sg:postcode":"36830",
    "sg:province":"AL",
    "wof:name":"Auburn Christian Student Ctr",
    "wof:placetype":"venue"
},
  "geometry": {"coordinates":[-85.481641,32.597542],"type":"Point"}
}