{
  "type": "Feature",
  "properties": {
    "addr:full":"104 Hammond Rd Harvest AL 35749",
    "addr:housenumber":"104",
    "addr:postcode":"35749",
    "addr:street":"Hammond Rd",
    "iso:country":"US",
    "sg:address":"104 Hammond Rd",
    "sg:city":"Harvest",
    "sg:phone":"+1 256 721 4677",
    "sg:postcode":"35749",
    "sg:province":"AL",
    "sg:tags":[
        "irrigation",
        "system"
    ],
    "wof:name":"Hughes Irrigation",
    "wof:placetype":"venue"
},
  "geometry": {"coordinates":[-86.772682,34.82102],"type":"Point"}
}