{
  "type": "Feature",
  "properties": {
    "addr:full":"2001 2nd Ave E Oneonta AL 35121",
    "addr:housenumber":"2001",
    "addr:postcode":"35121",
    "addr:street":"2Nd Ave E",
    "iso:country":"US",
    "sg:address":"2001 2nd Ave E",
    "sg:city":"Oneonta",
    "sg:classifiers":[
        {
            "category":"Manufacturing",
            "subcategory":"Tools & Machinery",
            "type":"Manufacturing & Wholesale Goods"
        }
    ],
    "sg:phone":"+1 205 625 3891",
    "sg:postcode":"35121",
    "sg:province":"AL",
    "sg:tags":[
        "machine",
        "shop"
    ],
    "wof:name":"Loftus/Robbins Inc",
    "wof:placetype":"venue"
},
  "geometry": {"coordinates":[-86.454838,33.967369],"type":"Point"}
}