{
  "type": "Feature",
  "properties": {
    "addr:full":"10545 Co Rd 45 Centre AL 35960",
    "addr:housenumber":"10545;45",
    "addr:postcode":"35960",
    "addr:street":"Co Rd;Centre",
    "iso:country":"US",
    "sg:address":"10545 Co Rd 45",
    "sg:city":"Centre",
    "sg:classifiers":[
        {
            "category":"Farming",
            "subcategory":"Nursery",
            "type":"Manufacturing & Wholesale Goods"
        }
    ],
    "sg:phone":"+1 256 475 3520",
    "sg:postcode":"35960",
    "sg:province":"AL",
    "sg:tags":[
        "vineyard",
        "ornamental",
        "grape"
    ],
    "wof:name":"Curtis Graham",
    "wof:placetype":"venue"
},
  "geometry": {"coordinates":[-85.49838699999999,34.127119],"type":"Point"}
}