{
  "type": "Feature",
  "properties": {
    "iso:country":"US",
    "sg:address":"320 Montclair Dr",
    "sg:city":"Gadsden",
    "sg:classifiers":[
        {
            "category":"Manufacturing",
            "subcategory":"Tools & Machinery",
            "type":"Manufacturing & Wholesale Goods"
        }
    ],
    "sg:phone":"+1 256 442 6255",
    "sg:postcode":"35901",
    "sg:province":"AL",
    "sg:tags":[
        "filtering",
        "material",
        "supply"
    ],
    "wof:name":"Alabama Filer Specialists Inc",
    "wof:placetype":"venue"
},
  "geometry": {"coordinates":[-86.005793,33.949089],"type":"Point"}
}