{
  "type": "Feature",
  "properties": {
    "iso:country":"US",
    "sg:address":"1820 Bexar Ave W",
    "sg:city":"Hamilton",
    "sg:classifiers":[
        {
            "category":"Manufacturing",
            "subcategory":"Metals",
            "type":"Manufacturing & Wholesale Goods"
        }
    ],
    "sg:phone":"+1 205 921 2208",
    "sg:postcode":"35570",
    "sg:province":"AL",
    "sg:tags":[
        "steel"
    ],
    "wof:name":"Big D Welding",
    "wof:placetype":"venue"
},
  "geometry": {"coordinates":[-88.016439,34.155589],"type":"Point"}
}