{
  "type": "Feature",
  "properties": {
    "iso:country":"US",
    "sg:address":"14 Forest Home Pl",
    "sg:city":"Trinity",
    "sg:classifiers":[
        {
            "category":"Freight",
            "type":"Transportation"
        }
    ],
    "sg:phone":"+1 256 353 5705",
    "sg:postcode":"35673",
    "sg:province":"AL",
    "sg:tags":[
        "operator",
        "local",
        "trucking"
    ],
    "wof:name":"South & South Trucking Inc",
    "wof:placetype":"venue"
},
  "geometry": {"coordinates":[-87.066613,34.611987],"type":"Point"}
}