{
  "type": "Feature",
  "properties": {
    "iso:country":"US",
    "sg:address":"725 Lisa Ln",
    "sg:city":"Birmingham",
    "sg:classifiers":[
        {
            "category":"Restaurant",
            "type":"Food & Drink"
        }
    ],
    "sg:phone":"+1 205 838 1442",
    "sg:postcode":"35206",
    "sg:province":"AL",
    "sg:tags":[
        "eating",
        "real estate"
    ],
    "wof:name":"Famous Properties Corporation",
    "wof:placetype":"venue"
},
  "geometry": {"coordinates":[-86.679361,33.584056],"type":"Point"}
}