{
  "type": "Feature",
  "properties": {
    "addr:full":"211 Co Rd 455 Killen AL 35645",
    "addr:housenumber":"211",
    "addr:postcode":"35645",
    "addr:street":"Co Rd 455",
    "iso:country":"US",
    "sg:address":"211 Co Rd 455",
    "sg:city":"Killen",
    "sg:classifiers":[
        {
            "category":"Building & Trades",
            "subcategory":"Construction",
            "type":"Services"
        }
    ],
    "sg:phone":"+1 256 757 1140",
    "sg:postcode":"35645",
    "sg:province":"AL",
    "sg:tags":[
        "house"
    ],
    "wof:name":"Alabama Sunrooms",
    "wof:placetype":"venue"
},
  "geometry": {"coordinates":[-87.56434299999999,34.8552],"type":"Point"}
}