{
  "type": "Feature",
  "properties": {
    "addr:full":"2330 McFarland Blvd E Tuscaloosa AL 35404",
    "addr:housenumber":"2330",
    "addr:postcode":"35404",
    "addr:street":"Mcfarland Blvd E",
    "iso:country":"US",
    "sg:address":"2330 McFarland Blvd E",
    "sg:city":"Tuscaloosa",
    "sg:classifiers":[
        {
            "category":"Professional",
            "subcategory":"Accounting & Tax Preparation",
            "type":"Services"
        }
    ],
    "sg:phone":"+1 205 758 3474",
    "sg:postcode":"35404",
    "sg:province":"AL",
    "sg:tags":[
        "return"
    ],
    "wof:name":"H & R Block",
    "wof:placetype":"venue"
},
  "geometry": {"coordinates":[-87.525918,33.188865],"type":"Point"}
}