{
  "type": "Feature",
  "properties": {
    "iso:country":"US",
    "sg:address":"708 Bank St",
    "sg:city":"Birmingham",
    "sg:classifiers":[
        {
            "category":"Retail",
            "subcategory":"Repair Shop",
            "type":"Services"
        }
    ],
    "sg:phone":"+1 205 780 8019",
    "sg:postcode":"35224",
    "sg:province":"AL",
    "sg:tags":[
        "appliance",
        "electrical"
    ],
    "wof:name":"Central Appliance Service",
    "wof:placetype":"venue"
},
  "geometry": {"coordinates":[-86.921561,33.505214],"type":"Point"}
}