{
  "type": "Feature",
  "properties": {
    "iso:country":"US",
    "sg:address":"2105 Mastin Lake Rd NW",
    "sg:city":"Huntsville",
    "sg:classifiers":[
        {
            "category":"Personal",
            "subcategory":"Beauty Salon",
            "type":"Services"
        }
    ],
    "sg:phone":"+1 256 852 0690",
    "sg:postcode":"35810",
    "sg:province":"AL",
    "sg:tags":[
        "shop"
    ],
    "wof:name":"Max Ask Styling Salon",
    "wof:placetype":"venue"
},
  "geometry": {"coordinates":[-86.58694,34.771039],"type":"Point"}
}