{
  "type": "Feature",
  "properties": {
    "addr:full":"117 84th St N Birmingham AL 35206",
    "addr:housenumber":"117",
    "addr:postcode":"35206",
    "addr:street":"84Th St N",
    "iso:country":"US",
    "sg:address":"117 84th St N",
    "sg:city":"Birmingham",
    "sg:classifiers":[
        {
            "category":"Government",
            "subcategory":"Police Station",
            "type":"Public Place"
        }
    ],
    "sg:phone":"+1 205 254 2685",
    "sg:postcode":"35206",
    "sg:province":"AL",
    "sg:tags":[
        "department"
    ],
    "wof:name":"Birmingham Police Dept",
    "wof:placetype":"venue"
},
  "geometry": {"coordinates":[-86.723698,33.573723],"type":"Point"}
}