{
  "type": "Feature",
  "properties": {
    "iso:country":"US",
    "sg:address":"7400 Cahaba Valley Rd",
    "sg:city":"Birmingham",
    "sg:classifiers":[
        {
            "category":"Professional",
            "subcategory":"Business Services",
            "type":"Services"
        }
    ],
    "sg:phone":"+1 205 980 1870",
    "sg:postcode":"35242",
    "sg:province":"AL",
    "wof:name":"Open Systems Group Inc",
    "wof:placetype":"venue"
},
  "geometry": {"coordinates":[-86.661468,33.437466],"type":"Point"}
}