{
  "type": "Feature",
  "properties": {
    "iso:country":"US",
    "sg:address":"7360 Theodore Dawes Rd",
    "sg:city":"Theodore",
    "sg:classifiers":[
        {
            "category":"Autos & Motor Vehicles",
            "subcategory":"Fuel & Gas Station",
            "type":"Retail Goods"
        }
    ],
    "sg:phone":"+1 251 653 1210",
    "sg:postcode":"36582",
    "sg:province":"AL",
    "sg:tags":[
        "station",
        "gasoline"
    ],
    "wof:name":"Seaborn Texaco",
    "wof:placetype":"venue"
},
  "geometry": {"coordinates":[-88.218788,30.567899],"type":"Point"}
}