{
  "type": "Feature",
  "properties": {
    "addr:full":"2806 Bob Wallace Ave SW Huntsville AL 35805",
    "addr:housenumber":"2806",
    "addr:postcode":"35805",
    "addr:street":"Bob Wallace Ave Sw",
    "iso:country":"US",
    "sg:address":"2806 Bob Wallace Ave SW",
    "sg:city":"Huntsville",
    "sg:classifiers":[
        {
            "category":"Home & Garden",
            "subcategory":"Carpets & Floor Coverings",
            "type":"Retail Goods"
        }
    ],
    "sg:phone":"+1 256 536 8086",
    "sg:postcode":"35805",
    "sg:province":"AL",
    "sg:tags":[
        "dealer",
        "rug"
    ],
    "wof:name":"Haley's Flooring & Interiors",
    "wof:placetype":"venue"
},
  "geometry": {"coordinates":[-86.601682,34.711439],"type":"Point"}
}