{
  "type": "Feature",
  "properties": {
    "iso:country":"US",
    "sg:address":"1635 Perry Hill Rd",
    "sg:city":"Montgomery",
    "sg:classifiers":[
        {
            "category":"Food & Beverages",
            "subcategory":"Groceries & Convenience Stores",
            "type":"Retail Goods"
        }
    ],
    "sg:phone":"+1 334 244 1636",
    "sg:postcode":"36106",
    "sg:province":"AL",
    "sg:tags":[
        "supermarket"
    ],
    "wof:name":"Brunos 231",
    "wof:placetype":"venue"
},
  "geometry": {"coordinates":[-86.243772,32.3541],"type":"Point"}
}