{
  "type": "Feature",
  "properties": {
    "iso:country":"US",
    "sg:address":"319 McKenzie St",
    "sg:city":"Foley",
    "sg:classifiers":[
        {
            "category":"Shopping",
            "subcategory":"Used Merchandise",
            "type":"Retail Goods"
        },
        {
            "category":"Banks & Credit Unions",
            "subcategory":"Bank",
            "type":"Services"
        }
    ],
    "sg:phone":"+1 251 970 2274",
    "sg:postcode":"36535",
    "sg:province":"AL",
    "sg:tags":[
        "loan"
    ],
    "wof:name":"Title Pawn Express",
    "wof:placetype":"venue"
},
  "geometry": {"coordinates":[-87.683755,30.404698],"type":"Point"}
}