{
  "type": "Feature",
  "properties": {
    "iso:country":"US",
    "sg:address":"802 Main Ave NE",
    "sg:city":"Cullman",
    "sg:classifiers":[
        {
            "category":"Shopping",
            "subcategory":"Shoes",
            "type":"Retail Goods"
        }
    ],
    "sg:phone":"+1 256 739 3858",
    "sg:postcode":"35055",
    "sg:province":"AL",
    "wof:name":"House of Shoes",
    "wof:placetype":"venue"
},
  "geometry": {"coordinates":[-86.847576,34.185436],"type":"Point"}
}