{
  "type": "Feature",
  "properties": {
    "addr:full":"233 Deatsville Hwy Millbrook AL 36054",
    "addr:housenumber":"233",
    "addr:postcode":"36054",
    "addr:street":"Deatsville Hwy",
    "iso:country":"US",
    "sg:address":"233 Deatsville Hwy",
    "sg:city":"Millbrook",
    "sg:classifiers":[
        {
            "category":"Real Estate",
            "subcategory":"Real Estate Agent",
            "type":"Services"
        }
    ],
    "sg:phone":"+1 334 290 1914",
    "sg:postcode":"36054",
    "sg:province":"AL",
    "wof:name":"Sun Real Estate",
    "wof:placetype":"venue"
},
  "geometry": {"coordinates":[-86.37539599999999,32.521273],"type":"Point"}
}