{
  "type": "Feature",
  "properties": {
    "addr:full":"1858 Seale St Mobile AL 36617",
    "addr:housenumber":"1858",
    "addr:postcode":"36617",
    "addr:street":"Seale St",
    "iso:country":"US",
    "sg:address":"1858 Seale St",
    "sg:city":"Mobile",
    "sg:classifiers":[
        {
            "category":"Retail",
            "subcategory":"Portrait Studio",
            "type":"Services"
        }
    ],
    "sg:phone":"+1 251 457 6966",
    "sg:postcode":"36617",
    "sg:province":"AL",
    "sg:tags":[
        "photographer"
    ],
    "wof:name":"Murphy's Photography Svc",
    "wof:placetype":"venue"
},
  "geometry": {"coordinates":[-88.084943,30.718164],"type":"Point"}
}