{
  "type": "Feature",
  "properties": {
    "iso:country":"US",
    "sg:address":"122 1st St SE",
    "sg:city":"Hamilton",
    "sg:classifiers":[
        {
            "category":"Professional",
            "subcategory":"Lawyer & Legal Services",
            "type":"Services"
        }
    ],
    "sg:phone":"+1 205 921 7488",
    "sg:postcode":"35570",
    "sg:province":"AL",
    "sg:tags":[
        "attorney"
    ],
    "wof:name":"J O Isom",
    "wof:placetype":"venue"
},
  "geometry": {"coordinates":[-87.98770500000001,34.14089],"type":"Point"}
}