{
  "type": "Feature",
  "properties": {
    "iso:country":"US",
    "sg:address":"9235 Vallaris St S",
    "sg:city":"Mobile",
    "sg:classifiers":[
        {
            "category":"Utilities",
            "subcategory":"Refuse",
            "type":"Services"
        }
    ],
    "sg:phone":"+1 251 639 9733",
    "sg:postcode":"36608",
    "sg:province":"AL",
    "sg:tags":[
        "system"
    ],
    "wof:name":"H & L Sanitation",
    "wof:placetype":"venue"
},
  "geometry": {"coordinates":[-88.259551,30.717465],"type":"Point"}
}