{
  "type": "Feature",
  "properties": {
    "addr:full":"101 Resource Center Pkwy Birmingham AL 35242",
    "addr:housenumber":"101",
    "addr:postcode":"35242",
    "addr:street":"Resource Center Pkwy",
    "iso:country":"US",
    "sg:address":"101 Resource Center Pkwy",
    "sg:city":"Birmingham",
    "sg:classifiers":[
        {
            "category":"Restaurant",
            "type":"Food & Drink"
        }
    ],
    "sg:phone":"+1 205 995 0059",
    "sg:postcode":"35242",
    "sg:province":"AL",
    "sg:tags":[
        "eating"
    ],
    "sg:website":"www.bahamabreeze.com",
    "wof:name":"Bahama Breeze",
    "wof:placetype":"venue"
},
  "geometry": {"coordinates":[-86.707571,33.427202],"type":"Point"}
}