{
  "type": "Feature",
  "properties": {
    "iso:country":"US",
    "sg:address":"3 Co Rd 40",
    "sg:city":"Eufaula",
    "sg:classifiers":[
        {
            "category":"Freight",
            "type":"Transportation"
        }
    ],
    "sg:phone":"+1 334 687 6238",
    "sg:postcode":"36027",
    "sg:province":"AL",
    "sg:tags":[
        "operator",
        "local",
        "trucking"
    ],
    "wof:name":"Mud Bugs Trucking LLC",
    "wof:placetype":"venue"
},
  "geometry": {"coordinates":[-85.190735,31.767996],"type":"Point"}
}