{
  "type": "Feature",
  "properties": {
    "iso:country":"US",
    "sg:address":"250 Hillcrest Dr",
    "sg:city":"Andalusia",
    "sg:classifiers":[
        {
            "category":"Government",
            "subcategory":"Office",
            "type":"Public Place"
        }
    ],
    "sg:phone":"+1 334 428 2687",
    "sg:postcode":"36420",
    "sg:province":"AL",
    "sg:tags":[
        "admin",
        "affairs",
        "state"
    ],
    "wof:name":"Covington Cnty Veterans Affair",
    "wof:placetype":"venue"
},
  "geometry": {"coordinates":[-86.501876,31.313477],"type":"Point"}
}