{
  "type": "Feature",
  "properties": {
    "iso:country":"US",
    "sg:address":"6500 Co Rd 217",
    "sg:city":"Hillsboro",
    "sg:classifiers":[
        {
            "category":"Shopping",
            "subcategory":"Music",
            "type":"Retail Goods"
        }
    ],
    "sg:phone":"+1 256 974 9820",
    "sg:postcode":"35643",
    "sg:province":"AL",
    "wof:name":"Reeds Video",
    "wof:placetype":"venue"
},
  "geometry": {"coordinates":[-87.20199100000001,34.569693],"type":"Point"}
}