{
  "type": "Feature",
  "properties": {
    "iso:country":"US",
    "sg:address":"6603 Terrace Ct",
    "sg:city":"Fairfield",
    "sg:classifiers":[
        {
            "category":"Professional",
            "subcategory":"Computer Services",
            "type":"Services"
        }
    ],
    "sg:phone":"+1 205 923 8805",
    "sg:postcode":"35064",
    "sg:province":"AL",
    "sg:tags":[
        "management",
        "facility"
    ],
    "wof:name":"Cutressa Inc",
    "wof:placetype":"venue"
},
  "geometry": {"coordinates":[-86.916128,33.4724],"type":"Point"}
}