{
  "type": "Feature",
  "properties": {
    "iso:country":"US",
    "sg:address":"203 Kirkland St",
    "sg:city":"Abbeville",
    "sg:classifiers":[
        {
            "category":"Retail",
            "subcategory":"Laundry & Dry Cleaning",
            "type":"Services"
        }
    ],
    "sg:phone":"+1 334 585 3533",
    "sg:postcode":"36310",
    "sg:province":"AL",
    "sg:tags":[
        "drycleaning",
        "plant"
    ],
    "wof:name":"Richardson Cleaners",
    "wof:placetype":"venue"
},
  "geometry": {"coordinates":[-85.250431,31.569274],"type":"Point"}
}