{
  "type": "Feature",
  "properties": {
    "iso:country":"US",
    "sg:address":"9831 Harvest Ln",
    "sg:city":"Tuscaloosa",
    "sg:classifiers":[
        {
            "category":"Professional",
            "type":"Services"
        }
    ],
    "sg:phone":"+1 205 752 4690",
    "sg:postcode":"35405",
    "sg:province":"AL",
    "wof:name":"Matthew Summerford",
    "wof:placetype":"venue"
},
  "geometry": {"coordinates":[-87.54580799999999,33.117557],"type":"Point"}
}