{
  "type": "Feature",
  "properties": {
    "iso:country":"US",
    "sg:address":"2616 Shoal Pl",
    "sg:city":"Northport",
    "sg:classifiers":[
        {
            "category":"Manufacturing",
            "subcategory":"Printing",
            "type":"Manufacturing & Wholesale Goods"
        }
    ],
    "sg:phone":"+1 205 330 0227",
    "sg:postcode":"35473",
    "sg:province":"AL",
    "sg:tags":[
        "publisher"
    ],
    "wof:name":"Tuscaloosa Christian Family",
    "wof:placetype":"venue"
},
  "geometry": {"coordinates":[-87.585381,33.250546],"type":"Point"}
}