{
  "type": "Feature",
  "properties": {
    "iso:country":"US",
    "sg:address":"808 Downtowner Blvd",
    "sg:city":"Mobile",
    "sg:classifiers":[
        {
            "category":"Professional",
            "subcategory":"Lawyer & Legal Services",
            "type":"Services"
        }
    ],
    "sg:phone":"+1 251 461 9990",
    "sg:postcode":"36609",
    "sg:province":"AL",
    "sg:tags":[
        "attorney"
    ],
    "wof:name":"Resolutions LLC",
    "wof:placetype":"venue"
},
  "geometry": {"coordinates":[-88.140205,30.673358],"type":"Point"}
}