{
  "type": "Feature",
  "properties": {
    "iso:country":"US",
    "sg:address":"325 Co Rd 606",
    "sg:city":"Hanceville",
    "sg:classifiers":[
        {
            "category":"Building & Trades",
            "subcategory":"Construction",
            "type":"Services"
        }
    ],
    "sg:phone":"+1 256 352 4760",
    "sg:postcode":"35077",
    "sg:province":"AL",
    "sg:tags":[
        "utility",
        "contractor"
    ],
    "wof:name":"Bussman Construction Co Inc",
    "wof:placetype":"venue"
},
  "geometry": {"coordinates":[-86.778856,34.102325],"type":"Point"}
}