{
  "type": "Feature",
  "properties": {
    "iso:country":"US",
    "sg:address":"21 Ellis St",
    "sg:city":"Russellville",
    "sg:classifiers":[
        {
            "category":"Professional",
            "subcategory":"Management & Consulting",
            "type":"Services"
        }
    ],
    "sg:phone":"+1 256 332 1090",
    "sg:postcode":"35654",
    "sg:province":"AL",
    "sg:tags":[
        "consultant",
        "security",
        "system"
    ],
    "wof:name":"THS Security",
    "wof:placetype":"venue"
},
  "geometry": {"coordinates":[-87.71139700000001,34.493235],"type":"Point"}
}