{
  "type": "Feature",
  "properties": {
    "iso:country":"US",
    "sg:address":"4104 Cogswell Ave",
    "sg:city":"Pell City",
    "sg:classifiers":[
        {
            "category":"Bars & Pubs",
            "type":"Food & Drink"
        }
    ],
    "sg:phone":"+1 205 814 5482",
    "sg:postcode":"35125",
    "sg:province":"AL",
    "sg:tags":[
        "drinking"
    ],
    "wof:name":"Her-Icanes Sports Bar",
    "wof:placetype":"venue"
},
  "geometry": {"coordinates":[-86.257482,33.592209],"type":"Point"}
}