{
  "type": "Feature",
  "properties": {
    "iso:country":"US",
    "sg:address":"2216 Executive Park Dr",
    "sg:city":"Opelika",
    "sg:classifiers":[
        {
            "category":"Government",
            "subcategory":"Office",
            "type":"Public Place"
        }
    ],
    "sg:phone":"+1 334 745 6221",
    "sg:postcode":"36801",
    "sg:province":"AL",
    "sg:tags":[
        "legislative",
        "body"
    ],
    "wof:name":"Congressman Bob Riley",
    "wof:placetype":"venue"
},
  "geometry": {"coordinates":[-85.438365,32.629287],"type":"Point"}
}