{
  "type": "Feature",
  "properties": {
    "addr:full":"1101 Worthy Ave Dothan AL 36303",
    "addr:housenumber":"1101",
    "addr:postcode":"36303",
    "addr:street":"Worthy Ave",
    "iso:country":"US",
    "sg:address":"1101 Worthy Ave",
    "sg:city":"Dothan",
    "sg:classifiers":[
        {
            "category":"Organizations",
            "subcategory":"Religious Organization",
            "type":"Services"
        }
    ],
    "sg:phone":"+1 334 677 2991",
    "sg:postcode":"36303",
    "sg:province":"AL",
    "wof:name":"7th United Holiness Church",
    "wof:placetype":"venue"
},
  "geometry": {"coordinates":[-85.371275,31.237633],"type":"Point"}
}