{
  "type": "Feature",
  "properties": {
    "addr:full":"1230 Westgate Pkwy Dothan AL 36303",
    "addr:housenumber":"1230",
    "addr:postcode":"36303",
    "addr:street":"Westgate Pkwy",
    "iso:country":"US",
    "sg:address":"1230 Westgate Pkwy",
    "sg:city":"Dothan",
    "sg:classifiers":[
        {
            "category":"Personal",
            "subcategory":"Beauty Salon",
            "type":"Services"
        }
    ],
    "sg:phone":"+1 334 712 1600",
    "sg:postcode":"36303",
    "sg:province":"AL",
    "sg:tags":[
        "manicuring"
    ],
    "wof:name":"Fancy Nails",
    "wof:placetype":"venue"
},
  "geometry": {"coordinates":[-85.43496399999999,31.25367],"type":"Point"}
}