{
  "type": "Feature",
  "properties": {
    "addr:full":"2345 1st St S Birmingham AL 35205",
    "addr:housenumber":"2345",
    "addr:postcode":"35205",
    "addr:street":"1St St S",
    "iso:country":"US",
    "sg:address":"2345 1st St S",
    "sg:city":"Birmingham",
    "sg:classifiers":[
        {
            "category":"Retail",
            "subcategory":"Funeral Services",
            "type":"Services"
        }
    ],
    "sg:phone":"+1 205 592 6500",
    "sg:postcode":"35205",
    "sg:province":"AL",
    "wof:name":"Mullins Funeral Service East",
    "wof:placetype":"venue"
},
  "geometry": {"coordinates":[-86.828703,33.478527],"type":"Point"}
}