{
  "type": "Feature",
  "properties": {
    "iso:country":"US",
    "sg:address":"108 Mallard Dr",
    "sg:city":"Troy",
    "sg:classifiers":[
        {
            "category":"Recreation",
            "type":"Entertainment"
        }
    ],
    "sg:phone":"+1 334 566 2159",
    "sg:postcode":"36081",
    "sg:province":"AL",
    "sg:tags":[
        "club",
        "sport"
    ],
    "wof:name":"Troy Tennis Assn",
    "wof:placetype":"venue"
},
  "geometry": {"coordinates":[-85.90472800000001,31.794697],"type":"Point"}
}