{
  "type": "Feature",
  "properties": {
    "iso:country":"US",
    "sg:address":"604 Old Montgomery Hwy",
    "sg:city":"Wetumpka",
    "sg:classifiers":[
        {
            "category":"Building & Trades",
            "subcategory":"Construction",
            "type":"Services"
        }
    ],
    "sg:phone":"+1 334 567 5523",
    "sg:postcode":"36092",
    "sg:province":"AL",
    "sg:tags":[
        "small",
        "repair",
        "remodeling",
        "family",
        "house"
    ],
    "wof:name":"Richard Clay Murrell",
    "wof:placetype":"venue"
},
  "geometry": {"coordinates":[-86.20706800000001,32.513296],"type":"Point"}
}