{
  "type": "Feature",
  "properties": {
    "iso:country":"US",
    "sg:address":"231 Prospector Rd",
    "sg:city":"Hackleburg",
    "sg:classifiers":[
        {
            "category":"Building & Trades",
            "subcategory":"Plumbing",
            "type":"Services"
        }
    ],
    "sg:phone":"+1 205 935 3546",
    "sg:postcode":"35564",
    "sg:province":"AL",
    "sg:tags":[
        "contractor"
    ],
    "wof:name":"Shackelford & Son Heating",
    "wof:placetype":"venue"
},
  "geometry": {"coordinates":[-87.85287099999999,34.233049],"type":"Point"}
}