{
  "type": "Feature",
  "properties": {
    "addr:full":"1205 Altadena Rise Birmingham AL 35242",
    "addr:housenumber":"1205",
    "addr:postcode":"35242",
    "addr:street":"Altadena Rise",
    "iso:country":"US",
    "sg:address":"1205 Altadena Rise",
    "sg:city":"Birmingham",
    "sg:classifiers":[
        {
            "category":"Building & Trades",
            "subcategory":"Landscaping Services",
            "type":"Services"
        }
    ],
    "sg:phone":"+1 205 915 4975",
    "sg:postcode":"35242",
    "sg:province":"AL",
    "wof:name":"Michael L Gaddis",
    "wof:placetype":"venue"
},
  "geometry": {"coordinates":[-86.73878499999999,33.413518],"type":"Point"}
}