{
  "type": "Feature",
  "properties": {
    "iso:country":"US",
    "sg:address":"9 S Ann Ave",
    "sg:city":"Tallassee",
    "sg:classifiers":[
        {
            "category":"Shopping",
            "subcategory":"Clothing, Apparel, & Fashions",
            "type":"Retail Goods"
        }
    ],
    "sg:phone":"+1 334 283 5695",
    "sg:postcode":"36078",
    "sg:province":"AL",
    "sg:tags":[
        "family"
    ],
    "wof:name":"Copywrite Clothing Company",
    "wof:placetype":"venue"
},
  "geometry": {"coordinates":[-85.893227,32.533092],"type":"Point"}
}