{
  "type": "Feature",
  "properties": {
    "iso:country":"US",
    "sg:address":"10616 Taylors Ferry Rd",
    "sg:city":"Bessemer",
    "sg:classifiers":[
        {
            "category":"Building & Trades",
            "subcategory":"Construction",
            "type":"Services"
        }
    ],
    "sg:phone":"+1 205 436 3439",
    "sg:postcode":"35023",
    "sg:province":"AL",
    "sg:tags":[
        "concrete",
        "work",
        "contractor"
    ],
    "wof:name":"Heads Alton Contracting Co",
    "wof:placetype":"venue"
},
  "geometry": {"coordinates":[-87.199974,33.547118],"type":"Point"}
}