{
  "type": "Feature",
  "properties": {
    "addr:full":"2533 US Hwy 82 Prattville AL 36067",
    "addr:housenumber":"2533",
    "addr:postcode":"36067",
    "addr:street":"Us Hwy 82",
    "iso:country":"US",
    "sg:address":"2533 US Hwy 82",
    "sg:city":"Prattville",
    "sg:classifiers":[
        {
            "category":"Organizations",
            "subcategory":"Religious Organization",
            "type":"Services"
        }
    ],
    "sg:phone":"+1 334 365 0714",
    "sg:postcode":"36067",
    "sg:province":"AL",
    "wof:name":"Peace Baptist Church",
    "wof:placetype":"venue"
},
  "geometry": {"coordinates":[-86.641071,32.537385],"type":"Point"}
}