{
  "type": "Feature",
  "properties": {
    "addr:full":"13500 Jefferey Rd Wilmer AL 36587",
    "addr:housenumber":"13500",
    "addr:postcode":"36587",
    "addr:street":"Jefferey Rd",
    "iso:country":"US",
    "sg:address":"13500 Jefferey Rd",
    "sg:city":"Wilmer",
    "sg:classifiers":[
        {
            "category":"Professional",
            "subcategory":"Business Services",
            "type":"Services"
        }
    ],
    "sg:phone":"+1 251 645 0897",
    "sg:postcode":"36587",
    "sg:province":"AL",
    "wof:name":"Chili Peppers",
    "wof:placetype":"venue"
},
  "geometry": {"coordinates":[-88.361182,30.79172],"type":"Point"}
}