{
  "type": "Feature",
  "properties": {
    "iso:country":"US",
    "sg:address":"236 6th Ave",
    "sg:city":"Ashville",
    "sg:classifiers":[
        {
            "category":"Professional",
            "subcategory":"Lawyer & Legal Services",
            "type":"Services"
        }
    ],
    "sg:phone":"+1 205 594 7749",
    "sg:postcode":"35953",
    "sg:province":"AL",
    "sg:tags":[
        "attorney"
    ],
    "wof:name":"Fred W Teague",
    "wof:placetype":"venue"
},
  "geometry": {"coordinates":[-86.25145500000001,33.836442],"type":"Point"}
}