{
  "type": "Feature",
  "properties": {
    "iso:country":"US",
    "sg:address":"151 Hinds Rd",
    "sg:city":"Arab",
    "sg:classifiers":[
        {
            "category":"Home & Garden",
            "subcategory":"Building Materials",
            "type":"Retail Goods"
        },
        {
            "category":"Building & Trades",
            "subcategory":"Construction",
            "type":"Services"
        }
    ],
    "sg:phone":"+1 256 753 2948",
    "sg:postcode":"35016",
    "sg:province":"AL",
    "sg:tags":[
        "mfg",
        "contractor",
        "member",
        "wood",
        "structural",
        "truss",
        "carpentry"
    ],
    "wof:name":"Trusswalk Truss Company",
    "wof:placetype":"venue"
},
  "geometry": {"coordinates":[-86.436979,34.359041],"type":"Point"}
}