{
  "type": "Feature",
  "properties": {
    "iso:country":"US",
    "sg:address":"306 Walnut St",
    "sg:city":"Greenville",
    "sg:classifiers":[
        {
            "category":"Organizations",
            "subcategory":"Religious Organization",
            "type":"Services"
        }
    ],
    "sg:phone":"+1 334 382 3001",
    "sg:postcode":"36037",
    "sg:province":"AL",
    "sg:tags":[
        "church"
    ],
    "wof:name":"Walnut Street Church Of Christ",
    "wof:placetype":"venue"
},
  "geometry": {"coordinates":[-86.62137,31.828737],"type":"Point"}
}