{
  "type": "Feature",
  "properties": {
    "iso:country":"US",
    "sg:address":"1801 41st St",
    "sg:city":"Valley",
    "sg:classifiers":[
        {
            "category":"Organizations",
            "subcategory":"Religious Organization",
            "type":"Services"
        }
    ],
    "sg:phone":"+1 334 756 2929",
    "sg:postcode":"36854",
    "sg:province":"AL",
    "sg:tags":[
        "church"
    ],
    "wof:name":"Faith Baptist Church Inc",
    "wof:placetype":"venue"
},
  "geometry": {"coordinates":[-85.174286,32.831801],"type":"Point"}
}