{
  "type": "Feature",
  "properties": {
    "iso:country":"US",
    "sg:address":"1501 Mulberry St",
    "sg:city":"Montgomery",
    "sg:classifiers":[
        {
            "category":"Insurance",
            "subcategory":"Insurance Agent",
            "type":"Services"
        }
    ],
    "sg:phone":"+1 334 834 7565",
    "sg:postcode":"36106",
    "sg:province":"AL",
    "wof:name":"Alex Bowden Insurance Inc",
    "wof:placetype":"venue"
},
  "geometry": {"coordinates":[-86.283136,32.365032],"type":"Point"}
}