{
  "type": "Feature",
  "properties": {
    "iso:country":"US",
    "sg:address":"501 9th Ave",
    "sg:city":"Birmingham",
    "sg:classifiers":[
        {
            "category":"Organizations",
            "subcategory":"Community Association",
            "type":"Services"
        }
    ],
    "sg:phone":"+1 205 999 6159",
    "sg:postcode":"35228",
    "sg:province":"AL",
    "sg:tags":[
        "shelter"
    ],
    "wof:name":"Guiding Light Mission II Inc",
    "wof:placetype":"venue"
},
  "geometry": {"coordinates":[-86.940038,33.453185],"type":"Point"}
}