{
  "type": "Feature",
  "properties": {
    "iso:country":"US",
    "sg:address":"3226 Rainbow Dr",
    "sg:city":"Rainbow City",
    "sg:classifiers":[
        {
            "category":"Health Services",
            "subcategory":"Doctor",
            "type":"Services"
        }
    ],
    "sg:phone":"+1 256 442 8380",
    "sg:postcode":"35906",
    "sg:province":"AL",
    "sg:tags":[
        "physician",
        "surgeon",
        "medical"
    ],
    "wof:name":"S P Sancheti MD",
    "wof:placetype":"venue"
},
  "geometry": {"coordinates":[-86.032676,33.961354],"type":"Point"}
}