{
  "type": "Feature",
  "properties": {
    "iso:country":"US",
    "sg:address":"2092 US Hwy 31",
    "sg:city":"Hartselle",
    "sg:classifiers":[
        {
            "category":"Autos & Motor Vehicles",
            "subcategory":"Automobile Sales",
            "type":"Retail Goods"
        }
    ],
    "sg:phone":"+1 256 751 3654",
    "sg:postcode":"35640",
    "sg:province":"AL",
    "sg:tags":[
        "car",
        "dealer"
    ],
    "wof:name":"Robert's Auto Sales",
    "wof:placetype":"venue"
},
  "geometry": {"coordinates":[-86.95764800000001,34.47136],"type":"Point"}
}