{
  "type": "Feature",
  "properties": {
    "addr:full":"2133 Powderly Ave SW Birmingham AL 35211",
    "addr:postcode":"2133;35211",
    "addr:street":"Powderly Ave Sw",
    "iso:country":"US",
    "sg:address":"2133 Powderly Ave SW",
    "sg:city":"Birmingham",
    "sg:classifiers":[
        {
            "category":"Shopping",
            "subcategory":"Catalog Store",
            "type":"Retail Goods"
        }
    ],
    "sg:phone":"+1 205 923 4560",
    "sg:postcode":"35211",
    "sg:province":"AL",
    "sg:tags":[
        "house",
        "mail",
        "concrete",
        "contractor"
    ],
    "wof:name":"Wehby & Assoc Desgr Stamps",
    "wof:placetype":"venue"
},
  "geometry": {"coordinates":[-86.873454,33.468358],"type":"Point"}
}