{
  "type": "Feature",
  "properties": {
    "iso:country":"US",
    "sg:address":"33145 State Rte 69",
    "sg:city":"Jasper",
    "sg:classifiers":[
        {
            "category":"Building & Trades",
            "subcategory":"Plumbing",
            "type":"Services"
        }
    ],
    "sg:phone":"+1 205 221 7166",
    "sg:postcode":"35504",
    "sg:province":"AL",
    "sg:tags":[
        "contractor"
    ],
    "wof:name":"Universal Mechanical Services",
    "wof:placetype":"venue"
},
  "geometry": {"coordinates":[-87.122202,33.907709],"type":"Point"}
}