{
  "type": "Feature",
  "properties": {
    "addr:full":"4359 Antares Ln Mobile AL 36693",
    "addr:housenumber":"4359",
    "addr:postcode":"36693",
    "addr:street":"Antares Ln",
    "iso:country":"US",
    "sg:address":"4359 Antares Ln",
    "sg:city":"Mobile",
    "sg:classifiers":[
        {
            "category":"Recreation",
            "subcategory":"Arcade",
            "type":"Entertainment"
        }
    ],
    "sg:phone":"+1 251 661 1192",
    "sg:postcode":"36693",
    "sg:province":"AL",
    "sg:tags":[
        "device",
        "operator",
        "sporting",
        "amusement"
    ],
    "wof:name":"West Side Amusement Inc",
    "wof:placetype":"venue"
},
  "geometry": {"coordinates":[-88.15518400000001,30.624585],"type":"Point"}
}