{
  "type": "Feature",
  "properties": {
    "addr:full":"8520 Bellingrath Rd Theodore AL 36582",
    "addr:housenumber":"8520",
    "addr:postcode":"36582",
    "addr:street":"Bellingrath Rd",
    "iso:country":"US",
    "sg:address":"8520 Bellingrath Rd",
    "sg:city":"Theodore",
    "sg:classifiers":[
        {
            "category":"Wholesale",
            "subcategory":"Electrical",
            "type":"Manufacturing & Wholesale Goods"
        }
    ],
    "sg:phone":"+1 251 653 4094",
    "sg:postcode":"36582",
    "sg:province":"AL",
    "sg:tags":[
        "electric",
        "motor"
    ],
    "wof:name":"R & W Electric Co",
    "wof:placetype":"venue"
},
  "geometry": {"coordinates":[-88.170236,30.516706],"type":"Point"}
}