{
  "type": "Feature",
  "properties": {
    "iso:country":"US",
    "sg:address":"201 Rogers Ln",
    "sg:city":"Prattville",
    "sg:classifiers":[
        {
            "category":"Building & Trades",
            "subcategory":"Construction",
            "type":"Services"
        }
    ],
    "sg:phone":"+1 334 361 0696",
    "sg:postcode":"36066",
    "sg:province":"AL",
    "sg:tags":[
        "contractor"
    ],
    "wof:name":"John or Davey Brewer",
    "wof:placetype":"venue"
},
  "geometry": {"coordinates":[-86.454237,32.578493],"type":"Point"}
}