{
  "type": "Feature",
  "properties": {
    "addr:full":"4517 Southlake Pkwy Birmingham AL 35244",
    "addr:housenumber":"4517",
    "addr:postcode":"35244",
    "addr:street":"Southlake Pkwy",
    "iso:country":"US",
    "sg:address":"4517 Southlake Pkwy",
    "sg:city":"Birmingham",
    "sg:classifiers":[
        {
            "category":"Health Services",
            "subcategory":"Medical Lab",
            "type":"Services"
        }
    ],
    "sg:phone":"+1 205 985 0600",
    "sg:postcode":"35244",
    "sg:province":"AL",
    "sg:tags":[
        "laboratory"
    ],
    "wof:name":"Med Plex Diagnostic Center",
    "wof:placetype":"venue"
},
  "geometry": {"coordinates":[-86.761314,33.382664],"type":"Point"}
}