{
  "type": "Feature",
  "properties": {
    "iso:country":"US",
    "sg:address":"3428 Atlanta Hwy",
    "sg:city":"Montgomery",
    "sg:classifiers":[
        {
            "category":"Restaurant",
            "type":"Food & Drink"
        }
    ],
    "sg:phone":"+1 334 279 7890",
    "sg:postcode":"36109",
    "sg:province":"AL",
    "sg:tags":[
        "eating"
    ],
    "wof:name":"Mary B's Buffet",
    "wof:placetype":"venue"
},
  "geometry": {"coordinates":[-86.25809599999999,32.385157],"type":"Point"}
}