{
  "type": "Feature",
  "properties": {
    "iso:country":"US",
    "sg:address":"301 S 4th St",
    "sg:city":"Gadsden",
    "sg:classifiers":[
        {
            "category":"Professional",
            "subcategory":"Business Services",
            "type":"Services"
        }
    ],
    "sg:phone":"+1 256 546 7565",
    "sg:postcode":"35901",
    "sg:province":"AL",
    "sg:tags":[
        "inventory",
        "computing"
    ],
    "wof:name":"R G I S Inventory Specialists",
    "wof:placetype":"venue"
},
  "geometry": {"coordinates":[-86.00565400000001,34.008689],"type":"Point"}
}