{
  "type": "Feature",
  "properties": {
    "iso:country":"US",
    "sg:address":"2075 Hwy 77",
    "sg:city":"Attalla",
    "sg:classifiers":[
        {
            "category":"Wholesale",
            "subcategory":"Auto Parts",
            "type":"Manufacturing & Wholesale Goods"
        }
    ],
    "sg:phone":"+1 256 538 5444",
    "sg:postcode":"35954",
    "sg:province":"AL",
    "sg:tags":[
        "automobile",
        "rebuilt"
    ],
    "wof:name":"L C Auto Sales & Parts Inc",
    "wof:placetype":"venue"
},
  "geometry": {"coordinates":[-86.117563,34.021502],"type":"Point"}
}