{
  "type": "Feature",
  "properties": {
    "iso:country":"US",
    "sg:address":"405 Oxford St",
    "sg:city":"Heflin",
    "sg:classifiers":[
        {
            "category":"Home & Garden",
            "subcategory":"Furniture",
            "type":"Retail Goods"
        }
    ],
    "sg:phone":"+1 256 463 2617",
    "sg:postcode":"36264",
    "sg:province":"AL",
    "wof:name":"Braden Woodworks",
    "wof:placetype":"venue"
},
  "geometry": {"coordinates":[-85.590076,33.651136],"type":"Point"}
}