{
  "type": "Feature",
  "properties": {
    "addr:full":"9378 State Rte 119 Alabaster AL 35007",
    "addr:housenumber":"9378",
    "addr:postcode":"35007",
    "addr:street":"State Rte 119",
    "iso:country":"US",
    "sg:address":"9378 State Rte 119",
    "sg:city":"Alabaster",
    "sg:classifiers":[
        {
            "category":"Autos & Motor Vehicles",
            "subcategory":"Automobile Sales",
            "type":"Retail Goods"
        }
    ],
    "sg:phone":"+1 205 620 3336",
    "sg:postcode":"35007",
    "sg:province":"AL",
    "sg:tags":[
        "used"
    ],
    "wof:name":"Clean Car Auto Sales",
    "wof:placetype":"venue"
},
  "geometry": {"coordinates":[-86.826329,33.215756],"type":"Point"}
}