{
  "type": "Feature",
  "properties": {
    "iso:country":"US",
    "sg:address":"2528 Spring Ave SW",
    "sg:city":"Decatur",
    "sg:classifiers":[
        {
            "category":"Professional",
            "subcategory":"Business Services",
            "type":"Services"
        }
    ],
    "sg:phone":"+1 256 355 2226",
    "sg:postcode":"35601",
    "sg:province":"AL",
    "sg:tags":[
        "arbitration"
    ],
    "wof:name":"Better Business Bureau of",
    "wof:placetype":"venue"
},
  "geometry": {"coordinates":[-86.999956,34.564286],"type":"Point"}
}