{
  "type": "Feature",
  "properties": {
    "iso:country":"US",
    "sg:address":"2933 Pump House Rd",
    "sg:city":"Birmingham",
    "sg:classifiers":[
        {
            "category":"Real Estate",
            "subcategory":"Architect",
            "type":"Services"
        }
    ],
    "sg:phone":"+1 205 871 8794",
    "sg:postcode":"35243",
    "sg:province":"AL",
    "wof:name":"Katherine Shannon Owens Arch",
    "wof:placetype":"venue"
},
  "geometry": {"coordinates":[-86.743314,33.456609],"type":"Point"}
}