{
  "type": "Feature",
  "properties": {
    "iso:country":"US",
    "sg:address":"2501 Jordan Ln NW",
    "sg:city":"Huntsville",
    "sg:classifiers":[
        {
            "category":"Shopping",
            "subcategory":"Discount & Variety Stores",
            "type":"Retail Goods"
        },
        {
            "category":"Shopping",
            "subcategory":"Department Store",
            "type":"Retail Goods"
        }
    ],
    "sg:phone":"+1 256 864 0028",
    "sg:postcode":"35816",
    "sg:province":"AL",
    "sg:tags":[
        "shop"
    ],
    "wof:name":"Family Dollar Stores",
    "wof:placetype":"venue"
},
  "geometry": {"coordinates":[-86.63941199999999,34.756085],"type":"Point"}
}