{
  "type": "Feature",
  "properties": {
    "iso:country":"US",
    "sg:address":"120 S Royal Ave",
    "sg:city":"Florence",
    "sg:classifiers":[
        {
            "category":"Home & Garden",
            "subcategory":"Household Appliances",
            "type":"Retail Goods"
        }
    ],
    "sg:phone":"+1 256 764 6121",
    "sg:postcode":"35630",
    "sg:province":"AL",
    "sg:tags":[
        "new",
        "used",
        "furniture"
    ],
    "wof:name":"K&W Used Furniture",
    "wof:placetype":"venue"
},
  "geometry": {"coordinates":[-87.656909,34.802315],"type":"Point"}
}