{
  "type": "Feature",
  "properties": {
    "iso:country":"US",
    "sg:address":"133 S Main St",
    "sg:city":"Arab",
    "sg:classifiers":[
        {
            "category":"Health Services",
            "subcategory":"Optometrist",
            "type":"Services"
        }
    ],
    "sg:phone":"+1 256 931 4994",
    "sg:postcode":"35016",
    "sg:province":"AL",
    "wof:name":"Glasses For Less",
    "wof:placetype":"venue"
},
  "geometry": {"coordinates":[-86.495822,34.31496],"type":"Point"}
}