{
  "type": "Feature",
  "properties": {
    "iso:country":"US",
    "sg:address":"1718 Veterans Memorial Pkwy",
    "sg:city":"Tuscaloosa",
    "sg:classifiers":[
        {
            "category":"Health Services",
            "subcategory":"Doctor",
            "type":"Services"
        }
    ],
    "sg:phone":"+1 205 349 1641",
    "sg:postcode":"35404",
    "sg:province":"AL",
    "sg:tags":[
        "physician",
        "surgeon",
        "medical"
    ],
    "wof:name":"Alabama Family Medical Center",
    "wof:placetype":"venue"
},
  "geometry": {"coordinates":[-87.514003,33.197579],"type":"Point"}
}