{
  "type": "Feature",
  "properties": {
    "iso:country":"US",
    "sg:address":"604 Morris Blvd",
    "sg:city":"Birmingham",
    "sg:classifiers":[
        {
            "category":"Professional",
            "subcategory":"Business Services",
            "type":"Services"
        }
    ],
    "sg:phone":"+1 205 940 9927",
    "sg:postcode":"35209",
    "sg:province":"AL",
    "wof:name":"Vietaly Enterprises Inc",
    "wof:placetype":"venue"
},
  "geometry": {"coordinates":[-86.813354,33.46546],"type":"Point"}
}