{
  "type": "Feature",
  "properties": {
    "addr:full":"357 Corktree Cir Auburn AL 36832",
    "addr:housenumber":"357",
    "addr:postcode":"36832",
    "addr:street":"Corktree Cir",
    "iso:country":"US",
    "sg:address":"357 Corktree Cir",
    "sg:city":"Auburn",
    "sg:classifiers":[
        {
            "category":"Professional",
            "subcategory":"Accounting & Tax Preparation",
            "type":"Services"
        }
    ],
    "sg:phone":"+1 334 821 6961",
    "sg:postcode":"36832",
    "sg:province":"AL",
    "wof:name":"Gail C Cobb",
    "wof:placetype":"venue"
},
  "geometry": {"coordinates":[-85.484724,32.579743],"type":"Point"}
}