{
  "type": "Feature",
  "properties": {
    "iso:country":"US",
    "sg:address":"280 Wicksburg Rd",
    "sg:city":"Newton",
    "sg:classifiers":[
        {
            "category":"Professional",
            "type":"Services"
        }
    ],
    "sg:phone":"+1 334 692 4221",
    "sg:postcode":"36352",
    "sg:province":"AL",
    "wof:name":"Parker Scarlet",
    "wof:placetype":"venue"
},
  "geometry": {"coordinates":[-85.62029699999999,31.22415],"type":"Point"}
}