{
  "type": "Feature",
  "properties": {
    "iso:country":"US",
    "sg:address":"535 Laurel Ln",
    "sg:city":"Dixons Mills",
    "sg:classifiers":[
        {
            "category":"Freight",
            "type":"Transportation"
        }
    ],
    "sg:phone":"+1 334 992 2885",
    "sg:postcode":"36736",
    "sg:province":"AL",
    "sg:tags":[
        "operator",
        "trucking"
    ],
    "wof:name":"Blanco Enterprises",
    "wof:placetype":"venue"
},
  "geometry": {"coordinates":[-87.772807,32.050871],"type":"Point"}
}