{
  "type": "Feature",
  "properties": {
    "addr:full":"23980 John T Reid Pkwy Scottsboro AL 35768",
    "addr:housenumber":"23980",
    "addr:postcode":"35768",
    "addr:street":"John T Reid Pkwy Scottsboro",
    "iso:country":"US",
    "sg:address":"23980 John T Reid Pkwy",
    "sg:city":"Scottsboro",
    "sg:classifiers":[
        {
            "category":"Restaurant",
            "type":"Food & Drink"
        }
    ],
    "sg:phone":"+1 256 259 6888",
    "sg:postcode":"35768",
    "sg:province":"AL",
    "sg:tags":[
        "steak"
    ],
    "wof:name":"Western Sizzlin Steakhouse",
    "wof:placetype":"venue"
},
  "geometry": {"coordinates":[-86.02964299999999,34.64986],"type":"Point"}
}