{
  "type": "Feature",
  "properties": {
    "iso:country":"US",
    "sg:address":"23980 John T Reid Pkwy",
    "sg:city":"Scottsboro",
    "sg:classifiers":[
        {
            "category":"Restaurant",
            "type":"Food & Drink"
        }
    ],
    "sg:phone":"+1 256 259 6888",
    "sg:postcode":"35768",
    "sg:province":"AL",
    "sg:tags":[
        "steak"
    ],
    "wof:name":"Western Sizzlin Steakhouse",
    "wof:placetype":"venue"
},
  "geometry": {"coordinates":[-86.029643,34.64986],"type":"Point"}
}