{
  "type": "Feature",
  "properties": {
    "iso:country":"US",
    "sg:address":"2120 Jameson Pl SW",
    "sg:city":"Decatur",
    "sg:classifiers":[
        {
            "category":"Travel",
            "subcategory":"Hotels & Motels",
            "type":"Entertainment"
        }
    ],
    "sg:phone":"+1 256 355 2229",
    "sg:postcode":"35603",
    "sg:province":"AL",
    "wof:name":"Jameson Inns",
    "wof:placetype":"venue"
},
  "geometry": {"coordinates":[-87.020816,34.579192],"type":"Point"}
}