{
  "type": "Feature",
  "properties": {
    "addr:full":"1700 Firestone Ave Muscle Shoals AL 35661",
    "addr:housenumber":"1700",
    "addr:postcode":"35661",
    "addr:street":"Firestone Ave",
    "iso:country":"US",
    "sg:address":"1700 Firestone Ave",
    "sg:city":"Muscle Shoals",
    "sg:classifiers":[
        {
            "category":"Organizations",
            "subcategory":"Religious Organization",
            "type":"Services"
        }
    ],
    "sg:phone":"+1 256 383 7914",
    "sg:postcode":"35661",
    "sg:province":"AL",
    "wof:name":"Muscle Shoals Church Of God",
    "wof:placetype":"venue"
},
  "geometry": {"coordinates":[-87.64867599999999,34.744479],"type":"Point"}
}