{
  "type": "Feature",
  "properties": {
    "addr:full":"1404 Gilmer Ave Tallassee AL 36078",
    "addr:housenumber":"1404",
    "addr:postcode":"36078",
    "addr:street":"Gilmer Ave",
    "iso:country":"US",
    "sg:address":"1404 Gilmer Ave",
    "sg:city":"Tallassee",
    "sg:classifiers":[
        {
            "category":"Retail",
            "subcategory":"Auto Repair",
            "type":"Services"
        }
    ],
    "sg:phone":"+1 334 252 1425",
    "sg:postcode":"36078",
    "sg:province":"AL",
    "sg:tags":[
        "repairing",
        "automobile"
    ],
    "wof:name":"C & C Transmission & Auto Repr",
    "wof:placetype":"venue"
},
  "geometry": {"coordinates":[-85.91345,32.548608],"type":"Point"}
}