{
  "type": "Feature",
  "properties": {
    "addr:full":"7947 US Hwy 231 Dothan AL 36301",
    "addr:housenumber":"7947",
    "addr:postcode":"36301",
    "addr:street":"Us Hwy 231",
    "iso:country":"US",
    "sg:address":"7947 US Hwy 231",
    "sg:city":"Dothan",
    "sg:classifiers":[
        {
            "category":"Home & Garden",
            "subcategory":"Garden Supply",
            "type":"Retail Goods"
        }
    ],
    "sg:phone":"+1 334 677 3866",
    "sg:postcode":"36301",
    "sg:province":"AL",
    "sg:tags":[
        "nurseryman"
    ],
    "wof:name":"D and J Nursery & Outlet",
    "wof:placetype":"venue"
},
  "geometry": {"coordinates":[-85.40464299999999,31.112768],"type":"Point"}
}