{
  "type": "Feature",
  "properties": {
    "iso:country":"US",
    "sg:address":"849 Dennison Ave SW",
    "sg:city":"Birmingham",
    "sg:classifiers":[
        {
            "category":"Retail",
            "subcategory":"Self-service Laundry",
            "type":"Services"
        }
    ],
    "sg:phone":"+1 205 251 2448",
    "sg:postcode":"35211",
    "sg:province":"AL",
    "sg:tags":[
        "garment",
        "coin",
        "agent"
    ],
    "wof:name":"Flamingo Dry Cleaners",
    "wof:placetype":"venue"
},
  "geometry": {"coordinates":[-86.84490099999999,33.480565],"type":"Point"}
}