{
  "type": "Feature",
  "properties": {
    "iso:country":"US",
    "sg:address":"211 Amphitheater Rd",
    "sg:city":"Pelham",
    "sg:classifiers":[
        {
            "category":"Shopping",
            "type":"Retail Goods"
        }
    ],
    "sg:phone":"+1 205 621 7393",
    "sg:postcode":"35124",
    "sg:province":"AL",
    "sg:tags":[
        "trophy",
        "medal",
        "award"
    ],
    "wof:name":"Crown Trophy",
    "wof:placetype":"venue"
},
  "geometry": {"coordinates":[-86.79066899999999,33.32789],"type":"Point"}
}