{
  "type": "Feature",
  "properties": {
    "iso:country":"US",
    "sg:address":"20 Co Rd 127",
    "sg:city":"Montevallo",
    "sg:classifiers":[
        {
            "category":"Freight",
            "type":"Transportation"
        }
    ],
    "sg:phone":"+1 205 665 7205",
    "sg:postcode":"35115",
    "sg:province":"AL",
    "sg:tags":[
        "broker",
        "trucking"
    ],
    "wof:name":"Broadheads Trucking",
    "wof:placetype":"venue"
},
  "geometry": {"coordinates":[-86.807692,33.056312],"type":"Point"}
}