{
  "type": "Feature",
  "properties": {
    "iso:country":"US",
    "sg:address":"3523 Mobile Hwy",
    "sg:city":"Montgomery",
    "sg:classifiers":[
        {
            "category":"Wholesale",
            "subcategory":"Machinery & Supplies",
            "type":"Manufacturing & Wholesale Goods"
        }
    ],
    "sg:phone":"+1 334 286 9999",
    "sg:postcode":"36108",
    "sg:province":"AL",
    "sg:tags":[
        "tractor"
    ],
    "wof:name":"Equipment & Parts Specialty Co",
    "wof:placetype":"venue"
},
  "geometry": {"coordinates":[-86.34096700000001,32.337889],"type":"Point"}
}