{
  "type": "Feature",
  "properties": {
    "iso:country":"US",
    "sg:address":"1199 Capshaw Rd",
    "sg:city":"Harvest",
    "sg:classifiers":[
        {
            "category":"Building & Trades",
            "subcategory":"Construction",
            "type":"Services"
        }
    ],
    "sg:phone":"+1 256 837 1216",
    "sg:postcode":"35749",
    "sg:province":"AL",
    "sg:tags":[
        "residential",
        "commercial"
    ],
    "wof:name":"Miller Construction Co Inc",
    "wof:placetype":"venue"
},
  "geometry": {"coordinates":[-86.758898,34.772817],"type":"Point"}
}