{
  "type": "Feature",
  "properties": {
    "iso:country":"US",
    "sg:address":"838 S Memorial Dr",
    "sg:city":"Prattville",
    "sg:classifiers":[
        {
            "category":"Personal",
            "subcategory":"Beauty Salon",
            "type":"Services"
        }
    ],
    "sg:phone":"+1 334 365 7503",
    "sg:postcode":"36067",
    "sg:province":"AL",
    "sg:tags":[
        "shop"
    ],
    "wof:name":"Port Of Hair",
    "wof:placetype":"venue"
},
  "geometry": {"coordinates":[-86.449188,32.457743],"type":"Point"}
}