{
  "type": "Feature",
  "properties": {
    "addr:full":"101 E I65 Service Rd S Mobile AL 36606",
    "addr:housenumber":"101",
    "addr:postcode":"36606",
    "addr:street":"E I65 Service Rd S",
    "iso:country":"US",
    "sg:address":"101 E I65 Service Rd S",
    "sg:city":"Mobile",
    "sg:classifiers":[
        {
            "category":"Deli",
            "type":"Food & Drink"
        }
    ],
    "sg:menulink":"http://www.allmenus.com/al/mobile/125837-blimpie-subs--sandwiches/menu/",
    "sg:phone":"+1 251 476 3983",
    "sg:postcode":"36606",
    "sg:province":"AL",
    "sg:tags":[
        "wrap",
        "american",
        "sandwich"
    ],
    "wof:name":"Blimpie Subs & Sandwiches",
    "wof:placetype":"venue"
},
  "geometry": {"coordinates":[-88.123591,30.687244],"type":"Point"}
}