{
  "type": "Feature",
  "properties": {
    "iso:country":"US",
    "sg:address":"318 Patrician Dr S",
    "sg:city":"Spanish Fort",
    "sg:classifiers":[
        {
            "category":"Health Services",
            "subcategory":"Doctor",
            "type":"Services"
        }
    ],
    "sg:phone":"+1 251 626 0394",
    "sg:postcode":"36527",
    "sg:province":"AL",
    "sg:tags":[
        "medical"
    ],
    "wof:name":"Bayou Labatre Rural Health",
    "wof:placetype":"venue"
},
  "geometry": {"coordinates":[-87.911604,30.660433],"type":"Point"}
}