{
  "type": "Feature",
  "properties": {
    "addr:full":"9016 Madison Blvd Madison AL 35758",
    "addr:housenumber":"9016",
    "addr:postcode":"35758",
    "addr:street":"Madison Blvd",
    "iso:country":"US",
    "sg:address":"9016 Madison Blvd",
    "sg:city":"Madison",
    "sg:classifiers":[
        {
            "category":"Restaurant",
            "type":"Food & Drink"
        }
    ],
    "sg:phone":"+1 256 461 7766",
    "sg:postcode":"35758",
    "sg:province":"AL",
    "wof:name":"China Buffet",
    "wof:placetype":"venue"
},
  "geometry": {"coordinates":[-86.75497300000001,34.675471],"type":"Point"}
}