{
  "type": "Feature",
  "properties": {
    "iso:country":"US",
    "sg:address":"8112 Jackson Trace Rd",
    "sg:city":"Lincoln",
    "sg:classifiers":[
        {
            "category":"Manufacturing",
            "subcategory":"Retail Goods",
            "type":"Manufacturing & Wholesale Goods"
        }
    ],
    "sg:phone":"+1 205 763 2116",
    "sg:postcode":"35096",
    "sg:province":"AL",
    "sg:tags":[
        "product",
        "mfg"
    ],
    "wof:name":"Five Star Industries Inc",
    "wof:placetype":"venue"
},
  "geometry": {"coordinates":[-86.085599,33.558079],"type":"Point"}
}