{
  "type": "Feature",
  "properties": {
    "iso:country":"US",
    "sg:address":"605 W Canal Dr",
    "sg:city":"Gulf Shores",
    "sg:classifiers":[
        {
            "category":"Professional",
            "type":"Services"
        }
    ],
    "sg:phone":"+1 251 968 8436",
    "sg:postcode":"36542",
    "sg:province":"AL",
    "wof:name":"Modern Surgical",
    "wof:placetype":"venue"
},
  "geometry": {"coordinates":[-87.706414,30.277891],"type":"Point"}
}