{
  "type": "Feature",
  "properties": {
    "iso:country":"US",
    "sg:address":"145 Coliseum Blvd",
    "sg:city":"Montgomery",
    "sg:classifiers":[
        {
            "category":"Organizations",
            "subcategory":"Community Association",
            "type":"Services"
        }
    ],
    "sg:phone":"+1 334 272 9164",
    "sg:postcode":"36109",
    "sg:province":"AL",
    "wof:name":"Girl Scouts Council",
    "wof:placetype":"venue"
},
  "geometry": {"coordinates":[-86.257491,32.386337],"type":"Point"}
}