{
  "type": "Feature",
  "properties": {
    "addr:full":"715 Skyland Blvd E Tuscaloosa AL 35405",
    "addr:housenumber":"715",
    "addr:postcode":"35405",
    "addr:street":"Skyland Blvd E",
    "iso:country":"US",
    "sg:address":"715 Skyland Blvd E",
    "sg:city":"Tuscaloosa",
    "sg:classifiers":[
        {
            "category":"Real Estate",
            "subcategory":"Real Estate Agent",
            "type":"Services"
        }
    ],
    "sg:phone":"+1 205 345 4550",
    "sg:postcode":"35405",
    "sg:province":"AL",
    "sg:tags":[
        "residential",
        "speculative",
        "builder",
        "o"
    ],
    "wof:name":"Smith Danny Realty",
    "wof:placetype":"venue"
},
  "geometry": {"coordinates":[-87.530061,33.167505],"type":"Point"}
}