{
  "type": "Feature",
  "properties": {
    "iso:country":"US",
    "sg:address":"600 E Commerce St",
    "sg:city":"Greenville",
    "sg:classifiers":[
        {
            "category":"Professional",
            "subcategory":"Lawyer & Legal Services",
            "type":"Services"
        }
    ],
    "sg:phone":"+1 334 382 3123",
    "sg:postcode":"36037",
    "sg:province":"AL",
    "sg:tags":[
        "attorney"
    ],
    "wof:name":"Poole & Poole",
    "wof:placetype":"venue"
},
  "geometry": {"coordinates":[-86.61838,31.829594],"type":"Point"}
}