{
  "type": "Feature",
  "properties": {
    "iso:country":"US",
    "sg:address":"209 Shirley Dr",
    "sg:city":"Florence",
    "sg:classifiers":[
        {
            "category":"Professional",
            "type":"Services"
        }
    ],
    "sg:phone":"+1 256 767 0422",
    "sg:postcode":"35633",
    "sg:province":"AL",
    "wof:name":"Tommy & Marie Thompson",
    "wof:placetype":"venue"
},
  "geometry": {"coordinates":[-87.682596,34.850614],"type":"Point"}
}