{
  "type": "Feature",
  "properties": {
    "iso:country":"US",
    "sg:address":"494 Fombys Ferry Rd",
    "sg:city":"Ohatchee",
    "sg:classifiers":[
        {
            "category":"Professional",
            "subcategory":"Management & Consulting",
            "type":"Services"
        }
    ],
    "sg:phone":"+1 256 892 0687",
    "sg:postcode":"36271",
    "sg:province":"AL",
    "sg:tags":[
        "business"
    ],
    "wof:name":"Huttenstine Consulting",
    "wof:placetype":"venue"
},
  "geometry": {"coordinates":[-86.111597,33.706416],"type":"Point"}
}