{
  "type": "Feature",
  "properties": {
    "iso:country":"US",
    "sg:address":"1101 16th Ave SE",
    "sg:city":"Decatur",
    "sg:classifiers":[
        {
            "category":"Shopping",
            "subcategory":"Pharmacy",
            "type":"Retail Goods"
        }
    ],
    "sg:phone":"+1 256 355 6225",
    "sg:postcode":"35601",
    "sg:province":"AL",
    "wof:name":"1302 Summerville Rd SE",
    "wof:placetype":"venue"
},
  "geometry": {"coordinates":[-86.967395,34.590652],"type":"Point"}
}