{
  "type": "Feature",
  "properties": {
    "iso:country":"US",
    "sg:address":"2950 Rucker Blvd",
    "sg:city":"Enterprise",
    "sg:classifiers":[
        {
            "category":"Restaurant",
            "type":"Food & Drink"
        }
    ],
    "sg:phone":"+1 334 308 2550",
    "sg:postcode":"36330",
    "sg:province":"AL",
    "sg:tags":[
        "italian"
    ],
    "wof:name":"Tuscanys Olde World Dining LLC",
    "wof:placetype":"venue"
},
  "geometry": {"coordinates":[-85.797418,31.333523],"type":"Point"}
}