{
  "type": "Feature",
  "properties": {
    "addr:full":"2900 Steeple Chase Ln Montgomery AL 36116",
    "addr:housenumber":"2900",
    "addr:postcode":"36116",
    "addr:street":"Steeple Chase Ln",
    "iso:country":"US",
    "sg:address":"2900 Steeple Chase Ln",
    "sg:city":"Montgomery",
    "sg:classifiers":[
        {
            "category":"Real Estate",
            "subcategory":"Real Estate Operator",
            "type":"Services"
        }
    ],
    "sg:phone":"+1 334 409 5934",
    "sg:postcode":"36116",
    "sg:province":"AL",
    "sg:tags":[
        "apartment"
    ],
    "wof:name":"Corner Stone Apartments",
    "wof:placetype":"venue"
},
  "geometry": {"coordinates":[-86.22153900000001,32.340261],"type":"Point"}
}