{
  "type": "Feature",
  "properties": {
    "iso:country":"US",
    "sg:address":"4004 State Rte 132",
    "sg:city":"Oneonta",
    "sg:classifiers":[
        {
            "category":"Building & Trades",
            "subcategory":"Construction",
            "type":"Services"
        }
    ],
    "sg:phone":"+1 205 274 0956",
    "sg:postcode":"35121",
    "sg:province":"AL",
    "sg:tags":[
        "house"
    ],
    "wof:name":"Pat Ratliff Custom Homes Inc",
    "wof:placetype":"venue"
},
  "geometry": {"coordinates":[-86.40607,33.96932],"type":"Point"}
}