{
  "type": "Feature",
  "properties": {
    "iso:country":"US",
    "sg:address":"40 State Farm Pkwy",
    "sg:city":"Birmingham",
    "sg:classifiers":[
        {
            "category":"Travel",
            "subcategory":"Hotels & Motels",
            "type":"Entertainment"
        }
    ],
    "sg:phone":"+1 205 290 0102",
    "sg:postcode":"35209",
    "sg:province":"AL",
    "sg:tags":[
        "operation"
    ],
    "wof:name":"Studioplus 27",
    "wof:placetype":"venue"
},
  "geometry": {"coordinates":[-86.819585,33.453613],"type":"Point"}
}