{
  "type": "Feature",
  "properties": {
    "iso:country":"US",
    "sg:address":"31318 US Hwy 431",
    "sg:city":"Grant",
    "sg:classifiers":[
        {
            "category":"Autos & Motor Vehicles",
            "subcategory":"Boat Sales",
            "type":"Retail Goods"
        }
    ],
    "sg:phone":"+1 256 582 7586",
    "sg:postcode":"35747",
    "sg:province":"AL",
    "wof:name":"Alabama Marine",
    "wof:placetype":"venue"
},
  "geometry": {"coordinates":[-86.372884,34.475817],"type":"Point"}
}