{
  "type": "Feature",
  "properties": {
    "addr:full":"1160 S Lawrence St Montgomery AL 36104",
    "addr:housenumber":"1160",
    "addr:postcode":"36104",
    "addr:street":"S Lawrence St",
    "iso:country":"US",
    "sg:address":"1160 S Lawrence St",
    "sg:city":"Montgomery",
    "sg:classifiers":[
        {
            "category":"Professional",
            "subcategory":"Engineering",
            "type":"Services"
        }
    ],
    "sg:phone":"+1 334 263 6451",
    "sg:postcode":"36104",
    "sg:province":"AL",
    "wof:name":"Dickey & Associates Inc",
    "wof:placetype":"venue"
},
  "geometry": {"coordinates":[-86.305742,32.362071],"type":"Point"}
}