{
  "type": "Feature",
  "properties": {
    "iso:country":"US",
    "sg:address":"4997 Cusseta Rd",
    "sg:city":"Lanett",
    "sg:classifiers":[
        {
            "category":"Retail",
            "subcategory":"Auto Repair",
            "type":"Services"
        }
    ],
    "sg:phone":"+1 334 576 6040",
    "sg:postcode":"36863",
    "sg:province":"AL",
    "sg:tags":[
        "body",
        "automobile",
        "painting",
        "general"
    ],
    "wof:name":"Gray's Body Shop",
    "wof:placetype":"venue"
},
  "geometry": {"coordinates":[-85.235878,32.821369],"type":"Point"}
}