{
  "type": "Feature",
  "properties": {
    "addr:full":"275 4th Ct Mobile AL 36603",
    "addr:housenumber":"275",
    "addr:postcode":"36603",
    "addr:street":"4Th Ct",
    "iso:country":"US",
    "sg:address":"275 4th Ct",
    "sg:city":"Mobile",
    "sg:classifiers":[
        {
            "category":"Government",
            "subcategory":"Office",
            "type":"Public Place"
        }
    ],
    "sg:phone":"+1 251 434 2302",
    "sg:postcode":"36603",
    "sg:province":"AL",
    "sg:tags":[
        "village"
    ],
    "wof:name":"Mobile Housing Board",
    "wof:placetype":"venue"
},
  "geometry": {"coordinates":[-88.05003600000001,30.702138],"type":"Point"}
}