{
  "type": "Feature",
  "properties": {
    "iso:country":"US",
    "sg:address":"403 Kent Dr",
    "sg:city":"Dothan",
    "sg:classifiers":[
        {
            "category":"Professional",
            "type":"Services"
        }
    ],
    "sg:phone":"+1 334 678 6788",
    "sg:postcode":"36303",
    "sg:province":"AL",
    "wof:name":"Bill Derolf",
    "wof:placetype":"venue"
},
  "geometry": {"coordinates":[-85.427744,31.232613],"type":"Point"}
}