{
  "type": "Feature",
  "properties": {
    "iso:country":"US",
    "sg:address":"699 US Hwy 231",
    "sg:city":"Laceys Spring",
    "sg:classifiers":[
        {
            "category":"Restaurant",
            "type":"Food & Drink"
        }
    ],
    "sg:phone":"+1 256 881 0122",
    "sg:postcode":"35754",
    "sg:province":"AL",
    "wof:name":"Pepper's Laceys Spring Diner",
    "wof:placetype":"venue"
},
  "geometry": {"coordinates":[-86.581653,34.55899],"type":"Point"}
}