{
  "type": "Feature",
  "properties": {
    "iso:country":"US",
    "sg:address":"309 26th Ct NW",
    "sg:city":"Birmingham",
    "sg:classifiers":[
        {
            "category":"Professional",
            "subcategory":"Computer Services",
            "type":"Services"
        }
    ],
    "sg:phone":"+1 205 853 2826",
    "sg:postcode":"35215",
    "sg:province":"AL",
    "sg:tags":[
        "repair",
        "sales",
        "business",
        "residential"
    ],
    "wof:name":"69 Productions",
    "wof:placetype":"venue"
},
  "geometry": {"coordinates":[-86.694124,33.654305],"type":"Point"}
}