{
  "type": "Feature",
  "properties": {
    "addr:full":"4405 Birmingport Rd Birmingham AL 35118",
    "addr:housenumber":"4405",
    "addr:postcode":"35118",
    "addr:street":"Birmingport Rd",
    "iso:country":"US",
    "sg:address":"4405 Birmingport Rd",
    "sg:city":"Birmingham",
    "sg:classifiers":[
        {
            "category":"Manufacturing",
            "subcategory":"Tools & Machinery",
            "type":"Manufacturing & Wholesale Goods"
        }
    ],
    "sg:phone":"+1 205 787 9021",
    "sg:postcode":"35118",
    "sg:province":"AL",
    "sg:tags":[
        "machine",
        "shop"
    ],
    "wof:name":"Bonham Metal Works Co",
    "wof:placetype":"venue"
},
  "geometry": {"coordinates":[-86.984872,33.538464],"type":"Point"}
}