{
  "type": "Feature",
  "properties": {
    "iso:country":"US",
    "sg:address":"218 Alexandria Heights Cir",
    "sg:city":"Alexandria",
    "sg:classifiers":[
        {
            "category":"Health Services",
            "subcategory":"Clinic",
            "type":"Services"
        }
    ],
    "sg:phone":"+1 256 847 8088",
    "sg:postcode":"36250",
    "sg:province":"AL",
    "wof:name":"New-ERA Bridal",
    "wof:placetype":"venue"
},
  "geometry": {"coordinates":[-85.895402,33.789268],"type":"Point"}
}