{
  "type": "Feature",
  "properties": {
    "addr:full":"202 Adelaide St SW Jacksonville AL 36265",
    "addr:housenumber":"202",
    "addr:postcode":"36265",
    "addr:street":"Adelaide St Sw",
    "iso:country":"US",
    "sg:address":"202 Adelaide St SW",
    "sg:city":"Jacksonville",
    "sg:classifiers":[
        {
            "category":"Personal",
            "type":"Services"
        }
    ],
    "sg:phone":"+1 256 435 3862",
    "sg:postcode":"36265",
    "sg:province":"AL",
    "wof:name":"Mr Fixit",
    "wof:placetype":"venue"
},
  "geometry": {"coordinates":[-85.762804,33.799672],"type":"Point"}
}