{
  "type": "Feature",
  "properties": {
    "iso:country":"US",
    "sg:address":"163 W 5th St",
    "sg:city":"Prattville",
    "sg:classifiers":[
        {
            "category":"Social Services",
            "type":"Services"
        }
    ],
    "sg:phone":"+1 334 361 0505",
    "sg:postcode":"36067",
    "sg:province":"AL",
    "sg:tags":[
        "organization",
        "welfare"
    ],
    "wof:name":"Community Action Ctr",
    "wof:placetype":"venue"
},
  "geometry": {"coordinates":[-86.474139,32.464313],"type":"Point"}
}