{
  "type": "Feature",
  "properties": {
    "addr:full":"3416 23rd St Tuscaloosa AL 35401",
    "addr:housenumber":"3416",
    "addr:postcode":"35401",
    "addr:street":"23Rd St",
    "iso:country":"US",
    "sg:address":"3416 23rd St",
    "sg:city":"Tuscaloosa",
    "sg:classifiers":[
        {
            "category":"Restaurant",
            "type":"Food & Drink"
        }
    ],
    "sg:phone":"+1 205 886 7230",
    "sg:postcode":"35401",
    "sg:province":"AL",
    "sg:tags":[
        "grocery",
        "eating"
    ],
    "wof:name":"Westside Snack Shop",
    "wof:placetype":"venue"
},
  "geometry": {"coordinates":[-87.583491,33.192303],"type":"Point"}
}