{
  "type": "Feature",
  "properties": {
    "iso:country":"US",
    "sg:address":"500 Trade Center St",
    "sg:city":"Montgomery",
    "sg:classifiers":[
        {
            "category":"Freight",
            "type":"Transportation"
        }
    ],
    "sg:phone":"+1 334 265 4443",
    "sg:postcode":"36108",
    "sg:province":"AL",
    "sg:tags":[
        "operator",
        "trucking"
    ],
    "sg:website":"www.odfl.com",
    "wof:name":"Old Dominion Freight Line Inc",
    "wof:placetype":"venue"
},
  "geometry": {"coordinates":[-86.345697,32.369166],"type":"Point"}
}