{
  "type": "Feature",
  "properties": {
    "iso:country":"US",
    "sg:address":"1015 Lauderdale St",
    "sg:city":"Selma",
    "sg:classifiers":[
        {
            "category":"Home & Garden",
            "subcategory":"Building Materials",
            "type":"Retail Goods"
        }
    ],
    "sg:phone":"+1 334 874 9091",
    "sg:postcode":"36701",
    "sg:province":"AL",
    "sg:tags":[
        "construction",
        "w"
    ],
    "wof:name":"Standard Glass Co",
    "wof:placetype":"venue"
},
  "geometry": {"coordinates":[-87.0255,32.415026],"type":"Point"}
}