{
  "type": "Feature",
  "properties": {
    "iso:country":"US",
    "sg:address":"1760 Carter Hill Rd",
    "sg:city":"Montgomery",
    "sg:classifiers":[
        {
            "category":"Restaurant",
            "type":"Food & Drink"
        }
    ],
    "sg:phone":"+1 334 834 8811",
    "sg:postcode":"36106",
    "sg:province":"AL",
    "sg:tags":[
        "eating"
    ],
    "wof:name":"China Sea Kitchen",
    "wof:placetype":"venue"
},
  "geometry": {"coordinates":[-86.28271100000001,32.358261],"type":"Point"}
}