{
  "type": "Feature",
  "properties": {
    "addr:full":"1431 Chestnut St Gadsden AL 35901",
    "addr:housenumber":"1431",
    "addr:postcode":"35901",
    "addr:street":"Chestnut St",
    "iso:country":"US",
    "sg:address":"1431 Chestnut St",
    "sg:city":"Gadsden",
    "sg:classifiers":[
        {
            "category":"Organizations",
            "subcategory":"Religious Organization",
            "type":"Services"
        }
    ],
    "sg:phone":"+1 256 546 5683",
    "sg:postcode":"35901",
    "sg:province":"AL",
    "wof:name":"Interdnmntnal Assn of Churches",
    "wof:placetype":"venue"
},
  "geometry": {"coordinates":[-86.023946,34.014256],"type":"Point"}
}