{
  "type": "Feature",
  "properties": {
    "addr:full":"395 Co Rd 15 Oneonta AL 35121",
    "addr:housenumber":"395;15",
    "addr:postcode":"35121",
    "addr:street":"Co Rd",
    "iso:country":"US",
    "sg:address":"395 Co Rd 15",
    "sg:city":"Oneonta",
    "sg:classifiers":[
        {
            "category":"Organizations",
            "subcategory":"Religious Organization",
            "type":"Services"
        }
    ],
    "sg:phone":"+1 205 274 8061",
    "sg:postcode":"35121",
    "sg:province":"AL",
    "sg:tags":[
        "church"
    ],
    "wof:name":"Clear Springs Methodist Church",
    "wof:placetype":"venue"
},
  "geometry": {"coordinates":[-86.56294699999999,33.863246],"type":"Point"}
}