{
  "type": "Feature",
  "properties": {
    "iso:country":"US",
    "sg:address":"100 Inverness Clfs",
    "sg:city":"Birmingham",
    "sg:classifiers":[
        {
            "category":"Restaurant",
            "type":"Food & Drink"
        }
    ],
    "sg:menulink":"http://www.allmenus.com/al/alabaster-helena/254821-ohenrys-coffees/menu/",
    "sg:phone":"+1 205 995 2077",
    "sg:postcode":"35242",
    "sg:province":"AL",
    "wof:name":"O'Henry's Coffees",
    "wof:placetype":"venue"
},
  "geometry": {"coordinates":[-86.705003,33.407459],"type":"Point"}
}