{
  "type": "Feature",
  "properties": {
    "iso:country":"US",
    "sg:address":"528 4th Ave N",
    "sg:city":"Bessemer",
    "sg:classifiers":[
        {
            "category":"Food & Beverages",
            "subcategory":"Groceries & Convenience Stores",
            "type":"Retail Goods"
        }
    ],
    "sg:phone":"+1 205 424 6625",
    "sg:postcode":"35020",
    "sg:province":"AL",
    "sg:tags":[
        "grocer"
    ],
    "wof:name":"Fourth Avenue Super Market",
    "wof:placetype":"venue"
},
  "geometry": {"coordinates":[-86.966859,33.388064],"type":"Point"}
}