{
  "type": "Feature",
  "properties": {
    "iso:country":"US",
    "sg:address":"3055 Spring Hill Ave",
    "sg:city":"Mobile",
    "sg:classifiers":[
        {
            "category":"Social Services",
            "subcategory":"Child Care",
            "type":"Services"
        }
    ],
    "sg:phone":"+1 251 473 6154",
    "sg:postcode":"36607",
    "sg:province":"AL",
    "sg:tags":[
        "day"
    ],
    "wof:name":"Kids & Co Learning Center",
    "wof:placetype":"venue"
},
  "geometry": {"coordinates":[-88.112159,30.700082],"type":"Point"}
}