{
  "type": "Feature",
  "properties": {
    "iso:country":"US",
    "sg:address":"3951 Airport Blvd",
    "sg:city":"Mobile",
    "sg:classifiers":[
        {
            "category":"Autos & Motor Vehicles",
            "subcategory":"Fuel & Gas Station",
            "type":"Retail Goods"
        }
    ],
    "sg:phone":"+1 251 414 2822",
    "sg:postcode":"36608",
    "sg:province":"AL",
    "sg:tags":[
        "station",
        "gasoline"
    ],
    "wof:name":"Spur Station",
    "wof:placetype":"venue"
},
  "geometry": {"coordinates":[-88.149414,30.67597],"type":"Point"}
}