{
  "type": "Feature",
  "properties": {
    "addr:full":"1616 Dandridge St SW Decatur AL 35601",
    "addr:housenumber":"1616",
    "addr:postcode":"35601",
    "addr:street":"Dandridge St Sw",
    "iso:country":"US",
    "sg:address":"1616 Dandridge St SW",
    "sg:city":"Decatur",
    "sg:classifiers":[
        {
            "category":"Freight",
            "type":"Transportation"
        }
    ],
    "sg:phone":"+1 256 355 3811",
    "sg:postcode":"35601",
    "sg:province":"AL",
    "sg:tags":[
        "trucking"
    ],
    "wof:name":"Landstar Ligon Inc",
    "wof:placetype":"venue"
},
  "geometry": {"coordinates":[-87.01186800000001,34.588918],"type":"Point"}
}