{
  "type": "Feature",
  "properties": {
    "addr:full":"620 Zeigler Cir W Mobile AL 36608",
    "addr:housenumber":"620",
    "addr:postcode":"36608",
    "addr:street":"Zeigler Cir W",
    "iso:country":"US",
    "sg:address":"620 Zeigler Cir W",
    "sg:city":"Mobile",
    "sg:classifiers":[
        {
            "category":"Organizations",
            "subcategory":"Membership Organization",
            "type":"Services"
        }
    ],
    "sg:phone":"+1 251 633 3531",
    "sg:postcode":"36608",
    "sg:province":"AL",
    "sg:tags":[
        "society",
        "humane"
    ],
    "wof:name":"Society For Prevention-Cruelty",
    "wof:placetype":"venue"
},
  "geometry": {"coordinates":[-88.215296,30.702308],"type":"Point"}
}