{
  "type": "Feature",
  "properties": {
    "iso:country":"US",
    "sg:address":"4616 Gilley St",
    "sg:city":"Guntersville",
    "sg:classifiers":[
        {
            "category":"Building & Trades",
            "subcategory":"Plumbing",
            "type":"Services"
        }
    ],
    "sg:phone":"+1 256 582 8262",
    "sg:postcode":"35976",
    "sg:province":"AL",
    "sg:tags":[
        "conditioning",
        "air",
        "system",
        "contractor"
    ],
    "wof:name":"Davis Heating & Cooling Svc",
    "wof:placetype":"venue"
},
  "geometry": {"coordinates":[-86.291844,34.309192],"type":"Point"}
}