{
  "type": "Feature",
  "properties": {
    "iso:country":"US",
    "sg:address":"306 Pine Dr",
    "sg:city":"Henagar",
    "sg:classifiers":[
        {
            "category":"Farming",
            "subcategory":"Farm",
            "type":"Manufacturing & Wholesale Goods"
        }
    ],
    "sg:phone":"+1 256 657 5548",
    "sg:postcode":"35978",
    "sg:province":"AL",
    "sg:tags":[
        "crop",
        "general"
    ],
    "wof:name":"Murdock Farms",
    "wof:placetype":"venue"
},
  "geometry": {"coordinates":[-85.76375899999999,34.61988],"type":"Point"}
}