{
  "type": "Feature",
  "properties": {
    "iso:country":"US",
    "sg:address":"233 Summit Blvd",
    "sg:city":"Birmingham",
    "sg:phone":"+1 205 967 0040",
    "sg:postcode":"35243",
    "sg:province":"AL",
    "sg:website":"http://www.pfchangs.com/",
    "wof:name":"P.F. Chang's China Bistro",
    "wof:placetype":"venue"
},
  "geometry": {"coordinates":[-86.73092699999999,33.447603],"type":"Point"}
}