{
  "type": "Feature",
  "properties": {
    "addr:full":"6625 Jenean St Cottondale AL 35453",
    "addr:postcode":"6625;35453",
    "addr:street":"Jenean St",
    "iso:country":"US",
    "sg:address":"6625 Jenean St",
    "sg:city":"Cottondale",
    "sg:classifiers":[
        {
            "category":"Retail",
            "subcategory":"Auto Repair",
            "type":"Services"
        }
    ],
    "sg:phone":"+1 205 556 4566",
    "sg:postcode":"35453",
    "sg:province":"AL",
    "sg:tags":[
        "wrecker"
    ],
    "wof:name":"Whisenhant Towing",
    "wof:placetype":"venue"
},
  "geometry": {"coordinates":[-87.45016099999999,33.191359],"type":"Point"}
}