{
  "type": "Feature",
  "properties": {
    "iso:country":"US",
    "sg:address":"464 Bass Cir NW",
    "sg:city":"Huntsville",
    "sg:classifiers":[
        {
            "category":"Building & Trades",
            "subcategory":"Construction",
            "type":"Services"
        }
    ],
    "sg:phone":"+1 256 539 1944",
    "sg:postcode":"35801",
    "sg:province":"AL",
    "sg:tags":[
        "home",
        "improvement"
    ],
    "wof:name":"Hoover General Contractors LLC",
    "wof:placetype":"venue"
},
  "geometry": {"coordinates":[-86.589433,34.747069],"type":"Point"}
}