{
  "type": "Feature",
  "properties": {
    "addr:full":"230 85th St N Birmingham AL 35206",
    "addr:housenumber":"230",
    "addr:postcode":"35206",
    "addr:street":"85Th St N",
    "iso:country":"US",
    "sg:address":"230 85th St N",
    "sg:city":"Birmingham",
    "sg:classifiers":[
        {
            "category":"Organizations",
            "subcategory":"Religious Organization",
            "type":"Services"
        }
    ],
    "sg:phone":"+1 205 833 6222",
    "sg:postcode":"35206",
    "sg:province":"AL",
    "sg:tags":[
        "church"
    ],
    "wof:name":"Forty Six Street Baptst Church",
    "wof:placetype":"venue"
},
  "geometry": {"coordinates":[-86.72206,33.57487],"type":"Point"}
}