{
  "type": "Feature",
  "properties": {
    "iso:country":"US",
    "sg:address":"2330 2nd Ave S",
    "sg:city":"Birmingham",
    "sg:classifiers":[
        {
            "category":"Building & Trades",
            "subcategory":"Construction",
            "type":"Services"
        }
    ],
    "sg:phone":"+1 205 254 1820",
    "sg:postcode":"35233",
    "sg:province":"AL",
    "sg:tags":[
        "specializing",
        "remodeling",
        "contractor"
    ],
    "wof:name":"Irwin Brothers Remodeling",
    "wof:placetype":"venue"
},
  "geometry": {"coordinates":[-86.798138,33.513374],"type":"Point"}
}