{
  "type": "Feature",
  "properties": {
    "iso:country":"US",
    "sg:address":"10312 Co Rd 81",
    "sg:city":"Gordon",
    "sg:classifiers":[
        {
            "category":"Freight",
            "type":"Transportation"
        }
    ],
    "sg:phone":"+1 334 691 4561",
    "sg:postcode":"36343",
    "sg:province":"AL",
    "sg:tags":[
        "operator",
        "local",
        "trucking"
    ],
    "wof:name":"Jerue Trucking",
    "wof:placetype":"venue"
},
  "geometry": {"coordinates":[-85.209772,31.01216],"type":"Point"}
}