{
  "type": "Feature",
  "properties": {
    "iso:country":"US",
    "sg:address":"4221 50th Ave N",
    "sg:city":"Birmingham",
    "sg:classifiers":[
        {
            "category":"Building & Trades",
            "subcategory":"Construction",
            "type":"Services"
        }
    ],
    "sg:phone":"+1 205 849 0508",
    "sg:postcode":"35217",
    "sg:province":"AL",
    "sg:tags":[
        "carpentry",
        "contractor"
    ],
    "wof:name":"Tara Mia Instalation",
    "wof:placetype":"venue"
},
  "geometry": {"coordinates":[-86.774761,33.572414],"type":"Point"}
}