{
  "type": "Feature",
  "properties": {
    "addr:full":"122 Camden Cir Madison AL 35758",
    "addr:housenumber":"122",
    "addr:postcode":"35758",
    "addr:street":"Camden Cir",
    "iso:country":"US",
    "sg:address":"122 Camden Cir",
    "sg:city":"Madison",
    "sg:classifiers":[
        {
            "category":"Professional",
            "subcategory":"Business Services",
            "type":"Services"
        }
    ],
    "sg:phone":"+1 256 464 5965",
    "sg:postcode":"35758",
    "sg:province":"AL",
    "wof:name":"Lynd Enterprises Inc",
    "wof:placetype":"venue"
},
  "geometry": {"coordinates":[-86.78304900000001,34.713802],"type":"Point"}
}