{
  "type": "Feature",
  "properties": {
    "addr:full":"60 Maxwell Blvd E Montgomery AL 36112",
    "addr:housenumber":"60",
    "addr:postcode":"36112",
    "addr:street":"Maxwell Blvd E",
    "iso:country":"US",
    "sg:address":"60 Maxwell Blvd E",
    "sg:city":"Montgomery",
    "sg:classifiers":[
        {
            "category":"Professional",
            "subcategory":"Business Services",
            "type":"Services"
        }
    ],
    "sg:phone":"+1 334 953 7519",
    "sg:postcode":"36112",
    "sg:province":"AL",
    "sg:tags":[
        "purchasing"
    ],
    "wof:name":"42nd Services Squadron",
    "wof:placetype":"venue"
},
  "geometry": {"coordinates":[-86.346688,32.380052],"type":"Point"}
}