{
  "type": "Feature",
  "properties": {
    "iso:country":"US",
    "sg:address":"8551 Tanner Williams Rd",
    "sg:city":"Mobile",
    "sg:classifiers":[
        {
            "category":"Government",
            "subcategory":"Office",
            "type":"Public Place"
        }
    ],
    "sg:phone":"+1 251 441 6872",
    "sg:postcode":"36608",
    "sg:province":"AL",
    "sg:tags":[
        "transportation"
    ],
    "wof:name":"Mwr Officer",
    "wof:placetype":"venue"
},
  "geometry": {"coordinates":[-88.244369,30.700805],"type":"Point"}
}