{
  "type": "Feature",
  "properties": {
    "addr:full":"463 S Oates St Dothan AL 36301",
    "addr:housenumber":"463",
    "addr:postcode":"36301",
    "addr:street":"S Oates St",
    "iso:country":"US",
    "sg:address":"463 S Oates St",
    "sg:city":"Dothan",
    "sg:classifiers":[
        {
            "category":"Retail",
            "subcategory":"Car Wash",
            "type":"Services"
        }
    ],
    "sg:phone":"+1 334 677 1621",
    "sg:postcode":"36301",
    "sg:province":"AL",
    "sg:tags":[
        "polishing",
        "carwash",
        "washing"
    ],
    "wof:name":"Perfect Touch Car Wsh & Auto D",
    "wof:placetype":"venue"
},
  "geometry": {"coordinates":[-85.392949,31.218992],"type":"Point"}
}