{
  "type": "Feature",
  "properties": {
    "iso:country":"US",
    "sg:address":"1808 7th Ave S",
    "sg:city":"Birmingham",
    "sg:classifiers":[
        {
            "category":"Education",
            "subcategory":"College",
            "type":"Public Place"
        }
    ],
    "sg:phone":"+1 205 934 6387",
    "sg:postcode":"35233",
    "sg:province":"AL",
    "wof:name":"Uab/Immunobiology/Tr",
    "wof:placetype":"venue"
},
  "geometry": {"coordinates":[-86.80141,33.505208],"type":"Point"}
}