{
  "type": "Feature",
  "properties": {
    "iso:country":"US",
    "sg:address":"805 Eagle Rd",
    "sg:city":"Dothan",
    "sg:classifiers":[
        {
            "category":"Professional",
            "type":"Services"
        }
    ],
    "sg:phone":"+1 334 699 3078",
    "sg:postcode":"36303",
    "sg:province":"AL",
    "wof:name":"G Williams",
    "wof:placetype":"venue"
},
  "geometry": {"coordinates":[-85.371835,31.231698],"type":"Point"}
}