{
  "type": "Feature",
  "properties": {
    "iso:country":"US",
    "sg:address":"1301 W Montgomery Rd",
    "sg:city":"Tuskegee Inst",
    "sg:classifiers":[
        {
            "category":"Shopping",
            "subcategory":"Gifts & Souvenirs",
            "type":"Retail Goods"
        }
    ],
    "sg:phone":"+1 334 727 1130",
    "sg:postcode":"36088",
    "sg:province":"AL",
    "sg:tags":[
        "shop"
    ],
    "wof:name":"Felder's Gift & Variety Shop",
    "wof:placetype":"venue"
},
  "geometry": {"coordinates":[-85.709339,32.428232],"type":"Point"}
}