{
  "type": "Feature",
  "properties": {
    "addr:full":"3208 Sexton Rd SE Decatur AL 35603",
    "addr:housenumber":"3208",
    "addr:postcode":"35603",
    "addr:street":"Sexton Rd Se",
    "iso:country":"US",
    "sg:address":"3208 Sexton Rd SE",
    "sg:city":"Decatur",
    "sg:classifiers":[
        {
            "category":"Retail",
            "subcategory":"Auto Repair",
            "type":"Services"
        }
    ],
    "sg:phone":"+1 256 355 5521",
    "sg:postcode":"35603",
    "sg:province":"AL",
    "wof:name":"Service Plus Inc",
    "wof:placetype":"venue"
},
  "geometry": {"coordinates":[-86.976708,34.545471],"type":"Point"}
}