{
  "type": "Feature",
  "properties": {
    "addr:full":"2509 Highland Ave Montgomery AL 36107",
    "addr:housenumber":"2509",
    "addr:postcode":"36107",
    "addr:street":"Highland Ave",
    "iso:country":"US",
    "sg:address":"2509 Highland Ave",
    "sg:city":"Montgomery",
    "sg:classifiers":[
        {
            "category":"Shopping",
            "subcategory":"Hobbies, Toys, & Games",
            "type":"Retail Goods"
        }
    ],
    "sg:phone":"+1 334 264 2349",
    "sg:postcode":"36107",
    "sg:province":"AL",
    "wof:name":"South Alabama Ceramic Supply",
    "wof:placetype":"venue"
},
  "geometry": {"coordinates":[-86.274427,32.372434],"type":"Point"}
}