{
  "type": "Feature",
  "properties": {
    "iso:country":"US",
    "sg:address":"4243 E Lake Blvd",
    "sg:city":"Birmingham",
    "sg:classifiers":[
        {
            "category":"Airport",
            "type":"Transportation"
        }
    ],
    "sg:phone":"+1 205 849 3820",
    "sg:postcode":"35217",
    "sg:province":"AL",
    "sg:tags":[
        "aircraft",
        "maintenance"
    ],
    "wof:name":"Jetsouth Corporation",
    "wof:placetype":"venue"
},
  "geometry": {"coordinates":[-86.772963,33.557408],"type":"Point"}
}