{
  "type": "Feature",
  "properties": {
    "iso:country":"US",
    "sg:address":"7201 Stemley Bridge Rd",
    "sg:city":"Talladega",
    "sg:classifiers":[
        {
            "category":"Building & Trades",
            "subcategory":"Construction",
            "type":"Services"
        }
    ],
    "sg:phone":"+1 256 268 2680",
    "sg:postcode":"35160",
    "sg:province":"AL",
    "sg:tags":[
        "concrete",
        "contractor"
    ],
    "wof:name":"Cochran Concrete Inc",
    "wof:placetype":"venue"
},
  "geometry": {"coordinates":[-86.202518,33.514835],"type":"Point"}
}