{
  "type": "Feature",
  "properties": {
    "addr:full":"3479 Gulf Shores Pkwy Gulf Shores AL 36542",
    "addr:housenumber":"3479",
    "addr:postcode":"36542",
    "addr:street":"Gulf Shores Pkwy",
    "iso:country":"US",
    "sg:address":"3479 Gulf Shores Pkwy",
    "sg:city":"Gulf Shores",
    "sg:classifiers":[
        {
            "category":"Real Estate",
            "subcategory":"Real Estate Agent",
            "type":"Services"
        }
    ],
    "sg:phone":"+1 251 943 5850",
    "sg:postcode":"36542",
    "sg:province":"AL",
    "wof:name":"Realty Executives",
    "wof:placetype":"venue"
},
  "geometry": {"coordinates":[-87.683243,30.302286],"type":"Point"}
}