{
  "type": "Feature",
  "properties": {
    "addr:full":"601 Highland Ave Anniston AL 36207",
    "addr:housenumber":"601",
    "addr:postcode":"36207",
    "addr:street":"Highland Ave",
    "iso:country":"US",
    "sg:address":"601 Highland Ave",
    "sg:city":"Anniston",
    "sg:classifiers":[
        {
            "category":"Organizations",
            "subcategory":"Community Association",
            "type":"Services"
        }
    ],
    "sg:phone":"+1 256 237 4615",
    "sg:postcode":"36207",
    "sg:province":"AL",
    "sg:tags":[
        "club"
    ],
    "wof:name":"Anniston Country Club",
    "wof:placetype":"venue"
},
  "geometry": {"coordinates":[-85.818676,33.652861],"type":"Point"}
}