{
  "type": "Feature",
  "properties": {
    "iso:country":"US",
    "sg:address":"411 4th St",
    "sg:city":"Cuba",
    "sg:classifiers":[
        {
            "category":"Government",
            "subcategory":"Fire Station",
            "type":"Public Place"
        }
    ],
    "sg:phone":"+1 205 392 7181",
    "sg:postcode":"36907",
    "sg:province":"AL",
    "sg:tags":[
        "protection"
    ],
    "wof:name":"Cuba Town of Fire",
    "wof:placetype":"venue"
},
  "geometry": {"coordinates":[-88.379382,32.429449],"type":"Point"}
}