{
  "type": "Feature",
  "properties": {
    "iso:country":"US",
    "sg:address":"1221 16th St N",
    "sg:city":"Birmingham",
    "sg:classifiers":[
        {
            "category":"Organizations",
            "subcategory":"Religious Organization",
            "type":"Services"
        }
    ],
    "sg:phone":"+1 205 252 3677",
    "sg:postcode":"35204",
    "sg:province":"AL",
    "wof:name":"Robert L Crim Rev",
    "wof:placetype":"venue"
},
  "geometry": {"coordinates":[-86.820116,33.524811],"type":"Point"}
}