{
  "type": "Feature",
  "properties": {
    "addr:full":"1524 Catoma Ln NE Cullman AL 35055",
    "addr:housenumber":"1524",
    "addr:postcode":"35055",
    "addr:street":"Catoma Ln Ne",
    "iso:country":"US",
    "sg:address":"1524 Catoma Ln NE",
    "sg:city":"Cullman",
    "sg:classifiers":[
        {
            "category":"Autos & Motor Vehicles",
            "subcategory":"Automobile Sales",
            "type":"Retail Goods"
        }
    ],
    "sg:phone":"+1 256 739 4036",
    "sg:postcode":"35055",
    "sg:province":"AL",
    "sg:tags":[
        "used"
    ],
    "wof:name":"Turney Auto Sales",
    "wof:placetype":"venue"
},
  "geometry": {"coordinates":[-86.814606,34.192828],"type":"Point"}
}