{
  "type": "Feature",
  "properties": {
    "iso:country":"US",
    "sg:address":"2171 Douglas Ave",
    "sg:city":"Brewton",
    "sg:classifiers":[
        {
            "category":"Autos & Motor Vehicles",
            "subcategory":"Fuel & Gas Station",
            "type":"Retail Goods"
        },
        {
            "category":"Food & Beverages",
            "subcategory":"Groceries & Convenience Stores",
            "type":"Retail Goods"
        }
    ],
    "sg:phone":"+1 251 867 7678",
    "sg:postcode":"36426",
    "sg:province":"AL",
    "sg:website":"http://www.tomt.com",
    "wof:name":"Tom Thumb Food & Pharmacy",
    "wof:placetype":"venue"
},
  "geometry": {"coordinates":[-87.06217599999999,31.13847],"type":"Point"}
}