{
  "type": "Feature",
  "properties": {
    "iso:country":"US",
    "sg:address":"2210 8th St",
    "sg:city":"Tuscaloosa",
    "sg:classifiers":[
        {
            "category":"Real Estate",
            "subcategory":"Real Estate Services",
            "type":"Services"
        }
    ],
    "sg:phone":"+1 205 345 7444",
    "sg:postcode":"35401",
    "sg:province":"AL",
    "sg:tags":[
        "company",
        "title"
    ],
    "wof:name":"Tuscaloosa Title Co",
    "wof:placetype":"venue"
},
  "geometry": {"coordinates":[-87.565693,33.207468],"type":"Point"}
}