{
  "type": "Feature",
  "properties": {
    "iso:country":"US",
    "sg:address":"120 Hillcrest Dr",
    "sg:city":"Andalusia",
    "sg:classifiers":[
        {
            "category":"Social Services",
            "subcategory":"Child Care",
            "type":"Services"
        }
    ],
    "sg:phone":"+1 334 222 8114",
    "sg:postcode":"36420",
    "sg:province":"AL",
    "sg:tags":[
        "school",
        "day"
    ],
    "wof:name":"Little Friends Pre School",
    "wof:placetype":"venue"
},
  "geometry": {"coordinates":[-86.501248,31.313617],"type":"Point"}
}