{
  "type": "Feature",
  "properties": {
    "addr:full":"9711 Twin Beach Rd Fairhope AL 36532",
    "addr:housenumber":"9711",
    "addr:postcode":"36532",
    "addr:street":"Twin Beach Rd",
    "iso:country":"US",
    "sg:address":"9711 Twin Beach Rd",
    "sg:city":"Fairhope",
    "sg:classifiers":[
        {
            "category":"Farming",
            "subcategory":"Farm",
            "type":"Manufacturing & Wholesale Goods"
        }
    ],
    "sg:phone":"+1 251 928 4311",
    "sg:postcode":"36532",
    "sg:province":"AL",
    "sg:tags":[
        "crop",
        "general"
    ],
    "wof:name":"Bee Natural Farm",
    "wof:placetype":"venue"
},
  "geometry": {"coordinates":[-87.857669,30.501844],"type":"Point"}
}