{
  "type": "Feature",
  "properties": {
    "addr:full":"1644 Kahatchee Loop Childersburg AL 35044",
    "addr:housenumber":"1644",
    "addr:postcode":"35044",
    "addr:street":"Kahatchee Loop",
    "iso:country":"US",
    "sg:address":"1644 Kahatchee Loop",
    "sg:city":"Childersburg",
    "sg:classifiers":[
        {
            "category":"Mining & Drilling",
            "type":"Manufacturing & Wholesale Goods"
        }
    ],
    "sg:phone":"+1 256 378 7407",
    "sg:postcode":"35044",
    "sg:province":"AL",
    "sg:tags":[
        "stone"
    ],
    "wof:name":"ASI Stone Inc",
    "wof:placetype":"venue"
},
  "geometry": {"coordinates":[-86.421774,33.211187],"type":"Point"}
}