{
  "type": "Feature",
  "properties": {
    "addr:full":"4123 Woodland Hills Dr Tuscaloosa AL 35405",
    "addr:housenumber":"4123",
    "addr:postcode":"35405",
    "addr:street":"Woodland Hills Dr",
    "iso:country":"US",
    "sg:address":"4123 Woodland Hills Dr",
    "sg:city":"Tuscaloosa",
    "sg:classifiers":[
        {
            "category":"Building & Trades",
            "subcategory":"Cleaning & Sanitation",
            "type":"Services"
        }
    ],
    "sg:phone":"+1 205 633 0861",
    "sg:postcode":"35405",
    "sg:province":"AL",
    "sg:tags":[
        "maintenance"
    ],
    "wof:name":"Bajo Cleaning Service",
    "wof:placetype":"venue"
},
  "geometry": {"coordinates":[-87.48337600000001,33.180016],"type":"Point"}
}