{
  "type": "Feature",
  "properties": {
    "iso:country":"US",
    "sg:address":"2400 Pavan Dr",
    "sg:city":"Mobile",
    "sg:classifiers":[
        {
            "category":"Building & Trades",
            "subcategory":"Electrical",
            "type":"Services"
        }
    ],
    "sg:phone":"+1 251 666 2535",
    "sg:postcode":"36693",
    "sg:province":"AL",
    "sg:tags":[
        "electrical",
        "contractor"
    ],
    "wof:name":"Burris Electric",
    "wof:placetype":"venue"
},
  "geometry": {"coordinates":[-88.17688699999999,30.639408],"type":"Point"}
}