{
  "type": "Feature",
  "properties": {
    "iso:country":"US",
    "sg:address":"4612 Sylvaner Ln",
    "sg:city":"Birmingham",
    "sg:classifiers":[
        {
            "category":"Retail",
            "subcategory":"Portrait Studio",
            "type":"Services"
        }
    ],
    "sg:phone":"+1 205 985 9269",
    "sg:postcode":"35244",
    "sg:province":"AL",
    "sg:tags":[
        "photo"
    ],
    "wof:name":"Eleven Eleven Images",
    "wof:placetype":"venue"
},
  "geometry": {"coordinates":[-86.76425999999999,33.392388],"type":"Point"}
}