{
  "type": "Feature",
  "properties": {
    "iso:country":"US",
    "sg:address":"433 Valley Ave",
    "sg:city":"Birmingham",
    "sg:classifiers":[
        {
            "category":"Recreation",
            "type":"Entertainment"
        }
    ],
    "sg:phone":"+1 205 942 5115",
    "sg:postcode":"35209",
    "sg:province":"AL",
    "wof:name":"Spin & Win Arcade",
    "wof:placetype":"venue"
},
  "geometry": {"coordinates":[-86.818641,33.473279],"type":"Point"}
}