{
  "type": "Feature",
  "properties": {
    "addr:full":"4971 Meadow Brook Rd Birmingham AL 35242",
    "addr:housenumber":"4971",
    "addr:postcode":"35242",
    "addr:street":"Meadow Brook Rd",
    "iso:country":"US",
    "sg:address":"4971 Meadow Brook Rd",
    "sg:city":"Birmingham",
    "sg:classifiers":[
        {
            "category":"Building & Trades",
            "subcategory":"Construction",
            "type":"Services"
        }
    ],
    "sg:phone":"+1 205 408 8880",
    "sg:postcode":"35242",
    "sg:province":"AL",
    "sg:tags":[
        "general",
        "contractor"
    ],
    "wof:name":"Grace Construction Products",
    "wof:placetype":"venue"
},
  "geometry": {"coordinates":[-86.692707,33.410194],"type":"Point"}
}