{
  "type": "Feature",
  "properties": {
    "iso:country":"US",
    "sg:address":"3975 Joyce Cir",
    "sg:city":"Moody",
    "sg:classifiers":[
        {
            "category":"Professional",
            "type":"Services"
        }
    ],
    "sg:phone":"+1 205 640 3110",
    "sg:postcode":"35004",
    "sg:province":"AL",
    "wof:name":"Moody Dogg Pound Inc",
    "wof:placetype":"venue"
},
  "geometry": {"coordinates":[-86.471721,33.625522],"type":"Point"}
}