{
  "type": "Feature",
  "properties": {
    "iso:country":"US",
    "sg:address":"237 Lakeview Ln",
    "sg:city":"Sylacauga",
    "sg:classifiers":[
        {
            "category":"Professional",
            "type":"Services"
        }
    ],
    "sg:phone":"+1 256 245 2822",
    "sg:postcode":"35151",
    "sg:province":"AL",
    "wof:name":"Southernl Exterior Creations",
    "wof:placetype":"venue"
},
  "geometry": {"coordinates":[-86.48826800000001,33.19043],"type":"Point"}
}