{
  "type": "Feature",
  "properties": {
    "addr:full":"2604 Helton Dr Florence AL 35630",
    "addr:housenumber":"2604",
    "addr:postcode":"35630",
    "addr:street":"Helton Dr",
    "iso:country":"US",
    "sg:address":"2604 Helton Dr",
    "sg:city":"Florence",
    "sg:classifiers":[
        {
            "category":"Retail",
            "subcategory":"Auto Repair",
            "type":"Services"
        }
    ],
    "sg:phone":"+1 256 764 4545",
    "sg:postcode":"35630",
    "sg:province":"AL",
    "sg:tags":[
        "repairing",
        "automobile",
        "automotive"
    ],
    "wof:name":"Express Oil Change",
    "wof:placetype":"venue"
},
  "geometry": {"coordinates":[-87.670907,34.840543],"type":"Point"}
}