{
  "type": "Feature",
  "properties": {
    "iso:country":"US",
    "sg:address":"4680 Rangeline Rd",
    "sg:city":"Mobile",
    "sg:classifiers":[
        {
            "category":"Building & Trades",
            "subcategory":"Construction",
            "type":"Services"
        }
    ],
    "sg:phone":"+1 251 661 6773",
    "sg:postcode":"36619",
    "sg:province":"AL",
    "sg:tags":[
        "contractor"
    ],
    "wof:name":"Loper Jl Construction Co",
    "wof:placetype":"venue"
},
  "geometry": {"coordinates":[-88.147868,30.593029],"type":"Point"}
}