{
  "type": "Feature",
  "properties": {
    "iso:country":"US",
    "sg:address":"1147 Rifle Range Rd",
    "sg:city":"Wetumpka",
    "sg:classifiers":[
        {
            "category":"Professional",
            "subcategory":"Business Services",
            "type":"Services"
        }
    ],
    "sg:phone":"+1 334 567 9927",
    "sg:postcode":"36093",
    "sg:province":"AL",
    "sg:tags":[
        "event"
    ],
    "wof:name":"Plaid Fox",
    "wof:placetype":"venue"
},
  "geometry": {"coordinates":[-86.158379,32.45104],"type":"Point"}
}