{
  "type": "Feature",
  "properties": {
    "iso:country":"US",
    "sg:address":"236 Co Rd 279",
    "sg:city":"Valley Grande",
    "sg:classifiers":[
        {
            "category":"Home & Garden",
            "subcategory":"Garden Supply",
            "type":"Retail Goods"
        }
    ],
    "sg:phone":"+1 334 872 2600",
    "sg:postcode":"36701",
    "sg:province":"AL",
    "sg:tags":[
        "lawn",
        "mower"
    ],
    "wof:name":"Hudson's Small Engines",
    "wof:placetype":"venue"
},
  "geometry": {"coordinates":[-87.056031,32.526679],"type":"Point"}
}