{
  "type": "Feature",
  "properties": {
    "addr:full":"24 W 13th St Anniston AL 36201",
    "addr:housenumber":"24",
    "addr:postcode":"36201",
    "addr:street":"W 13Th St",
    "iso:country":"US",
    "sg:address":"24 W 13th St",
    "sg:city":"Anniston",
    "sg:classifiers":[
        {
            "category":"Personal",
            "subcategory":"Beauty Salon",
            "type":"Services"
        }
    ],
    "sg:phone":"+1 256 237 5577",
    "sg:postcode":"36201",
    "sg:province":"AL",
    "sg:tags":[
        "shop"
    ],
    "wof:name":"Illusions",
    "wof:placetype":"venue"
},
  "geometry": {"coordinates":[-85.83029000000001,33.661132],"type":"Point"}
}