{
  "type": "Feature",
  "properties": {
    "iso:country":"US",
    "sg:address":"285 Gibbs St",
    "sg:city":"Troy",
    "sg:classifiers":[
        {
            "category":"Education",
            "subcategory":"School",
            "type":"Public Place"
        }
    ],
    "sg:phone":"+1 334 566 5395",
    "sg:postcode":"36081",
    "sg:province":"AL",
    "wof:name":"Troy-Pike Reg Center For Tech",
    "wof:placetype":"venue"
},
  "geometry": {"coordinates":[-85.957321,31.820221],"type":"Point"}
}