{
  "type": "Feature",
  "properties": {
    "iso:country":"US",
    "sg:address":"1500 Love Branch Rd",
    "sg:city":"Toney",
    "sg:classifiers":[
        {
            "category":"Building & Trades",
            "subcategory":"Equipment Rental",
            "type":"Services"
        }
    ],
    "sg:phone":"+1 256 837 4915",
    "sg:postcode":"35773",
    "sg:province":"AL",
    "wof:name":"Safari Tan & Gifts",
    "wof:placetype":"venue"
},
  "geometry": {"coordinates":[-86.784272,34.875195],"type":"Point"}
}