{
  "type": "Feature",
  "properties": {
    "iso:country":"US",
    "sg:address":"8416 US Hwy 431",
    "sg:city":"Owens Cross Rds",
    "sg:classifiers":[
        {
            "category":"Retail",
            "subcategory":"Auto Repair",
            "type":"Services"
        }
    ],
    "sg:phone":"+1 256 723 4050",
    "sg:postcode":"35763",
    "sg:province":"AL",
    "sg:tags":[
        "wrecker"
    ],
    "wof:name":"Brown's Wrecker Svc",
    "wof:placetype":"venue"
},
  "geometry": {"coordinates":[-86.453473,34.598884],"type":"Point"}
}