{
  "type": "Feature",
  "properties": {
    "addr:full":"100 25th St S Birmingham AL 35233",
    "addr:housenumber":"100",
    "addr:postcode":"35233",
    "addr:street":"25Th St S",
    "iso:country":"US",
    "sg:address":"100 25th St S",
    "sg:city":"Birmingham",
    "sg:classifiers":[
        {
            "category":"Retail",
            "subcategory":"Auto Repair",
            "type":"Services"
        }
    ],
    "sg:phone":"+1 205 453 0241",
    "sg:postcode":"35233",
    "sg:province":"AL",
    "sg:tags":[
        "shop",
        "automotive",
        "general"
    ],
    "wof:name":"Phoenix Energy Corp",
    "wof:placetype":"venue"
},
  "geometry": {"coordinates":[-86.796683,33.514614],"type":"Point"}
}