{
  "type": "Feature",
  "properties": {
    "addr:full":"741 Church Rd Gadsden AL 35904",
    "addr:housenumber":"741",
    "addr:postcode":"35904",
    "addr:street":"Church Rd",
    "iso:country":"US",
    "sg:address":"741 Church Rd",
    "sg:city":"Gadsden",
    "sg:classifiers":[
        {
            "category":"Professional",
            "subcategory":"Lawyer & Legal Services",
            "type":"Services"
        }
    ],
    "sg:phone":"+1 256 546 8662",
    "sg:postcode":"35904",
    "sg:province":"AL",
    "wof:name":"Stewart E Burns",
    "wof:placetype":"venue"
},
  "geometry": {"coordinates":[-86.008565,34.053435],"type":"Point"}
}