{
  "type": "Feature",
  "properties": {
    "addr:full":"1020 Downtowner Blvd Mobile AL 36609",
    "addr:housenumber":"1020",
    "addr:postcode":"36609",
    "addr:street":"Downtowner Blvd",
    "iso:country":"US",
    "sg:address":"1020 Downtowner Blvd",
    "sg:city":"Mobile",
    "sg:classifiers":[
        {
            "category":"Professional",
            "type":"Services"
        }
    ],
    "sg:phone":"+1 251 316 3542",
    "sg:postcode":"36609",
    "sg:province":"AL",
    "sg:tags":[
        "establishment"
    ],
    "wof:name":"Us Gov Small Bus Admin",
    "wof:placetype":"venue"
},
  "geometry": {"coordinates":[-88.141346,30.668274],"type":"Point"}
}