{
  "type": "Feature",
  "properties": {
    "addr:full":"701 W Section Ave Foley AL 36535",
    "addr:housenumber":"701",
    "addr:postcode":"36535",
    "addr:street":"W Section Ave",
    "iso:country":"US",
    "sg:address":"701 W Section Ave",
    "sg:city":"Foley",
    "sg:classifiers":[
        {
            "category":"Building & Trades",
            "subcategory":"Construction",
            "type":"Services"
        }
    ],
    "sg:phone":"+1 251 943 4940",
    "sg:postcode":"36535",
    "sg:province":"AL",
    "sg:tags":[
        "restoration",
        "cleaning",
        "patio",
        "deck"
    ],
    "wof:name":"Lease-A-Spouse Inc",
    "wof:placetype":"venue"
},
  "geometry": {"coordinates":[-87.695847,30.41405],"type":"Point"}
}