{
  "type": "Feature",
  "properties": {
    "addr:full":"1311 Potter Ave Bessemer AL 35020",
    "addr:housenumber":"1311",
    "addr:postcode":"35020",
    "addr:street":"Potter Ave",
    "iso:country":"US",
    "sg:address":"1311 Potter Ave",
    "sg:city":"Bessemer",
    "sg:classifiers":[
        {
            "category":"Building & Trades",
            "subcategory":"Construction",
            "type":"Services"
        }
    ],
    "sg:phone":"+1 205 368 7182",
    "sg:postcode":"35020",
    "sg:province":"AL",
    "sg:tags":[
        "hanging",
        "contractor"
    ],
    "wof:name":"J & A Painting",
    "wof:placetype":"venue"
},
  "geometry": {"coordinates":[-86.976116,33.358678],"type":"Point"}
}