{
  "type": "Feature",
  "properties": {
    "addr:full":"3983 Cottage Hill Rd Mobile AL 36609",
    "addr:housenumber":"3983",
    "addr:postcode":"36609",
    "addr:street":"Cottage Hill Rd",
    "iso:country":"US",
    "sg:address":"3983 Cottage Hill Rd",
    "sg:city":"Mobile",
    "sg:classifiers":[
        {
            "category":"Autos & Motor Vehicles",
            "subcategory":"Auto Supplies",
            "type":"Retail Goods"
        }
    ],
    "sg:phone":"+1 251 660 6222",
    "sg:postcode":"36609",
    "sg:province":"AL",
    "sg:tags":[
        "automobile",
        "parts"
    ],
    "wof:name":"Autozone",
    "wof:placetype":"venue"
},
  "geometry": {"coordinates":[-88.139535,30.653069],"type":"Point"}
}