{
  "type": "Feature",
  "properties": {
    "iso:country":"US",
    "sg:address":"4216 Lomac St",
    "sg:city":"Montgomery",
    "sg:classifiers":[
        {
            "category":"Health Services",
            "subcategory":"Health Practitioner",
            "type":"Services"
        }
    ],
    "sg:phone":"+1 334 277 5956",
    "sg:postcode":"36106",
    "sg:province":"AL",
    "sg:tags":[
        "psychologist"
    ],
    "wof:name":"Glen Bannister",
    "wof:placetype":"venue"
},
  "geometry": {"coordinates":[-86.229376,32.358261],"type":"Point"}
}