{
  "type": "Feature",
  "properties": {
    "addr:full":"746 Commerce Dr Alexander City AL 35010",
    "addr:housenumber":"746",
    "addr:postcode":"35010",
    "addr:street":"Commerce Dr",
    "iso:country":"US",
    "sg:address":"746 Commerce Dr",
    "sg:city":"Alexander City",
    "sg:classifiers":[
        {
            "category":"Health Services",
            "subcategory":"Doctor",
            "type":"Services"
        }
    ],
    "sg:phone":"+1 256 329 0999",
    "sg:postcode":"35010",
    "sg:province":"AL",
    "sg:tags":[
        "dentist"
    ],
    "wof:name":"Oral & Maxillofacial Surgery",
    "wof:placetype":"venue"
},
  "geometry": {"coordinates":[-85.968653,32.937486],"type":"Point"}
}