{
  "type": "Feature",
  "properties": {
    "iso:country":"US",
    "sg:address":"235 Co Rd 482",
    "sg:city":"Centre",
    "sg:classifiers":[
        {
            "category":"Building & Trades",
            "subcategory":"Electrical",
            "type":"Services"
        }
    ],
    "sg:phone":"+1 256 475 3375",
    "sg:postcode":"35960",
    "sg:province":"AL",
    "sg:tags":[
        "electric",
        "contractor"
    ],
    "wof:name":"Pruitt Phase Electric",
    "wof:placetype":"venue"
},
  "geometry": {"coordinates":[-85.482497,34.160022],"type":"Point"}
}