{
  "type": "Feature",
  "properties": {
    "iso:country":"US",
    "sg:address":"101 Market St W",
    "sg:city":"Athens",
    "sg:classifiers":[
        {
            "category":"Restaurant",
            "type":"Food & Drink"
        }
    ],
    "sg:phone":"+1 256 233 1314",
    "sg:postcode":"35611",
    "sg:province":"AL",
    "wof:name":"Boxcar Diner",
    "wof:placetype":"venue"
},
  "geometry": {"coordinates":[-86.970019,34.803258],"type":"Point"}
}