{
  "type": "Feature",
  "properties": {
    "addr:full":"101 Market St W Athens AL 35611",
    "addr:housenumber":"101",
    "addr:postcode":"35611",
    "addr:street":"Market St W",
    "iso:country":"US",
    "sg:address":"101 Market St W",
    "sg:city":"Athens",
    "sg:classifiers":[
        {
            "category":"Restaurant",
            "type":"Food & Drink"
        }
    ],
    "sg:phone":"+1 256 233 1314",
    "sg:postcode":"35611",
    "sg:province":"AL",
    "wof:name":"Boxcar Diner",
    "wof:placetype":"venue"
},
  "geometry": {"coordinates":[-86.97001899999999,34.803258],"type":"Point"}
}