{
  "type": "Feature",
  "properties": {
    "iso:country":"US",
    "sg:address":"1259 Windmill Pl W",
    "sg:city":"Mobile",
    "sg:classifiers":[
        {
            "category":"Wholesale",
            "subcategory":"Durable Goods & Equipment",
            "type":"Manufacturing & Wholesale Goods"
        }
    ],
    "sg:phone":"+1 251 633 3096",
    "sg:postcode":"36695",
    "sg:province":"AL",
    "sg:tags":[
        "exporter"
    ],
    "wof:name":"Intelect Inc",
    "wof:placetype":"venue"
},
  "geometry": {"coordinates":[-88.209135,30.663927],"type":"Point"}
}