{
  "type": "Feature",
  "properties": {
    "iso:country":"US",
    "sg:address":"400 S Montgomery Ave",
    "sg:city":"Sheffield",
    "sg:classifiers":[
        {
            "category":"Shopping",
            "subcategory":"Used Merchandise",
            "type":"Retail Goods"
        }
    ],
    "sg:phone":"+1 256 386 8600",
    "sg:postcode":"35660",
    "sg:province":"AL",
    "wof:name":"Keepers of Past Antique MA",
    "wof:placetype":"venue"
},
  "geometry": {"coordinates":[-87.69878,34.753405],"type":"Point"}
}