{
  "type": "Feature",
  "properties": {
    "iso:country":"US",
    "sg:address":"3109 Western Woods Dr",
    "sg:city":"Mobile",
    "sg:classifiers":[
        {
            "category":"Freight",
            "type":"Transportation"
        }
    ],
    "sg:phone":"+1 251 649 4749",
    "sg:postcode":"36618",
    "sg:province":"AL",
    "sg:tags":[
        "operator",
        "local",
        "trucking"
    ],
    "wof:name":"Wilkins Delivery Services LLC",
    "wof:placetype":"venue"
},
  "geometry": {"coordinates":[-88.20320100000001,30.754064],"type":"Point"}
}