{
  "type": "Feature",
  "properties": {
    "addr:full":"141 1st St Anniston AL 36201",
    "addr:housenumber":"141",
    "addr:postcode":"36201",
    "addr:street":"1St St",
    "iso:country":"US",
    "sg:address":"141 1st St",
    "sg:city":"Anniston",
    "sg:classifiers":[
        {
            "category":"Retail",
            "subcategory":"Laundry & Dry Cleaning",
            "type":"Services"
        }
    ],
    "sg:phone":"+1 256 236 6277",
    "sg:postcode":"36201",
    "sg:province":"AL",
    "sg:tags":[
        "cleaners",
        "rug",
        "carpet"
    ],
    "wof:name":"Twentieth Century Carpet",
    "wof:placetype":"venue"
},
  "geometry": {"coordinates":[-85.89561999999999,33.651758],"type":"Point"}
}