{
  "type": "Feature",
  "properties": {
    "iso:country":"US",
    "sg:address":"105 King St",
    "sg:city":"Glenwood",
    "sg:classifiers":[
        {
            "category":"Building & Trades",
            "subcategory":"Construction",
            "type":"Services"
        }
    ],
    "sg:phone":"+1 334 335 5617",
    "sg:postcode":"36034",
    "sg:province":"AL",
    "sg:tags":[
        "excavating",
        "contractor"
    ],
    "wof:name":"N & N Contracting",
    "wof:placetype":"venue"
},
  "geometry": {"coordinates":[-86.16892300000001,31.668669],"type":"Point"}
}