{
  "type": "Feature",
  "properties": {
    "iso:country":"US",
    "sg:address":"105 Co Rd 431",
    "sg:city":"Killen",
    "sg:classifiers":[
        {
            "category":"Organizations",
            "subcategory":"Religious Organization",
            "type":"Services"
        }
    ],
    "sg:phone":"+1 256 757 1782",
    "sg:postcode":"35645",
    "sg:province":"AL",
    "sg:tags":[
        "church"
    ],
    "wof:name":"Antioch Church Of Christ",
    "wof:placetype":"venue"
},
  "geometry": {"coordinates":[-87.467952,34.897994],"type":"Point"}
}