{
  "type": "Feature",
  "properties": {
    "iso:country":"US",
    "sg:address":"3945 Government Blvd",
    "sg:city":"Mobile",
    "sg:classifiers":[
        {
            "category":"Autos & Motor Vehicles",
            "subcategory":"Fuel & Gas Station",
            "type":"Retail Goods"
        }
    ],
    "sg:phone":"+1 251 660 9752",
    "sg:postcode":"36693",
    "sg:province":"AL",
    "sg:tags":[
        "grocery",
        "station",
        "gasoline"
    ],
    "wof:name":"B P Exploration & Oil Inc",
    "wof:placetype":"venue"
},
  "geometry": {"coordinates":[-88.13981200000001,30.638002],"type":"Point"}
}