{
  "type": "Feature",
  "properties": {
    "iso:country":"US",
    "sg:address":"2603 Newby Rd SW",
    "sg:city":"Huntsville",
    "sg:classifiers":[
        {
            "category":"Retail",
            "subcategory":"Repair Shop",
            "type":"Services"
        }
    ],
    "sg:phone":"+1 256 534 5596",
    "sg:postcode":"35805",
    "sg:province":"AL",
    "sg:tags":[
        "refrigeration",
        "contractor"
    ],
    "wof:name":"Gibbs & Sons Heating & Cooling",
    "wof:placetype":"venue"
},
  "geometry": {"coordinates":[-86.597762,34.711984],"type":"Point"}
}