{
  "type": "Feature",
  "properties": {
    "iso:country":"US",
    "sg:address":"5665 Carmichael Rd",
    "sg:city":"Montgomery",
    "sg:classifiers":[
        {
            "category":"Shopping",
            "subcategory":"Bicycles & Sporting Goods",
            "type":"Retail Goods"
        }
    ],
    "sg:phone":"+1 334 260 9075",
    "sg:postcode":"36117",
    "sg:province":"AL",
    "sg:tags":[
        "apparel",
        "bowling",
        "accessory"
    ],
    "wof:name":"Bowlers Aid Pro Shops",
    "wof:placetype":"venue"
},
  "geometry": {"coordinates":[-86.21305099999999,32.359873],"type":"Point"}
}