{
  "type": "Feature",
  "properties": {
    "iso:country":"US",
    "sg:address":"822 Regal Dr SW",
    "sg:city":"Huntsville",
    "sg:classifiers":[
        {
            "category":"Shopping",
            "subcategory":"Clothing, Apparel, & Fashions",
            "type":"Retail Goods"
        }
    ],
    "sg:phone":"+1 256 533 9333",
    "sg:postcode":"35801",
    "sg:province":"AL",
    "sg:tags":[
        "shop",
        "bridal"
    ],
    "wof:name":"Modern Brides Inc",
    "wof:placetype":"venue"
},
  "geometry": {"coordinates":[-86.587031,34.709018],"type":"Point"}
}