{
  "type": "Feature",
  "properties": {
    "iso:country":"US",
    "sg:address":"3069 Allison Bonnett Memorial Dr",
    "sg:city":"Bessemer",
    "sg:classifiers":[
        {
            "category":"Restaurant",
            "type":"Food & Drink"
        }
    ],
    "sg:menulink":"http://www.allmenus.com/al/birmingham/190202-mcdonalds/menu/",
    "sg:postcode":"35023",
    "sg:province":"AL",
    "sg:tags":[
        "burger",
        "american"
    ],
    "wof:name":"McDonald's",
    "wof:placetype":"venue"
},
  "geometry": {"coordinates":[-86.984261,33.450315],"type":"Point"}
}