{
  "type": "Feature",
  "properties": {
    "addr:full":"1110 Jackson Dr Athens AL 35611",
    "addr:housenumber":"1110",
    "addr:postcode":"35611",
    "addr:street":"Jackson Dr",
    "iso:country":"US",
    "sg:address":"1110 Jackson Dr",
    "sg:city":"Athens",
    "sg:classifiers":[
        {
            "category":"Organizations",
            "subcategory":"Religious Organization",
            "type":"Services"
        }
    ],
    "sg:phone":"+1 256 232 1609",
    "sg:postcode":"35611",
    "sg:province":"AL",
    "sg:tags":[
        "church"
    ],
    "wof:name":"Church of Christ",
    "wof:placetype":"venue"
},
  "geometry": {"coordinates":[-86.98797,34.816818],"type":"Point"}
}