{
  "type": "Feature",
  "properties": {
    "addr:full":"4160 Guilford Rd Birmingham AL 35242",
    "addr:housenumber":"4160",
    "addr:postcode":"35242",
    "addr:street":"Guilford Rd",
    "iso:country":"US",
    "sg:address":"4160 Guilford Rd",
    "sg:city":"Birmingham",
    "sg:classifiers":[
        {
            "category":"Professional",
            "subcategory":"Engineering",
            "type":"Services"
        }
    ],
    "sg:phone":"+1 205 995 4758",
    "sg:postcode":"35242",
    "sg:province":"AL",
    "wof:name":"Consulting Etc",
    "wof:placetype":"venue"
},
  "geometry": {"coordinates":[-86.63279300000001,33.419304],"type":"Point"}
}