{
  "type": "Feature",
  "properties": {
    "iso:country":"US",
    "sg:address":"3400 Michael Blvd",
    "sg:city":"Mobile",
    "sg:classifiers":[
        {
            "category":"Professional",
            "subcategory":"Lawyer & Legal Services",
            "type":"Services"
        }
    ],
    "sg:phone":"+1 251 343 2800",
    "sg:postcode":"36609",
    "sg:province":"AL",
    "wof:name":"Turner Ellen T Attorney At Law",
    "wof:placetype":"venue"
},
  "geometry": {"coordinates":[-88.130056,30.661866],"type":"Point"}
}