{
  "type": "Feature",
  "properties": {
    "addr:full":"3400 Michael Blvd Mobile AL 36609",
    "addr:housenumber":"3400",
    "addr:postcode":"36609",
    "addr:street":"Michael Blvd",
    "iso:country":"US",
    "sg:address":"3400 Michael Blvd",
    "sg:city":"Mobile",
    "sg:classifiers":[
        {
            "category":"Professional",
            "subcategory":"Lawyer & Legal Services",
            "type":"Services"
        }
    ],
    "sg:phone":"+1 251 343 2800",
    "sg:postcode":"36609",
    "sg:province":"AL",
    "wof:name":"Turner Ellen T Attorney At Law",
    "wof:placetype":"venue"
},
  "geometry": {"coordinates":[-88.130056,30.661866],"type":"Point"}
}