{
  "type": "Feature",
  "properties": {
    "iso:country":"US",
    "sg:address":"1828 Bassett Ave SE",
    "sg:city":"Decatur",
    "sg:classifiers":[
        {
            "category":"Health Services",
            "subcategory":"Medical Lab",
            "type":"Services"
        }
    ],
    "sg:phone":"+1 256 355 4604",
    "sg:postcode":"35601",
    "sg:province":"AL",
    "sg:tags":[
        "laboratory"
    ],
    "wof:name":"Walker Dental Laboratory Inc",
    "wof:placetype":"venue"
},
  "geometry": {"coordinates":[-86.977626,34.574724],"type":"Point"}
}