{
  "type": "Feature",
  "properties": {
    "iso:country":"US",
    "sg:address":"4904 Oak Circle Dr N",
    "sg:city":"Mobile",
    "sg:classifiers":[
        {
            "category":"Personal",
            "subcategory":"Hair Removal",
            "type":"Services"
        }
    ],
    "sg:phone":"+1 251 661 8673",
    "sg:postcode":"36609",
    "sg:province":"AL",
    "sg:tags":[
        "insurance"
    ],
    "wof:name":"Asset Verification Inc",
    "wof:placetype":"venue"
},
  "geometry": {"coordinates":[-88.15624,30.6523],"type":"Point"}
}