{
  "type": "Feature",
  "properties": {
    "iso:country":"US",
    "sg:address":"520 N Gilmer Ave",
    "sg:city":"Lanett",
    "sg:classifiers":[
        {
            "category":"Retail",
            "subcategory":"Auto Repair",
            "type":"Services"
        }
    ],
    "sg:phone":"+1 334 644 2376",
    "sg:postcode":"36863",
    "sg:province":"AL",
    "sg:tags":[
        "body",
        "automobile",
        "painting",
        "repairing"
    ],
    "sg:website":"http://www.bellford.com",
    "wof:name":"Bell's Collision Center",
    "wof:placetype":"venue"
},
  "geometry": {"coordinates":[-85.186448,32.870292],"type":"Point"}
}