{
  "type": "Feature",
  "properties": {
    "iso:country":"US",
    "sg:address":"370 Saraland Blvd N",
    "sg:city":"Saraland",
    "sg:classifiers":[
        {
            "category":"Insurance",
            "subcategory":"Insurance Agent",
            "type":"Services"
        }
    ],
    "sg:phone":"+1 251 675 5490",
    "sg:postcode":"36571",
    "sg:province":"AL",
    "wof:name":"Alfa Insurance Corp",
    "wof:placetype":"venue"
},
  "geometry": {"coordinates":[-88.06873,30.830315],"type":"Point"}
}