{
  "type": "Feature",
  "properties": {
    "iso:country":"US",
    "sg:address":"1325 44th St N",
    "sg:city":"Birmingham",
    "sg:classifiers":[
        {
            "category":"Organizations",
            "subcategory":"Religious Organization",
            "type":"Services"
        }
    ],
    "sg:phone":"+1 205 595 2704",
    "sg:postcode":"35212",
    "sg:province":"AL",
    "wof:name":"Faith Tabernacle Delivera",
    "wof:placetype":"venue"
},
  "geometry": {"coordinates":[-86.772236,33.547549],"type":"Point"}
}