{
  "type": "Feature",
  "properties": {
    "iso:country":"US",
    "sg:address":"27707 McLemore Cir",
    "sg:city":"Harvest",
    "sg:classifiers":[
        {
            "category":"Banks & Credit Unions",
            "subcategory":"Bank",
            "type":"Services"
        }
    ],
    "sg:phone":"+1 256 216 0676",
    "sg:postcode":"35749",
    "sg:province":"AL",
    "sg:tags":[
        "loan",
        "real estate"
    ],
    "wof:name":"Great Financial Mortgage",
    "wof:placetype":"venue"
},
  "geometry": {"coordinates":[-86.831771,34.780055],"type":"Point"}
}