{
  "type": "Feature",
  "properties": {
    "addr:full":"38 Davis Dr Montgomery AL 36105",
    "addr:housenumber":"38",
    "addr:postcode":"36105",
    "addr:street":"Davis Dr",
    "iso:country":"US",
    "sg:address":"38 Davis Dr",
    "sg:city":"Montgomery",
    "sg:classifiers":[
        {
            "category":"Building & Trades",
            "subcategory":"Construction",
            "type":"Services"
        }
    ],
    "sg:phone":"+1 334 284 2204",
    "sg:postcode":"36105",
    "sg:province":"AL",
    "sg:tags":[
        "installer",
        "fence",
        "contractor"
    ],
    "wof:name":"Pride Alabama Fence Company",
    "wof:placetype":"venue"
},
  "geometry": {"coordinates":[-86.303607,32.328332],"type":"Point"}
}