{
  "type": "Feature",
  "properties": {
    "addr:full":"4000 Eagle Point Corporate Dr Birmingham AL 35242",
    "addr:housenumber":"4000",
    "addr:postcode":"35242",
    "addr:street":"Eagle Point Corporate Dr",
    "iso:country":"US",
    "sg:address":"4000 Eagle Point Corporate Dr",
    "sg:city":"Birmingham",
    "sg:classifiers":[
        {
            "category":"Social Services",
            "type":"Services"
        }
    ],
    "sg:phone":"+1 205 991 2064",
    "sg:postcode":"35242",
    "sg:province":"AL",
    "wof:name":"Eaglelake Consultant",
    "wof:placetype":"venue"
},
  "geometry": {"coordinates":[-86.665471,33.399744],"type":"Point"}
}