{
  "type": "Feature",
  "properties": {
    "addr:full":"16598 Al Highway 117 Henagar AL 35978",
    "addr:housenumber":"16598",
    "addr:postcode":"35978",
    "addr:street":"Al Highway 117",
    "iso:country":"US",
    "sg:address":"16598 Al Highway 117",
    "sg:city":"Henagar",
    "sg:classifiers":[
        {
            "category":"Professional",
            "subcategory":"Lawyer & Legal Services",
            "type":"Services"
        }
    ],
    "sg:phone":"+1 256 657 2020",
    "sg:postcode":"35978",
    "sg:province":"AL",
    "sg:tags":[
        "attorney",
        "practice",
        "plan"
    ],
    "wof:name":"Hartline, Gary B Attorney At Law",
    "wof:placetype":"venue"
},
  "geometry": {"coordinates":[-85.650051,34.656396],"type":"Point"}
}