{
  "type": "Feature",
  "properties": {
    "iso:country":"US",
    "sg:address":"3533 Bermuda Dr",
    "sg:city":"Birmingham",
    "sg:classifiers":[
        {
            "category":"Manufacturing",
            "subcategory":"Retail Goods",
            "type":"Manufacturing & Wholesale Goods"
        }
    ],
    "sg:phone":"+1 205 957 0025",
    "sg:postcode":"35210",
    "sg:province":"AL",
    "sg:tags":[
        "product",
        "mfg"
    ],
    "wof:name":"Miller Mfg & Sales Inc",
    "wof:placetype":"venue"
},
  "geometry": {"coordinates":[-86.68397299999999,33.52294],"type":"Point"}
}