{
  "type": "Feature",
  "properties": {
    "addr:full":"703 17th St NW Aliceville AL 35442",
    "addr:housenumber":"703",
    "addr:postcode":"35442",
    "addr:street":"17Th St Nw Aliceville",
    "iso:country":"US",
    "sg:address":"703 17th St NW",
    "sg:city":"Aliceville",
    "sg:classifiers":[
        {
            "category":"Health Services",
            "subcategory":"Nursing And Care Facility",
            "type":"Services"
        }
    ],
    "sg:phone":"+1 205 373 6307",
    "sg:postcode":"35442",
    "sg:province":"AL",
    "sg:tags":[
        "home",
        "skilled"
    ],
    "wof:name":"Aliceville Manor Nursing Home",
    "wof:placetype":"venue"
},
  "geometry": {"coordinates":[-88.166158,33.137087],"type":"Point"}
}