{
  "type": "Feature",
  "properties": {
    "iso:country":"US",
    "sg:address":"70 Mockingbird Cir",
    "sg:city":"Pell City",
    "sg:classifiers":[
        {
            "category":"Building & Trades",
            "subcategory":"Construction",
            "type":"Services"
        }
    ],
    "sg:phone":"+1 205 884 0838",
    "sg:postcode":"35128",
    "sg:province":"AL",
    "sg:tags":[
        "home",
        "builder"
    ],
    "wof:name":"St Clair Home Builders Assn",
    "wof:placetype":"venue"
},
  "geometry": {"coordinates":[-86.202772,33.53999],"type":"Point"}
}