{
  "type": "Feature",
  "properties": {
    "iso:country":"US",
    "sg:address":"5700 Lucy Grade Rd",
    "sg:city":"Ashford",
    "sg:classifiers":[
        {
            "category":"Wholesale",
            "subcategory":"Meat",
            "type":"Manufacturing & Wholesale Goods"
        }
    ],
    "sg:phone":"+1 334 899 5106",
    "sg:postcode":"36312",
    "sg:province":"AL",
    "sg:tags":[
        "sausage",
        "mfg"
    ],
    "wof:name":"Pittman Incorporated",
    "wof:placetype":"venue"
},
  "geometry": {"coordinates":[-85.26154099999999,31.128462],"type":"Point"}
}