{
  "type": "Feature",
  "properties": {
    "addr:full":"300 Clinton Ave E Huntsville AL 35801",
    "addr:housenumber":"300",
    "addr:postcode":"35801",
    "addr:street":"Clinton Ave E",
    "iso:country":"US",
    "sg:address":"300 Clinton Ave E",
    "sg:city":"Huntsville",
    "sg:classifiers":[
        {
            "category":"Real Estate",
            "subcategory":"Architect",
            "type":"Services"
        }
    ],
    "sg:phone":"+1 256 539 1511",
    "sg:postcode":"35801",
    "sg:province":"AL",
    "wof:name":"William Boehme & Assoc",
    "wof:placetype":"venue"
},
  "geometry": {"coordinates":[-86.583506,34.732839],"type":"Point"}
}