{
  "type": "Feature",
  "properties": {
    "iso:country":"US",
    "sg:address":"289 S Northington St",
    "sg:city":"Prattville",
    "sg:classifiers":[
        {
            "category":"Professional",
            "subcategory":"Business Services",
            "type":"Services"
        }
    ],
    "sg:phone":"+1 334 361 0770",
    "sg:postcode":"36067",
    "sg:province":"AL",
    "wof:name":"Deborah Platt",
    "wof:placetype":"venue"
},
  "geometry": {"coordinates":[-86.467133,32.460712],"type":"Point"}
}