{
  "type": "Feature",
  "properties": {
    "addr:full":"620 Opelika Rd Auburn AL 36830",
    "addr:housenumber":"620",
    "addr:postcode":"36830",
    "addr:street":"Opelika Rd",
    "iso:country":"US",
    "sg:address":"620 Opelika Rd",
    "sg:city":"Auburn",
    "sg:classifiers":[
        {
            "category":"Retail",
            "subcategory":"Auto Repair",
            "type":"Services"
        }
    ],
    "sg:phone":"+1 334 821 7044",
    "sg:postcode":"36830",
    "sg:province":"AL",
    "sg:tags":[
        "automotive",
        "general"
    ],
    "wof:name":"Auburn Alignment & Brake Svc",
    "wof:placetype":"venue"
},
  "geometry": {"coordinates":[-85.466765,32.615517],"type":"Point"}
}