{
  "type": "Feature",
  "properties": {
    "iso:country":"US",
    "sg:address":"787 2nd St",
    "sg:city":"Helena",
    "sg:classifiers":[
        {
            "category":"Railroad",
            "type":"Transportation"
        }
    ],
    "sg:phone":"+1 205 664 3169",
    "sg:postcode":"35080",
    "sg:province":"AL",
    "sg:tags":[
        "operator",
        "line"
    ],
    "wof:name":"CSX Transportation Inc",
    "wof:placetype":"venue"
},
  "geometry": {"coordinates":[-86.844065,33.295195],"type":"Point"}
}