{
  "type": "Feature",
  "properties": {
    "iso:country":"US",
    "sg:address":"3430 Mayfair Rd",
    "sg:city":"Montgomery",
    "sg:classifiers":[
        {
            "category":"Professional",
            "subcategory":"Business Services",
            "type":"Services"
        }
    ],
    "sg:phone":"+1 334 271 3868",
    "sg:postcode":"36109",
    "sg:province":"AL",
    "wof:name":"Interior Solutions LLC",
    "wof:placetype":"venue"
},
  "geometry": {"coordinates":[-86.255296,32.392025],"type":"Point"}
}