{
  "type": "Feature",
  "properties": {
    "addr:full":"520 Paulk Rd Ramer AL 36069",
    "addr:housenumber":"520",
    "addr:postcode":"36069",
    "addr:street":"Paulk Rd",
    "iso:country":"US",
    "sg:address":"520 Paulk Rd",
    "sg:city":"Ramer",
    "sg:classifiers":[
        {
            "category":"Manufacturing",
            "subcategory":"Tools & Machinery",
            "type":"Manufacturing & Wholesale Goods"
        },
        {
            "category":"Manufacturing",
            "subcategory":"Motor Vehicles & Parts",
            "type":"Manufacturing & Wholesale Goods"
        }
    ],
    "sg:phone":"+1 334 562 9331",
    "sg:postcode":"36069",
    "sg:province":"AL",
    "sg:tags":[
        "body",
        "industrial",
        "truck",
        "mfg"
    ],
    "wof:name":"Ramer Manufacturing Inc",
    "wof:placetype":"venue"
},
  "geometry": {"coordinates":[-86.19259700000001,32.12594],"type":"Point"}
}