{
  "type": "Feature",
  "properties": {
    "iso:country":"US",
    "sg:address":"5867 State Rte 27",
    "sg:city":"Enterprise",
    "sg:classifiers":[
        {
            "category":"Autos & Motor Vehicles",
            "subcategory":"Fuel & Gas Station",
            "type":"Retail Goods"
        }
    ],
    "sg:phone":"+1 334 347 5192",
    "sg:postcode":"36330",
    "sg:province":"AL",
    "sg:tags":[
        "oil"
    ],
    "wof:name":"Cannon Oil Corp Station",
    "wof:placetype":"venue"
},
  "geometry": {"coordinates":[-85.886595,31.264129],"type":"Point"}
}