{
  "type": "Feature",
  "properties": {
    "iso:country":"US",
    "sg:address":"1009 Beechdale Rd",
    "sg:city":"Montgomery",
    "sg:classifiers":[
        {
            "category":"Building & Trades",
            "subcategory":"Construction",
            "type":"Services"
        }
    ],
    "sg:phone":"+1 334 272 1305",
    "sg:postcode":"36109",
    "sg:province":"AL",
    "sg:tags":[
        "nonresidential"
    ],
    "wof:name":"Clifford Fred Contractor",
    "wof:placetype":"venue"
},
  "geometry": {"coordinates":[-86.248428,32.364871],"type":"Point"}
}