{
  "type": "Feature",
  "properties": {
    "addr:full":"2724 Summerfield Pl Phenix City AL 36867",
    "addr:housenumber":"2724",
    "addr:postcode":"36867",
    "addr:street":"Summerfield Pl Phenix City Al",
    "iso:country":"US",
    "sg:address":"2724 Summerfield Pl",
    "sg:city":"Phenix City",
    "sg:classifiers":[
        {
            "category":"Professional",
            "subcategory":"Management & Consulting",
            "type":"Services"
        }
    ],
    "sg:phone":"+1 334 298 1745",
    "sg:postcode":"36867",
    "sg:province":"AL",
    "sg:tags":[
        "business"
    ],
    "wof:name":"Lsw Consulting Inc",
    "wof:placetype":"venue"
},
  "geometry": {"coordinates":[-85.034053,32.521112],"type":"Point"}
}