{
  "type": "Feature",
  "properties": {
    "addr:full":"170 Country Club Dr Ozark AL 36360",
    "addr:housenumber":"170",
    "addr:postcode":"36360",
    "addr:street":"Country Club Dr",
    "iso:country":"US",
    "sg:address":"170 Country Club Dr",
    "sg:city":"Ozark",
    "sg:classifiers":[
        {
            "category":"Organizations",
            "subcategory":"Religious Organization",
            "type":"Services"
        }
    ],
    "sg:phone":"+1 334 774 4941",
    "sg:postcode":"36360",
    "sg:province":"AL",
    "sg:tags":[
        "church"
    ],
    "wof:name":"First Assembly Of God",
    "wof:placetype":"venue"
},
  "geometry": {"coordinates":[-85.61815,31.475209],"type":"Point"}
}