{
  "type": "Feature",
  "properties": {
    "iso:country":"US",
    "sg:address":"237 Redwood St",
    "sg:city":"Birmingham",
    "sg:classifiers":[
        {
            "category":"Professional",
            "type":"Services"
        }
    ],
    "sg:phone":"+1 205 951 2642",
    "sg:postcode":"35210",
    "sg:province":"AL",
    "wof:name":"U&I Creative Services Inc",
    "wof:placetype":"venue"
},
  "geometry": {"coordinates":[-86.723842,33.521732],"type":"Point"}
}