{
  "type": "Feature",
  "properties": {
    "iso:country":"US",
    "sg:address":"2728 10th Ave S",
    "sg:city":"Birmingham",
    "sg:classifiers":[
        {
            "category":"Personal",
            "subcategory":"Beauty Salon",
            "type":"Services"
        }
    ],
    "sg:phone":"+1 205 930 9597",
    "sg:postcode":"35205",
    "sg:province":"AL",
    "sg:tags":[
        "shop"
    ],
    "wof:name":"Hair Masters",
    "wof:placetype":"venue"
},
  "geometry": {"coordinates":[-86.786433,33.508431],"type":"Point"}
}