{
  "type": "Feature",
  "properties": {
    "addr:full":"4521 S Court St Montgomery AL 36105",
    "addr:housenumber":"4521",
    "addr:postcode":"36105",
    "addr:street":"S Court",
    "iso:country":"US",
    "sg:address":"4521 S Court St",
    "sg:city":"Montgomery",
    "sg:classifiers":[
        {
            "category":"Food & Beverages",
            "subcategory":"Groceries & Convenience Stores",
            "type":"Retail Goods"
        }
    ],
    "sg:phone":"+1 334 281 5911",
    "sg:postcode":"36105",
    "sg:province":"AL",
    "wof:name":"United Food & Fuel",
    "wof:placetype":"venue"
},
  "geometry": {"coordinates":[-86.307715,32.323961],"type":"Point"}
}