{
  "type": "Feature",
  "properties": {
    "addr:full":"3700 Huntsville Ave Brighton AL 35020",
    "addr:postcode":"3700;35020",
    "addr:street":"Huntsville Ave",
    "iso:country":"US",
    "sg:address":"3700 Huntsville Ave",
    "sg:city":"Brighton",
    "sg:classifiers":[
        {
            "category":"Personal",
            "subcategory":"Barber",
            "type":"Services"
        }
    ],
    "sg:phone":"+1 205 425 3208",
    "sg:postcode":"35020",
    "sg:province":"AL",
    "sg:tags":[
        "shop"
    ],
    "wof:name":"Eades Barber & Style",
    "wof:placetype":"venue"
},
  "geometry": {"coordinates":[-86.95130899999999,33.430346],"type":"Point"}
}