{
  "type": "Feature",
  "properties": {
    "iso:country":"US",
    "sg:address":"526 Walnut St",
    "sg:city":"Gadsden",
    "sg:classifiers":[
        {
            "category":"Insurance",
            "subcategory":"Insurance Agent",
            "type":"Services"
        }
    ],
    "sg:phone":"+1 256 543 0068",
    "sg:postcode":"35901",
    "sg:province":"AL",
    "wof:name":"J P Lipscomb & Assoc",
    "wof:placetype":"venue"
},
  "geometry": {"coordinates":[-86.007543,34.011274],"type":"Point"}
}