{
  "type": "Feature",
  "properties": {
    "iso:country":"US",
    "sg:address":"6820 Oats Dr",
    "sg:city":"Montgomery",
    "sg:classifiers":[
        {
            "category":"Recreation",
            "type":"Entertainment"
        }
    ],
    "sg:phone":"+1 334 420 4386",
    "sg:postcode":"36117",
    "sg:province":"AL",
    "sg:tags":[
        "skating",
        "center"
    ],
    "wof:name":"Fun Zone Inc",
    "wof:placetype":"venue"
},
  "geometry": {"coordinates":[-86.179057,32.381073],"type":"Point"}
}