{
  "type": "Feature",
  "properties": {
    "iso:country":"US",
    "sg:address":"1505 Highway 31 SW",
    "sg:city":"Hartselle",
    "sg:classifiers":[
        {
            "category":"Personal",
            "subcategory":"Beauty Salon",
            "type":"Services"
        }
    ],
    "sg:phone":"+1 256 773 9360",
    "sg:postcode":"35640",
    "sg:province":"AL",
    "wof:name":"Pam's Beauty Salon",
    "wof:placetype":"venue"
},
  "geometry": {"coordinates":[-86.92779,34.423691],"type":"Point"}
}