{
  "type": "Feature",
  "properties": {
    "addr:full":"2170 Highland Ave S Birmingham AL 35205",
    "addr:housenumber":"2170",
    "addr:postcode":"35205",
    "addr:street":"Highland Ave S",
    "iso:country":"US",
    "sg:address":"2170 Highland Ave S",
    "sg:city":"Birmingham",
    "sg:classifiers":[
        {
            "category":"Shopping",
            "subcategory":"Crafts & Fabrics",
            "type":"Retail Goods"
        }
    ],
    "sg:phone":"+1 205 558 4680",
    "sg:postcode":"35205",
    "sg:province":"AL",
    "sg:tags":[
        "sewing"
    ],
    "wof:name":"Jennro LLC",
    "wof:placetype":"venue"
},
  "geometry": {"coordinates":[-86.791853,33.500124],"type":"Point"}
}