{
  "type": "Feature",
  "properties": {
    "iso:country":"US",
    "sg:address":"401 Oak Hill Rd",
    "sg:city":"Jasper",
    "sg:classifiers":[
        {
            "category":"Shopping",
            "subcategory":"Florist",
            "type":"Retail Goods"
        }
    ],
    "sg:phone":"+1 205 221 1555",
    "sg:postcode":"35504",
    "sg:province":"AL",
    "wof:name":"Marie's Flower Basket",
    "wof:placetype":"venue"
},
  "geometry": {"coordinates":[-87.283968,33.854079],"type":"Point"}
}