{
  "type": "Feature",
  "properties": {
    "iso:country":"US",
    "sg:address":"6522 Old Tuscaloosa Hwy",
    "sg:city":"Mc Calla",
    "sg:classifiers":[
        {
            "category":"Retail",
            "subcategory":"Laundry & Dry Cleaning",
            "type":"Services"
        }
    ],
    "sg:phone":"+1 205 477 0440",
    "sg:postcode":"35111",
    "sg:province":"AL",
    "wof:name":"A & S Carpet Cleaning",
    "wof:placetype":"venue"
},
  "geometry": {"coordinates":[-87.037036,33.319222],"type":"Point"}
}