{
  "type": "Feature",
  "properties": {
    "iso:country":"US",
    "sg:address":"956 Cherokee Rd",
    "sg:city":"Alexander City",
    "sg:classifiers":[
        {
            "category":"Professional",
            "subcategory":"Lawyer & Legal Services",
            "type":"Services"
        }
    ],
    "sg:phone":"+1 256 329 1552",
    "sg:postcode":"35010",
    "sg:province":"AL",
    "sg:tags":[
        "attorney"
    ],
    "wof:name":"G Daniel Brown Attorney At Law",
    "wof:placetype":"venue"
},
  "geometry": {"coordinates":[-85.951388,32.9347],"type":"Point"}
}