{
  "type": "Feature",
  "properties": {
    "iso:country":"US",
    "sg:address":"2000 Riverchase Galleria",
    "sg:city":"Birmingham",
    "sg:classifiers":[
        {
            "category":"Shopping",
            "subcategory":"Gifts & Souvenirs",
            "type":"Retail Goods"
        }
    ],
    "sg:phone":"+1 205 985 0265",
    "sg:postcode":"35244",
    "sg:province":"AL",
    "wof:name":"Kirklands Galleria",
    "wof:placetype":"venue"
},
  "geometry": {"coordinates":[-86.810181,33.376836],"type":"Point"}
}