{
  "type": "Feature",
  "properties": {
    "iso:country":"US",
    "sg:address":"11650 Potter Tract Rd",
    "sg:city":"Grand Bay",
    "sg:classifiers":[
        {
            "category":"Farming",
            "subcategory":"Farm",
            "type":"Manufacturing & Wholesale Goods"
        }
    ],
    "sg:phone":"+1 251 865 4126",
    "sg:postcode":"36541",
    "sg:province":"AL",
    "sg:tags":[
        "crop",
        "general"
    ],
    "wof:name":"Clint Mayo",
    "wof:placetype":"venue"
},
  "geometry": {"coordinates":[-88.34345,30.446812],"type":"Point"}
}