{
  "type": "Feature",
  "properties": {
    "iso:country":"US",
    "sg:address":"620 E 21st Ave",
    "sg:city":"Gulf Shores",
    "sg:classifiers":[
        {
            "category":"Health Services",
            "subcategory":"Nursing And Care Facility",
            "type":"Services"
        }
    ],
    "sg:phone":"+1 251 967 3866",
    "sg:postcode":"36542",
    "sg:province":"AL",
    "wof:name":"Age Well At Home Inc",
    "wof:placetype":"venue"
},
  "geometry": {"coordinates":[-87.676664,30.274585],"type":"Point"}
}