{
  "type": "Feature",
  "properties": {
    "iso:country":"US",
    "sg:address":"13020 Camelot Dr SE",
    "sg:city":"Huntsville",
    "sg:classifiers":[
        {
            "category":"Shopping",
            "type":"Retail Goods"
        }
    ],
    "sg:phone":"+1 256 714 1403",
    "sg:postcode":"35803",
    "sg:province":"AL",
    "sg:tags":[
        "merchandise"
    ],
    "wof:name":"Steve Robertson",
    "wof:placetype":"venue"
},
  "geometry": {"coordinates":[-86.531424,34.623394],"type":"Point"}
}