{
  "type": "Feature",
  "properties": {
    "addr:full":"5505 Johnson Rd Theodore AL 36582",
    "addr:housenumber":"5505",
    "addr:postcode":"36582",
    "addr:street":"Johnson Rd",
    "iso:country":"US",
    "sg:address":"5505 Johnson Rd",
    "sg:city":"Theodore",
    "sg:classifiers":[
        {
            "category":"Retail",
            "subcategory":"Auto Repair",
            "type":"Services"
        }
    ],
    "sg:phone":"+1 251 653 4416",
    "sg:postcode":"36582",
    "sg:province":"AL",
    "sg:tags":[
        "repairing",
        "automobile",
        "body"
    ],
    "wof:name":"Florio's Corvettes",
    "wof:placetype":"venue"
},
  "geometry": {"coordinates":[-88.190804,30.574723],"type":"Point"}
}