{
  "type": "Feature",
  "properties": {
    "addr:full":"1654 Gadsden Hwy Birmingham AL 35235",
    "addr:housenumber":"1654",
    "addr:postcode":"35235",
    "addr:street":"Gadsden Hwy",
    "iso:country":"US",
    "sg:address":"1654 Gadsden Hwy",
    "sg:city":"Birmingham",
    "sg:classifiers":[
        {
            "category":"Retail",
            "subcategory":"Portrait Studio",
            "type":"Services"
        }
    ],
    "sg:phone":"+1 205 655 5813",
    "sg:postcode":"35235",
    "sg:province":"AL",
    "sg:tags":[
        "photo"
    ],
    "wof:name":"Lifetouch Inc",
    "wof:placetype":"venue"
},
  "geometry": {"coordinates":[-86.63876999999999,33.602199],"type":"Point"}
}