{
  "type": "Feature",
  "properties": {
    "iso:country":"US",
    "sg:address":"3783 S Alabama Ave",
    "sg:city":"Monroeville",
    "sg:classifiers":[
        {
            "category":"Restaurant",
            "type":"Food & Drink"
        }
    ],
    "sg:menulink":"http://www.allmenus.com/al/monroeville/204689-taco-bell/menu/",
    "sg:postcode":"36460",
    "sg:province":"AL",
    "sg:tags":[
        "mexican"
    ],
    "wof:name":"Taco Bell",
    "wof:placetype":"venue"
},
  "geometry": {"coordinates":[-87.33621599999999,31.477187],"type":"Point"}
}