{
  "type": "Feature",
  "properties": {
    "iso:country":"US",
    "sg:address":"1306 Baywood Rd",
    "sg:city":"Dothan",
    "sg:classifiers":[
        {
            "category":"Professional",
            "type":"Services"
        }
    ],
    "sg:phone":"+1 334 677 5031",
    "sg:postcode":"36305",
    "sg:province":"AL",
    "wof:name":"Barbara I Manuel",
    "wof:placetype":"venue"
},
  "geometry": {"coordinates":[-85.47621,31.224374],"type":"Point"}
}