{
  "type": "Feature",
  "properties": {
    "addr:full":"300 N Dean Rd Auburn AL 36830",
    "addr:housenumber":"300",
    "addr:postcode":"36830",
    "addr:street":"N Dean Rd",
    "iso:country":"US",
    "sg:address":"300 N Dean Rd",
    "sg:city":"Auburn",
    "sg:classifiers":[
        {
            "category":"Personal",
            "subcategory":"Beauty Salon",
            "type":"Services"
        }
    ],
    "sg:phone":"+1 334 826 3511",
    "sg:postcode":"36830",
    "sg:province":"AL",
    "sg:tags":[
        "shop",
        "manicuring"
    ],
    "wof:name":"Nail Love",
    "wof:placetype":"venue"
},
  "geometry": {"coordinates":[-85.464822,32.609434],"type":"Point"}
}