{
  "type": "Feature",
  "properties": {
    "addr:full":"2506 Spring Ave SW Decatur AL 35601",
    "addr:housenumber":"2506",
    "addr:postcode":"35601",
    "addr:street":"Spring Ave Sw",
    "iso:country":"US",
    "sg:address":"2506 Spring Ave SW",
    "sg:city":"Decatur",
    "sg:classifiers":[
        {
            "category":"Real Estate",
            "subcategory":"Real Estate Operator",
            "type":"Services"
        }
    ],
    "sg:phone":"+1 256 355 6371",
    "sg:postcode":"35601",
    "sg:province":"AL",
    "sg:tags":[
        "apartment"
    ],
    "wof:name":"Lodge Apartments",
    "wof:placetype":"venue"
},
  "geometry": {"coordinates":[-87.000027,34.564439],"type":"Point"}
}