{
  "type": "Feature",
  "properties": {
    "iso:country":"US",
    "sg:address":"1105 Head St",
    "sg:city":"Albertville",
    "sg:classifiers":[
        {
            "category":"Real Estate",
            "subcategory":"Real Estate Operator",
            "type":"Services"
        }
    ],
    "sg:phone":"+1 256 878 8544",
    "sg:postcode":"35950",
    "sg:province":"AL",
    "sg:tags":[
        "apartment"
    ],
    "wof:name":"Emerald Court Apartments",
    "wof:placetype":"venue"
},
  "geometry": {"coordinates":[-86.222569,34.264395],"type":"Point"}
}