{
  "type": "Feature",
  "properties": {
    "addr:full":"110 8th St NW Arab AL 35016",
    "addr:housenumber":"110",
    "addr:postcode":"35016",
    "addr:street":"8Th St Nw",
    "iso:country":"US",
    "sg:address":"110 8th St NW",
    "sg:city":"Arab",
    "sg:classifiers":[
        {
            "category":"Real Estate",
            "subcategory":"Real Estate Operator",
            "type":"Services"
        }
    ],
    "sg:phone":"+1 256 586 3328",
    "sg:postcode":"35016",
    "sg:province":"AL",
    "sg:tags":[
        "apartment"
    ],
    "wof:name":"Greentree Apts",
    "wof:placetype":"venue"
},
  "geometry": {"coordinates":[-86.50838,34.316805],"type":"Point"}
}