{
  "type": "Feature",
  "properties": {
    "iso:country":"US",
    "sg:address":"720 Fulton Springs Rd",
    "sg:city":"Alabaster",
    "sg:classifiers":[
        {
            "category":"Wholesale",
            "subcategory":"Construction Materials",
            "type":"Manufacturing & Wholesale Goods"
        },
        {
            "category":"Home & Garden",
            "subcategory":"Building Materials",
            "type":"Retail Goods"
        }
    ],
    "sg:phone":"+1 205 621 2383",
    "sg:postcode":"35007",
    "sg:province":"AL",
    "sg:tags":[
        "lumber"
    ],
    "wof:name":"Case Engineered Lumber Inc",
    "wof:placetype":"venue"
},
  "geometry": {"coordinates":[-86.813434,33.214779],"type":"Point"}
}