{
  "type": "Feature",
  "properties": {
    "iso:country":"US",
    "sg:address":"270 Commerce Pkwy",
    "sg:city":"Pelham",
    "sg:classifiers":[
        {
            "category":"Retail",
            "subcategory":"Portrait Studio",
            "type":"Services"
        },
        {
            "category":"Retail",
            "subcategory":"Photofinishing",
            "type":"Services"
        }
    ],
    "sg:phone":"+1 205 982 0703",
    "sg:postcode":"35124",
    "sg:province":"AL",
    "sg:tags":[
        "photo",
        "finishing",
        "photographic",
        "laboratory"
    ],
    "wof:name":"Belmont Professional Color Lab",
    "wof:placetype":"venue"
},
  "geometry": {"coordinates":[-86.795321,33.33042],"type":"Point"}
}