{
  "type": "Feature",
  "properties": {
    "iso:country":"US",
    "sg:address":"479 Co Rd 827",
    "sg:city":"Cullman",
    "sg:classifiers":[
        {
            "category":"Retail",
            "subcategory":"Laundry & Dry Cleaning",
            "type":"Services"
        }
    ],
    "sg:phone":"+1 256 747 9006",
    "sg:postcode":"35057",
    "sg:province":"AL",
    "sg:tags":[
        "cleaners",
        "rug",
        "carpet"
    ],
    "wof:name":"Wilhite Carpet Cleaning",
    "wof:placetype":"venue"
},
  "geometry": {"coordinates":[-86.983579,34.183066],"type":"Point"}
}