{
  "type": "Feature",
  "properties": {
    "iso:country":"US",
    "sg:address":"3011 Ross Clark Cir",
    "sg:city":"Dothan",
    "sg:classifiers":[
        {
            "category":"Travel",
            "subcategory":"Hotels & Motels",
            "type":"Entertainment"
        }
    ],
    "sg:phone":"+1 334 699 3950",
    "sg:postcode":"36301",
    "sg:province":"AL",
    "wof:name":"Veda",
    "wof:placetype":"venue"
},
  "geometry": {"coordinates":[-85.432457,31.22455],"type":"Point"}
}