{
  "type": "Feature",
  "properties": {
    "iso:country":"US",
    "sg:address":"300 US Hwy 31",
    "sg:city":"Bay Minette",
    "sg:classifiers":[
        {
            "category":"Health Services",
            "subcategory":"Chiropractor",
            "type":"Services"
        }
    ],
    "sg:phone":"+1 251 580 4145",
    "sg:postcode":"36507",
    "sg:province":"AL",
    "wof:name":"Daniel Fmly Chropractic Clinic",
    "wof:placetype":"venue"
},
  "geometry": {"coordinates":[-87.77070399999999,30.88448],"type":"Point"}
}