{
  "type": "Feature",
  "properties": {
    "iso:country":"US",
    "sg:address":"4956 Valleydale Rd",
    "sg:city":"Birmingham",
    "sg:classifiers":[
        {
            "category":"Shopping",
            "subcategory":"Computers & Home Electronics",
            "type":"Retail Goods"
        }
    ],
    "sg:phone":"+1 205 991 7590",
    "sg:postcode":"35242",
    "sg:province":"AL",
    "sg:tags":[
        "software"
    ],
    "wof:name":"Automotive Systems Inc",
    "wof:placetype":"venue"
},
  "geometry": {"coordinates":[-86.720006,33.395626],"type":"Point"}
}