{
  "type": "Feature",
  "properties": {
    "addr:full":"265 Valley Rd Oneonta AL 35121",
    "addr:housenumber":"265",
    "addr:postcode":"35121",
    "addr:street":"Valley Rd",
    "iso:country":"US",
    "sg:address":"265 Valley Rd",
    "sg:city":"Oneonta",
    "sg:classifiers":[
        {
            "category":"Restaurant",
            "type":"Food & Drink"
        }
    ],
    "sg:menulink":"http://www.allmenus.com/al/oneonta/80799-papa-johns-pizza/menu/",
    "sg:phone":"+1 205 625 5606",
    "sg:postcode":"35121",
    "sg:province":"AL",
    "sg:tags":[
        "american",
        "pizza"
    ],
    "wof:name":"Papa John's Pizza",
    "wof:placetype":"venue"
},
  "geometry": {"coordinates":[-86.465371,33.952451],"type":"Point"}
}