{
  "type": "Feature",
  "properties": {
    "iso:country":"US",
    "sg:address":"1501 University Blvd",
    "sg:city":"Tuscaloosa",
    "sg:classifiers":[
        {
            "category":"Manufacturing",
            "subcategory":"Printing",
            "type":"Manufacturing & Wholesale Goods"
        }
    ],
    "sg:phone":"+1 205 345 7900",
    "sg:postcode":"35401",
    "sg:province":"AL",
    "sg:tags":[
        "lithographic",
        "b",
        "commercial",
        "typesetting"
    ],
    "wof:name":"Pressto Printing Inc",
    "wof:placetype":"venue"
},
  "geometry": {"coordinates":[-87.557198,33.211518],"type":"Point"}
}