{
  "type": "Feature",
  "properties": {
    "iso:country":"US",
    "sg:address":"101 5th Ave SE",
    "sg:city":"Red Bay",
    "sg:classifiers":[
        {
            "category":"Wholesale",
            "subcategory":"Auto Parts",
            "type":"Manufacturing & Wholesale Goods"
        }
    ],
    "sg:phone":"+1 256 356 2161",
    "sg:postcode":"35582",
    "sg:province":"AL",
    "sg:tags":[
        "automobile",
        "supply"
    ],
    "wof:name":"City Auto Parts",
    "wof:placetype":"venue"
},
  "geometry": {"coordinates":[-88.144528,34.440629],"type":"Point"}
}