{
  "type": "Feature",
  "properties": {
    "addr:full":"104 Water Oak Ct Harvest AL 35749",
    "addr:housenumber":"104",
    "addr:postcode":"35749",
    "addr:street":"Water Oak Ct",
    "iso:country":"US",
    "sg:address":"104 Water Oak Ct",
    "sg:city":"Harvest",
    "sg:classifiers":[
        {
            "category":"Professional",
            "type":"Services"
        }
    ],
    "sg:phone":"+1 256 837 3307",
    "sg:postcode":"35749",
    "sg:province":"AL",
    "wof:name":"Supply & Demand",
    "wof:placetype":"venue"
},
  "geometry": {"coordinates":[-86.76101800000001,34.787675],"type":"Point"}
}