{
  "type": "Feature",
  "properties": {
    "iso:country":"US",
    "sg:address":"216 S Marengo St",
    "sg:city":"Florence",
    "sg:classifiers":[
        {
            "category":"Health Services",
            "subcategory":"Doctor",
            "type":"Services"
        }
    ],
    "sg:phone":"+1 256 767 1701",
    "sg:postcode":"35630",
    "sg:province":"AL",
    "sg:tags":[
        "physician",
        "surgeon"
    ],
    "wof:name":"Tri-Cities Allergy Clinic",
    "wof:placetype":"venue"
},
  "geometry": {"coordinates":[-87.683984,34.793026],"type":"Point"}
}