{
  "type": "Feature",
  "properties": {
    "iso:country":"US",
    "sg:address":"5336 Stadium Trace Pkwy",
    "sg:city":"Birmingham",
    "sg:classifiers":[
        {
            "category":"Personal",
            "subcategory":"Beauty Salon",
            "type":"Services"
        }
    ],
    "sg:phone":"+1 205 982 1405",
    "sg:postcode":"35244",
    "sg:province":"AL",
    "sg:tags":[
        "shop"
    ],
    "wof:name":"Wells of Beauty",
    "wof:placetype":"venue"
},
  "geometry": {"coordinates":[-86.851517,33.338937],"type":"Point"}
}