{
  "type": "Feature",
  "properties": {
    "addr:full":"201 2nd St Greenville AL 36037",
    "addr:housenumber":"201",
    "addr:postcode":"36037",
    "addr:street":"2Nd St",
    "iso:country":"US",
    "sg:address":"201 2nd St",
    "sg:city":"Greenville",
    "sg:classifiers":[
        {
            "category":"Building & Trades",
            "subcategory":"Construction",
            "type":"Services"
        }
    ],
    "sg:phone":"+1 334 371 4100",
    "sg:postcode":"36037",
    "sg:province":"AL",
    "sg:tags":[
        "contractor"
    ],
    "wof:name":"D & B Construction",
    "wof:placetype":"venue"
},
  "geometry": {"coordinates":[-86.607562,31.833031],"type":"Point"}
}