{
  "type": "Feature",
  "properties": {
    "iso:country":"US",
    "sg:address":"6751 Co Rd 17",
    "sg:city":"Maylene",
    "sg:classifiers":[
        {
            "category":"Cinema",
            "subcategory":"Movie Rental",
            "type":"Entertainment"
        }
    ],
    "sg:phone":"+1 205 663 4062",
    "sg:postcode":"35114",
    "sg:province":"AL",
    "sg:tags":[
        "video",
        "tape"
    ],
    "wof:name":"Carousel Video",
    "wof:placetype":"venue"
},
  "geometry": {"coordinates":[-86.852877,33.24858],"type":"Point"}
}