{
  "type": "Feature",
  "properties": {
    "iso:country":"US",
    "sg:address":"75 State Rte 179",
    "sg:city":"Boaz",
    "sg:classifiers":[
        {
            "category":"Retail",
            "subcategory":"Auto Repair",
            "type":"Services"
        }
    ],
    "sg:phone":"+1 256 593 3992",
    "sg:postcode":"35957",
    "sg:province":"AL",
    "sg:tags":[
        "body"
    ],
    "wof:name":"Horace Williams Body Shop",
    "wof:placetype":"venue"
},
  "geometry": {"coordinates":[-86.188154,34.191086],"type":"Point"}
}