{
  "type": "Feature",
  "properties": {
    "iso:country":"US",
    "sg:address":"406 N Eufaula Ave",
    "sg:city":"Eufaula",
    "sg:classifiers":[
        {
            "category":"Real Estate",
            "subcategory":"Real Estate Operator",
            "type":"Services"
        }
    ],
    "sg:phone":"+1 334 687 7311",
    "sg:postcode":"36027",
    "sg:province":"AL",
    "sg:tags":[
        "apartment"
    ],
    "wof:name":"Heritage Apartments",
    "wof:placetype":"venue"
},
  "geometry": {"coordinates":[-85.145976,31.896789],"type":"Point"}
}