{
  "type": "Feature",
  "properties": {
    "addr:full":"2125 Luverne St Montgomery AL 36104",
    "addr:housenumber":"2125",
    "addr:postcode":"36104",
    "addr:street":"Luverne St",
    "iso:country":"US",
    "sg:address":"2125 Luverne St",
    "sg:city":"Montgomery",
    "sg:classifiers":[
        {
            "category":"Organizations",
            "subcategory":"Religious Organization",
            "type":"Services"
        }
    ],
    "sg:phone":"+1 334 264 1243",
    "sg:postcode":"36104",
    "sg:province":"AL",
    "sg:tags":[
        "church"
    ],
    "wof:name":"New Bethel Holiness Church",
    "wof:placetype":"venue"
},
  "geometry": {"coordinates":[-86.328952,32.371398],"type":"Point"}
}