{
  "type": "Feature",
  "properties": {
    "addr:full":"362 Pinehill Dr Mobile AL 36606",
    "addr:housenumber":"362",
    "addr:postcode":"36606",
    "addr:street":"Pinehill Dr",
    "iso:country":"US",
    "sg:address":"362 Pinehill Dr",
    "sg:city":"Mobile",
    "sg:classifiers":[
        {
            "category":"Organizations",
            "subcategory":"Professional Association",
            "type":"Services"
        }
    ],
    "sg:phone":"+1 251 479 2199",
    "sg:postcode":"36606",
    "sg:province":"AL",
    "sg:website":"www.eesf.org",
    "wof:name":"Elevator Escalator Safety",
    "wof:placetype":"venue"
},
  "geometry": {"coordinates":[-88.097117,30.673648],"type":"Point"}
}