{
  "type": "Feature",
  "properties": {
    "iso:country":"US",
    "sg:address":"9 2nd Ave N",
    "sg:city":"Birmingham",
    "sg:classifiers":[
        {
            "category":"Personal",
            "subcategory":"Beauty Salon",
            "type":"Services"
        }
    ],
    "sg:phone":"+1 205 254 3366",
    "sg:postcode":"35204",
    "sg:province":"AL",
    "wof:name":"Lefty's",
    "wof:placetype":"venue"
},
  "geometry": {"coordinates":[-86.834875,33.502801],"type":"Point"}
}