{
  "type": "Feature",
  "properties": {
    "iso:country":"US",
    "sg:address":"63 Dekalb Dr SW",
    "sg:city":"Rainsville",
    "sg:classifiers":[
        {
            "category":"Professional",
            "subcategory":"Business Services",
            "type":"Services"
        },
        {
            "category":"Professional",
            "subcategory":"Management & Consulting",
            "type":"Services"
        }
    ],
    "sg:phone":"+1 256 638 1869",
    "sg:postcode":"35986",
    "sg:province":"AL",
    "sg:tags":[
        "consultant",
        "direct",
        "sales",
        "design",
        "interior",
        "retail",
        "decorator"
    ],
    "wof:name":"Decorating Featuring Home Inte",
    "wof:placetype":"venue"
},
  "geometry": {"coordinates":[-85.85333799999999,34.496443],"type":"Point"}
}