{
  "type": "Feature",
  "properties": {
    "iso:country":"US",
    "sg:address":"3306 Gurley Ave",
    "sg:city":"Gadsden",
    "sg:classifiers":[
        {
            "category":"Health Services",
            "subcategory":"Chiropractor",
            "type":"Services"
        }
    ],
    "sg:phone":"+1 256 492 6800",
    "sg:postcode":"35903",
    "sg:province":"AL",
    "wof:name":"Lett Chiropractic Clinic",
    "wof:placetype":"venue"
},
  "geometry": {"coordinates":[-85.945993,33.96648],"type":"Point"}
}