{
  "type": "Feature",
  "properties": {
    "iso:country":"US",
    "sg:address":"1330 Hargrove Rd",
    "sg:city":"Tuscaloosa",
    "sg:classifiers":[
        {
            "category":"Bars & Pubs",
            "type":"Food & Drink"
        }
    ],
    "sg:phone":"+1 205 758 9332",
    "sg:postcode":"35401",
    "sg:province":"AL",
    "sg:tags":[
        "lounge",
        "drinking",
        "cocktail"
    ],
    "wof:name":"Harry's Bar",
    "wof:placetype":"venue"
},
  "geometry": {"coordinates":[-87.557056,33.193769],"type":"Point"}
}