{
  "type": "Feature",
  "properties": {
    "iso:country":"US",
    "sg:address":"114 Temple Ave N",
    "sg:city":"Fayette",
    "sg:classifiers":[
        {
            "category":"Travel",
            "subcategory":"Hotels & Motels",
            "type":"Entertainment"
        }
    ],
    "sg:phone":"+1 205 932 7673",
    "sg:postcode":"35555",
    "sg:province":"AL",
    "sg:tags":[
        "operation"
    ],
    "wof:name":"Rose House Inn",
    "wof:placetype":"venue"
},
  "geometry": {"coordinates":[-87.830836,33.68532],"type":"Point"}
}