{
  "type": "Feature",
  "properties": {
    "addr:full":"125 James Madison Dr SW Huntsville AL 35824",
    "addr:housenumber":"125",
    "addr:postcode":"35824",
    "addr:street":"James Madison Dr Sw",
    "iso:country":"US",
    "sg:address":"125 James Madison Dr SW",
    "sg:city":"Huntsville",
    "sg:classifiers":[
        {
            "category":"Restaurant",
            "type":"Food & Drink"
        }
    ],
    "sg:phone":"+1 256 461 8590",
    "sg:postcode":"35824",
    "sg:province":"AL",
    "wof:name":"Heaven's Farmacy",
    "wof:placetype":"venue"
},
  "geometry": {"coordinates":[-86.75409399999999,34.657095],"type":"Point"}
}