{
  "type": "Feature",
  "properties": {
    "iso:country":"US",
    "sg:address":"1668 Federal Dr",
    "sg:city":"Montgomery",
    "sg:classifiers":[
        {
            "category":"Shopping",
            "subcategory":"Bicycles & Sporting Goods",
            "type":"Retail Goods"
        }
    ],
    "sg:phone":"+1 334 272 4608",
    "sg:postcode":"36107",
    "sg:province":"AL",
    "sg:tags":[
        "bait",
        "fishing"
    ],
    "wof:name":"Cherry's East",
    "wof:placetype":"venue"
},
  "geometry": {"coordinates":[-86.267375,32.403902],"type":"Point"}
}