{
  "type": "Feature",
  "properties": {
    "iso:country":"US",
    "sg:address":"2915 Leeth Gap Cutoff Rd",
    "sg:city":"Boaz",
    "sg:classifiers":[
        {
            "category":"Autos & Motor Vehicles",
            "subcategory":"Automobile Sales",
            "type":"Retail Goods"
        }
    ],
    "sg:phone":"+1 256 840 2047",
    "sg:postcode":"35956",
    "sg:province":"AL",
    "sg:tags":[
        "car",
        "dealer"
    ],
    "wof:name":"Midway Auto Brokers",
    "wof:placetype":"venue"
},
  "geometry": {"coordinates":[-86.052795,34.179804],"type":"Point"}
}