{
  "type": "Feature",
  "properties": {
    "iso:country":"US",
    "sg:address":"850 S Broad St",
    "sg:city":"Mobile",
    "sg:classifiers":[
        {
            "category":"Personal",
            "subcategory":"Beauty Salon",
            "type":"Services"
        }
    ],
    "sg:phone":"+1 251 438 3500",
    "sg:postcode":"36603",
    "sg:province":"AL",
    "sg:tags":[
        "shop"
    ],
    "wof:name":"J RS Platinum Hair Designs",
    "wof:placetype":"venue"
},
  "geometry": {"coordinates":[-88.055515,30.668363],"type":"Point"}
}