{
  "type": "Feature",
  "properties": {
    "iso:country":"US",
    "sg:address":"4300 Old Pump Station Rd",
    "sg:city":"Gadsden",
    "sg:classifiers":[
        {
            "category":"Autos & Motor Vehicles",
            "subcategory":"Auto Supplies",
            "type":"Retail Goods"
        }
    ],
    "sg:phone":"+1 256 442 4008",
    "sg:postcode":"35904",
    "sg:province":"AL",
    "sg:tags":[
        "tire"
    ],
    "wof:name":"E-Z Tire & Diesel Svc",
    "wof:placetype":"venue"
},
  "geometry": {"coordinates":[-86.085101,34.00016],"type":"Point"}
}