{
  "type": "Feature",
  "properties": {
    "iso:country":"US",
    "sg:address":"604 Brake St N",
    "sg:city":"Warrior",
    "sg:classifiers":[
        {
            "category":"Building & Trades",
            "subcategory":"Construction",
            "type":"Services"
        }
    ],
    "sg:phone":"+1 205 647 2179",
    "sg:postcode":"35180",
    "sg:province":"AL",
    "sg:tags":[
        "contractor"
    ],
    "wof:name":"Johns Ceramic Tile",
    "wof:placetype":"venue"
},
  "geometry": {"coordinates":[-86.806671,33.818301],"type":"Point"}
}