{
  "type": "Feature",
  "properties": {
    "addr:full":"604 Brake St N Warrior AL 35180",
    "addr:housenumber":"604",
    "addr:postcode":"35180",
    "addr:street":"Brake St N Warrior",
    "iso:country":"US",
    "sg:address":"604 Brake St N",
    "sg:city":"Warrior",
    "sg:classifiers":[
        {
            "category":"Building & Trades",
            "subcategory":"Construction",
            "type":"Services"
        }
    ],
    "sg:phone":"+1 205 647 2179",
    "sg:postcode":"35180",
    "sg:province":"AL",
    "sg:tags":[
        "contractor"
    ],
    "wof:name":"Johns Ceramic Tile",
    "wof:placetype":"venue"
},
  "geometry": {"coordinates":[-86.80667099999999,33.818301],"type":"Point"}
}