{
  "type": "Feature",
  "properties": {
    "iso:country":"US",
    "sg:address":"2001 Carolina Ave",
    "sg:city":"Bessemer",
    "sg:classifiers":[
        {
            "category":"Retail",
            "subcategory":"Repair Shop",
            "type":"Services"
        }
    ],
    "sg:phone":"+1 205 424 0471",
    "sg:postcode":"35020",
    "sg:province":"AL",
    "wof:name":"Ronalds Lawnmower Repair",
    "wof:placetype":"venue"
},
  "geometry": {"coordinates":[-86.948323,33.402896],"type":"Point"}
}