{
  "type": "Feature",
  "properties": {
    "addr:full":"153 Old County Shop Rd Ramer AL 36069",
    "addr:housenumber":"153",
    "addr:postcode":"36069",
    "addr:street":"Old;Shop Rd",
    "iso:country":"US",
    "sg:address":"153 Old County Shop Rd",
    "sg:city":"Ramer",
    "sg:classifiers":[
        {
            "category":"Government",
            "subcategory":"Fire Station",
            "type":"Public Place"
        }
    ],
    "sg:phone":"+1 334 284 0934",
    "sg:postcode":"36069",
    "sg:province":"AL",
    "sg:tags":[
        "department"
    ],
    "wof:name":"Snowdoun Volunteer Fire Dept",
    "wof:placetype":"venue"
},
  "geometry": {"coordinates":[-86.26624099999999,32.132033],"type":"Point"}
}