{
  "type": "Feature",
  "properties": {
    "iso:country":"US",
    "sg:address":"1011 Avalon Ave",
    "sg:city":"Muscle Shoals",
    "sg:classifiers":[
        {
            "category":"Health Services",
            "subcategory":"Doctor",
            "type":"Services"
        }
    ],
    "sg:phone":"+1 256 383 8736",
    "sg:postcode":"35661",
    "sg:province":"AL",
    "sg:tags":[
        "dentist"
    ],
    "wof:name":"James D Hudson DDS",
    "wof:placetype":"venue"
},
  "geometry": {"coordinates":[-87.654817,34.744628],"type":"Point"}
}