{
  "type": "Feature",
  "properties": {
    "iso:country":"US",
    "sg:address":"309 Handy Homes",
    "sg:city":"Florence",
    "sg:classifiers":[
        {
            "category":"Health Services",
            "subcategory":"Doctor",
            "type":"Services"
        }
    ],
    "sg:phone":"+1 256 760 4713",
    "sg:postcode":"35630",
    "sg:province":"AL",
    "sg:tags":[
        "clinic"
    ],
    "wof:name":"Community Health Clinic",
    "wof:placetype":"venue"
},
  "geometry": {"coordinates":[-87.686565,34.799414],"type":"Point"}
}