{
  "type": "Feature",
  "properties": {
    "iso:country":"US",
    "sg:address":"8 Spruce St",
    "sg:city":"Daleville",
    "sg:classifiers":[
        {
            "category":"Retail",
            "subcategory":"Repair Shop",
            "type":"Services"
        }
    ],
    "sg:phone":"+1 334 503 6972",
    "sg:postcode":"36322",
    "sg:province":"AL",
    "wof:name":"Cohens Lock & Keys",
    "wof:placetype":"venue"
},
  "geometry": {"coordinates":[-85.686159,31.305793],"type":"Point"}
}