{
  "type": "Feature",
  "properties": {
    "iso:country":"US",
    "sg:address":"201 Yeager Pkwy",
    "sg:city":"Pelham",
    "sg:classifiers":[
        {
            "category":"Professional",
            "type":"Services"
        }
    ],
    "sg:phone":"+1 205 685 9384",
    "sg:postcode":"35124",
    "sg:province":"AL",
    "sg:tags":[
        "establishment"
    ],
    "wof:name":"KCS Group",
    "wof:placetype":"venue"
},
  "geometry": {"coordinates":[-86.80979000000001,33.289777],"type":"Point"}
}