{
  "type": "Feature",
  "properties": {
    "iso:country":"US",
    "sg:address":"3091 Gaston Ave",
    "sg:city":"Montgomery",
    "sg:classifiers":[
        {
            "category":"Health Services",
            "subcategory":"Chiropractor",
            "type":"Services"
        }
    ],
    "sg:phone":"+1 334 834 6282",
    "sg:postcode":"36105",
    "sg:province":"AL",
    "wof:name":"Alabama Family Chiropractic",
    "wof:placetype":"venue"
},
  "geometry": {"coordinates":[-86.318305,32.351465],"type":"Point"}
}