{
  "type": "Feature",
  "properties": {
    "iso:country":"US",
    "sg:address":"10 Saraland Blvd S",
    "sg:city":"Saraland",
    "sg:classifiers":[
        {
            "category":"Restaurant",
            "type":"Food & Drink"
        }
    ],
    "sg:phone":"+1 251 679 4703",
    "sg:postcode":"36571",
    "sg:province":"AL",
    "wof:name":"King's Seafood",
    "wof:placetype":"venue"
},
  "geometry": {"coordinates":[-88.070035,30.821343],"type":"Point"}
}