{
  "type": "Feature",
  "properties": {
    "addr:full":"2034 2nd St S Birmingham AL 35205",
    "addr:housenumber":"2034",
    "addr:postcode":"35205",
    "addr:street":"2Nd St S",
    "iso:country":"US",
    "sg:address":"2034 2nd St S",
    "sg:city":"Birmingham",
    "sg:classifiers":[
        {
            "category":"Real Estate",
            "subcategory":"Real Estate Agent",
            "type":"Services"
        }
    ],
    "sg:phone":"+1 205 323 1151",
    "sg:postcode":"35205",
    "sg:province":"AL",
    "sg:tags":[
        "security",
        "system"
    ],
    "wof:name":"Kizziah Company",
    "wof:placetype":"venue"
},
  "geometry": {"coordinates":[-86.82440099999999,33.485794],"type":"Point"}
}