{
  "type": "Feature",
  "properties": {
    "addr:full":"19360 Highway 43 Mount Vernon AL 36560",
    "addr:housenumber":"19360",
    "addr:postcode":"36560",
    "addr:street":"Highway 43;Vernon",
    "iso:country":"US",
    "sg:address":"19360 Highway 43",
    "sg:city":"Mount Vernon",
    "sg:classifiers":[
        {
            "category":"Personal",
            "subcategory":"Nail Salon",
            "type":"Services"
        }
    ],
    "sg:phone":"+1 251 829 4887",
    "sg:postcode":"36560",
    "sg:province":"AL",
    "wof:name":"Stridneys Hair Salon",
    "wof:placetype":"venue"
},
  "geometry": {"coordinates":[-88.00942999999999,31.117783],"type":"Point"}
}