{
  "type": "Feature",
  "properties": {
    "iso:country":"US",
    "sg:address":"1031 Gurnee Ave",
    "sg:city":"Anniston",
    "sg:classifiers":[
        {
            "category":"Manufacturing",
            "subcategory":"Signs",
            "type":"Manufacturing & Wholesale Goods"
        }
    ],
    "sg:phone":"+1 256 236 2416",
    "sg:postcode":"36201",
    "sg:province":"AL",
    "sg:tags":[
        "specialty",
        "mfg"
    ],
    "wof:name":"Howell Signs",
    "wof:placetype":"venue"
},
  "geometry": {"coordinates":[-85.83145,33.657171],"type":"Point"}
}