{
  "type": "Feature",
  "properties": {
    "iso:country":"US",
    "sg:address":"5901 Airport Blvd Ste E",
    "sg:city":"Mobile",
    "sg:classifiers":[
        {
            "category":"Health Services",
            "subcategory":"Doctor",
            "type":"Services"
        },
        {
            "category":"Community Center",
            "type":"Public Place"
        }
    ],
    "sg:phone":"+1 251 342 0505",
    "sg:postcode":"36608",
    "sg:province":"AL",
    "sg:tags":[
        "physician",
        "medical",
        "surgeon"
    ],
    "sg:website":"http://www.bioidenticalhormoneMD.com",
    "wof:name":"Brock, Larry MD",
    "wof:placetype":"venue"
},
  "geometry": {"coordinates":[-88.17791699999999,30.675949],"type":"Point"}
}