{
  "type": "Feature",
  "properties": {
    "iso:country":"US",
    "sg:address":"1222 Antioch Rd",
    "sg:city":"Somerville",
    "sg:classifiers":[
        {
            "category":"Manufacturing",
            "subcategory":"Rubber & Plastics",
            "type":"Manufacturing & Wholesale Goods"
        }
    ],
    "sg:phone":"+1 256 778 8141",
    "sg:postcode":"35670",
    "sg:province":"AL",
    "wof:name":"Amdek Inc",
    "wof:placetype":"venue"
},
  "geometry": {"coordinates":[-86.737744,34.476931],"type":"Point"}
}