{
  "type": "Feature",
  "properties": {
    "iso:country":"US",
    "sg:address":"900 Commons Dr",
    "sg:city":"Dothan",
    "sg:classifiers":[
        {
            "category":"Utilities",
            "subcategory":"Telephone",
            "type":"Services"
        }
    ],
    "sg:phone":"+1 334 792 3304",
    "sg:postcode":"36303",
    "sg:province":"AL",
    "sg:tags":[
        "company"
    ],
    "wof:name":"Alltel Communications",
    "wof:placetype":"venue"
},
  "geometry": {"coordinates":[-85.42788299999999,31.255077],"type":"Point"}
}