{
  "type": "Feature",
  "properties": {
    "iso:country":"US",
    "sg:address":"121 N Main St",
    "sg:city":"Enterprise",
    "sg:classifiers":[
        {
            "category":"Shopping",
            "type":"Retail Goods"
        }
    ],
    "sg:phone":"+1 334 347 4446",
    "sg:postcode":"36330",
    "sg:province":"AL",
    "sg:tags":[
        "equipment",
        "care",
        "health",
        "home"
    ],
    "wof:name":"Enterprise Home Health Supply",
    "wof:placetype":"venue"
},
  "geometry": {"coordinates":[-85.854746,31.315187],"type":"Point"}
}