{
  "type": "Feature",
  "properties": {
    "iso:country":"US",
    "sg:address":"5600 Bodine Rd",
    "sg:city":"Guntersville",
    "sg:classifiers":[
        {
            "category":"Shopping",
            "subcategory":"Bicycles & Sporting Goods",
            "type":"Retail Goods"
        }
    ],
    "sg:phone":"+1 256 571 7373",
    "sg:postcode":"35976",
    "sg:province":"AL",
    "wof:name":"Powerfit Exercise Equipment",
    "wof:placetype":"venue"
},
  "geometry": {"coordinates":[-86.313275,34.31245],"type":"Point"}
}