{
  "type": "Feature",
  "properties": {
    "addr:full":"6407 Cedar Point Dr NW Huntsville AL 35810",
    "addr:housenumber":"6407",
    "addr:postcode":"35810",
    "addr:street":"Cedar Point Dr Nw",
    "iso:country":"US",
    "sg:address":"6407 Cedar Point Dr NW",
    "sg:city":"Huntsville",
    "sg:classifiers":[
        {
            "category":"Manufacturing",
            "subcategory":"Printing",
            "type":"Manufacturing & Wholesale Goods"
        }
    ],
    "sg:phone":"+1 256 851 9118",
    "sg:postcode":"35810",
    "sg:province":"AL",
    "sg:tags":[
        "company",
        "graphics"
    ],
    "wof:name":"Destiny Productions",
    "wof:placetype":"venue"
},
  "geometry": {"coordinates":[-86.616941,34.802806],"type":"Point"}
}