{
  "type": "Feature",
  "properties": {
    "iso:country":"US",
    "sg:address":"1556 Gulf Shores Pkwy",
    "sg:city":"Gulf Shores",
    "sg:classifiers":[
        {
            "category":"Real Estate",
            "subcategory":"Architect",
            "type":"Services"
        }
    ],
    "sg:phone":"+1 251 981 5414",
    "sg:postcode":"36542",
    "sg:province":"AL",
    "wof:name":"Brad Lee Patterson Architect",
    "wof:placetype":"venue"
},
  "geometry": {"coordinates":[-87.688218,30.26984],"type":"Point"}
}