{
  "type": "Feature",
  "properties": {
    "iso:country":"US",
    "sg:address":"508 McAdams Ave",
    "sg:city":"Daphne",
    "sg:classifiers":[
        {
            "category":"Professional",
            "subcategory":"Management & Consulting",
            "type":"Services"
        }
    ],
    "sg:phone":"+1 251 621 8522",
    "sg:postcode":"36526",
    "sg:province":"AL",
    "sg:tags":[
        "business"
    ],
    "wof:name":"Glovia International",
    "wof:placetype":"venue"
},
  "geometry": {"coordinates":[-87.905553,30.596356],"type":"Point"}
}