{
  "type": "Feature",
  "properties": {
    "iso:country":"US",
    "sg:address":"604 6th Ave NE",
    "sg:city":"Decatur",
    "sg:classifiers":[
        {
            "category":"Autos & Motor Vehicles",
            "subcategory":"Fuel & Gas Station",
            "type":"Retail Goods"
        },
        {
            "category":"Food & Beverages",
            "subcategory":"Groceries & Convenience Stores",
            "type":"Retail Goods"
        }
    ],
    "sg:phone":"+1 256 351 6522",
    "sg:postcode":"35601",
    "sg:province":"AL",
    "sg:website":"http://www.circle11.com",
    "wof:name":"Circle C Food Store",
    "wof:placetype":"venue"
},
  "geometry": {"coordinates":[-86.979895,34.607029],"type":"Point"}
}