{
  "type": "Feature",
  "properties": {
    "iso:country":"US",
    "sg:address":"716 Boligee St",
    "sg:city":"Eutaw",
    "sg:classifiers":[
        {
            "category":"Shopping",
            "subcategory":"Gifts & Souvenirs",
            "type":"Retail Goods"
        }
    ],
    "sg:phone":"+1 205 372 3562",
    "sg:postcode":"35462",
    "sg:province":"AL",
    "wof:name":"Vollraths",
    "wof:placetype":"venue"
},
  "geometry": {"coordinates":[-87.896667,32.840662],"type":"Point"}
}