{
  "type": "Feature",
  "properties": {
    "iso:country":"US",
    "sg:address":"246 Co Rd 10",
    "sg:city":"Tuskegee",
    "sg:classifiers":[
        {
            "category":"Government",
            "subcategory":"Police Station",
            "type":"Public Place"
        }
    ],
    "sg:phone":"+1 334 724 2544",
    "sg:postcode":"36083",
    "sg:province":"AL",
    "sg:tags":[
        "sheriff"
    ],
    "wof:name":"Macon County Sheriff Dept",
    "wof:placetype":"venue"
},
  "geometry": {"coordinates":[-85.642014,32.401782],"type":"Point"}
}