{
  "type": "Feature",
  "properties": {
    "addr:full":"710 N Main St Tuscumbia AL 35674",
    "addr:housenumber":"710",
    "addr:postcode":"35674",
    "addr:street":"N Main St",
    "iso:country":"US",
    "sg:address":"710 N Main St",
    "sg:city":"Tuscumbia",
    "sg:classifiers":[
        {
            "category":"Social Services",
            "subcategory":"Child Care",
            "type":"Services"
        }
    ],
    "sg:phone":"+1 256 381 4080",
    "sg:postcode":"35674",
    "sg:province":"AL",
    "sg:tags":[
        "day"
    ],
    "wof:name":"Miss Jane's Day Care",
    "wof:placetype":"venue"
},
  "geometry": {"coordinates":[-87.703294,34.741364],"type":"Point"}
}