{
  "type": "Feature",
  "properties": {
    "iso:country":"US",
    "sg:address":"118 Ryan Ave",
    "sg:city":"Mobile",
    "sg:classifiers":[
        {
            "category":"Manufacturing",
            "subcategory":"Lumber",
            "type":"Manufacturing & Wholesale Goods"
        }
    ],
    "sg:phone":"+1 251 476 4023",
    "sg:postcode":"36607",
    "sg:province":"AL",
    "sg:tags":[
        "operation",
        "timber",
        "tract"
    ],
    "wof:name":"McCall Farms LLC",
    "wof:placetype":"venue"
},
  "geometry": {"coordinates":[-88.093165,30.690619],"type":"Point"}
}