{
  "type": "Feature",
  "properties": {
    "iso:country":"US",
    "sg:address":"720 Pratt Ave NE",
    "sg:city":"Huntsville",
    "sg:classifiers":[
        {
            "category":"Professional",
            "type":"Services"
        }
    ],
    "sg:phone":"+1 256 428 5555",
    "sg:postcode":"35801",
    "sg:province":"AL",
    "wof:name":"Starfish",
    "wof:placetype":"venue"
},
  "geometry": {"coordinates":[-86.575717,34.738686],"type":"Point"}
}