{
  "type": "Feature",
  "properties": {
    "addr:full":"1209 S Noble St Anniston AL 36201",
    "addr:housenumber":"1209",
    "addr:postcode":"36201",
    "addr:street":"S Noble St",
    "iso:country":"US",
    "sg:address":"1209 S Noble St",
    "sg:city":"Anniston",
    "sg:classifiers":[
        {
            "category":"Wholesale",
            "subcategory":"Motor Vehicles",
            "type":"Manufacturing & Wholesale Goods"
        }
    ],
    "sg:phone":"+1 256 238 9542",
    "sg:postcode":"36201",
    "sg:province":"AL",
    "sg:tags":[
        "automobile"
    ],
    "wof:name":"G & L Wholesale Cars",
    "wof:placetype":"venue"
},
  "geometry": {"coordinates":[-85.829013,33.629491],"type":"Point"}
}