{
  "type": "Feature",
  "properties": {
    "iso:country":"US",
    "sg:address":"7565 Grier Rd",
    "sg:city":"Wetumpka",
    "sg:classifiers":[
        {
            "category":"Manufacturing",
            "subcategory":"Building Materials",
            "type":"Manufacturing & Wholesale Goods"
        }
    ],
    "sg:phone":"+1 334 567 3641",
    "sg:postcode":"36092",
    "sg:province":"AL",
    "sg:tags":[
        "product",
        "wood"
    ],
    "wof:name":"Grier Frame & Crafts",
    "wof:placetype":"venue"
},
  "geometry": {"coordinates":[-86.155843,32.698065],"type":"Point"}
}