{
  "type": "Feature",
  "properties": {
    "addr:full":"321 N Hull St Montgomery AL 36104",
    "addr:housenumber":"321",
    "addr:postcode":"36104",
    "addr:street":"N Hull St",
    "iso:country":"US",
    "sg:address":"321 N Hull St",
    "sg:city":"Montgomery",
    "sg:classifiers":[
        {
            "category":"Professional",
            "subcategory":"Lawyer & Legal Services",
            "type":"Services"
        }
    ],
    "sg:phone":"+1 334 834 2135",
    "sg:postcode":"36104",
    "sg:province":"AL",
    "sg:tags":[
        "attorney"
    ],
    "wof:name":"Mc Iver & Poole",
    "wof:placetype":"venue"
},
  "geometry": {"coordinates":[-86.304017,32.381902],"type":"Point"}
}