{
  "type": "Feature",
  "properties": {
    "iso:country":"US",
    "sg:address":"2133 32nd Ave N",
    "sg:city":"Birmingham",
    "sg:classifiers":[
        {
            "category":"Organizations",
            "subcategory":"Religious Organization",
            "type":"Services"
        }
    ],
    "sg:phone":"+1 205 328 3937",
    "sg:postcode":"35207",
    "sg:province":"AL",
    "wof:name":"Wrights Chapel Unitd Methodst",
    "wof:placetype":"venue"
},
  "geometry": {"coordinates":[-86.824954,33.551833],"type":"Point"}
}