{
  "type": "Feature",
  "properties": {
    "iso:country":"US",
    "sg:address":"1417 17th St N",
    "sg:city":"Birmingham",
    "sg:classifiers":[
        {
            "category":"Professional",
            "subcategory":"Employment Agencies",
            "type":"Services"
        }
    ],
    "sg:phone":"+1 205 244 1444",
    "sg:postcode":"35204",
    "sg:province":"AL",
    "wof:name":"Hunter Hussein & Associates",
    "wof:placetype":"venue"
},
  "geometry": {"coordinates":[-86.820516,33.528137],"type":"Point"}
}