{
  "type": "Feature",
  "properties": {
    "iso:country":"US",
    "sg:address":"1077 W Main St",
    "sg:city":"Dothan",
    "sg:classifiers":[
        {
            "category":"Personal",
            "subcategory":"Beauty Salon",
            "type":"Services"
        }
    ],
    "sg:phone":"+1 334 712 9063",
    "sg:postcode":"36301",
    "sg:province":"AL",
    "wof:name":"Janice's Salon",
    "wof:placetype":"venue"
},
  "geometry": {"coordinates":[-85.405484,31.226294],"type":"Point"}
}