{
  "type": "Feature",
  "properties": {
    "iso:country":"US",
    "sg:address":"55 Golfview Dr NE",
    "sg:city":"Arab",
    "sg:classifiers":[
        {
            "category":"Health Services",
            "subcategory":"Doctor",
            "type":"Services"
        }
    ],
    "sg:phone":"+1 256 586 8100",
    "sg:postcode":"35016",
    "sg:province":"AL",
    "sg:tags":[
        "dentist"
    ],
    "wof:name":"John W York II DDS",
    "wof:placetype":"venue"
},
  "geometry": {"coordinates":[-86.50173,34.343198],"type":"Point"}
}