{
  "type": "Feature",
  "properties": {
    "iso:country":"US",
    "sg:address":"380 Fairhope Ave",
    "sg:city":"Fairhope",
    "sg:classifiers":[
        {
            "category":"Shopping",
            "subcategory":"Clothing, Apparel, & Fashions",
            "type":"Retail Goods"
        }
    ],
    "sg:phone":"+1 251 928 5564",
    "sg:postcode":"36532",
    "sg:province":"AL",
    "sg:website":"www.mfcasuals.com",
    "wof:name":"M & F Casuals",
    "wof:placetype":"venue"
},
  "geometry": {"coordinates":[-87.904444,30.522952],"type":"Point"}
}