{
  "type": "Feature",
  "properties": {
    "iso:country":"US",
    "sg:address":"3982 Double Bridge Rd",
    "sg:city":"Steele",
    "sg:classifiers":[
        {
            "category":"Shopping",
            "type":"Retail Goods"
        }
    ],
    "sg:phone":"+1 205 594 3122",
    "sg:postcode":"35987",
    "sg:province":"AL",
    "sg:tags":[
        "spa",
        "hot",
        "tub"
    ],
    "wof:name":"Martin Spas",
    "wof:placetype":"venue"
},
  "geometry": {"coordinates":[-86.249994,33.898055],"type":"Point"}
}