{
  "type": "Feature",
  "properties": {
    "iso:country":"US",
    "sg:address":"2256 Montgomery Hwy",
    "sg:city":"Dothan",
    "sg:classifiers":[
        {
            "category":"Personal",
            "type":"Services"
        }
    ],
    "sg:phone":"+1 334 792 9514",
    "sg:postcode":"36303",
    "sg:province":"AL",
    "sg:tags":[
        "therapist",
        "massage"
    ],
    "wof:name":"Golden E-Scentials",
    "wof:placetype":"venue"
},
  "geometry": {"coordinates":[-85.415347,31.241318],"type":"Point"}
}