{
  "type": "Feature",
  "properties": {
    "addr:full":"811 21st Ave Tuscaloosa AL 35401",
    "addr:housenumber":"811",
    "addr:postcode":"35401",
    "addr:street":"21St Ave",
    "iso:country":"US",
    "sg:address":"811 21st Ave",
    "sg:city":"Tuscaloosa",
    "sg:classifiers":[
        {
            "category":"Professional",
            "subcategory":"Lawyer & Legal Services",
            "type":"Services"
        }
    ],
    "sg:phone":"+1 205 345 0966",
    "sg:postcode":"35401",
    "sg:province":"AL",
    "sg:website":"www.sogollaw.com",
    "wof:name":"Joel L Sogol",
    "wof:placetype":"venue"
},
  "geometry": {"coordinates":[-87.562692,33.207278],"type":"Point"}
}