{
  "type": "Feature",
  "properties": {
    "iso:country":"US",
    "sg:address":"445 State Rte 69",
    "sg:city":"Hanceville",
    "sg:classifiers":[
        {
            "category":"Real Estate",
            "subcategory":"Real Estate Agent",
            "type":"Services"
        }
    ],
    "sg:phone":"+1 256 287 1349",
    "sg:postcode":"35077",
    "sg:province":"AL",
    "sg:tags":[
        "agency",
        "rental"
    ],
    "wof:name":"Bestway Rental Inc",
    "wof:placetype":"venue"
},
  "geometry": {"coordinates":[-86.871561,34.050226],"type":"Point"}
}