{
  "type": "Feature",
  "properties": {
    "iso:country":"US",
    "sg:address":"2369 Gardner Dairy Rd",
    "sg:city":"Dadeville",
    "sg:classifiers":[
        {
            "category":"Building & Trades",
            "subcategory":"Construction",
            "type":"Services"
        }
    ],
    "sg:phone":"+1 256 825 0169",
    "sg:postcode":"36853",
    "sg:province":"AL",
    "sg:tags":[
        "residential"
    ],
    "wof:name":"Kane Building LLC",
    "wof:placetype":"venue"
},
  "geometry": {"coordinates":[-85.753985,32.897301],"type":"Point"}
}