{
  "type": "Feature",
  "properties": {
    "iso:country":"US",
    "sg:address":"3095 Cahaba Valley Rd",
    "sg:city":"Pelham",
    "sg:classifiers":[
        {
            "category":"Professional",
            "subcategory":"Business Services",
            "type":"Services"
        }
    ],
    "sg:phone":"+1 205 988 0192",
    "sg:postcode":"35124",
    "sg:province":"AL",
    "wof:name":"D McGuire Enterprises",
    "wof:placetype":"venue"
},
  "geometry": {"coordinates":[-86.745477,33.355519],"type":"Point"}
}