{
  "type": "Feature",
  "properties": {
    "iso:country":"US",
    "sg:address":"2340 Whitesburg Dr S",
    "sg:city":"Huntsville",
    "sg:classifiers":[
        {
            "category":"Shopping",
            "subcategory":"Pharmacy",
            "type":"Retail Goods"
        }
    ],
    "sg:phone":"+1 256 533 6180",
    "sg:postcode":"35801",
    "sg:province":"AL",
    "wof:name":"CVS",
    "wof:placetype":"venue"
},
  "geometry": {"coordinates":[-86.575683,34.714346],"type":"Point"}
}