{
  "type": "Feature",
  "properties": {
    "addr:full":"4389 Alabama Ave Monroeville AL 36460",
    "addr:housenumber":"4389",
    "addr:postcode":"36460",
    "addr:street":"Alabama Ave",
    "iso:country":"US",
    "sg:address":"4389 Alabama Ave",
    "sg:city":"Monroeville",
    "sg:classifiers":[
        {
            "category":"Travel",
            "subcategory":"Hotels & Motels",
            "type":"Entertainment"
        }
    ],
    "sg:phone":"+1 251 743 3297",
    "sg:postcode":"36460",
    "sg:province":"AL",
    "sg:tags":[
        "franchised"
    ],
    "wof:name":"Days Inn",
    "wof:placetype":"venue"
},
  "geometry": {"coordinates":[-87.344758,31.469813],"type":"Point"}
}