{
  "type": "Feature",
  "properties": {
    "iso:country":"US",
    "sg:address":"779 J D Love Rd",
    "sg:city":"Ashford",
    "sg:phone":"+1 334 792 0352",
    "sg:postcode":"36312",
    "sg:province":"AL",
    "sg:tags":[
        "farm",
        "field",
        "crop",
        "cotton"
    ],
    "wof:name":"Floyd Ham",
    "wof:placetype":"venue"
},
  "geometry": {"coordinates":[-85.208749,31.287666],"type":"Point"}
}