{
  "type": "Feature",
  "properties": {
    "addr:full":"118 N Ross St Auburn AL 36830",
    "addr:housenumber":"118",
    "addr:postcode":"36830",
    "addr:street":"N Ross St",
    "iso:country":"US",
    "sg:address":"118 N Ross St",
    "sg:city":"Auburn",
    "sg:classifiers":[
        {
            "category":"Health Services",
            "subcategory":"Doctor",
            "type":"Services"
        }
    ],
    "sg:phone":"+1 334 826 3842",
    "sg:postcode":"36830",
    "sg:province":"AL",
    "sg:tags":[
        "clinic",
        "medical"
    ],
    "wof:name":"Soft Tissue Therapy",
    "wof:placetype":"venue"
},
  "geometry": {"coordinates":[-85.475098,32.608597],"type":"Point"}
}