{
  "type": "Feature",
  "properties": {
    "addr:full":"805 N Section St Fairhope AL 36532",
    "addr:housenumber":"805",
    "addr:postcode":"36532",
    "addr:street":"N Section St",
    "iso:country":"US",
    "sg:address":"805 N Section St",
    "sg:city":"Fairhope",
    "sg:classifiers":[
        {
            "category":"Professional",
            "subcategory":"Accounting & Tax Preparation",
            "type":"Services"
        }
    ],
    "sg:phone":"+1 251 928 7823",
    "sg:postcode":"36532",
    "sg:province":"AL",
    "sg:tags":[
        "return"
    ],
    "wof:name":"Lowery Tax & Financial Service",
    "wof:placetype":"venue"
},
  "geometry": {"coordinates":[-87.89854200000001,30.541404],"type":"Point"}
}