{
  "type": "Feature",
  "properties": {
    "addr:full":"2621 Three Notch Rd Enterprise AL 36330",
    "addr:housenumber":"2621",
    "addr:postcode":"36330",
    "addr:street":"Three Notch Rd Enterprise",
    "iso:country":"US",
    "sg:address":"2621 Three Notch Rd",
    "sg:city":"Enterprise",
    "sg:classifiers":[
        {
            "category":"Farming",
            "subcategory":"Dairy Farm",
            "type":"Manufacturing & Wholesale Goods"
        }
    ],
    "sg:phone":"+1 334 347 2534",
    "sg:postcode":"36330",
    "sg:province":"AL",
    "wof:name":"Edwin & Phillip Martin Dairy",
    "wof:placetype":"venue"
},
  "geometry": {"coordinates":[-85.823905,31.282992],"type":"Point"}
}