{
  "type": "Feature",
  "properties": {
    "iso:country":"US",
    "sg:address":"533 Broadway Ave",
    "sg:city":"Sylacauga",
    "sg:classifiers":[
        {
            "category":"Government",
            "subcategory":"Office",
            "type":"Public Place"
        }
    ],
    "sg:phone":"+1 256 249 3603",
    "sg:postcode":"35150",
    "sg:province":"AL",
    "sg:tags":[
        "force",
        "station",
        "armed",
        "recruiting"
    ],
    "wof:name":"US Marine Corps Recruiting",
    "wof:placetype":"venue"
},
  "geometry": {"coordinates":[-86.250968,33.158033],"type":"Point"}
}