{
  "type": "Feature",
  "properties": {
    "addr:full":"2248 Houston St Florence AL 35630",
    "addr:housenumber":"2248",
    "addr:postcode":"35630",
    "addr:street":"Houston St",
    "iso:country":"US",
    "sg:address":"2248 Houston St",
    "sg:city":"Florence",
    "sg:classifiers":[
        {
            "category":"Communications",
            "subcategory":"Film & Video Production",
            "type":"Services"
        }
    ],
    "sg:phone":"+1 256 767 1616",
    "sg:postcode":"35630",
    "sg:province":"AL",
    "sg:tags":[
        "taping"
    ],
    "wof:name":"Data Video Taping",
    "wof:placetype":"venue"
},
  "geometry": {"coordinates":[-87.687048,34.830849],"type":"Point"}
}