{
  "type": "Feature",
  "properties": {
    "iso:country":"US",
    "sg:address":"1103 Co Rd 1194",
    "sg:city":"Vinemont",
    "sg:classifiers":[
        {
            "category":"Freight",
            "type":"Transportation"
        }
    ],
    "sg:phone":"+1 256 734 1470",
    "sg:postcode":"35179",
    "sg:province":"AL",
    "sg:tags":[
        "trucking"
    ],
    "wof:name":"R E Garrison Trucking Co Inc",
    "wof:placetype":"venue"
},
  "geometry": {"coordinates":[-86.917409,34.234202],"type":"Point"}
}