{
  "type": "Feature",
  "properties": {
    "iso:country":"US",
    "sg:address":"2406 State Rte 14",
    "sg:city":"Autaugaville",
    "sg:classifiers":[
        {
            "category":"Personal",
            "subcategory":"Beauty Salon",
            "type":"Services"
        }
    ],
    "sg:phone":"+1 334 358 3363",
    "sg:postcode":"36003",
    "sg:province":"AL",
    "wof:name":"Beauty Shack",
    "wof:placetype":"venue"
},
  "geometry": {"coordinates":[-86.653042,32.433432],"type":"Point"}
}