{
  "type": "Feature",
  "properties": {
    "iso:country":"US",
    "sg:address":"812 W Main St",
    "sg:city":"Dothan",
    "sg:classifiers":[
        {
            "category":"Autos & Motor Vehicles",
            "subcategory":"Fuel & Gas Station",
            "type":"Retail Goods"
        }
    ],
    "sg:phone":"+1 334 792 7298",
    "sg:postcode":"36301",
    "sg:province":"AL",
    "sg:tags":[
        "oil"
    ],
    "wof:name":"Shell Food Mart",
    "wof:placetype":"venue"
},
  "geometry": {"coordinates":[-85.40308,31.225971],"type":"Point"}
}