{
  "type": "Feature",
  "properties": {
    "iso:country":"US",
    "sg:address":"5032 Whatley St",
    "sg:city":"Birmingham",
    "sg:classifiers":[
        {
            "category":"Professional",
            "subcategory":"Computer Services",
            "type":"Services"
        }
    ],
    "sg:phone":"+1 205 428 6636",
    "sg:postcode":"35228",
    "sg:province":"AL",
    "sg:tags":[
        "datum"
    ],
    "wof:name":"Networker 2000",
    "wof:placetype":"venue"
},
  "geometry": {"coordinates":[-86.91792,33.447866],"type":"Point"}
}