{
  "type": "Feature",
  "properties": {
    "iso:country":"US",
    "sg:address":"5724 US Hwy 280",
    "sg:city":"Birmingham",
    "sg:classifiers":[
        {
            "category":"Professional",
            "subcategory":"Advertising",
            "type":"Services"
        }
    ],
    "sg:phone":"+1 205 991 1185",
    "sg:postcode":"35242",
    "sg:province":"AL",
    "sg:tags":[
        "representative"
    ],
    "wof:name":"Wise Staffing Inc",
    "wof:placetype":"venue"
},
  "geometry": {"coordinates":[-86.667358,33.381327],"type":"Point"}
}