{
  "type": "Feature",
  "properties": {
    "addr:full":"1065 Co Rd 35 Pelham AL 35124",
    "addr:housenumber":"1065;35",
    "addr:postcode":"35124",
    "addr:street":"Co Rd",
    "iso:country":"US",
    "sg:address":"1065 Co Rd 35",
    "sg:city":"Pelham",
    "sg:classifiers":[
        {
            "category":"Retail",
            "subcategory":"Repair Shop",
            "type":"Services"
        }
    ],
    "sg:phone":"+1 205 663 7178",
    "sg:postcode":"35124",
    "sg:province":"AL",
    "sg:tags":[
        "pressure",
        "cleaning"
    ],
    "wof:name":"Magic City Pressure Cleaning",
    "wof:placetype":"venue"
},
  "geometry": {"coordinates":[-86.793381,33.292279],"type":"Point"}
}