{
  "type": "Feature",
  "properties": {
    "addr:full":"111 Old Columbus Rd Opelika AL 36804",
    "addr:housenumber":"111",
    "addr:postcode":"36804",
    "addr:street":"Old Columbus Rd",
    "iso:country":"US",
    "sg:address":"111 Old Columbus Rd",
    "sg:city":"Opelika",
    "sg:classifiers":[
        {
            "category":"Building & Trades",
            "subcategory":"Construction",
            "type":"Services"
        }
    ],
    "sg:phone":"+1 334 749 8865",
    "sg:postcode":"36804",
    "sg:province":"AL",
    "sg:tags":[
        "paving",
        "contractor"
    ],
    "wof:name":"East Alabama Paving Co",
    "wof:placetype":"venue"
},
  "geometry": {"coordinates":[-85.36783,32.625333],"type":"Point"}
}