{
  "type": "Feature",
  "properties": {
    "addr:full":"676 S McQueen Smith Rd Prattville AL 36066",
    "addr:housenumber":"676",
    "addr:postcode":"36066",
    "addr:street":"S Mcqueen Smith Rd",
    "iso:country":"US",
    "sg:address":"676 S McQueen Smith Rd",
    "sg:city":"Prattville",
    "sg:classifiers":[
        {
            "category":"Professional",
            "subcategory":"Accounting & Tax Preparation",
            "type":"Services"
        }
    ],
    "sg:phone":"+1 334 361 1040",
    "sg:postcode":"36066",
    "sg:province":"AL",
    "sg:tags":[
        "return"
    ],
    "wof:name":"P C Income Tax",
    "wof:placetype":"venue"
},
  "geometry": {"coordinates":[-86.418176,32.461423],"type":"Point"}
}