{
  "type": "Feature",
  "properties": {
    "addr:full":"207 8th St N Clanton AL 35045",
    "addr:housenumber":"207",
    "addr:postcode":"35045",
    "addr:street":"8Th St N",
    "iso:country":"US",
    "sg:address":"207 8th St N",
    "sg:city":"Clanton",
    "sg:classifiers":[
        {
            "category":"Organizations",
            "subcategory":"Religious Organization",
            "type":"Services"
        }
    ],
    "sg:phone":"+1 205 755 0490",
    "sg:postcode":"35045",
    "sg:province":"AL",
    "sg:tags":[
        "church"
    ],
    "wof:name":"First United Methodist Church",
    "wof:placetype":"venue"
},
  "geometry": {"coordinates":[-86.632924,32.838434],"type":"Point"}
}