{
  "type": "Feature",
  "properties": {
    "iso:country":"US",
    "sg:address":"1556 Grandview Trl",
    "sg:city":"Warrior",
    "sg:classifiers":[
        {
            "category":"Retail",
            "subcategory":"Repair Shop",
            "type":"Services"
        }
    ],
    "sg:phone":"+1 205 647 2107",
    "sg:postcode":"35180",
    "sg:province":"AL",
    "wof:name":"Smoke Rise Sam Johnson TV Svc",
    "wof:placetype":"venue"
},
  "geometry": {"coordinates":[-86.835355,33.893053],"type":"Point"}
}