{
  "type": "Feature",
  "properties": {
    "addr:full":"136 S Sage Ave Mobile AL 36606",
    "addr:housenumber":"136",
    "addr:postcode":"36606",
    "addr:street":"S Sage Ave",
    "iso:country":"US",
    "sg:address":"136 S Sage Ave",
    "sg:city":"Mobile",
    "sg:classifiers":[
        {
            "category":"Shopping",
            "subcategory":"Clothing, Apparel, & Fashions",
            "type":"Retail Goods"
        }
    ],
    "sg:phone":"+1 251 341 1480",
    "sg:postcode":"36606",
    "sg:province":"AL",
    "sg:tags":[
        "clo",
        "wear",
        "furniture"
    ],
    "wof:name":"Tiny Town",
    "wof:placetype":"venue"
},
  "geometry": {"coordinates":[-88.114689,30.684619],"type":"Point"}
}