{
  "type": "Feature",
  "properties": {
    "iso:country":"US",
    "sg:address":"109 Pettus St",
    "sg:city":"Dothan",
    "sg:classifiers":[
        {
            "category":"Shopping",
            "subcategory":"Books",
            "type":"Retail Goods"
        }
    ],
    "sg:phone":"+1 334 792 3921",
    "sg:postcode":"36301",
    "sg:province":"AL",
    "wof:name":"Friends Dothan Houston County",
    "wof:placetype":"venue"
},
  "geometry": {"coordinates":[-85.400187,31.223619],"type":"Point"}
}