{
  "type": "Feature",
  "properties": {
    "iso:country":"US",
    "sg:address":"3221 3rd Ave S",
    "sg:city":"Birmingham",
    "sg:classifiers":[
        {
            "category":"Professional",
            "type":"Services"
        }
    ],
    "sg:phone":"+1 205 251 4250",
    "sg:postcode":"35222",
    "sg:province":"AL",
    "wof:name":"Dynacare Laboratoriesarl Lab S",
    "wof:placetype":"venue"
},
  "geometry": {"coordinates":[-86.78501900000001,33.518268],"type":"Point"}
}