{
  "type": "Feature",
  "properties": {
    "iso:country":"US",
    "sg:address":"3715 Lakeside Ct",
    "sg:city":"Mobile",
    "sg:classifiers":[
        {
            "category":"Professional",
            "type":"Services"
        }
    ],
    "sg:phone":"+1 251 662 8322",
    "sg:postcode":"36693",
    "sg:province":"AL",
    "wof:name":"Landlink",
    "wof:placetype":"venue"
},
  "geometry": {"coordinates":[-88.129079,30.65112],"type":"Point"}
}