{
  "type": "Feature",
  "properties": {
    "addr:full":"401 19th St N Bessemer AL 35020",
    "addr:housenumber":"401",
    "addr:postcode":"35020",
    "addr:street":"19Th St N",
    "iso:country":"US",
    "sg:address":"401 19th St N",
    "sg:city":"Bessemer",
    "sg:classifiers":[
        {
            "category":"Shopping",
            "subcategory":"Computers & Home Electronics",
            "type":"Retail Goods"
        }
    ],
    "sg:phone":"+1 205 426 8383",
    "sg:postcode":"35020",
    "sg:province":"AL",
    "sg:tags":[
        "equipment",
        "dealer"
    ],
    "wof:name":"J H Collier Computers",
    "wof:placetype":"venue"
},
  "geometry": {"coordinates":[-86.955094,33.403456],"type":"Point"}
}