{
  "type": "Feature",
  "properties": {
    "addr:full":"240 Howard Ballard Dr Ashland AL 36251",
    "addr:housenumber":"240",
    "addr:postcode":"36251",
    "addr:street":"Howard Ballard Dr",
    "iso:country":"US",
    "sg:address":"240 Howard Ballard Dr",
    "sg:city":"Ashland",
    "sg:classifiers":[
        {
            "category":"Organizations",
            "subcategory":"Religious Organization",
            "type":"Services"
        }
    ],
    "sg:phone":"+1 256 354 2738",
    "sg:postcode":"36251",
    "sg:province":"AL",
    "sg:tags":[
        "church"
    ],
    "wof:name":"New Life Christian Ctr",
    "wof:placetype":"venue"
},
  "geometry": {"coordinates":[-85.850561,33.276126],"type":"Point"}
}