{
  "type": "Feature",
  "properties": {
    "addr:full":"4386 Cook Springs Rd Pell City AL 35125",
    "addr:housenumber":"4386",
    "addr:postcode":"35125",
    "addr:street":"Cook Springs Rd",
    "iso:country":"US",
    "sg:address":"4386 Cook Springs Rd",
    "sg:city":"Pell City",
    "sg:classifiers":[
        {
            "category":"Professional",
            "subcategory":"Management & Consulting",
            "type":"Services"
        }
    ],
    "sg:phone":"+1 205 338 3865",
    "sg:postcode":"35125",
    "sg:province":"AL",
    "sg:tags":[
        "specialty",
        "business"
    ],
    "wof:name":"Warren & Assoc Construction",
    "wof:placetype":"venue"
},
  "geometry": {"coordinates":[-86.359492,33.639982],"type":"Point"}
}