{
  "type": "Feature",
  "properties": {
    "addr:full":"1081 Gray Rd Boaz AL 35957",
    "addr:housenumber":"1081",
    "addr:postcode":"35957",
    "addr:street":"Gray Rd",
    "iso:country":"US",
    "sg:address":"1081 Gray Rd",
    "sg:city":"Boaz",
    "sg:classifiers":[
        {
            "category":"Retail",
            "subcategory":"Laundry & Dry Cleaning",
            "type":"Services"
        }
    ],
    "sg:phone":"+1 256 878 8144",
    "sg:postcode":"35957",
    "sg:province":"AL",
    "wof:name":"Alabama Carpet Cleaning",
    "wof:placetype":"venue"
},
  "geometry": {"coordinates":[-86.16034399999999,34.249041],"type":"Point"}
}