{
  "type": "Feature",
  "properties": {
    "iso:country":"US",
    "sg:address":"438 Oakwood Ave",
    "sg:city":"Bessemer",
    "sg:classifiers":[
        {
            "category":"Real Estate",
            "subcategory":"Real Estate Operator",
            "type":"Services"
        }
    ],
    "sg:phone":"+1 205 497 0360",
    "sg:postcode":"35023",
    "sg:province":"AL",
    "sg:tags":[
        "apartment"
    ],
    "wof:name":"Edenberry Apartments",
    "wof:placetype":"venue"
},
  "geometry": {"coordinates":[-87.000023,33.459828],"type":"Point"}
}