{
  "type": "Feature",
  "properties": {
    "addr:full":"8040 Wade Rd Warrior AL 35180",
    "addr:housenumber":"8040",
    "addr:postcode":"35180",
    "addr:street":"Wade Rd",
    "iso:country":"US",
    "sg:address":"8040 Wade Rd",
    "sg:city":"Warrior",
    "sg:phone":"+1 205 647 0485",
    "sg:postcode":"35180",
    "sg:province":"AL",
    "sg:tags":[
        "farm",
        "rice"
    ],
    "wof:name":"Terry Thomas Farms",
    "wof:placetype":"venue"
},
  "geometry": {"coordinates":[-86.939239,33.785815],"type":"Point"}
}