{
  "type": "Feature",
  "properties": {
    "iso:country":"US",
    "sg:address":"513 Lurleen B Wallace Blvd S",
    "sg:city":"Tuscaloosa",
    "sg:classifiers":[
        {
            "category":"Retail",
            "subcategory":"Repair Shop",
            "type":"Services"
        }
    ],
    "sg:phone":"+1 205 349 3990",
    "sg:postcode":"35401",
    "sg:province":"AL",
    "sg:tags":[
        "refinishing",
        "furniture"
    ],
    "wof:name":"Strip Shop",
    "wof:placetype":"venue"
},
  "geometry": {"coordinates":[-87.5706,33.208238],"type":"Point"}
}