{
  "type": "Feature",
  "properties": {
    "iso:country":"US",
    "sg:address":"66 Continuation St",
    "sg:city":"Pittsview",
    "sg:classifiers":[
        {
            "category":"Organizations",
            "subcategory":"Religious Organization",
            "type":"Services"
        }
    ],
    "sg:phone":"+1 334 616 7300",
    "sg:postcode":"36871",
    "sg:province":"AL",
    "sg:tags":[
        "place",
        "worship",
        "church"
    ],
    "wof:name":"Saint John Ame Church",
    "wof:placetype":"venue"
},
  "geometry": {"coordinates":[-85.17152,32.125065],"type":"Point"}
}