{
  "type": "Feature",
  "properties": {
    "iso:country":"US",
    "sg:address":"1580 Patton Chapel Rd",
    "sg:city":"Birmingham",
    "sg:classifiers":[
        {
            "category":"Education",
            "subcategory":"School",
            "type":"Public Place"
        }
    ],
    "sg:phone":"+1 205 439 2600",
    "sg:postcode":"35226",
    "sg:province":"AL",
    "wof:name":"Harriette W Gwin Elementary",
    "wof:placetype":"venue"
},
  "geometry": {"coordinates":[-86.829735,33.387069],"type":"Point"}
}