{
  "type": "Feature",
  "properties": {
    "iso:country":"US",
    "sg:address":"2864 S Brannon Stand Rd",
    "sg:city":"Dothan",
    "sg:classifiers":[
        {
            "category":"Organizations",
            "subcategory":"Religious Organization",
            "type":"Services"
        }
    ],
    "sg:phone":"+1 334 792 4842",
    "sg:postcode":"36305",
    "sg:province":"AL",
    "sg:tags":[
        "church"
    ],
    "sg:website":"www.mtgilead.com",
    "wof:name":"Mount Gilead Baptist Church",
    "wof:placetype":"venue"
},
  "geometry": {"coordinates":[-85.480054,31.200581],"type":"Point"}
}