{
  "type": "Feature",
  "properties": {
    "addr:full":"269 Friendship Church Rd Reform AL 35481",
    "addr:housenumber":"269",
    "addr:postcode":"35481",
    "addr:street":"Friendship Church Rd",
    "iso:country":"US",
    "sg:address":"269 Friendship Church Rd",
    "sg:city":"Reform",
    "sg:classifiers":[
        {
            "category":"Shopping",
            "subcategory":"Florist",
            "type":"Retail Goods"
        },
        {
            "category":"Building & Trades",
            "subcategory":"Landscaping Services",
            "type":"Services"
        }
    ],
    "sg:phone":"+1 205 375 8241",
    "sg:postcode":"35481",
    "sg:province":"AL",
    "wof:name":"Friendship Florist & Grnhse",
    "wof:placetype":"venue"
},
  "geometry": {"coordinates":[-88.010408,33.435391],"type":"Point"}
}