{
  "type": "Feature",
  "properties": {
    "addr:full":"2804 Opelika Rd Phenix City AL 36870",
    "addr:housenumber":"2804",
    "addr:postcode":"36870",
    "addr:street":"Opelika Rd Phenix",
    "iso:country":"US",
    "sg:address":"2804 Opelika Rd",
    "sg:city":"Phenix City",
    "sg:classifiers":[
        {
            "category":"Mining & Drilling",
            "type":"Manufacturing & Wholesale Goods"
        }
    ],
    "sg:phone":"+1 334 298 3275",
    "sg:postcode":"36870",
    "sg:province":"AL",
    "sg:tags":[
        "construction"
    ],
    "wof:name":"Dykes & Son Paving",
    "wof:placetype":"venue"
},
  "geometry": {"coordinates":[-85.047934,32.493637],"type":"Point"}
}