{
  "type": "Feature",
  "properties": {
    "addr:full":"3093 Allison-Bonnett Memorial Dr Hueytown AL 35023",
    "addr:housenumber":"3093",
    "addr:postcode":"35023",
    "addr:street":"Allison-Bonnett Memorial Dr",
    "iso:country":"US",
    "sg:address":"3093 Allison-Bonnett Memorial Dr",
    "sg:city":"Hueytown",
    "sg:classifiers":[
        {
            "category":"Building & Trades",
            "subcategory":"Plumbing",
            "type":"Services"
        }
    ],
    "sg:phone":"+1 205 491 2861",
    "sg:postcode":"35023",
    "sg:province":"AL",
    "sg:tags":[
        "plumbing",
        "contractor"
    ],
    "wof:name":"Darden Co",
    "wof:placetype":"venue"
},
  "geometry": {"coordinates":[-86.988231,33.453995],"type":"Point"}
}