{
  "type": "Feature",
  "properties": {
    "iso:country":"US",
    "sg:address":"715 Co Rd 10",
    "sg:city":"Auburn",
    "sg:classifiers":[
        {
            "category":"Building & Trades",
            "subcategory":"Construction",
            "type":"Services"
        }
    ],
    "sg:phone":"+1 334 750 1234",
    "sg:postcode":"36830",
    "sg:province":"AL",
    "sg:tags":[
        "home",
        "improvement"
    ],
    "wof:name":"Custom Services",
    "wof:placetype":"venue"
},
  "geometry": {"coordinates":[-85.508583,32.538965],"type":"Point"}
}