{
  "type": "Feature",
  "properties": {
    "addr:full":"3600 Richard Arrington Jr Blvd N Birmingham AL 35234",
    "addr:housenumber":"3600",
    "addr:postcode":"35234",
    "addr:street":"Richard Arrington Jr Blvd N",
    "iso:country":"US",
    "sg:address":"3600 Richard Arrington Jr Blvd N",
    "sg:city":"Birmingham",
    "sg:classifiers":[
        {
            "category":"Building & Trades",
            "subcategory":"Electrical",
            "type":"Services"
        }
    ],
    "sg:phone":"+1 205 323 0108",
    "sg:postcode":"35234",
    "sg:province":"AL",
    "sg:tags":[
        "electric",
        "contractor"
    ],
    "wof:name":"Craig's Electrical Svc",
    "wof:placetype":"venue"
},
  "geometry": {"coordinates":[-86.787359,33.5362],"type":"Point"}
}