{
  "type": "Feature",
  "properties": {
    "iso:country":"US",
    "sg:address":"402 Cox Creek Pkwy",
    "sg:city":"Florence",
    "sg:classifiers":[
        {
            "category":"Banks & Credit Unions",
            "subcategory":"Bank",
            "type":"Services"
        }
    ],
    "sg:phone":"+1 256 767 8585",
    "sg:postcode":"35630",
    "sg:province":"AL",
    "sg:website":"www.suntrust.com",
    "wof:name":"Sun Trust Bank",
    "wof:placetype":"venue"
},
  "geometry": {"coordinates":[-87.642048,34.843163],"type":"Point"}
}