{
  "type": "Feature",
  "properties": {
    "iso:country":"US",
    "sg:address":"3740 Marie Cook Dr",
    "sg:city":"Montgomery",
    "sg:classifiers":[
        {
            "category":"Farming",
            "subcategory":"Livestock Farm",
            "type":"Manufacturing & Wholesale Goods"
        }
    ],
    "sg:phone":"+1 334 272 0512",
    "sg:postcode":"36109",
    "sg:province":"AL",
    "sg:tags":[
        "beef",
        "feedlot",
        "cattle"
    ],
    "wof:name":"Woodrow Vaughan",
    "wof:placetype":"venue"
},
  "geometry": {"coordinates":[-86.246723,32.395496],"type":"Point"}
}