{
  "type": "Feature",
  "properties": {
    "iso:country":"US",
    "sg:address":"2017 3rd Ave N",
    "sg:city":"Birmingham",
    "sg:classifiers":[
        {
            "category":"Social Services",
            "subcategory":"Job Training",
            "type":"Services"
        }
    ],
    "sg:phone":"+1 205 326 3351",
    "sg:postcode":"35203",
    "sg:province":"AL",
    "sg:tags":[
        "rehabilitation"
    ],
    "wof:name":"William A Crunk",
    "wof:placetype":"venue"
},
  "geometry": {"coordinates":[-86.80567000000001,33.51678],"type":"Point"}
}