{
  "type": "Feature",
  "properties": {
    "iso:country":"US",
    "sg:address":"501 Memorial Pkwy NW",
    "sg:city":"Huntsville",
    "sg:classifiers":[
        {
            "category":"Wholesale",
            "subcategory":"Office Equipment",
            "type":"Manufacturing & Wholesale Goods"
        }
    ],
    "sg:phone":"+1 256 512 0067",
    "sg:postcode":"35801",
    "sg:province":"AL",
    "sg:tags":[
        "machine",
        "duplicating",
        "copying"
    ],
    "wof:name":"Economy Copier Svc",
    "wof:placetype":"venue"
},
  "geometry": {"coordinates":[-86.598172,34.735137],"type":"Point"}
}