{
  "type": "Feature",
  "properties": {
    "addr:full":"11216 Big Hurricane Rd Brookwood AL 35444",
    "addr:housenumber":"11216",
    "addr:postcode":"35444",
    "addr:street":"Big Hurricane Rd",
    "iso:country":"US",
    "sg:address":"11216 Big Hurricane Rd",
    "sg:city":"Brookwood",
    "sg:classifiers":[
        {
            "category":"Organizations",
            "subcategory":"Religious Organization",
            "type":"Services"
        }
    ],
    "sg:phone":"+1 205 556 0870",
    "sg:postcode":"35444",
    "sg:province":"AL",
    "sg:tags":[
        "church"
    ],
    "wof:name":"Big Hurricane Baptist Church",
    "wof:placetype":"venue"
},
  "geometry": {"coordinates":[-87.32226300000001,33.228624],"type":"Point"}
}