{
  "type": "Feature",
  "properties": {
    "iso:country":"US",
    "sg:address":"174 W Valley Ave",
    "sg:city":"Homewood",
    "sg:classifiers":[
        {
            "category":"Wholesale",
            "subcategory":"Construction Materials",
            "type":"Manufacturing & Wholesale Goods"
        }
    ],
    "sg:phone":"+1 205 942 3233",
    "sg:postcode":"35209",
    "sg:province":"AL",
    "sg:tags":[
        "granite"
    ],
    "wof:name":"Granite Design",
    "wof:placetype":"venue"
},
  "geometry": {"coordinates":[-86.838346,33.464609],"type":"Point"}
}