{
  "type": "Feature",
  "properties": {
    "addr:full":"965 S Memorial Dr Prattville AL 36067",
    "addr:housenumber":"965",
    "addr:postcode":"36067",
    "addr:street":"S Memorial Dr",
    "iso:country":"US",
    "sg:address":"965 S Memorial Dr",
    "sg:city":"Prattville",
    "sg:classifiers":[
        {
            "category":"Retail",
            "subcategory":"Veterinary Services",
            "type":"Services"
        },
        {
            "category":"Retail",
            "subcategory":"Animal Services",
            "type":"Services"
        }
    ],
    "sg:phone":"+1 334 365 3830",
    "sg:postcode":"36067",
    "sg:province":"AL",
    "sg:tags":[
        "veterinarian"
    ],
    "wof:name":"Animal Care Center",
    "wof:placetype":"venue"
},
  "geometry": {"coordinates":[-86.447626,32.456576],"type":"Point"}
}