{
  "type": "Feature",
  "properties": {
    "iso:country":"US",
    "sg:address":"320 Co Rd 638",
    "sg:city":"Roanoke",
    "sg:classifiers":[
        {
            "category":"Retail",
            "subcategory":"Auto Repair",
            "type":"Services"
        }
    ],
    "sg:phone":"+1 334 863 6512",
    "sg:postcode":"36274",
    "sg:province":"AL",
    "sg:tags":[
        "body",
        "automobile",
        "painting"
    ],
    "wof:name":"Wendell's Body Shop",
    "wof:placetype":"venue"
},
  "geometry": {"coordinates":[-85.314439,33.229164],"type":"Point"}
}