{
  "type": "Feature",
  "properties": {
    "iso:country":"US",
    "sg:address":"8577 State Hwy 22",
    "sg:city":"Selma",
    "sg:classifiers":[
        {
            "category":"Government",
            "subcategory":"Fire Station",
            "type":"Public Place"
        }
    ],
    "sg:phone":"+1 334 875 3600",
    "sg:postcode":"36701",
    "sg:province":"AL",
    "sg:tags":[
        "department"
    ],
    "wof:name":"Valley Grande Volunteer Fire",
    "wof:placetype":"venue"
},
  "geometry": {"coordinates":[-86.98183,32.524358],"type":"Point"}
}