{
  "type": "Feature",
  "properties": {
    "iso:country":"US",
    "sg:address":"1354 Mardis Mill Rd",
    "sg:city":"Blountsville",
    "sg:classifiers":[
        {
            "category":"Organizations",
            "subcategory":"Religious Organization",
            "type":"Services"
        }
    ],
    "sg:phone":"+1 205 429 3929",
    "sg:postcode":"35031",
    "sg:province":"AL",
    "wof:name":"Flon Missions Inc",
    "wof:placetype":"venue"
},
  "geometry": {"coordinates":[-86.56085400000001,34.057688],"type":"Point"}
}