{
  "type": "Feature",
  "properties": {
    "iso:country":"US",
    "sg:address":"308 Oak St",
    "sg:city":"Tuscumbia",
    "sg:classifiers":[
        {
            "category":"Organizations",
            "subcategory":"Religious Organization",
            "type":"Services"
        }
    ],
    "sg:phone":"+1 256 381 2388",
    "sg:postcode":"35674",
    "sg:province":"AL",
    "sg:tags":[
        "church"
    ],
    "wof:name":"Sweetwater Baptist Church",
    "wof:placetype":"venue"
},
  "geometry": {"coordinates":[-87.6843,34.73552],"type":"Point"}
}