{
  "type": "Feature",
  "properties": {
    "iso:country":"US",
    "sg:address":"3935 Reeves St",
    "sg:city":"Dothan",
    "sg:classifiers":[
        {
            "category":"Home & Garden",
            "subcategory":"Building Materials",
            "type":"Retail Goods"
        }
    ],
    "sg:phone":"+1 334 678 9295",
    "sg:postcode":"36303",
    "sg:province":"AL",
    "sg:tags":[
        "glass",
        "window",
        "plate"
    ],
    "wof:name":"Glazing Contractors",
    "wof:placetype":"venue"
},
  "geometry": {"coordinates":[-85.372353,31.277027],"type":"Point"}
}