{
  "type": "Feature",
  "properties": {
    "iso:country":"US",
    "sg:address":"5371 State Rte 67",
    "sg:city":"Somerville",
    "sg:classifiers":[
        {
            "category":"Local Transit",
            "type":"Transportation"
        }
    ],
    "sg:phone":"+1 256 778 9900",
    "sg:postcode":"35670",
    "sg:province":"AL",
    "sg:tags":[
        "passenger"
    ],
    "wof:name":"Station 2",
    "wof:placetype":"venue"
},
  "geometry": {"coordinates":[-86.755077,34.445279],"type":"Point"}
}