{
  "type": "Feature",
  "properties": {
    "addr:full":"900 Williams Ave NE Fort Payne AL 35967",
    "addr:housenumber":"900",
    "addr:postcode":"35967",
    "addr:street":"Williams Ave Ne",
    "iso:country":"US",
    "sg:address":"900 Williams Ave NE",
    "sg:city":"Fort Payne",
    "sg:classifiers":[
        {
            "category":"Wholesale",
            "subcategory":"Toys & Hobbies",
            "type":"Manufacturing & Wholesale Goods"
        }
    ],
    "sg:phone":"+1 256 845 2950",
    "sg:postcode":"35967",
    "sg:province":"AL",
    "sg:tags":[
        "wholesaler"
    ],
    "wof:name":"C J's Wholesale",
    "wof:placetype":"venue"
},
  "geometry": {"coordinates":[-85.683263,34.480241],"type":"Point"}
}