{
  "type": "Feature",
  "properties": {
    "iso:country":"US",
    "sg:address":"12648 Jessie Jackson Pkwy",
    "sg:city":"Courtland",
    "sg:classifiers":[
        {
            "category":"Health Services",
            "subcategory":"Health Practitioner",
            "type":"Services"
        }
    ],
    "sg:phone":"+1 256 637 2126",
    "sg:postcode":"35618",
    "sg:province":"AL",
    "sg:tags":[
        "nutritionist"
    ],
    "wof:name":"North Courtland Nutrition Ctr",
    "wof:placetype":"venue"
},
  "geometry": {"coordinates":[-87.308817,34.677249],"type":"Point"}
}