{
  "type": "Feature",
  "properties": {
    "addr:full":"2555 Dauphin St Mobile AL 36606",
    "addr:housenumber":"2555",
    "addr:postcode":"36606",
    "addr:street":"Dauphin St",
    "iso:country":"US",
    "sg:address":"2555 Dauphin St",
    "sg:city":"Mobile",
    "sg:classifiers":[
        {
            "category":"Real Estate",
            "subcategory":"Real Estate Agent",
            "type":"Services"
        }
    ],
    "sg:phone":"+1 251 479 5033",
    "sg:postcode":"36606",
    "sg:province":"AL",
    "sg:tags":[
        "house",
        "construct"
    ],
    "wof:name":"Gandy Agency",
    "wof:placetype":"venue"
},
  "geometry": {"coordinates":[-88.100618,30.687362],"type":"Point"}
}