{
  "type": "Feature",
  "properties": {
    "iso:country":"US",
    "sg:address":"1437 Shady Ln NE",
    "sg:city":"Arab",
    "sg:classifiers":[
        {
            "category":"Professional",
            "subcategory":"Management & Consulting",
            "type":"Services"
        }
    ],
    "sg:phone":"+1 256 931 7026",
    "sg:postcode":"35016",
    "sg:province":"AL",
    "sg:tags":[
        "business"
    ],
    "wof:name":"JB Consultants",
    "wof:placetype":"venue"
},
  "geometry": {"coordinates":[-86.472049,34.340936],"type":"Point"}
}