{
  "type": "Feature",
  "properties": {
    "iso:country":"US",
    "sg:address":"420 Quintard Ave",
    "sg:city":"Anniston",
    "sg:classifiers":[
        {
            "category":"Autos & Motor Vehicles",
            "subcategory":"Automobile Sales",
            "type":"Retail Goods"
        }
    ],
    "sg:phone":"+1 256 236 4444",
    "sg:postcode":"36201",
    "sg:province":"AL",
    "sg:tags":[
        "car",
        "dealer"
    ],
    "sg:website":"www.ron-newton.com",
    "wof:name":"Newton Pontiac-CADILLAC GMC",
    "wof:placetype":"venue"
},
  "geometry": {"coordinates":[-85.82684999999999,33.65044],"type":"Point"}
}