{
  "type": "Feature",
  "properties": {
    "iso:country":"US",
    "sg:address":"5457 Tyler Loop Rd",
    "sg:city":"Pinson",
    "sg:classifiers":[
        {
            "category":"Manufacturing",
            "subcategory":"Toys & Sporting Goods",
            "type":"Manufacturing & Wholesale Goods"
        }
    ],
    "sg:phone":"+1 205 854 2817",
    "sg:postcode":"35126",
    "sg:province":"AL",
    "sg:tags":[
        "stuffed",
        "doll"
    ],
    "wof:name":"Across The Tracks",
    "wof:placetype":"venue"
},
  "geometry": {"coordinates":[-86.650584,33.660289],"type":"Point"}
}