{
  "type": "Feature",
  "properties": {
    "iso:country":"US",
    "sg:address":"835 Snow St",
    "sg:city":"Oxford",
    "sg:classifiers":[
        {
            "category":"Autos & Motor Vehicles",
            "subcategory":"Automobile Sales",
            "type":"Retail Goods"
        }
    ],
    "sg:phone":"+1 256 835 6818",
    "sg:postcode":"36203",
    "sg:province":"AL",
    "sg:tags":[
        "car",
        "dealer"
    ],
    "wof:name":"Davis Auto Sales",
    "wof:placetype":"venue"
},
  "geometry": {"coordinates":[-85.822698,33.615313],"type":"Point"}
}