{
  "type": "Feature",
  "properties": {
    "addr:full":"206 Stephens St York AL 36925",
    "addr:housenumber":"206",
    "addr:postcode":"36925",
    "addr:street":"Stephens St",
    "iso:country":"US",
    "sg:address":"206 Stephens St",
    "sg:city":"York",
    "sg:classifiers":[
        {
            "category":"Wholesale",
            "subcategory":"Hardware",
            "type":"Manufacturing & Wholesale Goods"
        }
    ],
    "sg:phone":"+1 205 392 4808",
    "sg:postcode":"36925",
    "sg:province":"AL",
    "sg:tags":[
        "equipment",
        "heating",
        "system"
    ],
    "wof:name":"Ferrelgas",
    "wof:placetype":"venue"
},
  "geometry": {"coordinates":[-88.298965,32.485929],"type":"Point"}
}