{
  "type": "Feature",
  "properties": {
    "addr:full":"1333 Five Mile Rd Birmingham AL 35215",
    "addr:housenumber":"1333",
    "addr:postcode":"35215",
    "addr:street":"Five Mile Rd",
    "iso:country":"US",
    "sg:address":"1333 Five Mile Rd",
    "sg:city":"Birmingham",
    "sg:classifiers":[
        {
            "category":"Wholesale",
            "subcategory":"Vending Machines",
            "type":"Manufacturing & Wholesale Goods"
        }
    ],
    "sg:phone":"+1 205 856 5655",
    "sg:postcode":"35215",
    "sg:province":"AL",
    "sg:tags":[
        "operator"
    ],
    "wof:name":"Triple CCC Vending",
    "wof:placetype":"venue"
},
  "geometry": {"coordinates":[-86.694024,33.614635],"type":"Point"}
}