{
  "type": "Feature",
  "properties": {
    "addr:full":"8760 Hall Rd Grand Bay AL 36541",
    "addr:housenumber":"8760",
    "addr:postcode":"36541",
    "addr:street":"Hall Rd",
    "iso:country":"US",
    "sg:address":"8760 Hall Rd",
    "sg:city":"Grand Bay",
    "sg:classifiers":[
        {
            "category":"Building & Trades",
            "subcategory":"Plumbing",
            "type":"Services"
        }
    ],
    "sg:phone":"+1 251 865 0181",
    "sg:postcode":"36541",
    "sg:province":"AL",
    "sg:tags":[
        "conditioning",
        "air",
        "system",
        "contractor"
    ],
    "wof:name":"Kenneth Blackwell & Assoc Inc",
    "wof:placetype":"venue"
},
  "geometry": {"coordinates":[-88.381452,30.507066],"type":"Point"}
}