{
  "type": "Feature",
  "properties": {
    "addr:full":"54 McFarland Blvd Northport AL 35476",
    "addr:housenumber":"54",
    "addr:postcode":"35476",
    "addr:street":"Mcfarland Blvd",
    "iso:country":"US",
    "sg:address":"54 McFarland Blvd",
    "sg:city":"Northport",
    "sg:classifiers":[
        {
            "category":"Banks & Credit Unions",
            "subcategory":"Bank",
            "type":"Services"
        }
    ],
    "sg:phone":"+1 205 752 2744",
    "sg:postcode":"35476",
    "sg:province":"AL",
    "wof:name":"First National Bank",
    "wof:placetype":"venue"
},
  "geometry": {"coordinates":[-87.554064,33.236499],"type":"Point"}
}