{
  "type": "Feature",
  "properties": {
    "iso:country":"US",
    "sg:address":"1334 Washington St NW",
    "sg:city":"Huntsville",
    "sg:classifiers":[
        {
            "category":"Insurance",
            "subcategory":"Insurance Agent",
            "type":"Services"
        }
    ],
    "sg:phone":"+1 256 533 1200",
    "sg:postcode":"35801",
    "sg:province":"AL",
    "wof:name":"Allstate Insurance",
    "wof:placetype":"venue"
},
  "geometry": {"coordinates":[-86.588511,34.74852],"type":"Point"}
}