{
  "type": "Feature",
  "properties": {
    "addr:full":"22170 Pine St Robertsdale AL 36567",
    "addr:housenumber":"22170",
    "addr:postcode":"36567",
    "addr:street":"Pine St",
    "iso:country":"US",
    "sg:address":"22170 Pine St",
    "sg:city":"Robertsdale",
    "sg:classifiers":[
        {
            "category":"Social Services",
            "subcategory":"Child Care",
            "type":"Services"
        }
    ],
    "sg:phone":"+1 251 947 6155",
    "sg:postcode":"36567",
    "sg:province":"AL",
    "sg:tags":[
        "day"
    ],
    "wof:name":"Glenda's Day Care",
    "wof:placetype":"venue"
},
  "geometry": {"coordinates":[-87.70711799999999,30.547477],"type":"Point"}
}