{
  "type": "Feature",
  "properties": {
    "iso:country":"US",
    "sg:address":"2106 N Hills Dr",
    "sg:city":"Opelika",
    "sg:classifiers":[
        {
            "category":"Professional",
            "subcategory":"Detective & Security Services",
            "type":"Services"
        }
    ],
    "sg:phone":"+1 334 501 3149",
    "sg:postcode":"36801",
    "sg:province":"AL",
    "sg:tags":[
        "guard"
    ],
    "wof:name":"Randy M Armstrong",
    "wof:placetype":"venue"
},
  "geometry": {"coordinates":[-85.385841,32.676335],"type":"Point"}
}