{
  "type": "Feature",
  "properties": {
    "addr:full":"194 State Rte 195 Jasper AL 35503",
    "addr:housenumber":"194",
    "addr:postcode":"35503",
    "addr:street":"State Rte 195",
    "iso:country":"US",
    "sg:address":"194 State Rte 195",
    "sg:city":"Jasper",
    "sg:classifiers":[
        {
            "category":"Shopping",
            "subcategory":"Gifts & Souvenirs",
            "type":"Retail Goods"
        }
    ],
    "sg:phone":"+1 205 221 3806",
    "sg:postcode":"35503",
    "sg:province":"AL",
    "wof:name":"Kountry Kuzins",
    "wof:placetype":"venue"
},
  "geometry": {"coordinates":[-87.287925,33.853236],"type":"Point"}
}