{
  "type": "Feature",
  "properties": {
    "iso:country":"US",
    "sg:address":"13191 State Hwy 160",
    "sg:city":"Cleveland",
    "sg:classifiers":[
        {
            "category":"Home & Garden",
            "subcategory":"Garden Supply",
            "type":"Retail Goods"
        }
    ],
    "sg:phone":"+1 205 559 8280",
    "sg:postcode":"35049",
    "sg:province":"AL",
    "sg:tags":[
        "nurseryman"
    ],
    "wof:name":"M & M Nursery",
    "wof:placetype":"venue"
},
  "geometry": {"coordinates":[-86.653627,33.960273],"type":"Point"}
}