{
  "type": "Feature",
  "properties": {
    "addr:full":"15487 State Rte 71 Pisgah AL 35765",
    "addr:housenumber":"15487",
    "addr:postcode":"35765",
    "addr:street":"State Rte 71 Pisgah",
    "iso:country":"US",
    "sg:address":"15487 State Rte 71",
    "sg:city":"Pisgah",
    "sg:classifiers":[
        {
            "category":"Shopping",
            "subcategory":"Catalog Store",
            "type":"Retail Goods"
        }
    ],
    "sg:phone":"+1 256 451 1095",
    "sg:postcode":"35765",
    "sg:province":"AL",
    "sg:tags":[
        "showroom"
    ],
    "wof:name":"This & That II",
    "wof:placetype":"venue"
},
  "geometry": {"coordinates":[-85.762732,34.702754],"type":"Point"}
}