{
  "type": "Feature",
  "properties": {
    "iso:country":"US",
    "sg:address":"951 1st Ave W",
    "sg:city":"Alabaster",
    "sg:classifiers":[
        {
            "category":"Professional",
            "subcategory":"Accounting & Tax Preparation",
            "type":"Services"
        }
    ],
    "sg:phone":"+1 205 685 0507",
    "sg:postcode":"35007",
    "sg:province":"AL",
    "sg:tags":[
        "bookkeeping",
        "general"
    ],
    "wof:name":"Harper Tax Svc",
    "wof:placetype":"venue"
},
  "geometry": {"coordinates":[-86.827806,33.244188],"type":"Point"}
}