{
  "type": "Feature",
  "properties": {
    "iso:country":"US",
    "sg:address":"7145 State Rte 65",
    "sg:city":"Trenton",
    "sg:classifiers":[
        {
            "category":"Personal",
            "type":"Services"
        }
    ],
    "sg:phone":"+1 256 776 2931",
    "sg:postcode":"35774",
    "sg:province":"AL",
    "wof:name":"New Idea Home Improvments",
    "wof:placetype":"venue"
},
  "geometry": {"coordinates":[-86.25223800000001,34.744614],"type":"Point"}
}