{
  "type": "Feature",
  "properties": {
    "addr:full":"3045 Woodley Rd Montgomery AL 36116",
    "addr:housenumber":"3045",
    "addr:postcode":"36116",
    "addr:street":"Woodley Rd",
    "iso:country":"US",
    "sg:address":"3045 Woodley Rd",
    "sg:city":"Montgomery",
    "sg:classifiers":[
        {
            "category":"Personal",
            "subcategory":"Barber",
            "type":"Services"
        }
    ],
    "sg:phone":"+1 334 288 6855",
    "sg:postcode":"36116",
    "sg:province":"AL",
    "sg:tags":[
        "shop"
    ],
    "wof:name":"A J's Haircuts & Style",
    "wof:placetype":"venue"
},
  "geometry": {"coordinates":[-86.264707,32.327083],"type":"Point"}
}