{
  "type": "Feature",
  "properties": {
    "iso:country":"US",
    "sg:address":"31380 US Hwy 431",
    "sg:city":"Five Points",
    "sg:classifiers":[
        {
            "category":"Wholesale",
            "subcategory":"Construction Materials",
            "type":"Manufacturing & Wholesale Goods"
        }
    ],
    "sg:phone":"+1 334 864 0014",
    "sg:postcode":"36855",
    "sg:province":"AL",
    "sg:tags":[
        "timberland",
        "company",
        "timber"
    ],
    "wof:name":"Baseline Forest Svc Inc",
    "wof:placetype":"venue"
},
  "geometry": {"coordinates":[-85.33529900000001,33.071014],"type":"Point"}
}