{
  "type": "Feature",
  "properties": {
    "iso:country":"US",
    "sg:address":"226 N Sequoia Blvd",
    "sg:city":"Florence",
    "sg:classifiers":[
        {
            "category":"Retail",
            "subcategory":"Laundry & Dry Cleaning",
            "type":"Services"
        }
    ],
    "sg:phone":"+1 256 767 4227",
    "sg:postcode":"35630",
    "sg:province":"AL",
    "sg:tags":[
        "cleaners",
        "rug",
        "carpet"
    ],
    "wof:name":"Taylor's Carpet & Upholstery",
    "wof:placetype":"venue"
},
  "geometry": {"coordinates":[-87.659137,34.837927],"type":"Point"}
}