{
  "type": "Feature",
  "properties": {
    "iso:country":"US",
    "sg:address":"605 Smith Ave",
    "sg:city":"Elba",
    "sg:classifiers":[
        {
            "category":"Professional",
            "type":"Services"
        }
    ],
    "sg:phone":"+1 334 897 0134",
    "sg:postcode":"36323",
    "sg:province":"AL",
    "wof:name":"Kenneth Hughes",
    "wof:placetype":"venue"
},
  "geometry": {"coordinates":[-86.059034,31.419986],"type":"Point"}
}