{
  "type": "Feature",
  "properties": {
    "addr:full":"912 Highland Ave Selma AL 36701",
    "addr:housenumber":"912",
    "addr:postcode":"36701",
    "addr:street":"Highland Ave",
    "iso:country":"US",
    "sg:address":"912 Highland Ave",
    "sg:city":"Selma",
    "sg:classifiers":[
        {
            "category":"Professional",
            "subcategory":"Employment Agencies",
            "type":"Services"
        }
    ],
    "sg:phone":"+1 334 875 6680",
    "sg:postcode":"36701",
    "sg:province":"AL",
    "sg:tags":[
        "opportunity"
    ],
    "wof:name":"Manpower Temporary Svc",
    "wof:placetype":"venue"
},
  "geometry": {"coordinates":[-87.026151,32.43119],"type":"Point"}
}