{
  "type": "Feature",
  "properties": {
    "addr:full":"407 Beltline Rd SW Decatur AL 35601",
    "addr:housenumber":"407",
    "addr:postcode":"35601",
    "addr:street":"Beltline Rd Sw",
    "iso:country":"US",
    "sg:address":"407 Beltline Rd SW",
    "sg:city":"Decatur",
    "sg:classifiers":[
        {
            "category":"Bars & Pubs",
            "type":"Food & Drink"
        },
        {
            "category":"Restaurant",
            "type":"Food & Drink"
        }
    ],
    "sg:menulink":"http://www.allmenus.com/al/decatur/34518-cracker-barrel-old-country-store/menu/",
    "sg:phone":"+1 256 350 6263",
    "sg:postcode":"35601",
    "sg:province":"AL",
    "sg:tags":[
        "american",
        "southern"
    ],
    "wof:name":"Cracker Barrel Old Country Store",
    "wof:placetype":"venue"
},
  "geometry": {"coordinates":[-86.99073799999999,34.559881],"type":"Point"}
}