{
  "type": "Feature",
  "properties": {
    "iso:country":"US",
    "sg:address":"205 W Martin Luther King Hwy",
    "sg:city":"Tuskegee",
    "sg:classifiers":[
        {
            "category":"Bus Station",
            "type":"Transportation"
        }
    ],
    "sg:phone":"+1 334 727 1290",
    "sg:postcode":"36083",
    "sg:province":"AL",
    "sg:tags":[
        "facility"
    ],
    "wof:name":"Greyhound Bus Station",
    "wof:placetype":"venue"
},
  "geometry": {"coordinates":[-85.691505,32.422924],"type":"Point"}
}