{
  "type": "Feature",
  "properties": {
    "iso:country":"US",
    "sg:address":"411 Coliseum Blvd",
    "sg:city":"Montgomery",
    "sg:classifiers":[
        {
            "category":"Government",
            "subcategory":"Post Office",
            "type":"Public Place"
        }
    ],
    "sg:phone":"+1 334 279 3172",
    "sg:postcode":"36109",
    "sg:province":"AL",
    "sg:tags":[
        "postal",
        "us"
    ],
    "wof:name":"Eastbrook Station",
    "wof:placetype":"venue"
},
  "geometry": {"coordinates":[-86.257538,32.390659],"type":"Point"}
}