{
  "type": "Feature",
  "properties": {
    "iso:country":"US",
    "sg:address":"1490 Repoll Rd",
    "sg:city":"Mobile",
    "sg:classifiers":[
        {
            "category":"Personal",
            "subcategory":"Beauty Salon",
            "type":"Services"
        }
    ],
    "sg:phone":"+1 251 634 9786",
    "sg:postcode":"36695",
    "sg:province":"AL",
    "wof:name":"Jamies Hair Studio",
    "wof:placetype":"venue"
},
  "geometry": {"coordinates":[-88.284944,30.660946],"type":"Point"}
}