{
  "type": "Feature",
  "properties": {
    "addr:full":"10900 Gregg Rd Semmes AL 36575",
    "addr:housenumber":"10900",
    "addr:postcode":"36575",
    "addr:street":"Gregg Rd",
    "iso:country":"US",
    "sg:address":"10900 Gregg Rd",
    "sg:city":"Semmes",
    "sg:classifiers":[
        {
            "category":"Building & Trades",
            "subcategory":"Construction",
            "type":"Services"
        }
    ],
    "sg:phone":"+1 251 649 2962",
    "sg:postcode":"36575",
    "sg:province":"AL",
    "sg:tags":[
        "contractor"
    ],
    "wof:name":"T Southern Masonry",
    "wof:placetype":"venue"
},
  "geometry": {"coordinates":[-88.300192,30.784177],"type":"Point"}
}