{
  "type": "Feature",
  "properties": {
    "iso:country":"US",
    "sg:address":"1803 Shirt Tail Bend Rd",
    "sg:city":"New Hope",
    "sg:classifiers":[
        {
            "category":"Building & Trades",
            "subcategory":"Construction",
            "type":"Services"
        }
    ],
    "sg:phone":"+1 256 723 4503",
    "sg:postcode":"35760",
    "sg:province":"AL",
    "sg:tags":[
        "house"
    ],
    "wof:name":"McDonald Const",
    "wof:placetype":"venue"
},
  "geometry": {"coordinates":[-86.351387,34.505655],"type":"Point"}
}