{
  "type": "Feature",
  "properties": {
    "addr:full":"210 Lakeforest Dothan AL 36301",
    "addr:housenumber":"210",
    "addr:postcode":"36301",
    "addr:street":"Lakeforest",
    "iso:country":"US",
    "sg:address":"210 Lakeforest",
    "sg:city":"Dothan",
    "sg:classifiers":[
        {
            "category":"Education",
            "subcategory":"Library",
            "type":"Public Place"
        }
    ],
    "sg:phone":"+1 334 794 9790",
    "sg:postcode":"36301",
    "sg:province":"AL",
    "wof:name":"Billy Branch & Virginia",
    "wof:placetype":"venue"
},
  "geometry": {"coordinates":[-85.420436,31.180719],"type":"Point"}
}