{
  "type": "Feature",
  "properties": {
    "iso:country":"US",
    "sg:address":"1007 Goodyear Ave",
    "sg:city":"Gadsden",
    "sg:classifiers":[
        {
            "category":"Professional",
            "type":"Services"
        }
    ],
    "sg:phone":"+1 256 494 9894",
    "sg:postcode":"35903",
    "sg:province":"AL",
    "wof:name":"Emergency Room Office",
    "wof:placetype":"venue"
},
  "geometry": {"coordinates":[-85.971035,34.009362],"type":"Point"}
}