{
  "type": "Feature",
  "properties": {
    "iso:country":"US",
    "sg:address":"399 Azalea Rd",
    "sg:city":"Mobile",
    "sg:classifiers":[
        {
            "category":"Autos & Motor Vehicles",
            "subcategory":"Fuel & Gas Station",
            "type":"Retail Goods"
        }
    ],
    "sg:phone":"+1 251 316 0095",
    "sg:postcode":"36609",
    "sg:province":"AL",
    "sg:tags":[
        "oil"
    ],
    "wof:name":"Azalea Road Chevron",
    "wof:placetype":"venue"
},
  "geometry": {"coordinates":[-88.150262,30.670181],"type":"Point"}
}