{
  "type": "Feature",
  "properties": {
    "addr:full":"4735 Norrel Dr Trussville AL 35173",
    "addr:housenumber":"4735",
    "addr:postcode":"35173",
    "addr:street":"Norrel Dr",
    "iso:country":"US",
    "sg:address":"4735 Norrel Dr",
    "sg:city":"Trussville",
    "sg:classifiers":[
        {
            "category":"Sports & Exercise",
            "subcategory":"Gym",
            "type":"Entertainment"
        }
    ],
    "sg:phone":"+1 205 655 4035",
    "sg:postcode":"35173",
    "sg:province":"AL",
    "sg:tags":[
        "club",
        "health",
        "studio",
        "gymnasium"
    ],
    "wof:name":"Curves Of Trussville",
    "wof:placetype":"venue"
},
  "geometry": {"coordinates":[-86.614976,33.639531],"type":"Point"}
}