{
  "type": "Feature",
  "properties": {
    "iso:country":"US",
    "sg:address":"2390 Armstrong Loop",
    "sg:city":"Hayden",
    "sg:classifiers":[
        {
            "category":"Utilities",
            "subcategory":"Refuse",
            "type":"Services"
        }
    ],
    "sg:phone":"+1 205 647 6569",
    "sg:postcode":"35079",
    "sg:province":"AL",
    "sg:tags":[
        "garbage",
        "collection"
    ],
    "wof:name":"Blount County Landfill",
    "wof:placetype":"venue"
},
  "geometry": {"coordinates":[-86.715664,33.892097],"type":"Point"}
}