{
  "type": "Feature",
  "properties": {
    "addr:full":"1427 US Hwy 43 Thomasville AL 36784",
    "addr:housenumber":"1427",
    "addr:postcode":"36784",
    "addr:street":"Us Hwy 43",
    "iso:country":"US",
    "sg:address":"1427 US Hwy 43",
    "sg:city":"Thomasville",
    "sg:phone":"+1 334 636 8246",
    "sg:postcode":"36784",
    "sg:province":"AL",
    "sg:tags":[
        "oil",
        "gasoline"
    ],
    "wof:name":"Merritt Oil Co",
    "wof:placetype":"venue"
},
  "geometry": {"coordinates":[-87.743548,31.894389],"type":"Point"}
}