{
  "type": "Feature",
  "properties": {
    "addr:full":"5200 State Rte 69 Northport AL 35473",
    "addr:housenumber":"5200",
    "addr:postcode":"35473",
    "addr:street":"State Rte 69",
    "iso:country":"US",
    "sg:address":"5200 State Rte 69",
    "sg:city":"Northport",
    "sg:classifiers":[
        {
            "category":"Wholesale",
            "subcategory":"Electrical",
            "type":"Manufacturing & Wholesale Goods"
        }
    ],
    "sg:phone":"+1 205 339 7969",
    "sg:postcode":"35473",
    "sg:province":"AL",
    "sg:tags":[
        "electric",
        "motor"
    ],
    "wof:name":"Ike's Motor Co LLC",
    "wof:placetype":"venue"
},
  "geometry": {"coordinates":[-87.57115899999999,33.257661],"type":"Point"}
}