{
  "type": "Feature",
  "properties": {
    "addr:full":"1732 Shades View Ln Birmingham AL 35216",
    "addr:housenumber":"1732",
    "addr:postcode":"35216",
    "addr:street":"Shades View Ln",
    "iso:country":"US",
    "sg:address":"1732 Shades View Ln",
    "sg:city":"Birmingham",
    "sg:classifiers":[
        {
            "category":"Professional",
            "subcategory":"Computer Services",
            "type":"Services"
        }
    ],
    "sg:phone":"+1 205 823 2800",
    "sg:postcode":"35216",
    "sg:province":"AL",
    "sg:tags":[
        "related"
    ],
    "wof:name":"K L Harrison Consultants Inc",
    "wof:placetype":"venue"
},
  "geometry": {"coordinates":[-86.80290599999999,33.440328],"type":"Point"}
}