{
  "type": "Feature",
  "properties": {
    "addr:full":"426 W College St Florence AL 35630",
    "addr:housenumber":"426",
    "addr:postcode":"35630",
    "addr:street":"W College St",
    "iso:country":"US",
    "sg:address":"426 W College St",
    "sg:city":"Florence",
    "sg:classifiers":[
        {
            "category":"Health Services",
            "subcategory":"Doctor",
            "type":"Services"
        }
    ],
    "sg:phone":"+1 256 718 4041",
    "sg:postcode":"35630",
    "sg:province":"AL",
    "sg:tags":[
        "medical"
    ],
    "wof:name":"Shoals Orthopedics",
    "wof:placetype":"venue"
},
  "geometry": {"coordinates":[-87.68012,34.797286],"type":"Point"}
}