{
  "type": "Feature",
  "properties": {
    "addr:full":"1525 Foster St Montgomery AL 36104",
    "addr:housenumber":"1525",
    "addr:postcode":"36104",
    "addr:street":"Foster St",
    "iso:country":"US",
    "sg:address":"1525 Foster St",
    "sg:city":"Montgomery",
    "sg:classifiers":[
        {
            "category":"Food & Beverages",
            "subcategory":"Groceries & Convenience Stores",
            "type":"Retail Goods"
        }
    ],
    "sg:phone":"+1 334 264 7667",
    "sg:postcode":"36104",
    "sg:province":"AL",
    "wof:name":"S & M Convenience Store",
    "wof:placetype":"venue"
},
  "geometry": {"coordinates":[-86.298078,32.395267],"type":"Point"}
}