{
  "type": "Feature",
  "properties": {
    "iso:country":"US",
    "sg:address":"1860 Warrenton Rd",
    "sg:city":"Guntersville",
    "sg:classifiers":[
        {
            "category":"Farming",
            "subcategory":"Livestock Farm",
            "type":"Manufacturing & Wholesale Goods"
        }
    ],
    "sg:phone":"+1 256 582 8884",
    "sg:postcode":"35976",
    "sg:province":"AL",
    "sg:tags":[
        "beef",
        "feedlot",
        "cattle"
    ],
    "wof:name":"Mike Deck Farms",
    "wof:placetype":"venue"
},
  "geometry": {"coordinates":[-86.36701499999999,34.342215],"type":"Point"}
}