{
  "type": "Feature",
  "properties": {
    "iso:country":"US",
    "sg:address":"3904 Oakwood Dr",
    "sg:city":"Adamsville",
    "sg:classifiers":[
        {
            "category":"Organizations",
            "subcategory":"Religious Organization",
            "type":"Services"
        }
    ],
    "sg:phone":"+1 205 674 6531",
    "sg:postcode":"35005",
    "sg:province":"AL",
    "wof:name":"Midway United Methodist Church",
    "wof:placetype":"venue"
},
  "geometry": {"coordinates":[-86.94307,33.589224],"type":"Point"}
}