{
  "type": "Feature",
  "properties": {
    "addr:full":"212 W Saunders Rd Dothan AL 36301",
    "addr:housenumber":"212",
    "addr:postcode":"36301",
    "addr:street":"W Saunders Rd",
    "iso:country":"US",
    "sg:address":"212 W Saunders Rd",
    "sg:city":"Dothan",
    "sg:classifiers":[
        {
            "category":"Restaurant",
            "type":"Food & Drink"
        }
    ],
    "sg:phone":"+1 334 671 5823",
    "sg:postcode":"36301",
    "sg:province":"AL",
    "sg:tags":[
        "eating"
    ],
    "wof:name":"Papparazzi Italian Eatery",
    "wof:placetype":"venue"
},
  "geometry": {"coordinates":[-85.40424899999999,31.160048],"type":"Point"}
}