{
  "type": "Feature",
  "properties": {
    "iso:country":"US",
    "sg:address":"7740 Union St",
    "sg:city":"Citronelle",
    "sg:classifiers":[
        {
            "category":"Organizations",
            "subcategory":"Religious Organization",
            "type":"Services"
        }
    ],
    "sg:phone":"+1 251 866 7868",
    "sg:postcode":"36522",
    "sg:province":"AL",
    "wof:name":"Whispering Pines Baptist Camp",
    "wof:placetype":"venue"
},
  "geometry": {"coordinates":[-88.223201,31.092196],"type":"Point"}
}