{
  "type": "Feature",
  "properties": {
    "iso:country":"US",
    "sg:address":"205 East St",
    "sg:city":"Athens",
    "sg:classifiers":[
        {
            "category":"Professional",
            "subcategory":"Computer Services",
            "type":"Services"
        }
    ],
    "sg:phone":"+1 256 232 3432",
    "sg:postcode":"35611",
    "sg:province":"AL",
    "sg:tags":[
        "related"
    ],
    "wof:name":"Bengalcore",
    "wof:placetype":"venue"
},
  "geometry": {"coordinates":[-86.965854,34.802115],"type":"Point"}
}