{
  "type": "Feature",
  "properties": {
    "addr:full":"614 Madison St Huntsville AL 35801",
    "addr:housenumber":"614",
    "addr:postcode":"35801",
    "addr:street":"Madison St",
    "iso:country":"US",
    "sg:address":"614 Madison St",
    "sg:city":"Huntsville",
    "sg:classifiers":[
        {
            "category":"Shopping",
            "subcategory":"Used Merchandise",
            "type":"Retail Goods"
        }
    ],
    "sg:phone":"+1 256 539 9803",
    "sg:postcode":"35801",
    "sg:province":"AL",
    "sg:tags":[
        "antique"
    ],
    "wof:name":"Darwin Antiques",
    "wof:placetype":"venue"
},
  "geometry": {"coordinates":[-86.582354,34.725615],"type":"Point"}
}