{
  "type": "Feature",
  "properties": {
    "addr:full":"2712 31st Ave N Birmingham AL 35207",
    "addr:housenumber":"2712",
    "addr:postcode":"35207",
    "addr:street":"31St Ave N",
    "iso:country":"US",
    "sg:address":"2712 31st Ave N",
    "sg:city":"Birmingham",
    "sg:classifiers":[
        {
            "category":"Real Estate",
            "subcategory":"Real Estate Operator",
            "type":"Services"
        }
    ],
    "sg:phone":"+1 205 322 0728",
    "sg:postcode":"35207",
    "sg:province":"AL",
    "sg:tags":[
        "apartment"
    ],
    "wof:name":"Birmingham Towers",
    "wof:placetype":"venue"
},
  "geometry": {"coordinates":[-86.815597,33.553648],"type":"Point"}
}