{
  "type": "Feature",
  "properties": {
    "iso:country":"US",
    "sg:address":"7121 Holtville Rd",
    "sg:city":"Wetumpka",
    "sg:classifiers":[
        {
            "category":"Organizations",
            "subcategory":"Religious Organization",
            "type":"Services"
        }
    ],
    "sg:phone":"+1 334 567 6468",
    "sg:postcode":"36092",
    "sg:province":"AL",
    "sg:tags":[
        "church"
    ],
    "wof:name":"Holtville Riverside Baptist",
    "wof:placetype":"venue"
},
  "geometry": {"coordinates":[-86.276675,32.616718],"type":"Point"}
}