{
  "type": "Feature",
  "properties": {
    "addr:full":"410 Chestnut St Gadsden AL 35901",
    "addr:housenumber":"410",
    "addr:postcode":"35901",
    "addr:street":"Chestnut St",
    "iso:country":"US",
    "sg:address":"410 Chestnut St",
    "sg:city":"Gadsden",
    "sg:classifiers":[
        {
            "category":"Bars & Pubs",
            "type":"Food & Drink"
        }
    ],
    "sg:phone":"+1 256 546 4229",
    "sg:postcode":"35901",
    "sg:province":"AL",
    "sg:tags":[
        "drinking"
    ],
    "wof:name":"Peabodys",
    "wof:placetype":"venue"
},
  "geometry": {"coordinates":[-86.005155,34.01268],"type":"Point"}
}