{
  "type": "Feature",
  "properties": {
    "iso:country":"US",
    "sg:address":"2815 Moseley Hill Rd",
    "sg:city":"Moody",
    "sg:classifiers":[
        {
            "category":"Shopping",
            "type":"Retail Goods"
        }
    ],
    "sg:phone":"+1 205 640 5880",
    "sg:postcode":"35004",
    "sg:province":"AL",
    "sg:tags":[
        "trophy",
        "medal",
        "award"
    ],
    "wof:name":"Frank S Moseley",
    "wof:placetype":"venue"
},
  "geometry": {"coordinates":[-86.506614,33.596705],"type":"Point"}
}