{
  "type": "Feature",
  "properties": {
    "iso:country":"US",
    "sg:address":"101 N Houston St",
    "sg:city":"Athens",
    "sg:classifiers":[
        {
            "category":"Education",
            "subcategory":"Library",
            "type":"Public Place"
        }
    ],
    "sg:phone":"+1 256 233 8770",
    "sg:postcode":"35611",
    "sg:province":"AL",
    "wof:name":"Houston Public Lib & Museum",
    "wof:placetype":"venue"
},
  "geometry": {"coordinates":[-86.974386,34.804625],"type":"Point"}
}