{
  "type": "Feature",
  "properties": {
    "addr:full":"11845 State Rte 25 Calera AL 35040",
    "addr:housenumber":"11845",
    "addr:postcode":"35040",
    "addr:street":"State Rte 25",
    "iso:country":"US",
    "sg:address":"11845 State Rte 25",
    "sg:city":"Calera",
    "sg:classifiers":[
        {
            "category":"Autos & Motor Vehicles",
            "subcategory":"Fuel & Gas Station",
            "type":"Retail Goods"
        }
    ],
    "sg:phone":"+1 205 668 2950",
    "sg:postcode":"35040",
    "sg:province":"AL",
    "sg:tags":[
        "plaza",
        "truck",
        "stops"
    ],
    "wof:name":"Speed Trac",
    "wof:placetype":"venue"
},
  "geometry": {"coordinates":[-86.735923,33.103688],"type":"Point"}
}