{
  "type": "Feature",
  "properties": {
    "iso:country":"US",
    "sg:address":"6572 Old Tuscaloosa Hwy",
    "sg:city":"Mc Calla",
    "sg:classifiers":[
        {
            "category":"Building & Trades",
            "subcategory":"Construction",
            "type":"Services"
        }
    ],
    "sg:phone":"+1 205 477 0201",
    "sg:postcode":"35111",
    "sg:province":"AL",
    "sg:tags":[
        "contractor"
    ],
    "wof:name":"Blanset Painting & Drywall",
    "wof:placetype":"venue"
},
  "geometry": {"coordinates":[-87.03851400000001,33.317512],"type":"Point"}
}