{
  "type": "Feature",
  "properties": {
    "addr:full":"10 Coffield Dr Phenix City AL 36870",
    "addr:housenumber":"10",
    "addr:postcode":"36870",
    "addr:street":"Coffield Dr Phenix",
    "iso:country":"US",
    "sg:address":"10 Coffield Dr",
    "sg:city":"Phenix City",
    "sg:classifiers":[
        {
            "category":"Building & Trades",
            "subcategory":"Electrical",
            "type":"Services"
        }
    ],
    "sg:phone":"+1 334 297 2352",
    "sg:postcode":"36870",
    "sg:province":"AL",
    "sg:tags":[
        "electric",
        "contractor"
    ],
    "wof:name":"H & J Electrical Svc",
    "wof:placetype":"venue"
},
  "geometry": {"coordinates":[-85.102317,32.470307],"type":"Point"}
}