{
  "type": "Feature",
  "properties": {
    "addr:full":"2515 Co Rd 44 Camp Hill AL 36850",
    "addr:housenumber":"2515;44",
    "addr:postcode":"36850",
    "addr:street":"Co Rd",
    "iso:country":"US",
    "sg:address":"2515 Co Rd 44",
    "sg:city":"Camp Hill",
    "sg:classifiers":[
        {
            "category":"Building & Trades",
            "subcategory":"Construction",
            "type":"Services"
        }
    ],
    "sg:phone":"+1 256 896 2511",
    "sg:postcode":"36850",
    "sg:province":"AL",
    "sg:tags":[
        "house"
    ],
    "wof:name":"Benco Construction",
    "wof:placetype":"venue"
},
  "geometry": {"coordinates":[-85.584889,32.847839],"type":"Point"}
}