{
  "type": "Feature",
  "properties": {
    "iso:country":"US",
    "sg:address":"1305 Glenwick Cir",
    "sg:city":"Birmingham",
    "sg:classifiers":[
        {
            "category":"Retail",
            "subcategory":"Auto Repair",
            "type":"Services"
        }
    ],
    "sg:phone":"+1 205 853 2750",
    "sg:postcode":"35235",
    "sg:province":"AL",
    "sg:tags":[
        "body"
    ],
    "wof:name":"Karmondi Custom Cars",
    "wof:placetype":"venue"
},
  "geometry": {"coordinates":[-86.670225,33.598626],"type":"Point"}
}