{
  "type": "Feature",
  "properties": {
    "iso:country":"US",
    "sg:address":"3930 Grants Mill Rd",
    "sg:city":"Birmingham",
    "sg:classifiers":[
        {
            "category":"Travel",
            "subcategory":"Hotels & Motels",
            "type":"Entertainment"
        }
    ],
    "sg:phone":"+1 205 933 0444",
    "sg:postcode":"35210",
    "sg:province":"AL",
    "sg:tags":[
        "lodging"
    ],
    "sg:website":"http://www.birminghameasti20suites.hamptoninn.com",
    "wof:name":"Hampton Inn and Suites",
    "wof:placetype":"venue"
},
  "geometry": {"coordinates":[-86.691648,33.532099],"type":"Point"}
}