{
  "type": "Feature",
  "properties": {
    "iso:country":"US",
    "sg:address":"744 N Oates St",
    "sg:city":"Dothan",
    "sg:classifiers":[
        {
            "category":"Arts & Performance",
            "subcategory":"Theater",
            "type":"Entertainment"
        }
    ],
    "sg:phone":"+1 334 702 6999",
    "sg:postcode":"36303",
    "sg:province":"AL",
    "sg:tags":[
        "group"
    ],
    "wof:name":"The Mall",
    "wof:placetype":"venue"
},
  "geometry": {"coordinates":[-85.394817,31.232009],"type":"Point"}
}