{
  "type": "Feature",
  "properties": {
    "iso:country":"US",
    "sg:address":"3255 Dobbs Rd",
    "sg:city":"Alexander City",
    "sg:classifiers":[
        {
            "category":"Building & Trades",
            "subcategory":"Construction",
            "type":"Services"
        }
    ],
    "sg:phone":"+1 256 354 3024",
    "sg:postcode":"35010",
    "sg:province":"AL",
    "sg:tags":[
        "house"
    ],
    "wof:name":"Ryals Construction",
    "wof:placetype":"venue"
},
  "geometry": {"coordinates":[-85.94027,32.972369],"type":"Point"}
}