{
  "type": "Feature",
  "properties": {
    "iso:country":"US",
    "sg:address":"233 Boulevard",
    "sg:city":"Valley",
    "sg:classifiers":[
        {
            "category":"Professional",
            "type":"Services"
        }
    ],
    "sg:phone":"+1 334 756 5190",
    "sg:postcode":"36854",
    "sg:province":"AL",
    "sg:tags":[
        "establishment"
    ],
    "wof:name":"Chattahoochee Valley Imaging",
    "wof:placetype":"venue"
},
  "geometry": {"coordinates":[-85.184418,32.795403],"type":"Point"}
}