{
  "type": "Feature",
  "properties": {
    "iso:country":"US",
    "sg:address":"850 Winchester Rd NE",
    "sg:city":"Huntsville",
    "sg:classifiers":[
        {
            "category":"Shopping",
            "subcategory":"Gifts & Souvenirs",
            "type":"Retail Goods"
        }
    ],
    "sg:phone":"+1 256 858 3818",
    "sg:postcode":"35811",
    "sg:province":"AL",
    "sg:website":"www.jandlracing.com",
    "wof:name":"J & L Racing Collectibles",
    "wof:placetype":"venue"
},
  "geometry": {"coordinates":[-86.539377,34.796293],"type":"Point"}
}