{
  "type": "Feature",
  "properties": {
    "iso:country":"US",
    "sg:address":"17003 State Rte 22",
    "sg:city":"Clanton",
    "sg:classifiers":[
        {
            "category":"Autos & Motor Vehicles",
            "subcategory":"Fuel & Gas Station",
            "type":"Retail Goods"
        }
    ],
    "sg:phone":"+1 205 755 7635",
    "sg:postcode":"35045",
    "sg:province":"AL",
    "sg:tags":[
        "station",
        "gasoline"
    ],
    "wof:name":"Hitchin Post",
    "wof:placetype":"venue"
},
  "geometry": {"coordinates":[-86.750731,32.820952],"type":"Point"}
}