{
  "type": "Feature",
  "properties": {
    "iso:country":"US",
    "sg:address":"54 N Sage Ave",
    "sg:city":"Mobile",
    "sg:classifiers":[
        {
            "category":"Professional",
            "type":"Services"
        }
    ],
    "sg:phone":"+1 251 471 0047",
    "sg:postcode":"36607",
    "sg:province":"AL",
    "sg:tags":[
        "establishment"
    ],
    "wof:name":"Lyde Associates",
    "wof:placetype":"venue"
},
  "geometry": {"coordinates":[-88.114607,30.693638],"type":"Point"}
}