{
  "type": "Feature",
  "properties": {
    "iso:country":"US",
    "sg:address":"4445 51st Ave SW",
    "sg:city":"Lanett",
    "sg:classifiers":[
        {
            "category":"Airport",
            "type":"Transportation"
        }
    ],
    "sg:phone":"+1 334 576 6998",
    "sg:postcode":"36863",
    "sg:province":"AL",
    "wof:name":"Lanett Muicipal Airport",
    "wof:placetype":"venue"
},
  "geometry": {"coordinates":[-85.232389,32.812769],"type":"Point"}
}