{
  "type": "Feature",
  "properties": {
    "addr:full":"20 Andrews Dr Daleville AL 36322",
    "addr:housenumber":"20",
    "addr:postcode":"36322",
    "addr:street":"Andrews Dr",
    "iso:country":"US",
    "sg:address":"20 Andrews Dr",
    "sg:city":"Daleville",
    "sg:classifiers":[
        {
            "category":"Professional",
            "subcategory":"Research",
            "type":"Services"
        }
    ],
    "sg:phone":"+1 256 831 5741",
    "sg:postcode":"36322",
    "sg:province":"AL",
    "sg:tags":[
        "development",
        "laboratory"
    ],
    "wof:name":"K R Komarek Briquetting Rsrch",
    "wof:placetype":"venue"
},
  "geometry": {"coordinates":[-85.703203,31.316608],"type":"Point"}
}