{
  "type": "Feature",
  "properties": {
    "iso:country":"US",
    "sg:address":"4807 Peartree Ct",
    "sg:city":"Tuscaloosa",
    "sg:classifiers":[
        {
            "category":"Communications",
            "subcategory":"Film & Video Production",
            "type":"Services"
        }
    ],
    "sg:phone":"+1 205 556 5547",
    "sg:postcode":"35405",
    "sg:province":"AL",
    "sg:tags":[
        "motion"
    ],
    "wof:name":"Thru Productions",
    "wof:placetype":"venue"
},
  "geometry": {"coordinates":[-87.468376,33.162447],"type":"Point"}
}