{
  "type": "Feature",
  "properties": {
    "iso:country":"US",
    "sg:address":"7465 State Rte 157",
    "sg:city":"Florence",
    "sg:phone":"+1 256 760 1016",
    "sg:postcode":"35633",
    "sg:province":"AL",
    "sg:tags":[
        "farm",
        "cotton"
    ],
    "wof:name":"Steve Oakley Farm",
    "wof:placetype":"venue"
},
  "geometry": {"coordinates":[-87.739197,34.901018],"type":"Point"}
}