{
  "type": "Feature",
  "properties": {
    "iso:country":"US",
    "sg:address":"13868 Co Rd 400",
    "sg:city":"Hillsboro",
    "sg:phone":"+1 256 637 2069",
    "sg:postcode":"35643",
    "sg:province":"AL",
    "sg:tags":[
        "wheat",
        "beef",
        "farm",
        "corn",
        "soybean",
        "cattle"
    ],
    "wof:name":"Glenn Acers",
    "wof:placetype":"venue"
},
  "geometry": {"coordinates":[-87.15534700000001,34.674971],"type":"Point"}
}