{
  "type": "Feature",
  "properties": {
    "iso:country":"US",
    "sg:address":"1100 13th St E",
    "sg:city":"Tuscaloosa",
    "sg:classifiers":[
        {
            "category":"Manufacturing",
            "subcategory":"Motor Vehicles & Parts",
            "type":"Manufacturing & Wholesale Goods"
        }
    ],
    "sg:phone":"+1 205 366 0902",
    "sg:postcode":"35404",
    "sg:province":"AL",
    "sg:tags":[
        "mfg"
    ],
    "wof:name":"Alabama Axle Specialists Inc",
    "wof:placetype":"venue"
},
  "geometry": {"coordinates":[-87.521657,33.200933],"type":"Point"}
}