{
  "type": "Feature",
  "properties": {
    "iso:country":"US",
    "sg:address":"2329 S Park Ave",
    "sg:city":"Dothan",
    "sg:classifiers":[
        {
            "category":"Food & Beverages",
            "subcategory":"Groceries & Convenience Stores",
            "type":"Retail Goods"
        }
    ],
    "sg:phone":"+1 334 712 7782",
    "sg:postcode":"36301",
    "sg:province":"AL",
    "sg:tags":[
        "grocer"
    ],
    "wof:name":"T C's Petro",
    "wof:placetype":"venue"
},
  "geometry": {"coordinates":[-85.411483,31.199501],"type":"Point"}
}