{
  "type": "Feature",
  "properties": {
    "addr:full":"191 Oak Ter Somerville AL 35670",
    "addr:housenumber":"191",
    "addr:postcode":"35670",
    "addr:street":"Oak Ter",
    "iso:country":"US",
    "sg:address":"191 Oak Ter",
    "sg:city":"Somerville",
    "sg:classifiers":[
        {
            "category":"Freight",
            "type":"Transportation"
        }
    ],
    "sg:phone":"+1 256 498 0669",
    "sg:postcode":"35670",
    "sg:province":"AL",
    "sg:tags":[
        "hauler"
    ],
    "wof:name":"Jack & Michaels Transport Inc",
    "wof:placetype":"venue"
},
  "geometry": {"coordinates":[-86.609757,34.443871],"type":"Point"}
}