{
  "type": "Feature",
  "properties": {
    "iso:country":"US",
    "sg:address":"2227 Cobbs Ford Rd",
    "sg:city":"Prattville",
    "sg:classifiers":[
        {
            "category":"Retail",
            "subcategory":"Laundry & Dry Cleaning",
            "type":"Services"
        },
        {
            "category":"Home & Garden",
            "subcategory":"Carpets & Floor Coverings",
            "type":"Retail Goods"
        }
    ],
    "sg:phone":"+1 334 285 1932",
    "sg:postcode":"36066",
    "sg:province":"AL",
    "sg:tags":[
        "cleaners",
        "rug"
    ],
    "wof:name":"Carol's Carpet",
    "wof:placetype":"venue"
},
  "geometry": {"coordinates":[-86.410816,32.459804],"type":"Point"}
}