{
  "type": "Feature",
  "properties": {
    "iso:country":"US",
    "sg:address":"685 Panola Rd",
    "sg:city":"Lapine",
    "sg:classifiers":[
        {
            "category":"Wholesale",
            "subcategory":"Vending Machines",
            "type":"Manufacturing & Wholesale Goods"
        }
    ],
    "sg:phone":"+1 334 537 9623",
    "sg:postcode":"36046",
    "sg:province":"AL",
    "sg:tags":[
        "operator"
    ],
    "wof:name":"Cls Vending Inc",
    "wof:placetype":"venue"
},
  "geometry": {"coordinates":[-86.388231,31.971779],"type":"Point"}
}