{
  "type": "Feature",
  "properties": {
    "addr:full":"241 US Hwy 31 Hartselle AL 35640",
    "addr:housenumber":"241",
    "addr:postcode":"35640",
    "addr:street":"Us Hwy 31",
    "iso:country":"US",
    "sg:address":"241 US Hwy 31",
    "sg:city":"Hartselle",
    "sg:classifiers":[
        {
            "category":"Shopping",
            "type":"Retail Goods"
        }
    ],
    "sg:phone":"+1 256 773 6323",
    "sg:postcode":"35640",
    "sg:province":"AL",
    "sg:tags":[
        "cosmetic",
        "perfume"
    ],
    "wof:name":"Merle Norman Cosmetics",
    "wof:placetype":"venue"
},
  "geometry": {"coordinates":[-86.943263,34.44443],"type":"Point"}
}