{
  "type": "Feature",
  "properties": {
    "iso:country":"US",
    "sg:address":"100 Englewood Dr",
    "sg:city":"Fairfield",
    "sg:classifiers":[
        {
            "category":"Government",
            "subcategory":"Office",
            "type":"Public Place"
        }
    ],
    "sg:phone":"+1 205 783 6025",
    "sg:postcode":"35064",
    "sg:province":"AL",
    "sg:tags":[
        "fire",
        "protection"
    ],
    "wof:name":"Fire Department 2",
    "wof:placetype":"venue"
},
  "geometry": {"coordinates":[-86.920743,33.458425],"type":"Point"}
}