{
  "type": "Feature",
  "properties": {
    "iso:country":"US",
    "sg:address":"13 Brown Meadow Ln",
    "sg:city":"Boaz",
    "sg:classifiers":[
        {
            "category":"Professional",
            "type":"Services"
        }
    ],
    "sg:phone":"+1 256 593 9976",
    "sg:postcode":"35957",
    "sg:province":"AL",
    "wof:name":"Randy Gilliland",
    "wof:placetype":"venue"
},
  "geometry": {"coordinates":[-86.13486899999999,34.240874],"type":"Point"}
}