{
  "type": "Feature",
  "properties": {
    "iso:country":"US",
    "sg:address":"11665 US Hwy 278 E",
    "sg:city":"Piedmont",
    "sg:classifiers":[
        {
            "category":"Utilities",
            "subcategory":"Refuse",
            "type":"Services"
        }
    ],
    "sg:phone":"+1 256 492 9349",
    "sg:postcode":"36272",
    "sg:province":"AL",
    "sg:tags":[
        "system"
    ],
    "wof:name":"J & J Salvage",
    "wof:placetype":"venue"
},
  "geometry": {"coordinates":[-85.76521099999999,33.967053],"type":"Point"}
}