{
  "type": "Feature",
  "properties": {
    "iso:country":"US",
    "sg:address":"1305 Wanda Dr NW",
    "sg:city":"Arab",
    "sg:classifiers":[
        {
            "category":"Professional",
            "subcategory":"Business Services",
            "type":"Services"
        }
    ],
    "sg:phone":"+1 256 586 6204",
    "sg:postcode":"35016",
    "sg:province":"AL",
    "sg:tags":[
        "hanger",
        "sign"
    ],
    "wof:name":"Masterbuilt Billboards",
    "wof:placetype":"venue"
},
  "geometry": {"coordinates":[-86.519242,34.322022],"type":"Point"}
}