{
  "type": "Feature",
  "properties": {
    "iso:country":"US",
    "sg:address":"106 N Main St",
    "sg:city":"Enterprise",
    "sg:classifiers":[
        {
            "category":"Shopping",
            "subcategory":"Stationery & Office Supplies",
            "type":"Retail Goods"
        }
    ],
    "sg:phone":"+1 334 347 2659",
    "sg:postcode":"36330",
    "sg:province":"AL",
    "sg:tags":[
        "machine",
        "se",
        "furniture"
    ],
    "wof:name":"Central Office Products",
    "wof:placetype":"venue"
},
  "geometry": {"coordinates":[-85.854634,31.315289],"type":"Point"}
}