{
  "type": "Feature",
  "properties": {
    "addr:full":"2204 Morgan Rd Bessemer AL 35022",
    "addr:housenumber":"2204",
    "addr:postcode":"35022",
    "addr:street":"Morgan Rd",
    "iso:country":"US",
    "sg:address":"2204 Morgan Rd",
    "sg:city":"Bessemer",
    "sg:classifiers":[
        {
            "category":"Home & Garden",
            "subcategory":"Furniture",
            "type":"Retail Goods"
        }
    ],
    "sg:phone":"+1 205 243 4188",
    "sg:postcode":"35022",
    "sg:province":"AL",
    "sg:tags":[
        "store"
    ],
    "wof:name":"Mike S Used Furniture",
    "wof:placetype":"venue"
},
  "geometry": {"coordinates":[-86.93753700000001,33.357201],"type":"Point"}
}