{
  "type": "Feature",
  "properties": {
    "addr:full":"2835 Pyramid Ave Montgomery AL 36105",
    "addr:housenumber":"2835",
    "addr:postcode":"36105",
    "addr:street":"Pyramid Ave",
    "iso:country":"US",
    "sg:address":"2835 Pyramid Ave",
    "sg:city":"Montgomery",
    "sg:classifiers":[
        {
            "category":"Freight",
            "type":"Transportation"
        }
    ],
    "sg:phone":"+1 334 280 2876",
    "sg:postcode":"36105",
    "sg:province":"AL",
    "wof:name":"Re Garrison Trnsprtn Lakeside",
    "wof:placetype":"venue"
},
  "geometry": {"coordinates":[-86.35637800000001,32.278137],"type":"Point"}
}