{
  "type": "Feature",
  "properties": {
    "iso:country":"US",
    "sg:address":"3940 Birmingham Hwy",
    "sg:city":"Montgomery",
    "sg:classifiers":[
        {
            "category":"Retail",
            "subcategory":"Auto Repair",
            "type":"Services"
        }
    ],
    "sg:phone":"+1 334 262 0692",
    "sg:postcode":"36108",
    "sg:province":"AL",
    "sg:tags":[
        "commercial",
        "trailer"
    ],
    "wof:name":"H & M Trailer Repair Inc",
    "wof:placetype":"venue"
},
  "geometry": {"coordinates":[-86.388795,32.39091],"type":"Point"}
}