{
  "type": "Feature",
  "properties": {
    "iso:country":"US",
    "sg:address":"507 N Perry St",
    "sg:city":"Montgomery",
    "sg:classifiers":[
        {
            "category":"Retail",
            "subcategory":"Auto Repair",
            "type":"Services"
        }
    ],
    "sg:phone":"+1 334 263 9928",
    "sg:postcode":"36104",
    "sg:province":"AL",
    "sg:tags":[
        "suppl",
        "general"
    ],
    "wof:name":"Cylinder Head Exchange",
    "wof:placetype":"venue"
},
  "geometry": {"coordinates":[-86.307853,32.384095],"type":"Point"}
}