{
  "type": "Feature",
  "properties": {
    "iso:country":"US",
    "sg:address":"302 S 4th St",
    "sg:city":"Gadsden",
    "sg:classifiers":[
        {
            "category":"Health Services",
            "subcategory":"Medical Lab",
            "type":"Services"
        }
    ],
    "sg:phone":"+1 256 543 2990",
    "sg:postcode":"35901",
    "sg:province":"AL",
    "sg:tags":[
        "laboratory"
    ],
    "wof:name":"Laboratory Corporation America",
    "wof:placetype":"venue"
},
  "geometry": {"coordinates":[-86.005576,34.008706],"type":"Point"}
}