{
  "type": "Feature",
  "properties": {
    "addr:full":"2609 Artie St SW Huntsville AL 35805",
    "addr:postcode":"2609;35805",
    "addr:street":"Artie St Sw",
    "iso:country":"US",
    "sg:address":"2609 Artie St SW",
    "sg:city":"Huntsville",
    "sg:classifiers":[
        {
            "category":"Home & Garden",
            "subcategory":"Building Materials",
            "type":"Retail Goods"
        }
    ],
    "sg:phone":"+1 256 539 9377",
    "sg:postcode":"35805",
    "sg:province":"AL",
    "sg:tags":[
        "contractor"
    ],
    "wof:name":"Pella Window & Door",
    "wof:placetype":"venue"
},
  "geometry": {"coordinates":[-86.59276699999999,34.708699],"type":"Point"}
}