{
  "type": "Feature",
  "properties": {
    "iso:country":"US",
    "sg:address":"5733 State Rte 195",
    "sg:city":"Jasper",
    "sg:classifiers":[
        {
            "category":"Freight",
            "type":"Transportation"
        }
    ],
    "sg:phone":"+1 205 221 5208",
    "sg:postcode":"35503",
    "sg:province":"AL",
    "sg:tags":[
        "operator",
        "local",
        "trucking"
    ],
    "wof:name":"Stiles Trucking Company Inc",
    "wof:placetype":"venue"
},
  "geometry": {"coordinates":[-87.322982,33.935462],"type":"Point"}
}