{
  "type": "Feature",
  "properties": {
    "iso:country":"US",
    "sg:address":"1621 Virginia St",
    "sg:city":"Mobile",
    "sg:classifiers":[
        {
            "category":"Arena",
            "subcategory":"Sports Club",
            "type":"Entertainment"
        }
    ],
    "sg:phone":"+1 251 208 2500",
    "sg:postcode":"36604",
    "sg:province":"AL",
    "sg:tags":[
        "athletic",
        "fields",
        "stadium"
    ],
    "wof:name":"Ernest F Ladd Memorial Stadium",
    "wof:placetype":"venue"
},
  "geometry": {"coordinates":[-88.07438999999999,30.67457],"type":"Point"}
}