{
  "type": "Feature",
  "properties": {
    "iso:country":"US",
    "sg:address":"103 Hickory Nut Dr",
    "sg:city":"Dothan",
    "sg:classifiers":[
        {
            "category":"Retail",
            "subcategory":"Laundry & Dry Cleaning",
            "type":"Services"
        }
    ],
    "sg:phone":"+1 334 792 2391",
    "sg:postcode":"36301",
    "sg:province":"AL",
    "sg:tags":[
        "cleaners",
        "rug",
        "carpet"
    ],
    "wof:name":"Action Carpet Cleaning Inc",
    "wof:placetype":"venue"
},
  "geometry": {"coordinates":[-85.36532699999999,31.188007],"type":"Point"}
}