{
  "type": "Feature",
  "properties": {
    "addr:full":"400 Hagood St Birmingham AL 35213",
    "addr:housenumber":"400",
    "addr:postcode":"35213",
    "addr:street":"Hagood St",
    "iso:country":"US",
    "sg:address":"400 Hagood St",
    "sg:city":"Birmingham",
    "sg:classifiers":[
        {
            "category":"Professional",
            "type":"Services"
        }
    ],
    "sg:phone":"+1 205 871 9273",
    "sg:postcode":"35213",
    "sg:province":"AL",
    "wof:name":"Groundskeeper",
    "wof:placetype":"venue"
},
  "geometry": {"coordinates":[-86.73801899999999,33.513557],"type":"Point"}
}