{
  "type": "Feature",
  "properties": {
    "iso:country":"US",
    "sg:address":"186 1st Ave",
    "sg:city":"Jemison",
    "sg:classifiers":[
        {
            "category":"Building & Trades",
            "subcategory":"Construction",
            "type":"Services"
        }
    ],
    "sg:phone":"+1 205 688 2366",
    "sg:postcode":"35085",
    "sg:province":"AL",
    "sg:tags":[
        "hanging",
        "contractor"
    ],
    "wof:name":"H and M Painter Inc",
    "wof:placetype":"venue"
},
  "geometry": {"coordinates":[-86.72869900000001,32.942462],"type":"Point"}
}