{
  "type": "Feature",
  "properties": {
    "iso:country":"US",
    "sg:address":"3040 Bluebill Dr",
    "sg:city":"Mobile",
    "sg:classifiers":[
        {
            "category":"Farming",
            "subcategory":"Livestock Farm",
            "type":"Manufacturing & Wholesale Goods"
        }
    ],
    "sg:phone":"+1 251 634 8283",
    "sg:postcode":"36695",
    "sg:province":"AL",
    "sg:tags":[
        "animal",
        "general"
    ],
    "wof:name":"Circle R Farms & Services",
    "wof:placetype":"venue"
},
  "geometry": {"coordinates":[-88.222528,30.627977],"type":"Point"}
}