{
  "type": "Feature",
  "properties": {
    "iso:country":"US",
    "sg:address":"118 Moulton St E",
    "sg:city":"Decatur",
    "sg:classifiers":[
        {
            "category":"Insurance",
            "subcategory":"Title Insurance",
            "type":"Services"
        }
    ],
    "sg:phone":"+1 256 309 5730",
    "sg:postcode":"35601",
    "sg:province":"AL",
    "wof:name":"Real Estate Loan Svc-Alabama",
    "wof:placetype":"venue"
},
  "geometry": {"coordinates":[-86.98529,34.604013],"type":"Point"}
}