{
  "type": "Feature",
  "properties": {
    "iso:country":"US",
    "sg:address":"106A Depot St",
    "sg:city":"Slocomb",
    "sg:classifiers":[
        {
            "category":"Building & Trades",
            "subcategory":"Construction",
            "type":"Services"
        }
    ],
    "sg:phone":"+1 205 529 8292",
    "sg:postcode":"36375",
    "sg:province":"AL",
    "sg:tags":[
        "industrial",
        "contractors-commercial"
    ],
    "wof:name":"The Bmc Group",
    "wof:placetype":"venue"
},
  "geometry": {"coordinates":[-85.520877,31.137103],"type":"Point"}
}