{
  "type": "Feature",
  "properties": {
    "iso:country":"US",
    "sg:address":"14391 US Hwy 411",
    "sg:city":"Odenville",
    "sg:classifiers":[
        {
            "category":"Shopping",
            "subcategory":"Used Merchandise",
            "type":"Retail Goods"
        }
    ],
    "sg:phone":"+1 205 629 0247",
    "sg:postcode":"35120",
    "sg:province":"AL",
    "sg:tags":[
        "antique"
    ],
    "wof:name":"Charlotte's Web Antiques",
    "wof:placetype":"venue"
},
  "geometry": {"coordinates":[-86.394338,33.685813],"type":"Point"}
}