{
  "type": "Feature",
  "properties": {
    "iso:country":"US",
    "sg:address":"376 Westgate Pkwy",
    "sg:city":"Dothan",
    "sg:classifiers":[
        {
            "category":"Personal",
            "type":"Services"
        }
    ],
    "sg:phone":"+1 334 699 2774",
    "sg:postcode":"36303",
    "sg:province":"AL",
    "wof:name":"Serenity Spa & Gifts Salon",
    "wof:placetype":"venue"
},
  "geometry": {"coordinates":[-85.434456,31.234627],"type":"Point"}
}