{
  "type": "Feature",
  "properties": {
    "iso:country":"US",
    "sg:address":"13454 New Cut Rd",
    "sg:city":"Athens",
    "sg:classifiers":[
        {
            "category":"Social Services",
            "subcategory":"Child Care",
            "type":"Services"
        }
    ],
    "sg:phone":"+1 256 729 6690",
    "sg:postcode":"35611",
    "sg:province":"AL",
    "wof:name":"Fun & Learn Day Care",
    "wof:placetype":"venue"
},
  "geometry": {"coordinates":[-87.083398,34.821273],"type":"Point"}
}