{
  "type": "Feature",
  "properties": {
    "iso:country":"US",
    "sg:address":"2031 S College St",
    "sg:city":"Auburn",
    "sg:classifiers":[
        {
            "category":"Retail",
            "subcategory":"Laundry & Dry Cleaning",
            "type":"Services"
        }
    ],
    "sg:phone":"+1 334 502 5040",
    "sg:postcode":"36832",
    "sg:province":"AL",
    "sg:tags":[
        "linen",
        "supply"
    ],
    "wof:name":"Gameday Towel Co",
    "wof:placetype":"venue"
},
  "geometry": {"coordinates":[-85.504512,32.5617],"type":"Point"}
}