{
  "type": "Feature",
  "properties": {
    "addr:full":"1125 11th Pl S Birmingham AL 35205",
    "addr:housenumber":"1125",
    "addr:postcode":"35205",
    "addr:street":"11Th Pl S",
    "iso:country":"US",
    "sg:address":"1125 11th Pl S",
    "sg:city":"Birmingham",
    "sg:classifiers":[
        {
            "category":"Wholesale",
            "subcategory":"Machinery & Supplies",
            "type":"Manufacturing & Wholesale Goods"
        }
    ],
    "sg:phone":"+1 205 252 4794",
    "sg:postcode":"35205",
    "sg:province":"AL",
    "sg:tags":[
        "instrument",
        "valve",
        "piping",
        "sales",
        "for"
    ],
    "wof:name":"Alabama Piping Components LLC",
    "wof:placetype":"venue"
},
  "geometry": {"coordinates":[-86.809178,33.494373],"type":"Point"}
}