{
  "type": "Feature",
  "properties": {
    "iso:country":"US",
    "sg:address":"1751 Strollaway Ln",
    "sg:city":"Birmingham",
    "sg:classifiers":[
        {
            "category":"Professional",
            "subcategory":"Management & Consulting",
            "type":"Services"
        }
    ],
    "sg:phone":"+1 205 934 7161",
    "sg:postcode":"35226",
    "sg:province":"AL",
    "wof:name":"Joseph Telfair",
    "wof:placetype":"venue"
},
  "geometry": {"coordinates":[-86.819086,33.38642],"type":"Point"}
}