{
  "type": "Feature",
  "properties": {
    "iso:country":"US",
    "sg:address":"636 Howe St",
    "sg:city":"Montgomery",
    "sg:classifiers":[
        {
            "category":"Retail",
            "subcategory":"Auto Repair",
            "type":"Services"
        }
    ],
    "sg:phone":"+1 334 215 8988",
    "sg:postcode":"36104",
    "sg:province":"AL",
    "sg:tags":[
        "wrecker"
    ],
    "wof:name":"B & R Materials",
    "wof:placetype":"venue"
},
  "geometry": {"coordinates":[-86.297908,32.39094],"type":"Point"}
}