{
  "type": "Feature",
  "properties": {
    "iso:country":"US",
    "sg:address":"601 Farrah Cir",
    "sg:city":"Dothan",
    "sg:classifiers":[
        {
            "category":"Health Services",
            "subcategory":"Doctor",
            "type":"Services"
        }
    ],
    "sg:phone":"+1 334 792 2638",
    "sg:postcode":"36301",
    "sg:province":"AL",
    "sg:tags":[
        "dentist"
    ],
    "wof:name":"John H Davis Jr DDS",
    "wof:placetype":"venue"
},
  "geometry": {"coordinates":[-85.42406,31.21399],"type":"Point"}
}