{
  "type": "Feature",
  "properties": {
    "iso:country":"US",
    "sg:address":"401 28th St S",
    "sg:city":"Birmingham",
    "sg:classifiers":[
        {
            "category":"Building & Trades",
            "subcategory":"Equipment Rental",
            "type":"Services"
        },
        {
            "category":"Shopping",
            "subcategory":"Computers & Home Electronics",
            "type":"Retail Goods"
        }
    ],
    "sg:phone":"+1 205 328 5231",
    "sg:postcode":"35233",
    "sg:province":"AL",
    "sg:tags":[
        "stereo",
        "leasing",
        "supply",
        "video",
        "audio",
        "equipment-renting",
        "audio-visual"
    ],
    "sg:website":"http://www.holtav.com",
    "wof:name":"Holt A V",
    "wof:placetype":"venue"
},
  "geometry": {"coordinates":[-86.791061,33.514309],"type":"Point"}
}