{
  "type": "Feature",
  "properties": {
    "addr:full":"2206 17th St E Tuscaloosa AL 35404",
    "addr:housenumber":"2206",
    "addr:postcode":"35404",
    "addr:street":"17Th St",
    "iso:country":"US",
    "sg:address":"2206 17th St E",
    "sg:city":"Tuscaloosa",
    "sg:classifiers":[
        {
            "category":"Organizations",
            "subcategory":"Religious Organization",
            "type":"Services"
        }
    ],
    "sg:phone":"+1 205 553 9420",
    "sg:postcode":"35404",
    "sg:province":"AL",
    "wof:name":"Temple Baptist Church",
    "wof:placetype":"venue"
},
  "geometry": {"coordinates":[-87.510777,33.194742],"type":"Point"}
}