{
  "type": "Feature",
  "properties": {
    "addr:full":"822 Westgate Pkwy Dothan AL 36303",
    "addr:housenumber":"822",
    "addr:postcode":"36303",
    "addr:street":"Westgate Pkwy",
    "iso:country":"US",
    "sg:address":"822 Westgate Pkwy",
    "sg:city":"Dothan",
    "sg:classifiers":[
        {
            "category":"Professional",
            "type":"Services"
        }
    ],
    "sg:phone":"+1 334 794 9520",
    "sg:postcode":"36303",
    "sg:province":"AL",
    "wof:name":"Robert Woodall",
    "wof:placetype":"venue"
},
  "geometry": {"coordinates":[-85.436339,31.245401],"type":"Point"}
}