{
  "type": "Feature",
  "properties": {
    "addr:full":"452 Cramer Ave Montgomery AL 36104",
    "addr:housenumber":"452",
    "addr:postcode":"36104",
    "addr:street":"Cramer Ave",
    "iso:country":"US",
    "sg:address":"452 Cramer Ave",
    "sg:city":"Montgomery",
    "sg:classifiers":[
        {
            "category":"Organizations",
            "subcategory":"Religious Organization",
            "type":"Services"
        }
    ],
    "sg:phone":"+1 334 269 9412",
    "sg:postcode":"36104",
    "sg:province":"AL",
    "wof:name":"Shiloh Baptist Church",
    "wof:placetype":"venue"
},
  "geometry": {"coordinates":[-86.301782,32.364444],"type":"Point"}
}