{
  "type": "Feature",
  "properties": {
    "addr:full":"392 Copeland Ferry Rd Cordova AL 35550",
    "addr:housenumber":"392",
    "addr:postcode":"35550",
    "addr:street":"Copeland Ferry Rd",
    "iso:country":"US",
    "sg:address":"392 Copeland Ferry Rd",
    "sg:city":"Cordova",
    "sg:classifiers":[
        {
            "category":"Organizations",
            "subcategory":"Religious Organization",
            "type":"Services"
        }
    ],
    "sg:phone":"+1 205 483 6118",
    "sg:postcode":"35550",
    "sg:province":"AL",
    "wof:name":"Bethel Development Inc",
    "wof:placetype":"venue"
},
  "geometry": {"coordinates":[-87.17805300000001,33.677155],"type":"Point"}
}