{
  "type": "Feature",
  "properties": {
    "addr:full":"7740 Cliffs Landing Rd Bay Minette AL 36507",
    "addr:housenumber":"7740",
    "addr:postcode":"36507",
    "addr:street":"Cliffs Landing Rd",
    "iso:country":"US",
    "sg:address":"7740 Cliffs Landing Rd",
    "sg:city":"Bay Minette",
    "sg:classifiers":[
        {
            "category":"Bars & Pubs",
            "type":"Food & Drink"
        }
    ],
    "sg:phone":"+1 251 580 0057",
    "sg:postcode":"36507",
    "sg:province":"AL",
    "wof:name":"Lodge",
    "wof:placetype":"venue"
},
  "geometry": {"coordinates":[-87.89048699999999,30.86209],"type":"Point"}
}