{
  "type": "Feature",
  "properties": {
    "addr:full":"1105 Columbus Pkwy Opelika AL 36804",
    "addr:housenumber":"1105",
    "addr:postcode":"36804",
    "addr:street":"Columbus Pkwy Opelika",
    "iso:country":"US",
    "sg:address":"1105 Columbus Pkwy",
    "sg:city":"Opelika",
    "sg:classifiers":[
        {
            "category":"Travel",
            "subcategory":"Hotels & Motels",
            "type":"Entertainment"
        }
    ],
    "sg:phone":"+1 334 749 8377",
    "sg:postcode":"36804",
    "sg:province":"AL",
    "wof:name":"Knights Inn",
    "wof:placetype":"venue"
},
  "geometry": {"coordinates":[-85.351524,32.643533],"type":"Point"}
}