{
  "type": "Feature",
  "properties": {
    "iso:country":"US",
    "sg:address":"17550 US Hwy 11",
    "sg:city":"Vance",
    "sg:classifiers":[
        {
            "category":"Professional",
            "subcategory":"Management & Consulting",
            "type":"Services"
        }
    ],
    "sg:phone":"+1 205 553 2353",
    "sg:postcode":"35490",
    "sg:province":"AL",
    "sg:tags":[
        "consultant",
        "automation"
    ],
    "wof:name":"SAR Automation",
    "wof:placetype":"venue"
},
  "geometry": {"coordinates":[-87.26917400000001,33.172905],"type":"Point"}
}