{
  "type": "Feature",
  "properties": {
    "iso:country":"US",
    "sg:address":"2020 Hackberry Ln",
    "sg:city":"Tuscaloosa",
    "sg:classifiers":[
        {
            "category":"Building & Trades",
            "subcategory":"Construction",
            "type":"Services"
        }
    ],
    "sg:phone":"+1 205 349 4445",
    "sg:postcode":"35401",
    "sg:province":"AL",
    "sg:tags":[
        "general",
        "contractor"
    ],
    "wof:name":"Browns Construction",
    "wof:placetype":"venue"
},
  "geometry": {"coordinates":[-87.543058,33.19231],"type":"Point"}
}