{
  "type": "Feature",
  "properties": {
    "iso:country":"US",
    "sg:address":"5420 Wares Ferry Rd",
    "sg:city":"Montgomery",
    "sg:classifiers":[
        {
            "category":"Retail",
            "subcategory":"Auto Rental",
            "type":"Services"
        }
    ],
    "sg:phone":"+1 334 271 0999",
    "sg:postcode":"36109",
    "sg:province":"AL",
    "sg:tags":[
        "passenger",
        "car"
    ],
    "wof:name":"Hixons Rndy Auto Rntl Mntgmery",
    "wof:placetype":"venue"
},
  "geometry": {"coordinates":[-86.211629,32.391159],"type":"Point"}
}