{
  "type": "Feature",
  "properties": {
    "iso:country":"US",
    "sg:address":"16679 Groundhog Rd",
    "sg:city":"Adger",
    "sg:classifiers":[
        {
            "category":"Professional",
            "type":"Services"
        }
    ],
    "sg:phone":"+1 205 491 8491",
    "sg:postcode":"35006",
    "sg:province":"AL",
    "wof:name":"Dan M Grantham",
    "wof:placetype":"venue"
},
  "geometry": {"coordinates":[-87.263342,33.417197],"type":"Point"}
}