{
  "type": "Feature",
  "properties": {
    "iso:country":"US",
    "sg:address":"1931 Eva Rd",
    "sg:city":"Eva",
    "sg:classifiers":[
        {
            "category":"Autos & Motor Vehicles",
            "subcategory":"Fuel & Gas Station",
            "type":"Retail Goods"
        }
    ],
    "sg:phone":"+1 256 737 0255",
    "sg:postcode":"35621",
    "sg:province":"AL",
    "sg:tags":[
        "oil"
    ],
    "wof:name":"Moore's Texaco",
    "wof:placetype":"venue"
},
  "geometry": {"coordinates":[-86.746231,34.381044],"type":"Point"}
}