{
  "type": "Feature",
  "properties": {
    "iso:country":"US",
    "sg:address":"1270 Blakely Rd",
    "sg:city":"Oneonta",
    "sg:classifiers":[
        {
            "category":"Retail",
            "subcategory":"Repair Shop",
            "type":"Services"
        }
    ],
    "sg:phone":"+1 205 274 2222",
    "sg:postcode":"35121",
    "sg:province":"AL",
    "sg:tags":[
        "radio"
    ],
    "wof:name":"Total Radio Service",
    "wof:placetype":"venue"
},
  "geometry": {"coordinates":[-86.371997,33.945376],"type":"Point"}
}