{
  "type": "Feature",
  "properties": {
    "iso:country":"US",
    "sg:address":"3612 Afton Brae Dr",
    "sg:city":"Anniston",
    "sg:classifiers":[
        {
            "category":"Professional",
            "type":"Services"
        }
    ],
    "sg:phone":"+1 256 237 7341",
    "sg:postcode":"36207",
    "sg:province":"AL",
    "wof:name":"Mrs Nora Leavell",
    "wof:placetype":"venue"
},
  "geometry": {"coordinates":[-85.781406,33.645048],"type":"Point"}
}