{
  "type": "Feature",
  "properties": {
    "addr:full":"1843 Darby Dr Florence AL 35630",
    "addr:housenumber":"1843",
    "addr:postcode":"35630",
    "addr:street":"Darby Dr",
    "iso:country":"US",
    "sg:address":"1843 Darby Dr",
    "sg:city":"Florence",
    "sg:classifiers":[
        {
            "category":"Shopping",
            "type":"Retail Goods"
        }
    ],
    "sg:phone":"+1 256 764 7410",
    "sg:postcode":"35630",
    "sg:province":"AL",
    "sg:tags":[
        "trophy",
        "medal",
        "merchandise",
        "award"
    ],
    "wof:name":"Frank Lary's Trophy Shop",
    "wof:placetype":"venue"
},
  "geometry": {"coordinates":[-87.65629800000001,34.826041],"type":"Point"}
}