{
  "type": "Feature",
  "properties": {
    "addr:full":"110 Arrow Rd Jasper AL 35501",
    "addr:housenumber":"110",
    "addr:postcode":"35501",
    "addr:street":"Arrow Rd",
    "iso:country":"US",
    "sg:address":"110 Arrow Rd",
    "sg:city":"Jasper",
    "sg:phone":"+1 205 221 4747",
    "sg:postcode":"35501",
    "sg:province":"AL",
    "sg:tags":[
        "oil"
    ],
    "wof:name":"Mathews & Mathews Inc",
    "wof:placetype":"venue"
},
  "geometry": {"coordinates":[-87.225419,33.836169],"type":"Point"}
}