{
  "type": "Feature",
  "properties": {
    "iso:country":"US",
    "sg:address":"710 Hereford Ln",
    "sg:city":"Tuscumbia",
    "sg:classifiers":[
        {
            "category":"Shopping",
            "subcategory":"Crafts & Fabrics",
            "type":"Retail Goods"
        }
    ],
    "sg:phone":"+1 256 383 7246",
    "sg:postcode":"35674",
    "sg:province":"AL",
    "sg:tags":[
        "sewing"
    ],
    "wof:name":"Muscle Shoals Fabric Fair",
    "wof:placetype":"venue"
},
  "geometry": {"coordinates":[-87.59932,34.698151],"type":"Point"}
}