{
  "type": "Feature",
  "properties": {
    "addr:full":"8901 Airport Blvd Mobile AL 36608",
    "addr:housenumber":"8901",
    "addr:postcode":"36608",
    "addr:street":"Airport Blvd",
    "iso:country":"US",
    "sg:address":"8901 Airport Blvd",
    "sg:city":"Mobile",
    "sg:classifiers":[
        {
            "category":"Education",
            "subcategory":"School",
            "type":"Public Place"
        }
    ],
    "sg:phone":"+1 251 221 3000",
    "sg:postcode":"36608",
    "sg:province":"AL",
    "wof:name":"Baker High School",
    "wof:placetype":"venue"
},
  "geometry": {"coordinates":[-88.26575,30.671726],"type":"Point"}
}