{
  "type": "Feature",
  "properties": {
    "addr:full":"204 W Lamar Ave Tuscumbia AL 35674",
    "addr:housenumber":"204",
    "addr:postcode":"35674",
    "addr:street":"W Lamar Ave",
    "iso:country":"US",
    "sg:address":"204 W Lamar Ave",
    "sg:city":"Tuscumbia",
    "sg:classifiers":[
        {
            "category":"Building & Trades",
            "subcategory":"Construction",
            "type":"Services"
        }
    ],
    "sg:phone":"+1 256 381 7968",
    "sg:postcode":"35674",
    "sg:province":"AL",
    "sg:tags":[
        "contractor"
    ],
    "wof:name":"Benny Smith Drywall Co",
    "wof:placetype":"venue"
},
  "geometry": {"coordinates":[-87.720315,34.724205],"type":"Point"}
}