{
  "type": "Feature",
  "properties": {
    "addr:full":"408 7th St N Clanton AL 35045",
    "addr:housenumber":"408",
    "addr:postcode":"35045",
    "addr:street":"7Th St N",
    "iso:country":"US",
    "sg:address":"408 7th St N",
    "sg:city":"Clanton",
    "sg:classifiers":[
        {
            "category":"Shopping",
            "subcategory":"Discount & Variety Stores",
            "type":"Retail Goods"
        }
    ],
    "sg:phone":"+1 205 755 7372",
    "sg:postcode":"35045",
    "sg:province":"AL",
    "sg:tags":[
        "merchandise",
        "general"
    ],
    "wof:name":"Clanton Catalog Sales",
    "wof:placetype":"venue"
},
  "geometry": {"coordinates":[-86.63270900000001,32.842245],"type":"Point"}
}