{
  "type": "Feature",
  "properties": {
    "addr:full":"1200 Johnson Ave Anniston AL 36201",
    "addr:housenumber":"1200",
    "addr:postcode":"36201",
    "addr:street":"Johnson Ave",
    "iso:country":"US",
    "sg:address":"1200 Johnson Ave",
    "sg:city":"Anniston",
    "sg:classifiers":[
        {
            "category":"Education",
            "subcategory":"School",
            "type":"Public Place"
        }
    ],
    "sg:phone":"+1 256 231 5040",
    "sg:postcode":"36201",
    "sg:province":"AL",
    "wof:name":"Constantine Elementary School",
    "wof:placetype":"venue"
},
  "geometry": {"coordinates":[-85.833337,33.633793],"type":"Point"}
}