{
  "type": "Feature",
  "properties": {
    "addr:full":"190 US Hwy 80 Montgomery AL 36105",
    "addr:housenumber":"190",
    "addr:postcode":"36105",
    "addr:street":"Us Hwy 80",
    "iso:country":"US",
    "sg:address":"190 US Hwy 80",
    "sg:city":"Montgomery",
    "sg:classifiers":[
        {
            "category":"Retail",
            "subcategory":"Auto Repair",
            "type":"Services"
        }
    ],
    "sg:phone":"+1 334 278 4454",
    "sg:postcode":"36105",
    "sg:province":"AL",
    "sg:tags":[
        "tire"
    ],
    "wof:name":"Billy's Tire Ctr",
    "wof:placetype":"venue"
},
  "geometry": {"coordinates":[-86.311605,32.326751],"type":"Point"}
}