{
  "type": "Feature",
  "properties": {
    "iso:country":"US",
    "sg:address":"4000 Park Ave SW",
    "sg:city":"Birmingham",
    "sg:classifiers":[
        {
            "category":"Food & Beverages",
            "subcategory":"Groceries & Convenience Stores",
            "type":"Retail Goods"
        }
    ],
    "sg:phone":"+1 205 925 3894",
    "sg:postcode":"35221",
    "sg:province":"AL",
    "wof:name":"Thomas Grocery",
    "wof:placetype":"venue"
},
  "geometry": {"coordinates":[-86.898646,33.450899],"type":"Point"}
}