{
  "type": "Feature",
  "properties": {
    "addr:full":"1031 14th St Calera AL 35040",
    "addr:housenumber":"1031",
    "addr:postcode":"35040",
    "addr:street":"14Th St",
    "iso:country":"US",
    "sg:address":"1031 14th St",
    "sg:city":"Calera",
    "sg:classifiers":[
        {
            "category":"Retail",
            "subcategory":"Auto Repair",
            "type":"Services"
        }
    ],
    "sg:phone":"+1 205 668 0099",
    "sg:postcode":"35040",
    "sg:province":"AL",
    "sg:tags":[
        "body"
    ],
    "wof:name":"Peeks Auto Tops & Interiors",
    "wof:placetype":"venue"
},
  "geometry": {"coordinates":[-86.755346,33.105404],"type":"Point"}
}