{
  "type": "Feature",
  "properties": {
    "addr:full":"1213 Catskill Cir SE Huntsville AL 35802",
    "addr:housenumber":"1213",
    "addr:postcode":"35802",
    "addr:street":"Catskill Cir Se",
    "iso:country":"US",
    "sg:address":"1213 Catskill Cir SE",
    "sg:city":"Huntsville",
    "sg:classifiers":[
        {
            "category":"Shopping",
            "subcategory":"Clothing, Apparel, & Fashions",
            "type":"Retail Goods"
        }
    ],
    "sg:phone":"+1 256 883 5779",
    "sg:postcode":"35802",
    "sg:province":"AL",
    "wof:name":"Ann S Basic To Elegance",
    "wof:placetype":"venue"
},
  "geometry": {"coordinates":[-86.539929,34.647529],"type":"Point"}
}