{
  "type": "Feature",
  "properties": {
    "iso:country":"US",
    "sg:address":"718 Honeysuckle Rd",
    "sg:city":"Dothan",
    "sg:classifiers":[
        {
            "category":"Professional",
            "subcategory":"Management & Consulting",
            "type":"Services"
        }
    ],
    "sg:phone":"+1 334 792 3212",
    "sg:postcode":"36305",
    "sg:province":"AL",
    "sg:tags":[
        "personnel",
        "consultant"
    ],
    "wof:name":"Personnel Resources",
    "wof:placetype":"venue"
},
  "geometry": {"coordinates":[-85.434917,31.219928],"type":"Point"}
}