{
  "type": "Feature",
  "properties": {
    "iso:country":"US",
    "sg:address":"153 Church St",
    "sg:city":"Section",
    "sg:classifiers":[
        {
            "category":"Organizations",
            "subcategory":"Religious Organization",
            "type":"Services"
        }
    ],
    "sg:phone":"+1 256 228 6611",
    "sg:postcode":"35771",
    "sg:province":"AL",
    "sg:tags":[
        "church"
    ],
    "wof:name":"Section Methodist Church",
    "wof:placetype":"venue"
},
  "geometry": {"coordinates":[-85.98682700000001,34.57758],"type":"Point"}
}