{
  "type": "Feature",
  "properties": {
    "iso:country":"US",
    "sg:address":"9525 US Hwy 72",
    "sg:city":"Cherokee",
    "sg:classifiers":[
        {
            "category":"Social Services",
            "type":"Services"
        }
    ],
    "sg:phone":"+1 256 359 6160",
    "sg:postcode":"35616",
    "sg:province":"AL",
    "sg:tags":[
        "youth",
        "organization",
        "center"
    ],
    "wof:name":"Cherokee Dixie Youth",
    "wof:placetype":"venue"
},
  "geometry": {"coordinates":[-87.95844099999999,34.749089],"type":"Point"}
}