{
  "type": "Feature",
  "properties": {
    "iso:country":"US",
    "sg:address":"18427 Pennsylvania St",
    "sg:city":"Robertsdale",
    "sg:classifiers":[
        {
            "category":"Restaurant",
            "type":"Food & Drink"
        }
    ],
    "sg:phone":"+1 251 947 4000",
    "sg:postcode":"36567",
    "sg:province":"AL",
    "wof:name":"Ivey's",
    "wof:placetype":"venue"
},
  "geometry": {"coordinates":[-87.70969700000001,30.554536],"type":"Point"}
}