{
  "type": "Feature",
  "properties": {
    "addr:full":"4213 31st Ave E Tuscaloosa AL 35405",
    "addr:housenumber":"4213",
    "addr:postcode":"35405",
    "addr:street":"31St Ave E",
    "iso:country":"US",
    "sg:address":"4213 31st Ave E",
    "sg:city":"Tuscaloosa",
    "sg:classifiers":[
        {
            "category":"Professional",
            "subcategory":"Computer Services",
            "type":"Services"
        }
    ],
    "sg:phone":"+1 205 553 0708",
    "sg:postcode":"35405",
    "sg:province":"AL",
    "sg:tags":[
        "repair"
    ],
    "wof:name":"Pelicom Technologies",
    "wof:placetype":"venue"
},
  "geometry": {"coordinates":[-87.497362,33.169731],"type":"Point"}
}