{
  "type": "Feature",
  "properties": {
    "addr:full":"511 Cobb St Birmingham AL 35209",
    "addr:housenumber":"511",
    "addr:postcode":"35209",
    "addr:street":"Cobb St",
    "iso:country":"US",
    "sg:address":"511 Cobb St",
    "sg:city":"Birmingham",
    "sg:classifiers":[
        {
            "category":"Professional",
            "type":"Services"
        }
    ],
    "sg:phone":"+1 205 942 3454",
    "sg:postcode":"35209",
    "sg:province":"AL",
    "sg:tags":[
        "establishment"
    ],
    "wof:name":"FBK Intl Corp",
    "wof:placetype":"venue"
},
  "geometry": {"coordinates":[-86.82639,33.461509],"type":"Point"}
}