{
  "type": "Feature",
  "properties": {
    "iso:country":"US",
    "sg:address":"2815 Forbes Dr",
    "sg:city":"Montgomery",
    "sg:classifiers":[
        {
            "category":"Organizations",
            "subcategory":"Religious Organization",
            "type":"Services"
        }
    ],
    "sg:phone":"+1 334 269 2389",
    "sg:postcode":"36110",
    "sg:province":"AL",
    "sg:tags":[
        "church"
    ],
    "wof:name":"Catholic Archdiocese-Mobile",
    "wof:placetype":"venue"
},
  "geometry": {"coordinates":[-86.28743,32.423874],"type":"Point"}
}