{
  "type": "Feature",
  "properties": {
    "addr:full":"106 E Sears St Valley AL 36854",
    "addr:housenumber":"106",
    "addr:postcode":"36854",
    "addr:street":"E Sears St",
    "iso:country":"US",
    "sg:address":"106 E Sears St",
    "sg:city":"Valley",
    "sg:classifiers":[
        {
            "category":"Retail",
            "subcategory":"Auto Repair",
            "type":"Services"
        }
    ],
    "sg:phone":"+1 334 756 4771",
    "sg:postcode":"36854",
    "sg:province":"AL",
    "sg:tags":[
        "automotive"
    ],
    "wof:name":"Advance Towing",
    "wof:placetype":"venue"
},
  "geometry": {"coordinates":[-85.191294,32.790305],"type":"Point"}
}