{
  "type": "Feature",
  "properties": {
    "iso:country":"US",
    "sg:address":"2430 Helton St",
    "sg:city":"Gadsden",
    "sg:classifiers":[
        {
            "category":"Building & Trades",
            "subcategory":"Construction",
            "type":"Services"
        }
    ],
    "sg:phone":"+1 256 543 8443",
    "sg:postcode":"35904",
    "sg:province":"AL",
    "sg:tags":[
        "siding",
        "contractor"
    ],
    "wof:name":"Carl Smith Vinyl Siding",
    "wof:placetype":"venue"
},
  "geometry": {"coordinates":[-86.046424,34.035068],"type":"Point"}
}