{
  "type": "Feature",
  "properties": {
    "iso:country":"US",
    "sg:address":"5850 Sardis Rd",
    "sg:city":"Boaz",
    "sg:classifiers":[
        {
            "category":"Organizations",
            "subcategory":"Religious Organization",
            "type":"Services"
        }
    ],
    "sg:phone":"+1 256 593 1900",
    "sg:postcode":"35956",
    "sg:province":"AL",
    "wof:name":"Bethlhem Mssnary Baptst Church",
    "wof:placetype":"venue"
},
  "geometry": {"coordinates":[-86.052548,34.182761],"type":"Point"}
}