{
  "type": "Feature",
  "properties": {
    "iso:country":"US",
    "sg:address":"315 Ball Park Rd",
    "sg:city":"Pelham",
    "sg:classifiers":[
        {
            "category":"Recreation",
            "type":"Entertainment"
        }
    ],
    "sg:phone":"+1 205 620 6428",
    "sg:postcode":"35124",
    "sg:province":"AL",
    "sg:tags":[
        "executive",
        "tennis",
        "court"
    ],
    "wof:name":"Pelham Tennis Center",
    "wof:placetype":"venue"
},
  "geometry": {"coordinates":[-86.808144,33.303593],"type":"Point"}
}