{
  "type": "Feature",
  "properties": {
    "iso:country":"US",
    "sg:address":"410 Johnston St SE",
    "sg:city":"Decatur",
    "sg:classifiers":[
        {
            "category":"Organizations",
            "subcategory":"Non-profit Organization",
            "type":"Services"
        }
    ],
    "sg:phone":"+1 256 353 6497",
    "sg:postcode":"35601",
    "sg:province":"AL",
    "sg:tags":[
        "info",
        "addiction",
        "abuse",
        "treatment",
        "drug"
    ],
    "wof:name":"Bridge Drug Counseling Ctr",
    "wof:placetype":"venue"
},
  "geometry": {"coordinates":[-86.980143,34.602872],"type":"Point"}
}