{
  "type": "Feature",
  "properties": {
    "iso:country":"US",
    "sg:address":"620 W Selma St",
    "sg:city":"Dothan",
    "sg:classifiers":[
        {
            "category":"Organizations",
            "subcategory":"Religious Organization",
            "type":"Services"
        }
    ],
    "sg:phone":"+1 334 794 2405",
    "sg:postcode":"36301",
    "sg:province":"AL",
    "sg:tags":[
        "church"
    ],
    "wof:name":"Peoples Church",
    "wof:placetype":"venue"
},
  "geometry": {"coordinates":[-85.399879,31.210124],"type":"Point"}
}