{
  "type": "Feature",
  "properties": {
    "iso:country":"US",
    "sg:address":"1223 Douglas Ave",
    "sg:city":"Brewton",
    "sg:classifiers":[
        {
            "category":"Cinema",
            "subcategory":"Movie Rental",
            "type":"Entertainment"
        }
    ],
    "sg:phone":"+1 251 867 2949",
    "sg:postcode":"36426",
    "sg:province":"AL",
    "sg:tags":[
        "video",
        "tape"
    ],
    "wof:name":"Movie Gallery",
    "wof:placetype":"venue"
},
  "geometry": {"coordinates":[-87.06871099999999,31.127059],"type":"Point"}
}