{
  "type": "Feature",
  "properties": {
    "iso:country":"US",
    "sg:address":"812 Springlake Cir NE",
    "sg:city":"Birmingham",
    "sg:classifiers":[
        {
            "category":"Retail",
            "subcategory":"Repair Shop",
            "type":"Services"
        }
    ],
    "sg:phone":"+1 205 323 4814",
    "sg:postcode":"35215",
    "sg:province":"AL",
    "sg:tags":[
        "refrigeration",
        "electrical"
    ],
    "wof:name":"Coker Appliance Service",
    "wof:placetype":"venue"
},
  "geometry": {"coordinates":[-86.670031,33.619799],"type":"Point"}
}