{
  "type": "Feature",
  "properties": {
    "iso:country":"US",
    "sg:address":"110 Tanglefoot Dr",
    "sg:city":"Huntsville",
    "sg:classifiers":[
        {
            "category":"Communications",
            "subcategory":"Film & Video Production",
            "type":"Services"
        }
    ],
    "sg:phone":"+1 256 859 0026",
    "sg:postcode":"35811",
    "sg:province":"AL",
    "sg:tags":[
        "training",
        "corporate",
        "wedding"
    ],
    "wof:name":"Innovative Video Productions",
    "wof:placetype":"venue"
},
  "geometry": {"coordinates":[-86.499315,34.791039],"type":"Point"}
}