{
  "type": "Feature",
  "properties": {
    "addr:full":"125 Alison Dr Alexander City AL 35010",
    "addr:housenumber":"125",
    "addr:postcode":"35010",
    "addr:street":"Alison Dr",
    "iso:country":"US",
    "sg:address":"125 Alison Dr",
    "sg:city":"Alexander City",
    "sg:classifiers":[
        {
            "category":"Health Services",
            "subcategory":"Doctor",
            "type":"Services"
        }
    ],
    "sg:phone":"+1 256 234 5003",
    "sg:postcode":"35010",
    "sg:province":"AL",
    "wof:name":"E Kenneth Howards Jr DMD PC",
    "wof:placetype":"venue"
},
  "geometry": {"coordinates":[-85.96966,32.929402],"type":"Point"}
}