{
  "type": "Feature",
  "properties": {
    "iso:country":"US",
    "sg:address":"221 Godwin Rd",
    "sg:city":"Tallassee",
    "sg:classifiers":[
        {
            "category":"Building & Trades",
            "subcategory":"Plumbing",
            "type":"Services"
        }
    ],
    "sg:phone":"+1 334 283 2452",
    "sg:postcode":"36078",
    "sg:province":"AL",
    "sg:tags":[
        "contractor"
    ],
    "wof:name":"Teel Plumbing Co Inc",
    "wof:placetype":"venue"
},
  "geometry": {"coordinates":[-85.906335,32.542358],"type":"Point"}
}