{
  "type": "Feature",
  "properties": {
    "addr:full":"8220 Old Federal Rd Montgomery AL 36117",
    "addr:housenumber":"8220",
    "addr:postcode":"36117",
    "addr:street":"Old Federal Rd",
    "iso:country":"US",
    "sg:address":"8220 Old Federal Rd",
    "sg:city":"Montgomery",
    "sg:classifiers":[
        {
            "category":"Professional",
            "subcategory":"Accounting & Tax Preparation",
            "type":"Services"
        }
    ],
    "sg:phone":"+1 334 271 0205",
    "sg:postcode":"36117",
    "sg:province":"AL",
    "sg:tags":[
        "accountant"
    ],
    "wof:name":"Mark Jennings & Co",
    "wof:placetype":"venue"
},
  "geometry": {"coordinates":[-86.170282,32.341598],"type":"Point"}
}