{
  "type": "Feature",
  "properties": {
    "iso:country":"US",
    "sg:address":"817 S Memorial Dr",
    "sg:city":"Prattville",
    "sg:classifiers":[
        {
            "category":"Shopping",
            "subcategory":"Used Merchandise",
            "type":"Retail Goods"
        },
        {
            "category":"Banks & Credit Unions",
            "subcategory":"Bank",
            "type":"Services"
        }
    ],
    "sg:phone":"+1 334 365 1790",
    "sg:postcode":"36067",
    "sg:province":"AL",
    "sg:tags":[
        "loan"
    ],
    "wof:name":"Fast Cash Title Exchange Inc",
    "wof:placetype":"venue"
},
  "geometry": {"coordinates":[-86.448725,32.457581],"type":"Point"}
}