{
  "type": "Feature",
  "properties": {
    "addr:full":"8801 US Hwy 231 Arab AL 35016",
    "addr:housenumber":"8801",
    "addr:postcode":"35016",
    "addr:street":"Us Hwy 231",
    "iso:country":"US",
    "sg:address":"8801 US Hwy 231",
    "sg:city":"Arab",
    "sg:classifiers":[
        {
            "category":"Sports & Exercise",
            "subcategory":"Gym",
            "type":"Entertainment"
        }
    ],
    "sg:phone":"+1 256 931 2160",
    "sg:postcode":"35016",
    "sg:province":"AL",
    "sg:tags":[
        "fitness",
        "physical",
        "facility"
    ],
    "wof:name":"Elite Fitness",
    "wof:placetype":"venue"
},
  "geometry": {"coordinates":[-86.51351200000001,34.375389],"type":"Point"}
}