{
  "type": "Feature",
  "properties": {
    "iso:country":"US",
    "sg:address":"13 Office Park Cir",
    "sg:city":"Mountain Brook",
    "sg:classifiers":[
        {
            "category":"Professional",
            "subcategory":"Engineering",
            "type":"Services"
        }
    ],
    "sg:phone":"+1 205 870 8455",
    "sg:postcode":"35223",
    "sg:province":"AL",
    "sg:tags":[
        "engineer"
    ],
    "wof:name":"Land WFPE",
    "wof:placetype":"venue"
},
  "geometry": {"coordinates":[-86.769502,33.478776],"type":"Point"}
}