{
  "type": "Feature",
  "properties": {
    "addr:full":"120 Cahaba Valley Pkwy W Pelham AL 35124",
    "addr:housenumber":"120",
    "addr:postcode":"35124",
    "addr:street":"Cahaba Valley Pkwy W",
    "iso:country":"US",
    "sg:address":"120 Cahaba Valley Pkwy W",
    "sg:city":"Pelham",
    "sg:classifiers":[
        {
            "category":"Health Services",
            "subcategory":"Doctor",
            "type":"Services"
        }
    ],
    "sg:phone":"+1 205 988 0469",
    "sg:postcode":"35124",
    "sg:province":"AL",
    "sg:tags":[
        "clinic"
    ],
    "wof:name":"Cahaba Valley Dialysis Ctr",
    "wof:placetype":"venue"
},
  "geometry": {"coordinates":[-86.78985,33.340587],"type":"Point"}
}