{
  "type": "Feature",
  "properties": {
    "iso:country":"US",
    "sg:address":"3909 N Jackson Hwy",
    "sg:city":"Sheffield",
    "sg:classifiers":[
        {
            "category":"Shopping",
            "subcategory":"Used Merchandise",
            "type":"Retail Goods"
        }
    ],
    "sg:phone":"+1 256 383 2277",
    "sg:postcode":"35660",
    "sg:province":"AL",
    "sg:tags":[
        "antique"
    ],
    "wof:name":"Unlimited Antiques",
    "wof:placetype":"venue"
},
  "geometry": {"coordinates":[-87.670681,34.770756],"type":"Point"}
}