{
  "type": "Feature",
  "properties": {
    "addr:full":"1070 Blue Pond Rd Leesburg AL 35983",
    "addr:housenumber":"1070",
    "addr:postcode":"35983",
    "addr:street":"Blue Pond Rd",
    "iso:country":"US",
    "sg:address":"1070 Blue Pond Rd",
    "sg:city":"Leesburg",
    "sg:classifiers":[
        {
            "category":"Professional",
            "type":"Services"
        }
    ],
    "sg:phone":"+1 256 526 8674",
    "sg:postcode":"35983",
    "sg:province":"AL",
    "wof:name":"Franklin Brewster",
    "wof:placetype":"venue"
},
  "geometry": {"coordinates":[-85.751171,34.195357],"type":"Point"}
}