{
  "type": "Feature",
  "properties": {
    "iso:country":"US",
    "sg:address":"1184 Ashville Rd NE",
    "sg:city":"Leeds",
    "sg:classifiers":[
        {
            "category":"Building & Trades",
            "subcategory":"Construction",
            "type":"Services"
        }
    ],
    "sg:phone":"+1 205 966 5722",
    "sg:postcode":"35094",
    "sg:province":"AL",
    "sg:tags":[
        "residential"
    ],
    "wof:name":"Cq Systems Inc",
    "wof:placetype":"venue"
},
  "geometry": {"coordinates":[-86.534057,33.55371],"type":"Point"}
}