{
  "type": "Feature",
  "properties": {
    "iso:country":"US",
    "sg:address":"107 Small St",
    "sg:city":"Albertville",
    "sg:classifiers":[
        {
            "category":"Personal",
            "subcategory":"Beauty Salon",
            "type":"Services"
        }
    ],
    "sg:phone":"+1 256 891 0222",
    "sg:postcode":"35950",
    "sg:province":"AL",
    "sg:tags":[
        "shop"
    ],
    "wof:name":"Stylistic Salon",
    "wof:placetype":"venue"
},
  "geometry": {"coordinates":[-86.222761,34.280862],"type":"Point"}
}