{
  "type": "Feature",
  "properties": {
    "addr:full":"704 Huntsville Ave Birmingham AL 35217",
    "addr:housenumber":"704",
    "addr:postcode":"35217",
    "addr:street":"Huntsville Ave",
    "iso:country":"US",
    "sg:address":"704 Huntsville Ave",
    "sg:city":"Birmingham",
    "sg:classifiers":[
        {
            "category":"Retail",
            "subcategory":"Auto Repair",
            "type":"Services"
        }
    ],
    "sg:phone":"+1 205 849 9445",
    "sg:postcode":"35217",
    "sg:province":"AL",
    "wof:name":"Specialty Automotive",
    "wof:placetype":"venue"
},
  "geometry": {"coordinates":[-86.784103,33.5742],"type":"Point"}
}