{
  "type": "Feature",
  "properties": {
    "iso:country":"US",
    "sg:address":"1385 US Hwy 31",
    "sg:city":"Prattville",
    "sg:classifiers":[
        {
            "category":"Building & Trades",
            "subcategory":"Construction",
            "type":"Services"
        }
    ],
    "sg:phone":"+1 334 358 8810",
    "sg:postcode":"36067",
    "sg:province":"AL",
    "sg:tags":[
        "nonresidential"
    ],
    "wof:name":"Metal Shop",
    "wof:placetype":"venue"
},
  "geometry": {"coordinates":[-86.432664,32.443476],"type":"Point"}
}