{
  "type": "Feature",
  "properties": {
    "iso:country":"US",
    "sg:address":"60 King St",
    "sg:city":"Atmore",
    "sg:classifiers":[
        {
            "category":"Personal",
            "subcategory":"Barber",
            "type":"Services"
        }
    ],
    "sg:phone":"+1 251 368 7080",
    "sg:postcode":"36502",
    "sg:province":"AL",
    "wof:name":"Joe's Hair Place",
    "wof:placetype":"venue"
},
  "geometry": {"coordinates":[-87.489024,31.028032],"type":"Point"}
}