{
  "type": "Feature",
  "properties": {
    "addr:full":"107 Springdale Ave Bessemer AL 35023",
    "addr:housenumber":"107",
    "addr:postcode":"35023",
    "addr:street":"Springdale Ave",
    "iso:country":"US",
    "sg:address":"107 Springdale Ave",
    "sg:city":"Bessemer",
    "sg:classifiers":[
        {
            "category":"Building & Trades",
            "subcategory":"Cleaning & Sanitation",
            "type":"Services"
        }
    ],
    "sg:phone":"+1 205 491 5827",
    "sg:postcode":"35023",
    "sg:province":"AL",
    "sg:tags":[
        "maintenance"
    ],
    "wof:name":"Realtors Friend",
    "wof:placetype":"venue"
},
  "geometry": {"coordinates":[-86.993869,33.452425],"type":"Point"}
}