{
  "type": "Feature",
  "properties": {
    "addr:full":"2140 US Hwy 78 Oxford AL 36203",
    "addr:housenumber":"2140",
    "addr:postcode":"36203",
    "addr:street":"Us Hwy 78",
    "iso:country":"US",
    "sg:address":"2140 US Hwy 78",
    "sg:city":"Oxford",
    "sg:classifiers":[
        {
            "category":"Organizations",
            "subcategory":"Religious Organization",
            "type":"Services"
        }
    ],
    "sg:phone":"+1 256 831 0651",
    "sg:postcode":"36203",
    "sg:province":"AL",
    "sg:tags":[
        "church"
    ],
    "wof:name":"Church-Christ-Betta View Hills",
    "wof:placetype":"venue"
},
  "geometry": {"coordinates":[-85.881309,33.592903],"type":"Point"}
}