{
  "type": "Feature",
  "properties": {
    "addr:full":"2819 E Meighan Blvd Gadsden AL 35903",
    "addr:housenumber":"2819",
    "addr:postcode":"35903",
    "addr:street":"E Meighan Blvd",
    "iso:country":"US",
    "sg:address":"2819 E Meighan Blvd",
    "sg:city":"Gadsden",
    "sg:classifiers":[
        {
            "category":"Retail",
            "subcategory":"Auto Repair",
            "type":"Services"
        }
    ],
    "sg:phone":"+1 256 492 2869",
    "sg:postcode":"35903",
    "sg:province":"AL",
    "sg:tags":[
        "truck"
    ],
    "wof:name":"Clowdus Garage",
    "wof:placetype":"venue"
},
  "geometry": {"coordinates":[-85.95470299999999,33.977636],"type":"Point"}
}