{
  "type": "Feature",
  "properties": {
    "iso:country":"US",
    "sg:address":"705 S Main St",
    "sg:city":"Wetumpka",
    "sg:classifiers":[
        {
            "category":"Home & Garden",
            "subcategory":"Building Materials",
            "type":"Retail Goods"
        }
    ],
    "sg:phone":"+1 334 567 5266",
    "sg:postcode":"36092",
    "sg:province":"AL",
    "sg:tags":[
        "mixed",
        "concrete"
    ],
    "wof:name":"Strickland Brothers Ready Mix",
    "wof:placetype":"venue"
},
  "geometry": {"coordinates":[-86.207024,32.529033],"type":"Point"}
}