{
  "type": "Feature",
  "properties": {
    "addr:full":"703 Columbia Hwy Dothan AL 36301",
    "addr:housenumber":"703",
    "addr:postcode":"36301",
    "addr:street":"Columbia Hwy",
    "iso:country":"US",
    "sg:address":"703 Columbia Hwy",
    "sg:city":"Dothan",
    "sg:classifiers":[
        {
            "category":"Building & Trades",
            "subcategory":"Plumbing",
            "type":"Services"
        }
    ],
    "sg:phone":"+1 334 792 8002",
    "sg:postcode":"36301",
    "sg:province":"AL",
    "sg:tags":[
        "conditioning",
        "air",
        "system",
        "contractor"
    ],
    "wof:name":"Smith Heating & Cooling",
    "wof:placetype":"venue"
},
  "geometry": {"coordinates":[-85.380368,31.221291],"type":"Point"}
}