{
  "type": "Feature",
  "properties": {
    "iso:country":"US",
    "sg:address":"614 State Rte 165",
    "sg:city":"Fort Mitchell",
    "sg:classifiers":[
        {
            "category":"Food & Beverages",
            "subcategory":"Groceries & Convenience Stores",
            "type":"Retail Goods"
        }
    ],
    "sg:phone":"+1 334 855 4790",
    "sg:postcode":"36856",
    "sg:province":"AL",
    "wof:name":"Petro Food Mart",
    "wof:placetype":"venue"
},
  "geometry": {"coordinates":[-85.020285,32.338267],"type":"Point"}
}