{
  "type": "Feature",
  "properties": {
    "iso:country":"US",
    "sg:address":"212 Rome Ave",
    "sg:city":"Piedmont",
    "sg:classifiers":[
        {
            "category":"Health Services",
            "subcategory":"Chiropractor",
            "type":"Services"
        }
    ],
    "sg:phone":"+1 256 447 2366",
    "sg:postcode":"36272",
    "sg:province":"AL",
    "wof:name":"Family Chiropractic Office",
    "wof:placetype":"venue"
},
  "geometry": {"coordinates":[-85.619808,33.921218],"type":"Point"}
}