{
  "type": "Feature",
  "properties": {
    "iso:country":"US",
    "sg:address":"458 Dauphin Island Pkwy",
    "sg:city":"Mobile",
    "sg:classifiers":[
        {
            "category":"Personal",
            "subcategory":"Beauty Salon",
            "type":"Services"
        }
    ],
    "sg:phone":"+1 251 473 3919",
    "sg:postcode":"36606",
    "sg:province":"AL",
    "sg:tags":[
        "shop"
    ],
    "wof:name":"Salon De Renee",
    "wof:placetype":"venue"
},
  "geometry": {"coordinates":[-88.087142,30.673777],"type":"Point"}
}