{
  "type": "Feature",
  "properties": {
    "iso:country":"US",
    "sg:address":"2855 Ross Clark Cir",
    "sg:city":"Dothan",
    "sg:classifiers":[
        {
            "category":"Banks & Credit Unions",
            "subcategory":"Bank",
            "type":"Services"
        }
    ],
    "sg:phone":"+1 334 793 2662",
    "sg:postcode":"36301",
    "sg:province":"AL",
    "sg:tags":[
        "loan"
    ],
    "wof:name":"First South PCA",
    "wof:placetype":"venue"
},
  "geometry": {"coordinates":[-85.430219,31.214675],"type":"Point"}
}