{
  "type": "Feature",
  "properties": {
    "addr:full":"340 Technacenter Dr Montgomery AL 36117",
    "addr:housenumber":"340",
    "addr:postcode":"36117",
    "addr:street":"Technacenter Dr",
    "iso:country":"US",
    "sg:address":"340 Technacenter Dr",
    "sg:city":"Montgomery",
    "sg:classifiers":[
        {
            "category":"Manufacturing",
            "subcategory":"Printing",
            "type":"Manufacturing & Wholesale Goods"
        }
    ],
    "sg:phone":"+1 334 215 2737",
    "sg:postcode":"36117",
    "sg:province":"AL",
    "sg:tags":[
        "publisher"
    ],
    "sg:website":"www.alabamaliving.com",
    "wof:name":"Alabama Living Magazine",
    "wof:placetype":"venue"
},
  "geometry": {"coordinates":[-86.137595,32.37091],"type":"Point"}
}