{
  "type": "Feature",
  "properties": {
    "iso:country":"US",
    "sg:address":"116 4th St SW",
    "sg:city":"Cullman",
    "sg:classifiers":[
        {
            "category":"Shopping",
            "subcategory":"Clothing, Apparel, & Fashions",
            "type":"Retail Goods"
        }
    ],
    "sg:phone":"+1 256 734 4404",
    "sg:postcode":"35070",
    "sg:province":"AL",
    "wof:name":"LA Rae Renea",
    "wof:placetype":"venue"
},
  "geometry": {"coordinates":[-86.750149,34.011876],"type":"Point"}
}