{
  "type": "Feature",
  "properties": {
    "iso:country":"US",
    "sg:address":"5555 US Hwy 431",
    "sg:city":"Albertville",
    "sg:classifiers":[
        {
            "category":"Retail",
            "subcategory":"Auto Repair",
            "type":"Services"
        }
    ],
    "sg:phone":"+1 256 878 1912",
    "sg:postcode":"35950",
    "sg:province":"AL",
    "sg:tags":[
        "repairing",
        "automobile",
        "general"
    ],
    "wof:name":"Bruce Foreign Car Service",
    "wof:placetype":"venue"
},
  "geometry": {"coordinates":[-86.186281,34.258909],"type":"Point"}
}