{
  "type": "Feature",
  "properties": {
    "iso:country":"US",
    "sg:address":"700 N Brindlee Mountain Pkwy",
    "sg:city":"Arab",
    "sg:classifiers":[
        {
            "category":"Restaurant",
            "type":"Food & Drink"
        }
    ],
    "sg:menulink":"http://www.allmenus.com/al/arab/190103-mcdonalds/menu/",
    "sg:postcode":"35016",
    "sg:province":"AL",
    "sg:tags":[
        "burger",
        "american"
    ],
    "wof:name":"McDonald's",
    "wof:placetype":"venue"
},
  "geometry": {"coordinates":[-86.502866,34.326234],"type":"Point"}
}