{
  "type": "Feature",
  "properties": {
    "iso:country":"US",
    "sg:address":"5 Tony Dr",
    "sg:city":"Phenix City",
    "sg:classifiers":[
        {
            "category":"Professional",
            "subcategory":"Art Services",
            "type":"Services"
        }
    ],
    "sg:phone":"+1 334 298 7281",
    "sg:postcode":"36869",
    "sg:province":"AL",
    "sg:tags":[
        "photo",
        "photography",
        "commercial",
        "studio",
        "portrait"
    ],
    "wof:name":"Ritz Studio",
    "wof:placetype":"venue"
},
  "geometry": {"coordinates":[-85.065595,32.385683],"type":"Point"}
}