{
  "type": "Feature",
  "properties": {
    "addr:full":"258 State Rte 36 Hartselle AL 35640",
    "addr:housenumber":"258",
    "addr:postcode":"35640",
    "addr:street":"State Rte 36",
    "iso:country":"US",
    "sg:address":"258 State Rte 36",
    "sg:city":"Hartselle",
    "sg:classifiers":[
        {
            "category":"Autos & Motor Vehicles",
            "subcategory":"Automobile Sales",
            "type":"Retail Goods"
        }
    ],
    "sg:phone":"+1 256 751 1698",
    "sg:postcode":"35640",
    "sg:province":"AL",
    "sg:tags":[
        "new",
        "used",
        "dealer",
        "car"
    ],
    "wof:name":"Miller Auto Sales",
    "wof:placetype":"venue"
},
  "geometry": {"coordinates":[-86.8905,34.448632],"type":"Point"}
}