{
  "type": "Feature",
  "properties": {
    "iso:country":"US",
    "sg:address":"1181 Whigham Pl",
    "sg:city":"Tuscaloosa",
    "sg:classifiers":[
        {
            "category":"Home & Garden",
            "subcategory":"Building Materials",
            "type":"Retail Goods"
        }
    ],
    "sg:phone":"+1 205 345 8588",
    "sg:postcode":"35405",
    "sg:province":"AL",
    "sg:tags":[
        "door"
    ],
    "wof:name":"Overhead Door Corp",
    "wof:placetype":"venue"
},
  "geometry": {"coordinates":[-87.554271,33.159313],"type":"Point"}
}