{
  "type": "Feature",
  "properties": {
    "iso:country":"US",
    "sg:address":"9 18th St SW",
    "sg:city":"Birmingham",
    "sg:classifiers":[
        {
            "category":"Retail",
            "subcategory":"Auto Repair",
            "type":"Services"
        }
    ],
    "sg:phone":"+1 205 781 7051",
    "sg:postcode":"35211",
    "sg:province":"AL",
    "sg:tags":[
        "body"
    ],
    "wof:name":"Precision Auto Body",
    "wof:placetype":"venue"
},
  "geometry": {"coordinates":[-86.866805,33.494652],"type":"Point"}
}