{
  "type": "Feature",
  "properties": {
    "iso:country":"US",
    "sg:address":"121 17th St W",
    "sg:city":"Jasper",
    "sg:classifiers":[
        {
            "category":"Government",
            "subcategory":"Office",
            "type":"Public Place"
        }
    ],
    "sg:phone":"+1 205 384 9349",
    "sg:postcode":"35501",
    "sg:province":"AL",
    "sg:tags":[
        "village"
    ],
    "wof:name":"Jasper City Auditorium",
    "wof:placetype":"venue"
},
  "geometry": {"coordinates":[-87.27603000000001,33.834761],"type":"Point"}
}