{
  "type": "Feature",
  "properties": {
    "iso:country":"US",
    "sg:address":"193 S Herring Rd",
    "sg:city":"Opelika",
    "sg:phone":"+1 334 298 0208",
    "sg:postcode":"36804",
    "sg:province":"AL",
    "sg:tags":[
        "scale"
    ],
    "wof:name":"Bizerba USA",
    "wof:placetype":"venue"
},
  "geometry": {"coordinates":[-85.278869,32.420299],"type":"Point"}
}