{
  "type": "Feature",
  "properties": {
    "addr:full":"4121 Wall St Montgomery AL 36106",
    "addr:housenumber":"4121",
    "addr:postcode":"36106",
    "addr:street":"Wall St",
    "iso:country":"US",
    "sg:address":"4121 Wall St",
    "sg:city":"Montgomery",
    "sg:classifiers":[
        {
            "category":"Professional",
            "subcategory":"Management & Consulting",
            "type":"Services"
        }
    ],
    "sg:phone":"+1 334 396 8952",
    "sg:postcode":"36106",
    "sg:province":"AL",
    "sg:tags":[
        "communications",
        "consultant"
    ],
    "wof:name":"Southern Communications",
    "wof:placetype":"venue"
},
  "geometry": {"coordinates":[-86.23352199999999,32.359936],"type":"Point"}
}