{
  "type": "Feature",
  "properties": {
    "iso:country":"US",
    "sg:address":"116 W 2nd St",
    "sg:city":"Sylacauga",
    "sg:classifiers":[
        {
            "category":"Shopping",
            "subcategory":"Used Merchandise",
            "type":"Retail Goods"
        }
    ],
    "sg:phone":"+1 256 245 1932",
    "sg:postcode":"35150",
    "sg:province":"AL",
    "wof:name":"Broadway Pawn Shop",
    "wof:placetype":"venue"
},
  "geometry": {"coordinates":[-86.251617,33.17047],"type":"Point"}
}