{
  "type": "Feature",
  "properties": {
    "iso:country":"US",
    "sg:address":"3514 Conger Rd SW",
    "sg:city":"Huntsville",
    "sg:classifiers":[
        {
            "category":"Professional",
            "subcategory":"Accounting & Tax Preparation",
            "type":"Services"
        }
    ],
    "sg:phone":"+1 256 881 0300",
    "sg:postcode":"35805",
    "sg:province":"AL",
    "wof:name":"Tax Accounting Bookkeeping Svc",
    "wof:placetype":"venue"
},
  "geometry": {"coordinates":[-86.61922800000001,34.689218],"type":"Point"}
}