{
  "type": "Feature",
  "properties": {
    "iso:country":"US",
    "sg:address":"9681 15th Street Rd",
    "sg:city":"Bessemer",
    "sg:classifiers":[
        {
            "category":"Organizations",
            "subcategory":"Religious Organization",
            "type":"Services"
        }
    ],
    "sg:phone":"+1 205 491 8350",
    "sg:postcode":"35023",
    "sg:province":"AL",
    "wof:name":"Mud Creek Baptist Associaiton",
    "wof:placetype":"venue"
},
  "geometry": {"coordinates":[-87.06139899999999,33.477128],"type":"Point"}
}