{
  "type": "Feature",
  "properties": {
    "iso:country":"US",
    "sg:address":"1589 Darby Dr",
    "sg:city":"Florence",
    "sg:classifiers":[
        {
            "category":"Shopping",
            "subcategory":"Bicycles & Sporting Goods",
            "type":"Retail Goods"
        }
    ],
    "sg:phone":"+1 256 766 0966",
    "sg:postcode":"35630",
    "sg:province":"AL",
    "wof:name":"First Place Athletics",
    "wof:placetype":"venue"
},
  "geometry": {"coordinates":[-87.657189,34.819319],"type":"Point"}
}