{
  "type": "Feature",
  "properties": {
    "iso:country":"US",
    "sg:address":"118 Countryside Ln",
    "sg:city":"Bessemer",
    "sg:classifiers":[
        {
            "category":"Retail",
            "subcategory":"Auto Repair",
            "type":"Services"
        }
    ],
    "sg:phone":"+1 205 425 3035",
    "sg:postcode":"35022",
    "sg:province":"AL",
    "sg:tags":[
        "automotive"
    ],
    "wof:name":"Ravco Inc",
    "wof:placetype":"venue"
},
  "geometry": {"coordinates":[-86.913777,33.301949],"type":"Point"}
}