{
  "type": "Feature",
  "properties": {
    "addr:full":"1045 State Rte 119 Alabaster AL 35007",
    "addr:housenumber":"1045",
    "addr:postcode":"35007",
    "addr:street":"State Rte 119",
    "iso:country":"US",
    "sg:address":"1045 State Rte 119",
    "sg:city":"Alabaster",
    "sg:classifiers":[
        {
            "category":"Retail",
            "subcategory":"Car Wash",
            "type":"Services"
        }
    ],
    "sg:phone":"+1 205 663 1633",
    "sg:postcode":"35007",
    "sg:province":"AL",
    "sg:tags":[
        "carwash"
    ],
    "wof:name":"Alabaster Car-Care & Detailing",
    "wof:placetype":"venue"
},
  "geometry": {"coordinates":[-86.814654,33.252524],"type":"Point"}
}