{
  "type": "Feature",
  "properties": {
    "iso:country":"US",
    "sg:address":"170 Graphics Drive",
    "sg:city":"Madison",
    "sg:classifiers":[
        {
            "category":"Professional",
            "subcategory":"Computer Services",
            "type":"Services"
        }
    ],
    "sg:phone":"+1 256 730 2000",
    "sg:postcode":"35758",
    "sg:province":"AL",
    "sg:website":"http://www.intergraph.com",
    "wof:name":"Intergraph",
    "wof:placetype":"venue"
},
  "geometry": {"coordinates":[-86.750331,34.672378],"type":"Point"}
}