{
  "type": "Feature",
  "properties": {
    "iso:country":"US",
    "sg:address":"327 Columbus St E",
    "sg:city":"Fayette",
    "sg:classifiers":[
        {
            "category":"Insurance",
            "subcategory":"Insurance Agent",
            "type":"Services"
        }
    ],
    "sg:phone":"+1 205 932 6796",
    "sg:postcode":"35555",
    "sg:province":"AL",
    "wof:name":"State Farm Insurance",
    "wof:placetype":"venue"
},
  "geometry": {"coordinates":[-87.82769,33.684523],"type":"Point"}
}