{
  "type": "Feature",
  "properties": {
    "iso:country":"US",
    "sg:address":"201 Hargrove Rd E",
    "sg:city":"Tuscaloosa",
    "sg:classifiers":[
        {
            "category":"Shopping",
            "subcategory":"Department Store",
            "type":"Retail Goods"
        }
    ],
    "sg:phone":"+1 205 752 4903",
    "sg:postcode":"35401",
    "sg:province":"AL",
    "sg:tags":[
        "shop"
    ],
    "wof:name":"Discount C Store Inc",
    "wof:placetype":"venue"
},
  "geometry": {"coordinates":[-87.533639,33.188555],"type":"Point"}
}