{
  "type": "Feature",
  "properties": {
    "iso:country":"US",
    "sg:address":"702 27th Pl S",
    "sg:city":"Birmingham",
    "sg:classifiers":[
        {
            "category":"Wholesale",
            "subcategory":"Medical Equipment & Supplies",
            "type":"Manufacturing & Wholesale Goods"
        }
    ],
    "sg:phone":"+1 205 328 1701",
    "sg:postcode":"35233",
    "sg:province":"AL",
    "sg:tags":[
        "therapy"
    ],
    "wof:name":"Blue Gel Company",
    "wof:placetype":"venue"
},
  "geometry": {"coordinates":[-86.789611,33.510247],"type":"Point"}
}