{
  "type": "Feature",
  "properties": {
    "iso:country":"US",
    "sg:address":"1544 Temple Ave N",
    "sg:city":"Fayette",
    "sg:classifiers":[
        {
            "category":"Shopping",
            "subcategory":"Department Store",
            "type":"Retail Goods"
        }
    ],
    "sg:phone":"+1 205 904 8515",
    "sg:postcode":"35555",
    "sg:province":"AL",
    "wof:name":"Sears Roebuck & Co",
    "wof:placetype":"venue"
},
  "geometry": {"coordinates":[-87.825733,33.704628],"type":"Point"}
}