{
  "type": "Feature",
  "properties": {
    "addr:full":"22 Tecumseh Dr Montgomery AL 36117",
    "addr:housenumber":"22",
    "addr:postcode":"36117",
    "addr:street":"Tecumseh Dr",
    "iso:country":"US",
    "sg:address":"22 Tecumseh Dr",
    "sg:city":"Montgomery",
    "sg:classifiers":[
        {
            "category":"Wholesale",
            "subcategory":"Electrical",
            "type":"Manufacturing & Wholesale Goods"
        }
    ],
    "sg:phone":"+1 334 396 5540",
    "sg:postcode":"36117",
    "sg:province":"AL",
    "sg:tags":[
        "equipment",
        "parts",
        "electronic"
    ],
    "wof:name":"M Y A Incorporated",
    "wof:placetype":"venue"
},
  "geometry": {"coordinates":[-86.144886,32.381247],"type":"Point"}
}