{
  "type": "Feature",
  "properties": {
    "iso:country":"US",
    "sg:address":"314 2nd Ave SE",
    "sg:city":"Fayette",
    "sg:classifiers":[
        {
            "category":"Professional",
            "subcategory":"Accounting & Tax Preparation",
            "type":"Services"
        }
    ],
    "sg:phone":"+1 205 932 6632",
    "sg:postcode":"35555",
    "sg:province":"AL",
    "wof:name":"Charles Aderholt",
    "wof:placetype":"venue"
},
  "geometry": {"coordinates":[-87.829054,33.682476],"type":"Point"}
}