{
  "type": "Feature",
  "properties": {
    "iso:country":"US",
    "sg:address":"2637 3rd St NE",
    "sg:city":"Birmingham",
    "sg:classifiers":[
        {
            "category":"Professional",
            "subcategory":"Detective & Security Services",
            "type":"Services"
        }
    ],
    "sg:phone":"+1 205 854 2899",
    "sg:postcode":"35215",
    "sg:province":"AL",
    "sg:tags":[
        "system"
    ],
    "wof:name":"Security By Elmore Inc",
    "wof:placetype":"venue"
},
  "geometry": {"coordinates":[-86.676447,33.65544],"type":"Point"}
}