{
  "type": "Feature",
  "properties": {
    "addr:full":"2328 Bluff Rd Birmingham AL 35226",
    "addr:housenumber":"2328",
    "addr:postcode":"35226",
    "addr:street":"Bluff Rd",
    "iso:country":"US",
    "sg:address":"2328 Bluff Rd",
    "sg:city":"Birmingham",
    "sg:classifiers":[
        {
            "category":"Building & Trades",
            "subcategory":"Construction",
            "type":"Services"
        }
    ],
    "sg:phone":"+1 205 979 9084",
    "sg:postcode":"35226",
    "sg:province":"AL",
    "sg:tags":[
        "contractor"
    ],
    "wof:name":"Baker Roofing",
    "wof:placetype":"venue"
},
  "geometry": {"coordinates":[-86.844712,33.408944],"type":"Point"}
}