{
  "type": "Feature",
  "properties": {
    "addr:full":"1015 Medical Center Pkwy Selma AL 36701",
    "addr:housenumber":"1015",
    "addr:postcode":"36701",
    "addr:street":"Medical Center Pkwy",
    "iso:country":"US",
    "sg:address":"1015 Medical Center Pkwy",
    "sg:city":"Selma",
    "sg:classifiers":[
        {
            "category":"Banks & Credit Unions",
            "subcategory":"Bank",
            "type":"Services"
        }
    ],
    "sg:phone":"+1 334 876 9886",
    "sg:postcode":"36701",
    "sg:province":"AL",
    "wof:name":"Peoples Bank & Trust Co",
    "wof:placetype":"venue"
},
  "geometry": {"coordinates":[-87.05301799999999,32.428371],"type":"Point"}
}