{
  "type": "Feature",
  "properties": {
    "addr:full":"1433 Panorama Dr Birmingham AL 35216",
    "addr:housenumber":"1433",
    "addr:postcode":"35216",
    "addr:street":"Panorama Dr",
    "iso:country":"US",
    "sg:address":"1433 Panorama Dr",
    "sg:city":"Birmingham",
    "sg:classifiers":[
        {
            "category":"Wholesale",
            "subcategory":"Home Furnishings",
            "type":"Manufacturing & Wholesale Goods"
        }
    ],
    "sg:phone":"+1 205 978 0603",
    "sg:postcode":"35216",
    "sg:province":"AL",
    "sg:tags":[
        "steel",
        "stainless",
        "cookware"
    ],
    "wof:name":"First Amer Credit",
    "wof:placetype":"venue"
},
  "geometry": {"coordinates":[-86.778487,33.430217],"type":"Point"}
}