{
  "type": "Feature",
  "properties": {
    "iso:country":"US",
    "sg:address":"230 N 3rd St",
    "sg:city":"Gadsden",
    "sg:classifiers":[
        {
            "category":"Banks & Credit Unions",
            "subcategory":"Bank",
            "type":"Services"
        }
    ],
    "sg:phone":"+1 256 547 2572",
    "sg:postcode":"35901",
    "sg:province":"AL",
    "sg:website":"www.exba.com",
    "wof:name":"Exchange Bank",
    "wof:placetype":"venue"
},
  "geometry": {"coordinates":[-86.001147,34.01345],"type":"Point"}
}