{
  "type": "Feature",
  "properties": {
    "addr:full":"5101 Pike Rd Pike Road AL 36064",
    "addr:housenumber":"5101",
    "addr:postcode":"36064",
    "addr:street":"Pike Rd Pike Road",
    "iso:country":"US",
    "sg:address":"5101 Pike Rd",
    "sg:city":"Pike Road",
    "sg:classifiers":[
        {
            "category":"Freight",
            "type":"Transportation"
        }
    ],
    "sg:phone":"+1 334 288 5230",
    "sg:postcode":"36064",
    "sg:province":"AL",
    "sg:tags":[
        "operator",
        "local",
        "trucking"
    ],
    "wof:name":"Tri County Trucking LLC",
    "wof:placetype":"venue"
},
  "geometry": {"coordinates":[-86.10223499999999,32.279855],"type":"Point"}
}