{
  "type": "Feature",
  "properties": {
    "iso:country":"US",
    "sg:address":"2570 Callaway Rd",
    "sg:city":"Gulf Shores",
    "sg:classifiers":[
        {
            "category":"Personal",
            "subcategory":"Beauty Salon",
            "type":"Services"
        }
    ],
    "sg:phone":"+1 251 968 7103",
    "sg:postcode":"36542",
    "sg:province":"AL",
    "sg:tags":[
        "shop"
    ],
    "wof:name":"Fingers & Toes By Carole",
    "wof:placetype":"venue"
},
  "geometry": {"coordinates":[-87.719599,30.261107],"type":"Point"}
}