{
  "type": "Feature",
  "properties": {
    "iso:country":"US",
    "sg:address":"6284 US Hwy 431",
    "sg:city":"Albertville",
    "sg:classifiers":[
        {
            "category":"Shopping",
            "subcategory":"Shoes",
            "type":"Retail Goods"
        }
    ],
    "sg:phone":"+1 256 878 4000",
    "sg:postcode":"35950",
    "sg:province":"AL",
    "sg:tags":[
        "boot"
    ],
    "wof:name":"Trading Post The",
    "wof:placetype":"venue"
},
  "geometry": {"coordinates":[-86.194157,34.267983],"type":"Point"}
}