{
  "type": "Feature",
  "properties": {
    "addr:full":"317 W Clay St Sylacauga AL 35150",
    "addr:housenumber":"317",
    "addr:postcode":"35150",
    "addr:street":"W Clay St",
    "iso:country":"US",
    "sg:address":"317 W Clay St",
    "sg:city":"Sylacauga",
    "sg:classifiers":[
        {
            "category":"Professional",
            "type":"Services"
        }
    ],
    "sg:phone":"+1 256 249 4518",
    "sg:postcode":"35150",
    "sg:province":"AL",
    "wof:name":"Grass & More",
    "wof:placetype":"venue"
},
  "geometry": {"coordinates":[-86.257036,33.161289],"type":"Point"}
}