{
  "type": "Feature",
  "properties": {
    "iso:country":"US",
    "sg:address":"1006 3rd Ave",
    "sg:city":"Opelika",
    "sg:classifiers":[
        {
            "category":"Professional",
            "type":"Services"
        }
    ],
    "sg:phone":"+1 334 749 4714",
    "sg:postcode":"36801",
    "sg:province":"AL",
    "wof:name":"Cat Island Studios",
    "wof:placetype":"venue"
},
  "geometry": {"coordinates":[-85.385554,32.648546],"type":"Point"}
}