{
  "type": "Feature",
  "properties": {
    "iso:country":"US",
    "sg:address":"1250 Opelika Rd",
    "sg:city":"Auburn",
    "sg:classifiers":[
        {
            "category":"Retail",
            "subcategory":"Auto Repair",
            "type":"Services"
        }
    ],
    "sg:phone":"+1 334 821 6033",
    "sg:postcode":"36830",
    "sg:province":"AL",
    "sg:tags":[
        "wrecker"
    ],
    "wof:name":"Auburn Master Towing",
    "wof:placetype":"venue"
},
  "geometry": {"coordinates":[-85.457432,32.620643],"type":"Point"}
}