{
  "type": "Feature",
  "properties": {
    "iso:country":"US",
    "sg:address":"1765 Moore Place Rd",
    "sg:city":"Livingston",
    "sg:classifiers":[
        {
            "category":"Organizations",
            "subcategory":"Religious Organization",
            "type":"Services"
        }
    ],
    "sg:phone":"+1 205 652 7996",
    "sg:postcode":"35470",
    "sg:province":"AL",
    "wof:name":"Christian Fllwshp Word of Life",
    "wof:placetype":"venue"
},
  "geometry": {"coordinates":[-88.098658,32.558288],"type":"Point"}
}