{
  "type": "Feature",
  "properties": {
    "iso:country":"US",
    "sg:address":"3150 9th Ct",
    "sg:city":"Tuscaloosa",
    "sg:classifiers":[
        {
            "category":"Recreation",
            "type":"Entertainment"
        }
    ],
    "sg:phone":"+1 205 345 0999",
    "sg:postcode":"35401",
    "sg:province":"AL",
    "sg:tags":[
        "instruction",
        "gymnastic"
    ],
    "wof:name":"Tuscaloosa Tumbling Tides",
    "wof:placetype":"venue"
},
  "geometry": {"coordinates":[-87.549181,33.181494],"type":"Point"}
}