{
  "type": "Feature",
  "properties": {
    "iso:country":"US",
    "sg:address":"319 Shelby Forest Dr",
    "sg:city":"Chelsea",
    "sg:classifiers":[
        {
            "category":"Food & Beverages",
            "subcategory":"Liquor & Beverages",
            "type":"Retail Goods"
        }
    ],
    "sg:phone":"+1 205 678 2327",
    "sg:postcode":"35043",
    "sg:province":"AL",
    "sg:tags":[
        "alcoholic"
    ],
    "wof:name":"Chelsea Spirits LLC",
    "wof:placetype":"venue"
},
  "geometry": {"coordinates":[-86.669453,33.286864],"type":"Point"}
}