{
  "type": "Feature",
  "properties": {
    "iso:country":"US",
    "sg:address":"18706 Orchard Dr",
    "sg:city":"Summerdale",
    "sg:classifiers":[
        {
            "category":"Building & Trades",
            "subcategory":"Construction",
            "type":"Services"
        }
    ],
    "sg:phone":"+1 251 989 6858",
    "sg:postcode":"36580",
    "sg:province":"AL",
    "sg:tags":[
        "contractor"
    ],
    "wof:name":"Garcia Drywall",
    "wof:placetype":"venue"
},
  "geometry": {"coordinates":[-87.638582,30.499919],"type":"Point"}
}