{
  "type": "Feature",
  "properties": {
    "iso:country":"US",
    "sg:address":"211 S 5th St",
    "sg:city":"Gadsden",
    "sg:classifiers":[
        {
            "category":"Professional",
            "subcategory":"Advertising",
            "type":"Services"
        }
    ],
    "sg:phone":"+1 256 546 9599",
    "sg:postcode":"35901",
    "sg:province":"AL",
    "sg:tags":[
        "counselor"
    ],
    "wof:name":"Exposure Ink",
    "wof:placetype":"venue"
},
  "geometry": {"coordinates":[-86.006085,34.011742],"type":"Point"}
}