{
  "type": "Feature",
  "properties": {
    "addr:full":"4928 Co Rd 107 Scottsboro AL 35768",
    "addr:housenumber":"4928",
    "addr:postcode":"35768",
    "addr:street":"Co Rd 107",
    "iso:country":"US",
    "sg:address":"4928 Co Rd 107",
    "sg:city":"Scottsboro",
    "sg:classifiers":[
        {
            "category":"Manufacturing",
            "subcategory":"Lumber",
            "type":"Manufacturing & Wholesale Goods"
        }
    ],
    "sg:phone":"+1 256 587 3316",
    "sg:postcode":"35768",
    "sg:province":"AL",
    "sg:tags":[
        "logging"
    ],
    "wof:name":"Phillip Dean Logging",
    "wof:placetype":"venue"
},
  "geometry": {"coordinates":[-86.098399,34.821013],"type":"Point"}
}