{
  "type": "Feature",
  "properties": {
    "iso:country":"US",
    "sg:address":"4730 McFarland Blvd E",
    "sg:city":"Tuscaloosa",
    "sg:classifiers":[
        {
            "category":"Shopping",
            "subcategory":"Computers & Home Electronics",
            "type":"Retail Goods"
        }
    ],
    "sg:phone":"+1 205 752 5090",
    "sg:postcode":"35405",
    "sg:province":"AL",
    "sg:tags":[
        "television",
        "radio"
    ],
    "wof:name":"Rex TV & Appliances",
    "wof:placetype":"venue"
},
  "geometry": {"coordinates":[-87.525674,33.166694],"type":"Point"}
}