{
  "type": "Feature",
  "properties": {
    "iso:country":"US",
    "sg:address":"1609 Belle Cir",
    "sg:city":"Opelika",
    "sg:classifiers":[
        {
            "category":"Retail",
            "subcategory":"Repair Shop",
            "type":"Services"
        }
    ],
    "sg:phone":"+1 334 749 1999",
    "sg:postcode":"36801",
    "sg:province":"AL",
    "sg:tags":[
        "refrigeration"
    ],
    "wof:name":"Steve Hanson",
    "wof:placetype":"venue"
},
  "geometry": {"coordinates":[-85.342939,32.667872],"type":"Point"}
}