{
  "type": "Feature",
  "properties": {
    "iso:country":"US",
    "sg:address":"3664 Dauphin St",
    "sg:city":"Mobile",
    "sg:classifiers":[
        {
            "category":"Real Estate",
            "subcategory":"Real Estate Agent",
            "type":"Services"
        }
    ],
    "sg:phone":"+1 251 344 9220",
    "sg:postcode":"36608",
    "sg:province":"AL",
    "sg:website":"www.robertsbrothers.com",
    "wof:name":"Roberts Brothers Real Estate",
    "wof:placetype":"venue"
},
  "geometry": {"coordinates":[-88.13378400000001,30.685563],"type":"Point"}
}