{
  "type": "Feature",
  "properties": {
    "iso:country":"US",
    "sg:address":"801 Princeton Ave SW",
    "sg:city":"Birmingham",
    "sg:classifiers":[
        {
            "category":"Health Services",
            "subcategory":"Doctor",
            "type":"Services"
        }
    ],
    "sg:phone":"+1 205 788 9567",
    "sg:postcode":"35211",
    "sg:province":"AL",
    "sg:tags":[
        "physician",
        "surgeon"
    ],
    "wof:name":"BMC Pathology Group",
    "wof:placetype":"venue"
},
  "geometry": {"coordinates":[-86.849215,33.497231],"type":"Point"}
}