{
  "type": "Feature",
  "properties": {
    "addr:full":"2310 Whitesburg Dr S Huntsville AL 35801",
    "addr:housenumber":"2310",
    "addr:postcode":"35801",
    "addr:street":"Whitesburg Dr S",
    "iso:country":"US",
    "sg:address":"2310 Whitesburg Dr S",
    "sg:city":"Huntsville",
    "sg:classifiers":[
        {
            "category":"Health Services",
            "subcategory":"Medical Lab",
            "type":"Services"
        }
    ],
    "sg:phone":"+1 256 534 6298",
    "sg:postcode":"35801",
    "sg:province":"AL",
    "sg:tags":[
        "laboratory"
    ],
    "wof:name":"Hall's Orthodontic Appliance",
    "wof:placetype":"venue"
},
  "geometry": {"coordinates":[-86.576801,34.716008],"type":"Point"}
}