{
  "type": "Feature",
  "properties": {
    "iso:country":"US",
    "sg:address":"2239 3rd Ave",
    "sg:city":"Dothan",
    "sg:classifiers":[
        {
            "category":"Shopping",
            "type":"Retail Goods"
        }
    ],
    "sg:phone":"+1 334 702 1200",
    "sg:postcode":"36301",
    "sg:province":"AL",
    "sg:tags":[
        "equipment",
        "hot",
        "tub",
        "pool",
        "sauna"
    ],
    "wof:name":"Family Pool Spa Billiard Ctrs",
    "wof:placetype":"venue"
},
  "geometry": {"coordinates":[-85.379509,31.190966],"type":"Point"}
}