{
  "type": "Feature",
  "properties": {
    "iso:country":"US",
    "sg:address":"108 Gentle Cir",
    "sg:city":"Scottsboro",
    "sg:classifiers":[
        {
            "category":"Manufacturing",
            "subcategory":"Metals",
            "type":"Manufacturing & Wholesale Goods"
        }
    ],
    "sg:phone":"+1 256 776 3786",
    "sg:postcode":"35769",
    "sg:province":"AL",
    "sg:tags":[
        "mfg",
        "parts",
        "missile"
    ],
    "wof:name":"Swaim Machine Co Inc",
    "wof:placetype":"venue"
},
  "geometry": {"coordinates":[-86.027049,34.615413],"type":"Point"}
}