{
  "type": "Feature",
  "properties": {
    "iso:country":"US",
    "sg:address":"370 Selma Hwy",
    "sg:city":"Prattville",
    "sg:classifiers":[
        {
            "category":"Professional",
            "subcategory":"Management & Consulting",
            "type":"Services"
        }
    ],
    "sg:phone":"+1 334 365 7823",
    "sg:postcode":"36067",
    "sg:province":"AL",
    "sg:tags":[
        "fuel"
    ],
    "wof:name":"Drinkard Management Co",
    "wof:placetype":"venue"
},
  "geometry": {"coordinates":[-86.467198,32.448977],"type":"Point"}
}