{
  "type": "Feature",
  "properties": {
    "iso:country":"US",
    "sg:address":"805 North St E",
    "sg:city":"Talladega",
    "sg:classifiers":[
        {
            "category":"Health Services",
            "subcategory":"Clinic",
            "type":"Services"
        }
    ],
    "sg:phone":"+1 256 315 1662",
    "sg:postcode":"35160",
    "sg:province":"AL",
    "sg:tags":[
        "kidney",
        "dialysis",
        "center"
    ],
    "wof:name":"Northeast Ala Kidney Clinic",
    "wof:placetype":"venue"
},
  "geometry": {"coordinates":[-86.083428,33.440673],"type":"Point"}
}