{
  "type": "Feature",
  "properties": {
    "iso:country":"US",
    "sg:address":"9367 Butler St",
    "sg:city":"Huxford",
    "sg:classifiers":[
        {
            "category":"Freight",
            "type":"Transportation"
        }
    ],
    "sg:phone":"+1 251 294 5627",
    "sg:postcode":"36502",
    "sg:province":"FL",
    "sg:tags":[
        "operator",
        "trucking"
    ],
    "wof:name":"B&B Trucking",
    "wof:placetype":"venue"
},
  "geometry": {"coordinates":[-87.430397,31.234913],"type":"Point"}
}