{
  "type": "Feature",
  "properties": {
    "iso:country":"US",
    "sg:address":"2420 1st Ave N",
    "sg:city":"Birmingham",
    "sg:classifiers":[
        {
            "category":"Personal",
            "type":"Services"
        }
    ],
    "sg:phone":"+1 205 252 3600",
    "sg:postcode":"35204",
    "sg:province":"AL",
    "sg:tags":[
        "formal",
        "wear",
        "rent"
    ],
    "wof:name":"Mr Burch Cleaners",
    "wof:placetype":"venue"
},
  "geometry": {"coordinates":[-86.79906699999999,33.517647],"type":"Point"}
}