{
  "type": "Feature",
  "properties": {
    "iso:country":"US",
    "sg:address":"113 N Henry St",
    "sg:city":"Gadsden",
    "sg:classifiers":[
        {
            "category":"Professional",
            "subcategory":"Computer Services",
            "type":"Services"
        }
    ],
    "sg:phone":"+1 256 547 1894",
    "sg:postcode":"35901",
    "sg:province":"AL",
    "sg:tags":[
        "repair"
    ],
    "wof:name":"E & M Svc",
    "wof:placetype":"venue"
},
  "geometry": {"coordinates":[-86.005644,34.015766],"type":"Point"}
}