{
  "type": "Feature",
  "properties": {
    "iso:country":"US",
    "sg:address":"215 Haynes St",
    "sg:city":"Talladega",
    "sg:classifiers":[
        {
            "category":"Restaurant",
            "type":"Food & Drink"
        }
    ],
    "sg:phone":"+1 256 362 9200",
    "sg:postcode":"35160",
    "sg:province":"AL",
    "wof:name":"Taco Bell",
    "wof:placetype":"venue"
},
  "geometry": {"coordinates":[-86.081289,33.435041],"type":"Point"}
}