{
  "type": "Feature",
  "properties": {
    "iso:country":"US",
    "sg:address":"5612 L Ave",
    "sg:city":"Birmingham",
    "sg:classifiers":[
        {
            "category":"Organizations",
            "subcategory":"Religious Organization",
            "type":"Services"
        }
    ],
    "sg:phone":"+1 205 923 7566",
    "sg:postcode":"35208",
    "sg:province":"AL",
    "wof:name":"Johnson Barnard Rev",
    "wof:placetype":"venue"
},
  "geometry": {"coordinates":[-86.897405,33.478996],"type":"Point"}
}