{
  "type": "Feature",
  "properties": {
    "iso:country":"US",
    "sg:address":"6108 Hidden Brook Dr",
    "sg:city":"Trussville",
    "sg:classifiers":[
        {
            "category":"Social Services",
            "subcategory":"Child Care",
            "type":"Services"
        }
    ],
    "sg:phone":"+1 205 655 0277",
    "sg:postcode":"35173",
    "sg:province":"AL",
    "sg:tags":[
        "day"
    ],
    "wof:name":"Start To Finish Ldscpg LLC",
    "wof:placetype":"venue"
},
  "geometry": {"coordinates":[-86.620658,33.600945],"type":"Point"}
}