{
  "type": "Feature",
  "properties": {
    "addr:full":"6108 Hidden Brook Dr Trussville AL 35173",
    "addr:housenumber":"6108",
    "addr:postcode":"35173",
    "addr:street":"Hidden Brook Dr",
    "iso:country":"US",
    "sg:address":"6108 Hidden Brook Dr",
    "sg:city":"Trussville",
    "sg:classifiers":[
        {
            "category":"Social Services",
            "subcategory":"Child Care",
            "type":"Services"
        }
    ],
    "sg:phone":"+1 205 655 0277",
    "sg:postcode":"35173",
    "sg:province":"AL",
    "sg:tags":[
        "day"
    ],
    "wof:name":"Start To Finish Ldscpg LLC",
    "wof:placetype":"venue"
},
  "geometry": {"coordinates":[-86.62065800000001,33.600945],"type":"Point"}
}