{
  "type": "Feature",
  "properties": {
    "iso:country":"US",
    "sg:address":"702 Heatherbrooke Rd",
    "sg:city":"Birmingham",
    "sg:classifiers":[
        {
            "category":"Professional",
            "subcategory":"Employment Agencies",
            "type":"Services"
        }
    ],
    "sg:phone":"+1 205 408 1111",
    "sg:postcode":"35242",
    "sg:province":"AL",
    "wof:name":"Ros Testing",
    "wof:placetype":"venue"
},
  "geometry": {"coordinates":[-86.699794,33.428316],"type":"Point"}
}