{
  "type": "Feature",
  "properties": {
    "addr:full":"6075 Steeple Chase Dr Pinson AL 35126",
    "addr:housenumber":"6075",
    "addr:postcode":"35126",
    "addr:street":"Steeple Chase Dr",
    "iso:country":"US",
    "sg:address":"6075 Steeple Chase Dr",
    "sg:city":"Pinson",
    "sg:classifiers":[
        {
            "category":"Building & Trades",
            "subcategory":"Construction",
            "type":"Services"
        }
    ],
    "sg:phone":"+1 205 681 9702",
    "sg:postcode":"35126",
    "sg:province":"AL",
    "sg:tags":[
        "carpentry",
        "contractor"
    ],
    "wof:name":"Millwood Cabinet Shop",
    "wof:placetype":"venue"
},
  "geometry": {"coordinates":[-86.616291,33.687491],"type":"Point"}
}