{
  "type": "Feature",
  "properties": {
    "iso:country":"US",
    "sg:address":"2540 Gordon Terry Pkwy",
    "sg:city":"Decatur",
    "sg:classifiers":[
        {
            "category":"Wholesale",
            "subcategory":"Scrap",
            "type":"Manufacturing & Wholesale Goods"
        }
    ],
    "sg:phone":"+1 256 351 0422",
    "sg:postcode":"35601",
    "sg:province":"AL",
    "sg:tags":[
        "waste",
        "material"
    ],
    "wof:name":"A & S Metals Inc",
    "wof:placetype":"venue"
},
  "geometry": {"coordinates":[-87.04185099999999,34.599717],"type":"Point"}
}