{
  "type": "Feature",
  "properties": {
    "addr:full":"3711 US Hwy 80 Phenix City AL 36870",
    "addr:housenumber":"3711",
    "addr:postcode":"36870",
    "addr:street":"Us Hwy 80 Phenix City Al",
    "iso:country":"US",
    "sg:address":"3711 US Hwy 80",
    "sg:city":"Phenix City",
    "sg:classifiers":[
        {
            "category":"Shopping",
            "subcategory":"Used Merchandise",
            "type":"Retail Goods"
        }
    ],
    "sg:phone":"+1 334 291 1947",
    "sg:postcode":"36870",
    "sg:province":"AL",
    "sg:tags":[
        "pawnbroker"
    ],
    "wof:name":"Mick's Music & More",
    "wof:placetype":"venue"
},
  "geometry": {"coordinates":[-85.059629,32.470096],"type":"Point"}
}