{
  "type": "Feature",
  "properties": {
    "iso:country":"US",
    "sg:address":"108 Pebble Brook Cir",
    "sg:city":"Madison",
    "sg:classifiers":[
        {
            "category":"Building & Trades",
            "subcategory":"Construction",
            "type":"Services"
        }
    ],
    "sg:phone":"+1 256 721 7767",
    "sg:postcode":"35758",
    "sg:province":"AL",
    "sg:tags":[
        "house",
        "builder",
        "ma",
        "deck"
    ],
    "wof:name":"Renovations Unlimited LLC",
    "wof:placetype":"venue"
},
  "geometry": {"coordinates":[-86.746055,34.744772],"type":"Point"}
}