{
  "type": "Feature",
  "properties": {
    "iso:country":"US",
    "sg:address":"1810 Shoal Run Trl",
    "sg:city":"Birmingham",
    "sg:classifiers":[
        {
            "category":"Local Transit",
            "type":"Transportation"
        }
    ],
    "sg:phone":"+1 205 980 6877",
    "sg:postcode":"35242",
    "sg:province":"AL",
    "sg:tags":[
        "passenger"
    ],
    "wof:name":"Potluck Delivery",
    "wof:placetype":"venue"
},
  "geometry": {"coordinates":[-86.671298,33.414209],"type":"Point"}
}