{
  "type": "Feature",
  "properties": {
    "iso:country":"US",
    "sg:address":"10 Inverness Center Pkwy",
    "sg:city":"Birmingham",
    "sg:classifiers":[
        {
            "category":"Wholesale",
            "subcategory":"Meat",
            "type":"Manufacturing & Wholesale Goods"
        }
    ],
    "sg:phone":"+1 205 995 0072",
    "sg:postcode":"35242",
    "sg:province":"AL",
    "sg:tags":[
        "packer"
    ],
    "wof:name":"Bryan Foods Inc",
    "wof:placetype":"venue"
},
  "geometry": {"coordinates":[-86.702996,33.424507],"type":"Point"}
}