{
  "type": "Feature",
  "properties": {
    "iso:country":"US",
    "sg:address":"5000 Bradford Blvd NW",
    "sg:city":"Huntsville",
    "sg:classifiers":[
        {
            "category":"Professional",
            "subcategory":"Business Services",
            "type":"Services"
        }
    ],
    "sg:phone":"+1 256 864 9600",
    "sg:postcode":"35805",
    "sg:province":"AL",
    "sg:tags":[
        "telemarketing"
    ],
    "sg:website":"www.west.com",
    "wof:name":"West Telemarketing",
    "wof:placetype":"venue"
},
  "geometry": {"coordinates":[-86.662038,34.726474],"type":"Point"}
}