{
  "type": "Feature",
  "properties": {
    "iso:country":"US",
    "sg:address":"250 Co Rd 214",
    "sg:city":"Woodville",
    "sg:phone":"+1 256 776 3793",
    "sg:postcode":"35776",
    "sg:province":"AL",
    "sg:tags":[
        "farm",
        "corn",
        "soybean",
        "crop",
        "general"
    ],
    "wof:name":"Roy Womack",
    "wof:placetype":"venue"
},
  "geometry": {"coordinates":[-86.278803,34.603273],"type":"Point"}
}