{
  "type": "Feature",
  "properties": {
    "iso:country":"US",
    "sg:address":"1606 Industrial Park Dr",
    "sg:city":"Mobile",
    "sg:classifiers":[
        {
            "category":"Professional",
            "subcategory":"Computer Services",
            "type":"Services"
        }
    ],
    "sg:phone":"+1 251 338 0349",
    "sg:postcode":"36693",
    "sg:province":"AL",
    "wof:name":"Automotive Computer Svc Inc",
    "wof:placetype":"venue"
},
  "geometry": {"coordinates":[-88.130037,30.632323],"type":"Point"}
}