{
  "type": "Feature",
  "properties": {
    "addr:full":"505 Cobb St Birmingham AL 35209",
    "addr:housenumber":"505",
    "addr:postcode":"35209",
    "addr:street":"Cobb St",
    "iso:country":"US",
    "sg:address":"505 Cobb St",
    "sg:city":"Birmingham",
    "sg:classifiers":[
        {
            "category":"Home & Garden",
            "subcategory":"Building Materials",
            "type":"Retail Goods"
        }
    ],
    "sg:phone":"+1 205 945 1808",
    "sg:postcode":"35209",
    "sg:province":"AL",
    "sg:tags":[
        "wallpaper"
    ],
    "wof:name":"Wallpaper Factory Outlet Inc",
    "wof:placetype":"venue"
},
  "geometry": {"coordinates":[-86.826386,33.461391],"type":"Point"}
}