{
  "type": "Feature",
  "properties": {
    "iso:country":"US",
    "sg:address":"20585 Co Rd 13",
    "sg:city":"Fairhope",
    "sg:classifiers":[
        {
            "category":"Home & Garden",
            "subcategory":"Building Materials",
            "type":"Retail Goods"
        }
    ],
    "sg:phone":"+1 251 660 0112",
    "sg:postcode":"36532",
    "sg:province":"AL",
    "sg:tags":[
        "door"
    ],
    "wof:name":"Overhead Door Co Of Mobile",
    "wof:placetype":"venue"
},
  "geometry": {"coordinates":[-87.8691,30.528182],"type":"Point"}
}