{
  "type": "Feature",
  "properties": {
    "iso:country":"US",
    "sg:address":"4157 Eva Rd",
    "sg:city":"Eva",
    "sg:classifiers":[
        {
            "category":"Retail",
            "subcategory":"Auto Repair",
            "type":"Services"
        }
    ],
    "sg:phone":"+1 256 796 4450",
    "sg:postcode":"35621",
    "sg:province":"AL",
    "sg:tags":[
        "repairing",
        "automobile"
    ],
    "wof:name":"First Fleet",
    "wof:placetype":"venue"
},
  "geometry": {"coordinates":[-86.759715,34.330398],"type":"Point"}
}