{
  "type": "Feature",
  "properties": {
    "iso:country":"US",
    "sg:address":"29330 State Rte 79",
    "sg:city":"Scottsboro",
    "sg:classifiers":[
        {
            "category":"Building & Trades",
            "subcategory":"Landscaping Services",
            "type":"Services"
        }
    ],
    "sg:phone":"+1 256 587 3453",
    "sg:postcode":"35768",
    "sg:province":"AL",
    "wof:name":"Sealey Cnstr Bckhoe Dozer Work",
    "wof:placetype":"venue"
},
  "geometry": {"coordinates":[-86.084692,34.913047],"type":"Point"}
}