{
  "type": "Feature",
  "properties": {
    "addr:full":"1007 Goodyear Ave Gadsden AL 35903",
    "addr:housenumber":"1007",
    "addr:postcode":"35903",
    "addr:street":"Goodyear Ave",
    "iso:country":"US",
    "sg:address":"1007 Goodyear Ave",
    "sg:city":"Gadsden",
    "sg:classifiers":[
        {
            "category":"Health Services",
            "subcategory":"Doctor",
            "type":"Services"
        }
    ],
    "sg:phone":"+1 256 494 5123",
    "sg:postcode":"35903",
    "sg:province":"AL",
    "sg:tags":[
        "physician",
        "surgeon"
    ],
    "wof:name":"Ghaith Ajamoughli MD",
    "wof:placetype":"venue"
},
  "geometry": {"coordinates":[-85.971035,34.009362],"type":"Point"}
}