{
  "type": "Feature",
  "properties": {
    "iso:country":"US",
    "sg:address":"2349 Danville Rd SW",
    "sg:city":"Decatur",
    "sg:classifiers":[
        {
            "category":"Health Services",
            "subcategory":"Doctor",
            "type":"Services"
        }
    ],
    "sg:phone":"+1 256 355 0555",
    "sg:postcode":"35603",
    "sg:province":"AL",
    "sg:tags":[
        "physician",
        "pediatrics",
        "family",
        "practice",
        "surgeons",
        "medicine",
        "surgeon"
    ],
    "wof:name":"Anderson, Scott A MD",
    "wof:placetype":"venue"
},
  "geometry": {"coordinates":[-87.01618999999999,34.56929],"type":"Point"}
}