{
  "type": "Feature",
  "properties": {
    "iso:country":"US",
    "sg:address":"2011 Harmon St",
    "sg:city":"Montgomery",
    "sg:classifiers":[
        {
            "category":"Building & Trades",
            "subcategory":"Construction",
            "type":"Services"
        }
    ],
    "sg:phone":"+1 334 207 8420",
    "sg:postcode":"36107",
    "sg:province":"AL",
    "sg:tags":[
        "roofing",
        "contractor"
    ],
    "wof:name":"Cleary Roofing",
    "wof:placetype":"venue"
},
  "geometry": {"coordinates":[-86.275158,32.395159],"type":"Point"}
}