{
  "type": "Feature",
  "properties": {
    "iso:country":"US",
    "sg:address":"4860 Bush Ln",
    "sg:city":"Mobile",
    "sg:classifiers":[
        {
            "category":"Wholesale",
            "subcategory":"Machinery & Supplies",
            "type":"Manufacturing & Wholesale Goods"
        }
    ],
    "sg:phone":"+1 251 602 0008",
    "sg:postcode":"36619",
    "sg:province":"AL",
    "sg:tags":[
        "manufacturer",
        "safety",
        "chuck",
        "for",
        "representative"
    ],
    "wof:name":"Boschert LLC",
    "wof:placetype":"venue"
},
  "geometry": {"coordinates":[-88.17923,30.595638],"type":"Point"}
}