{
  "type": "Feature",
  "properties": {
    "iso:country":"US",
    "sg:address":"1411 Gilmer Ave",
    "sg:city":"Tallassee",
    "sg:classifiers":[
        {
            "category":"Banks & Credit Unions",
            "subcategory":"Bank",
            "type":"Services"
        }
    ],
    "sg:phone":"+1 334 252 0462",
    "sg:postcode":"36078",
    "sg:province":"AL",
    "wof:name":"Peoples Bank & Trust",
    "wof:placetype":"venue"
},
  "geometry": {"coordinates":[-85.913453,32.548405],"type":"Point"}
}