{
  "type": "Feature",
  "properties": {
    "iso:country":"US",
    "sg:address":"2153 Airport Blvd",
    "sg:city":"Mobile",
    "sg:classifiers":[
        {
            "category":"Insurance",
            "subcategory":"Insurance Agent",
            "type":"Services"
        }
    ],
    "sg:phone":"+1 251 450 0061",
    "sg:postcode":"36608",
    "sg:province":"AL",
    "sg:website":"www.burkholderinsurance.com",
    "wof:name":"Burkholder Insurance Inc",
    "wof:placetype":"venue"
},
  "geometry": {"coordinates":[-88.092719,30.676379],"type":"Point"}
}