{
  "type": "Feature",
  "properties": {
    "iso:country":"US",
    "sg:address":"105 Trade Center Dr",
    "sg:city":"Birmingham",
    "sg:classifiers":[
        {
            "category":"Professional",
            "subcategory":"Business Services",
            "type":"Services"
        }
    ],
    "sg:phone":"+1 205 823 7824",
    "sg:postcode":"35244",
    "sg:province":"AL",
    "sg:tags":[
        "broker",
        "merchandise"
    ],
    "wof:name":"Magic City Brokers",
    "wof:placetype":"venue"
},
  "geometry": {"coordinates":[-86.801248,33.348604],"type":"Point"}
}