{
  "type": "Feature",
  "properties": {
    "iso:country":"US",
    "sg:address":"235 Co Rd 361",
    "sg:city":"Pelham",
    "sg:classifiers":[
        {
            "category":"Wholesale",
            "subcategory":"Medical Equipment & Supplies",
            "type":"Manufacturing & Wholesale Goods"
        }
    ],
    "sg:phone":"+1 205 620 9919",
    "sg:postcode":"35124",
    "sg:province":"AL",
    "sg:tags":[
        "electronics"
    ],
    "wof:name":"Medical Imaging Svc",
    "wof:placetype":"venue"
},
  "geometry": {"coordinates":[-86.798858,33.288621],"type":"Point"}
}