{
  "type": "Feature",
  "properties": {
    "addr:full":"16057 Oneal Rd Athens AL 35614",
    "addr:housenumber":"16057",
    "addr:postcode":"35614",
    "addr:street":"Oneal Rd",
    "iso:country":"US",
    "sg:address":"16057 Oneal Rd",
    "sg:city":"Athens",
    "sg:classifiers":[
        {
            "category":"Manufacturing",
            "subcategory":"Glass & Minerals",
            "type":"Manufacturing & Wholesale Goods"
        }
    ],
    "sg:phone":"+1 256 232 6568",
    "sg:postcode":"35614",
    "sg:province":"AL",
    "sg:tags":[
        "concrete",
        "product",
        "material",
        "who",
        "mfg"
    ],
    "wof:name":"Kyle Concrete Products",
    "wof:placetype":"venue"
},
  "geometry": {"coordinates":[-87.03491200000001,34.835078],"type":"Point"}
}