{
  "type": "Feature",
  "properties": {
    "iso:country":"US",
    "sg:address":"110 S Main St",
    "sg:city":"Wetumpka",
    "sg:classifiers":[
        {
            "category":"Autos & Motor Vehicles",
            "subcategory":"Auto Supplies",
            "type":"Retail Goods"
        }
    ],
    "sg:phone":"+1 334 567 4371",
    "sg:postcode":"36092",
    "sg:province":"AL",
    "sg:tags":[
        "automobile",
        "parts"
    ],
    "wof:name":"O'Reilly Auto Parts",
    "wof:placetype":"venue"
},
  "geometry": {"coordinates":[-86.20559799999999,32.536655],"type":"Point"}
}