{
  "type": "Feature",
  "properties": {
    "iso:country":"US",
    "sg:address":"913 E Commerce St",
    "sg:city":"Greenville",
    "sg:classifiers":[
        {
            "category":"Building & Trades",
            "subcategory":"Construction",
            "type":"Services"
        }
    ],
    "sg:phone":"+1 334 382 3388",
    "sg:postcode":"36037",
    "sg:province":"AL",
    "sg:tags":[
        "concrete",
        "contractor"
    ],
    "wof:name":"Farnum Construction LLC",
    "wof:placetype":"venue"
},
  "geometry": {"coordinates":[-86.614414,31.829735],"type":"Point"}
}