{
  "type": "Feature",
  "properties": {
    "iso:country":"US",
    "sg:address":"815 Dalraida Rd",
    "sg:city":"Montgomery",
    "sg:classifiers":[
        {
            "category":"Building & Trades",
            "subcategory":"Construction",
            "type":"Services"
        }
    ],
    "sg:phone":"+1 334 273 0015",
    "sg:postcode":"36109",
    "sg:province":"AL",
    "sg:tags":[
        "downspouts",
        "gutter"
    ],
    "wof:name":"M T Svc",
    "wof:placetype":"venue"
},
  "geometry": {"coordinates":[-86.245099,32.3984],"type":"Point"}
}