{
  "type": "Feature",
  "properties": {
    "addr:full":"42 Sayreton Dr Birmingham AL 35207",
    "addr:housenumber":"42",
    "addr:postcode":"35207",
    "addr:street":"Sayreton Dr",
    "iso:country":"US",
    "sg:address":"42 Sayreton Dr",
    "sg:city":"Birmingham",
    "sg:classifiers":[
        {
            "category":"Freight",
            "type":"Transportation"
        }
    ],
    "sg:phone":"+1 205 324 2323",
    "sg:postcode":"35207",
    "sg:province":"AL",
    "sg:tags":[
        "trucking"
    ],
    "wof:name":"Decker Trucking Co",
    "wof:placetype":"venue"
},
  "geometry": {"coordinates":[-86.839804,33.563663],"type":"Point"}
}