{
  "type": "Feature",
  "properties": {
    "addr:full":"14820 Bishop Trce Lillian AL 36549",
    "addr:housenumber":"14820",
    "addr:postcode":"36549",
    "addr:street":"Bishop Trce",
    "iso:country":"US",
    "sg:address":"14820 Bishop Trce",
    "sg:city":"Lillian",
    "sg:classifiers":[
        {
            "category":"Building & Trades",
            "subcategory":"Construction",
            "type":"Services"
        }
    ],
    "sg:phone":"+1 251 962 2574",
    "sg:postcode":"36549",
    "sg:province":"AL",
    "sg:tags":[
        "excavating",
        "contractor"
    ],
    "wof:name":"Gene's Dozer Svc",
    "wof:placetype":"venue"
},
  "geometry": {"coordinates":[-87.44657100000001,30.437732],"type":"Point"}
}