{
  "type": "Feature",
  "properties": {
    "addr:full":"1118 Old Hwy 231 N Troy AL 36081",
    "addr:housenumber":"1118",
    "addr:postcode":"36081",
    "addr:street":"Old Hwy 231 N",
    "iso:country":"US",
    "sg:address":"1118 Old Hwy 231 N",
    "sg:city":"Troy",
    "sg:classifiers":[
        {
            "category":"Restaurant",
            "type":"Food & Drink"
        }
    ],
    "sg:phone":"+1 334 566 1022",
    "sg:postcode":"36081",
    "sg:province":"AL",
    "wof:name":"Blimpie Subs & Salads",
    "wof:placetype":"venue"
},
  "geometry": {"coordinates":[-86.00163499999999,31.863077],"type":"Point"}
}