{
  "type": "Feature",
  "properties": {
    "addr:full":"1383 Brickyard Rd Phenix City AL 36869",
    "addr:housenumber":"1383",
    "addr:postcode":"36869",
    "addr:street":"Brickyard Rd Phenix",
    "iso:country":"US",
    "sg:address":"1383 Brickyard Rd",
    "sg:city":"Phenix City",
    "sg:classifiers":[
        {
            "category":"Freight",
            "type":"Transportation"
        }
    ],
    "sg:phone":"+1 334 297 3817",
    "sg:postcode":"36869",
    "sg:province":"AL",
    "sg:tags":[
        "local",
        "trucking"
    ],
    "wof:name":"Joe-Ryan Enterprises Inc",
    "wof:placetype":"venue"
},
  "geometry": {"coordinates":[-84.994968,32.419144],"type":"Point"}
}