{
  "type": "Feature",
  "properties": {
    "addr:full":"2462 Morgan Rd Bessemer AL 35022",
    "addr:housenumber":"2462",
    "addr:postcode":"35022",
    "addr:street":"Morgan Rd",
    "iso:country":"US",
    "sg:address":"2462 Morgan Rd",
    "sg:city":"Bessemer",
    "sg:classifiers":[
        {
            "category":"Autos & Motor Vehicles",
            "subcategory":"Fuel & Gas Station",
            "type":"Retail Goods"
        }
    ],
    "sg:phone":"+1 205 428 1697",
    "sg:postcode":"35022",
    "sg:province":"AL",
    "sg:tags":[
        "station",
        "gasoline"
    ],
    "wof:name":"Greenwood Auto Service",
    "wof:placetype":"venue"
},
  "geometry": {"coordinates":[-86.933105,33.347702],"type":"Point"}
}