{
  "type": "Feature",
  "properties": {
    "iso:country":"US",
    "sg:address":"223 Riverchase Trl",
    "sg:city":"Birmingham",
    "sg:classifiers":[
        {
            "category":"Retail",
            "subcategory":"Repair Shop",
            "type":"Services"
        }
    ],
    "sg:phone":"+1 205 682 3059",
    "sg:postcode":"35244",
    "sg:province":"AL",
    "wof:name":"Vines Professional Cleaning",
    "wof:placetype":"venue"
},
  "geometry": {"coordinates":[-86.790667,33.354806],"type":"Point"}
}