{
  "type": "Feature",
  "properties": {
    "addr:full":"1154 Hollingsworth Dr Wellington AL 36279",
    "addr:housenumber":"1154",
    "addr:postcode":"36279",
    "addr:street":"Hollingsworth Dr",
    "iso:country":"US",
    "sg:address":"1154 Hollingsworth Dr",
    "sg:city":"Wellington",
    "sg:classifiers":[
        {
            "category":"Manufacturing",
            "subcategory":"Tools & Machinery",
            "type":"Manufacturing & Wholesale Goods"
        }
    ],
    "sg:phone":"+1 256 492 8826",
    "sg:postcode":"36279",
    "sg:province":"AL",
    "sg:tags":[
        "machine",
        "shop"
    ],
    "wof:name":"Wireworks",
    "wof:placetype":"venue"
},
  "geometry": {"coordinates":[-85.90826300000001,33.897917],"type":"Point"}
}