{
  "type": "Feature",
  "properties": {
    "iso:country":"US",
    "sg:address":"1154 Hollingsworth Dr",
    "sg:city":"Wellington",
    "sg:classifiers":[
        {
            "category":"Manufacturing",
            "subcategory":"Tools & Machinery",
            "type":"Manufacturing & Wholesale Goods"
        }
    ],
    "sg:phone":"+1 256 492 8826",
    "sg:postcode":"36279",
    "sg:province":"AL",
    "sg:tags":[
        "machine",
        "shop"
    ],
    "wof:name":"Wireworks",
    "wof:placetype":"venue"
},
  "geometry": {"coordinates":[-85.908263,33.897917],"type":"Point"}
}