{
  "type": "Feature",
  "properties": {
    "iso:country":"US",
    "sg:address":"840 Oak Grove Rd",
    "sg:city":"Homewood",
    "sg:classifiers":[
        {
            "category":"Health Services",
            "subcategory":"Podiatrist",
            "type":"Services"
        }
    ],
    "sg:phone":"+1 205 942 0514",
    "sg:postcode":"35209",
    "sg:province":"AL",
    "wof:name":"David Roberson DPM",
    "wof:placetype":"venue"
},
  "geometry": {"coordinates":[-86.828732,33.457108],"type":"Point"}
}