{
  "type": "Feature",
  "properties": {
    "addr:full":"215 Green Cove Rd SE Huntsville AL 35803",
    "addr:housenumber":"215",
    "addr:postcode":"35803",
    "addr:street":"Green Cove Rd Se",
    "iso:country":"US",
    "sg:address":"215 Green Cove Rd SE",
    "sg:city":"Huntsville",
    "sg:classifiers":[
        {
            "category":"Retail",
            "subcategory":"Veterinary Services",
            "type":"Services"
        }
    ],
    "sg:phone":"+1 256 882 0219",
    "sg:postcode":"35803",
    "sg:province":"AL",
    "sg:tags":[
        "veterinarian"
    ],
    "wof:name":"Gereen Cove Pet Hospital",
    "wof:placetype":"venue"
},
  "geometry": {"coordinates":[-86.559229,34.595312],"type":"Point"}
}