{
  "type": "Feature",
  "properties": {
    "addr:full":"1211 Old Hwy 231 N Troy AL 36079",
    "addr:housenumber":"1211",
    "addr:postcode":"36079",
    "addr:street":"Old Hwy 231 N",
    "iso:country":"US",
    "sg:address":"1211 Old Hwy 231 N",
    "sg:city":"Troy",
    "sg:classifiers":[
        {
            "category":"Building & Trades",
            "subcategory":"Equipment Rental",
            "type":"Services"
        }
    ],
    "sg:phone":"+1 334 566 3511",
    "sg:postcode":"36079",
    "sg:province":"AL",
    "sg:tags":[
        "appliance"
    ],
    "wof:name":"Hometown Rental Ctr",
    "wof:placetype":"venue"
},
  "geometry": {"coordinates":[-86.002589,31.865577],"type":"Point"}
}