{
  "type": "Feature",
  "properties": {
    "iso:country":"US",
    "sg:address":"3150 Lorna Rd",
    "sg:city":"Birmingham",
    "sg:classifiers":[
        {
            "category":"Shopping",
            "subcategory":"Clothing, Apparel, & Fashions",
            "type":"Retail Goods"
        }
    ],
    "sg:phone":"+1 205 978 9990",
    "sg:postcode":"35216",
    "sg:province":"AL",
    "sg:tags":[
        "wear"
    ],
    "wof:name":"Raggedy Anns Chld CL Cnsgnmt",
    "wof:placetype":"venue"
},
  "geometry": {"coordinates":[-86.80243,33.398179],"type":"Point"}
}