{
  "type": "Feature",
  "properties": {
    "iso:country":"US",
    "sg:address":"4392 Rice Mine Rd NE",
    "sg:city":"Tuscaloosa",
    "sg:classifiers":[
        {
            "category":"Food & Beverages",
            "subcategory":"Groceries & Convenience Stores",
            "type":"Retail Goods"
        }
    ],
    "sg:phone":"+1 205 752 0520",
    "sg:postcode":"35406",
    "sg:province":"AL",
    "sg:tags":[
        "grocer",
        "gasoline"
    ],
    "wof:name":"Reed's Grocery",
    "wof:placetype":"venue"
},
  "geometry": {"coordinates":[-87.51420299999999,33.256295],"type":"Point"}
}