{
  "type": "Feature",
  "properties": {
    "addr:full":"4885 Co Rd 246 Smiths AL 36877",
    "addr:housenumber":"4885",
    "addr:postcode":"36877",
    "addr:street":"Co Rd 246 Smiths",
    "iso:country":"US",
    "sg:address":"4885 Co Rd 246",
    "sg:city":"Smiths",
    "sg:classifiers":[
        {
            "category":"Organizations",
            "subcategory":"Religious Organization",
            "type":"Services"
        }
    ],
    "sg:phone":"+1 334 291 1161",
    "sg:postcode":"36877",
    "sg:province":"AL",
    "sg:tags":[
        "god",
        "assembly",
        "church"
    ],
    "wof:name":"Cavalry Tbernacle Assembly God",
    "wof:placetype":"venue"
},
  "geometry": {"coordinates":[-85.13617600000001,32.539168],"type":"Point"}
}