{
  "type": "Feature",
  "properties": {
    "iso:country":"US",
    "sg:address":"205 Williams Ave SE",
    "sg:city":"Huntsville",
    "sg:classifiers":[
        {
            "category":"Insurance",
            "subcategory":"Insurance Agent",
            "type":"Services"
        }
    ],
    "sg:phone":"+1 256 564 7422",
    "sg:postcode":"35801",
    "sg:province":"AL",
    "wof:name":"Kimberly A Ford",
    "wof:placetype":"venue"
},
  "geometry": {"coordinates":[-86.582016,34.729009],"type":"Point"}
}