{
  "type": "Feature",
  "properties": {
    "iso:country":"US",
    "sg:address":"8718 Co Rd 17",
    "sg:city":"Woodville",
    "sg:classifiers":[
        {
            "category":"Organizations",
            "subcategory":"Religious Organization",
            "type":"Services"
        }
    ],
    "sg:phone":"+1 256 587 9044",
    "sg:postcode":"35776",
    "sg:province":"AL",
    "sg:tags":[
        "church"
    ],
    "wof:name":"Independent Church Of God",
    "wof:placetype":"venue"
},
  "geometry": {"coordinates":[-86.15970799999999,34.74433],"type":"Point"}
}