{
  "type": "Feature",
  "properties": {
    "iso:country":"US",
    "sg:address":"27220 C R Watson Rd",
    "sg:city":"Robertsdale",
    "sg:classifiers":[
        {
            "category":"Wholesale",
            "subcategory":"Farm Supplies",
            "type":"Manufacturing & Wholesale Goods"
        }
    ],
    "sg:phone":"+1 251 931 0455",
    "sg:postcode":"36567",
    "sg:province":"AL",
    "sg:tags":[
        "raw",
        "product",
        "material"
    ],
    "wof:name":"CD San Angelena Enterprises",
    "wof:placetype":"venue"
},
  "geometry": {"coordinates":[-87.437988,30.618651],"type":"Point"}
}