{
  "type": "Feature",
  "properties": {
    "iso:country":"US",
    "sg:address":"1023 15th St",
    "sg:city":"Tuscaloosa",
    "sg:classifiers":[
        {
            "category":"Manufacturing",
            "subcategory":"Jewelry",
            "type":"Manufacturing & Wholesale Goods"
        }
    ],
    "sg:phone":"+1 205 345 0555",
    "sg:postcode":"35401",
    "sg:province":"AL",
    "sg:website":"www.benchmarkrings.com",
    "wof:name":"Benchmark Inc",
    "wof:placetype":"venue"
},
  "geometry": {"coordinates":[-87.55099,33.199089],"type":"Point"}
}