{
  "type": "Feature",
  "properties": {
    "iso:country":"US",
    "sg:address":"147 Saddlebred Pvt Dr",
    "sg:city":"Hartselle",
    "sg:classifiers":[
        {
            "category":"Recreation",
            "type":"Entertainment"
        }
    ],
    "sg:phone":"+1 256 773 2182",
    "sg:postcode":"35640",
    "sg:province":"AL",
    "sg:tags":[
        "stable"
    ],
    "wof:name":"B-W Stables",
    "wof:placetype":"venue"
},
  "geometry": {"coordinates":[-86.842746,34.460925],"type":"Point"}
}