{
  "type": "Feature",
  "properties": {
    "iso:country":"US",
    "sg:address":"104 4th Ave NE",
    "sg:city":"Cullman",
    "sg:classifiers":[
        {
            "category":"Personal",
            "type":"Services"
        }
    ],
    "sg:phone":"+1 256 739 3578",
    "sg:postcode":"35055",
    "sg:province":"AL",
    "wof:name":"Cullman Massage Therapy Clinic",
    "wof:placetype":"venue"
},
  "geometry": {"coordinates":[-86.840457,34.180059],"type":"Point"}
}