{
  "type": "Feature",
  "properties": {
    "addr:full":"2809 5th Aly S Birmingham AL 35233",
    "addr:housenumber":"2809",
    "addr:postcode":"35233",
    "addr:street":"5Th Aly S",
    "iso:country":"US",
    "sg:address":"2809 5th Aly S",
    "sg:city":"Birmingham",
    "sg:classifiers":[
        {
            "category":"Restaurant",
            "type":"Food & Drink"
        }
    ],
    "sg:phone":"+1 205 252 9431",
    "sg:postcode":"35233",
    "sg:province":"AL",
    "sg:tags":[
        "eating"
    ],
    "wof:name":"Yarbrough Companies Inc",
    "wof:placetype":"venue"
},
  "geometry": {"coordinates":[-86.788723,33.513362],"type":"Point"}
}