{
  "type": "Feature",
  "properties": {
    "addr:full":"12424 Cannonball Run Mc Calla AL 35111",
    "addr:housenumber":"12424",
    "addr:postcode":"35111",
    "addr:street":"Cannonball Run Mc Calla Al",
    "iso:country":"US",
    "sg:address":"12424 Cannonball Run",
    "sg:city":"Mc Calla",
    "sg:classifiers":[
        {
            "category":"Professional",
            "type":"Services"
        }
    ],
    "sg:phone":"+1 205 477 6997",
    "sg:postcode":"35111",
    "sg:province":"AL",
    "wof:name":"Ray Services Inc",
    "wof:placetype":"venue"
},
  "geometry": {"coordinates":[-87.085544,33.258457],"type":"Point"}
}