{
  "type": "Feature",
  "properties": {
    "iso:country":"US",
    "sg:address":"3773 Arlington Oaks Dr",
    "sg:city":"Mobile",
    "sg:classifiers":[
        {
            "category":"Professional",
            "type":"Services"
        }
    ],
    "sg:phone":"+1 251 607 9653",
    "sg:postcode":"36695",
    "sg:province":"AL",
    "wof:name":"Mack Morris Dr",
    "wof:placetype":"venue"
},
  "geometry": {"coordinates":[-88.270465,30.612569],"type":"Point"}
}