{
  "type": "Feature",
  "properties": {
    "iso:country":"US",
    "sg:address":"145 Katherine Ave",
    "sg:city":"Ozark",
    "sg:classifiers":[
        {
            "category":"Professional",
            "subcategory":"Employment Agencies",
            "type":"Services"
        }
    ],
    "sg:phone":"+1 334 445 6329",
    "sg:postcode":"36360",
    "sg:province":"AL",
    "sg:tags":[
        "help",
        "supply"
    ],
    "wof:name":"United Probill Inc",
    "wof:placetype":"venue"
},
  "geometry": {"coordinates":[-85.63352399999999,31.45385],"type":"Point"}
}