{
  "type": "Feature",
  "properties": {
    "addr:full":"1910 Main Ave SW Cullman AL 35055",
    "addr:housenumber":"1910",
    "addr:postcode":"35055",
    "addr:street":"Main Ave Sw",
    "iso:country":"US",
    "sg:address":"1910 Main Ave SW",
    "sg:city":"Cullman",
    "sg:classifiers":[
        {
            "category":"Shopping",
            "subcategory":"Pharmacy",
            "type":"Retail Goods"
        }
    ],
    "sg:phone":"+1 256 734 1662",
    "sg:postcode":"35055",
    "sg:province":"AL",
    "wof:name":"Mc Swain's Pharmacy",
    "wof:placetype":"venue"
},
  "geometry": {"coordinates":[-86.848313,34.150182],"type":"Point"}
}