{
  "type": "Feature",
  "properties": {
    "iso:country":"US",
    "sg:address":"400 Chase Park S",
    "sg:city":"Birmingham",
    "sg:classifiers":[
        {
            "category":"Manufacturing",
            "subcategory":"Printing",
            "type":"Manufacturing & Wholesale Goods"
        }
    ],
    "sg:phone":"+1 205 987 6500",
    "sg:postcode":"35244",
    "sg:province":"AL",
    "sg:tags":[
        "directory",
        "phone",
        "publishing"
    ],
    "wof:name":"BellSouth",
    "wof:placetype":"venue"
},
  "geometry": {"coordinates":[-86.795372,33.365473],"type":"Point"}
}