{
  "type": "Feature",
  "properties": {
    "iso:country":"US",
    "sg:address":"624 Garden Hill Dr",
    "sg:city":"Tuscaloosa",
    "sg:classifiers":[
        {
            "category":"Personal",
            "subcategory":"Beauty Salon",
            "type":"Services"
        }
    ],
    "sg:phone":"+1 205 752 3974",
    "sg:postcode":"35405",
    "sg:province":"AL",
    "sg:tags":[
        "shop"
    ],
    "wof:name":"Wynnes Details and Style",
    "wof:placetype":"venue"
},
  "geometry": {"coordinates":[-87.546347,33.129608],"type":"Point"}
}