{
  "type": "Feature",
  "properties": {
    "iso:country":"US",
    "sg:address":"529 Le Grand Pl",
    "sg:city":"Montgomery",
    "sg:classifiers":[
        {
            "category":"Professional",
            "subcategory":"Accounting & Tax Preparation",
            "type":"Services"
        }
    ],
    "sg:phone":"+1 334 834 9783",
    "sg:postcode":"36106",
    "sg:province":"AL",
    "wof:name":"Ray Rawlings PA",
    "wof:placetype":"venue"
},
  "geometry": {"coordinates":[-86.29837000000001,32.352375],"type":"Point"}
}