{
  "type": "Feature",
  "properties": {
    "addr:full":"2204 Annandale Rd SE Huntsville AL 35801",
    "addr:housenumber":"2204",
    "addr:postcode":"35801",
    "addr:street":"Annandale Rd Se",
    "iso:country":"US",
    "sg:address":"2204 Annandale Rd SE",
    "sg:city":"Huntsville",
    "sg:classifiers":[
        {
            "category":"Shopping",
            "subcategory":"Used Merchandise",
            "type":"Retail Goods"
        }
    ],
    "sg:phone":"+1 256 534 2183",
    "sg:postcode":"35801",
    "sg:province":"AL",
    "wof:name":"Hill J Antiques & Gifts",
    "wof:placetype":"venue"
},
  "geometry": {"coordinates":[-86.549829,34.720468],"type":"Point"}
}