{
  "type": "Feature",
  "properties": {
    "addr:full":"2979 State Rte 119 Montevallo AL 35115",
    "addr:housenumber":"2979",
    "addr:postcode":"35115",
    "addr:street":"State Rte 119",
    "iso:country":"US",
    "sg:address":"2979 State Rte 119",
    "sg:city":"Montevallo",
    "sg:classifiers":[
        {
            "category":"Shopping",
            "subcategory":"Used Merchandise",
            "type":"Retail Goods"
        }
    ],
    "sg:phone":"+1 205 665 2446",
    "sg:postcode":"35115",
    "sg:province":"AL",
    "wof:name":"Cedar Creek Antiques",
    "wof:placetype":"venue"
},
  "geometry": {"coordinates":[-86.835999,33.129893],"type":"Point"}
}