{
  "type": "Feature",
  "properties": {
    "iso:country":"US",
    "sg:address":"4802 University Dr NW",
    "sg:city":"Huntsville",
    "sg:classifiers":[
        {
            "category":"Restaurant",
            "type":"Food & Drink"
        }
    ],
    "sg:menulink":"http://www.allmenus.com/al/huntsville/72807-pizza-hut/menu/",
    "sg:phone":"+1 256 837 1207",
    "sg:postcode":"35816",
    "sg:province":"AL",
    "sg:tags":[
        "american",
        "pizza"
    ],
    "wof:name":"Pizza Hut",
    "wof:placetype":"venue"
},
  "geometry": {"coordinates":[-86.65215600000001,34.73705],"type":"Point"}
}