{
  "type": "Feature",
  "properties": {
    "iso:country":"US",
    "sg:address":"1302 4th St SW",
    "sg:city":"Cullman",
    "sg:classifiers":[
        {
            "category":"Wholesale",
            "subcategory":"Electrical",
            "type":"Manufacturing & Wholesale Goods"
        }
    ],
    "sg:phone":"+1 256 734 9624",
    "sg:postcode":"35055",
    "sg:province":"AL",
    "sg:tags":[
        "equipment"
    ],
    "wof:name":"Consolidated Elec Distrs 1547",
    "wof:placetype":"venue"
},
  "geometry": {"coordinates":[-86.853927,34.172025],"type":"Point"}
}