{
  "type": "Feature",
  "properties": {
    "iso:country":"US",
    "sg:address":"13375 Jefferey Rd",
    "sg:city":"Wilmer",
    "sg:classifiers":[
        {
            "category":"Building & Trades",
            "subcategory":"Construction",
            "type":"Services"
        }
    ],
    "sg:phone":"+1 251 649 4759",
    "sg:postcode":"36587",
    "sg:province":"AL",
    "sg:tags":[
        "steel",
        "roofing",
        "contractor",
        "equipment",
        "grain",
        "bin",
        "erects"
    ],
    "wof:name":"Holloway's Construction Co",
    "wof:placetype":"venue"
},
  "geometry": {"coordinates":[-88.362118,30.791567],"type":"Point"}
}