{
  "type": "Feature",
  "properties": {
    "iso:country":"US",
    "sg:address":"11455 Co Rd 9",
    "sg:city":"Millport",
    "sg:classifiers":[
        {
            "category":"Organizations",
            "subcategory":"Religious Organization",
            "type":"Services"
        }
    ],
    "sg:phone":"+1 205 662 4407",
    "sg:postcode":"35576",
    "sg:province":"AL",
    "sg:tags":[
        "church"
    ],
    "wof:name":"Asbury Methodist Church",
    "wof:placetype":"venue"
},
  "geometry": {"coordinates":[-88.168359,33.682117],"type":"Point"}
}