{
  "type": "Feature",
  "properties": {
    "addr:full":"201 James Record Rd SW Huntsville AL 35824",
    "addr:housenumber":"201",
    "addr:postcode":"35824",
    "addr:street":"James Record Rd Sw",
    "iso:country":"US",
    "sg:address":"201 James Record Rd SW",
    "sg:city":"Huntsville",
    "sg:classifiers":[
        {
            "category":"Retail",
            "subcategory":"Repair Shop",
            "type":"Services"
        }
    ],
    "sg:phone":"+1 256 774 4109",
    "sg:postcode":"35824",
    "sg:province":"AL",
    "sg:tags":[
        "electronics",
        "consumer"
    ],
    "wof:name":"Zenith Video Tech Corporation",
    "wof:placetype":"venue"
},
  "geometry": {"coordinates":[-86.77437500000001,34.659104],"type":"Point"}
}