{
  "type": "Feature",
  "properties": {
    "addr:full":"990 S Memorial Dr Prattville AL 36067",
    "addr:housenumber":"990",
    "addr:postcode":"36067",
    "addr:street":"S Memorial Dr",
    "iso:country":"US",
    "sg:address":"990 S Memorial Dr",
    "sg:city":"Prattville",
    "sg:classifiers":[
        {
            "category":"Insurance",
            "subcategory":"Insurance Agent",
            "type":"Services"
        }
    ],
    "sg:phone":"+1 334 365 9800",
    "sg:postcode":"36067",
    "sg:province":"AL",
    "wof:name":"Physicians Mutual Insurance Co",
    "wof:placetype":"venue"
},
  "geometry": {"coordinates":[-86.448528,32.457013],"type":"Point"}
}