{
  "type": "Feature",
  "properties": {
    "iso:country":"US",
    "sg:address":"1333 Whites Mill Rd",
    "sg:city":"Valley",
    "sg:classifiers":[
        {
            "category":"Personal",
            "subcategory":"Beauty Salon",
            "type":"Services"
        }
    ],
    "sg:phone":"+1 334 756 7465",
    "sg:postcode":"36854",
    "sg:province":"AL",
    "sg:tags":[
        "shop"
    ],
    "wof:name":"Family Affair",
    "wof:placetype":"venue"
},
  "geometry": {"coordinates":[-85.183609,32.783913],"type":"Point"}
}