{
  "type": "Feature",
  "properties": {
    "addr:full":"160 Brooklane Dr Bessemer AL 35023",
    "addr:housenumber":"160",
    "addr:postcode":"35023",
    "addr:street":"Brooklane Dr",
    "iso:country":"US",
    "sg:address":"160 Brooklane Dr",
    "sg:city":"Bessemer",
    "sg:classifiers":[
        {
            "category":"Personal",
            "subcategory":"Beauty Salon",
            "type":"Services"
        }
    ],
    "sg:phone":"+1 205 497 4440",
    "sg:postcode":"35023",
    "sg:province":"AL",
    "sg:tags":[
        "shop"
    ],
    "wof:name":"Nail Works",
    "wof:placetype":"venue"
},
  "geometry": {"coordinates":[-86.97909199999999,33.447363],"type":"Point"}
}