{
  "type": "Feature",
  "properties": {
    "iso:country":"US",
    "sg:address":"1300 W Montgomery Ave",
    "sg:city":"Sheffield",
    "sg:classifiers":[
        {
            "category":"Retail",
            "subcategory":"Funeral Services",
            "type":"Services"
        }
    ],
    "sg:phone":"+1 256 381 7030",
    "sg:postcode":"35660",
    "sg:province":"AL",
    "sg:tags":[
        "director"
    ],
    "wof:name":"Trinity Memorial",
    "wof:placetype":"venue"
},
  "geometry": {"coordinates":[-87.703214,34.7531],"type":"Point"}
}