{
  "type": "Feature",
  "properties": {
    "addr:full":"1672 Montclair Rd Irondale AL 35210",
    "addr:housenumber":"1672",
    "addr:postcode":"35210",
    "addr:street":"Montclair Rd",
    "iso:country":"US",
    "sg:address":"1672 Montclair Rd",
    "sg:city":"Irondale",
    "sg:classifiers":[
        {
            "category":"Home & Garden",
            "subcategory":"Furniture",
            "type":"Retail Goods"
        },
        {
            "category":"Home & Garden",
            "subcategory":"Home Furnishings",
            "type":"Retail Goods"
        },
        {
            "category":"Home & Garden",
            "subcategory":"Carpets & Floor Coverings",
            "type":"Retail Goods"
        }
    ],
    "sg:phone":"+1 205 956 0188",
    "sg:postcode":"35210",
    "sg:province":"AL",
    "sg:tags":[
        "bedroom",
        "set",
        "store",
        "bed",
        "mattress"
    ],
    "sg:website":"http://www.mattressfirm.com",
    "wof:name":"Mattress Firm",
    "wof:placetype":"venue"
},
  "geometry": {"coordinates":[-86.718681,33.526887],"type":"Point"}
}