{
  "type": "Feature",
  "properties": {
    "addr:full":"700 Energy Center Blvd Northport AL 35473",
    "addr:housenumber":"700",
    "addr:postcode":"35473",
    "addr:street":"Energy Center Blvd",
    "iso:country":"US",
    "sg:address":"700 Energy Center Blvd",
    "sg:city":"Northport",
    "sg:classifiers":[
        {
            "category":"Health Services",
            "subcategory":"Doctor",
            "type":"Services"
        }
    ],
    "sg:phone":"+1 205 391 9777",
    "sg:postcode":"35473",
    "sg:province":"AL",
    "sg:tags":[
        "medical"
    ],
    "wof:name":"Kyle Echols MD",
    "wof:placetype":"venue"
},
  "geometry": {"coordinates":[-87.556138,33.239914],"type":"Point"}
}