{
  "type": "Feature",
  "properties": {
    "iso:country":"US",
    "sg:address":"2503 Southtown Ct S",
    "sg:city":"Birmingham",
    "sg:classifiers":[
        {
            "category":"Place Of Worship",
            "type":"Public Place"
        }
    ],
    "sg:phone":"+1 205 504 2562",
    "sg:postcode":"35205",
    "sg:province":"AL",
    "sg:tags":[
        "church"
    ],
    "wof:name":"Voice Of Reason, Inc.",
    "wof:placetype":"venue"
},
  "geometry": {"coordinates":[-86.792665,33.507153],"type":"Point"}
}