{
  "type": "Feature",
  "properties": {
    "addr:full":"125 N Broadnax St Dadeville AL 36853",
    "addr:housenumber":"125",
    "addr:postcode":"36853",
    "addr:street":"N Broadnax St",
    "iso:country":"US",
    "sg:address":"125 N Broadnax St",
    "sg:city":"Dadeville",
    "sg:classifiers":[
        {
            "category":"Government",
            "subcategory":"Court House",
            "type":"Public Place"
        }
    ],
    "sg:phone":"+1 256 825 4268",
    "sg:postcode":"36853",
    "sg:province":"AL",
    "sg:tags":[
        "county"
    ],
    "wof:name":"Tallapoosa Cnty Probate Judge",
    "wof:placetype":"venue"
},
  "geometry": {"coordinates":[-85.76360200000001,32.831141],"type":"Point"}
}