{
  "type": "Feature",
  "properties": {
    "iso:country":"US",
    "sg:address":"5018 US Hwy 80",
    "sg:city":"Opelika",
    "sg:classifiers":[
        {
            "category":"Building & Trades",
            "subcategory":"Construction",
            "type":"Services"
        }
    ],
    "sg:phone":"+1 334 298 5991",
    "sg:postcode":"36804",
    "sg:province":"AL",
    "sg:tags":[
        "house"
    ],
    "wof:name":"Construction Careers Americ",
    "wof:placetype":"venue"
},
  "geometry": {"coordinates":[-85.27513,32.445005],"type":"Point"}
}