{
  "type": "Feature",
  "properties": {
    "iso:country":"US",
    "sg:address":"5874 Co Rd 79",
    "sg:city":"Daviston",
    "sg:classifiers":[
        {
            "category":"Social Services",
            "subcategory":"Adult Care",
            "type":"Services"
        },
        {
            "category":"Social Services",
            "subcategory":"Child Care",
            "type":"Services"
        }
    ],
    "sg:phone":"+1 256 395 9343",
    "sg:postcode":"36256",
    "sg:province":"AL",
    "sg:tags":[
        "home",
        "day",
        "residential"
    ],
    "wof:name":"Country Acres Care Homes",
    "wof:placetype":"venue"
},
  "geometry": {"coordinates":[-85.658483,33.033773],"type":"Point"}
}