{
  "type": "Feature",
  "properties": {
    "iso:country":"US",
    "sg:address":"8580 Madison Blvd",
    "sg:city":"Madison",
    "sg:classifiers":[
        {
            "category":"Personal",
            "subcategory":"Beauty Salon",
            "type":"Services"
        }
    ],
    "sg:phone":"+1 256 772 5771",
    "sg:postcode":"35758",
    "sg:province":"AL",
    "sg:tags":[
        "shop"
    ],
    "wof:name":"Cuts By Us",
    "wof:placetype":"venue"
},
  "geometry": {"coordinates":[-86.739093,34.681839],"type":"Point"}
}