{
  "type": "Feature",
  "properties": {
    "iso:country":"US",
    "sg:address":"3226 Stillman Blvd",
    "sg:city":"Tuscaloosa",
    "sg:classifiers":[
        {
            "category":"Banks & Credit Unions",
            "subcategory":"Bank",
            "type":"Services"
        }
    ],
    "sg:phone":"+1 205 758 5939",
    "sg:postcode":"35401",
    "sg:province":"AL",
    "sg:tags":[
        "cashing",
        "check"
    ],
    "wof:name":"One Stop Financial Ctr Inc",
    "wof:placetype":"venue"
},
  "geometry": {"coordinates":[-87.579103,33.202012],"type":"Point"}
}