{
  "type": "Feature",
  "properties": {
    "iso:country":"US",
    "sg:address":"3459 Purdy Dr NW",
    "sg:city":"Huntsville",
    "sg:classifiers":[
        {
            "category":"Building & Trades",
            "subcategory":"Cleaning & Sanitation",
            "type":"Services"
        }
    ],
    "sg:phone":"+1 256 859 4807",
    "sg:postcode":"35810",
    "sg:province":"AL",
    "wof:name":"Nuhouse Cleaning Svc",
    "wof:placetype":"venue"
},
  "geometry": {"coordinates":[-86.620699,34.753868],"type":"Point"}
}