{
  "type": "Feature",
  "properties": {
    "addr:full":"2011 2nd Ave E Oneonta AL 35121",
    "addr:housenumber":"2011",
    "addr:postcode":"35121",
    "addr:street":"2Nd Ave E",
    "iso:country":"US",
    "sg:address":"2011 2nd Ave E",
    "sg:city":"Oneonta",
    "sg:classifiers":[
        {
            "category":"Building & Trades",
            "subcategory":"Pest Control",
            "type":"Services"
        }
    ],
    "sg:phone":"+1 205 274 0037",
    "sg:postcode":"35121",
    "sg:province":"AL",
    "wof:name":"Hallman Pest Control Inc",
    "wof:placetype":"venue"
},
  "geometry": {"coordinates":[-86.45250900000001,33.96932],"type":"Point"}
}