{
  "type": "Feature",
  "properties": {
    "iso:country":"US",
    "sg:address":"6232 Spanish Trail Dr",
    "sg:city":"Theodore",
    "sg:classifiers":[
        {
            "category":"Real Estate",
            "subcategory":"Real Estate Operator",
            "type":"Services"
        }
    ],
    "sg:phone":"+1 251 654 0033",
    "sg:postcode":"36582",
    "sg:province":"AL",
    "sg:tags":[
        "apartment"
    ],
    "wof:name":"Spanish Oak Inn",
    "wof:placetype":"venue"
},
  "geometry": {"coordinates":[-88.213323,30.561648],"type":"Point"}
}