{
  "type": "Feature",
  "properties": {
    "iso:country":"US",
    "sg:address":"21840 Sedlack Rd",
    "sg:city":"Silverhill",
    "sg:classifiers":[
        {
            "category":"Building & Trades",
            "subcategory":"Construction",
            "type":"Services"
        }
    ],
    "sg:phone":"+1 251 945 5693",
    "sg:postcode":"36576",
    "sg:province":"AL",
    "sg:tags":[
        "house"
    ],
    "wof:name":"J&P Home Builders Inc",
    "wof:placetype":"venue"
},
  "geometry": {"coordinates":[-87.776155,30.540593],"type":"Point"}
}