{
  "type": "Feature",
  "properties": {
    "addr:full":"565 Fieldstown Rd Gardendale AL 35071",
    "addr:housenumber":"565",
    "addr:postcode":"35071",
    "addr:street":"Fieldstown Rd",
    "iso:country":"US",
    "sg:address":"565 Fieldstown Rd",
    "sg:city":"Gardendale",
    "sg:classifiers":[
        {
            "category":"Autos & Motor Vehicles",
            "subcategory":"Fuel & Gas Station",
            "type":"Retail Goods"
        }
    ],
    "sg:phone":"+1 205 631 0235",
    "sg:postcode":"35071",
    "sg:province":"AL",
    "sg:tags":[
        "gasoline"
    ],
    "wof:name":"Chevron",
    "wof:placetype":"venue"
},
  "geometry": {"coordinates":[-86.818606,33.651928],"type":"Point"}
}