{
  "type": "Feature",
  "properties": {
    "addr:full":"1055 Springhill Ave Mobile AL 36604",
    "addr:housenumber":"1055",
    "addr:postcode":"36604",
    "addr:street":"Springhill Ave",
    "iso:country":"US",
    "sg:address":"1055 Springhill Ave",
    "sg:city":"Mobile",
    "sg:classifiers":[
        {
            "category":"Personal",
            "subcategory":"Beauty Salon",
            "type":"Services"
        }
    ],
    "sg:phone":"+1 251 434 0044",
    "sg:postcode":"36604",
    "sg:province":"AL",
    "sg:tags":[
        "shop",
        "barber"
    ],
    "wof:name":"New Attitude Hair Salon",
    "wof:placetype":"venue"
},
  "geometry": {"coordinates":[-88.06012200000001,30.691215],"type":"Point"}
}