{
  "type": "Feature",
  "properties": {
    "iso:country":"US",
    "sg:address":"604 Strauss St",
    "sg:city":"Dothan",
    "sg:classifiers":[
        {
            "category":"Building & Trades",
            "subcategory":"Construction",
            "type":"Services"
        }
    ],
    "sg:phone":"+1 334 702 0732",
    "sg:postcode":"36301",
    "sg:province":"AL",
    "sg:tags":[
        "contractor"
    ],
    "wof:name":"J & J Ceramic Tile Inc",
    "wof:placetype":"venue"
},
  "geometry": {"coordinates":[-85.405754,31.217436],"type":"Point"}
}