{
  "type": "Feature",
  "properties": {
    "addr:full":"7001 Crestwood Blvd Birmingham AL 35210",
    "addr:housenumber":"7001",
    "addr:postcode":"35210",
    "addr:street":"Crestwood Blvd",
    "iso:country":"US",
    "sg:address":"7001 Crestwood Blvd",
    "sg:city":"Birmingham",
    "sg:classifiers":[
        {
            "category":"Cafe",
            "type":"Food & Drink"
        }
    ],
    "sg:menulink":"http://www.allmenus.com/al/birmingham/255317-alfredos-pizza-cafe/menu/",
    "sg:phone":"+1 205 591 1410",
    "sg:postcode":"35210",
    "sg:province":"AL",
    "sg:tags":[
        "american",
        "pizza"
    ],
    "wof:name":"Alfredo's Pizza Cafe",
    "wof:placetype":"venue"
},
  "geometry": {"coordinates":[-86.725393,33.529976],"type":"Point"}
}