{
  "type": "Feature",
  "properties": {
    "iso:country":"US",
    "sg:address":"7914 Memorial Pkwy SW",
    "sg:city":"Huntsville",
    "sg:classifiers":[
        {
            "category":"Retail",
            "subcategory":"Repair Shop",
            "type":"Services"
        }
    ],
    "sg:phone":"+1 256 881 9300",
    "sg:postcode":"35802",
    "sg:province":"AL",
    "sg:tags":[
        "lock",
        "system",
        "locksmith",
        "pa",
        "security",
        "electronic"
    ],
    "wof:name":"Locktec",
    "wof:placetype":"venue"
},
  "geometry": {"coordinates":[-86.571274,34.662478],"type":"Point"}
}