{
  "type": "Feature",
  "properties": {
    "addr:full":"92 Redstone Way Birmingham AL 35215",
    "addr:housenumber":"92",
    "addr:postcode":"35215",
    "addr:street":"Redstone Way",
    "iso:country":"US",
    "sg:address":"92 Redstone Way",
    "sg:city":"Birmingham",
    "sg:classifiers":[
        {
            "category":"Communications",
            "subcategory":"Film & Video Production",
            "type":"Services"
        }
    ],
    "sg:phone":"+1 205 854 2999",
    "sg:postcode":"35215",
    "sg:province":"AL",
    "sg:tags":[
        "dvds-rental",
        "tape",
        "sale",
        "taping"
    ],
    "sg:website":"http://www.familyvideo.com",
    "wof:name":"Family Video",
    "wof:placetype":"venue"
},
  "geometry": {"coordinates":[-86.718191,33.612281],"type":"Point"}
}