{
  "type": "Feature",
  "properties": {
    "addr:full":"4875 Tufts Rd Mobile AL 36619",
    "addr:housenumber":"4875",
    "addr:postcode":"36619",
    "addr:street":"Tufts Rd",
    "iso:country":"US",
    "sg:address":"4875 Tufts Rd",
    "sg:city":"Mobile",
    "sg:classifiers":[
        {
            "category":"Building & Trades",
            "subcategory":"Plumbing",
            "type":"Services"
        }
    ],
    "sg:phone":"+1 251 666 2165",
    "sg:postcode":"36619",
    "sg:province":"AL",
    "sg:tags":[
        "repair",
        "mechanical",
        "contractor",
        "pressure",
        "v",
        "fabricates"
    ],
    "sg:website":"www.arccontrols.com",
    "wof:name":"ARC Controls Inc",
    "wof:placetype":"venue"
},
  "geometry": {"coordinates":[-88.14321099999999,30.588053],"type":"Point"}
}