{
  "type": "Feature",
  "properties": {
    "iso:country":"US",
    "sg:address":"301 Autauga St",
    "sg:city":"Wetumpka",
    "sg:classifiers":[
        {
            "category":"Retail",
            "subcategory":"Car Wash",
            "type":"Services"
        }
    ],
    "sg:phone":"+1 334 567 5303",
    "sg:postcode":"36092",
    "sg:province":"AL",
    "sg:tags":[
        "automobile",
        "detail",
        "clean"
    ],
    "wof:name":"Quick Wash & Detail",
    "wof:placetype":"venue"
},
  "geometry": {"coordinates":[-86.219459,32.542415],"type":"Point"}
}