{
  "type": "Feature",
  "properties": {
    "iso:country":"US",
    "sg:address":"11249 Co Rd 65",
    "sg:city":"Foley",
    "sg:classifiers":[
        {
            "category":"Personal",
            "subcategory":"Beauty Salon",
            "type":"Services"
        }
    ],
    "sg:phone":"+1 251 943 4695",
    "sg:postcode":"36535",
    "sg:province":"AL",
    "sg:tags":[
        "shop"
    ],
    "wof:name":"A Curl & Style",
    "wof:placetype":"venue"
},
  "geometry": {"coordinates":[-87.717264,30.388469],"type":"Point"}
}