{
  "type": "Feature",
  "properties": {
    "addr:full":"900 18th St Birmingham AL 35218",
    "addr:housenumber":"900",
    "addr:postcode":"35218",
    "addr:street":"18Th St",
    "iso:country":"US",
    "sg:address":"900 18th St",
    "sg:city":"Birmingham",
    "sg:classifiers":[
        {
            "category":"Retail",
            "subcategory":"Auto Repair",
            "type":"Services"
        }
    ],
    "sg:phone":"+1 205 786 0521",
    "sg:postcode":"35218",
    "sg:province":"AL",
    "sg:tags":[
        "repairing",
        "automobile"
    ],
    "wof:name":"David's Automotive",
    "wof:placetype":"venue"
},
  "geometry": {"coordinates":[-86.891398,33.511645],"type":"Point"}
}