{
  "type": "Feature",
  "properties": {
    "addr:full":"24657 Co Rd 38 Summerdale AL 36580",
    "addr:housenumber":"24657;38",
    "addr:postcode":"36580",
    "addr:street":"Co Rd",
    "iso:country":"US",
    "sg:address":"24657 Co Rd 38",
    "sg:city":"Summerdale",
    "sg:classifiers":[
        {
            "category":"Professional",
            "type":"Services"
        },
        {
            "category":"Retail",
            "subcategory":"Repair Shop",
            "type":"Services"
        }
    ],
    "sg:phone":"+1 251 988 8085",
    "sg:postcode":"36580",
    "sg:province":"AL",
    "sg:tags":[
        "establishment"
    ],
    "wof:name":"Jonny's House Of Horsepower",
    "wof:placetype":"venue"
},
  "geometry": {"coordinates":[-87.60163900000001,30.509625],"type":"Point"}
}