{
  "type": "Feature",
  "properties": {
    "addr:full":"307 Columbia Hwy Dothan AL 36301",
    "addr:housenumber":"307",
    "addr:postcode":"36301",
    "addr:street":"Columbia Hwy",
    "iso:country":"US",
    "sg:address":"307 Columbia Hwy",
    "sg:city":"Dothan",
    "sg:classifiers":[
        {
            "category":"Banks & Credit Unions",
            "subcategory":"Bank",
            "type":"Services"
        }
    ],
    "sg:phone":"+1 334 678 0035",
    "sg:postcode":"36301",
    "sg:province":"AL",
    "sg:tags":[
        "cashing",
        "check"
    ],
    "wof:name":"Cash 4 Check",
    "wof:placetype":"venue"
},
  "geometry": {"coordinates":[-85.386132,31.222128],"type":"Point"}
}