{
  "type": "Feature",
  "properties": {
    "addr:full":"348 Pinehurst Dr Georgiana AL 36033",
    "addr:housenumber":"348",
    "addr:postcode":"36033",
    "addr:street":"Pinehurst Dr Georgiana",
    "iso:country":"US",
    "sg:address":"348 Pinehurst Dr",
    "sg:city":"Georgiana",
    "sg:classifiers":[
        {
            "category":"Professional",
            "type":"Services"
        }
    ],
    "sg:phone":"+1 334 376 5360",
    "sg:postcode":"36033",
    "sg:province":"AL",
    "wof:name":"Barbara Hall",
    "wof:placetype":"venue"
},
  "geometry": {"coordinates":[-86.73815999999999,31.636381],"type":"Point"}
}