{
  "type": "Feature",
  "properties": {
    "addr:full":"2064 US Hwy 231 Ozark AL 36360",
    "addr:housenumber":"2064",
    "addr:postcode":"36360",
    "addr:street":"Us Hwy 231",
    "iso:country":"US",
    "sg:address":"2064 US Hwy 231",
    "sg:city":"Ozark",
    "sg:classifiers":[
        {
            "category":"Travel",
            "subcategory":"Hotels & Motels",
            "type":"Entertainment"
        }
    ],
    "sg:phone":"+1 334 774 5166",
    "sg:postcode":"36360",
    "sg:province":"AL",
    "wof:name":"All American Ozark Inn",
    "wof:placetype":"venue"
},
  "geometry": {"coordinates":[-85.610472,31.41933],"type":"Point"}
}