{
  "type": "Feature",
  "properties": {
    "iso:country":"US",
    "sg:address":"369 N Mobile St",
    "sg:city":"Fairhope",
    "sg:classifiers":[
        {
            "category":"Professional",
            "type":"Services"
        }
    ],
    "sg:phone":"+1 251 929 7790",
    "sg:postcode":"36532",
    "sg:province":"AL",
    "sg:tags":[
        "establishment"
    ],
    "wof:name":"Bay Break",
    "wof:placetype":"venue"
},
  "geometry": {"coordinates":[-87.905241,30.533265],"type":"Point"}
}