{
  "type": "Feature",
  "properties": {
    "iso:country":"US",
    "sg:address":"504 14th St",
    "sg:city":"Tuscaloosa",
    "sg:classifiers":[
        {
            "category":"Shopping",
            "subcategory":"Books",
            "type":"Retail Goods"
        }
    ],
    "sg:phone":"+1 205 345 3910",
    "sg:postcode":"35401",
    "sg:province":"AL",
    "wof:name":"Off Campus College Bookstore",
    "wof:placetype":"venue"
},
  "geometry": {"coordinates":[-87.544698,33.200174],"type":"Point"}
}