{
  "type": "Feature",
  "properties": {
    "addr:full":"301 Market St NE Decatur AL 35601",
    "addr:housenumber":"301",
    "addr:postcode":"35601",
    "addr:street":"Market St Ne",
    "iso:country":"US",
    "sg:address":"301 Market St NE",
    "sg:city":"Decatur",
    "sg:classifiers":[
        {
            "category":"Personal",
            "subcategory":"Beauty Salon",
            "type":"Services"
        }
    ],
    "sg:phone":"+1 256 353 2413",
    "sg:postcode":"35601",
    "sg:province":"AL",
    "wof:name":"Anita's Riverwalk Salon",
    "wof:placetype":"venue"
},
  "geometry": {"coordinates":[-86.979361,34.61271],"type":"Point"}
}