{
  "type": "Feature",
  "properties": {
    "addr:full":"501 E Main St Prattville AL 36067",
    "addr:housenumber":"501",
    "addr:postcode":"36067",
    "addr:street":"E Main St",
    "iso:country":"US",
    "sg:address":"501 E Main St",
    "sg:city":"Prattville",
    "sg:classifiers":[
        {
            "category":"Retail",
            "subcategory":"Car Wash",
            "type":"Services"
        }
    ],
    "sg:phone":"+1 334 365 9376",
    "sg:postcode":"36067",
    "sg:province":"AL",
    "sg:tags":[
        "carwash"
    ],
    "wof:name":"A J Car Wash",
    "wof:placetype":"venue"
},
  "geometry": {"coordinates":[-86.46173400000001,32.459477],"type":"Point"}
}