{
  "type": "Feature",
  "properties": {
    "iso:country":"US",
    "sg:address":"3054 Leeman Ferry Rd SW",
    "sg:city":"Huntsville",
    "sg:classifiers":[
        {
            "category":"Building & Trades",
            "subcategory":"Construction",
            "type":"Services"
        }
    ],
    "sg:phone":"+1 256 880 2788",
    "sg:postcode":"35801",
    "sg:province":"AL",
    "sg:tags":[
        "general",
        "contractor"
    ],
    "wof:name":"Mc Quinn & Eastep Construction",
    "wof:placetype":"venue"
},
  "geometry": {"coordinates":[-86.59167,34.705343],"type":"Point"}
}