{
  "type": "Feature",
  "properties": {
    "iso:country":"US",
    "sg:address":"67420 State Rte 77",
    "sg:city":"Talladega",
    "sg:classifiers":[
        {
            "category":"Food & Beverages",
            "subcategory":"Groceries & Convenience Stores",
            "type":"Retail Goods"
        }
    ],
    "sg:phone":"+1 256 362 2484",
    "sg:postcode":"35160",
    "sg:province":"AL",
    "sg:tags":[
        "grocer"
    ],
    "wof:name":"Shell Discount Food Mart",
    "wof:placetype":"venue"
},
  "geometry": {"coordinates":[-86.119751,33.476228],"type":"Point"}
}