{
  "type": "Feature",
  "properties": {
    "addr:full":"700 Valley Ave Birmingham AL 35209",
    "addr:housenumber":"700",
    "addr:postcode":"35209",
    "addr:street":"Valley Ave",
    "iso:country":"US",
    "sg:address":"700 Valley Ave",
    "sg:city":"Birmingham",
    "sg:classifiers":[
        {
            "category":"Autos & Motor Vehicles",
            "subcategory":"Fuel & Gas Station",
            "type":"Retail Goods"
        }
    ],
    "sg:phone":"+1 205 942 7632",
    "sg:postcode":"35209",
    "sg:province":"AL",
    "sg:website":"http://www.texaco.com",
    "wof:name":"Beacon Parkway Texaco",
    "wof:placetype":"venue"
},
  "geometry": {"coordinates":[-86.816101,33.475361],"type":"Point"}
}