{
  "type": "Feature",
  "properties": {
    "addr:full":"214 W 1st St Sylacauga AL 35150",
    "addr:housenumber":"214",
    "addr:postcode":"35150",
    "addr:street":"W 1St St",
    "iso:country":"US",
    "sg:address":"214 W 1st St",
    "sg:city":"Sylacauga",
    "sg:classifiers":[
        {
            "category":"Manufacturing",
            "subcategory":"Printing",
            "type":"Manufacturing & Wholesale Goods"
        }
    ],
    "sg:phone":"+1 256 245 3236",
    "sg:postcode":"35150",
    "sg:province":"AL",
    "sg:tags":[
        "commercial"
    ],
    "sg:website":"www.swenprint.com",
    "wof:name":"SWEN Communications Inc",
    "wof:placetype":"venue"
},
  "geometry": {"coordinates":[-86.255486,33.169384],"type":"Point"}
}