{
  "type": "Feature",
  "properties": {
    "iso:country":"US",
    "sg:address":"1042 Earl Roberts Rd",
    "sg:city":"Anniston",
    "sg:classifiers":[
        {
            "category":"Building & Trades",
            "subcategory":"Construction",
            "type":"Services"
        }
    ],
    "sg:phone":"+1 256 237 3224",
    "sg:postcode":"36207",
    "sg:province":"AL",
    "sg:tags":[
        "steel",
        "erection",
        "structural"
    ],
    "wof:name":"Camp Construction Co",
    "wof:placetype":"venue"
},
  "geometry": {"coordinates":[-85.664726,33.685912],"type":"Point"}
}