{
  "type": "Feature",
  "properties": {
    "addr:full":"19070 S Greeno Rd Fairhope AL 36532",
    "addr:housenumber":"19070",
    "addr:postcode":"36532",
    "addr:street":"S Greeno Rd",
    "iso:country":"US",
    "sg:address":"19070 S Greeno Rd",
    "sg:city":"Fairhope",
    "sg:phone":"+1 251 928 1826",
    "sg:postcode":"36532",
    "sg:province":"AL",
    "sg:tags":[
        "gasoline",
        "product",
        "oil",
        "petroleum"
    ],
    "wof:name":"Gas-N-Go Oil Co Inc",
    "wof:placetype":"venue"
},
  "geometry": {"coordinates":[-87.88605200000001,30.502673],"type":"Point"}
}