{
  "type": "Feature",
  "properties": {
    "addr:full":"1813 Rankin Pl NW Huntsville AL 35816",
    "addr:housenumber":"1813",
    "addr:postcode":"35816",
    "addr:street":"Rankin Pl Nw",
    "iso:country":"US",
    "sg:address":"1813 Rankin Pl NW",
    "sg:city":"Huntsville",
    "sg:classifiers":[
        {
            "category":"Manufacturing",
            "subcategory":"Tools & Machinery",
            "type":"Manufacturing & Wholesale Goods"
        }
    ],
    "sg:phone":"+1 256 721 0240",
    "sg:postcode":"35816",
    "sg:province":"AL",
    "sg:tags":[
        "machine",
        "shop"
    ],
    "wof:name":"Hodge Machine Co",
    "wof:placetype":"venue"
},
  "geometry": {"coordinates":[-86.642385,34.748712],"type":"Point"}
}