{
  "type": "Feature",
  "properties": {
    "iso:country":"US",
    "sg:address":"208 Hackberry Way",
    "sg:city":"Chelsea",
    "sg:classifiers":[
        {
            "category":"Professional",
            "subcategory":"Business Services",
            "type":"Services"
        }
    ],
    "sg:phone":"+1 205 678 7854",
    "sg:postcode":"35043",
    "sg:province":"AL",
    "wof:name":"Mnd Group LLC",
    "wof:placetype":"venue"
},
  "geometry": {"coordinates":[-86.64486100000001,33.339902],"type":"Point"}
}