{
  "type": "Feature",
  "properties": {
    "iso:country":"US",
    "sg:address":"3015 Old Opelika Rd",
    "sg:city":"Opelika",
    "sg:classifiers":[
        {
            "category":"Organizations",
            "subcategory":"Religious Organization",
            "type":"Services"
        }
    ],
    "sg:phone":"+1 334 749 9112",
    "sg:postcode":"36801",
    "sg:province":"AL",
    "sg:tags":[
        "church"
    ],
    "sg:website":"www.airviewchurch.org",
    "wof:name":"Airview Church Of God",
    "wof:placetype":"venue"
},
  "geometry": {"coordinates":[-85.42103299999999,32.619074],"type":"Point"}
}