{
  "type": "Feature",
  "properties": {
    "addr:full":"3200 Monte Doro Dr Birmingham AL 35216",
    "addr:housenumber":"3200",
    "addr:postcode":"35216",
    "addr:street":"Monte Doro Dr",
    "iso:country":"US",
    "sg:address":"3200 Monte Doro Dr",
    "sg:city":"Birmingham",
    "sg:classifiers":[
        {
            "category":"Retail",
            "subcategory":"Car Wash",
            "type":"Services"
        }
    ],
    "sg:phone":"+1 205 979 0157",
    "sg:postcode":"35216",
    "sg:province":"AL",
    "sg:tags":[
        "carwash"
    ],
    "wof:name":"Rainbow Pressur Wsh",
    "wof:placetype":"venue"
},
  "geometry": {"coordinates":[-86.80333,33.404688],"type":"Point"}
}