{
  "type": "Feature",
  "properties": {
    "iso:country":"US",
    "sg:address":"3101 Rainbow Dr",
    "sg:city":"Rainbow City",
    "sg:classifiers":[
        {
            "category":"Food & Beverages",
            "subcategory":"Groceries & Convenience Stores",
            "type":"Retail Goods"
        }
    ],
    "sg:phone":"+1 256 442 6726",
    "sg:postcode":"35906",
    "sg:province":"AL",
    "sg:tags":[
        "grocer"
    ],
    "wof:name":"Mini-Mart Store",
    "wof:placetype":"venue"
},
  "geometry": {"coordinates":[-86.030536,33.96297],"type":"Point"}
}