{
  "type": "Feature",
  "properties": {
    "iso:country":"US",
    "sg:address":"2245 Bessemer Rd",
    "sg:city":"Birmingham",
    "sg:classifiers":[
        {
            "category":"Shopping",
            "subcategory":"Bicycles & Sporting Goods",
            "type":"Retail Goods"
        }
    ],
    "sg:phone":"+1 205 781 7130",
    "sg:postcode":"35208",
    "sg:province":"AL",
    "wof:name":"Hibbett Sporting Goods Inc",
    "wof:placetype":"venue"
},
  "geometry": {"coordinates":[-86.87861100000001,33.495313],"type":"Point"}
}