{
  "type": "Feature",
  "properties": {
    "iso:country":"US",
    "sg:address":"400 Co Rd 441",
    "sg:city":"Centre",
    "sg:classifiers":[
        {
            "category":"Restaurant",
            "type":"Food & Drink"
        }
    ],
    "sg:phone":"+1 256 927 8897",
    "sg:postcode":"35960",
    "sg:province":"AL",
    "sg:tags":[
        "eating"
    ],
    "wof:name":"Creek Side Fish & Grill",
    "wof:placetype":"venue"
},
  "geometry": {"coordinates":[-85.659032,34.1095],"type":"Point"}
}