{
  "type": "Feature",
  "properties": {
    "iso:country":"US",
    "sg:address":"963 Creamer Rd",
    "sg:city":"Wetumpka",
    "sg:classifiers":[
        {
            "category":"Education",
            "subcategory":"Library",
            "type":"Public Place"
        }
    ],
    "sg:phone":"+1 334 567 9658",
    "sg:postcode":"36093",
    "sg:province":"AL",
    "wof:name":"Between Branches",
    "wof:placetype":"venue"
},
  "geometry": {"coordinates":[-86.109527,32.523411],"type":"Point"}
}