{
  "type": "Feature",
  "properties": {
    "addr:full":"2301 Reeves St Dothan AL 36303",
    "addr:housenumber":"2301",
    "addr:postcode":"36303",
    "addr:street":"Reeves St",
    "iso:country":"US",
    "sg:address":"2301 Reeves St",
    "sg:city":"Dothan",
    "sg:classifiers":[
        {
            "category":"Shopping",
            "subcategory":"Discount & Variety Stores",
            "type":"Retail Goods"
        }
    ],
    "sg:phone":"+1 334 673 0926",
    "sg:postcode":"36303",
    "sg:province":"AL",
    "wof:name":"Dollar General",
    "wof:placetype":"venue"
},
  "geometry": {"coordinates":[-85.38888799999999,31.25446],"type":"Point"}
}