{
  "type": "Feature",
  "properties": {
    "iso:country":"US",
    "sg:address":"301 Westgate Pkwy",
    "sg:city":"Dothan",
    "sg:classifiers":[
        {
            "category":"Health Services",
            "subcategory":"Hospital",
            "type":"Services"
        }
    ],
    "sg:phone":"+1 334 615 2302",
    "sg:postcode":"36303",
    "sg:province":"AL",
    "wof:name":"Flowers Hospital",
    "wof:placetype":"venue"
},
  "geometry": {"coordinates":[-85.434577,31.231704],"type":"Point"}
}