{
  "type": "Feature",
  "properties": {
    "addr:full":"764 E Glenn Ave Auburn AL 36830",
    "addr:housenumber":"764",
    "addr:postcode":"36830",
    "addr:street":"E Glenn Ave",
    "iso:country":"US",
    "sg:address":"764 E Glenn Ave",
    "sg:city":"Auburn",
    "sg:classifiers":[
        {
            "category":"Health Services",
            "subcategory":"Chiropractor",
            "type":"Services"
        }
    ],
    "sg:phone":"+1 334 501 4691",
    "sg:postcode":"36830",
    "sg:province":"AL",
    "wof:name":"Meals Ryan J DC",
    "wof:placetype":"venue"
},
  "geometry": {"coordinates":[-85.46698499999999,32.608931],"type":"Point"}
}