{
  "type": "Feature",
  "properties": {
    "iso:country":"US",
    "sg:address":"1120 Hillcrest Rd",
    "sg:city":"Mobile",
    "sg:classifiers":[
        {
            "category":"Professional",
            "subcategory":"Computer Services",
            "type":"Services"
        }
    ],
    "sg:phone":"+1 251 633 6275",
    "sg:postcode":"36695",
    "sg:province":"AL",
    "sg:tags":[
        "consultant",
        "designer"
    ],
    "wof:name":"Micro-2 Inc",
    "wof:placetype":"venue"
},
  "geometry": {"coordinates":[-88.190775,30.666992],"type":"Point"}
}