{
  "type": "Feature",
  "properties": {
    "addr:full":"204 Daryl St Livingston AL 35470",
    "addr:housenumber":"204",
    "addr:postcode":"35470",
    "addr:street":"Daryl St",
    "iso:country":"US",
    "sg:address":"204 Daryl St",
    "sg:city":"Livingston",
    "sg:classifiers":[
        {
            "category":"Insurance",
            "subcategory":"Insurance Agent",
            "type":"Services"
        }
    ],
    "sg:phone":"+1 205 652 1544",
    "sg:postcode":"35470",
    "sg:province":"AL",
    "sg:tags":[
        "adjuster"
    ],
    "wof:name":"C R Peden",
    "wof:placetype":"venue"
},
  "geometry": {"coordinates":[-88.201836,32.607566],"type":"Point"}
}