{
  "type": "Feature",
  "properties": {
    "iso:country":"US",
    "sg:address":"1240 1st St N",
    "sg:city":"Alabaster",
    "sg:classifiers":[
        {
            "category":"Manufacturing",
            "subcategory":"Printing",
            "type":"Manufacturing & Wholesale Goods"
        }
    ],
    "sg:phone":"+1 205 621 8822",
    "sg:postcode":"35007",
    "sg:province":"AL",
    "sg:tags":[
        "newspaper"
    ],
    "wof:name":"Paisano",
    "wof:placetype":"venue"
},
  "geometry": {"coordinates":[-86.813156,33.257554],"type":"Point"}
}