{
  "type": "Feature",
  "properties": {
    "iso:country":"US",
    "sg:address":"424 S Oates St",
    "sg:city":"Dothan",
    "sg:classifiers":[
        {
            "category":"Professional",
            "subcategory":"Lawyer & Legal Services",
            "type":"Services"
        }
    ],
    "sg:phone":"+1 334 702 4335",
    "sg:postcode":"36301",
    "sg:province":"AL",
    "sg:tags":[
        "attorney"
    ],
    "wof:name":"G Wayne Ashbee",
    "wof:placetype":"venue"
},
  "geometry": {"coordinates":[-85.393105,31.218503],"type":"Point"}
}