{
  "type": "Feature",
  "properties": {
    "addr:full":"1613 Jackson Blvd Birmingham AL 35217",
    "addr:housenumber":"1613",
    "addr:postcode":"35217",
    "addr:street":"Jackson Blvd",
    "iso:country":"US",
    "sg:address":"1613 Jackson Blvd",
    "sg:city":"Birmingham",
    "sg:classifiers":[
        {
            "category":"Manufacturing",
            "subcategory":"Printing",
            "type":"Manufacturing & Wholesale Goods"
        }
    ],
    "sg:phone":"+1 205 849 9366",
    "sg:postcode":"35217",
    "sg:province":"AL",
    "sg:tags":[
        "commercial"
    ],
    "wof:name":"Complete Printing Svc",
    "wof:placetype":"venue"
},
  "geometry": {"coordinates":[-86.77012999999999,33.582386],"type":"Point"}
}