{
  "type": "Feature",
  "properties": {
    "addr:full":"401 Noble St Anniston AL 36201",
    "addr:housenumber":"401",
    "addr:postcode":"36201",
    "addr:street":"Noble St",
    "iso:country":"US",
    "sg:address":"401 Noble St",
    "sg:city":"Anniston",
    "sg:classifiers":[
        {
            "category":"Social Services",
            "type":"Services"
        }
    ],
    "sg:phone":"+1 256 236 0391",
    "sg:postcode":"36201",
    "sg:province":"AL",
    "sg:tags":[
        "organization",
        "welfare"
    ],
    "wof:name":"American Red Cross",
    "wof:placetype":"venue"
},
  "geometry": {"coordinates":[-85.82972100000001,33.650822],"type":"Point"}
}