{
  "type": "Feature",
  "properties": {
    "addr:full":"520 W Thomason Cir Opelika AL 36801",
    "addr:housenumber":"520",
    "addr:postcode":"36801",
    "addr:street":"W Thomason Cir",
    "iso:country":"US",
    "sg:address":"520 W Thomason Cir",
    "sg:city":"Opelika",
    "sg:classifiers":[
        {
            "category":"Social Services",
            "subcategory":"Job Training",
            "type":"Services"
        }
    ],
    "sg:phone":"+1 334 749 1259",
    "sg:postcode":"36801",
    "sg:province":"AL",
    "wof:name":"Vocational Rehabilitation Svc",
    "wof:placetype":"venue"
},
  "geometry": {"coordinates":[-85.408466,32.639184],"type":"Point"}
}