{
  "type": "Feature",
  "properties": {
    "addr:full":"1080 Montgomery Hwy Vestavia AL 35216",
    "addr:housenumber":"1080",
    "addr:postcode":"35216",
    "addr:street":"Montgomery Hwy Vestavia",
    "iso:country":"US",
    "sg:address":"1080 Montgomery Hwy",
    "sg:city":"Vestavia",
    "sg:classifiers":[
        {
            "category":"Shopping",
            "subcategory":"Bicycles & Sporting Goods",
            "type":"Retail Goods"
        }
    ],
    "sg:phone":"+1 205 979 2222",
    "sg:postcode":"35216",
    "sg:province":"AL",
    "wof:name":"Faceoff Alabama",
    "wof:placetype":"venue"
},
  "geometry": {"coordinates":[-86.788704,33.437702],"type":"Point"}
}