{
  "type": "Feature",
  "properties": {
    "iso:country":"US",
    "sg:address":"1405 Alexander Dr",
    "sg:city":"Dothan",
    "sg:classifiers":[
        {
            "category":"Professional",
            "subcategory":"Art Services",
            "type":"Services"
        }
    ],
    "sg:phone":"+1 334 792 7331",
    "sg:postcode":"36301",
    "sg:province":"AL",
    "sg:tags":[
        "graphic",
        "design",
        "publishing",
        "desktop"
    ],
    "wof:name":"Bers-Man Publishing",
    "wof:placetype":"venue"
},
  "geometry": {"coordinates":[-85.370231,31.211668],"type":"Point"}
}