{
  "type": "Feature",
  "properties": {
    "iso:country":"US",
    "sg:address":"115 S Roberta Ave",
    "sg:city":"Dothan",
    "sg:classifiers":[
        {
            "category":"Building & Trades",
            "subcategory":"Construction",
            "type":"Services"
        }
    ],
    "sg:phone":"+1 334 792 6068",
    "sg:postcode":"36301",
    "sg:province":"AL",
    "sg:tags":[
        "contractor"
    ],
    "wof:name":"Stan West",
    "wof:placetype":"venue"
},
  "geometry": {"coordinates":[-85.419021,31.225096],"type":"Point"}
}