{
  "type": "Feature",
  "properties": {
    "iso:country":"US",
    "sg:address":"74 Meadowlark Ln",
    "sg:city":"Blountsville",
    "sg:classifiers":[
        {
            "category":"Real Estate",
            "subcategory":"Real Estate Operator",
            "type":"Services"
        }
    ],
    "sg:phone":"+1 205 429 3779",
    "sg:postcode":"35031",
    "sg:province":"AL",
    "sg:tags":[
        "apartment"
    ],
    "wof:name":"Meadowlark Village Apartments",
    "wof:placetype":"venue"
},
  "geometry": {"coordinates":[-86.600003,34.079816],"type":"Point"}
}