{
  "type": "Feature",
  "properties": {
    "iso:country":"US",
    "sg:address":"5002 Whitling Dr",
    "sg:city":"Pelham",
    "sg:classifiers":[
        {
            "category":"Wholesale",
            "subcategory":"Sporting Goods",
            "type":"Manufacturing & Wholesale Goods"
        }
    ],
    "sg:phone":"+1 205 664 3332",
    "sg:postcode":"35124",
    "sg:province":"AL",
    "sg:tags":[
        "for",
        "racquetball",
        "comp",
        "an",
        "mail",
        "retail",
        "order"
    ],
    "wof:name":"Vincent Fitness Products",
    "wof:placetype":"venue"
},
  "geometry": {"coordinates":[-86.827063,33.289141],"type":"Point"}
}