{
  "type": "Feature",
  "properties": {
    "iso:country":"US",
    "sg:address":"6007 University Blvd E",
    "sg:city":"Cottondale",
    "sg:classifiers":[
        {
            "category":"Wholesale",
            "subcategory":"Machinery & Supplies",
            "type":"Manufacturing & Wholesale Goods"
        }
    ],
    "sg:phone":"+1 205 556 3333",
    "sg:postcode":"35453",
    "sg:province":"AL",
    "sg:tags":[
        "equipment",
        "log",
        "splitting"
    ],
    "wof:name":"G & S Equipment Co Inc",
    "wof:placetype":"venue"
},
  "geometry": {"coordinates":[-87.456966,33.189224],"type":"Point"}
}