{
  "type": "Feature",
  "properties": {
    "iso:country":"US",
    "sg:address":"737 Co Rd 448",
    "sg:city":"Elba",
    "sg:classifiers":[
        {
            "category":"Farming",
            "subcategory":"Poultry Farm",
            "type":"Manufacturing & Wholesale Goods"
        }
    ],
    "sg:phone":"+1 334 898 2974",
    "sg:postcode":"36323",
    "sg:province":"AL",
    "wof:name":"Davis Poultry Farm",
    "wof:placetype":"venue"
},
  "geometry": {"coordinates":[-86.055559,31.299878],"type":"Point"}
}