{
  "type": "Feature",
  "properties": {
    "iso:country":"US",
    "sg:address":"116 Spring Pl",
    "sg:city":"Alabaster",
    "sg:classifiers":[
        {
            "category":"Shopping",
            "subcategory":"Computers & Home Electronics",
            "type":"Retail Goods"
        }
    ],
    "sg:phone":"+1 205 620 1935",
    "sg:postcode":"35007",
    "sg:province":"AL",
    "wof:name":"Alabama Computers & Commu",
    "wof:placetype":"venue"
},
  "geometry": {"coordinates":[-86.819692,33.266557],"type":"Point"}
}