{
  "type": "Feature",
  "properties": {
    "addr:full":"521 Oliver Rd Montgomery AL 36117",
    "addr:housenumber":"521",
    "addr:postcode":"36117",
    "addr:street":"Oliver Rd",
    "iso:country":"US",
    "sg:address":"521 Oliver Rd",
    "sg:city":"Montgomery",
    "sg:classifiers":[
        {
            "category":"Wholesale",
            "subcategory":"Stationery",
            "type":"Manufacturing & Wholesale Goods"
        }
    ],
    "sg:phone":"+1 334 271 1413",
    "sg:postcode":"36117",
    "sg:province":"AL",
    "sg:tags":[
        "paper",
        "center"
    ],
    "wof:name":"IKON Office Solutions",
    "wof:placetype":"venue"
},
  "geometry": {"coordinates":[-86.20706800000001,32.396171],"type":"Point"}
}