{
  "type": "Feature",
  "properties": {
    "iso:country":"US",
    "sg:address":"1102 20th St S",
    "sg:city":"Birmingham",
    "sg:classifiers":[
        {
            "category":"Professional",
            "subcategory":"Engineering",
            "type":"Services"
        }
    ],
    "sg:phone":"+1 205 879 4462",
    "sg:postcode":"35205",
    "sg:province":"AL",
    "sg:website":"www.gmcnetwork.com",
    "wof:name":"Goodwyn Mills & Cawood Inc",
    "wof:placetype":"venue"
},
  "geometry": {"coordinates":[-86.796362,33.500574],"type":"Point"}
}