{
  "type": "Feature",
  "properties": {
    "iso:country":"US",
    "sg:address":"310 S 3rd St",
    "sg:city":"Gadsden",
    "sg:classifiers":[
        {
            "category":"Government",
            "subcategory":"Office",
            "type":"Public Place"
        }
    ],
    "sg:phone":"+1 256 546 9262",
    "sg:postcode":"35901",
    "sg:province":"AL",
    "wof:name":"Chapter 13 Trustee",
    "wof:placetype":"venue"
},
  "geometry": {"coordinates":[-86.004271,34.008613],"type":"Point"}
}