{
  "type": "Feature",
  "properties": {
    "addr:full":"10931 Co Rd 50 Clanton AL 35045",
    "addr:housenumber":"10931;50",
    "addr:postcode":"35045",
    "addr:street":"Co Rd",
    "iso:country":"US",
    "sg:address":"10931 Co Rd 50",
    "sg:city":"Clanton",
    "sg:classifiers":[
        {
            "category":"Professional",
            "type":"Services"
        }
    ],
    "sg:phone":"+1 205 646 2125",
    "sg:postcode":"35045",
    "sg:province":"AL",
    "wof:name":"Quote 4u Inc",
    "wof:placetype":"venue"
},
  "geometry": {"coordinates":[-86.69320999999999,32.931786],"type":"Point"}
}