{
  "type": "Feature",
  "properties": {
    "addr:full":"104 Ave B Atmore AL 36502",
    "addr:housenumber":"104",
    "addr:postcode":"36502",
    "addr:street":"Ave B",
    "iso:country":"US",
    "sg:address":"104 Ave B",
    "sg:city":"Atmore",
    "sg:classifiers":[
        {
            "category":"Shopping",
            "subcategory":"Gifts & Souvenirs",
            "type":"Retail Goods"
        }
    ],
    "sg:phone":"+1 251 446 9289",
    "sg:postcode":"36502",
    "sg:province":"AL",
    "wof:name":"Cookie Jar",
    "wof:placetype":"venue"
},
  "geometry": {"coordinates":[-87.493359,31.036662],"type":"Point"}
}