{
  "type": "Feature",
  "properties": {
    "iso:country":"US",
    "sg:address":"6389 Atlanta Hwy",
    "sg:city":"Montgomery",
    "sg:classifiers":[
        {
            "category":"Retail",
            "subcategory":"Laundry & Dry Cleaning",
            "type":"Services"
        }
    ],
    "sg:phone":"+1 334 272 7124",
    "sg:postcode":"36117",
    "sg:province":"AL",
    "sg:tags":[
        "cleaners"
    ],
    "wof:name":"Dixie Service Cleaners",
    "wof:placetype":"venue"
},
  "geometry": {"coordinates":[-86.187256,32.38241],"type":"Point"}
}