{
  "type": "Feature",
  "properties": {
    "iso:country":"US",
    "sg:address":"1813 Hayden Ave",
    "sg:city":"Auburn",
    "sg:classifiers":[
        {
            "category":"Building & Trades",
            "subcategory":"Landscaping Services",
            "type":"Services"
        }
    ],
    "sg:phone":"+1 334 821 0481",
    "sg:postcode":"36830",
    "sg:province":"AL",
    "sg:tags":[
        "landscape"
    ],
    "wof:name":"D&K Landscaping",
    "wof:placetype":"venue"
},
  "geometry": {"coordinates":[-85.439839,32.590812],"type":"Point"}
}