{
  "type": "Feature",
  "properties": {
    "addr:full":"6128 Double Oak Way Birmingham AL 35242",
    "addr:housenumber":"6128",
    "addr:postcode":"35242",
    "addr:street":"Double Oak Way",
    "iso:country":"US",
    "sg:address":"6128 Double Oak Way",
    "sg:city":"Birmingham",
    "sg:classifiers":[
        {
            "category":"Building & Trades",
            "subcategory":"Construction",
            "type":"Services"
        }
    ],
    "sg:phone":"+1 205 980 8363",
    "sg:postcode":"35242",
    "sg:province":"AL",
    "sg:tags":[
        "painter"
    ],
    "wof:name":"Lazenby's Decorative Painting",
    "wof:placetype":"venue"
},
  "geometry": {"coordinates":[-86.633432,33.397573],"type":"Point"}
}