{
  "type": "Feature",
  "properties": {
    "iso:country":"US",
    "sg:address":"258 Creekside Dr",
    "sg:city":"Florence",
    "sg:classifiers":[
        {
            "category":"Professional",
            "type":"Services"
        }
    ],
    "sg:phone":"+1 256 767 9834",
    "sg:postcode":"35630",
    "sg:province":"AL",
    "wof:name":"Adler Tsp LLC",
    "wof:placetype":"venue"
},
  "geometry": {"coordinates":[-87.715279,34.819781],"type":"Point"}
}