{
  "type": "Feature",
  "properties": {
    "addr:full":"324 Azalea Rd Mobile AL 36609",
    "addr:housenumber":"324",
    "addr:postcode":"36609",
    "addr:street":"Azalea Rd",
    "iso:country":"US",
    "sg:address":"324 Azalea Rd",
    "sg:city":"Mobile",
    "sg:classifiers":[
        {
            "category":"Banks & Credit Unions",
            "subcategory":"Bank",
            "type":"Services"
        }
    ],
    "sg:phone":"+1 251 340 0355",
    "sg:postcode":"36609",
    "sg:province":"AL",
    "sg:tags":[
        "cashing",
        "check"
    ],
    "wof:name":"Check Cashing Ctr",
    "wof:placetype":"venue"
},
  "geometry": {"coordinates":[-88.14863800000001,30.672484],"type":"Point"}
}