{
  "type": "Feature",
  "properties": {
    "addr:full":"8186 Castlehill Rd Birmingham AL 35242",
    "addr:housenumber":"8186",
    "addr:postcode":"35242",
    "addr:street":"Castlehill Rd",
    "iso:country":"US",
    "sg:address":"8186 Castlehill Rd",
    "sg:city":"Birmingham",
    "sg:classifiers":[
        {
            "category":"Education",
            "subcategory":"Vocational School",
            "type":"Public Place"
        }
    ],
    "sg:phone":"+1 205 307 8889",
    "sg:postcode":"35242",
    "sg:province":"AL",
    "sg:tags":[
        "consultant",
        "computer",
        "software"
    ],
    "wof:name":"Openingargument",
    "wof:placetype":"venue"
},
  "geometry": {"coordinates":[-86.642883,33.437984],"type":"Point"}
}