{
  "type": "Feature",
  "properties": {
    "iso:country":"US",
    "sg:address":"5386 Connie Cir",
    "sg:city":"Montgomery",
    "sg:classifiers":[
        {
            "category":"Building & Trades",
            "subcategory":"Construction",
            "type":"Services"
        }
    ],
    "sg:phone":"+1 334 280 0098",
    "sg:postcode":"36108",
    "sg:province":"AL",
    "sg:tags":[
        "house",
        "improvement",
        "home"
    ],
    "wof:name":"Jackson Construction Company",
    "wof:placetype":"venue"
},
  "geometry": {"coordinates":[-86.343809,32.299149],"type":"Point"}
}