{
  "type": "Feature",
  "properties": {
    "iso:country":"US",
    "sg:address":"1088 9th Ave SW",
    "sg:city":"Bessemer",
    "sg:classifiers":[
        {
            "category":"Health Services",
            "subcategory":"Clinic",
            "type":"Services"
        }
    ],
    "sg:phone":"+1 205 428 6322",
    "sg:postcode":"35022",
    "sg:province":"AL",
    "sg:tags":[
        "home",
        "care"
    ],
    "wof:name":"Able Home Health",
    "wof:placetype":"venue"
},
  "geometry": {"coordinates":[-86.99504,33.369388],"type":"Point"}
}