{
  "type": "Feature",
  "properties": {
    "iso:country":"US",
    "sg:address":"2315 Costarides St",
    "sg:city":"Mobile",
    "sg:classifiers":[
        {
            "category":"Social Services",
            "subcategory":"Adult Care",
            "type":"Services"
        }
    ],
    "sg:phone":"+1 251 574 5245",
    "sg:postcode":"36617",
    "sg:province":"AL",
    "sg:tags":[
        "residential"
    ],
    "wof:name":"Brown  Judge George Office",
    "wof:placetype":"venue"
},
  "geometry": {"coordinates":[-88.09337499999999,30.700034],"type":"Point"}
}