{
  "type": "Feature",
  "properties": {
    "iso:country":"US",
    "sg:address":"915 Co Rd 55",
    "sg:city":"Clanton",
    "sg:classifiers":[
        {
            "category":"Wholesale",
            "subcategory":"Home Furnishings",
            "type":"Manufacturing & Wholesale Goods"
        }
    ],
    "sg:phone":"+1 205 755 7558",
    "sg:postcode":"35046",
    "sg:province":"AL",
    "sg:tags":[
        "frame",
        "matting",
        "supply"
    ],
    "wof:name":"Dixie Matting & Graphics",
    "wof:placetype":"venue"
},
  "geometry": {"coordinates":[-86.60238,32.918775],"type":"Point"}
}