{
  "type": "Feature",
  "properties": {
    "addr:full":"160 Village Springs Rd Springville AL 35146",
    "addr:housenumber":"160",
    "addr:postcode":"35146",
    "addr:street":"Village Springs Rd",
    "iso:country":"US",
    "sg:address":"160 Village Springs Rd",
    "sg:city":"Springville",
    "sg:classifiers":[
        {
            "category":"Restaurant",
            "type":"Food & Drink"
        }
    ],
    "sg:menulink":"http://www.allmenus.com/al/springville/120889-subway/menu/",
    "sg:phone":"+1 205 467 6634",
    "sg:postcode":"35146",
    "sg:province":"AL",
    "sg:tags":[
        "american",
        "sandwich"
    ],
    "wof:name":"Subway",
    "wof:placetype":"venue"
},
  "geometry": {"coordinates":[-86.48505,33.77443],"type":"Point"}
}