{
  "type": "Feature",
  "properties": {
    "iso:country":"US",
    "sg:address":"2512 Aspen Cove Dr",
    "sg:city":"Birmingham",
    "sg:phone":"+1 205 969 1918",
    "sg:postcode":"35243",
    "sg:province":"AL",
    "sg:tags":[
        "product",
        "petroleum"
    ],
    "wof:name":"Shell",
    "wof:placetype":"venue"
},
  "geometry": {"coordinates":[-86.764128,33.426414],"type":"Point"}
}