{
  "type": "Feature",
  "properties": {
    "addr:full":"313 1st Ave E Oneonta AL 35121",
    "addr:housenumber":"313",
    "addr:postcode":"35121",
    "addr:street":"1St Ave E",
    "iso:country":"US",
    "sg:address":"313 1st Ave E",
    "sg:city":"Oneonta",
    "sg:classifiers":[
        {
            "category":"Shopping",
            "subcategory":"Clothing, Apparel, & Fashions",
            "type":"Retail Goods"
        }
    ],
    "sg:phone":"+1 205 625 3459",
    "sg:postcode":"35121",
    "sg:province":"AL",
    "sg:tags":[
        "g",
        "accessory"
    ],
    "wof:name":"Darlene's",
    "wof:placetype":"venue"
},
  "geometry": {"coordinates":[-86.47353200000001,33.94641],"type":"Point"}
}