{
  "type": "Feature",
  "properties": {
    "iso:country":"US",
    "sg:address":"5015 Linwood Dr",
    "sg:city":"Birmingham",
    "sg:classifiers":[
        {
            "category":"Education",
            "subcategory":"Special Training",
            "type":"Public Place"
        }
    ],
    "sg:phone":"+1 205 991 5539",
    "sg:postcode":"35244",
    "sg:province":"AL",
    "wof:name":"Instrument Society of AME",
    "wof:placetype":"venue"
},
  "geometry": {"coordinates":[-86.736003,33.386907],"type":"Point"}
}