{
  "type": "Feature",
  "properties": {
    "iso:country":"US",
    "sg:address":"3158 Louisville St",
    "sg:city":"Clio",
    "sg:classifiers":[
        {
            "category":"Professional",
            "type":"Services"
        }
    ],
    "sg:phone":"+1 334 397 3427",
    "sg:postcode":"36017",
    "sg:province":"AL",
    "wof:name":"Joanna Valencia",
    "wof:placetype":"venue"
},
  "geometry": {"coordinates":[-85.605734,31.715847],"type":"Point"}
}