{
  "type": "Feature",
  "properties": {
    "iso:country":"US",
    "sg:address":"341 S Chestnut St",
    "sg:city":"Prattville",
    "sg:classifiers":[
        {
            "category":"Professional",
            "subcategory":"Lawyer & Legal Services",
            "type":"Services"
        }
    ],
    "sg:phone":"+1 334 365 2686",
    "sg:postcode":"36067",
    "sg:province":"AL",
    "wof:name":"Robert O Burton Attorney",
    "wof:placetype":"venue"
},
  "geometry": {"coordinates":[-86.472724,32.459489],"type":"Point"}
}