{
  "type": "Feature",
  "properties": {
    "iso:country":"US",
    "sg:address":"3875 Chapel Ln S",
    "sg:city":"Birmingham",
    "sg:classifiers":[
        {
            "category":"Home & Garden",
            "subcategory":"Home Furnishings",
            "type":"Retail Goods"
        },
        {
            "category":"Home & Garden",
            "subcategory":"Furniture",
            "type":"Retail Goods"
        }
    ],
    "sg:phone":"+1 205 985 1566",
    "sg:postcode":"35244",
    "sg:province":"AL",
    "sg:tags":[
        "furniture-children's",
        "store"
    ],
    "sg:website":"http://www.rooms2go.com",
    "wof:name":"Rooms To Go",
    "wof:placetype":"venue"
},
  "geometry": {"coordinates":[-86.815003,33.377072],"type":"Point"}
}