{
  "type": "Feature",
  "properties": {
    "addr:full":"300 Lincoln St Gadsden AL 35904",
    "addr:housenumber":"300",
    "addr:postcode":"35904",
    "addr:street":"Lincoln St",
    "iso:country":"US",
    "sg:address":"300 Lincoln St",
    "sg:city":"Gadsden",
    "sg:classifiers":[
        {
            "category":"Retail",
            "subcategory":"Auto Repair",
            "type":"Services"
        }
    ],
    "sg:phone":"+1 256 546 2568",
    "sg:postcode":"35904",
    "sg:province":"AL",
    "sg:tags":[
        "repairing",
        "automotive",
        "automobile",
        "general"
    ],
    "wof:name":"Griff's Garage",
    "wof:placetype":"venue"
},
  "geometry": {"coordinates":[-86.05811199999999,34.014404],"type":"Point"}
}