{
  "type": "Feature",
  "properties": {
    "addr:full":"8072 Eastaboga Rd Eastaboga AL 36260",
    "addr:housenumber":"8072",
    "addr:postcode":"36260",
    "addr:street":"Eastaboga Rd",
    "iso:country":"US",
    "sg:address":"8072 Eastaboga Rd",
    "sg:city":"Eastaboga",
    "sg:classifiers":[
        {
            "category":"Building & Trades",
            "subcategory":"Plumbing",
            "type":"Services"
        }
    ],
    "sg:phone":"+1 256 831 6029",
    "sg:postcode":"36260",
    "sg:province":"AL",
    "sg:tags":[
        "plumbing",
        "contractor"
    ],
    "wof:name":"Dulaney Plumbing & Heating Co",
    "wof:placetype":"venue"
},
  "geometry": {"coordinates":[-86.039249,33.564583],"type":"Point"}
}