{
  "type": "Feature",
  "properties": {
    "addr:full":"3544 US Hwy 431 Phenix City AL 36867",
    "addr:housenumber":"3544",
    "addr:postcode":"36867",
    "addr:street":"Us Hwy 431 Phenix City Al",
    "iso:country":"US",
    "sg:address":"3544 US Hwy 431",
    "sg:city":"Phenix City",
    "sg:classifiers":[
        {
            "category":"Insurance",
            "subcategory":"Insurance Agent",
            "type":"Services"
        }
    ],
    "sg:phone":"+1 334 297 2902",
    "sg:postcode":"36867",
    "sg:province":"AL",
    "wof:name":"Alfa Insurance Corp",
    "wof:placetype":"venue"
},
  "geometry": {"coordinates":[-85.049525,32.503145],"type":"Point"}
}