{
  "type": "Feature",
  "properties": {
    "iso:country":"US",
    "sg:address":"5000 US Hwy 431",
    "sg:city":"Albertville",
    "sg:classifiers":[
        {
            "category":"Professional",
            "subcategory":"Employment Agencies",
            "type":"Services"
        }
    ],
    "sg:phone":"+1 256 894 6363",
    "sg:postcode":"35950",
    "sg:province":"AL",
    "sg:tags":[
        "opportunity"
    ],
    "wof:name":"Team Employment Services LLC",
    "wof:placetype":"venue"
},
  "geometry": {"coordinates":[-86.18166100000001,34.254146],"type":"Point"}
}