{
  "type": "Feature",
  "properties": {
    "addr:full":"460 E Main St Dothan AL 36301",
    "addr:housenumber":"460",
    "addr:postcode":"36301",
    "addr:street":"E Main St",
    "iso:country":"US",
    "sg:address":"460 E Main St",
    "sg:city":"Dothan",
    "sg:classifiers":[
        {
            "category":"Banks & Credit Unions",
            "subcategory":"Bank",
            "type":"Services"
        }
    ],
    "sg:phone":"+1 334 793 7777",
    "sg:postcode":"36301",
    "sg:province":"AL",
    "sg:tags":[
        "loan"
    ],
    "wof:name":"Small Loans Inc",
    "wof:placetype":"venue"
},
  "geometry": {"coordinates":[-85.386822,31.222962],"type":"Point"}
}