{
  "type": "Feature",
  "properties": {
    "iso:country":"US",
    "sg:address":"300 Corporate Pkwy",
    "sg:city":"Birmingham",
    "sg:classifiers":[
        {
            "category":"Restaurant",
            "type":"Food & Drink"
        }
    ],
    "sg:phone":"+1 205 972 0144",
    "sg:postcode":"35242",
    "sg:province":"AL",
    "sg:tags":[
        "eating"
    ],
    "wof:name":"Popeyes Chicken & Biscuits",
    "wof:placetype":"venue"
},
  "geometry": {"coordinates":[-86.68489700000001,33.414955],"type":"Point"}
}