{
  "type": "Feature",
  "properties": {
    "addr:full":"333 N Gould Ave Mobile AL 36612",
    "addr:housenumber":"333",
    "addr:postcode":"36612",
    "addr:street":"N Gould Ave",
    "iso:country":"US",
    "sg:address":"333 N Gould Ave",
    "sg:city":"Mobile",
    "sg:classifiers":[
        {
            "category":"Food & Beverages",
            "subcategory":"Groceries & Convenience Stores",
            "type":"Retail Goods"
        }
    ],
    "sg:phone":"+1 334 283 6982",
    "sg:postcode":"36612",
    "sg:province":"AL",
    "wof:name":"S & H Grocery",
    "wof:placetype":"venue"
},
  "geometry": {"coordinates":[-88.10538,30.761894],"type":"Point"}
}