{
  "type": "Feature",
  "properties": {
    "iso:country":"US",
    "sg:address":"1910 Ross Clark Cir",
    "sg:city":"Dothan",
    "sg:classifiers":[
        {
            "category":"Banks & Credit Unions",
            "subcategory":"Investment Brokerage",
            "type":"Services"
        }
    ],
    "sg:phone":"+1 334 673 8850",
    "sg:postcode":"36301",
    "sg:province":"AL",
    "wof:name":"Accent Real Est & Investment",
    "wof:placetype":"venue"
},
  "geometry": {"coordinates":[-85.385445,31.191742],"type":"Point"}
}