{
  "type": "Feature",
  "properties": {
    "addr:full":"8774 Tanner Williams Rd Mobile AL 36608",
    "addr:housenumber":"8774",
    "addr:postcode":"36608",
    "addr:street":"Tanner Williams Rd",
    "iso:country":"US",
    "sg:address":"8774 Tanner Williams Rd",
    "sg:city":"Mobile",
    "sg:classifiers":[
        {
            "category":"Food & Beverages",
            "subcategory":"Groceries & Convenience Stores",
            "type":"Retail Goods"
        }
    ],
    "sg:phone":"+1 251 633 8390",
    "sg:postcode":"36608",
    "sg:province":"AL",
    "wof:name":"M & D Quickstop",
    "wof:placetype":"venue"
},
  "geometry": {"coordinates":[-88.24975499999999,30.705816],"type":"Point"}
}