{
  "type": "Feature",
  "properties": {
    "addr:full":"1300 SW 8th St Sheffield AL 35660",
    "addr:housenumber":"1300",
    "addr:postcode":"35660",
    "addr:street":"Sw 8Th St",
    "iso:country":"US",
    "sg:address":"1300 SW 8th St",
    "sg:city":"Sheffield",
    "sg:classifiers":[
        {
            "category":"Social Services",
            "type":"Services"
        }
    ],
    "sg:phone":"+1 256 314 0995",
    "sg:postcode":"35660",
    "sg:province":"AL",
    "sg:tags":[
        "youth",
        "organization",
        "center"
    ],
    "wof:name":"Colbert County Youth Center",
    "wof:placetype":"venue"
},
  "geometry": {"coordinates":[-87.70886900000001,34.746814],"type":"Point"}
}