{
  "type": "Feature",
  "properties": {
    "iso:country":"US",
    "sg:address":"4314 Halls Mill Rd",
    "sg:city":"Mobile",
    "sg:classifiers":[
        {
            "category":"Professional",
            "subcategory":"Business Services",
            "type":"Services"
        }
    ],
    "sg:phone":"+1 251 666 7600",
    "sg:postcode":"36693",
    "sg:province":"AL",
    "sg:tags":[
        "mfg",
        "specialty",
        "typesetting"
    ],
    "wof:name":"Sign Shop",
    "wof:placetype":"venue"
},
  "geometry": {"coordinates":[-88.139432,30.619982],"type":"Point"}
}