{
  "type": "Feature",
  "properties": {
    "iso:country":"US",
    "sg:address":"111 Everett Cir",
    "sg:city":"Silas",
    "sg:classifiers":[
        {
            "category":"Organizations",
            "subcategory":"Religious Organization",
            "type":"Services"
        }
    ],
    "sg:phone":"+1 251 542 9600",
    "sg:postcode":"36919",
    "sg:province":"AL",
    "wof:name":"Shiloh Baptist",
    "wof:placetype":"venue"
},
  "geometry": {"coordinates":[-88.330841,31.778967],"type":"Point"}
}