{
  "type": "Feature",
  "properties": {
    "addr:full":"3532 Vann Rd Birmingham AL 35235",
    "addr:housenumber":"3532",
    "addr:postcode":"35235",
    "addr:street":"Vann Rd",
    "iso:country":"US",
    "sg:address":"3532 Vann Rd",
    "sg:city":"Birmingham",
    "sg:classifiers":[
        {
            "category":"Insurance",
            "subcategory":"Insurance Agent",
            "type":"Services"
        }
    ],
    "sg:phone":"+1 205 655 4927",
    "sg:postcode":"35235",
    "sg:province":"AL",
    "wof:name":"Liberty Mutual Insurance",
    "wof:placetype":"venue"
},
  "geometry": {"coordinates":[-86.632615,33.606835],"type":"Point"}
}