{
  "type": "Feature",
  "properties": {
    "iso:country":"US",
    "sg:address":"2212 Reeves St",
    "sg:city":"Dothan",
    "sg:classifiers":[
        {
            "category":"Home & Garden",
            "subcategory":"Mobile Homes",
            "type":"Retail Goods"
        }
    ],
    "sg:phone":"+1 334 712 0292",
    "sg:postcode":"36303",
    "sg:province":"AL",
    "sg:tags":[
        "accessory"
    ],
    "wof:name":"Courtneys Mobile Home Supplies",
    "wof:placetype":"venue"
},
  "geometry": {"coordinates":[-85.387919,31.255684],"type":"Point"}
}