{
  "type": "Feature",
  "properties": {
    "iso:country":"US",
    "sg:address":"5534 28th Ave",
    "sg:city":"Valley",
    "sg:classifiers":[
        {
            "category":"Organizations",
            "subcategory":"Religious Organization",
            "type":"Services"
        }
    ],
    "sg:phone":"+1 334 756 7228",
    "sg:postcode":"36854",
    "sg:province":"AL",
    "wof:name":"West End Baptist Church",
    "wof:placetype":"venue"
},
  "geometry": {"coordinates":[-85.18524600000001,32.820417],"type":"Point"}
}