{
  "type": "Feature",
  "properties": {
    "iso:country":"US",
    "sg:address":"3928 Montclair Rd",
    "sg:city":"Birmingham",
    "sg:classifiers":[
        {
            "category":"Professional",
            "subcategory":"Accounting & Tax Preparation",
            "type":"Services"
        }
    ],
    "sg:phone":"+1 205 879 9148",
    "sg:postcode":"35213",
    "sg:province":"AL",
    "sg:tags":[
        "accountant"
    ],
    "wof:name":"Farr & Farr PC",
    "wof:placetype":"venue"
},
  "geometry": {"coordinates":[-86.759537,33.507287],"type":"Point"}
}