{
  "type": "Feature",
  "properties": {
    "iso:country":"US",
    "sg:address":"116 Shady Ln",
    "sg:city":"Somerville",
    "sg:classifiers":[
        {
            "category":"Building & Trades",
            "subcategory":"Construction",
            "type":"Services"
        }
    ],
    "sg:phone":"+1 256 498 5929",
    "sg:postcode":"35670",
    "sg:province":"AL",
    "sg:tags":[
        "house"
    ],
    "wof:name":"Steve Walters",
    "wof:placetype":"venue"
},
  "geometry": {"coordinates":[-86.617656,34.448037],"type":"Point"}
}