{
  "type": "Feature",
  "properties": {
    "addr:full":"314 Co Rd 107 Montevallo AL 35115",
    "addr:housenumber":"314;107",
    "addr:postcode":"35115",
    "addr:street":"Co Rd",
    "iso:country":"US",
    "sg:address":"314 Co Rd 107",
    "sg:city":"Montevallo",
    "sg:classifiers":[
        {
            "category":"Communications",
            "type":"Services"
        },
        {
            "category":"Organizations",
            "subcategory":"Religious Organization",
            "type":"Services"
        }
    ],
    "sg:phone":"+1 205 665 5345",
    "sg:postcode":"35115",
    "sg:province":"AL",
    "wof:name":"Church Communications Network",
    "wof:placetype":"venue"
},
  "geometry": {"coordinates":[-86.800774,33.153687],"type":"Point"}
}