{
  "type": "Feature",
  "properties": {
    "iso:country":"US",
    "sg:address":"12390 Airport Blvd",
    "sg:city":"Mobile",
    "sg:classifiers":[
        {
            "category":"Building & Trades",
            "subcategory":"Construction",
            "type":"Services"
        }
    ],
    "sg:phone":"+1 251 639 1906",
    "sg:postcode":"36608",
    "sg:province":"AL",
    "sg:tags":[
        "bridge",
        "street",
        "site",
        "highway"
    ],
    "wof:name":"C Thornton Inc",
    "wof:placetype":"venue"
},
  "geometry": {"coordinates":[-88.381131,30.638646],"type":"Point"}
}