{
  "type": "Feature",
  "properties": {
    "iso:country":"US",
    "sg:address":"954 Boles Rd",
    "sg:city":"New Market",
    "sg:classifiers":[
        {
            "category":"Building & Trades",
            "subcategory":"Plumbing",
            "type":"Services"
        }
    ],
    "sg:phone":"+1 256 828 8686",
    "sg:postcode":"35761",
    "sg:province":"AL",
    "sg:tags":[
        "conditioning",
        "air",
        "system",
        "contractor"
    ],
    "wof:name":"Freeman Heating & Air",
    "wof:placetype":"venue"
},
  "geometry": {"coordinates":[-86.50741499999999,34.957775],"type":"Point"}
}