{
  "type": "Feature",
  "properties": {
    "addr:full":"2703 Avalon Ave Muscle Shoals AL 35661",
    "addr:housenumber":"2703",
    "addr:postcode":"35661",
    "addr:street":"Avalon Ave",
    "iso:country":"US",
    "sg:address":"2703 Avalon Ave",
    "sg:city":"Muscle Shoals",
    "sg:classifiers":[
        {
            "category":"Manufacturing",
            "subcategory":"Metals",
            "type":"Manufacturing & Wholesale Goods"
        }
    ],
    "sg:phone":"+1 256 248 8500",
    "sg:postcode":"35661",
    "sg:province":"AL",
    "sg:tags":[
        "stamping"
    ],
    "sg:website":"www.whitesellcorp.com",
    "wof:name":"Whitesell Corp",
    "wof:placetype":"venue"
},
  "geometry": {"coordinates":[-87.639014,34.744458],"type":"Point"}
}