{
  "type": "Feature",
  "properties": {
    "addr:full":"2335 Floyd Bradford Rd Trussville AL 35173",
    "addr:housenumber":"2335",
    "addr:postcode":"35173",
    "addr:street":"Floyd Bradford Rd",
    "iso:country":"US",
    "sg:address":"2335 Floyd Bradford Rd",
    "sg:city":"Trussville",
    "sg:classifiers":[
        {
            "category":"Organizations",
            "subcategory":"Religious Organization",
            "type":"Services"
        }
    ],
    "sg:phone":"+1 205 655 4519",
    "sg:postcode":"35173",
    "sg:province":"AL",
    "wof:name":"Lola City First Baptist Church",
    "wof:placetype":"venue"
},
  "geometry": {"coordinates":[-86.601851,33.571807],"type":"Point"}
}