{
  "type": "Feature",
  "properties": {
    "addr:full":"227 Galloway Rd Brundidge AL 36010",
    "addr:housenumber":"227",
    "addr:postcode":"36010",
    "addr:street":"Galloway Rd",
    "iso:country":"US",
    "sg:address":"227 Galloway Rd",
    "sg:city":"Brundidge",
    "sg:classifiers":[
        {
            "category":"Organizations",
            "subcategory":"Religious Organization",
            "type":"Services"
        }
    ],
    "sg:phone":"+1 334 735 0254",
    "sg:postcode":"36010",
    "sg:province":"AL",
    "sg:tags":[
        "church"
    ],
    "wof:name":"County Line Missionary Bapt",
    "wof:placetype":"venue"
},
  "geometry": {"coordinates":[-85.81915600000001,31.72845],"type":"Point"}
}