{
  "type": "Feature",
  "properties": {
    "iso:country":"US",
    "sg:address":"15460 Sandstone Rd",
    "sg:city":"Northport",
    "sg:classifiers":[
        {
            "category":"Personal",
            "type":"Services"
        }
    ],
    "sg:phone":"+1 205 310 3330",
    "sg:postcode":"35475",
    "sg:province":"AL",
    "sg:tags":[
        "therapist",
        "massage"
    ],
    "wof:name":"Ted Tretter Massage Therapy",
    "wof:placetype":"venue"
},
  "geometry": {"coordinates":[-87.574658,33.359439],"type":"Point"}
}