{
  "type": "Feature",
  "properties": {
    "iso:country":"US",
    "sg:address":"14766 Maryanna Dr",
    "sg:city":"Athens",
    "sg:classifiers":[
        {
            "category":"Building & Trades",
            "subcategory":"Construction",
            "type":"Services"
        }
    ],
    "sg:phone":"+1 256 771 0663",
    "sg:postcode":"35613",
    "sg:province":"AL",
    "sg:tags":[
        "residential"
    ],
    "wof:name":"Alans Superior Buildings",
    "wof:placetype":"venue"
},
  "geometry": {"coordinates":[-86.897739,34.770956],"type":"Point"}
}