{
  "type": "Feature",
  "properties": {
    "addr:full":"18078 US Hwy 29 Brewton AL 36426",
    "addr:postcode":"18078;36426",
    "addr:street":"Us Hwy 29",
    "iso:country":"US",
    "sg:address":"18078 US Hwy 29",
    "sg:city":"Brewton",
    "sg:classifiers":[
        {
            "category":"Organizations",
            "subcategory":"Community Association",
            "type":"Services"
        }
    ],
    "sg:phone":"+1 251 867 8887",
    "sg:postcode":"36426",
    "sg:province":"AL",
    "wof:name":"Holley AF Enterprises",
    "wof:placetype":"venue"
},
  "geometry": {"coordinates":[-86.809116,31.16358],"type":"Point"}
}