{
  "type": "Feature",
  "properties": {
    "iso:country":"US",
    "sg:address":"229 Co Rd 201",
    "sg:city":"Montevallo",
    "sg:classifiers":[
        {
            "category":"Freight",
            "type":"Transportation"
        }
    ],
    "sg:phone":"+1 205 665 7100",
    "sg:postcode":"35115",
    "sg:province":"AL",
    "sg:tags":[
        "operator",
        "trucking"
    ],
    "wof:name":"B & R Mobile Home",
    "wof:placetype":"venue"
},
  "geometry": {"coordinates":[-86.812765,33.068686],"type":"Point"}
}