{
  "type": "Feature",
  "properties": {
    "iso:country":"US",
    "sg:address":"700 S Quintard Ave",
    "sg:city":"Oxford",
    "sg:classifiers":[
        {
            "category":"Personal",
            "subcategory":"Barber",
            "type":"Services"
        }
    ],
    "sg:phone":"+1 256 831 1190",
    "sg:postcode":"36203",
    "sg:province":"AL",
    "wof:name":"Razor's Edge",
    "wof:placetype":"venue"
},
  "geometry": {"coordinates":[-85.82775700000001,33.614453],"type":"Point"}
}