{
  "type": "Feature",
  "properties": {
    "addr:full":"2655 Flatwood Rd Wetumpka AL 36092",
    "addr:housenumber":"2655",
    "addr:postcode":"36092",
    "addr:street":"Flatwood Rd",
    "iso:country":"US",
    "sg:address":"2655 Flatwood Rd",
    "sg:city":"Wetumpka",
    "sg:classifiers":[
        {
            "category":"Building & Trades",
            "subcategory":"Plumbing",
            "type":"Services"
        }
    ],
    "sg:phone":"+1 334 567 8513",
    "sg:postcode":"36092",
    "sg:province":"AL",
    "sg:tags":[
        "plumbing",
        "heating",
        "air"
    ],
    "wof:name":"Terry Mustin Plumbing Company",
    "wof:placetype":"venue"
},
  "geometry": {"coordinates":[-86.281063,32.569613],"type":"Point"}
}