{
  "type": "Feature",
  "properties": {
    "iso:country":"US",
    "sg:address":"800 Conti St",
    "sg:city":"Mobile",
    "sg:classifiers":[
        {
            "category":"Real Estate",
            "subcategory":"Real Estate Operator",
            "type":"Services"
        }
    ],
    "sg:phone":"+1 251 432 2312",
    "sg:postcode":"36602",
    "sg:province":"AL",
    "sg:tags":[
        "apartment"
    ],
    "wof:name":"Baptist Oaks Apartments",
    "wof:placetype":"venue"
},
  "geometry": {"coordinates":[-88.053179,30.687317],"type":"Point"}
}