{
  "type": "Feature",
  "properties": {
    "iso:country":"US",
    "sg:address":"5450 Mount Olive Church Rd",
    "sg:city":"Trussville",
    "sg:classifiers":[
        {
            "category":"Organizations",
            "subcategory":"Religious Organization",
            "type":"Services"
        }
    ],
    "sg:phone":"+1 205 655 0798",
    "sg:postcode":"35173",
    "sg:province":"AL",
    "sg:website":"www.deerfootbaptist.org",
    "wof:name":"Deerfoot Baptist Church",
    "wof:placetype":"venue"
},
  "geometry": {"coordinates":[-86.58412300000001,33.662548],"type":"Point"}
}