{
  "type": "Feature",
  "properties": {
    "iso:country":"US",
    "sg:address":"65 School Ave",
    "sg:city":"Phil Campbell",
    "sg:classifiers":[
        {
            "category":"Education",
            "subcategory":"School",
            "type":"Public Place"
        }
    ],
    "sg:phone":"+1 205 993 5311",
    "sg:postcode":"35581",
    "sg:province":"AL",
    "wof:name":"Phil Campbell High School",
    "wof:placetype":"venue"
},
  "geometry": {"coordinates":[-87.706704,34.350228],"type":"Point"}
}