{
  "type": "Feature",
  "properties": {
    "addr:full":"91 Water Tower Rd Montevallo AL 35115",
    "addr:housenumber":"91",
    "addr:postcode":"35115",
    "addr:street":"Water Tower Rd",
    "iso:country":"US",
    "sg:address":"91 Water Tower Rd",
    "sg:city":"Montevallo",
    "sg:classifiers":[
        {
            "category":"Taxi",
            "type":"Transportation"
        }
    ],
    "sg:phone":"+1 205 665 1062",
    "sg:postcode":"35115",
    "sg:province":"AL",
    "sg:tags":[
        "taxicab"
    ],
    "wof:name":"Hatcher Cab Company",
    "wof:placetype":"venue"
},
  "geometry": {"coordinates":[-87.00130900000001,33.148286],"type":"Point"}
}