{
  "type": "Feature",
  "properties": {
    "iso:country":"US",
    "sg:address":"1201 11th Ave S",
    "sg:city":"Birmingham",
    "sg:classifiers":[
        {
            "category":"Manufacturing",
            "subcategory":"Aerospace",
            "type":"Manufacturing & Wholesale Goods"
        }
    ],
    "sg:phone":"+1 205 640 1177",
    "sg:postcode":"35205",
    "sg:province":"AL",
    "sg:tags":[
        "aircraft"
    ],
    "wof:name":"Aero Vulcan LLC",
    "wof:placetype":"venue"
},
  "geometry": {"coordinates":[-86.80601799999999,33.496001],"type":"Point"}
}