{
  "type": "Feature",
  "properties": {
    "iso:country":"US",
    "sg:address":"2009 9th Ave",
    "sg:city":"Haleyville",
    "sg:classifiers":[
        {
            "category":"Professional",
            "subcategory":"Accounting & Tax Preparation",
            "type":"Services"
        }
    ],
    "sg:phone":"+1 205 486 7568",
    "sg:postcode":"35565",
    "sg:province":"AL",
    "wof:name":"Booahker & Schillaci Company",
    "wof:placetype":"venue"
},
  "geometry": {"coordinates":[-87.623989,34.227958],"type":"Point"}
}