{
  "type": "Feature",
  "properties": {
    "addr:full":"1708 Alm Dr NE Huntsville AL 35811",
    "addr:postcode":"1708;35811",
    "addr:street":"Alm Dr Ne",
    "iso:country":"US",
    "sg:address":"1708 Alm Dr NE",
    "sg:city":"Huntsville",
    "sg:classifiers":[
        {
            "category":"Building & Trades",
            "subcategory":"Construction",
            "type":"Services"
        }
    ],
    "sg:phone":"+1 256 539 8266",
    "sg:postcode":"35811",
    "sg:province":"AL",
    "sg:tags":[
        "house"
    ],
    "wof:name":"Vann Construction Co",
    "wof:placetype":"venue"
},
  "geometry": {"coordinates":[-86.562765,34.75666],"type":"Point"}
}