{
  "type": "Feature",
  "properties": {
    "addr:full":"19934 State Rte 35 Woodville AL 35776",
    "addr:housenumber":"19934",
    "addr:postcode":"35776",
    "addr:street":"State Rte 35",
    "iso:country":"US",
    "sg:address":"19934 State Rte 35",
    "sg:city":"Woodville",
    "sg:classifiers":[
        {
            "category":"Farming",
            "subcategory":"Farm",
            "type":"Manufacturing & Wholesale Goods"
        }
    ],
    "sg:phone":"+1 256 574 1164",
    "sg:postcode":"35776",
    "sg:province":"AL",
    "sg:tags":[
        "crop",
        "general"
    ],
    "wof:name":"Leon McClure",
    "wof:placetype":"venue"
},
  "geometry": {"coordinates":[-86.12652799999999,34.686135],"type":"Point"}
}