{
  "type": "Feature",
  "properties": {
    "iso:country":"US",
    "sg:address":"649 State Rte 36",
    "sg:city":"Hartselle",
    "sg:classifiers":[
        {
            "category":"Restaurant",
            "type":"Food & Drink"
        }
    ],
    "sg:phone":"+1 256 751 0780",
    "sg:postcode":"35640",
    "sg:province":"AL",
    "sg:tags":[
        "eating"
    ],
    "wof:name":"Smoky Carol Cafe",
    "wof:placetype":"venue"
},
  "geometry": {"coordinates":[-86.87541,34.448231],"type":"Point"}
}