{
  "type": "Feature",
  "properties": {
    "iso:country":"US",
    "sg:address":"17664 Hallman Rd",
    "sg:city":"Northport",
    "sg:classifiers":[
        {
            "category":"Railroad",
            "type":"Transportation"
        }
    ],
    "sg:phone":"+1 205 339 8801",
    "sg:postcode":"35475",
    "sg:province":"AL",
    "sg:tags":[
        "rail"
    ],
    "wof:name":"Gary Phillips",
    "wof:placetype":"venue"
},
  "geometry": {"coordinates":[-87.733707,33.415879],"type":"Point"}
}