{
  "type": "Feature",
  "properties": {
    "iso:country":"US",
    "sg:address":"2991 Co Rd 13",
    "sg:city":"Hamilton",
    "sg:classifiers":[
        {
            "category":"Organizations",
            "subcategory":"Religious Organization",
            "type":"Services"
        }
    ],
    "sg:phone":"+1 205 921 0597",
    "sg:postcode":"35570",
    "sg:province":"AL",
    "sg:tags":[
        "church"
    ],
    "wof:name":"Mount Zion 2 CME Church",
    "wof:placetype":"venue"
},
  "geometry": {"coordinates":[-88.148825,34.162687],"type":"Point"}
}