{
  "type": "Feature",
  "properties": {
    "addr:full":"3105 Ross Clark Cir Dothan AL 36303",
    "addr:housenumber":"3105",
    "addr:postcode":"36303",
    "addr:street":"Ross Clark Cir",
    "iso:country":"US",
    "sg:address":"3105 Ross Clark Cir",
    "sg:city":"Dothan",
    "sg:classifiers":[
        {
            "category":"Restaurant",
            "type":"Food & Drink"
        }
    ],
    "sg:phone":"+1 334 792 0416",
    "sg:postcode":"36303",
    "sg:province":"AL",
    "sg:tags":[
        "chinese"
    ],
    "wof:name":"Canton House Chinese Rest LLC",
    "wof:placetype":"venue"
},
  "geometry": {"coordinates":[-85.432204,31.229037],"type":"Point"}
}