{
  "type": "Feature",
  "properties": {
    "addr:full":"133 Rubye Ln Gurley AL 35748",
    "addr:housenumber":"133",
    "addr:postcode":"35748",
    "addr:street":"Rubye Ln Gurley",
    "iso:country":"US",
    "sg:address":"133 Rubye Ln",
    "sg:city":"Gurley",
    "sg:classifiers":[
        {
            "category":"Building & Trades",
            "subcategory":"Construction",
            "type":"Services"
        }
    ],
    "sg:phone":"+1 256 379 3589",
    "sg:postcode":"35748",
    "sg:province":"AL",
    "sg:tags":[
        "hanging",
        "wallpaper",
        "contractor"
    ],
    "wof:name":"Melanie's Wallpapering",
    "wof:placetype":"venue"
},
  "geometry": {"coordinates":[-86.392223,34.839158],"type":"Point"}
}