{
  "type": "Feature",
  "properties": {
    "iso:country":"US",
    "sg:address":"3804 Derby Downs Dr",
    "sg:city":"Tuscaloosa",
    "sg:classifiers":[
        {
            "category":"Organizations",
            "subcategory":"Religious Organization",
            "type":"Services"
        }
    ],
    "sg:phone":"+1 205 799 6285",
    "sg:postcode":"35405",
    "sg:province":"AL",
    "sg:tags":[
        "nazarene",
        "church"
    ],
    "wof:name":"Alabama South District/Nyi",
    "wof:placetype":"venue"
},
  "geometry": {"coordinates":[-87.487712,33.165973],"type":"Point"}
}