{
  "type": "Feature",
  "properties": {
    "iso:country":"US",
    "sg:address":"1041 Sunset Blvd",
    "sg:city":"Birmingham",
    "sg:classifiers":[
        {
            "category":"Manufacturing",
            "subcategory":"Chemicals & Compounds",
            "type":"Manufacturing & Wholesale Goods"
        }
    ],
    "sg:phone":"+1 205 592 9482",
    "sg:postcode":"35213",
    "sg:province":"AL",
    "sg:tags":[
        "agricultural",
        "mfg"
    ],
    "wof:name":"Lornas Therapeutic Massa",
    "wof:placetype":"venue"
},
  "geometry": {"coordinates":[-86.740067,33.520615],"type":"Point"}
}