{
  "type": "Feature",
  "properties": {
    "iso:country":"US",
    "sg:address":"111 N 3 Notch St",
    "sg:city":"Troy",
    "sg:classifiers":[
        {
            "category":"Manufacturing",
            "subcategory":"Printing",
            "type":"Manufacturing & Wholesale Goods"
        }
    ],
    "sg:phone":"+1 334 566 5545",
    "sg:postcode":"36081",
    "sg:province":"AL",
    "sg:tags":[
        "commercial"
    ],
    "wof:name":"Bundles of Joy",
    "wof:placetype":"venue"
},
  "geometry": {"coordinates":[-85.972109,31.808497],"type":"Point"}
}