{
  "type": "Feature",
  "properties": {
    "iso:country":"US",
    "sg:address":"1728 5th Ave N",
    "sg:city":"Birmingham",
    "sg:classifiers":[
        {
            "category":"Professional",
            "subcategory":"Lawyer & Legal Services",
            "type":"Services"
        }
    ],
    "sg:phone":"+1 205 252 3999",
    "sg:postcode":"35203",
    "sg:province":"AL",
    "wof:name":"Wiggins & Davis LLC",
    "wof:placetype":"venue"
},
  "geometry": {"coordinates":[-86.811375,33.516627],"type":"Point"}
}