{
  "type": "Feature",
  "properties": {
    "iso:country":"US",
    "sg:address":"3384 Schillinger Rd S",
    "sg:city":"Mobile",
    "sg:classifiers":[
        {
            "category":"Professional",
            "subcategory":"Business Services",
            "type":"Services"
        }
    ],
    "sg:phone":"+1 251 634 1987",
    "sg:postcode":"36695",
    "sg:province":"AL",
    "wof:name":"G S Robinson",
    "wof:placetype":"venue"
},
  "geometry": {"coordinates":[-88.225022,30.610471],"type":"Point"}
}