{
  "type": "Feature",
  "properties": {
    "iso:country":"US",
    "sg:address":"2256 Rocky Ridge Rd",
    "sg:city":"Birmingham",
    "sg:classifiers":[
        {
            "category":"Professional",
            "subcategory":"Art Services",
            "type":"Services"
        }
    ],
    "sg:phone":"+1 205 823 6700",
    "sg:postcode":"35216",
    "sg:province":"AL",
    "sg:tags":[
        "graphic",
        "designer"
    ],
    "wof:name":"Bruno Designs",
    "wof:placetype":"venue"
},
  "geometry": {"coordinates":[-86.784233,33.403604],"type":"Point"}
}