{
  "type": "Feature",
  "properties": {
    "iso:country":"US",
    "sg:address":"321 Tuthill Ln",
    "sg:city":"Mobile",
    "sg:classifiers":[
        {
            "category":"Health Services",
            "subcategory":"Doctor",
            "type":"Services"
        }
    ],
    "sg:phone":"+1 251 342 1064",
    "sg:postcode":"36608",
    "sg:province":"AL",
    "sg:tags":[
        "medical"
    ],
    "wof:name":"Wm C Gewin Dr",
    "wof:placetype":"venue"
},
  "geometry": {"coordinates":[-88.138541,30.704366],"type":"Point"}
}