{
  "type": "Feature",
  "properties": {
    "iso:country":"US",
    "sg:address":"3105 Mcclellan Blvd",
    "sg:city":"Anniston",
    "sg:classifiers":[
        {
            "category":"Bars & Pubs",
            "type":"Food & Drink"
        }
    ],
    "sg:menulink":"http://www.allmenus.com/al/anniston/254888-dads-bar-b-que/menu/",
    "sg:phone":"+1 256 238 4323",
    "sg:postcode":"36201",
    "sg:province":"AL",
    "wof:name":"Dad's Bar-b-que",
    "wof:placetype":"venue"
},
  "geometry": {"coordinates":[-85.82432799999999,33.682269],"type":"Point"}
}