{
  "type": "Feature",
  "properties": {
    "iso:country":"US",
    "sg:address":"1640 Dauphin Island Pkwy",
    "sg:city":"Mobile",
    "sg:classifiers":[
        {
            "category":"Organizations",
            "subcategory":"Labor Organization",
            "type":"Services"
        }
    ],
    "sg:phone":"+1 251 478 0916",
    "sg:postcode":"36605",
    "sg:province":"AL",
    "wof:name":"Mobile Maritime Port Council",
    "wof:placetype":"venue"
},
  "geometry": {"coordinates":[-88.089065,30.637127],"type":"Point"}
}