{
  "type": "Feature",
  "properties": {
    "iso:country":"US",
    "sg:address":"4401 Northern Blvd",
    "sg:city":"Montgomery",
    "sg:classifiers":[
        {
            "category":"Government",
            "subcategory":"Office",
            "type":"Public Place"
        }
    ],
    "sg:phone":"+1 334 277 5866",
    "sg:postcode":"36110",
    "sg:province":"AL",
    "sg:tags":[
        "state"
    ],
    "wof:name":"State Of Al Surplus Property",
    "wof:placetype":"venue"
},
  "geometry": {"coordinates":[-86.22950899999999,32.42105],"type":"Point"}
}