{
  "type": "Feature",
  "properties": {
    "iso:country":"US",
    "sg:address":"122 Market St",
    "sg:city":"Moundville",
    "sg:classifiers":[
        {
            "category":"Government",
            "subcategory":"Police Station",
            "type":"Public Place"
        }
    ],
    "sg:phone":"+1 205 367 8492",
    "sg:postcode":"35474",
    "sg:province":"AL",
    "sg:tags":[
        "state"
    ],
    "wof:name":"Senator Phil Poole",
    "wof:placetype":"venue"
},
  "geometry": {"coordinates":[-87.626487,32.997559],"type":"Point"}
}