{
  "type": "Feature",
  "properties": {
    "iso:country":"US",
    "sg:address":"8312 Anchor Way",
    "sg:city":"Tuscaloosa",
    "sg:classifiers":[
        {
            "category":"Banks & Credit Unions",
            "subcategory":"Investment Brokerage",
            "type":"Services"
        }
    ],
    "sg:phone":"+1 205 246 0693",
    "sg:postcode":"35406",
    "sg:province":"AL",
    "sg:tags":[
        "consultant",
        "planning",
        "financial"
    ],
    "wof:name":"Firebird Financial LLC",
    "wof:placetype":"venue"
},
  "geometry": {"coordinates":[-87.501943,33.295566],"type":"Point"}
}