{
  "type": "Feature",
  "properties": {
    "addr:full":"201 Oak Hill Rd Jasper AL 35504",
    "addr:housenumber":"201",
    "addr:postcode":"35504",
    "addr:street":"Oak Hill Rd",
    "iso:country":"US",
    "sg:address":"201 Oak Hill Rd",
    "sg:city":"Jasper",
    "sg:classifiers":[
        {
            "category":"Professional",
            "type":"Services"
        }
    ],
    "sg:phone":"+1 205 295 1552",
    "sg:postcode":"35504",
    "sg:province":"AL",
    "sg:tags":[
        "establishment"
    ],
    "wof:name":"Redgewood",
    "wof:placetype":"venue"
},
  "geometry": {"coordinates":[-87.286897,33.854464],"type":"Point"}
}