{
  "type": "Feature",
  "properties": {
    "iso:country":"US",
    "sg:address":"813 S Eufaula Ave",
    "sg:city":"Eufaula",
    "sg:classifiers":[
        {
            "category":"Travel",
            "subcategory":"Hotels & Motels",
            "type":"Entertainment"
        }
    ],
    "sg:phone":"+1 334 687 2457",
    "sg:postcode":"36027",
    "sg:province":"AL",
    "wof:name":"Town Terrace Motel Inc",
    "wof:placetype":"venue"
},
  "geometry": {"coordinates":[-85.150557,31.876769],"type":"Point"}
}