{
  "type": "Feature",
  "properties": {
    "iso:country":"US",
    "sg:address":"112 S Montgomery Ave",
    "sg:city":"Sheffield",
    "sg:classifiers":[
        {
            "category":"Restaurant",
            "type":"Food & Drink"
        }
    ],
    "sg:phone":"+1 256 383 3347",
    "sg:postcode":"35660",
    "sg:province":"AL",
    "sg:tags":[
        "eating"
    ],
    "wof:name":"Pizza Plus II",
    "wof:placetype":"venue"
},
  "geometry": {"coordinates":[-87.69883900000001,34.756566],"type":"Point"}
}