{
  "type": "Feature",
  "properties": {
    "addr:full":"2462 Promwood Loop Montgomery AL 36106",
    "addr:housenumber":"2462",
    "addr:postcode":"36106",
    "addr:street":"Promwood Loop",
    "iso:country":"US",
    "sg:address":"2462 Promwood Loop",
    "sg:city":"Montgomery",
    "sg:classifiers":[
        {
            "category":"Real Estate",
            "subcategory":"Real Estate Operator",
            "type":"Services"
        }
    ],
    "sg:phone":"+1 334 279 9454",
    "sg:postcode":"36106",
    "sg:province":"AL",
    "sg:tags":[
        "apartment"
    ],
    "wof:name":"Colonial Grand",
    "wof:placetype":"venue"
},
  "geometry": {"coordinates":[-86.22658699999999,32.35075],"type":"Point"}
}