{
  "type": "Feature",
  "properties": {
    "iso:country":"US",
    "sg:address":"150 W Park Loop NW",
    "sg:city":"Huntsville",
    "sg:classifiers":[
        {
            "category":"Professional",
            "subcategory":"Computer Services",
            "type":"Services"
        }
    ],
    "sg:phone":"+1 256 430 0390",
    "sg:postcode":"35806",
    "sg:province":"AL",
    "sg:tags":[
        "programing",
        "custom"
    ],
    "wof:name":"DSCI",
    "wof:placetype":"venue"
},
  "geometry": {"coordinates":[-86.689973,34.745528],"type":"Point"}
}