{
  "type": "Feature",
  "properties": {
    "addr:full":"100 N Craft Hwy Chickasaw AL 36611",
    "addr:housenumber":"100",
    "addr:postcode":"36611",
    "addr:street":"N Craft Hwy",
    "iso:country":"US",
    "sg:address":"100 N Craft Hwy",
    "sg:city":"Chickasaw",
    "sg:classifiers":[
        {
            "category":"Restaurant",
            "type":"Food & Drink"
        }
    ],
    "sg:phone":"+1 334 456 7664",
    "sg:postcode":"36611",
    "sg:province":"AL",
    "sg:tags":[
        "fast"
    ],
    "wof:name":"Whataburger",
    "wof:placetype":"venue"
},
  "geometry": {"coordinates":[-88.07388899999999,30.761224],"type":"Point"}
}