{
  "type": "Feature",
  "properties": {
    "iso:country":"US",
    "sg:address":"834 McGougin Rd",
    "sg:city":"Brewton",
    "sg:classifiers":[
        {
            "category":"Building & Trades",
            "subcategory":"Construction",
            "type":"Services"
        }
    ],
    "sg:phone":"+1 251 867 9601",
    "sg:postcode":"36426",
    "sg:province":"AL",
    "sg:tags":[
        "contractor"
    ],
    "wof:name":"James Pugh Construction",
    "wof:placetype":"venue"
},
  "geometry": {"coordinates":[-87.083085,31.180268],"type":"Point"}
}