{
  "type": "Feature",
  "properties": {
    "iso:country":"US",
    "sg:address":"3321 McFarland Blvd",
    "sg:city":"Northport",
    "sg:classifiers":[
        {
            "category":"Autos & Motor Vehicles",
            "subcategory":"Automobile Sales",
            "type":"Retail Goods"
        }
    ],
    "sg:phone":"+1 205 333 8151",
    "sg:postcode":"35476",
    "sg:province":"AL",
    "sg:tags":[
        "car",
        "dealer"
    ],
    "wof:name":"Northport Motor Co",
    "wof:placetype":"venue"
},
  "geometry": {"coordinates":[-87.590409,33.240217],"type":"Point"}
}