{
  "type": "Feature",
  "properties": {
    "iso:country":"US",
    "sg:address":"1905 Florence Blvd",
    "sg:city":"Florence",
    "sg:classifiers":[
        {
            "category":"Insurance",
            "subcategory":"Insurance Agent",
            "type":"Services"
        }
    ],
    "sg:phone":"+1 256 765 0088",
    "sg:postcode":"35630",
    "sg:province":"AL",
    "wof:name":"Farm Bureau Insurance",
    "wof:placetype":"venue"
},
  "geometry": {"coordinates":[-87.649883,34.822709],"type":"Point"}
}