{
  "type": "Feature",
  "properties": {
    "iso:country":"US",
    "sg:address":"211 Co Rd 455",
    "sg:city":"Killen",
    "sg:classifiers":[
        {
            "category":"Building & Trades",
            "subcategory":"Construction",
            "type":"Services"
        }
    ],
    "sg:phone":"+1 256 757 9861",
    "sg:postcode":"35645",
    "sg:province":"AL",
    "sg:tags":[
        "house"
    ],
    "wof:name":"Moores Siding & Gutter Co",
    "wof:placetype":"venue"
},
  "geometry": {"coordinates":[-87.564343,34.8552],"type":"Point"}
}