{
  "type": "Feature",
  "properties": {
    "addr:full":"5330 Co Rd 22 Centre AL 35960",
    "addr:housenumber":"5330;22",
    "addr:postcode":"35960",
    "addr:street":"Co Rd;Centre",
    "iso:country":"US",
    "sg:address":"5330 Co Rd 22",
    "sg:city":"Centre",
    "sg:classifiers":[
        {
            "category":"Food & Beverages",
            "subcategory":"Groceries & Convenience Stores",
            "type":"Retail Goods"
        }
    ],
    "sg:phone":"+1 256 475 3670",
    "sg:postcode":"35960",
    "sg:province":"AL",
    "sg:tags":[
        "sporting"
    ],
    "wof:name":"Cowan Creek Grocery & Marina",
    "wof:placetype":"venue"
},
  "geometry": {"coordinates":[-85.59475999999999,34.143462],"type":"Point"}
}