{
  "type": "Feature",
  "properties": {
    "iso:country":"US",
    "sg:address":"664 Azalea Rd",
    "sg:city":"Mobile",
    "sg:classifiers":[
        {
            "category":"Freight",
            "type":"Transportation"
        }
    ],
    "sg:phone":"+1 251 602 6874",
    "sg:postcode":"36609",
    "sg:province":"AL",
    "sg:tags":[
        "warehouse",
        "mini",
        "commercial",
        "storage"
    ],
    "wof:name":"Public Storage Inc",
    "wof:placetype":"venue"
},
  "geometry": {"coordinates":[-88.141688,30.655896],"type":"Point"}
}