{
  "type": "Feature",
  "properties": {
    "iso:country":"US",
    "sg:address":"29 Dale St",
    "sg:city":"Saraland",
    "sg:classifiers":[
        {
            "category":"Building & Trades",
            "subcategory":"Plumbing",
            "type":"Services"
        }
    ],
    "sg:phone":"+1 251 679 0026",
    "sg:postcode":"36571",
    "sg:province":"AL",
    "sg:tags":[
        "contractor"
    ],
    "wof:name":"Advantage Drain & Plumbing",
    "wof:placetype":"venue"
},
  "geometry": {"coordinates":[-88.061257,30.820575],"type":"Point"}
}