{
  "type": "Feature",
  "properties": {
    "iso:country":"US",
    "sg:address":"7322 Queenstown Ave",
    "sg:city":"Birmingham",
    "sg:classifiers":[
        {
            "category":"Professional",
            "subcategory":"Business Services",
            "type":"Services"
        }
    ],
    "sg:phone":"+1 205 836 6498",
    "sg:postcode":"35206",
    "sg:province":"AL",
    "wof:name":"K & M Enterprises",
    "wof:placetype":"venue"
},
  "geometry": {"coordinates":[-86.716219,33.552604],"type":"Point"}
}