{
  "type": "Feature",
  "properties": {
    "iso:country":"US",
    "sg:address":"10822 State Rte 168",
    "sg:city":"Boaz",
    "sg:classifiers":[
        {
            "category":"Shopping",
            "subcategory":"Clothing, Apparel, & Fashions",
            "type":"Retail Goods"
        }
    ],
    "sg:phone":"+1 256 593 4180",
    "sg:postcode":"35957",
    "sg:province":"AL",
    "sg:tags":[
        "infant",
        "wear"
    ],
    "wof:name":"Bocksteen's Childrens Clothing",
    "wof:placetype":"venue"
},
  "geometry": {"coordinates":[-86.153997,34.198343],"type":"Point"}
}