{
  "type": "Feature",
  "properties": {
    "addr:full":"218 N Carlisle St Albertville AL 35950",
    "addr:housenumber":"218",
    "addr:postcode":"35950",
    "addr:street":"N Carlisle St",
    "iso:country":"US",
    "sg:address":"218 N Carlisle St",
    "sg:city":"Albertville",
    "sg:classifiers":[
        {
            "category":"Personal",
            "subcategory":"Beauty Salon",
            "type":"Services"
        }
    ],
    "sg:phone":"+1 256 891 8111",
    "sg:postcode":"35950",
    "sg:province":"AL",
    "sg:tags":[
        "shop"
    ],
    "wof:name":"Hair Shop",
    "wof:placetype":"venue"
},
  "geometry": {"coordinates":[-86.20652200000001,34.270414],"type":"Point"}
}