{
  "type": "Feature",
  "properties": {
    "iso:country":"US",
    "sg:address":"2707 W Clinton Ave",
    "sg:city":"Huntsville",
    "sg:classifiers":[
        {
            "category":"Professional",
            "subcategory":"Management & Consulting",
            "type":"Services"
        },
        {
            "category":"Professional",
            "subcategory":"Accounting & Tax Preparation",
            "type":"Services"
        }
    ],
    "sg:phone":"+1 256 534 5572",
    "sg:postcode":"35805",
    "sg:province":"AL",
    "sg:tags":[
        "s",
        "return",
        "filing"
    ],
    "wof:name":"Fidelity Tax and Payroll Svcs",
    "wof:placetype":"venue"
},
  "geometry": {"coordinates":[-86.608866,34.719397],"type":"Point"}
}