{
  "type": "Feature",
  "properties": {
    "iso:country":"US",
    "sg:address":"1929 2nd Ave N",
    "sg:city":"Birmingham",
    "sg:classifiers":[
        {
            "category":"Shopping",
            "subcategory":"Jewelry",
            "type":"Retail Goods"
        }
    ],
    "sg:phone":"+1 205 251 1351",
    "sg:postcode":"35203",
    "sg:province":"AL",
    "sg:tags":[
        "jeweler"
    ],
    "wof:name":"Isbell's Jewelry Co",
    "wof:placetype":"venue"
},
  "geometry": {"coordinates":[-86.806635,33.515103],"type":"Point"}
}