{
  "type": "Feature",
  "properties": {
    "iso:country":"US",
    "sg:address":"1231 N Eufaula Ave",
    "sg:city":"Eufaula",
    "sg:classifiers":[
        {
            "category":"Sports & Exercise",
            "subcategory":"Bowling",
            "type":"Entertainment"
        }
    ],
    "sg:phone":"+1 334 616 7447",
    "sg:postcode":"36027",
    "sg:province":"AL",
    "sg:tags":[
        "center"
    ],
    "wof:name":"Lake City Bowling",
    "wof:placetype":"venue"
},
  "geometry": {"coordinates":[-85.147519,31.918484],"type":"Point"}
}