{
  "type": "Feature",
  "properties": {
    "iso:country":"US",
    "sg:address":"12600 Airport Rd",
    "sg:city":"Bay Minette",
    "sg:classifiers":[
        {
            "category":"Autos & Motor Vehicles",
            "subcategory":"Fuel & Gas Station",
            "type":"Retail Goods"
        }
    ],
    "sg:phone":"+1 251 937 6544",
    "sg:postcode":"36507",
    "sg:province":"AL",
    "sg:tags":[
        "station"
    ],
    "wof:name":"Hinote Service Center",
    "wof:placetype":"venue"
},
  "geometry": {"coordinates":[-87.799658,30.877782],"type":"Point"}
}