{
  "type": "Feature",
  "properties": {
    "iso:country":"US",
    "sg:address":"1105 E Park Dr",
    "sg:city":"Birmingham",
    "sg:classifiers":[
        {
            "category":"Health Services",
            "subcategory":"Doctor",
            "type":"Services"
        },
        {
            "category":"Professional",
            "subcategory":"Employment Agencies",
            "type":"Services"
        },
        {
            "category":"Organizations",
            "subcategory":"Professional Association",
            "type":"Services"
        }
    ],
    "sg:phone":"+1 205 833 6003",
    "sg:postcode":"35235",
    "sg:province":"AL",
    "sg:tags":[
        "physician",
        "surgeon",
        "employer"
    ],
    "sg:website":"http://www.noorrahman.com",
    "wof:name":"Da Vita Birmingham East Dlsys",
    "wof:placetype":"venue"
},
  "geometry": {"coordinates":[-86.680909,33.587534],"type":"Point"}
}