{
  "type": "Feature",
  "properties": {
    "iso:country":"US",
    "sg:address":"70311 Main St",
    "sg:city":"Blountsville",
    "sg:classifiers":[
        {
            "category":"Shopping",
            "subcategory":"Used Merchandise",
            "type":"Retail Goods"
        }
    ],
    "sg:phone":"+1 205 429 4975",
    "sg:postcode":"35031",
    "sg:province":"AL",
    "sg:tags":[
        "antique"
    ],
    "wof:name":"Yesterdays",
    "wof:placetype":"venue"
},
  "geometry": {"coordinates":[-86.58089099999999,34.094693],"type":"Point"}
}