{
  "type": "Feature",
  "properties": {
    "addr:full":"7119 6th Ave Altoona AL 35952",
    "addr:housenumber":"7119",
    "addr:postcode":"35952",
    "addr:street":"6Th Ave",
    "iso:country":"US",
    "sg:address":"7119 6th Ave",
    "sg:city":"Altoona",
    "sg:classifiers":[
        {
            "category":"Restaurant",
            "type":"Food & Drink"
        }
    ],
    "sg:phone":"+1 205 589 6769",
    "sg:postcode":"35952",
    "sg:province":"AL",
    "wof:name":"Pioneer Restaurant",
    "wof:placetype":"venue"
},
  "geometry": {"coordinates":[-86.326009,34.024385],"type":"Point"}
}