{
  "type": "Feature",
  "properties": {
    "iso:country":"US",
    "sg:address":"1900 Center Point Pkwy",
    "sg:city":"Birmingham",
    "sg:classifiers":[
        {
            "category":"Professional",
            "subcategory":"Lawyer & Legal Services",
            "type":"Services"
        }
    ],
    "sg:phone":"+1 205 969 0434",
    "sg:postcode":"35215",
    "sg:province":"AL",
    "wof:name":"Roger W Lee",
    "wof:placetype":"venue"
},
  "geometry": {"coordinates":[-86.683897,33.636306],"type":"Point"}
}