{
  "type": "Feature",
  "properties": {
    "iso:country":"US",
    "sg:address":"11200 US Hwy 231",
    "sg:city":"Wetumpka",
    "sg:classifiers":[
        {
            "category":"Building & Trades",
            "subcategory":"Construction",
            "type":"Services"
        }
    ],
    "sg:phone":"+1 334 567 2442",
    "sg:postcode":"36092",
    "sg:province":"AL",
    "sg:tags":[
        "contractor"
    ],
    "wof:name":"Fausnight Iron & Woodworks",
    "wof:placetype":"venue"
},
  "geometry": {"coordinates":[-86.212095,32.590475],"type":"Point"}
}