{
  "type": "Feature",
  "properties": {
    "addr:full":"2023 4th Ave N Birmingham AL 35203",
    "addr:housenumber":"2023",
    "addr:postcode":"35203",
    "addr:street":"4Th Ave N",
    "iso:country":"US",
    "sg:address":"2023 4th Ave N",
    "sg:city":"Birmingham",
    "sg:classifiers":[
        {
            "category":"Social Services",
            "type":"Services"
        }
    ],
    "sg:phone":"+1 205 328 7540",
    "sg:postcode":"35203",
    "sg:province":"AL",
    "sg:tags":[
        "probation"
    ],
    "wof:name":"Alabama Court Services",
    "wof:placetype":"venue"
},
  "geometry": {"coordinates":[-86.806381,33.51765],"type":"Point"}
}