{
  "type": "Feature",
  "properties": {
    "addr:full":"201 N 3rd St Gadsden AL 35901",
    "addr:housenumber":"201",
    "addr:postcode":"35901",
    "addr:street":"N 3Rd St",
    "iso:country":"US",
    "sg:address":"201 N 3rd St",
    "sg:city":"Gadsden",
    "sg:classifiers":[
        {
            "category":"Professional",
            "type":"Services"
        }
    ],
    "sg:phone":"+1 256 546 3331",
    "sg:postcode":"35901",
    "sg:province":"AL",
    "wof:name":"Stover Stewart & Phillips",
    "wof:placetype":"venue"
},
  "geometry": {"coordinates":[-86.001322,34.013322],"type":"Point"}
}