{
  "type": "Feature",
  "properties": {
    "iso:country":"US",
    "sg:address":"106 S Main St",
    "sg:city":"Linden",
    "sg:classifiers":[
        {
            "category":"Personal",
            "subcategory":"Beauty Salon",
            "type":"Services"
        }
    ],
    "sg:phone":"+1 334 295 8390",
    "sg:postcode":"36748",
    "sg:province":"AL",
    "sg:tags":[
        "shop",
        "merchandise"
    ],
    "wof:name":"Merle Norman Cosmetics",
    "wof:placetype":"venue"
},
  "geometry": {"coordinates":[-87.79804,32.306192],"type":"Point"}
}