{
  "type": "Feature",
  "properties": {
    "iso:country":"US",
    "sg:address":"207 Hunter Ridge Ln",
    "sg:city":"Pell City",
    "sg:classifiers":[
        {
            "category":"Shopping",
            "type":"Retail Goods"
        }
    ],
    "sg:phone":"+1 205 338 1563",
    "sg:postcode":"35128",
    "sg:province":"AL",
    "sg:tags":[
        "textile",
        "medical",
        "goo"
    ],
    "wof:name":"Surgical Relief Systems Inc",
    "wof:placetype":"venue"
},
  "geometry": {"coordinates":[-86.209168,33.550809],"type":"Point"}
}