{
  "type": "Feature",
  "properties": {
    "iso:country":"US",
    "sg:address":"5365 1st Ave N",
    "sg:city":"Birmingham",
    "sg:classifiers":[
        {
            "category":"Wholesale",
            "subcategory":"Machinery & Supplies",
            "type":"Manufacturing & Wholesale Goods"
        }
    ],
    "sg:phone":"+1 205 595 2888",
    "sg:postcode":"35212",
    "sg:province":"AL",
    "sg:tags":[
        "beauty"
    ],
    "wof:name":"Beauty Max",
    "wof:placetype":"venue"
},
  "geometry": {"coordinates":[-86.753664,33.539018],"type":"Point"}
}