{
  "type": "Feature",
  "properties": {
    "iso:country":"US",
    "sg:address":"120 15th St E",
    "sg:city":"Tuscaloosa",
    "sg:classifiers":[
        {
            "category":"Real Estate",
            "subcategory":"Real Estate Operator",
            "type":"Services"
        }
    ],
    "sg:phone":"+1 205 752 3232",
    "sg:postcode":"35401",
    "sg:province":"AL",
    "sg:tags":[
        "apartment"
    ],
    "sg:website":"www.universitydowns.com",
    "wof:name":"University Downs Apartments",
    "wof:placetype":"venue"
},
  "geometry": {"coordinates":[-87.534084,33.198146],"type":"Point"}
}