{
  "type": "Feature",
  "properties": {
    "iso:country":"US",
    "sg:address":"420 Inverness Lndg",
    "sg:city":"Birmingham",
    "sg:classifiers":[
        {
            "category":"Health Services",
            "subcategory":"Chiropractor",
            "type":"Services"
        }
    ],
    "sg:phone":"+1 205 991 3511",
    "sg:postcode":"35242",
    "sg:province":"AL",
    "wof:name":"Chiropractic Today",
    "wof:placetype":"venue"
},
  "geometry": {"coordinates":[-86.704793,33.407996],"type":"Point"}
}