{
  "type": "Feature",
  "properties": {
    "addr:full":"105 23rd Ct Phenix City AL 36869",
    "addr:housenumber":"105",
    "addr:postcode":"36869",
    "addr:street":"23Rd Ct Phenix City Al",
    "iso:country":"US",
    "sg:address":"105 23rd Ct",
    "sg:city":"Phenix City",
    "sg:classifiers":[
        {
            "category":"Freight",
            "type":"Transportation"
        }
    ],
    "sg:phone":"+1 334 297 8707",
    "sg:postcode":"36869",
    "sg:province":"AL",
    "sg:tags":[
        "carrier",
        "common"
    ],
    "wof:name":"H & B Trucking Company LLC",
    "wof:placetype":"venue"
},
  "geometry": {"coordinates":[-85.023169,32.449435],"type":"Point"}
}