{
  "type": "Feature",
  "properties": {
    "addr:full":"42700 Amelia Rd Bay Minette AL 36507",
    "addr:housenumber":"42700",
    "addr:postcode":"36507",
    "addr:street":"Amelia Rd",
    "iso:country":"US",
    "sg:address":"42700 Amelia Rd",
    "sg:city":"Bay Minette",
    "sg:classifiers":[
        {
            "category":"Organizations",
            "subcategory":"Religious Organization",
            "type":"Services"
        }
    ],
    "sg:phone":"+1 251 937 6750",
    "sg:postcode":"36507",
    "sg:province":"AL",
    "sg:tags":[
        "church"
    ],
    "wof:name":"Bethlehem Baptist Church",
    "wof:placetype":"venue"
},
  "geometry": {"coordinates":[-87.763541,30.847098],"type":"Point"}
}