{
  "type": "Feature",
  "properties": {
    "addr:full":"1854 Keats Dr NW Huntsville AL 35810",
    "addr:housenumber":"1854",
    "addr:postcode":"35810",
    "addr:street":"Keats Dr Nw",
    "iso:country":"US",
    "sg:address":"1854 Keats Dr NW",
    "sg:city":"Huntsville",
    "sg:classifiers":[
        {
            "category":"Building & Trades",
            "subcategory":"Construction",
            "type":"Services"
        }
    ],
    "sg:phone":"+1 256 859 4509",
    "sg:postcode":"35810",
    "sg:province":"AL",
    "sg:tags":[
        "new",
        "industrial",
        "renovation"
    ],
    "sg:website":"www.rfvandiver.com",
    "wof:name":"R F Vandiver Construction Co",
    "wof:placetype":"venue"
},
  "geometry": {"coordinates":[-86.594917,34.756992],"type":"Point"}
}