{
  "type": "Feature",
  "properties": {
    "iso:country":"US",
    "sg:address":"1111 Pickens St",
    "sg:city":"Moulton",
    "sg:classifiers":[
        {
            "category":"Real Estate",
            "subcategory":"Real Estate Operator",
            "type":"Services"
        }
    ],
    "sg:phone":"+1 256 974 9495",
    "sg:postcode":"35650",
    "sg:province":"AL",
    "sg:tags":[
        "apartment"
    ],
    "wof:name":"Rosewood Manor Apartments",
    "wof:placetype":"venue"
},
  "geometry": {"coordinates":[-87.282279,34.483921],"type":"Point"}
}