{
  "type": "Feature",
  "properties": {
    "iso:country":"US",
    "sg:address":"429 Carlisle Rd",
    "sg:city":"Munford",
    "sg:classifiers":[
        {
            "category":"Freight",
            "type":"Transportation"
        }
    ],
    "sg:phone":"+1 256 362 7729",
    "sg:postcode":"36268",
    "sg:province":"AL",
    "sg:tags":[
        "operator",
        "local",
        "trucking"
    ],
    "wof:name":"Donald E & Debbie M Hudgins",
    "wof:placetype":"venue"
},
  "geometry": {"coordinates":[-86.026995,33.424816],"type":"Point"}
}