{
  "type": "Feature",
  "properties": {
    "addr:full":"3006 27th St N Birmingham AL 35207",
    "addr:housenumber":"3006",
    "addr:postcode":"35207",
    "addr:street":"27Th St N",
    "iso:country":"US",
    "sg:address":"3006 27th St N",
    "sg:city":"Birmingham",
    "sg:classifiers":[
        {
            "category":"Personal",
            "subcategory":"Beauty Salon",
            "type":"Services"
        }
    ],
    "sg:phone":"+1 205 324 5575",
    "sg:postcode":"35207",
    "sg:province":"AL",
    "sg:tags":[
        "hair",
        "stylist"
    ],
    "wof:name":"Dot's Total Hair Care",
    "wof:placetype":"venue"
},
  "geometry": {"coordinates":[-86.816523,33.552278],"type":"Point"}
}