{
  "type": "Feature",
  "properties": {
    "iso:country":"US",
    "sg:address":"815 E Main St",
    "sg:city":"Prattville",
    "sg:classifiers":[
        {
            "category":"Restaurant",
            "type":"Food & Drink"
        }
    ],
    "sg:phone":"+1 334 358 8363",
    "sg:postcode":"36067",
    "sg:province":"AL",
    "wof:name":"Fortune Lucky Chinese Buffet",
    "wof:placetype":"venue"
},
  "geometry": {"coordinates":[-86.451673,32.460486],"type":"Point"}
}