{
  "type": "Feature",
  "properties": {
    "iso:country":"US",
    "sg:address":"915 Plantation Way",
    "sg:city":"Montgomery",
    "sg:classifiers":[
        {
            "category":"Freight",
            "type":"Transportation"
        }
    ],
    "sg:phone":"+1 334 213 0351",
    "sg:postcode":"36117",
    "sg:province":"AL",
    "sg:tags":[
        "commercial",
        "storage"
    ],
    "wof:name":"Plantation Way Storage",
    "wof:placetype":"venue"
},
  "geometry": {"coordinates":[-86.206781,32.401116],"type":"Point"}
}