{
  "type": "Feature",
  "properties": {
    "iso:country":"US",
    "sg:address":"8 Lakewood Pl",
    "sg:city":"Phenix City",
    "sg:classifiers":[
        {
            "category":"Professional",
            "type":"Services"
        }
    ],
    "sg:phone":"+1 334 297 6239",
    "sg:postcode":"36867",
    "sg:province":"AL",
    "wof:name":"Sheila Long",
    "wof:placetype":"venue"
},
  "geometry": {"coordinates":[-85.028267,32.502593],"type":"Point"}
}