{
  "type": "Feature",
  "properties": {
    "addr:full":"192 Jeffrey Ct Ozark AL 36360",
    "addr:housenumber":"192",
    "addr:postcode":"36360",
    "addr:street":"Jeffrey Ct",
    "iso:country":"US",
    "sg:address":"192 Jeffrey Ct",
    "sg:city":"Ozark",
    "sg:classifiers":[
        {
            "category":"Personal",
            "subcategory":"Beauty Salon",
            "type":"Services"
        }
    ],
    "sg:phone":"+1 334 445 4605",
    "sg:postcode":"36360",
    "sg:province":"AL",
    "sg:tags":[
        "shop"
    ],
    "wof:name":"Main Stop Salon",
    "wof:placetype":"venue"
},
  "geometry": {"coordinates":[-85.66496600000001,31.427504],"type":"Point"}
}