{
  "type": "Feature",
  "properties": {
    "iso:country":"US",
    "sg:address":"10960 Quinley Rd",
    "sg:city":"Bay Minette",
    "sg:classifiers":[
        {
            "category":"Food & Beverages",
            "subcategory":"Meat & Fish",
            "type":"Retail Goods"
        }
    ],
    "sg:phone":"+1 251 621 8183",
    "sg:postcode":"36507",
    "sg:province":"AL",
    "sg:tags":[
        "seafood"
    ],
    "wof:name":"R & R Seafood",
    "wof:placetype":"venue"
},
  "geometry": {"coordinates":[-87.83661499999999,30.835126],"type":"Point"}
}