{
  "type": "Feature",
  "properties": {
    "iso:country":"US",
    "sg:address":"350 11th St SW",
    "sg:city":"Arab",
    "sg:classifiers":[
        {
            "category":"Manufacturing",
            "subcategory":"Tools & Machinery",
            "type":"Manufacturing & Wholesale Goods"
        },
        {
            "category":"Manufacturing",
            "subcategory":"Electronics",
            "type":"Manufacturing & Wholesale Goods"
        }
    ],
    "sg:phone":"+1 256 931 8000",
    "sg:postcode":"35016",
    "sg:province":"AL",
    "sg:tags":[
        "boards",
        "mfg",
        "equipment",
        "printed",
        "circuit",
        "electric"
    ],
    "wof:name":"Current Circuits  Inc",
    "wof:placetype":"venue"
},
  "geometry": {"coordinates":[-86.515101,34.313597],"type":"Point"}
}