{
  "type": "Feature",
  "properties": {
    "addr:full":"20870 State Rte 59 Robertsdale AL 36567",
    "addr:housenumber":"20870",
    "addr:postcode":"36567",
    "addr:street":"State Rte 59 Robertsdale",
    "iso:country":"US",
    "sg:address":"20870 State Rte 59",
    "sg:city":"Robertsdale",
    "sg:classifiers":[
        {
            "category":"Retail",
            "subcategory":"Auto Rental",
            "type":"Services"
        }
    ],
    "sg:phone":"+1 251 989 7334",
    "sg:postcode":"36567",
    "sg:province":"AL",
    "sg:tags":[
        "renting",
        "truck",
        "leasing"
    ],
    "wof:name":"U-Haul Co",
    "wof:placetype":"venue"
},
  "geometry": {"coordinates":[-87.70832299999999,30.530411],"type":"Point"}
}