{
  "type": "Feature",
  "properties": {
    "iso:country":"US",
    "sg:address":"1709 E State St",
    "sg:city":"Sheffield",
    "sg:classifiers":[
        {
            "category":"Organizations",
            "subcategory":"Labor Organization",
            "type":"Services"
        }
    ],
    "sg:phone":"+1 256 381 9966",
    "sg:postcode":"35660",
    "sg:province":"AL",
    "wof:name":"Iron Workers 477 Apprentiship",
    "wof:placetype":"venue"
},
  "geometry": {"coordinates":[-87.670361,34.768367],"type":"Point"}
}