{
  "type": "Feature",
  "properties": {
    "addr:full":"2080 Valleydale Rd Birmingham AL 35244",
    "addr:housenumber":"2080",
    "addr:postcode":"35244",
    "addr:street":"Valleydale Rd",
    "iso:country":"US",
    "sg:address":"2080 Valleydale Rd",
    "sg:city":"Birmingham",
    "sg:classifiers":[
        {
            "category":"Personal",
            "subcategory":"Beauty Salon",
            "type":"Services"
        }
    ],
    "sg:phone":"+1 205 985 0579",
    "sg:postcode":"35244",
    "sg:province":"AL",
    "wof:name":"New Image Beauty Salon",
    "wof:placetype":"venue"
},
  "geometry": {"coordinates":[-86.78380799999999,33.351487],"type":"Point"}
}