{
  "type": "Feature",
  "properties": {
    "iso:country":"US",
    "sg:address":"1815 6th Ave SE",
    "sg:city":"Decatur",
    "sg:classifiers":[
        {
            "category":"Professional",
            "subcategory":"Business Services",
            "type":"Services"
        }
    ],
    "sg:phone":"+1 256 341 9964",
    "sg:postcode":"35601",
    "sg:province":"AL",
    "wof:name":"West Enterprise",
    "wof:placetype":"venue"
},
  "geometry": {"coordinates":[-86.974832,34.575238],"type":"Point"}
}