{
  "type": "Feature",
  "properties": {
    "iso:country":"US",
    "sg:address":"4138 Sprague Ave",
    "sg:city":"Anniston",
    "sg:classifiers":[
        {
            "category":"Building & Trades",
            "subcategory":"Construction",
            "type":"Services"
        }
    ],
    "sg:phone":"+1 256 237 0333",
    "sg:postcode":"36206",
    "sg:province":"AL",
    "sg:tags":[
        "general",
        "contractor"
    ],
    "wof:name":"Eugene Turner General Contr",
    "wof:placetype":"venue"
},
  "geometry": {"coordinates":[-85.828566,33.698458],"type":"Point"}
}