{
  "type": "Feature",
  "properties": {
    "iso:country":"US",
    "sg:address":"9211 Cottage Hill Rd",
    "sg:city":"Mobile",
    "sg:classifiers":[
        {
            "category":"Shopping",
            "type":"Retail Goods"
        }
    ],
    "sg:phone":"+1 251 633 6336",
    "sg:postcode":"36695",
    "sg:province":"AL",
    "sg:tags":[
        "shop",
        "a",
        "grooming",
        "pet",
        "boarding"
    ],
    "wof:name":"Animal Barn",
    "wof:placetype":"venue"
},
  "geometry": {"coordinates":[-88.255161,30.639954],"type":"Point"}
}