{
  "type": "Feature",
  "properties": {
    "addr:full":"110 Court St N Talladega AL 35160",
    "addr:housenumber":"110",
    "addr:postcode":"35160",
    "addr:street":"Court St N",
    "iso:country":"US",
    "sg:address":"110 Court St N",
    "sg:city":"Talladega",
    "sg:classifiers":[
        {
            "category":"Personal",
            "subcategory":"Beauty Salon",
            "type":"Services"
        },
        {
            "category":"Personal",
            "subcategory":"Barber",
            "type":"Services"
        }
    ],
    "sg:phone":"+1 256 362 2805",
    "sg:postcode":"35160",
    "sg:province":"AL",
    "sg:tags":[
        "shop"
    ],
    "wof:name":"Margie's Beauty Salon",
    "wof:placetype":"venue"
},
  "geometry": {"coordinates":[-86.103229,33.435089],"type":"Point"}
}