{
  "type": "Feature",
  "properties": {
    "iso:country":"US",
    "sg:address":"9200 Parkway E",
    "sg:city":"Birmingham",
    "sg:classifiers":[
        {
            "category":"Food & Beverages",
            "subcategory":"Groceries & Convenience Stores",
            "type":"Retail Goods"
        }
    ],
    "sg:phone":"+1 205 836 3385",
    "sg:postcode":"35206",
    "sg:province":"AL",
    "wof:name":"Gulf Mart",
    "wof:placetype":"venue"
},
  "geometry": {"coordinates":[-86.70010499999999,33.587405],"type":"Point"}
}