{
  "type": "Feature",
  "properties": {
    "iso:country":"US",
    "sg:address":"35717 US Hwy 231",
    "sg:city":"Ashville",
    "sg:classifiers":[
        {
            "category":"Health Services",
            "subcategory":"Doctor",
            "type":"Services"
        }
    ],
    "sg:phone":"+1 205 594 5176",
    "sg:postcode":"35953",
    "sg:province":"AL",
    "sg:tags":[
        "osteopathic"
    ],
    "wof:name":"Willis D Randall Dr",
    "wof:placetype":"venue"
},
  "geometry": {"coordinates":[-86.27161700000001,33.847126],"type":"Point"}
}