{
  "type": "Feature",
  "properties": {
    "iso:country":"US",
    "sg:address":"21783 State Rte 59",
    "sg:city":"Robertsdale",
    "sg:classifiers":[
        {
            "category":"Health Services",
            "subcategory":"Health Practitioner",
            "type":"Services"
        }
    ],
    "sg:phone":"+1 251 947 3410",
    "sg:postcode":"36567",
    "sg:province":"AL",
    "sg:tags":[
        "therapist",
        "physical"
    ],
    "wof:name":"Encore Rehabilitation",
    "wof:placetype":"venue"
},
  "geometry": {"coordinates":[-87.708423,30.538547],"type":"Point"}
}