{
  "type": "Feature",
  "properties": {
    "iso:country":"US",
    "sg:address":"10015 US Hwy 280",
    "sg:city":"Harpersville",
    "sg:classifiers":[
        {
            "category":"Professional",
            "subcategory":"Business Services",
            "type":"Services"
        }
    ],
    "sg:phone":"+1 205 678 0277",
    "sg:postcode":"35147",
    "sg:province":"AL",
    "wof:name":"Yucatan Trading",
    "wof:placetype":"venue"
},
  "geometry": {"coordinates":[-86.518111,33.355234],"type":"Point"}
}