{
  "type": "Feature",
  "properties": {
    "iso:country":"US",
    "sg:address":"140 N Jackson St",
    "sg:city":"Grove Hill",
    "sg:classifiers":[
        {
            "category":"Food & Beverages",
            "subcategory":"Groceries & Convenience Stores",
            "type":"Retail Goods"
        }
    ],
    "sg:phone":"+1 251 275 8865",
    "sg:postcode":"36451",
    "sg:province":"AL",
    "sg:tags":[
        "station",
        "gasoline"
    ],
    "wof:name":"Econ 7",
    "wof:placetype":"venue"
},
  "geometry": {"coordinates":[-87.776643,31.709854],"type":"Point"}
}