{
  "type": "Feature",
  "properties": {
    "iso:country":"US",
    "sg:address":"13386 US Hwy 231",
    "sg:city":"Union Grove",
    "sg:classifiers":[
        {
            "category":"Building & Trades",
            "subcategory":"Plumbing",
            "type":"Services"
        }
    ],
    "sg:phone":"+1 256 498 5000",
    "sg:postcode":"35175",
    "sg:province":"AL",
    "sg:tags":[
        "contractor"
    ],
    "wof:name":"Morrow Heating & Cooling",
    "wof:placetype":"venue"
},
  "geometry": {"coordinates":[-86.546671,34.435346],"type":"Point"}
}