{
  "type": "Feature",
  "properties": {
    "iso:country":"US",
    "sg:address":"303 Beall Ln",
    "sg:city":"Daphne",
    "sg:classifiers":[
        {
            "category":"Shopping",
            "subcategory":"Beauty & Cosmetics",
            "type":"Retail Goods"
        }
    ],
    "sg:phone":"+1 251 626 1686",
    "sg:postcode":"36526",
    "sg:province":"AL",
    "sg:tags":[
        "merchandise"
    ],
    "wof:name":"Jenny W Mullins",
    "wof:placetype":"venue"
},
  "geometry": {"coordinates":[-87.906801,30.591351],"type":"Point"}
}