{
  "type": "Feature",
  "properties": {
    "iso:country":"US",
    "sg:address":"2605 Dawes Rd",
    "sg:city":"Mobile",
    "sg:classifiers":[
        {
            "category":"Organizations",
            "subcategory":"Religious Organization",
            "type":"Services"
        }
    ],
    "sg:phone":"+1 251 639 1959",
    "sg:postcode":"36695",
    "sg:province":"AL",
    "sg:tags":[
        "church"
    ],
    "sg:website":"www.praisefamily.org",
    "wof:name":"Praise Family Church",
    "wof:placetype":"venue"
},
  "geometry": {"coordinates":[-88.252557,30.625557],"type":"Point"}
}