{
  "type": "Feature",
  "properties": {
    "iso:country":"US",
    "sg:address":"415 Cook Springs Rd",
    "sg:city":"Pell City",
    "sg:classifiers":[
        {
            "category":"Social Services",
            "subcategory":"Job Training",
            "type":"Services"
        }
    ],
    "sg:phone":"+1 205 884 5262",
    "sg:postcode":"35125",
    "sg:province":"AL",
    "sg:tags":[
        "rehabilitation"
    ],
    "wof:name":"Rehab Care Group",
    "wof:placetype":"venue"
},
  "geometry": {"coordinates":[-86.394534,33.59679],"type":"Point"}
}