{
  "type": "Feature",
  "properties": {
    "iso:country":"US",
    "sg:address":"2564 Co Rd 151",
    "sg:city":"Opelika",
    "sg:classifiers":[
        {
            "category":"Manufacturing",
            "subcategory":"Paper Products",
            "type":"Manufacturing & Wholesale Goods"
        }
    ],
    "sg:phone":"+1 334 745 5666",
    "sg:postcode":"36804",
    "sg:province":"AL",
    "sg:tags":[
        "paperboard",
        "mfg"
    ],
    "wof:name":"Mead Corporation",
    "wof:placetype":"venue"
},
  "geometry": {"coordinates":[-85.29362,32.585728],"type":"Point"}
}