{
  "type": "Feature",
  "properties": {
    "addr:full":"518 S Brundidge St Troy AL 36081",
    "addr:housenumber":"518",
    "addr:postcode":"36081",
    "addr:street":"S Brundidge St",
    "iso:country":"US",
    "sg:address":"518 S Brundidge St",
    "sg:city":"Troy",
    "sg:classifiers":[
        {
            "category":"Organizations",
            "subcategory":"Religious Organization",
            "type":"Services"
        }
    ],
    "sg:phone":"+1 334 566 2522",
    "sg:postcode":"36081",
    "sg:province":"AL",
    "sg:tags":[
        "church"
    ],
    "wof:name":"Christian Life Church",
    "wof:placetype":"venue"
},
  "geometry": {"coordinates":[-85.966458,31.80312],"type":"Point"}
}