{
  "type": "Feature",
  "properties": {
    "iso:country":"US",
    "sg:address":"1147 Bankhead Hwy W",
    "sg:city":"Birmingham",
    "sg:classifiers":[
        {
            "category":"Personal",
            "subcategory":"Beauty Salon",
            "type":"Services"
        }
    ],
    "sg:phone":"+1 205 252 3739",
    "sg:postcode":"35204",
    "sg:province":"AL",
    "sg:tags":[
        "shop"
    ],
    "wof:name":"Bernie's Headquarters",
    "wof:placetype":"venue"
},
  "geometry": {"coordinates":[-86.858543,33.533129],"type":"Point"}
}