{
  "type": "Feature",
  "properties": {
    "addr:full":"330 Co Rd 540 Scottsboro AL 35768",
    "addr:housenumber":"330",
    "addr:postcode":"35768",
    "addr:street":"Co Rd 540",
    "iso:country":"US",
    "sg:address":"330 Co Rd 540",
    "sg:city":"Scottsboro",
    "sg:classifiers":[
        {
            "category":"Farming",
            "subcategory":"Livestock Farm",
            "type":"Manufacturing & Wholesale Goods"
        }
    ],
    "sg:phone":"+1 256 574 5146",
    "sg:postcode":"35768",
    "sg:province":"AL",
    "sg:tags":[
        "feedlot",
        "field",
        "crop",
        "beef",
        "cattle"
    ],
    "wof:name":"Claude McGaha",
    "wof:placetype":"venue"
},
  "geometry": {"coordinates":[-86.174843,34.63618],"type":"Point"}
}