{
  "type": "Feature",
  "properties": {
    "addr:full":"1703 Central Pkwy SW Decatur AL 35601",
    "addr:housenumber":"1703",
    "addr:postcode":"35601",
    "addr:street":"Central Pkwy Sw",
    "iso:country":"US",
    "sg:address":"1703 Central Pkwy SW",
    "sg:city":"Decatur",
    "sg:classifiers":[
        {
            "category":"Home & Garden",
            "subcategory":"Carpets & Floor Coverings",
            "type":"Retail Goods"
        }
    ],
    "sg:phone":"+1 256 350 8411",
    "sg:postcode":"35601",
    "sg:province":"AL",
    "wof:name":"Carpet Store",
    "wof:placetype":"venue"
},
  "geometry": {"coordinates":[-86.98559299999999,34.578112],"type":"Point"}
}