{
  "type": "Feature",
  "properties": {
    "addr:full":"3066 Zelda Rd Montgomery AL 36106",
    "addr:housenumber":"3066",
    "addr:postcode":"36106",
    "addr:street":"Zelda Rd",
    "iso:country":"US",
    "sg:address":"3066 Zelda Rd",
    "sg:city":"Montgomery",
    "sg:classifiers":[
        {
            "category":"Professional",
            "subcategory":"Computer Services",
            "type":"Services"
        }
    ],
    "sg:phone":"+1 334 277 3040",
    "sg:postcode":"36106",
    "sg:province":"AL",
    "sg:tags":[
        "information",
        "consulting",
        "technology"
    ],
    "wof:name":"Totus",
    "wof:placetype":"venue"
},
  "geometry": {"coordinates":[-86.26415900000001,32.354308],"type":"Point"}
}