{
  "type": "Feature",
  "properties": {
    "iso:country":"US",
    "sg:address":"1602 Church St SE",
    "sg:city":"Decatur",
    "sg:classifiers":[
        {
            "category":"Social Services",
            "subcategory":"Job Training",
            "type":"Services"
        }
    ],
    "sg:phone":"+1 256 350 1458",
    "sg:postcode":"35601",
    "sg:province":"AL",
    "sg:tags":[
        "retardation",
        "disabled",
        "mental",
        "dev"
    ],
    "wof:name":"Center For Dvlmntly Disabled",
    "wof:placetype":"venue"
},
  "geometry": {"coordinates":[-86.965881,34.601798],"type":"Point"}
}