{
  "type": "Feature",
  "properties": {
    "iso:country":"US",
    "sg:address":"1500 McCain Pkwy",
    "sg:city":"Pelham",
    "sg:classifiers":[
        {
            "category":"Wholesale",
            "subcategory":"Machinery & Supplies",
            "type":"Manufacturing & Wholesale Goods"
        },
        {
            "category":"Professional",
            "subcategory":"Business Services",
            "type":"Services"
        }
    ],
    "sg:phone":"+1 205 621 8860",
    "sg:postcode":"35124",
    "sg:province":"AL",
    "sg:tags":[
        "trailer"
    ],
    "wof:name":"Kelly Trailer Sales & Service",
    "wof:placetype":"venue"
},
  "geometry": {"coordinates":[-86.798018,33.274891],"type":"Point"}
}