{
  "type": "Feature",
  "properties": {
    "iso:country":"US",
    "sg:address":"2311 State Rte 79",
    "sg:city":"Guntersville",
    "sg:classifiers":[
        {
            "category":"Building & Trades",
            "subcategory":"Construction",
            "type":"Services"
        }
    ],
    "sg:phone":"+1 256 582 6896",
    "sg:postcode":"35976",
    "sg:province":"AL",
    "sg:tags":[
        "general",
        "contractor"
    ],
    "wof:name":"Chorba Contracting Corp",
    "wof:placetype":"venue"
},
  "geometry": {"coordinates":[-86.309217,34.340984],"type":"Point"}
}