{
  "type": "Feature",
  "properties": {
    "addr:full":"3758 Dauphin Island Pkwy Mobile AL 36605",
    "addr:housenumber":"3758",
    "addr:postcode":"36605",
    "addr:street":"Dauphin Island Pkwy",
    "iso:country":"US",
    "sg:address":"3758 Dauphin Island Pkwy",
    "sg:city":"Mobile",
    "sg:classifiers":[
        {
            "category":"Restaurant",
            "type":"Food & Drink"
        }
    ],
    "sg:phone":"+1 251 473 1401",
    "sg:postcode":"36605",
    "sg:province":"AL",
    "sg:tags":[
        "barbecue"
    ],
    "wof:name":"Smokey Dembo Smokehouse",
    "wof:placetype":"venue"
},
  "geometry": {"coordinates":[-88.07946699999999,30.59338],"type":"Point"}
}