{
  "type": "Feature",
  "properties": {
    "iso:country":"US",
    "sg:address":"3207 Northgate Dr",
    "sg:city":"Opelika",
    "sg:classifiers":[
        {
            "category":"Shopping",
            "type":"Retail Goods"
        }
    ],
    "sg:phone":"+1 334 749 2483",
    "sg:postcode":"36801",
    "sg:province":"AL",
    "sg:tags":[
        "merchandise"
    ],
    "wof:name":"Engagement Store Inc",
    "wof:placetype":"venue"
},
  "geometry": {"coordinates":[-85.424271,32.666054],"type":"Point"}
}