{
  "type": "Feature",
  "properties": {
    "iso:country":"US",
    "sg:address":"205 Brook Highland Ln",
    "sg:city":"Birmingham",
    "sg:classifiers":[
        {
            "category":"Health Services",
            "subcategory":"Health Practitioner",
            "type":"Services"
        }
    ],
    "sg:phone":"+1 205 402 7393",
    "sg:postcode":"35242",
    "sg:province":"AL",
    "wof:name":"Massage Works",
    "wof:placetype":"venue"
},
  "geometry": {"coordinates":[-86.68132,33.424839],"type":"Point"}
}