{
  "type": "Feature",
  "properties": {
    "iso:country":"US",
    "sg:address":"511 Saraland Cir",
    "sg:city":"Saraland",
    "sg:classifiers":[
        {
            "category":"Building & Trades",
            "subcategory":"Construction",
            "type":"Services"
        }
    ],
    "sg:phone":"+1 251 679 9911",
    "sg:postcode":"36571",
    "sg:province":"AL",
    "sg:tags":[
        "contractor"
    ],
    "wof:name":"Sulco Acoustical Cnstr Co",
    "wof:placetype":"venue"
},
  "geometry": {"coordinates":[-88.073563,30.833508],"type":"Point"}
}