{
  "type": "Feature",
  "properties": {
    "iso:country":"US",
    "sg:address":"13128 US Hwy 411",
    "sg:city":"Centre",
    "sg:classifiers":[
        {
            "category":"Freight",
            "type":"Transportation"
        }
    ],
    "sg:phone":"+1 256 475 6312",
    "sg:postcode":"35960",
    "sg:province":"AL",
    "sg:tags":[
        "operator",
        "trucking"
    ],
    "wof:name":"Kerico Transportation Inc",
    "wof:placetype":"venue"
},
  "geometry": {"coordinates":[-85.478632,34.090574],"type":"Point"}
}