{
  "type": "Feature",
  "properties": {
    "addr:full":"5060 Vaughn Rd Montgomery AL 36116",
    "addr:housenumber":"5060",
    "addr:postcode":"36116",
    "addr:street":"Vaughn Rd",
    "iso:country":"US",
    "sg:address":"5060 Vaughn Rd",
    "sg:city":"Montgomery",
    "sg:classifiers":[
        {
            "category":"Restaurant",
            "type":"Food & Drink"
        }
    ],
    "sg:phone":"+1 334 260 0061",
    "sg:postcode":"36116",
    "sg:province":"AL",
    "sg:tags":[
        "drinking",
        "eating"
    ],
    "wof:name":"Celebrations",
    "wof:placetype":"venue"
},
  "geometry": {"coordinates":[-86.221036,32.343256],"type":"Point"}
}