{
  "type": "Feature",
  "properties": {
    "iso:country":"US",
    "sg:address":"1002 Willow Cove Cir SE",
    "sg:city":"Huntsville",
    "sg:classifiers":[
        {
            "category":"Professional",
            "subcategory":"Business Services",
            "type":"Services"
        }
    ],
    "sg:phone":"+1 256 882 0748",
    "sg:postcode":"35802",
    "sg:province":"AL",
    "sg:tags":[
        "work",
        "background",
        "investigation",
        "contract"
    ],
    "wof:name":"Mahlon H Jones Jr",
    "wof:placetype":"venue"
},
  "geometry": {"coordinates":[-86.54476099999999,34.648648],"type":"Point"}
}