{
  "type": "Feature",
  "properties": {
    "iso:country":"US",
    "sg:address":"17045 Celeste Rd",
    "sg:city":"Citronelle",
    "sg:classifiers":[
        {
            "category":"Building & Trades",
            "subcategory":"Electrical",
            "type":"Services"
        }
    ],
    "sg:phone":"+1 251 866 9278",
    "sg:postcode":"36522",
    "sg:province":"AL",
    "sg:tags":[
        "electrical",
        "contractor"
    ],
    "wof:name":"Helveston Electric Co Inc",
    "wof:placetype":"venue"
},
  "geometry": {"coordinates":[-88.202158,31.047465],"type":"Point"}
}