{
  "type": "Feature",
  "properties": {
    "addr:full":"302 4th Ave NE Decatur AL 35601",
    "addr:housenumber":"302",
    "addr:postcode":"35601",
    "addr:street":"4Th Ave Ne",
    "iso:country":"US",
    "sg:address":"302 4th Ave NE",
    "sg:city":"Decatur",
    "sg:classifiers":[
        {
            "category":"Education",
            "subcategory":"School",
            "type":"Public Place"
        }
    ],
    "sg:phone":"+1 256 552 3000",
    "sg:postcode":"35601",
    "sg:province":"AL",
    "sg:tags":[
        "district"
    ],
    "wof:name":"Decatur City Board Education",
    "wof:placetype":"venue"
},
  "geometry": {"coordinates":[-86.98241400000001,34.606621],"type":"Point"}
}