{
  "type": "Feature",
  "properties": {
    "iso:country":"US",
    "sg:address":"302 4th Ave NE",
    "sg:city":"Decatur",
    "sg:classifiers":[
        {
            "category":"Education",
            "subcategory":"School",
            "type":"Public Place"
        }
    ],
    "sg:phone":"+1 256 552 3000",
    "sg:postcode":"35601",
    "sg:province":"AL",
    "sg:tags":[
        "district"
    ],
    "wof:name":"Decatur City Board Education",
    "wof:placetype":"venue"
},
  "geometry": {"coordinates":[-86.982414,34.606621],"type":"Point"}
}