{
  "type": "Feature",
  "properties": {
    "iso:country":"US",
    "sg:address":"1795 Kowaliga Rd",
    "sg:city":"Eclectic",
    "sg:classifiers":[
        {
            "category":"Home & Garden",
            "subcategory":"Furniture",
            "type":"Retail Goods"
        }
    ],
    "sg:phone":"+1 334 541 3195",
    "sg:postcode":"36024",
    "sg:province":"AL",
    "wof:name":"Johnson Furniture Co",
    "wof:placetype":"venue"
},
  "geometry": {"coordinates":[-86.04987800000001,32.652053],"type":"Point"}
}