{
  "type": "Feature",
  "properties": {
    "iso:country":"US",
    "sg:address":"2550 Alabama Ave",
    "sg:city":"Monroeville",
    "sg:classifiers":[
        {
            "category":"Autos & Motor Vehicles",
            "subcategory":"Fuel & Gas Station",
            "type":"Retail Goods"
        }
    ],
    "sg:phone":"+1 251 575 5823",
    "sg:postcode":"36460",
    "sg:province":"AL",
    "sg:tags":[
        "oil"
    ],
    "wof:name":"Shell Rapid Lube",
    "wof:placetype":"venue"
},
  "geometry": {"coordinates":[-87.332591,31.480656],"type":"Point"}
}