{
  "type": "Feature",
  "properties": {
    "iso:country":"US",
    "sg:address":"508 Cherry St",
    "sg:city":"Gadsden",
    "sg:classifiers":[
        {
            "category":"Building & Trades",
            "subcategory":"Construction",
            "type":"Services"
        }
    ],
    "sg:phone":"+1 256 546 0116",
    "sg:postcode":"35901",
    "sg:province":"AL",
    "sg:tags":[
        "home",
        "improvement"
    ],
    "wof:name":"Quality Home Repair",
    "wof:placetype":"venue"
},
  "geometry": {"coordinates":[-86.00777100000001,34.00582],"type":"Point"}
}