{
  "type": "Feature",
  "properties": {
    "iso:country":"US",
    "sg:address":"764 McNeil Ave",
    "sg:city":"Mobile",
    "sg:classifiers":[
        {
            "category":"Government",
            "subcategory":"Office",
            "type":"Public Place"
        }
    ],
    "sg:phone":"+1 251 343 7475",
    "sg:postcode":"36609",
    "sg:province":"AL",
    "sg:tags":[
        "management"
    ],
    "wof:name":"Structures Unlimited HM Imprv",
    "wof:placetype":"venue"
},
  "geometry": {"coordinates":[-88.184337,30.675917],"type":"Point"}
}