{
  "type": "Feature",
  "properties": {
    "iso:country":"US",
    "sg:address":"5213 Hamilton Blvd",
    "sg:city":"Theodore",
    "sg:classifiers":[
        {
            "category":"Manufacturing",
            "subcategory":"Food",
            "type":"Manufacturing & Wholesale Goods"
        }
    ],
    "sg:phone":"+1 251 653 6450",
    "sg:postcode":"36582",
    "sg:province":"AL",
    "sg:tags":[
        "product",
        "manufacturer"
    ],
    "sg:website":"www.alcopelandinvestments.com",
    "wof:name":"Diversified Foods & Seasoning",
    "wof:placetype":"venue"
},
  "geometry": {"coordinates":[-88.123733,30.552476],"type":"Point"}
}