{
  "type": "Feature",
  "properties": {
    "addr:full":"6915 US Hwy 431 Albertville AL 35950",
    "addr:housenumber":"6915",
    "addr:postcode":"35950",
    "addr:street":"Us Hwy 431",
    "iso:country":"US",
    "sg:address":"6915 US Hwy 431",
    "sg:city":"Albertville",
    "sg:classifiers":[
        {
            "category":"Restaurant",
            "type":"Food & Drink"
        }
    ],
    "sg:phone":"+1 256 891 1551",
    "sg:postcode":"35950",
    "sg:province":"AL",
    "sg:tags":[
        "eating"
    ],
    "wof:name":"Pizza Hut",
    "wof:placetype":"venue"
},
  "geometry": {"coordinates":[-86.200481,34.274143],"type":"Point"}
}