{
  "type": "Feature",
  "properties": {
    "iso:country":"US",
    "sg:address":"3120 Bozeman Dr",
    "sg:city":"Montgomery",
    "sg:classifiers":[
        {
            "category":"Professional",
            "subcategory":"Accounting & Tax Preparation",
            "type":"Services"
        }
    ],
    "sg:phone":"+1 334 262 6862",
    "sg:postcode":"36108",
    "sg:province":"AL",
    "sg:tags":[
        "return"
    ],
    "wof:name":"Nells Tax Services",
    "wof:placetype":"venue"
},
  "geometry": {"coordinates":[-86.342073,32.346348],"type":"Point"}
}