{
  "type": "Feature",
  "properties": {
    "iso:country":"US",
    "sg:address":"1025 Co Rd 511",
    "sg:city":"Valley",
    "sg:classifiers":[
        {
            "category":"Shopping",
            "subcategory":"Jewelry",
            "type":"Retail Goods"
        }
    ],
    "sg:phone":"+1 334 756 7234",
    "sg:postcode":"36854",
    "sg:province":"AL",
    "wof:name":"National Design Products",
    "wof:placetype":"venue"
},
  "geometry": {"coordinates":[-85.20003800000001,32.776542],"type":"Point"}
}