{
  "type": "Feature",
  "properties": {
    "addr:full":"2104 Miller Ferry Way Huntsville AL 35801",
    "addr:housenumber":"2104",
    "addr:postcode":"35801",
    "addr:street":"Miller Ferry Way",
    "iso:country":"US",
    "sg:address":"2104 Miller Ferry Way",
    "sg:city":"Huntsville",
    "sg:classifiers":[
        {
            "category":"Professional",
            "subcategory":"Computer Services",
            "type":"Services"
        }
    ],
    "sg:phone":"+1 256 881 9818",
    "sg:postcode":"35801",
    "sg:province":"AL",
    "sg:website":"www.identid.com",
    "wof:name":"Colmar Enterprises Inc",
    "wof:placetype":"venue"
},
  "geometry": {"coordinates":[-86.59357199999999,34.698036],"type":"Point"}
}