{
  "type": "Feature",
  "properties": {
    "addr:full":"3265 US Hwy 78 Oxford AL 36203",
    "addr:housenumber":"3265",
    "addr:postcode":"36203",
    "addr:street":"Us Hwy 78",
    "iso:country":"US",
    "sg:address":"3265 US Hwy 78",
    "sg:city":"Oxford",
    "sg:classifiers":[
        {
            "category":"Professional",
            "subcategory":"Business Services",
            "type":"Services"
        }
    ],
    "sg:phone":"+1 256 831 0404",
    "sg:postcode":"36203",
    "sg:province":"AL",
    "wof:name":"Iris Enterprises",
    "wof:placetype":"venue"
},
  "geometry": {"coordinates":[-85.899317,33.592733],"type":"Point"}
}