{
  "type": "Feature",
  "properties": {
    "addr:full":"90 Cain Rd Chelsea AL 35043",
    "addr:housenumber":"90",
    "addr:postcode":"35043",
    "addr:street":"Cain Rd",
    "iso:country":"US",
    "sg:address":"90 Cain Rd",
    "sg:city":"Chelsea",
    "sg:classifiers":[
        {
            "category":"Recreation",
            "type":"Entertainment"
        }
    ],
    "sg:phone":"+1 205 678 2292",
    "sg:postcode":"35043",
    "sg:province":"AL",
    "wof:name":"Deer Valley Golf Practice Tee",
    "wof:placetype":"venue"
},
  "geometry": {"coordinates":[-86.71606800000001,33.321664],"type":"Point"}
}