{
  "type": "Feature",
  "properties": {
    "iso:country":"US",
    "sg:address":"718 Sunset Dr",
    "sg:city":"Rainbow City",
    "sg:classifiers":[
        {
            "category":"Building & Trades",
            "subcategory":"Construction",
            "type":"Services"
        }
    ],
    "sg:phone":"+1 256 442 7054",
    "sg:postcode":"35906",
    "sg:province":"AL",
    "sg:tags":[
        "excavation",
        "contractor"
    ],
    "wof:name":"Rainbow City Backhoe Service",
    "wof:placetype":"venue"
},
  "geometry": {"coordinates":[-86.097888,33.895193],"type":"Point"}
}