{
  "type": "Feature",
  "properties": {
    "iso:country":"US",
    "sg:address":"102 Champion Dr",
    "sg:city":"Opp",
    "sg:classifiers":[
        {
            "category":"Home & Garden",
            "subcategory":"Building Materials",
            "type":"Retail Goods"
        }
    ],
    "sg:phone":"+1 334 493 8531",
    "sg:postcode":"36467",
    "sg:province":"AL",
    "wof:name":"Opp Windshield Repair",
    "wof:placetype":"venue"
},
  "geometry": {"coordinates":[-86.233704,31.280248],"type":"Point"}
}