{
  "type": "Feature",
  "properties": {
    "addr:full":"5080 State Hwy 160 Hayden AL 35079",
    "addr:housenumber":"5080",
    "addr:postcode":"35079",
    "addr:street":"State Hwy 160",
    "iso:country":"US",
    "sg:address":"5080 State Hwy 160",
    "sg:city":"Hayden",
    "sg:classifiers":[
        {
            "category":"Organizations",
            "subcategory":"Religious Organization",
            "type":"Services"
        }
    ],
    "sg:phone":"+1 205 647 3357",
    "sg:postcode":"35079",
    "sg:province":"AL",
    "sg:tags":[
        "church"
    ],
    "wof:name":"Hayden Baptist Church",
    "wof:placetype":"venue"
},
  "geometry": {"coordinates":[-86.755701,33.891551],"type":"Point"}
}