{
  "type": "Feature",
  "properties": {
    "iso:country":"US",
    "sg:address":"3412 Westbury Pl",
    "sg:city":"Birmingham",
    "sg:classifiers":[
        {
            "category":"Professional",
            "type":"Services"
        }
    ],
    "sg:phone":"+1 205 967 9367",
    "sg:postcode":"35223",
    "sg:province":"AL",
    "wof:name":"Scott Melissa Creative Svcs",
    "wof:placetype":"venue"
},
  "geometry": {"coordinates":[-86.726438,33.485224],"type":"Point"}
}