{
  "type": "Feature",
  "properties": {
    "iso:country":"US",
    "sg:address":"312 Shoals Ave",
    "sg:city":"Killen",
    "sg:classifiers":[
        {
            "category":"Restaurant",
            "type":"Food & Drink"
        }
    ],
    "sg:phone":"+1 256 810 2763",
    "sg:postcode":"35645",
    "sg:province":"AL",
    "sg:tags":[
        "eating"
    ],
    "wof:name":"Sonic Resturant",
    "wof:placetype":"venue"
},
  "geometry": {"coordinates":[-87.553515,34.866146],"type":"Point"}
}