{
  "type": "Feature",
  "properties": {
    "iso:country":"US",
    "sg:address":"103 Cloverleaf Dr",
    "sg:city":"Athens",
    "sg:classifiers":[
        {
            "category":"Social Services",
            "subcategory":"Child Care",
            "type":"Services"
        },
        {
            "category":"Social Services",
            "type":"Services"
        }
    ],
    "sg:phone":"+1 256 216 8761",
    "sg:postcode":"35611",
    "sg:province":"AL",
    "sg:tags":[
        "center",
        "day"
    ],
    "wof:name":"Christian Care Placement Ctr",
    "wof:placetype":"venue"
},
  "geometry": {"coordinates":[-86.953219,34.78544],"type":"Point"}
}