{
  "type": "Feature",
  "properties": {
    "addr:full":"112 Bel Air Cir Daphne AL 36526",
    "addr:housenumber":"112",
    "addr:postcode":"36526",
    "addr:street":"Bel Air Cir",
    "iso:country":"US",
    "sg:address":"112 Bel Air Cir",
    "sg:city":"Daphne",
    "sg:classifiers":[
        {
            "category":"Retail",
            "subcategory":"Laundry & Dry Cleaning",
            "type":"Services"
        }
    ],
    "sg:phone":"+1 251 621 3966",
    "sg:postcode":"36526",
    "sg:province":"AL",
    "wof:name":"Diaper Land Inc",
    "wof:placetype":"venue"
},
  "geometry": {"coordinates":[-87.89071300000001,30.644901],"type":"Point"}
}