{
  "type": "Feature",
  "properties": {
    "iso:country":"US",
    "sg:address":"3783 Alabama Ave",
    "sg:city":"Monroeville",
    "sg:classifiers":[
        {
            "category":"Professional",
            "type":"Services"
        }
    ],
    "sg:phone":"+1 251 575 9687",
    "sg:postcode":"36460",
    "sg:province":"AL",
    "sg:tags":[
        "establishment"
    ],
    "wof:name":"Mtatm",
    "wof:placetype":"venue"
},
  "geometry": {"coordinates":[-87.333483,31.479671],"type":"Point"}
}