{
  "type": "Feature",
  "properties": {
    "iso:country":"US",
    "sg:address":"1994 Lee St",
    "sg:city":"Rutledge",
    "sg:classifiers":[
        {
            "category":"Building & Trades",
            "subcategory":"Construction",
            "type":"Services"
        }
    ],
    "sg:phone":"+1 334 335 6474",
    "sg:postcode":"36071",
    "sg:province":"AL",
    "sg:tags":[
        "excavation",
        "contractor"
    ],
    "wof:name":"Vickery Construction",
    "wof:placetype":"venue"
},
  "geometry": {"coordinates":[-86.322673,31.727901],"type":"Point"}
}