{
  "type": "Feature",
  "properties": {
    "iso:country":"US",
    "sg:address":"419 Buckeye Ave",
    "sg:city":"Selma",
    "sg:classifiers":[
        {
            "category":"Retail",
            "subcategory":"Auto Repair",
            "type":"Services"
        }
    ],
    "sg:phone":"+1 334 874 7777",
    "sg:postcode":"36701",
    "sg:province":"AL",
    "sg:tags":[
        "automotive"
    ],
    "wof:name":"J WS Automotive Pnt & Bdy Sp",
    "wof:placetype":"venue"
},
  "geometry": {"coordinates":[-87.033831,32.415419],"type":"Point"}
}