{
  "type": "Feature",
  "properties": {
    "iso:country":"US",
    "sg:address":"1727 Forrest Ave",
    "sg:city":"Gadsden",
    "sg:classifiers":[
        {
            "category":"Retail",
            "subcategory":"Auto Repair",
            "type":"Services"
        }
    ],
    "sg:phone":"+1 256 547 1549",
    "sg:postcode":"35901",
    "sg:province":"AL",
    "sg:tags":[
        "automotive",
        "wrecker",
        "general"
    ],
    "wof:name":"Easterwood Wrecker Svc & Gar",
    "wof:placetype":"venue"
},
  "geometry": {"coordinates":[-86.027057,34.019203],"type":"Point"}
}