{
  "type": "Feature",
  "properties": {
    "iso:country":"US",
    "sg:address":"15330 US Hwy 431",
    "sg:city":"Hazel Green",
    "sg:classifiers":[
        {
            "category":"Health Services",
            "subcategory":"Clinic",
            "type":"Services"
        }
    ],
    "sg:phone":"+1 256 828 3321",
    "sg:postcode":"35750",
    "sg:province":"AL",
    "sg:tags":[
        "medical",
        "specialty",
        "outpatient"
    ],
    "wof:name":"Primary Medical Care Clinic",
    "wof:placetype":"venue"
},
  "geometry": {"coordinates":[-86.568322,34.967771],"type":"Point"}
}