{
  "type": "Feature",
  "properties": {
    "iso:country":"US",
    "sg:address":"1505 Wilmer Ave",
    "sg:city":"Anniston",
    "sg:classifiers":[
        {
            "category":"Professional",
            "subcategory":"Employment Agencies",
            "type":"Services"
        }
    ],
    "sg:phone":"+1 256 237 7111",
    "sg:postcode":"36201",
    "sg:province":"AL",
    "sg:tags":[
        "opportunity"
    ],
    "wof:name":"Dynamic Staffing Svc",
    "wof:placetype":"venue"
},
  "geometry": {"coordinates":[-85.828404,33.665014],"type":"Point"}
}