{
  "type": "Feature",
  "properties": {
    "addr:full":"844 S Memorial Dr Prattville AL 36067",
    "addr:housenumber":"844",
    "addr:postcode":"36067",
    "addr:street":"S Memorial Dr",
    "iso:country":"US",
    "sg:address":"844 S Memorial Dr",
    "sg:city":"Prattville",
    "sg:classifiers":[
        {
            "category":"Retail",
            "subcategory":"Auto Repair",
            "type":"Services"
        }
    ],
    "sg:phone":"+1 334 365 2098",
    "sg:postcode":"36067",
    "sg:province":"AL",
    "sg:tags":[
        "repairing",
        "automobile"
    ],
    "wof:name":"Carroll's Radiator & Wrecker",
    "wof:placetype":"venue"
},
  "geometry": {"coordinates":[-86.449308,32.457827],"type":"Point"}
}