{
  "type": "Feature",
  "properties": {
    "addr:full":"3502 Rainbow Dr Rainbow City AL 35906",
    "addr:housenumber":"3502",
    "addr:postcode":"35906",
    "addr:street":"Rainbow Dr",
    "iso:country":"US",
    "sg:address":"3502 Rainbow Dr",
    "sg:city":"Rainbow City",
    "sg:classifiers":[
        {
            "category":"Health Services",
            "subcategory":"Clinic",
            "type":"Services"
        }
    ],
    "sg:phone":"+1 256 442 2779",
    "sg:postcode":"35906",
    "sg:province":"AL",
    "sg:tags":[
        "specialty",
        "outpatient"
    ],
    "wof:name":"HealthSouth",
    "wof:placetype":"venue"
},
  "geometry": {"coordinates":[-86.041887,33.954375],"type":"Point"}
}