{
  "type": "Feature",
  "properties": {
    "addr:full":"3000 Co Rd 200 Florence AL 35633",
    "addr:housenumber":"3000",
    "addr:postcode":"35633",
    "addr:street":"Co Rd 200",
    "iso:country":"US",
    "sg:address":"3000 Co Rd 200",
    "sg:city":"Florence",
    "sg:classifiers":[
        {
            "category":"Education",
            "subcategory":"School",
            "type":"Public Place"
        }
    ],
    "sg:phone":"+1 256 764 2903",
    "sg:postcode":"35633",
    "sg:province":"AL",
    "wof:name":"Central High School",
    "wof:placetype":"venue"
},
  "geometry": {"coordinates":[-87.798081,34.898707],"type":"Point"}
}