{
  "type": "Feature",
  "properties": {
    "iso:country":"US",
    "sg:address":"194 E 1st St",
    "sg:city":"Luverne",
    "sg:classifiers":[
        {
            "category":"Education",
            "subcategory":"School",
            "type":"Public Place"
        }
    ],
    "sg:phone":"+1 334 335 6151",
    "sg:postcode":"36049",
    "sg:province":"AL",
    "wof:name":"Luverne Elementary School",
    "wof:placetype":"venue"
},
  "geometry": {"coordinates":[-86.26177,31.717744],"type":"Point"}
}