{
  "type": "Feature",
  "properties": {
    "addr:full":"215 12th St W Birmingham AL 35208",
    "addr:housenumber":"215",
    "addr:postcode":"35208",
    "addr:street":"12Th St W",
    "iso:country":"US",
    "sg:address":"215 12th St W",
    "sg:city":"Birmingham",
    "sg:classifiers":[
        {
            "category":"Building & Trades",
            "subcategory":"Landscaping Services",
            "type":"Services"
        }
    ],
    "sg:phone":"+1 205 249 0080",
    "sg:postcode":"35208",
    "sg:province":"AL",
    "sg:tags":[
        "landscape"
    ],
    "wof:name":"J Gardens & Maintenance",
    "wof:placetype":"venue"
},
  "geometry": {"coordinates":[-86.856914,33.503943],"type":"Point"}
}