{
  "type": "Feature",
  "properties": {
    "addr:full":"1944 Co Rd 461 Kinston AL 36453",
    "addr:housenumber":"1944;461",
    "addr:postcode":"36453",
    "addr:street":"Co Rd",
    "iso:country":"US",
    "sg:address":"1944 Co Rd 461",
    "sg:city":"Kinston",
    "sg:phone":"+1 334 565 3507",
    "sg:postcode":"36453",
    "sg:province":"AL",
    "sg:tags":[
        "farm",
        "field",
        "crop"
    ],
    "wof:name":"M P Howell",
    "wof:placetype":"venue"
},
  "geometry": {"coordinates":[-86.073928,31.250589],"type":"Point"}
}