{
  "type": "Feature",
  "properties": {
    "iso:country":"US",
    "sg:address":"1517 Shirt Tail Bend Rd",
    "sg:city":"New Hope",
    "sg:classifiers":[
        {
            "category":"Manufacturing",
            "subcategory":"Tools & Machinery",
            "type":"Manufacturing & Wholesale Goods"
        }
    ],
    "sg:phone":"+1 256 723 2665",
    "sg:postcode":"35760",
    "sg:province":"AL",
    "sg:tags":[
        "machine",
        "shop"
    ],
    "wof:name":"B & D Machine Shop",
    "wof:placetype":"venue"
},
  "geometry": {"coordinates":[-86.36309900000001,34.504037],"type":"Point"}
}