{
  "type": "Feature",
  "properties": {
    "iso:country":"US",
    "sg:address":"2901 Cahaba Rd",
    "sg:city":"Birmingham",
    "sg:classifiers":[
        {
            "category":"Shopping",
            "subcategory":"Used Merchandise",
            "type":"Retail Goods"
        },
        {
            "category":"Home & Garden",
            "subcategory":"Furniture",
            "type":"Retail Goods"
        }
    ],
    "sg:phone":"+1 205 879 0529",
    "sg:postcode":"35223",
    "sg:province":"AL",
    "sg:tags":[
        "antique",
        "furnishing"
    ],
    "wof:name":"Iron Art Inc",
    "wof:placetype":"venue"
},
  "geometry": {"coordinates":[-86.771677,33.481493],"type":"Point"}
}