{
  "type": "Feature",
  "properties": {
    "iso:country":"US",
    "sg:address":"3058 Leeman Ferry Rd SW",
    "sg:city":"Huntsville",
    "sg:classifiers":[
        {
            "category":"Professional",
            "subcategory":"Advertising",
            "type":"Services"
        }
    ],
    "sg:phone":"+1 256 650 5200",
    "sg:postcode":"35801",
    "sg:province":"AL",
    "sg:tags":[
        "counselor"
    ],
    "wof:name":"Media Stratagies",
    "wof:placetype":"venue"
},
  "geometry": {"coordinates":[-86.59174299999999,34.701671],"type":"Point"}
}