{
  "type": "Feature",
  "properties": {
    "iso:country":"US",
    "sg:address":"1675 McMillan Ave SW",
    "sg:city":"Birmingham",
    "sg:classifiers":[
        {
            "category":"Health Services",
            "subcategory":"Doctor",
            "type":"Services"
        }
    ],
    "sg:phone":"+1 205 957 0106",
    "sg:postcode":"35211",
    "sg:province":"AL",
    "wof:name":"Dan Miles Dr",
    "wof:placetype":"venue"
},
  "geometry": {"coordinates":[-86.860695,33.484258],"type":"Point"}
}