{
  "type": "Feature",
  "properties": {
    "addr:full":"3250 Airport Blvd Mobile AL 36606",
    "addr:housenumber":"3250",
    "addr:postcode":"36606",
    "addr:street":"Airport Blvd",
    "iso:country":"US",
    "sg:address":"3250 Airport Blvd",
    "sg:city":"Mobile",
    "sg:classifiers":[
        {
            "category":"Real Estate",
            "subcategory":"Real Estate Operator",
            "type":"Services"
        }
    ],
    "sg:phone":"+1 251 471 1945",
    "sg:postcode":"36606",
    "sg:province":"AL",
    "sg:tags":[
        "mall",
        "shopping",
        "center"
    ],
    "wof:name":"Springdale Mall",
    "wof:placetype":"venue"
},
  "geometry": {"coordinates":[-88.120486,30.676193],"type":"Point"}
}