{
  "type": "Feature",
  "properties": {
    "iso:country":"US",
    "sg:address":"8145 Oldfield Rd SW",
    "sg:city":"Huntsville",
    "sg:classifiers":[
        {
            "category":"Shopping",
            "subcategory":"Used Merchandise",
            "type":"Retail Goods"
        }
    ],
    "sg:phone":"+1 256 679 7214",
    "sg:postcode":"35802",
    "sg:province":"AL",
    "sg:tags":[
        "shop",
        "consignment"
    ],
    "wof:name":"Miriam B Frank Retailer",
    "wof:placetype":"venue"
},
  "geometry": {"coordinates":[-86.567842,34.659149],"type":"Point"}
}