{
  "type": "Feature",
  "properties": {
    "iso:country":"US",
    "sg:address":"621 Boll Weevil Cir",
    "sg:city":"Enterprise",
    "sg:classifiers":[
        {
            "category":"Shopping",
            "subcategory":"Clothing, Apparel, & Fashions",
            "type":"Retail Goods"
        }
    ],
    "sg:phone":"+1 334 393 7647",
    "sg:postcode":"36330",
    "sg:province":"AL",
    "wof:name":"Claw Hammer Creations LLC",
    "wof:placetype":"venue"
},
  "geometry": {"coordinates":[-85.864113,31.333332],"type":"Point"}
}