{
  "type": "Feature",
  "properties": {
    "iso:country":"US",
    "sg:address":"151 Tinker Ct",
    "sg:city":"Dothan",
    "sg:classifiers":[
        {
            "category":"Manufacturing",
            "subcategory":"Motor Vehicles & Parts",
            "type":"Manufacturing & Wholesale Goods"
        }
    ],
    "sg:phone":"+1 334 793 6367",
    "sg:postcode":"36303",
    "sg:province":"AL",
    "sg:tags":[
        "muffler",
        "exhaust",
        "system"
    ],
    "wof:name":"Full Line Exhaust",
    "wof:placetype":"venue"
},
  "geometry": {"coordinates":[-85.38301199999999,31.248612],"type":"Point"}
}