{
  "type": "Feature",
  "properties": {
    "iso:country":"US",
    "sg:address":"204 S Commerce St",
    "sg:city":"Geneva",
    "sg:classifiers":[
        {
            "category":"Shopping",
            "subcategory":"Florist",
            "type":"Retail Goods"
        }
    ],
    "sg:phone":"+1 334 684 6557",
    "sg:postcode":"36340",
    "sg:province":"AL",
    "wof:name":"Ceramic Arts & Crafts",
    "wof:placetype":"venue"
},
  "geometry": {"coordinates":[-85.865847,31.037796],"type":"Point"}
}