{
  "type": "Feature",
  "properties": {
    "iso:country":"US",
    "sg:address":"2002 Bogue Dr",
    "sg:city":"Scottsboro",
    "sg:classifiers":[
        {
            "category":"Building & Trades",
            "subcategory":"Construction",
            "type":"Services"
        }
    ],
    "sg:phone":"+1 256 574 4823",
    "sg:postcode":"35769",
    "sg:province":"AL",
    "sg:tags":[
        "marking",
        "maintenance",
        "parking"
    ],
    "wof:name":"Street Dept-Barn",
    "wof:placetype":"venue"
},
  "geometry": {"coordinates":[-85.99613600000001,34.658757],"type":"Point"}
}