{
  "type": "Feature",
  "properties": {
    "addr:full":"315 Franklin St SE Huntsville AL 35801",
    "addr:housenumber":"315",
    "addr:postcode":"35801",
    "addr:street":"Franklin St Se",
    "iso:country":"US",
    "sg:address":"315 Franklin St SE",
    "sg:city":"Huntsville",
    "sg:classifiers":[
        {
            "category":"Professional",
            "subcategory":"Lawyer & Legal Services",
            "type":"Services"
        }
    ],
    "sg:phone":"+1 256 533 3740",
    "sg:postcode":"35801",
    "sg:province":"AL",
    "sg:tags":[
        "attorney"
    ],
    "sg:website":"www.abphlaw.com",
    "wof:name":"Ables Baxter Parker & Hall",
    "wof:placetype":"venue"
},
  "geometry": {"coordinates":[-86.583629,34.729421],"type":"Point"}
}