{
  "type": "Feature",
  "properties": {
    "addr:full":"114 Woods End Rd Huntsville AL 35806",
    "addr:housenumber":"114",
    "addr:postcode":"35806",
    "addr:street":"Woods End Rd",
    "iso:country":"US",
    "sg:address":"114 Woods End Rd",
    "sg:city":"Huntsville",
    "sg:classifiers":[
        {
            "category":"Shopping",
            "subcategory":"Gifts & Souvenirs",
            "type":"Retail Goods"
        }
    ],
    "sg:phone":"+1 256 489 0660",
    "sg:postcode":"35806",
    "sg:province":"AL",
    "wof:name":"Rebeccas Cottage",
    "wof:placetype":"venue"
},
  "geometry": {"coordinates":[-86.683768,34.792985],"type":"Point"}
}