{
  "type": "Feature",
  "properties": {
    "iso:country":"US",
    "sg:address":"139 N Weakley St",
    "sg:city":"Florence",
    "sg:classifiers":[
        {
            "category":"Building & Trades",
            "subcategory":"Construction",
            "type":"Services"
        }
    ],
    "sg:phone":"+1 256 764 9490",
    "sg:postcode":"35630",
    "sg:province":"AL",
    "sg:tags":[
        "contractor"
    ],
    "wof:name":"Envirnmntal Protective Coating",
    "wof:placetype":"venue"
},
  "geometry": {"coordinates":[-87.636969,34.818777],"type":"Point"}
}