{
  "type": "Feature",
  "properties": {
    "addr:full":"319 Gilbert Ferry Rd SW Attalla AL 35954",
    "addr:housenumber":"319",
    "addr:postcode":"35954",
    "addr:street":"Gilbert Ferry Rd Sw",
    "iso:country":"US",
    "sg:address":"319 Gilbert Ferry Rd SW",
    "sg:city":"Attalla",
    "sg:classifiers":[
        {
            "category":"Food & Beverages",
            "subcategory":"Groceries & Convenience Stores",
            "type":"Retail Goods"
        }
    ],
    "sg:phone":"+1 256 538 0114",
    "sg:postcode":"35954",
    "sg:province":"AL",
    "wof:name":"Burtons Store 33",
    "wof:placetype":"venue"
},
  "geometry": {"coordinates":[-86.11642399999999,34.006107],"type":"Point"}
}