{
  "type": "Feature",
  "properties": {
    "iso:country":"US",
    "sg:address":"319 Gilbert Ferry Rd SW",
    "sg:city":"Attalla",
    "sg:classifiers":[
        {
            "category":"Food & Beverages",
            "subcategory":"Groceries & Convenience Stores",
            "type":"Retail Goods"
        }
    ],
    "sg:phone":"+1 256 538 0114",
    "sg:postcode":"35954",
    "sg:province":"AL",
    "wof:name":"Burtons Store 33",
    "wof:placetype":"venue"
},
  "geometry": {"coordinates":[-86.116424,34.006107],"type":"Point"}
}