{
  "type": "Feature",
  "properties": {
    "iso:country":"US",
    "sg:address":"1855 Montgomery Hwy",
    "sg:city":"Birmingham",
    "sg:classifiers":[
        {
            "category":"Shopping",
            "subcategory":"Discount & Variety Stores",
            "type":"Retail Goods"
        }
    ],
    "sg:phone":"+1 205 989 9473",
    "sg:postcode":"35244",
    "sg:province":"AL",
    "wof:name":"Big Lots",
    "wof:placetype":"venue"
},
  "geometry": {"coordinates":[-86.79512,33.350966],"type":"Point"}
}