{
  "type": "Feature",
  "properties": {
    "iso:country":"US",
    "sg:address":"1045 N Brindlee Mountain Pkwy",
    "sg:city":"Arab",
    "sg:classifiers":[
        {
            "category":"Home & Garden",
            "subcategory":"Building Materials",
            "type":"Retail Goods"
        }
    ],
    "sg:phone":"+1 256 586 0770",
    "sg:postcode":"35016",
    "sg:province":"AL",
    "sg:website":"www.marvins.com",
    "wof:name":"Marvin's Building Materials",
    "wof:placetype":"venue"
},
  "geometry": {"coordinates":[-86.503122,34.332204],"type":"Point"}
}