{
  "type": "Feature",
  "properties": {
    "iso:country":"US",
    "sg:address":"1718 4th Ave N",
    "sg:city":"Bessemer",
    "sg:classifiers":[
        {
            "category":"Autos & Motor Vehicles",
            "subcategory":"Auto Supplies",
            "type":"Retail Goods"
        },
        {
            "category":"Wholesale",
            "subcategory":"Painting Supplies",
            "type":"Manufacturing & Wholesale Goods"
        }
    ],
    "sg:phone":"+1 205 426 4277",
    "sg:postcode":"35020",
    "sg:province":"AL",
    "sg:tags":[
        "automobile",
        "parts",
        "paint"
    ],
    "wof:name":"American Auto Paint & Supplies",
    "wof:placetype":"venue"
},
  "geometry": {"coordinates":[-86.955662,33.401886],"type":"Point"}
}