{
  "type": "Feature",
  "properties": {
    "iso:country":"US",
    "sg:address":"2025 3rd Ave N",
    "sg:city":"Birmingham",
    "sg:classifiers":[
        {
            "category":"Professional",
            "subcategory":"Lawyer & Legal Services",
            "type":"Services"
        }
    ],
    "sg:phone":"+1 205 324 3537",
    "sg:postcode":"35203",
    "sg:province":"AL",
    "sg:tags":[
        "attorney"
    ],
    "wof:name":"Jeffrey A Brooks",
    "wof:placetype":"venue"
},
  "geometry": {"coordinates":[-86.805763,33.516728],"type":"Point"}
}