{
  "type": "Feature",
  "properties": {
    "iso:country":"US",
    "sg:address":"3001 20th Ave",
    "sg:city":"Valley",
    "sg:classifiers":[
        {
            "category":"Cinema",
            "subcategory":"Movie Rental",
            "type":"Entertainment"
        }
    ],
    "sg:phone":"+1 334 768 2172",
    "sg:postcode":"36854",
    "sg:province":"AL",
    "sg:tags":[
        "video",
        "tape",
        "store"
    ],
    "wof:name":"Movie Gallery",
    "wof:placetype":"venue"
},
  "geometry": {"coordinates":[-85.180922,32.843952],"type":"Point"}
}