{
  "type": "Feature",
  "properties": {
    "addr:full":"3802 Mill Creek Ave Tuscaloosa AL 35401",
    "addr:housenumber":"3802",
    "addr:postcode":"35401",
    "addr:street":"Mill Creek Ave",
    "iso:country":"US",
    "sg:address":"3802 Mill Creek Ave",
    "sg:city":"Tuscaloosa",
    "sg:classifiers":[
        {
            "category":"Real Estate",
            "subcategory":"Real Estate Agent",
            "type":"Services"
        }
    ],
    "sg:phone":"+1 205 750 2485",
    "sg:postcode":"35401",
    "sg:province":"AL",
    "wof:name":"Burns & Corder Realty Inc",
    "wof:placetype":"venue"
},
  "geometry": {"coordinates":[-87.556673,33.172297],"type":"Point"}
}