{
  "type": "Feature",
  "properties": {
    "addr:full":"5005 Garth Rd SE Huntsville AL 35802",
    "addr:housenumber":"5005",
    "addr:postcode":"35802",
    "addr:street":"Garth Rd Se",
    "iso:country":"US",
    "sg:address":"5005 Garth Rd SE",
    "sg:city":"Huntsville",
    "sg:classifiers":[
        {
            "category":"Farming",
            "subcategory":"Livestock Farm",
            "type":"Manufacturing & Wholesale Goods"
        }
    ],
    "sg:phone":"+1 256 881 0751",
    "sg:postcode":"35802",
    "sg:province":"AL",
    "sg:tags":[
        "cattle"
    ],
    "wof:name":"Jones G W Farm",
    "wof:placetype":"venue"
},
  "geometry": {"coordinates":[-86.552251,34.693493],"type":"Point"}
}