{
  "type": "Feature",
  "properties": {
    "iso:country":"US",
    "sg:address":"1114 Strathmore Ave",
    "sg:city":"Dothan",
    "sg:classifiers":[
        {
            "category":"Professional",
            "subcategory":"Computer Services",
            "type":"Services"
        }
    ],
    "sg:phone":"+1 334 792 7700",
    "sg:postcode":"36303",
    "sg:province":"AL",
    "sg:tags":[
        "related"
    ],
    "wof:name":"Robin Skinner",
    "wof:placetype":"venue"
},
  "geometry": {"coordinates":[-85.439395,31.24957],"type":"Point"}
}