{
  "type": "Feature",
  "properties": {
    "addr:full":"9064 Helena Rd Pelham AL 35124",
    "addr:housenumber":"9064",
    "addr:postcode":"35124",
    "addr:street":"Helena Rd",
    "iso:country":"US",
    "sg:address":"9064 Helena Rd",
    "sg:city":"Pelham",
    "sg:classifiers":[
        {
            "category":"Wholesale",
            "subcategory":"Machinery & Supplies",
            "type":"Manufacturing & Wholesale Goods"
        }
    ],
    "sg:phone":"+1 205 988 8623",
    "sg:postcode":"35124",
    "sg:province":"AL",
    "sg:tags":[
        "equipment",
        "industrial"
    ],
    "wof:name":"Bipco",
    "wof:placetype":"venue"
},
  "geometry": {"coordinates":[-86.801024,33.34372],"type":"Point"}
}