{
  "type": "Feature",
  "properties": {
    "iso:country":"US",
    "sg:address":"3720 Jordan Ln NW",
    "sg:city":"Huntsville",
    "sg:classifiers":[
        {
            "category":"Food & Beverages",
            "subcategory":"Liquor & Beverages",
            "type":"Retail Goods"
        }
    ],
    "sg:phone":"+1 256 858 0880",
    "sg:postcode":"35806",
    "sg:province":"AL",
    "wof:name":"Drink",
    "wof:placetype":"venue"
},
  "geometry": {"coordinates":[-86.668138,34.79239],"type":"Point"}
}