{
  "type": "Feature",
  "properties": {
    "addr:full":"1203 Morningside Dr SW Cullman AL 35055",
    "addr:housenumber":"1203",
    "addr:postcode":"35055",
    "addr:street":"Morningside Dr Sw",
    "iso:country":"US",
    "sg:address":"1203 Morningside Dr SW",
    "sg:city":"Cullman",
    "sg:classifiers":[
        {
            "category":"Shopping",
            "type":"Retail Goods"
        }
    ],
    "sg:phone":"+1 256 739 3986",
    "sg:postcode":"35055",
    "sg:province":"AL",
    "sg:tags":[
        "cosmetic",
        "perfume"
    ],
    "wof:name":"Mary Kay Cosmetics",
    "wof:placetype":"venue"
},
  "geometry": {"coordinates":[-86.853005,34.154487],"type":"Point"}
}