{
  "type": "Feature",
  "properties": {
    "iso:country":"US",
    "sg:address":"613 N 14th St",
    "sg:city":"Lanett",
    "sg:classifiers":[
        {
            "category":"Retail",
            "subcategory":"Auto Repair",
            "type":"Services"
        }
    ],
    "sg:phone":"+1 334 644 1247",
    "sg:postcode":"36863",
    "sg:province":"AL",
    "sg:tags":[
        "body"
    ],
    "wof:name":"Valley Body & Fender Works",
    "wof:placetype":"venue"
},
  "geometry": {"coordinates":[-85.198138,32.875598],"type":"Point"}
}