{
  "type": "Feature",
  "properties": {
    "iso:country":"US",
    "sg:address":"301 N Pickett St",
    "sg:city":"Autaugaville",
    "sg:classifiers":[
        {
            "category":"Retail",
            "subcategory":"Auto Repair",
            "type":"Services"
        }
    ],
    "sg:phone":"+1 334 361 8007",
    "sg:postcode":"36003",
    "sg:province":"AL",
    "sg:tags":[
        "general"
    ],
    "wof:name":"Autaugaville Auto Center",
    "wof:placetype":"venue"
},
  "geometry": {"coordinates":[-86.655891,32.437133],"type":"Point"}
}