{
  "type": "Feature",
  "properties": {
    "iso:country":"US",
    "sg:address":"2100 Lakeshore Dr",
    "sg:city":"Homewood",
    "sg:classifiers":[
        {
            "category":"Government",
            "subcategory":"Office",
            "type":"Public Place"
        }
    ],
    "sg:phone":"+1 205 871 8632",
    "sg:postcode":"35209",
    "sg:province":"AL",
    "sg:tags":[
        "state",
        "security"
    ],
    "wof:name":"Army National Guard Recruiter",
    "wof:placetype":"venue"
},
  "geometry": {"coordinates":[-86.783828,33.465972],"type":"Point"}
}