{
  "type": "Feature",
  "properties": {
    "iso:country":"US",
    "sg:address":"2013 16th St",
    "sg:city":"Birmingham",
    "sg:classifiers":[
        {
            "category":"Building & Trades",
            "subcategory":"Construction",
            "type":"Services"
        }
    ],
    "sg:phone":"+1 205 903 7484",
    "sg:postcode":"35218",
    "sg:province":"AL",
    "sg:tags":[
        "painter"
    ],
    "wof:name":"Anderson Painting",
    "wof:placetype":"venue"
},
  "geometry": {"coordinates":[-86.881428,33.512915],"type":"Point"}
}