{
  "type": "Feature",
  "properties": {
    "addr:full":"381 Mendel Pkwy E Montgomery AL 36117",
    "addr:housenumber":"381",
    "addr:postcode":"36117",
    "addr:street":"Mendel Pkwy E",
    "iso:country":"US",
    "sg:address":"381 Mendel Pkwy E",
    "sg:city":"Montgomery",
    "sg:classifiers":[
        {
            "category":"Communications",
            "subcategory":"Radio Station",
            "type":"Services"
        }
    ],
    "sg:phone":"+1 334 274 8900",
    "sg:postcode":"36117",
    "sg:province":"AL",
    "sg:tags":[
        "company",
        "broadcasting"
    ],
    "wof:name":"89.1 FM",
    "wof:placetype":"venue"
},
  "geometry": {"coordinates":[-86.201995,32.379767],"type":"Point"}
}