{
  "type": "Feature",
  "properties": {
    "iso:country":"US",
    "sg:address":"15431 Line Rd",
    "sg:city":"Athens",
    "sg:classifiers":[
        {
            "category":"Building & Trades",
            "subcategory":"Construction",
            "type":"Services"
        }
    ],
    "sg:phone":"+1 256 230 2979",
    "sg:postcode":"35613",
    "sg:province":"AL",
    "sg:tags":[
        "hanging",
        "contractor"
    ],
    "wof:name":"Icon Blue Painting & Design",
    "wof:placetype":"venue"
},
  "geometry": {"coordinates":[-86.908562,34.780316],"type":"Point"}
}