{
  "type": "Feature",
  "properties": {
    "iso:country":"US",
    "sg:address":"11 Lafayette St",
    "sg:city":"Alexander City",
    "sg:classifiers":[
        {
            "category":"Organizations",
            "subcategory":"Non-profit Organization",
            "type":"Services"
        }
    ],
    "sg:phone":"+1 256 329 2273",
    "sg:postcode":"35010",
    "sg:province":"AL",
    "sg:tags":[
        "alternative",
        "abortion"
    ],
    "wof:name":"Sav-A-Life",
    "wof:placetype":"venue"
},
  "geometry": {"coordinates":[-85.956773,32.950544],"type":"Point"}
}