{
  "type": "Feature",
  "properties": {
    "iso:country":"US",
    "sg:address":"1113 3rd St NE",
    "sg:city":"Cullman",
    "sg:classifiers":[
        {
            "category":"Building & Trades",
            "subcategory":"Construction",
            "type":"Services"
        }
    ],
    "sg:phone":"+1 256 734 7815",
    "sg:postcode":"35055",
    "sg:province":"AL",
    "sg:tags":[
        "insulation",
        "contractor",
        "carpet",
        "furniture"
    ],
    "wof:name":"C F & G Carpet",
    "wof:placetype":"venue"
},
  "geometry": {"coordinates":[-86.831142,34.179981],"type":"Point"}
}