{
  "type": "Feature",
  "properties": {
    "addr:full":"600 S Brundidge St Troy AL 36081",
    "addr:housenumber":"600",
    "addr:postcode":"36081",
    "addr:street":"S Brundidge St",
    "iso:country":"US",
    "sg:address":"600 S Brundidge St",
    "sg:city":"Troy",
    "sg:classifiers":[
        {
            "category":"Shopping",
            "subcategory":"Clothing, Apparel, & Fashions",
            "type":"Retail Goods"
        }
    ],
    "sg:phone":"+1 334 566 2191",
    "sg:postcode":"36081",
    "sg:province":"AL",
    "sg:tags":[
        "furnishing"
    ],
    "wof:name":"Mall",
    "wof:placetype":"venue"
},
  "geometry": {"coordinates":[-85.965694,31.801136],"type":"Point"}
}