{
  "type": "Feature",
  "properties": {
    "iso:country":"US",
    "sg:address":"35 Sevier Ave",
    "sg:city":"Florence",
    "sg:classifiers":[
        {
            "category":"Organizations",
            "subcategory":"Religious Organization",
            "type":"Services"
        }
    ],
    "sg:phone":"+1 256 766 5421",
    "sg:postcode":"35630",
    "sg:province":"AL",
    "sg:tags":[
        "child",
        "day",
        "care"
    ],
    "wof:name":"Nursery The",
    "wof:placetype":"venue"
},
  "geometry": {"coordinates":[-87.623085,34.829454],"type":"Point"}
}