{
  "type": "Feature",
  "properties": {
    "addr:full":"2001 McFarland Blvd E Tuscaloosa AL 35404",
    "addr:housenumber":"2001",
    "addr:postcode":"35404",
    "addr:street":"Mcfarland Blvd E",
    "iso:country":"US",
    "sg:address":"2001 McFarland Blvd E",
    "sg:city":"Tuscaloosa",
    "sg:classifiers":[
        {
            "category":"Food & Beverages",
            "subcategory":"Groceries & Convenience Stores",
            "type":"Retail Goods"
        },
        {
            "category":"Shopping",
            "subcategory":"Pharmacy",
            "type":"Retail Goods"
        }
    ],
    "sg:phone":"+1 205 345 5855",
    "sg:postcode":"35404",
    "sg:province":"AL",
    "sg:tags":[
        "grocer"
    ],
    "wof:name":"Bruno's Food & Pharmacy",
    "wof:placetype":"venue"
},
  "geometry": {"coordinates":[-87.52580399999999,33.195886],"type":"Point"}
}