{
  "type": "Feature",
  "properties": {
    "iso:country":"US",
    "sg:address":"222 W Cusseta St",
    "sg:city":"Dadeville",
    "sg:classifiers":[
        {
            "category":"Professional",
            "subcategory":"Employment Agencies",
            "type":"Services"
        }
    ],
    "sg:phone":"+1 256 825 3999",
    "sg:postcode":"36853",
    "sg:province":"AL",
    "sg:tags":[
        "consulting",
        "management"
    ],
    "wof:name":"Cone Financial Group Inc",
    "wof:placetype":"venue"
},
  "geometry": {"coordinates":[-85.764985,32.831507],"type":"Point"}
}