{
  "type": "Feature",
  "properties": {
    "addr:full":"1201 Newell Pkwy Montgomery AL 36110",
    "addr:housenumber":"1201",
    "addr:postcode":"36110",
    "addr:street":"Newell Pkwy",
    "iso:country":"US",
    "sg:address":"1201 Newell Pkwy",
    "sg:city":"Montgomery",
    "sg:classifiers":[
        {
            "category":"Wholesale",
            "subcategory":"Machinery & Supplies",
            "type":"Manufacturing & Wholesale Goods"
        },
        {
            "category":"Wholesale",
            "subcategory":"Stationery",
            "type":"Manufacturing & Wholesale Goods"
        }
    ],
    "sg:phone":"+1 334 244 0555",
    "sg:postcode":"36110",
    "sg:province":"AL",
    "sg:tags":[
        "paper",
        "janitor"
    ],
    "sg:website":"www.centralpaper-al.com",
    "wof:name":"Central Paper Company Inc",
    "wof:placetype":"venue"
},
  "geometry": {"coordinates":[-86.26160299999999,32.413359],"type":"Point"}
}