{
  "type": "Feature",
  "properties": {
    "addr:full":"1212 Gunter Ave Guntersville AL 35976",
    "addr:housenumber":"1212",
    "addr:postcode":"35976",
    "addr:street":"Gunter Ave",
    "iso:country":"US",
    "sg:address":"1212 Gunter Ave",
    "sg:city":"Guntersville",
    "sg:classifiers":[
        {
            "category":"Real Estate",
            "subcategory":"Real Estate Agent",
            "type":"Services"
        }
    ],
    "sg:phone":"+1 256 582 6900",
    "sg:postcode":"35976",
    "sg:province":"AL",
    "sg:website":"www.guntersville.coldwellbankergraben.co",
    "wof:name":"Graben Real Estate Inc",
    "wof:placetype":"venue"
},
  "geometry": {"coordinates":[-86.300786,34.349015],"type":"Point"}
}