{
  "type": "Feature",
  "properties": {
    "addr:full":"216 W Irvine Ave Florence AL 35630",
    "addr:housenumber":"216",
    "addr:postcode":"35630",
    "addr:street":"W Irvine Ave",
    "iso:country":"US",
    "sg:address":"216 W Irvine Ave",
    "sg:city":"Florence",
    "sg:classifiers":[
        {
            "category":"Social Services",
            "type":"Services"
        }
    ],
    "sg:phone":"+1 256 766 8220",
    "sg:postcode":"35630",
    "sg:province":"AL",
    "sg:tags":[
        "youth",
        "organization",
        "center"
    ],
    "wof:name":"Boys & Girls Clubs-Nw Alabama",
    "wof:placetype":"venue"
},
  "geometry": {"coordinates":[-87.681634,34.804385],"type":"Point"}
}