{
  "type": "Feature",
  "properties": {
    "iso:country":"US",
    "sg:address":"2135 Mount Meigs Rd",
    "sg:city":"Montgomery",
    "sg:classifiers":[
        {
            "category":"Building & Trades",
            "subcategory":"Plumbing",
            "type":"Services"
        }
    ],
    "sg:phone":"+1 334 265 1791",
    "sg:postcode":"36107",
    "sg:province":"AL",
    "sg:tags":[
        "plumbing",
        "contractor"
    ],
    "wof:name":"Roy's Plumbing Repairs",
    "wof:placetype":"venue"
},
  "geometry": {"coordinates":[-86.278043,32.378209],"type":"Point"}
}