{
  "type": "Feature",
  "properties": {
    "iso:country":"US",
    "sg:address":"2787 Pelham Pkwy",
    "sg:city":"Pelham",
    "sg:classifiers":[
        {
            "category":"Personal",
            "subcategory":"Beauty Salon",
            "type":"Services"
        }
    ],
    "sg:phone":"+1 205 663 4005",
    "sg:postcode":"35124",
    "sg:province":"AL",
    "sg:tags":[
        "shop"
    ],
    "wof:name":"Splash Hair Studio",
    "wof:placetype":"venue"
},
  "geometry": {"coordinates":[-86.80465599999999,33.307617],"type":"Point"}
}