{
  "type": "Feature",
  "properties": {
    "addr:full":"1530 Schillinger Rd S Mobile AL 36695",
    "addr:housenumber":"1530",
    "addr:postcode":"36695",
    "addr:street":"Schillinger Rd S",
    "iso:country":"US",
    "sg:address":"1530 Schillinger Rd S",
    "sg:city":"Mobile",
    "sg:classifiers":[
        {
            "category":"Home & Garden",
            "subcategory":"Building Materials",
            "type":"Retail Goods"
        },
        {
            "category":"Building & Trades",
            "subcategory":"Construction",
            "type":"Services"
        }
    ],
    "sg:phone":"+1 251 635 1500",
    "sg:postcode":"36695",
    "sg:province":"AL",
    "sg:tags":[
        "fence-sales",
        "fence",
        "contractor"
    ],
    "sg:website":"http://www.turnerwilsonfence.com/",
    "wof:name":"Turner-Wilson Fence Co",
    "wof:placetype":"venue"
},
  "geometry": {"coordinates":[-88.225273,30.658971],"type":"Point"}
}