{
  "type": "Feature",
  "properties": {
    "iso:country":"US",
    "sg:address":"240 US Hwy 31",
    "sg:city":"Hartselle",
    "sg:classifiers":[
        {
            "category":"Banks & Credit Unions",
            "subcategory":"Bank",
            "type":"Services"
        }
    ],
    "sg:phone":"+1 256 751 0300",
    "sg:postcode":"35640",
    "sg:province":"AL",
    "sg:tags":[
        "loan"
    ],
    "wof:name":"First State Loans Of Hartselle",
    "wof:placetype":"venue"
},
  "geometry": {"coordinates":[-86.94284,34.444148],"type":"Point"}
}