{
  "type": "Feature",
  "properties": {
    "addr:full":"8390 US Hwy 231 Dothan AL 36301",
    "addr:housenumber":"8390",
    "addr:postcode":"36301",
    "addr:street":"Us Hwy 231",
    "iso:country":"US",
    "sg:address":"8390 US Hwy 231",
    "sg:city":"Dothan",
    "sg:classifiers":[
        {
            "category":"Restaurant",
            "type":"Food & Drink"
        }
    ],
    "sg:phone":"+1 334 702 4693",
    "sg:postcode":"36301",
    "sg:province":"AL",
    "wof:name":"Subway Sandwiches & Salads",
    "wof:placetype":"venue"
},
  "geometry": {"coordinates":[-85.40558299999999,31.105646],"type":"Point"}
}