{
  "type": "Feature",
  "properties": {
    "addr:full":"816 Selma Ave Selma AL 36701",
    "addr:housenumber":"816",
    "addr:postcode":"36701",
    "addr:street":"Selma Ave",
    "iso:country":"US",
    "sg:address":"816 Selma Ave",
    "sg:city":"Selma",
    "sg:classifiers":[
        {
            "category":"Government",
            "subcategory":"Office",
            "type":"Public Place"
        }
    ],
    "sg:phone":"+1 334 874 2143",
    "sg:postcode":"36701",
    "sg:province":"AL",
    "sg:tags":[
        "village"
    ],
    "wof:name":"Selma Ceramic Art Program",
    "wof:placetype":"venue"
},
  "geometry": {"coordinates":[-87.02275,32.408148],"type":"Point"}
}