{
  "type": "Feature",
  "properties": {
    "iso:country":"US",
    "sg:address":"2529 Ewing Ave",
    "sg:city":"Gadsden",
    "sg:classifiers":[
        {
            "category":"Autos & Motor Vehicles",
            "subcategory":"Fuel & Gas Station",
            "type":"Retail Goods"
        }
    ],
    "sg:phone":"+1 256 547 2215",
    "sg:postcode":"35901",
    "sg:province":"AL",
    "sg:tags":[
        "station",
        "gasoline"
    ],
    "wof:name":"K & C Texaco",
    "wof:placetype":"venue"
},
  "geometry": {"coordinates":[-85.95475,34.05336],"type":"Point"}
}