{
  "type": "Feature",
  "properties": {
    "addr:full":"18203 Wallace Chapel Rd Vance AL 35490",
    "addr:housenumber":"18203",
    "addr:postcode":"35490",
    "addr:street":"Wallace Chapel Rd",
    "iso:country":"US",
    "sg:address":"18203 Wallace Chapel Rd",
    "sg:city":"Vance",
    "sg:classifiers":[
        {
            "category":"Retail",
            "subcategory":"Repair Shop",
            "type":"Services"
        }
    ],
    "sg:phone":"+1 205 233 0700",
    "sg:postcode":"35490",
    "sg:province":"AL",
    "sg:tags":[
        "welding"
    ],
    "wof:name":"Heritage Steel & Fabrication",
    "wof:placetype":"venue"
},
  "geometry": {"coordinates":[-87.239082,33.146301],"type":"Point"}
}