{
  "type": "Feature",
  "properties": {
    "iso:country":"US",
    "sg:address":"340 S 2nd St",
    "sg:city":"Gadsden",
    "sg:classifiers":[
        {
            "category":"Social Services",
            "subcategory":"Job Training",
            "type":"Services"
        }
    ],
    "sg:phone":"+1 256 547 4407",
    "sg:postcode":"35901",
    "sg:province":"AL",
    "sg:tags":[
        "retardation",
        "disabled",
        "mental",
        "dev"
    ],
    "wof:name":"Etowah Cherokee County Mental",
    "wof:placetype":"venue"
},
  "geometry": {"coordinates":[-86.002595,34.008797],"type":"Point"}
}