{
  "type": "Feature",
  "properties": {
    "iso:country":"US",
    "sg:address":"605 Seminary St",
    "sg:city":"Dothan",
    "sg:classifiers":[
        {
            "category":"Shopping",
            "subcategory":"Gifts & Souvenirs",
            "type":"Retail Goods"
        }
    ],
    "sg:phone":"+1 334 702 0131",
    "sg:postcode":"36303",
    "sg:province":"AL",
    "sg:tags":[
        "shop"
    ],
    "wof:name":"Gift Baskets",
    "wof:placetype":"venue"
},
  "geometry": {"coordinates":[-85.389425,31.231424],"type":"Point"}
}