{
  "type": "Feature",
  "properties": {
    "iso:country":"US",
    "sg:address":"2322 Reid School House Rd",
    "sg:city":"Trafford",
    "sg:classifiers":[
        {
            "category":"Manufacturing",
            "subcategory":"Glass & Minerals",
            "type":"Manufacturing & Wholesale Goods"
        }
    ],
    "sg:phone":"+1 205 229 2557",
    "sg:postcode":"35172",
    "sg:province":"AL",
    "sg:tags":[
        "concrete",
        "product",
        "mfg"
    ],
    "wof:name":"County Line Quarry",
    "wof:placetype":"venue"
},
  "geometry": {"coordinates":[-86.69266500000001,33.845578],"type":"Point"}
}