{
  "type": "Feature",
  "properties": {
    "iso:country":"US",
    "sg:address":"108 Argyle Ct",
    "sg:city":"Gadsden",
    "sg:classifiers":[
        {
            "category":"Health Services",
            "subcategory":"Doctor",
            "type":"Services"
        }
    ],
    "sg:phone":"+1 256 547 3246",
    "sg:postcode":"35904",
    "sg:province":"AL",
    "wof:name":"Wayne Milam",
    "wof:placetype":"venue"
},
  "geometry": {"coordinates":[-86.017437,34.050598],"type":"Point"}
}