{
  "type": "Feature",
  "properties": {
    "iso:country":"US",
    "sg:address":"400 2nd Ave",
    "sg:city":"Mulga",
    "sg:classifiers":[
        {
            "category":"Organizations",
            "subcategory":"Religious Organization",
            "type":"Services"
        }
    ],
    "sg:phone":"+1 205 786 3031",
    "sg:postcode":"35118",
    "sg:province":"AL",
    "sg:tags":[
        "church"
    ],
    "wof:name":"First Baptist Church E Mulga",
    "wof:placetype":"venue"
},
  "geometry": {"coordinates":[-86.976506,33.544461],"type":"Point"}
}