{
  "type": "Feature",
  "properties": {
    "iso:country":"US",
    "sg:address":"353 E Mill Ave",
    "sg:city":"Brantley",
    "sg:classifiers":[
        {
            "category":"Organizations",
            "subcategory":"Religious Organization",
            "type":"Services"
        }
    ],
    "sg:phone":"+1 334 527 3284",
    "sg:postcode":"36009",
    "sg:province":"AL",
    "sg:tags":[
        "clergy"
    ],
    "wof:name":"St Matthew AME Parsonage",
    "wof:placetype":"venue"
},
  "geometry": {"coordinates":[-86.24963099999999,31.587436],"type":"Point"}
}