{
  "type": "Feature",
  "properties": {
    "addr:full":"220 Co Rd 1077 Danville AL 35179",
    "addr:housenumber":"220;1077",
    "addr:postcode":"35179",
    "addr:street":"Co Rd",
    "iso:country":"US",
    "sg:address":"220 Co Rd 1077",
    "sg:city":"Danville",
    "sg:classifiers":[
        {
            "category":"Professional",
            "subcategory":"Business Services",
            "type":"Services"
        }
    ],
    "sg:phone":"+1 256 462 3743",
    "sg:postcode":"35179",
    "sg:province":"AL",
    "sg:tags":[
        "personal",
        "bureau",
        "broker",
        "agent"
    ],
    "wof:name":"Tim Rutherford Construction",
    "wof:placetype":"venue"
},
  "geometry": {"coordinates":[-87.09293099999999,34.309298],"type":"Point"}
}