{
  "type": "Feature",
  "properties": {
    "iso:country":"US",
    "sg:address":"1745 Blount Ave",
    "sg:city":"Guntersville",
    "sg:classifiers":[
        {
            "category":"Government",
            "subcategory":"Fire Station",
            "type":"Public Place"
        }
    ],
    "sg:phone":"+1 256 571 7575",
    "sg:postcode":"35976",
    "sg:province":"AL",
    "sg:tags":[
        "department",
        "protection"
    ],
    "wof:name":"Guntersville Fire Rescue Dept",
    "wof:placetype":"venue"
},
  "geometry": {"coordinates":[-86.307329,34.341023],"type":"Point"}
}