{
  "type": "Feature",
  "properties": {
    "iso:country":"US",
    "sg:address":"5510 McFarland Blvd",
    "sg:city":"Northport",
    "sg:classifiers":[
        {
            "category":"Shopping",
            "subcategory":"Pharmacy",
            "type":"Retail Goods"
        }
    ],
    "sg:phone":"+1 205 333 1216",
    "sg:postcode":"35476",
    "sg:province":"AL",
    "wof:name":"Food Max Pharmacy",
    "wof:placetype":"venue"
},
  "geometry": {"coordinates":[-87.607698,33.236582],"type":"Point"}
}