{
  "type": "Feature",
  "properties": {
    "iso:country":"US",
    "sg:address":"800 Downtowner Loop W",
    "sg:city":"Mobile",
    "sg:classifiers":[
        {
            "category":"Wholesale",
            "subcategory":"Electrical",
            "type":"Manufacturing & Wholesale Goods"
        }
    ],
    "sg:phone":"+1 251 343 4870",
    "sg:postcode":"36609",
    "sg:province":"AL",
    "sg:tags":[
        "installation",
        "electronic",
        "sales",
        "surveillance"
    ],
    "sg:website":"www.seitek.com",
    "wof:name":"Security Equipment Inc",
    "wof:placetype":"venue"
},
  "geometry": {"coordinates":[-88.144441,30.672646],"type":"Point"}
}