{
  "type": "Feature",
  "properties": {
    "iso:country":"US",
    "sg:address":"231 Karaway Hill",
    "sg:city":"Gadsden",
    "sg:classifiers":[
        {
            "category":"Retail",
            "subcategory":"Car Wash",
            "type":"Services"
        }
    ],
    "sg:phone":"+1 256 549 0071",
    "sg:postcode":"35901",
    "sg:province":"AL",
    "sg:tags":[
        "carwash"
    ],
    "wof:name":"C & J Clean Up Shop",
    "wof:placetype":"venue"
},
  "geometry": {"coordinates":[-85.950801,34.023749],"type":"Point"}
}