{
  "type": "Feature",
  "properties": {
    "iso:country":"US",
    "sg:address":"3025 US Hwy 98",
    "sg:city":"Daphne",
    "sg:classifiers":[
        {
            "category":"Retail",
            "subcategory":"Photofinishing",
            "type":"Services"
        }
    ],
    "sg:phone":"+1 251 621 0224",
    "sg:postcode":"36526",
    "sg:province":"AL",
    "sg:tags":[
        "laboratory"
    ],
    "wof:name":"Walgreens",
    "wof:placetype":"venue"
},
  "geometry": {"coordinates":[-87.89211899999999,30.5526],"type":"Point"}
}