{
  "type": "Feature",
  "properties": {
    "iso:country":"US",
    "sg:address":"358 Glenwood Dr",
    "sg:city":"Winfield",
    "sg:classifiers":[
        {
            "category":"Shopping",
            "subcategory":"Catalog Store",
            "type":"Retail Goods"
        }
    ],
    "sg:phone":"+1 205 487 2015",
    "sg:postcode":"35594",
    "sg:province":"AL",
    "sg:tags":[
        "mail",
        "house"
    ],
    "wof:name":"Gems Online",
    "wof:placetype":"venue"
},
  "geometry": {"coordinates":[-87.807627,33.918952],"type":"Point"}
}