{
  "type": "Feature",
  "properties": {
    "iso:country":"US",
    "sg:address":"10860 US Hwy 72",
    "sg:city":"Rogersville",
    "sg:classifiers":[
        {
            "category":"Professional",
            "subcategory":"Business Services",
            "type":"Services"
        }
    ],
    "sg:phone":"+1 256 247 5969",
    "sg:postcode":"35652",
    "sg:province":"AL",
    "wof:name":"Bargain Outlet",
    "wof:placetype":"venue"
},
  "geometry": {"coordinates":[-87.384465,34.847016],"type":"Point"}
}