{
  "type": "Feature",
  "properties": {
    "iso:country":"US",
    "sg:address":"218 Calhoun Ave",
    "sg:city":"Sylacauga",
    "sg:classifiers":[
        {
            "category":"Personal",
            "type":"Services"
        }
    ],
    "sg:phone":"+1 256 245 2772",
    "sg:postcode":"35150",
    "sg:province":"AL",
    "sg:tags":[
        "consultant",
        "wedding"
    ],
    "wof:name":"Nan's Flowers & Gifts",
    "wof:placetype":"venue"
},
  "geometry": {"coordinates":[-86.249662,33.171355],"type":"Point"}
}