{
  "type": "Feature",
  "properties": {
    "iso:country":"US",
    "sg:address":"6645 Loveless Park Loop",
    "sg:city":"Bessemer",
    "sg:classifiers":[
        {
            "category":"Recreation",
            "type":"Entertainment"
        }
    ],
    "sg:phone":"+1 205 428 0536",
    "sg:postcode":"35022",
    "sg:province":"AL",
    "sg:tags":[
        "club",
        "membership"
    ],
    "wof:name":"Wayne Vining Hunting Club",
    "wof:placetype":"venue"
},
  "geometry": {"coordinates":[-86.985433,33.316843],"type":"Point"}
}