{
  "type": "Feature",
  "properties": {
    "iso:country":"US",
    "sg:address":"5913 Southhall Rd",
    "sg:city":"Birmingham",
    "sg:classifiers":[
        {
            "category":"Food & Beverages",
            "subcategory":"Groceries & Convenience Stores",
            "type":"Retail Goods"
        }
    ],
    "sg:phone":"+1 205 591 1389",
    "sg:postcode":"35213",
    "sg:province":"AL",
    "wof:name":"Village Market & Deli",
    "wof:placetype":"venue"
},
  "geometry": {"coordinates":[-86.73520000000001,33.523834],"type":"Point"}
}