{
  "type": "Feature",
  "properties": {
    "iso:country":"US",
    "sg:address":"4740 Radio Rd",
    "sg:city":"Montgomery",
    "sg:classifiers":[
        {
            "category":"Communications",
            "subcategory":"Radio Station",
            "type":"Services"
        }
    ],
    "sg:phone":"+1 334 954 9226",
    "sg:postcode":"36116",
    "sg:province":"AL",
    "sg:tags":[
        "company",
        "broadcasting"
    ],
    "wof:name":"WBAM",
    "wof:placetype":"venue"
},
  "geometry": {"coordinates":[-86.22604,32.313067],"type":"Point"}
}