{
  "type": "Feature",
  "properties": {
    "addr:full":"10161 US Hwy 31 Hanceville AL 35077",
    "addr:housenumber":"10161",
    "addr:postcode":"35077",
    "addr:street":"Us Hwy 31",
    "iso:country":"US",
    "sg:address":"10161 US Hwy 31",
    "sg:city":"Hanceville",
    "sg:classifiers":[
        {
            "category":"Retail",
            "subcategory":"Veterinary Services",
            "type":"Services"
        }
    ],
    "sg:phone":"+1 256 739 9318",
    "sg:postcode":"35077",
    "sg:province":"AL",
    "wof:name":"Animal Medical Hospital",
    "wof:placetype":"venue"
},
  "geometry": {"coordinates":[-86.81495700000001,34.125884],"type":"Point"}
}