{
  "type": "Feature",
  "properties": {
    "iso:country":"US",
    "sg:address":"10161 US Hwy 31",
    "sg:city":"Hanceville",
    "sg:classifiers":[
        {
            "category":"Retail",
            "subcategory":"Veterinary Services",
            "type":"Services"
        }
    ],
    "sg:phone":"+1 256 739 9318",
    "sg:postcode":"35077",
    "sg:province":"AL",
    "wof:name":"Animal Medical Hospital",
    "wof:placetype":"venue"
},
  "geometry": {"coordinates":[-86.814957,34.125884],"type":"Point"}
}