{
  "type": "Feature",
  "properties": {
    "iso:country":"US",
    "sg:address":"11280 Georgia Rd",
    "sg:city":"Eclectic",
    "sg:classifiers":[
        {
            "category":"Food & Beverages",
            "subcategory":"Groceries & Convenience Stores",
            "type":"Retail Goods"
        }
    ],
    "sg:phone":"+1 334 541 3906",
    "sg:postcode":"36024",
    "sg:province":"AL",
    "sg:tags":[
        "grocer"
    ],
    "wof:name":"Hicks Grocery",
    "wof:placetype":"venue"
},
  "geometry": {"coordinates":[-86.052524,32.648219],"type":"Point"}
}