{
  "type": "Feature",
  "properties": {
    "iso:country":"US",
    "sg:address":"1358 15th Pl SW",
    "sg:city":"Birmingham",
    "sg:classifiers":[
        {
            "category":"Organizations",
            "subcategory":"Religious Organization",
            "type":"Services"
        }
    ],
    "sg:phone":"+1 205 925 8537",
    "sg:postcode":"35211",
    "sg:province":"AL",
    "wof:name":"Saint Mark AME Church Westend",
    "wof:placetype":"venue"
},
  "geometry": {"coordinates":[-86.85038,33.482241],"type":"Point"}
}