{
  "type": "Feature",
  "properties": {
    "iso:country":"US",
    "sg:address":"3507 Old Montgomery Hwy",
    "sg:city":"Birmingham",
    "sg:classifiers":[
        {
            "category":"Professional",
            "subcategory":"Accounting & Tax Preparation",
            "type":"Services"
        }
    ],
    "sg:phone":"+1 205 871 1974",
    "sg:postcode":"35209",
    "sg:province":"AL",
    "sg:tags":[
        "accountant"
    ],
    "wof:name":"Lee Alan Co",
    "wof:placetype":"venue"
},
  "geometry": {"coordinates":[-86.781862,33.471181],"type":"Point"}
}