{
  "type": "Feature",
  "properties": {
    "addr:full":"9694 Madison Blvd Madison AL 35758",
    "addr:housenumber":"9694",
    "addr:postcode":"35758",
    "addr:street":"Madison Blvd",
    "iso:country":"US",
    "sg:address":"9694 Madison Blvd",
    "sg:city":"Madison",
    "sg:classifiers":[
        {
            "category":"Wholesale",
            "subcategory":"Medical Equipment & Supplies",
            "type":"Manufacturing & Wholesale Goods"
        },
        {
            "category":"Health Services",
            "subcategory":"Clinic",
            "type":"Services"
        }
    ],
    "sg:phone":"+1 256 536 7336",
    "sg:postcode":"35758",
    "sg:province":"AL",
    "sg:tags":[
        "physician",
        "surgeon"
    ],
    "wof:name":"Cornerstone Medical Inc",
    "wof:placetype":"venue"
},
  "geometry": {"coordinates":[-86.78017699999999,34.665307],"type":"Point"}
}