{
  "type": "Feature",
  "properties": {
    "iso:country":"US",
    "sg:address":"2260 E University Dr",
    "sg:city":"Auburn",
    "sg:classifiers":[
        {
            "category":"Banks & Credit Unions",
            "subcategory":"Bank",
            "type":"Services"
        }
    ],
    "sg:phone":"+1 334 826 0850",
    "sg:postcode":"36830",
    "sg:province":"AL",
    "sg:tags":[
        "loan",
        "real estate"
    ],
    "wof:name":"Northstar Mortgage Group LLC",
    "wof:placetype":"venue"
},
  "geometry": {"coordinates":[-85.474076,32.631854],"type":"Point"}
}