{
  "type": "Feature",
  "properties": {
    "addr:full":"1165 Ross Clark Cir Dothan AL 36301",
    "addr:housenumber":"1165",
    "addr:postcode":"36301",
    "addr:street":"Ross Clark Cir",
    "iso:country":"US",
    "sg:address":"1165 Ross Clark Cir",
    "sg:city":"Dothan",
    "sg:classifiers":[
        {
            "category":"Restaurant",
            "type":"Food & Drink"
        }
    ],
    "sg:menulink":"http://www.allmenus.com/al/dothan/166451-burger-king/menu/",
    "sg:phone":"+1 334 678 8336",
    "sg:postcode":"36301",
    "sg:province":"AL",
    "sg:tags":[
        "burger",
        "american"
    ],
    "wof:name":"Burger King",
    "wof:placetype":"venue"
},
  "geometry": {"coordinates":[-85.36191700000001,31.212726],"type":"Point"}
}