{
  "type": "Feature",
  "properties": {
    "iso:country":"US",
    "sg:address":"85 McMillan Rd",
    "sg:city":"Notasulga",
    "sg:classifiers":[
        {
            "category":"Local Transit",
            "type":"Transportation"
        }
    ],
    "sg:phone":"+1 334 887 8595",
    "sg:postcode":"36866",
    "sg:province":"AL",
    "wof:name":"Express 85 Inc",
    "wof:placetype":"venue"
},
  "geometry": {"coordinates":[-85.615851,32.511142],"type":"Point"}
}