{
  "type": "Feature",
  "properties": {
    "iso:country":"US",
    "sg:address":"9002 Parkway E",
    "sg:city":"Birmingham",
    "sg:classifiers":[
        {
            "category":"Government",
            "subcategory":"Office",
            "type":"Public Place"
        }
    ],
    "sg:phone":"+1 205 833 9707",
    "sg:postcode":"35206",
    "sg:province":"AL",
    "sg:tags":[
        "national",
        "security"
    ],
    "wof:name":"Department of Military Alabama",
    "wof:placetype":"venue"
},
  "geometry": {"coordinates":[-86.712046,33.579764],"type":"Point"}
}