{
  "type": "Feature",
  "properties": {
    "addr:full":"577 State Rte 134 Headland AL 36345",
    "addr:housenumber":"577",
    "addr:postcode":"36345",
    "addr:street":"State Rte 134 Headland",
    "iso:country":"US",
    "sg:address":"577 State Rte 134",
    "sg:city":"Headland",
    "sg:classifiers":[
        {
            "category":"Wholesale",
            "subcategory":"Farm Supplies",
            "type":"Manufacturing & Wholesale Goods"
        }
    ],
    "sg:phone":"+1 334 693 3332",
    "sg:postcode":"36345",
    "sg:province":"AL",
    "sg:tags":[
        "peanut",
        "product"
    ],
    "sg:website":"www.gpc.com",
    "wof:name":"Golden Peanut Co",
    "wof:placetype":"venue"
},
  "geometry": {"coordinates":[-85.33221399999999,31.351382],"type":"Point"}
}