{
  "type": "Feature",
  "properties": {
    "iso:country":"US",
    "sg:address":"1067 Woodley Rd",
    "sg:city":"Montgomery",
    "sg:classifiers":[
        {
            "category":"Home & Garden",
            "subcategory":"Carpets & Floor Coverings",
            "type":"Retail Goods"
        }
    ],
    "sg:phone":"+1 334 834 5792",
    "sg:postcode":"36106",
    "sg:province":"AL",
    "sg:tags":[
        "dealer",
        "rug"
    ],
    "wof:name":"Cloverdale Oriental Rug Market",
    "wof:placetype":"venue"
},
  "geometry": {"coordinates":[-86.291,32.351479],"type":"Point"}
}