{
  "type": "Feature",
  "properties": {
    "addr:full":"13560 Christian Dr Northport AL 35475",
    "addr:housenumber":"13560",
    "addr:postcode":"35475",
    "addr:street":"Christian Dr",
    "iso:country":"US",
    "sg:address":"13560 Christian Dr",
    "sg:city":"Northport",
    "sg:classifiers":[
        {
            "category":"Retail",
            "subcategory":"Auto Repair",
            "type":"Services"
        }
    ],
    "sg:phone":"+1 205 330 1504",
    "sg:postcode":"35475",
    "sg:province":"AL",
    "sg:tags":[
        "general"
    ],
    "wof:name":"Kirklins Garage",
    "wof:placetype":"venue"
},
  "geometry": {"coordinates":[-87.636388,33.306295],"type":"Point"}
}