{
  "type": "Feature",
  "properties": {
    "iso:country":"US",
    "sg:address":"263 Co Rd 72",
    "sg:city":"Hanceville",
    "sg:classifiers":[
        {
            "category":"Retail",
            "subcategory":"Repair Shop",
            "type":"Services"
        }
    ],
    "sg:phone":"+1 256 287 1887",
    "sg:postcode":"35077",
    "sg:province":"AL",
    "sg:tags":[
        "refrigeration"
    ],
    "wof:name":"R&B Air Tool Svc",
    "wof:placetype":"venue"
},
  "geometry": {"coordinates":[-86.897567,33.975615],"type":"Point"}
}