{
  "type": "Feature",
  "properties": {
    "iso:country":"US",
    "sg:address":"532 Bell Point Rd",
    "sg:city":"Laceys Spring",
    "sg:classifiers":[
        {
            "category":"Shopping",
            "subcategory":"Computers & Home Electronics",
            "type":"Retail Goods"
        }
    ],
    "sg:phone":"+1 256 337 3154",
    "sg:postcode":"35754",
    "sg:province":"AL",
    "sg:tags":[
        "equipment",
        "electronic",
        "supply"
    ],
    "wof:name":"Electronic Business Svc",
    "wof:placetype":"venue"
},
  "geometry": {"coordinates":[-86.603408,34.510138],"type":"Point"}
}