{
  "type": "Feature",
  "properties": {
    "iso:country":"US",
    "sg:address":"2507 7th Ave S",
    "sg:city":"Birmingham",
    "sg:classifiers":[
        {
            "category":"Retail",
            "subcategory":"Animal Services",
            "type":"Services"
        }
    ],
    "sg:phone":"+1 205 250 0004",
    "sg:postcode":"35233",
    "sg:province":"AL",
    "sg:tags":[
        "pet",
        "grooming",
        "washing"
    ],
    "wof:name":"Lakeview Grooming",
    "wof:placetype":"venue"
},
  "geometry": {"coordinates":[-86.792013,33.509517],"type":"Point"}
}