{
  "type": "Feature",
  "properties": {
    "iso:country":"US",
    "sg:address":"2433 Carraway Blvd",
    "sg:city":"Birmingham",
    "sg:classifiers":[
        {
            "category":"Freight",
            "type":"Transportation"
        }
    ],
    "sg:phone":"+1 205 970 4165",
    "sg:postcode":"35234",
    "sg:province":"AL",
    "sg:tags":[
        "operator",
        "trucking"
    ],
    "wof:name":"G&J Transportation",
    "wof:placetype":"venue"
},
  "geometry": {"coordinates":[-86.814913,33.544455],"type":"Point"}
}