{
  "type": "Feature",
  "properties": {
    "iso:country":"US",
    "sg:address":"7 Western Byp",
    "sg:city":"Clayton",
    "sg:classifiers":[
        {
            "category":"Health Services",
            "subcategory":"Doctor",
            "type":"Services"
        }
    ],
    "sg:phone":"+1 334 775 3235",
    "sg:postcode":"36016",
    "sg:province":"AL",
    "sg:tags":[
        "physician",
        "surgeon"
    ],
    "wof:name":"Clayton Family Health Ctr",
    "wof:placetype":"venue"
},
  "geometry": {"coordinates":[-85.46041,31.872346],"type":"Point"}
}