{
  "type": "Feature",
  "properties": {
    "iso:country":"US",
    "sg:address":"7671 Country Squire Dr",
    "sg:city":"Mobile",
    "sg:classifiers":[
        {
            "category":"Organizations",
            "subcategory":"Religious Organization",
            "type":"Services"
        }
    ],
    "sg:phone":"+1 251 634 3044",
    "sg:postcode":"36695",
    "sg:province":"AL",
    "wof:name":"Kazanjian Karning Rev",
    "wof:placetype":"venue"
},
  "geometry": {"coordinates":[-88.223493,30.631916],"type":"Point"}
}