{
  "type": "Feature",
  "properties": {
    "iso:country":"US",
    "sg:address":"24 N Main St",
    "sg:city":"Wedowee",
    "sg:classifiers":[
        {
            "category":"Government",
            "subcategory":"Office",
            "type":"Public Place"
        }
    ],
    "sg:phone":"+1 256 357 2122",
    "sg:postcode":"36278",
    "sg:province":"AL",
    "sg:tags":[
        "village"
    ],
    "wof:name":"Wedowee Senior Citizens Svc",
    "wof:placetype":"venue"
},
  "geometry": {"coordinates":[-85.484771,33.309438],"type":"Point"}
}