{
  "type": "Feature",
  "properties": {
    "iso:country":"US",
    "sg:address":"25812 State Hwy 75",
    "sg:city":"Oneonta",
    "sg:classifiers":[
        {
            "category":"Autos & Motor Vehicles",
            "subcategory":"Fuel & Gas Station",
            "type":"Retail Goods"
        }
    ],
    "sg:phone":"+1 205 625 3700",
    "sg:postcode":"35121",
    "sg:province":"AL",
    "sg:tags":[
        "oil"
    ],
    "wof:name":"Allgood Grocery",
    "wof:placetype":"venue"
},
  "geometry": {"coordinates":[-86.510602,33.911916],"type":"Point"}
}