{
  "type": "Feature",
  "properties": {
    "addr:full":"732 Grants Mill Rd Birmingham AL 35210",
    "addr:housenumber":"732",
    "addr:postcode":"35210",
    "addr:street":"Grants Mill Rd",
    "iso:country":"US",
    "sg:address":"732 Grants Mill Rd",
    "sg:city":"Birmingham",
    "sg:classifiers":[
        {
            "category":"Home & Garden",
            "subcategory":"Carpets & Floor Coverings",
            "type":"Retail Goods"
        }
    ],
    "sg:phone":"+1 205 956 5882",
    "sg:postcode":"35210",
    "sg:province":"AL",
    "sg:tags":[
        "dealer",
        "rug"
    ],
    "wof:name":"Carpets Mill Direct",
    "wof:placetype":"venue"
},
  "geometry": {"coordinates":[-86.69441999999999,33.532546],"type":"Point"}
}