{
  "type": "Feature",
  "properties": {
    "iso:country":"US",
    "sg:address":"3100 Greensboro Ave",
    "sg:city":"Tuscaloosa",
    "sg:classifiers":[
        {
            "category":"Mining & Drilling",
            "type":"Manufacturing & Wholesale Goods"
        }
    ],
    "sg:phone":"+1 205 349 1117",
    "sg:postcode":"35401",
    "sg:province":"AL",
    "sg:tags":[
        "exploration"
    ],
    "wof:name":"Jabsco Oil LLC",
    "wof:placetype":"venue"
},
  "geometry": {"coordinates":[-87.553542,33.181761],"type":"Point"}
}