{
  "type": "Feature",
  "properties": {
    "iso:country":"US",
    "sg:address":"2606 Marlin Dr SE",
    "sg:city":"Huntsville",
    "sg:classifiers":[
        {
            "category":"Professional",
            "subcategory":"Computer Services",
            "type":"Services"
        }
    ],
    "sg:phone":"+1 256 882 7000",
    "sg:postcode":"35803",
    "sg:province":"AL",
    "sg:tags":[
        "prepackaged",
        "software"
    ],
    "wof:name":"S 4 Inc",
    "wof:placetype":"venue"
},
  "geometry": {"coordinates":[-86.529358,34.622558],"type":"Point"}
}