{
  "type": "Feature",
  "properties": {
    "iso:country":"US",
    "sg:address":"7559 Union Academy Ada Rd",
    "sg:city":"Hope Hull",
    "sg:classifiers":[
        {
            "category":"Recreation",
            "type":"Entertainment"
        }
    ],
    "sg:phone":"+1 334 288 3552",
    "sg:postcode":"36043",
    "sg:province":"AL",
    "wof:name":"Crazy Critters",
    "wof:placetype":"venue"
},
  "geometry": {"coordinates":[-86.39694799999999,32.116495],"type":"Point"}
}