{
  "type": "Feature",
  "properties": {
    "addr:full":"40471 US Hwy 280 Sylacauga AL 35150",
    "addr:postcode":"40471;35150",
    "addr:street":"Us Hwy 280",
    "iso:country":"US",
    "sg:address":"40471 US Hwy 280",
    "sg:city":"Sylacauga",
    "sg:phone":"+1 256 245 7476",
    "sg:postcode":"35150",
    "sg:province":"AL",
    "sg:tags":[
        "gas"
    ],
    "wof:name":"Deupree's Propane Gas Inc",
    "wof:placetype":"venue"
},
  "geometry": {"coordinates":[-86.29794,33.180046],"type":"Point"}
}