{
  "type": "Feature",
  "properties": {
    "iso:country":"US",
    "sg:address":"1057 Rosa L Parks Ave",
    "sg:city":"Montgomery",
    "sg:classifiers":[
        {
            "category":"Personal",
            "subcategory":"Barber",
            "type":"Services"
        }
    ],
    "sg:phone":"+1 334 264 3222",
    "sg:postcode":"36108",
    "sg:province":"AL",
    "wof:name":"West Side Barber Shop & Supply",
    "wof:placetype":"venue"
},
  "geometry": {"coordinates":[-86.316845,32.362516],"type":"Point"}
}