{
  "type": "Feature",
  "properties": {
    "iso:country":"US",
    "sg:address":"313 W College St",
    "sg:city":"Florence",
    "sg:classifiers":[
        {
            "category":"Health Services",
            "subcategory":"Doctor",
            "type":"Services"
        }
    ],
    "sg:phone":"+1 256 767 1111",
    "sg:postcode":"35630",
    "sg:province":"AL",
    "wof:name":"Beaumont Shelton DMD",
    "wof:placetype":"venue"
},
  "geometry": {"coordinates":[-87.678384,34.797858],"type":"Point"}
}