{
  "type": "Feature",
  "properties": {
    "iso:country":"US",
    "sg:address":"2901 Southwood Rd",
    "sg:city":"Birmingham",
    "sg:classifiers":[
        {
            "category":"Professional",
            "subcategory":"Business Services",
            "type":"Services"
        }
    ],
    "sg:phone":"+1 205 870 4787",
    "sg:postcode":"35223",
    "sg:province":"AL",
    "wof:name":"Nancy Smith Interiors",
    "wof:placetype":"venue"
},
  "geometry": {"coordinates":[-86.754836,33.484626],"type":"Point"}
}