{
  "type": "Feature",
  "properties": {
    "iso:country":"US",
    "sg:address":"4940 Altamont Rd S",
    "sg:city":"Birmingham",
    "sg:classifiers":[
        {
            "category":"Real Estate",
            "subcategory":"Architect",
            "type":"Services"
        }
    ],
    "sg:phone":"+1 205 592 0166",
    "sg:postcode":"35220",
    "sg:province":"AL",
    "sg:tags":[
        "architectural"
    ],
    "wof:name":"David L Peacher Inc",
    "wof:placetype":"venue"
},
  "geometry": {"coordinates":[-86.755648,33.516176],"type":"Point"}
}