{
  "type": "Feature",
  "properties": {
    "addr:full":"1444 Tallapoosa St Notasulga AL 36866",
    "addr:housenumber":"1444",
    "addr:postcode":"36866",
    "addr:street":"Tallapoosa St",
    "iso:country":"US",
    "sg:address":"1444 Tallapoosa St",
    "sg:city":"Notasulga",
    "sg:classifiers":[
        {
            "category":"Autos & Motor Vehicles",
            "subcategory":"Automobile Sales",
            "type":"Retail Goods"
        }
    ],
    "sg:phone":"+1 334 257 3295",
    "sg:postcode":"36866",
    "sg:province":"AL",
    "sg:tags":[
        "used"
    ],
    "wof:name":"Whitman Auto Sales Inc",
    "wof:placetype":"venue"
},
  "geometry": {"coordinates":[-85.68903400000001,32.572322],"type":"Point"}
}