{
  "type": "Feature",
  "properties": {
    "iso:country":"US",
    "sg:address":"35411 US Hwy 280",
    "sg:city":"Sylacauga",
    "sg:classifiers":[
        {
            "category":"Retail",
            "subcategory":"Laundry & Dry Cleaning",
            "type":"Services"
        }
    ],
    "sg:phone":"+1 256 872 2770",
    "sg:postcode":"35150",
    "sg:province":"AL",
    "sg:tags":[
        "cleaners",
        "rug",
        "carpet"
    ],
    "wof:name":"Affordable Carpet Care & Rug",
    "wof:placetype":"venue"
},
  "geometry": {"coordinates":[-86.334902,33.242171],"type":"Point"}
}