{
  "type": "Feature",
  "properties": {
    "addr:full":"201 W Section Ave Foley AL 36535",
    "addr:housenumber":"201",
    "addr:postcode":"36535",
    "addr:street":"W Section Ave",
    "iso:country":"US",
    "sg:address":"201 W Section Ave",
    "sg:city":"Foley",
    "sg:classifiers":[
        {
            "category":"Government",
            "subcategory":"Court House",
            "type":"Public Place"
        }
    ],
    "sg:phone":"+1 251 943 5061",
    "sg:postcode":"36535",
    "sg:province":"AL",
    "wof:name":"Office of Dist",
    "wof:placetype":"venue"
},
  "geometry": {"coordinates":[-87.68519999999999,30.414092],"type":"Point"}
}