{
  "type": "Feature",
  "properties": {
    "addr:full":"1007 Bridge Ave Northport AL 35476",
    "addr:housenumber":"1007",
    "addr:postcode":"35476",
    "addr:street":"Bridge Ave",
    "iso:country":"US",
    "sg:address":"1007 Bridge Ave",
    "sg:city":"Northport",
    "sg:classifiers":[
        {
            "category":"Banks & Credit Unions",
            "subcategory":"Bank",
            "type":"Services"
        }
    ],
    "sg:phone":"+1 205 562 9650",
    "sg:postcode":"35476",
    "sg:province":"AL",
    "sg:tags":[
        "loan",
        "real estate"
    ],
    "wof:name":"Mortgage Brokers Group",
    "wof:placetype":"venue"
},
  "geometry": {"coordinates":[-87.575565,33.223774],"type":"Point"}
}