{
  "type": "Feature",
  "properties": {
    "iso:country":"US",
    "sg:address":"9861 Parkway E",
    "sg:city":"Birmingham",
    "sg:phone":"+1 205 854 5518",
    "sg:postcode":"35215",
    "sg:province":"AL",
    "wof:name":"Parkway Tire & Automotive Inc",
    "wof:placetype":"venue"
},
  "geometry": {"coordinates":[-86.689745,33.606595],"type":"Point"}
}