{
  "type": "Feature",
  "properties": {
    "iso:country":"US",
    "sg:address":"530 Riverbend Pl",
    "sg:city":"Florence",
    "sg:classifiers":[
        {
            "category":"Professional",
            "subcategory":"Business Services",
            "type":"Services"
        }
    ],
    "sg:phone":"+1 256 765 9995",
    "sg:postcode":"35630",
    "sg:province":"AL",
    "wof:name":"Susan Trousdale Interior",
    "wof:placetype":"venue"
},
  "geometry": {"coordinates":[-87.694507,34.788787],"type":"Point"}
}