{
  "type": "Feature",
  "properties": {
    "addr:full":"1019 W Meighan Blvd Gadsden AL 35901",
    "addr:housenumber":"1019",
    "addr:postcode":"35901",
    "addr:street":"W Meighan Blvd",
    "iso:country":"US",
    "sg:address":"1019 W Meighan Blvd",
    "sg:city":"Gadsden",
    "sg:classifiers":[
        {
            "category":"Restaurant",
            "type":"Food & Drink"
        }
    ],
    "sg:phone":"+1 256 546 2946",
    "sg:postcode":"35901",
    "sg:province":"AL",
    "wof:name":"Bar-B-Q Bob's",
    "wof:placetype":"venue"
},
  "geometry": {"coordinates":[-86.016992,34.019905],"type":"Point"}
}