{
  "type": "Feature",
  "properties": {
    "iso:country":"US",
    "sg:address":"3214 E Main St",
    "sg:city":"Dothan",
    "sg:classifiers":[
        {
            "category":"Travel",
            "subcategory":"Hotels & Motels",
            "type":"Entertainment"
        }
    ],
    "sg:phone":"+1 334 793 6784",
    "sg:postcode":"36301",
    "sg:province":"AL",
    "sg:tags":[
        "operation"
    ],
    "wof:name":"Keshan Inc",
    "wof:placetype":"venue"
},
  "geometry": {"coordinates":[-85.34621799999999,31.203297],"type":"Point"}
}