{
  "type": "Feature",
  "properties": {
    "iso:country":"US",
    "sg:address":"815 McKenzie St",
    "sg:city":"Foley",
    "sg:classifiers":[
        {
            "category":"Health Services",
            "subcategory":"Optometrist",
            "type":"Services"
        }
    ],
    "sg:phone":"+1 251 943 5115",
    "sg:postcode":"36535",
    "sg:province":"AL",
    "wof:name":"Douglas B Hixson Od",
    "wof:placetype":"venue"
},
  "geometry": {"coordinates":[-87.683814,30.414408],"type":"Point"}
}