{
  "type": "Feature",
  "properties": {
    "addr:full":"6327 US Hwy 72 Gurley AL 35748",
    "addr:housenumber":"6327",
    "addr:postcode":"35748",
    "addr:street":"Us Hwy 72 Gurley",
    "iso:country":"US",
    "sg:address":"6327 US Hwy 72",
    "sg:city":"Gurley",
    "sg:classifiers":[
        {
            "category":"Food & Beverages",
            "subcategory":"Groceries & Convenience Stores",
            "type":"Retail Goods"
        }
    ],
    "sg:phone":"+1 256 776 3661",
    "sg:postcode":"35748",
    "sg:province":"AL",
    "sg:tags":[
        "grocer"
    ],
    "wof:name":"Piggly Wiggly",
    "wof:placetype":"venue"
},
  "geometry": {"coordinates":[-86.371467,34.694825],"type":"Point"}
}