{
  "type": "Feature",
  "properties": {
    "iso:country":"US",
    "sg:address":"510 Killingsworth Cove Rd",
    "sg:city":"Gurley",
    "sg:classifiers":[
        {
            "category":"Home & Garden",
            "subcategory":"Furniture",
            "type":"Retail Goods"
        }
    ],
    "sg:phone":"+1 256 776 2155",
    "sg:postcode":"35748",
    "sg:province":"AL",
    "sg:tags":[
        "wholesale"
    ],
    "wof:name":"Furniture Outlet USA LLC",
    "wof:placetype":"venue"
},
  "geometry": {"coordinates":[-86.37186699999999,34.756563],"type":"Point"}
}