{
  "type": "Feature",
  "properties": {
    "iso:country":"US",
    "sg:address":"1118 N Wilson Ave",
    "sg:city":"Mobile",
    "sg:classifiers":[
        {
            "category":"Autos & Motor Vehicles",
            "subcategory":"Automobile Sales",
            "type":"Retail Goods"
        }
    ],
    "sg:phone":"+1 251 456 8666",
    "sg:postcode":"36610",
    "sg:province":"AL",
    "sg:tags":[
        "used"
    ],
    "wof:name":"Divine Auto Sales",
    "wof:placetype":"venue"
},
  "geometry": {"coordinates":[-88.078861,30.744927],"type":"Point"}
}