{
  "type": "Feature",
  "properties": {
    "addr:full":"225 S Main St Boaz AL 35957",
    "addr:housenumber":"225",
    "addr:postcode":"35957",
    "addr:street":"S Main St",
    "iso:country":"US",
    "sg:address":"225 S Main St",
    "sg:city":"Boaz",
    "sg:classifiers":[
        {
            "category":"Building & Trades",
            "subcategory":"Construction",
            "type":"Services"
        }
    ],
    "sg:phone":"+1 256 840 2834",
    "sg:postcode":"35957",
    "sg:province":"AL",
    "sg:tags":[
        "industrial"
    ],
    "wof:name":"Superior Structures of Boaz",
    "wof:placetype":"venue"
},
  "geometry": {"coordinates":[-86.16519700000001,34.196546],"type":"Point"}
}