{
  "type": "Feature",
  "properties": {
    "iso:country":"US",
    "sg:address":"1102 Comanche Trl",
    "sg:city":"Anniston",
    "sg:classifiers":[
        {
            "category":"Building & Trades",
            "subcategory":"Cleaning & Sanitation",
            "type":"Services"
        }
    ],
    "sg:phone":"+1 256 847 1002",
    "sg:postcode":"36206",
    "sg:province":"AL",
    "sg:tags":[
        "janitor"
    ],
    "wof:name":"Masterclene Carpet & Tile",
    "wof:placetype":"venue"
},
  "geometry": {"coordinates":[-85.86149500000001,33.726584],"type":"Point"}
}