{
  "type": "Feature",
  "properties": {
    "iso:country":"US",
    "sg:address":"2310 Market Pl SW",
    "sg:city":"Huntsville",
    "sg:classifiers":[
        {
            "category":"Banks & Credit Unions",
            "subcategory":"Bank",
            "type":"Services"
        }
    ],
    "sg:phone":"+1 256 551 0123",
    "sg:postcode":"35801",
    "sg:province":"AL",
    "sg:tags":[
        "loan",
        "real estate"
    ],
    "wof:name":"First Federal Bank Mortgage",
    "wof:placetype":"venue"
},
  "geometry": {"coordinates":[-86.588542,34.714023],"type":"Point"}
}