{
  "type": "Feature",
  "properties": {
    "iso:country":"US",
    "sg:address":"2100 18th St S",
    "sg:city":"Birmingham",
    "sg:classifiers":[
        {
            "category":"Education",
            "subcategory":"School",
            "type":"Public Place"
        }
    ],
    "sg:phone":"+1 205 379 2000",
    "sg:postcode":"35209",
    "sg:province":"AL",
    "sg:tags":[
        "executive"
    ],
    "wof:name":"Jefferson County Board Educatn",
    "wof:placetype":"venue"
},
  "geometry": {"coordinates":[-86.79272,33.48744],"type":"Point"}
}