{
  "type": "Feature",
  "properties": {
    "addr:full":"612 15th St E Tuscaloosa AL 35401",
    "addr:housenumber":"612",
    "addr:postcode":"35401",
    "addr:street":"15Th St",
    "iso:country":"US",
    "sg:address":"612 15th St E",
    "sg:city":"Tuscaloosa",
    "sg:classifiers":[
        {
            "category":"Retail",
            "subcategory":"Portrait Studio",
            "type":"Services"
        }
    ],
    "sg:phone":"+1 205 633 0148",
    "sg:postcode":"35401",
    "sg:province":"AL",
    "sg:tags":[
        "photographer"
    ],
    "wof:name":"Olan Mills Portrait Studio",
    "wof:placetype":"venue"
},
  "geometry": {"coordinates":[-87.527512,33.197397],"type":"Point"}
}