{
  "type": "Feature",
  "properties": {
    "iso:country":"US",
    "sg:address":"105 Alabama Ave W",
    "sg:city":"Lafayette",
    "sg:classifiers":[
        {
            "category":"Government",
            "subcategory":"Jail",
            "type":"Public Place"
        }
    ],
    "sg:phone":"+1 334 864 4336",
    "sg:postcode":"36862",
    "sg:province":"AL",
    "sg:tags":[
        "correctional",
        "institution"
    ],
    "wof:name":"Chambers Cnty Detention Fcilty",
    "wof:placetype":"venue"
},
  "geometry": {"coordinates":[-85.404526,32.899658],"type":"Point"}
}