{
  "type": "Feature",
  "properties": {
    "iso:country":"US",
    "sg:address":"1061 Lake Shore Dr",
    "sg:city":"Cropwell",
    "sg:classifiers":[
        {
            "category":"Professional",
            "type":"Services"
        }
    ],
    "sg:phone":"+1 205 525 5683",
    "sg:postcode":"35054",
    "sg:province":"AL",
    "wof:name":"United Daughters of Confe",
    "wof:placetype":"venue"
},
  "geometry": {"coordinates":[-86.32535900000001,33.475121],"type":"Point"}
}