{
  "type": "Feature",
  "properties": {
    "iso:country":"US",
    "sg:address":"8400 Forest Dr",
    "sg:city":"Foley",
    "sg:classifiers":[
        {
            "category":"Professional",
            "type":"Services"
        }
    ],
    "sg:phone":"+1 251 928 9255",
    "sg:postcode":"36535",
    "sg:province":"AL",
    "wof:name":"Rodney Williamson",
    "wof:placetype":"venue"
},
  "geometry": {"coordinates":[-87.609746,30.346853],"type":"Point"}
}