{
  "type": "Feature",
  "properties": {
    "addr:full":"464 Gilmer Ave Tallassee AL 36078",
    "addr:housenumber":"464",
    "addr:postcode":"36078",
    "addr:street":"Gilmer Ave",
    "iso:country":"US",
    "sg:address":"464 Gilmer Ave",
    "sg:city":"Tallassee",
    "sg:classifiers":[
        {
            "category":"Restaurant",
            "type":"Food & Drink"
        }
    ],
    "sg:menulink":"http://www.allmenus.com/al/tallassee/121020-subway/menu/",
    "sg:phone":"+1 334 283 2247",
    "sg:postcode":"36078",
    "sg:province":"AL",
    "sg:tags":[
        "american",
        "sandwich"
    ],
    "wof:name":"Subway",
    "wof:placetype":"venue"
},
  "geometry": {"coordinates":[-85.90401,32.543078],"type":"Point"}
}