{
  "type": "Feature",
  "properties": {
    "addr:full":"932 Rainbow Dr Gadsden AL 35901",
    "addr:housenumber":"932",
    "addr:postcode":"35901",
    "addr:street":"Rainbow Dr",
    "iso:country":"US",
    "sg:address":"932 Rainbow Dr",
    "sg:city":"Gadsden",
    "sg:classifiers":[
        {
            "category":"Shopping",
            "type":"Retail Goods"
        },
        {
            "category":"Shopping",
            "subcategory":"Optical Goods",
            "type":"Retail Goods"
        }
    ],
    "sg:phone":"+1 256 543 7011",
    "sg:postcode":"35901",
    "sg:province":"AL",
    "sg:tags":[
        "merchandise"
    ],
    "wof:name":"Eyear Optical Inc",
    "wof:placetype":"venue"
},
  "geometry": {"coordinates":[-86.00436000000001,33.997877],"type":"Point"}
}