{
  "type": "Feature",
  "properties": {
    "iso:country":"US",
    "sg:address":"2869 Pleasant Valley Rd",
    "sg:city":"Mobile",
    "sg:classifiers":[
        {
            "category":"Professional",
            "subcategory":"Research",
            "type":"Services"
        }
    ],
    "sg:phone":"+1 251 479 9205",
    "sg:postcode":"36606",
    "sg:province":"AL",
    "sg:tags":[
        "environmental",
        "ecological"
    ],
    "wof:name":"ACT Laboratory Inc",
    "wof:placetype":"venue"
},
  "geometry": {"coordinates":[-88.110859,30.661543],"type":"Point"}
}