{
  "type": "Feature",
  "properties": {
    "iso:country":"US",
    "sg:address":"1108 E Lafayette St",
    "sg:city":"Dothan",
    "sg:classifiers":[
        {
            "category":"Manufacturing",
            "subcategory":"Tools & Machinery",
            "type":"Manufacturing & Wholesale Goods"
        }
    ],
    "sg:phone":"+1 334 794 3897",
    "sg:postcode":"36301",
    "sg:province":"AL",
    "sg:tags":[
        "equipment",
        "mfg"
    ],
    "wof:name":"B Mets",
    "wof:placetype":"venue"
},
  "geometry": {"coordinates":[-85.376009,31.218945],"type":"Point"}
}