{
  "type": "Feature",
  "properties": {
    "iso:country":"US",
    "sg:address":"1710 Alabama Ave",
    "sg:city":"Jasper",
    "sg:classifiers":[
        {
            "category":"Government",
            "subcategory":"Office",
            "type":"Public Place"
        }
    ],
    "sg:phone":"+1 205 387 1879",
    "sg:postcode":"35501",
    "sg:province":"AL",
    "sg:tags":[
        "federal"
    ],
    "wof:name":"Natural Resources Conservation",
    "wof:placetype":"venue"
},
  "geometry": {"coordinates":[-87.27468500000001,33.834758],"type":"Point"}
}