{
  "type": "Feature",
  "properties": {
    "addr:full":"111 Jack Fendley Dr Oneonta AL 35121",
    "addr:housenumber":"111",
    "addr:postcode":"35121",
    "addr:street":"Jack Fendley Dr",
    "iso:country":"US",
    "sg:address":"111 Jack Fendley Dr",
    "sg:city":"Oneonta",
    "sg:classifiers":[
        {
            "category":"Social Services",
            "type":"Services"
        }
    ],
    "sg:phone":"+1 205 625 4476",
    "sg:postcode":"35121",
    "sg:province":"AL",
    "sg:tags":[
        "organization",
        "welfare"
    ],
    "wof:name":"Senior Citizen's Ctr",
    "wof:placetype":"venue"
},
  "geometry": {"coordinates":[-86.46831400000001,33.947386],"type":"Point"}
}