{
  "type": "Feature",
  "properties": {
    "addr:full":"901 Tulip Poplar Ln Birmingham AL 35244",
    "addr:housenumber":"901",
    "addr:postcode":"35244",
    "addr:street":"Tulip Poplar Ln",
    "iso:country":"US",
    "sg:address":"901 Tulip Poplar Ln",
    "sg:city":"Birmingham",
    "sg:classifiers":[
        {
            "category":"Wholesale",
            "subcategory":"Groceries",
            "type":"Manufacturing & Wholesale Goods"
        }
    ],
    "sg:phone":"+1 205 988 0730",
    "sg:postcode":"35244",
    "sg:province":"AL",
    "sg:tags":[
        "general"
    ],
    "wof:name":"US Foodservice",
    "wof:placetype":"venue"
},
  "geometry": {"coordinates":[-86.807588,33.353937],"type":"Point"}
}