{
  "type": "Feature",
  "properties": {
    "iso:country":"US",
    "sg:address":"1171 Huffman Rd",
    "sg:city":"Birmingham",
    "sg:classifiers":[
        {
            "category":"Restaurant",
            "type":"Food & Drink"
        }
    ],
    "sg:phone":"+1 205 853 9926",
    "sg:postcode":"35215",
    "sg:province":"AL",
    "sg:tags":[
        "eating"
    ],
    "wof:name":"Pete S Sneaky Hot Dogs",
    "wof:placetype":"venue"
},
  "geometry": {"coordinates":[-86.687359,33.612195],"type":"Point"}
}