{
  "type": "Feature",
  "properties": {
    "iso:country":"US",
    "sg:address":"3366 State Rte 20",
    "sg:city":"Decatur",
    "sg:classifiers":[
        {
            "category":"Professional",
            "subcategory":"Business Services",
            "type":"Services"
        }
    ],
    "sg:phone":"+1 256 301 1910",
    "sg:postcode":"35601",
    "sg:province":"AL",
    "sg:tags":[
        "electrical",
        "system",
        "power"
    ],
    "wof:name":"B & H Ind Electrical Mntnc",
    "wof:placetype":"venue"
},
  "geometry": {"coordinates":[-87.064392,34.619997],"type":"Point"}
}