{
  "type": "Feature",
  "properties": {
    "addr:full":"2233 Mc Burney Dr Florence AL 35630",
    "addr:housenumber":"2233",
    "addr:postcode":"35630",
    "addr:street":"Mc Burney Dr",
    "iso:country":"US",
    "sg:address":"2233 Mc Burney Dr",
    "sg:city":"Florence",
    "sg:classifiers":[
        {
            "category":"Organizations",
            "subcategory":"Community Association",
            "type":"Services"
        }
    ],
    "sg:phone":"+1 256 768 2700",
    "sg:postcode":"35630",
    "sg:province":"AL",
    "wof:name":"Pta Alabama Congress",
    "wof:placetype":"venue"
},
  "geometry": {"coordinates":[-87.682149,34.831239],"type":"Point"}
}