{
  "type": "Feature",
  "properties": {
    "iso:country":"US",
    "sg:address":"815 Florentine Dr",
    "sg:city":"Birmingham",
    "sg:classifiers":[
        {
            "category":"Retail",
            "subcategory":"Repair Shop",
            "type":"Services"
        },
        {
            "category":"Professional",
            "subcategory":"Business Services",
            "type":"Services"
        }
    ],
    "sg:phone":"+1 205 853 3455",
    "sg:postcode":"35215",
    "sg:province":"AL",
    "sg:tags":[
        "embroidery"
    ],
    "wof:name":"Lock S Monogramming Inc",
    "wof:placetype":"venue"
},
  "geometry": {"coordinates":[-86.67826,33.61386],"type":"Point"}
}