{
  "type": "Feature",
  "properties": {
    "iso:country":"US",
    "sg:address":"605 E Washington St",
    "sg:city":"Demopolis",
    "sg:classifiers":[
        {
            "category":"Home & Garden",
            "subcategory":"Carpets & Floor Coverings",
            "type":"Retail Goods"
        }
    ],
    "sg:phone":"+1 334 289 6993",
    "sg:postcode":"36732",
    "sg:province":"AL",
    "wof:name":"Carpet Alley",
    "wof:placetype":"venue"
},
  "geometry": {"coordinates":[-87.831017,32.517405],"type":"Point"}
}