{
  "type": "Feature",
  "properties": {
    "addr:full":"410 Paxton Ave Gadsden AL 35905",
    "addr:housenumber":"410",
    "addr:postcode":"35905",
    "addr:street":"Paxton Ave",
    "iso:country":"US",
    "sg:address":"410 Paxton Ave",
    "sg:city":"Gadsden",
    "sg:classifiers":[
        {
            "category":"Organizations",
            "subcategory":"Labor Organization",
            "type":"Services"
        }
    ],
    "sg:phone":"+1 256 492 3502",
    "sg:postcode":"35905",
    "sg:province":"AL",
    "wof:name":"Uswa",
    "wof:placetype":"venue"
},
  "geometry": {"coordinates":[-85.932104,33.965752],"type":"Point"}
}