{
  "type": "Feature",
  "properties": {
    "iso:country":"US",
    "sg:address":"1084 N Brindlee Mountain Pkwy",
    "sg:city":"Arab",
    "sg:classifiers":[
        {
            "category":"Building & Trades",
            "subcategory":"Equipment Rental",
            "type":"Services"
        },
        {
            "category":"Shopping",
            "subcategory":"Music",
            "type":"Retail Goods"
        }
    ],
    "sg:phone":"+1 256 586 1939",
    "sg:postcode":"35016",
    "sg:province":"AL",
    "sg:tags":[
        "video",
        "disc",
        "cassette",
        "tape"
    ],
    "wof:name":"Arab T V & Video Rental",
    "wof:placetype":"venue"
},
  "geometry": {"coordinates":[-86.503086,34.33137],"type":"Point"}
}