{
  "type": "Feature",
  "properties": {
    "addr:full":"3521 65th Ave Tuscaloosa AL 35401",
    "addr:housenumber":"3521",
    "addr:postcode":"35401",
    "addr:street":"65Th Ave",
    "iso:country":"US",
    "sg:address":"3521 65th Ave",
    "sg:city":"Tuscaloosa",
    "sg:classifiers":[
        {
            "category":"Freight",
            "type":"Transportation"
        }
    ],
    "sg:phone":"+1 205 752 2408",
    "sg:postcode":"35401",
    "sg:province":"AL",
    "sg:tags":[
        "operator",
        "excavation",
        "trucking",
        "local",
        "contractor"
    ],
    "wof:name":"L C Harris Landfill",
    "wof:placetype":"venue"
},
  "geometry": {"coordinates":[-87.61814699999999,33.179342],"type":"Point"}
}