{
  "type": "Feature",
  "properties": {
    "iso:country":"US",
    "sg:address":"4113 Eva Rd",
    "sg:city":"Eva",
    "sg:classifiers":[
        {
            "category":"Banks & Credit Unions",
            "subcategory":"Bank",
            "type":"Services"
        }
    ],
    "sg:phone":"+1 256 796 2201",
    "sg:postcode":"35621",
    "sg:province":"AL",
    "wof:name":"Eva Bank",
    "wof:placetype":"venue"
},
  "geometry": {"coordinates":[-86.759337,34.331591],"type":"Point"}
}