{
  "type": "Feature",
  "properties": {
    "iso:country":"US",
    "sg:address":"11227 Co Rd 157",
    "sg:city":"Moulton",
    "sg:classifiers":[
        {
            "category":"Shopping",
            "subcategory":"Used Merchandise",
            "type":"Retail Goods"
        }
    ],
    "sg:phone":"+1 256 974 0709",
    "sg:postcode":"35650",
    "sg:province":"AL",
    "sg:tags":[
        "pawnbroker"
    ],
    "wof:name":"Alabama Title Pawn",
    "wof:placetype":"venue"
},
  "geometry": {"coordinates":[-87.271581,34.478672],"type":"Point"}
}