{
  "type": "Feature",
  "properties": {
    "addr:full":"1000 Leighton Ave Anniston AL 36207",
    "addr:housenumber":"1000",
    "addr:postcode":"36207",
    "addr:street":"Leighton Ave",
    "iso:country":"US",
    "sg:address":"1000 Leighton Ave",
    "sg:city":"Anniston",
    "sg:classifiers":[
        {
            "category":"Social Services",
            "subcategory":"Child Care",
            "type":"Services"
        }
    ],
    "sg:phone":"+1 256 236 4123",
    "sg:postcode":"36207",
    "sg:province":"AL",
    "sg:tags":[
        "kindergarten",
        "academic",
        "school"
    ],
    "wof:name":"Grace Episcopal Pre School",
    "wof:placetype":"venue"
},
  "geometry": {"coordinates":[-85.825062,33.65799],"type":"Point"}
}