{
  "type": "Feature",
  "properties": {
    "iso:country":"US",
    "sg:address":"3820 Harrison Rd",
    "sg:city":"Montgomery",
    "sg:classifiers":[
        {
            "category":"Professional",
            "subcategory":"Detective & Security Services",
            "type":"Services"
        }
    ],
    "sg:phone":"+1 334 272 8859",
    "sg:postcode":"36109",
    "sg:province":"AL",
    "sg:tags":[
        "car"
    ],
    "wof:name":"Action Security",
    "wof:placetype":"venue"
},
  "geometry": {"coordinates":[-86.244637,32.367057],"type":"Point"}
}