{
  "type": "Feature",
  "properties": {
    "iso:country":"US",
    "sg:address":"6754 Taylor Cir",
    "sg:city":"Montgomery",
    "sg:classifiers":[
        {
            "category":"Professional",
            "subcategory":"Accounting & Tax Preparation",
            "type":"Services"
        }
    ],
    "sg:phone":"+1 334 270 3234",
    "sg:postcode":"36117",
    "sg:province":"AL",
    "sg:tags":[
        "consultant"
    ],
    "wof:name":"River Tree Systems",
    "wof:placetype":"venue"
},
  "geometry": {"coordinates":[-86.175329,32.347174],"type":"Point"}
}