{
  "type": "Feature",
  "properties": {
    "addr:full":"4468 Center Point Rd Pinson AL 35126",
    "addr:housenumber":"4468",
    "addr:postcode":"35126",
    "addr:street":"Center Point Rd",
    "iso:country":"US",
    "sg:address":"4468 Center Point Rd",
    "sg:city":"Pinson",
    "sg:classifiers":[
        {
            "category":"Restaurant",
            "type":"Food & Drink"
        }
    ],
    "sg:phone":"+1 205 680 5225",
    "sg:postcode":"35126",
    "sg:province":"AL",
    "wof:name":"Jack's",
    "wof:placetype":"venue"
},
  "geometry": {"coordinates":[-86.6828,33.688801],"type":"Point"}
}