{
  "type": "Feature",
  "properties": {
    "addr:full":"263 Dexter Ave Mobile AL 36604",
    "addr:housenumber":"263",
    "addr:postcode":"36604",
    "addr:street":"Dexter Ave",
    "iso:country":"US",
    "sg:address":"263 Dexter Ave",
    "sg:city":"Mobile",
    "sg:classifiers":[
        {
            "category":"Wholesale",
            "subcategory":"Home Furnishings",
            "type":"Manufacturing & Wholesale Goods"
        }
    ],
    "sg:phone":"+1 251 476 6518",
    "sg:postcode":"36604",
    "sg:province":"AL",
    "sg:tags":[
        "interior",
        "candle",
        "whole",
        "sale",
        "gift"
    ],
    "wof:name":"Hidgifts",
    "wof:placetype":"venue"
},
  "geometry": {"coordinates":[-88.070933,30.677569],"type":"Point"}
}