{
  "type": "Feature",
  "properties": {
    "addr:full":"143 Co Rd 104 Prattville AL 36066",
    "addr:housenumber":"143",
    "addr:postcode":"36066",
    "addr:street":"Co Rd 104",
    "iso:country":"US",
    "sg:address":"143 Co Rd 104",
    "sg:city":"Prattville",
    "sg:classifiers":[
        {
            "category":"Professional",
            "subcategory":"Management & Consulting",
            "type":"Services"
        }
    ],
    "sg:phone":"+1 334 358 4760",
    "sg:postcode":"36066",
    "sg:province":"AL",
    "sg:tags":[
        "consultant",
        "waste"
    ],
    "wof:name":"EGS Inc",
    "wof:placetype":"venue"
},
  "geometry": {"coordinates":[-86.453141,32.572245],"type":"Point"}
}