{
  "type": "Feature",
  "properties": {
    "iso:country":"US",
    "sg:address":"6604 Walt Dr",
    "sg:city":"Birmingham",
    "sg:classifiers":[
        {
            "category":"Freight",
            "type":"Transportation"
        }
    ],
    "sg:phone":"+1 205 991 8427",
    "sg:postcode":"35242",
    "sg:province":"AL",
    "sg:tags":[
        "general"
    ],
    "wof:name":"Uncle Bobs Storage",
    "wof:placetype":"venue"
},
  "geometry": {"coordinates":[-86.665145,33.414023],"type":"Point"}
}