{
  "type": "Feature",
  "properties": {
    "iso:country":"US",
    "sg:address":"500 Crawford Rd",
    "sg:city":"Opelika",
    "sg:classifiers":[
        {
            "category":"Insurance",
            "subcategory":"Hazard Insurance",
            "type":"Services"
        }
    ],
    "sg:phone":"+1 334 705 0185",
    "sg:postcode":"36804",
    "sg:province":"AL",
    "sg:tags":[
        "bond"
    ],
    "wof:name":"MVW Enterprises Inc",
    "wof:placetype":"venue"
},
  "geometry": {"coordinates":[-85.36267,32.616805],"type":"Point"}
}