{
  "type": "Feature",
  "properties": {
    "addr:full":"2013 Rainbow Dr Gadsden AL 35901",
    "addr:housenumber":"2013",
    "addr:postcode":"35901",
    "addr:street":"Rainbow Dr",
    "iso:country":"US",
    "sg:address":"2013 Rainbow Dr",
    "sg:city":"Gadsden",
    "sg:classifiers":[
        {
            "category":"Utilities",
            "subcategory":"Mobile Phone",
            "type":"Services"
        }
    ],
    "sg:phone":"+1 256 481 2355",
    "sg:postcode":"35901",
    "sg:province":"AL",
    "sg:tags":[
        "telephone",
        "cellular"
    ],
    "wof:name":"Corr Wireless",
    "wof:placetype":"venue"
},
  "geometry": {"coordinates":[-86.016677,33.973777],"type":"Point"}
}