{
  "type": "Feature",
  "properties": {
    "iso:country":"US",
    "sg:address":"4121 Carmichael Ct",
    "sg:city":"Montgomery",
    "sg:classifiers":[
        {
            "category":"Organizations",
            "subcategory":"Professional Association",
            "type":"Services"
        }
    ],
    "sg:phone":"+1 334 260 2902",
    "sg:postcode":"36106",
    "sg:province":"AL",
    "sg:website":"www.arello.com",
    "wof:name":"A Rello",
    "wof:placetype":"venue"
},
  "geometry": {"coordinates":[-86.238516,32.357571],"type":"Point"}
}