{
  "type": "Feature",
  "properties": {
    "addr:full":"12831 Brandon Ln Madison AL 35756",
    "addr:housenumber":"12831",
    "addr:postcode":"35756",
    "addr:street":"Brandon Ln",
    "iso:country":"US",
    "sg:address":"12831 Brandon Ln",
    "sg:city":"Madison",
    "sg:classifiers":[
        {
            "category":"Building & Trades",
            "subcategory":"Construction",
            "type":"Services"
        }
    ],
    "sg:phone":"+1 256 426 8034",
    "sg:postcode":"35756",
    "sg:province":"AL",
    "sg:tags":[
        "home",
        "improvement"
    ],
    "wof:name":"Performance Home Restoration",
    "wof:placetype":"venue"
},
  "geometry": {"coordinates":[-86.79273000000001,34.739715],"type":"Point"}
}