{
  "type": "Feature",
  "properties": {
    "iso:country":"US",
    "sg:address":"2585 Sparkman Dr NW",
    "sg:city":"Huntsville",
    "sg:classifiers":[
        {
            "category":"Health Services",
            "subcategory":"Medical Lab",
            "type":"Services"
        }
    ],
    "sg:phone":"+1 256 852 6161",
    "sg:postcode":"35810",
    "sg:province":"AL",
    "wof:name":"Family Dentistry",
    "wof:placetype":"venue"
},
  "geometry": {"coordinates":[-86.59848100000001,34.763296],"type":"Point"}
}