{
  "type": "Feature",
  "properties": {
    "addr:full":"1906 Rainbow Dr Gadsden AL 35901",
    "addr:housenumber":"1906",
    "addr:postcode":"35901",
    "addr:street":"Rainbow Dr",
    "iso:country":"US",
    "sg:address":"1906 Rainbow Dr",
    "sg:city":"Gadsden",
    "sg:classifiers":[
        {
            "category":"Shopping",
            "subcategory":"Shoes",
            "type":"Retail Goods"
        }
    ],
    "sg:phone":"+1 256 549 1264",
    "sg:postcode":"35901",
    "sg:province":"AL",
    "sg:tags":[
        "shoe",
        "store"
    ],
    "wof:name":"Rainbow Shoes & Accessories",
    "wof:placetype":"venue"
},
  "geometry": {"coordinates":[-86.0141,33.975241],"type":"Point"}
}