{
  "type": "Feature",
  "properties": {
    "iso:country":"US",
    "sg:address":"8224 Co Rd 36",
    "sg:city":"Altoona",
    "sg:classifiers":[
        {
            "category":"Education",
            "subcategory":"School",
            "type":"Public Place"
        }
    ],
    "sg:phone":"+1 205 466 5604",
    "sg:postcode":"35952",
    "sg:province":"AL",
    "wof:name":"Bible Way Christian Academy",
    "wof:placetype":"venue"
},
  "geometry": {"coordinates":[-86.37604,34.106027],"type":"Point"}
}