{
  "type": "Feature",
  "properties": {
    "iso:country":"US",
    "sg:address":"6605 W Jefferson Rd",
    "sg:city":"Quinton",
    "sg:classifiers":[
        {
            "category":"Organizations",
            "subcategory":"Religious Organization",
            "type":"Services"
        }
    ],
    "sg:phone":"+1 205 674 5555",
    "sg:postcode":"35130",
    "sg:province":"AL",
    "sg:tags":[
        "church"
    ],
    "wof:name":"New Life Worship Ctr",
    "wof:placetype":"venue"
},
  "geometry": {"coordinates":[-87.061179,33.646991],"type":"Point"}
}