{
  "type": "Feature",
  "properties": {
    "iso:country":"US",
    "sg:address":"2819 3rd St",
    "sg:city":"Montgomery",
    "sg:classifiers":[
        {
            "category":"Personal",
            "subcategory":"Beauty Salon",
            "type":"Services"
        }
    ],
    "sg:phone":"+1 334 288 0552",
    "sg:postcode":"36108",
    "sg:province":"AL",
    "sg:tags":[
        "shop"
    ],
    "wof:name":"Braids Stylist",
    "wof:placetype":"venue"
},
  "geometry": {"coordinates":[-86.344423,32.335111],"type":"Point"}
}