{
  "type": "Feature",
  "properties": {
    "iso:country":"US",
    "sg:address":"8 Main St",
    "sg:city":"Headland",
    "sg:classifiers":[
        {
            "category":"Shopping",
            "subcategory":"Gifts & Souvenirs",
            "type":"Retail Goods"
        }
    ],
    "sg:phone":"+1 334 693 4747",
    "sg:postcode":"36345",
    "sg:province":"AL",
    "sg:tags":[
        "shop"
    ],
    "wof:name":"Imagrations Gift & Craft Shop",
    "wof:placetype":"venue"
},
  "geometry": {"coordinates":[-85.34289,31.352545],"type":"Point"}
}