{
  "type": "Feature",
  "properties": {
    "iso:country":"US",
    "sg:address":"404 14th St SE",
    "sg:city":"Cullman",
    "sg:classifiers":[
        {
            "category":"Professional",
            "subcategory":"Management & Consulting",
            "type":"Services"
        }
    ],
    "sg:phone":"+1 256 737 5089",
    "sg:postcode":"35055",
    "sg:province":"AL",
    "sg:tags":[
        "personal",
        "household",
        "retail",
        "product"
    ],
    "wof:name":"Nationwide Specialty Pdts LLC",
    "wof:placetype":"venue"
},
  "geometry": {"coordinates":[-86.83134099999999,34.165531],"type":"Point"}
}