{
  "type": "Feature",
  "properties": {
    "iso:country":"US",
    "sg:address":"5124 Troy Hwy",
    "sg:city":"Montgomery",
    "sg:classifiers":[
        {
            "category":"Retail",
            "subcategory":"Repair Shop",
            "type":"Services"
        },
        {
            "category":"Shopping",
            "subcategory":"Bicycles & Sporting Goods",
            "type":"Retail Goods"
        }
    ],
    "sg:phone":"+1 334 281 7676",
    "sg:postcode":"36116",
    "sg:province":"AL",
    "sg:tags":[
        "a",
        "taxidermist",
        "supply",
        "related",
        "operates",
        "as",
        "taxidermy"
    ],
    "wof:name":"Foster Taxidermy Studio & Sup",
    "wof:placetype":"venue"
},
  "geometry": {"coordinates":[-86.20719200000001,32.302558],"type":"Point"}
}