{
  "type": "Feature",
  "properties": {
    "iso:country":"US",
    "sg:address":"509 E Cummings Ave",
    "sg:city":"Opp",
    "sg:classifiers":[
        {
            "category":"Shopping",
            "subcategory":"Pharmacy",
            "type":"Retail Goods"
        }
    ],
    "sg:phone":"+1 334 493 6563",
    "sg:postcode":"36467",
    "sg:province":"AL",
    "wof:name":"Rite Aid",
    "wof:placetype":"venue"
},
  "geometry": {"coordinates":[-86.25338600000001,31.280454],"type":"Point"}
}