{
  "type": "Feature",
  "properties": {
    "iso:country":"US",
    "sg:address":"425 Argosy Rd",
    "sg:city":"Arab",
    "sg:classifiers":[
        {
            "category":"Manufacturing",
            "subcategory":"Tools & Machinery",
            "type":"Manufacturing & Wholesale Goods"
        }
    ],
    "sg:phone":"+1 256 586 8051",
    "sg:postcode":"35016",
    "sg:province":"AL",
    "sg:tags":[
        "repair",
        "industrial",
        "mfg",
        "die",
        "machine",
        "special"
    ],
    "wof:name":"C N C Systems Inc",
    "wof:placetype":"venue"
},
  "geometry": {"coordinates":[-86.435687,34.339726],"type":"Point"}
}