{
  "type": "Feature",
  "properties": {
    "iso:country":"US",
    "sg:address":"4424 Florence Blvd",
    "sg:city":"Florence",
    "sg:classifiers":[
        {
            "category":"Autos & Motor Vehicles",
            "subcategory":"Boat Sales",
            "type":"Retail Goods"
        }
    ],
    "sg:phone":"+1 256 757 1181",
    "sg:postcode":"35634",
    "sg:province":"AL",
    "sg:tags":[
        "equipment",
        "supply"
    ],
    "wof:name":"EBM Enterprises",
    "wof:placetype":"venue"
},
  "geometry": {"coordinates":[-87.573915,34.848722],"type":"Point"}
}