{
  "type": "Feature",
  "properties": {
    "iso:country":"US",
    "sg:address":"402 Office Park Dr Ste 203",
    "sg:city":"Birmingham",
    "sg:classifiers":[
        {
            "category":"Social Services",
            "subcategory":"Job Training",
            "type":"Services"
        }
    ],
    "sg:phone":"+1 205 408 0600",
    "sg:postcode":"35223",
    "sg:province":"AL",
    "sg:tags":[
        "consultant"
    ],
    "sg:website":"http://www.saundersbusiness.com",
    "wof:name":"Saunders Business Solutions",
    "wof:placetype":"venue"
},
  "geometry": {"coordinates":[-86.777993,33.476721],"type":"Point"}
}