{
  "type": "Feature",
  "properties": {
    "iso:country":"US",
    "sg:address":"3160 Park Cir",
    "sg:city":"Millbrook",
    "sg:classifiers":[
        {
            "category":"Organizations",
            "subcategory":"Professional Association",
            "type":"Services"
        }
    ],
    "sg:phone":"+1 334 285 0085",
    "sg:postcode":"36054",
    "sg:province":"AL",
    "sg:tags":[
        "chambers",
        "commerce"
    ],
    "wof:name":"Millbrook Chamber Of Commerce",
    "wof:placetype":"venue"
},
  "geometry": {"coordinates":[-86.364389,32.476155],"type":"Point"}
}