{
  "type": "Feature",
  "properties": {
    "addr:full":"389 Brentwood Ave Trussville AL 35173",
    "addr:housenumber":"389",
    "addr:postcode":"35173",
    "addr:street":"Brentwood Ave",
    "iso:country":"US",
    "sg:address":"389 Brentwood Ave",
    "sg:city":"Trussville",
    "sg:classifiers":[
        {
            "category":"Professional",
            "type":"Services"
        }
    ],
    "sg:phone":"+1 205 655 9348",
    "sg:postcode":"35173",
    "sg:province":"AL",
    "wof:name":"Asquared Services",
    "wof:placetype":"venue"
},
  "geometry": {"coordinates":[-86.61644800000001,33.626011],"type":"Point"}
}