{
  "type": "Feature",
  "properties": {
    "iso:country":"US",
    "sg:address":"9318 US Hwy 98",
    "sg:city":"Fairhope",
    "sg:classifiers":[
        {
            "category":"Travel",
            "subcategory":"Campground",
            "type":"Entertainment"
        }
    ],
    "sg:phone":"+1 251 928 8233",
    "sg:postcode":"36532",
    "sg:province":"AL",
    "wof:name":"Driftwood RV",
    "wof:placetype":"venue"
},
  "geometry": {"coordinates":[-87.864268,30.421262],"type":"Point"}
}