{
  "type": "Feature",
  "properties": {
    "iso:country":"US",
    "sg:address":"2707 18th Pl S",
    "sg:city":"Birmingham",
    "sg:classifiers":[
        {
            "category":"Wholesale",
            "subcategory":"Machinery & Supplies",
            "type":"Manufacturing & Wholesale Goods"
        }
    ],
    "sg:phone":"+1 205 871 1060",
    "sg:postcode":"35209",
    "sg:province":"AL",
    "sg:tags":[
        "tool"
    ],
    "wof:name":"Applied Machine & Tooling Inc",
    "wof:placetype":"venue"
},
  "geometry": {"coordinates":[-86.790645,33.482879],"type":"Point"}
}