{
  "type": "Feature",
  "properties": {
    "addr:full":"113 Seale Ave Union Springs AL 36089",
    "addr:housenumber":"113",
    "addr:postcode":"36089",
    "addr:street":"Seale Ave Union",
    "iso:country":"US",
    "sg:address":"113 Seale Ave",
    "sg:city":"Union Springs",
    "sg:classifiers":[
        {
            "category":"Professional",
            "type":"Services"
        }
    ],
    "sg:phone":"+1 334 738 2672",
    "sg:postcode":"36089",
    "sg:province":"AL",
    "wof:name":"C & A Raybons Alternative Care",
    "wof:placetype":"venue"
},
  "geometry": {"coordinates":[-85.71874200000001,32.1419],"type":"Point"}
}