{
  "type": "Feature",
  "properties": {
    "iso:country":"US",
    "sg:address":"2100 3rd Ave N",
    "sg:city":"Birmingham",
    "sg:classifiers":[
        {
            "category":"Professional",
            "subcategory":"Lawyer & Legal Services",
            "type":"Services"
        }
    ],
    "sg:phone":"+1 205 250 5000",
    "sg:postcode":"35205",
    "sg:province":"AL",
    "sg:tags":[
        "attorney"
    ],
    "sg:website":"www.arlaw.com",
    "wof:name":"Adams & Reese Lange Simpson",
    "wof:placetype":"venue"
},
  "geometry": {"coordinates":[-86.80415,33.517612],"type":"Point"}
}