{
  "type": "Feature",
  "properties": {
    "addr:full":"241 S Main St Arab AL 35016",
    "addr:housenumber":"241",
    "addr:postcode":"35016",
    "addr:street":"S Main St",
    "iso:country":"US",
    "sg:address":"241 S Main St",
    "sg:city":"Arab",
    "sg:classifiers":[
        {
            "category":"Manufacturing",
            "subcategory":"Petroleum Products",
            "type":"Manufacturing & Wholesale Goods"
        }
    ],
    "sg:phone":"+1 256 586 6885",
    "sg:postcode":"35016",
    "sg:province":"AL",
    "wof:name":"Williams Petroleum Inc",
    "wof:placetype":"venue"
},
  "geometry": {"coordinates":[-86.49596200000001,34.313098],"type":"Point"}
}