{
  "type": "Feature",
  "properties": {
    "addr:full":"2025 Center Point Pkwy Birmingham AL 35215",
    "addr:housenumber":"2025",
    "addr:postcode":"35215",
    "addr:street":"Center Point Pkwy",
    "iso:country":"US",
    "sg:address":"2025 Center Point Pkwy",
    "sg:city":"Birmingham",
    "sg:classifiers":[
        {
            "category":"Shopping",
            "subcategory":"Jewelry",
            "type":"Retail Goods"
        }
    ],
    "sg:phone":"+1 205 853 1665",
    "sg:postcode":"35215",
    "sg:province":"AL",
    "sg:tags":[
        "diamond"
    ],
    "wof:name":"Alabama Wholesale Diamonds",
    "wof:placetype":"venue"
},
  "geometry": {"coordinates":[-86.68362,33.638833],"type":"Point"}
}