{
  "type": "Feature",
  "properties": {
    "iso:country":"US",
    "sg:address":"110 Pelham Rd S",
    "sg:city":"Jacksonville",
    "sg:classifiers":[
        {
            "category":"Personal",
            "subcategory":"Beauty Salon",
            "type":"Services"
        }
    ],
    "sg:phone":"+1 256 435 3334",
    "sg:postcode":"36265",
    "sg:province":"AL",
    "sg:tags":[
        "manicuring"
    ],
    "wof:name":"Serenity Day Spa",
    "wof:placetype":"venue"
},
  "geometry": {"coordinates":[-85.761268,33.810734],"type":"Point"}
}