{
  "type": "Feature",
  "properties": {
    "iso:country":"US",
    "sg:address":"410 Jackson Trace Rd",
    "sg:city":"Talladega",
    "sg:classifiers":[
        {
            "category":"Freight",
            "type":"Transportation"
        }
    ],
    "sg:phone":"+1 256 761 2922",
    "sg:postcode":"35160",
    "sg:province":"AL",
    "sg:tags":[
        "trucking"
    ],
    "wof:name":"Dove Trans",
    "wof:placetype":"venue"
},
  "geometry": {"coordinates":[-86.104756,33.458025],"type":"Point"}
}