{
  "type": "Feature",
  "properties": {
    "iso:country":"US",
    "sg:address":"6521 Highway 69 S",
    "sg:city":"Tuscaloosa",
    "sg:classifiers":[
        {
            "category":"Fast Food",
            "type":"Food & Drink"
        },
        {
            "category":"Bars & Pubs",
            "type":"Food & Drink"
        },
        {
            "category":"Restaurant",
            "type":"Food & Drink"
        },
        {
            "category":"Professional",
            "type":"Services"
        }
    ],
    "sg:phone":"+1 205 345 8580",
    "sg:postcode":"35405",
    "sg:province":"AL",
    "sg:tags":[
        "mexican",
        "take",
        "caterer"
    ],
    "wof:name":"La Fiesta Mexican Grill",
    "wof:placetype":"venue"
},
  "geometry": {"coordinates":[-87.549002,33.155735],"type":"Point"}
}