{
  "type": "Feature",
  "properties": {
    "addr:full":"300 Richard Arrington Jr Blvd N Birmingham AL 35203",
    "addr:housenumber":"300",
    "addr:postcode":"35203",
    "addr:street":"Richard Arrington Jr Blvd N",
    "iso:country":"US",
    "sg:address":"300 Richard Arrington Jr Blvd N",
    "sg:city":"Birmingham",
    "sg:classifiers":[
        {
            "category":"Professional",
            "subcategory":"Lawyer & Legal Services",
            "type":"Services"
        }
    ],
    "sg:phone":"+1 205 458 3979",
    "sg:postcode":"35203",
    "sg:province":"AL",
    "wof:name":"Bert P Taylor",
    "wof:placetype":"venue"
},
  "geometry": {"coordinates":[-86.806141,33.517868],"type":"Point"}
}