{
  "type": "Feature",
  "properties": {
    "iso:country":"US",
    "sg:address":"1409 Short Spruce St",
    "sg:city":"Gadsden",
    "sg:classifiers":[
        {
            "category":"Organizations",
            "subcategory":"Religious Organization",
            "type":"Services"
        }
    ],
    "sg:phone":"+1 256 546 7708",
    "sg:postcode":"35901",
    "sg:province":"AL",
    "sg:tags":[
        "church"
    ],
    "wof:name":"AOH Church Of God Number One",
    "wof:placetype":"venue"
},
  "geometry": {"coordinates":[-86.024472,34.007592],"type":"Point"}
}