{
  "type": "Feature",
  "properties": {
    "addr:full":"226 Snake Hill Rd Trussville AL 35173",
    "addr:housenumber":"226",
    "addr:postcode":"35173",
    "addr:street":"Snake Hill Rd",
    "iso:country":"US",
    "sg:address":"226 Snake Hill Rd",
    "sg:city":"Trussville",
    "sg:classifiers":[
        {
            "category":"Shopping",
            "subcategory":"Gifts & Souvenirs",
            "type":"Retail Goods"
        }
    ],
    "sg:phone":"+1 205 655 4433",
    "sg:postcode":"35173",
    "sg:province":"AL",
    "wof:name":"Daz Originals",
    "wof:placetype":"venue"
},
  "geometry": {"coordinates":[-86.609076,33.635923],"type":"Point"}
}