{
  "type": "Feature",
  "properties": {
    "addr:full":"2700 Pelham Pkwy Pelham AL 35124",
    "addr:housenumber":"2700",
    "addr:postcode":"35124",
    "addr:street":"Pelham Pkwy",
    "iso:country":"US",
    "sg:address":"2700 Pelham Pkwy",
    "sg:city":"Pelham",
    "sg:classifiers":[
        {
            "category":"Social Services",
            "type":"Services"
        }
    ],
    "sg:phone":"+1 205 685 0373",
    "sg:postcode":"35124",
    "sg:province":"AL",
    "sg:tags":[
        "counselor",
        "marriage",
        "family"
    ],
    "wof:name":"Complete Family Pastoral Ctr",
    "wof:placetype":"venue"
},
  "geometry": {"coordinates":[-86.80301799999999,33.310595],"type":"Point"}
}