{
  "type": "Feature",
  "properties": {
    "iso:country":"US",
    "sg:address":"2700 Pelham Pkwy",
    "sg:city":"Pelham",
    "sg:classifiers":[
        {
            "category":"Social Services",
            "type":"Services"
        }
    ],
    "sg:phone":"+1 205 685 0373",
    "sg:postcode":"35124",
    "sg:province":"AL",
    "sg:tags":[
        "counselor",
        "marriage",
        "family"
    ],
    "wof:name":"Complete Family Pastoral Ctr",
    "wof:placetype":"venue"
},
  "geometry": {"coordinates":[-86.803018,33.310595],"type":"Point"}
}