{
  "type": "Feature",
  "properties": {
    "addr:city":"Montgomery",
    "addr:full":"919 Felder Ave Montgomery, Al 36106",
    "addr:house_number":"919",
    "addr:housenumber":"919",
    "addr:phone":"+1 334-264-4222",
    "addr:postcode":"36106",
    "addr:road":"Felder Ave",
    "addr:state":"AL",
    "addr:street":"Felder Ave",
    "iso:country":"US",
    "sg:address":"919 Felder Ave",
    "sg:city":"Montgomery",
    "sg:classifiers":[
        {
            "category":"Museum",
            "type":"Entertainment"
        }
    ],
    "sg:phone":"+1 334 264 4222",
    "sg:postcode":"36106",
    "sg:province":"AL",
    "wof:airports":[
        102527231,
        102525683
    ],
    "wof:name":"Fitzgerald And Fitzgerald Museum",
    "wof:placetype":"venue"
},
  "geometry": {"coordinates":[-86.29266,32.35837],"type":"Point"}
}