{
  "type": "Feature",
  "properties": {
    "iso:country":"US",
    "sg:address":"919 Felder Ave",
    "sg:city":"Montgomery",
    "sg:classifiers":[
        {
            "category":"Museum",
            "type":"Entertainment"
        }
    ],
    "sg:phone":"+1 334 264 4222",
    "sg:postcode":"36106",
    "sg:province":"AL",
    "wof:name":"Fitzgerald & Fitzgerald Museum",
    "wof:placetype":"venue"
},
  "geometry": {"coordinates":[-86.291893,32.35837],"type":"Point"}
}