{
  "type": "Feature",
  "properties": {
    "iso:country":"US",
    "sg:address":"550 Flightline Dr",
    "sg:city":"Dothan",
    "sg:classifiers":[
        {
            "category":"Building & Trades",
            "subcategory":"Equipment Rental",
            "type":"Services"
        }
    ],
    "sg:phone":"+1 334 983 4814",
    "sg:postcode":"36303",
    "sg:province":"AL",
    "sg:tags":[
        "aircraft",
        "leasing",
        "charter"
    ],
    "wof:name":"Dothan Air Charter",
    "wof:placetype":"venue"
},
  "geometry": {"coordinates":[-85.453231,31.318491],"type":"Point"}
}