{
  "type": "Feature",
  "properties": {
    "addr:full":"2014 10th Ave Tuscaloosa AL 35401",
    "addr:housenumber":"2014",
    "addr:postcode":"35401",
    "addr:street":"10Th Ave",
    "iso:country":"US",
    "sg:address":"2014 10th Ave",
    "sg:city":"Tuscaloosa",
    "sg:classifiers":[
        {
            "category":"Real Estate",
            "subcategory":"Real Estate Agent",
            "type":"Services"
        }
    ],
    "sg:phone":"+1 205 345 1233",
    "sg:postcode":"35401",
    "sg:province":"AL",
    "wof:name":"GRI Garrett Realty",
    "wof:placetype":"venue"
},
  "geometry": {"coordinates":[-87.551242,33.192923],"type":"Point"}
}