{
  "type": "Feature",
  "properties": {
    "iso:country":"US",
    "sg:address":"251 N Bayou St",
    "sg:city":"Mobile",
    "sg:classifiers":[
        {
            "category":"Government",
            "subcategory":"Office",
            "type":"Public Place"
        }
    ],
    "sg:phone":"+1 251 690 8868",
    "sg:postcode":"36603",
    "sg:province":"AL",
    "wof:name":"Mobile County Rabies Control",
    "wof:placetype":"venue"
},
  "geometry": {"coordinates":[-88.054996,30.692733],"type":"Point"}
}