{
  "type": "Feature",
  "properties": {
    "iso:country":"US",
    "sg:address":"4712 Clarendon Dr",
    "sg:city":"Mobile",
    "sg:classifiers":[
        {
            "category":"Building & Trades",
            "subcategory":"Plumbing",
            "type":"Services"
        }
    ],
    "sg:phone":"+1 251 660 1005",
    "sg:postcode":"36619",
    "sg:province":"AL",
    "sg:tags":[
        "conditioning",
        "air",
        "system",
        "contractor"
    ],
    "wof:name":"Huff Air Conditioning & Htg",
    "wof:placetype":"venue"
},
  "geometry": {"coordinates":[-88.232854,30.595323],"type":"Point"}
}