{
  "type": "Feature",
  "properties": {
    "iso:country":"US",
    "sg:address":"700 Mohican Cir",
    "sg:city":"Birmingham",
    "sg:classifiers":[
        {
            "category":"Building & Trades",
            "subcategory":"Electrical",
            "type":"Services"
        }
    ],
    "sg:phone":"+1 205 798 0843",
    "sg:postcode":"35214",
    "sg:province":"AL",
    "sg:tags":[
        "electrical",
        "contractor"
    ],
    "wof:name":"BP Electric Co",
    "wof:placetype":"venue"
},
  "geometry": {"coordinates":[-86.88496,33.563293],"type":"Point"}
}