{
  "type": "Feature",
  "properties": {
    "iso:country":"US",
    "sg:address":"4231 Mobile Hwy",
    "sg:city":"Montgomery",
    "sg:classifiers":[
        {
            "category":"Travel",
            "subcategory":"Hotels & Motels",
            "type":"Entertainment"
        }
    ],
    "sg:phone":"+1 334 288 0610",
    "sg:postcode":"36108",
    "sg:province":"AL",
    "wof:name":"Peddlers Inn",
    "wof:placetype":"venue"
},
  "geometry": {"coordinates":[-86.343677,32.330052],"type":"Point"}
}