{
  "type": "Feature",
  "properties": {
    "addr:full":"2030 US Hwy 78 Oxford AL 36203",
    "addr:housenumber":"2030",
    "addr:postcode":"36203",
    "addr:street":"Us Hwy 78",
    "iso:country":"US",
    "sg:address":"2030 US Hwy 78",
    "sg:city":"Oxford",
    "sg:classifiers":[
        {
            "category":"Restaurant",
            "type":"Food & Drink"
        }
    ],
    "sg:phone":"+1 256 831 0096",
    "sg:postcode":"36203",
    "sg:province":"AL",
    "wof:name":"Subway Sandwiches & Salads",
    "wof:placetype":"venue"
},
  "geometry": {"coordinates":[-85.879836,33.593346],"type":"Point"}
}