{
  "type": "Feature",
  "properties": {
    "addr:full":"1414 Overlook Rd Birmingham AL 35209",
    "addr:housenumber":"1414",
    "addr:postcode":"35209",
    "addr:street":"Overlook Rd",
    "iso:country":"US",
    "sg:address":"1414 Overlook Rd",
    "sg:city":"Birmingham",
    "sg:classifiers":[
        {
            "category":"Health Services",
            "subcategory":"Clinic",
            "type":"Services"
        }
    ],
    "sg:phone":"+1 205 871 8440",
    "sg:postcode":"35209",
    "sg:province":"AL",
    "wof:name":"Key Occupational Health Svcs",
    "wof:placetype":"venue"
},
  "geometry": {"coordinates":[-86.800922,33.468439],"type":"Point"}
}