{
  "type": "Feature",
  "properties": {
    "iso:country":"US",
    "sg:address":"2222 Nabors Rd SW",
    "sg:city":"Birmingham",
    "sg:classifiers":[
        {
            "category":"Freight",
            "type":"Transportation"
        }
    ],
    "sg:phone":"+1 205 925 6587",
    "sg:postcode":"35211",
    "sg:province":"AL",
    "sg:tags":[
        "operator",
        "local",
        "trucking"
    ],
    "wof:name":"Bill Hintons Trckg Inc A Corp",
    "wof:placetype":"venue"
},
  "geometry": {"coordinates":[-86.872023,33.460948],"type":"Point"}
}