{
  "type": "Feature",
  "properties": {
    "iso:country":"US",
    "sg:address":"9757 US Hwy 43",
    "sg:city":"Killen",
    "sg:classifiers":[
        {
            "category":"Shopping",
            "subcategory":"Used Merchandise",
            "type":"Retail Goods"
        },
        {
            "category":"Food & Beverages",
            "subcategory":"Groceries & Convenience Stores",
            "type":"Retail Goods"
        }
    ],
    "sg:phone":"+1 256 757 4321",
    "sg:postcode":"35645",
    "sg:province":"AL",
    "sg:tags":[
        "flea",
        "market"
    ],
    "wof:name":"J & M's Variety Flea Market",
    "wof:placetype":"venue"
},
  "geometry": {"coordinates":[-87.51479999999999,34.988148],"type":"Point"}
}