{
  "type": "Feature",
  "properties": {
    "iso:country":"US",
    "sg:address":"2012 Veterans Memorial Dr",
    "sg:city":"Birmingham",
    "sg:classifiers":[
        {
            "category":"Shopping",
            "subcategory":"Department Store",
            "type":"Retail Goods"
        }
    ],
    "sg:phone":"+1 205 798 0808",
    "sg:postcode":"35214",
    "sg:province":"AL",
    "wof:name":"Peebles",
    "wof:placetype":"venue"
},
  "geometry": {"coordinates":[-86.90797000000001,33.574417],"type":"Point"}
}