{
  "type": "Feature",
  "properties": {
    "addr:full":"13699 Co Rd 379 Valley AL 36854",
    "addr:housenumber":"13699;379",
    "addr:postcode":"36854",
    "addr:street":"Co Rd",
    "iso:country":"US",
    "sg:address":"13699 Co Rd 379",
    "sg:city":"Valley",
    "sg:classifiers":[
        {
            "category":"Professional",
            "type":"Services"
        }
    ],
    "sg:phone":"+1 334 749 1019",
    "sg:postcode":"36854",
    "sg:province":"AL",
    "wof:name":"Phillip V Wood Jr",
    "wof:placetype":"venue"
},
  "geometry": {"coordinates":[-85.15084299999999,32.738864],"type":"Point"}
}