{
  "type": "Feature",
  "properties": {
    "iso:country":"US",
    "sg:address":"766 E University Dr",
    "sg:city":"Auburn",
    "sg:classifiers":[
        {
            "category":"Organizations",
            "subcategory":"Religious Organization",
            "type":"Services"
        }
    ],
    "sg:phone":"+1 334 887 3782",
    "sg:postcode":"36830",
    "sg:province":"AL",
    "sg:website":"www.parkway-auburn.org",
    "wof:name":"Parkway Baptist Church",
    "wof:placetype":"venue"
},
  "geometry": {"coordinates":[-85.46822400000001,32.585233],"type":"Point"}
}