{
  "type": "Feature",
  "properties": {
    "addr:full":"419 E Laurel St Scottsboro AL 35768",
    "addr:housenumber":"419",
    "addr:postcode":"35768",
    "addr:street":"E Laurel St",
    "iso:country":"US",
    "sg:address":"419 E Laurel St",
    "sg:city":"Scottsboro",
    "sg:classifiers":[
        {
            "category":"Professional",
            "subcategory":"Accounting & Tax Preparation",
            "type":"Services"
        }
    ],
    "sg:phone":"+1 256 259 0831",
    "sg:postcode":"35768",
    "sg:province":"AL",
    "sg:tags":[
        "return",
        "filing"
    ],
    "wof:name":"Howton's Tax Svc",
    "wof:placetype":"venue"
},
  "geometry": {"coordinates":[-86.031057,34.672896],"type":"Point"}
}