{
  "type": "Feature",
  "properties": {
    "addr:full":"2428 6th Ave S Birmingham AL 35233",
    "addr:housenumber":"2428",
    "addr:postcode":"35233",
    "addr:street":"6Th Ave S",
    "iso:country":"US",
    "sg:address":"2428 6th Ave S",
    "sg:city":"Birmingham",
    "sg:classifiers":[
        {
            "category":"Manufacturing",
            "subcategory":"Tools & Machinery",
            "type":"Manufacturing & Wholesale Goods"
        },
        {
            "category":"Home & Garden",
            "subcategory":"Household Appliances",
            "type":"Retail Goods"
        },
        {
            "category":"Building & Trades",
            "subcategory":"Electrical",
            "type":"Services"
        },
        {
            "category":"Home & Garden",
            "subcategory":"Kitchen Supply",
            "type":"Retail Goods"
        }
    ],
    "sg:phone":"+1 205 252 0076",
    "sg:postcode":"35233",
    "sg:province":"AL",
    "sg:tags":[
        "electrician",
        "equipment-wholesale",
        "utensil",
        "ice",
        "range",
        "cookware",
        "ovens-dealers",
        "making",
        "manufacturer"
    ],
    "wof:name":"Bresco",
    "wof:placetype":"venue"
},
  "geometry": {"coordinates":[-86.794775,33.509828],"type":"Point"}
}