{
  "type": "Feature",
  "properties": {
    "iso:country":"US",
    "sg:address":"26961 John T Reid Pkwy",
    "sg:city":"Scottsboro",
    "sg:classifiers":[
        {
            "category":"Building & Trades",
            "subcategory":"Construction",
            "type":"Services"
        }
    ],
    "sg:phone":"+1 256 259 2569",
    "sg:postcode":"35768",
    "sg:province":"AL",
    "sg:tags":[
        "downspouts",
        "gutter"
    ],
    "wof:name":"T J's Metal Mfg",
    "wof:placetype":"venue"
},
  "geometry": {"coordinates":[-85.98449,34.698204],"type":"Point"}
}