{
  "type": "Feature",
  "properties": {
    "addr:full":"200 Bob Wallace Ave SW Huntsville AL 35801",
    "addr:housenumber":"200",
    "addr:postcode":"35801",
    "addr:street":"Bob Wallace Ave Sw",
    "iso:country":"US",
    "sg:address":"200 Bob Wallace Ave SW",
    "sg:city":"Huntsville",
    "sg:classifiers":[
        {
            "category":"Health Services",
            "subcategory":"Doctor",
            "type":"Services"
        }
    ],
    "sg:phone":"+1 256 539 6634",
    "sg:postcode":"35801",
    "sg:province":"AL",
    "sg:tags":[
        "dentist"
    ],
    "wof:name":"Ross Rehfeld DMD",
    "wof:placetype":"venue"
},
  "geometry": {"coordinates":[-86.577192,34.712657],"type":"Point"}
}