{
  "type": "Feature",
  "properties": {
    "addr:full":"767 US Hwy 31 Alabaster AL 35007",
    "addr:housenumber":"767",
    "addr:postcode":"35007",
    "addr:street":"Us Hwy 31",
    "iso:country":"US",
    "sg:address":"767 US Hwy 31",
    "sg:city":"Alabaster",
    "sg:classifiers":[
        {
            "category":"Wholesale",
            "subcategory":"Toys & Hobbies",
            "type":"Manufacturing & Wholesale Goods"
        }
    ],
    "sg:phone":"+1 205 663 2717",
    "sg:postcode":"35007",
    "sg:province":"AL",
    "sg:tags":[
        "firework"
    ],
    "wof:name":"Noodie's Spectacular Fireworks",
    "wof:placetype":"venue"
},
  "geometry": {"coordinates":[-86.784769,33.210836],"type":"Point"}
}