{
  "type": "Feature",
  "properties": {
    "iso:country":"US",
    "sg:address":"3705 Pleasant Hill Rd",
    "sg:city":"Wetumpka",
    "sg:classifiers":[
        {
            "category":"Building & Trades",
            "subcategory":"Plumbing",
            "type":"Services"
        }
    ],
    "sg:phone":"+1 334 541 5224",
    "sg:postcode":"36092",
    "sg:province":"AL",
    "sg:tags":[
        "contractor"
    ],
    "wof:name":"TNT Air Cndtioning Liabilities",
    "wof:placetype":"venue"
},
  "geometry": {"coordinates":[-86.073307,32.628354],"type":"Point"}
}