{
  "type": "Feature",
  "properties": {
    "iso:country":"US",
    "sg:address":"607 Dusy St",
    "sg:city":"Dothan",
    "sg:classifiers":[
        {
            "category":"Restaurant",
            "type":"Food & Drink"
        }
    ],
    "sg:phone":"+1 334 794 2063",
    "sg:postcode":"36301",
    "sg:province":"AL",
    "wof:name":"Carribean Nights",
    "wof:placetype":"venue"
},
  "geometry": {"coordinates":[-85.394454,31.215783],"type":"Point"}
}