{
  "type": "Feature",
  "properties": {
    "iso:country":"US",
    "sg:address":"5051 Newburn Rd",
    "sg:city":"Eight Mile",
    "sg:classifiers":[
        {
            "category":"Organizations",
            "subcategory":"Religious Organization",
            "type":"Services"
        }
    ],
    "sg:phone":"+1 251 649 6419",
    "sg:postcode":"36613",
    "sg:province":"AL",
    "wof:name":"Chas M Couey",
    "wof:placetype":"venue"
},
  "geometry": {"coordinates":[-88.22574400000001,30.795754],"type":"Point"}
}