{
  "type": "Feature",
  "properties": {
    "iso:country":"US",
    "sg:address":"108 E Tuscaloosa St",
    "sg:city":"Florence",
    "sg:classifiers":[
        {
            "category":"Local Transit",
            "type":"Transportation"
        }
    ],
    "sg:phone":"+1 256 740 6900",
    "sg:postcode":"35630",
    "sg:province":"AL",
    "sg:tags":[
        "limousine"
    ],
    "wof:name":"D C Limousine",
    "wof:placetype":"venue"
},
  "geometry": {"coordinates":[-87.676337,34.803283],"type":"Point"}
}