{
  "type": "Feature",
  "properties": {
    "addr:full":"150 8th Ave N Birmingham AL 35204",
    "addr:housenumber":"150",
    "addr:postcode":"35204",
    "addr:street":"8Th Ave N",
    "iso:country":"US",
    "sg:address":"150 8th Ave N",
    "sg:city":"Birmingham",
    "sg:classifiers":[
        {
            "category":"Professional",
            "subcategory":"Management & Consulting",
            "type":"Services"
        }
    ],
    "sg:phone":"+1 205 324 0641",
    "sg:postcode":"35204",
    "sg:province":"AL",
    "wof:name":"Birmingham Housing Authority",
    "wof:placetype":"venue"
},
  "geometry": {"coordinates":[-86.833737,33.514067],"type":"Point"}
}