{
  "type": "Feature",
  "properties": {
    "iso:country":"US",
    "sg:address":"272 Oscar Patterson Rd",
    "sg:city":"Meridianville",
    "sg:classifiers":[
        {
            "category":"Building & Trades",
            "subcategory":"Electrical",
            "type":"Services"
        }
    ],
    "sg:phone":"+1 256 828 6226",
    "sg:postcode":"35759",
    "sg:province":"AL",
    "sg:tags":[
        "residential",
        "commercial",
        "work",
        "electrical"
    ],
    "wof:name":"Cherokee Electric",
    "wof:placetype":"venue"
},
  "geometry": {"coordinates":[-86.510267,34.880685],"type":"Point"}
}