{
  "type": "Feature",
  "properties": {
    "addr:full":"562 Cahaba Valley Rd Pelham AL 35124",
    "addr:housenumber":"562",
    "addr:postcode":"35124",
    "addr:street":"Cahaba Valley Rd",
    "iso:country":"US",
    "sg:address":"562 Cahaba Valley Rd",
    "sg:city":"Pelham",
    "sg:phone":"+1 205 403 0456",
    "sg:postcode":"35124",
    "sg:province":"AL",
    "sg:tags":[
        "oil"
    ],
    "wof:name":"Higginbotham Oil Co",
    "wof:placetype":"venue"
},
  "geometry": {"coordinates":[-86.783455,33.334936],"type":"Point"}
}