{
  "type": "Feature",
  "properties": {
    "addr:full":"415 Almon Ave Tuscumbia AL 35674",
    "addr:housenumber":"415",
    "addr:postcode":"35674",
    "addr:street":"Almon Ave",
    "iso:country":"US",
    "sg:address":"415 Almon Ave",
    "sg:city":"Tuscumbia",
    "sg:classifiers":[
        {
            "category":"Professional",
            "type":"Services"
        }
    ],
    "sg:phone":"+1 256 381 3004",
    "sg:postcode":"35674",
    "sg:province":"AL",
    "wof:name":"Kevin D Manning",
    "wof:placetype":"venue"
},
  "geometry": {"coordinates":[-87.709068,34.737504],"type":"Point"}
}