{
  "type": "Feature",
  "properties": {
    "iso:country":"US",
    "sg:address":"3124 Waterman Dr SE",
    "sg:city":"Owens Cross Rds",
    "sg:classifiers":[
        {
            "category":"Professional",
            "type":"Services"
        }
    ],
    "sg:phone":"+1 256 512 5615",
    "sg:postcode":"35763",
    "sg:province":"AL",
    "sg:tags":[
        "establishment"
    ],
    "wof:name":"Ximmons Co",
    "wof:placetype":"venue"
},
  "geometry": {"coordinates":[-86.460847,34.661357],"type":"Point"}
}