{
  "type": "Feature",
  "properties": {
    "addr:full":"925 4th St NW Red Bay AL 35582",
    "addr:housenumber":"925",
    "addr:postcode":"35582",
    "addr:street":"4Th St Nw Red Bay",
    "iso:country":"US",
    "sg:address":"925 4th St NW",
    "sg:city":"Red Bay",
    "sg:classifiers":[
        {
            "category":"Health Services",
            "subcategory":"Doctor",
            "type":"Services"
        }
    ],
    "sg:phone":"+1 256 356 9511",
    "sg:postcode":"35582",
    "sg:province":"AL",
    "sg:tags":[
        "physician",
        "surgeon"
    ],
    "wof:name":"Medical Clinic Of Red Bay",
    "wof:placetype":"venue"
},
  "geometry": {"coordinates":[-88.149112,34.45557],"type":"Point"}
}