{
  "type": "Feature",
  "properties": {
    "iso:country":"US",
    "sg:address":"4520 State Rte 68",
    "sg:city":"Cedar Bluff",
    "sg:classifiers":[
        {
            "category":"Autos & Motor Vehicles",
            "subcategory":"Automobile Sales",
            "type":"Retail Goods"
        }
    ],
    "sg:phone":"+1 256 779 5753",
    "sg:postcode":"35959",
    "sg:province":"AL",
    "sg:tags":[
        "car",
        "used",
        "dealer"
    ],
    "wof:name":"G A Bama Used Vehicles & Paint",
    "wof:placetype":"venue"
},
  "geometry": {"coordinates":[-85.605459,34.229965],"type":"Point"}
}