{
  "type": "Feature",
  "properties": {
    "iso:country":"US",
    "sg:address":"242 Co Rd 361",
    "sg:city":"Albertville",
    "sg:classifiers":[
        {
            "category":"Building & Trades",
            "subcategory":"Pest Control",
            "type":"Services"
        }
    ],
    "sg:phone":"+1 256 659 5167",
    "sg:postcode":"35951",
    "sg:province":"AL",
    "wof:name":"Laser Pest Control",
    "wof:placetype":"venue"
},
  "geometry": {"coordinates":[-86.069448,34.38495],"type":"Point"}
}