{
  "type": "Feature",
  "properties": {
    "iso:country":"US",
    "sg:address":"1966 Halls Mill Rd",
    "sg:city":"Mobile",
    "sg:classifiers":[
        {
            "category":"Personal",
            "subcategory":"Beauty Salon",
            "type":"Services"
        }
    ],
    "sg:phone":"+1 251 473 9560",
    "sg:postcode":"36606",
    "sg:province":"AL",
    "sg:tags":[
        "shop"
    ],
    "wof:name":"Undeniable Best",
    "wof:placetype":"venue"
},
  "geometry": {"coordinates":[-88.08505,30.666501],"type":"Point"}
}