{
  "type": "Feature",
  "properties": {
    "iso:country":"US",
    "sg:address":"2481 State Rte 205",
    "sg:city":"Albertville",
    "sg:classifiers":[
        {
            "category":"Professional",
            "subcategory":"Accounting & Tax Preparation",
            "type":"Services"
        }
    ],
    "sg:phone":"+1 256 878 7293",
    "sg:postcode":"35950",
    "sg:province":"AL",
    "sg:tags":[
        "return",
        "filing"
    ],
    "wof:name":"Albertville Business Service",
    "wof:placetype":"venue"
},
  "geometry": {"coordinates":[-86.256008,34.278331],"type":"Point"}
}