{
  "type": "Feature",
  "properties": {
    "iso:country":"US",
    "sg:address":"7265 State Rte 9",
    "sg:city":"Centre",
    "sg:classifiers":[
        {
            "category":"Professional",
            "subcategory":"Accounting & Tax Preparation",
            "type":"Services"
        }
    ],
    "sg:phone":"+1 256 927 5382",
    "sg:postcode":"35960",
    "sg:province":"AL",
    "sg:tags":[
        "accountant"
    ],
    "wof:name":"Goodgame Burleson & Cotton",
    "wof:placetype":"venue"
},
  "geometry": {"coordinates":[-85.611719,34.066092],"type":"Point"}
}