{
  "type": "Feature",
  "properties": {
    "iso:country":"US",
    "sg:address":"3940 Pinson Valley Pkwy",
    "sg:city":"Birmingham",
    "sg:classifiers":[
        {
            "category":"Manufacturing",
            "subcategory":"Printing",
            "type":"Manufacturing & Wholesale Goods"
        }
    ],
    "sg:phone":"+1 205 853 1368",
    "sg:postcode":"35217",
    "sg:province":"AL",
    "sg:tags":[
        "printer"
    ],
    "sg:website":"www.jsprinting.com",
    "wof:name":"J & S Printing",
    "wof:placetype":"venue"
},
  "geometry": {"coordinates":[-86.728552,33.634385],"type":"Point"}
}