{
  "type": "Feature",
  "properties": {
    "iso:country":"US",
    "sg:address":"1200 High Point Rd",
    "sg:city":"Albertville",
    "sg:classifiers":[
        {
            "category":"Food & Beverages",
            "subcategory":"Groceries & Convenience Stores",
            "type":"Retail Goods"
        }
    ],
    "sg:phone":"+1 256 878 5219",
    "sg:postcode":"35950",
    "sg:province":"AL",
    "sg:tags":[
        "station",
        "gasoline"
    ],
    "wof:name":"Fullers Grocery",
    "wof:placetype":"venue"
},
  "geometry": {"coordinates":[-86.223463,34.258219],"type":"Point"}
}