{
  "type": "Feature",
  "properties": {
    "iso:country":"US",
    "sg:address":"1115 Douglas Ave",
    "sg:city":"Brewton",
    "sg:classifiers":[
        {
            "category":"Bars & Pubs",
            "type":"Food & Drink"
        }
    ],
    "sg:phone":"+1 251 809 2702",
    "sg:postcode":"36426",
    "sg:province":"AL",
    "sg:tags":[
        "drinking"
    ],
    "wof:name":"Upper Deck Bar & Grille",
    "wof:placetype":"venue"
},
  "geometry": {"coordinates":[-87.068676,31.124736],"type":"Point"}
}