{
  "type": "Feature",
  "properties": {
    "addr:full":"1915 Rideout Dr NW Huntsville AL 35806",
    "addr:housenumber":"1915",
    "addr:postcode":"35806",
    "addr:street":"Rideout Dr Nw",
    "iso:country":"US",
    "sg:address":"1915 Rideout Dr NW",
    "sg:city":"Huntsville",
    "sg:classifiers":[
        {
            "category":"Real Estate",
            "subcategory":"Real Estate Operator",
            "type":"Services"
        }
    ],
    "sg:phone":"+1 256 830 1046",
    "sg:postcode":"35806",
    "sg:province":"AL",
    "sg:tags":[
        "apartment"
    ],
    "wof:name":"Willow Run Adventist Towers",
    "wof:placetype":"venue"
},
  "geometry": {"coordinates":[-86.66983399999999,34.753728],"type":"Point"}
}