{
  "type": "Feature",
  "properties": {
    "addr:full":"1307 S Commercial Dr Foley AL 36535",
    "addr:housenumber":"1307",
    "addr:postcode":"36535",
    "addr:street":"S Commercial Dr",
    "iso:country":"US",
    "sg:address":"1307 S Commercial Dr",
    "sg:city":"Foley",
    "sg:classifiers":[
        {
            "category":"Shopping",
            "subcategory":"Used Merchandise",
            "type":"Retail Goods"
        }
    ],
    "sg:phone":"+1 251 970 3550",
    "sg:postcode":"36535",
    "sg:province":"AL",
    "sg:tags":[
        "shop",
        "thrift"
    ],
    "wof:name":"Once & Again",
    "wof:placetype":"venue"
},
  "geometry": {"coordinates":[-87.682455,30.392036],"type":"Point"}
}