{
  "type": "Feature",
  "properties": {
    "iso:country":"US",
    "sg:address":"701 21st Ave NW",
    "sg:city":"Birmingham",
    "sg:classifiers":[
        {
            "category":"Shopping",
            "subcategory":"Clothing, Apparel, & Fashions",
            "type":"Retail Goods"
        }
    ],
    "sg:phone":"+1 205 253 6110",
    "sg:postcode":"35215",
    "sg:province":"AL",
    "wof:name":"Cassandras Fashions",
    "wof:placetype":"venue"
},
  "geometry": {"coordinates":[-86.706798,33.639671],"type":"Point"}
}