{
  "type": "Feature",
  "properties": {
    "iso:country":"US",
    "sg:address":"1805 Bessemer Rd",
    "sg:city":"Birmingham",
    "sg:classifiers":[
        {
            "category":"Health Services",
            "subcategory":"Doctor",
            "type":"Services"
        }
    ],
    "sg:phone":"+1 205 925 1116",
    "sg:postcode":"35208",
    "sg:province":"AL",
    "sg:tags":[
        "dentist"
    ],
    "wof:name":"Elvin G Harnsberry DDS",
    "wof:placetype":"venue"
},
  "geometry": {"coordinates":[-86.886363,33.489476],"type":"Point"}
}