{
  "type": "Feature",
  "properties": {
    "iso:country":"US",
    "sg:address":"2960 Zelda Rd",
    "sg:city":"Montgomery",
    "sg:classifiers":[
        {
            "category":"Real Estate",
            "subcategory":"Real Estate Agent",
            "type":"Services"
        }
    ],
    "sg:phone":"+1 334 215 4510",
    "sg:postcode":"36106",
    "sg:province":"AL",
    "wof:name":"Curry Properties Inc",
    "wof:placetype":"venue"
},
  "geometry": {"coordinates":[-86.264858,32.357127],"type":"Point"}
}