{
  "type": "Feature",
  "properties": {
    "addr:full":"16865 N River Shores Rd Northport AL 35475",
    "addr:housenumber":"16865",
    "addr:postcode":"35475",
    "addr:street":"N River Shores Rd",
    "iso:country":"US",
    "sg:address":"16865 N River Shores Rd",
    "sg:city":"Northport",
    "sg:classifiers":[
        {
            "category":"Building & Trades",
            "subcategory":"Cleaning & Sanitation",
            "type":"Services"
        }
    ],
    "sg:phone":"+1 205 333 8217",
    "sg:postcode":"35475",
    "sg:province":"AL",
    "sg:tags":[
        "maintenance"
    ],
    "wof:name":"Professional Cleaning Services",
    "wof:placetype":"venue"
},
  "geometry": {"coordinates":[-87.563496,33.4072],"type":"Point"}
}