{
  "type": "Feature",
  "properties": {
    "iso:country":"US",
    "sg:address":"1551 Springhill Ave",
    "sg:city":"Mobile",
    "sg:classifiers":[
        {
            "category":"Communications",
            "subcategory":"Radio Station",
            "type":"Services"
        }
    ],
    "sg:phone":"+1 251 432 5572",
    "sg:postcode":"36604",
    "sg:province":"AL",
    "sg:tags":[
        "company",
        "broadcasting"
    ],
    "sg:website":"www.wabbam.com",
    "wof:name":"WABB",
    "wof:placetype":"venue"
},
  "geometry": {"coordinates":[-88.073072,30.69241],"type":"Point"}
}