{
  "type": "Feature",
  "properties": {
    "iso:country":"US",
    "sg:address":"120 Butler Sq",
    "sg:city":"Greenville",
    "sg:classifiers":[
        {
            "category":"Shopping",
            "subcategory":"Department Store",
            "type":"Retail Goods"
        },
        {
            "category":"Shopping",
            "subcategory":"Clothing, Apparel, & Fashions",
            "type":"Retail Goods"
        }
    ],
    "sg:phone":"+1 334 382 4945",
    "sg:postcode":"36037",
    "sg:province":"AL",
    "sg:tags":[
        "family"
    ],
    "wof:name":"Goodys Family Clothing Inc",
    "wof:placetype":"venue"
},
  "geometry": {"coordinates":[-86.637009,31.84762],"type":"Point"}
}