{
  "type": "Feature",
  "properties": {
    "iso:country":"US",
    "sg:address":"103 W Scott Ave",
    "sg:city":"Albertville",
    "sg:classifiers":[
        {
            "category":"Building & Trades",
            "subcategory":"Construction",
            "type":"Services"
        }
    ],
    "sg:phone":"+1 256 878 8828",
    "sg:postcode":"35950",
    "sg:province":"AL",
    "sg:tags":[
        "house",
        "contractor"
    ],
    "wof:name":"Ray Kennamer Construction Inc",
    "wof:placetype":"venue"
},
  "geometry": {"coordinates":[-86.20805,34.271112],"type":"Point"}
}