{
  "type": "Feature",
  "properties": {
    "addr:full":"2470 Peeks Hill Rd Ohatchee AL 36271",
    "addr:housenumber":"2470",
    "addr:postcode":"36271",
    "addr:street":"Peeks Hill Rd",
    "iso:country":"US",
    "sg:address":"2470 Peeks Hill Rd",
    "sg:city":"Ohatchee",
    "sg:classifiers":[
        {
            "category":"Building & Trades",
            "subcategory":"Construction",
            "type":"Services"
        }
    ],
    "sg:phone":"+1 256 892 3800",
    "sg:postcode":"36271",
    "sg:province":"AL",
    "sg:tags":[
        "maker",
        "cabinet"
    ],
    "wof:name":"Martin Moulding & Cabinet",
    "wof:placetype":"venue"
},
  "geometry": {"coordinates":[-85.96687799999999,33.852347],"type":"Point"}
}