{
  "type": "Feature",
  "properties": {
    "iso:country":"US",
    "sg:address":"2470 Peeks Hill Rd",
    "sg:city":"Ohatchee",
    "sg:classifiers":[
        {
            "category":"Building & Trades",
            "subcategory":"Construction",
            "type":"Services"
        }
    ],
    "sg:phone":"+1 256 892 3800",
    "sg:postcode":"36271",
    "sg:province":"AL",
    "sg:tags":[
        "maker",
        "cabinet"
    ],
    "wof:name":"Martin Moulding & Cabinet",
    "wof:placetype":"venue"
},
  "geometry": {"coordinates":[-85.966878,33.852347],"type":"Point"}
}