{
  "type": "Feature",
  "properties": {
    "iso:country":"US",
    "sg:address":"969 Co Rd 643",
    "sg:city":"Cullman",
    "sg:classifiers":[
        {
            "category":"Farming",
            "subcategory":"Livestock Farm",
            "type":"Manufacturing & Wholesale Goods"
        }
    ],
    "sg:phone":"+1 256 739 6366",
    "sg:postcode":"35055",
    "sg:province":"AL",
    "sg:tags":[
        "beef",
        "feedlot",
        "cattle"
    ],
    "wof:name":"Max Brannan",
    "wof:placetype":"venue"
},
  "geometry": {"coordinates":[-86.721332,34.142137],"type":"Point"}
}