{
  "type": "Feature",
  "properties": {
    "iso:country":"US",
    "sg:address":"1857 Mount Olive Rd",
    "sg:city":"Gardendale",
    "sg:classifiers":[
        {
            "category":"Personal",
            "subcategory":"Beauty Salon",
            "type":"Services"
        }
    ],
    "sg:phone":"+1 205 631 3302",
    "sg:postcode":"35071",
    "sg:province":"AL",
    "wof:name":"Bridewell Beauty Shop",
    "wof:placetype":"venue"
},
  "geometry": {"coordinates":[-86.823677,33.669115],"type":"Point"}
}