{
  "type": "Feature",
  "properties": {
    "iso:country":"US",
    "sg:address":"1101 Viking Dr",
    "sg:city":"Jasper",
    "sg:classifiers":[
        {
            "category":"Insurance",
            "subcategory":"Insurance Agent",
            "type":"Services"
        }
    ],
    "sg:phone":"+1 205 387 0531",
    "sg:postcode":"35501",
    "sg:province":"AL",
    "wof:name":"Liberty National Life Ins Co",
    "wof:placetype":"venue"
},
  "geometry": {"coordinates":[-87.261279,33.834563],"type":"Point"}
}