{
  "type": "Feature",
  "properties": {
    "addr:full":"744 Murphy Hill Rd Toney AL 35773",
    "addr:housenumber":"744",
    "addr:postcode":"35773",
    "addr:street":"Murphy Hill Rd",
    "iso:country":"US",
    "sg:address":"744 Murphy Hill Rd",
    "sg:city":"Toney",
    "sg:classifiers":[
        {
            "category":"Manufacturing",
            "subcategory":"Apparel",
            "type":"Manufacturing & Wholesale Goods"
        }
    ],
    "sg:phone":"+1 256 828 2783",
    "sg:postcode":"35773",
    "sg:province":"AL",
    "sg:tags":[
        "mfr",
        "accessory"
    ],
    "wof:name":"Neo Outdoor Products",
    "wof:placetype":"venue"
},
  "geometry": {"coordinates":[-86.634052,34.900132],"type":"Point"}
}