{
  "type": "Feature",
  "properties": {
    "iso:country":"US",
    "sg:address":"4418 9th Ave",
    "sg:city":"Birmingham",
    "sg:classifiers":[
        {
            "category":"Real Estate",
            "subcategory":"Real Estate Agent",
            "type":"Services"
        }
    ],
    "sg:phone":"+1 205 591 9064",
    "sg:postcode":"35224",
    "sg:province":"AL",
    "sg:tags":[
        "authorities",
        "housing"
    ],
    "wof:name":"Birmingham Housing Authority",
    "wof:placetype":"venue"
},
  "geometry": {"coordinates":[-86.921959,33.503809],"type":"Point"}
}