{
  "type": "Feature",
  "properties": {
    "iso:country":"US",
    "sg:address":"3158 Queenstown Rd",
    "sg:city":"Trussville",
    "sg:classifiers":[
        {
            "category":"Professional",
            "subcategory":"Business Services",
            "type":"Services"
        }
    ],
    "sg:phone":"+1 205 655 1978",
    "sg:postcode":"35173",
    "sg:province":"AL",
    "wof:name":"Birmingham Wired Technologies",
    "wof:placetype":"venue"
},
  "geometry": {"coordinates":[-86.609039,33.595409],"type":"Point"}
}