{
  "type": "Feature",
  "properties": {
    "iso:country":"US",
    "sg:address":"909 2nd Ave E",
    "sg:city":"Oneonta",
    "sg:classifiers":[
        {
            "category":"Shopping",
            "subcategory":"Tobacco",
            "type":"Retail Goods"
        }
    ],
    "sg:phone":"+1 205 274 2960",
    "sg:postcode":"35121",
    "sg:province":"AL",
    "sg:tags":[
        "product"
    ],
    "wof:name":"Tobacco Discount Depot",
    "wof:placetype":"venue"
},
  "geometry": {"coordinates":[-86.468675,33.951445],"type":"Point"}
}