{
  "type": "Feature",
  "properties": {
    "iso:country":"US",
    "sg:address":"760 State Rte 30",
    "sg:city":"Eufaula",
    "sg:classifiers":[
        {
            "category":"Building & Trades",
            "subcategory":"Construction",
            "type":"Services"
        },
        {
            "category":"Government",
            "subcategory":"Office",
            "type":"Public Place"
        }
    ],
    "sg:phone":"+1 334 687 3161",
    "sg:postcode":"36027",
    "sg:province":"AL",
    "sg:tags":[
        "state",
        "program",
        "highway",
        "maintenance"
    ],
    "wof:name":"Transportation Alabama Dept",
    "wof:placetype":"venue"
},
  "geometry": {"coordinates":[-85.227738,31.876557],"type":"Point"}
}