{
  "type": "Feature",
  "properties": {
    "iso:country":"US",
    "sg:address":"1150 Pinson St",
    "sg:city":"Birmingham",
    "sg:classifiers":[
        {
            "category":"Building & Trades",
            "subcategory":"Locksmith",
            "type":"Services"
        }
    ],
    "sg:phone":"+1 205 216 2388",
    "sg:postcode":"35217",
    "sg:province":"AL",
    "sg:tags":[
        "key"
    ],
    "wof:name":"A A Alpha Locksmith",
    "wof:placetype":"venue"
},
  "geometry": {"coordinates":[-86.776016,33.580878],"type":"Point"}
}