{
  "type": "Feature",
  "properties": {
    "iso:country":"US",
    "sg:address":"5082 Shelby Dr",
    "sg:city":"Birmingham",
    "sg:classifiers":[
        {
            "category":"Shopping",
            "subcategory":"Gifts & Souvenirs",
            "type":"Retail Goods"
        }
    ],
    "sg:phone":"+1 205 995 0460",
    "sg:postcode":"35242",
    "sg:province":"AL",
    "wof:name":"Chattels Gifts & Decor",
    "wof:placetype":"venue"
},
  "geometry": {"coordinates":[-86.68365799999999,33.403445],"type":"Point"}
}