{
  "type": "Feature",
  "properties": {
    "iso:country":"US",
    "sg:address":"2241 US Hwy 78",
    "sg:city":"Oxford",
    "sg:classifiers":[
        {
            "category":"Professional",
            "subcategory":"Engineering",
            "type":"Services"
        }
    ],
    "sg:phone":"+1 256 835 1155",
    "sg:postcode":"36203",
    "sg:province":"AL",
    "sg:tags":[
        "engineer"
    ],
    "wof:name":"Gallet & Assoc",
    "wof:placetype":"venue"
},
  "geometry": {"coordinates":[-85.880084,33.593173],"type":"Point"}
}