{
  "type": "Feature",
  "properties": {
    "addr:full":"217 7th St N Clanton AL 35045",
    "addr:housenumber":"217",
    "addr:postcode":"35045",
    "addr:street":"7Th St N",
    "iso:country":"US",
    "sg:address":"217 7th St N",
    "sg:city":"Clanton",
    "sg:classifiers":[
        {
            "category":"Manufacturing",
            "subcategory":"Printing",
            "type":"Manufacturing & Wholesale Goods"
        }
    ],
    "sg:phone":"+1 205 280 3944",
    "sg:postcode":"35045",
    "sg:province":"AL",
    "sg:tags":[
        "printer"
    ],
    "wof:name":"Bee Hive",
    "wof:placetype":"venue"
},
  "geometry": {"coordinates":[-86.63158300000001,32.839939],"type":"Point"}
}