{
  "type": "Feature",
  "properties": {
    "iso:country":"US",
    "sg:address":"1568 Monterey Pl",
    "sg:city":"Mobile",
    "sg:classifiers":[
        {
            "category":"Professional",
            "type":"Services"
        }
    ],
    "sg:phone":"+1 251 476 7567",
    "sg:postcode":"36604",
    "sg:province":"AL",
    "wof:name":"Charles M Phillips Jr",
    "wof:placetype":"venue"
},
  "geometry": {"coordinates":[-88.074584,30.684098],"type":"Point"}
}