{
  "type": "Feature",
  "properties": {
    "iso:country":"US",
    "sg:address":"2116 Bone Dry Rd",
    "sg:city":"Warrior",
    "sg:classifiers":[
        {
            "category":"Wholesale",
            "subcategory":"Farm Supplies",
            "type":"Manufacturing & Wholesale Goods"
        }
    ],
    "sg:phone":"+1 205 647 4700",
    "sg:postcode":"35180",
    "sg:province":"AL",
    "sg:tags":[
        "livestock"
    ],
    "wof:name":"Landmark Services",
    "wof:placetype":"venue"
},
  "geometry": {"coordinates":[-86.761725,33.791885],"type":"Point"}
}