{
  "type": "Feature",
  "properties": {
    "iso:country":"US",
    "sg:address":"1308 N Main St",
    "sg:city":"Wedowee",
    "sg:classifiers":[
        {
            "category":"Food & Beverages",
            "subcategory":"Groceries & Convenience Stores",
            "type":"Retail Goods"
        }
    ],
    "sg:phone":"+1 256 357 9108",
    "sg:postcode":"36278",
    "sg:province":"AL",
    "wof:name":"Wedowee Citgo",
    "wof:placetype":"venue"
},
  "geometry": {"coordinates":[-85.487926,33.317042],"type":"Point"}
}