{
  "type": "Feature",
  "properties": {
    "addr:full":"1349 Hueytown Rd Bessemer AL 35023",
    "addr:housenumber":"1349",
    "addr:postcode":"35023",
    "addr:street":"Hueytown Rd",
    "iso:country":"US",
    "sg:address":"1349 Hueytown Rd",
    "sg:city":"Bessemer",
    "sg:classifiers":[
        {
            "category":"Restaurant",
            "type":"Food & Drink"
        },
        {
            "category":"Ice Cream",
            "type":"Food & Drink"
        }
    ],
    "sg:menulink":"http://www.allmenus.com/al/birmingham/164722-dairy-queen/menu/",
    "sg:phone":"+1 205 491 2798",
    "sg:postcode":"35023",
    "sg:province":"AL",
    "sg:tags":[
        "burger",
        "american",
        "ice",
        "cream"
    ],
    "wof:name":"Dairy Queen",
    "wof:placetype":"venue"
},
  "geometry": {"coordinates":[-86.996523,33.446601],"type":"Point"}
}