{
  "type": "Feature",
  "properties": {
    "iso:country":"US",
    "sg:address":"721 Herbert Clark Rd",
    "sg:city":"Toney",
    "sg:phone":"+1 256 859 2728",
    "sg:postcode":"35773",
    "sg:province":"AL",
    "sg:tags":[
        "farm",
        "cotton"
    ],
    "wof:name":"Micky Smith",
    "wof:placetype":"venue"
},
  "geometry": {"coordinates":[-86.726106,34.908714],"type":"Point"}
}