{
  "type": "Feature",
  "properties": {
    "iso:country":"US",
    "sg:address":"4020 Old Greensboro Rd",
    "sg:city":"Tuscaloosa",
    "sg:classifiers":[
        {
            "category":"Home & Garden",
            "subcategory":"Garden Supply",
            "type":"Retail Goods"
        }
    ],
    "sg:phone":"+1 205 758 7939",
    "sg:postcode":"35405",
    "sg:province":"AL",
    "wof:name":"Countryside Nursery",
    "wof:placetype":"venue"
},
  "geometry": {"coordinates":[-87.54604399999999,33.169253],"type":"Point"}
}