{
  "type": "Feature",
  "properties": {
    "iso:country":"US",
    "sg:address":"525 Harper Springs Rd",
    "sg:city":"Sylacauga",
    "sg:classifiers":[
        {
            "category":"Organizations",
            "subcategory":"Religious Organization",
            "type":"Services"
        }
    ],
    "sg:phone":"+1 256 249 3949",
    "sg:postcode":"35150",
    "sg:province":"AL",
    "sg:tags":[
        "church"
    ],
    "wof:name":"Harper Spring Baptist Church",
    "wof:placetype":"venue"
},
  "geometry": {"coordinates":[-86.225137,33.203943],"type":"Point"}
}