{
  "type": "Feature",
  "properties": {
    "iso:country":"US",
    "sg:address":"205 NW 1st St",
    "sg:city":"Summerdale",
    "sg:classifiers":[
        {
            "category":"Personal",
            "subcategory":"Beauty Salon",
            "type":"Services"
        }
    ],
    "sg:phone":"+1 251 988 1969",
    "sg:postcode":"36580",
    "sg:province":"AL",
    "wof:name":"Generations",
    "wof:placetype":"venue"
},
  "geometry": {"coordinates":[-87.700299,30.489088],"type":"Point"}
}