{
  "type": "Feature",
  "properties": {
    "addr:full":"8816 US Hwy 431 Roanoke AL 36274",
    "addr:housenumber":"8816",
    "addr:postcode":"36274",
    "addr:street":"Us Hwy 431",
    "iso:country":"US",
    "sg:address":"8816 US Hwy 431",
    "sg:city":"Roanoke",
    "sg:classifiers":[
        {
            "category":"Food & Beverages",
            "subcategory":"Groceries & Convenience Stores",
            "type":"Retail Goods"
        }
    ],
    "sg:phone":"+1 334 863 4944",
    "sg:postcode":"36274",
    "sg:province":"AL",
    "wof:name":"Rock Stand Quick Stop",
    "wof:placetype":"venue"
},
  "geometry": {"coordinates":[-85.41727899999999,33.209939],"type":"Point"}
}