{
  "type": "Feature",
  "properties": {
    "iso:country":"US",
    "sg:address":"1145 Co Rd 94",
    "sg:city":"Hamilton",
    "sg:classifiers":[
        {
            "category":"Manufacturing",
            "subcategory":"Apparel",
            "type":"Manufacturing & Wholesale Goods"
        }
    ],
    "sg:phone":"+1 205 921 9923",
    "sg:postcode":"35570",
    "sg:province":"AL",
    "sg:tags":[
        "shirt"
    ],
    "wof:name":"Textile Projects",
    "wof:placetype":"venue"
},
  "geometry": {"coordinates":[-88.058203,34.16786],"type":"Point"}
}