{
  "type": "Feature",
  "properties": {
    "iso:country":"US",
    "sg:address":"101 Glen Abbey Way",
    "sg:city":"Alabaster",
    "sg:classifiers":[
        {
            "category":"Wholesale",
            "subcategory":"Apparel",
            "type":"Manufacturing & Wholesale Goods"
        }
    ],
    "sg:phone":"+1 205 620 5086",
    "sg:postcode":"35007",
    "sg:province":"AL",
    "sg:tags":[
        "clothing"
    ],
    "wof:name":"Thoroughbred Classics LLC",
    "wof:placetype":"venue"
},
  "geometry": {"coordinates":[-86.796039,33.255719],"type":"Point"}
}