{
  "type": "Feature",
  "properties": {
    "iso:country":"US",
    "sg:address":"1520 Francis Ave SW",
    "sg:city":"Birmingham",
    "sg:classifiers":[
        {
            "category":"Social Services",
            "type":"Services"
        }
    ],
    "sg:phone":"+1 205 942 1285",
    "sg:postcode":"35211",
    "sg:province":"AL",
    "wof:name":"Frederick Japal",
    "wof:placetype":"venue"
},
  "geometry": {"coordinates":[-86.854397,33.467087],"type":"Point"}
}