{
  "type": "Feature",
  "properties": {
    "addr:full":"308 6th St S Oneonta AL 35121",
    "addr:housenumber":"308",
    "addr:postcode":"35121",
    "addr:street":"6Th St S",
    "iso:country":"US",
    "sg:address":"308 6th St S",
    "sg:city":"Oneonta",
    "sg:classifiers":[
        {
            "category":"Personal",
            "subcategory":"Tanning Parlor",
            "type":"Services"
        }
    ],
    "sg:phone":"+1 205 274 8826",
    "sg:postcode":"35121",
    "sg:province":"AL",
    "sg:tags":[
        "salon"
    ],
    "wof:name":"Sunsational Tans",
    "wof:placetype":"venue"
},
  "geometry": {"coordinates":[-86.467209,33.944612],"type":"Point"}
}