{
  "type": "Feature",
  "properties": {
    "iso:country":"US",
    "sg:address":"178 Winchester Rd NE",
    "sg:city":"Huntsville",
    "sg:classifiers":[
        {
            "category":"Wholesale",
            "subcategory":"Electrical",
            "type":"Manufacturing & Wholesale Goods"
        }
    ],
    "sg:phone":"+1 256 337 2520",
    "sg:postcode":"35811",
    "sg:province":"AL",
    "sg:tags":[
        "equipment"
    ],
    "wof:name":"Stephones Car Alarm & ACC",
    "wof:placetype":"venue"
},
  "geometry": {"coordinates":[-86.567911,34.792645],"type":"Point"}
}