{
  "type": "Feature",
  "properties": {
    "addr:full":"228 14th St E Tuscaloosa AL 35401",
    "addr:housenumber":"228",
    "addr:postcode":"35401",
    "addr:street":"14Th St",
    "iso:country":"US",
    "sg:address":"228 14th St E",
    "sg:city":"Tuscaloosa",
    "sg:classifiers":[
        {
            "category":"Health Services",
            "subcategory":"Chiropractor",
            "type":"Services"
        }
    ],
    "sg:phone":"+1 205 345 2009",
    "sg:postcode":"35401",
    "sg:province":"AL",
    "wof:name":"Richardson David Dr",
    "wof:placetype":"venue"
},
  "geometry": {"coordinates":[-87.528792,33.199415],"type":"Point"}
}