{
  "type": "Feature",
  "properties": {
    "addr:full":"1602 W Hobbs St Athens AL 35611",
    "addr:housenumber":"1602",
    "addr:postcode":"35611",
    "addr:street":"W Hobbs St",
    "iso:country":"US",
    "sg:address":"1602 W Hobbs St",
    "sg:city":"Athens",
    "sg:classifiers":[
        {
            "category":"Organizations",
            "subcategory":"Religious Organization",
            "type":"Services"
        }
    ],
    "sg:phone":"+1 256 232 4705",
    "sg:postcode":"35611",
    "sg:province":"AL",
    "sg:tags":[
        "church"
    ],
    "sg:website":"www.westhobbsstreetchurchofchrist.org",
    "wof:name":"Church-Christ West Hobbs St",
    "wof:placetype":"venue"
},
  "geometry": {"coordinates":[-86.989842,34.805215],"type":"Point"}
}