{
  "type": "Feature",
  "properties": {
    "iso:country":"US",
    "sg:address":"339 Persimmon Dr",
    "sg:city":"Auburn",
    "sg:classifiers":[
        {
            "category":"Home & Garden",
            "subcategory":"Home Furnishings",
            "type":"Retail Goods"
        }
    ],
    "sg:phone":"+1 334 826 1702",
    "sg:postcode":"36830",
    "sg:province":"AL",
    "sg:tags":[
        "material"
    ],
    "wof:name":"Elite Shutter Co",
    "wof:placetype":"venue"
},
  "geometry": {"coordinates":[-85.521696,32.534609],"type":"Point"}
}