{
  "type": "Feature",
  "properties": {
    "iso:country":"US",
    "sg:address":"1605 4th Ter W",
    "sg:city":"Birmingham",
    "sg:classifiers":[
        {
            "category":"Retail",
            "subcategory":"Repair Shop",
            "type":"Services"
        }
    ],
    "sg:phone":"+1 205 785 0963",
    "sg:postcode":"35208",
    "sg:province":"AL",
    "wof:name":"Don Thomason Services",
    "wof:placetype":"venue"
},
  "geometry": {"coordinates":[-86.864417,33.50789],"type":"Point"}
}