{
  "type": "Feature",
  "properties": {
    "iso:country":"US",
    "sg:address":"4537 Dolly Ridge Rd",
    "sg:city":"Birmingham",
    "sg:classifiers":[
        {
            "category":"Education",
            "subcategory":"Special Training",
            "type":"Public Place"
        }
    ],
    "sg:phone":"+1 205 967 3442",
    "sg:postcode":"35243",
    "sg:province":"AL",
    "wof:name":"Richard B Shepard M D",
    "wof:placetype":"venue"
},
  "geometry": {"coordinates":[-86.744319,33.444128],"type":"Point"}
}