{
  "type": "Feature",
  "properties": {
    "iso:country":"US",
    "sg:address":"1103 23rd St N",
    "sg:city":"Pell City",
    "sg:classifiers":[
        {
            "category":"Real Estate",
            "subcategory":"Real Estate Operator",
            "type":"Services"
        }
    ],
    "sg:phone":"+1 205 338 4922",
    "sg:postcode":"35125",
    "sg:province":"AL",
    "sg:tags":[
        "apartment"
    ],
    "wof:name":"Everglades Apartments",
    "wof:placetype":"venue"
},
  "geometry": {"coordinates":[-86.285909,33.600592],"type":"Point"}
}