{
  "type": "Feature",
  "properties": {
    "iso:country":"US",
    "sg:address":"74 Pine Mountain Rd",
    "sg:city":"Remlap",
    "sg:classifiers":[
        {
            "category":"Manufacturing",
            "subcategory":"Building Materials",
            "type":"Manufacturing & Wholesale Goods"
        }
    ],
    "sg:phone":"+1 205 681 3045",
    "sg:postcode":"35133",
    "sg:province":"AL",
    "sg:tags":[
        "cabinet"
    ],
    "wof:name":"C & C Woodworks Inc",
    "wof:placetype":"venue"
},
  "geometry": {"coordinates":[-86.59853,33.815576],"type":"Point"}
}