{
  "type": "Feature",
  "properties": {
    "iso:country":"US",
    "sg:address":"1905 Co Rd 458",
    "sg:city":"Woodland",
    "sg:classifiers":[
        {
            "category":"Organizations",
            "subcategory":"Religious Organization",
            "type":"Services"
        }
    ],
    "sg:phone":"+1 256 449 6499",
    "sg:postcode":"36280",
    "sg:province":"AL",
    "sg:tags":[
        "church"
    ],
    "wof:name":"Providence Baptist Church",
    "wof:placetype":"venue"
},
  "geometry": {"coordinates":[-85.344714,33.40389],"type":"Point"}
}