{
  "type": "Feature",
  "properties": {
    "iso:country":"US",
    "sg:address":"2119 Short Line Dr",
    "sg:city":"Montgomery",
    "sg:classifiers":[
        {
            "category":"Organizations",
            "subcategory":"Professional Association",
            "type":"Services"
        }
    ],
    "sg:phone":"+1 334 271 7555",
    "sg:postcode":"36116",
    "sg:province":"AL",
    "sg:website":"www.acoe.us",
    "wof:name":"Alabama Conference-Educators",
    "wof:placetype":"venue"
},
  "geometry": {"coordinates":[-86.19436,32.332602],"type":"Point"}
}