{
  "type": "Feature",
  "properties": {
    "iso:country":"US",
    "sg:address":"1518 Greensboro Ave",
    "sg:city":"Tuscaloosa",
    "sg:classifiers":[
        {
            "category":"Professional",
            "subcategory":"Advertising",
            "type":"Services"
        }
    ],
    "sg:phone":"+1 205 248 6222",
    "sg:postcode":"35401",
    "sg:province":"AL",
    "wof:name":"Resulting Systems Inc",
    "wof:placetype":"venue"
},
  "geometry": {"coordinates":[-87.564319,33.199849],"type":"Point"}
}