{
  "type": "Feature",
  "properties": {
    "iso:country":"US",
    "sg:address":"496 Shady Pt",
    "sg:city":"Alexander City",
    "sg:classifiers":[
        {
            "category":"Building & Trades",
            "subcategory":"Construction",
            "type":"Services"
        }
    ],
    "sg:phone":"+1 256 825 7655",
    "sg:postcode":"35010",
    "sg:province":"AL",
    "sg:tags":[
        "hanging",
        "painter",
        "contractor"
    ],
    "wof:name":"Welch Painting Contractor",
    "wof:placetype":"venue"
},
  "geometry": {"coordinates":[-85.877496,32.896635],"type":"Point"}
}