{
  "type": "Feature",
  "properties": {
    "iso:country":"US",
    "sg:address":"12335 Bethany Ln",
    "sg:city":"Duncanville",
    "sg:classifiers":[
        {
            "category":"Real Estate",
            "subcategory":"Architect",
            "type":"Services"
        }
    ],
    "sg:phone":"+1 205 758 3203",
    "sg:postcode":"35456",
    "sg:province":"AL",
    "sg:tags":[
        "architectural"
    ],
    "wof:name":"Designs By Delana",
    "wof:placetype":"venue"
},
  "geometry": {"coordinates":[-87.440316,33.076003],"type":"Point"}
}