{
  "type": "Feature",
  "properties": {
    "addr:full":"240 Westchester Dr Madison AL 35758",
    "addr:housenumber":"240",
    "addr:postcode":"35758",
    "addr:street":"Westchester Dr",
    "iso:country":"US",
    "sg:address":"240 Westchester Dr",
    "sg:city":"Madison",
    "sg:classifiers":[
        {
            "category":"Wholesale",
            "subcategory":"Machinery & Supplies",
            "type":"Manufacturing & Wholesale Goods"
        },
        {
            "category":"Wholesale",
            "subcategory":"Hardware",
            "type":"Manufacturing & Wholesale Goods"
        }
    ],
    "sg:phone":"+1 256 772 7300",
    "sg:postcode":"35758",
    "sg:province":"AL",
    "sg:tags":[
        "fastener",
        "industrial"
    ],
    "sg:website":"www.centuryfasteners.com",
    "wof:name":"Century Fasteners Corp",
    "wof:placetype":"venue"
},
  "geometry": {"coordinates":[-86.765962,34.679866],"type":"Point"}
}