{
  "type": "Feature",
  "properties": {
    "addr:full":"8097 Madison Blvd Madison AL 35758",
    "addr:housenumber":"8097",
    "addr:postcode":"35758",
    "addr:street":"Madison Blvd",
    "iso:country":"US",
    "sg:address":"8097 Madison Blvd",
    "sg:city":"Madison",
    "sg:classifiers":[
        {
            "category":"Real Estate",
            "subcategory":"Real Estate Agent",
            "type":"Services"
        }
    ],
    "sg:phone":"+1 256 774 2728",
    "sg:postcode":"35758",
    "sg:province":"AL",
    "wof:name":"Realtysouth HPH Properties",
    "wof:placetype":"venue"
},
  "geometry": {"coordinates":[-86.721141,34.688751],"type":"Point"}
}