{
  "type": "Feature",
  "properties": {
    "addr:full":"131 Jackson Ave Madison AL 35758",
    "addr:housenumber":"131",
    "addr:postcode":"35758",
    "addr:street":"Jackson Ave",
    "iso:country":"US",
    "sg:address":"131 Jackson Ave",
    "sg:city":"Madison",
    "sg:classifiers":[
        {
            "category":"Organizations",
            "subcategory":"Religious Organization",
            "type":"Services"
        }
    ],
    "sg:phone":"+1 256 772 2004",
    "sg:postcode":"35758",
    "sg:province":"AL",
    "wof:name":"Pearl Ministries",
    "wof:placetype":"venue"
},
  "geometry": {"coordinates":[-86.757081,34.686472],"type":"Point"}
}