{
  "type": "Feature",
  "properties": {
    "iso:country":"US",
    "sg:address":"1925 5th Ave N",
    "sg:city":"Bessemer",
    "sg:classifiers":[
        {
            "category":"Retail",
            "subcategory":"Auto Repair",
            "type":"Services"
        }
    ],
    "sg:phone":"+1 205 426 6410",
    "sg:postcode":"35020",
    "sg:province":"AL",
    "sg:tags":[
        "automotive"
    ],
    "wof:name":"Cheese Carburetor Repair Shop",
    "wof:placetype":"venue"
},
  "geometry": {"coordinates":[-86.954808,33.404552],"type":"Point"}
}