{
  "type": "Feature",
  "properties": {
    "addr:full":"28779 Nick Davis Rd Harvest AL 35742",
    "addr:postcode":"28779;35742",
    "addr:street":"Nick Davis Rd",
    "iso:country":"US",
    "sg:address":"28779 Nick Davis Rd",
    "sg:city":"Harvest",
    "sg:classifiers":[
        {
            "category":"Government",
            "subcategory":"Jail",
            "type":"Public Place"
        }
    ],
    "sg:phone":"+1 256 233 4600",
    "sg:postcode":"35742",
    "sg:province":"AL",
    "sg:tags":[
        "correctional",
        "institution"
    ],
    "wof:name":"Limestone Correctional Fcilty",
    "wof:placetype":"venue"
},
  "geometry": {"coordinates":[-86.81403,34.802811],"type":"Point"}
}