{
  "type": "Feature",
  "properties": {
    "addr:full":"150 N Royal St Mobile AL 36602",
    "addr:housenumber":"150",
    "addr:postcode":"36602",
    "addr:street":"N Royal St",
    "iso:country":"US",
    "sg:address":"150 N Royal St",
    "sg:city":"Mobile",
    "sg:classifiers":[
        {
            "category":"Professional",
            "subcategory":"Lawyer & Legal Services",
            "type":"Services"
        }
    ],
    "sg:phone":"+1 334 432 7800",
    "sg:postcode":"36602",
    "sg:province":"AL",
    "wof:name":"Clute & Clements Law Office",
    "wof:placetype":"venue"
},
  "geometry": {"coordinates":[-88.04218299999999,30.695463],"type":"Point"}
}