{
  "type": "Feature",
  "properties": {
    "addr:full":"130 Cedar Cove Dr Pelham AL 35124",
    "addr:housenumber":"130",
    "addr:postcode":"35124",
    "addr:street":"Cedar Cove Dr",
    "iso:country":"US",
    "sg:address":"130 Cedar Cove Dr",
    "sg:city":"Pelham",
    "sg:classifiers":[
        {
            "category":"Restaurant",
            "type":"Food & Drink"
        }
    ],
    "sg:phone":"+1 205 991 0070",
    "sg:postcode":"35124",
    "sg:province":"AL",
    "sg:tags":[
        "eating"
    ],
    "wof:name":"Dominos Pizza",
    "wof:placetype":"venue"
},
  "geometry": {"coordinates":[-86.821217,33.303253],"type":"Point"}
}