{
  "type": "Feature",
  "properties": {
    "iso:country":"US",
    "sg:address":"2104 Chapel Rd",
    "sg:city":"Birmingham",
    "sg:classifiers":[
        {
            "category":"Building & Trades",
            "subcategory":"Construction",
            "type":"Services"
        }
    ],
    "sg:phone":"+1 205 822 0040",
    "sg:postcode":"35226",
    "sg:province":"AL",
    "sg:tags":[
        "contractor"
    ],
    "wof:name":"Matrix Construction Company",
    "wof:placetype":"venue"
},
  "geometry": {"coordinates":[-86.852686,33.397619],"type":"Point"}
}