{
  "type": "Feature",
  "properties": {
    "iso:country":"US",
    "sg:address":"2212 Bide A Wee Dr NE",
    "sg:city":"Huntsville",
    "sg:classifiers":[
        {
            "category":"Wholesale",
            "subcategory":"Durable Goods & Equipment",
            "type":"Manufacturing & Wholesale Goods"
        }
    ],
    "sg:phone":"+1 256 533 7343",
    "sg:postcode":"35801",
    "sg:province":"AL",
    "sg:tags":[
        "representative",
        "manufacturer"
    ],
    "wof:name":"A H & Assoc",
    "wof:placetype":"venue"
},
  "geometry": {"coordinates":[-86.556485,34.747635],"type":"Point"}
}