{
  "type": "Feature",
  "properties": {
    "iso:country":"US",
    "sg:address":"5864 Creel Rd",
    "sg:city":"Theodore",
    "sg:classifiers":[
        {
            "category":"Manufacturing",
            "subcategory":"Tools & Machinery",
            "type":"Manufacturing & Wholesale Goods"
        }
    ],
    "sg:phone":"+1 251 653 9755",
    "sg:postcode":"36582",
    "sg:province":"AL",
    "sg:tags":[
        "machine",
        "mfg",
        "instr",
        "air"
    ],
    "wof:name":"Crown Plastics",
    "wof:placetype":"venue"
},
  "geometry": {"coordinates":[-88.225452,30.567595],"type":"Point"}
}