{
  "type": "Feature",
  "properties": {
    "iso:country":"US",
    "sg:address":"3779 Moore Rd",
    "sg:city":"Grady",
    "sg:classifiers":[
        {
            "category":"Organizations",
            "subcategory":"Religious Organization",
            "type":"Services"
        }
    ],
    "sg:phone":"+1 256 584 7424",
    "sg:postcode":"36036",
    "sg:province":"AL",
    "wof:name":"Community Baptist Church",
    "wof:placetype":"venue"
},
  "geometry": {"coordinates":[-86.077409,32.020624],"type":"Point"}
}