{
  "type": "Feature",
  "properties": {
    "iso:country":"US",
    "sg:address":"1612 3rd St W",
    "sg:city":"Birmingham",
    "sg:classifiers":[
        {
            "category":"Building & Trades",
            "subcategory":"Construction",
            "type":"Services"
        }
    ],
    "sg:phone":"+1 205 854 7539",
    "sg:postcode":"35204",
    "sg:province":"AL",
    "sg:tags":[
        "system",
        "contractor",
        "air conditioning"
    ],
    "wof:name":"Northwest A C & Heat",
    "wof:placetype":"venue"
},
  "geometry": {"coordinates":[-86.840783,33.527028],"type":"Point"}
}