{
  "type": "Feature",
  "properties": {
    "addr:full":"12674 State Rte 33 Moulton AL 35650",
    "addr:housenumber":"12674",
    "addr:postcode":"35650",
    "addr:street":"State Rte 33",
    "iso:country":"US",
    "sg:address":"12674 State Rte 33",
    "sg:city":"Moulton",
    "sg:classifiers":[
        {
            "category":"Personal",
            "subcategory":"Beauty Salon",
            "type":"Services"
        }
    ],
    "sg:phone":"+1 256 974 6695",
    "sg:postcode":"35650",
    "sg:province":"AL",
    "wof:name":"Beauchamp Beauty Shop",
    "wof:placetype":"venue"
},
  "geometry": {"coordinates":[-87.292593,34.453506],"type":"Point"}
}