{
  "type": "Feature",
  "properties": {
    "iso:country":"US",
    "sg:address":"2508 Oakwood Ave NW",
    "sg:city":"Huntsville",
    "sg:classifiers":[
        {
            "category":"Building & Trades",
            "subcategory":"Plumbing",
            "type":"Services"
        }
    ],
    "sg:phone":"+1 256 534 4321",
    "sg:postcode":"35810",
    "sg:province":"AL",
    "sg:tags":[
        "conditioning",
        "air",
        "system",
        "contractor"
    ],
    "wof:name":"Barry's Maintenance Svc",
    "wof:placetype":"venue"
},
  "geometry": {"coordinates":[-86.60910800000001,34.749527],"type":"Point"}
}