{
  "type": "Feature",
  "properties": {
    "iso:country":"US",
    "sg:address":"1313 5th Pl",
    "sg:city":"Birmingham",
    "sg:classifiers":[
        {
            "category":"Organizations",
            "subcategory":"Religious Organization",
            "type":"Services"
        }
    ],
    "sg:phone":"+1 205 798 6010",
    "sg:postcode":"35214",
    "sg:province":"AL",
    "wof:name":"Clinton Patterson",
    "wof:placetype":"venue"
},
  "geometry": {"coordinates":[-86.875587,33.529056],"type":"Point"}
}