{
  "type": "Feature",
  "properties": {
    "iso:country":"US",
    "sg:address":"425 Co Rd 1141",
    "sg:city":"Cullman",
    "sg:classifiers":[
        {
            "category":"Farming",
            "subcategory":"Livestock Farm",
            "type":"Manufacturing & Wholesale Goods"
        }
    ],
    "sg:phone":"+1 256 734 9066",
    "sg:postcode":"35057",
    "sg:province":"AL",
    "sg:tags":[
        "chicken",
        "beef",
        "feedlot",
        "cattle"
    ],
    "wof:name":"Anthony Thompson",
    "wof:placetype":"venue"
},
  "geometry": {"coordinates":[-86.925985,34.208217],"type":"Point"}
}