{
  "type": "Feature",
  "properties": {
    "iso:country":"US",
    "sg:address":"8636 Cox Gap Rd",
    "sg:city":"Boaz",
    "sg:classifiers":[
        {
            "category":"Organizations",
            "subcategory":"Religious Organization",
            "type":"Services"
        }
    ],
    "sg:phone":"+1 256 593 5199",
    "sg:postcode":"35956",
    "sg:province":"AL",
    "wof:name":"Cornerstone Baptist Church",
    "wof:placetype":"venue"
},
  "geometry": {"coordinates":[-86.13229,34.161913],"type":"Point"}
}