{
  "type": "Feature",
  "properties": {
    "addr:full":"888 Co Rd 8 Woodville AL 35776",
    "addr:housenumber":"888",
    "addr:postcode":"35776",
    "addr:street":"Co Rd 8",
    "iso:country":"US",
    "sg:address":"888 Co Rd 8",
    "sg:city":"Woodville",
    "sg:classifiers":[
        {
            "category":"Restaurant",
            "type":"Food & Drink"
        }
    ],
    "sg:phone":"+1 256 587 0335",
    "sg:postcode":"35776",
    "sg:province":"AL",
    "sg:tags":[
        "eating"
    ],
    "wof:name":"Pleasant Groves Restaurant",
    "wof:placetype":"venue"
},
  "geometry": {"coordinates":[-86.175832,34.748875],"type":"Point"}
}