{
  "type": "Feature",
  "properties": {
    "iso:country":"US",
    "sg:address":"136 W Oxmoor Rd",
    "sg:city":"Homewood",
    "sg:classifiers":[
        {
            "category":"Real Estate",
            "subcategory":"Real Estate Agent",
            "type":"Services"
        }
    ],
    "sg:phone":"+1 205 833 1420",
    "sg:postcode":"35209",
    "sg:province":"AL",
    "wof:name":"HUD Home Network",
    "wof:placetype":"venue"
},
  "geometry": {"coordinates":[-86.84123,33.446841],"type":"Point"}
}