{
  "type": "Feature",
  "properties": {
    "iso:country":"US",
    "sg:address":"29279 US Hwy 98",
    "sg:city":"Daphne",
    "sg:classifiers":[
        {
            "category":"Autos & Motor Vehicles",
            "subcategory":"Fuel & Gas Station",
            "type":"Retail Goods"
        }
    ],
    "sg:phone":"+1 251 621 8449",
    "sg:postcode":"36526",
    "sg:province":"AL",
    "sg:tags":[
        "oil"
    ],
    "wof:name":"Lake Forest Shell",
    "wof:placetype":"venue"
},
  "geometry": {"coordinates":[-87.912824,30.644153],"type":"Point"}
}