{
  "type": "Feature",
  "properties": {
    "iso:country":"US",
    "sg:address":"3548 Overton Rd",
    "sg:city":"Birmingham",
    "sg:classifiers":[
        {
            "category":"Organizations",
            "subcategory":"Community Association",
            "type":"Services"
        }
    ],
    "sg:phone":"+1 205 969 2837",
    "sg:postcode":"35223",
    "sg:province":"AL",
    "wof:name":"PHI Delta Kappa of Batheles",
    "wof:placetype":"venue"
},
  "geometry": {"coordinates":[-86.711314,33.48506],"type":"Point"}
}