{
  "type": "Feature",
  "properties": {
    "addr:full":"213 N Main St Tuskegee AL 36083",
    "addr:housenumber":"213",
    "addr:postcode":"36083",
    "addr:street":"N Main St",
    "iso:country":"US",
    "sg:address":"213 N Main St",
    "sg:city":"Tuskegee",
    "sg:classifiers":[
        {
            "category":"Social Services",
            "type":"Services"
        }
    ],
    "sg:phone":"+1 334 724 2609",
    "sg:postcode":"36083",
    "sg:province":"AL",
    "sg:tags":[
        "probation"
    ],
    "wof:name":"Juvenile Probation Agency",
    "wof:placetype":"venue"
},
  "geometry": {"coordinates":[-85.691884,32.425113],"type":"Point"}
}