{
  "type": "Feature",
  "properties": {
    "addr:full":"109 Furr St Mobile AL 36607",
    "addr:housenumber":"109",
    "addr:postcode":"36607",
    "addr:street":"Furr St",
    "iso:country":"US",
    "sg:address":"109 Furr St",
    "sg:city":"Mobile",
    "sg:classifiers":[
        {
            "category":"Home & Garden",
            "subcategory":"Building Materials",
            "type":"Retail Goods"
        }
    ],
    "sg:phone":"+1 251 471 3666",
    "sg:postcode":"36607",
    "sg:province":"AL",
    "wof:name":"Advanced Industrial Coating",
    "wof:placetype":"venue"
},
  "geometry": {"coordinates":[-88.12222199999999,30.701177],"type":"Point"}
}