{
  "type": "Feature",
  "properties": {
    "iso:country":"US",
    "sg:address":"1518 Autumn Wood Dr",
    "sg:city":"Birmingham",
    "sg:classifiers":[
        {
            "category":"Professional",
            "subcategory":"Computer Services",
            "type":"Services"
        }
    ],
    "sg:phone":"+1 205 999 4953",
    "sg:postcode":"35216",
    "sg:province":"AL",
    "wof:name":"Eot Business Solutions",
    "wof:placetype":"venue"
},
  "geometry": {"coordinates":[-86.78891900000001,33.390026],"type":"Point"}
}