{
  "type": "Feature",
  "properties": {
    "addr:full":"2660 Queenstown Rd Birmingham AL 35210",
    "addr:housenumber":"2660",
    "addr:postcode":"35210",
    "addr:street":"Queenstown Rd",
    "iso:country":"US",
    "sg:address":"2660 Queenstown Rd",
    "sg:city":"Birmingham",
    "sg:classifiers":[
        {
            "category":"Wholesale",
            "subcategory":"Hardware",
            "type":"Manufacturing & Wholesale Goods"
        }
    ],
    "sg:phone":"+1 205 833 3390",
    "sg:postcode":"35210",
    "sg:province":"AL",
    "sg:tags":[
        "equipment"
    ],
    "wof:name":"Jamco Inc",
    "wof:placetype":"venue"
},
  "geometry": {"coordinates":[-86.63529699999999,33.579237],"type":"Point"}
}