{
  "type": "Feature",
  "properties": {
    "addr:full":"824 Co Rd 61 Roanoke AL 36274",
    "addr:housenumber":"824;61",
    "addr:postcode":"36274",
    "addr:street":"Co Rd",
    "iso:country":"US",
    "sg:address":"824 Co Rd 61",
    "sg:city":"Roanoke",
    "sg:classifiers":[
        {
            "category":"Professional",
            "subcategory":"Business Services",
            "type":"Services"
        }
    ],
    "sg:phone":"+1 334 863 2458",
    "sg:postcode":"36274",
    "sg:province":"AL",
    "wof:name":"Nelson Interior Design",
    "wof:placetype":"venue"
},
  "geometry": {"coordinates":[-85.403683,33.19777],"type":"Point"}
}