{
  "type": "Feature",
  "properties": {
    "iso:country":"US",
    "sg:address":"15506 US Hwy 29",
    "sg:city":"Brewton",
    "sg:classifiers":[
        {
            "category":"Food & Beverages",
            "subcategory":"Groceries & Convenience Stores",
            "type":"Retail Goods"
        }
    ],
    "sg:phone":"+1 251 809 0066",
    "sg:postcode":"36426",
    "sg:province":"AL",
    "wof:name":"Country Store",
    "wof:placetype":"venue"
},
  "geometry": {"coordinates":[-86.849212,31.152669],"type":"Point"}
}