{
  "type": "Feature",
  "properties": {
    "iso:country":"US",
    "sg:address":"5030 Bradford Blvd NW",
    "sg:city":"Huntsville",
    "sg:classifiers":[
        {
            "category":"Manufacturing",
            "subcategory":"Tools & Machinery",
            "type":"Manufacturing & Wholesale Goods"
        }
    ],
    "sg:phone":"+1 256 704 2461",
    "sg:postcode":"35805",
    "sg:province":"AL",
    "sg:tags":[
        "industry",
        "aerospace"
    ],
    "wof:name":"3 D Research",
    "wof:placetype":"venue"
},
  "geometry": {"coordinates":[-86.663413,34.727193],"type":"Point"}
}