{
  "type": "Feature",
  "properties": {
    "iso:country":"US",
    "sg:address":"307 W Adams St",
    "sg:city":"Dothan",
    "sg:classifiers":[
        {
            "category":"Real Estate",
            "subcategory":"Architect",
            "type":"Services"
        }
    ],
    "sg:phone":"+1 334 712 9721",
    "sg:postcode":"36303",
    "sg:province":"AL",
    "wof:name":"G Mark Pepe",
    "wof:placetype":"venue"
},
  "geometry": {"coordinates":[-85.39714,31.226582],"type":"Point"}
}