{
  "type": "Feature",
  "properties": {
    "iso:country":"US",
    "sg:address":"8935 US Hwy 231",
    "sg:city":"Wetumpka",
    "sg:classifiers":[
        {
            "category":"Government",
            "subcategory":"Office",
            "type":"Public Place"
        }
    ],
    "sg:phone":"+1 334 567 1123",
    "sg:postcode":"36092",
    "sg:province":"AL",
    "wof:name":"Elmore County Circuit Clerk",
    "wof:placetype":"venue"
},
  "geometry": {"coordinates":[-86.19490999999999,32.564371],"type":"Point"}
}