{
  "type": "Feature",
  "properties": {
    "iso:country":"US",
    "sg:address":"1104 Old Hwy 231 N",
    "sg:city":"Troy",
    "sg:classifiers":[
        {
            "category":"Restaurant",
            "type":"Food & Drink"
        }
    ],
    "sg:phone":"+1 334 566 2672",
    "sg:postcode":"36081",
    "sg:province":"AL",
    "sg:tags":[
        "eating"
    ],
    "wof:name":"Pizza Hut",
    "wof:placetype":"venue"
},
  "geometry": {"coordinates":[-86.00172600000001,31.863235],"type":"Point"}
}