{
  "type": "Feature",
  "properties": {
    "addr:full":"412 S Ann St Mobile AL 36604",
    "addr:housenumber":"412",
    "addr:postcode":"36604",
    "addr:street":"S Ann St",
    "iso:country":"US",
    "sg:address":"412 S Ann St",
    "sg:city":"Mobile",
    "sg:classifiers":[
        {
            "category":"Shopping",
            "subcategory":"Florist",
            "type":"Retail Goods"
        }
    ],
    "sg:phone":"+1 251 432 7695",
    "sg:postcode":"36604",
    "sg:province":"AL",
    "wof:name":"Ann Street Flowers & Gifts",
    "wof:placetype":"venue"
},
  "geometry": {"coordinates":[-88.06729799999999,30.675449],"type":"Point"}
}