{
  "type": "Feature",
  "properties": {
    "iso:country":"US",
    "sg:address":"5160 Greystone Way",
    "sg:city":"Birmingham",
    "sg:classifiers":[
        {
            "category":"Professional",
            "subcategory":"Management & Consulting",
            "type":"Services"
        }
    ],
    "sg:phone":"+1 205 991 6995",
    "sg:postcode":"35242",
    "sg:province":"AL",
    "wof:name":"Monysted Capital Corp",
    "wof:placetype":"venue"
},
  "geometry": {"coordinates":[-86.64093099999999,33.433822],"type":"Point"}
}