{
  "type": "Feature",
  "properties": {
    "iso:country":"US",
    "sg:address":"163 N Leland Dr",
    "sg:city":"Florence",
    "sg:classifiers":[
        {
            "category":"Professional",
            "subcategory":"Management & Consulting",
            "type":"Services"
        }
    ],
    "sg:phone":"+1 256 718 1643",
    "sg:postcode":"35630",
    "sg:province":"AL",
    "wof:name":"Transformation Systems",
    "wof:placetype":"venue"
},
  "geometry": {"coordinates":[-87.629796,34.822865],"type":"Point"}
}