{
  "type": "Feature",
  "properties": {
    "addr:full":"402 US Hwy 31 Hartselle AL 35640",
    "addr:housenumber":"402",
    "addr:postcode":"35640",
    "addr:street":"Us Hwy 31",
    "iso:country":"US",
    "sg:address":"402 US Hwy 31",
    "sg:city":"Hartselle",
    "sg:classifiers":[
        {
            "category":"Restaurant",
            "type":"Food & Drink"
        }
    ],
    "sg:phone":"+1 256 773 0412",
    "sg:postcode":"35640",
    "sg:province":"AL",
    "sg:tags":[
        "eating"
    ],
    "sg:website":"www.sonicdrivein.com",
    "wof:name":"Sonic Drive-In",
    "wof:placetype":"venue"
},
  "geometry": {"coordinates":[-86.943682,34.446211],"type":"Point"}
}