{
  "type": "Feature",
  "properties": {
    "iso:country":"US",
    "sg:address":"1310 37th St E",
    "sg:city":"Tuscaloosa",
    "sg:classifiers":[
        {
            "category":"Professional",
            "type":"Services"
        }
    ],
    "sg:phone":"+1 205 553 2051",
    "sg:postcode":"35405",
    "sg:province":"AL",
    "wof:name":"Mattie Davis",
    "wof:placetype":"venue"
},
  "geometry": {"coordinates":[-87.51925,33.175405],"type":"Point"}
}