{
  "type": "Feature",
  "properties": {
    "addr:full":"873 86th St S Birmingham AL 35206",
    "addr:housenumber":"873",
    "addr:postcode":"35206",
    "addr:street":"86Th St S",
    "iso:country":"US",
    "sg:address":"873 86th St S",
    "sg:city":"Birmingham",
    "sg:classifiers":[
        {
            "category":"Professional",
            "type":"Services"
        },
        {
            "category":"Shopping",
            "subcategory":"Clothing, Apparel, & Fashions",
            "type":"Retail Goods"
        }
    ],
    "sg:phone":"+1 205 833 8000",
    "sg:postcode":"35206",
    "sg:province":"AL",
    "sg:tags":[
        "dancing",
        "supply"
    ],
    "wof:name":"Majesty Praise Wear",
    "wof:placetype":"venue"
},
  "geometry": {"coordinates":[-86.704295,33.57157],"type":"Point"}
}