{
  "type": "Feature",
  "properties": {
    "iso:country":"US",
    "sg:address":"2693 Co Rd 48",
    "sg:city":"Russellville",
    "sg:classifiers":[
        {
            "category":"Building & Trades",
            "subcategory":"Construction",
            "type":"Services"
        }
    ],
    "sg:phone":"+1 256 332 5453",
    "sg:postcode":"35654",
    "sg:province":"AL",
    "sg:tags":[
        "house"
    ],
    "wof:name":"Billy Fuller Builders",
    "wof:placetype":"venue"
},
  "geometry": {"coordinates":[-87.676237,34.507407],"type":"Point"}
}