{
  "type": "Feature",
  "properties": {
    "iso:country":"US",
    "sg:address":"109 Kirkland Rd",
    "sg:city":"Seale",
    "sg:classifiers":[
        {
            "category":"Wholesale",
            "subcategory":"Meat",
            "type":"Manufacturing & Wholesale Goods"
        }
    ],
    "sg:phone":"+1 334 297 4663",
    "sg:postcode":"36875",
    "sg:province":"AL",
    "sg:tags":[
        "packer",
        "plant",
        "packing"
    ],
    "wof:name":"Wilson's Farm Meat Processing",
    "wof:placetype":"venue"
},
  "geometry": {"coordinates":[-85.145342,32.385033],"type":"Point"}
}