{
  "type": "Feature",
  "properties": {
    "addr:full":"1 White Oak Rd Oneonta AL 35121",
    "addr:housenumber":"1",
    "addr:postcode":"35121",
    "addr:street":"White Oak Rd",
    "iso:country":"US",
    "sg:address":"1 White Oak Rd",
    "sg:city":"Oneonta",
    "sg:classifiers":[
        {
            "category":"Shopping",
            "subcategory":"Jewelry",
            "type":"Retail Goods"
        }
    ],
    "sg:phone":"+1 205 625 4855",
    "sg:postcode":"35121",
    "sg:province":"AL",
    "wof:name":"Cjs Collectables",
    "wof:placetype":"venue"
},
  "geometry": {"coordinates":[-86.458726,33.954048],"type":"Point"}
}