{
  "type": "Feature",
  "properties": {
    "iso:country":"US",
    "sg:address":"927 5th Ave NE",
    "sg:city":"Attalla",
    "sg:classifiers":[
        {
            "category":"Autos & Motor Vehicles",
            "subcategory":"Automobile Sales",
            "type":"Retail Goods"
        }
    ],
    "sg:phone":"+1 256 538 0707",
    "sg:postcode":"35954",
    "sg:province":"AL",
    "sg:tags":[
        "car",
        "dealer"
    ],
    "wof:name":"Mack Jones Motors",
    "wof:placetype":"venue"
},
  "geometry": {"coordinates":[-86.071694,34.019453],"type":"Point"}
}