{
  "type": "Feature",
  "properties": {
    "iso:country":"US",
    "sg:address":"691 Co Rd 10",
    "sg:city":"Maplesville",
    "sg:classifiers":[
        {
            "category":"Manufacturing",
            "subcategory":"Metals",
            "type":"Manufacturing & Wholesale Goods"
        }
    ],
    "sg:phone":"+1 334 366 1819",
    "sg:postcode":"36750",
    "sg:province":"AL",
    "sg:tags":[
        "fabrication",
        "structural"
    ],
    "wof:name":"In Line Steel Inc",
    "wof:placetype":"venue"
},
  "geometry": {"coordinates":[-86.883623,32.78423],"type":"Point"}
}