{
  "type": "Feature",
  "properties": {
    "addr:full":"306 E Watson St Andalusia AL 36420",
    "addr:housenumber":"306",
    "addr:postcode":"36420",
    "addr:street":"E Watson St",
    "iso:country":"US",
    "sg:address":"306 E Watson St",
    "sg:city":"Andalusia",
    "sg:classifiers":[
        {
            "category":"Building & Trades",
            "subcategory":"Construction",
            "type":"Services"
        }
    ],
    "sg:phone":"+1 334 222 3316",
    "sg:postcode":"36420",
    "sg:province":"AL",
    "sg:tags":[
        "marking",
        "maintenance",
        "parking"
    ],
    "wof:name":"Andalusia City Street Dept",
    "wof:placetype":"venue"
},
  "geometry": {"coordinates":[-86.47683000000001,31.303204],"type":"Point"}
}