{
  "type": "Feature",
  "properties": {
    "addr:full":"365 Chewacla Dr Auburn AL 36830",
    "addr:housenumber":"365",
    "addr:postcode":"36830",
    "addr:street":"Chewacla Dr",
    "iso:country":"US",
    "sg:address":"365 Chewacla Dr",
    "sg:city":"Auburn",
    "sg:classifiers":[
        {
            "category":"Building & Trades",
            "subcategory":"Construction",
            "type":"Services"
        }
    ],
    "sg:phone":"+1 334 821 1589",
    "sg:postcode":"36830",
    "sg:province":"AL",
    "sg:tags":[
        "housing"
    ],
    "wof:name":"Frank A Miller",
    "wof:placetype":"venue"
},
  "geometry": {"coordinates":[-85.47098,32.598864],"type":"Point"}
}