{
  "type": "Feature",
  "properties": {
    "addr:full":"63 Marco Dr Decatur AL 35603",
    "addr:housenumber":"63",
    "addr:postcode":"35603",
    "addr:street":"Marco Dr",
    "iso:country":"US",
    "sg:address":"63 Marco Dr",
    "sg:city":"Decatur",
    "sg:classifiers":[
        {
            "category":"Travel",
            "subcategory":"Hotels & Motels",
            "type":"Entertainment"
        }
    ],
    "sg:phone":"+1 256 351 0190",
    "sg:postcode":"35603",
    "sg:province":"AL",
    "sg:tags":[
        "operation"
    ],
    "wof:name":"Days Inn",
    "wof:placetype":"venue"
},
  "geometry": {"coordinates":[-86.90160899999999,34.531676],"type":"Point"}
}