{
  "type": "Feature",
  "properties": {
    "addr:full":"900 Logan Ave SW Cullman AL 35055",
    "addr:housenumber":"900",
    "addr:postcode":"35055",
    "addr:street":"Logan Ave Sw",
    "iso:country":"US",
    "sg:address":"900 Logan Ave SW",
    "sg:city":"Cullman",
    "sg:classifiers":[
        {
            "category":"Building & Trades",
            "subcategory":"Construction",
            "type":"Services"
        }
    ],
    "sg:phone":"+1 256 734 3337",
    "sg:postcode":"35055",
    "sg:province":"AL",
    "sg:tags":[
        "general",
        "contractor"
    ],
    "wof:name":"Dale Pearson Construction",
    "wof:placetype":"venue"
},
  "geometry": {"coordinates":[-86.865405,34.16729],"type":"Point"}
}