{
  "type": "Feature",
  "properties": {
    "addr:full":"1709 3rd Ave N Bessemer AL 35020",
    "addr:housenumber":"1709",
    "addr:postcode":"35020",
    "addr:street":"3Rd Ave N",
    "iso:country":"US",
    "sg:address":"1709 3rd Ave N",
    "sg:city":"Bessemer",
    "sg:phone":"+1 205 424 7827",
    "sg:postcode":"35020",
    "sg:province":"AL",
    "wof:name":"Western Star",
    "wof:placetype":"venue"
},
  "geometry": {"coordinates":[-86.95525000000001,33.400469],"type":"Point"}
}