{
  "type": "Feature",
  "properties": {
    "iso:country":"US",
    "sg:address":"626 Clinton Ave E",
    "sg:city":"Huntsville",
    "sg:classifiers":[
        {
            "category":"Manufacturing",
            "subcategory":"Tools & Machinery",
            "type":"Manufacturing & Wholesale Goods"
        }
    ],
    "sg:phone":"+1 256 519 3656",
    "sg:postcode":"35801",
    "sg:province":"AL",
    "sg:tags":[
        "press",
        "punch",
        "mfg"
    ],
    "wof:name":"Bruderer Inc",
    "wof:placetype":"venue"
},
  "geometry": {"coordinates":[-86.578463,34.735381],"type":"Point"}
}