{
  "type": "Feature",
  "properties": {
    "iso:country":"US",
    "sg:address":"3071 Ross Clark Cir",
    "sg:city":"Dothan",
    "sg:classifiers":[
        {
            "category":"Travel",
            "subcategory":"Hotels & Motels",
            "type":"Entertainment"
        }
    ],
    "sg:phone":"+1 334 671 3700",
    "sg:postcode":"36301",
    "sg:province":"AL",
    "wof:name":"Holiday Inn",
    "wof:placetype":"venue"
},
  "geometry": {"coordinates":[-85.43243699999999,31.226549],"type":"Point"}
}