{
  "type": "Feature",
  "properties": {
    "iso:country":"US",
    "sg:address":"231 S 3rd St",
    "sg:city":"Gadsden",
    "sg:classifiers":[
        {
            "category":"Real Estate",
            "subcategory":"Real Estate Agent",
            "type":"Services"
        }
    ],
    "sg:phone":"+1 256 549 1327",
    "sg:postcode":"35901",
    "sg:province":"AL",
    "sg:tags":[
        "business"
    ],
    "wof:name":"Baker Realty & Appraisal",
    "wof:placetype":"venue"
},
  "geometry": {"coordinates":[-86.00345,34.010377],"type":"Point"}
}