{
  "type": "Feature",
  "properties": {
    "addr:full":"833 Rockingham Rd Birmingham AL 35235",
    "addr:housenumber":"833",
    "addr:postcode":"35235",
    "addr:street":"Rockingham Rd",
    "iso:country":"US",
    "sg:address":"833 Rockingham Rd",
    "sg:city":"Birmingham",
    "sg:classifiers":[
        {
            "category":"Professional",
            "subcategory":"Engineering",
            "type":"Services"
        }
    ],
    "sg:phone":"+1 205 854 0160",
    "sg:postcode":"35235",
    "sg:province":"AL",
    "wof:name":"Walker Engineering Inc",
    "wof:placetype":"venue"
},
  "geometry": {"coordinates":[-86.67339,33.601033],"type":"Point"}
}