{
  "type": "Feature",
  "properties": {
    "iso:country":"US",
    "sg:address":"2061 23rd Ave S",
    "sg:city":"Birmingham",
    "sg:classifiers":[
        {
            "category":"Restaurant",
            "type":"Food & Drink"
        }
    ],
    "sg:phone":"+1 205 871 1495",
    "sg:postcode":"35223",
    "sg:province":"AL",
    "sg:tags":[
        "eating"
    ],
    "wof:name":"Younguns Concession Inc",
    "wof:placetype":"venue"
},
  "geometry": {"coordinates":[-86.785713,33.489243],"type":"Point"}
}