{
  "type": "Feature",
  "properties": {
    "addr:full":"1477 Slaughter Rd Madison AL 35758",
    "addr:housenumber":"1477",
    "addr:postcode":"35758",
    "addr:street":"Slaughter Rd",
    "iso:country":"US",
    "sg:address":"1477 Slaughter Rd",
    "sg:city":"Madison",
    "sg:classifiers":[
        {
            "category":"Organizations",
            "subcategory":"Religious Organization",
            "type":"Services"
        }
    ],
    "sg:phone":"+1 256 895 9228",
    "sg:postcode":"35758",
    "sg:province":"AL",
    "wof:name":"Living Word Fellowship",
    "wof:placetype":"venue"
},
  "geometry": {"coordinates":[-86.713964,34.739278],"type":"Point"}
}