{
  "type": "Feature",
  "properties": {
    "addr:full":"959 E Main St Prattville AL 36066",
    "addr:housenumber":"959",
    "addr:postcode":"36066",
    "addr:street":"E Main St",
    "iso:country":"US",
    "sg:address":"959 E Main St",
    "sg:city":"Prattville",
    "sg:classifiers":[
        {
            "category":"Shopping",
            "subcategory":"Pharmacy",
            "type":"Retail Goods"
        }
    ],
    "sg:phone":"+1 334 358 1630",
    "sg:postcode":"36066",
    "sg:province":"AL",
    "wof:name":"Medicine Shoppe",
    "wof:placetype":"venue"
},
  "geometry": {"coordinates":[-86.447768,32.460393],"type":"Point"}
}