{
  "type": "Feature",
  "properties": {
    "addr:full":"1900 28th Ave S Homewood AL 35209",
    "addr:housenumber":"1900",
    "addr:postcode":"35209",
    "addr:street":"28Th Ave S Homewood",
    "iso:country":"US",
    "sg:address":"1900 28th Ave S",
    "sg:city":"Homewood",
    "sg:classifiers":[
        {
            "category":"Banks & Credit Unions",
            "subcategory":"Investment Brokerage",
            "type":"Services"
        }
    ],
    "sg:phone":"+1 205 879 6198",
    "sg:postcode":"35209",
    "sg:province":"AL",
    "sg:tags":[
        "security"
    ],
    "wof:name":"Edward Jones Co",
    "wof:placetype":"venue"
},
  "geometry": {"coordinates":[-86.788534,33.481225],"type":"Point"}
}