{
  "type": "Feature",
  "properties": {
    "addr:full":"437 Green St Birmingham AL 35214",
    "addr:housenumber":"437",
    "addr:postcode":"35214",
    "addr:street":"Green St",
    "iso:country":"US",
    "sg:address":"437 Green St",
    "sg:city":"Birmingham",
    "sg:classifiers":[
        {
            "category":"Restaurant",
            "type":"Food & Drink"
        }
    ],
    "sg:menulink":"http://www.allmenus.com/al/birmingham/98267-qdoba/menu/",
    "sg:phone":"+1 205 941 1492",
    "sg:postcode":"35214",
    "sg:province":"AL",
    "sg:tags":[
        "mexican"
    ],
    "wof:name":"Qdoba",
    "wof:placetype":"venue"
},
  "geometry": {"coordinates":[-86.897946,33.537473],"type":"Point"}
}