{
  "type": "Feature",
  "properties": {
    "iso:country":"US",
    "sg:address":"55 Forrest Dr",
    "sg:city":"Eclectic",
    "sg:classifiers":[
        {
            "category":"Shopping",
            "subcategory":"Clothing, Apparel, & Fashions",
            "type":"Retail Goods"
        }
    ],
    "sg:phone":"+1 334 857 3302",
    "sg:postcode":"36024",
    "sg:province":"AL",
    "sg:tags":[
        "ready"
    ],
    "wof:name":"Me-Mas 2",
    "wof:placetype":"venue"
},
  "geometry": {"coordinates":[-86.04985,32.738751],"type":"Point"}
}