{
  "type": "Feature",
  "properties": {
    "iso:country":"US",
    "sg:address":"29770 Hayden Dr",
    "sg:city":"Orange Beach",
    "sg:classifiers":[
        {
            "category":"Building & Trades",
            "subcategory":"Construction",
            "type":"Services"
        }
    ],
    "sg:phone":"+1 251 981 5017",
    "sg:postcode":"36561",
    "sg:province":"AL",
    "sg:tags":[
        "contractor"
    ],
    "wof:name":"Construction Consulting Svcs",
    "wof:placetype":"venue"
},
  "geometry": {"coordinates":[-87.518299,30.309554],"type":"Point"}
}