{
  "type": "Feature",
  "properties": {
    "iso:country":"US",
    "sg:address":"410 17th St N",
    "sg:city":"Birmingham",
    "sg:classifiers":[
        {
            "category":"Shopping",
            "subcategory":"Florist",
            "type":"Retail Goods"
        }
    ],
    "sg:phone":"+1 205 252 1722",
    "sg:postcode":"35203",
    "sg:province":"AL",
    "wof:name":"Your Flower Shop",
    "wof:placetype":"venue"
},
  "geometry": {"coordinates":[-86.812021,33.515343],"type":"Point"}
}