{
  "type": "Feature",
  "properties": {
    "iso:country":"US",
    "sg:address":"398 Hillabee Dr",
    "sg:city":"Montgomery",
    "sg:classifiers":[
        {
            "category":"Professional",
            "subcategory":"Business Services",
            "type":"Services"
        }
    ],
    "sg:phone":"+1 334 273 8813",
    "sg:postcode":"36117",
    "sg:province":"AL",
    "wof:name":"Gardner Group Inc",
    "wof:placetype":"venue"
},
  "geometry": {"coordinates":[-86.146365,32.383565],"type":"Point"}
}