{
  "type": "Feature",
  "properties": {
    "addr:full":"202 Harrand Creek Dr Enterprise AL 36330",
    "addr:housenumber":"202",
    "addr:postcode":"36330",
    "addr:street":"Harrand Creek Dr",
    "iso:country":"US",
    "sg:address":"202 Harrand Creek Dr",
    "sg:city":"Enterprise",
    "sg:classifiers":[
        {
            "category":"Building & Trades",
            "subcategory":"Construction",
            "type":"Services"
        }
    ],
    "sg:phone":"+1 334 308 2264",
    "sg:postcode":"36330",
    "sg:province":"AL",
    "sg:tags":[
        "general",
        "contractor"
    ],
    "wof:name":"Great American Dream",
    "wof:placetype":"venue"
},
  "geometry": {"coordinates":[-85.821877,31.333245],"type":"Point"}
}