{
  "type": "Feature",
  "properties": {
    "iso:country":"US",
    "sg:address":"144 Chandler St",
    "sg:city":"Millport",
    "sg:classifiers":[
        {
            "category":"Manufacturing",
            "subcategory":"Tools & Machinery",
            "type":"Manufacturing & Wholesale Goods"
        }
    ],
    "sg:phone":"+1 205 662 3737",
    "sg:postcode":"35576",
    "sg:province":"AL",
    "sg:tags":[
        "industrial",
        "mfg"
    ],
    "wof:name":"Millport Tool & Die",
    "wof:placetype":"venue"
},
  "geometry": {"coordinates":[-88.087002,33.560517],"type":"Point"}
}