{
  "type": "Feature",
  "properties": {
    "iso:country":"US",
    "sg:address":"1437 Linda Vista Dr",
    "sg:city":"Birmingham",
    "sg:classifiers":[
        {
            "category":"Building & Trades",
            "subcategory":"Construction",
            "type":"Services"
        }
    ],
    "sg:phone":"+1 205 823 2537",
    "sg:postcode":"35226",
    "sg:province":"AL",
    "sg:tags":[
        "home",
        "contractor"
    ],
    "wof:name":"Schilleci Development Co Inc",
    "wof:placetype":"venue"
},
  "geometry": {"coordinates":[-86.815214,33.430148],"type":"Point"}
}