{
  "type": "Feature",
  "properties": {
    "iso:country":"US",
    "sg:address":"2021 Golf Course Rd",
    "sg:city":"Pell City",
    "sg:classifiers":[
        {
            "category":"Organizations",
            "subcategory":"Community Association",
            "type":"Services"
        }
    ],
    "sg:phone":"+1 205 338 2066",
    "sg:postcode":"35128",
    "sg:province":"AL",
    "sg:tags":[
        "club"
    ],
    "wof:name":"Pell City Country Club",
    "wof:placetype":"venue"
},
  "geometry": {"coordinates":[-86.259945,33.558515],"type":"Point"}
}