{
  "type": "Feature",
  "properties": {
    "iso:country":"US",
    "sg:address":"3520 Scenic Dr",
    "sg:city":"Mobile",
    "sg:classifiers":[
        {
            "category":"Professional",
            "subcategory":"Lawyer & Legal Services",
            "type":"Services"
        }
    ],
    "sg:phone":"+1 251 476 1910",
    "sg:postcode":"36605",
    "sg:province":"AL",
    "sg:tags":[
        "attorney"
    ],
    "wof:name":"Charles H Erwin",
    "wof:placetype":"venue"
},
  "geometry": {"coordinates":[-88.110774,30.596609],"type":"Point"}
}