{
  "type": "Feature",
  "properties": {
    "addr:full":"2508 US Hwy 31 Pelham AL 35124",
    "addr:housenumber":"2508",
    "addr:postcode":"35124",
    "addr:street":"Us Hwy 31",
    "iso:country":"US",
    "sg:address":"2508 US Hwy 31",
    "sg:city":"Pelham",
    "sg:classifiers":[
        {
            "category":"Health Services",
            "subcategory":"Doctor",
            "type":"Services"
        }
    ],
    "sg:phone":"+1 205 664 0880",
    "sg:postcode":"35124",
    "sg:province":"AL",
    "sg:tags":[
        "clinic"
    ],
    "wof:name":"Cahaba Family Medicine",
    "wof:placetype":"venue"
},
  "geometry": {"coordinates":[-86.795677,33.322829],"type":"Point"}
}