{
  "type": "Feature",
  "properties": {
    "iso:country":"US",
    "sg:address":"1203 Gautier St",
    "sg:city":"Tuskegee",
    "sg:classifiers":[
        {
            "category":"Social Services",
            "subcategory":"Child Care",
            "type":"Services"
        }
    ],
    "sg:phone":"+1 334 725 1500",
    "sg:postcode":"36083",
    "sg:province":"AL",
    "sg:tags":[
        "day"
    ],
    "wof:name":"Kiddie Castle Daycare Center",
    "wof:placetype":"venue"
},
  "geometry": {"coordinates":[-85.691362,32.409816],"type":"Point"}
}