{
  "type": "Feature",
  "properties": {
    "iso:country":"US",
    "sg:address":"411 N Appletree St",
    "sg:city":"Dothan",
    "sg:classifiers":[
        {
            "category":"Taxi",
            "type":"Transportation"
        }
    ],
    "sg:phone":"+1 334 702 8323",
    "sg:postcode":"36303",
    "sg:province":"AL",
    "sg:tags":[
        "taxicab"
    ],
    "wof:name":"Quick Service Cab Co",
    "wof:placetype":"venue"
},
  "geometry": {"coordinates":[-85.390618,31.228901],"type":"Point"}
}