{
  "type": "Feature",
  "properties": {
    "addr:full":"7096 Co Rd 1 Gallion AL 36742",
    "addr:housenumber":"7096",
    "addr:postcode":"36742",
    "addr:street":"Co Rd 1 Gallion",
    "iso:country":"US",
    "sg:address":"7096 Co Rd 1",
    "sg:city":"Gallion",
    "sg:classifiers":[
        {
            "category":"Building & Trades",
            "subcategory":"Plumbing",
            "type":"Services"
        }
    ],
    "sg:phone":"+1 334 289 0687",
    "sg:postcode":"36742",
    "sg:province":"AL",
    "sg:tags":[
        "contractor"
    ],
    "wof:name":"Crepps Mechanical & Electrical",
    "wof:placetype":"venue"
},
  "geometry": {"coordinates":[-87.71355800000001,32.498439],"type":"Point"}
}