{
  "type": "Feature",
  "properties": {
    "iso:country":"US",
    "sg:address":"7096 Co Rd 1",
    "sg:city":"Gallion",
    "sg:classifiers":[
        {
            "category":"Building & Trades",
            "subcategory":"Plumbing",
            "type":"Services"
        }
    ],
    "sg:phone":"+1 334 289 0687",
    "sg:postcode":"36742",
    "sg:province":"AL",
    "sg:tags":[
        "contractor"
    ],
    "wof:name":"Crepps Mechanical & Electrical",
    "wof:placetype":"venue"
},
  "geometry": {"coordinates":[-87.713558,32.498439],"type":"Point"}
}