{
  "type": "Feature",
  "properties": {
    "addr:full":"3833 Ross Clark Cir Dothan AL 36303",
    "addr:housenumber":"3833",
    "addr:postcode":"36303",
    "addr:street":"Ross Clark Cir",
    "iso:country":"US",
    "sg:address":"3833 Ross Clark Cir",
    "sg:city":"Dothan",
    "sg:classifiers":[
        {
            "category":"Health Services",
            "subcategory":"Clinic",
            "type":"Services"
        }
    ],
    "sg:phone":"+1 334 792 9744",
    "sg:postcode":"36303",
    "sg:province":"AL",
    "sg:tags":[
        "banks",
        "blood",
        "center"
    ],
    "sg:website":"www.lifesouth.org",
    "wof:name":"Lifesouth Community Blood Ctr",
    "wof:placetype":"venue"
},
  "geometry": {"coordinates":[-85.41058099999999,31.253274],"type":"Point"}
}