{
  "type": "Feature",
  "properties": {
    "addr:full":"816 Azalea Rd Mobile AL 36693",
    "addr:housenumber":"816",
    "addr:postcode":"36693",
    "addr:street":"Azalea Rd",
    "iso:country":"US",
    "sg:address":"816 Azalea Rd",
    "sg:city":"Mobile",
    "sg:classifiers":[
        {
            "category":"Insurance",
            "subcategory":"Insurance Agent",
            "type":"Services"
        }
    ],
    "sg:phone":"+1 251 661 3098",
    "sg:postcode":"36693",
    "sg:province":"AL",
    "wof:name":"Darling Agency Inc",
    "wof:placetype":"venue"
},
  "geometry": {"coordinates":[-88.139933,30.653015],"type":"Point"}
}