{
  "type": "Feature",
  "properties": {
    "iso:country":"US",
    "sg:address":"1074 Cathedral Cir",
    "sg:city":"Madison",
    "sg:classifiers":[
        {
            "category":"Professional",
            "subcategory":"Management & Consulting",
            "type":"Services"
        }
    ],
    "sg:phone":"+1 256 325 1820",
    "sg:postcode":"35758",
    "sg:province":"AL",
    "wof:name":"Charles M Snelling Inc",
    "wof:placetype":"venue"
},
  "geometry": {"coordinates":[-86.742656,34.712698],"type":"Point"}
}