{
  "type": "Feature",
  "properties": {
    "iso:country":"US",
    "sg:address":"22787 State Rte 59",
    "sg:city":"Robertsdale",
    "sg:classifiers":[
        {
            "category":"Insurance",
            "subcategory":"Insurance Agent",
            "type":"Services"
        }
    ],
    "sg:phone":"+1 251 947 7301",
    "sg:postcode":"36567",
    "sg:province":"AL",
    "wof:name":"Insurance Center Inc",
    "wof:placetype":"venue"
},
  "geometry": {"coordinates":[-87.710744,30.556779],"type":"Point"}
}