{
  "type": "Feature",
  "properties": {
    "addr:full":"2 20th St N Birmingham AL 35203",
    "addr:housenumber":"2",
    "addr:postcode":"35203",
    "addr:street":"20Th St N",
    "iso:country":"US",
    "sg:address":"2 20th St N",
    "sg:city":"Birmingham",
    "sg:classifiers":[
        {
            "category":"Government",
            "subcategory":"Office",
            "type":"Public Place"
        }
    ],
    "sg:phone":"+1 205 731 4082",
    "sg:postcode":"35203",
    "sg:province":"AL",
    "sg:tags":[
        "mediation"
    ],
    "wof:name":"Federal Mdtion Cnciliation Svc",
    "wof:placetype":"venue"
},
  "geometry": {"coordinates":[-86.805246,33.513821],"type":"Point"}
}