{
  "type": "Feature",
  "properties": {
    "iso:country":"US",
    "sg:address":"105 Princeton Pkwy",
    "sg:city":"Birmingham",
    "sg:classifiers":[
        {
            "category":"Shopping",
            "subcategory":"Clothing, Apparel, & Fashions",
            "type":"Retail Goods"
        }
    ],
    "sg:phone":"+1 205 942 5266",
    "sg:postcode":"35211",
    "sg:province":"AL",
    "sg:tags":[
        "uniform",
        "supply"
    ],
    "wof:name":"G & K Svc",
    "wof:placetype":"venue"
},
  "geometry": {"coordinates":[-86.847345,33.502427],"type":"Point"}
}