{
  "type": "Feature",
  "properties": {
    "addr:full":"3850 Greensboro Ave Tuscaloosa AL 35405",
    "addr:housenumber":"3850",
    "addr:postcode":"35405",
    "addr:street":"Greensboro Ave",
    "iso:country":"US",
    "sg:address":"3850 Greensboro Ave",
    "sg:city":"Tuscaloosa",
    "sg:classifiers":[
        {
            "category":"Professional",
            "subcategory":"Advertising",
            "type":"Services"
        }
    ],
    "sg:phone":"+1 205 345 3471",
    "sg:postcode":"35405",
    "sg:province":"AL",
    "sg:website":"www.lamar.com",
    "wof:name":"Lamar Advertising Co",
    "wof:placetype":"venue"
},
  "geometry": {"coordinates":[-87.54710300000001,33.173266],"type":"Point"}
}