{
  "type": "Feature",
  "properties": {
    "iso:country":"US",
    "sg:address":"5649 US Hwy 431",
    "sg:city":"Brownsboro",
    "sg:classifiers":[
        {
            "category":"Wholesale",
            "subcategory":"Auto Parts",
            "type":"Manufacturing & Wholesale Goods"
        }
    ],
    "sg:phone":"+1 256 518 9500",
    "sg:postcode":"35741",
    "sg:province":"AL",
    "sg:tags":[
        "automobile",
        "rebuilt"
    ],
    "wof:name":"Big Cove Salvage",
    "wof:placetype":"venue"
},
  "geometry": {"coordinates":[-86.50254,34.688892],"type":"Point"}
}