{
  "type": "Feature",
  "properties": {
    "iso:country":"US",
    "sg:address":"531 W Laurel Ave",
    "sg:city":"Foley",
    "sg:classifiers":[
        {
            "category":"Freight",
            "type":"Transportation"
        }
    ],
    "sg:phone":"+1 251 964 7535",
    "sg:postcode":"36535",
    "sg:province":"AL",
    "sg:tags":[
        "trucking"
    ],
    "wof:name":"Core Logistics",
    "wof:placetype":"venue"
},
  "geometry": {"coordinates":[-87.693586,30.40649],"type":"Point"}
}