{
  "type": "Feature",
  "properties": {
    "addr:full":"7011 Countryside Cir Pinson AL 35126",
    "addr:housenumber":"7011",
    "addr:postcode":"35126",
    "addr:street":"Countryside Cir",
    "iso:country":"US",
    "sg:address":"7011 Countryside Cir",
    "sg:city":"Pinson",
    "sg:classifiers":[
        {
            "category":"Professional",
            "subcategory":"Business Services",
            "type":"Services"
        }
    ],
    "sg:phone":"+1 205 681 0385",
    "sg:postcode":"35126",
    "sg:province":"AL",
    "sg:tags":[
        "embroidery"
    ],
    "wof:name":"Embroidery Concepts",
    "wof:placetype":"venue"
},
  "geometry": {"coordinates":[-86.585812,33.710278],"type":"Point"}
}