{
  "type": "Feature",
  "properties": {
    "addr:full":"312 Palmer Rd Madison AL 35758",
    "addr:housenumber":"312",
    "addr:postcode":"35758",
    "addr:street":"Palmer Rd",
    "iso:country":"US",
    "sg:address":"312 Palmer Rd",
    "sg:city":"Madison",
    "sg:classifiers":[
        {
            "category":"Professional",
            "subcategory":"Engineering",
            "type":"Services"
        }
    ],
    "sg:phone":"+1 256 461 1366",
    "sg:postcode":"35758",
    "sg:province":"AL",
    "wof:name":"Southern Geomatics",
    "wof:placetype":"venue"
},
  "geometry": {"coordinates":[-86.765094,34.692099],"type":"Point"}
}