{
  "type": "Feature",
  "properties": {
    "iso:country":"US",
    "sg:address":"1530 6th Ave SE Ste A",
    "sg:city":"Decatur",
    "sg:classifiers":[
        {
            "category":"Food & Beverages",
            "subcategory":"Groceries & Convenience Stores",
            "type":"Retail Goods"
        }
    ],
    "sg:phone":"+1 256 350 5731",
    "sg:postcode":"35601",
    "sg:province":"AL",
    "wof:name":"La Guerrerense",
    "wof:placetype":"venue"
},
  "geometry": {"coordinates":[-86.980476,34.5838],"type":"Point"}
}