{
  "type": "Feature",
  "properties": {
    "iso:country":"US",
    "sg:address":"755 Chickasaw St",
    "sg:city":"Dothan",
    "sg:classifiers":[
        {
            "category":"Professional",
            "type":"Services"
        }
    ],
    "sg:phone":"+1 334 702 8027",
    "sg:postcode":"36303",
    "sg:province":"AL",
    "wof:name":"Laura Wilson",
    "wof:placetype":"venue"
},
  "geometry": {"coordinates":[-85.401498,31.231736],"type":"Point"}
}