{
  "type": "Feature",
  "properties": {
    "iso:country":"US",
    "sg:address":"2704 College Ave",
    "sg:city":"Jackson",
    "sg:classifiers":[
        {
            "category":"Autos & Motor Vehicles",
            "subcategory":"Auto Supplies",
            "type":"Retail Goods"
        }
    ],
    "sg:phone":"+1 251 246 0066",
    "sg:postcode":"36545",
    "sg:province":"AL",
    "wof:name":"C & D Automotive",
    "wof:placetype":"venue"
},
  "geometry": {"coordinates":[-87.88819,31.53619],"type":"Point"}
}