{
  "type": "Feature",
  "properties": {
    "addr:full":"1054 S Holt St Montgomery AL 36108",
    "addr:housenumber":"1054",
    "addr:postcode":"36108",
    "addr:street":"S Holt St",
    "iso:country":"US",
    "sg:address":"1054 S Holt St",
    "sg:city":"Montgomery",
    "sg:classifiers":[
        {
            "category":"Food & Beverages",
            "subcategory":"Groceries & Convenience Stores",
            "type":"Retail Goods"
        }
    ],
    "sg:phone":"+1 334 263 9803",
    "sg:postcode":"36108",
    "sg:province":"AL",
    "sg:tags":[
        "grocer"
    ],
    "wof:name":"Hub's Superette",
    "wof:placetype":"venue"
},
  "geometry": {"coordinates":[-86.320685,32.363182],"type":"Point"}
}