{
  "type": "Feature",
  "properties": {
    "iso:country":"US",
    "sg:address":"9480 Cottage Hill Rd",
    "sg:city":"Mobile",
    "sg:classifiers":[
        {
            "category":"Professional",
            "subcategory":"Business Services",
            "type":"Services"
        }
    ],
    "sg:phone":"+1 251 633 2771",
    "sg:postcode":"36695",
    "sg:province":"AL",
    "wof:name":"Interior Designs Direct",
    "wof:placetype":"venue"
},
  "geometry": {"coordinates":[-88.263271,30.640095],"type":"Point"}
}