{
  "type": "Feature",
  "properties": {
    "iso:country":"US",
    "sg:address":"6900 2nd Ave S",
    "sg:city":"Birmingham",
    "sg:classifiers":[
        {
            "category":"Mining & Drilling",
            "type":"Manufacturing & Wholesale Goods"
        }
    ],
    "sg:phone":"+1 205 833 6544",
    "sg:postcode":"35212",
    "sg:province":"AL",
    "sg:tags":[
        "stone"
    ],
    "wof:name":"Custom Stone Shop",
    "wof:placetype":"venue"
},
  "geometry": {"coordinates":[-86.73312799999999,33.551603],"type":"Point"}
}