{
  "type": "Feature",
  "properties": {
    "addr:full":"401 Co Hwy 59 Brilliant AL 35548",
    "addr:housenumber":"401",
    "addr:postcode":"35548",
    "addr:street":"Co Hwy 59 Brilliant",
    "iso:country":"US",
    "sg:address":"401 Co Hwy 59",
    "sg:city":"Brilliant",
    "sg:classifiers":[
        {
            "category":"Freight",
            "type":"Transportation"
        }
    ],
    "sg:phone":"+1 205 465 2644",
    "sg:postcode":"35548",
    "sg:province":"AL",
    "sg:tags":[
        "trucking"
    ],
    "wof:name":"RMC Trucking",
    "wof:placetype":"venue"
},
  "geometry": {"coordinates":[-87.688479,34.097361],"type":"Point"}
}