{
  "type": "Feature",
  "properties": {
    "iso:country":"US",
    "sg:address":"401 Co Hwy 59",
    "sg:city":"Brilliant",
    "sg:classifiers":[
        {
            "category":"Freight",
            "type":"Transportation"
        }
    ],
    "sg:phone":"+1 205 465 2644",
    "sg:postcode":"35548",
    "sg:province":"AL",
    "sg:tags":[
        "trucking"
    ],
    "wof:name":"RMC Trucking",
    "wof:placetype":"venue"
},
  "geometry": {"coordinates":[-87.688479,34.097361],"type":"Point"}
}