{
  "type": "Feature",
  "properties": {
    "iso:country":"US",
    "sg:address":"1009 Barnes St",
    "sg:city":"Eutaw",
    "sg:classifiers":[
        {
            "category":"Shopping",
            "subcategory":"Florist",
            "type":"Retail Goods"
        }
    ],
    "sg:phone":"+1 205 372 0303",
    "sg:postcode":"35462",
    "sg:province":"AL",
    "wof:name":"Eutaw Market",
    "wof:placetype":"venue"
},
  "geometry": {"coordinates":[-87.907053,32.851807],"type":"Point"}
}