{
  "type": "Feature",
  "properties": {
    "iso:country":"US",
    "sg:address":"2265 Pinson Valley Pkwy",
    "sg:city":"Birmingham",
    "sg:classifiers":[
        {
            "category":"Retail",
            "subcategory":"Auto Rental",
            "type":"Services"
        }
    ],
    "sg:phone":"+1 205 808 0056",
    "sg:postcode":"35217",
    "sg:province":"AL",
    "sg:tags":[
        "utility"
    ],
    "wof:name":"Transport International Pool",
    "wof:placetype":"venue"
},
  "geometry": {"coordinates":[-86.75555799999999,33.601445],"type":"Point"}
}