{
  "type": "Feature",
  "properties": {
    "iso:country":"US",
    "sg:address":"1945 Davis Dr",
    "sg:city":"Gadsden",
    "sg:classifiers":[
        {
            "category":"Health Services",
            "subcategory":"Nursing And Care Facility",
            "type":"Services"
        }
    ],
    "sg:phone":"+1 256 547 4938",
    "sg:postcode":"35904",
    "sg:province":"AL",
    "sg:tags":[
        "home",
        "skilled",
        "convalescent"
    ],
    "wof:name":"Gadsden Health Care Center",
    "wof:placetype":"venue"
},
  "geometry": {"coordinates":[-86.029495,33.991686],"type":"Point"}
}