{
  "type": "Feature",
  "properties": {
    "iso:country":"US",
    "sg:address":"356 Fields Rd",
    "sg:city":"Laceys Spring",
    "sg:classifiers":[
        {
            "category":"Farming",
            "subcategory":"Livestock Farm",
            "type":"Manufacturing & Wholesale Goods"
        }
    ],
    "sg:phone":"+1 256 881 4345",
    "sg:postcode":"35754",
    "sg:province":"AL",
    "sg:tags":[
        "beef",
        "feedlot",
        "cattle"
    ],
    "wof:name":"Wayne Brown",
    "wof:placetype":"venue"
},
  "geometry": {"coordinates":[-86.601276,34.559717],"type":"Point"}
}