{
  "type": "Feature",
  "properties": {
    "iso:country":"US",
    "sg:address":"603 Pinto Dr",
    "sg:city":"Dothan",
    "sg:classifiers":[
        {
            "category":"Social Services",
            "subcategory":"Child Care",
            "type":"Services"
        }
    ],
    "sg:phone":"+1 334 677 6995",
    "sg:postcode":"36301",
    "sg:province":"AL",
    "wof:name":"Annie's Child Care Svc",
    "wof:placetype":"venue"
},
  "geometry": {"coordinates":[-85.369555,31.209089],"type":"Point"}
}