{
  "type": "Feature",
  "properties": {
    "addr:full":"5550 McFarland Blvd Northport AL 35476",
    "addr:housenumber":"5550",
    "addr:postcode":"35476",
    "addr:street":"Mcfarland Blvd",
    "iso:country":"US",
    "sg:address":"5550 McFarland Blvd",
    "sg:city":"Northport",
    "sg:classifiers":[
        {
            "category":"Utilities",
            "subcategory":"Mobile Phone",
            "type":"Services"
        }
    ],
    "sg:phone":"+1 205 330 8722",
    "sg:postcode":"35476",
    "sg:province":"AL",
    "sg:tags":[
        "telephone",
        "cellular"
    ],
    "wof:name":"South Central Wireless",
    "wof:placetype":"venue"
},
  "geometry": {"coordinates":[-87.60736900000001,33.236673],"type":"Point"}
}