{
  "type": "Feature",
  "properties": {
    "iso:country":"US",
    "sg:address":"3096 Columbus Rd",
    "sg:city":"Valley",
    "sg:classifiers":[
        {
            "category":"Food & Beverages",
            "subcategory":"Groceries & Convenience Stores",
            "type":"Retail Goods"
        }
    ],
    "sg:phone":"+1 334 756 3968",
    "sg:postcode":"36854",
    "sg:province":"AL",
    "sg:tags":[
        "grocer"
    ],
    "wof:name":"Milner's Grocery & Deli",
    "wof:placetype":"venue"
},
  "geometry": {"coordinates":[-85.152355,32.776356],"type":"Point"}
}