{
  "type": "Feature",
  "properties": {
    "iso:country":"US",
    "sg:address":"147 N East St",
    "sg:city":"Talladega",
    "sg:classifiers":[
        {
            "category":"Government",
            "subcategory":"Office",
            "type":"Public Place"
        }
    ],
    "sg:phone":"+1 256 761 2111",
    "sg:postcode":"35160",
    "sg:province":"AL",
    "wof:name":"Talladega County Juvenile Ofc",
    "wof:placetype":"venue"
},
  "geometry": {"coordinates":[-86.102733,33.437205],"type":"Point"}
}