{
  "type": "Feature",
  "properties": {
    "iso:country":"US",
    "sg:address":"119 E Church St",
    "sg:city":"Columbia",
    "sg:classifiers":[
        {
            "category":"Food & Beverages",
            "subcategory":"Groceries & Convenience Stores",
            "type":"Retail Goods"
        }
    ],
    "sg:phone":"+1 334 696 4563",
    "sg:postcode":"36319",
    "sg:province":"AL",
    "sg:tags":[
        "grocer"
    ],
    "wof:name":"Buster's IGA Foodliner",
    "wof:placetype":"venue"
},
  "geometry": {"coordinates":[-85.340111,31.351329],"type":"Point"}
}