{
  "type": "Feature",
  "properties": {
    "iso:country":"US",
    "sg:address":"2615 Co Rd 113",
    "sg:city":"Montevallo",
    "sg:classifiers":[
        {
            "category":"Professional",
            "subcategory":"Research",
            "type":"Services"
        }
    ],
    "sg:phone":"+1 205 665 7188",
    "sg:postcode":"35115",
    "sg:province":"AL",
    "sg:tags":[
        "commercial",
        "physical"
    ],
    "wof:name":"Old Oak Farm",
    "wof:placetype":"venue"
},
  "geometry": {"coordinates":[-86.826002,33.048802],"type":"Point"}
}