{
  "type": "Feature",
  "properties": {
    "addr:full":"5410 Bent Tree Cir Orange Beach AL 36561",
    "addr:housenumber":"5410",
    "addr:postcode":"36561",
    "addr:street":"Bent Tree Cir",
    "iso:country":"US",
    "sg:address":"5410 Bent Tree Cir",
    "sg:city":"Orange Beach",
    "sg:classifiers":[
        {
            "category":"Building & Trades",
            "subcategory":"Construction",
            "type":"Services"
        }
    ],
    "sg:phone":"+1 251 974 5477",
    "sg:postcode":"36561",
    "sg:province":"AL",
    "sg:tags":[
        "handyman"
    ],
    "wof:name":"Handy Services",
    "wof:placetype":"venue"
},
  "geometry": {"coordinates":[-87.518812,30.3056],"type":"Point"}
}