{
  "type": "Feature",
  "properties": {
    "iso:country":"US",
    "sg:address":"5566 US Hwy 431",
    "sg:city":"Brownsboro",
    "sg:classifiers":[
        {
            "category":"Manufacturing",
            "subcategory":"Building Materials",
            "type":"Manufacturing & Wholesale Goods"
        }
    ],
    "sg:phone":"+1 256 534 0102",
    "sg:postcode":"35741",
    "sg:province":"AL",
    "sg:tags":[
        "cabinet"
    ],
    "wof:name":"Woodcraft Specialties Co",
    "wof:placetype":"venue"
},
  "geometry": {"coordinates":[-86.505433,34.689613],"type":"Point"}
}