{
  "type": "Feature",
  "properties": {
    "iso:country":"US",
    "sg:address":"138 N East St",
    "sg:city":"Talladega",
    "sg:classifiers":[
        {
            "category":"Professional",
            "subcategory":"Lawyer & Legal Services",
            "type":"Services"
        }
    ],
    "sg:phone":"+1 256 362 3154",
    "sg:postcode":"35160",
    "sg:province":"AL",
    "sg:tags":[
        "attorney"
    ],
    "wof:name":"Stringer Montgomery Montgomery",
    "wof:placetype":"venue"
},
  "geometry": {"coordinates":[-86.102753,33.437304],"type":"Point"}
}