{
  "type": "Feature",
  "properties": {
    "addr:full":"17175 N Lake Dr Bay Minette AL 36507",
    "addr:housenumber":"17175",
    "addr:postcode":"36507",
    "addr:street":"N Lake Dr",
    "iso:country":"US",
    "sg:address":"17175 N Lake Dr",
    "sg:city":"Bay Minette",
    "sg:classifiers":[
        {
            "category":"Professional",
            "type":"Services"
        }
    ],
    "sg:phone":"+1 251 937 7216",
    "sg:postcode":"36507",
    "sg:province":"AL",
    "wof:name":"Security Objective Service",
    "wof:placetype":"venue"
},
  "geometry": {"coordinates":[-87.732116,30.854083],"type":"Point"}
}