{
  "type": "Feature",
  "properties": {
    "addr:full":"313 Beirne Ave NE Huntsville AL 35801",
    "addr:housenumber":"313",
    "addr:postcode":"35801",
    "addr:street":"Beirne Ave Ne",
    "iso:country":"US",
    "sg:address":"313 Beirne Ave NE",
    "sg:city":"Huntsville",
    "sg:classifiers":[
        {
            "category":"Organizations",
            "subcategory":"Religious Organization",
            "type":"Services"
        }
    ],
    "sg:phone":"+1 256 534 0270",
    "sg:postcode":"35801",
    "sg:province":"AL",
    "wof:name":"Draper Memorial",
    "wof:placetype":"venue"
},
  "geometry": {"coordinates":[-86.580651,34.740992],"type":"Point"}
}