{
  "type": "Feature",
  "properties": {
    "iso:country":"US",
    "sg:address":"4941 Court S",
    "sg:city":"Birmingham",
    "sg:classifiers":[
        {
            "category":"Social Services",
            "subcategory":"Child Care",
            "type":"Services"
        }
    ],
    "sg:phone":"+1 205 925 5001",
    "sg:postcode":"35208",
    "sg:province":"AL",
    "sg:tags":[
        "day"
    ],
    "wof:name":"Kids World",
    "wof:placetype":"venue"
},
  "geometry": {"coordinates":[-86.878477,33.487241],"type":"Point"}
}