{
  "type": "Feature",
  "properties": {
    "iso:country":"US",
    "sg:address":"1107 12th St",
    "sg:city":"Tuscaloosa",
    "sg:classifiers":[
        {
            "category":"Building & Trades",
            "subcategory":"Construction",
            "type":"Services"
        }
    ],
    "sg:phone":"+1 205 750 2066",
    "sg:postcode":"35401",
    "sg:province":"AL",
    "sg:tags":[
        "hanging",
        "contractor"
    ],
    "wof:name":"Pruitt Painting Timothy",
    "wof:placetype":"venue"
},
  "geometry": {"coordinates":[-87.553415,33.20393],"type":"Point"}
}