{
  "type": "Feature",
  "properties": {
    "iso:country":"US",
    "sg:address":"4 Hickory Ln",
    "sg:city":"Tuscaloosa",
    "sg:classifiers":[
        {
            "category":"Building & Trades",
            "subcategory":"Landscaping Services",
            "type":"Services"
        }
    ],
    "sg:phone":"+1 205 349 1861",
    "sg:postcode":"35404",
    "sg:province":"AL",
    "wof:name":"Treadway S Lawn Care",
    "wof:placetype":"venue"
},
  "geometry": {"coordinates":[-87.517114,33.187802],"type":"Point"}
}