{
  "type": "Feature",
  "properties": {
    "addr:full":"1628 Blount Ave Guntersville AL 35976",
    "addr:housenumber":"1628",
    "addr:postcode":"35976",
    "addr:street":"Blount Ave",
    "iso:country":"US",
    "sg:address":"1628 Blount Ave",
    "sg:city":"Guntersville",
    "sg:classifiers":[
        {
            "category":"Building & Trades",
            "subcategory":"Construction",
            "type":"Services"
        }
    ],
    "sg:phone":"+1 256 582 6990",
    "sg:postcode":"35976",
    "sg:province":"AL",
    "sg:tags":[
        "house",
        "builder",
        "home"
    ],
    "wof:name":"Pacific Construction",
    "wof:placetype":"venue"
},
  "geometry": {"coordinates":[-86.305797,34.342528],"type":"Point"}
}