{
  "type": "Feature",
  "properties": {
    "iso:country":"US",
    "sg:address":"2005 Mount Meigs Rd",
    "sg:city":"Montgomery",
    "sg:classifiers":[
        {
            "category":"Wholesale",
            "subcategory":"Hardware",
            "type":"Manufacturing & Wholesale Goods"
        },
        {
            "category":"Home & Garden",
            "subcategory":"Building Materials",
            "type":"Retail Goods"
        }
    ],
    "sg:phone":"+1 334 269 0014",
    "sg:postcode":"36107",
    "sg:province":"AL",
    "sg:tags":[
        "plumbing",
        "fixture",
        "supply"
    ],
    "wof:name":"Capitol Plumbing Supply LLC",
    "wof:placetype":"venue"
},
  "geometry": {"coordinates":[-86.279196,32.377834],"type":"Point"}
}