{
  "type": "Feature",
  "properties": {
    "iso:country":"US",
    "sg:address":"129 Covey Chase",
    "sg:city":"Tuscaloosa",
    "sg:classifiers":[
        {
            "category":"Health Services",
            "subcategory":"Doctor",
            "type":"Services"
        }
    ],
    "sg:phone":"+1 205 345 0650",
    "sg:postcode":"35406",
    "sg:province":"AL",
    "wof:name":"Charles E Johnson",
    "wof:placetype":"venue"
},
  "geometry": {"coordinates":[-87.535814,33.241183],"type":"Point"}
}