{
  "type": "Feature",
  "properties": {
    "iso:country":"US",
    "sg:address":"1570 Skyland Blvd E",
    "sg:city":"Tuscaloosa",
    "sg:classifiers":[
        {
            "category":"Freight",
            "type":"Transportation"
        }
    ],
    "sg:phone":"+1 205 556 2555",
    "sg:postcode":"35405",
    "sg:province":"AL",
    "sg:tags":[
        "special"
    ],
    "wof:name":"Security Storage",
    "wof:placetype":"venue"
},
  "geometry": {"coordinates":[-87.513969,33.168868],"type":"Point"}
}