{
  "type": "Feature",
  "properties": {
    "iso:country":"US",
    "sg:address":"1724 McCurdy Ave N",
    "sg:city":"Rainsville",
    "sg:classifiers":[
        {
            "category":"Shopping",
            "subcategory":"Gifts & Souvenirs",
            "type":"Retail Goods"
        }
    ],
    "sg:phone":"+1 256 638 9222",
    "sg:postcode":"35986",
    "sg:province":"AL",
    "sg:tags":[
        "shop"
    ],
    "wof:name":"Stiefel House",
    "wof:placetype":"venue"
},
  "geometry": {"coordinates":[-85.831941,34.515393],"type":"Point"}
}