{
  "type": "Feature",
  "properties": {
    "iso:country":"US",
    "sg:address":"235 Williams Rd",
    "sg:city":"Altoona",
    "sg:classifiers":[
        {
            "category":"Professional",
            "type":"Services"
        }
    ],
    "sg:phone":"+1 205 466 5767",
    "sg:postcode":"35952",
    "sg:province":"AL",
    "wof:name":"Sherrie Thompson",
    "wof:placetype":"venue"
},
  "geometry": {"coordinates":[-86.37138400000001,34.070391],"type":"Point"}
}