{
  "type": "Feature",
  "properties": {
    "addr:full":"440 Azalea Rd Mobile AL 36609",
    "addr:housenumber":"440",
    "addr:postcode":"36609",
    "addr:street":"Azalea Rd",
    "iso:country":"US",
    "sg:address":"440 Azalea Rd",
    "sg:city":"Mobile",
    "sg:classifiers":[
        {
            "category":"Building & Trades",
            "subcategory":"Construction",
            "type":"Services"
        }
    ],
    "sg:phone":"+1 251 380 0555",
    "sg:postcode":"36609",
    "sg:province":"AL",
    "sg:tags":[
        "contractor"
    ],
    "wof:name":"James Ray Builders Inc",
    "wof:placetype":"venue"
},
  "geometry": {"coordinates":[-88.15160899999999,30.667105],"type":"Point"}
}