{
  "type": "Feature",
  "properties": {
    "iso:country":"US",
    "sg:address":"1300 13th St N",
    "sg:city":"Bessemer",
    "sg:classifiers":[
        {
            "category":"Home & Garden",
            "subcategory":"Building Materials",
            "type":"Retail Goods"
        }
    ],
    "sg:phone":"+1 205 425 5218",
    "sg:postcode":"35020",
    "sg:province":"AL",
    "wof:name":"Cowboys Fence Inc",
    "wof:placetype":"venue"
},
  "geometry": {"coordinates":[-86.972006,33.403455],"type":"Point"}
}