{
  "type": "Feature",
  "properties": {
    "addr:full":"2214 Stouts Rd Birmingham AL 35234",
    "addr:housenumber":"2214",
    "addr:postcode":"35234",
    "addr:street":"Stouts Rd",
    "iso:country":"US",
    "sg:address":"2214 Stouts Rd",
    "sg:city":"Birmingham",
    "sg:classifiers":[
        {
            "category":"Arts & Performance",
            "subcategory":"Theater",
            "type":"Entertainment"
        }
    ],
    "sg:phone":"+1 205 322 7888",
    "sg:postcode":"35234",
    "sg:province":"AL",
    "sg:tags":[
        "group"
    ],
    "wof:name":"Check Mate Entertainment",
    "wof:placetype":"venue"
},
  "geometry": {"coordinates":[-86.81959999999999,33.539749],"type":"Point"}
}