{
  "type": "Feature",
  "properties": {
    "addr:full":"1211 Bridge Ave Northport AL 35476",
    "addr:housenumber":"1211",
    "addr:postcode":"35476",
    "addr:street":"Bridge Ave",
    "iso:country":"US",
    "sg:address":"1211 Bridge Ave",
    "sg:city":"Northport",
    "sg:classifiers":[
        {
            "category":"Retail",
            "subcategory":"Car Wash",
            "type":"Services"
        }
    ],
    "sg:phone":"+1 205 759 2886",
    "sg:postcode":"35476",
    "sg:province":"AL",
    "sg:tags":[
        "carwash"
    ],
    "wof:name":"Dynamic Detailing",
    "wof:placetype":"venue"
},
  "geometry": {"coordinates":[-87.57572399999999,33.224586],"type":"Point"}
}