{
  "type": "Feature",
  "properties": {
    "iso:country":"US",
    "sg:address":"880 Montclair Rd",
    "sg:city":"Birmingham",
    "sg:classifiers":[
        {
            "category":"Health Services",
            "subcategory":"Doctor",
            "type":"Services"
        }
    ],
    "sg:phone":"+1 205 271 8000",
    "sg:postcode":"35213",
    "sg:province":"AL",
    "sg:tags":[
        "physician",
        "surgeon"
    ],
    "wof:name":"Birmingham Gastroenterology",
    "wof:placetype":"venue"
},
  "geometry": {"coordinates":[-86.747856,33.514191],"type":"Point"}
}