{
  "type": "Feature",
  "properties": {
    "iso:country":"US",
    "sg:address":"1600 Brackenrich Dr",
    "sg:city":"Weaver",
    "sg:classifiers":[
        {
            "category":"Manufacturing",
            "subcategory":"Signs",
            "type":"Manufacturing & Wholesale Goods"
        }
    ],
    "sg:phone":"+1 256 820 4352",
    "sg:postcode":"36277",
    "sg:province":"AL",
    "sg:tags":[
        "specialty",
        "mfg"
    ],
    "wof:name":"Corn Crib Sign Pntg & Artwork",
    "wof:placetype":"venue"
},
  "geometry": {"coordinates":[-85.818354,33.767331],"type":"Point"}
}