{
  "type": "Feature",
  "properties": {
    "addr:full":"1916 Cobbs Ford Rd Prattville AL 36066",
    "addr:housenumber":"1916",
    "addr:postcode":"36066",
    "addr:street":"Cobbs Ford Rd",
    "iso:country":"US",
    "sg:address":"1916 Cobbs Ford Rd",
    "sg:city":"Prattville",
    "sg:classifiers":[
        {
            "category":"Banks & Credit Unions",
            "subcategory":"Bank",
            "type":"Services"
        }
    ],
    "sg:phone":"+1 334 351 0200",
    "sg:postcode":"36066",
    "sg:province":"AL",
    "wof:name":"Bank Trust Of Alabama",
    "wof:placetype":"venue"
},
  "geometry": {"coordinates":[-86.41785,32.460545],"type":"Point"}
}