{
  "type": "Feature",
  "properties": {
    "addr:full":"499 W 3rd St Sylacauga AL 35150",
    "addr:housenumber":"499",
    "addr:postcode":"35150",
    "addr:street":"W 3Rd St",
    "iso:country":"US",
    "sg:address":"499 W 3rd St",
    "sg:city":"Sylacauga",
    "sg:classifiers":[
        {
            "category":"Health Services",
            "subcategory":"Doctor",
            "type":"Services"
        }
    ],
    "sg:phone":"+1 256 245 6039",
    "sg:postcode":"35150",
    "sg:province":"AL",
    "sg:tags":[
        "dentist"
    ],
    "wof:name":"David P Currie DDS",
    "wof:placetype":"venue"
},
  "geometry": {"coordinates":[-86.25520899999999,33.171614],"type":"Point"}
}