{
  "type": "Feature",
  "properties": {
    "addr:full":"1781 Shelton Shores Dr Talladega AL 35160",
    "addr:housenumber":"1781",
    "addr:postcode":"35160",
    "addr:street":"Shelton Shores Dr Talladega",
    "iso:country":"US",
    "sg:address":"1781 Shelton Shores Dr",
    "sg:city":"Talladega",
    "sg:classifiers":[
        {
            "category":"Professional",
            "subcategory":"Accounting & Tax Preparation",
            "type":"Services"
        }
    ],
    "sg:phone":"+1 205 763 7883",
    "sg:postcode":"35160",
    "sg:province":"AL",
    "sg:tags":[
        "accountant",
        "public",
        "certified"
    ],
    "wof:name":"Brad Thomason CPA",
    "wof:placetype":"venue"
},
  "geometry": {"coordinates":[-86.150738,33.556226],"type":"Point"}
}