{
  "type": "Feature",
  "properties": {
    "addr:full":"19 The Downs Tuscaloosa AL 35401",
    "addr:housenumber":"19",
    "addr:postcode":"35401",
    "addr:street":"The Downs",
    "iso:country":"US",
    "sg:address":"19 The Downs",
    "sg:city":"Tuscaloosa",
    "sg:classifiers":[
        {
            "category":"Building & Trades",
            "subcategory":"Landscaping Services",
            "type":"Services"
        }
    ],
    "sg:phone":"+1 205 394 3825",
    "sg:postcode":"35401",
    "sg:province":"AL",
    "wof:name":"Grassroots Lawn & Landscape",
    "wof:placetype":"venue"
},
  "geometry": {"coordinates":[-87.55069399999999,33.190095],"type":"Point"}
}