{
  "type": "Feature",
  "properties": {
    "addr:full":"954 Bell St Montgomery AL 36104",
    "addr:housenumber":"954",
    "addr:postcode":"36104",
    "addr:street":"Bell St",
    "iso:country":"US",
    "sg:address":"954 Bell St",
    "sg:city":"Montgomery",
    "sg:classifiers":[
        {
            "category":"Food & Beverages",
            "subcategory":"Groceries & Convenience Stores",
            "type":"Retail Goods"
        }
    ],
    "sg:phone":"+1 334 834 2466",
    "sg:postcode":"36104",
    "sg:province":"AL",
    "wof:name":"Golden Time Grocery",
    "wof:placetype":"venue"
},
  "geometry": {"coordinates":[-86.32709199999999,32.377473],"type":"Point"}
}