{
  "type": "Feature",
  "properties": {
    "addr:full":"12678 Co Rd 65 Foley AL 36535",
    "addr:housenumber":"12678;65",
    "addr:postcode":"36535",
    "addr:street":"Co Rd",
    "iso:country":"US",
    "sg:address":"12678 Co Rd 65",
    "sg:city":"Foley",
    "sg:classifiers":[
        {
            "category":"Wholesale",
            "subcategory":"Machinery & Supplies",
            "type":"Manufacturing & Wholesale Goods"
        }
    ],
    "sg:phone":"+1 251 943 8320",
    "sg:postcode":"36535",
    "sg:province":"AL",
    "sg:tags":[
        "equipment",
        "parts",
        "tractor"
    ],
    "wof:name":"H & H Tractor & Machine Shop",
    "wof:placetype":"venue"
},
  "geometry": {"coordinates":[-87.71719299999999,30.411153],"type":"Point"}
}