{
  "type": "Feature",
  "properties": {
    "iso:country":"US",
    "sg:address":"104 6th Ave S",
    "sg:city":"Birmingham",
    "sg:classifiers":[
        {
            "category":"Restaurant",
            "type":"Food & Drink"
        }
    ],
    "sg:phone":"+1 205 322 0994",
    "sg:postcode":"35205",
    "sg:province":"AL",
    "sg:tags":[
        "eating"
    ],
    "wof:name":"Leonards Bar B Q & Burger Hut",
    "wof:placetype":"venue"
},
  "geometry": {"coordinates":[-86.826909,33.494602],"type":"Point"}
}