{
  "type": "Feature",
  "properties": {
    "iso:country":"US",
    "sg:address":"1423 Gadsden Hwy",
    "sg:city":"Birmingham",
    "sg:classifiers":[
        {
            "category":"Banks & Credit Unions",
            "subcategory":"Bank",
            "type":"Services"
        }
    ],
    "sg:phone":"+1 205 661 9882",
    "sg:postcode":"35235",
    "sg:province":"AL",
    "sg:tags":[
        "cashing",
        "check"
    ],
    "wof:name":"Check 'n Go",
    "wof:placetype":"venue"
},
  "geometry": {"coordinates":[-86.646244,33.595478],"type":"Point"}
}