{
  "type": "Feature",
  "properties": {
    "addr:full":"1931 Cobbs Ford Rd Prattville AL 36066",
    "addr:housenumber":"1931",
    "addr:postcode":"36066",
    "addr:street":"Cobbs Ford Rd",
    "iso:country":"US",
    "sg:address":"1931 Cobbs Ford Rd",
    "sg:city":"Prattville",
    "sg:classifiers":[
        {
            "category":"Shopping",
            "subcategory":"Computers & Home Electronics",
            "type":"Retail Goods"
        }
    ],
    "sg:phone":"+1 334 358 0910",
    "sg:postcode":"36066",
    "sg:province":"AL",
    "wof:name":"Radio Shack",
    "wof:placetype":"venue"
},
  "geometry": {"coordinates":[-86.417956,32.460406],"type":"Point"}
}