{
  "type": "Feature",
  "properties": {
    "addr:full":"2330 University Blvd Tuscaloosa AL 35401",
    "addr:housenumber":"2330",
    "addr:postcode":"35401",
    "addr:street":"University Blvd",
    "iso:country":"US",
    "sg:address":"2330 University Blvd",
    "sg:city":"Tuscaloosa",
    "sg:classifiers":[
        {
            "category":"Professional",
            "subcategory":"Lawyer & Legal Services",
            "type":"Services"
        }
    ],
    "sg:phone":"+1 205 342 3622",
    "sg:postcode":"35401",
    "sg:province":"AL",
    "sg:tags":[
        "attorney"
    ],
    "wof:name":"Dennis Harmon",
    "wof:placetype":"venue"
},
  "geometry": {"coordinates":[-87.56799599999999,33.210087],"type":"Point"}
}