{
  "type": "Feature",
  "properties": {
    "addr:full":"800 Montclair Rd Birmingham AL 35213",
    "addr:housenumber":"800",
    "addr:postcode":"35213",
    "addr:street":"Montclair Rd",
    "iso:country":"US",
    "sg:address":"800 Montclair Rd",
    "sg:city":"Birmingham",
    "sg:classifiers":[
        {
            "category":"Health Services",
            "subcategory":"Doctor",
            "type":"Services"
        }
    ],
    "sg:phone":"+1 205 592 5318",
    "sg:postcode":"35213",
    "sg:province":"AL",
    "sg:tags":[
        "physician",
        "surgeon"
    ],
    "wof:name":"A Fc Plastic & Reconstructive",
    "wof:placetype":"venue"
},
  "geometry": {"coordinates":[-86.744749,33.516504],"type":"Point"}
}