{
  "type": "Feature",
  "properties": {
    "iso:country":"US",
    "sg:address":"1250 W Grand Ave",
    "sg:city":"Rainbow City",
    "sg:classifiers":[
        {
            "category":"Autos & Motor Vehicles",
            "subcategory":"Auto Supplies",
            "type":"Retail Goods"
        }
    ],
    "sg:phone":"+1 256 442 4418",
    "sg:postcode":"35906",
    "sg:province":"AL",
    "sg:tags":[
        "tire"
    ],
    "wof:name":"O K Tire Svc",
    "wof:placetype":"venue"
},
  "geometry": {"coordinates":[-86.068135,33.981644],"type":"Point"}
}