{
  "type": "Feature",
  "properties": {
    "iso:country":"US",
    "sg:address":"1015 US Hwy 431",
    "sg:city":"Anniston",
    "sg:classifiers":[
        {
            "category":"Travel",
            "subcategory":"Hotels & Motels",
            "type":"Entertainment"
        }
    ],
    "sg:phone":"+1 256 237 2525",
    "sg:postcode":"36206",
    "sg:province":"AL",
    "sg:tags":[
        "operation"
    ],
    "wof:name":"Villager Lodge",
    "wof:placetype":"venue"
},
  "geometry": {"coordinates":[-85.832234,33.703416],"type":"Point"}
}