{
  "type": "Feature",
  "properties": {
    "addr:full":"105 2nd Ave NW Fayette AL 35555",
    "addr:housenumber":"105",
    "addr:postcode":"35555",
    "addr:street":"2Nd Ave Nw",
    "iso:country":"US",
    "sg:address":"105 2nd Ave NW",
    "sg:city":"Fayette",
    "sg:classifiers":[
        {
            "category":"Real Estate",
            "subcategory":"Architect",
            "type":"Services"
        }
    ],
    "sg:phone":"+1 205 932 7810",
    "sg:postcode":"35555",
    "sg:province":"AL",
    "sg:tags":[
        "architectural"
    ],
    "wof:name":"Jim Berry Associated Architect",
    "wof:placetype":"venue"
},
  "geometry": {"coordinates":[-87.83265299999999,33.685933],"type":"Point"}
}