{
  "type": "Feature",
  "properties": {
    "iso:country":"US",
    "sg:address":"1821 Timber Ln NE",
    "sg:city":"Fort Payne",
    "sg:classifiers":[
        {
            "category":"Professional",
            "type":"Services"
        }
    ],
    "sg:phone":"+1 256 845 2656",
    "sg:postcode":"35967",
    "sg:province":"AL",
    "wof:name":"Wayne Whitley",
    "wof:placetype":"venue"
},
  "geometry": {"coordinates":[-85.606831,34.482314],"type":"Point"}
}