{
  "type": "Feature",
  "properties": {
    "iso:country":"US",
    "sg:address":"5200 1st Ave N",
    "sg:city":"Birmingham",
    "sg:classifiers":[
        {
            "category":"Organizations",
            "subcategory":"Community Association",
            "type":"Services"
        }
    ],
    "sg:phone":"+1 205 592 2555",
    "sg:postcode":"35212",
    "sg:province":"AL",
    "sg:tags":[
        "military"
    ],
    "wof:name":"American Legion",
    "wof:placetype":"venue"
},
  "geometry": {"coordinates":[-86.757654,33.537208],"type":"Point"}
}