{
  "type": "Feature",
  "properties": {
    "addr:full":"5843 Co Rd 189 Florence AL 35633",
    "addr:housenumber":"5843",
    "addr:postcode":"35633",
    "addr:street":"Co Rd 189",
    "iso:country":"US",
    "sg:address":"5843 Co Rd 189",
    "sg:city":"Florence",
    "sg:classifiers":[
        {
            "category":"Restaurant",
            "type":"Food & Drink"
        }
    ],
    "sg:phone":"+1 256 764 8304",
    "sg:postcode":"35633",
    "sg:province":"AL",
    "wof:name":"Rhodesville Cafe",
    "wof:placetype":"venue"
},
  "geometry": {"coordinates":[-87.868521,34.861159],"type":"Point"}
}