{
  "type": "Feature",
  "properties": {
    "iso:country":"US",
    "sg:address":"204 Jackson Ave N",
    "sg:city":"Russellville",
    "sg:classifiers":[
        {
            "category":"Government",
            "subcategory":"Office",
            "type":"Public Place"
        }
    ],
    "sg:phone":"+1 256 332 8111",
    "sg:postcode":"35653",
    "sg:province":"AL",
    "sg:tags":[
        "transportation"
    ],
    "wof:name":"Project Engineers Office",
    "wof:placetype":"venue"
},
  "geometry": {"coordinates":[-87.728915,34.507573],"type":"Point"}
}