{
  "type": "Feature",
  "properties": {
    "iso:country":"US",
    "sg:address":"3122 Mountain Brow Rd",
    "sg:city":"Oxford",
    "sg:classifiers":[
        {
            "category":"Restaurant",
            "type":"Food & Drink"
        }
    ],
    "sg:phone":"+1 256 831 4330",
    "sg:postcode":"36203",
    "sg:province":"AL",
    "sg:tags":[
        "eating"
    ],
    "wof:name":"Ricky Noell",
    "wof:placetype":"venue"
},
  "geometry": {"coordinates":[-85.887916,33.594334],"type":"Point"}
}