{
  "type": "Feature",
  "properties": {
    "addr:full":"1020 Bankhead Hwy W Birmingham AL 35204",
    "addr:housenumber":"1020",
    "addr:postcode":"35204",
    "addr:street":"Bankhead Hwy W",
    "iso:country":"US",
    "sg:address":"1020 Bankhead Hwy W",
    "sg:city":"Birmingham",
    "sg:classifiers":[
        {
            "category":"Professional",
            "type":"Services"
        }
    ],
    "sg:phone":"+1 205 251 1557",
    "sg:postcode":"35204",
    "sg:province":"AL",
    "sg:tags":[
        "establishment"
    ],
    "wof:name":"Arcadis G & M",
    "wof:placetype":"venue"
},
  "geometry": {"coordinates":[-86.854956,33.531958],"type":"Point"}
}