{
  "type": "Feature",
  "properties": {
    "addr:full":"1586 Montgomery Hwy Birmingham AL 35216",
    "addr:housenumber":"1586",
    "addr:postcode":"35216",
    "addr:street":"Montgomery Hwy",
    "iso:country":"US",
    "sg:address":"1586 Montgomery Hwy",
    "sg:city":"Birmingham",
    "sg:classifiers":[
        {
            "category":"Shopping",
            "type":"Retail Goods"
        }
    ],
    "sg:phone":"+1 205 823 7033",
    "sg:postcode":"35216",
    "sg:province":"AL",
    "sg:tags":[
        "merchandise"
    ],
    "wof:name":"Advanced Payphone Distributors",
    "wof:placetype":"venue"
},
  "geometry": {"coordinates":[-86.806028,33.400222],"type":"Point"}
}