{
  "type": "Feature",
  "properties": {
    "iso:country":"US",
    "sg:address":"302 Lovejoy Pl",
    "sg:city":"Gadsden",
    "sg:classifiers":[
        {
            "category":"Freight",
            "type":"Transportation"
        }
    ],
    "sg:phone":"+1 256 546 7632",
    "sg:postcode":"35904",
    "sg:province":"AL",
    "sg:tags":[
        "operator",
        "trucking"
    ],
    "wof:name":"F&J Co LLC",
    "wof:placetype":"venue"
},
  "geometry": {"coordinates":[-86.016995,34.04204],"type":"Point"}
}