{
  "type": "Feature",
  "properties": {
    "addr:full":"6290 Co Rd 490 Hanceville AL 35077",
    "addr:housenumber":"6290",
    "addr:postcode":"490;35077",
    "addr:street":"Co Rd",
    "iso:country":"US",
    "sg:address":"6290 Co Rd 490",
    "sg:city":"Hanceville",
    "sg:classifiers":[
        {
            "category":"Retail",
            "subcategory":"Auto Repair",
            "type":"Services"
        }
    ],
    "sg:phone":"+1 256 734 5823",
    "sg:postcode":"35077",
    "sg:province":"AL",
    "sg:tags":[
        "automobile",
        "lubrication",
        "general"
    ],
    "wof:name":"Truck Express Lube Inc",
    "wof:placetype":"venue"
},
  "geometry": {"coordinates":[-86.862292,34.058879],"type":"Point"}
}