{
  "type": "Feature",
  "properties": {
    "iso:country":"US",
    "sg:address":"805 Steele Station Rd",
    "sg:city":"Rainbow City",
    "sg:classifiers":[
        {
            "category":"Recreation",
            "type":"Entertainment"
        }
    ],
    "sg:phone":"+1 256 442 3517",
    "sg:postcode":"35906",
    "sg:province":"AL",
    "sg:tags":[
        "instruction",
        "gymnastic"
    ],
    "wof:name":"Champions Gymnastics Club",
    "wof:placetype":"venue"
},
  "geometry": {"coordinates":[-86.05367,33.977143],"type":"Point"}
}