{
  "type": "Feature",
  "properties": {
    "iso:country":"US",
    "sg:address":"1590 Youngs Chapel Rd",
    "sg:city":"Piedmont",
    "sg:classifiers":[
        {
            "category":"Building & Trades",
            "subcategory":"Construction",
            "type":"Services"
        }
    ],
    "sg:phone":"+1 256 492 0606",
    "sg:postcode":"36272",
    "sg:province":"AL",
    "sg:tags":[
        "house"
    ],
    "wof:name":"Jim Christopher Cnstr LLC",
    "wof:placetype":"venue"
},
  "geometry": {"coordinates":[-85.780167,33.994769],"type":"Point"}
}