{
  "type": "Feature",
  "properties": {
    "addr:full":"6111 Deramus Ave NW Huntsville AL 35806",
    "addr:housenumber":"6111",
    "addr:postcode":"35806",
    "addr:street":"Deramus Ave Nw",
    "iso:country":"US",
    "sg:address":"6111 Deramus Ave NW",
    "sg:city":"Huntsville",
    "sg:classifiers":[
        {
            "category":"Professional",
            "type":"Services"
        }
    ],
    "sg:phone":"+1 256 683 1078",
    "sg:postcode":"35806",
    "sg:province":"AL",
    "wof:name":"William Otis Collins Svc",
    "wof:placetype":"venue"
},
  "geometry": {"coordinates":[-86.66014199999999,34.717356],"type":"Point"}
}