{
  "type": "Feature",
  "properties": {
    "iso:country":"US",
    "sg:address":"225 Ann St",
    "sg:city":"Montgomery",
    "sg:classifiers":[
        {
            "category":"Education",
            "subcategory":"School",
            "type":"Public Place"
        }
    ],
    "sg:phone":"+1 334 269 3742",
    "sg:postcode":"36107",
    "sg:province":"AL",
    "wof:name":"Lee High School",
    "wof:placetype":"venue"
},
  "geometry": {"coordinates":[-86.272148,32.377537],"type":"Point"}
}