{
  "type": "Feature",
  "properties": {
    "addr:full":"29 Co Rd 940 Cullman AL 35057",
    "addr:housenumber":"29",
    "addr:postcode":"35057",
    "addr:street":"Co Rd 940",
    "iso:country":"US",
    "sg:address":"29 Co Rd 940",
    "sg:city":"Cullman",
    "sg:classifiers":[
        {
            "category":"Shopping",
            "subcategory":"Department Store",
            "type":"Retail Goods"
        }
    ],
    "sg:phone":"+1 256 747 4992",
    "sg:postcode":"35057",
    "sg:province":"AL",
    "sg:tags":[
        "shop"
    ],
    "wof:name":"Family Dollar Store",
    "wof:placetype":"venue"
},
  "geometry": {"coordinates":[-87.05228099999999,34.209821],"type":"Point"}
}