{
  "type": "Feature",
  "properties": {
    "addr:full":"204 59th St S Birmingham AL 35212",
    "addr:housenumber":"204",
    "addr:postcode":"35212",
    "addr:street":"59Th St S",
    "iso:country":"US",
    "sg:address":"204 59th St S",
    "sg:city":"Birmingham",
    "sg:classifiers":[
        {
            "category":"Real Estate",
            "subcategory":"Real Estate Operator",
            "type":"Services"
        }
    ],
    "sg:phone":"+1 205 591 8039",
    "sg:postcode":"35212",
    "sg:province":"AL",
    "sg:tags":[
        "apartment"
    ],
    "wof:name":"Don West Manor-Handicapped",
    "wof:placetype":"venue"
},
  "geometry": {"coordinates":[-86.74786899999999,33.541381],"type":"Point"}
}