{
  "type": "Feature",
  "properties": {
    "addr:full":"3250 Wetumpka Hwy Montgomery AL 36110",
    "addr:housenumber":"3250",
    "addr:postcode":"36110",
    "addr:street":"Wetumpka Hwy",
    "iso:country":"US",
    "sg:address":"3250 Wetumpka Hwy",
    "sg:city":"Montgomery",
    "sg:classifiers":[
        {
            "category":"Sports & Exercise",
            "subcategory":"Golf",
            "type":"Entertainment"
        },
        {
            "category":"Recreation",
            "type":"Entertainment"
        }
    ],
    "sg:phone":"+1 334 279 5318",
    "sg:postcode":"36110",
    "sg:province":"AL",
    "sg:tags":[
        "shop",
        "driving",
        "practice",
        "course",
        "range",
        "retail",
        "public"
    ],
    "wof:name":"Cypress Farms Golf Center",
    "wof:placetype":"venue"
},
  "geometry": {"coordinates":[-86.218119,32.436713],"type":"Point"}
}