{
  "type": "Feature",
  "properties": {
    "iso:country":"US",
    "sg:address":"1567 Co Rd 327",
    "sg:city":"Danville",
    "sg:classifiers":[
        {
            "category":"Home & Garden",
            "subcategory":"Furniture",
            "type":"Retail Goods"
        }
    ],
    "sg:phone":"+1 256 350 5100",
    "sg:postcode":"35619",
    "sg:province":"AL",
    "wof:name":"Premier Furniture",
    "wof:placetype":"venue"
},
  "geometry": {"coordinates":[-87.122872,34.492729],"type":"Point"}
}