{
  "type": "Feature",
  "properties": {
    "addr:full":"1 Commerce Sq Gadsden AL 35901",
    "addr:housenumber":"1",
    "addr:postcode":"35901",
    "addr:street":"Commerce Sq",
    "iso:country":"US",
    "sg:address":"1 Commerce Sq",
    "sg:city":"Gadsden",
    "sg:classifiers":[
        {
            "category":"Health Services",
            "subcategory":"Doctor",
            "type":"Services"
        }
    ],
    "sg:phone":"+1 256 547 3122",
    "sg:postcode":"35901",
    "sg:province":"AL",
    "sg:tags":[
        "physician",
        "surgeon"
    ],
    "wof:name":"Medical Society Of Etowah Cnty",
    "wof:placetype":"venue"
},
  "geometry": {"coordinates":[-86.001531,34.010034],"type":"Point"}
}