{
  "type": "Feature",
  "properties": {
    "iso:country":"US",
    "sg:address":"2301 15th Ave",
    "sg:city":"Northport",
    "sg:classifiers":[
        {
            "category":"Wholesale",
            "subcategory":"Non-durable Goods",
            "type":"Manufacturing & Wholesale Goods"
        }
    ],
    "sg:phone":"+1 205 330 1417",
    "sg:postcode":"35476",
    "sg:province":"AL",
    "wof:name":"PC Distribution",
    "wof:placetype":"venue"
},
  "geometry": {"coordinates":[-87.57275,33.231661],"type":"Point"}
}