{
  "type": "Feature",
  "properties": {
    "addr:full":"13775 S Wintzell Ave Bayou La Batre AL 36509",
    "addr:housenumber":"13775",
    "addr:postcode":"36509",
    "addr:street":"S Wintzell Ave Bayou La",
    "iso:country":"US",
    "sg:address":"13775 S Wintzell Ave",
    "sg:city":"Bayou La Batre",
    "sg:classifiers":[
        {
            "category":"Government",
            "subcategory":"Fire Station",
            "type":"Public Place"
        }
    ],
    "sg:phone":"+1 251 824 2133",
    "sg:postcode":"36509",
    "sg:province":"AL",
    "sg:tags":[
        "department"
    ],
    "wof:name":"Bayou LA Batre Fire Dept",
    "wof:placetype":"venue"
},
  "geometry": {"coordinates":[-88.24771,30.405254],"type":"Point"}
}