{
  "type": "Feature",
  "properties": {
    "addr:full":"3780 Lorna Rd Birmingham AL 35216",
    "addr:housenumber":"3780",
    "addr:postcode":"35216",
    "addr:street":"Lorna Rd",
    "iso:country":"US",
    "sg:address":"3780 Lorna Rd",
    "sg:city":"Birmingham",
    "sg:classifiers":[
        {
            "category":"Cinema",
            "subcategory":"Movie Rental",
            "type":"Entertainment"
        }
    ],
    "sg:phone":"+1 205 987 9001",
    "sg:postcode":"35216",
    "sg:province":"AL",
    "sg:tags":[
        "leasing",
        "video",
        "disc",
        "tape"
    ],
    "sg:website":"www.blockbuster.com",
    "wof:name":"Blockbuster Video",
    "wof:placetype":"venue"
},
  "geometry": {"coordinates":[-86.802421,33.377904],"type":"Point"}
}