{
  "type": "Feature",
  "properties": {
    "addr:full":"912 Van Ave Daphne AL 36526",
    "addr:housenumber":"912",
    "addr:postcode":"36526",
    "addr:street":"Van Ave",
    "iso:country":"US",
    "sg:address":"912 Van Ave",
    "sg:city":"Daphne",
    "sg:classifiers":[
        {
            "category":"Personal",
            "subcategory":"Beauty Salon",
            "type":"Services"
        }
    ],
    "sg:phone":"+1 251 621 3915",
    "sg:postcode":"36526",
    "sg:province":"AL",
    "sg:tags":[
        "shop"
    ],
    "wof:name":"Above Sill",
    "wof:placetype":"venue"
},
  "geometry": {"coordinates":[-87.900598,30.597791],"type":"Point"}
}