{
  "type": "Feature",
  "properties": {
    "iso:country":"US",
    "sg:address":"1110 Leroy Stevens Rd",
    "sg:city":"Mobile",
    "sg:classifiers":[
        {
            "category":"Personal",
            "type":"Services"
        }
    ],
    "sg:phone":"+1 251 633 7887",
    "sg:postcode":"36695",
    "sg:province":"AL",
    "wof:name":"Modern Tans",
    "wof:placetype":"venue"
},
  "geometry": {"coordinates":[-88.23599,30.669372],"type":"Point"}
}