{
  "type": "Feature",
  "properties": {
    "addr:full":"11622 Chigger Ridge Rd Brookwood AL 35444",
    "addr:housenumber":"11622",
    "addr:postcode":"35444",
    "addr:street":"Chigger Ridge Rd",
    "iso:country":"US",
    "sg:address":"11622 Chigger Ridge Rd",
    "sg:city":"Brookwood",
    "sg:classifiers":[
        {
            "category":"Retail",
            "subcategory":"Repair Shop",
            "type":"Services"
        }
    ],
    "sg:phone":"+1 205 556 9484",
    "sg:postcode":"35444",
    "sg:province":"AL",
    "wof:name":"Harrys Septic Tank Services",
    "wof:placetype":"venue"
},
  "geometry": {"coordinates":[-87.341487,33.243166],"type":"Point"}
}