{
  "type": "Feature",
  "properties": {
    "addr:full":"12160 State Rte 104 Fairhope AL 36532",
    "addr:housenumber":"12160",
    "addr:postcode":"36532",
    "addr:street":"State Rte 104",
    "iso:country":"US",
    "sg:address":"12160 State Rte 104",
    "sg:city":"Fairhope",
    "sg:classifiers":[
        {
            "category":"Building & Trades",
            "subcategory":"Construction",
            "type":"Services"
        }
    ],
    "sg:phone":"+1 251 928 8046",
    "sg:postcode":"36532",
    "sg:province":"AL",
    "sg:tags":[
        "general",
        "contractor"
    ],
    "wof:name":"Mabry Stone Builder & Realtor",
    "wof:placetype":"venue"
},
  "geometry": {"coordinates":[-87.815944,30.545437],"type":"Point"}
}