{
  "type": "Feature",
  "properties": {
    "addr:full":"3511 Napier Field Rd Dothan AL 36303",
    "addr:housenumber":"3511",
    "addr:postcode":"36303",
    "addr:street":"Napier Field Rd",
    "iso:country":"US",
    "sg:address":"3511 Napier Field Rd",
    "sg:city":"Dothan",
    "sg:classifiers":[
        {
            "category":"Autos & Motor Vehicles",
            "subcategory":"Automobile Sales",
            "type":"Retail Goods"
        }
    ],
    "sg:phone":"+1 334 983 9338",
    "sg:postcode":"36303",
    "sg:province":"AL",
    "sg:tags":[
        "car",
        "dealer"
    ],
    "wof:name":"American Dream Used Cars",
    "wof:placetype":"venue"
},
  "geometry": {"coordinates":[-85.447435,31.278581],"type":"Point"}
}