{
  "type": "Feature",
  "properties": {
    "addr:full":"3750 Airport Blvd Mobile AL 36608",
    "addr:housenumber":"3750",
    "addr:postcode":"36608",
    "addr:street":"Airport Blvd",
    "iso:country":"US",
    "sg:address":"3750 Airport Blvd",
    "sg:city":"Mobile",
    "sg:classifiers":[
        {
            "category":"Professional",
            "subcategory":"Business Services",
            "type":"Services"
        }
    ],
    "sg:phone":"+1 251 460 4096",
    "sg:postcode":"36608",
    "sg:province":"AL",
    "wof:name":"UPS Stores The",
    "wof:placetype":"venue"
},
  "geometry": {"coordinates":[-88.137152,30.67611],"type":"Point"}
}