{
  "type": "Feature",
  "properties": {
    "iso:country":"US",
    "sg:address":"1033 22nd St S",
    "sg:city":"Birmingham",
    "sg:classifiers":[
        {
            "category":"Real Estate",
            "subcategory":"Real Estate Operator",
            "type":"Services"
        }
    ],
    "sg:phone":"+1 205 226 8666",
    "sg:postcode":"35205",
    "sg:province":"AL",
    "sg:tags":[
        "apartment"
    ],
    "wof:name":"Canterbury Gardens Apts",
    "wof:placetype":"venue"
},
  "geometry": {"coordinates":[-86.79239,33.50289],"type":"Point"}
}