{
  "type": "Feature",
  "properties": {
    "iso:country":"US",
    "sg:address":"5327 Halls Mill Rd",
    "sg:city":"Mobile",
    "sg:classifiers":[
        {
            "category":"Bakery",
            "type":"Food & Drink"
        }
    ],
    "sg:menulink":"http://www.allmenus.com/al/mobile/99925-golden-corral/menu/",
    "sg:phone":"+1 251 660 7122",
    "sg:postcode":"36619",
    "sg:province":"AL",
    "sg:tags":[
        "american",
        "pastry"
    ],
    "wof:name":"Golden Corral",
    "wof:placetype":"venue"
},
  "geometry": {"coordinates":[-88.16430699999999,30.595737],"type":"Point"}
}