{
  "type": "Feature",
  "properties": {
    "iso:country":"US",
    "sg:address":"1975 Co Rd 63",
    "sg:city":"Prattville",
    "sg:classifiers":[
        {
            "category":"Organizations",
            "subcategory":"Religious Organization",
            "type":"Services"
        }
    ],
    "sg:phone":"+1 334 358 9388",
    "sg:postcode":"36067",
    "sg:province":"AL",
    "sg:tags":[
        "church"
    ],
    "wof:name":"Church Of Jesus Christ House",
    "wof:placetype":"venue"
},
  "geometry": {"coordinates":[-86.573909,32.557778],"type":"Point"}
}