{
  "type": "Feature",
  "properties": {
    "iso:country":"US",
    "sg:address":"131 Old Ladiga Rd",
    "sg:city":"Piedmont",
    "sg:classifiers":[
        {
            "category":"Wholesale",
            "subcategory":"Machinery & Supplies",
            "type":"Manufacturing & Wholesale Goods"
        }
    ],
    "sg:phone":"+1 256 447 7728",
    "sg:postcode":"36272",
    "sg:province":"AL",
    "sg:tags":[
        "equipment",
        "industrial"
    ],
    "wof:name":"Piedmont Equipment & Hydraulic",
    "wof:placetype":"venue"
},
  "geometry": {"coordinates":[-85.598854,33.926769],"type":"Point"}
}