{
  "type": "Feature",
  "properties": {
    "iso:country":"US",
    "sg:address":"2305 Governors Dr SW",
    "sg:city":"Huntsville",
    "sg:classifiers":[
        {
            "category":"Autos & Motor Vehicles",
            "subcategory":"Fuel & Gas Station",
            "type":"Retail Goods"
        }
    ],
    "sg:phone":"+1 256 534 7315",
    "sg:postcode":"35805",
    "sg:province":"AL",
    "sg:tags":[
        "oil"
    ],
    "wof:name":"Sam's Mini Mart",
    "wof:placetype":"venue"
},
  "geometry": {"coordinates":[-86.596995,34.719824],"type":"Point"}
}