{
  "type": "Feature",
  "properties": {
    "iso:country":"US",
    "sg:address":"289 Dunloe Dr",
    "sg:city":"Madison",
    "sg:classifiers":[
        {
            "category":"Retail",
            "subcategory":"Repair Shop",
            "type":"Services"
        }
    ],
    "sg:phone":"+1 256 730 5570",
    "sg:postcode":"35757",
    "sg:province":"AL",
    "sg:tags":[
        "related"
    ],
    "wof:name":"Teranetix Repair Operation",
    "wof:placetype":"venue"
},
  "geometry": {"coordinates":[-86.735975,34.793651],"type":"Point"}
}