{
  "type": "Feature",
  "properties": {
    "iso:country":"US",
    "sg:address":"331 16th Ave S",
    "sg:city":"Birmingham",
    "sg:classifiers":[
        {
            "category":"Recreation",
            "type":"Entertainment"
        }
    ],
    "sg:phone":"+1 205 252 0038",
    "sg:postcode":"35205",
    "sg:province":"AL",
    "sg:tags":[
        "tennis",
        "court"
    ],
    "wof:name":"George Ward Tennis Ctr",
    "wof:placetype":"venue"
},
  "geometry": {"coordinates":[-86.821491,33.491368],"type":"Point"}
}