{
  "type": "Feature",
  "properties": {
    "addr:full":"507 Jacona St Chickasaw AL 36611",
    "addr:housenumber":"507",
    "addr:postcode":"36611",
    "addr:street":"Jacona St",
    "iso:country":"US",
    "sg:address":"507 Jacona St",
    "sg:city":"Chickasaw",
    "sg:classifiers":[
        {
            "category":"Organizations",
            "subcategory":"Religious Organization",
            "type":"Services"
        }
    ],
    "sg:phone":"+1 251 457 2436",
    "sg:postcode":"36611",
    "sg:province":"AL",
    "sg:tags":[
        "church"
    ],
    "wof:name":"Christian Fellowship Church",
    "wof:placetype":"venue"
},
  "geometry": {"coordinates":[-88.08578799999999,30.765659],"type":"Point"}
}