{
  "type": "Feature",
  "properties": {
    "iso:country":"US",
    "sg:address":"1661 Brewster Rd",
    "sg:city":"Birmingham",
    "sg:classifiers":[
        {
            "category":"Organizations",
            "subcategory":"Religious Organization",
            "type":"Services"
        }
    ],
    "sg:phone":"+1 205 853 0378",
    "sg:postcode":"35235",
    "sg:province":"AL",
    "wof:name":"Brewster Road Baptist Church",
    "wof:placetype":"venue"
},
  "geometry": {"coordinates":[-86.655393,33.625784],"type":"Point"}
}