{
  "type": "Feature",
  "properties": {
    "iso:country":"US",
    "sg:address":"1263 Old Railroad Bed Rd",
    "sg:city":"Madison",
    "sg:classifiers":[
        {
            "category":"Retail",
            "subcategory":"Auto Repair",
            "type":"Services"
        }
    ],
    "sg:phone":"+1 256 895 0266",
    "sg:postcode":"35757",
    "sg:province":"AL",
    "wof:name":"A Best Value Auto Parts",
    "wof:placetype":"venue"
},
  "geometry": {"coordinates":[-86.785875,34.765775],"type":"Point"}
}