{
  "type": "Feature",
  "properties": {
    "iso:country":"US",
    "sg:address":"6253 Ferguson Ln",
    "sg:city":"Gardendale",
    "sg:classifiers":[
        {
            "category":"Building & Trades",
            "subcategory":"Construction",
            "type":"Services"
        }
    ],
    "sg:phone":"+1 205 870 7817",
    "sg:postcode":"35071",
    "sg:province":"AL",
    "sg:tags":[
        "contractor"
    ],
    "wof:name":"G&E GUTter&window Co Inc",
    "wof:placetype":"venue"
},
  "geometry": {"coordinates":[-86.81142199999999,33.687479],"type":"Point"}
}