{
  "type": "Feature",
  "properties": {
    "addr:full":"10156 Co Rd 51 Jemison AL 35085",
    "addr:housenumber":"10156;51",
    "addr:postcode":"35085",
    "addr:street":"Co Rd",
    "iso:country":"US",
    "sg:address":"10156 Co Rd 51",
    "sg:city":"Jemison",
    "sg:classifiers":[
        {
            "category":"Building & Trades",
            "subcategory":"Electrical",
            "type":"Services"
        }
    ],
    "sg:phone":"+1 205 646 1117",
    "sg:postcode":"35085",
    "sg:province":"AL",
    "sg:tags":[
        "electric",
        "contractor"
    ],
    "wof:name":"C J Electric",
    "wof:placetype":"venue"
},
  "geometry": {"coordinates":[-86.662943,32.970249],"type":"Point"}
}