{
  "type": "Feature",
  "properties": {
    "iso:country":"US",
    "sg:address":"917 Tate Dr",
    "sg:city":"Dothan",
    "sg:classifiers":[
        {
            "category":"Wholesale",
            "subcategory":"Auto Parts",
            "type":"Manufacturing & Wholesale Goods"
        }
    ],
    "sg:phone":"+1 334 678 1522",
    "sg:postcode":"36301",
    "sg:province":"AL",
    "sg:tags":[
        "automotive",
        "tire"
    ],
    "wof:name":"Hornsby Tire",
    "wof:placetype":"venue"
},
  "geometry": {"coordinates":[-85.40523899999999,31.204649],"type":"Point"}
}