{
  "type": "Feature",
  "properties": {
    "addr:full":"2512 Lurleen B Wallace Blvd Northport AL 35476",
    "addr:housenumber":"2512;b",
    "addr:postcode":"35476",
    "addr:street":"Lurleen;Wallace Blvd",
    "iso:country":"US",
    "sg:address":"2512 Lurleen B Wallace Blvd",
    "sg:city":"Northport",
    "sg:classifiers":[
        {
            "category":"Professional",
            "subcategory":"Management & Consulting",
            "type":"Services"
        }
    ],
    "sg:phone":"+1 205 333 9090",
    "sg:postcode":"35476",
    "sg:province":"AL",
    "sg:tags":[
        "consultant",
        "business"
    ],
    "wof:name":"Education Research Ctr",
    "wof:placetype":"venue"
},
  "geometry": {"coordinates":[-87.576598,33.234681],"type":"Point"}
}