{
  "type": "Feature",
  "properties": {
    "addr:full":"48 Medical Park Dr E Birmingham AL 35235",
    "addr:housenumber":"48",
    "addr:postcode":"35235",
    "addr:street":"Medical Park Dr E",
    "iso:country":"US",
    "sg:address":"48 Medical Park Dr E",
    "sg:city":"Birmingham",
    "sg:classifiers":[
        {
            "category":"Health Services",
            "subcategory":"Doctor",
            "type":"Services"
        }
    ],
    "sg:phone":"+1 205 838 1811",
    "sg:postcode":"35235",
    "sg:province":"AL",
    "sg:tags":[
        "dermatologist"
    ],
    "wof:name":"Payne Rex R Dr",
    "wof:placetype":"venue"
},
  "geometry": {"coordinates":[-86.665802,33.594299],"type":"Point"}
}