{
  "type": "Feature",
  "properties": {
    "iso:country":"US",
    "sg:address":"5726 Bent Creek Dr",
    "sg:city":"Pinson",
    "sg:classifiers":[
        {
            "category":"Restaurant",
            "type":"Food & Drink"
        }
    ],
    "sg:phone":"+1 205 680 6685",
    "sg:postcode":"35126",
    "sg:province":"AL",
    "sg:tags":[
        "eating"
    ],
    "wof:name":"Catering By Netta",
    "wof:placetype":"venue"
},
  "geometry": {"coordinates":[-86.624293,33.710859],"type":"Point"}
}