{
  "type": "Feature",
  "properties": {
    "iso:country":"US",
    "sg:address":"102 E Dr Hicks Blvd",
    "sg:city":"Florence",
    "sg:classifiers":[
        {
            "category":"Banks & Credit Unions",
            "subcategory":"Bank",
            "type":"Services"
        }
    ],
    "sg:phone":"+1 256 767 8290",
    "sg:postcode":"35630",
    "sg:province":"AL",
    "sg:website":"www.southtrust.com",
    "wof:name":"South Trust Bank",
    "wof:placetype":"venue"
},
  "geometry": {"coordinates":[-87.672865,34.797967],"type":"Point"}
}