{
  "type": "Feature",
  "properties": {
    "iso:country":"US",
    "sg:address":"928 Pine Hill Rd",
    "sg:city":"Birmingham",
    "sg:classifiers":[
        {
            "category":"Building & Trades",
            "subcategory":"Construction",
            "type":"Services"
        }
    ],
    "sg:phone":"+1 205 520 5172",
    "sg:postcode":"35235",
    "sg:province":"AL",
    "sg:tags":[
        "contractor"
    ],
    "wof:name":"Southstern Fundation Solutions",
    "wof:placetype":"venue"
},
  "geometry": {"coordinates":[-86.66529,33.620058],"type":"Point"}
}