{
  "type": "Feature",
  "properties": {
    "iso:country":"US",
    "sg:address":"1306 Main St E",
    "sg:city":"Hartselle",
    "sg:classifiers":[
        {
            "category":"Food & Beverages",
            "subcategory":"Groceries & Convenience Stores",
            "type":"Retail Goods"
        }
    ],
    "sg:phone":"+1 256 773 8422",
    "sg:postcode":"35640",
    "sg:province":"AL",
    "wof:name":"Kountry Korner",
    "wof:placetype":"venue"
},
  "geometry": {"coordinates":[-86.911694,34.44925],"type":"Point"}
}