{
  "type": "Feature",
  "properties": {
    "iso:country":"US",
    "sg:address":"1911 Hine St S",
    "sg:city":"Athens",
    "sg:classifiers":[
        {
            "category":"Organizations",
            "subcategory":"Religious Organization",
            "type":"Services"
        }
    ],
    "sg:phone":"+1 256 233 5552",
    "sg:postcode":"35611",
    "sg:province":"AL",
    "sg:tags":[
        "church"
    ],
    "wof:name":"Ebenezer Missionary Baptist",
    "wof:placetype":"venue"
},
  "geometry": {"coordinates":[-86.98348900000001,34.784227],"type":"Point"}
}