{
  "type": "Feature",
  "properties": {
    "addr:full":"6885 US Hwy 231 Dothan AL 36301",
    "addr:housenumber":"6885",
    "addr:postcode":"36301",
    "addr:street":"Us Hwy 231",
    "iso:country":"US",
    "sg:address":"6885 US Hwy 231",
    "sg:city":"Dothan",
    "sg:classifiers":[
        {
            "category":"Building & Trades",
            "subcategory":"Construction",
            "type":"Services"
        }
    ],
    "sg:phone":"+1 334 678 8401",
    "sg:postcode":"36301",
    "sg:province":"AL",
    "sg:tags":[
        "home",
        "general",
        "family",
        "contractor"
    ],
    "wof:name":"Jubilee Builders LLC",
    "wof:placetype":"venue"
},
  "geometry": {"coordinates":[-85.403507,31.127863],"type":"Point"}
}