{
  "type": "Feature",
  "properties": {
    "iso:country":"US",
    "sg:address":"4632 14th Ave N",
    "sg:city":"Birmingham",
    "sg:classifiers":[
        {
            "category":"Professional",
            "type":"Services"
        }
    ],
    "sg:phone":"+1 205 591 4949",
    "sg:postcode":"35212",
    "sg:province":"AL",
    "wof:name":"Paradise Grdns Rsource Dev Ctr",
    "wof:placetype":"venue"
},
  "geometry": {"coordinates":[-86.76733299999999,33.547672],"type":"Point"}
}