{
  "type": "Feature",
  "properties": {
    "iso:country":"US",
    "sg:address":"14740 Ridge Rd",
    "sg:city":"Summerdale",
    "sg:classifiers":[
        {
            "category":"Professional",
            "subcategory":"Secretarial Services",
            "type":"Services"
        }
    ],
    "sg:phone":"+1 251 988 1378",
    "sg:postcode":"36580",
    "sg:province":"AL",
    "sg:tags":[
        "reporting",
        "court"
    ],
    "wof:name":"MHB Business Svc",
    "wof:placetype":"venue"
},
  "geometry": {"coordinates":[-87.80477999999999,30.439394],"type":"Point"}
}