{
  "type": "Feature",
  "properties": {
    "iso:country":"US",
    "sg:address":"3107 25th Ave",
    "sg:city":"Tuscaloosa",
    "sg:classifiers":[
        {
            "category":"Building & Trades",
            "subcategory":"Construction",
            "type":"Services"
        }
    ],
    "sg:phone":"+1 205 752 2890",
    "sg:postcode":"35401",
    "sg:province":"AL",
    "sg:tags":[
        "utility",
        "contractor"
    ],
    "wof:name":"ECI Telecom",
    "wof:placetype":"venue"
},
  "geometry": {"coordinates":[-87.555466,33.181893],"type":"Point"}
}