{
  "type": "Feature",
  "properties": {
    "addr:full":"107 S Edwards St Enterprise AL 36330",
    "addr:housenumber":"107",
    "addr:postcode":"36330",
    "addr:street":"S Edwards St",
    "iso:country":"US",
    "sg:address":"107 S Edwards St",
    "sg:city":"Enterprise",
    "sg:classifiers":[
        {
            "category":"Health Services",
            "subcategory":"Doctor",
            "type":"Services"
        }
    ],
    "sg:phone":"+1 334 347 0096",
    "sg:postcode":"36330",
    "sg:province":"AL",
    "wof:name":"Oliver Charles Orthodontist PC",
    "wof:placetype":"venue"
},
  "geometry": {"coordinates":[-85.852358,31.31481],"type":"Point"}
}