{
  "type": "Feature",
  "properties": {
    "addr:full":"1917 Lay Dam Rd Clanton AL 35045",
    "addr:housenumber":"1917",
    "addr:postcode":"35045",
    "addr:street":"Lay Dam Rd",
    "iso:country":"US",
    "sg:address":"1917 Lay Dam Rd",
    "sg:city":"Clanton",
    "sg:classifiers":[
        {
            "category":"Retail",
            "subcategory":"Laundry & Dry Cleaning",
            "type":"Services"
        }
    ],
    "sg:phone":"+1 205 280 0448",
    "sg:postcode":"35045",
    "sg:province":"AL",
    "sg:tags":[
        "building",
        "maintenance"
    ],
    "wof:name":"Personal Touch Cleaning Svc",
    "wof:placetype":"venue"
},
  "geometry": {"coordinates":[-86.621516,32.8624],"type":"Point"}
}