{
  "type": "Feature",
  "properties": {
    "iso:country":"US",
    "sg:address":"1522 6th Ave SE",
    "sg:city":"Decatur",
    "sg:classifiers":[
        {
            "category":"Social Services",
            "subcategory":"Job Training",
            "type":"Services"
        }
    ],
    "sg:phone":"+1 256 350 0444",
    "sg:postcode":"35601",
    "sg:province":"AL",
    "sg:tags":[
        "rehabilitation"
    ],
    "wof:name":"Healthsouth Rehabilitation Ctr",
    "wof:placetype":"venue"
},
  "geometry": {"coordinates":[-86.98030300000001,34.583171],"type":"Point"}
}