{
  "type": "Feature",
  "properties": {
    "addr:full":"805 Friendship Rd Tallassee AL 36078",
    "addr:housenumber":"805",
    "addr:postcode":"36078",
    "addr:street":"Friendship Rd",
    "iso:country":"US",
    "sg:address":"805 Friendship Rd",
    "sg:city":"Tallassee",
    "sg:classifiers":[
        {
            "category":"Health Services",
            "subcategory":"Doctor",
            "type":"Services"
        }
    ],
    "sg:phone":"+1 334 283 6541",
    "sg:postcode":"36078",
    "sg:province":"AL",
    "sg:tags":[
        "medical"
    ],
    "wof:name":"David L Angle MD",
    "wof:placetype":"venue"
},
  "geometry": {"coordinates":[-85.91174700000001,32.535195],"type":"Point"}
}