{
  "type": "Feature",
  "properties": {
    "iso:country":"US",
    "sg:address":"707 Market St W",
    "sg:city":"Athens",
    "sg:classifiers":[
        {
            "category":"Health Services",
            "subcategory":"Doctor",
            "type":"Services"
        }
    ],
    "sg:phone":"+1 256 232 4510",
    "sg:postcode":"35611",
    "sg:province":"AL",
    "sg:tags":[
        "medical"
    ],
    "wof:name":"Wm S Pennington MD",
    "wof:placetype":"venue"
},
  "geometry": {"coordinates":[-86.977765,34.803443],"type":"Point"}
}