{
  "type": "Feature",
  "properties": {
    "iso:country":"US",
    "sg:address":"1341 Tara Dr",
    "sg:city":"Columbiana",
    "sg:classifiers":[
        {
            "category":"Wholesale",
            "subcategory":"Machinery & Supplies",
            "type":"Manufacturing & Wholesale Goods"
        }
    ],
    "sg:phone":"+1 205 678 8224",
    "sg:postcode":"35051",
    "sg:province":"AL",
    "wof:name":"Machinery Systems Inc",
    "wof:placetype":"venue"
},
  "geometry": {"coordinates":[-86.639579,33.302489],"type":"Point"}
}