{
  "type": "Feature",
  "properties": {
    "iso:country":"US",
    "sg:address":"380 Springdale Rd",
    "sg:city":"Birmingham",
    "sg:classifiers":[
        {
            "category":"Building & Trades",
            "subcategory":"Locksmith",
            "type":"Services"
        }
    ],
    "sg:phone":"+1 205 533 6627",
    "sg:postcode":"35217",
    "sg:province":"AL",
    "sg:tags":[
        "key"
    ],
    "wof:name":"Action Locksmith",
    "wof:placetype":"venue"
},
  "geometry": {"coordinates":[-86.767476,33.597763],"type":"Point"}
}