{
  "type": "Feature",
  "properties": {
    "addr:full":"6509 Eagle Ridge Ln Pinson AL 35126",
    "addr:housenumber":"6509",
    "addr:postcode":"35126",
    "addr:street":"Eagle Ridge Ln",
    "iso:country":"US",
    "sg:address":"6509 Eagle Ridge Ln",
    "sg:city":"Pinson",
    "sg:classifiers":[
        {
            "category":"Wholesale",
            "subcategory":"Auto Parts",
            "type":"Manufacturing & Wholesale Goods"
        }
    ],
    "sg:phone":"+1 205 680 9218",
    "sg:postcode":"35126",
    "sg:province":"AL",
    "wof:name":"Matco Tools",
    "wof:placetype":"venue"
},
  "geometry": {"coordinates":[-86.61344,33.695921],"type":"Point"}
}