{
  "type": "Feature",
  "properties": {
    "iso:country":"US",
    "sg:address":"1087 Downtowner Blvd",
    "sg:city":"Mobile",
    "sg:classifiers":[
        {
            "category":"Real Estate",
            "subcategory":"Real Estate Agent",
            "type":"Services"
        }
    ],
    "sg:phone":"+1 251 342 1636",
    "sg:postcode":"36609",
    "sg:province":"AL",
    "wof:name":"Gleason & Assoc Inc",
    "wof:placetype":"venue"
},
  "geometry": {"coordinates":[-88.142607,30.667073],"type":"Point"}
}