{
  "type": "Feature",
  "properties": {
    "iso:country":"US",
    "sg:address":"1473 Montgomery Hwy",
    "sg:city":"Birmingham",
    "sg:classifiers":[
        {
            "category":"Restaurant",
            "type":"Food & Drink"
        }
    ],
    "sg:menulink":"http://www.allmenus.com/al/birmingham/100566-captain-ds-seafood/menu/",
    "sg:phone":"+1 205 823 4279",
    "sg:postcode":"35216",
    "sg:province":"AL",
    "sg:tags":[
        "seafood",
        "american"
    ],
    "wof:name":"Captain D's Seafood",
    "wof:placetype":"venue"
},
  "geometry": {"coordinates":[-86.802637,33.4171],"type":"Point"}
}