{
  "type": "Feature",
  "properties": {
    "addr:full":"600 Mulberry Ave Anniston AL 36201",
    "addr:housenumber":"600",
    "addr:postcode":"36201",
    "addr:street":"Mulberry Ave",
    "iso:country":"US",
    "sg:address":"600 Mulberry Ave",
    "sg:city":"Anniston",
    "sg:classifiers":[
        {
            "category":"Organizations",
            "subcategory":"Religious Organization",
            "type":"Services"
        }
    ],
    "sg:phone":"+1 256 237 4274",
    "sg:postcode":"36201",
    "sg:province":"AL",
    "wof:name":"Christian Fellowship Bb Church",
    "wof:placetype":"venue"
},
  "geometry": {"coordinates":[-85.83788,33.653231],"type":"Point"}
}