{
  "type": "Feature",
  "properties": {
    "addr:full":"124 Woodland Acres Prattville AL 36067",
    "addr:housenumber":"124",
    "addr:postcode":"36067",
    "addr:street":"Woodland Acres",
    "iso:country":"US",
    "sg:address":"124 Woodland Acres",
    "sg:city":"Prattville",
    "sg:classifiers":[
        {
            "category":"Communications",
            "subcategory":"Television Station",
            "type":"Services"
        }
    ],
    "sg:phone":"+1 334 361 6492",
    "sg:postcode":"36067",
    "sg:province":"AL",
    "wof:name":"Hometown Ftv",
    "wof:placetype":"venue"
},
  "geometry": {"coordinates":[-86.481576,32.473285],"type":"Point"}
}