{
  "type": "Feature",
  "properties": {
    "addr:full":"5455 Co Rd 51 Wilsonville AL 35186",
    "addr:housenumber":"5455",
    "addr:postcode":"35186",
    "addr:street":"Co Rd 51",
    "iso:country":"US",
    "sg:address":"5455 Co Rd 51",
    "sg:city":"Wilsonville",
    "sg:classifiers":[
        {
            "category":"Building & Trades",
            "subcategory":"Construction",
            "type":"Services"
        }
    ],
    "sg:phone":"+1 205 678 8800",
    "sg:postcode":"35186",
    "sg:province":"AL",
    "sg:tags":[
        "pipeline",
        "sewer",
        "contractor"
    ],
    "wof:name":"Mc Cullough Rehab Contractors",
    "wof:placetype":"venue"
},
  "geometry": {"coordinates":[-86.555795,33.321546],"type":"Point"}
}