{
  "type": "Feature",
  "properties": {
    "iso:country":"US",
    "sg:address":"2052 S College St",
    "sg:city":"Auburn",
    "sg:classifiers":[
        {
            "category":"Professional",
            "subcategory":"Management & Consulting",
            "type":"Services"
        }
    ],
    "sg:phone":"+1 334 826 0307",
    "sg:postcode":"36832",
    "sg:province":"AL",
    "sg:tags":[
        "business"
    ],
    "wof:name":"Cosgrove & Associates",
    "wof:placetype":"venue"
},
  "geometry": {"coordinates":[-85.501628,32.56731],"type":"Point"}
}