{
  "type": "Feature",
  "properties": {
    "addr:full":"466 E Main St Prattville AL 36067",
    "addr:housenumber":"466",
    "addr:postcode":"36067",
    "addr:street":"E Main St",
    "iso:country":"US",
    "sg:address":"466 E Main St",
    "sg:city":"Prattville",
    "sg:classifiers":[
        {
            "category":"Wholesale",
            "subcategory":"Medical Equipment & Supplies",
            "type":"Manufacturing & Wholesale Goods"
        }
    ],
    "sg:phone":"+1 334 358 4332",
    "sg:postcode":"36067",
    "sg:province":"AL",
    "sg:tags":[
        "physician",
        "surgeon"
    ],
    "wof:name":"Med-Ex",
    "wof:placetype":"venue"
},
  "geometry": {"coordinates":[-86.461896,32.459387],"type":"Point"}
}