{
  "type": "Feature",
  "properties": {
    "iso:country":"US",
    "sg:address":"607 Mohawk St",
    "sg:city":"Mobile",
    "sg:classifiers":[
        {
            "category":"Organizations",
            "subcategory":"Professional Association",
            "type":"Services"
        }
    ],
    "sg:phone":"+1 251 471 1211",
    "sg:postcode":"36606",
    "sg:province":"AL",
    "wof:name":"BGI Grant Writers",
    "wof:placetype":"venue"
},
  "geometry": {"coordinates":[-88.09419,30.66842],"type":"Point"}
}