{
  "type": "Feature",
  "properties": {
    "addr:full":"1440 Highway Dr Oxford AL 36203",
    "addr:housenumber":"1440",
    "addr:postcode":"36203",
    "addr:street":"Highway Dr",
    "iso:country":"US",
    "sg:address":"1440 Highway Dr",
    "sg:city":"Oxford",
    "sg:classifiers":[
        {
            "category":"Health Services",
            "subcategory":"Medical Lab",
            "type":"Services"
        }
    ],
    "sg:phone":"+1 256 832 5430",
    "sg:postcode":"36203",
    "sg:province":"AL",
    "sg:tags":[
        "laboratory"
    ],
    "wof:name":"Lab South Inc",
    "wof:placetype":"venue"
},
  "geometry": {"coordinates":[-85.813789,33.614323],"type":"Point"}
}