{
  "type": "Feature",
  "properties": {
    "addr:full":"150 E Renfroe Rd Talladega AL 35160",
    "addr:housenumber":"150",
    "addr:postcode":"35160",
    "addr:street":"E Renfroe Rd",
    "iso:country":"US",
    "sg:address":"150 E Renfroe Rd",
    "sg:city":"Talladega",
    "sg:classifiers":[
        {
            "category":"Government",
            "subcategory":"Jail",
            "type":"Public Place"
        }
    ],
    "sg:phone":"+1 256 362 6117",
    "sg:postcode":"35160",
    "sg:province":"AL",
    "sg:tags":[
        "county",
        "govt",
        "institution"
    ],
    "wof:name":"Talladega County Jail",
    "wof:placetype":"venue"
},
  "geometry": {"coordinates":[-86.14921699999999,33.426469],"type":"Point"}
}