{
  "type": "Feature",
  "properties": {
    "iso:country":"US",
    "sg:address":"1310 Oakwood Ave NE",
    "sg:city":"Huntsville",
    "sg:classifiers":[
        {
            "category":"Building & Trades",
            "subcategory":"Construction",
            "type":"Services"
        }
    ],
    "sg:phone":"+1 256 536 7890",
    "sg:postcode":"35811",
    "sg:province":"AL",
    "sg:tags":[
        "contractor"
    ],
    "wof:name":"Zack James Sheet Metal",
    "wof:placetype":"venue"
},
  "geometry": {"coordinates":[-86.567711,34.748894],"type":"Point"}
}