{
  "type": "Feature",
  "properties": {
    "addr:full":"1231 Newell Pkwy Montgomery AL 36110",
    "addr:housenumber":"1231",
    "addr:postcode":"36110",
    "addr:street":"Newell Pkwy",
    "iso:country":"US",
    "sg:address":"1231 Newell Pkwy",
    "sg:city":"Montgomery",
    "sg:classifiers":[
        {
            "category":"Manufacturing",
            "subcategory":"Textiles",
            "type":"Manufacturing & Wholesale Goods"
        },
        {
            "category":"Professional",
            "subcategory":"Business Services",
            "type":"Services"
        }
    ],
    "sg:phone":"+1 334 396 6633",
    "sg:postcode":"36110",
    "sg:province":"AL",
    "sg:tags":[
        "plant",
        "silk",
        "finishing",
        "fiber",
        "embroidery"
    ],
    "wof:name":"A B Sportswear Inc",
    "wof:placetype":"venue"
},
  "geometry": {"coordinates":[-86.26087200000001,32.413892],"type":"Point"}
}