{
  "type": "Feature",
  "properties": {
    "iso:country":"US",
    "sg:address":"125 True Vine Rd",
    "sg:city":"Aliceville",
    "sg:classifiers":[
        {
            "category":"Organizations",
            "subcategory":"Religious Organization",
            "type":"Services"
        }
    ],
    "sg:phone":"+1 205 373 3953",
    "sg:postcode":"35442",
    "sg:province":"AL",
    "wof:name":"True Vine Pentecostal Church",
    "wof:placetype":"venue"
},
  "geometry": {"coordinates":[-88.220029,33.204225],"type":"Point"}
}