{
  "type": "Feature",
  "properties": {
    "iso:country":"US",
    "sg:address":"3009 Crabtree Ln E",
    "sg:city":"Mobile",
    "sg:classifiers":[
        {
            "category":"Building & Trades",
            "subcategory":"Construction",
            "type":"Services"
        }
    ],
    "sg:phone":"+1 251 645 5247",
    "sg:postcode":"36618",
    "sg:province":"AL",
    "sg:tags":[
        "house"
    ],
    "wof:name":"Breland Brothers Construc",
    "wof:placetype":"venue"
},
  "geometry": {"coordinates":[-88.211065,30.751038],"type":"Point"}
}