{
  "type": "Feature",
  "properties": {
    "iso:country":"US",
    "sg:address":"333 Franklin St SE",
    "sg:city":"Huntsville",
    "sg:classifiers":[
        {
            "category":"Professional",
            "subcategory":"Business Services",
            "type":"Services"
        },
        {
            "category":"Health Services",
            "subcategory":"Health Practitioner",
            "type":"Services"
        }
    ],
    "sg:phone":"+1 256 533 2506",
    "sg:postcode":"35801",
    "sg:province":"AL",
    "sg:tags":[
        "psychologist"
    ],
    "wof:name":"Benchmark Psychology Assoc Inc",
    "wof:placetype":"venue"
},
  "geometry": {"coordinates":[-86.58373,34.729572],"type":"Point"}
}