{
  "type": "Feature",
  "properties": {
    "iso:country":"US",
    "sg:address":"4909 Friday Cir",
    "sg:city":"Tuscaloosa",
    "sg:classifiers":[
        {
            "category":"Food & Beverages",
            "subcategory":"Fruits & Vegetables",
            "type":"Retail Goods"
        }
    ],
    "sg:phone":"+1 205 758 4550",
    "sg:postcode":"35401",
    "sg:province":"AL",
    "wof:name":"Hardys Produce",
    "wof:placetype":"venue"
},
  "geometry": {"coordinates":[-87.581147,33.16818],"type":"Point"}
}