{
  "type": "Feature",
  "properties": {
    "iso:country":"US",
    "sg:address":"846 Butler Dr",
    "sg:city":"Mobile",
    "sg:classifiers":[
        {
            "category":"Shopping",
            "subcategory":"Stationery & Office Supplies",
            "type":"Retail Goods"
        }
    ],
    "sg:phone":"+1 251 661 0971",
    "sg:postcode":"36693",
    "sg:province":"AL",
    "sg:tags":[
        "rubber",
        "stamp",
        "plastic"
    ],
    "wof:name":"Bst",
    "wof:placetype":"venue"
},
  "geometry": {"coordinates":[-88.130914,30.650807],"type":"Point"}
}