{
  "type": "Feature",
  "properties": {
    "iso:country":"US",
    "sg:address":"26280 State Rte 69",
    "sg:city":"Jasper",
    "sg:classifiers":[
        {
            "category":"Farming",
            "subcategory":"Nursery",
            "type":"Manufacturing & Wholesale Goods"
        }
    ],
    "sg:phone":"+1 205 387 2805",
    "sg:postcode":"35504",
    "sg:province":"AL",
    "sg:tags":[
        "greenhouse"
    ],
    "wof:name":"Barton's Greenhouse",
    "wof:placetype":"venue"
},
  "geometry": {"coordinates":[-87.20153000000001,33.844865],"type":"Point"}
}