{
  "type": "Feature",
  "properties": {
    "addr:full":"7015 Beachshore Dr Gulf Shores AL 36542",
    "addr:housenumber":"7015",
    "addr:postcode":"36542",
    "addr:street":"Beachshore Dr",
    "iso:country":"US",
    "sg:address":"7015 Beachshore Dr",
    "sg:city":"Gulf Shores",
    "sg:classifiers":[
        {
            "category":"Travel",
            "subcategory":"Travel Agent",
            "type":"Entertainment"
        }
    ],
    "sg:phone":"+1 251 540 2240",
    "sg:postcode":"36542",
    "sg:province":"AL",
    "sg:tags":[
        "operator",
        "tour"
    ],
    "wof:name":"Caribbean Pacific Safari",
    "wof:placetype":"venue"
},
  "geometry": {"coordinates":[-87.902732,30.231122],"type":"Point"}
}