{
  "type": "Feature",
  "properties": {
    "iso:country":"US",
    "sg:address":"2975 State Rte 64",
    "sg:city":"Killen",
    "sg:classifiers":[
        {
            "category":"Building & Trades",
            "subcategory":"Plumbing",
            "type":"Services"
        }
    ],
    "sg:phone":"+1 256 757 1391",
    "sg:postcode":"35645",
    "sg:province":"AL",
    "sg:tags":[
        "contractor"
    ],
    "wof:name":"Beavers Heating & Cooling",
    "wof:placetype":"venue"
},
  "geometry": {"coordinates":[-87.489257,34.944032],"type":"Point"}
}