{
  "type": "Feature",
  "properties": {
    "iso:country":"US",
    "sg:address":"128 Anderson St W",
    "sg:city":"Scottsboro",
    "sg:classifiers":[
        {
            "category":"Shopping",
            "subcategory":"Jewelry",
            "type":"Retail Goods"
        }
    ],
    "sg:phone":"+1 256 574 3672",
    "sg:postcode":"35769",
    "sg:province":"AL",
    "sg:tags":[
        "jeweler"
    ],
    "wof:name":"Johnson Jewel",
    "wof:placetype":"venue"
},
  "geometry": {"coordinates":[-86.066091,34.613276],"type":"Point"}
}