{
  "type": "Feature",
  "properties": {
    "iso:country":"US",
    "sg:address":"5504 State Rte 69",
    "sg:city":"Northport",
    "sg:classifiers":[
        {
            "category":"Wholesale",
            "subcategory":"Machinery & Supplies",
            "type":"Manufacturing & Wholesale Goods"
        }
    ],
    "sg:phone":"+1 205 339 7212",
    "sg:postcode":"35473",
    "sg:province":"AL",
    "sg:tags":[
        "equipment"
    ],
    "wof:name":"Tuscaloosa Forest Products",
    "wof:placetype":"venue"
},
  "geometry": {"coordinates":[-87.572352,33.260059],"type":"Point"}
}