{
  "type": "Feature",
  "properties": {
    "iso:country":"US",
    "sg:address":"3816 Dauphin Island Pkwy",
    "sg:city":"Mobile",
    "sg:classifiers":[
        {
            "category":"Professional",
            "subcategory":"Business Services",
            "type":"Services"
        }
    ],
    "sg:phone":"+1 251 476 4996",
    "sg:postcode":"36605",
    "sg:province":"AL",
    "wof:name":"Dixie Pump & Supply Inc",
    "wof:placetype":"venue"
},
  "geometry": {"coordinates":[-88.07992400000001,30.591854],"type":"Point"}
}