{
  "type": "Feature",
  "properties": {
    "iso:country":"US",
    "sg:address":"131 Portzer Rd",
    "sg:city":"Jasper",
    "sg:classifiers":[
        {
            "category":"Social Services",
            "type":"Services"
        }
    ],
    "sg:phone":"+1 205 387 0902",
    "sg:postcode":"35504",
    "sg:province":"AL",
    "wof:name":"Russell James E EDS LPC",
    "wof:placetype":"venue"
},
  "geometry": {"coordinates":[-87.169866,33.861997],"type":"Point"}
}