{
  "type": "Feature",
  "properties": {
    "addr:full":"2582 W Main St Dothan AL 36301",
    "addr:housenumber":"2582",
    "addr:postcode":"36301",
    "addr:street":"W Main St",
    "iso:country":"US",
    "sg:address":"2582 W Main St",
    "sg:city":"Dothan",
    "sg:classifiers":[
        {
            "category":"Professional",
            "subcategory":"Advertising",
            "type":"Services"
        }
    ],
    "sg:phone":"+1 334 794 0100",
    "sg:postcode":"36301",
    "sg:province":"AL",
    "sg:tags":[
        "counselor",
        "agency"
    ],
    "sg:website":"www.dress-up.com",
    "wof:name":"Farnham & Galey Advertising",
    "wof:placetype":"venue"
},
  "geometry": {"coordinates":[-85.42641500000001,31.228456],"type":"Point"}
}