{
  "type": "Feature",
  "properties": {
    "iso:country":"US",
    "sg:address":"2559 Co Rd 52",
    "sg:city":"Moundville",
    "sg:classifiers":[
        {
            "category":"Personal",
            "subcategory":"Beauty Salon",
            "type":"Services"
        }
    ],
    "sg:phone":"+1 205 371 4699",
    "sg:postcode":"35474",
    "sg:province":"AL",
    "wof:name":"Cuttin' Up With Sandi",
    "wof:placetype":"venue"
},
  "geometry": {"coordinates":[-87.601462,32.965576],"type":"Point"}
}