{
  "type": "Feature",
  "properties": {
    "addr:full":"2123 9th St Tuscaloosa AL 35401",
    "addr:housenumber":"2123",
    "addr:postcode":"35401",
    "addr:street":"9Th St",
    "iso:country":"US",
    "sg:address":"2123 9th St",
    "sg:city":"Tuscaloosa",
    "sg:classifiers":[
        {
            "category":"Professional",
            "subcategory":"Research",
            "type":"Services"
        }
    ],
    "sg:phone":"+1 205 758 6328",
    "sg:postcode":"35401",
    "sg:province":"AL",
    "sg:tags":[
        "educational"
    ],
    "wof:name":"American Academy Of Judicial",
    "wof:placetype":"venue"
},
  "geometry": {"coordinates":[-87.563731,33.206781],"type":"Point"}
}