{
  "type": "Feature",
  "properties": {
    "iso:country":"US",
    "sg:address":"3653 Shandwick Pl",
    "sg:city":"Birmingham",
    "sg:classifiers":[
        {
            "category":"Real Estate",
            "subcategory":"Developer",
            "type":"Services"
        }
    ],
    "sg:phone":"+1 205 980 6131",
    "sg:postcode":"35242",
    "sg:province":"AL",
    "wof:name":"Leadership Development Inc",
    "wof:placetype":"venue"
},
  "geometry": {"coordinates":[-86.65817699999999,33.426888],"type":"Point"}
}