{
  "type": "Feature",
  "properties": {
    "iso:country":"US",
    "sg:address":"4000 Higginbotham Dr",
    "sg:city":"Pinson",
    "sg:classifiers":[
        {
            "category":"Shopping",
            "subcategory":"Jewelry",
            "type":"Retail Goods"
        }
    ],
    "sg:phone":"+1 205 681 9092",
    "sg:postcode":"35126",
    "sg:province":"AL",
    "wof:name":"Laura Finn Jewelry Dist",
    "wof:placetype":"venue"
},
  "geometry": {"coordinates":[-86.709346,33.763405],"type":"Point"}
}