{
  "type": "Feature",
  "properties": {
    "iso:country":"US",
    "sg:address":"2325 Boykin Blvd",
    "sg:city":"Mobile",
    "sg:classifiers":[
        {
            "category":"Social Services",
            "type":"Services"
        }
    ],
    "sg:phone":"+1 251 479 1957",
    "sg:postcode":"36605",
    "sg:province":"AL",
    "sg:tags":[
        "shelter",
        "emergency"
    ],
    "wof:name":"Salvation Army Chld Wns Shlter",
    "wof:placetype":"venue"
},
  "geometry": {"coordinates":[-88.096733,30.59397],"type":"Point"}
}