{
  "type": "Feature",
  "properties": {
    "addr:full":"420 N Decatur St Montgomery AL 36104",
    "addr:housenumber":"420",
    "addr:postcode":"36104",
    "addr:street":"N Decatur St",
    "iso:country":"US",
    "sg:address":"420 N Decatur St",
    "sg:city":"Montgomery",
    "sg:classifiers":[
        {
            "category":"Personal",
            "subcategory":"Beauty Salon",
            "type":"Services"
        }
    ],
    "sg:phone":"+1 334 269 9008",
    "sg:postcode":"36104",
    "sg:province":"AL",
    "sg:tags":[
        "shop"
    ],
    "wof:name":"Reno Beauty Salon & Barber Sp",
    "wof:placetype":"venue"
},
  "geometry": {"coordinates":[-86.302682,32.383058],"type":"Point"}
}