{
  "type": "Feature",
  "properties": {
    "addr:full":"105 Hansell St Montgomery AL 36112",
    "addr:housenumber":"105",
    "addr:postcode":"36112",
    "addr:street":"Hansell St",
    "iso:country":"US",
    "sg:address":"105 Hansell St",
    "sg:city":"Montgomery",
    "sg:classifiers":[
        {
            "category":"Government",
            "subcategory":"Office",
            "type":"Public Place"
        }
    ],
    "sg:phone":"+1 334 834 2236",
    "sg:postcode":"36112",
    "sg:province":"AL",
    "sg:tags":[
        "civil",
        "patrol",
        "air"
    ],
    "wof:name":"Civil Air Patrol Inc",
    "wof:placetype":"venue"
},
  "geometry": {"coordinates":[-86.34897100000001,32.379656],"type":"Point"}
}