{
  "type": "Feature",
  "properties": {
    "iso:country":"US",
    "sg:address":"16979 Co Rd 21",
    "sg:city":"Alpine",
    "sg:classifiers":[
        {
            "category":"Home & Garden",
            "subcategory":"Mobile Homes",
            "type":"Retail Goods"
        }
    ],
    "sg:phone":"+1 256 208 0907",
    "sg:postcode":"35150",
    "sg:province":"AL",
    "wof:name":"Outlet Center The",
    "wof:placetype":"venue"
},
  "geometry": {"coordinates":[-86.218214,33.247766],"type":"Point"}
}