{
  "type": "Feature",
  "properties": {
    "addr:full":"8416 US Hwy 431 Owens Cross Rds AL 35763",
    "addr:housenumber":"8416",
    "addr:postcode":"35763",
    "addr:street":"Us Hwy 431 Owens Cross Rds",
    "iso:country":"US",
    "sg:address":"8416 US Hwy 431",
    "sg:city":"Owens Cross Rds",
    "sg:classifiers":[
        {
            "category":"Manufacturing",
            "subcategory":"Tools & Machinery",
            "type":"Manufacturing & Wholesale Goods"
        }
    ],
    "sg:phone":"+1 256 725 3636",
    "sg:postcode":"35763",
    "sg:province":"AL",
    "sg:tags":[
        "machine",
        "shop"
    ],
    "wof:name":"Riverfax Precisions Machining",
    "wof:placetype":"venue"
},
  "geometry": {"coordinates":[-86.453473,34.598884],"type":"Point"}
}