{
  "type": "Feature",
  "properties": {
    "addr:full":"706 Broad St Stevenson AL 35772",
    "addr:housenumber":"706",
    "addr:postcode":"35772",
    "addr:street":"Broad St",
    "iso:country":"US",
    "sg:address":"706 Broad St",
    "sg:city":"Stevenson",
    "sg:classifiers":[
        {
            "category":"Real Estate",
            "subcategory":"Real Estate Operator",
            "type":"Services"
        }
    ],
    "sg:phone":"+1 256 437 8333",
    "sg:postcode":"35772",
    "sg:province":"AL",
    "sg:tags":[
        "apartment"
    ],
    "wof:name":"Skyview Apartments",
    "wof:placetype":"venue"
},
  "geometry": {"coordinates":[-85.829938,34.866801],"type":"Point"}
}