{
  "type": "Feature",
  "properties": {
    "addr:full":"214 W Alabama St Florence AL 35630",
    "addr:housenumber":"214",
    "addr:postcode":"35630",
    "addr:street":"W Alabama St",
    "iso:country":"US",
    "sg:address":"214 W Alabama St",
    "sg:city":"Florence",
    "sg:classifiers":[
        {
            "category":"Professional",
            "subcategory":"Credit Reporting & Collection",
            "type":"Services"
        }
    ],
    "sg:phone":"+1 256 764 4448",
    "sg:postcode":"35630",
    "sg:province":"AL",
    "sg:tags":[
        "agency"
    ],
    "wof:name":"NCCA",
    "wof:placetype":"venue"
},
  "geometry": {"coordinates":[-87.676563,34.797674],"type":"Point"}
}