{
  "type": "Feature",
  "properties": {
    "iso:country":"US",
    "sg:address":"810 Veterans Memorial Pkwy",
    "sg:city":"Lanett",
    "sg:classifiers":[
        {
            "category":"Autos & Motor Vehicles",
            "subcategory":"Automobile Sales",
            "type":"Retail Goods"
        }
    ],
    "sg:phone":"+1 334 576 2212",
    "sg:postcode":"36863",
    "sg:province":"AL",
    "sg:tags":[
        "dealers-used",
        "car",
        "cars-wholesale"
    ],
    "wof:name":"Cain Auto Sales",
    "wof:placetype":"venue"
},
  "geometry": {"coordinates":[-85.20360599999999,32.851295],"type":"Point"}
}