{
  "type": "Feature",
  "properties": {
    "addr:full":"3816 Palisades Dr Tuscaloosa AL 35405",
    "addr:housenumber":"3816",
    "addr:postcode":"35405",
    "addr:street":"Palisades Dr",
    "iso:country":"US",
    "sg:address":"3816 Palisades Dr",
    "sg:city":"Tuscaloosa",
    "sg:classifiers":[
        {
            "category":"Health Services",
            "subcategory":"Doctor",
            "type":"Services"
        }
    ],
    "sg:phone":"+1 205 633 3541",
    "sg:postcode":"35405",
    "sg:province":"AL",
    "sg:tags":[
        "medical"
    ],
    "wof:name":"Medical Associates West Ala PC",
    "wof:placetype":"venue"
},
  "geometry": {"coordinates":[-87.497974,33.172877],"type":"Point"}
}