{
  "type": "Feature",
  "properties": {
    "iso:country":"US",
    "sg:address":"1 N Hopper St",
    "sg:city":"Montgomery",
    "sg:classifiers":[
        {
            "category":"Real Estate",
            "subcategory":"Real Estate Operator",
            "type":"Services"
        }
    ],
    "sg:phone":"+1 334 265 4229",
    "sg:postcode":"36107",
    "sg:province":"AL",
    "sg:tags":[
        "apartment"
    ],
    "wof:name":"Oaks Apartments",
    "wof:placetype":"venue"
},
  "geometry": {"coordinates":[-86.28859199999999,32.38171],"type":"Point"}
}