{
  "type": "Feature",
  "properties": {
    "iso:country":"US",
    "sg:address":"374 Co Rd 24",
    "sg:city":"Montevallo",
    "sg:classifiers":[
        {
            "category":"Organizations",
            "subcategory":"Religious Organization",
            "type":"Services"
        }
    ],
    "sg:phone":"+1 205 620 4222",
    "sg:postcode":"35115",
    "sg:province":"AL",
    "sg:tags":[
        "church"
    ],
    "wof:name":"Ebenezer United Methodist Chr",
    "wof:placetype":"venue"
},
  "geometry": {"coordinates":[-86.811617,33.165545],"type":"Point"}
}