{
  "type": "Feature",
  "properties": {
    "addr:full":"901 S Christine Ave Anniston AL 36207",
    "addr:housenumber":"901",
    "addr:postcode":"36207",
    "addr:street":"S Christine Ave",
    "iso:country":"US",
    "sg:address":"901 S Christine Ave",
    "sg:city":"Anniston",
    "sg:classifiers":[
        {
            "category":"Building & Trades",
            "subcategory":"Electrical",
            "type":"Services"
        }
    ],
    "sg:phone":"+1 256 235 2688",
    "sg:postcode":"36207",
    "sg:province":"AL",
    "sg:tags":[
        "electrical",
        "contractor"
    ],
    "wof:name":"Electrical Maint Inst",
    "wof:placetype":"venue"
},
  "geometry": {"coordinates":[-85.82232999999999,33.635294],"type":"Point"}
}