{
  "type": "Feature",
  "properties": {
    "iso:country":"US",
    "sg:address":"1628 2nd Ave SW",
    "sg:city":"Cullman",
    "sg:classifiers":[
        {
            "category":"Food & Beverages",
            "subcategory":"Groceries & Convenience Stores",
            "type":"Retail Goods"
        }
    ],
    "sg:phone":"+1 256 775 1907",
    "sg:postcode":"35055",
    "sg:province":"AL",
    "wof:name":"LA Mexicana",
    "wof:placetype":"venue"
},
  "geometry": {"coordinates":[-86.823633,34.139623],"type":"Point"}
}