{
  "type": "Feature",
  "properties": {
    "iso:country":"US",
    "sg:address":"7620 Main St",
    "sg:city":"Adger",
    "sg:classifiers":[
        {
            "category":"Organizations",
            "subcategory":"Religious Organization",
            "type":"Services"
        }
    ],
    "sg:phone":"+1 205 428 1325",
    "sg:postcode":"35006",
    "sg:province":"AL",
    "sg:tags":[
        "church"
    ],
    "wof:name":"Holiness Deliverance Tbrncl",
    "wof:placetype":"venue"
},
  "geometry": {"coordinates":[-87.09695000000001,33.370194],"type":"Point"}
}