{
  "type": "Feature",
  "properties": {
    "iso:country":"US",
    "sg:address":"1137 11th Ave S",
    "sg:city":"Birmingham",
    "sg:classifiers":[
        {
            "category":"Education",
            "subcategory":"Special Training",
            "type":"Public Place"
        }
    ],
    "sg:phone":"+1 205 326 0138",
    "sg:postcode":"35205",
    "sg:province":"AL",
    "sg:tags":[
        "educational"
    ],
    "wof:name":"Birmingham Board Of Education",
    "wof:placetype":"venue"
},
  "geometry": {"coordinates":[-86.80948,33.49475],"type":"Point"}
}