{
  "type": "Feature",
  "properties": {
    "iso:country":"US",
    "sg:address":"1535 Schillinger Rd S",
    "sg:city":"Mobile",
    "sg:classifiers":[
        {
            "category":"Banks & Credit Unions",
            "subcategory":"Bank",
            "type":"Services"
        }
    ],
    "sg:phone":"+1 251 635 1389",
    "sg:postcode":"36695",
    "sg:province":"AL",
    "sg:tags":[
        "financing"
    ],
    "wof:name":"Pennstar Financial",
    "wof:placetype":"venue"
},
  "geometry": {"coordinates":[-88.22500100000001,30.65579],"type":"Point"}
}