{
  "type": "Feature",
  "properties": {
    "iso:country":"US",
    "sg:address":"4900 Corporate Dr NW",
    "sg:city":"Huntsville",
    "sg:classifiers":[
        {
            "category":"Shopping",
            "subcategory":"Computers & Home Electronics",
            "type":"Retail Goods"
        }
    ],
    "sg:phone":"+1 256 837 1956",
    "sg:postcode":"35805",
    "sg:province":"AL",
    "sg:tags":[
        "software"
    ],
    "sg:website":"www.redhat.com",
    "wof:name":"Red Hat Inc",
    "wof:placetype":"venue"
},
  "geometry": {"coordinates":[-86.66286,34.733396],"type":"Point"}
}