{
  "type": "Feature",
  "properties": {
    "addr:full":"45 N Belmont Dr Gadsden AL 35904",
    "addr:housenumber":"45",
    "addr:postcode":"35904",
    "addr:street":"N Belmont Dr",
    "iso:country":"US",
    "sg:address":"45 N Belmont Dr",
    "sg:city":"Gadsden",
    "sg:classifiers":[
        {
            "category":"Shopping",
            "subcategory":"Florist",
            "type":"Retail Goods"
        }
    ],
    "sg:phone":"+1 256 547 2305",
    "sg:postcode":"35904",
    "sg:province":"AL",
    "wof:name":"Chris Tucker Designs",
    "wof:placetype":"venue"
},
  "geometry": {"coordinates":[-85.99264599999999,34.057082],"type":"Point"}
}