{
  "type": "Feature",
  "properties": {
    "iso:country":"US",
    "sg:address":"2407 Montevallo Rd",
    "sg:city":"Birmingham",
    "sg:classifiers":[
        {
            "category":"Shopping",
            "subcategory":"Florist",
            "type":"Retail Goods"
        }
    ],
    "sg:phone":"+1 205 870 1666",
    "sg:postcode":"35223",
    "sg:province":"AL",
    "wof:name":"Mountain Brook Flower Shop",
    "wof:placetype":"venue"
},
  "geometry": {"coordinates":[-86.772705,33.484367],"type":"Point"}
}