{
  "type": "Feature",
  "properties": {
    "iso:country":"US",
    "sg:address":"508 Selma Ave",
    "sg:city":"Selma",
    "sg:classifiers":[
        {
            "category":"Organizations",
            "subcategory":"Membership Organization",
            "type":"Services"
        }
    ],
    "sg:phone":"+1 334 874 9017",
    "sg:postcode":"36701",
    "sg:province":"AL",
    "wof:name":"Selma Art Guild Gallery",
    "wof:placetype":"venue"
},
  "geometry": {"coordinates":[-87.026301,32.406502],"type":"Point"}
}