{
  "type": "Feature",
  "properties": {
    "iso:country":"US",
    "sg:address":"119 Starr Cir",
    "sg:city":"Adamsville",
    "sg:classifiers":[
        {
            "category":"Building & Trades",
            "subcategory":"Construction",
            "type":"Services"
        }
    ],
    "sg:phone":"+1 205 674 6818",
    "sg:postcode":"35005",
    "sg:province":"AL",
    "sg:tags":[
        "roofing",
        "contractor"
    ],
    "wof:name":"AIA Pro Roofing Systems",
    "wof:placetype":"venue"
},
  "geometry": {"coordinates":[-86.980778,33.608132],"type":"Point"}
}