{
  "type": "Feature",
  "properties": {
    "iso:country":"US",
    "sg:address":"222 W Clark Ave",
    "sg:city":"Prichard",
    "sg:classifiers":[
        {
            "category":"Arena",
            "subcategory":"Sports Club",
            "type":"Entertainment"
        }
    ],
    "sg:phone":"+1 251 452 7917",
    "sg:postcode":"36610",
    "sg:province":"AL",
    "sg:tags":[
        "athletic",
        "fields",
        "stadium"
    ],
    "wof:name":"Prichard Municipal Stadium",
    "wof:placetype":"venue"
},
  "geometry": {"coordinates":[-88.084145,30.733069],"type":"Point"}
}