{
  "type": "Feature",
  "properties": {
    "iso:country":"US",
    "sg:address":"302 Haven Dr",
    "sg:city":"Dothan",
    "sg:classifiers":[
        {
            "category":"Social Services",
            "subcategory":"Child Care",
            "type":"Services"
        }
    ],
    "sg:phone":"+1 334 712 9162",
    "sg:postcode":"36301",
    "sg:province":"AL",
    "sg:tags":[
        "center"
    ],
    "wof:name":"Child Developement Ctr",
    "wof:placetype":"venue"
},
  "geometry": {"coordinates":[-85.366438,31.213907],"type":"Point"}
}