{
  "type": "Feature",
  "properties": {
    "iso:country":"US",
    "sg:address":"2109 Danville Rd SW",
    "sg:city":"Decatur",
    "sg:classifiers":[
        {
            "category":"Personal",
            "subcategory":"Beauty Salon",
            "type":"Services"
        }
    ],
    "sg:phone":"+1 256 350 9337",
    "sg:postcode":"35601",
    "sg:province":"AL",
    "wof:name":"P Zazz",
    "wof:placetype":"venue"
},
  "geometry": {"coordinates":[-87.010946,34.573573],"type":"Point"}
}