{
  "type": "Feature",
  "properties": {
    "iso:country":"US",
    "sg:address":"63 Montgomery Ave",
    "sg:city":"Thorsby",
    "sg:classifiers":[
        {
            "category":"Restaurant",
            "type":"Food & Drink"
        }
    ],
    "sg:phone":"+1 205 688 1746",
    "sg:postcode":"35171",
    "sg:province":"AL",
    "wof:name":"Tacos Y Tortas Donchemo",
    "wof:placetype":"venue"
},
  "geometry": {"coordinates":[-86.716859,32.916285],"type":"Point"}
}