{
  "type": "Feature",
  "properties": {
    "iso:country":"US",
    "sg:address":"2225 Bark Cir",
    "sg:city":"Birmingham",
    "sg:classifiers":[
        {
            "category":"Wholesale",
            "subcategory":"Machinery & Supplies",
            "type":"Manufacturing & Wholesale Goods"
        }
    ],
    "sg:phone":"+1 205 425 0798",
    "sg:postcode":"35244",
    "sg:province":"AL",
    "sg:tags":[
        "valve"
    ],
    "wof:name":"Flowserve Corp",
    "wof:placetype":"venue"
},
  "geometry": {"coordinates":[-86.900725,33.338611],"type":"Point"}
}