{
  "type": "Feature",
  "properties": {
    "iso:country":"US",
    "sg:address":"4206 Rainbow Dr",
    "sg:city":"Rainbow City",
    "sg:classifiers":[
        {
            "category":"Autos & Motor Vehicles",
            "subcategory":"Automobile Sales",
            "type":"Retail Goods"
        }
    ],
    "sg:phone":"+1 256 442 8002",
    "sg:postcode":"35906",
    "sg:province":"AL",
    "sg:tags":[
        "used"
    ],
    "wof:name":"Whitley Motors",
    "wof:placetype":"venue"
},
  "geometry": {"coordinates":[-86.059666,33.941497],"type":"Point"}
}