{
  "type": "Feature",
  "properties": {
    "addr:full":"4206 Rainbow Dr Rainbow City AL 35906",
    "addr:housenumber":"4206",
    "addr:postcode":"35906",
    "addr:street":"Rainbow Dr",
    "iso:country":"US",
    "sg:address":"4206 Rainbow Dr",
    "sg:city":"Rainbow City",
    "sg:classifiers":[
        {
            "category":"Autos & Motor Vehicles",
            "subcategory":"Automobile Sales",
            "type":"Retail Goods"
        }
    ],
    "sg:phone":"+1 256 442 8002",
    "sg:postcode":"35906",
    "sg:province":"AL",
    "sg:tags":[
        "used"
    ],
    "wof:name":"Whitley Motors",
    "wof:placetype":"venue"
},
  "geometry": {"coordinates":[-86.05966600000001,33.941497],"type":"Point"}
}