{
  "type": "Feature",
  "properties": {
    "iso:country":"US",
    "sg:address":"2417 Holmes Ave NW",
    "sg:city":"Huntsville",
    "sg:classifiers":[
        {
            "category":"Organizations",
            "subcategory":"Religious Organization",
            "type":"Services"
        }
    ],
    "sg:phone":"+1 256 288 0078",
    "sg:postcode":"35816",
    "sg:province":"AL",
    "sg:tags":[
        "church"
    ],
    "wof:name":"Church Of Philadelphia",
    "wof:placetype":"venue"
},
  "geometry": {"coordinates":[-86.602712,34.729651],"type":"Point"}
}