{
  "type": "Feature",
  "properties": {
    "addr:full":"3288 Wall Triana Hwy Huntsville AL 35824",
    "addr:housenumber":"3288",
    "addr:postcode":"35824",
    "addr:street":"Wall Triana Hwy",
    "iso:country":"US",
    "sg:address":"3288 Wall Triana Hwy",
    "sg:city":"Huntsville",
    "sg:classifiers":[
        {
            "category":"Wholesale",
            "subcategory":"Construction Materials",
            "type":"Manufacturing & Wholesale Goods"
        }
    ],
    "sg:phone":"+1 256 772 7351",
    "sg:postcode":"35824",
    "sg:province":"AL",
    "sg:tags":[
        "concrete",
        "accessory"
    ],
    "wof:name":"Construction Materials Limited",
    "wof:placetype":"venue"
},
  "geometry": {"coordinates":[-86.752306,34.664989],"type":"Point"}
}