{
  "type": "Feature",
  "properties": {
    "iso:country":"US",
    "sg:address":"205 S Seminary St",
    "sg:city":"Florence",
    "sg:classifiers":[
        {
            "category":"Insurance",
            "subcategory":"Insurance Agent",
            "type":"Services"
        }
    ],
    "sg:phone":"+1 256 740 8292",
    "sg:postcode":"35630",
    "sg:province":"AL",
    "wof:name":"Modern Woodmen Of America",
    "wof:placetype":"venue"
},
  "geometry": {"coordinates":[-87.673528,34.798932],"type":"Point"}
}