{
  "type": "Feature",
  "properties": {
    "iso:country":"US",
    "sg:address":"1360 Hartford Hwy",
    "sg:city":"Dothan",
    "sg:classifiers":[
        {
            "category":"Sports & Exercise",
            "subcategory":"Gym",
            "type":"Entertainment"
        }
    ],
    "sg:phone":"+1 334 702 8888",
    "sg:postcode":"36301",
    "sg:province":"AL",
    "sg:tags":[
        "fitness",
        "physical",
        "facility"
    ],
    "wof:name":"Fitness For Ladies",
    "wof:placetype":"venue"
},
  "geometry": {"coordinates":[-85.41435300000001,31.213787],"type":"Point"}
}