{
  "type": "Feature",
  "properties": {
    "iso:country":"US",
    "sg:address":"762 Savannah St",
    "sg:city":"Mobile",
    "sg:classifiers":[
        {
            "category":"Freight",
            "type":"Transportation"
        }
    ],
    "sg:phone":"+1 251 433 5806",
    "sg:postcode":"36603",
    "sg:province":"AL",
    "sg:tags":[
        "delivery"
    ],
    "wof:name":"Rush Delivery Svc",
    "wof:placetype":"venue"
},
  "geometry": {"coordinates":[-88.051389,30.68014],"type":"Point"}
}