{
  "type": "Feature",
  "properties": {
    "addr:full":"723 3rd Ave W Birmingham AL 35208",
    "addr:housenumber":"723",
    "addr:postcode":"35208",
    "addr:street":"3Rd Ave W",
    "iso:country":"US",
    "sg:address":"723 3rd Ave W",
    "sg:city":"Birmingham",
    "sg:classifiers":[
        {
            "category":"Retail",
            "subcategory":"Auto Repair",
            "type":"Services"
        }
    ],
    "sg:phone":"+1 205 780 0444",
    "sg:postcode":"35208",
    "sg:province":"AL",
    "sg:tags":[
        "body",
        "automobile",
        "painting"
    ],
    "wof:name":"Al's Auto Sales & Body Shop",
    "wof:placetype":"venue"
},
  "geometry": {"coordinates":[-86.848775,33.505266],"type":"Point"}
}