{
  "type": "Feature",
  "properties": {
    "iso:country":"US",
    "sg:address":"33321 US Hwy 98",
    "sg:city":"Lillian",
    "sg:classifiers":[
        {
            "category":"Building & Trades",
            "subcategory":"Construction",
            "type":"Services"
        }
    ],
    "sg:phone":"+1 251 986 3599",
    "sg:postcode":"36549",
    "sg:province":"AL",
    "sg:tags":[
        "house"
    ],
    "wof:name":"Elberta Construction Co",
    "wof:placetype":"venue"
},
  "geometry": {"coordinates":[-87.45835599999999,30.414574],"type":"Point"}
}