{
  "type": "Feature",
  "properties": {
    "iso:country":"US",
    "sg:address":"103 Hightower Rd",
    "sg:city":"Harvest",
    "sg:classifiers":[
        {
            "category":"Organizations",
            "subcategory":"Community Association",
            "type":"Services"
        }
    ],
    "sg:phone":"+1 256 852 4135",
    "sg:postcode":"35749",
    "sg:province":"AL",
    "wof:name":"Grace Chapter",
    "wof:placetype":"venue"
},
  "geometry": {"coordinates":[-86.689642,34.821048],"type":"Point"}
}