{
  "type": "Feature",
  "properties": {
    "iso:country":"US",
    "sg:address":"4654 Pleasant Springs Dr",
    "sg:city":"Tuskegee",
    "sg:classifiers":[
        {
            "category":"Autos & Motor Vehicles",
            "subcategory":"Fuel & Gas Station",
            "type":"Retail Goods"
        }
    ],
    "sg:phone":"+1 334 727 9611",
    "sg:postcode":"36083",
    "sg:province":"AL",
    "sg:tags":[
        "oil"
    ],
    "wof:name":"Franklin Amoco",
    "wof:placetype":"venue"
},
  "geometry": {"coordinates":[-85.785303,32.435987],"type":"Point"}
}