{
  "type": "Feature",
  "properties": {
    "iso:country":"US",
    "sg:address":"13772 Curtis Dr",
    "sg:city":"Foley",
    "sg:classifiers":[
        {
            "category":"Recreation",
            "subcategory":"Marina",
            "type":"Entertainment"
        }
    ],
    "sg:phone":"+1 251 978 2016",
    "sg:postcode":"36535",
    "sg:province":"AL",
    "sg:tags":[
        "repair",
        "marine"
    ],
    "wof:name":"Cline's Marine Svc",
    "wof:placetype":"venue"
},
  "geometry": {"coordinates":[-87.776341,30.42194],"type":"Point"}
}