{
  "type": "Feature",
  "properties": {
    "iso:country":"US",
    "sg:address":"363 US Hwy 431",
    "sg:city":"Boaz",
    "sg:classifiers":[
        {
            "category":"Shopping",
            "subcategory":"Bicycles & Sporting Goods",
            "type":"Retail Goods"
        }
    ],
    "sg:phone":"+1 256 593 8111",
    "sg:postcode":"35957",
    "sg:province":"AL",
    "sg:tags":[
        "equipment",
        "golf",
        "supply"
    ],
    "wof:name":"Golf Plus",
    "wof:placetype":"venue"
},
  "geometry": {"coordinates":[-86.147935,34.192088],"type":"Point"}
}