{
  "type": "Feature",
  "properties": {
    "addr:full":"153 Sweetgum Dr Russellville AL 35654",
    "addr:housenumber":"153",
    "addr:postcode":"35654",
    "addr:street":"Sweetgum Dr",
    "iso:country":"US",
    "sg:address":"153 Sweetgum Dr",
    "sg:city":"Russellville",
    "sg:classifiers":[
        {
            "category":"Retail",
            "subcategory":"Repair Shop",
            "type":"Services"
        }
    ],
    "sg:phone":"+1 256 331 9020",
    "sg:postcode":"35654",
    "sg:province":"AL",
    "sg:tags":[
        "scooter",
        "motorcycle",
        "motor"
    ],
    "wof:name":"Hawkin's Custom Cycle",
    "wof:placetype":"venue"
},
  "geometry": {"coordinates":[-87.69765700000001,34.480173],"type":"Point"}
}