{
  "type": "Feature",
  "properties": {
    "iso:country":"US",
    "sg:address":"145 Good Hope School Rd",
    "sg:city":"Cullman",
    "sg:classifiers":[
        {
            "category":"Social Services",
            "subcategory":"Child Care",
            "type":"Services"
        }
    ],
    "sg:phone":"+1 256 734 5142",
    "sg:postcode":"35057",
    "sg:province":"AL",
    "sg:tags":[
        "day"
    ],
    "wof:name":"Kids Stuff Day Care",
    "wof:placetype":"venue"
},
  "geometry": {"coordinates":[-86.879621,34.101943],"type":"Point"}
}