{
  "type": "Feature",
  "properties": {
    "addr:full":"144 Bluff Creek Rd Pittsview AL 36871",
    "addr:housenumber":"144",
    "addr:postcode":"36871",
    "addr:street":"Bluff Creek Rd",
    "iso:country":"US",
    "sg:address":"144 Bluff Creek Rd",
    "sg:city":"Pittsview",
    "sg:classifiers":[
        {
            "category":"Government",
            "subcategory":"Office",
            "type":"Public Place"
        }
    ],
    "sg:phone":"+1 334 855 9918",
    "sg:postcode":"36871",
    "sg:province":"AL",
    "sg:tags":[
        "federal"
    ],
    "wof:name":"US Army Corps Of Engineers",
    "wof:placetype":"venue"
},
  "geometry": {"coordinates":[-85.01987699999999,32.189099],"type":"Point"}
}