{
  "type": "Feature",
  "properties": {
    "addr:full":"5529 Cobblestone Dr Pinson AL 35126",
    "addr:housenumber":"5529",
    "addr:postcode":"35126",
    "addr:street":"Cobblestone Dr",
    "iso:country":"US",
    "sg:address":"5529 Cobblestone Dr",
    "sg:city":"Pinson",
    "sg:classifiers":[
        {
            "category":"Professional",
            "type":"Services"
        }
    ],
    "sg:phone":"+1 205 680 1898",
    "sg:postcode":"35126",
    "sg:province":"AL",
    "wof:name":"James S Crane",
    "wof:placetype":"venue"
},
  "geometry": {"coordinates":[-86.63592199999999,33.68738],"type":"Point"}
}