{
  "type": "Feature",
  "properties": {
    "iso:country":"US",
    "sg:address":"3535 Grandview Pkwy",
    "sg:city":"Birmingham",
    "sg:classifiers":[
        {
            "category":"Banks & Credit Unions",
            "subcategory":"Investment Brokerage",
            "type":"Services"
        }
    ],
    "sg:phone":"+1 205 967 8974",
    "sg:postcode":"35243",
    "sg:province":"AL",
    "sg:tags":[
        "advisory",
        "financial"
    ],
    "wof:name":"AIG Valic",
    "wof:placetype":"venue"
},
  "geometry": {"coordinates":[-86.721242,33.440485],"type":"Point"}
}