{
  "type": "Feature",
  "properties": {
    "iso:country":"US",
    "sg:address":"3336 Florence Blvd",
    "sg:city":"Florence",
    "sg:classifiers":[
        {
            "category":"Real Estate",
            "subcategory":"Real Estate Agent",
            "type":"Services"
        }
    ],
    "sg:phone":"+1 256 718 1055",
    "sg:postcode":"35634",
    "sg:province":"AL",
    "wof:name":"Remax Shoals",
    "wof:placetype":"venue"
},
  "geometry": {"coordinates":[-87.607176,34.836185],"type":"Point"}
}