{
  "type": "Feature",
  "properties": {
    "addr:full":"4415 Co Rd 21 Horton AL 35980",
    "addr:housenumber":"4415;21",
    "addr:postcode":"35980",
    "addr:street":"Co Rd",
    "iso:country":"US",
    "sg:address":"4415 Co Rd 21",
    "sg:city":"Horton",
    "sg:classifiers":[
        {
            "category":"Organizations",
            "subcategory":"Religious Organization",
            "type":"Services"
        }
    ],
    "sg:phone":"+1 205 466 7696",
    "sg:postcode":"35980",
    "sg:province":"AL",
    "sg:tags":[
        "church"
    ],
    "wof:name":"Pleasant Grove Methodist Chr",
    "wof:placetype":"venue"
},
  "geometry": {"coordinates":[-86.39372899999999,34.159512],"type":"Point"}
}