{
  "type": "Feature",
  "properties": {
    "iso:country":"US",
    "sg:address":"7309 Earlwood Rd",
    "sg:city":"Fairfield",
    "sg:classifiers":[
        {
            "category":"Personal",
            "type":"Services"
        }
    ],
    "sg:phone":"+1 205 925 1933",
    "sg:postcode":"35064",
    "sg:province":"AL",
    "wof:name":"Elegant Bride Wedding Conslnts",
    "wof:placetype":"venue"
},
  "geometry": {"coordinates":[-86.92296399999999,33.460771],"type":"Point"}
}