{
  "type": "Feature",
  "properties": {
    "iso:country":"US",
    "sg:address":"1613 Armstrong St NW",
    "sg:city":"Huntsville",
    "sg:classifiers":[
        {
            "category":"Autos & Motor Vehicles",
            "subcategory":"Automobile Sales",
            "type":"Retail Goods"
        },
        {
            "category":"Autos & Motor Vehicles",
            "subcategory":"Auto Supplies",
            "type":"Retail Goods"
        },
        {
            "category":"Retail",
            "subcategory":"Auto Repair",
            "type":"Services"
        }
    ],
    "sg:phone":"+1 256 797 1207",
    "sg:postcode":"35816",
    "sg:province":"AL",
    "sg:tags":[
        "transmission",
        "car",
        "used",
        "road",
        "service-automotive"
    ],
    "sg:website":"http://a1reliableservice.com",
    "wof:name":"A1- Reliable & Auto Sales",
    "wof:placetype":"venue"
},
  "geometry": {"coordinates":[-86.61520299999999,34.739988],"type":"Point"}
}