{
  "type": "Feature",
  "properties": {
    "iso:country":"US",
    "sg:address":"6670 Service Rd",
    "sg:city":"Trussville",
    "sg:classifiers":[
        {
            "category":"Professional",
            "subcategory":"Business Services",
            "type":"Services"
        }
    ],
    "sg:phone":"+1 205 661 1243",
    "sg:postcode":"35173",
    "sg:province":"AL",
    "wof:name":"Acfs",
    "wof:placetype":"venue"
},
  "geometry": {"coordinates":[-86.596494,33.658204],"type":"Point"}
}