{
  "type": "Feature",
  "properties": {
    "iso:country":"US",
    "sg:address":"2231 Cobbs Ford Rd",
    "sg:city":"Prattville",
    "sg:classifiers":[
        {
            "category":"Autos & Motor Vehicles",
            "subcategory":"Automobile Sales",
            "type":"Retail Goods"
        }
    ],
    "sg:phone":"+1 334 290 1700",
    "sg:postcode":"36066",
    "sg:province":"AL",
    "sg:tags":[
        "car",
        "dealer"
    ],
    "wof:name":"Manning Motor Co",
    "wof:placetype":"venue"
},
  "geometry": {"coordinates":[-86.410856,32.459806],"type":"Point"}
}