{
  "type": "Feature",
  "properties": {
    "iso:country":"US",
    "sg:address":"110 12th St N",
    "sg:city":"Birmingham",
    "sg:classifiers":[
        {
            "category":"Professional",
            "type":"Services"
        }
    ],
    "sg:phone":"+1 205 714 3701",
    "sg:postcode":"35203",
    "sg:province":"AL",
    "sg:tags":[
        "establishment"
    ],
    "wof:name":"Key 2 Ideas",
    "wof:placetype":"venue"
},
  "geometry": {"coordinates":[-86.81741,33.509965],"type":"Point"}
}