{
  "type": "Feature",
  "properties": {
    "addr:full":"2895 North Rd Gardendale AL 35071",
    "addr:housenumber":"2895",
    "addr:postcode":"35071",
    "addr:street":"North Rd",
    "iso:country":"US",
    "sg:address":"2895 North Rd",
    "sg:city":"Gardendale",
    "sg:classifiers":[
        {
            "category":"Building & Trades",
            "subcategory":"Construction",
            "type":"Services"
        }
    ],
    "sg:phone":"+1 205 631 3201",
    "sg:postcode":"35071",
    "sg:province":"AL",
    "wof:name":"Gravitt Construction Inc",
    "wof:placetype":"venue"
},
  "geometry": {"coordinates":[-86.83123500000001,33.695852],"type":"Point"}
}