{
  "type": "Feature",
  "properties": {
    "iso:country":"US",
    "sg:address":"1370 Kirby Bridge Rd",
    "sg:city":"Danville",
    "sg:classifiers":[
        {
            "category":"Retail",
            "subcategory":"Laundry & Dry Cleaning",
            "type":"Services"
        }
    ],
    "sg:phone":"+1 256 751 4789",
    "sg:postcode":"35619",
    "sg:province":"AL",
    "sg:tags":[
        "residential",
        "carpet"
    ],
    "wof:name":"Pro Clean Carpet & Uphl Care",
    "wof:placetype":"venue"
},
  "geometry": {"coordinates":[-87.081523,34.488809],"type":"Point"}
}