{
  "type": "Feature",
  "properties": {
    "iso:country":"US",
    "sg:address":"254 McConnel St",
    "sg:city":"York",
    "sg:classifiers":[
        {
            "category":"Organizations",
            "subcategory":"Religious Organization",
            "type":"Services"
        }
    ],
    "sg:phone":"+1 205 392 5385",
    "sg:postcode":"36925",
    "sg:province":"AL",
    "wof:name":"First Baptist Church York",
    "wof:placetype":"venue"
},
  "geometry": {"coordinates":[-88.300884,32.484303],"type":"Point"}
}