{
  "type": "Feature",
  "properties": {
    "addr:full":"112 Green Leaf Dr Montgomery AL 36108",
    "addr:housenumber":"112",
    "addr:postcode":"36108",
    "addr:street":"Green Leaf Dr",
    "iso:country":"US",
    "sg:address":"112 Green Leaf Dr",
    "sg:city":"Montgomery",
    "sg:classifiers":[
        {
            "category":"Organizations",
            "subcategory":"Religious Organization",
            "type":"Services"
        }
    ],
    "sg:phone":"+1 334 284 6225",
    "sg:postcode":"36108",
    "sg:province":"AL",
    "sg:tags":[
        "church"
    ],
    "wof:name":"Jehovah's Witnesses-Kingdom Hl",
    "wof:placetype":"venue"
},
  "geometry": {"coordinates":[-86.347435,32.300346],"type":"Point"}
}