{
  "type": "Feature",
  "properties": {
    "iso:country":"US",
    "sg:address":"1109 Cimarron Trl",
    "sg:city":"Birmingham",
    "sg:classifiers":[
        {
            "category":"Professional",
            "subcategory":"Computer Services",
            "type":"Services"
        }
    ],
    "sg:phone":"+1 205 841 2012",
    "sg:postcode":"35215",
    "sg:province":"AL",
    "wof:name":"B J S Technologies Inc",
    "wof:placetype":"venue"
},
  "geometry": {"coordinates":[-86.732349,33.616887],"type":"Point"}
}