{
  "type": "Feature",
  "properties": {
    "iso:country":"US",
    "sg:address":"257 Saint Anthony St",
    "sg:city":"Mobile",
    "sg:classifiers":[
        {
            "category":"Professional",
            "subcategory":"Lawyer & Legal Services",
            "type":"Services"
        }
    ],
    "sg:phone":"+1 251 433 2650",
    "sg:postcode":"36603",
    "sg:province":"AL",
    "sg:tags":[
        "attorney"
    ],
    "wof:name":"Thomas GF Landry Attrny LLC",
    "wof:placetype":"venue"
},
  "geometry": {"coordinates":[-88.046233,30.694118],"type":"Point"}
}