{
  "type": "Feature",
  "properties": {
    "addr:full":"2516 23rd St Birmingham AL 35208",
    "addr:housenumber":"2516",
    "addr:postcode":"35208",
    "addr:street":"23Rd St",
    "iso:country":"US",
    "sg:address":"2516 23rd St",
    "sg:city":"Birmingham",
    "sg:classifiers":[
        {
            "category":"Shopping",
            "subcategory":"Clothing, Apparel, & Fashions",
            "type":"Retail Goods"
        }
    ],
    "sg:phone":"+1 205 788 3125",
    "sg:postcode":"35208",
    "sg:province":"AL",
    "wof:name":"Marthas Boutique",
    "wof:placetype":"venue"
},
  "geometry": {"coordinates":[-86.874588,33.506334],"type":"Point"}
}