{
  "type": "Feature",
  "properties": {
    "iso:country":"US",
    "sg:address":"441 N Bay Springs Rd",
    "sg:city":"Dothan",
    "sg:classifiers":[
        {
            "category":"Building & Trades",
            "subcategory":"Plumbing",
            "type":"Services"
        }
    ],
    "sg:phone":"+1 334 714 2954",
    "sg:postcode":"36303",
    "sg:province":"AL",
    "sg:tags":[
        "contractor"
    ],
    "wof:name":"S Merritt Heating Cooling",
    "wof:placetype":"venue"
},
  "geometry": {"coordinates":[-85.528862,31.245262],"type":"Point"}
}