{
  "type": "Feature",
  "properties": {
    "iso:country":"US",
    "sg:address":"2848 Berkeley Dr",
    "sg:city":"Birmingham",
    "sg:classifiers":[
        {
            "category":"Shopping",
            "subcategory":"Computers & Home Electronics",
            "type":"Retail Goods"
        }
    ],
    "sg:phone":"+1 205 991 8679",
    "sg:postcode":"35242",
    "sg:province":"AL",
    "sg:tags":[
        "software"
    ],
    "sg:website":"www.cncinc.com",
    "wof:name":"Computer & Consulting LLC",
    "wof:placetype":"venue"
},
  "geometry": {"coordinates":[-86.729547,33.395689],"type":"Point"}
}