{
  "type": "Feature",
  "properties": {
    "addr:full":"517 McKenzie St Foley AL 36535",
    "addr:housenumber":"517",
    "addr:postcode":"36535",
    "addr:street":"Mckenzie St",
    "iso:country":"US",
    "sg:address":"517 McKenzie St",
    "sg:city":"Foley",
    "sg:classifiers":[
        {
            "category":"Organizations",
            "subcategory":"Religious Organization",
            "type":"Services"
        }
    ],
    "sg:phone":"+1 251 943 2686",
    "sg:postcode":"36535",
    "sg:province":"AL",
    "wof:name":"Church of Christ",
    "wof:placetype":"venue"
},
  "geometry": {"coordinates":[-87.68376600000001,30.40283],"type":"Point"}
}