{
  "type": "Feature",
  "properties": {
    "iso:country":"US",
    "sg:address":"1679 McCain Pkwy",
    "sg:city":"Pelham",
    "sg:classifiers":[
        {
            "category":"Professional",
            "subcategory":"Management & Consulting",
            "type":"Services"
        }
    ],
    "sg:phone":"+1 205 664 5755",
    "sg:postcode":"35124",
    "sg:province":"AL",
    "wof:name":"Dollar Financial Services",
    "wof:placetype":"venue"
},
  "geometry": {"coordinates":[-86.79766600000001,33.271896],"type":"Point"}
}