{
  "type": "Feature",
  "properties": {
    "addr:full":"200 S Court St Florence AL 35630",
    "addr:housenumber":"200",
    "addr:postcode":"35630",
    "addr:street":"S Court St",
    "iso:country":"US",
    "sg:address":"200 S Court St",
    "sg:city":"Florence",
    "sg:classifiers":[
        {
            "category":"Government",
            "subcategory":"Office",
            "type":"Public Place"
        }
    ],
    "sg:phone":"+1 256 760 5750",
    "sg:postcode":"35630",
    "sg:province":"AL",
    "wof:name":"Lauderdale County Commission",
    "wof:placetype":"venue"
},
  "geometry": {"coordinates":[-87.67476000000001,34.798351],"type":"Point"}
}