{
  "type": "Feature",
  "properties": {
    "iso:country":"US",
    "sg:address":"2249 State Rte 195",
    "sg:city":"Jasper",
    "sg:classifiers":[
        {
            "category":"Retail",
            "subcategory":"Auto Rental",
            "type":"Services"
        }
    ],
    "sg:phone":"+1 205 387 9735",
    "sg:postcode":"35503",
    "sg:province":"AL",
    "sg:tags":[
        "renting",
        "leasing",
        "trailer"
    ],
    "wof:name":"U-Haul Co",
    "wof:placetype":"venue"
},
  "geometry": {"coordinates":[-87.282692,33.883288],"type":"Point"}
}