{
  "type": "Feature",
  "properties": {
    "addr:full":"11751 US Hwy 82 Maplesville AL 36750",
    "addr:housenumber":"11751",
    "addr:postcode":"36750",
    "addr:street":"Us Hwy 82 Maplesville",
    "iso:country":"US",
    "sg:address":"11751 US Hwy 82",
    "sg:city":"Maplesville",
    "sg:classifiers":[
        {
            "category":"Organizations",
            "subcategory":"Religious Organization",
            "type":"Services"
        }
    ],
    "sg:phone":"+1 334 366 1484",
    "sg:postcode":"36750",
    "sg:province":"AL",
    "sg:tags":[
        "church"
    ],
    "wof:name":"University Hwy Church Of God",
    "wof:placetype":"venue"
},
  "geometry": {"coordinates":[-86.829322,32.713091],"type":"Point"}
}