{
  "type": "Feature",
  "properties": {
    "iso:country":"US",
    "sg:address":"214 Barnett Blvd",
    "sg:city":"Tallassee",
    "sg:classifiers":[
        {
            "category":"Government",
            "subcategory":"Office",
            "type":"Public Place"
        }
    ],
    "sg:phone":"+1 334 283 6571",
    "sg:postcode":"36078",
    "sg:province":"AL",
    "sg:tags":[
        "city"
    ],
    "wof:name":"Tallassee City Clerk",
    "wof:placetype":"venue"
},
  "geometry": {"coordinates":[-85.894874,32.536304],"type":"Point"}
}