{
  "type": "Feature",
  "properties": {
    "addr:full":"113 Carnegie Loop Meridianville AL 35759",
    "addr:housenumber":"113",
    "addr:postcode":"35759",
    "addr:street":"Carnegie Loop",
    "iso:country":"US",
    "sg:address":"113 Carnegie Loop",
    "sg:city":"Meridianville",
    "sg:classifiers":[
        {
            "category":"Building & Trades",
            "subcategory":"Construction",
            "type":"Services"
        }
    ],
    "sg:phone":"+1 256 828 7172",
    "sg:postcode":"35759",
    "sg:province":"AL",
    "sg:tags":[
        "insulating",
        "drywall",
        "contractor"
    ],
    "wof:name":"Michaels Drywall",
    "wof:placetype":"venue"
},
  "geometry": {"coordinates":[-86.568021,34.87076],"type":"Point"}
}