{
  "type": "Feature",
  "properties": {
    "addr:full":"113 2nd Ave NE Cullman AL 35055",
    "addr:housenumber":"113",
    "addr:postcode":"35055",
    "addr:street":"2Nd Ave Ne",
    "iso:country":"US",
    "sg:address":"113 2nd Ave NE",
    "sg:city":"Cullman",
    "sg:classifiers":[
        {
            "category":"Insurance",
            "subcategory":"Insurance Agent",
            "type":"Services"
        }
    ],
    "sg:phone":"+1 256 734 6009",
    "sg:postcode":"35055",
    "sg:province":"AL",
    "wof:name":"Primerica Financial Svc",
    "wof:placetype":"venue"
},
  "geometry": {"coordinates":[-86.842727,34.179027],"type":"Point"}
}