{
  "type": "Feature",
  "properties": {
    "iso:country":"US",
    "sg:address":"4420 Veterans Memorial Dr",
    "sg:city":"Fairfield",
    "sg:classifiers":[
        {
            "category":"Autos & Motor Vehicles",
            "subcategory":"Auto Supplies",
            "type":"Retail Goods"
        }
    ],
    "sg:phone":"+1 205 786 4566",
    "sg:postcode":"35064",
    "sg:province":"AL",
    "sg:tags":[
        "filter",
        "gas"
    ],
    "wof:name":"ENK Ind Filter & Battery Co",
    "wof:placetype":"venue"
},
  "geometry": {"coordinates":[-86.91693,33.493634],"type":"Point"}
}