{
  "type": "Feature",
  "properties": {
    "iso:country":"US",
    "sg:address":"824 McFarland Blvd",
    "sg:city":"Northport",
    "sg:classifiers":[
        {
            "category":"Professional",
            "type":"Services"
        },
        {
            "category":"Restaurant",
            "type":"Food & Drink"
        }
    ],
    "sg:phone":"+1 205 330 4000",
    "sg:postcode":"35476",
    "sg:province":"AL",
    "wof:name":"Golden Rule Bbq Northport",
    "wof:placetype":"venue"
},
  "geometry": {"coordinates":[-87.562217,33.237133],"type":"Point"}
}