{
  "type": "Feature",
  "properties": {
    "iso:country":"US",
    "sg:address":"1110 Hillcrest Rd",
    "sg:city":"Mobile",
    "sg:classifiers":[
        {
            "category":"Professional",
            "subcategory":"Accounting & Tax Preparation",
            "type":"Services"
        }
    ],
    "sg:phone":"+1 251 639 9174",
    "sg:postcode":"36695",
    "sg:province":"AL",
    "wof:name":"Global Administrative Services",
    "wof:placetype":"venue"
},
  "geometry": {"coordinates":[-88.190775,30.667509],"type":"Point"}
}