{
  "type": "Feature",
  "properties": {
    "iso:country":"US",
    "sg:address":"3620 Co Rd 11",
    "sg:city":"Florence",
    "sg:classifiers":[
        {
            "category":"Building & Trades",
            "subcategory":"Plumbing",
            "type":"Services"
        }
    ],
    "sg:phone":"+1 256 764 5878",
    "sg:postcode":"35633",
    "sg:province":"AL",
    "sg:tags":[
        "heating",
        "contractor"
    ],
    "wof:name":"Certified Heating & Cooling",
    "wof:placetype":"venue"
},
  "geometry": {"coordinates":[-87.731773,34.960358],"type":"Point"}
}