{
  "type": "Feature",
  "properties": {
    "iso:country":"US",
    "sg:address":"908 Shelton Beach Rd",
    "sg:city":"Saraland",
    "sg:classifiers":[
        {
            "category":"Building & Trades",
            "subcategory":"Plumbing",
            "type":"Services"
        }
    ],
    "sg:phone":"+1 251 675 9477",
    "sg:postcode":"36571",
    "sg:province":"AL",
    "sg:tags":[
        "conditioning",
        "air",
        "system",
        "contractor"
    ],
    "wof:name":"Mobil Aire Heating & Air Cond",
    "wof:placetype":"venue"
},
  "geometry": {"coordinates":[-88.095674,30.809523],"type":"Point"}
}