{
  "type": "Feature",
  "properties": {
    "iso:country":"US",
    "sg:address":"134 1st St SE",
    "sg:city":"Vernon",
    "sg:classifiers":[
        {
            "category":"Food & Beverages",
            "subcategory":"Groceries & Convenience Stores",
            "type":"Retail Goods"
        }
    ],
    "sg:phone":"+1 205 695 7449",
    "sg:postcode":"35592",
    "sg:province":"AL",
    "wof:name":"T J's Mini Mart",
    "wof:placetype":"venue"
},
  "geometry": {"coordinates":[-88.108743,33.754257],"type":"Point"}
}