{
  "type": "Feature",
  "properties": {
    "iso:country":"US",
    "sg:address":"1806 Wilkinson St",
    "sg:city":"Athens",
    "sg:classifiers":[
        {
            "category":"Professional",
            "subcategory":"Management & Consulting",
            "type":"Services"
        }
    ],
    "sg:phone":"+1 256 232 2386",
    "sg:postcode":"35611",
    "sg:province":"AL",
    "sg:tags":[
        "consultant",
        "industrial"
    ],
    "wof:name":"Limestone County Economic Dev",
    "wof:placetype":"venue"
},
  "geometry": {"coordinates":[-86.967289,34.819631],"type":"Point"}
}