{
  "type": "Feature",
  "properties": {
    "iso:country":"US",
    "sg:address":"255 Murfee Dr",
    "sg:city":"Prattville",
    "sg:classifiers":[
        {
            "category":"Building & Trades",
            "subcategory":"Construction",
            "type":"Services"
        }
    ],
    "sg:phone":"+1 334 361 2881",
    "sg:postcode":"36066",
    "sg:province":"AL",
    "sg:tags":[
        "hanging",
        "contractor"
    ],
    "wof:name":"B & A Painting",
    "wof:placetype":"venue"
},
  "geometry": {"coordinates":[-86.410736,32.431151],"type":"Point"}
}