{
  "type": "Feature",
  "properties": {
    "iso:country":"US",
    "sg:address":"3704 Airport Blvd",
    "sg:city":"Mobile",
    "sg:classifiers":[
        {
            "category":"Restaurant",
            "type":"Food & Drink"
        }
    ],
    "sg:menulink":"http://www.allmenus.com/al/mobile/95276-lone-star-steakhouse--saloon/menu/",
    "sg:phone":"+1 251 341 0220",
    "sg:postcode":"36608",
    "sg:province":"AL",
    "sg:tags":[
        "american",
        "steakhouse"
    ],
    "wof:name":"Lone Star Steakhouse & Saloon",
    "wof:placetype":"venue"
},
  "geometry": {"coordinates":[-88.134956,30.676423],"type":"Point"}
}