{
  "type": "Feature",
  "properties": {
    "iso:country":"US",
    "sg:address":"16 Belcher Dr",
    "sg:city":"Pelham",
    "sg:classifiers":[
        {
            "category":"Manufacturing",
            "subcategory":"Textiles",
            "type":"Manufacturing & Wholesale Goods"
        },
        {
            "category":"Manufacturing",
            "subcategory":"Chemicals & Compounds",
            "type":"Manufacturing & Wholesale Goods"
        }
    ],
    "sg:phone":"+1 205 664 2255",
    "sg:postcode":"35124",
    "sg:province":"AL",
    "sg:tags":[
        "synthetic",
        "resin",
        "mfg"
    ],
    "wof:name":"Southern Foundry Resin Inc",
    "wof:placetype":"venue"
},
  "geometry": {"coordinates":[-86.798229,33.321587],"type":"Point"}
}