{
  "type": "Feature",
  "properties": {
    "addr:full":"16 Belcher Dr Pelham AL 35124",
    "addr:housenumber":"16",
    "addr:postcode":"35124",
    "addr:street":"Belcher Dr",
    "iso:country":"US",
    "sg:address":"16 Belcher Dr",
    "sg:city":"Pelham",
    "sg:classifiers":[
        {
            "category":"Manufacturing",
            "subcategory":"Textiles",
            "type":"Manufacturing & Wholesale Goods"
        },
        {
            "category":"Manufacturing",
            "subcategory":"Chemicals & Compounds",
            "type":"Manufacturing & Wholesale Goods"
        }
    ],
    "sg:phone":"+1 205 664 2255",
    "sg:postcode":"35124",
    "sg:province":"AL",
    "sg:tags":[
        "synthetic",
        "resin",
        "mfg"
    ],
    "wof:name":"Southern Foundry Resin Inc",
    "wof:placetype":"venue"
},
  "geometry": {"coordinates":[-86.79822900000001,33.321587],"type":"Point"}
}