{
  "type": "Feature",
  "properties": {
    "iso:country":"US",
    "sg:address":"574 Posey Rd",
    "sg:city":"Blountsville",
    "sg:classifiers":[
        {
            "category":"Retail",
            "subcategory":"Repair Shop",
            "type":"Services"
        }
    ],
    "sg:phone":"+1 205 429 4594",
    "sg:postcode":"35031",
    "sg:province":"AL",
    "sg:tags":[
        "equipment",
        "conditioning",
        "air"
    ],
    "wof:name":"Central Air Svc",
    "wof:placetype":"venue"
},
  "geometry": {"coordinates":[-86.557473,34.043492],"type":"Point"}
}