{
  "type": "Feature",
  "properties": {
    "iso:country":"US",
    "sg:address":"144 Arrowhead Dr",
    "sg:city":"Montgomery",
    "sg:classifiers":[
        {
            "category":"Shopping",
            "type":"Retail Goods"
        }
    ],
    "sg:phone":"+1 334 244 9400",
    "sg:postcode":"36117",
    "sg:province":"AL",
    "sg:tags":[
        "merchandise"
    ],
    "wof:name":"Pet Mall Inc",
    "wof:placetype":"venue"
},
  "geometry": {"coordinates":[-86.14564,32.377889],"type":"Point"}
}