{
  "type": "Feature",
  "properties": {
    "addr:full":"3715 Dauphin St Mobile AL 36608",
    "addr:housenumber":"3715",
    "addr:postcode":"36608",
    "addr:street":"Dauphin St",
    "iso:country":"US",
    "sg:address":"3715 Dauphin St",
    "sg:city":"Mobile",
    "sg:classifiers":[
        {
            "category":"Professional",
            "subcategory":"Management & Consulting",
            "type":"Services"
        },
        {
            "category":"Health Services",
            "subcategory":"Medical Lab",
            "type":"Services"
        }
    ],
    "sg:phone":"+1 251 342 7489",
    "sg:postcode":"36608",
    "sg:province":"AL",
    "sg:tags":[
        "laboratory",
        "business"
    ],
    "wof:name":"Industrial Drug Testing Inc",
    "wof:placetype":"venue"
},
  "geometry": {"coordinates":[-88.138879,30.685506],"type":"Point"}
}