{
  "type": "Feature",
  "properties": {
    "addr:full":"2695 Pelham Pkwy Pelham AL 35124",
    "addr:housenumber":"2695",
    "addr:postcode":"35124",
    "addr:street":"Pelham Pkwy",
    "iso:country":"US",
    "sg:address":"2695 Pelham Pkwy",
    "sg:city":"Pelham",
    "sg:classifiers":[
        {
            "category":"Banks & Credit Unions",
            "subcategory":"Bank",
            "type":"Services"
        }
    ],
    "sg:phone":"+1 205 414 3660",
    "sg:postcode":"35124",
    "sg:province":"AL",
    "wof:name":"Bank Of Alabama",
    "wof:placetype":"venue"
},
  "geometry": {"coordinates":[-86.800543,33.314324],"type":"Point"}
}