{
  "type": "Feature",
  "properties": {
    "iso:country":"US",
    "sg:address":"25604 Friendship Rd",
    "sg:city":"Daphne",
    "sg:classifiers":[
        {
            "category":"Communications",
            "subcategory":"Film & Video Production",
            "type":"Services"
        }
    ],
    "sg:phone":"+1 251 621 1800",
    "sg:postcode":"36526",
    "sg:province":"AL",
    "sg:tags":[
        "taping"
    ],
    "wof:name":"CVS Teleproductions",
    "wof:placetype":"venue"
},
  "geometry": {"coordinates":[-87.877321,30.597559],"type":"Point"}
}