{
  "type": "Feature",
  "properties": {
    "addr:full":"3215 Atlanta Hwy Montgomery AL 36109",
    "addr:housenumber":"3215",
    "addr:postcode":"36109",
    "addr:street":"Atlanta Hwy",
    "iso:country":"US",
    "sg:address":"3215 Atlanta Hwy",
    "sg:city":"Montgomery",
    "sg:classifiers":[
        {
            "category":"Retail",
            "subcategory":"Auto Rental",
            "type":"Services"
        }
    ],
    "sg:phone":"+1 334 272 4279",
    "sg:postcode":"36109",
    "sg:province":"AL",
    "sg:tags":[
        "truck"
    ],
    "wof:name":"U-Haul",
    "wof:placetype":"venue"
},
  "geometry": {"coordinates":[-86.264044,32.38381],"type":"Point"}
}