{
  "type": "Feature",
  "properties": {
    "addr:full":"2670 Old Birmingham Hwy Sylacauga AL 35150",
    "addr:housenumber":"2670",
    "addr:postcode":"35150",
    "addr:street":"Old Birmingham Hwy",
    "iso:country":"US",
    "sg:address":"2670 Old Birmingham Hwy",
    "sg:city":"Sylacauga",
    "sg:classifiers":[
        {
            "category":"Autos & Motor Vehicles",
            "subcategory":"Boat Sales",
            "type":"Retail Goods"
        }
    ],
    "sg:phone":"+1 256 245 8920",
    "sg:postcode":"35150",
    "sg:province":"AL",
    "sg:tags":[
        "dealer",
        "sales"
    ],
    "wof:name":"Sylacauga Marine & Atv",
    "wof:placetype":"venue"
},
  "geometry": {"coordinates":[-86.287531,33.186424],"type":"Point"}
}