{
  "type": "Feature",
  "properties": {
    "addr:full":"1615 21 Ct Phenix City AL 36867",
    "addr:housenumber":"1615",
    "addr:postcode":"36867",
    "addr:street":"21 Ct Phenix City Al",
    "iso:country":"US",
    "sg:address":"1615 21 Ct",
    "sg:city":"Phenix City",
    "sg:classifiers":[
        {
            "category":"Health Services",
            "subcategory":"Doctor",
            "type":"Services"
        }
    ],
    "sg:phone":"+1 334 297 4883",
    "sg:postcode":"36867",
    "sg:province":"AL",
    "sg:tags":[
        "physician",
        "surgeon"
    ],
    "wof:name":"Greensnake Medical Clinic",
    "wof:placetype":"venue"
},
  "geometry": {"coordinates":[-85.02274199999999,32.47538],"type":"Point"}
}