{
  "type": "Feature",
  "properties": {
    "iso:country":"US",
    "sg:address":"117 Ware Dr NE",
    "sg:city":"Huntsville",
    "sg:classifiers":[
        {
            "category":"Autos & Motor Vehicles",
            "subcategory":"Automobile Sales",
            "type":"Retail Goods"
        }
    ],
    "sg:phone":"+1 256 859 2970",
    "sg:postcode":"35811",
    "sg:province":"AL",
    "sg:tags":[
        "car",
        "used",
        "dealer"
    ],
    "wof:name":"Berry John Used Cars",
    "wof:placetype":"venue"
},
  "geometry": {"coordinates":[-86.538768,34.792919],"type":"Point"}
}