{
  "type": "Feature",
  "properties": {
    "iso:country":"US",
    "sg:address":"20758 Pleasant Grove Rd",
    "sg:city":"Vance",
    "sg:classifiers":[
        {
            "category":"Manufacturing",
            "subcategory":"Apparel",
            "type":"Manufacturing & Wholesale Goods"
        }
    ],
    "sg:phone":"+1 205 477 9355",
    "sg:postcode":"35490",
    "sg:province":"AL",
    "sg:tags":[
        "household",
        "furnishing",
        "mfg"
    ],
    "wof:name":"Bama Broom & Mop",
    "wof:placetype":"venue"
},
  "geometry": {"coordinates":[-87.159138,33.298768],"type":"Point"}
}