{
  "type": "Feature",
  "properties": {
    "iso:country":"US",
    "sg:address":"9564 State Rte 119",
    "sg:city":"Alabaster",
    "sg:classifiers":[
        {
            "category":"Retail",
            "subcategory":"Auto Repair",
            "type":"Services"
        }
    ],
    "sg:phone":"+1 205 663 3603",
    "sg:postcode":"35007",
    "sg:province":"AL",
    "sg:tags":[
        "repairing",
        "automobile"
    ],
    "wof:name":"Performance Lube",
    "wof:placetype":"venue"
},
  "geometry": {"coordinates":[-86.82441,33.219132],"type":"Point"}
}