{
  "type": "Feature",
  "properties": {
    "iso:country":"US",
    "sg:address":"1036 Green Springs Ave S",
    "sg:city":"Birmingham",
    "sg:classifiers":[
        {
            "category":"Building & Trades",
            "subcategory":"Construction",
            "type":"Services"
        }
    ],
    "sg:phone":"+1 205 322 6491",
    "sg:postcode":"35205",
    "sg:province":"AL",
    "sg:tags":[
        "contractor"
    ],
    "wof:name":"Old Town Restoration",
    "wof:placetype":"venue"
},
  "geometry": {"coordinates":[-86.813124,33.485999],"type":"Point"}
}