{
  "type": "Feature",
  "properties": {
    "addr:full":"8 Village Sq Clanton AL 35045",
    "addr:housenumber":"8",
    "addr:postcode":"35045",
    "addr:street":"Village Sq",
    "iso:country":"US",
    "sg:address":"8 Village Sq",
    "sg:city":"Clanton",
    "sg:classifiers":[
        {
            "category":"Food & Beverages",
            "subcategory":"Specialty",
            "type":"Retail Goods"
        }
    ],
    "sg:phone":"+1 205 755 3620",
    "sg:postcode":"35045",
    "sg:province":"AL",
    "sg:tags":[
        "health",
        "diet"
    ],
    "wof:name":"Herb & Nutrition Ctr",
    "wof:placetype":"venue"
},
  "geometry": {"coordinates":[-86.630684,32.836961],"type":"Point"}
}