{
  "type": "Feature",
  "properties": {
    "addr:full":"200 N Main St Columbiana AL 35051",
    "addr:housenumber":"200",
    "addr:postcode":"35051",
    "addr:street":"N Main St",
    "iso:country":"US",
    "sg:address":"200 N Main St",
    "sg:city":"Columbiana",
    "sg:classifiers":[
        {
            "category":"Organizations",
            "subcategory":"Religious Organization",
            "type":"Services"
        }
    ],
    "sg:phone":"+1 205 669 7164",
    "sg:postcode":"35051",
    "sg:province":"AL",
    "sg:tags":[
        "church"
    ],
    "sg:website":"www.columbianaumc.com",
    "wof:name":"Columbiana United Meth Church",
    "wof:placetype":"venue"
},
  "geometry": {"coordinates":[-86.607085,33.182094],"type":"Point"}
}