{
  "type": "Feature",
  "properties": {
    "addr:full":"9418 Huntingdon Ct Montgomery AL 36117",
    "addr:housenumber":"9418",
    "addr:postcode":"36117",
    "addr:street":"Huntingdon Ct",
    "iso:country":"US",
    "sg:address":"9418 Huntingdon Ct",
    "sg:city":"Montgomery",
    "sg:classifiers":[
        {
            "category":"Professional",
            "subcategory":"Business Services",
            "type":"Services"
        }
    ],
    "sg:phone":"+1 334 318 0107",
    "sg:postcode":"36117",
    "sg:province":"AL",
    "sg:tags":[
        "interior",
        "consultant",
        "design",
        "decorator"
    ],
    "wof:name":"Browder Interior Trim",
    "wof:placetype":"venue"
},
  "geometry": {"coordinates":[-86.150116,32.345725],"type":"Point"}
}