{
  "type": "Feature",
  "properties": {
    "addr:full":"1930 Co Rd 701 Clanton AL 35045",
    "addr:housenumber":"1930;701",
    "addr:postcode":"35045",
    "addr:street":"Co Rd",
    "iso:country":"US",
    "sg:address":"1930 Co Rd 701",
    "sg:city":"Clanton",
    "sg:classifiers":[
        {
            "category":"Professional",
            "subcategory":"Business Services",
            "type":"Services"
        }
    ],
    "sg:phone":"+1 205 755 5833",
    "sg:postcode":"35045",
    "sg:province":"AL",
    "wof:name":"Mitchell Enterprises",
    "wof:placetype":"venue"
},
  "geometry": {"coordinates":[-86.653235,32.851871],"type":"Point"}
}