{
  "type": "Feature",
  "properties": {
    "addr:full":"8780 State Rte 168 Boaz AL 35957",
    "addr:housenumber":"8780",
    "addr:postcode":"35957",
    "addr:street":"State Rte 168",
    "iso:country":"US",
    "sg:address":"8780 State Rte 168",
    "sg:city":"Boaz",
    "sg:classifiers":[
        {
            "category":"Autos & Motor Vehicles",
            "subcategory":"Automobile Sales",
            "type":"Retail Goods"
        }
    ],
    "sg:phone":"+1 256 593 8293",
    "sg:postcode":"35957",
    "sg:province":"AL",
    "sg:tags":[
        "car",
        "dealer"
    ],
    "wof:name":"Brooks Motors Inc",
    "wof:placetype":"venue"
},
  "geometry": {"coordinates":[-86.186947,34.192724],"type":"Point"}
}