{
  "type": "Feature",
  "properties": {
    "addr:full":"6753 Remington Cir Pelham AL 35124",
    "addr:housenumber":"6753",
    "addr:postcode":"35124",
    "addr:street":"Remington Cir",
    "iso:country":"US",
    "sg:address":"6753 Remington Cir",
    "sg:city":"Pelham",
    "sg:classifiers":[
        {
            "category":"Professional",
            "subcategory":"Computer Services",
            "type":"Services"
        }
    ],
    "sg:phone":"+1 205 403 3995",
    "sg:postcode":"35124",
    "sg:province":"AL",
    "sg:tags":[
        "datum"
    ],
    "wof:name":"Astraa Inc",
    "wof:placetype":"venue"
},
  "geometry": {"coordinates":[-86.77752,33.345662],"type":"Point"}
}