{
  "type": "Feature",
  "properties": {
    "iso:country":"US",
    "sg:address":"6 Commerce Ave",
    "sg:city":"Hueytown",
    "sg:classifiers":[
        {
            "category":"Home & Garden",
            "subcategory":"Home Furnishings",
            "type":"Retail Goods"
        }
    ],
    "sg:phone":"+1 205 491 8363",
    "sg:postcode":"35023",
    "sg:province":"AL",
    "sg:tags":[
        "mirror"
    ],
    "wof:name":"Emerald Mirror & Glass",
    "wof:placetype":"venue"
},
  "geometry": {"coordinates":[-86.975739,33.436497],"type":"Point"}
}