{
  "type": "Feature",
  "properties": {
    "iso:country":"US",
    "sg:address":"144 Jetplex Ln",
    "sg:city":"Madison",
    "sg:classifiers":[
        {
            "category":"Shopping",
            "subcategory":"Bicycles & Sporting Goods",
            "type":"Retail Goods"
        },
        {
            "category":"Sports & Exercise",
            "subcategory":"Golf",
            "type":"Entertainment"
        }
    ],
    "sg:phone":"+1 256 864 1900",
    "sg:postcode":"35758",
    "sg:province":"AL",
    "sg:tags":[
        "equipment",
        "course",
        "supply"
    ],
    "sg:website":"http://www.finest.com",
    "wof:name":"S K Fiber Golf",
    "wof:placetype":"venue"
},
  "geometry": {"coordinates":[-86.775903,34.670173],"type":"Point"}
}