{
  "type": "Feature",
  "properties": {
    "addr:full":"2024 Temple Ave N Fayette AL 35555",
    "addr:housenumber":"2024",
    "addr:postcode":"35555",
    "addr:street":"Temple Ave N",
    "iso:country":"US",
    "sg:address":"2024 Temple Ave N",
    "sg:city":"Fayette",
    "sg:classifiers":[
        {
            "category":"Autos & Motor Vehicles",
            "subcategory":"Automobile Sales",
            "type":"Retail Goods"
        }
    ],
    "sg:phone":"+1 205 932 5225",
    "sg:postcode":"35555",
    "sg:province":"AL",
    "sg:tags":[
        "car",
        "dealer"
    ],
    "sg:website":"www.averyfordmercury.com",
    "wof:name":"Avery Ford-Mercury",
    "wof:placetype":"venue"
},
  "geometry": {"coordinates":[-87.81717399999999,33.717818],"type":"Point"}
}