{
  "type": "Feature",
  "properties": {
    "iso:country":"US",
    "sg:address":"96 Hinds St",
    "sg:city":"Pelham",
    "sg:classifiers":[
        {
            "category":"Manufacturing",
            "subcategory":"Glass & Minerals",
            "type":"Manufacturing & Wholesale Goods"
        }
    ],
    "sg:phone":"+1 205 620 5335",
    "sg:postcode":"35124",
    "sg:province":"AL",
    "sg:tags":[
        "cut",
        "mfg"
    ],
    "wof:name":"Cahaba Valley Stone & Tile LLC",
    "wof:placetype":"venue"
},
  "geometry": {"coordinates":[-86.815652,33.280789],"type":"Point"}
}