{
  "type": "Feature",
  "properties": {
    "iso:country":"US",
    "sg:address":"1712 2nd Ave N",
    "sg:city":"Bessemer",
    "sg:classifiers":[
        {
            "category":"Retail",
            "subcategory":"Laundry & Dry Cleaning",
            "type":"Services"
        }
    ],
    "sg:phone":"+1 205 424 0106",
    "sg:postcode":"35020",
    "sg:province":"AL",
    "sg:tags":[
        "drycleaning",
        "plant"
    ],
    "wof:name":"Smith Cleaners",
    "wof:placetype":"venue"
},
  "geometry": {"coordinates":[-86.953566,33.400799],"type":"Point"}
}