{
  "type": "Feature",
  "properties": {
    "iso:country":"US",
    "sg:address":"180 Park Pl",
    "sg:city":"Leighton",
    "sg:classifiers":[
        {
            "category":"Organizations",
            "subcategory":"Professional Association",
            "type":"Services"
        }
    ],
    "sg:phone":"+1 256 446 8837",
    "sg:postcode":"35646",
    "sg:province":"AL",
    "wof:name":"Reynolds Alloys Recr Assn",
    "wof:placetype":"venue"
},
  "geometry": {"coordinates":[-87.509337,34.741878],"type":"Point"}
}