{
  "type": "Feature",
  "properties": {
    "iso:country":"US",
    "sg:address":"14025 5th Ave",
    "sg:city":"Bayou La Batre",
    "sg:classifiers":[
        {
            "category":"Professional",
            "subcategory":"Testing Lab",
            "type":"Services"
        }
    ],
    "sg:phone":"+1 251 824 4452",
    "sg:postcode":"36509",
    "sg:province":"AL",
    "sg:tags":[
        "laboratory"
    ],
    "wof:name":"Global X-Ray & Testing Corp",
    "wof:placetype":"venue"
},
  "geometry": {"coordinates":[-88.248976,30.398544],"type":"Point"}
}