{
  "type": "Feature",
  "properties": {
    "addr:full":"677 University Blvd S Mobile AL 36609",
    "addr:housenumber":"677",
    "addr:postcode":"36609",
    "addr:street":"University Blvd S",
    "iso:country":"US",
    "sg:address":"677 University Blvd S",
    "sg:city":"Mobile",
    "sg:classifiers":[
        {
            "category":"Banks & Credit Unions",
            "subcategory":"Investment Brokerage",
            "type":"Services"
        }
    ],
    "sg:phone":"+1 251 666 2299",
    "sg:postcode":"36609",
    "sg:province":"AL",
    "sg:tags":[
        "consultant",
        "planning",
        "financial"
    ],
    "wof:name":"Mony Group",
    "wof:placetype":"venue"
},
  "geometry": {"coordinates":[-88.163191,30.661739],"type":"Point"}
}