{
  "type": "Feature",
  "properties": {
    "iso:country":"US",
    "sg:address":"950 Co Rd 1598",
    "sg:city":"Baileyton",
    "sg:classifiers":[
        {
            "category":"Wholesale",
            "subcategory":"Plants",
            "type":"Manufacturing & Wholesale Goods"
        }
    ],
    "sg:phone":"+1 256 302 0611",
    "sg:postcode":"35019",
    "sg:province":"AL",
    "sg:tags":[
        "supply"
    ],
    "wof:name":"Arab Wholesale Nursery",
    "wof:placetype":"venue"
},
  "geometry": {"coordinates":[-86.600886,34.294165],"type":"Point"}
}