{
  "type": "Feature",
  "properties": {
    "iso:country":"US",
    "sg:address":"231 Hanchey St",
    "sg:city":"Troy",
    "sg:classifiers":[
        {
            "category":"Wholesale",
            "subcategory":"Farm Supplies",
            "type":"Manufacturing & Wholesale Goods"
        }
    ],
    "sg:phone":"+1 334 566 1202",
    "sg:postcode":"36081",
    "sg:province":"AL",
    "sg:tags":[
        "peanut",
        "product"
    ],
    "wof:name":"Sessions Co Inc",
    "wof:placetype":"venue"
},
  "geometry": {"coordinates":[-85.968965,31.80482],"type":"Point"}
}