{
  "type": "Feature",
  "properties": {
    "iso:country":"US",
    "sg:address":"4240 Carmichael Ct N",
    "sg:city":"Montgomery",
    "sg:classifiers":[
        {
            "category":"Real Estate",
            "subcategory":"Real Estate Agent",
            "type":"Services"
        }
    ],
    "sg:phone":"+1 334 323 1005",
    "sg:postcode":"36106",
    "sg:province":"AL",
    "sg:website":"www.remax-montgomery-al.com",
    "wof:name":"Re/Max",
    "wof:placetype":"venue"
},
  "geometry": {"coordinates":[-86.236026,32.358977],"type":"Point"}
}