{
  "type": "Feature",
  "properties": {
    "addr:full":"818 Memphis St Dothan AL 36301",
    "addr:housenumber":"818",
    "addr:postcode":"36301",
    "addr:street":"Memphis St",
    "iso:country":"US",
    "sg:address":"818 Memphis St",
    "sg:city":"Dothan",
    "sg:classifiers":[
        {
            "category":"Professional",
            "type":"Services"
        }
    ],
    "sg:phone":"+1 334 673 1139",
    "sg:postcode":"36301",
    "sg:province":"AL",
    "wof:name":"Chris Wright",
    "wof:placetype":"venue"
},
  "geometry": {"coordinates":[-85.3818,31.211022],"type":"Point"}
}