{
  "type": "Feature",
  "properties": {
    "iso:country":"US",
    "sg:address":"788 Old US Hwy 231",
    "sg:city":"Wetumpka",
    "sg:classifiers":[
        {
            "category":"Restaurant",
            "type":"Food & Drink"
        }
    ],
    "sg:phone":"+1 334 514 7184",
    "sg:postcode":"36092",
    "sg:province":"AL",
    "sg:tags":[
        "eating"
    ],
    "wof:name":"White Wings",
    "wof:placetype":"venue"
},
  "geometry": {"coordinates":[-86.22341,32.603432],"type":"Point"}
}