{
  "type": "Feature",
  "properties": {
    "iso:country":"US",
    "sg:address":"701 Pine Grove Rd",
    "sg:city":"Harvest",
    "sg:classifiers":[
        {
            "category":"Professional",
            "subcategory":"Business Services",
            "type":"Services"
        }
    ],
    "sg:phone":"+1 256 837 6852",
    "sg:postcode":"35749",
    "sg:province":"AL",
    "wof:name":"Johnson Group Inc",
    "wof:placetype":"venue"
},
  "geometry": {"coordinates":[-86.762111,34.794134],"type":"Point"}
}