{
  "type": "Feature",
  "properties": {
    "iso:country":"US",
    "sg:address":"642 Maggie St",
    "sg:city":"Montgomery",
    "sg:classifiers":[
        {
            "category":"Organizations",
            "subcategory":"Religious Organization",
            "type":"Services"
        }
    ],
    "sg:phone":"+1 334 263 3215",
    "sg:postcode":"36106",
    "sg:province":"AL",
    "wof:name":"Maggie Street Baptist Church",
    "wof:placetype":"venue"
},
  "geometry": {"coordinates":[-86.290544,32.371023],"type":"Point"}
}