{
  "type": "Feature",
  "properties": {
    "iso:country":"US",
    "sg:address":"109 Caldwell St",
    "sg:city":"Greenville",
    "sg:classifiers":[
        {
            "category":"Government",
            "subcategory":"Office",
            "type":"Public Place"
        }
    ],
    "sg:phone":"+1 334 382 4400",
    "sg:postcode":"36037",
    "sg:province":"AL",
    "wof:name":"Butler County Office",
    "wof:placetype":"venue"
},
  "geometry": {"coordinates":[-86.626077,31.828421],"type":"Point"}
}