{
  "type": "Feature",
  "properties": {
    "iso:country":"US",
    "sg:address":"5362 Raines Dr",
    "sg:city":"Mobile",
    "sg:classifiers":[
        {
            "category":"Professional",
            "subcategory":"Computer Services",
            "type":"Services"
        }
    ],
    "sg:phone":"+1 251 661 0634",
    "sg:postcode":"36609",
    "sg:province":"AL",
    "sg:tags":[
        "datum"
    ],
    "wof:name":"Cheapgunpartscom",
    "wof:placetype":"venue"
},
  "geometry": {"coordinates":[-88.166425,30.654085],"type":"Point"}
}