{
  "type": "Feature",
  "properties": {
    "addr:full":"86 Weibel Dr Birmingham AL 35228",
    "addr:housenumber":"86",
    "addr:postcode":"35228",
    "addr:street":"Weibel Dr",
    "iso:country":"US",
    "sg:address":"86 Weibel Dr",
    "sg:city":"Birmingham",
    "sg:classifiers":[
        {
            "category":"Restaurant",
            "type":"Food & Drink"
        }
    ],
    "sg:phone":"+1 205 925 9007",
    "sg:postcode":"35228",
    "sg:province":"AL",
    "sg:tags":[
        "eating"
    ],
    "wof:name":"Rallys Hamburgers",
    "wof:placetype":"venue"
},
  "geometry": {"coordinates":[-86.91184800000001,33.463533],"type":"Point"}
}