{
  "type": "Feature",
  "properties": {
    "iso:country":"US",
    "sg:address":"5364 Nanette Dr",
    "sg:city":"Mobile",
    "sg:classifiers":[
        {
            "category":"Personal",
            "subcategory":"Beauty Salon",
            "type":"Services"
        }
    ],
    "sg:phone":"+1 251 661 5962",
    "sg:postcode":"36619",
    "sg:province":"AL",
    "sg:tags":[
        "shop",
        "barber"
    ],
    "wof:name":"Hair It Is",
    "wof:placetype":"venue"
},
  "geometry": {"coordinates":[-88.20546,30.584351],"type":"Point"}
}