{
  "type": "Feature",
  "properties": {
    "iso:country":"US",
    "sg:address":"5550 McFarland Blvd",
    "sg:city":"Northport",
    "sg:classifiers":[
        {
            "category":"Retail",
            "subcategory":"Laundry & Dry Cleaning",
            "type":"Services"
        }
    ],
    "sg:phone":"+1 205 333 2866",
    "sg:postcode":"35476",
    "sg:province":"AL",
    "sg:tags":[
        "cleaners"
    ],
    "wof:name":"1 Stop Laundry",
    "wof:placetype":"venue"
},
  "geometry": {"coordinates":[-87.60736900000001,33.236673],"type":"Point"}
}