{
  "type": "Feature",
  "properties": {
    "iso:country":"US",
    "sg:address":"4938 Garris Ln",
    "sg:city":"Gulf Shores",
    "sg:classifiers":[
        {
            "category":"Professional",
            "subcategory":"Management & Consulting",
            "type":"Services"
        }
    ],
    "sg:phone":"+1 251 454 2940",
    "sg:postcode":"36542",
    "sg:province":"AL",
    "sg:tags":[
        "crane",
        "marine",
        "certification"
    ],
    "wof:name":"Hyleca Inc",
    "wof:placetype":"venue"
},
  "geometry": {"coordinates":[-87.686775,30.296754],"type":"Point"}
}