{
  "type": "Feature",
  "properties": {
    "addr:full":"2051 Somerset Ln Birmingham AL 35242",
    "addr:housenumber":"2051",
    "addr:postcode":"35242",
    "addr:street":"Somerset Ln",
    "iso:country":"US",
    "sg:address":"2051 Somerset Ln",
    "sg:city":"Birmingham",
    "sg:classifiers":[
        {
            "category":"Building & Trades",
            "subcategory":"Construction",
            "type":"Services"
        }
    ],
    "sg:phone":"+1 205 991 3501",
    "sg:postcode":"35242",
    "sg:province":"AL",
    "sg:tags":[
        "house"
    ],
    "wof:name":"Homeimprovement Store",
    "wof:placetype":"venue"
},
  "geometry": {"coordinates":[-86.680892,33.430652],"type":"Point"}
}