{
  "type": "Feature",
  "properties": {
    "iso:country":"US",
    "sg:address":"8337 US Hwy 431",
    "sg:city":"Albertville",
    "sg:classifiers":[
        {
            "category":"Utilities",
            "subcategory":"Mobile Phone",
            "type":"Services"
        }
    ],
    "sg:phone":"+1 256 878 2055",
    "sg:postcode":"35950",
    "sg:province":"AL",
    "sg:tags":[
        "communication",
        "radio",
        "telephone"
    ],
    "wof:name":"Cingular Wireless",
    "wof:placetype":"venue"
},
  "geometry": {"coordinates":[-86.222477,34.282235],"type":"Point"}
}