{
  "type": "Feature",
  "properties": {
    "iso:country":"US",
    "sg:address":"30524 Highway 278",
    "sg:city":"Addison",
    "sg:classifiers":[
        {
            "category":"Shopping",
            "subcategory":"Florist",
            "type":"Retail Goods"
        }
    ],
    "sg:phone":"+1 256 747 1635",
    "sg:postcode":"35540",
    "sg:province":"AL",
    "wof:name":"Howse Of Flowers The",
    "wof:placetype":"venue"
},
  "geometry": {"coordinates":[-87.21212199999999,34.186929],"type":"Point"}
}