{
  "type": "Feature",
  "properties": {
    "addr:full":"107 Yeager Ct NW Huntsville AL 35806",
    "addr:housenumber":"107",
    "addr:postcode":"35806",
    "addr:street":"Yeager Ct Nw",
    "iso:country":"US",
    "sg:address":"107 Yeager Ct NW",
    "sg:city":"Huntsville",
    "sg:classifiers":[
        {
            "category":"Building & Trades",
            "subcategory":"Construction",
            "type":"Services"
        }
    ],
    "sg:phone":"+1 256 851 7003",
    "sg:postcode":"35806",
    "sg:province":"AL",
    "sg:tags":[
        "acoustical",
        "drywall",
        "contractor"
    ],
    "wof:name":"Wayne's Acoustical & Drywall",
    "wof:placetype":"venue"
},
  "geometry": {"coordinates":[-86.665919,34.780761],"type":"Point"}
}