{
  "type": "Feature",
  "properties": {
    "iso:country":"US",
    "sg:address":"26094 State Rte 69",
    "sg:city":"Jasper",
    "sg:classifiers":[
        {
            "category":"Restaurant",
            "type":"Food & Drink"
        }
    ],
    "sg:phone":"+1 205 295 9833",
    "sg:postcode":"35504",
    "sg:province":"AL",
    "sg:tags":[
        "eating"
    ],
    "wof:name":"B & W Mobile Foods",
    "wof:placetype":"venue"
},
  "geometry": {"coordinates":[-87.204968,33.843914],"type":"Point"}
}