{
  "type": "Feature",
  "properties": {
    "addr:full":"26094 State Rte 69 Jasper AL 35504",
    "addr:housenumber":"26094",
    "addr:postcode":"35504",
    "addr:street":"State Rte 69",
    "iso:country":"US",
    "sg:address":"26094 State Rte 69",
    "sg:city":"Jasper",
    "sg:classifiers":[
        {
            "category":"Restaurant",
            "type":"Food & Drink"
        }
    ],
    "sg:phone":"+1 205 295 9833",
    "sg:postcode":"35504",
    "sg:province":"AL",
    "sg:tags":[
        "eating"
    ],
    "wof:name":"B & W Mobile Foods",
    "wof:placetype":"venue"
},
  "geometry": {"coordinates":[-87.20496799999999,33.843914],"type":"Point"}
}