{
  "type": "Feature",
  "properties": {
    "iso:country":"US",
    "sg:address":"2053 Mitchell Young Rd",
    "sg:city":"Montgomery",
    "sg:phone":"+1 334 286 8300",
    "sg:postcode":"36108",
    "sg:province":"AL",
    "sg:tags":[
        "food",
        "equipment",
        "processing"
    ],
    "wof:name":"Feldmeier/Alabama Equipment",
    "wof:placetype":"venue"
},
  "geometry": {"coordinates":[-86.44295099999999,32.319817],"type":"Point"}
}