{
  "type": "Feature",
  "properties": {
    "iso:country":"US",
    "sg:address":"1274 E Main St",
    "sg:city":"Prattville",
    "sg:classifiers":[
        {
            "category":"Organizations",
            "subcategory":"Religious Organization",
            "type":"Services"
        }
    ],
    "sg:phone":"+1 334 365 3412",
    "sg:postcode":"36066",
    "sg:province":"AL",
    "wof:name":"Prattville Church",
    "wof:placetype":"venue"
},
  "geometry": {"coordinates":[-86.435369,32.460457],"type":"Point"}
}