{
  "type": "Feature",
  "properties": {
    "iso:country":"US",
    "sg:address":"119 40th St NW",
    "sg:city":"Fort Payne",
    "sg:classifiers":[
        {
            "category":"Building & Trades",
            "subcategory":"Equipment Rental",
            "type":"Services"
        }
    ],
    "sg:phone":"+1 256 845 7575",
    "sg:postcode":"35967",
    "sg:province":"AL",
    "sg:tags":[
        "steel",
        "prefabricated",
        "panel",
        "bridges"
    ],
    "sg:website":"www.baileybridge.com",
    "wof:name":"Bailey Bridges Inc",
    "wof:placetype":"venue"
},
  "geometry": {"coordinates":[-85.686829,34.483272],"type":"Point"}
}