{
  "type": "Feature",
  "properties": {
    "addr:full":"3215 Lodge Rd NW Huntsville AL 35810",
    "addr:housenumber":"3215",
    "addr:postcode":"35810",
    "addr:street":"Lodge Rd Nw",
    "iso:country":"US",
    "sg:address":"3215 Lodge Rd NW",
    "sg:city":"Huntsville",
    "sg:classifiers":[
        {
            "category":"Social Services",
            "subcategory":"Child Care",
            "type":"Services"
        }
    ],
    "sg:phone":"+1 256 851 9789",
    "sg:postcode":"35810",
    "sg:province":"AL",
    "sg:tags":[
        "day"
    ],
    "wof:name":"Busy Bee Christian Day Care",
    "wof:placetype":"venue"
},
  "geometry": {"coordinates":[-86.64569899999999,34.770454],"type":"Point"}
}