{
  "type": "Feature",
  "properties": {
    "addr:full":"1808 11th St SE Decatur AL 35601",
    "addr:housenumber":"1808",
    "addr:postcode":"35601",
    "addr:street":"11Th St Se",
    "iso:country":"US",
    "sg:address":"1808 11th St SE",
    "sg:city":"Decatur",
    "sg:classifiers":[
        {
            "category":"Shopping",
            "subcategory":"Clothing, Apparel, & Fashions",
            "type":"Retail Goods"
        }
    ],
    "sg:phone":"+1 256 432 3994",
    "sg:postcode":"35601",
    "sg:province":"AL",
    "sg:tags":[
        "t"
    ],
    "wof:name":"Green's T Shirt Outlet",
    "wof:placetype":"venue"
},
  "geometry": {"coordinates":[-86.966157,34.58415],"type":"Point"}
}