{
  "type": "Feature",
  "properties": {
    "addr:full":"13436 Co Rd 3 Fairhope AL 36532",
    "addr:housenumber":"13436",
    "addr:postcode":"36532",
    "addr:street":"Co Rd 3",
    "iso:country":"US",
    "sg:address":"13436 Co Rd 3",
    "sg:city":"Fairhope",
    "sg:classifiers":[
        {
            "category":"Health Services",
            "subcategory":"Hospital",
            "type":"Services"
        }
    ],
    "sg:phone":"+1 251 990 6780",
    "sg:postcode":"36532",
    "sg:province":"AL",
    "sg:tags":[
        "mental"
    ],
    "wof:name":"Fairhope Mental Health Svc",
    "wof:placetype":"venue"
},
  "geometry": {"coordinates":[-87.89884000000001,30.444721],"type":"Point"}
}