{
  "type": "Feature",
  "properties": {
    "iso:country":"US",
    "sg:address":"1030 S Brundidge St",
    "sg:city":"Troy",
    "sg:classifiers":[
        {
            "category":"Insurance",
            "subcategory":"Insurance Agent",
            "type":"Services"
        }
    ],
    "sg:phone":"+1 334 566 2484",
    "sg:postcode":"36081",
    "sg:province":"AL",
    "wof:name":"Troy Flowers Insurance LLC",
    "wof:placetype":"venue"
},
  "geometry": {"coordinates":[-85.966127,31.795008],"type":"Point"}
}