{
  "type": "Feature",
  "properties": {
    "iso:country":"US",
    "sg:address":"2120 Marchfield Dr E",
    "sg:city":"Mobile",
    "sg:classifiers":[
        {
            "category":"Professional",
            "type":"Services"
        }
    ],
    "sg:phone":"+1 251 602 0136",
    "sg:postcode":"36693",
    "sg:province":"AL",
    "sg:tags":[
        "establishment"
    ],
    "wof:name":"Sweet Inspirations",
    "wof:placetype":"venue"
},
  "geometry": {"coordinates":[-88.145886,30.645531],"type":"Point"}
}