{
  "type": "Feature",
  "properties": {
    "addr:full":"721 Lakeside Dr Mobile AL 36693",
    "addr:housenumber":"721",
    "addr:postcode":"36693",
    "addr:street":"Lakeside Dr",
    "iso:country":"US",
    "sg:address":"721 Lakeside Dr",
    "sg:city":"Mobile",
    "sg:classifiers":[
        {
            "category":"Building & Trades",
            "subcategory":"Plumbing",
            "type":"Services"
        }
    ],
    "sg:phone":"+1 251 661 6082",
    "sg:postcode":"36693",
    "sg:province":"AL",
    "sg:tags":[
        "product",
        "management",
        "energy",
        "system"
    ],
    "wof:name":"GE Energy Svc Refurbished Prts",
    "wof:placetype":"venue"
},
  "geometry": {"coordinates":[-88.12881899999999,30.658002],"type":"Point"}
}