{
  "type": "Feature",
  "properties": {
    "iso:country":"US",
    "sg:address":"7326 Whitney Dr",
    "sg:city":"Pinson",
    "sg:classifiers":[
        {
            "category":"Wholesale",
            "subcategory":"Vending Machines",
            "type":"Manufacturing & Wholesale Goods"
        }
    ],
    "sg:phone":"+1 205 680 9327",
    "sg:postcode":"35126",
    "sg:province":"AL",
    "sg:tags":[
        "operator"
    ],
    "wof:name":"Vending Ventures",
    "wof:placetype":"venue"
},
  "geometry": {"coordinates":[-86.582962,33.711345],"type":"Point"}
}