{
  "type": "Feature",
  "properties": {
    "iso:country":"US",
    "sg:address":"6157 Airport Blvd",
    "sg:city":"Mobile",
    "sg:classifiers":[
        {
            "category":"Insurance",
            "subcategory":"Insurance Agent",
            "type":"Services"
        }
    ],
    "sg:phone":"+1 251 344 4015",
    "sg:postcode":"36608",
    "sg:province":"AL",
    "wof:name":"Farmers Insurance Group",
    "wof:placetype":"venue"
},
  "geometry": {"coordinates":[-88.184197,30.675897],"type":"Point"}
}