{
  "type": "Feature",
  "properties": {
    "iso:country":"US",
    "sg:address":"207 Orion St",
    "sg:city":"Troy",
    "sg:classifiers":[
        {
            "category":"Retail",
            "subcategory":"Car Wash",
            "type":"Services"
        }
    ],
    "sg:phone":"+1 334 808 8348",
    "sg:postcode":"36081",
    "sg:province":"AL",
    "sg:tags":[
        "carwash"
    ],
    "wof:name":"Ultimate Carwash",
    "wof:placetype":"venue"
},
  "geometry": {"coordinates":[-85.97183,31.818534],"type":"Point"}
}