{
  "type": "Feature",
  "properties": {
    "iso:country":"US",
    "sg:address":"324 Pineville Rd",
    "sg:city":"Monroeville",
    "sg:classifiers":[
        {
            "category":"Organizations",
            "subcategory":"Religious Organization",
            "type":"Services"
        }
    ],
    "sg:phone":"+1 251 575 2790",
    "sg:postcode":"36460",
    "sg:province":"AL",
    "sg:tags":[
        "methodist",
        "church"
    ],
    "wof:name":"Monroville Untd Methdst Church",
    "wof:placetype":"venue"
},
  "geometry": {"coordinates":[-87.320807,31.529157],"type":"Point"}
}