{
  "type": "Feature",
  "properties": {
    "addr:full":"113 John D Seifert Dr Ozark AL 36360",
    "addr:housenumber":"113",
    "addr:postcode":"36360",
    "addr:street":"John;Seifert Dr",
    "iso:country":"US",
    "sg:address":"113 John D Seifert Dr",
    "sg:city":"Ozark",
    "sg:classifiers":[
        {
            "category":"Retail",
            "subcategory":"Repair Shop",
            "type":"Services"
        }
    ],
    "sg:phone":"+1 334 774 5685",
    "sg:postcode":"36360",
    "sg:province":"AL",
    "sg:tags":[
        "repairing",
        "lawn",
        "mower"
    ],
    "wof:name":"East Gate Lawn Mower",
    "wof:placetype":"venue"
},
  "geometry": {"coordinates":[-85.678675,31.399551],"type":"Point"}
}