{
  "type": "Feature",
  "properties": {
    "addr:full":"302 Anniston St Weaver AL 36277",
    "addr:housenumber":"302",
    "addr:postcode":"36277",
    "addr:street":"Anniston St",
    "iso:country":"US",
    "sg:address":"302 Anniston St",
    "sg:city":"Weaver",
    "sg:classifiers":[
        {
            "category":"Manufacturing",
            "subcategory":"Tools & Machinery",
            "type":"Manufacturing & Wholesale Goods"
        }
    ],
    "sg:phone":"+1 256 820 1818",
    "sg:postcode":"36277",
    "sg:province":"AL",
    "sg:tags":[
        "die",
        "maker"
    ],
    "wof:name":"Russell Machine Co",
    "wof:placetype":"venue"
},
  "geometry": {"coordinates":[-85.813693,33.746259],"type":"Point"}
}