{
  "type": "Feature",
  "properties": {
    "iso:country":"US",
    "sg:address":"4372 US Hwy 231",
    "sg:city":"Union Grove",
    "sg:classifiers":[
        {
            "category":"Autos & Motor Vehicles",
            "subcategory":"Fuel & Gas Station",
            "type":"Retail Goods"
        }
    ],
    "sg:phone":"+1 256 498 2809",
    "sg:postcode":"35175",
    "sg:province":"AL",
    "sg:tags":[
        "oil"
    ],
    "wof:name":"Raceway Service Station",
    "wof:placetype":"venue"
},
  "geometry": {"coordinates":[-86.56669599999999,34.469444],"type":"Point"}
}