{
  "type": "Feature",
  "properties": {
    "iso:country":"US",
    "sg:address":"2403 Zinnia Dr",
    "sg:city":"Bessemer",
    "sg:classifiers":[
        {
            "category":"Building & Trades",
            "subcategory":"Construction",
            "type":"Services"
        }
    ],
    "sg:phone":"+1 205 491 6635",
    "sg:postcode":"35023",
    "sg:province":"AL",
    "sg:tags":[
        "contractor"
    ],
    "wof:name":"Roofing Guru",
    "wof:placetype":"venue"
},
  "geometry": {"coordinates":[-86.974193,33.426778],"type":"Point"}
}