{
  "type": "Feature",
  "properties": {
    "addr:full":"2726 Hwy 77 Attalla AL 35954",
    "addr:housenumber":"2726",
    "addr:postcode":"35954",
    "addr:street":"Hwy 77 Attalla",
    "iso:country":"US",
    "sg:address":"2726 Hwy 77",
    "sg:city":"Attalla",
    "sg:classifiers":[
        {
            "category":"Autos & Motor Vehicles",
            "subcategory":"Fuel & Gas Station",
            "type":"Retail Goods"
        }
    ],
    "sg:phone":"+1 256 538 7221",
    "sg:postcode":"35954",
    "sg:province":"AL",
    "sg:tags":[
        "station",
        "gasoline"
    ],
    "wof:name":"Ivalee Chevron",
    "wof:placetype":"venue"
},
  "geometry": {"coordinates":[-86.11969000000001,34.036237],"type":"Point"}
}