{
  "type": "Feature",
  "properties": {
    "iso:country":"US",
    "sg:address":"244 Century Park S",
    "sg:city":"Birmingham",
    "sg:classifiers":[
        {
            "category":"Shopping",
            "subcategory":"Shoes",
            "type":"Retail Goods"
        }
    ],
    "sg:phone":"+1 205 595 0970",
    "sg:postcode":"35226",
    "sg:province":"AL",
    "sg:tags":[
        "shoe",
        "store"
    ],
    "wof:name":"Famous Footwear",
    "wof:placetype":"venue"
},
  "geometry": {"coordinates":[-86.80953700000001,33.414882],"type":"Point"}
}