{
  "type": "Feature",
  "properties": {
    "iso:country":"US",
    "sg:address":"201 Office Park Dr",
    "sg:city":"Birmingham",
    "sg:classifiers":[
        {
            "category":"Place Of Worship",
            "type":"Public Place"
        },
        {
            "category":"Organizations",
            "subcategory":"Religious Organization",
            "type":"Services"
        }
    ],
    "sg:phone":"+1 205 871 1914",
    "sg:postcode":"35223",
    "sg:province":"AL",
    "sg:tags":[
        "church"
    ],
    "wof:name":"Advent Park",
    "wof:placetype":"venue"
},
  "geometry": {"coordinates":[-86.77522999999999,33.477669],"type":"Point"}
}