{
  "type": "Feature",
  "properties": {
    "iso:country":"US",
    "sg:address":"1411 Gurnee Ave",
    "sg:city":"Anniston",
    "sg:classifiers":[
        {
            "category":"Social Services",
            "type":"Services"
        }
    ],
    "sg:phone":"+1 256 237 6144",
    "sg:postcode":"36201",
    "sg:province":"AL",
    "sg:tags":[
        "organization",
        "individual",
        "family",
        "welfare"
    ],
    "wof:name":"Community Enabler Developers",
    "wof:placetype":"venue"
},
  "geometry": {"coordinates":[-85.831487,33.66336],"type":"Point"}
}