{
  "type": "Feature",
  "properties": {
    "iso:country":"US",
    "sg:address":"146 Stone Meadow Ln",
    "sg:city":"Madison",
    "sg:classifiers":[
        {
            "category":"Shopping",
            "type":"Retail Goods"
        }
    ],
    "sg:phone":"+1 256 772 1837",
    "sg:postcode":"35758",
    "sg:province":"AL",
    "sg:tags":[
        "merchandise"
    ],
    "wof:name":"Jessica Cummings",
    "wof:placetype":"venue"
},
  "geometry": {"coordinates":[-86.739206,34.711017],"type":"Point"}
}