{
  "type": "Feature",
  "properties": {
    "addr:full":"460 Jimshill Rd Wetumpka AL 36093",
    "addr:housenumber":"460",
    "addr:postcode":"36093",
    "addr:street":"Jimshill Rd",
    "iso:country":"US",
    "sg:address":"460 Jimshill Rd",
    "sg:city":"Wetumpka",
    "sg:classifiers":[
        {
            "category":"Professional",
            "subcategory":"Management & Consulting",
            "type":"Services"
        }
    ],
    "sg:phone":"+1 334 514 1688",
    "sg:postcode":"36093",
    "sg:province":"AL",
    "sg:tags":[
        "business"
    ],
    "wof:name":"Dynamic Contract & Consultant",
    "wof:placetype":"venue"
},
  "geometry": {"coordinates":[-86.16588400000001,32.529935],"type":"Point"}
}