{
  "type": "Feature",
  "properties": {
    "addr:full":"717 Lakeside Dr Mobile AL 36693",
    "addr:housenumber":"717",
    "addr:postcode":"36693",
    "addr:street":"Lakeside Dr",
    "iso:country":"US",
    "sg:address":"717 Lakeside Dr",
    "sg:city":"Mobile",
    "sg:classifiers":[
        {
            "category":"Autos & Motor Vehicles",
            "subcategory":"Automobile Sales",
            "type":"Retail Goods"
        }
    ],
    "sg:phone":"+1 251 661 1905",
    "sg:postcode":"36693",
    "sg:province":"AL",
    "sg:tags":[
        "car",
        "dealer"
    ],
    "wof:name":"D & S Automotive",
    "wof:placetype":"venue"
},
  "geometry": {"coordinates":[-88.129514,30.658245],"type":"Point"}
}