{
  "type": "Feature",
  "properties": {
    "iso:country":"US",
    "sg:address":"1151 Temple Cir",
    "sg:city":"Alexander City",
    "sg:classifiers":[
        {
            "category":"Professional",
            "subcategory":"Business Services",
            "type":"Services"
        }
    ],
    "sg:phone":"+1 256 329 3348",
    "sg:postcode":"35010",
    "sg:province":"AL",
    "wof:name":"Appraisal & Inspection Service",
    "wof:placetype":"venue"
},
  "geometry": {"coordinates":[-85.96433,32.923689],"type":"Point"}
}