{
  "type": "Feature",
  "properties": {
    "iso:country":"US",
    "sg:address":"307 McKenzie St",
    "sg:city":"Foley",
    "sg:classifiers":[
        {
            "category":"Health Services",
            "subcategory":"Hospital",
            "type":"Services"
        }
    ],
    "sg:phone":"+1 251 955 1232",
    "sg:postcode":"36535",
    "sg:province":"AL",
    "sg:tags":[
        "mental"
    ],
    "wof:name":"Coastal Counseling Assoc",
    "wof:placetype":"venue"
},
  "geometry": {"coordinates":[-87.683755,30.404806],"type":"Point"}
}