{
  "type": "Feature",
  "properties": {
    "iso:country":"US",
    "sg:address":"2304 Longleaf Way",
    "sg:city":"Birmingham",
    "sg:classifiers":[
        {
            "category":"Health Services",
            "subcategory":"Doctor",
            "type":"Services"
        }
    ],
    "sg:phone":"+1 205 823 7693",
    "sg:postcode":"35243",
    "sg:province":"AL",
    "sg:tags":[
        "medical"
    ],
    "wof:name":"Mylan S Tucker Dr",
    "wof:placetype":"venue"
},
  "geometry": {"coordinates":[-86.75832800000001,33.418828],"type":"Point"}
}