{
  "type": "Feature",
  "properties": {
    "addr:full":"3652 Spring Valley Rd Birmingham AL 35223",
    "addr:housenumber":"3652",
    "addr:postcode":"35223",
    "addr:street":"Spring Valley Rd",
    "iso:country":"US",
    "sg:address":"3652 Spring Valley Rd",
    "sg:city":"Birmingham",
    "sg:classifiers":[
        {
            "category":"Manufacturing",
            "subcategory":"Aerospace",
            "type":"Manufacturing & Wholesale Goods"
        }
    ],
    "sg:phone":"+1 205 967 1623",
    "sg:postcode":"35223",
    "sg:province":"AL",
    "sg:tags":[
        "aircraft",
        "mfg"
    ],
    "wof:name":"Dewberry Real Estate",
    "wof:placetype":"venue"
},
  "geometry": {"coordinates":[-86.71301200000001,33.499215],"type":"Point"}
}