{
  "type": "Feature",
  "properties": {
    "addr:full":"406 White Ave Fairhope AL 36532",
    "addr:housenumber":"406",
    "addr:postcode":"36532",
    "addr:street":"White Ave",
    "iso:country":"US",
    "sg:address":"406 White Ave",
    "sg:city":"Fairhope",
    "sg:classifiers":[
        {
            "category":"Building & Trades",
            "subcategory":"Construction",
            "type":"Services"
        }
    ],
    "sg:phone":"+1 251 928 1261",
    "sg:postcode":"36532",
    "sg:province":"AL",
    "sg:tags":[
        "hanging",
        "contractor"
    ],
    "wof:name":"Dp McFarland Painting",
    "wof:placetype":"venue"
},
  "geometry": {"coordinates":[-87.90300000000001,30.51719],"type":"Point"}
}