{
  "type": "Feature",
  "properties": {
    "iso:country":"US",
    "sg:address":"2522 Commerce Sq W",
    "sg:city":"Irondale",
    "sg:classifiers":[
        {
            "category":"Building & Trades",
            "subcategory":"Construction",
            "type":"Services"
        }
    ],
    "sg:phone":"+1 205 951 0840",
    "sg:postcode":"35210",
    "sg:province":"AL",
    "sg:tags":[
        "remodeling",
        "closet"
    ],
    "wof:name":"Closet Factory",
    "wof:placetype":"venue"
},
  "geometry": {"coordinates":[-86.69998,33.541445],"type":"Point"}
}