{
  "type": "Feature",
  "properties": {
    "iso:country":"US",
    "sg:address":"701 W Grand Ave",
    "sg:city":"Rainbow City",
    "sg:classifiers":[
        {
            "category":"Wholesale",
            "subcategory":"Motor Vehicles",
            "type":"Manufacturing & Wholesale Goods"
        }
    ],
    "sg:phone":"+1 256 442 1998",
    "sg:postcode":"35906",
    "sg:province":"AL",
    "sg:tags":[
        "car"
    ],
    "wof:name":"Wholesale Used Cars",
    "wof:placetype":"venue"
},
  "geometry": {"coordinates":[-86.05395300000001,33.972345],"type":"Point"}
}