{
  "type": "Feature",
  "properties": {
    "addr:full":"1820 Hand Ave Mobile AL 36612",
    "addr:housenumber":"1820",
    "addr:postcode":"36612",
    "addr:street":"Hand Ave",
    "iso:country":"US",
    "sg:address":"1820 Hand Ave",
    "sg:city":"Mobile",
    "sg:classifiers":[
        {
            "category":"Wholesale",
            "subcategory":"Durable Goods & Equipment",
            "type":"Manufacturing & Wholesale Goods"
        }
    ],
    "sg:phone":"+1 251 456 6950",
    "sg:postcode":"36612",
    "sg:province":"AL",
    "wof:name":"Mobile Forest Products Inc",
    "wof:placetype":"venue"
},
  "geometry": {"coordinates":[-88.11418399999999,30.746584],"type":"Point"}
}