{
  "type": "Feature",
  "properties": {
    "iso:country":"US",
    "sg:address":"859 Cox Creek Pkwy",
    "sg:city":"Florence",
    "sg:classifiers":[
        {
            "category":"Restaurant",
            "type":"Food & Drink"
        }
    ],
    "sg:menulink":"http://www.allmenus.com/al/florence/72819-pizza-hut/menu/",
    "sg:phone":"+1 256 767 5300",
    "sg:postcode":"35630",
    "sg:province":"AL",
    "sg:tags":[
        "american",
        "pizza"
    ],
    "wof:name":"Pizza Hut",
    "wof:placetype":"venue"
},
  "geometry": {"coordinates":[-87.670883,34.842838],"type":"Point"}
}