{
  "type": "Feature",
  "properties": {
    "iso:country":"US",
    "sg:address":"2255 US Hwy 278",
    "sg:city":"Cullman",
    "sg:classifiers":[
        {
            "category":"Retail",
            "subcategory":"Auto Repair",
            "type":"Services"
        }
    ],
    "sg:phone":"+1 256 734 7388",
    "sg:postcode":"35057",
    "sg:province":"AL",
    "sg:tags":[
        "body"
    ],
    "wof:name":"K & K Auto Body",
    "wof:placetype":"venue"
},
  "geometry": {"coordinates":[-86.912803,34.183595],"type":"Point"}
}