{
  "type": "Feature",
  "properties": {
    "iso:country":"US",
    "sg:address":"1423 Gadsden Hwy",
    "sg:city":"Birmingham",
    "sg:classifiers":[
        {
            "category":"Shopping",
            "subcategory":"Shoes",
            "type":"Retail Goods"
        }
    ],
    "sg:phone":"+1 205 655 9288",
    "sg:postcode":"35235",
    "sg:province":"AL",
    "sg:tags":[
        "store"
    ],
    "wof:name":"Red Wing Shoes",
    "wof:placetype":"venue"
},
  "geometry": {"coordinates":[-86.64659899999999,33.5952],"type":"Point"}
}