{
  "type": "Feature",
  "properties": {
    "addr:full":"140 Jack Cole Rd Hayden AL 35079",
    "addr:housenumber":"140",
    "addr:postcode":"35079",
    "addr:street":"Jack Cole Rd",
    "iso:country":"US",
    "sg:address":"140 Jack Cole Rd",
    "sg:city":"Hayden",
    "sg:classifiers":[
        {
            "category":"Building & Trades",
            "subcategory":"Construction",
            "type":"Services"
        }
    ],
    "sg:phone":"+1 205 647 5536",
    "sg:postcode":"35079",
    "sg:province":"AL",
    "sg:tags":[
        "general",
        "contractor"
    ],
    "wof:name":"True Set Construction",
    "wof:placetype":"venue"
},
  "geometry": {"coordinates":[-86.78959399999999,33.926713],"type":"Point"}
}