{
  "type": "Feature",
  "properties": {
    "addr:full":"2542 Co Rd 6 Florence AL 35633",
    "addr:housenumber":"2542;6",
    "addr:postcode":"35633",
    "addr:street":"Co Rd",
    "iso:country":"US",
    "sg:address":"2542 Co Rd 6",
    "sg:city":"Florence",
    "sg:classifiers":[
        {
            "category":"Organizations",
            "subcategory":"Religious Organization",
            "type":"Services"
        }
    ],
    "sg:phone":"+1 256 766 1631",
    "sg:postcode":"35633",
    "sg:province":"AL",
    "sg:tags":[
        "church"
    ],
    "wof:name":"Good Hope Missionary Baptist",
    "wof:placetype":"venue"
},
  "geometry": {"coordinates":[-87.84130500000001,34.887675],"type":"Point"}
}