{
  "type": "Feature",
  "properties": {
    "iso:country":"US",
    "sg:address":"1185 Kershaw St",
    "sg:city":"Montgomery",
    "sg:classifiers":[
        {
            "category":"Wholesale",
            "subcategory":"Machinery & Supplies",
            "type":"Manufacturing & Wholesale Goods"
        }
    ],
    "sg:phone":"+1 334 834 3705",
    "sg:postcode":"36108",
    "sg:province":"AL",
    "sg:tags":[
        "repair"
    ],
    "wof:name":"Tieco Inc",
    "wof:placetype":"venue"
},
  "geometry": {"coordinates":[-86.354775,32.353899],"type":"Point"}
}