{
  "type": "Feature",
  "properties": {
    "iso:country":"US",
    "sg:address":"1223 Co Rd 315",
    "sg:city":"Bryant",
    "sg:classifiers":[
        {
            "category":"Manufacturing",
            "subcategory":"Printing",
            "type":"Manufacturing & Wholesale Goods"
        }
    ],
    "sg:phone":"+1 256 597 3546",
    "sg:postcode":"35958",
    "sg:province":"AL",
    "sg:tags":[
        "publisher"
    ],
    "wof:name":"Family Heritage Books",
    "wof:placetype":"venue"
},
  "geometry": {"coordinates":[-85.590294,34.873973],"type":"Point"}
}