{
  "type": "Feature",
  "properties": {
    "iso:country":"US",
    "sg:address":"1158 Co Rd 35",
    "sg:city":"Hamilton",
    "sg:classifiers":[
        {
            "category":"Food & Beverages",
            "subcategory":"Groceries & Convenience Stores",
            "type":"Retail Goods"
        }
    ],
    "sg:phone":"+1 205 921 9219",
    "sg:postcode":"35570",
    "sg:province":"AL",
    "wof:name":"River Road Citgo",
    "wof:placetype":"venue"
},
  "geometry": {"coordinates":[-87.999368,34.093858],"type":"Point"}
}