{
  "type": "Feature",
  "properties": {
    "iso:country":"US",
    "sg:address":"202 Inverness Center Dr",
    "sg:city":"Birmingham",
    "sg:classifiers":[
        {
            "category":"Health Services",
            "subcategory":"Doctor",
            "type":"Services"
        }
    ],
    "sg:phone":"+1 205 981 3301",
    "sg:postcode":"35242",
    "sg:province":"AL",
    "wof:name":"Birmingham Endodontics",
    "wof:placetype":"venue"
},
  "geometry": {"coordinates":[-86.702216,33.420316],"type":"Point"}
}