{
  "type": "Feature",
  "properties": {
    "iso:country":"US",
    "sg:address":"929 S Noble St",
    "sg:city":"Anniston",
    "sg:classifiers":[
        {
            "category":"Wholesale",
            "subcategory":"Office Equipment",
            "type":"Manufacturing & Wholesale Goods"
        }
    ],
    "sg:phone":"+1 256 237 8797",
    "sg:postcode":"36201",
    "sg:province":"AL",
    "sg:tags":[
        "machine",
        "duplicating",
        "copying"
    ],
    "sg:website":"www.garing.com",
    "wof:name":"Garing Business Machines",
    "wof:placetype":"venue"
},
  "geometry": {"coordinates":[-85.828459,33.634387],"type":"Point"}
}