{
  "type": "Feature",
  "properties": {
    "addr:full":"1022 Edgewood Blvd Birmingham AL 35209",
    "addr:housenumber":"1022",
    "addr:postcode":"35209",
    "addr:street":"Edgewood Blvd",
    "iso:country":"US",
    "sg:address":"1022 Edgewood Blvd",
    "sg:city":"Birmingham",
    "sg:classifiers":[
        {
            "category":"Professional",
            "subcategory":"Business Services",
            "type":"Services"
        }
    ],
    "sg:phone":"+1 205 870 5101",
    "sg:postcode":"35209",
    "sg:province":"AL",
    "wof:name":"David W Chapman",
    "wof:placetype":"venue"
},
  "geometry": {"coordinates":[-86.808432,33.465515],"type":"Point"}
}