{
  "type": "Feature",
  "properties": {
    "iso:country":"US",
    "sg:address":"420 S Seale Rd",
    "sg:city":"Phenix City",
    "sg:classifiers":[
        {
            "category":"Real Estate",
            "subcategory":"Real Estate Agent",
            "type":"Services"
        }
    ],
    "sg:phone":"+1 334 448 9010",
    "sg:postcode":"36869",
    "sg:province":"AL",
    "wof:name":"Rodney Hamrick Realty",
    "wof:placetype":"venue"
},
  "geometry": {"coordinates":[-85.039419,32.417863],"type":"Point"}
}