{
  "type": "Feature",
  "properties": {
    "iso:country":"US",
    "sg:address":"1150 State Docks Rd",
    "sg:city":"Eufaula",
    "sg:classifiers":[
        {
            "category":"Manufacturing",
            "subcategory":"Metals",
            "type":"Manufacturing & Wholesale Goods"
        },
        {
            "category":"Manufacturing",
            "subcategory":"Building Materials",
            "type":"Manufacturing & Wholesale Goods"
        }
    ],
    "sg:phone":"+1 334 687 5223",
    "sg:postcode":"36027",
    "sg:province":"AL",
    "sg:tags":[
        "product"
    ],
    "sg:website":"www.americanbuildings.com",
    "wof:name":"American Buildings Co Intl",
    "wof:placetype":"venue"
},
  "geometry": {"coordinates":[-85.14926800000001,31.857294],"type":"Point"}
}