{
  "type": "Feature",
  "properties": {
    "iso:country":"US",
    "sg:address":"8010 Airport Blvd",
    "sg:city":"Mobile",
    "sg:classifiers":[
        {
            "category":"Insurance",
            "subcategory":"Insurance Agent",
            "type":"Services"
        }
    ],
    "sg:phone":"+1 251 633 0606",
    "sg:postcode":"36608",
    "sg:province":"AL",
    "wof:name":"State Farm Insurance",
    "wof:placetype":"venue"
},
  "geometry": {"coordinates":[-88.236341,30.679252],"type":"Point"}
}