{
  "type": "Feature",
  "properties": {
    "addr:full":"190 Antioch Rd Somerville AL 35670",
    "addr:housenumber":"190",
    "addr:postcode":"35670",
    "addr:street":"Antioch Rd",
    "iso:country":"US",
    "sg:address":"190 Antioch Rd",
    "sg:city":"Somerville",
    "sg:classifiers":[
        {
            "category":"Freight",
            "type":"Transportation"
        }
    ],
    "sg:phone":"+1 256 778 8841",
    "sg:postcode":"35670",
    "sg:province":"AL",
    "sg:tags":[
        "local"
    ],
    "wof:name":"Johnny Shivers Transportation",
    "wof:placetype":"venue"
},
  "geometry": {"coordinates":[-86.738598,34.451496],"type":"Point"}
}