{
  "type": "Feature",
  "properties": {
    "iso:country":"US",
    "sg:address":"1001 Malley St",
    "sg:city":"Tuscaloosa",
    "sg:classifiers":[
        {
            "category":"Retail",
            "subcategory":"Auto Repair",
            "type":"Services"
        }
    ],
    "sg:phone":"+1 205 349 2641",
    "sg:postcode":"35405",
    "sg:province":"AL",
    "sg:tags":[
        "shop",
        "automotive",
        "repairing",
        "automobile"
    ],
    "wof:name":"Automotive Specialist Svc",
    "wof:placetype":"venue"
},
  "geometry": {"coordinates":[-87.55149,33.12717],"type":"Point"}
}