{
  "type": "Feature",
  "properties": {
    "addr:full":"651 Bay Springs Rd Centre AL 35960",
    "addr:housenumber":"651",
    "addr:postcode":"35960",
    "addr:street":"Bay Springs Rd",
    "iso:country":"US",
    "sg:address":"651 Bay Springs Rd",
    "sg:city":"Centre",
    "sg:classifiers":[
        {
            "category":"Real Estate",
            "subcategory":"Real Estate Operator",
            "type":"Services"
        }
    ],
    "sg:phone":"+1 256 927 5012",
    "sg:postcode":"35960",
    "sg:province":"AL",
    "sg:tags":[
        "apartment"
    ],
    "wof:name":"Cambridge Apartments",
    "wof:placetype":"venue"
},
  "geometry": {"coordinates":[-85.68987199999999,34.162062],"type":"Point"}
}