{
  "type": "Feature",
  "properties": {
    "addr:full":"5511 US Hwy 280 Birmingham AL 35242",
    "addr:housenumber":"5511",
    "addr:postcode":"35242",
    "addr:street":"Us Hwy 280",
    "iso:country":"US",
    "sg:address":"5511 US Hwy 280",
    "sg:city":"Birmingham",
    "sg:classifiers":[
        {
            "category":"Health Services",
            "subcategory":"Podiatrist",
            "type":"Services"
        }
    ],
    "sg:phone":"+1 205 980 2005",
    "sg:postcode":"35242",
    "sg:province":"AL",
    "wof:name":"Cahaba Podiatry Inc",
    "wof:placetype":"venue"
},
  "geometry": {"coordinates":[-86.664286,33.406484],"type":"Point"}
}