{
  "type": "Feature",
  "properties": {
    "iso:country":"US",
    "sg:address":"1230 Club House Pl",
    "sg:city":"Bessemer",
    "sg:classifiers":[
        {
            "category":"Health Services",
            "subcategory":"Doctor",
            "type":"Services"
        }
    ],
    "sg:phone":"+1 205 426 2626",
    "sg:postcode":"35020",
    "sg:province":"AL",
    "sg:tags":[
        "medical"
    ],
    "wof:name":"Pregnancy Test Center",
    "wof:placetype":"venue"
},
  "geometry": {"coordinates":[-86.946857,33.389776],"type":"Point"}
}