{
  "type": "Feature",
  "properties": {
    "addr:full":"2104 W Point Pkwy Opelika AL 36801",
    "addr:housenumber":"2104",
    "addr:postcode":"36801",
    "addr:street":"W Point Pkwy Opelika",
    "iso:country":"US",
    "sg:address":"2104 W Point Pkwy",
    "sg:city":"Opelika",
    "sg:classifiers":[
        {
            "category":"Food & Beverages",
            "subcategory":"Groceries & Convenience Stores",
            "type":"Retail Goods"
        }
    ],
    "sg:phone":"+1 334 749 9179",
    "sg:postcode":"36801",
    "sg:province":"AL",
    "sg:tags":[
        "grocer"
    ],
    "wof:name":"Joe's Grocery",
    "wof:placetype":"venue"
},
  "geometry": {"coordinates":[-85.33692499999999,32.67179],"type":"Point"}
}