{
  "type": "Feature",
  "properties": {
    "iso:country":"US",
    "sg:address":"4200 Pinson Valley Pkwy",
    "sg:city":"Birmingham",
    "sg:classifiers":[
        {
            "category":"Building & Trades",
            "subcategory":"Equipment Rental",
            "type":"Services"
        }
    ],
    "sg:phone":"+1 205 854 2022",
    "sg:postcode":"35215",
    "sg:province":"AL",
    "sg:tags":[
        "party",
        "supply"
    ],
    "wof:name":"Fun Source Rentals",
    "wof:placetype":"venue"
},
  "geometry": {"coordinates":[-86.725285,33.641224],"type":"Point"}
}