{
  "type": "Feature",
  "properties": {
    "iso:country":"US",
    "sg:address":"2518 Fosters Ferry Rd",
    "sg:city":"Tuscaloosa",
    "sg:classifiers":[
        {
            "category":"Social Services",
            "subcategory":"Child Care",
            "type":"Services"
        }
    ],
    "sg:phone":"+1 205 758 6401",
    "sg:postcode":"35401",
    "sg:province":"AL",
    "sg:tags":[
        "day"
    ],
    "wof:name":"Washington Square Day Care Ctr",
    "wof:placetype":"venue"
},
  "geometry": {"coordinates":[-87.588156,33.190179],"type":"Point"}
}