{
  "type": "Feature",
  "properties": {
    "addr:full":"3002 Mc Gehee Rd Montgomery AL 36111",
    "addr:housenumber":"3002",
    "addr:postcode":"36111",
    "addr:street":"Mc Gehee Rd",
    "iso:country":"US",
    "sg:address":"3002 Mc Gehee Rd",
    "sg:city":"Montgomery",
    "sg:classifiers":[
        {
            "category":"Insurance",
            "subcategory":"Insurance Agent",
            "type":"Services"
        }
    ],
    "sg:phone":"+1 334 286 4901",
    "sg:postcode":"36111",
    "sg:province":"AL",
    "wof:name":"Alfa Insurance Corp",
    "wof:placetype":"venue"
},
  "geometry": {"coordinates":[-86.258765,32.337647],"type":"Point"}
}