{
  "type": "Feature",
  "properties": {
    "iso:country":"US",
    "sg:address":"18012 Circle Dr",
    "sg:city":"Athens",
    "sg:classifiers":[
        {
            "category":"Restaurant",
            "type":"Food & Drink"
        }
    ],
    "sg:phone":"+1 256 233 7558",
    "sg:postcode":"35613",
    "sg:province":"AL",
    "sg:tags":[
        "eating"
    ],
    "wof:name":"H & H Barbeque",
    "wof:placetype":"venue"
},
  "geometry": {"coordinates":[-86.908638,34.81604],"type":"Point"}
}