{
  "type": "Feature",
  "properties": {
    "iso:country":"US",
    "sg:address":"443 Pine Ave SW",
    "sg:city":"Decatur",
    "sg:classifiers":[
        {
            "category":"Personal",
            "subcategory":"Barber",
            "type":"Services"
        }
    ],
    "sg:phone":"+1 256 552 0957",
    "sg:postcode":"35601",
    "sg:province":"AL",
    "sg:tags":[
        "shop"
    ],
    "wof:name":"Masters Touch",
    "wof:placetype":"venue"
},
  "geometry": {"coordinates":[-87.015495,34.60355],"type":"Point"}
}