{
  "type": "Feature",
  "properties": {
    "iso:country":"US",
    "sg:address":"25299 Canal Rd",
    "sg:city":"Orange Beach",
    "sg:classifiers":[
        {
            "category":"Personal",
            "subcategory":"Beauty Salon",
            "type":"Services"
        }
    ],
    "sg:phone":"+1 251 981 1196",
    "sg:postcode":"36561",
    "sg:province":"AL",
    "sg:tags":[
        "shop",
        "spa",
        "day"
    ],
    "wof:name":"Studio 3",
    "wof:placetype":"venue"
},
  "geometry": {"coordinates":[-87.59212599999999,30.29043],"type":"Point"}
}