{
  "type": "Feature",
  "properties": {
    "addr:full":"2031 US Hwy 78 Anniston AL 36203",
    "addr:housenumber":"2031",
    "addr:postcode":"36203",
    "addr:street":"Us Hwy 78",
    "iso:country":"US",
    "sg:address":"2031 US Hwy 78",
    "sg:city":"Anniston",
    "sg:classifiers":[
        {
            "category":"Food & Beverages",
            "subcategory":"Groceries & Convenience Stores",
            "type":"Retail Goods"
        }
    ],
    "sg:phone":"+1 256 831 7508",
    "sg:postcode":"36203",
    "sg:province":"AL",
    "wof:name":"Skinners Super Stop",
    "wof:placetype":"venue"
},
  "geometry": {"coordinates":[-85.87977600000001,33.593209],"type":"Point"}
}