{
  "type": "Feature",
  "properties": {
    "iso:country":"US",
    "sg:address":"945 Chestnut St",
    "sg:city":"Gadsden",
    "sg:classifiers":[
        {
            "category":"Professional",
            "subcategory":"Lawyer & Legal Services",
            "type":"Services"
        }
    ],
    "sg:phone":"+1 256 547 9222",
    "sg:postcode":"35901",
    "sg:province":"AL",
    "sg:tags":[
        "attorney"
    ],
    "wof:name":"Tammy W Parris",
    "wof:placetype":"venue"
},
  "geometry": {"coordinates":[-86.01611800000001,34.014164],"type":"Point"}
}