{
  "type": "Feature",
  "properties": {
    "iso:country":"US",
    "sg:address":"12686 US Hwy 80",
    "sg:city":"Montgomery",
    "sg:classifiers":[
        {
            "category":"Retail",
            "subcategory":"Auto Repair",
            "type":"Services"
        }
    ],
    "sg:phone":"+1 334 215 0245",
    "sg:postcode":"36117",
    "sg:province":"AL",
    "sg:tags":[
        "automotive",
        "general"
    ],
    "wof:name":"Waugh Auto Repair",
    "wof:placetype":"venue"
},
  "geometry": {"coordinates":[-86.103686,32.362356],"type":"Point"}
}