{
  "type": "Feature",
  "properties": {
    "iso:country":"US",
    "sg:address":"2702 Churchill Dr SE",
    "sg:city":"Huntsville",
    "sg:classifiers":[
        {
            "category":"Health Services",
            "subcategory":"Health Practitioner",
            "type":"Services"
        }
    ],
    "sg:phone":"+1 256 883 9889",
    "sg:postcode":"35801",
    "sg:province":"AL",
    "sg:tags":[
        "psychologist",
        "clinical"
    ],
    "wof:name":"Rogers Jon G PHD",
    "wof:placetype":"venue"
},
  "geometry": {"coordinates":[-86.563081,34.710826],"type":"Point"}
}