{
  "type": "Feature",
  "properties": {
    "addr:full":"2886 US Hwy 431 Boaz AL 35957",
    "addr:housenumber":"2886",
    "addr:postcode":"35957",
    "addr:street":"Us Hwy 431",
    "iso:country":"US",
    "sg:address":"2886 US Hwy 431",
    "sg:city":"Boaz",
    "sg:classifiers":[
        {
            "category":"Autos & Motor Vehicles",
            "subcategory":"Automobile Sales",
            "type":"Retail Goods"
        }
    ],
    "sg:phone":"+1 256 593 2433",
    "sg:postcode":"35957",
    "sg:province":"AL",
    "sg:tags":[
        "car",
        "used",
        "dealer"
    ],
    "wof:name":"Painter Billy & Sons Motors",
    "wof:placetype":"venue"
},
  "geometry": {"coordinates":[-86.16100400000001,34.226002],"type":"Point"}
}