{
  "type": "Feature",
  "properties": {
    "iso:country":"US",
    "sg:address":"30985 State Rte 25",
    "sg:city":"Wilsonville",
    "sg:classifiers":[
        {
            "category":"Manufacturing",
            "subcategory":"Building Materials",
            "type":"Manufacturing & Wholesale Goods"
        }
    ],
    "sg:phone":"+1 205 669 4211",
    "sg:postcode":"35186",
    "sg:province":"AL",
    "sg:tags":[
        "molding"
    ],
    "wof:name":"Specialty Wood Products Inc",
    "wof:placetype":"venue"
},
  "geometry": {"coordinates":[-86.479718,33.239527],"type":"Point"}
}