{
  "type": "Feature",
  "properties": {
    "iso:country":"US",
    "sg:address":"4831 Cove Creek Dr",
    "sg:city":"Brownsboro",
    "sg:classifiers":[
        {
            "category":"Real Estate",
            "subcategory":"Real Estate Agent",
            "type":"Services"
        }
    ],
    "sg:phone":"+1 256 534 3119",
    "sg:postcode":"35741",
    "sg:province":"AL",
    "wof:name":"Seeley Properties",
    "wof:placetype":"venue"
},
  "geometry": {"coordinates":[-86.508174,34.69642],"type":"Point"}
}