{
  "type": "Feature",
  "properties": {
    "iso:country":"US",
    "sg:address":"701 Douglas Dr",
    "sg:city":"Abbeville",
    "sg:classifiers":[
        {
            "category":"Professional",
            "subcategory":"Business Services",
            "type":"Services"
        }
    ],
    "sg:phone":"+1 334 585 3656",
    "sg:postcode":"36310",
    "sg:province":"AL",
    "sg:tags":[
        "consultant",
        "coach"
    ],
    "wof:name":"Mary Kay Cosmetics Consultant",
    "wof:placetype":"venue"
},
  "geometry": {"coordinates":[-85.10845999999999,31.652533],"type":"Point"}
}