{
  "type": "Feature",
  "properties": {
    "iso:country":"US",
    "sg:address":"265 Lyon Ln",
    "sg:city":"Birmingham",
    "sg:classifiers":[
        {
            "category":"Shopping",
            "subcategory":"Clothing, Apparel, & Fashions",
            "type":"Retail Goods"
        }
    ],
    "sg:phone":"+1 205 942 7055",
    "sg:postcode":"35211",
    "sg:province":"AL",
    "sg:tags":[
        "sportswear"
    ],
    "sg:website":"www.femaleplanet.com",
    "wof:name":"Level 10 Sportswear",
    "wof:placetype":"venue"
},
  "geometry": {"coordinates":[-86.85245,33.442495],"type":"Point"}
}