{
  "type": "Feature",
  "properties": {
    "addr:full":"246 Yellow Creek Rd Gallion AL 36742",
    "addr:housenumber":"246",
    "addr:postcode":"36742",
    "addr:street":"Yellow Creek Rd",
    "iso:country":"US",
    "sg:address":"246 Yellow Creek Rd",
    "sg:city":"Gallion",
    "sg:classifiers":[
        {
            "category":"Building & Trades",
            "subcategory":"Construction",
            "type":"Services"
        }
    ],
    "sg:phone":"+1 334 287 0468",
    "sg:postcode":"36742",
    "sg:province":"AL",
    "sg:tags":[
        "general",
        "contractor"
    ],
    "wof:name":"Strable Construction Inc",
    "wof:placetype":"venue"
},
  "geometry": {"coordinates":[-87.778667,32.541767],"type":"Point"}
}