{
  "type": "Feature",
  "properties": {
    "addr:full":"624 Skyland Blvd E Tuscaloosa AL 35405",
    "addr:housenumber":"624",
    "addr:postcode":"35405",
    "addr:street":"Skyland Blvd E",
    "iso:country":"US",
    "sg:address":"624 Skyland Blvd E",
    "sg:city":"Tuscaloosa",
    "sg:classifiers":[
        {
            "category":"Real Estate",
            "subcategory":"Developer",
            "type":"Services"
        }
    ],
    "sg:phone":"+1 205 345 3800",
    "sg:postcode":"35405",
    "sg:province":"AL",
    "sg:website":"www.ada504.com",
    "wof:name":"E & A Development Inc",
    "wof:placetype":"venue"
},
  "geometry": {"coordinates":[-87.52825799999999,33.167903],"type":"Point"}
}