{
  "type": "Feature",
  "properties": {
    "iso:country":"US",
    "sg:address":"5030 Old Montgomery Hwy",
    "sg:city":"Tuscaloosa",
    "sg:classifiers":[
        {
            "category":"Autos & Motor Vehicles",
            "subcategory":"Auto Supplies",
            "type":"Retail Goods"
        }
    ],
    "sg:phone":"+1 205 758 8361",
    "sg:postcode":"35405",
    "sg:province":"AL",
    "sg:tags":[
        "tire"
    ],
    "wof:name":"Tire Centers Inc",
    "wof:placetype":"venue"
},
  "geometry": {"coordinates":[-87.543592,33.162466],"type":"Point"}
}