{
  "type": "Feature",
  "properties": {
    "iso:country":"US",
    "sg:address":"1064 Eastdale Mall",
    "sg:city":"Montgomery",
    "sg:classifiers":[
        {
            "category":"Shopping",
            "subcategory":"Beauty & Cosmetics",
            "type":"Retail Goods"
        }
    ],
    "sg:phone":"+1 334 277 4233",
    "sg:postcode":"36117",
    "sg:province":"AL",
    "sg:tags":[
        "merchandise"
    ],
    "wof:name":"Merle Norman Cosmetics",
    "wof:placetype":"venue"
},
  "geometry": {"coordinates":[-86.20466500000001,32.385079],"type":"Point"}
}