{
  "type": "Feature",
  "properties": {
    "addr:full":"6042 Selma Hwy Montgomery AL 36108",
    "addr:housenumber":"6042",
    "addr:postcode":"36108",
    "addr:street":"Selma Hwy",
    "iso:country":"US",
    "sg:address":"6042 Selma Hwy",
    "sg:city":"Montgomery",
    "sg:classifiers":[
        {
            "category":"Retail",
            "subcategory":"Auto Repair",
            "type":"Services"
        }
    ],
    "sg:phone":"+1 334 288 1207",
    "sg:postcode":"36108",
    "sg:province":"AL",
    "sg:tags":[
        "general"
    ],
    "wof:name":"Gothard Brothers Automotive",
    "wof:placetype":"venue"
},
  "geometry": {"coordinates":[-86.40589,32.305744],"type":"Point"}
}