{
  "type": "Feature",
  "properties": {
    "iso:country":"US",
    "sg:address":"906 S Perry St",
    "sg:city":"Montgomery",
    "sg:classifiers":[
        {
            "category":"Professional",
            "subcategory":"Business Services",
            "type":"Services"
        }
    ],
    "sg:phone":"+1 334 262 5784",
    "sg:postcode":"36104",
    "sg:province":"AL",
    "sg:tags":[
        "fund",
        "promotion",
        "raising"
    ],
    "wof:name":"W & W Promotions",
    "wof:placetype":"venue"
},
  "geometry": {"coordinates":[-86.307022,32.363546],"type":"Point"}
}