{
  "type": "Feature",
  "properties": {
    "iso:country":"US",
    "sg:address":"312 S 3rd St",
    "sg:city":"Gadsden",
    "sg:classifiers":[
        {
            "category":"Government",
            "subcategory":"Office",
            "type":"Public Place"
        }
    ],
    "sg:phone":"+1 256 549 5396",
    "sg:postcode":"35901",
    "sg:province":"AL",
    "sg:tags":[
        "county"
    ],
    "wof:name":"Etowah Cnty Soil Conservation",
    "wof:placetype":"venue"
},
  "geometry": {"coordinates":[-86.004271,34.008634],"type":"Point"}
}