{
  "type": "Feature",
  "properties": {
    "iso:country":"US",
    "sg:address":"9545 State Rte 79",
    "sg:city":"Scottsboro",
    "sg:classifiers":[
        {
            "category":"Education",
            "subcategory":"School",
            "type":"Public Place"
        }
    ],
    "sg:phone":"+1 256 259 5398",
    "sg:postcode":"35768",
    "sg:province":"AL",
    "wof:name":"Living Word Christian Academy",
    "wof:placetype":"venue"
},
  "geometry": {"coordinates":[-86.100461,34.624877],"type":"Point"}
}