{
  "type": "Feature",
  "properties": {
    "iso:country":"US",
    "sg:address":"3087 Carter Hill Rd",
    "sg:city":"Montgomery",
    "sg:classifiers":[
        {
            "category":"Building & Trades",
            "subcategory":"Pest Control",
            "type":"Services"
        }
    ],
    "sg:phone":"+1 334 241 0001",
    "sg:postcode":"36111",
    "sg:province":"AL",
    "wof:name":"Flowers Pest Control",
    "wof:placetype":"venue"
},
  "geometry": {"coordinates":[-86.263517,32.352156],"type":"Point"}
}