{
  "type": "Feature",
  "properties": {
    "addr:full":"620 E Barbour St Eufaula AL 36027",
    "addr:housenumber":"620",
    "addr:postcode":"36027",
    "addr:street":"E Barbour St",
    "iso:country":"US",
    "sg:address":"620 E Barbour St",
    "sg:city":"Eufaula",
    "sg:classifiers":[
        {
            "category":"Travel",
            "subcategory":"Hotels & Motels",
            "type":"Entertainment"
        }
    ],
    "sg:phone":"+1 334 687 4811",
    "sg:postcode":"36027",
    "sg:province":"AL",
    "sg:tags":[
        "operation"
    ],
    "wof:name":"Lake Eufaula Motor Lodge",
    "wof:placetype":"venue"
},
  "geometry": {"coordinates":[-85.13681,31.891652],"type":"Point"}
}