{
  "type": "Feature",
  "properties": {
    "addr:full":"356 Dogwood Ln Mobile AL 36608",
    "addr:housenumber":"356",
    "addr:postcode":"36608",
    "addr:street":"Dogwood Ln",
    "iso:country":"US",
    "sg:address":"356 Dogwood Ln",
    "sg:city":"Mobile",
    "sg:classifiers":[
        {
            "category":"Professional",
            "subcategory":"Business Services",
            "type":"Services"
        }
    ],
    "sg:phone":"+1 251 344 5353",
    "sg:postcode":"36608",
    "sg:province":"AL",
    "wof:name":"Bmb Investments",
    "wof:placetype":"venue"
},
  "geometry": {"coordinates":[-88.13387,30.700197],"type":"Point"}
}