{
  "type": "Feature",
  "properties": {
    "iso:country":"US",
    "sg:address":"520 Co Rd 555",
    "sg:city":"Rogersville",
    "sg:classifiers":[
        {
            "category":"Shopping",
            "subcategory":"Gifts & Souvenirs",
            "type":"Retail Goods"
        }
    ],
    "sg:phone":"+1 256 247 9541",
    "sg:postcode":"35652",
    "sg:province":"AL",
    "wof:name":"Hiway 72 Trading Cards",
    "wof:placetype":"venue"
},
  "geometry": {"coordinates":[-87.267112,34.859161],"type":"Point"}
}