{
  "type": "Feature",
  "properties": {
    "iso:country":"US",
    "sg:address":"7692 Birmingport Rd",
    "sg:city":"Mulga",
    "sg:classifiers":[
        {
            "category":"Food & Beverages",
            "subcategory":"Groceries & Convenience Stores",
            "type":"Retail Goods"
        }
    ],
    "sg:phone":"+1 205 436 3920",
    "sg:postcode":"35118",
    "sg:province":"AL",
    "sg:tags":[
        "station",
        "gasoline"
    ],
    "wof:name":"Birmingport Grocery",
    "wof:placetype":"venue"
},
  "geometry": {"coordinates":[-87.103848,33.553309],"type":"Point"}
}