{
  "type": "Feature",
  "properties": {
    "iso:country":"US",
    "sg:address":"11584 Co Rd 24",
    "sg:city":"Verbena",
    "sg:classifiers":[
        {
            "category":"Food & Beverages",
            "subcategory":"Groceries & Convenience Stores",
            "type":"Retail Goods"
        }
    ],
    "sg:phone":"+1 205 755 4301",
    "sg:postcode":"36091",
    "sg:province":"AL",
    "sg:tags":[
        "grocer"
    ],
    "wof:name":"Sandy's Bent & Dent Grocery",
    "wof:placetype":"venue"
},
  "geometry": {"coordinates":[-86.54848,32.767453],"type":"Point"}
}