{
  "type": "Feature",
  "properties": {
    "iso:country":"US",
    "sg:address":"2210 Co Rd 29",
    "sg:city":"Alberta",
    "sg:classifiers":[
        {
            "category":"Organizations",
            "subcategory":"Religious Organization",
            "type":"Services"
        }
    ],
    "sg:phone":"+1 334 573 9080",
    "sg:postcode":"36720",
    "sg:province":"AL",
    "wof:name":"Mount Sinia Church",
    "wof:placetype":"venue"
},
  "geometry": {"coordinates":[-87.398805,32.219084],"type":"Point"}
}