{
  "type": "Feature",
  "properties": {
    "iso:country":"US",
    "sg:address":"4717 University Dr NW",
    "sg:city":"Huntsville",
    "sg:classifiers":[
        {
            "category":"Organizations",
            "subcategory":"Non-profit Organization",
            "type":"Services"
        },
        {
            "category":"Social Services",
            "subcategory":"Job Training",
            "type":"Services"
        }
    ],
    "sg:phone":"+1 256 837 5777",
    "sg:postcode":"35816",
    "sg:province":"AL",
    "sg:tags":[
        "retardation",
        "disabled",
        "mental",
        "dev"
    ],
    "wof:name":"Mental Retardation Services",
    "wof:placetype":"venue"
},
  "geometry": {"coordinates":[-86.648223,34.735758],"type":"Point"}
}