{
  "type": "Feature",
  "properties": {
    "iso:country":"US",
    "sg:address":"202 N George Wallace Dr",
    "sg:city":"Troy",
    "sg:classifiers":[
        {
            "category":"Government",
            "subcategory":"Office",
            "type":"Public Place"
        }
    ],
    "sg:phone":"+1 334 566 9186",
    "sg:postcode":"36081",
    "sg:province":"AL",
    "sg:tags":[
        "federal",
        "security"
    ],
    "wof:name":"US Army National Guard Rcrtng",
    "wof:placetype":"venue"
},
  "geometry": {"coordinates":[-85.948832,31.811836],"type":"Point"}
}