{
  "type": "Feature",
  "properties": {
    "iso:country":"US",
    "sg:address":"5101 Oscar Baxter Dr",
    "sg:city":"Tuscaloosa",
    "sg:classifiers":[
        {
            "category":"Food & Beverages",
            "subcategory":"Groceries & Convenience Stores",
            "type":"Retail Goods"
        }
    ],
    "sg:phone":"+1 205 366 1600",
    "sg:postcode":"35405",
    "sg:province":"AL",
    "wof:name":"Handi Mart 4",
    "wof:placetype":"venue"
},
  "geometry": {"coordinates":[-87.553021,33.165992],"type":"Point"}
}