{
  "type": "Feature",
  "properties": {
    "addr:full":"2687 Zelda Rd Montgomery AL 36107",
    "addr:housenumber":"2687",
    "addr:postcode":"36107",
    "addr:street":"Zelda Rd",
    "iso:country":"US",
    "sg:address":"2687 Zelda Rd",
    "sg:city":"Montgomery",
    "sg:classifiers":[
        {
            "category":"Restaurant",
            "type":"Food & Drink"
        }
    ],
    "sg:menulink":"http://www.allmenus.com/al/montgomery/198552-kfc---kentucky-fried-chicken/menu/",
    "sg:phone":"+1 334 271 5773",
    "sg:postcode":"36107",
    "sg:province":"AL",
    "sg:tags":[
        "american",
        "chicken"
    ],
    "wof:name":"KFC - Kentucky Fried Chicken",
    "wof:placetype":"venue"
},
  "geometry": {"coordinates":[-86.26818400000001,32.364113],"type":"Point"}
}