{
  "type": "Feature",
  "properties": {
    "iso:country":"US",
    "sg:address":"203 W Commerce St",
    "sg:city":"Greenville",
    "sg:classifiers":[
        {
            "category":"Shopping",
            "subcategory":"Beauty & Cosmetics",
            "type":"Retail Goods"
        }
    ],
    "sg:phone":"+1 334 382 9047",
    "sg:postcode":"36037",
    "sg:province":"AL",
    "sg:tags":[
        "clothing",
        "merchandise"
    ],
    "wof:name":"Robinson Beauty Supply Shop",
    "wof:placetype":"venue"
},
  "geometry": {"coordinates":[-86.626148,31.829647],"type":"Point"}
}