{
  "type": "Feature",
  "properties": {
    "iso:country":"US",
    "sg:address":"7010 Champion Blvd",
    "sg:city":"Birmingham",
    "sg:classifiers":[
        {
            "category":"Recreation",
            "type":"Entertainment"
        }
    ],
    "sg:phone":"+1 205 980 8880",
    "sg:postcode":"35242",
    "sg:province":"AL",
    "sg:tags":[
        "instruction",
        "gymnastic"
    ],
    "wof:name":"Greystone Sports Ctr Inc",
    "wof:placetype":"venue"
},
  "geometry": {"coordinates":[-86.663856,33.407075],"type":"Point"}
}