{
  "type": "Feature",
  "properties": {
    "addr:full":"1119 Cherokee Rd Alexander City AL 35010",
    "addr:housenumber":"1119",
    "addr:postcode":"35010",
    "addr:street":"Cherokee Rd",
    "iso:country":"US",
    "sg:address":"1119 Cherokee Rd",
    "sg:city":"Alexander City",
    "sg:classifiers":[
        {
            "category":"Retail",
            "subcategory":"Laundry & Dry Cleaning",
            "type":"Services"
        }
    ],
    "sg:phone":"+1 256 329 2695",
    "sg:postcode":"35010",
    "sg:province":"AL",
    "sg:tags":[
        "drycleaning",
        "plant"
    ],
    "wof:name":"Classic Cleaners",
    "wof:placetype":"venue"
},
  "geometry": {"coordinates":[-85.949451,32.932094],"type":"Point"}
}