{
  "type": "Feature",
  "properties": {
    "iso:country":"US",
    "sg:address":"3803 W Meighan Blvd",
    "sg:city":"Gadsden",
    "sg:classifiers":[
        {
            "category":"Organizations",
            "subcategory":"Labor Organization",
            "type":"Services"
        }
    ],
    "sg:phone":"+1 256 546 5730",
    "sg:postcode":"35904",
    "sg:province":"AL",
    "wof:name":"Health & Welfare Office",
    "wof:placetype":"venue"
},
  "geometry": {"coordinates":[-86.063229,34.022012],"type":"Point"}
}