{
  "type": "Feature",
  "properties": {
    "iso:country":"US",
    "sg:address":"4051 Sherborne Rd",
    "sg:city":"Birmingham",
    "sg:classifiers":[
        {
            "category":"Restaurant",
            "type":"Food & Drink"
        }
    ],
    "sg:phone":"+1 205 956 2690",
    "sg:postcode":"35210",
    "sg:province":"AL",
    "sg:tags":[
        "eating"
    ],
    "wof:name":"Southeast Subway Inc",
    "wof:placetype":"venue"
},
  "geometry": {"coordinates":[-86.66887,33.517536],"type":"Point"}
}