{
  "type": "Feature",
  "properties": {
    "addr:full":"140 Geronimo Cir Montevallo AL 35115",
    "addr:housenumber":"140",
    "addr:postcode":"35115",
    "addr:street":"Geronimo Cir",
    "iso:country":"US",
    "sg:address":"140 Geronimo Cir",
    "sg:city":"Montevallo",
    "sg:classifiers":[
        {
            "category":"Restaurant",
            "type":"Food & Drink"
        }
    ],
    "sg:phone":"+1 205 665 7972",
    "sg:postcode":"35115",
    "sg:province":"AL",
    "sg:tags":[
        "eating"
    ],
    "wof:name":"Firehouse Bar B Que & Grill",
    "wof:placetype":"venue"
},
  "geometry": {"coordinates":[-86.850471,33.110878],"type":"Point"}
}