{
  "type": "Feature",
  "properties": {
    "iso:country":"US",
    "sg:address":"3657 Pine Ln",
    "sg:city":"Bessemer",
    "sg:classifiers":[
        {
            "category":"Wholesale",
            "subcategory":"Hardware",
            "type":"Manufacturing & Wholesale Goods"
        }
    ],
    "sg:phone":"+1 205 428 2326",
    "sg:postcode":"35022",
    "sg:province":"AL",
    "sg:tags":[
        "used",
        "boiler"
    ],
    "sg:website":"www.adcoboiler.com",
    "wof:name":"ADCO Boiler Co",
    "wof:placetype":"venue"
},
  "geometry": {"coordinates":[-86.904326,33.342253],"type":"Point"}
}