{
  "type": "Feature",
  "properties": {
    "iso:country":"US",
    "sg:address":"1312 Bellview St",
    "sg:city":"Montgomery",
    "sg:classifiers":[
        {
            "category":"Building & Trades",
            "subcategory":"Landscaping Services",
            "type":"Services"
        }
    ],
    "sg:phone":"+1 334 263 5808",
    "sg:postcode":"36104",
    "sg:province":"AL",
    "wof:name":"Moores Lawn Services",
    "wof:placetype":"venue"
},
  "geometry": {"coordinates":[-86.314698,32.359913],"type":"Point"}
}