{
  "type": "Feature",
  "properties": {
    "iso:country":"US",
    "sg:address":"1119 Dearing Downs Dr",
    "sg:city":"Helena",
    "sg:classifiers":[
        {
            "category":"Restaurant",
            "type":"Food & Drink"
        }
    ],
    "sg:phone":"+1 205 253 4844",
    "sg:postcode":"35080",
    "sg:province":"AL",
    "sg:tags":[
        "eating"
    ],
    "wof:name":"Snoto Go",
    "wof:placetype":"venue"
},
  "geometry": {"coordinates":[-86.829257,33.281267],"type":"Point"}
}