{
  "type": "Feature",
  "properties": {
    "iso:country":"US",
    "sg:address":"12801 US Hwy 431",
    "sg:city":"Guntersville",
    "sg:classifiers":[
        {
            "category":"Building & Trades",
            "subcategory":"Construction",
            "type":"Services"
        }
    ],
    "sg:phone":"+1 256 582 6881",
    "sg:postcode":"35976",
    "sg:province":"AL",
    "sg:tags":[
        "commercial",
        "painting",
        "contractor"
    ],
    "wof:name":"Guntersville Paint Co Inc",
    "wof:placetype":"venue"
},
  "geometry": {"coordinates":[-86.290193,34.306076],"type":"Point"}
}