{
  "type": "Feature",
  "properties": {
    "addr:full":"47720 US Hwy 78 Lincoln AL 35096",
    "addr:postcode":"47720;35096",
    "addr:street":"Us Hwy 78",
    "iso:country":"US",
    "sg:address":"47720 US Hwy 78",
    "sg:city":"Lincoln",
    "sg:classifiers":[
        {
            "category":"Food & Beverages",
            "subcategory":"Groceries & Convenience Stores",
            "type":"Retail Goods"
        },
        {
            "category":"Autos & Motor Vehicles",
            "subcategory":"Fuel & Gas Station",
            "type":"Retail Goods"
        }
    ],
    "sg:phone":"+1 205 763 2559",
    "sg:postcode":"35096",
    "sg:province":"AL",
    "sg:tags":[
        "oil"
    ],
    "wof:name":"Pik -A-Dilly",
    "wof:placetype":"venue"
},
  "geometry": {"coordinates":[-86.112668,33.604878],"type":"Point"}
}