{
  "type": "Feature",
  "properties": {
    "iso:country":"US",
    "sg:address":"312 Clinton Ave W",
    "sg:city":"Huntsville",
    "sg:classifiers":[
        {
            "category":"Professional",
            "subcategory":"Employment Agencies",
            "type":"Services"
        }
    ],
    "sg:phone":"+1 256 551 7141",
    "sg:postcode":"35801",
    "sg:province":"AL",
    "sg:tags":[
        "organization",
        "employer"
    ],
    "wof:name":"Strategic Outsourcing Inc",
    "wof:placetype":"venue"
},
  "geometry": {"coordinates":[-86.58888,34.730136],"type":"Point"}
}