{
  "type": "Feature",
  "properties": {
    "iso:country":"US",
    "sg:address":"9486 Old Hwy 31",
    "sg:city":"Warrior",
    "sg:classifiers":[
        {
            "category":"Wholesale",
            "subcategory":"Machinery & Supplies",
            "type":"Manufacturing & Wholesale Goods"
        }
    ],
    "sg:phone":"+1 205 647 2020",
    "sg:postcode":"35180",
    "sg:province":"AL",
    "sg:tags":[
        "equipment",
        "mining",
        "construction"
    ],
    "wof:name":"Hallmark Equipment Inc",
    "wof:placetype":"venue"
},
  "geometry": {"coordinates":[-86.827519,33.792344],"type":"Point"}
}