{
  "type": "Feature",
  "properties": {
    "iso:country":"US",
    "sg:address":"2661 Elm St",
    "sg:city":"Tuscaloosa",
    "sg:classifiers":[
        {
            "category":"Wholesale",
            "subcategory":"Scrap",
            "type":"Manufacturing & Wholesale Goods"
        }
    ],
    "sg:phone":"+1 205 758 1838",
    "sg:postcode":"35401",
    "sg:province":"AL",
    "sg:tags":[
        "recycling",
        "center"
    ],
    "wof:name":"Waste Recycling Inc",
    "wof:placetype":"venue"
},
  "geometry": {"coordinates":[-87.568876,33.187939],"type":"Point"}
}