{
  "type": "Feature",
  "properties": {
    "iso:country":"US",
    "sg:address":"222 Bud Moore Rd",
    "sg:city":"Cottonwood",
    "sg:classifiers":[
        {
            "category":"Sports & Exercise",
            "subcategory":"Race Track",
            "type":"Entertainment"
        }
    ],
    "sg:phone":"+1 334 691 4431",
    "sg:postcode":"36320",
    "sg:province":"AL",
    "sg:tags":[
        "operation",
        "racing",
        "or"
    ],
    "wof:name":"Dothan Dragway",
    "wof:placetype":"venue"
},
  "geometry": {"coordinates":[-85.275156,31.102946],"type":"Point"}
}