{
  "type": "Feature",
  "properties": {
    "addr:full":"270 Doug Baker Blvd Birmingham AL 35242",
    "addr:housenumber":"270",
    "addr:postcode":"35242",
    "addr:street":"Doug Baker Blvd",
    "iso:country":"US",
    "sg:address":"270 Doug Baker Blvd",
    "sg:city":"Birmingham",
    "sg:classifiers":[
        {
            "category":"Restaurant",
            "type":"Food & Drink"
        }
    ],
    "sg:menulink":"http://www.allmenus.com/al/alabaster-helena/89445-moes-southwest-grill/menu/",
    "sg:phone":"+1 205 437 9998",
    "sg:postcode":"35242",
    "sg:province":"AL",
    "sg:tags":[
        "mexican"
    ],
    "wof:name":"Moe's Southwest Grill",
    "wof:placetype":"venue"
},
  "geometry": {"coordinates":[-86.67499100000001,33.411131],"type":"Point"}
}