{
  "type": "Feature",
  "properties": {
    "iso:country":"US",
    "sg:address":"1616 2nd Ave SW",
    "sg:city":"Cullman",
    "sg:classifiers":[
        {
            "category":"Organizations",
            "subcategory":"Religious Organization",
            "type":"Services"
        }
    ],
    "sg:phone":"+1 256 737 1926",
    "sg:postcode":"35055",
    "sg:province":"AL",
    "wof:name":"Joyce Tyson Ministries",
    "wof:placetype":"venue"
},
  "geometry": {"coordinates":[-86.823649,34.139639],"type":"Point"}
}