{
  "type": "Feature",
  "properties": {
    "iso:country":"US",
    "sg:address":"4330 Riveroaks Rd",
    "sg:city":"Millbrook",
    "sg:classifiers":[
        {
            "category":"Bars & Pubs",
            "type":"Food & Drink"
        }
    ],
    "sg:phone":"+1 334 290 0706",
    "sg:postcode":"36054",
    "sg:province":"AL",
    "sg:tags":[
        "drinking"
    ],
    "wof:name":"Dewys Lounge",
    "wof:placetype":"venue"
},
  "geometry": {"coordinates":[-86.356234,32.434304],"type":"Point"}
}