{
  "type": "Feature",
  "properties": {
    "iso:country":"US",
    "sg:address":"10571 State Rte 168",
    "sg:city":"Boaz",
    "sg:classifiers":[
        {
            "category":"Shopping",
            "subcategory":"Shoes",
            "type":"Retail Goods"
        }
    ],
    "sg:phone":"+1 256 593 5465",
    "sg:postcode":"35957",
    "sg:province":"AL",
    "wof:name":"Shoe Place",
    "wof:placetype":"venue"
},
  "geometry": {"coordinates":[-86.157696,34.19861],"type":"Point"}
}