{
  "type": "Feature",
  "properties": {
    "addr:full":"3212 7th Ave SW Huntsville AL 35805",
    "addr:housenumber":"3212",
    "addr:postcode":"35805",
    "addr:street":"7Th Ave Sw",
    "iso:country":"US",
    "sg:address":"3212 7th Ave SW",
    "sg:city":"Huntsville",
    "sg:classifiers":[
        {
            "category":"Professional",
            "subcategory":"Testing Lab",
            "type":"Services"
        }
    ],
    "sg:phone":"+1 256 539 7236",
    "sg:postcode":"35805",
    "sg:province":"AL",
    "sg:tags":[
        "correction",
        "radon"
    ],
    "wof:name":"Radon Solutions",
    "wof:placetype":"venue"
},
  "geometry": {"coordinates":[-86.610373,34.717985],"type":"Point"}
}