{
  "type": "Feature",
  "properties": {
    "iso:country":"US",
    "sg:address":"1360 Montgomery Hwy",
    "sg:city":"Birmingham",
    "sg:classifiers":[
        {
            "category":"Restaurant",
            "type":"Food & Drink"
        }
    ],
    "sg:menulink":"http://www.allmenus.com/al/birmingham/235024-roly-poly-sandwiches/menu/",
    "sg:phone":"+1 205 822 3362",
    "sg:postcode":"35216",
    "sg:province":"AL",
    "sg:tags":[
        "wrap",
        "american",
        "sandwich"
    ],
    "wof:name":"Roly Poly Sandwiches",
    "wof:placetype":"venue"
},
  "geometry": {"coordinates":[-86.793791,33.425831],"type":"Point"}
}