{
  "type": "Feature",
  "properties": {
    "iso:country":"US",
    "sg:address":"2104 Eva Rd",
    "sg:city":"Eva",
    "sg:classifiers":[
        {
            "category":"Building & Trades",
            "subcategory":"Construction",
            "type":"Services"
        }
    ],
    "sg:phone":"+1 256 482 8135",
    "sg:postcode":"35621",
    "sg:province":"AL",
    "sg:tags":[
        "general",
        "contractor"
    ],
    "wof:name":"Falls Construction",
    "wof:placetype":"venue"
},
  "geometry": {"coordinates":[-86.751537,34.379709],"type":"Point"}
}