{
  "type": "Feature",
  "properties": {
    "addr:full":"2829 7th St Tuscaloosa AL 35401",
    "addr:housenumber":"2829",
    "addr:postcode":"35401",
    "addr:street":"7Th St",
    "iso:country":"US",
    "sg:address":"2829 7th St",
    "sg:city":"Tuscaloosa",
    "sg:classifiers":[
        {
            "category":"Professional",
            "subcategory":"Lawyer & Legal Services",
            "type":"Services"
        }
    ],
    "sg:phone":"+1 205 750 0098",
    "sg:postcode":"35401",
    "sg:province":"AL",
    "sg:tags":[
        "attorney"
    ],
    "wof:name":"Paula Watkins",
    "wof:placetype":"venue"
},
  "geometry": {"coordinates":[-87.573868,33.206066],"type":"Point"}
}