{
  "type": "Feature",
  "properties": {
    "iso:country":"US",
    "sg:address":"8244 Old Federal Rd",
    "sg:city":"Montgomery",
    "sg:classifiers":[
        {
            "category":"Professional",
            "subcategory":"Lawyer & Legal Services",
            "type":"Services"
        }
    ],
    "sg:phone":"+1 334 396 5719",
    "sg:postcode":"36117",
    "sg:province":"AL",
    "wof:name":"Davis Hamilton Berry & Sexton",
    "wof:placetype":"venue"
},
  "geometry": {"coordinates":[-86.169544,32.341639],"type":"Point"}
}