{
  "type": "Feature",
  "properties": {
    "iso:country":"US",
    "sg:address":"4900 Pebble Shore Dr",
    "sg:city":"Opelika",
    "sg:classifiers":[
        {
            "category":"Professional",
            "subcategory":"Business Services",
            "type":"Services"
        }
    ],
    "sg:phone":"+1 334 749 3732",
    "sg:postcode":"36804",
    "sg:province":"AL",
    "wof:name":"A1 Enterprises LLC",
    "wof:placetype":"venue"
},
  "geometry": {"coordinates":[-85.361307,32.585269],"type":"Point"}
}