{
  "type": "Feature",
  "properties": {
    "addr:full":"650 Lee Road 268 Valley AL 36854",
    "addr:housenumber":"650",
    "addr:postcode":"36854",
    "addr:street":"Lee Road 268",
    "iso:country":"US",
    "sg:address":"650 Lee Road 268",
    "sg:city":"Valley",
    "sg:classifiers":[
        {
            "category":"Autos & Motor Vehicles",
            "subcategory":"Fuel & Gas Station",
            "type":"Retail Goods"
        }
    ],
    "sg:phone":"+1 334 768 3510",
    "sg:postcode":"36854",
    "sg:province":"AL",
    "sg:tags":[
        "gasoline"
    ],
    "wof:name":"Happy Stop III",
    "wof:placetype":"venue"
},
  "geometry": {"coordinates":[-85.26748499999999,32.73415],"type":"Point"}
}