{
  "type": "Feature",
  "properties": {
    "addr:full":"7015 US Hwy 72 Alt Huntsville AL 35758",
    "addr:housenumber":"7015",
    "addr:postcode":"35758",
    "addr:street":"Us Hwy 72 Alt",
    "iso:country":"US",
    "sg:address":"7015 US Hwy 72 Alt",
    "sg:city":"Huntsville",
    "sg:classifiers":[
        {
            "category":"Retail",
            "subcategory":"Auto Rental",
            "type":"Services"
        }
    ],
    "sg:phone":"+1 256 837 8786",
    "sg:postcode":"35758",
    "sg:province":"AL",
    "sg:tags":[
        "truck",
        "trailer",
        "utility"
    ],
    "wof:name":"U-Haul",
    "wof:placetype":"venue"
},
  "geometry": {"coordinates":[-86.677893,34.70644],"type":"Point"}
}