{
  "type": "Feature",
  "properties": {
    "iso:country":"US",
    "sg:address":"333 Choccolocco St",
    "sg:city":"Oxford",
    "sg:classifiers":[
        {
            "category":"Personal",
            "subcategory":"Beauty Salon",
            "type":"Services"
        }
    ],
    "sg:phone":"+1 256 835 9733",
    "sg:postcode":"36203",
    "sg:province":"AL",
    "sg:tags":[
        "shop"
    ],
    "wof:name":"D Chrisjen's",
    "wof:placetype":"venue"
},
  "geometry": {"coordinates":[-85.830697,33.615138],"type":"Point"}
}