{
  "type": "Feature",
  "properties": {
    "iso:country":"US",
    "sg:address":"6313 Red Hawk Cir",
    "sg:city":"Trussville",
    "sg:classifiers":[
        {
            "category":"Professional",
            "subcategory":"Business Services",
            "type":"Services"
        }
    ],
    "sg:phone":"+1 205 661 9748",
    "sg:postcode":"35173",
    "sg:province":"AL",
    "wof:name":"B&L Sales Inc",
    "wof:placetype":"venue"
},
  "geometry": {"coordinates":[-86.583964,33.684702],"type":"Point"}
}