{
  "type": "Feature",
  "properties": {
    "iso:country":"US",
    "sg:address":"1009 Winchester Rd NE",
    "sg:city":"Huntsville",
    "sg:classifiers":[
        {
            "category":"Food & Beverages",
            "subcategory":"Groceries & Convenience Stores",
            "type":"Retail Goods"
        }
    ],
    "sg:phone":"+1 256 858 9050",
    "sg:postcode":"35811",
    "sg:province":"AL",
    "wof:name":"Discount Food Mart 214",
    "wof:placetype":"venue"
},
  "geometry": {"coordinates":[-86.536185,34.798341],"type":"Point"}
}