{
  "type": "Feature",
  "properties": {
    "iso:country":"US",
    "sg:address":"3640 Menlo Ct",
    "sg:city":"Montgomery",
    "sg:classifiers":[
        {
            "category":"Retail",
            "subcategory":"Laundry & Dry Cleaning",
            "type":"Services"
        }
    ],
    "sg:phone":"+1 334 284 6415",
    "sg:postcode":"36116",
    "sg:province":"AL",
    "wof:name":"Emperor Carpet Cleaning",
    "wof:placetype":"venue"
},
  "geometry": {"coordinates":[-86.258982,32.307369],"type":"Point"}
}