{
  "type": "Feature",
  "properties": {
    "iso:country":"US",
    "sg:address":"3125 Mc Dow Ave NW",
    "sg:city":"Huntsville",
    "sg:classifiers":[
        {
            "category":"Professional",
            "subcategory":"Accounting & Tax Preparation",
            "type":"Services"
        }
    ],
    "sg:phone":"+1 256 536 9131",
    "sg:postcode":"35816",
    "sg:province":"AL",
    "sg:tags":[
        "accountant"
    ],
    "wof:name":"Gilmore's Accounting & Tax",
    "wof:placetype":"venue"
},
  "geometry": {"coordinates":[-86.621706,34.738655],"type":"Point"}
}