{
  "type": "Feature",
  "properties": {
    "iso:country":"US",
    "sg:address":"520 S Perry St",
    "sg:city":"Montgomery",
    "sg:classifiers":[
        {
            "category":"Shopping",
            "subcategory":"Stationery & Office Supplies",
            "type":"Retail Goods"
        }
    ],
    "sg:phone":"+1 334 262 0511",
    "sg:postcode":"36104",
    "sg:province":"AL",
    "sg:tags":[
        "equipment",
        "filing",
        "system"
    ],
    "wof:name":"Business Systems & Consultants",
    "wof:placetype":"venue"
},
  "geometry": {"coordinates":[-86.30721800000001,32.370416],"type":"Point"}
}