{
  "type": "Feature",
  "properties": {
    "addr:full":"3795 State Rte 13 Haleyville AL 35565",
    "addr:housenumber":"3795",
    "addr:postcode":"35565",
    "addr:street":"State Rte 13 Haleyville",
    "iso:country":"US",
    "sg:address":"3795 State Rte 13",
    "sg:city":"Haleyville",
    "sg:classifiers":[
        {
            "category":"Manufacturing",
            "subcategory":"Furniture",
            "type":"Manufacturing & Wholesale Goods"
        }
    ],
    "sg:phone":"+1 205 486 2208",
    "sg:postcode":"35565",
    "sg:province":"AL",
    "sg:tags":[
        "dinette",
        "set"
    ],
    "wof:name":"Rebco Furniture Mfg",
    "wof:placetype":"venue"
},
  "geometry": {"coordinates":[-87.62090499999999,34.218152],"type":"Point"}
}