{
  "type": "Feature",
  "properties": {
    "addr:full":"21627 US Hwy 31 Letohatchee AL 36047",
    "addr:postcode":"21627;36047",
    "addr:street":"Us Hwy 31 Letohatchee",
    "iso:country":"US",
    "sg:address":"21627 US Hwy 31",
    "sg:city":"Letohatchee",
    "sg:classifiers":[
        {
            "category":"Building & Trades",
            "subcategory":"Plumbing",
            "type":"Services"
        }
    ],
    "sg:phone":"+1 334 284 9150",
    "sg:postcode":"36047",
    "sg:province":"AL",
    "sg:tags":[
        "contractor"
    ],
    "wof:name":"Hill Heating & Air",
    "wof:placetype":"venue"
},
  "geometry": {"coordinates":[-86.406567,32.087456],"type":"Point"}
}