{
  "type": "Feature",
  "properties": {
    "iso:country":"US",
    "sg:address":"3608 US Hwy 431",
    "sg:city":"Phenix City",
    "sg:classifiers":[
        {
            "category":"Wholesale",
            "subcategory":"Jewelry",
            "type":"Manufacturing & Wholesale Goods"
        }
    ],
    "sg:phone":"+1 334 297 1115",
    "sg:postcode":"36867",
    "sg:province":"AL",
    "sg:tags":[
        "stone"
    ],
    "wof:name":"Wholesale Jewelers",
    "wof:placetype":"venue"
},
  "geometry": {"coordinates":[-85.04940499999999,32.50302],"type":"Point"}
}