{
  "type": "Feature",
  "properties": {
    "iso:country":"US",
    "sg:address":"432 S Randolph Ave",
    "sg:city":"Eufaula",
    "sg:classifiers":[
        {
            "category":"Retail",
            "subcategory":"Auto Repair",
            "type":"Services"
        }
    ],
    "sg:phone":"+1 334 687 6010",
    "sg:postcode":"36027",
    "sg:province":"AL",
    "sg:tags":[
        "general"
    ],
    "wof:name":"Rogers Auto Service",
    "wof:placetype":"venue"
},
  "geometry": {"coordinates":[-85.144037,31.887804],"type":"Point"}
}