{
  "type": "Feature",
  "properties": {
    "iso:country":"US",
    "sg:address":"3296 Co Rd 140",
    "sg:city":"Ider",
    "sg:classifiers":[
        {
            "category":"Real Estate",
            "subcategory":"Surveying",
            "type":"Services"
        }
    ],
    "sg:phone":"+1 256 632 6159",
    "sg:postcode":"35981",
    "sg:province":"AL",
    "sg:tags":[
        "surveyor"
    ],
    "wof:name":"Farris Surveying",
    "wof:placetype":"venue"
},
  "geometry": {"coordinates":[-85.67985899999999,34.714073],"type":"Point"}
}