{
  "type": "Feature",
  "properties": {
    "addr:full":"1805 8th Ave Tuscaloosa AL 35401",
    "addr:housenumber":"1805",
    "addr:postcode":"35401",
    "addr:street":"8Th Ave",
    "iso:country":"US",
    "sg:address":"1805 8th Ave",
    "sg:city":"Tuscaloosa",
    "sg:classifiers":[
        {
            "category":"Organizations",
            "subcategory":"Religious Organization",
            "type":"Services"
        }
    ],
    "sg:phone":"+1 205 391 2111",
    "sg:postcode":"35401",
    "sg:province":"AL",
    "sg:website":"www.trinitytuscaloosa.org",
    "wof:name":"Trinity Presbyterian Church",
    "wof:placetype":"venue"
},
  "geometry": {"coordinates":[-87.547766,33.195057],"type":"Point"}
}