{
  "type": "Feature",
  "properties": {
    "iso:country":"US",
    "sg:address":"1111 Industrial Pkwy",
    "sg:city":"Saraland",
    "sg:classifiers":[
        {
            "category":"Travel",
            "subcategory":"Hotels & Motels",
            "type":"Entertainment"
        }
    ],
    "sg:phone":"+1 251 679 8880",
    "sg:postcode":"36571",
    "sg:province":"AL",
    "sg:website":"http://www.choicehotels.com/hotel/al378",
    "wof:name":"Quality Inn",
    "wof:placetype":"venue"
},
  "geometry": {"coordinates":[-88.099531,30.802092],"type":"Point"}
}