{
  "type": "Feature",
  "properties": {
    "addr:full":"3675 Hood Ln Gadsden AL 35907",
    "addr:housenumber":"3675",
    "addr:postcode":"35907",
    "addr:street":"Hood Ln",
    "iso:country":"US",
    "sg:address":"3675 Hood Ln",
    "sg:city":"Gadsden",
    "sg:classifiers":[
        {
            "category":"Health Services",
            "subcategory":"Doctor",
            "type":"Services"
        }
    ],
    "sg:phone":"+1 256 413 7465",
    "sg:postcode":"35907",
    "sg:province":"AL",
    "sg:tags":[
        "medical"
    ],
    "wof:name":"Anniston Internal Medicine",
    "wof:placetype":"venue"
},
  "geometry": {"coordinates":[-86.067206,33.901856],"type":"Point"}
}