{
  "type": "Feature",
  "properties": {
    "iso:country":"US",
    "sg:address":"2671 Montgomery Hwy",
    "sg:city":"Dothan",
    "sg:classifiers":[
        {
            "category":"Shopping",
            "subcategory":"Used Merchandise",
            "type":"Retail Goods"
        }
    ],
    "sg:phone":"+1 334 671 8588",
    "sg:postcode":"36303",
    "sg:province":"AL",
    "wof:name":"Title Cash",
    "wof:placetype":"venue"
},
  "geometry": {"coordinates":[-85.420888,31.24554],"type":"Point"}
}