{
  "type": "Feature",
  "properties": {
    "iso:country":"US",
    "sg:address":"1 Henderson St",
    "sg:city":"Brewton",
    "sg:classifiers":[
        {
            "category":"Insurance",
            "subcategory":"Insurance Agent",
            "type":"Services"
        }
    ],
    "sg:phone":"+1 251 867 3282",
    "sg:postcode":"36426",
    "sg:province":"AL",
    "wof:name":"Mutual Savings Life Insurance",
    "wof:placetype":"venue"
},
  "geometry": {"coordinates":[-87.071615,31.106016],"type":"Point"}
}