{
  "type": "Feature",
  "properties": {
    "iso:country":"US",
    "sg:address":"2278 Halls Mill Rd",
    "sg:city":"Mobile",
    "sg:classifiers":[
        {
            "category":"Wholesale",
            "subcategory":"Fruits & Vegetables",
            "type":"Manufacturing & Wholesale Goods"
        }
    ],
    "sg:phone":"+1 251 479 9555",
    "sg:postcode":"36606",
    "sg:province":"AL",
    "sg:tags":[
        "shipper"
    ],
    "wof:name":"Emerald Coast Produce",
    "wof:placetype":"venue"
},
  "geometry": {"coordinates":[-88.09679,30.660487],"type":"Point"}
}