{
  "type": "Feature",
  "properties": {
    "addr:full":"1502 11th Ave Phenix City AL 36867",
    "addr:housenumber":"1502",
    "addr:postcode":"36867",
    "addr:street":"11Th Ave Phenix City Al",
    "iso:country":"US",
    "sg:address":"1502 11th Ave",
    "sg:city":"Phenix City",
    "sg:classifiers":[
        {
            "category":"Education",
            "subcategory":"School",
            "type":"Public Place"
        }
    ],
    "sg:phone":"+1 334 297 7915",
    "sg:postcode":"36867",
    "sg:province":"AL",
    "wof:name":"Phenix City Adult Basic Ed",
    "wof:placetype":"venue"
},
  "geometry": {"coordinates":[-85.008173,32.474131],"type":"Point"}
}