{
  "type": "Feature",
  "properties": {
    "iso:country":"US",
    "sg:address":"2001 Sparkman Dr NW",
    "sg:city":"Huntsville",
    "sg:classifiers":[
        {
            "category":"Autos & Motor Vehicles",
            "subcategory":"Automobile Sales",
            "type":"Retail Goods"
        }
    ],
    "sg:phone":"+1 256 852 7422",
    "sg:postcode":"35810",
    "sg:province":"AL",
    "sg:tags":[
        "car",
        "dealer"
    ],
    "wof:name":"J D Byrider Auto Sales",
    "wof:placetype":"venue"
},
  "geometry": {"coordinates":[-86.59068,34.762344],"type":"Point"}
}