{
  "type": "Feature",
  "properties": {
    "addr:full":"2395 Vaughn Rd Altoona AL 35952",
    "addr:housenumber":"2395",
    "addr:postcode":"35952",
    "addr:street":"Vaughn Rd",
    "iso:country":"US",
    "sg:address":"2395 Vaughn Rd",
    "sg:city":"Altoona",
    "sg:classifiers":[
        {
            "category":"Professional",
            "type":"Services"
        }
    ],
    "sg:phone":"+1 205 589 2882",
    "sg:postcode":"35952",
    "sg:province":"AL",
    "wof:name":"National Eligibility Express",
    "wof:placetype":"venue"
},
  "geometry": {"coordinates":[-86.24539,34.072954],"type":"Point"}
}