{
  "type": "Feature",
  "properties": {
    "iso:country":"US",
    "sg:address":"878 Co Rd 8",
    "sg:city":"Woodville",
    "sg:classifiers":[
        {
            "category":"Food & Beverages",
            "subcategory":"Groceries & Convenience Stores",
            "type":"Retail Goods"
        }
    ],
    "sg:phone":"+1 256 587 6050",
    "sg:postcode":"35776",
    "sg:province":"AL",
    "sg:tags":[
        "grocer"
    ],
    "wof:name":"Letcher Grocery",
    "wof:placetype":"venue"
},
  "geometry": {"coordinates":[-86.175701,34.748902],"type":"Point"}
}