{
  "type": "Feature",
  "properties": {
    "iso:country":"US",
    "sg:address":"1851 Montgomery Hwy",
    "sg:city":"Birmingham",
    "sg:classifiers":[
        {
            "category":"Restaurant",
            "type":"Food & Drink"
        }
    ],
    "sg:phone":"+1 205 987 1693",
    "sg:postcode":"35244",
    "sg:province":"AL",
    "sg:tags":[
        "cafeteria"
    ],
    "wof:name":"Piccadilly Cafeteria",
    "wof:placetype":"venue"
},
  "geometry": {"coordinates":[-86.795117,33.350835],"type":"Point"}
}