{
  "type": "Feature",
  "properties": {
    "addr:full":"419 S 5th St Gadsden AL 35901",
    "addr:housenumber":"419",
    "addr:postcode":"35901",
    "addr:street":"S 5Th St",
    "iso:country":"US",
    "sg:address":"419 S 5th St",
    "sg:city":"Gadsden",
    "sg:classifiers":[
        {
            "category":"Health Services",
            "subcategory":"Doctor",
            "type":"Services"
        }
    ],
    "sg:phone":"+1 256 547 6331",
    "sg:postcode":"35901",
    "sg:province":"AL",
    "sg:tags":[
        "medical"
    ],
    "wof:name":"Newman Charles L MD Facs",
    "wof:placetype":"venue"
},
  "geometry": {"coordinates":[-86.007446,34.007212],"type":"Point"}
}