{
  "type": "Feature",
  "properties": {
    "iso:country":"US",
    "sg:address":"133 N Emmett St",
    "sg:city":"Albertville",
    "sg:classifiers":[
        {
            "category":"Government",
            "subcategory":"Office",
            "type":"Public Place"
        }
    ],
    "sg:phone":"+1 256 878 8597",
    "sg:postcode":"35950",
    "sg:province":"AL",
    "wof:name":"Honorable Allen Timothy Jolley",
    "wof:placetype":"venue"
},
  "geometry": {"coordinates":[-86.209907,34.269086],"type":"Point"}
}