{
  "type": "Feature",
  "properties": {
    "iso:country":"US",
    "sg:address":"3450 Co Rd 388",
    "sg:city":"Valley",
    "sg:classifiers":[
        {
            "category":"Building & Trades",
            "subcategory":"Construction",
            "type":"Services"
        }
    ],
    "sg:phone":"+1 334 756 8486",
    "sg:postcode":"36854",
    "sg:province":"AL",
    "sg:tags":[
        "residential",
        "house"
    ],
    "wof:name":"Full Moon General Contracting",
    "wof:placetype":"venue"
},
  "geometry": {"coordinates":[-85.242315,32.749473],"type":"Point"}
}