{
  "type": "Feature",
  "properties": {
    "iso:country":"US",
    "sg:address":"118 Frazier St",
    "sg:city":"Brewton",
    "sg:classifiers":[
        {
            "category":"Manufacturing",
            "subcategory":"Tools & Machinery",
            "type":"Manufacturing & Wholesale Goods"
        },
        {
            "category":"Industrial Area",
            "type":"Public Place"
        }
    ],
    "sg:phone":"+1 251 809 8756",
    "sg:postcode":"36426",
    "sg:province":"AL",
    "sg:tags":[
        "repair",
        "equipment-repairing",
        "machinery-rebuild"
    ],
    "wof:name":"Dcl Machine Works",
    "wof:placetype":"venue"
},
  "geometry": {"coordinates":[-87.04693899999999,31.098697],"type":"Point"}
}