{
  "type": "Feature",
  "properties": {
    "iso:country":"US",
    "sg:address":"235 Edison St",
    "sg:city":"Dothan",
    "sg:classifiers":[
        {
            "category":"Manufacturing",
            "subcategory":"Glass & Minerals",
            "type":"Manufacturing & Wholesale Goods"
        }
    ],
    "sg:phone":"+1 334 792 1866",
    "sg:postcode":"36301",
    "sg:province":"AL",
    "sg:tags":[
        "fabricator",
        "fiber"
    ],
    "wof:name":"Replica Plastics",
    "wof:placetype":"venue"
},
  "geometry": {"coordinates":[-85.398626,31.222454],"type":"Point"}
}