{
  "type": "Feature",
  "properties": {
    "iso:country":"US",
    "sg:address":"3710 Mc Vay St SW",
    "sg:city":"Huntsville",
    "sg:classifiers":[
        {
            "category":"Building & Trades",
            "subcategory":"Cleaning & Sanitation",
            "type":"Services"
        }
    ],
    "sg:phone":"+1 256 534 3212",
    "sg:postcode":"35805",
    "sg:province":"AL",
    "sg:tags":[
        "maintenance"
    ],
    "wof:name":"Octane Janitorial Service",
    "wof:placetype":"venue"
},
  "geometry": {"coordinates":[-86.626053,34.70215],"type":"Point"}
}