{
  "type": "Feature",
  "properties": {
    "iso:country":"US",
    "sg:address":"601 Heflin Ave E",
    "sg:city":"Birmingham",
    "sg:classifiers":[
        {
            "category":"Organizations",
            "subcategory":"Religious Organization",
            "type":"Services"
        }
    ],
    "sg:phone":"+1 205 798 0037",
    "sg:postcode":"35214",
    "sg:province":"AL",
    "sg:tags":[
        "church"
    ],
    "wof:name":"Life Changers Christian Church",
    "wof:placetype":"venue"
},
  "geometry": {"coordinates":[-86.894054,33.5727],"type":"Point"}
}