{
  "type": "Feature",
  "properties": {
    "iso:country":"US",
    "sg:address":"213 Asphodel Dr",
    "sg:city":"Dothan",
    "sg:classifiers":[
        {
            "category":"Professional",
            "type":"Services"
        }
    ],
    "sg:phone":"+1 334 673 7495",
    "sg:postcode":"36303",
    "sg:province":"AL",
    "wof:name":"David A Hughes",
    "wof:placetype":"venue"
},
  "geometry": {"coordinates":[-85.493031,31.243266],"type":"Point"}
}