{
  "type": "Feature",
  "properties": {
    "addr:full":"2430 Corner Rd Warrior AL 35180",
    "addr:housenumber":"2430",
    "addr:postcode":"35180",
    "addr:street":"Corner Rd",
    "iso:country":"US",
    "sg:address":"2430 Corner Rd",
    "sg:city":"Warrior",
    "sg:classifiers":[
        {
            "category":"Food & Beverages",
            "subcategory":"Groceries & Convenience Stores",
            "type":"Retail Goods"
        }
    ],
    "sg:phone":"+1 205 647 2001",
    "sg:postcode":"35180",
    "sg:province":"AL",
    "wof:name":"Gilbert Convenience Store",
    "wof:placetype":"venue"
},
  "geometry": {"coordinates":[-86.916928,33.821816],"type":"Point"}
}