{
  "type": "Feature",
  "properties": {
    "iso:country":"US",
    "sg:address":"1615 Kathy Ln SW",
    "sg:city":"Decatur",
    "sg:classifiers":[
        {
            "category":"Health Services",
            "subcategory":"Doctor",
            "type":"Services"
        }
    ],
    "sg:phone":"+1 256 306 4154",
    "sg:postcode":"35603",
    "sg:province":"AL",
    "sg:tags":[
        "medical"
    ],
    "wof:name":"Hellard R Scott MD",
    "wof:placetype":"venue"
},
  "geometry": {"coordinates":[-87.02578200000001,34.582714],"type":"Point"}
}