{
  "type": "Feature",
  "properties": {
    "iso:country":"US",
    "sg:address":"6600 Woodmont Dr",
    "sg:city":"Tuscumbia",
    "sg:classifiers":[
        {
            "category":"Organizations",
            "subcategory":"Religious Organization",
            "type":"Services"
        }
    ],
    "sg:phone":"+1 256 381 4540",
    "sg:postcode":"35674",
    "sg:province":"AL",
    "sg:tags":[
        "church"
    ],
    "wof:name":"Colbert Heights Church Christ",
    "wof:placetype":"venue"
},
  "geometry": {"coordinates":[-87.700371,34.670728],"type":"Point"}
}