{
  "type": "Feature",
  "properties": {
    "iso:country":"US",
    "sg:address":"28 S Royal St",
    "sg:city":"Mobile",
    "sg:classifiers":[
        {
            "category":"Shopping",
            "subcategory":"Stationery & Office Supplies",
            "type":"Retail Goods"
        }
    ],
    "sg:phone":"+1 251 438 2851",
    "sg:postcode":"36602",
    "sg:province":"AL",
    "wof:name":"Olensky Brothers School House",
    "wof:placetype":"venue"
},
  "geometry": {"coordinates":[-88.040806,30.691817],"type":"Point"}
}