{
  "type": "Feature",
  "properties": {
    "iso:country":"US",
    "sg:address":"603 Alabama Ave N",
    "sg:city":"Fort Payne",
    "sg:classifiers":[
        {
            "category":"Building & Trades",
            "subcategory":"Landscaping Services",
            "type":"Services"
        }
    ],
    "sg:phone":"+1 256 845 6268",
    "sg:postcode":"35967",
    "sg:province":"AL",
    "sg:tags":[
        "landscape",
        "contractor"
    ],
    "wof:name":"Campbell's Yards & More",
    "wof:placetype":"venue"
},
  "geometry": {"coordinates":[-85.719419,34.447223],"type":"Point"}
}