{
  "type": "Feature",
  "properties": {
    "iso:country":"US",
    "sg:address":"209 W Sterret St",
    "sg:city":"Columbiana",
    "sg:classifiers":[
        {
            "category":"Building & Trades",
            "subcategory":"Construction",
            "type":"Services"
        }
    ],
    "sg:phone":"+1 205 669 2036",
    "sg:postcode":"35051",
    "sg:province":"AL",
    "sg:tags":[
        "contractor"
    ],
    "wof:name":"John Dudley Craftsman",
    "wof:placetype":"venue"
},
  "geometry": {"coordinates":[-86.60866,33.184276],"type":"Point"}
}