{
  "type": "Feature",
  "properties": {
    "addr:full":"326 Hoke St Gadsden AL 35903",
    "addr:housenumber":"326",
    "addr:postcode":"35903",
    "addr:street":"Hoke St",
    "iso:country":"US",
    "sg:address":"326 Hoke St",
    "sg:city":"Gadsden",
    "sg:classifiers":[
        {
            "category":"Manufacturing",
            "subcategory":"Printing",
            "type":"Manufacturing & Wholesale Goods"
        }
    ],
    "sg:phone":"+1 256 546 0111",
    "sg:postcode":"35903",
    "sg:province":"AL",
    "sg:tags":[
        "lithographic",
        "commercial",
        "typesetting"
    ],
    "wof:name":"Ridgeway Printing",
    "wof:placetype":"venue"
},
  "geometry": {"coordinates":[-85.97944099999999,34.002458],"type":"Point"}
}