{
  "type": "Feature",
  "properties": {
    "iso:country":"US",
    "sg:address":"326 Hoke St",
    "sg:city":"Gadsden",
    "sg:classifiers":[
        {
            "category":"Manufacturing",
            "subcategory":"Printing",
            "type":"Manufacturing & Wholesale Goods"
        }
    ],
    "sg:phone":"+1 256 546 0111",
    "sg:postcode":"35903",
    "sg:province":"AL",
    "sg:tags":[
        "lithographic",
        "commercial",
        "typesetting"
    ],
    "wof:name":"Ridgeway Printing",
    "wof:placetype":"venue"
},
  "geometry": {"coordinates":[-85.979441,34.002458],"type":"Point"}
}