{
  "type": "Feature",
  "properties": {
    "iso:country":"US",
    "sg:address":"335 Cogswell Ave",
    "sg:city":"Pell City",
    "sg:classifiers":[
        {
            "category":"Professional",
            "subcategory":"Management & Consulting",
            "type":"Services"
        }
    ],
    "sg:phone":"+1 205 814 1890",
    "sg:postcode":"35125",
    "sg:province":"AL",
    "sg:tags":[
        "employment",
        "screening"
    ],
    "wof:name":"W Harbison & Assoc",
    "wof:placetype":"venue"
},
  "geometry": {"coordinates":[-86.310634,33.588668],"type":"Point"}
}