{
  "type": "Feature",
  "properties": {
    "iso:country":"US",
    "sg:address":"1405 Hamric Dr E",
    "sg:city":"Oxford",
    "sg:classifiers":[
        {
            "category":"Restaurant",
            "type":"Food & Drink"
        }
    ],
    "sg:phone":"+1 256 835 0560",
    "sg:postcode":"36203",
    "sg:province":"AL",
    "sg:tags":[
        "eating",
        "caterer"
    ],
    "wof:name":"Alexander's The Great Events",
    "wof:placetype":"venue"
},
  "geometry": {"coordinates":[-85.811028,33.615003],"type":"Point"}
}