{
  "type": "Feature",
  "properties": {
    "addr:full":"1700 Oxmoor Rd Birmingham AL 35209",
    "addr:housenumber":"1700",
    "addr:postcode":"35209",
    "addr:street":"Oxmoor Rd",
    "iso:country":"US",
    "sg:address":"1700 Oxmoor Rd",
    "sg:city":"Birmingham",
    "sg:classifiers":[
        {
            "category":"Cafe",
            "type":"Food & Drink"
        }
    ],
    "sg:menulink":"http://www.allmenus.com/al/birmingham/53740-nabeels-cafe--market/menu/",
    "sg:phone":"+1 205 879 9292",
    "sg:postcode":"35209",
    "sg:province":"AL",
    "sg:tags":[
        "greek"
    ],
    "wof:name":"Nabeel's Cafe & Market",
    "wof:placetype":"venue"
},
  "geometry": {"coordinates":[-86.79733400000001,33.475348],"type":"Point"}
}