{
  "type": "Feature",
  "properties": {
    "iso:country":"US",
    "sg:address":"10288 Saint Alban Blvd SW",
    "sg:city":"Huntsville",
    "sg:classifiers":[
        {
            "category":"Farming",
            "subcategory":"Livestock Farm",
            "type":"Manufacturing & Wholesale Goods"
        }
    ],
    "sg:phone":"+1 256 881 8564",
    "sg:postcode":"35803",
    "sg:province":"AL",
    "sg:tags":[
        "beef",
        "feedlot",
        "cattle"
    ],
    "wof:name":"Scott Mobley",
    "wof:placetype":"venue"
},
  "geometry": {"coordinates":[-86.578824,34.6213],"type":"Point"}
}