{
  "type": "Feature",
  "properties": {
    "iso:country":"US",
    "sg:address":"1204 Island St",
    "sg:city":"Montevallo",
    "sg:classifiers":[
        {
            "category":"Real Estate",
            "subcategory":"Real Estate Agent",
            "type":"Services"
        }
    ],
    "sg:phone":"+1 205 665 7250",
    "sg:postcode":"35115",
    "sg:province":"AL",
    "sg:tags":[
        "authorities",
        "housing"
    ],
    "wof:name":"Montevallo Housing Authority",
    "wof:placetype":"venue"
},
  "geometry": {"coordinates":[-86.85818500000001,33.103536],"type":"Point"}
}