{
  "type": "Feature",
  "properties": {
    "iso:country":"US",
    "sg:address":"215 Ana Dr",
    "sg:city":"Florence",
    "sg:classifiers":[
        {
            "category":"Restaurant",
            "type":"Food & Drink"
        }
    ],
    "sg:phone":"+1 256 766 2036",
    "sg:postcode":"35630",
    "sg:province":"AL",
    "sg:tags":[
        "parlor",
        "eating",
        "ice",
        "cream"
    ],
    "wof:name":"TCBY",
    "wof:placetype":"venue"
},
  "geometry": {"coordinates":[-87.631229,34.831631],"type":"Point"}
}