{
  "type": "Feature",
  "properties": {
    "iso:country":"US",
    "sg:address":"935 Taylor Rd",
    "sg:city":"Tallassee",
    "sg:phone":"+1 334 283 6128",
    "sg:postcode":"36078",
    "sg:province":"AL",
    "sg:tags":[
        "farm",
        "cotton"
    ],
    "wof:name":"Daniel Taylor",
    "wof:placetype":"venue"
},
  "geometry": {"coordinates":[-85.91319300000001,32.463529],"type":"Point"}
}