{
  "type": "Feature",
  "properties": {
    "iso:country":"US",
    "sg:address":"1325 13th Ave E",
    "sg:city":"Tuscaloosa",
    "sg:classifiers":[
        {
            "category":"Professional",
            "type":"Services"
        }
    ],
    "sg:phone":"+1 205 554 0874",
    "sg:postcode":"35404",
    "sg:province":"AL",
    "sg:tags":[
        "establishment"
    ],
    "wof:name":"Elliott One",
    "wof:placetype":"venue"
},
  "geometry": {"coordinates":[-87.518704,33.199901],"type":"Point"}
}