{
  "type": "Feature",
  "properties": {
    "iso:country":"US",
    "sg:address":"950 Rainbow Dr",
    "sg:city":"Gadsden",
    "sg:classifiers":[
        {
            "category":"Social Services",
            "subcategory":"Child Care",
            "type":"Services"
        }
    ],
    "sg:phone":"+1 256 547 7729",
    "sg:postcode":"35901",
    "sg:province":"AL",
    "sg:tags":[
        "day"
    ],
    "wof:name":"C N I 46",
    "wof:placetype":"venue"
},
  "geometry": {"coordinates":[-86.00435400000001,33.998059],"type":"Point"}
}