{
  "type": "Feature",
  "properties": {
    "iso:country":"US",
    "sg:address":"1445 Old Lee Hwy",
    "sg:city":"Tuscumbia",
    "sg:classifiers":[
        {
            "category":"Home & Garden",
            "subcategory":"Building Materials",
            "type":"Retail Goods"
        }
    ],
    "sg:phone":"+1 256 383 6533",
    "sg:postcode":"35674",
    "sg:province":"AL",
    "sg:tags":[
        "planing",
        "mill",
        "lumber"
    ],
    "wof:name":"Walker Lumber Co Inc",
    "wof:placetype":"venue"
},
  "geometry": {"coordinates":[-87.737135,34.713685],"type":"Point"}
}