{
  "type": "Feature",
  "properties": {
    "iso:country":"US",
    "sg:address":"667 Saint Ives Rd",
    "sg:city":"Alpine",
    "sg:classifiers":[
        {
            "category":"Wholesale",
            "subcategory":"Petroleum",
            "type":"Manufacturing & Wholesale Goods"
        }
    ],
    "sg:phone":"+1 256 268 2623",
    "sg:postcode":"35014",
    "sg:province":"AL",
    "sg:tags":[
        "pipe",
        "line",
        "company"
    ],
    "wof:name":"Colonial Pipeline Co",
    "wof:placetype":"venue"
},
  "geometry": {"coordinates":[-86.251779,33.432567],"type":"Point"}
}