{
  "type": "Feature",
  "properties": {
    "addr:full":"2411 Whitesburg Dr S Huntsville AL 35801",
    "addr:housenumber":"2411",
    "addr:postcode":"35801",
    "addr:street":"Whitesburg Dr S",
    "iso:country":"US",
    "sg:address":"2411 Whitesburg Dr S",
    "sg:city":"Huntsville",
    "sg:classifiers":[
        {
            "category":"Professional",
            "subcategory":"Computer Services",
            "type":"Services"
        }
    ],
    "sg:phone":"+1 256 539 5265",
    "sg:postcode":"35801",
    "sg:province":"AL",
    "sg:tags":[
        "related"
    ],
    "wof:name":"Vesario",
    "wof:placetype":"venue"
},
  "geometry": {"coordinates":[-86.573206,34.710763],"type":"Point"}
}