{
  "type": "Feature",
  "properties": {
    "iso:country":"US",
    "sg:address":"2113 Old Monrovia Rd NW",
    "sg:city":"Huntsville",
    "sg:classifiers":[
        {
            "category":"Organizations",
            "subcategory":"Religious Organization",
            "type":"Services"
        }
    ],
    "sg:phone":"+1 256 430 0003",
    "sg:postcode":"35806",
    "sg:province":"AL",
    "sg:tags":[
        "methodist",
        "church"
    ],
    "sg:website":"www.graceumchsv.org",
    "wof:name":"Grace United Methodist Church",
    "wof:placetype":"venue"
},
  "geometry": {"coordinates":[-86.695877,34.763132],"type":"Point"}
}