{
  "type": "Feature",
  "properties": {
    "iso:country":"US",
    "sg:address":"920 US Hwy 72 E",
    "sg:city":"Athens",
    "sg:classifiers":[
        {
            "category":"Banks & Credit Unions",
            "subcategory":"Bank",
            "type":"Services"
        }
    ],
    "sg:phone":"+1 256 233 1381",
    "sg:postcode":"35611",
    "sg:province":"AL",
    "sg:tags":[
        "financing"
    ],
    "wof:name":"First Community Credit Corp",
    "wof:placetype":"venue"
},
  "geometry": {"coordinates":[-86.963128,34.788114],"type":"Point"}
}