{
  "type": "Feature",
  "properties": {
    "iso:country":"US",
    "sg:address":"18701 US Hwy 98",
    "sg:city":"Fairhope",
    "sg:classifiers":[
        {
            "category":"Social Services",
            "subcategory":"Child Care",
            "type":"Services"
        }
    ],
    "sg:phone":"+1 251 928 1662",
    "sg:postcode":"36532",
    "sg:province":"AL",
    "wof:name":"LA Casa De Amigos",
    "wof:placetype":"venue"
},
  "geometry": {"coordinates":[-87.886331,30.497102],"type":"Point"}
}