{
  "type": "Feature",
  "properties": {
    "addr:full":"660 Middle St Montevallo AL 35115",
    "addr:housenumber":"660",
    "addr:postcode":"35115",
    "addr:street":"Middle St",
    "iso:country":"US",
    "sg:address":"660 Middle St",
    "sg:city":"Montevallo",
    "sg:classifiers":[
        {
            "category":"Shopping",
            "subcategory":"Pharmacy",
            "type":"Retail Goods"
        }
    ],
    "sg:phone":"+1 205 665 1261",
    "sg:postcode":"35115",
    "sg:province":"AL",
    "sg:tags":[
        "drug",
        "store"
    ],
    "wof:name":"Montevallo Drug Co",
    "wof:placetype":"venue"
},
  "geometry": {"coordinates":[-86.86255300000001,33.099867],"type":"Point"}
}