{
  "type": "Feature",
  "properties": {
    "iso:country":"US",
    "sg:address":"103 Wickham Rd",
    "sg:city":"Madison",
    "sg:classifiers":[
        {
            "category":"Professional",
            "type":"Services"
        }
    ],
    "sg:phone":"+1 256 890 0530",
    "sg:postcode":"35757",
    "sg:province":"AL",
    "wof:name":"GNA Inc",
    "wof:placetype":"venue"
},
  "geometry": {"coordinates":[-86.73102299999999,34.820262],"type":"Point"}
}