{
  "type": "Feature",
  "properties": {
    "iso:country":"US",
    "sg:address":"3129 Cobblestone Dr",
    "sg:city":"Birmingham",
    "sg:classifiers":[
        {
            "category":"Shopping",
            "subcategory":"Gifts & Souvenirs",
            "type":"Retail Goods"
        }
    ],
    "sg:phone":"+1 205 681 2615",
    "sg:postcode":"35215",
    "sg:province":"AL",
    "wof:name":"Sheilas Gift Baskets",
    "wof:placetype":"venue"
},
  "geometry": {"coordinates":[-86.671475,33.675271],"type":"Point"}
}