{
  "type": "Feature",
  "properties": {
    "iso:country":"US",
    "sg:address":"900 Skyland Blvd E",
    "sg:city":"Tuscaloosa",
    "sg:classifiers":[
        {
            "category":"Recreation",
            "subcategory":"Arcade",
            "type":"Entertainment"
        }
    ],
    "sg:phone":"+1 205 345 1994",
    "sg:postcode":"35405",
    "sg:province":"AL",
    "sg:tags":[
        "video"
    ],
    "wof:name":"Diamond Jims",
    "wof:placetype":"venue"
},
  "geometry": {"coordinates":[-87.52233099999999,33.168237],"type":"Point"}
}