{
  "type": "Feature",
  "properties": {
    "addr:full":"100 Argyle Ct Gadsden AL 35904",
    "addr:housenumber":"100",
    "addr:postcode":"35904",
    "addr:street":"Argyle Ct",
    "iso:country":"US",
    "sg:address":"100 Argyle Ct",
    "sg:city":"Gadsden",
    "sg:classifiers":[
        {
            "category":"Professional",
            "subcategory":"Accounting & Tax Preparation",
            "type":"Services"
        }
    ],
    "sg:phone":"+1 256 547 6558",
    "sg:postcode":"35904",
    "sg:province":"AL",
    "sg:tags":[
        "bookkeeping",
        "general"
    ],
    "wof:name":"Total Accounting",
    "wof:placetype":"venue"
},
  "geometry": {"coordinates":[-86.01736699999999,34.050523],"type":"Point"}
}