{
  "type": "Feature",
  "properties": {
    "iso:country":"US",
    "sg:address":"3167 Dauphin St",
    "sg:city":"Mobile",
    "sg:classifiers":[
        {
            "category":"Health Services",
            "subcategory":"Optometrist",
            "type":"Services"
        }
    ],
    "sg:phone":"+1 251 476 0100",
    "sg:postcode":"36606",
    "sg:province":"AL",
    "wof:name":"Clardy Contact Lens Center",
    "wof:placetype":"venue"
},
  "geometry": {"coordinates":[-88.11790000000001,30.689569],"type":"Point"}
}