{
  "type": "Feature",
  "properties": {
    "addr:full":"11803 US Hwy 431 Ohatchee AL 36271",
    "addr:housenumber":"11803",
    "addr:postcode":"36271",
    "addr:street":"Us Hwy 431 Ohatchee",
    "iso:country":"US",
    "sg:address":"11803 US Hwy 431",
    "sg:city":"Ohatchee",
    "sg:classifiers":[
        {
            "category":"Building & Trades",
            "subcategory":"Plumbing",
            "type":"Services"
        }
    ],
    "sg:phone":"+1 256 892 3905",
    "sg:postcode":"36271",
    "sg:province":"AL",
    "sg:tags":[
        "plumbing",
        "contractor"
    ],
    "wof:name":"Sterling Plumbing LLC",
    "wof:placetype":"venue"
},
  "geometry": {"coordinates":[-85.915702,33.841398],"type":"Point"}
}