{
  "type": "Feature",
  "properties": {
    "iso:country":"US",
    "sg:address":"670 Creek Haven Rd",
    "sg:city":"Rainbow City",
    "sg:classifiers":[
        {
            "category":"Professional",
            "type":"Services"
        }
    ],
    "sg:phone":"+1 256 413 1920",
    "sg:postcode":"35906",
    "sg:province":"AL",
    "wof:name":"Michael Overby",
    "wof:placetype":"venue"
},
  "geometry": {"coordinates":[-86.105556,33.884374],"type":"Point"}
}