{
  "type": "Feature",
  "properties": {
    "iso:country":"US",
    "sg:address":"8884 Madison Blvd",
    "sg:city":"Madison",
    "sg:classifiers":[
        {
            "category":"Retail",
            "subcategory":"Auto Rental",
            "type":"Services"
        }
    ],
    "sg:phone":"+1 256 772 3176",
    "sg:postcode":"35758",
    "sg:province":"AL",
    "sg:tags":[
        "passenger",
        "car"
    ],
    "wof:name":"AMERICAR RENTAL SYSTEM",
    "wof:placetype":"venue"
},
  "geometry": {"coordinates":[-86.747208,34.678582],"type":"Point"}
}