{
  "type": "Feature",
  "properties": {
    "iso:country":"US",
    "sg:address":"4716 7th Ave S",
    "sg:city":"Birmingham",
    "sg:classifiers":[
        {
            "category":"Organizations",
            "subcategory":"Religious Organization",
            "type":"Services"
        }
    ],
    "sg:phone":"+1 205 592 9695",
    "sg:postcode":"35222",
    "sg:province":"AL",
    "wof:name":"Avondale Presbyterian Church",
    "wof:placetype":"venue"
},
  "geometry": {"coordinates":[-86.761404,33.524801],"type":"Point"}
}