{
  "type": "Feature",
  "properties": {
    "addr:full":"6880 Winton Blount Blvd Montgomery AL 36117",
    "addr:housenumber":"6880",
    "addr:postcode":"36117",
    "addr:street":"Winton Blount Blvd",
    "iso:country":"US",
    "sg:address":"6880 Winton Blount Blvd",
    "sg:city":"Montgomery",
    "sg:classifiers":[
        {
            "category":"Health Services",
            "subcategory":"Doctor",
            "type":"Services"
        }
    ],
    "sg:phone":"+1 334 270 5980",
    "sg:postcode":"36117",
    "sg:province":"AL",
    "sg:tags":[
        "dr"
    ],
    "wof:name":"Neurosrgery Assocs Cntl Ala PC",
    "wof:placetype":"venue"
},
  "geometry": {"coordinates":[-86.175427,32.377893],"type":"Point"}
}