{
  "type": "Feature",
  "properties": {
    "iso:country":"US",
    "sg:address":"15446 Shelby St",
    "sg:city":"Harvest",
    "sg:classifiers":[
        {
            "category":"Professional",
            "subcategory":"Computer Services",
            "type":"Services"
        }
    ],
    "sg:phone":"+1 256 232 8876",
    "sg:postcode":"35749",
    "sg:province":"AL",
    "sg:tags":[
        "prepackaged",
        "software",
        "custom"
    ],
    "wof:name":"Trent Systems",
    "wof:placetype":"venue"
},
  "geometry": {"coordinates":[-86.82962,34.779748],"type":"Point"}
}