{
  "type": "Feature",
  "properties": {
    "iso:country":"US",
    "sg:address":"3100 Highland Ave S",
    "sg:city":"Birmingham",
    "sg:classifiers":[
        {
            "category":"Organizations",
            "subcategory":"Religious Organization",
            "type":"Services"
        }
    ],
    "sg:phone":"+1 205 933 1830",
    "sg:postcode":"35205",
    "sg:province":"AL",
    "sg:tags":[
        "presbyterian",
        "church",
        "school",
        "day"
    ],
    "wof:name":"Childrens Fresh Air Farm",
    "wof:placetype":"venue"
},
  "geometry": {"coordinates":[-86.779124,33.508173],"type":"Point"}
}