{
  "type": "Feature",
  "properties": {
    "iso:country":"US",
    "sg:address":"2749 Moore Rd",
    "sg:city":"Adamsville",
    "sg:classifiers":[
        {
            "category":"Organizations",
            "subcategory":"Religious Organization",
            "type":"Services"
        }
    ],
    "sg:phone":"+1 205 674 7022",
    "sg:postcode":"35005",
    "sg:province":"AL",
    "wof:name":"Shady Grove Freewill",
    "wof:placetype":"venue"
},
  "geometry": {"coordinates":[-87.000423,33.58769],"type":"Point"}
}