{
  "type": "Feature",
  "properties": {
    "iso:country":"US",
    "sg:address":"3400 Meador Dr",
    "sg:city":"Mobile",
    "sg:classifiers":[
        {
            "category":"Manufacturing",
            "subcategory":"Tools & Machinery",
            "type":"Manufacturing & Wholesale Goods"
        }
    ],
    "sg:phone":"+1 251 479 5121",
    "sg:postcode":"36607",
    "sg:province":"AL",
    "sg:tags":[
        "pump"
    ],
    "sg:website":"www.johnstonpump.com",
    "wof:name":"Johnston Pump Co",
    "wof:placetype":"venue"
},
  "geometry": {"coordinates":[-88.119532,30.71088],"type":"Point"}
}