{
  "type": "Feature",
  "properties": {
    "iso:country":"US",
    "sg:address":"910 Adams St SE",
    "sg:city":"Huntsville",
    "sg:classifiers":[
        {
            "category":"Health Services",
            "subcategory":"Doctor",
            "type":"Services"
        }
    ],
    "sg:phone":"+1 256 533 7420",
    "sg:postcode":"35801",
    "sg:province":"AL",
    "sg:tags":[
        "physician",
        "surgeon",
        "surgeons",
        "obstetrics"
    ],
    "wof:name":"Clinic For Women",
    "wof:placetype":"venue"
},
  "geometry": {"coordinates":[-86.574231,34.721729],"type":"Point"}
}