{
  "type": "Feature",
  "properties": {
    "addr:full":"3405 Caffey Dr Montgomery AL 36108",
    "addr:housenumber":"3405",
    "addr:postcode":"36108",
    "addr:street":"Caffey Dr",
    "iso:country":"US",
    "sg:address":"3405 Caffey Dr",
    "sg:city":"Montgomery",
    "sg:classifiers":[
        {
            "category":"Retail",
            "subcategory":"Auto Repair",
            "type":"Services"
        }
    ],
    "sg:phone":"+1 334 288 0407",
    "sg:postcode":"36108",
    "sg:province":"AL",
    "sg:tags":[
        "automotive"
    ],
    "wof:name":"Joann Westery Auto",
    "wof:placetype":"venue"
},
  "geometry": {"coordinates":[-86.33692000000001,32.342955],"type":"Point"}
}