{
  "type": "Feature",
  "properties": {
    "iso:country":"US",
    "sg:address":"2009 Gallatin St SW",
    "sg:city":"Huntsville",
    "sg:classifiers":[
        {
            "category":"Professional",
            "subcategory":"Accounting & Tax Preparation",
            "type":"Services"
        }
    ],
    "sg:phone":"+1 256 533 7064",
    "sg:postcode":"35801",
    "sg:province":"AL",
    "sg:tags":[
        "billing"
    ],
    "wof:name":"Physician Management Co LLC",
    "wof:placetype":"venue"
},
  "geometry": {"coordinates":[-86.580966,34.719381],"type":"Point"}
}