{
  "type": "Feature",
  "properties": {
    "iso:country":"US",
    "sg:address":"330 Park Ave",
    "sg:city":"Mobile",
    "sg:classifiers":[
        {
            "category":"Home & Garden",
            "subcategory":"Hardware",
            "type":"Retail Goods"
        }
    ],
    "sg:phone":"+1 251 340 0958",
    "sg:postcode":"36695",
    "sg:province":"AL",
    "sg:tags":[
        "house",
        "construction"
    ],
    "wof:name":"Southern Brass",
    "wof:placetype":"venue"
},
  "geometry": {"coordinates":[-88.208388,30.679909],"type":"Point"}
}