{
  "type": "Feature",
  "properties": {
    "addr:full":"2800 Cahaba Rd Birmingham AL 35223",
    "addr:housenumber":"2800",
    "addr:postcode":"35223",
    "addr:street":"Cahaba Rd",
    "iso:country":"US",
    "sg:address":"2800 Cahaba Rd",
    "sg:city":"Birmingham",
    "sg:classifiers":[
        {
            "category":"Shopping",
            "subcategory":"Jewelry",
            "type":"Retail Goods"
        }
    ],
    "sg:phone":"+1 205 871 3276",
    "sg:postcode":"35223",
    "sg:province":"AL",
    "sg:tags":[
        "jeweler"
    ],
    "wof:name":"Bromberg & Company Inc",
    "wof:placetype":"venue"
},
  "geometry": {"coordinates":[-86.77371599999999,33.483947],"type":"Point"}
}