{
  "type": "Feature",
  "properties": {
    "iso:country":"US",
    "sg:address":"193 Cahaba Valley Pkwy",
    "sg:city":"Pelham",
    "sg:classifiers":[
        {
            "category":"Building & Trades",
            "subcategory":"Construction",
            "type":"Services"
        }
    ],
    "sg:phone":"+1 205 985 7378",
    "sg:postcode":"35124",
    "sg:province":"AL",
    "sg:tags":[
        "general",
        "contractor"
    ],
    "wof:name":"D L Acton Construction Co",
    "wof:placetype":"venue"
},
  "geometry": {"coordinates":[-86.785848,33.342549],"type":"Point"}
}