{
  "type": "Feature",
  "properties": {
    "iso:country":"US",
    "sg:address":"424 Cahaba Park Cir",
    "sg:city":"Birmingham",
    "sg:classifiers":[
        {
            "category":"Restaurant",
            "type":"Food & Drink"
        }
    ],
    "sg:menulink":"http://www.allmenus.com/al/chelsea/55593-subway/menu/",
    "sg:phone":"+1 205 995 5665",
    "sg:postcode":"35242",
    "sg:province":"AL",
    "sg:tags":[
        "american",
        "sandwich"
    ],
    "wof:name":"Subway",
    "wof:placetype":"venue"
},
  "geometry": {"coordinates":[-86.70595299999999,33.429808],"type":"Point"}
}