{
  "type": "Feature",
  "properties": {
    "iso:country":"US",
    "sg:address":"16800 Nelson Ln",
    "sg:city":"Gulf Shores",
    "sg:classifiers":[
        {
            "category":"Retail",
            "subcategory":"Repair Shop",
            "type":"Services"
        }
    ],
    "sg:phone":"+1 251 968 7974",
    "sg:postcode":"36542",
    "sg:province":"AL",
    "wof:name":"Nelson Boat Yard Inc",
    "wof:placetype":"venue"
},
  "geometry": {"coordinates":[-87.73722,30.289969],"type":"Point"}
}