{
  "type": "Feature",
  "properties": {
    "addr:full":"118 Washington St Selma AL 36703",
    "addr:housenumber":"118",
    "addr:postcode":"36703",
    "addr:street":"Washington St",
    "iso:country":"US",
    "sg:address":"118 Washington St",
    "sg:city":"Selma",
    "sg:classifiers":[
        {
            "category":"Restaurant",
            "type":"Food & Drink"
        }
    ],
    "sg:phone":"+1 334 875 8800",
    "sg:postcode":"36703",
    "sg:province":"AL",
    "sg:tags":[
        "eating"
    ],
    "wof:name":"Strong's No 2 Real Soul Food",
    "wof:placetype":"venue"
},
  "geometry": {"coordinates":[-87.019589,32.409397],"type":"Point"}
}