{
  "type": "Feature",
  "properties": {
    "iso:country":"US",
    "sg:address":"316 Greenbrier Dear Rd",
    "sg:city":"Anniston",
    "sg:classifiers":[
        {
            "category":"Home & Garden",
            "subcategory":"Building Materials",
            "type":"Retail Goods"
        },
        {
            "category":"Autos & Motor Vehicles",
            "subcategory":"Auto Supplies",
            "type":"Retail Goods"
        }
    ],
    "sg:phone":"+1 256 237 8521",
    "sg:postcode":"36207",
    "sg:province":"AL",
    "sg:tags":[
        "body",
        "plate",
        "window",
        "replacement",
        "glass"
    ],
    "wof:name":"Anniston Auto Trim & Glass Inc",
    "wof:placetype":"venue"
},
  "geometry": {"coordinates":[-85.82290999999999,33.637281],"type":"Point"}
}