{
  "type": "Feature",
  "properties": {
    "iso:country":"US",
    "sg:address":"1712 Rucker Blvd",
    "sg:city":"Enterprise",
    "sg:classifiers":[
        {
            "category":"Building & Trades",
            "subcategory":"Construction",
            "type":"Services"
        }
    ],
    "sg:phone":"+1 334 393 0662",
    "sg:postcode":"36330",
    "sg:province":"AL",
    "sg:tags":[
        "home",
        "builder"
    ],
    "wof:name":"Enterprise Joint Alabama",
    "wof:placetype":"venue"
},
  "geometry": {"coordinates":[-85.80318,31.332117],"type":"Point"}
}