{
  "type": "Feature",
  "properties": {
    "iso:country":"US",
    "sg:address":"4340 Vanderbilt Rd",
    "sg:city":"Birmingham",
    "sg:classifiers":[
        {
            "category":"Personal",
            "subcategory":"Beauty Salon",
            "type":"Services"
        }
    ],
    "sg:phone":"+1 205 849 6222",
    "sg:postcode":"35217",
    "sg:province":"AL",
    "wof:name":"Kreative Stylz",
    "wof:placetype":"venue"
},
  "geometry": {"coordinates":[-86.78349,33.56662],"type":"Point"}
}