{
  "type": "Feature",
  "properties": {
    "addr:full":"1711 4th Ave N Birmingham AL 35203",
    "addr:housenumber":"1711",
    "addr:postcode":"35203",
    "addr:street":"4Th Ave N",
    "iso:country":"US",
    "sg:address":"1711 4th Ave N",
    "sg:city":"Birmingham",
    "sg:classifiers":[
        {
            "category":"Personal",
            "subcategory":"Barber",
            "type":"Services"
        }
    ],
    "sg:phone":"+1 205 254 9038",
    "sg:postcode":"35203",
    "sg:province":"AL",
    "sg:tags":[
        "shop"
    ],
    "wof:name":"Magic City Barber Shop",
    "wof:placetype":"venue"
},
  "geometry": {"coordinates":[-86.810474,33.515714],"type":"Point"}
}