{
  "type": "Feature",
  "properties": {
    "iso:country":"US",
    "sg:address":"4204 Taylor Rd",
    "sg:city":"Dothan",
    "sg:classifiers":[
        {
            "category":"Retail",
            "subcategory":"Repair Shop",
            "type":"Services"
        }
    ],
    "sg:phone":"+1 334 792 0827",
    "sg:postcode":"36301",
    "sg:province":"AL",
    "sg:tags":[
        "upholsterer"
    ],
    "wof:name":"Dewey's Upholstery",
    "wof:placetype":"venue"
},
  "geometry": {"coordinates":[-85.462389,31.168647],"type":"Point"}
}