{
  "type": "Feature",
  "properties": {
    "iso:country":"US",
    "sg:address":"1504 Lafayette Pkwy",
    "sg:city":"Opelika",
    "sg:classifiers":[
        {
            "category":"Shopping",
            "type":"Retail Goods"
        }
    ],
    "sg:phone":"+1 334 845 9888",
    "sg:postcode":"36801",
    "sg:province":"AL",
    "sg:tags":[
        "telephone",
        "cellular"
    ],
    "wof:name":"Advantage Wireless",
    "wof:placetype":"venue"
},
  "geometry": {"coordinates":[-85.366727,32.665468],"type":"Point"}
}