{
  "type": "Feature",
  "properties": {
    "iso:country":"US",
    "sg:address":"601 State St",
    "sg:city":"Mobile",
    "sg:classifiers":[
        {
            "category":"Organizations",
            "subcategory":"Community Association",
            "type":"Services"
        }
    ],
    "sg:phone":"+1 251 432 8979",
    "sg:postcode":"36603",
    "sg:province":"AL",
    "wof:name":"Elks Club Number 244",
    "wof:placetype":"venue"
},
  "geometry": {"coordinates":[-88.052189,30.692912],"type":"Point"}
}