{
  "type": "Feature",
  "properties": {
    "addr:full":"250 Green Springs Hwy Homewood AL 35209",
    "addr:housenumber":"250",
    "addr:postcode":"35209",
    "addr:street":"Green Springs Hwy",
    "iso:country":"US",
    "sg:address":"250 Green Springs Hwy",
    "sg:city":"Homewood",
    "sg:classifiers":[
        {
            "category":"Restaurant",
            "type":"Food & Drink"
        }
    ],
    "sg:phone":"+1 205 942 8040",
    "sg:postcode":"35209",
    "sg:province":"AL",
    "wof:name":"Blimpie Subs & Salads",
    "wof:placetype":"venue"
},
  "geometry": {"coordinates":[-86.821563,33.465792],"type":"Point"}
}