{
  "type": "Feature",
  "properties": {
    "iso:country":"US",
    "sg:address":"25065 US Hwy 72",
    "sg:city":"Athens",
    "sg:classifiers":[
        {
            "category":"Building & Trades",
            "subcategory":"Construction",
            "type":"Services"
        }
    ],
    "sg:phone":"+1 256 232 4144",
    "sg:postcode":"35613",
    "sg:province":"AL",
    "sg:tags":[
        "business",
        "contractor"
    ],
    "wof:name":"Cal-Wal Pool Plastering Inc",
    "wof:placetype":"venue"
},
  "geometry": {"coordinates":[-86.893344,34.767025],"type":"Point"}
}