{
  "type": "Feature",
  "properties": {
    "iso:country":"US",
    "sg:address":"704 E Academy St",
    "sg:city":"Troy",
    "sg:classifiers":[
        {
            "category":"Personal",
            "subcategory":"Beauty Salon",
            "type":"Services"
        }
    ],
    "sg:phone":"+1 334 566 2539",
    "sg:postcode":"36081",
    "sg:province":"AL",
    "sg:tags":[
        "shop"
    ],
    "wof:name":"Pearl's Wig & Beauty Salon",
    "wof:placetype":"venue"
},
  "geometry": {"coordinates":[-85.965103,31.809163],"type":"Point"}
}