{
  "type": "Feature",
  "properties": {
    "iso:country":"US",
    "sg:address":"416 3rd Ave SE",
    "sg:city":"Cullman",
    "sg:classifiers":[
        {
            "category":"Professional",
            "subcategory":"Management & Consulting",
            "type":"Services"
        }
    ],
    "sg:phone":"+1 256 737 0002",
    "sg:postcode":"35055",
    "sg:province":"AL",
    "wof:name":"People Shop",
    "wof:placetype":"venue"
},
  "geometry": {"coordinates":[-86.839017,34.175337],"type":"Point"}
}