{
  "type": "Feature",
  "properties": {
    "addr:full":"724 Skyland Blvd Tuscaloosa AL 35405",
    "addr:housenumber":"724",
    "addr:postcode":"35405",
    "addr:street":"Skyland Blvd",
    "iso:country":"US",
    "sg:address":"724 Skyland Blvd",
    "sg:city":"Tuscaloosa",
    "sg:classifiers":[
        {
            "category":"Restaurant",
            "type":"Food & Drink"
        }
    ],
    "sg:menulink":"http://www.allmenus.com/al/tuscaloosa/96856-ihop/menu/",
    "sg:phone":"+1 205 366 1130",
    "sg:postcode":"35405",
    "sg:province":"AL",
    "sg:tags":[
        "sandwich",
        "salad",
        "burger",
        "soup",
        "american",
        "steakhouse",
        "wrap"
    ],
    "wof:name":"IHOP",
    "wof:placetype":"venue"
},
  "geometry": {"coordinates":[-87.547105,33.165307],"type":"Point"}
}