{
  "type": "Feature",
  "properties": {
    "addr:full":"988 Ingate Pass Brent AL 35034",
    "addr:housenumber":"988",
    "addr:postcode":"35034",
    "addr:street":"Ingate Pass",
    "iso:country":"US",
    "sg:address":"988 Ingate Pass",
    "sg:city":"Brent",
    "sg:classifiers":[
        {
            "category":"Building & Trades",
            "subcategory":"Construction",
            "type":"Services"
        }
    ],
    "sg:phone":"+1 205 225 0898",
    "sg:postcode":"35034",
    "sg:province":"AL",
    "sg:tags":[
        "house"
    ],
    "wof:name":"Anderson Construction Co",
    "wof:placetype":"venue"
},
  "geometry": {"coordinates":[-87.22407699999999,32.945442],"type":"Point"}
}