{
  "type": "Feature",
  "properties": {
    "iso:country":"US",
    "sg:address":"750 Dr Martin L King Jr Ave",
    "sg:city":"Mobile",
    "sg:classifiers":[
        {
            "category":"Organizations",
            "subcategory":"Religious Organization",
            "type":"Services"
        }
    ],
    "sg:phone":"+1 251 432 8858",
    "sg:postcode":"36603",
    "sg:province":"AL",
    "wof:name":"Metropolitan Afrcn Mthds Epscl",
    "wof:placetype":"venue"
},
  "geometry": {"coordinates":[-88.055427,30.696645],"type":"Point"}
}