{
  "type": "Feature",
  "properties": {
    "iso:country":"US",
    "sg:address":"2808 Lark Ln",
    "sg:city":"Oxford",
    "sg:classifiers":[
        {
            "category":"Retail",
            "subcategory":"Repair Shop",
            "type":"Services"
        },
        {
            "category":"Shopping",
            "subcategory":"Bicycles & Sporting Goods",
            "type":"Retail Goods"
        }
    ],
    "sg:phone":"+1 256 835 6671",
    "sg:postcode":"36203",
    "sg:province":"AL",
    "sg:tags":[
        "gun",
        "gunsmith"
    ],
    "wof:name":"Marshall's Gunsmithing",
    "wof:placetype":"venue"
},
  "geometry": {"coordinates":[-85.809371,33.58074],"type":"Point"}
}