{
  "type": "Feature",
  "properties": {
    "iso:country":"US",
    "sg:address":"7650 Natchez Trce Lp",
    "sg:city":"Wilmer",
    "sg:classifiers":[
        {
            "category":"Wholesale",
            "subcategory":"Construction Materials",
            "type":"Manufacturing & Wholesale Goods"
        }
    ],
    "sg:phone":"+1 251 645 2309",
    "sg:postcode":"36587",
    "sg:province":"AL",
    "sg:tags":[
        "sand",
        "gravel"
    ],
    "wof:name":"Jackson Creek Sand",
    "wof:placetype":"venue"
},
  "geometry": {"coordinates":[-88.327683,30.855912],"type":"Point"}
}