{
  "type": "Feature",
  "properties": {
    "iso:country":"US",
    "sg:address":"65 Main St W",
    "sg:city":"Rainsville",
    "sg:classifiers":[
        {
            "category":"Professional",
            "subcategory":"Lawyer & Legal Services",
            "type":"Services"
        }
    ],
    "sg:phone":"+1 256 638 1986",
    "sg:postcode":"35986",
    "sg:province":"AL",
    "sg:tags":[
        "attorney"
    ],
    "wof:name":"Baugh & Whitmire",
    "wof:placetype":"venue"
},
  "geometry": {"coordinates":[-85.84898699999999,34.494861],"type":"Point"}
}