{
  "type": "Feature",
  "properties": {
    "iso:country":"US",
    "sg:address":"8419 1st Ave N",
    "sg:city":"Birmingham",
    "sg:classifiers":[
        {
            "category":"Government",
            "subcategory":"Office",
            "type":"Public Place"
        }
    ],
    "sg:phone":"+1 205 836 6456",
    "sg:postcode":"35206",
    "sg:province":"AL",
    "sg:tags":[
        "city",
        "program"
    ],
    "wof:name":"Birmingham Street & Sanitation",
    "wof:placetype":"venue"
},
  "geometry": {"coordinates":[-86.720704,33.573972],"type":"Point"}
}