{
  "type": "Feature",
  "properties": {
    "iso:country":"US",
    "sg:address":"415 N East St",
    "sg:city":"Talladega",
    "sg:classifiers":[
        {
            "category":"Retail",
            "subcategory":"Auto Repair",
            "type":"Services"
        }
    ],
    "sg:phone":"+1 256 761 9100",
    "sg:postcode":"35160",
    "sg:province":"AL",
    "sg:tags":[
        "body",
        "automobile",
        "painting"
    ],
    "wof:name":"Pate's Collision Inc",
    "wof:placetype":"venue"
},
  "geometry": {"coordinates":[-86.10413,33.442956],"type":"Point"}
}