{
  "type": "Feature",
  "properties": {
    "iso:country":"US",
    "sg:address":"11007 Vivian Dr NW",
    "sg:city":"Huntsville",
    "sg:classifiers":[
        {
            "category":"Professional",
            "subcategory":"Computer Services",
            "type":"Services"
        }
    ],
    "sg:phone":"+1 256 859 1620",
    "sg:postcode":"35810",
    "sg:province":"AL",
    "sg:tags":[
        "consultant",
        "engineering",
        "system"
    ],
    "wof:name":"Eagleridge Technologies Inc",
    "wof:placetype":"venue"
},
  "geometry": {"coordinates":[-86.578073,34.810094],"type":"Point"}
}