{
  "type": "Feature",
  "properties": {
    "iso:country":"US",
    "sg:address":"2220 4th Ave",
    "sg:city":"Phenix City",
    "sg:classifiers":[
        {
            "category":"Food & Beverages",
            "subcategory":"Groceries & Convenience Stores",
            "type":"Retail Goods"
        }
    ],
    "sg:phone":"+1 334 297 3322",
    "sg:postcode":"36867",
    "sg:province":"AL",
    "wof:name":"Bizzy Bee Mart 3",
    "wof:placetype":"venue"
},
  "geometry": {"coordinates":[-84.998857,32.482875],"type":"Point"}
}