{
  "type": "Feature",
  "properties": {
    "addr:full":"1930 Gadsden Hwy Birmingham AL 35235",
    "addr:housenumber":"1930",
    "addr:postcode":"35235",
    "addr:street":"Gadsden Hwy",
    "iso:country":"US",
    "sg:address":"1930 Gadsden Hwy",
    "sg:city":"Birmingham",
    "sg:classifiers":[
        {
            "category":"Retail",
            "subcategory":"Storage",
            "type":"Services"
        }
    ],
    "sg:phone":"+1 205 655 1115",
    "sg:postcode":"35235",
    "sg:province":"AL",
    "sg:tags":[
        "self"
    ],
    "wof:name":"Metro Truck Rental",
    "wof:placetype":"venue"
},
  "geometry": {"coordinates":[-86.62779999999999,33.608898],"type":"Point"}
}