{
  "type": "Feature",
  "properties": {
    "iso:country":"US",
    "sg:address":"501 Lawrence St E",
    "sg:city":"Russellville",
    "sg:classifiers":[
        {
            "category":"Organizations",
            "subcategory":"Religious Organization",
            "type":"Services"
        }
    ],
    "sg:phone":"+1 256 331 0044",
    "sg:postcode":"35653",
    "sg:province":"AL",
    "sg:tags":[
        "church"
    ],
    "wof:name":"Grace Baptist Church",
    "wof:placetype":"venue"
},
  "geometry": {"coordinates":[-87.72546699999999,34.50305],"type":"Point"}
}