{
  "type": "Feature",
  "properties": {
    "iso:country":"US",
    "sg:address":"2325 Pansy St SW",
    "sg:city":"Huntsville",
    "sg:classifiers":[
        {
            "category":"Health Services",
            "subcategory":"Doctor",
            "type":"Services"
        }
    ],
    "sg:phone":"+1 256 534 2429",
    "sg:postcode":"35801",
    "sg:province":"AL",
    "sg:tags":[
        "medical"
    ],
    "wof:name":"Diplacido Bruce M MD",
    "wof:placetype":"venue"
},
  "geometry": {"coordinates":[-86.57748599999999,34.71414],"type":"Point"}
}