{
  "type": "Feature",
  "properties": {
    "iso:country":"US",
    "sg:address":"1033 W Fort Williams St",
    "sg:city":"Sylacauga",
    "sg:classifiers":[
        {
            "category":"Shopping",
            "subcategory":"Clothing, Apparel, & Fashions",
            "type":"Retail Goods"
        }
    ],
    "sg:phone":"+1 256 249 9988",
    "sg:postcode":"35150",
    "sg:province":"AL",
    "sg:tags":[
        "infant",
        "wear"
    ],
    "wof:name":"Buttons & Bows Children's Btq",
    "wof:placetype":"venue"
},
  "geometry": {"coordinates":[-86.266852,33.167267],"type":"Point"}
}