{
  "type": "Feature",
  "properties": {
    "iso:country":"US",
    "sg:address":"568 S Oates St",
    "sg:city":"Dothan",
    "sg:classifiers":[
        {
            "category":"Insurance",
            "subcategory":"Insurance Agent",
            "type":"Services"
        }
    ],
    "sg:phone":"+1 334 792 5101",
    "sg:postcode":"36301",
    "sg:province":"AL",
    "wof:name":"Slingluff United Insurance",
    "wof:placetype":"venue"
},
  "geometry": {"coordinates":[-85.393114,31.217813],"type":"Point"}
}