{
  "type": "Feature",
  "properties": {
    "iso:country":"US",
    "sg:address":"4123 4th Ave",
    "sg:city":"Brighton",
    "sg:classifiers":[
        {
            "category":"Personal",
            "subcategory":"Beauty Salon",
            "type":"Services"
        }
    ],
    "sg:phone":"+1 205 426 3366",
    "sg:postcode":"35020",
    "sg:province":"AL",
    "sg:tags":[
        "shop"
    ],
    "wof:name":"Annie's Beauty & Barber Salon",
    "wof:placetype":"venue"
},
  "geometry": {"coordinates":[-86.94454399999999,33.438792],"type":"Point"}
}