{
  "type": "Feature",
  "properties": {
    "iso:country":"US",
    "sg:address":"2922 7th St",
    "sg:city":"Tuscaloosa",
    "sg:classifiers":[
        {
            "category":"Shopping",
            "subcategory":"Music",
            "type":"Retail Goods"
        }
    ],
    "sg:phone":"+1 205 345 6611",
    "sg:postcode":"35401",
    "sg:province":"AL",
    "sg:tags":[
        "record",
        "tape",
        "cd"
    ],
    "wof:name":"Oz Music",
    "wof:placetype":"venue"
},
  "geometry": {"coordinates":[-87.575638,33.205718],"type":"Point"}
}