{
  "type": "Feature",
  "properties": {
    "iso:country":"US",
    "sg:address":"519 Buckingham Dr",
    "sg:city":"Montgomery",
    "sg:classifiers":[
        {
            "category":"Freight",
            "type":"Transportation"
        }
    ],
    "sg:phone":"+1 334 834 7012",
    "sg:postcode":"36116",
    "sg:province":"AL",
    "sg:tags":[
        "record"
    ],
    "wof:name":"Databank",
    "wof:placetype":"venue"
},
  "geometry": {"coordinates":[-86.297139,32.323859],"type":"Point"}
}