{
  "type": "Feature",
  "properties": {
    "iso:country":"US",
    "sg:address":"110 N Midway St",
    "sg:city":"Clayton",
    "sg:classifiers":[
        {
            "category":"Retail",
            "subcategory":"Laundry & Dry Cleaning",
            "type":"Services"
        }
    ],
    "sg:phone":"+1 334 775 8341",
    "sg:postcode":"36016",
    "sg:province":"AL",
    "sg:tags":[
        "cleaners"
    ],
    "wof:name":"Clayton Dry Cleaners",
    "wof:placetype":"venue"
},
  "geometry": {"coordinates":[-85.451667,31.884145],"type":"Point"}
}