{
  "type": "Feature",
  "properties": {
    "iso:country":"US",
    "sg:address":"10261 Hunters Ridge Dr",
    "sg:city":"Mobile",
    "sg:classifiers":[
        {
            "category":"Professional",
            "type":"Services"
        }
    ],
    "sg:phone":"+1 251 634 3400",
    "sg:postcode":"36695",
    "sg:province":"AL",
    "wof:name":"Karla Merritt",
    "wof:placetype":"venue"
},
  "geometry": {"coordinates":[-88.285838,30.656616],"type":"Point"}
}