{
  "type": "Feature",
  "properties": {
    "iso:country":"US",
    "sg:address":"231 Cahaba Ridge Dr",
    "sg:city":"Trussville",
    "sg:classifiers":[
        {
            "category":"Retail",
            "subcategory":"Repair Shop",
            "type":"Services"
        }
    ],
    "sg:phone":"+1 205 699 2428",
    "sg:postcode":"35173",
    "sg:province":"AL",
    "wof:name":"A Plus Lock & Key",
    "wof:placetype":"venue"
},
  "geometry": {"coordinates":[-86.551941,33.607025],"type":"Point"}
}