{
  "type": "Feature",
  "properties": {
    "iso:country":"US",
    "sg:address":"904 Bob Wallace Ave SW",
    "sg:city":"Huntsville",
    "sg:classifiers":[
        {
            "category":"Real Estate",
            "subcategory":"Real Estate Agent",
            "type":"Services"
        }
    ],
    "sg:phone":"+1 256 533 0265",
    "sg:postcode":"35801",
    "sg:province":"AL",
    "sg:tags":[
        "business"
    ],
    "wof:name":"Nettles Real Estate Services",
    "wof:placetype":"venue"
},
  "geometry": {"coordinates":[-86.58685699999999,34.711772],"type":"Point"}
}