{
  "type": "Feature",
  "properties": {
    "iso:country":"US",
    "sg:address":"306 4th Ave SE",
    "sg:city":"Decatur",
    "sg:classifiers":[
        {
            "category":"Banks & Credit Unions",
            "subcategory":"Bank",
            "type":"Services"
        }
    ],
    "sg:phone":"+1 256 301 6262",
    "sg:postcode":"35601",
    "sg:province":"AL",
    "wof:name":"Bank Of Decatur",
    "wof:placetype":"venue"
},
  "geometry": {"coordinates":[-86.98257099999999,34.600796],"type":"Point"}
}