{
  "type": "Feature",
  "properties": {
    "iso:country":"US",
    "sg:address":"4401 Dolly Ridge Rd",
    "sg:city":"Birmingham",
    "sg:classifiers":[
        {
            "category":"Park",
            "type":"Public Place"
        },
        {
            "category":"Community Center",
            "type":"Public Place"
        }
    ],
    "sg:phone":"+1 205 402 5480",
    "sg:postcode":"35243",
    "sg:province":"AL",
    "sg:tags":[
        "recreation"
    ],
    "sg:website":"http://www.vestavia.k12.al.us",
    "wof:name":"Cahaba Heights Parks & Recreation Board",
    "wof:placetype":"venue"
},
  "geometry": {"coordinates":[-86.739143,33.452499],"type":"Point"}
}