{
  "type": "Feature",
  "properties": {
    "iso:country":"US",
    "sg:address":"207 Tom Hodge Ln",
    "sg:city":"Scottsboro",
    "sg:classifiers":[
        {
            "category":"Building & Trades",
            "subcategory":"Electrical",
            "type":"Services"
        }
    ],
    "sg:phone":"+1 256 574 2688",
    "sg:postcode":"35768",
    "sg:province":"AL",
    "sg:tags":[
        "electrical",
        "contractor"
    ],
    "wof:name":"Bama Services",
    "wof:placetype":"venue"
},
  "geometry": {"coordinates":[-86.038686,34.667238],"type":"Point"}
}