{
  "type": "Feature",
  "properties": {
    "iso:country":"US",
    "sg:address":"818 McKenzie St",
    "sg:city":"Foley",
    "sg:classifiers":[
        {
            "category":"Professional",
            "subcategory":"Management & Consulting",
            "type":"Services"
        }
    ],
    "sg:phone":"+1 251 943 3770",
    "sg:postcode":"36535",
    "sg:province":"AL",
    "sg:tags":[
        "administrative"
    ],
    "wof:name":"Woerner Group Resources Inc",
    "wof:placetype":"venue"
},
  "geometry": {"coordinates":[-87.683664,30.41432],"type":"Point"}
}