{
  "type": "Feature",
  "properties": {
    "addr:full":"2000 S Cedar St Foley AL 36535",
    "addr:housenumber":"2000",
    "addr:postcode":"36535",
    "addr:street":"S Cedar St",
    "iso:country":"US",
    "sg:address":"2000 S Cedar St",
    "sg:city":"Foley",
    "sg:classifiers":[
        {
            "category":"Social Services",
            "type":"Services"
        }
    ],
    "sg:phone":"+1 251 943 1483",
    "sg:postcode":"36535",
    "sg:province":"AL",
    "sg:tags":[
        "association"
    ],
    "wof:name":"Foley Boys & Girls Clubs",
    "wof:placetype":"venue"
},
  "geometry": {"coordinates":[-87.69173499999999,30.384887],"type":"Point"}
}