{
  "type": "Feature",
  "properties": {
    "addr:full":"30923 Jay Dr Spanish Fort AL 36527",
    "addr:housenumber":"30923",
    "addr:postcode":"36527",
    "addr:street":"Jay Dr",
    "iso:country":"US",
    "sg:address":"30923 Jay Dr",
    "sg:city":"Spanish Fort",
    "sg:classifiers":[
        {
            "category":"Building & Trades",
            "subcategory":"Plumbing",
            "type":"Services"
        }
    ],
    "sg:phone":"+1 251 625 4454",
    "sg:postcode":"36527",
    "sg:province":"AL",
    "sg:tags":[
        "plumbing",
        "contractor"
    ],
    "wof:name":"Custom Plumbing and Piping",
    "wof:placetype":"venue"
},
  "geometry": {"coordinates":[-87.880201,30.673664],"type":"Point"}
}