{
  "type": "Feature",
  "properties": {
    "iso:country":"US",
    "sg:address":"2016 10th Ave S",
    "sg:city":"Birmingham",
    "sg:classifiers":[
        {
            "category":"Professional",
            "subcategory":"Art Services",
            "type":"Services"
        }
    ],
    "sg:phone":"+1 205 933 7198",
    "sg:postcode":"35205",
    "sg:province":"AL",
    "sg:tags":[
        "photography",
        "commercial"
    ],
    "wof:name":"Aerial Photography",
    "wof:placetype":"venue"
},
  "geometry": {"coordinates":[-86.796032,33.50259],"type":"Point"}
}