{
  "type": "Feature",
  "properties": {
    "iso:country":"US",
    "sg:address":"7990 N Lake Dr",
    "sg:city":"Trussville",
    "sg:classifiers":[
        {
            "category":"Building & Trades",
            "subcategory":"Cleaning & Sanitation",
            "type":"Services"
        }
    ],
    "sg:phone":"+1 205 661 6661",
    "sg:postcode":"35173",
    "sg:province":"AL",
    "sg:tags":[
        "maintenance"
    ],
    "wof:name":"Oak Park Chimney Corp",
    "wof:placetype":"venue"
},
  "geometry": {"coordinates":[-86.551841,33.628974],"type":"Point"}
}