{
  "type": "Feature",
  "properties": {
    "addr:full":"334 E Magnolia Ave Auburn AL 36830",
    "addr:housenumber":"334",
    "addr:postcode":"36830",
    "addr:street":"E Magnolia Ave",
    "iso:country":"US",
    "sg:address":"334 E Magnolia Ave",
    "sg:city":"Auburn",
    "sg:classifiers":[
        {
            "category":"Restaurant",
            "type":"Food & Drink"
        }
    ],
    "sg:menulink":"http://www.allmenus.com/al/auburn-opelika/120987-subway/menu/",
    "sg:phone":"+1 334 826 2476",
    "sg:postcode":"36830",
    "sg:province":"AL",
    "sg:tags":[
        "american",
        "sandwich"
    ],
    "wof:name":"Subway",
    "wof:placetype":"venue"
},
  "geometry": {"coordinates":[-85.47635,32.606544],"type":"Point"}
}