{
  "type": "Feature",
  "properties": {
    "iso:country":"US",
    "sg:address":"5179 Lamplighter Dr",
    "sg:city":"Pinson",
    "sg:classifiers":[
        {
            "category":"Professional",
            "type":"Services"
        }
    ],
    "sg:phone":"+1 205 681 1185",
    "sg:postcode":"35126",
    "sg:province":"AL",
    "wof:name":"Billy R Elders",
    "wof:placetype":"venue"
},
  "geometry": {"coordinates":[-86.649281,33.721536],"type":"Point"}
}