{
  "type": "Feature",
  "properties": {
    "addr:full":"6630 State Rte 162 Pine Hill AL 36769",
    "addr:housenumber":"6630",
    "addr:postcode":"36769",
    "addr:street":"State Rte 162;Hill",
    "iso:country":"US",
    "sg:address":"6630 State Rte 162",
    "sg:city":"Pine Hill",
    "sg:classifiers":[
        {
            "category":"Organizations",
            "subcategory":"Religious Organization",
            "type":"Services"
        }
    ],
    "sg:phone":"+1 334 385 2851",
    "sg:postcode":"36769",
    "sg:province":"AL",
    "wof:name":"Pine Grove Baptist Church",
    "wof:placetype":"venue"
},
  "geometry": {"coordinates":[-87.517281,32.031602],"type":"Point"}
}