{
  "type": "Feature",
  "properties": {
    "iso:country":"US",
    "sg:address":"17799 State Rte 180",
    "sg:city":"Gulf Shores",
    "sg:classifiers":[
        {
            "category":"Travel",
            "subcategory":"Hotels & Motels",
            "type":"Entertainment"
        }
    ],
    "sg:phone":"+1 251 968 7969",
    "sg:postcode":"36542",
    "sg:province":"AL",
    "sg:tags":[
        "cottage",
        "cabin"
    ],
    "wof:name":"Callaway's Cottages",
    "wof:placetype":"venue"
},
  "geometry": {"coordinates":[-87.721142,30.255848],"type":"Point"}
}