{
  "type": "Feature",
  "properties": {
    "iso:country":"US",
    "sg:address":"4210 Halls Mill Rd",
    "sg:city":"Mobile",
    "sg:classifiers":[
        {
            "category":"Wholesale",
            "subcategory":"Metals & Minerals",
            "type":"Manufacturing & Wholesale Goods"
        }
    ],
    "sg:phone":"+1 251 666 6770",
    "sg:postcode":"36693",
    "sg:province":"AL",
    "sg:tags":[
        "center"
    ],
    "wof:name":"Piping & Equipment Inc",
    "wof:placetype":"venue"
},
  "geometry": {"coordinates":[-88.138146,30.62331],"type":"Point"}
}