{
  "type": "Feature",
  "properties": {
    "addr:full":"112 Haven Dr Dothan AL 36301",
    "addr:housenumber":"112",
    "addr:postcode":"36301",
    "addr:street":"Haven Dr",
    "iso:country":"US",
    "sg:address":"112 Haven Dr",
    "sg:city":"Dothan",
    "sg:classifiers":[
        {
            "category":"Health Services",
            "subcategory":"Doctor",
            "type":"Services"
        }
    ],
    "sg:phone":"+1 334 677 6220",
    "sg:postcode":"36301",
    "sg:province":"AL",
    "sg:tags":[
        "physician",
        "surgeon"
    ],
    "wof:name":"Randall W Nichols MD",
    "wof:placetype":"venue"
},
  "geometry": {"coordinates":[-85.36626699999999,31.219049],"type":"Point"}
}