{
  "type": "Feature",
  "properties": {
    "iso:country":"US",
    "sg:address":"42245 Pine Grove Rd",
    "sg:city":"Bay Minette",
    "sg:classifiers":[
        {
            "category":"Manufacturing",
            "subcategory":"Tools & Machinery",
            "type":"Manufacturing & Wholesale Goods"
        },
        {
            "category":"Government",
            "subcategory":"Fire Station",
            "type":"Public Place"
        }
    ],
    "sg:phone":"+1 251 937 4034",
    "sg:postcode":"36507",
    "sg:province":"AL",
    "sg:tags":[
        "department",
        "industrial",
        "general",
        "protection",
        "mfg"
    ],
    "wof:name":"Pine Grove Volunteer Fr Dept A",
    "wof:placetype":"venue"
},
  "geometry": {"coordinates":[-87.751174,30.842668],"type":"Point"}
}