{
  "type": "Feature",
  "properties": {
    "iso:country":"US",
    "sg:address":"3900 Veona Daniels Rd",
    "sg:city":"Birmingham",
    "sg:classifiers":[
        {
            "category":"Utilities",
            "subcategory":"Refuse",
            "type":"Services"
        }
    ],
    "sg:phone":"+1 205 985 2340",
    "sg:postcode":"35244",
    "sg:province":"AL",
    "sg:tags":[
        "executive",
        "system"
    ],
    "wof:name":"Environmental Svc Dept",
    "wof:placetype":"venue"
},
  "geometry": {"coordinates":[-86.7869,33.374501],"type":"Point"}
}