{
  "type": "Feature",
  "properties": {
    "addr:full":"3501 Pulaski Pike NW Huntsville AL 35810",
    "addr:housenumber":"3501",
    "addr:postcode":"35810",
    "addr:street":"Pulaski Pike Nw",
    "iso:country":"US",
    "sg:address":"3501 Pulaski Pike NW",
    "sg:city":"Huntsville",
    "sg:classifiers":[
        {
            "category":"Autos & Motor Vehicles",
            "subcategory":"Fuel & Gas Station",
            "type":"Retail Goods"
        }
    ],
    "sg:phone":"+1 256 858 6606",
    "sg:postcode":"35810",
    "sg:province":"AL",
    "sg:tags":[
        "station",
        "gasoline",
        "oil"
    ],
    "wof:name":"Mastin Lake Chevron Food Mart",
    "wof:placetype":"venue"
},
  "geometry": {"coordinates":[-86.616675,34.772282],"type":"Point"}
}