{
  "type": "Feature",
  "properties": {
    "iso:country":"US",
    "sg:address":"515 16th Ave SE",
    "sg:city":"Decatur",
    "sg:classifiers":[
        {
            "category":"Organizations",
            "subcategory":"Religious Organization",
            "type":"Services"
        }
    ],
    "sg:phone":"+1 256 353 1830",
    "sg:postcode":"35601",
    "sg:province":"AL",
    "sg:tags":[
        "church"
    ],
    "wof:name":"Sixteenth Ave Baptist Church",
    "wof:placetype":"venue"
},
  "geometry": {"coordinates":[-86.967269,34.599119],"type":"Point"}
}