{
  "type": "Feature",
  "properties": {
    "addr:full":"9002 Parkway E Birmingham AL 35206",
    "addr:housenumber":"9002",
    "addr:postcode":"35206",
    "addr:street":"Parkway E",
    "iso:country":"US",
    "sg:address":"9002 Parkway E",
    "sg:city":"Birmingham",
    "sg:classifiers":[
        {
            "category":"Wholesale",
            "subcategory":"Groceries",
            "type":"Manufacturing & Wholesale Goods"
        }
    ],
    "sg:phone":"+1 205 836 2188",
    "sg:postcode":"35206",
    "sg:province":"AL",
    "sg:tags":[
        "food",
        "broker"
    ],
    "wof:name":"J & W Foods LLC",
    "wof:placetype":"venue"
},
  "geometry": {"coordinates":[-86.712046,33.579764],"type":"Point"}
}