{
  "type": "Feature",
  "properties": {
    "addr:full":"30906 State Rte 25 Wilsonville AL 35186",
    "addr:housenumber":"30906",
    "addr:postcode":"35186",
    "addr:street":"State Rte 25",
    "iso:country":"US",
    "sg:address":"30906 State Rte 25",
    "sg:city":"Wilsonville",
    "sg:classifiers":[
        {
            "category":"Personal",
            "type":"Services"
        }
    ],
    "sg:phone":"+1 205 670 5355",
    "sg:postcode":"35186",
    "sg:province":"AL",
    "wof:name":"Advanced Weight Loss Center In",
    "wof:placetype":"venue"
},
  "geometry": {"coordinates":[-86.481323,33.237069],"type":"Point"}
}