{
  "type": "Feature",
  "properties": {
    "iso:country":"US",
    "sg:address":"4016 Oak Shadow Ln",
    "sg:city":"Montgomery",
    "sg:classifiers":[
        {
            "category":"Professional",
            "subcategory":"Business Services",
            "type":"Services"
        }
    ],
    "sg:phone":"+1 334 213 0551",
    "sg:postcode":"36116",
    "sg:province":"AL",
    "wof:name":"Impasto Agency LLC",
    "wof:placetype":"venue"
},
  "geometry": {"coordinates":[-86.224225,32.326353],"type":"Point"}
}