{
  "type": "Feature",
  "properties": {
    "addr:full":"4320 Judith Ln SW Huntsville AL 35805",
    "addr:housenumber":"4320",
    "addr:postcode":"35805",
    "addr:street":"Judith Ln Sw",
    "iso:country":"US",
    "sg:address":"4320 Judith Ln SW",
    "sg:city":"Huntsville",
    "sg:classifiers":[
        {
            "category":"Professional",
            "subcategory":"Computer Services",
            "type":"Services"
        }
    ],
    "sg:phone":"+1 256 726 9289",
    "sg:postcode":"35805",
    "sg:province":"AL",
    "sg:tags":[
        "information",
        "support"
    ],
    "wof:name":"Southern It Professionals Inc",
    "wof:placetype":"venue"
},
  "geometry": {"coordinates":[-86.629831,34.714841],"type":"Point"}
}