{
  "type": "Feature",
  "properties": {
    "iso:country":"US",
    "sg:address":"1021 Meridian St N",
    "sg:city":"Huntsville",
    "sg:classifiers":[
        {
            "category":"Building & Trades",
            "subcategory":"Equipment Rental",
            "type":"Services"
        }
    ],
    "sg:phone":"+1 256 534 5701",
    "sg:postcode":"35801",
    "sg:province":"AL",
    "sg:tags":[
        "merchandise"
    ],
    "wof:name":"Mullins Special Occasions",
    "wof:placetype":"venue"
},
  "geometry": {"coordinates":[-86.585044,34.742715],"type":"Point"}
}