{
  "type": "Feature",
  "properties": {
    "addr:full":"1810 Merchants Dr Birmingham AL 35244",
    "addr:housenumber":"1810",
    "addr:postcode":"35244",
    "addr:street":"Merchants Dr",
    "iso:country":"US",
    "sg:address":"1810 Merchants Dr",
    "sg:city":"Birmingham",
    "sg:classifiers":[
        {
            "category":"Professional",
            "subcategory":"Management & Consulting",
            "type":"Services"
        }
    ],
    "sg:phone":"+1 205 989 7774",
    "sg:postcode":"35244",
    "sg:province":"AL",
    "wof:name":"Raytrans Management Inc",
    "wof:placetype":"venue"
},
  "geometry": {"coordinates":[-86.806251,33.373539],"type":"Point"}
}