{
  "type": "Feature",
  "properties": {
    "iso:country":"US",
    "sg:address":"5237 Henry Rd",
    "sg:city":"Eight Mile",
    "sg:classifiers":[
        {
            "category":"Building & Trades",
            "subcategory":"Construction",
            "type":"Services"
        }
    ],
    "sg:phone":"+1 251 457 6514",
    "sg:postcode":"36613",
    "sg:province":"AL",
    "sg:tags":[
        "excavation",
        "excavating",
        "work",
        "paving",
        "contractor"
    ],
    "wof:name":"Brownlee Construction Inc",
    "wof:placetype":"venue"
},
  "geometry": {"coordinates":[-88.166428,30.771071],"type":"Point"}
}