{
  "type": "Feature",
  "properties": {
    "iso:country":"US",
    "sg:address":"23 83rd St N",
    "sg:city":"Birmingham",
    "sg:classifiers":[
        {
            "category":"Retail",
            "subcategory":"Photofinishing",
            "type":"Services"
        }
    ],
    "sg:phone":"+1 205 836 2311",
    "sg:postcode":"35206",
    "sg:province":"AL",
    "sg:tags":[
        "lab"
    ],
    "wof:name":"First Photo",
    "wof:placetype":"venue"
},
  "geometry": {"coordinates":[-86.72167399999999,33.570903],"type":"Point"}
}