{
  "type": "Feature",
  "properties": {
    "iso:country":"US",
    "sg:address":"1550 W Andrews Ave",
    "sg:city":"Ozark",
    "sg:classifiers":[
        {
            "category":"Health Services",
            "subcategory":"Chiropractor",
            "type":"Services"
        }
    ],
    "sg:phone":"+1 334 445 2525",
    "sg:postcode":"36360",
    "sg:province":"AL",
    "wof:name":"Thompson Family Chiropractic",
    "wof:placetype":"venue"
},
  "geometry": {"coordinates":[-85.666965,31.436157],"type":"Point"}
}