{
  "type": "Feature",
  "properties": {
    "addr:full":"9952 Parkway E Birmingham AL 35215",
    "addr:housenumber":"9952",
    "addr:postcode":"35215",
    "addr:street":"Parkway E",
    "iso:country":"US",
    "sg:address":"9952 Parkway E",
    "sg:city":"Birmingham",
    "sg:classifiers":[
        {
            "category":"Home & Garden",
            "subcategory":"Furniture",
            "type":"Retail Goods"
        }
    ],
    "sg:phone":"+1 205 856 0886",
    "sg:postcode":"35215",
    "sg:province":"AL",
    "wof:name":"Southland Furniture LLC",
    "wof:placetype":"venue"
},
  "geometry": {"coordinates":[-86.688153,33.610805],"type":"Point"}
}