{
  "type": "Feature",
  "properties": {
    "addr:full":"1929 Lockhart Blvd Florala AL 36442",
    "addr:housenumber":"1929",
    "addr:postcode":"36442",
    "addr:street":"Lockhart Blvd",
    "iso:country":"US",
    "sg:address":"1929 Lockhart Blvd",
    "sg:city":"Florala",
    "sg:classifiers":[
        {
            "category":"Home & Garden",
            "subcategory":"Building Materials",
            "type":"Retail Goods"
        }
    ],
    "sg:phone":"+1 334 858 6142",
    "sg:postcode":"36442",
    "sg:province":"AL",
    "sg:website":"www.floralacoop.com",
    "wof:name":"Florala Farmers/Builders Coop",
    "wof:placetype":"venue"
},
  "geometry": {"coordinates":[-86.33584399999999,31.009066],"type":"Point"}
}