{
  "type": "Feature",
  "properties": {
    "iso:country":"US",
    "sg:address":"1110 Prospect Rd",
    "sg:city":"Nauvoo",
    "sg:classifiers":[
        {
            "category":"Social Services",
            "type":"Services"
        }
    ],
    "sg:phone":"+1 205 221 5388",
    "sg:postcode":"35578",
    "sg:province":"AL",
    "sg:tags":[
        "youth",
        "organization",
        "center"
    ],
    "wof:name":"Lupton Little League",
    "wof:placetype":"venue"
},
  "geometry": {"coordinates":[-87.402826,33.92301],"type":"Point"}
}