{
  "type": "Feature",
  "properties": {
    "iso:country":"US",
    "sg:address":"130 Neeley St NE",
    "sg:city":"Huntsville",
    "sg:classifiers":[
        {
            "category":"Home & Garden",
            "subcategory":"Building Materials",
            "type":"Retail Goods"
        }
    ],
    "sg:phone":"+1 256 539 0199",
    "sg:postcode":"35801",
    "sg:province":"AL",
    "sg:tags":[
        "auto",
        "window",
        "glass",
        "plate",
        "replacement"
    ],
    "wof:name":"Mc Neese Glass Co Inc",
    "wof:placetype":"venue"
},
  "geometry": {"coordinates":[-86.583691,34.747113],"type":"Point"}
}