{
  "type": "Feature",
  "properties": {
    "iso:country":"US",
    "sg:address":"3545 Old Hwy 9",
    "sg:city":"Cedar Bluff",
    "sg:classifiers":[
        {
            "category":"Restaurant",
            "type":"Food & Drink"
        }
    ],
    "sg:phone":"+1 256 779 5733",
    "sg:postcode":"35959",
    "sg:province":"AL",
    "wof:name":"Fibbers Restaurant",
    "wof:placetype":"venue"
},
  "geometry": {"coordinates":[-85.605722,34.220154],"type":"Point"}
}