{
  "type": "Feature",
  "properties": {
    "iso:country":"US",
    "sg:address":"9394 Thermal Rd",
    "sg:city":"Warrior",
    "sg:classifiers":[
        {
            "category":"Building & Trades",
            "subcategory":"Plumbing",
            "type":"Services"
        }
    ],
    "sg:phone":"+1 205 681 7683",
    "sg:postcode":"35180",
    "sg:province":"AL",
    "sg:tags":[
        "contractor"
    ],
    "wof:name":"Hannah Plumbing Co",
    "wof:placetype":"venue"
},
  "geometry": {"coordinates":[-86.71005700000001,33.794848],"type":"Point"}
}