{
  "type": "Feature",
  "properties": {
    "iso:country":"US",
    "sg:address":"415 Old Hwy 9",
    "sg:city":"Anniston",
    "sg:classifiers":[
        {
            "category":"Shopping",
            "subcategory":"Computers & Home Electronics",
            "type":"Retail Goods"
        }
    ],
    "sg:phone":"+1 256 435 1420",
    "sg:postcode":"36207",
    "sg:province":"AL",
    "wof:name":"Advisor Computer TEC",
    "wof:placetype":"venue"
},
  "geometry": {"coordinates":[-85.658117,33.649791],"type":"Point"}
}