{
  "type": "Feature",
  "properties": {
    "iso:country":"US",
    "sg:address":"1215 Old Hwy 231 N",
    "sg:city":"Troy",
    "sg:classifiers":[
        {
            "category":"Shopping",
            "subcategory":"Music",
            "type":"Retail Goods"
        }
    ],
    "sg:phone":"+1 334 807 0008",
    "sg:postcode":"36079",
    "sg:province":"AL",
    "sg:tags":[
        "video",
        "disc",
        "tape",
        "cassette"
    ],
    "wof:name":"Video Warehouse Of Troy",
    "wof:placetype":"venue"
},
  "geometry": {"coordinates":[-86.002574,31.865531],"type":"Point"}
}