{
  "type": "Feature",
  "properties": {
    "iso:country":"US",
    "sg:address":"3741 Colchester Rd",
    "sg:city":"Birmingham",
    "sg:classifiers":[
        {
            "category":"Real Estate",
            "subcategory":"Architect",
            "type":"Services"
        }
    ],
    "sg:phone":"+1 205 969 0026",
    "sg:postcode":"35223",
    "sg:province":"AL",
    "wof:name":"Donze Architects",
    "wof:placetype":"venue"
},
  "geometry": {"coordinates":[-86.73047200000001,33.471727],"type":"Point"}
}