{
  "type": "Feature",
  "properties": {
    "addr:full":"121 Co Rd 92 Prattville AL 36066",
    "addr:housenumber":"121;92",
    "addr:postcode":"36066",
    "addr:street":"Co Rd",
    "iso:country":"US",
    "sg:address":"121 Co Rd 92",
    "sg:city":"Prattville",
    "sg:classifiers":[
        {
            "category":"Personal",
            "subcategory":"Beauty Salon",
            "type":"Services"
        }
    ],
    "sg:phone":"+1 334 358 0591",
    "sg:postcode":"36066",
    "sg:province":"AL",
    "sg:tags":[
        "shop"
    ],
    "wof:name":"Classic Style & Tan",
    "wof:placetype":"venue"
},
  "geometry": {"coordinates":[-86.463854,32.584],"type":"Point"}
}