{
  "type": "Feature",
  "properties": {
    "addr:full":"206 S Mulberry Ave Butler AL 36904",
    "addr:housenumber":"206",
    "addr:postcode":"36904",
    "addr:street":"S Mulberry Ave",
    "iso:country":"US",
    "sg:address":"206 S Mulberry Ave",
    "sg:city":"Butler",
    "sg:classifiers":[
        {
            "category":"Health Services",
            "subcategory":"Hospital",
            "type":"Services"
        }
    ],
    "sg:phone":"+1 205 459 4080",
    "sg:postcode":"36904",
    "sg:province":"AL",
    "sg:tags":[
        "specialty",
        "psychiatric",
        "except"
    ],
    "wof:name":"Serenity Hospice Care LLC",
    "wof:placetype":"venue"
},
  "geometry": {"coordinates":[-88.221204,32.087088],"type":"Point"}
}