{
  "type": "Feature",
  "properties": {
    "iso:country":"US",
    "sg:address":"616 Adelle St SW",
    "sg:city":"Hartselle",
    "sg:classifiers":[
        {
            "category":"Real Estate",
            "subcategory":"Real Estate Agent",
            "type":"Services"
        }
    ],
    "sg:phone":"+1 256 773 5481",
    "sg:postcode":"35640",
    "sg:province":"AL",
    "sg:tags":[
        "authorities",
        "housing"
    ],
    "wof:name":"Hartselle City Housing Auth",
    "wof:placetype":"venue"
},
  "geometry": {"coordinates":[-86.938288,34.44039],"type":"Point"}
}