{
  "type": "Feature",
  "properties": {
    "addr:full":"3231 Bel Air Mall Mobile AL 36606",
    "addr:postcode":"3231;36606",
    "addr:street":"Bel Air Mall",
    "iso:country":"US",
    "sg:address":"3231 Bel Air Mall",
    "sg:city":"Mobile",
    "sg:classifiers":[
        {
            "category":"Shopping",
            "subcategory":"Clothing, Apparel, & Fashions",
            "type":"Retail Goods"
        }
    ],
    "sg:phone":"+1 251 450 5007",
    "sg:postcode":"36606",
    "sg:province":"AL",
    "sg:tags":[
        "sportswear"
    ],
    "sg:website":"www.pacsun.com",
    "wof:name":"Pacific Sunwear",
    "wof:placetype":"venue"
},
  "geometry": {"coordinates":[-88.12445099999999,30.673385],"type":"Point"}
}