{
  "type": "Feature",
  "properties": {
    "addr:full":"7250 State Rte 21 Sylacauga AL 35150",
    "addr:housenumber":"7250",
    "addr:postcode":"35150",
    "addr:street":"State Rte 21",
    "iso:country":"US",
    "sg:address":"7250 State Rte 21",
    "sg:city":"Sylacauga",
    "sg:classifiers":[
        {
            "category":"Shopping",
            "subcategory":"Clothing, Apparel, & Fashions",
            "type":"Retail Goods"
        }
    ],
    "sg:phone":"+1 256 245 4400",
    "sg:postcode":"35150",
    "sg:province":"AL",
    "sg:tags":[
        "uniform"
    ],
    "wof:name":"Proline Uniforms",
    "wof:placetype":"venue"
},
  "geometry": {"coordinates":[-86.252526,33.11549],"type":"Point"}
}