{
  "type": "Feature",
  "properties": {
    "addr:full":"404 19th St Birmingham AL 35218",
    "addr:housenumber":"404",
    "addr:postcode":"35218",
    "addr:street":"19Th St",
    "iso:country":"US",
    "sg:address":"404 19th St",
    "sg:city":"Birmingham",
    "sg:classifiers":[
        {
            "category":"Shopping",
            "subcategory":"Clothing, Apparel, & Fashions",
            "type":"Retail Goods"
        }
    ],
    "sg:phone":"+1 205 786 2256",
    "sg:postcode":"35218",
    "sg:province":"AL",
    "sg:tags":[
        "hat"
    ],
    "wof:name":"Bernie's Hats & Accessories",
    "wof:placetype":"venue"
},
  "geometry": {"coordinates":[-86.897447,33.513507],"type":"Point"}
}