{
  "type": "Feature",
  "properties": {
    "iso:country":"US",
    "sg:address":"12087 Veterans Memorial Pkwy",
    "sg:city":"Lafayette",
    "sg:classifiers":[
        {
            "category":"Organizations",
            "subcategory":"Religious Organization",
            "type":"Services"
        }
    ],
    "sg:phone":"+1 334 864 7522",
    "sg:postcode":"36862",
    "sg:province":"AL",
    "wof:name":"East Liberty Baptst Assocation",
    "wof:placetype":"venue"
},
  "geometry": {"coordinates":[-85.361182,32.885846],"type":"Point"}
}