{
  "type": "Feature",
  "properties": {
    "iso:country":"US",
    "sg:address":"1945 Feemster Gap Rd",
    "sg:city":"Guntersville",
    "sg:classifiers":[
        {
            "category":"Building & Trades",
            "subcategory":"Landscaping Services",
            "type":"Services"
        }
    ],
    "sg:phone":"+1 256 931 0441",
    "sg:postcode":"35976",
    "sg:province":"AL",
    "sg:tags":[
        "lawn",
        "care"
    ],
    "wof:name":"Browns Lawn Care",
    "wof:placetype":"venue"
},
  "geometry": {"coordinates":[-86.451199,34.267647],"type":"Point"}
}