{
  "type": "Feature",
  "properties": {
    "addr:full":"262 Glenaddie Ave Anniston AL 36201",
    "addr:housenumber":"262",
    "addr:postcode":"36201",
    "addr:street":"Glenaddie Ave",
    "iso:country":"US",
    "sg:address":"262 Glenaddie Ave",
    "sg:city":"Anniston",
    "sg:classifiers":[
        {
            "category":"Retail",
            "subcategory":"Animal Services",
            "type":"Services"
        }
    ],
    "sg:phone":"+1 256 820 5544",
    "sg:postcode":"36201",
    "sg:province":"AL",
    "wof:name":"R K Miniature Horses",
    "wof:placetype":"venue"
},
  "geometry": {"coordinates":[-85.836011,33.648906],"type":"Point"}
}