{
  "type": "Feature",
  "properties": {
    "addr:full":"402 17th St N Birmingham AL 35203",
    "addr:housenumber":"402",
    "addr:postcode":"35203",
    "addr:street":"17Th St N",
    "iso:country":"US",
    "sg:address":"402 17th St N",
    "sg:city":"Birmingham",
    "sg:classifiers":[
        {
            "category":"Health Services",
            "subcategory":"Medical Lab",
            "type":"Services"
        }
    ],
    "sg:phone":"+1 205 323 8080",
    "sg:postcode":"35203",
    "sg:province":"AL",
    "sg:tags":[
        "laboratory",
        "dental"
    ],
    "wof:name":"Citizens Dental Lab",
    "wof:placetype":"venue"
},
  "geometry": {"coordinates":[-86.812134,33.515541],"type":"Point"}
}