{
  "type": "Feature",
  "properties": {
    "iso:country":"US",
    "sg:address":"104 Rock Bridge Rd",
    "sg:city":"Dothan",
    "sg:classifiers":[
        {
            "category":"Professional",
            "subcategory":"Accounting & Tax Preparation",
            "type":"Services"
        }
    ],
    "sg:phone":"+1 334 793 3122",
    "sg:postcode":"36303",
    "sg:province":"AL",
    "sg:tags":[
        "accountant"
    ],
    "wof:name":"David W Parsons & Co",
    "wof:placetype":"venue"
},
  "geometry": {"coordinates":[-85.42975199999999,31.253712],"type":"Point"}
}