{
  "type": "Feature",
  "properties": {
    "iso:country":"US",
    "sg:address":"205 Dana Rd",
    "sg:city":"Warrior",
    "sg:classifiers":[
        {
            "category":"Organizations",
            "subcategory":"Religious Organization",
            "type":"Services"
        }
    ],
    "sg:phone":"+1 205 647 4157",
    "sg:postcode":"35180",
    "sg:province":"AL",
    "wof:name":"Westside Baptist Church",
    "wof:placetype":"venue"
},
  "geometry": {"coordinates":[-86.821898,33.800698],"type":"Point"}
}