{
  "type": "Feature",
  "properties": {
    "addr:full":"3011 Ross Clark Cir Dothan AL 36301",
    "addr:housenumber":"3011",
    "addr:postcode":"36301",
    "addr:street":"Ross Clark Cir",
    "iso:country":"US",
    "sg:address":"3011 Ross Clark Cir",
    "sg:city":"Dothan",
    "sg:classifiers":[
        {
            "category":"Banks & Credit Unions",
            "subcategory":"Investment Brokerage",
            "type":"Services"
        }
    ],
    "sg:phone":"+1 334 673 9804",
    "sg:postcode":"36301",
    "sg:province":"AL",
    "wof:name":"D & D Investments Inc",
    "wof:placetype":"venue"
},
  "geometry": {"coordinates":[-85.432509,31.222295],"type":"Point"}
}