{
  "type": "Feature",
  "properties": {
    "iso:country":"US",
    "sg:address":"16730 Oyster Bay Pl",
    "sg:city":"Gulf Shores",
    "sg:classifiers":[
        {
            "category":"Travel",
            "subcategory":"Hotels & Motels",
            "type":"Entertainment"
        }
    ],
    "sg:phone":"+1 251 968 7814",
    "sg:postcode":"36542",
    "sg:province":"AL",
    "sg:tags":[
        "operation"
    ],
    "wof:name":"Bon Secour Water Sports Inc",
    "wof:placetype":"venue"
},
  "geometry": {"coordinates":[-87.73875,30.294141],"type":"Point"}
}