{
  "type": "Feature",
  "properties": {
    "iso:country":"US",
    "sg:address":"6245 Old Rangeline Rd W",
    "sg:city":"Theodore",
    "sg:classifiers":[
        {
            "category":"Education",
            "subcategory":"Dance Studio",
            "type":"Public Place"
        }
    ],
    "sg:phone":"+1 251 408 0219",
    "sg:postcode":"36582",
    "sg:province":"AL",
    "wof:name":"Jubilee School Of Dance",
    "wof:placetype":"venue"
},
  "geometry": {"coordinates":[-88.123576,30.571686],"type":"Point"}
}