{
  "type": "Feature",
  "properties": {
    "iso:country":"US",
    "sg:address":"3764 Airport Blvd",
    "sg:city":"Mobile",
    "sg:classifiers":[
        {
            "category":"Shopping",
            "subcategory":"Clothing, Apparel, & Fashions",
            "type":"Retail Goods"
        }
    ],
    "sg:phone":"+1 251 344 6122",
    "sg:postcode":"36608",
    "sg:province":"AL",
    "wof:name":"Nathan's Fashions",
    "wof:placetype":"venue"
},
  "geometry": {"coordinates":[-88.136709,30.676112],"type":"Point"}
}