{
  "type": "Feature",
  "properties": {
    "iso:country":"US",
    "sg:address":"12445 State Rte 157",
    "sg:city":"Florence",
    "sg:classifiers":[
        {
            "category":"Personal",
            "subcategory":"Beauty Salon",
            "type":"Services"
        }
    ],
    "sg:phone":"+1 256 766 0409",
    "sg:postcode":"35633",
    "sg:province":"AL",
    "wof:name":"Shear Genius Hairstyles",
    "wof:placetype":"venue"
},
  "geometry": {"coordinates":[-87.787914,34.953634],"type":"Point"}
}