{
  "type": "Feature",
  "properties": {
    "iso:country":"US",
    "sg:address":"205 N Main St",
    "sg:city":"Arab",
    "sg:classifiers":[
        {
            "category":"Wholesale",
            "subcategory":"Furniture",
            "type":"Manufacturing & Wholesale Goods"
        }
    ],
    "sg:phone":"+1 256 586 6205",
    "sg:postcode":"35016",
    "sg:province":"AL",
    "wof:name":"Strawberry Marketing",
    "wof:placetype":"venue"
},
  "geometry": {"coordinates":[-86.495854,34.31856],"type":"Point"}
}