{
  "type": "Feature",
  "properties": {
    "iso:country":"US",
    "sg:address":"7751 Moffett Rd",
    "sg:city":"Semmes",
    "sg:classifiers":[
        {
            "category":"Restaurant",
            "type":"Food & Drink"
        }
    ],
    "sg:menulink":"http://www.allmenus.com/al/mobile/12811-churchs-chicken/menu/",
    "sg:phone":"+1 251 649 3273",
    "sg:postcode":"36575",
    "sg:province":"AL",
    "sg:tags":[
        "chicken",
        "wing"
    ],
    "wof:name":"Church's Chicken",
    "wof:placetype":"venue"
},
  "geometry": {"coordinates":[-88.22453899999999,30.76139],"type":"Point"}
}