{
  "type": "Feature",
  "properties": {
    "addr:full":"248 S Main St Arab AL 35016",
    "addr:housenumber":"248",
    "addr:postcode":"35016",
    "addr:street":"S Main St",
    "iso:country":"US",
    "sg:address":"248 S Main St",
    "sg:city":"Arab",
    "sg:classifiers":[
        {
            "category":"Personal",
            "subcategory":"Beauty Salon",
            "type":"Services"
        }
    ],
    "sg:phone":"+1 256 931 2009",
    "sg:postcode":"35016",
    "sg:province":"AL",
    "sg:tags":[
        "shop"
    ],
    "wof:name":"Masters Touch Salon",
    "wof:placetype":"venue"
},
  "geometry": {"coordinates":[-86.49612,34.312987],"type":"Point"}
}