{
  "type": "Feature",
  "properties": {
    "iso:country":"US",
    "sg:address":"82 Grover Ave",
    "sg:city":"Mobile",
    "sg:classifiers":[
        {
            "category":"Shopping",
            "subcategory":"Clothing, Apparel, & Fashions",
            "type":"Retail Goods"
        }
    ],
    "sg:phone":"+1 251 479 4587",
    "sg:postcode":"36610",
    "sg:province":"AL",
    "sg:tags":[
        "ready",
        "merchandise",
        "variety"
    ],
    "wof:name":"Labyzon Spcialty Var Unlimited",
    "wof:placetype":"venue"
},
  "geometry": {"coordinates":[-88.070826,30.733501],"type":"Point"}
}