{
  "type": "Feature",
  "properties": {
    "iso:country":"US",
    "sg:address":"316 University Blvd S",
    "sg:city":"Mobile",
    "sg:classifiers":[
        {
            "category":"Shopping",
            "subcategory":"Pharmacy",
            "type":"Retail Goods"
        }
    ],
    "sg:phone":"+1 251 343 0674",
    "sg:postcode":"36609",
    "sg:province":"AL",
    "wof:name":"Cvs",
    "wof:placetype":"venue"
},
  "geometry": {"coordinates":[-88.169559,30.664819],"type":"Point"}
}