{
  "type": "Feature",
  "properties": {
    "iso:country":"US",
    "sg:address":"1437 14th Ave",
    "sg:city":"Pleasant Grove",
    "sg:classifiers":[
        {
            "category":"Building & Trades",
            "subcategory":"Landscaping Services",
            "type":"Services"
        }
    ],
    "sg:phone":"+1 205 744 4219",
    "sg:postcode":"35127",
    "sg:province":"AL",
    "wof:name":"Lawns Unlimited",
    "wof:placetype":"venue"
},
  "geometry": {"coordinates":[-87.001192,33.475143],"type":"Point"}
}