{
  "type": "Feature",
  "properties": {
    "iso:country":"US",
    "sg:address":"5029 Pinnacle Sq",
    "sg:city":"Birmingham",
    "sg:classifiers":[
        {
            "category":"Fast Food",
            "type":"Food & Drink"
        },
        {
            "category":"Restaurant",
            "type":"Food & Drink"
        }
    ],
    "sg:phone":"+1 205 661 0492",
    "sg:postcode":"35235",
    "sg:province":"AL",
    "sg:tags":[
        "style",
        "hamburger",
        "family",
        "dog",
        "hot",
        "take",
        "american"
    ],
    "sg:website":"http://www.redrobin.com/",
    "wof:name":"Red Robin Gourmet Burgers",
    "wof:placetype":"venue"
},
  "geometry": {"coordinates":[-86.640968,33.60796],"type":"Point"}
}