{
  "type": "Feature",
  "properties": {
    "iso:country":"US",
    "sg:address":"3601 Stillman Blvd",
    "sg:city":"Tuscaloosa",
    "sg:classifiers":[
        {
            "category":"Education",
            "subcategory":"College",
            "type":"Public Place"
        }
    ],
    "sg:phone":"+1 205 349 4240",
    "sg:postcode":"35401",
    "sg:province":"AL",
    "sg:tags":[
        "academic",
        "school"
    ],
    "sg:website":"www.stillman.edu",
    "wof:name":"Stillman College",
    "wof:placetype":"venue"
},
  "geometry": {"coordinates":[-87.583128,33.200865],"type":"Point"}
}