{
  "type": "Feature",
  "properties": {
    "iso:country":"US",
    "sg:address":"1726 Webster St",
    "sg:city":"Muscle Shoals",
    "sg:classifiers":[
        {
            "category":"Building & Trades",
            "subcategory":"Construction",
            "type":"Services"
        }
    ],
    "sg:phone":"+1 256 381 2075",
    "sg:postcode":"35661",
    "sg:province":"AL",
    "sg:tags":[
        "insulation",
        "plastering",
        "drywall"
    ],
    "wof:name":"Custom Quality Insulation",
    "wof:placetype":"venue"
},
  "geometry": {"coordinates":[-87.620662,34.743698],"type":"Point"}
}