{
  "type": "Feature",
  "properties": {
    "iso:country":"US",
    "sg:address":"35 S Haardt Dr",
    "sg:city":"Montgomery",
    "sg:classifiers":[
        {
            "category":"Personal",
            "subcategory":"Beauty Salon",
            "type":"Services"
        }
    ],
    "sg:phone":"+1 334 262 5998",
    "sg:postcode":"36105",
    "sg:province":"AL",
    "sg:tags":[
        "shop"
    ],
    "wof:name":"Golden Comb Beauty Salon",
    "wof:placetype":"venue"
},
  "geometry": {"coordinates":[-86.31088699999999,32.343259],"type":"Point"}
}