{
  "type": "Feature",
  "properties": {
    "iso:country":"US",
    "sg:address":"128 Branch Dr",
    "sg:city":"Chelsea",
    "sg:classifiers":[
        {
            "category":"Professional",
            "type":"Services"
        }
    ],
    "sg:phone":"+1 205 678 7142",
    "sg:postcode":"35043",
    "sg:province":"AL",
    "wof:name":"San Oil Inc",
    "wof:placetype":"venue"
},
  "geometry": {"coordinates":[-86.628725,33.329089],"type":"Point"}
}