{
  "type": "Feature",
  "properties": {
    "addr:full":"126 Crow St Anniston AL 36201",
    "addr:housenumber":"126",
    "addr:postcode":"36201",
    "addr:street":"Crow St",
    "iso:country":"US",
    "sg:address":"126 Crow St",
    "sg:city":"Anniston",
    "sg:classifiers":[
        {
            "category":"Building & Trades",
            "subcategory":"Plumbing",
            "type":"Services"
        }
    ],
    "sg:phone":"+1 256 237 6643",
    "sg:postcode":"36201",
    "sg:province":"AL",
    "sg:tags":[
        "conditioning",
        "air",
        "system",
        "contractor"
    ],
    "wof:name":"Melson Heating & Cooling",
    "wof:placetype":"venue"
},
  "geometry": {"coordinates":[-85.88641800000001,33.6404],"type":"Point"}
}