{
  "type": "Feature",
  "properties": {
    "addr:full":"4000 Eagle Point Corporate Dr Birmingham AL 35242",
    "addr:housenumber":"4000",
    "addr:postcode":"35242",
    "addr:street":"Eagle Point Corporate Dr",
    "iso:country":"US",
    "sg:address":"4000 Eagle Point Corporate Dr",
    "sg:city":"Birmingham",
    "sg:classifiers":[
        {
            "category":"Professional",
            "subcategory":"Employment Agencies",
            "type":"Services"
        }
    ],
    "sg:phone":"+1 205 991 7456",
    "sg:postcode":"35242",
    "sg:province":"AL",
    "sg:tags":[
        "opportunity"
    ],
    "wof:name":"Taylor D & Associates Inc",
    "wof:placetype":"venue"
},
  "geometry": {"coordinates":[-86.665161,33.399811],"type":"Point"}
}