{
  "type": "Feature",
  "properties": {
    "addr:full":"301 Selma Rd Montevallo AL 35115",
    "addr:housenumber":"301",
    "addr:postcode":"35115",
    "addr:street":"Selma Rd",
    "iso:country":"US",
    "sg:address":"301 Selma Rd",
    "sg:city":"Montevallo",
    "sg:classifiers":[
        {
            "category":"Organizations",
            "subcategory":"Religious Organization",
            "type":"Services"
        }
    ],
    "sg:phone":"+1 205 665 5919",
    "sg:postcode":"35115",
    "sg:province":"AL",
    "sg:tags":[
        "church"
    ],
    "wof:name":"Faith Temple Deliverance",
    "wof:placetype":"venue"
},
  "geometry": {"coordinates":[-86.865347,33.095167],"type":"Point"}
}