{
  "type": "Feature",
  "properties": {
    "addr:full":"1710 1st Ave N Birmingham AL 35203",
    "addr:housenumber":"1710",
    "addr:postcode":"35203",
    "addr:street":"1St Ave N",
    "iso:country":"US",
    "sg:address":"1710 1st Ave N",
    "sg:city":"Birmingham",
    "sg:classifiers":[
        {
            "category":"Education",
            "subcategory":"Library",
            "type":"Public Place"
        }
    ],
    "sg:phone":"+1 205 254 1700",
    "sg:postcode":"35203",
    "sg:province":"AL",
    "sg:website":"http://www.jazzhall.com",
    "wof:name":"Public Library",
    "wof:placetype":"venue"
},
  "geometry": {"coordinates":[-86.80980700000001,33.512519],"type":"Point"}
}