{
  "type": "Feature",
  "properties": {
    "iso:country":"US",
    "sg:address":"7646 Cottonridge Rd",
    "sg:city":"Trussville",
    "sg:classifiers":[
        {
            "category":"Building & Trades",
            "subcategory":"Plumbing",
            "type":"Services"
        }
    ],
    "sg:phone":"+1 205 655 8350",
    "sg:postcode":"35173",
    "sg:province":"AL",
    "sg:tags":[
        "contractor"
    ],
    "wof:name":"Will & Pierce Agency",
    "wof:placetype":"venue"
},
  "geometry": {"coordinates":[-86.558037,33.662538],"type":"Point"}
}