{
  "type": "Feature",
  "properties": {
    "addr:full":"114 4th St SW Cullman AL 35070",
    "addr:housenumber":"114",
    "addr:postcode":"35070",
    "addr:street":"4Th St Sw",
    "iso:country":"US",
    "sg:address":"114 4th St SW",
    "sg:city":"Cullman",
    "sg:classifiers":[
        {
            "category":"Shopping",
            "subcategory":"Bicycles & Sporting Goods",
            "type":"Retail Goods"
        }
    ],
    "sg:phone":"+1 256 775 7657",
    "sg:postcode":"35070",
    "sg:province":"AL",
    "wof:name":"Jason Green Skateboards",
    "wof:placetype":"venue"
},
  "geometry": {"coordinates":[-86.750175,34.011879],"type":"Point"}
}