{
  "type": "Feature",
  "properties": {
    "iso:country":"US",
    "sg:address":"131 Main St",
    "sg:city":"Trussville",
    "sg:classifiers":[
        {
            "category":"Government",
            "subcategory":"Office",
            "type":"Public Place"
        }
    ],
    "sg:phone":"+1 205 655 7478",
    "sg:postcode":"35173",
    "sg:province":"AL",
    "sg:tags":[
        "legislative",
        "executive",
        "except",
        "general"
    ],
    "wof:name":"City of Trussville",
    "wof:placetype":"venue"
},
  "geometry": {"coordinates":[-86.599662,33.6222],"type":"Point"}
}