{
  "type": "Feature",
  "properties": {
    "addr:full":"884 Craze Rd Hartselle AL 35640",
    "addr:housenumber":"884",
    "addr:postcode":"35640",
    "addr:street":"Craze Rd",
    "iso:country":"US",
    "sg:address":"884 Craze Rd",
    "sg:city":"Hartselle",
    "sg:classifiers":[
        {
            "category":"Wholesale",
            "subcategory":"Durable Goods & Equipment",
            "type":"Manufacturing & Wholesale Goods"
        }
    ],
    "sg:phone":"+1 256 773 0744",
    "sg:postcode":"35640",
    "sg:province":"AL",
    "sg:tags":[
        "laboratory",
        "supply"
    ],
    "wof:name":"Anesco",
    "wof:placetype":"venue"
},
  "geometry": {"coordinates":[-87.060084,34.448542],"type":"Point"}
}