{
  "type": "Feature",
  "properties": {
    "iso:country":"US",
    "sg:address":"1254 Montlimar Dr",
    "sg:city":"Mobile",
    "sg:classifiers":[
        {
            "category":"Food & Beverages",
            "subcategory":"Groceries & Convenience Stores",
            "type":"Retail Goods"
        }
    ],
    "sg:phone":"+1 251 343 2602",
    "sg:postcode":"36609",
    "sg:province":"AL",
    "wof:name":"Lions Pride",
    "wof:placetype":"venue"
},
  "geometry": {"coordinates":[-88.133275,30.669874],"type":"Point"}
}