{
  "type": "Feature",
  "properties": {
    "iso:country":"US",
    "sg:address":"158 Valley Loop",
    "sg:city":"Winfield",
    "sg:classifiers":[
        {
            "category":"Autos & Motor Vehicles",
            "subcategory":"Fuel & Gas Station",
            "type":"Retail Goods"
        }
    ],
    "sg:phone":"+1 205 487 5424",
    "sg:postcode":"35594",
    "sg:province":"AL",
    "sg:tags":[
        "station",
        "gasoline"
    ],
    "wof:name":"Jbs",
    "wof:placetype":"venue"
},
  "geometry": {"coordinates":[-87.832348,33.945821],"type":"Point"}
}