{
  "type": "Feature",
  "properties": {
    "iso:country":"US",
    "sg:address":"440 Weogufka Rd",
    "sg:city":"Sylacauga",
    "sg:classifiers":[
        {
            "category":"Building & Trades",
            "subcategory":"Plumbing",
            "type":"Services"
        }
    ],
    "sg:phone":"+1 256 245 3120",
    "sg:postcode":"35151",
    "sg:province":"AL",
    "sg:tags":[
        "conditioning",
        "air",
        "electrical",
        "heating",
        "contractor"
    ],
    "wof:name":"Bailey Cecil Heating & AC Svc",
    "wof:placetype":"venue"
},
  "geometry": {"coordinates":[-86.247578,33.078669],"type":"Point"}
}