{
  "type": "Feature",
  "properties": {
    "iso:country":"US",
    "sg:address":"103 S Edgewood Dr",
    "sg:city":"Dothan",
    "sg:classifiers":[
        {
            "category":"Real Estate",
            "subcategory":"Developer",
            "type":"Services"
        }
    ],
    "sg:phone":"+1 334 793 9772",
    "sg:postcode":"36301",
    "sg:province":"AL",
    "sg:tags":[
        "cemetery",
        "merchandise"
    ],
    "wof:name":"Blue Boys Pet Cemetary",
    "wof:placetype":"venue"
},
  "geometry": {"coordinates":[-85.404358,31.225318],"type":"Point"}
}