{
  "type": "Feature",
  "properties": {
    "iso:country":"US",
    "sg:address":"2927 27th St N",
    "sg:city":"Birmingham",
    "sg:classifiers":[
        {
            "category":"Shopping",
            "subcategory":"Shoes",
            "type":"Retail Goods"
        }
    ],
    "sg:phone":"+1 205 322 7382",
    "sg:postcode":"35207",
    "sg:province":"AL",
    "wof:name":"Fashion Shoe Center",
    "wof:placetype":"venue"
},
  "geometry": {"coordinates":[-86.816138,33.551466],"type":"Point"}
}