{
  "type": "Feature",
  "properties": {
    "iso:country":"US",
    "sg:address":"2862 Dauphin St",
    "sg:city":"Mobile",
    "sg:classifiers":[
        {
            "category":"Banks & Credit Unions",
            "subcategory":"Investment Brokerage",
            "type":"Services"
        }
    ],
    "sg:phone":"+1 251 472 2800",
    "sg:postcode":"36606",
    "sg:province":"AL",
    "sg:tags":[
        "stock",
        "bond"
    ],
    "wof:name":"Morgan Stanley",
    "wof:placetype":"venue"
},
  "geometry": {"coordinates":[-88.109359,30.688523],"type":"Point"}
}