{
  "type": "Feature",
  "properties": {
    "addr:full":"3441 Radcliff Rd Saraland AL 36571",
    "addr:housenumber":"3441",
    "addr:postcode":"36571",
    "addr:street":"Radcliff Rd",
    "iso:country":"US",
    "sg:address":"3441 Radcliff Rd",
    "sg:city":"Saraland",
    "sg:classifiers":[
        {
            "category":"Manufacturing",
            "subcategory":"Metals",
            "type":"Manufacturing & Wholesale Goods"
        }
    ],
    "sg:phone":"+1 251 675 3811",
    "sg:postcode":"36571",
    "sg:province":"AL",
    "sg:tags":[
        "product",
        "fabricated",
        "mfg"
    ],
    "wof:name":"Deans David Woodworks",
    "wof:placetype":"venue"
},
  "geometry": {"coordinates":[-88.086476,30.891268],"type":"Point"}
}