{
  "type": "Feature",
  "properties": {
    "addr:full":"605 Springville Rd Birmingham AL 35215",
    "addr:housenumber":"605",
    "addr:postcode":"35215",
    "addr:street":"Springville Rd",
    "iso:country":"US",
    "sg:address":"605 Springville Rd",
    "sg:city":"Birmingham",
    "sg:classifiers":[
        {
            "category":"Shopping",
            "type":"Retail Goods"
        }
    ],
    "sg:phone":"+1 205 854 7854",
    "sg:postcode":"35215",
    "sg:province":"AL",
    "sg:tags":[
        "merchandise"
    ],
    "wof:name":"All Sports Trophy & Plaques",
    "wof:placetype":"venue"
},
  "geometry": {"coordinates":[-86.687427,33.608046],"type":"Point"}
}