{
  "type": "Feature",
  "properties": {
    "addr:full":"10 Westminster Way Mobile AL 36608",
    "addr:housenumber":"10",
    "addr:postcode":"36608",
    "addr:street":"Westminster Way",
    "iso:country":"US",
    "sg:address":"10 Westminster Way",
    "sg:city":"Mobile",
    "sg:classifiers":[
        {
            "category":"Organizations",
            "subcategory":"Religious Organization",
            "type":"Services"
        }
    ],
    "sg:phone":"+1 251 342 1550",
    "sg:postcode":"36608",
    "sg:province":"AL",
    "sg:tags":[
        "church"
    ],
    "sg:website":"www.springhillpresbyterian.org",
    "wof:name":"Spring Hill Presbyterian Chr",
    "wof:placetype":"venue"
},
  "geometry": {"coordinates":[-88.162859,30.689529],"type":"Point"}
}