{
  "type": "Feature",
  "properties": {
    "addr:full":"208 Daryl St Livingston AL 35470",
    "addr:housenumber":"208",
    "addr:postcode":"35470",
    "addr:street":"Daryl St",
    "iso:country":"US",
    "sg:address":"208 Daryl St",
    "sg:city":"Livingston",
    "sg:classifiers":[
        {
            "category":"Education",
            "subcategory":"School",
            "type":"Public Place"
        }
    ],
    "sg:phone":"+1 205 652 2748",
    "sg:postcode":"35470",
    "sg:province":"AL",
    "wof:name":"Tarakji Hs VT Inc Tste",
    "wof:placetype":"venue"
},
  "geometry": {"coordinates":[-88.201847,32.607538],"type":"Point"}
}