{
  "type": "Feature",
  "properties": {
    "addr:full":"1415 Main St Greensboro AL 36744",
    "addr:housenumber":"1415",
    "addr:postcode":"36744",
    "addr:street":"Main St",
    "iso:country":"US",
    "sg:address":"1415 Main St",
    "sg:city":"Greensboro",
    "sg:classifiers":[
        {
            "category":"Manufacturing",
            "subcategory":"Printing",
            "type":"Manufacturing & Wholesale Goods"
        }
    ],
    "sg:phone":"+1 334 624 3021",
    "sg:postcode":"36744",
    "sg:province":"AL",
    "sg:tags":[
        "newspaper"
    ],
    "wof:name":"Hale County Faith Tribune",
    "wof:placetype":"venue"
},
  "geometry": {"coordinates":[-87.59634800000001,32.704236],"type":"Point"}
}