{
  "type": "Feature",
  "properties": {
    "addr:full":"1002 Huntington Cir NW Arab AL 35016",
    "addr:housenumber":"1002",
    "addr:postcode":"35016",
    "addr:street":"Huntington Cir Nw",
    "iso:country":"US",
    "sg:address":"1002 Huntington Cir NW",
    "sg:city":"Arab",
    "sg:classifiers":[
        {
            "category":"Professional",
            "type":"Services"
        }
    ],
    "sg:phone":"+1 256 586 7293",
    "sg:postcode":"35016",
    "sg:province":"AL",
    "wof:name":"Commonwealth Financial Network",
    "wof:placetype":"venue"
},
  "geometry": {"coordinates":[-86.515019,34.333697],"type":"Point"}
}