{
  "type": "Feature",
  "properties": {
    "iso:country":"US",
    "sg:address":"4104 Coffee Dr SW",
    "sg:city":"Huntsville",
    "sg:classifiers":[
        {
            "category":"Professional",
            "subcategory":"Management & Consulting",
            "type":"Services"
        }
    ],
    "sg:phone":"+1 256 529 2626",
    "sg:postcode":"35805",
    "sg:province":"AL",
    "wof:name":"TCI",
    "wof:placetype":"venue"
},
  "geometry": {"coordinates":[-86.624433,34.710318],"type":"Point"}
}