{
  "type": "Feature",
  "properties": {
    "addr:full":"254 Stewart Rd Toney AL 35773",
    "addr:housenumber":"254",
    "addr:postcode":"35773",
    "addr:street":"Stewart Rd",
    "iso:country":"US",
    "sg:address":"254 Stewart Rd",
    "sg:city":"Toney",
    "sg:classifiers":[
        {
            "category":"Building & Trades",
            "subcategory":"Construction",
            "type":"Services"
        }
    ],
    "sg:phone":"+1 256 852 6689",
    "sg:postcode":"35773",
    "sg:province":"AL",
    "sg:tags":[
        "house"
    ],
    "wof:name":"Allphaze Construction & Remode",
    "wof:placetype":"venue"
},
  "geometry": {"coordinates":[-86.61015500000001,34.835729],"type":"Point"}
}