{
  "type": "Feature",
  "properties": {
    "iso:country":"US",
    "sg:address":"22 Inverness Center Pkwy",
    "sg:city":"Birmingham",
    "sg:classifiers":[
        {
            "category":"Professional",
            "subcategory":"Management & Consulting",
            "type":"Services"
        }
    ],
    "sg:phone":"+1 205 995 0519",
    "sg:postcode":"35242",
    "sg:province":"AL",
    "sg:tags":[
        "personnel",
        "consultant"
    ],
    "wof:name":"ASAP Staffing LLC",
    "wof:placetype":"venue"
},
  "geometry": {"coordinates":[-86.705004,33.423485],"type":"Point"}
}