{
  "type": "Feature",
  "properties": {
    "iso:country":"US",
    "sg:address":"127 Louisa St",
    "sg:city":"Warrior",
    "sg:classifiers":[
        {
            "category":"Personal",
            "type":"Services"
        }
    ],
    "sg:phone":"+1 205 647 4540",
    "sg:postcode":"35180",
    "sg:province":"AL",
    "wof:name":"Xtreme Tan",
    "wof:placetype":"venue"
},
  "geometry": {"coordinates":[-86.809394,33.812308],"type":"Point"}
}