{
  "type": "Feature",
  "properties": {
    "iso:country":"US",
    "sg:address":"100 Elm St",
    "sg:city":"Abbeville",
    "sg:classifiers":[
        {
            "category":"Education",
            "subcategory":"School",
            "type":"Public Place"
        }
    ],
    "sg:phone":"+1 334 585 3679",
    "sg:postcode":"36310",
    "sg:province":"AL",
    "wof:name":"Abbeville Elementary School",
    "wof:placetype":"venue"
},
  "geometry": {"coordinates":[-85.248661,31.567258],"type":"Point"}
}