{
  "type": "Feature",
  "properties": {
    "iso:country":"US",
    "sg:address":"401 3rd Ave",
    "sg:city":"Ashford",
    "sg:classifiers":[
        {
            "category":"Professional",
            "subcategory":"Computer Services",
            "type":"Services"
        }
    ],
    "sg:phone":"+1 334 899 3333",
    "sg:postcode":"36312",
    "sg:province":"AL",
    "sg:tags":[
        "isp",
        "provider",
        "internet"
    ],
    "wof:name":"Internet By Gracebasnowhill",
    "wof:placetype":"venue"
},
  "geometry": {"coordinates":[-85.23671,31.18611],"type":"Point"}
}