{
  "type": "Feature",
  "properties": {
    "iso:country":"US",
    "sg:address":"10308 Leicester Dr SW",
    "sg:city":"Huntsville",
    "sg:classifiers":[
        {
            "category":"Wholesale",
            "subcategory":"Drugs",
            "type":"Manufacturing & Wholesale Goods"
        }
    ],
    "sg:phone":"+1 256 882 6530",
    "sg:postcode":"35803",
    "sg:province":"AL",
    "wof:name":"Talk Minerals",
    "wof:placetype":"venue"
},
  "geometry": {"coordinates":[-86.57072,34.625474],"type":"Point"}
}