{
  "type": "Feature",
  "properties": {
    "addr:full":"10308 Leicester Dr SW Huntsville AL 35803",
    "addr:housenumber":"10308",
    "addr:postcode":"35803",
    "addr:street":"Leicester Dr Sw",
    "iso:country":"US",
    "sg:address":"10308 Leicester Dr SW",
    "sg:city":"Huntsville",
    "sg:classifiers":[
        {
            "category":"Wholesale",
            "subcategory":"Drugs",
            "type":"Manufacturing & Wholesale Goods"
        }
    ],
    "sg:phone":"+1 256 882 6530",
    "sg:postcode":"35803",
    "sg:province":"AL",
    "wof:name":"Talk Minerals",
    "wof:placetype":"venue"
},
  "geometry": {"coordinates":[-86.57071999999999,34.625474],"type":"Point"}
}