{
  "type": "Feature",
  "properties": {
    "iso:country":"US",
    "sg:address":"295 Kowaliga Marina Rd",
    "sg:city":"Alexander City",
    "sg:classifiers":[
        {
            "category":"Restaurant",
            "type":"Food & Drink"
        }
    ],
    "sg:menulink":"http://www.allmenus.com/al/alexander-city/55346-sinclairs-kowaliga/menu/",
    "sg:phone":"+1 334 857 2889",
    "sg:postcode":"35010",
    "sg:province":"AL",
    "sg:tags":[
        "american"
    ],
    "wof:name":"Sinclair's Kowaliga",
    "wof:placetype":"venue"
},
  "geometry": {"coordinates":[-85.93773400000001,32.858638],"type":"Point"}
}