{
  "type": "Feature",
  "properties": {
    "iso:country":"US",
    "sg:address":"79 Kennedy St",
    "sg:city":"Cullman",
    "sg:classifiers":[
        {
            "category":"Professional",
            "subcategory":"Business Services",
            "type":"Services"
        }
    ],
    "sg:phone":"+1 256 734 0896",
    "sg:postcode":"35058",
    "sg:province":"AL",
    "wof:name":"Mml Enterprises",
    "wof:placetype":"venue"
},
  "geometry": {"coordinates":[-86.863022,34.242514],"type":"Point"}
}