{
  "type": "Feature",
  "properties": {
    "iso:country":"US",
    "sg:address":"300 Medical Center Dr",
    "sg:city":"Gadsden",
    "sg:classifiers":[
        {
            "category":"Health Services",
            "subcategory":"Doctor",
            "type":"Services"
        }
    ],
    "sg:phone":"+1 256 492 3220",
    "sg:postcode":"35903",
    "sg:province":"AL",
    "sg:tags":[
        "medical"
    ],
    "wof:name":"Digestive Disease Specialist",
    "wof:placetype":"venue"
},
  "geometry": {"coordinates":[-85.965355,34.00869],"type":"Point"}
}