{
  "type": "Feature",
  "properties": {
    "iso:country":"US",
    "sg:address":"401 Hamric Dr W",
    "sg:city":"Oxford",
    "sg:classifiers":[
        {
            "category":"Building & Trades",
            "subcategory":"Pest Control",
            "type":"Services"
        }
    ],
    "sg:phone":"+1 256 831 2037",
    "sg:postcode":"36203",
    "sg:province":"AL",
    "wof:name":"Orkin Exterminating Co",
    "wof:placetype":"venue"
},
  "geometry": {"coordinates":[-85.85630999999999,33.60112],"type":"Point"}
}