{
  "type": "Feature",
  "properties": {
    "iso:country":"US",
    "sg:address":"3735 Gulf Shores Pkwy",
    "sg:city":"Gulf Shores",
    "sg:classifiers":[
        {
            "category":"Personal",
            "subcategory":"Beauty Salon",
            "type":"Services"
        }
    ],
    "sg:phone":"+1 251 968 2887",
    "sg:postcode":"36542",
    "sg:province":"AL",
    "wof:name":"Sea Clipper Hair Styles",
    "wof:placetype":"venue"
},
  "geometry": {"coordinates":[-87.683248,30.304956],"type":"Point"}
}