{
  "type": "Feature",
  "properties": {
    "iso:country":"US",
    "sg:address":"303 E Meighan Blvd",
    "sg:city":"Gadsden",
    "sg:classifiers":[
        {
            "category":"Restaurant",
            "type":"Food & Drink"
        }
    ],
    "sg:menulink":"http://www.allmenus.com/al/gadsden/163456-rallys/menu/",
    "sg:phone":"+1 205 547 5773",
    "sg:postcode":"35903",
    "sg:province":"AL",
    "sg:tags":[
        "sandwich",
        "dog",
        "burger",
        "hot",
        "wrap",
        "american"
    ],
    "wof:name":"Rally's",
    "wof:placetype":"venue"
},
  "geometry": {"coordinates":[-85.989285,34.010033],"type":"Point"}
}