{
  "type": "Feature",
  "properties": {
    "addr:full":"3407 Lorna Ln Birmingham AL 35216",
    "addr:housenumber":"3407",
    "addr:postcode":"35216",
    "addr:street":"Lorna Ln",
    "iso:country":"US",
    "sg:address":"3407 Lorna Ln",
    "sg:city":"Birmingham",
    "sg:classifiers":[
        {
            "category":"Wholesale",
            "subcategory":"Office Equipment",
            "type":"Manufacturing & Wholesale Goods"
        }
    ],
    "sg:phone":"+1 205 979 5679",
    "sg:postcode":"35216",
    "sg:province":"AL",
    "sg:tags":[
        "machine",
        "duplicating",
        "copying"
    ],
    "wof:name":"Graphic Corporation",
    "wof:placetype":"venue"
},
  "geometry": {"coordinates":[-86.794651,33.393381],"type":"Point"}
}