{
  "type": "Feature",
  "properties": {
    "addr:full":"2800 Hickory St Gadsden AL 35904",
    "addr:housenumber":"2800",
    "addr:postcode":"35904",
    "addr:street":"Hickory St",
    "iso:country":"US",
    "sg:address":"2800 Hickory St",
    "sg:city":"Gadsden",
    "sg:classifiers":[
        {
            "category":"Personal",
            "subcategory":"Beauty Salon",
            "type":"Services"
        }
    ],
    "sg:phone":"+1 256 546 0533",
    "sg:postcode":"35904",
    "sg:province":"AL",
    "sg:tags":[
        "shop"
    ],
    "wof:name":"Beauty Xposure Laboratories LL",
    "wof:placetype":"venue"
},
  "geometry": {"coordinates":[-86.046751,34.006921],"type":"Point"}
}