{
  "type": "Feature",
  "properties": {
    "iso:country":"US",
    "sg:address":"113 1st St NE",
    "sg:city":"Vernon",
    "sg:classifiers":[
        {
            "category":"Shopping",
            "subcategory":"Gifts & Souvenirs",
            "type":"Retail Goods"
        }
    ],
    "sg:phone":"+1 205 695 7324",
    "sg:postcode":"35592",
    "sg:province":"AL",
    "sg:tags":[
        "shop"
    ],
    "wof:name":"Debbie's Special Gifts",
    "wof:placetype":"venue"
},
  "geometry": {"coordinates":[-88.108271,33.757041],"type":"Point"}
}