{
  "type": "Feature",
  "properties": {
    "addr:full":"617 Montevallo Rd Alabaster AL 35007",
    "addr:housenumber":"617",
    "addr:postcode":"35007",
    "addr:street":"Montevallo Rd",
    "iso:country":"US",
    "sg:address":"617 Montevallo Rd",
    "sg:city":"Alabaster",
    "sg:classifiers":[
        {
            "category":"Personal",
            "subcategory":"Barber",
            "type":"Services"
        }
    ],
    "sg:phone":"+1 205 664 4956",
    "sg:postcode":"35007",
    "sg:province":"AL",
    "sg:tags":[
        "shop"
    ],
    "wof:name":"Modernistic Hair Desgin",
    "wof:placetype":"venue"
},
  "geometry": {"coordinates":[-86.818642,33.237895],"type":"Point"}
}