{
  "type": "Feature",
  "properties": {
    "addr:full":"1605 Center Point Pkwy Birmingham AL 35215",
    "addr:housenumber":"1605",
    "addr:postcode":"35215",
    "addr:street":"Center Point Pkwy",
    "iso:country":"US",
    "sg:address":"1605 Center Point Pkwy",
    "sg:city":"Birmingham",
    "sg:classifiers":[
        {
            "category":"Personal",
            "subcategory":"Beauty Salon",
            "type":"Services"
        }
    ],
    "sg:phone":"+1 205 853 1245",
    "sg:postcode":"35215",
    "sg:province":"AL",
    "sg:tags":[
        "shop"
    ],
    "wof:name":"Creative Hair Design",
    "wof:placetype":"venue"
},
  "geometry": {"coordinates":[-86.684854,33.63084],"type":"Point"}
}