{
  "type": "Feature",
  "properties": {
    "iso:country":"US",
    "sg:address":"1432 Westgate Pkwy",
    "sg:city":"Dothan",
    "sg:classifiers":[
        {
            "category":"Health Services",
            "subcategory":"Optometrist",
            "type":"Services"
        }
    ],
    "sg:phone":"+1 334 677 3937",
    "sg:postcode":"36303",
    "sg:province":"AL",
    "wof:name":"Advanced Eye Care",
    "wof:placetype":"venue"
},
  "geometry": {"coordinates":[-85.433803,31.256371],"type":"Point"}
}