{
  "type": "Feature",
  "properties": {
    "addr:full":"1518 Brown Ave Anniston AL 36201",
    "addr:housenumber":"1518",
    "addr:postcode":"36201",
    "addr:street":"Brown Ave",
    "iso:country":"US",
    "sg:address":"1518 Brown Ave",
    "sg:city":"Anniston",
    "sg:classifiers":[
        {
            "category":"Retail",
            "subcategory":"Funeral Services",
            "type":"Services"
        }
    ],
    "sg:phone":"+1 256 237 1717",
    "sg:postcode":"36201",
    "sg:province":"AL",
    "sg:tags":[
        "director"
    ],
    "wof:name":"Ervin Funeral Chapel",
    "wof:placetype":"venue"
},
  "geometry": {"coordinates":[-85.845851,33.663854],"type":"Point"}
}