{
  "type": "Feature",
  "properties": {
    "iso:country":"US",
    "sg:address":"1177 Denton Rd",
    "sg:city":"Dothan",
    "sg:classifiers":[
        {
            "category":"Retail",
            "subcategory":"Car Wash",
            "type":"Services"
        }
    ],
    "sg:phone":"+1 334 699 1663",
    "sg:postcode":"36303",
    "sg:province":"AL",
    "sg:tags":[
        "carwash"
    ],
    "wof:name":"Ronnie Clean Cars",
    "wof:placetype":"venue"
},
  "geometry": {"coordinates":[-85.407653,31.239292],"type":"Point"}
}