{
  "type": "Feature",
  "properties": {
    "addr:full":"2046 Springdale Ln Birmingham AL 35217",
    "addr:housenumber":"2046",
    "addr:postcode":"35217",
    "addr:street":"Springdale Ln",
    "iso:country":"US",
    "sg:address":"2046 Springdale Ln",
    "sg:city":"Birmingham",
    "sg:classifiers":[
        {
            "category":"Autos & Motor Vehicles",
            "subcategory":"Auto Supplies",
            "type":"Retail Goods"
        }
    ],
    "sg:phone":"+1 205 841 3237",
    "sg:postcode":"35217",
    "sg:province":"AL",
    "sg:tags":[
        "automobile",
        "parts"
    ],
    "sg:website":"www.autozone.com",
    "wof:name":"Autozone",
    "wof:placetype":"venue"
},
  "geometry": {"coordinates":[-86.768331,33.588565],"type":"Point"}
}