{
  "type": "Feature",
  "properties": {
    "addr:full":"2101 Ave C Birmingham AL 35218",
    "addr:housenumber":"2101",
    "addr:postcode":"35218",
    "addr:street":"Ave C",
    "iso:country":"US",
    "sg:address":"2101 Ave C",
    "sg:city":"Birmingham",
    "sg:classifiers":[
        {
            "category":"Social Services",
            "subcategory":"Child Care",
            "type":"Services"
        }
    ],
    "sg:phone":"+1 205 780 4880",
    "sg:postcode":"35218",
    "sg:province":"AL",
    "sg:tags":[
        "day"
    ],
    "wof:name":"Wee Manage Tuxedo Pre School",
    "wof:placetype":"venue"
},
  "geometry": {"coordinates":[-86.90093400000001,33.511746],"type":"Point"}
}