{
  "type": "Feature",
  "properties": {
    "addr:full":"2 Xavier Cir Birmingham AL 35213",
    "addr:housenumber":"2",
    "addr:postcode":"35213",
    "addr:street":"Xavier Cir",
    "iso:country":"US",
    "sg:address":"2 Xavier Cir",
    "sg:city":"Birmingham",
    "sg:classifiers":[
        {
            "category":"Education",
            "subcategory":"School",
            "type":"Public Place"
        }
    ],
    "sg:phone":"+1 205 871 1687",
    "sg:postcode":"35213",
    "sg:province":"AL",
    "sg:tags":[
        "organization",
        "religious"
    ],
    "wof:name":"St Francis Xavier School",
    "wof:placetype":"venue"
},
  "geometry": {"coordinates":[-86.741924,33.515341],"type":"Point"}
}