{
  "type": "Feature",
  "properties": {
    "addr:full":"82 Cullman Rd Arab AL 35016",
    "addr:housenumber":"82",
    "addr:postcode":"35016",
    "addr:street":"Cullman Rd",
    "iso:country":"US",
    "sg:address":"82 Cullman Rd",
    "sg:city":"Arab",
    "sg:classifiers":[
        {
            "category":"Shopping",
            "subcategory":"Gifts & Souvenirs",
            "type":"Retail Goods"
        }
    ],
    "sg:phone":"+1 256 931 2498",
    "sg:postcode":"35016",
    "sg:province":"AL",
    "wof:name":"Cupboard",
    "wof:placetype":"venue"
},
  "geometry": {"coordinates":[-86.496968,34.316634],"type":"Point"}
}