{
  "type": "Feature",
  "properties": {
    "addr:full":"303 Jordan Ln NW Huntsville AL 35805",
    "addr:housenumber":"303",
    "addr:postcode":"35805",
    "addr:street":"Jordan Ln Nw",
    "iso:country":"US",
    "sg:address":"303 Jordan Ln NW",
    "sg:city":"Huntsville",
    "sg:classifiers":[
        {
            "category":"Retail",
            "subcategory":"Repair Shop",
            "type":"Services"
        }
    ],
    "sg:phone":"+1 256 830 5937",
    "sg:postcode":"35805",
    "sg:province":"AL",
    "sg:tags":[
        "equipment",
        "locksmith",
        "lock"
    ],
    "wof:name":"Blair & Son Locksmith Svc",
    "wof:placetype":"venue"
},
  "geometry": {"coordinates":[-86.627644,34.723163],"type":"Point"}
}