{
  "type": "Feature",
  "properties": {
    "iso:country":"US",
    "sg:address":"8020 Moffett Rd",
    "sg:city":"Semmes",
    "sg:classifiers":[
        {
            "category":"Personal",
            "subcategory":"Beauty Salon",
            "type":"Services"
        }
    ],
    "sg:phone":"+1 251 645 2878",
    "sg:postcode":"36575",
    "sg:province":"AL",
    "sg:tags":[
        "shop"
    ],
    "wof:name":"Becky's Kreative Kuts",
    "wof:placetype":"venue"
},
  "geometry": {"coordinates":[-88.228099,30.764513],"type":"Point"}
}