{
  "type": "Feature",
  "properties": {
    "iso:country":"US",
    "sg:address":"137 Oxmoor Rd",
    "sg:city":"Homewood",
    "sg:classifiers":[
        {
            "category":"Retail",
            "subcategory":"Auto Repair",
            "type":"Services"
        }
    ],
    "sg:phone":"+1 205 916 2867",
    "sg:postcode":"35209",
    "sg:province":"AL",
    "sg:tags":[
        "automobile",
        "customizing"
    ],
    "wof:name":"DWD Plastics",
    "wof:placetype":"venue"
},
  "geometry": {"coordinates":[-86.832741,33.458917],"type":"Point"}
}