{
  "type": "Feature",
  "properties": {
    "iso:country":"US",
    "sg:address":"640 Grant St",
    "sg:city":"Bessemer",
    "sg:classifiers":[
        {
            "category":"Building & Trades",
            "subcategory":"Construction",
            "type":"Services"
        },
        {
            "category":"Recreation",
            "type":"Entertainment"
        }
    ],
    "sg:phone":"+1 205 481 9999",
    "sg:postcode":"35020",
    "sg:province":"AL",
    "sg:tags":[
        "heavy",
        "fishing",
        "lake"
    ],
    "wof:name":"Grant Street Fish Farm Market",
    "wof:placetype":"venue"
},
  "geometry": {"coordinates":[-86.982189,33.359147],"type":"Point"}
}