{
  "type": "Feature",
  "properties": {
    "addr:full":"411 Hughes Dr Huntsville AL 35808",
    "addr:housenumber":"411",
    "addr:postcode":"35808",
    "addr:street":"Hughes Dr",
    "iso:country":"US",
    "sg:address":"411 Hughes Dr",
    "sg:city":"Huntsville",
    "sg:classifiers":[
        {
            "category":"Professional",
            "type":"Services"
        }
    ],
    "sg:phone":"+1 256 772 8525",
    "sg:postcode":"35808",
    "sg:province":"AL",
    "sg:tags":[
        "establishment"
    ],
    "wof:name":"Big Tease",
    "wof:placetype":"venue"
},
  "geometry": {"coordinates":[-86.645231,34.706153],"type":"Point"}
}