{
  "type": "Feature",
  "properties": {
    "addr:full":"315 3rd St NW Attalla AL 35954",
    "addr:housenumber":"315",
    "addr:postcode":"35954",
    "addr:street":"3Rd St Nw Attalla",
    "iso:country":"US",
    "sg:address":"315 3rd St NW",
    "sg:city":"Attalla",
    "sg:classifiers":[
        {
            "category":"Shopping",
            "subcategory":"Pharmacy",
            "type":"Retail Goods"
        }
    ],
    "sg:phone":"+1 256 538 9699",
    "sg:postcode":"35954",
    "sg:province":"AL",
    "wof:name":"CVS",
    "wof:placetype":"venue"
},
  "geometry": {"coordinates":[-86.090245,34.020409],"type":"Point"}
}