{
  "type": "Feature",
  "properties": {
    "iso:country":"US",
    "sg:address":"5933 Windham Ct",
    "sg:city":"Mobile",
    "sg:classifiers":[
        {
            "category":"Wholesale",
            "subcategory":"Drugs",
            "type":"Manufacturing & Wholesale Goods"
        }
    ],
    "sg:phone":"+1 251 341 9465",
    "sg:postcode":"36608",
    "sg:province":"AL",
    "wof:name":"Ensearch Management Co Inc",
    "wof:placetype":"venue"
},
  "geometry": {"coordinates":[-88.179355,30.68843],"type":"Point"}
}