{
  "type": "Feature",
  "properties": {
    "iso:country":"US",
    "sg:address":"1008 Hillabee St",
    "sg:city":"Alexander City",
    "sg:classifiers":[
        {
            "category":"Wholesale",
            "subcategory":"Electrical",
            "type":"Manufacturing & Wholesale Goods"
        }
    ],
    "sg:phone":"+1 256 234 4440",
    "sg:postcode":"35010",
    "sg:province":"AL",
    "sg:tags":[
        "appliance"
    ],
    "wof:name":"Warren's Appliance Parts",
    "wof:placetype":"venue"
},
  "geometry": {"coordinates":[-85.94145399999999,32.943157],"type":"Point"}
}