{
  "type": "Feature",
  "properties": {
    "iso:country":"US",
    "sg:address":"1551 Schillinger Rd N",
    "sg:city":"Semmes",
    "sg:classifiers":[
        {
            "category":"Recreation",
            "type":"Entertainment"
        }
    ],
    "sg:phone":"+1 251 645 8498",
    "sg:postcode":"36575",
    "sg:province":"AL",
    "sg:tags":[
        "stable"
    ],
    "wof:name":"Schillinger Veterinary Clinic",
    "wof:placetype":"venue"
},
  "geometry": {"coordinates":[-88.225472,30.722894],"type":"Point"}
}