{
  "type": "Feature",
  "properties": {
    "addr:full":"1550 Opelika Rd Auburn AL 36830",
    "addr:housenumber":"1550",
    "addr:postcode":"36830",
    "addr:street":"Opelika Rd",
    "iso:country":"US",
    "sg:address":"1550 Opelika Rd",
    "sg:city":"Auburn",
    "sg:classifiers":[
        {
            "category":"Restaurant",
            "type":"Food & Drink"
        }
    ],
    "sg:menulink":"http://www.allmenus.com/al/auburn-opelika/56170-cicis-pizza-buffet/menu/",
    "sg:phone":"+1 334 821 2600",
    "sg:postcode":"36830",
    "sg:province":"AL",
    "sg:tags":[
        "american",
        "pizza"
    ],
    "wof:name":"CiCi's Pizza Buffet",
    "wof:placetype":"venue"
},
  "geometry": {"coordinates":[-85.450244,32.623066],"type":"Point"}
}