{
  "type": "Feature",
  "properties": {
    "iso:country":"US",
    "sg:address":"602 Wilburn St",
    "sg:city":"Athens",
    "sg:classifiers":[
        {
            "category":"Wholesale",
            "subcategory":"Non-durable Goods",
            "type":"Manufacturing & Wholesale Goods"
        }
    ],
    "sg:phone":"+1 256 232 4815",
    "sg:postcode":"35611",
    "sg:province":"AL",
    "sg:tags":[
        "item",
        "advertising",
        "specialty"
    ],
    "wof:name":"Athens Advertising Specialties",
    "wof:placetype":"venue"
},
  "geometry": {"coordinates":[-86.984829,34.809218],"type":"Point"}
}