{
  "type": "Feature",
  "properties": {
    "iso:country":"US",
    "sg:address":"547 Cullman Rd",
    "sg:city":"Arab",
    "sg:classifiers":[
        {
            "category":"Retail",
            "subcategory":"Car Wash",
            "type":"Services"
        }
    ],
    "sg:phone":"+1 256 586 5358",
    "sg:postcode":"35016",
    "sg:province":"AL",
    "sg:tags":[
        "carwash"
    ],
    "wof:name":"Westown Automatic & Self Svc",
    "wof:placetype":"venue"
},
  "geometry": {"coordinates":[-86.50244600000001,34.315114],"type":"Point"}
}