{
  "type": "Feature",
  "properties": {
    "iso:country":"US",
    "sg:address":"4023 Piedmont Dr SE",
    "sg:city":"Huntsville",
    "sg:classifiers":[
        {
            "category":"Shopping",
            "type":"Retail Goods"
        }
    ],
    "sg:phone":"+1 256 883 8878",
    "sg:postcode":"35802",
    "sg:province":"AL",
    "sg:tags":[
        "equipment",
        "telephone"
    ],
    "wof:name":"Verizon",
    "wof:placetype":"venue"
},
  "geometry": {"coordinates":[-86.56336400000001,34.702125],"type":"Point"}
}