{
  "type": "Feature",
  "properties": {
    "iso:country":"US",
    "sg:address":"1025 23rd St S",
    "sg:city":"Birmingham",
    "sg:classifiers":[
        {
            "category":"Professional",
            "subcategory":"Accounting & Tax Preparation",
            "type":"Services"
        }
    ],
    "sg:phone":"+1 205 322 2220",
    "sg:postcode":"35205",
    "sg:province":"AL",
    "sg:tags":[
        "bookkeeping",
        "general"
    ],
    "wof:name":"Galactic Payroll Svc",
    "wof:placetype":"venue"
},
  "geometry": {"coordinates":[-86.793216,33.504565],"type":"Point"}
}