{
  "type": "Feature",
  "properties": {
    "addr:full":"3780 Dawson St Leeds AL 35094",
    "addr:housenumber":"3780",
    "addr:postcode":"35094",
    "addr:street":"Dawson St",
    "iso:country":"US",
    "sg:address":"3780 Dawson St",
    "sg:city":"Leeds",
    "sg:classifiers":[
        {
            "category":"Wholesale",
            "subcategory":"Construction Materials",
            "type":"Manufacturing & Wholesale Goods"
        },
        {
            "category":"Home & Garden",
            "subcategory":"Furniture",
            "type":"Retail Goods"
        }
    ],
    "sg:phone":"+1 205 699 6924",
    "sg:postcode":"35094",
    "sg:province":"AL",
    "sg:tags":[
        "cabinet"
    ],
    "wof:name":"Dales's Custom Cabinets",
    "wof:placetype":"venue"
},
  "geometry": {"coordinates":[-86.541274,33.564042],"type":"Point"}
}