{
  "type": "Feature",
  "properties": {
    "addr:full":"15961 Dauphin Island Pkwy Coden AL 36523",
    "addr:housenumber":"15961",
    "addr:postcode":"36523",
    "addr:street":"Dauphin Island Pkwy Coden",
    "iso:country":"US",
    "sg:address":"15961 Dauphin Island Pkwy",
    "sg:city":"Coden",
    "sg:classifiers":[
        {
            "category":"Recreation",
            "type":"Entertainment"
        }
    ],
    "sg:phone":"+1 251 574 2267",
    "sg:postcode":"36523",
    "sg:province":"AL",
    "sg:tags":[
        "parks"
    ],
    "wof:name":"Bay Front Park",
    "wof:placetype":"venue"
},
  "geometry": {"coordinates":[-88.126401,30.341405],"type":"Point"}
}