{
  "type": "Feature",
  "properties": {
    "iso:country":"US",
    "sg:address":"905 W Prichard Ave",
    "sg:city":"Mobile",
    "sg:classifiers":[
        {
            "category":"Insurance",
            "subcategory":"Insurance Agent",
            "type":"Services"
        }
    ],
    "sg:phone":"+1 251 457 6388",
    "sg:postcode":"36610",
    "sg:province":"AL",
    "wof:name":"Southern Underwriters Agency",
    "wof:placetype":"venue"
},
  "geometry": {"coordinates":[-88.09354999999999,30.727365],"type":"Point"}
}