{
  "type": "Feature",
  "properties": {
    "addr:full":"1049 Putman Dr NW Huntsville AL 35816",
    "addr:housenumber":"1049",
    "addr:postcode":"35816",
    "addr:street":"Putman Dr Nw",
    "iso:country":"US",
    "sg:address":"1049 Putman Dr NW",
    "sg:city":"Huntsville",
    "sg:classifiers":[
        {
            "category":"Wholesale",
            "subcategory":"Hardware",
            "type":"Manufacturing & Wholesale Goods"
        }
    ],
    "sg:phone":"+1 256 837 7773",
    "sg:postcode":"35816",
    "sg:province":"AL",
    "sg:tags":[
        "refrigeration"
    ],
    "wof:name":"Totaline Parts & Supply",
    "wof:placetype":"venue"
},
  "geometry": {"coordinates":[-86.637034,34.739379],"type":"Point"}
}