{
  "type": "Feature",
  "properties": {
    "iso:country":"US",
    "sg:address":"6955 Charmingdale Dr S",
    "sg:city":"Mobile",
    "sg:classifiers":[
        {
            "category":"Home & Garden",
            "subcategory":"Building Materials",
            "type":"Retail Goods"
        }
    ],
    "sg:phone":"+1 251 653 8516",
    "sg:postcode":"36618",
    "sg:province":"AL",
    "wof:name":"Senah Lumber",
    "wof:placetype":"venue"
},
  "geometry": {"coordinates":[-88.20554799999999,30.749437],"type":"Point"}
}