{
  "type": "Feature",
  "properties": {
    "addr:full":"400 Dykes Rd Mobile AL 36608",
    "addr:housenumber":"400",
    "addr:postcode":"36608",
    "addr:street":"Dykes Rd",
    "iso:country":"US",
    "sg:address":"400 Dykes Rd",
    "sg:city":"Mobile",
    "sg:classifiers":[
        {
            "category":"Food & Beverages",
            "subcategory":"Groceries & Convenience Stores",
            "type":"Retail Goods"
        }
    ],
    "sg:phone":"+1 251 649 3579",
    "sg:postcode":"36608",
    "sg:province":"AL",
    "wof:name":"Handy Store The",
    "wof:placetype":"venue"
},
  "geometry": {"coordinates":[-88.284696,30.682104],"type":"Point"}
}