{
  "type": "Feature",
  "properties": {
    "iso:country":"US",
    "sg:address":"1920 Sparkman Dr NW",
    "sg:city":"Huntsville",
    "sg:classifiers":[
        {
            "category":"Personal",
            "subcategory":"Beauty Salon",
            "type":"Services"
        }
    ],
    "sg:phone":"+1 256 721 0087",
    "sg:postcode":"35816",
    "sg:province":"AL",
    "sg:tags":[
        "shop"
    ],
    "wof:name":"Shear Happiness",
    "wof:placetype":"venue"
},
  "geometry": {"coordinates":[-86.639505,34.755863],"type":"Point"}
}