{
  "type": "Feature",
  "properties": {
    "iso:country":"US",
    "sg:address":"1131 Co Rd 26",
    "sg:city":"Alabaster",
    "sg:classifiers":[
        {
            "category":"Shopping",
            "type":"Retail Goods"
        }
    ],
    "sg:phone":"+1 205 621 5949",
    "sg:postcode":"35007",
    "sg:province":"AL",
    "sg:tags":[
        "merchandise"
    ],
    "wof:name":"Linda Ables Retail Store",
    "wof:placetype":"venue"
},
  "geometry": {"coordinates":[-86.811538,33.215195],"type":"Point"}
}