{
  "type": "Feature",
  "properties": {
    "iso:country":"US",
    "sg:address":"153 S 9th St",
    "sg:city":"Gadsden",
    "sg:classifiers":[
        {
            "category":"Professional",
            "subcategory":"Lawyer & Legal Services",
            "type":"Services"
        }
    ],
    "sg:phone":"+1 256 546 3640",
    "sg:postcode":"35901",
    "sg:province":"AL",
    "sg:tags":[
        "attorney"
    ],
    "wof:name":"Justin D Hayes Attorney",
    "wof:placetype":"venue"
},
  "geometry": {"coordinates":[-86.013417,34.01577],"type":"Point"}
}