{
  "type": "Feature",
  "properties": {
    "iso:country":"US",
    "sg:address":"1591 US Hwy 11",
    "sg:city":"Trussville",
    "sg:classifiers":[
        {
            "category":"Retail",
            "subcategory":"Funeral Services",
            "type":"Services"
        }
    ],
    "sg:phone":"+1 205 322 0543",
    "sg:postcode":"35173",
    "sg:province":"AL",
    "sg:tags":[
        "director"
    ],
    "wof:name":"Jefferson Memerial Funeral Hms",
    "wof:placetype":"venue"
},
  "geometry": {"coordinates":[-86.509305,33.722266],"type":"Point"}
}