{
  "type": "Feature",
  "properties": {
    "addr:full":"7550 Assunta Ct Fairhope AL 36532",
    "addr:postcode":"7550;36532",
    "addr:street":"Assunta Ct",
    "iso:country":"US",
    "sg:address":"7550 Assunta Ct",
    "sg:city":"Fairhope",
    "sg:classifiers":[
        {
            "category":"Health Services",
            "subcategory":"Doctor",
            "type":"Services"
        }
    ],
    "sg:phone":"+1 251 928 4944",
    "sg:postcode":"36532",
    "sg:province":"AL",
    "sg:tags":[
        "physician",
        "surgeon"
    ],
    "wof:name":"Bay Shore Dermatology",
    "wof:placetype":"venue"
},
  "geometry": {"coordinates":[-87.893564,30.555174],"type":"Point"}
}