{
  "type": "Feature",
  "properties": {
    "addr:full":"1750 Navco Rd Mobile AL 36605",
    "addr:housenumber":"1750",
    "addr:postcode":"36605",
    "addr:street":"Navco Rd",
    "iso:country":"US",
    "sg:address":"1750 Navco Rd",
    "sg:city":"Mobile",
    "sg:classifiers":[
        {
            "category":"Home & Garden",
            "subcategory":"Building Materials",
            "type":"Retail Goods"
        }
    ],
    "sg:phone":"+1 251 433 1300",
    "sg:postcode":"36605",
    "sg:province":"AL",
    "sg:tags":[
        "shutter"
    ],
    "wof:name":"Shutters & More",
    "wof:placetype":"venue"
},
  "geometry": {"coordinates":[-88.10550600000001,30.631279],"type":"Point"}
}