{
  "type": "Feature",
  "properties": {
    "iso:country":"US",
    "sg:address":"1118 N Brindlee Mountain Pkwy",
    "sg:city":"Arab",
    "sg:classifiers":[
        {
            "category":"Shopping",
            "subcategory":"Discount & Variety Stores",
            "type":"Retail Goods"
        },
        {
            "category":"Shopping",
            "subcategory":"Department Store",
            "type":"Retail Goods"
        }
    ],
    "sg:phone":"+1 256 586 7090",
    "sg:postcode":"35016",
    "sg:province":"AL",
    "sg:tags":[
        "shop"
    ],
    "wof:name":"Dollar General",
    "wof:placetype":"venue"
},
  "geometry": {"coordinates":[-86.50322799999999,34.334639],"type":"Point"}
}