{
  "type": "Feature",
  "properties": {
    "iso:country":"US",
    "sg:address":"608 Rogers Rd",
    "sg:city":"Dothan",
    "sg:classifiers":[
        {
            "category":"Freight",
            "type":"Transportation"
        }
    ],
    "sg:phone":"+1 334 702 4845",
    "sg:postcode":"36303",
    "sg:province":"AL",
    "sg:tags":[
        "trucking"
    ],
    "sg:website":"www.con-way.com",
    "wof:name":"Con-Way Southern Express",
    "wof:placetype":"venue"
},
  "geometry": {"coordinates":[-85.405412,31.255387],"type":"Point"}
}