{
  "type": "Feature",
  "properties": {
    "iso:country":"US",
    "sg:address":"2901 Hillcrest Rd",
    "sg:city":"Mobile",
    "sg:classifiers":[
        {
            "category":"Organizations",
            "subcategory":"Religious Organization",
            "type":"Services"
        }
    ],
    "sg:phone":"+1 251 665 5110",
    "sg:postcode":"36695",
    "sg:province":"AL",
    "sg:tags":[
        "church"
    ],
    "sg:website":"www.portcitycoc.org",
    "wof:name":"Port City Church Of Christ",
    "wof:placetype":"venue"
},
  "geometry": {"coordinates":[-88.190782,30.622104],"type":"Point"}
}