{
  "type": "Feature",
  "properties": {
    "iso:country":"US",
    "sg:address":"107 Rita Ave",
    "sg:city":"Spanish Fort",
    "sg:classifiers":[
        {
            "category":"Farming",
            "subcategory":"Farm & Veterinary Services",
            "type":"Manufacturing & Wholesale Goods"
        }
    ],
    "sg:phone":"+1 251 377 5414",
    "sg:postcode":"36527",
    "sg:province":"AL",
    "sg:tags":[
        "preparation",
        "soil"
    ],
    "wof:name":"Get A Grip Services LLC",
    "wof:placetype":"venue"
},
  "geometry": {"coordinates":[-87.87848099999999,30.669856],"type":"Point"}
}