{
  "type": "Feature",
  "properties": {
    "iso:country":"US",
    "sg:address":"1415 Decatur Hwy",
    "sg:city":"Fultondale",
    "sg:classifiers":[
        {
            "category":"Shopping",
            "type":"Retail Goods"
        }
    ],
    "sg:phone":"+1 205 849 4444",
    "sg:postcode":"35068",
    "sg:province":"AL",
    "sg:tags":[
        "merchandise"
    ],
    "wof:name":"Crazy Bills Fireworks Inc",
    "wof:placetype":"venue"
},
  "geometry": {"coordinates":[-86.796887,33.612209],"type":"Point"}
}