{
  "type": "Feature",
  "properties": {
    "addr:full":"2501 Promberry Dr Montgomery AL 36106",
    "addr:housenumber":"2501",
    "addr:postcode":"36106",
    "addr:street":"Promberry Dr",
    "iso:country":"US",
    "sg:address":"2501 Promberry Dr",
    "sg:city":"Montgomery",
    "sg:classifiers":[
        {
            "category":"Real Estate",
            "subcategory":"Real Estate Agent",
            "type":"Services"
        }
    ],
    "sg:phone":"+1 334 396 9142",
    "sg:postcode":"36106",
    "sg:province":"AL",
    "wof:name":"Colonial Properties Area Ofc",
    "wof:placetype":"venue"
},
  "geometry": {"coordinates":[-86.226823,32.348034],"type":"Point"}
}