{
  "type": "Feature",
  "properties": {
    "iso:country":"US",
    "sg:address":"2653 Ruffner Rd",
    "sg:city":"Birmingham",
    "sg:classifiers":[
        {
            "category":"Manufacturing",
            "subcategory":"Glass & Minerals",
            "type":"Manufacturing & Wholesale Goods"
        }
    ],
    "sg:phone":"+1 205 956 1645",
    "sg:postcode":"35210",
    "sg:province":"AL",
    "sg:tags":[
        "ready",
        "concrete",
        "mfg"
    ],
    "wof:name":"Ready Mix USA Plant Maintenanc",
    "wof:placetype":"venue"
},
  "geometry": {"coordinates":[-86.672221,33.576165],"type":"Point"}
}