{
  "type": "Feature",
  "properties": {
    "iso:country":"US",
    "sg:address":"210 1st St N",
    "sg:city":"Alabaster",
    "sg:classifiers":[
        {
            "category":"Building & Trades",
            "subcategory":"Plumbing",
            "type":"Services"
        }
    ],
    "sg:phone":"+1 205 664 5566",
    "sg:postcode":"35007",
    "sg:province":"AL",
    "sg:tags":[
        "conditioning",
        "contractor",
        "system",
        "air"
    ],
    "wof:name":"Freedom Heating & AC INC",
    "wof:placetype":"venue"
},
  "geometry": {"coordinates":[-86.815539,33.246355],"type":"Point"}
}