{
  "type": "Feature",
  "properties": {
    "iso:country":"US",
    "sg:address":"5501 US Hwy 280",
    "sg:city":"Birmingham",
    "sg:classifiers":[
        {
            "category":"Health Services",
            "subcategory":"Doctor",
            "type":"Services"
        }
    ],
    "sg:phone":"+1 205 995 5020",
    "sg:postcode":"35242",
    "sg:province":"AL",
    "sg:tags":[
        "clinic"
    ],
    "wof:name":"Living Medicine",
    "wof:placetype":"venue"
},
  "geometry": {"coordinates":[-86.664211,33.40649],"type":"Point"}
}