{
  "type": "Feature",
  "properties": {
    "addr:full":"173 Redwood Ln Birmingham AL 35226",
    "addr:housenumber":"173",
    "addr:postcode":"35226",
    "addr:street":"Redwood Ln",
    "iso:country":"US",
    "sg:address":"173 Redwood Ln",
    "sg:city":"Birmingham",
    "sg:classifiers":[
        {
            "category":"Wholesale",
            "subcategory":"Vending Machines",
            "type":"Manufacturing & Wholesale Goods"
        }
    ],
    "sg:phone":"+1 205 979 4702",
    "sg:postcode":"35226",
    "sg:province":"AL",
    "sg:tags":[
        "operator"
    ],
    "wof:name":"Elite Vending Enterprise LLC",
    "wof:placetype":"venue"
},
  "geometry": {"coordinates":[-86.851063,33.381846],"type":"Point"}
}