{
  "type": "Feature",
  "properties": {
    "iso:country":"US",
    "sg:address":"22100 Co Rd 68",
    "sg:city":"Robertsdale",
    "sg:classifiers":[
        {
            "category":"Bars & Pubs",
            "type":"Food & Drink"
        }
    ],
    "sg:phone":"+1 251 580 3773",
    "sg:postcode":"36567",
    "sg:province":"AL",
    "sg:tags":[
        "drinking"
    ],
    "wof:name":"Coles Bar & Grill",
    "wof:placetype":"venue"
},
  "geometry": {"coordinates":[-87.643703,30.642309],"type":"Point"}
}