{
  "type": "Feature",
  "properties": {
    "iso:country":"US",
    "sg:address":"620 23rd Ter NW",
    "sg:city":"Birmingham",
    "sg:classifiers":[
        {
            "category":"Shopping",
            "subcategory":"Gifts & Souvenirs",
            "type":"Retail Goods"
        }
    ],
    "sg:phone":"+1 205 815 4510",
    "sg:postcode":"35215",
    "sg:province":"AL",
    "wof:name":"JS Gifts n Things",
    "wof:placetype":"venue"
},
  "geometry": {"coordinates":[-86.703789,33.646081],"type":"Point"}
}