{
  "type": "Feature",
  "properties": {
    "iso:country":"US",
    "sg:address":"2904 Ryecroft Rd",
    "sg:city":"Birmingham",
    "sg:classifiers":[
        {
            "category":"Professional",
            "type":"Services"
        }
    ],
    "sg:phone":"+1 205 970 6945",
    "sg:postcode":"35223",
    "sg:province":"AL",
    "wof:name":"Linda & Brian Grodner",
    "wof:placetype":"venue"
},
  "geometry": {"coordinates":[-86.740598,33.474524],"type":"Point"}
}