{
  "type": "Feature",
  "properties": {
    "iso:country":"US",
    "sg:address":"1640 Tune Ave",
    "sg:city":"Florence",
    "sg:classifiers":[
        {
            "category":"Education",
            "subcategory":"School",
            "type":"Public Place"
        }
    ],
    "sg:phone":"+1 256 768 2900",
    "sg:postcode":"35630",
    "sg:province":"AL",
    "wof:name":"Powell Elementary School",
    "wof:placetype":"venue"
},
  "geometry": {"coordinates":[-87.66101,34.820667],"type":"Point"}
}