{
  "type": "Feature",
  "properties": {
    "iso:country":"US",
    "sg:address":"33669 US Hwy 280",
    "sg:city":"Childersburg",
    "sg:classifiers":[
        {
            "category":"Banks & Credit Unions",
            "subcategory":"Bank",
            "type":"Services"
        }
    ],
    "sg:phone":"+1 256 378 0670",
    "sg:postcode":"35044",
    "sg:province":"AL",
    "wof:name":"First National America's",
    "wof:placetype":"venue"
},
  "geometry": {"coordinates":[-86.353184,33.267659],"type":"Point"}
}