{
  "type": "Feature",
  "properties": {
    "iso:country":"US",
    "sg:address":"8371 Highway 72 W",
    "sg:city":"Madison",
    "sg:classifiers":[
        {
            "category":"Health Services",
            "subcategory":"Hospital",
            "type":"Services"
        }
    ],
    "sg:phone":"+1 256 726 6977",
    "sg:postcode":"35758",
    "sg:province":"AL",
    "wof:name":"Huntsville Hospital Sleep Center",
    "wof:placetype":"venue"
},
  "geometry": {"coordinates":[-86.76286899999999,34.749615],"type":"Point"}
}