{
  "type": "Feature",
  "properties": {
    "iso:country":"US",
    "sg:address":"1327 Leighton Ave",
    "sg:city":"Anniston",
    "sg:classifiers":[
        {
            "category":"Building & Trades",
            "subcategory":"Construction",
            "type":"Services"
        }
    ],
    "sg:phone":"+1 256 237 3700",
    "sg:postcode":"36207",
    "sg:province":"AL",
    "sg:tags":[
        "house"
    ],
    "wof:name":"Habitat For Humanity of Calhou",
    "wof:placetype":"venue"
},
  "geometry": {"coordinates":[-85.824972,33.662043],"type":"Point"}
}