{
  "type": "Feature",
  "properties": {
    "iso:country":"US",
    "sg:address":"404 S 5th St",
    "sg:city":"Gadsden",
    "sg:classifiers":[
        {
            "category":"Health Services",
            "subcategory":"Doctor",
            "type":"Services"
        }
    ],
    "sg:phone":"+1 256 546 4604",
    "sg:postcode":"35901",
    "sg:province":"AL",
    "sg:tags":[
        "dentist"
    ],
    "wof:name":"Pediatric Dental Assoc",
    "wof:placetype":"venue"
},
  "geometry": {"coordinates":[-86.007346,34.007595],"type":"Point"}
}