{
  "type": "Feature",
  "properties": {
    "iso:country":"US",
    "sg:address":"739 W Arbor Dr NW",
    "sg:city":"Huntsville",
    "sg:classifiers":[
        {
            "category":"Building & Trades",
            "subcategory":"Construction",
            "type":"Services"
        }
    ],
    "sg:phone":"+1 256 533 0678",
    "sg:postcode":"35811",
    "sg:province":"AL",
    "sg:tags":[
        "contractor"
    ],
    "wof:name":"Neals Pressure Wshg Clg Servi",
    "wof:placetype":"venue"
},
  "geometry": {"coordinates":[-86.593874,34.75213],"type":"Point"}
}