{
  "type": "Feature",
  "properties": {
    "iso:country":"US",
    "sg:address":"401 20th Ave",
    "sg:city":"Northport",
    "sg:classifiers":[
        {
            "category":"Manufacturing",
            "subcategory":"Printing",
            "type":"Manufacturing & Wholesale Goods"
        }
    ],
    "sg:phone":"+1 205 759 3091",
    "sg:postcode":"35476",
    "sg:province":"AL",
    "sg:tags":[
        "newspaper"
    ],
    "sg:website":"www.northportgazette.com",
    "wof:name":"Northport Gazette",
    "wof:placetype":"venue"
},
  "geometry": {"coordinates":[-87.577728,33.218928],"type":"Point"}
}