{
  "type": "Feature",
  "properties": {
    "iso:country":"US",
    "sg:address":"592 George Todd Dr",
    "sg:city":"Montgomery",
    "sg:classifiers":[
        {
            "category":"Wholesale",
            "subcategory":"Office Equipment",
            "type":"Manufacturing & Wholesale Goods"
        },
        {
            "category":"Professional",
            "subcategory":"Business Services",
            "type":"Services"
        }
    ],
    "sg:phone":"+1 334 271 5767",
    "sg:postcode":"36117",
    "sg:province":"AL",
    "sg:tags":[
        "machine",
        "duplicating",
        "copying"
    ],
    "wof:name":"Nohab Business Products LLC",
    "wof:placetype":"venue"
},
  "geometry": {"coordinates":[-86.210116,32.400084],"type":"Point"}
}