{
  "type": "Feature",
  "properties": {
    "addr:full":"2426 Creel Rd Morris AL 35116",
    "addr:housenumber":"2426",
    "addr:postcode":"35116",
    "addr:street":"Creel Rd",
    "iso:country":"US",
    "sg:address":"2426 Creel Rd",
    "sg:city":"Morris",
    "sg:classifiers":[
        {
            "category":"Building & Trades",
            "subcategory":"Construction",
            "type":"Services"
        }
    ],
    "sg:phone":"+1 205 229 9658",
    "sg:postcode":"35116",
    "sg:province":"AL",
    "sg:tags":[
        "contractor"
    ],
    "wof:name":"Palmer Housing Contractors",
    "wof:placetype":"venue"
},
  "geometry": {"coordinates":[-86.746657,33.759325],"type":"Point"}
}