{
  "type": "Feature",
  "properties": {
    "iso:country":"US",
    "sg:address":"110 Co Rd 337",
    "sg:city":"Chelsea",
    "sg:classifiers":[
        {
            "category":"Social Services",
            "subcategory":"Child Care",
            "type":"Services"
        }
    ],
    "sg:phone":"+1 205 678 7123",
    "sg:postcode":"35043",
    "sg:province":"AL",
    "wof:name":"Ready Set Grow Child Dev Ctr",
    "wof:placetype":"venue"
},
  "geometry": {"coordinates":[-86.634128,33.333219],"type":"Point"}
}