{
  "type": "Feature",
  "properties": {
    "iso:country":"US",
    "sg:address":"3490 Hurricane Bay Dr",
    "sg:city":"Theodore",
    "sg:classifiers":[
        {
            "category":"Freight",
            "type":"Transportation"
        }
    ],
    "sg:phone":"+1 251 443 8383",
    "sg:postcode":"36582",
    "sg:province":"AL",
    "sg:tags":[
        "special"
    ],
    "wof:name":"Allied Van Lines Agent",
    "wof:placetype":"venue"
},
  "geometry": {"coordinates":[-88.118854,30.555072],"type":"Point"}
}