{
  "type": "Feature",
  "properties": {
    "iso:country":"US",
    "sg:address":"12338 US Hwy 431",
    "sg:city":"Meridianville",
    "sg:classifiers":[
        {
            "category":"Shopping",
            "subcategory":"Used Merchandise",
            "type":"Retail Goods"
        }
    ],
    "sg:phone":"+1 256 829 0740",
    "sg:postcode":"35759",
    "sg:province":"AL",
    "sg:tags":[
        "antique"
    ],
    "wof:name":"Reflections Of The Past",
    "wof:placetype":"venue"
},
  "geometry": {"coordinates":[-86.571123,34.870557],"type":"Point"}
}