{
  "type": "Feature",
  "properties": {
    "iso:country":"US",
    "sg:address":"8424 1st Ave Ste. 101 Leeds",
    "sg:city":"Leeds",
    "sg:classifiers":[
        {
            "category":"Retail",
            "subcategory":"Repair Shop",
            "type":"Services"
        },
        {
            "category":"Wholesale",
            "subcategory":"Machinery & Supplies",
            "type":"Manufacturing & Wholesale Goods"
        },
        {
            "category":"Building & Trades",
            "subcategory":"Equipment Rental",
            "type":"Services"
        },
        {
            "category":"Building & Trades",
            "subcategory":"Construction",
            "type":"Services"
        }
    ],
    "sg:phone":"+1 205 699 0741",
    "sg:postcode":"35094",
    "sg:province":"AL",
    "sg:tags":[
        "systems-repairing",
        "equipment-commercial",
        "restaurant",
        "machines-repair",
        "system",
        "ice",
        "specialty",
        "equipment-repair",
        "heating",
        "refrigeration",
        "industrial",
        "contractor",
        "air conditioning"
    ],
    "sg:website":"http://aeroheatingandair.liveonatt.com",
    "wof:name":"Aero Heating & Air Service, Inc",
    "wof:placetype":"venue"
},
  "geometry": {"coordinates":[-86.54570699999999,33.544121],"type":"Point"}
}