{
  "type": "Feature",
  "properties": {
    "iso:country":"US",
    "sg:address":"2611 Artie St SW",
    "sg:city":"Huntsville",
    "sg:classifiers":[
        {
            "category":"Retail",
            "subcategory":"Animal Services",
            "type":"Services"
        }
    ],
    "sg:phone":"+1 256 532 0515",
    "sg:postcode":"35805",
    "sg:province":"AL",
    "sg:tags":[
        "training",
        "dog"
    ],
    "wof:name":"Huntsville Kennel Club",
    "wof:placetype":"venue"
},
  "geometry": {"coordinates":[-86.592765,34.708754],"type":"Point"}
}