{
  "type": "Feature",
  "properties": {
    "iso:country":"US",
    "sg:address":"306 Dauphin St",
    "sg:city":"Mobile",
    "sg:classifiers":[
        {
            "category":"Personal",
            "subcategory":"Beauty Salon",
            "type":"Services"
        }
    ],
    "sg:phone":"+1 251 441 0880",
    "sg:postcode":"36602",
    "sg:province":"AL",
    "wof:name":"Chesser Art & Hair",
    "wof:placetype":"venue"
},
  "geometry": {"coordinates":[-88.045542,30.690696],"type":"Point"}
}