{
  "type": "Feature",
  "properties": {
    "iso:country":"US",
    "sg:address":"601 W Main St",
    "sg:city":"Centre",
    "sg:classifiers":[
        {
            "category":"Shopping",
            "subcategory":"Used Merchandise",
            "type":"Retail Goods"
        }
    ],
    "sg:phone":"+1 256 927 4423",
    "sg:postcode":"35960",
    "sg:province":"AL",
    "sg:tags":[
        "antique"
    ],
    "wof:name":"Centre Trading Post Inc",
    "wof:placetype":"venue"
},
  "geometry": {"coordinates":[-85.68581,34.153963],"type":"Point"}
}