{
  "type": "Feature",
  "properties": {
    "addr:full":"1930 3rd Ave Dothan AL 36301",
    "addr:housenumber":"1930",
    "addr:postcode":"36301",
    "addr:street":"3Rd Ave",
    "iso:country":"US",
    "sg:address":"1930 3rd Ave",
    "sg:city":"Dothan",
    "sg:classifiers":[
        {
            "category":"Organizations",
            "subcategory":"Religious Organization",
            "type":"Services"
        }
    ],
    "sg:phone":"+1 334 673 1610",
    "sg:postcode":"36301",
    "sg:province":"AL",
    "sg:tags":[
        "synagogue"
    ],
    "wof:name":"El Shaddai",
    "wof:placetype":"venue"
},
  "geometry": {"coordinates":[-85.379696,31.197633],"type":"Point"}
}