{
  "type": "Feature",
  "properties": {
    "addr:full":"113 N Gay St Auburn AL 36830",
    "addr:housenumber":"113",
    "addr:postcode":"36830",
    "addr:street":"N Gay St",
    "iso:country":"US",
    "sg:address":"113 N Gay St",
    "sg:city":"Auburn",
    "sg:classifiers":[
        {
            "category":"Professional",
            "subcategory":"Business Services",
            "type":"Services"
        }
    ],
    "sg:phone":"+1 334 826 9533",
    "sg:postcode":"36830",
    "sg:province":"AL",
    "sg:tags":[
        "interior",
        "consultant",
        "design",
        "decorator"
    ],
    "wof:name":"Custom Interiors",
    "wof:placetype":"venue"
},
  "geometry": {"coordinates":[-85.479975,32.607964],"type":"Point"}
}