{
  "type": "Feature",
  "properties": {
    "iso:country":"US",
    "sg:address":"2245 Halls Mill Rd",
    "sg:city":"Mobile",
    "sg:classifiers":[
        {
            "category":"Personal",
            "subcategory":"Barber",
            "type":"Services"
        }
    ],
    "sg:phone":"+1 251 471 3530",
    "sg:postcode":"36606",
    "sg:province":"AL",
    "wof:name":"Holcombe Avenue Barber Shop",
    "wof:placetype":"venue"
},
  "geometry": {"coordinates":[-88.095651,30.661288],"type":"Point"}
}