{
  "type": "Feature",
  "properties": {
    "iso:country":"US",
    "sg:address":"111 Church Hill Dr",
    "sg:city":"Grove Hill",
    "sg:classifiers":[
        {
            "category":"Utilities",
            "subcategory":"Water",
            "type":"Services"
        }
    ],
    "sg:phone":"+1 251 275 4378",
    "sg:postcode":"36451",
    "sg:province":"AL",
    "sg:tags":[
        "dealer"
    ],
    "wof:name":"Hamilton Bottled Water Svc",
    "wof:placetype":"venue"
},
  "geometry": {"coordinates":[-87.77995900000001,31.71015],"type":"Point"}
}