{
  "type": "Feature",
  "properties": {
    "iso:country":"US",
    "sg:address":"1811 S Railroad St",
    "sg:city":"Phenix City",
    "sg:classifiers":[
        {
            "category":"Retail",
            "subcategory":"Repair Shop",
            "type":"Services"
        }
    ],
    "sg:phone":"+1 334 298 4130",
    "sg:postcode":"36867",
    "sg:province":"AL",
    "sg:tags":[
        "welding"
    ],
    "wof:name":"Ivey's Portable Welding",
    "wof:placetype":"venue"
},
  "geometry": {"coordinates":[-85.019239,32.480162],"type":"Point"}
}