{
  "type": "Feature",
  "properties": {
    "iso:country":"US",
    "sg:address":"2420 E 2nd St",
    "sg:city":"Gulf Shores",
    "sg:classifiers":[
        {
            "category":"Restaurant",
            "type":"Food & Drink"
        }
    ],
    "sg:phone":"+1 251 968 3501",
    "sg:postcode":"36542",
    "sg:province":"AL",
    "sg:tags":[
        "eating"
    ],
    "wof:name":"Cazadores",
    "wof:placetype":"venue"
},
  "geometry": {"coordinates":[-87.683036,30.277446],"type":"Point"}
}