{
  "type": "Feature",
  "properties": {
    "iso:country":"US",
    "sg:address":"1480 Brockton Ln E",
    "sg:city":"Mobile",
    "sg:classifiers":[
        {
            "category":"Building & Trades",
            "subcategory":"Construction",
            "type":"Services"
        }
    ],
    "sg:phone":"+1 251 639 0803",
    "sg:postcode":"36695",
    "sg:province":"AL",
    "sg:tags":[
        "house",
        "residential"
    ],
    "wof:name":"Vaughans Construction",
    "wof:placetype":"venue"
},
  "geometry": {"coordinates":[-88.215158,30.660259],"type":"Point"}
}