{
  "type": "Feature",
  "properties": {
    "iso:country":"US",
    "sg:address":"1109 Jordan Ln NW",
    "sg:city":"Huntsville",
    "sg:classifiers":[
        {
            "category":"Food & Beverages",
            "subcategory":"Groceries & Convenience Stores",
            "type":"Retail Goods"
        }
    ],
    "sg:phone":"+1 256 837 8885",
    "sg:postcode":"35816",
    "sg:province":"AL",
    "sg:tags":[
        "grocer"
    ],
    "wof:name":"LA Noche Buena",
    "wof:placetype":"venue"
},
  "geometry": {"coordinates":[-86.627473,34.738476],"type":"Point"}
}