{
  "type": "Feature",
  "properties": {
    "iso:country":"US",
    "sg:address":"301 E Church St",
    "sg:city":"Atmore",
    "sg:classifiers":[
        {
            "category":"Wholesale",
            "subcategory":"Vending Machines",
            "type":"Manufacturing & Wholesale Goods"
        }
    ],
    "sg:phone":"+1 251 368 8997",
    "sg:postcode":"36502",
    "sg:province":"AL",
    "wof:name":"South Alabama Vending Co",
    "wof:placetype":"venue"
},
  "geometry": {"coordinates":[-87.489396,31.022621],"type":"Point"}
}