{
  "type": "Feature",
  "properties": {
    "addr:full":"5906 Monticello Dr Montgomery AL 36117",
    "addr:housenumber":"5906",
    "addr:postcode":"36117",
    "addr:street":"Monticello Dr",
    "iso:country":"US",
    "sg:address":"5906 Monticello Dr",
    "sg:city":"Montgomery",
    "sg:classifiers":[
        {
            "category":"Personal",
            "subcategory":"Beauty Salon",
            "type":"Services"
        }
    ],
    "sg:phone":"+1 334 244 2444",
    "sg:postcode":"36117",
    "sg:province":"AL",
    "sg:tags":[
        "shop"
    ],
    "wof:name":"J B Hair Crafters",
    "wof:placetype":"venue"
},
  "geometry": {"coordinates":[-86.208247,32.36516],"type":"Point"}
}