{
  "type": "Feature",
  "properties": {
    "addr:full":"1100 McKenzie St Foley AL 36535",
    "addr:housenumber":"1100",
    "addr:postcode":"36535",
    "addr:street":"Mckenzie St",
    "iso:country":"US",
    "sg:address":"1100 McKenzie St",
    "sg:city":"Foley",
    "sg:classifiers":[
        {
            "category":"Shopping",
            "subcategory":"Gifts & Souvenirs",
            "type":"Retail Goods"
        }
    ],
    "sg:phone":"+1 251 971 3003",
    "sg:postcode":"36535",
    "sg:province":"AL",
    "sg:tags":[
        "party",
        "supply"
    ],
    "wof:name":"Trees N Trends Inc",
    "wof:placetype":"venue"
},
  "geometry": {"coordinates":[-87.683362,30.397547],"type":"Point"}
}