{
  "type": "Feature",
  "properties": {
    "iso:country":"US",
    "sg:address":"118 59th St",
    "sg:city":"Fairfield",
    "sg:classifiers":[
        {
            "category":"Organizations",
            "subcategory":"Religious Organization",
            "type":"Services"
        }
    ],
    "sg:phone":"+1 205 785 3324",
    "sg:postcode":"35064",
    "sg:province":"AL",
    "sg:tags":[
        "church"
    ],
    "wof:name":"Fairfield First Church Of God",
    "wof:placetype":"venue"
},
  "geometry": {"coordinates":[-86.916802,33.479593],"type":"Point"}
}