{
  "type": "Feature",
  "properties": {
    "addr:full":"4177 State Rte 27 Enterprise AL 36330",
    "addr:housenumber":"4177",
    "addr:postcode":"36330",
    "addr:street":"State Rte 27 Enterprise",
    "iso:country":"US",
    "sg:address":"4177 State Rte 27",
    "sg:city":"Enterprise",
    "sg:classifiers":[
        {
            "category":"Retail",
            "subcategory":"Auto Repair",
            "type":"Services"
        }
    ],
    "sg:phone":"+1 334 393 5665",
    "sg:postcode":"36330",
    "sg:province":"AL",
    "sg:tags":[
        "repairing",
        "automobile"
    ],
    "wof:name":"Automotive Air Conditioning",
    "wof:placetype":"venue"
},
  "geometry": {"coordinates":[-85.81898700000001,31.377348],"type":"Point"}
}