{
  "type": "Feature",
  "properties": {
    "iso:country":"US",
    "sg:address":"1604 Shadywood Ct",
    "sg:city":"Opelika",
    "sg:classifiers":[
        {
            "category":"Retail",
            "subcategory":"Laundry & Dry Cleaning",
            "type":"Services"
        }
    ],
    "sg:phone":"+1 334 741 7354",
    "sg:postcode":"36801",
    "sg:province":"AL",
    "sg:tags":[
        "drycleaning",
        "plant"
    ],
    "wof:name":"Main St Laundry & Dry Cleaning",
    "wof:placetype":"venue"
},
  "geometry": {"coordinates":[-85.399759,32.671608],"type":"Point"}
}