{
  "type": "Feature",
  "properties": {
    "iso:country":"US",
    "sg:address":"2822 Fields Ave",
    "sg:city":"Gadsden",
    "sg:classifiers":[
        {
            "category":"Organizations",
            "subcategory":"Religious Organization",
            "type":"Services"
        }
    ],
    "sg:phone":"+1 256 492 5660",
    "sg:postcode":"35903",
    "sg:province":"AL",
    "sg:tags":[
        "church"
    ],
    "wof:name":"Kingdom Hall-Jehovah's Witness",
    "wof:placetype":"venue"
},
  "geometry": {"coordinates":[-85.954515,33.978894],"type":"Point"}
}