{
  "type": "Feature",
  "properties": {
    "iso:country":"US",
    "sg:address":"3320 Cliff Rd S",
    "sg:city":"Birmingham",
    "sg:classifiers":[
        {
            "category":"Professional",
            "type":"Services"
        }
    ],
    "sg:phone":"+1 205 322 0112",
    "sg:postcode":"35205",
    "sg:province":"AL",
    "wof:name":"Vosource Computer Serv",
    "wof:placetype":"venue"
},
  "geometry": {"coordinates":[-86.776392,33.506512],"type":"Point"}
}