{
  "type": "Feature",
  "properties": {
    "iso:country":"US",
    "sg:address":"305 State Ave",
    "sg:city":"Muscle Shoals",
    "sg:classifiers":[
        {
            "category":"Professional",
            "subcategory":"Accounting & Tax Preparation",
            "type":"Services"
        }
    ],
    "sg:phone":"+1 256 381 8299",
    "sg:postcode":"35661",
    "sg:province":"AL",
    "sg:tags":[
        "accountant"
    ],
    "wof:name":"Charles M Hester CPA",
    "wof:placetype":"venue"
},
  "geometry": {"coordinates":[-87.672685,34.743972],"type":"Point"}
}