{
  "type": "Feature",
  "properties": {
    "addr:full":"1505 Pearson Ave SW Birmingham AL 35211",
    "addr:housenumber":"1505",
    "addr:postcode":"35211",
    "addr:street":"Pearson Ave Sw",
    "iso:country":"US",
    "sg:address":"1505 Pearson Ave SW",
    "sg:city":"Birmingham",
    "sg:classifiers":[
        {
            "category":"Shopping",
            "subcategory":"Clothing, Apparel, & Fashions",
            "type":"Retail Goods"
        }
    ],
    "sg:phone":"+1 205 785 0505",
    "sg:postcode":"35211",
    "sg:province":"AL",
    "sg:tags":[
        "designer"
    ],
    "wof:name":"Kiswanna Atlanta New York",
    "wof:placetype":"venue"
},
  "geometry": {"coordinates":[-86.856605,33.486663],"type":"Point"}
}