{
  "type": "Feature",
  "properties": {
    "iso:country":"US",
    "sg:address":"9694 Madison Blvd",
    "sg:city":"Madison",
    "sg:classifiers":[
        {
            "category":"Wholesale",
            "subcategory":"Electrical",
            "type":"Manufacturing & Wholesale Goods"
        },
        {
            "category":"Building & Trades",
            "subcategory":"Plumbing",
            "type":"Services"
        }
    ],
    "sg:phone":"+1 256 461 7117",
    "sg:postcode":"35758",
    "sg:province":"AL",
    "sg:tags":[
        "control",
        "heating",
        "air"
    ],
    "wof:name":"Industrial Commercial Controls",
    "wof:placetype":"venue"
},
  "geometry": {"coordinates":[-86.780177,34.665307],"type":"Point"}
}