{
  "type": "Feature",
  "properties": {
    "iso:country":"US",
    "sg:address":"1200 Hackberry Ln",
    "sg:city":"Tuscaloosa",
    "sg:classifiers":[
        {
            "category":"Restaurant",
            "type":"Food & Drink"
        }
    ],
    "sg:phone":"+1 205 758 6520",
    "sg:postcode":"35401",
    "sg:province":"AL",
    "wof:name":"Jack's Family Restaurant",
    "wof:placetype":"venue"
},
  "geometry": {"coordinates":[-87.54306,33.202914],"type":"Point"}
}