{
  "type": "Feature",
  "properties": {
    "iso:country":"US",
    "sg:address":"330 E Meighan Blvd",
    "sg:city":"Gadsden",
    "sg:classifiers":[
        {
            "category":"Utilities",
            "subcategory":"Mobile Phone",
            "type":"Services"
        }
    ],
    "sg:phone":"+1 256 546 1061",
    "sg:postcode":"35903",
    "sg:province":"AL",
    "sg:tags":[
        "telephone",
        "cellular"
    ],
    "wof:name":"Planet Cellular",
    "wof:placetype":"venue"
},
  "geometry": {"coordinates":[-85.988505,34.009796],"type":"Point"}
}