{
  "type": "Feature",
  "properties": {
    "iso:country":"US",
    "sg:address":"4201 10th Ave N",
    "sg:city":"Birmingham",
    "sg:classifiers":[
        {
            "category":"Restaurant",
            "type":"Food & Drink"
        }
    ],
    "sg:phone":"+1 205 591 5831",
    "sg:postcode":"35212",
    "sg:province":"AL",
    "wof:name":"Church's Chicken",
    "wof:placetype":"venue"
},
  "geometry": {"coordinates":[-86.77512900000001,33.540331],"type":"Point"}
}