{
  "type": "Feature",
  "properties": {
    "iso:country":"US",
    "sg:address":"210 W Fern Ave",
    "sg:city":"Foley",
    "sg:classifiers":[
        {
            "category":"Building & Trades",
            "subcategory":"Construction",
            "type":"Services"
        }
    ],
    "sg:phone":"+1 251 955 1313",
    "sg:postcode":"36535",
    "sg:province":"AL",
    "sg:tags":[
        "tile",
        "dealer"
    ],
    "wof:name":"Diversified Flooring",
    "wof:placetype":"venue"
},
  "geometry": {"coordinates":[-87.687074,30.421517],"type":"Point"}
}