{
  "type": "Feature",
  "properties": {
    "iso:country":"US",
    "sg:address":"501 Shoals Ave",
    "sg:city":"Killen",
    "sg:classifiers":[
        {
            "category":"Autos & Motor Vehicles",
            "subcategory":"Auto Supplies",
            "type":"Retail Goods"
        }
    ],
    "sg:phone":"+1 256 757 5885",
    "sg:postcode":"35645",
    "sg:province":"AL",
    "sg:tags":[
        "four",
        "wheel",
        "drive",
        "accessory"
    ],
    "wof:name":"Tellico 4X4",
    "wof:placetype":"venue"
},
  "geometry": {"coordinates":[-87.548383,34.866199],"type":"Point"}
}