{
  "type": "Feature",
  "properties": {
    "iso:country":"US",
    "sg:address":"2117 Bellwood Dr",
    "sg:city":"Northport",
    "sg:classifiers":[
        {
            "category":"Professional",
            "type":"Services"
        }
    ],
    "sg:phone":"+1 205 758 4718",
    "sg:postcode":"35476",
    "sg:province":"AL",
    "sg:tags":[
        "establishment"
    ],
    "wof:name":"West Kid's",
    "wof:placetype":"venue"
},
  "geometry": {"coordinates":[-87.578172,33.226143],"type":"Point"}
}