{
  "type": "Feature",
  "properties": {
    "addr:full":"1000 Air Base Blvd Montgomery AL 36108",
    "addr:housenumber":"1000",
    "addr:postcode":"36108",
    "addr:street":"Air Base Blvd",
    "iso:country":"US",
    "sg:address":"1000 Air Base Blvd",
    "sg:city":"Montgomery",
    "sg:classifiers":[
        {
            "category":"Government",
            "subcategory":"Office",
            "type":"Public Place"
        }
    ],
    "sg:phone":"+1 334 240 1400",
    "sg:postcode":"36108",
    "sg:province":"AL",
    "sg:tags":[
        "federal",
        "security"
    ],
    "wof:name":"US Army National Guard",
    "wof:placetype":"venue"
},
  "geometry": {"coordinates":[-86.346166,32.354447],"type":"Point"}
}