{
  "type": "Feature",
  "properties": {
    "iso:country":"US",
    "sg:address":"6015 Weaver Rd",
    "sg:city":"Anniston",
    "sg:classifiers":[
        {
            "category":"Real Estate",
            "subcategory":"Real Estate Operator",
            "type":"Services"
        }
    ],
    "sg:phone":"+1 256 820 1628",
    "sg:postcode":"36206",
    "sg:province":"AL",
    "sg:tags":[
        "apartment"
    ],
    "wof:name":"Cedars Green Apartments",
    "wof:placetype":"venue"
},
  "geometry": {"coordinates":[-85.81661699999999,33.732895],"type":"Point"}
}