{
  "type": "Feature",
  "properties": {
    "iso:country":"US",
    "sg:address":"12731 Power Plant Rd",
    "sg:city":"Tuscaloosa",
    "sg:classifiers":[
        {
            "category":"Mining & Drilling",
            "type":"Manufacturing & Wholesale Goods"
        },
        {
            "category":"Manufacturing",
            "subcategory":"Watercraft",
            "type":"Manufacturing & Wholesale Goods"
        }
    ],
    "sg:phone":"+1 205 752 3573",
    "sg:postcode":"35406",
    "sg:province":"AL",
    "sg:tags":[
        "oil",
        "gas",
        "producer"
    ],
    "wof:name":"Delta Petroleum Corp",
    "wof:placetype":"venue"
},
  "geometry": {"coordinates":[-87.442318,33.28892],"type":"Point"}
}