{
  "type": "Feature",
  "properties": {
    "iso:country":"US",
    "sg:address":"13340 Jenkins Pit Rd",
    "sg:city":"Spanish Fort",
    "sg:classifiers":[
        {
            "category":"Wholesale",
            "subcategory":"Plants",
            "type":"Manufacturing & Wholesale Goods"
        }
    ],
    "sg:phone":"+1 251 626 6650",
    "sg:postcode":"36527",
    "sg:province":"AL",
    "sg:tags":[
        "supply"
    ],
    "wof:name":"Spanish Fort Nursery",
    "wof:placetype":"venue"
},
  "geometry": {"coordinates":[-87.800237,30.69116],"type":"Point"}
}