{
  "type": "Feature",
  "properties": {
    "iso:country":"US",
    "sg:address":"4112 Autumn Ln",
    "sg:city":"Birmingham",
    "sg:classifiers":[
        {
            "category":"Professional",
            "subcategory":"Engineering",
            "type":"Services"
        }
    ],
    "sg:phone":"+1 205 967 9960",
    "sg:postcode":"35243",
    "sg:province":"AL",
    "sg:tags":[
        "water",
        "treatment",
        "engineer"
    ],
    "wof:name":"Chris Matthews Construction",
    "wof:placetype":"venue"
},
  "geometry": {"coordinates":[-86.73257,33.456303],"type":"Point"}
}