{
  "type": "Feature",
  "properties": {
    "iso:country":"US",
    "sg:address":"8668 Lillian Pl",
    "sg:city":"Montgomery",
    "sg:classifiers":[
        {
            "category":"Shopping",
            "subcategory":"Gifts & Souvenirs",
            "type":"Retail Goods"
        }
    ],
    "sg:phone":"+1 334 271 5481",
    "sg:postcode":"36117",
    "sg:province":"AL",
    "sg:tags":[
        "party",
        "supply"
    ],
    "wof:name":"Merrily's Interiors",
    "wof:placetype":"venue"
},
  "geometry": {"coordinates":[-86.154274,32.357289],"type":"Point"}
}