{
  "type": "Feature",
  "properties": {
    "iso:country":"US",
    "sg:address":"245 River Dr",
    "sg:city":"Tuscumbia",
    "sg:classifiers":[
        {
            "category":"Shopping",
            "subcategory":"Pharmacy",
            "type":"Retail Goods"
        }
    ],
    "sg:phone":"+1 256 383 5890",
    "sg:postcode":"35674",
    "sg:province":"AL",
    "wof:name":"White's Drugs",
    "wof:placetype":"venue"
},
  "geometry": {"coordinates":[-87.740993,34.72968],"type":"Point"}
}