{
  "type": "Feature",
  "properties": {
    "addr:full":"3200 Airport Blvd Mobile AL 36606",
    "addr:housenumber":"3200",
    "addr:postcode":"36606",
    "addr:street":"Airport Blvd",
    "iso:country":"US",
    "sg:address":"3200 Airport Blvd",
    "sg:city":"Mobile",
    "sg:classifiers":[
        {
            "category":"Restaurant",
            "type":"Food & Drink"
        }
    ],
    "sg:phone":"+1 251 478 4160",
    "sg:postcode":"36606",
    "sg:province":"AL",
    "sg:tags":[
        "eating"
    ],
    "wof:name":"Exotic Wings & Things",
    "wof:placetype":"venue"
},
  "geometry": {"coordinates":[-88.119877,30.676194],"type":"Point"}
}