{
  "type": "Feature",
  "properties": {
    "iso:country":"US",
    "sg:address":"2801 W Mall Dr",
    "sg:city":"Florence",
    "sg:classifiers":[
        {
            "category":"Professional",
            "subcategory":"Accounting & Tax Preparation",
            "type":"Services"
        }
    ],
    "sg:phone":"+1 256 766 7707",
    "sg:postcode":"35630",
    "sg:province":"AL",
    "sg:tags":[
        "return",
        "filing"
    ],
    "wof:name":"Parkway Tax Svc",
    "wof:placetype":"venue"
},
  "geometry": {"coordinates":[-87.640619,34.840216],"type":"Point"}
}