{
  "type": "Feature",
  "properties": {
    "iso:country":"US",
    "sg:address":"1700 Lee Ave SW",
    "sg:city":"Birmingham",
    "sg:classifiers":[
        {
            "category":"Organizations",
            "subcategory":"Religious Organization",
            "type":"Services"
        }
    ],
    "sg:phone":"+1 205 929 4115",
    "sg:postcode":"35211",
    "sg:province":"AL",
    "sg:tags":[
        "church"
    ],
    "sg:website":"www.pmmw.org",
    "wof:name":"Cornerstone Restoration Church",
    "wof:placetype":"venue"
},
  "geometry": {"coordinates":[-86.864963,33.486157],"type":"Point"}
}