{
  "type": "Feature",
  "properties": {
    "addr:full":"1262 Co Rd 25 Opelika AL 36801",
    "addr:housenumber":"1262;25",
    "addr:postcode":"36801",
    "addr:street":"Co Rd",
    "iso:country":"US",
    "sg:address":"1262 Co Rd 25",
    "sg:city":"Opelika",
    "sg:classifiers":[
        {
            "category":"Building & Trades",
            "subcategory":"Cleaning & Sanitation",
            "type":"Services"
        }
    ],
    "sg:phone":"+1 334 737 1740",
    "sg:postcode":"36801",
    "sg:province":"AL",
    "sg:tags":[
        "janitor"
    ],
    "wof:name":"Maids",
    "wof:placetype":"venue"
},
  "geometry": {"coordinates":[-85.37557099999999,32.730351],"type":"Point"}
}