{
  "type": "Feature",
  "properties": {
    "addr:full":"1905 Liberty Ave Russellville AL 35653",
    "addr:housenumber":"1905",
    "addr:postcode":"35653",
    "addr:street":"Liberty Ave",
    "iso:country":"US",
    "sg:address":"1905 Liberty Ave",
    "sg:city":"Russellville",
    "sg:classifiers":[
        {
            "category":"Manufacturing",
            "subcategory":"Building Materials",
            "type":"Manufacturing & Wholesale Goods"
        }
    ],
    "sg:phone":"+1 256 331 0169",
    "sg:postcode":"35653",
    "sg:province":"AL",
    "sg:tags":[
        "mfg"
    ],
    "wof:name":"Mtw Creative Woodworking Inc",
    "wof:placetype":"venue"
},
  "geometry": {"coordinates":[-87.72727,34.525294],"type":"Point"}
}