{
  "type": "Feature",
  "properties": {
    "iso:country":"US",
    "sg:address":"902 Union Chapel Rd E",
    "sg:city":"Northport",
    "sg:classifiers":[
        {
            "category":"Sports & Exercise",
            "subcategory":"Gym",
            "type":"Entertainment"
        }
    ],
    "sg:phone":"+1 205 333 1999",
    "sg:postcode":"35473",
    "sg:province":"AL",
    "sg:tags":[
        "gymnasium"
    ],
    "wof:name":"Temple Gym",
    "wof:placetype":"venue"
},
  "geometry": {"coordinates":[-87.547512,33.265342],"type":"Point"}
}