{
  "type": "Feature",
  "properties": {
    "iso:country":"US",
    "sg:address":"8189 Vaughn Rd",
    "sg:city":"Montgomery",
    "sg:classifiers":[
        {
            "category":"Shopping",
            "subcategory":"Pharmacy",
            "type":"Retail Goods"
        }
    ],
    "sg:phone":"+1 334 277 4800",
    "sg:postcode":"36116",
    "sg:province":"AL",
    "wof:name":"Adams Drugs",
    "wof:placetype":"venue"
},
  "geometry": {"coordinates":[-86.173304,32.338819],"type":"Point"}
}