{
  "type": "Feature",
  "properties": {
    "iso:country":"US",
    "sg:address":"8603 Co Rd 30",
    "sg:city":"Woodville",
    "sg:classifiers":[
        {
            "category":"Building & Trades",
            "subcategory":"Construction",
            "type":"Services"
        }
    ],
    "sg:phone":"+1 256 776 3300",
    "sg:postcode":"35776",
    "sg:province":"AL",
    "sg:tags":[
        "floor",
        "laying",
        "contractor"
    ],
    "wof:name":"Harbin Flooring",
    "wof:placetype":"venue"
},
  "geometry": {"coordinates":[-86.233862,34.665249],"type":"Point"}
}