{
  "type": "Feature",
  "properties": {
    "iso:country":"US",
    "sg:address":"1804 6th Way NW",
    "sg:city":"Birmingham",
    "sg:classifiers":[
        {
            "category":"Professional",
            "subcategory":"Business Services",
            "type":"Services"
        }
    ],
    "sg:phone":"+1 205 853 1100",
    "sg:postcode":"35215",
    "sg:province":"AL",
    "wof:name":"Margarets Interiors",
    "wof:placetype":"venue"
},
  "geometry": {"coordinates":[-86.705511,33.637592],"type":"Point"}
}