{
  "type": "Feature",
  "properties": {
    "iso:country":"US",
    "sg:address":"14343 US Hwy 11",
    "sg:city":"Collinsville",
    "sg:classifiers":[
        {
            "category":"Shopping",
            "subcategory":"Clothing, Apparel, & Fashions",
            "type":"Retail Goods"
        }
    ],
    "sg:phone":"+1 256 845 7140",
    "sg:postcode":"35961",
    "sg:province":"AL",
    "wof:name":"Little River Outfitters",
    "wof:placetype":"venue"
},
  "geometry": {"coordinates":[-85.78441,34.367036],"type":"Point"}
}