{
  "type": "Feature",
  "properties": {
    "iso:country":"US",
    "sg:address":"2580 Pleasant Valley Rd",
    "sg:city":"Jacksonville",
    "sg:classifiers":[
        {
            "category":"Organizations",
            "subcategory":"Religious Organization",
            "type":"Services"
        }
    ],
    "sg:phone":"+1 256 435 3534",
    "sg:postcode":"36265",
    "sg:province":"AL",
    "wof:name":"Pleasant Vly Holiness Church",
    "wof:placetype":"venue"
},
  "geometry": {"coordinates":[-85.820977,33.862108],"type":"Point"}
}