{
  "type": "Feature",
  "properties": {
    "addr:full":"2801 7th Ave S Birmingham AL 35233",
    "addr:housenumber":"2801",
    "addr:postcode":"35233",
    "addr:street":"7Th Ave S",
    "iso:country":"US",
    "sg:address":"2801 7th Ave S",
    "sg:city":"Birmingham",
    "sg:classifiers":[
        {
            "category":"Restaurant",
            "type":"Food & Drink"
        }
    ],
    "sg:phone":"+1 205 328 7160",
    "sg:postcode":"35233",
    "sg:province":"AL",
    "sg:tags":[
        "eating"
    ],
    "wof:name":"Los Angeles Restaurant",
    "wof:placetype":"venue"
},
  "geometry": {"coordinates":[-86.78824400000001,33.511407],"type":"Point"}
}