{
  "type": "Feature",
  "properties": {
    "addr:full":"8188 Lightwood Rd Marbury AL 36051",
    "addr:housenumber":"8188",
    "addr:postcode":"36051",
    "addr:street":"Lightwood Rd",
    "iso:country":"US",
    "sg:address":"8188 Lightwood Rd",
    "sg:city":"Marbury",
    "sg:classifiers":[
        {
            "category":"Organizations",
            "subcategory":"Religious Organization",
            "type":"Services"
        }
    ],
    "sg:phone":"+1 334 569 2122",
    "sg:postcode":"36051",
    "sg:province":"AL",
    "sg:tags":[
        "church"
    ],
    "wof:name":"Union Congregational Christian",
    "wof:placetype":"venue"
},
  "geometry": {"coordinates":[-86.397599,32.715545],"type":"Point"}
}