{
  "type": "Feature",
  "properties": {
    "iso:country":"US",
    "sg:address":"4401 20th Ave",
    "sg:city":"Valley",
    "sg:classifiers":[
        {
            "category":"Building & Trades",
            "subcategory":"Construction",
            "type":"Services"
        }
    ],
    "sg:phone":"+1 334 756 5012",
    "sg:postcode":"36854",
    "sg:province":"AL",
    "sg:tags":[
        "general",
        "contractor"
    ],
    "sg:website":"www.danric.com",
    "wof:name":"Dan-Ric HOMES LLC",
    "wof:placetype":"venue"
},
  "geometry": {"coordinates":[-85.174925,32.828103],"type":"Point"}
}