{
  "type": "Feature",
  "properties": {
    "iso:country":"US",
    "sg:address":"3905 US Hwy 31",
    "sg:city":"Verbena",
    "sg:classifiers":[
        {
            "category":"Personal",
            "subcategory":"Beauty Salon",
            "type":"Services"
        }
    ],
    "sg:phone":"+1 205 280 8866",
    "sg:postcode":"36091",
    "sg:province":"AL",
    "wof:name":"Small Town Salon",
    "wof:placetype":"venue"
},
  "geometry": {"coordinates":[-86.49701,32.743749],"type":"Point"}
}