{
  "type": "Feature",
  "properties": {
    "iso:country":"US",
    "sg:address":"3943 Co Rd 22",
    "sg:city":"Plantersville",
    "sg:classifiers":[
        {
            "category":"Organizations",
            "subcategory":"Religious Organization",
            "type":"Services"
        }
    ],
    "sg:phone":"+1 334 366 0701",
    "sg:postcode":"36758",
    "sg:province":"AL",
    "sg:tags":[
        "church"
    ],
    "wof:name":"Bethel Grove Baptist Church",
    "wof:placetype":"venue"
},
  "geometry": {"coordinates":[-86.876405,32.628318],"type":"Point"}
}