{
  "type": "Feature",
  "properties": {
    "iso:country":"US",
    "sg:address":"6712 Co Rd 24",
    "sg:city":"Clanton",
    "sg:classifiers":[
        {
            "category":"Farming",
            "subcategory":"Livestock Farm",
            "type":"Manufacturing & Wholesale Goods"
        }
    ],
    "sg:phone":"+1 205 755 3786",
    "sg:postcode":"35045",
    "sg:province":"AL",
    "sg:tags":[
        "beef",
        "feedlot",
        "cattle"
    ],
    "wof:name":"Wendell Powell",
    "wof:placetype":"venue"
},
  "geometry": {"coordinates":[-86.606831,32.738943],"type":"Point"}
}