{
  "type": "Feature",
  "properties": {
    "iso:country":"US",
    "sg:address":"1115 N Eufaula Ave",
    "sg:city":"Eufaula",
    "sg:classifiers":[
        {
            "category":"Retail",
            "subcategory":"Repair Shop",
            "type":"Services"
        }
    ],
    "sg:phone":"+1 334 687 5468",
    "sg:postcode":"36027",
    "sg:province":"AL",
    "sg:tags":[
        "lock",
        "locksmith"
    ],
    "wof:name":"Harrison's Lock Svc",
    "wof:placetype":"venue"
},
  "geometry": {"coordinates":[-85.148062,31.914349],"type":"Point"}
}