{
  "type": "Feature",
  "properties": {
    "iso:country":"US",
    "sg:address":"5434 State Rte 171",
    "sg:city":"Fayette",
    "sg:classifiers":[
        {
            "category":"Manufacturing",
            "subcategory":"Lumber",
            "type":"Manufacturing & Wholesale Goods"
        }
    ],
    "sg:phone":"+1 205 932 6223",
    "sg:postcode":"35555",
    "sg:province":"AL",
    "sg:tags":[
        "forestry",
        "government"
    ],
    "wof:name":"Alabama Forestry Commission",
    "wof:placetype":"venue"
},
  "geometry": {"coordinates":[-87.83134200000001,33.619794],"type":"Point"}
}