{
  "type": "Feature",
  "properties": {
    "iso:country":"US",
    "sg:address":"2201 Williamsburg Dr",
    "sg:city":"Pelham",
    "sg:classifiers":[
        {
            "category":"Professional",
            "subcategory":"Employment Agencies",
            "type":"Services"
        }
    ],
    "sg:phone":"+1 205 663 5960",
    "sg:postcode":"35124",
    "sg:province":"AL",
    "wof:name":"Dynamic Resources Inc",
    "wof:placetype":"venue"
},
  "geometry": {"coordinates":[-86.809991,33.32853],"type":"Point"}
}