{
  "type": "Feature",
  "properties": {
    "iso:country":"US",
    "sg:address":"300 Pine Ridge Rd",
    "sg:city":"Bessemer",
    "sg:classifiers":[
        {
            "category":"Organizations",
            "subcategory":"Religious Organization",
            "type":"Services"
        }
    ],
    "sg:phone":"+1 205 436 3000",
    "sg:postcode":"35023",
    "sg:province":"AL",
    "wof:name":"Pine Ridge Baptist Church",
    "wof:placetype":"venue"
},
  "geometry": {"coordinates":[-87.181062,33.554257],"type":"Point"}
}