{
  "type": "Feature",
  "properties": {
    "addr:full":"137 S Eufaula Ave Eufaula AL 36027",
    "addr:housenumber":"137",
    "addr:postcode":"36027",
    "addr:street":"S Eufaula Ave",
    "iso:country":"US",
    "sg:address":"137 S Eufaula Ave",
    "sg:city":"Eufaula",
    "sg:classifiers":[
        {
            "category":"Shopping",
            "type":"Retail Goods"
        }
    ],
    "sg:phone":"+1 334 687 9981",
    "sg:postcode":"36027",
    "sg:province":"AL",
    "sg:tags":[
        "art",
        "gallery",
        "dealer"
    ],
    "wof:name":"Art Services",
    "wof:placetype":"venue"
},
  "geometry": {"coordinates":[-85.145534,31.890921],"type":"Point"}
}