{
  "type": "Feature",
  "properties": {
    "addr:full":"110 Commerce Dr Pelham AL 35124",
    "addr:housenumber":"110",
    "addr:postcode":"35124",
    "addr:street":"Commerce Dr",
    "iso:country":"US",
    "sg:address":"110 Commerce Dr",
    "sg:city":"Pelham",
    "sg:classifiers":[
        {
            "category":"Manufacturing",
            "subcategory":"Tools & Machinery",
            "type":"Manufacturing & Wholesale Goods"
        }
    ],
    "sg:phone":"+1 205 663 0533",
    "sg:postcode":"35124",
    "sg:province":"AL",
    "sg:tags":[
        "control",
        "cylinder",
        "fluid",
        "power",
        "mfg"
    ],
    "wof:name":"Morin Actuator",
    "wof:placetype":"venue"
},
  "geometry": {"coordinates":[-86.802578,33.291785],"type":"Point"}
}