{
  "type": "Feature",
  "properties": {
    "iso:country":"US",
    "sg:address":"6513 Avenue E",
    "sg:city":"Fairfield",
    "sg:classifiers":[
        {
            "category":"Organizations",
            "subcategory":"Religious Organization",
            "type":"Services"
        }
    ],
    "sg:phone":"+1 205 787 5207",
    "sg:postcode":"35064",
    "sg:province":"AL",
    "wof:name":"Saint Paul A M E Church",
    "wof:placetype":"venue"
},
  "geometry": {"coordinates":[-86.911631,33.474109],"type":"Point"}
}