{
  "type": "Feature",
  "properties": {
    "iso:country":"US",
    "sg:address":"2567 Fairlane Dr",
    "sg:city":"Montgomery",
    "sg:classifiers":[
        {
            "category":"Professional",
            "subcategory":"Engineering",
            "type":"Services"
        }
    ],
    "sg:phone":"+1 334 271 1444",
    "sg:postcode":"36116",
    "sg:province":"AL",
    "sg:tags":[
        "engineer"
    ],
    "wof:name":"CH2M Hill",
    "wof:placetype":"venue"
},
  "geometry": {"coordinates":[-86.237329,32.331666],"type":"Point"}
}