{
  "type": "Feature",
  "properties": {
    "iso:country":"US",
    "sg:address":"1518 W Andrews Ave",
    "sg:city":"Ozark",
    "sg:classifiers":[
        {
            "category":"Real Estate",
            "subcategory":"Real Estate Operator",
            "type":"Services"
        }
    ],
    "sg:phone":"+1 334 774 0003",
    "sg:postcode":"36360",
    "sg:province":"AL",
    "sg:tags":[
        "apartment"
    ],
    "wof:name":"Jasmine Hill Apartments",
    "wof:placetype":"venue"
},
  "geometry": {"coordinates":[-85.66684,31.436347],"type":"Point"}
}