{
  "type": "Feature",
  "properties": {
    "iso:country":"US",
    "sg:address":"1241 Geneva Hwy",
    "sg:city":"Enterprise",
    "sg:classifiers":[
        {
            "category":"Wholesale",
            "subcategory":"Farm Supplies",
            "type":"Manufacturing & Wholesale Goods"
        }
    ],
    "sg:phone":"+1 334 347 9007",
    "sg:postcode":"36330",
    "sg:province":"AL",
    "wof:name":"Bonnie Lawn & Garden Center",
    "wof:placetype":"venue"
},
  "geometry": {"coordinates":[-85.864171,31.293776],"type":"Point"}
}