{
  "type": "Feature",
  "properties": {
    "addr:full":"2201 University Dr NW Huntsville AL 35816",
    "addr:housenumber":"2201",
    "addr:postcode":"35816",
    "addr:street":"University Dr Nw",
    "iso:country":"US",
    "sg:address":"2201 University Dr NW",
    "sg:city":"Huntsville",
    "sg:classifiers":[
        {
            "category":"Restaurant",
            "type":"Food & Drink"
        }
    ],
    "sg:menulink":"http://www.allmenus.com/al/huntsville/55653-subway/menu/",
    "sg:phone":"+1 256 539 7625",
    "sg:postcode":"35816",
    "sg:province":"AL",
    "sg:tags":[
        "american",
        "sandwich"
    ],
    "wof:name":"Subway",
    "wof:placetype":"venue"
},
  "geometry": {"coordinates":[-86.60374299999999,34.738588],"type":"Point"}
}