{
  "type": "Feature",
  "properties": {
    "iso:country":"US",
    "sg:address":"820 Bradley St SW",
    "sg:city":"Decatur",
    "sg:classifiers":[
        {
            "category":"Personal",
            "subcategory":"Beauty Salon",
            "type":"Services"
        }
    ],
    "sg:phone":"+1 256 301 1555",
    "sg:postcode":"35601",
    "sg:province":"AL",
    "wof:name":"Peluqueria Marie",
    "wof:placetype":"venue"
},
  "geometry": {"coordinates":[-86.998558,34.571209],"type":"Point"}
}