{
  "type": "Feature",
  "properties": {
    "addr:full":"2801 US Hwy 80 Phenix City AL 36870",
    "addr:housenumber":"2801",
    "addr:postcode":"36870",
    "addr:street":"Us Hwy 80 Phenix City Al",
    "iso:country":"US",
    "sg:address":"2801 US Hwy 80",
    "sg:city":"Phenix City",
    "sg:classifiers":[
        {
            "category":"Retail",
            "subcategory":"Auto Repair",
            "type":"Services"
        }
    ],
    "sg:phone":"+1 334 297 1767",
    "sg:postcode":"36870",
    "sg:province":"AL",
    "sg:tags":[
        "repairing",
        "automobile"
    ],
    "wof:name":"Generic Transmission",
    "wof:placetype":"venue"
},
  "geometry": {"coordinates":[-85.03266000000001,32.475299],"type":"Point"}
}