{
  "type": "Feature",
  "properties": {
    "iso:country":"US",
    "sg:address":"146 E Broad St",
    "sg:city":"Eufaula",
    "sg:classifiers":[
        {
            "category":"Shopping",
            "subcategory":"Pharmacy",
            "type":"Retail Goods"
        }
    ],
    "sg:phone":"+1 334 687 3591",
    "sg:postcode":"36027",
    "sg:province":"AL",
    "wof:name":"Eufaula Drugs Valu-Rite",
    "wof:placetype":"venue"
},
  "geometry": {"coordinates":[-85.144893,31.893216],"type":"Point"}
}