{
  "type": "Feature",
  "properties": {
    "addr:full":"2908 W Main St Mobile AL 36612",
    "addr:housenumber":"2908",
    "addr:postcode":"36612",
    "addr:street":"W Main St",
    "iso:country":"US",
    "sg:address":"2908 W Main St",
    "sg:city":"Mobile",
    "sg:classifiers":[
        {
            "category":"Mining & Drilling",
            "type":"Manufacturing & Wholesale Goods"
        }
    ],
    "sg:phone":"+1 251 246 2333",
    "sg:postcode":"36612",
    "sg:province":"AL",
    "sg:tags":[
        "sand",
        "gravel",
        "mine"
    ],
    "wof:name":"Jackson Land Fill Reclmtn Prjc",
    "wof:placetype":"venue"
},
  "geometry": {"coordinates":[-88.104226,30.750191],"type":"Point"}
}