{
  "type": "Feature",
  "properties": {
    "iso:country":"US",
    "sg:address":"2120 Wildwood Pl",
    "sg:city":"Mobile",
    "sg:classifiers":[
        {
            "category":"Professional",
            "subcategory":"Accounting & Tax Preparation",
            "type":"Services"
        }
    ],
    "sg:phone":"+1 251 665 4545",
    "sg:postcode":"36609",
    "sg:province":"AL",
    "sg:tags":[
        "business"
    ],
    "wof:name":"Integrated Technologies Corp",
    "wof:placetype":"venue"
},
  "geometry": {"coordinates":[-88.172831,30.644367],"type":"Point"}
}