{
  "type": "Feature",
  "properties": {
    "addr:full":"7297 Old Mitylene Rd Montgomery AL 36117",
    "addr:housenumber":"7297",
    "addr:postcode":"36117",
    "addr:street":"Old Mitylene Rd",
    "iso:country":"US",
    "sg:address":"7297 Old Mitylene Rd",
    "sg:city":"Montgomery",
    "sg:classifiers":[
        {
            "category":"Building & Trades",
            "subcategory":"Landscaping Services",
            "type":"Services"
        }
    ],
    "sg:phone":"+1 334 272 6408",
    "sg:postcode":"36117",
    "sg:province":"AL",
    "wof:name":"JPS Lawn Service",
    "wof:placetype":"venue"
},
  "geometry": {"coordinates":[-86.160228,32.396767],"type":"Point"}
}