{
  "type": "Feature",
  "properties": {
    "iso:country":"US",
    "sg:address":"10081 Snake Rd",
    "sg:city":"Athens",
    "sg:classifiers":[
        {
            "category":"Organizations",
            "subcategory":"Religious Organization",
            "type":"Services"
        }
    ],
    "sg:phone":"+1 256 729 1705",
    "sg:postcode":"35611",
    "sg:province":"AL",
    "wof:name":"Saint Paul Mssnary Bptst Chrch",
    "wof:placetype":"venue"
},
  "geometry": {"coordinates":[-87.14533400000001,34.777364],"type":"Point"}
}