{
  "type": "Feature",
  "properties": {
    "iso:country":"US",
    "sg:address":"3412 W Chapel Hill Rd",
    "sg:city":"Decatur",
    "sg:classifiers":[
        {
            "category":"Professional",
            "type":"Services"
        }
    ],
    "sg:phone":"+1 256 351 0923",
    "sg:postcode":"35603",
    "sg:province":"AL",
    "wof:name":"Ray & Michelle Dotson",
    "wof:placetype":"venue"
},
  "geometry": {"coordinates":[-87.062347,34.546742],"type":"Point"}
}