{
  "type": "Feature",
  "properties": {
    "addr:full":"204 3rd St NE Lafayette AL 36862",
    "addr:housenumber":"204",
    "addr:postcode":"36862",
    "addr:street":"3Rd St Ne",
    "iso:country":"US",
    "sg:address":"204 3rd St NE",
    "sg:city":"Lafayette",
    "sg:classifiers":[
        {
            "category":"Freight",
            "type":"Transportation"
        }
    ],
    "sg:phone":"+1 334 864 7334",
    "sg:postcode":"36862",
    "sg:province":"AL",
    "sg:tags":[
        "operator",
        "local",
        "trucking"
    ],
    "wof:name":"Brooks Trucking Co",
    "wof:placetype":"venue"
},
  "geometry": {"coordinates":[-85.395892,32.902909],"type":"Point"}
}