{
  "type": "Feature",
  "properties": {
    "iso:country":"US",
    "sg:address":"24257 Co Rd 55",
    "sg:city":"Loxley",
    "sg:classifiers":[
        {
            "category":"Building & Trades",
            "subcategory":"Construction",
            "type":"Services"
        }
    ],
    "sg:phone":"+1 251 947 3915",
    "sg:postcode":"36551",
    "sg:province":"AL",
    "sg:tags":[
        "house",
        "nonresidential"
    ],
    "wof:name":"Gary Powers Development Inc",
    "wof:placetype":"venue"
},
  "geometry": {"coordinates":[-87.750776,30.578751],"type":"Point"}
}