{
  "type": "Feature",
  "properties": {
    "addr:full":"6419 Willow Brook Run W Mobile AL 36608",
    "addr:housenumber":"6419",
    "addr:postcode":"36608",
    "addr:street":"Willow Brook Run W",
    "iso:country":"US",
    "sg:address":"6419 Willow Brook Run W",
    "sg:city":"Mobile",
    "sg:classifiers":[
        {
            "category":"Retail",
            "subcategory":"Repair Shop",
            "type":"Services"
        }
    ],
    "sg:phone":"+1 251 341 0333",
    "sg:postcode":"36608",
    "sg:province":"AL",
    "sg:tags":[
        "clocks",
        "parts"
    ],
    "wof:name":"Clockworks",
    "wof:placetype":"venue"
},
  "geometry": {"coordinates":[-88.19338500000001,30.682554],"type":"Point"}
}