{
  "type": "Feature",
  "properties": {
    "iso:country":"US",
    "sg:address":"7527 66th St S",
    "sg:city":"Birmingham",
    "sg:classifiers":[
        {
            "category":"Real Estate",
            "subcategory":"Real Estate Agent",
            "type":"Services"
        }
    ],
    "sg:phone":"+1 205 521 7820",
    "sg:postcode":"35212",
    "sg:province":"AL",
    "sg:tags":[
        "authorities",
        "housing"
    ],
    "wof:name":"Birmingham Housing Authority",
    "wof:placetype":"venue"
},
  "geometry": {"coordinates":[-86.725494,33.543127],"type":"Point"}
}