{
  "type": "Feature",
  "properties": {
    "iso:country":"US",
    "sg:address":"35000 Magnolia Farms Rd",
    "sg:city":"Robertsdale",
    "sg:classifiers":[
        {
            "category":"Recreation",
            "type":"Entertainment"
        }
    ],
    "sg:phone":"+1 251 931 3337",
    "sg:postcode":"36567",
    "sg:province":"AL",
    "sg:tags":[
        "club",
        "membership"
    ],
    "wof:name":"Turkey Flat Hunting Club",
    "wof:placetype":"venue"
},
  "geometry": {"coordinates":[-87.431023,30.616753],"type":"Point"}
}