{
  "type": "Feature",
  "properties": {
    "iso:country":"US",
    "sg:address":"7471 Theodore Dawes Rd",
    "sg:city":"Theodore",
    "sg:classifiers":[
        {
            "category":"Retail",
            "subcategory":"Auto Repair",
            "type":"Services"
        }
    ],
    "sg:phone":"+1 251 653 8586",
    "sg:postcode":"36582",
    "sg:province":"AL",
    "sg:tags":[
        "installs",
        "automotive",
        "upholstery",
        "glass"
    ],
    "wof:name":"All Purpose Auto Glass & Uphl",
    "wof:placetype":"venue"
},
  "geometry": {"coordinates":[-88.219191,30.568288],"type":"Point"}
}