{
  "type": "Feature",
  "properties": {
    "iso:country":"US",
    "sg:address":"160 Wesley Childers Rd",
    "sg:city":"New Hope",
    "sg:classifiers":[
        {
            "category":"Farming",
            "subcategory":"Livestock Farm",
            "type":"Manufacturing & Wholesale Goods"
        }
    ],
    "sg:phone":"+1 256 723 4880",
    "sg:postcode":"35760",
    "sg:province":"AL",
    "sg:tags":[
        "real",
        "beef",
        "lessor",
        "cattle",
        "property",
        "feedlot"
    ],
    "wof:name":"Jones Odie",
    "wof:placetype":"venue"
},
  "geometry": {"coordinates":[-86.366811,34.552236],"type":"Point"}
}