{
  "type": "Feature",
  "properties": {
    "addr:full":"115 W Willow St Scottsboro AL 35768",
    "addr:housenumber":"115",
    "addr:postcode":"35768",
    "addr:street":"W Willow St",
    "iso:country":"US",
    "sg:address":"115 W Willow St",
    "sg:city":"Scottsboro",
    "sg:classifiers":[
        {
            "category":"Professional",
            "subcategory":"Accounting & Tax Preparation",
            "type":"Services"
        }
    ],
    "sg:phone":"+1 256 259 1704",
    "sg:postcode":"35768",
    "sg:province":"AL",
    "sg:tags":[
        "return",
        "filing"
    ],
    "wof:name":"Bramblett Tax Svc",
    "wof:placetype":"venue"
},
  "geometry": {"coordinates":[-86.035082,34.67352],"type":"Point"}
}