{
  "type": "Feature",
  "properties": {
    "iso:country":"US",
    "sg:address":"3048 Dorchester Dr",
    "sg:city":"Montgomery",
    "sg:classifiers":[
        {
            "category":"Retail",
            "subcategory":"Funeral Services",
            "type":"Services"
        }
    ],
    "sg:phone":"+1 334 613 1866",
    "sg:postcode":"36116",
    "sg:province":"AL",
    "sg:tags":[
        "director"
    ],
    "wof:name":"Montgomery Memorial Funeral Hm",
    "wof:placetype":"venue"
},
  "geometry": {"coordinates":[-86.259409,32.322037],"type":"Point"}
}