{
  "type": "Feature",
  "properties": {
    "iso:country":"US",
    "sg:address":"2315 Roberts Ln",
    "sg:city":"Florence",
    "sg:classifiers":[
        {
            "category":"Organizations",
            "subcategory":"Religious Organization",
            "type":"Services"
        }
    ],
    "sg:phone":"+1 256 760 9900",
    "sg:postcode":"35630",
    "sg:province":"AL",
    "sg:tags":[
        "church"
    ],
    "wof:name":"Creekside Church Of Christ",
    "wof:placetype":"venue"
},
  "geometry": {"coordinates":[-87.692536,34.832205],"type":"Point"}
}