{
  "type": "Feature",
  "properties": {
    "addr:full":"2787 Co Rd 11 Pelham AL 35124",
    "addr:housenumber":"2787;11",
    "addr:postcode":"35124",
    "addr:street":"Co Rd",
    "iso:country":"US",
    "sg:address":"2787 Co Rd 11",
    "sg:city":"Pelham",
    "sg:classifiers":[
        {
            "category":"Manufacturing",
            "subcategory":"Metals",
            "type":"Manufacturing & Wholesale Goods"
        }
    ],
    "sg:phone":"+1 205 663 6961",
    "sg:postcode":"35124",
    "sg:province":"AL",
    "sg:tags":[
        "joint",
        "expansion"
    ],
    "sg:website":"www.valleyofbham.com",
    "wof:name":"Valley Of Birmingham",
    "wof:placetype":"venue"
},
  "geometry": {"coordinates":[-86.786317,33.271439],"type":"Point"}
}