{
  "type": "Feature",
  "properties": {
    "addr:full":"3004 Mulberry Rd Selma AL 36703",
    "addr:housenumber":"3004",
    "addr:postcode":"36703",
    "addr:street":"Mulberry Rd",
    "iso:country":"US",
    "sg:address":"3004 Mulberry Rd",
    "sg:city":"Selma",
    "sg:classifiers":[
        {
            "category":"Retail",
            "subcategory":"Auto Repair",
            "type":"Services"
        }
    ],
    "sg:phone":"+1 334 872 2238",
    "sg:postcode":"36703",
    "sg:province":"AL",
    "sg:tags":[
        "truck"
    ],
    "wof:name":"Selma Truck & Trailer",
    "wof:placetype":"venue"
},
  "geometry": {"coordinates":[-87.00172999999999,32.404719],"type":"Point"}
}