{
  "type": "Feature",
  "properties": {
    "iso:country":"US",
    "sg:address":"3157 Cahaba Heights Rd",
    "sg:city":"Birmingham",
    "sg:classifiers":[
        {
            "category":"Shopping",
            "subcategory":"Clothing, Apparel, & Fashions",
            "type":"Retail Goods"
        }
    ],
    "sg:phone":"+1 205 969 3132",
    "sg:postcode":"35243",
    "sg:province":"AL",
    "sg:tags":[
        "accessory"
    ],
    "wof:name":"Latest Thing LLC",
    "wof:placetype":"venue"
},
  "geometry": {"coordinates":[-86.737155,33.456488],"type":"Point"}
}