{
  "type": "Feature",
  "properties": {
    "iso:country":"US",
    "sg:address":"80 Cogswell Ave",
    "sg:city":"Pell City",
    "sg:classifiers":[
        {
            "category":"Retail",
            "subcategory":"Auto Repair",
            "type":"Services"
        }
    ],
    "sg:phone":"+1 205 338 4563",
    "sg:postcode":"35125",
    "sg:province":"AL",
    "sg:tags":[
        "body",
        "general"
    ],
    "wof:name":"Hammonds Body Shop",
    "wof:placetype":"venue"
},
  "geometry": {"coordinates":[-86.316058,33.588397],"type":"Point"}
}