{
  "type": "Feature",
  "properties": {
    "addr:full":"2224 24th Ave N Birmingham AL 35234",
    "addr:housenumber":"2224",
    "addr:postcode":"35234",
    "addr:street":"24Th Ave N",
    "iso:country":"US",
    "sg:address":"2224 24th Ave N",
    "sg:city":"Birmingham",
    "sg:classifiers":[
        {
            "category":"Freight",
            "type":"Transportation"
        }
    ],
    "sg:phone":"+1 205 251 1222",
    "sg:postcode":"35234",
    "sg:province":"AL",
    "sg:tags":[
        "distance",
        "storage",
        "long",
        "trucking",
        "without",
        "local"
    ],
    "wof:name":"Commercial Hauling Co Inc",
    "wof:placetype":"venue"
},
  "geometry": {"coordinates":[-86.81967299999999,33.543366],"type":"Point"}
}