{
  "type": "Feature",
  "properties": {
    "iso:country":"US",
    "sg:address":"2114 Norris Rd NW",
    "sg:city":"Huntsville",
    "sg:classifiers":[
        {
            "category":"Professional",
            "type":"Services"
        }
    ],
    "sg:phone":"+1 256 520 3843",
    "sg:postcode":"35810",
    "sg:province":"AL",
    "wof:name":"Kobalt Services",
    "wof:placetype":"venue"
},
  "geometry": {"coordinates":[-86.586943,34.784363],"type":"Point"}
}