{
  "type": "Feature",
  "properties": {
    "addr:full":"3879 State Rte 188 Coden AL 36523",
    "addr:housenumber":"3879",
    "addr:postcode":"36523",
    "addr:street":"State Rte 188",
    "iso:country":"US",
    "sg:address":"3879 State Rte 188",
    "sg:city":"Coden",
    "sg:classifiers":[
        {
            "category":"Food & Beverages",
            "subcategory":"Groceries & Convenience Stores",
            "type":"Retail Goods"
        }
    ],
    "sg:phone":"+1 251 873 5009",
    "sg:postcode":"36523",
    "sg:province":"AL",
    "wof:name":"Lilleys Country Store",
    "wof:placetype":"venue"
},
  "geometry": {"coordinates":[-88.13237599999999,30.365817],"type":"Point"}
}