{
  "type": "Feature",
  "properties": {
    "iso:country":"US",
    "sg:address":"1101 Greensboro Ave",
    "sg:city":"Tuscaloosa",
    "sg:classifiers":[
        {
            "category":"Banks & Credit Unions",
            "subcategory":"Bank",
            "type":"Services"
        }
    ],
    "sg:phone":"+1 205 750 8645",
    "sg:postcode":"35401",
    "sg:province":"AL",
    "wof:name":"National Bank Of Commerce",
    "wof:placetype":"venue"
},
  "geometry": {"coordinates":[-87.56558099999999,33.20319],"type":"Point"}
}