{
  "type": "Feature",
  "properties": {
    "addr:full":"7150 Cedar St Mobile AL 36608",
    "addr:housenumber":"7150",
    "addr:postcode":"36608",
    "addr:street":"Cedar St",
    "iso:country":"US",
    "sg:address":"7150 Cedar St",
    "sg:city":"Mobile",
    "sg:classifiers":[
        {
            "category":"Building & Trades",
            "subcategory":"Landscaping Services",
            "type":"Services"
        }
    ],
    "sg:phone":"+1 251 343 3970",
    "sg:postcode":"36608",
    "sg:province":"AL",
    "wof:name":"New Life Lawn Care",
    "wof:placetype":"venue"
},
  "geometry": {"coordinates":[-88.209999,30.689875],"type":"Point"}
}