{
  "type": "Feature",
  "properties": {
    "addr:full":"103 Dauphin St Mobile AL 36602",
    "addr:housenumber":"103",
    "addr:postcode":"36602",
    "addr:street":"Dauphin St",
    "iso:country":"US",
    "sg:address":"103 Dauphin St",
    "sg:city":"Mobile",
    "sg:classifiers":[
        {
            "category":"Professional",
            "subcategory":"Lawyer & Legal Services",
            "type":"Services"
        }
    ],
    "sg:phone":"+1 251 694 1139",
    "sg:postcode":"36602",
    "sg:province":"AL",
    "sg:tags":[
        "attorney"
    ],
    "wof:name":"Joseph Altadonna",
    "wof:placetype":"venue"
},
  "geometry": {"coordinates":[-88.041635,30.691929],"type":"Point"}
}