{
  "type": "Feature",
  "properties": {
    "addr:full":"201 E Lafayette St Dadeville AL 36853",
    "addr:housenumber":"201",
    "addr:postcode":"36853",
    "addr:street":"E Lafayette St",
    "iso:country":"US",
    "sg:address":"201 E Lafayette St",
    "sg:city":"Dadeville",
    "sg:classifiers":[
        {
            "category":"Utilities",
            "subcategory":"Electric",
            "type":"Services"
        }
    ],
    "sg:phone":"+1 256 825 4649",
    "sg:postcode":"36853",
    "sg:province":"AL",
    "wof:name":"Alabama Power Company",
    "wof:placetype":"venue"
},
  "geometry": {"coordinates":[-85.761275,32.832952],"type":"Point"}
}