{
  "type": "Feature",
  "properties": {
    "iso:country":"US",
    "sg:address":"9071 Manley Vines Camp Rd",
    "sg:city":"Bessemer",
    "sg:classifiers":[
        {
            "category":"Building & Trades",
            "subcategory":"Construction",
            "type":"Services"
        }
    ],
    "sg:phone":"+1 205 436 3966",
    "sg:postcode":"35023",
    "sg:province":"AL",
    "sg:tags":[
        "excavation",
        "contractor"
    ],
    "wof:name":"Cain Trucking",
    "wof:placetype":"venue"
},
  "geometry": {"coordinates":[-87.14933,33.551884],"type":"Point"}
}