{
  "type": "Feature",
  "properties": {
    "iso:country":"US",
    "sg:address":"1871 Slaughter Rd",
    "sg:city":"Madison",
    "sg:classifiers":[
        {
            "category":"Organizations",
            "subcategory":"Professional Association",
            "type":"Services"
        }
    ],
    "sg:phone":"+1 256 895 6904",
    "sg:postcode":"35758",
    "sg:province":"AL",
    "sg:tags":[
        "consulting",
        "business"
    ],
    "wof:name":"I-Car",
    "wof:placetype":"venue"
},
  "geometry": {"coordinates":[-86.714456,34.752916],"type":"Point"}
}