{
  "type": "Feature",
  "properties": {
    "iso:country":"US",
    "sg:address":"2774 Mount Olive Rd",
    "sg:city":"Mount Olive",
    "sg:classifiers":[
        {
            "category":"Personal",
            "type":"Services"
        }
    ],
    "sg:phone":"+1 205 631 6086",
    "sg:postcode":"35117",
    "sg:province":"AL",
    "wof:name":"Endless Summers",
    "wof:placetype":"venue"
},
  "geometry": {"coordinates":[-86.859524,33.672939],"type":"Point"}
}