{
  "type": "Feature",
  "properties": {
    "iso:country":"US",
    "sg:address":"2406 Stratford Rd SE",
    "sg:city":"Decatur",
    "sg:classifiers":[
        {
            "category":"Restaurant",
            "type":"Food & Drink"
        }
    ],
    "sg:phone":"+1 256 355 9071",
    "sg:postcode":"35601",
    "sg:province":"AL",
    "sg:tags":[
        "style",
        "family"
    ],
    "wof:name":"The Casual Gourmet",
    "wof:placetype":"venue"
},
  "geometry": {"coordinates":[-86.95116,34.573236],"type":"Point"}
}