{
  "type": "Feature",
  "properties": {
    "addr:full":"107 Iris Cir Daphne AL 36526",
    "addr:housenumber":"107",
    "addr:postcode":"36526",
    "addr:street":"Iris Cir",
    "iso:country":"US",
    "sg:address":"107 Iris Cir",
    "sg:city":"Daphne",
    "sg:classifiers":[
        {
            "category":"Shopping",
            "subcategory":"Tobacco",
            "type":"Retail Goods"
        }
    ],
    "sg:phone":"+1 251 625 1241",
    "sg:postcode":"36526",
    "sg:province":"AL",
    "sg:tags":[
        "product",
        "beverage",
        "alcoholic"
    ],
    "wof:name":"Tobacco Jacks",
    "wof:placetype":"venue"
},
  "geometry": {"coordinates":[-87.903914,30.637969],"type":"Point"}
}