{
  "type": "Feature",
  "properties": {
    "iso:country":"US",
    "sg:address":"58 Vine St",
    "sg:city":"Birmingham",
    "sg:classifiers":[
        {
            "category":"Health Services",
            "subcategory":"Doctor",
            "type":"Services"
        }
    ],
    "sg:phone":"+1 205 870 4205",
    "sg:postcode":"35213",
    "sg:province":"AL",
    "wof:name":"Southern Eye Center",
    "wof:placetype":"venue"
},
  "geometry": {"coordinates":[-86.755022,33.503045],"type":"Point"}
}