{
  "type": "Feature",
  "properties": {
    "iso:country":"US",
    "sg:address":"224 City Park Dr SE",
    "sg:city":"Arab",
    "sg:classifiers":[
        {
            "category":"Recreation",
            "type":"Entertainment"
        }
    ],
    "sg:phone":"+1 256 586 6328",
    "sg:postcode":"35016",
    "sg:province":"AL",
    "sg:tags":[
        "pool",
        "swimming"
    ],
    "wof:name":"Arab City Swimming Pool",
    "wof:placetype":"venue"
},
  "geometry": {"coordinates":[-86.493589,34.309031],"type":"Point"}
}