{
  "type": "Feature",
  "properties": {
    "addr:full":"463 Opelika Rd Auburn AL 36830",
    "addr:housenumber":"463",
    "addr:postcode":"36830",
    "addr:street":"Opelika Rd",
    "iso:country":"US",
    "sg:address":"463 Opelika Rd",
    "sg:city":"Auburn",
    "sg:classifiers":[
        {
            "category":"Personal",
            "subcategory":"Beauty Salon",
            "type":"Services"
        }
    ],
    "sg:phone":"+1 334 821 8846",
    "sg:postcode":"36830",
    "sg:province":"AL",
    "wof:name":"G & S House Of Styles",
    "wof:placetype":"venue"
},
  "geometry": {"coordinates":[-85.472179,32.613634],"type":"Point"}
}