{
  "type": "Feature",
  "properties": {
    "iso:country":"US",
    "sg:address":"2509 Leroy Stevens Rd",
    "sg:city":"Mobile",
    "sg:classifiers":[
        {
            "category":"Building & Trades",
            "subcategory":"Construction",
            "type":"Services"
        },
        {
            "category":"Home & Garden",
            "subcategory":"Furniture",
            "type":"Retail Goods"
        }
    ],
    "sg:phone":"+1 251 639 1360",
    "sg:postcode":"36695",
    "sg:province":"AL",
    "sg:tags":[
        "cabinet",
        "maker",
        "custom"
    ],
    "wof:name":"Vo Woodworking Inc",
    "wof:placetype":"venue"
},
  "geometry": {"coordinates":[-88.233046,30.63291],"type":"Point"}
}