{
  "type": "Feature",
  "properties": {
    "iso:country":"US",
    "sg:address":"1307 Daphne Ave",
    "sg:city":"Daphne",
    "sg:classifiers":[
        {
            "category":"Health Services",
            "subcategory":"Nursing And Care Facility",
            "type":"Services"
        },
        {
            "category":"Social Services",
            "subcategory":"Adult Care",
            "type":"Services"
        }
    ],
    "sg:phone":"+1 251 625 0802",
    "sg:postcode":"36526",
    "sg:province":"AL",
    "sg:tags":[
        "home",
        "intermediate",
        "residential"
    ],
    "wof:name":"Gardens Of Daphne",
    "wof:placetype":"venue"
},
  "geometry": {"coordinates":[-87.888716,30.603876],"type":"Point"}
}