{
  "type": "Feature",
  "properties": {
    "iso:country":"US",
    "sg:address":"1737 Montgomery Hwy",
    "sg:city":"Dothan",
    "sg:classifiers":[
        {
            "category":"Professional",
            "subcategory":"Accounting & Tax Preparation",
            "type":"Services"
        }
    ],
    "sg:phone":"+1 334 699 4000",
    "sg:postcode":"36303",
    "sg:province":"AL",
    "sg:tags":[
        "return",
        "filing"
    ],
    "wof:name":"Express Tax",
    "wof:placetype":"venue"
},
  "geometry": {"coordinates":[-85.408521,31.238984],"type":"Point"}
}