{
  "type": "Feature",
  "properties": {
    "iso:country":"US",
    "sg:address":"4009 Cogswell Ave",
    "sg:city":"Pell City",
    "sg:classifiers":[
        {
            "category":"Freight",
            "type":"Transportation"
        }
    ],
    "sg:phone":"+1 205 338 6253",
    "sg:postcode":"35125",
    "sg:province":"AL",
    "sg:tags":[
        "commercial",
        "storage",
        "general"
    ],
    "wof:name":"Hand's Mini Storage",
    "wof:placetype":"venue"
},
  "geometry": {"coordinates":[-86.261415,33.592784],"type":"Point"}
}