{
  "type": "Feature",
  "properties": {
    "addr:full":"3670 Galleria Cir Birmingham AL 35244",
    "addr:housenumber":"3670",
    "addr:postcode":"35244",
    "addr:street":"Galleria Cir",
    "iso:country":"US",
    "sg:address":"3670 Galleria Cir",
    "sg:city":"Birmingham",
    "sg:phone":"+1 205 988 8141",
    "sg:postcode":"35244",
    "sg:province":"AL",
    "sg:website":"http://www.homedepot.com",
    "wof:name":"The Home Depot",
    "wof:placetype":"venue"
},
  "geometry": {"coordinates":[-86.811059,33.378284],"type":"Point"}
}