{
  "type": "Feature",
  "properties": {
    "iso:country":"US",
    "sg:address":"4300 Alatex Rd",
    "sg:city":"Montgomery",
    "sg:classifiers":[
        {
            "category":"Shopping",
            "subcategory":"Discount & Variety Stores",
            "type":"Retail Goods"
        }
    ],
    "sg:phone":"+1 334 284 1166",
    "sg:postcode":"36108",
    "sg:province":"AL",
    "sg:tags":[
        "merchandise",
        "general"
    ],
    "wof:name":"Piknik Products Co Warehouse",
    "wof:placetype":"venue"
},
  "geometry": {"coordinates":[-86.406082,32.312636],"type":"Point"}
}