{
  "type": "Feature",
  "properties": {
    "iso:country":"US",
    "sg:address":"6752 US Hwy 280",
    "sg:city":"Alexander City",
    "sg:classifiers":[
        {
            "category":"Autos & Motor Vehicles",
            "subcategory":"Recreational Vehicle Sales",
            "type":"Retail Goods"
        }
    ],
    "sg:phone":"+1 256 234 0806",
    "sg:postcode":"35010",
    "sg:province":"AL",
    "sg:tags":[
        "camper",
        "pick"
    ],
    "wof:name":"A Number 1 Camper Sales",
    "wof:placetype":"venue"
},
  "geometry": {"coordinates":[-85.908402,32.906464],"type":"Point"}
}