{
  "type": "Feature",
  "properties": {
    "addr:full":"175 1st Ave NW Vernon AL 35555",
    "addr:housenumber":"175",
    "addr:postcode":"35555",
    "addr:street":"1St Ave Nw",
    "iso:country":"US",
    "sg:address":"175 1st Ave NW",
    "sg:city":"Vernon",
    "sg:classifiers":[
        {
            "category":"Building & Trades",
            "subcategory":"Plumbing",
            "type":"Services"
        }
    ],
    "sg:phone":"+1 205 695 7072",
    "sg:postcode":"35555",
    "sg:province":"AL",
    "sg:tags":[
        "heat",
        "pump"
    ],
    "wof:name":"Lamar Heating & Cooling Svc",
    "wof:placetype":"venue"
},
  "geometry": {"coordinates":[-88.109028,33.757827],"type":"Point"}
}