{
  "type": "Feature",
  "properties": {
    "iso:country":"US",
    "sg:address":"571 Co Rd 1859",
    "sg:city":"Arab",
    "sg:classifiers":[
        {
            "category":"Building & Trades",
            "subcategory":"Construction",
            "type":"Services"
        }
    ],
    "sg:phone":"+1 256 586 5948",
    "sg:postcode":"35016",
    "sg:province":"AL",
    "sg:tags":[
        "drainage",
        "contractor"
    ],
    "wof:name":"Brindlee Mountain Rooter",
    "wof:placetype":"venue"
},
  "geometry": {"coordinates":[-86.477413,34.271111],"type":"Point"}
}