{
  "type": "Feature",
  "properties": {
    "addr:full":"14710 Co Rd 87 Elberta AL 36530",
    "addr:housenumber":"14710;87",
    "addr:postcode":"36530",
    "addr:street":"Co Rd",
    "iso:country":"US",
    "sg:address":"14710 Co Rd 87",
    "sg:city":"Elberta",
    "sg:classifiers":[
        {
            "category":"Wholesale",
            "subcategory":"Farm Supplies",
            "type":"Manufacturing & Wholesale Goods"
        }
    ],
    "sg:phone":"+1 251 986 5478",
    "sg:postcode":"36530",
    "sg:province":"AL",
    "wof:name":"Gulf Kist Seed",
    "wof:placetype":"venue"
},
  "geometry": {"coordinates":[-87.581345,30.439228],"type":"Point"}
}