{
  "type": "Feature",
  "properties": {
    "addr:full":"254 6th Ave Ashville AL 35953",
    "addr:housenumber":"254",
    "addr:postcode":"35953",
    "addr:street":"6Th Ave",
    "iso:country":"US",
    "sg:address":"254 6th Ave",
    "sg:city":"Ashville",
    "sg:classifiers":[
        {
            "category":"Wholesale",
            "subcategory":"Construction Materials",
            "type":"Manufacturing & Wholesale Goods"
        }
    ],
    "sg:phone":"+1 205 594 4451",
    "sg:postcode":"35953",
    "sg:province":"AL",
    "sg:tags":[
        "timberland",
        "company",
        "timber"
    ],
    "wof:name":"Covered Bridge Timber Inc",
    "wof:placetype":"venue"
},
  "geometry": {"coordinates":[-86.251205,33.836429],"type":"Point"}
}