{
  "type": "Feature",
  "properties": {
    "addr:full":"2315 University Blvd Tuscaloosa AL 35401",
    "addr:housenumber":"2315",
    "addr:postcode":"35401",
    "addr:street":"University Blvd",
    "iso:country":"US",
    "sg:address":"2315 University Blvd",
    "sg:city":"Tuscaloosa",
    "sg:classifiers":[
        {
            "category":"Shopping",
            "type":"Retail Goods"
        }
    ],
    "sg:phone":"+1 205 464 0053",
    "sg:postcode":"35401",
    "sg:province":"AL",
    "sg:tags":[
        "art",
        "gallery",
        "dealer"
    ],
    "wof:name":"Harrison Galleries LLC",
    "wof:placetype":"venue"
},
  "geometry": {"coordinates":[-87.56704999999999,33.210107],"type":"Point"}
}