{
  "type": "Feature",
  "properties": {
    "iso:country":"US",
    "sg:address":"2075 Co Rd 703",
    "sg:city":"Cullman",
    "sg:classifiers":[
        {
            "category":"Building & Trades",
            "subcategory":"Construction",
            "type":"Services"
        }
    ],
    "sg:phone":"+1 256 739 3000",
    "sg:postcode":"35055",
    "sg:province":"AL",
    "sg:tags":[
        "general",
        "contractor"
    ],
    "wof:name":"Mitch Brock Construction",
    "wof:placetype":"venue"
},
  "geometry": {"coordinates":[-86.784401,34.155795],"type":"Point"}
}