{
  "type": "Feature",
  "properties": {
    "iso:country":"US",
    "sg:address":"8650 Minnie Brown Rd",
    "sg:city":"Montgomery",
    "sg:classifiers":[
        {
            "category":"Building & Trades",
            "subcategory":"Construction",
            "type":"Services"
        }
    ],
    "sg:phone":"+1 334 215 4463",
    "sg:postcode":"36117",
    "sg:province":"AL",
    "sg:tags":[
        "contractor"
    ],
    "wof:name":"Cahaba Disaster Recovery",
    "wof:placetype":"venue"
},
  "geometry": {"coordinates":[-86.139663,32.361704],"type":"Point"}
}