{
  "type": "Feature",
  "properties": {
    "iso:country":"US",
    "sg:address":"171 Cleage Dr",
    "sg:city":"Birmingham",
    "sg:classifiers":[
        {
            "category":"Manufacturing",
            "subcategory":"Metals",
            "type":"Manufacturing & Wholesale Goods"
        }
    ],
    "sg:phone":"+1 205 956 5440",
    "sg:postcode":"35217",
    "sg:province":"AL",
    "sg:tags":[
        "tubing"
    ],
    "wof:name":"American Tube Mfg",
    "wof:placetype":"venue"
},
  "geometry": {"coordinates":[-86.73985,33.62688],"type":"Point"}
}