{
  "type": "Feature",
  "properties": {
    "addr:full":"214 Oak St NE Decatur AL 35601",
    "addr:housenumber":"214",
    "addr:postcode":"35601",
    "addr:street":"Oak St Ne",
    "iso:country":"US",
    "sg:address":"214 Oak St NE",
    "sg:city":"Decatur",
    "sg:classifiers":[
        {
            "category":"Government",
            "subcategory":"Police Station",
            "type":"Public Place"
        }
    ],
    "sg:phone":"+1 256 351 7867",
    "sg:postcode":"35601",
    "sg:province":"AL",
    "sg:tags":[
        "sheriff"
    ],
    "wof:name":"Sheriff Drug Unit",
    "wof:placetype":"venue"
},
  "geometry": {"coordinates":[-86.98622,34.608173],"type":"Point"}
}