{
  "type": "Feature",
  "properties": {
    "addr:full":"19204 Old Hwy 25 Columbiana AL 35051",
    "addr:housenumber":"19204",
    "addr:postcode":"35051",
    "addr:street":"Old Hwy 25",
    "iso:country":"US",
    "sg:address":"19204 Old Hwy 25",
    "sg:city":"Columbiana",
    "sg:classifiers":[
        {
            "category":"Retail",
            "subcategory":"Repair Shop",
            "type":"Services"
        }
    ],
    "sg:phone":"+1 205 669 0544",
    "sg:postcode":"35051",
    "sg:province":"AL",
    "sg:tags":[
        "refrigerator",
        "freezer"
    ],
    "wof:name":"Apperson Refrigeration Svc",
    "wof:placetype":"venue"
},
  "geometry": {"coordinates":[-86.629237,33.16574],"type":"Point"}
}