{
  "type": "Feature",
  "properties": {
    "iso:country":"US",
    "sg:address":"4198 Montgomery Hwy",
    "sg:city":"Dothan",
    "sg:classifiers":[
        {
            "category":"Organizations",
            "subcategory":"Religious Organization",
            "type":"Services"
        }
    ],
    "sg:phone":"+1 334 673 4673",
    "sg:postcode":"36303",
    "sg:province":"AL",
    "sg:tags":[
        "church"
    ],
    "wof:name":"Pointe Ministries",
    "wof:placetype":"venue"
},
  "geometry": {"coordinates":[-85.43845,31.262041],"type":"Point"}
}