{
  "type": "Feature",
  "properties": {
    "addr:full":"2044 Obrig Ave Guntersville AL 35976",
    "addr:housenumber":"2044",
    "addr:postcode":"35976",
    "addr:street":"Obrig Ave",
    "iso:country":"US",
    "sg:address":"2044 Obrig Ave",
    "sg:city":"Guntersville",
    "sg:classifiers":[
        {
            "category":"Shopping",
            "type":"Retail Goods"
        }
    ],
    "sg:phone":"+1 256 582 0606",
    "sg:postcode":"35976",
    "sg:province":"AL",
    "sg:tags":[
        "trophy",
        "medal",
        "award"
    ],
    "wof:name":"Top Notch Trophies",
    "wof:placetype":"venue"
},
  "geometry": {"coordinates":[-86.313714,34.338782],"type":"Point"}
}