{
  "type": "Feature",
  "properties": {
    "addr:full":"2000 16th St N Birmingham AL 35204",
    "addr:housenumber":"2000",
    "addr:postcode":"35204",
    "addr:street":"16Th St N",
    "iso:country":"US",
    "sg:address":"2000 16th St N",
    "sg:city":"Birmingham",
    "sg:classifiers":[
        {
            "category":"Autos & Motor Vehicles",
            "subcategory":"Recreational Vehicle Sales",
            "type":"Retail Goods"
        }
    ],
    "sg:phone":"+1 205 328 7405",
    "sg:postcode":"35204",
    "sg:province":"AL",
    "sg:tags":[
        "canopy",
        "shell",
        "truck",
        "cap"
    ],
    "wof:name":"Kimerling Truck Parts & Eqpt",
    "wof:placetype":"venue"
},
  "geometry": {"coordinates":[-86.828126,33.537373],"type":"Point"}
}