{
  "type": "Feature",
  "properties": {
    "iso:country":"US",
    "sg:address":"401 Woodward Ave",
    "sg:city":"Muscle Shoals",
    "sg:classifiers":[
        {
            "category":"Home & Garden",
            "subcategory":"Garden Supply",
            "type":"Retail Goods"
        }
    ],
    "sg:phone":"+1 256 381 9612",
    "sg:postcode":"35661",
    "sg:province":"AL",
    "sg:tags":[
        "nurseryman",
        "center"
    ],
    "wof:name":"Porter Garden Center",
    "wof:placetype":"venue"
},
  "geometry": {"coordinates":[-87.667574,34.756009],"type":"Point"}
}