{
  "type": "Feature",
  "properties": {
    "addr:full":"2501 Briarwood Ave SW Fort Payne AL 35967",
    "addr:housenumber":"2501",
    "addr:postcode":"35967",
    "addr:street":"Briarwood Ave Sw",
    "iso:country":"US",
    "sg:address":"2501 Briarwood Ave SW",
    "sg:city":"Fort Payne",
    "sg:classifiers":[
        {
            "category":"Real Estate",
            "subcategory":"Real Estate Operator",
            "type":"Services"
        }
    ],
    "sg:phone":"+1 256 845 2128",
    "sg:postcode":"35967",
    "sg:province":"AL",
    "sg:tags":[
        "apartment"
    ],
    "wof:name":"Briarwood Apartments",
    "wof:placetype":"venue"
},
  "geometry": {"coordinates":[-85.76517800000001,34.421818],"type":"Point"}
}