{
  "type": "Feature",
  "properties": {
    "iso:country":"US",
    "sg:address":"115 Johnston St SE",
    "sg:city":"Decatur",
    "sg:classifiers":[
        {
            "category":"Professional",
            "subcategory":"Lawyer & Legal Services",
            "type":"Services"
        }
    ],
    "sg:phone":"+1 256 353 6824",
    "sg:postcode":"35601",
    "sg:province":"AL",
    "sg:tags":[
        "attorney"
    ],
    "wof:name":"Coleman & Sedlak",
    "wof:placetype":"venue"
},
  "geometry": {"coordinates":[-86.985254,34.602809],"type":"Point"}
}