{
  "type": "Feature",
  "properties": {
    "iso:country":"US",
    "sg:address":"20270 US Hwy 43",
    "sg:city":"Mt Vernon",
    "sg:classifiers":[
        {
            "category":"Food & Beverages",
            "subcategory":"Groceries & Convenience Stores",
            "type":"Retail Goods"
        }
    ],
    "sg:phone":"+1 251 829 9076",
    "sg:postcode":"36560",
    "sg:province":"AL",
    "wof:name":"O C's Quick Stop",
    "wof:placetype":"venue"
},
  "geometry": {"coordinates":[-88.00947499999999,31.115801],"type":"Point"}
}