{
  "type": "Feature",
  "properties": {
    "iso:country":"US",
    "sg:address":"421 E Laurel St",
    "sg:city":"Scottsboro",
    "sg:classifiers":[
        {
            "category":"Personal",
            "subcategory":"Beauty Salon",
            "type":"Services"
        }
    ],
    "sg:phone":"+1 256 574 4247",
    "sg:postcode":"35768",
    "sg:province":"AL",
    "sg:tags":[
        "shop"
    ],
    "wof:name":"Rumours",
    "wof:placetype":"venue"
},
  "geometry": {"coordinates":[-86.031038,34.672896],"type":"Point"}
}