{
  "type": "Feature",
  "properties": {
    "iso:country":"US",
    "sg:address":"7801 White Oak Cir",
    "sg:city":"Pinson",
    "sg:classifiers":[
        {
            "category":"Personal",
            "subcategory":"Beauty Salon",
            "type":"Services"
        }
    ],
    "sg:phone":"+1 205 681 4446",
    "sg:postcode":"35126",
    "sg:province":"AL",
    "sg:tags":[
        "shop"
    ],
    "wof:name":"Spring Street Salon",
    "wof:placetype":"venue"
},
  "geometry": {"coordinates":[-86.683474,33.731331],"type":"Point"}
}