{
  "type": "Feature",
  "properties": {
    "addr:full":"694 Commerce St Prattville AL 36066",
    "addr:housenumber":"694",
    "addr:postcode":"36066",
    "addr:street":"Commerce St",
    "iso:country":"US",
    "sg:address":"694 Commerce St",
    "sg:city":"Prattville",
    "sg:classifiers":[
        {
            "category":"Insurance",
            "subcategory":"Insurance Agent",
            "type":"Services"
        }
    ],
    "sg:phone":"+1 334 358 5515",
    "sg:postcode":"36066",
    "sg:province":"AL",
    "wof:name":"Acceptance Insurance Co",
    "wof:placetype":"venue"
},
  "geometry": {"coordinates":[-86.420637,32.45824],"type":"Point"}
}