{
  "type": "Feature",
  "properties": {
    "iso:country":"US",
    "sg:address":"125 Norwood Ct",
    "sg:city":"Florence",
    "sg:classifiers":[
        {
            "category":"Building & Trades",
            "subcategory":"Construction",
            "type":"Services"
        }
    ],
    "sg:phone":"+1 256 767 9096",
    "sg:postcode":"35630",
    "sg:province":"AL",
    "sg:tags":[
        "concrete",
        "contractor"
    ],
    "wof:name":"Williams Custom Concrete",
    "wof:placetype":"venue"
},
  "geometry": {"coordinates":[-87.682658,34.834583],"type":"Point"}
}