{
  "type": "Feature",
  "properties": {
    "addr:full":"800 Elm St Troy AL 36082",
    "addr:housenumber":"800",
    "addr:postcode":"36082",
    "addr:street":"Elm St",
    "iso:country":"US",
    "sg:address":"800 Elm St",
    "sg:city":"Troy",
    "sg:classifiers":[
        {
            "category":"Education",
            "subcategory":"School",
            "type":"Public Place"
        }
    ],
    "sg:phone":"+1 334 566 5770",
    "sg:postcode":"36082",
    "sg:province":"AL",
    "sg:website":"www.troyschools.net",
    "wof:name":"Charles Henderson Middle Schl",
    "wof:placetype":"venue"
},
  "geometry": {"coordinates":[-85.95675300000001,31.807382],"type":"Point"}
}