{
  "type": "Feature",
  "properties": {
    "iso:country":"US",
    "sg:address":"9177 State Rte 155",
    "sg:city":"Montevallo",
    "sg:classifiers":[
        {
            "category":"Food & Beverages",
            "subcategory":"Groceries & Convenience Stores",
            "type":"Retail Goods"
        }
    ],
    "sg:phone":"+1 205 665 0085",
    "sg:postcode":"35115",
    "sg:province":"AL",
    "wof:name":"Hawkins Discount Grocers",
    "wof:placetype":"venue"
},
  "geometry": {"coordinates":[-86.84078,33.088217],"type":"Point"}
}