{
  "type": "Feature",
  "properties": {
    "addr:full":"2920 Lomb Ave Birmingham AL 35208",
    "addr:postcode":"2920;35208",
    "addr:street":"Lomb Ave",
    "iso:country":"US",
    "sg:address":"2920 Lomb Ave",
    "sg:city":"Birmingham",
    "sg:classifiers":[
        {
            "category":"Communications",
            "type":"Services"
        }
    ],
    "sg:phone":"+1 205 780 7600",
    "sg:postcode":"35208",
    "sg:province":"AL",
    "sg:tags":[
        "communication"
    ],
    "wof:name":"Nu Text Communications",
    "wof:placetype":"venue"
},
  "geometry": {"coordinates":[-86.868104,33.500574],"type":"Point"}
}