{
  "type": "Feature",
  "properties": {
    "iso:country":"US",
    "sg:address":"148 Dean Rd",
    "sg:city":"Alexander City",
    "sg:classifiers":[
        {
            "category":"Organizations",
            "subcategory":"Religious Organization",
            "type":"Services"
        }
    ],
    "sg:phone":"+1 256 234 6971",
    "sg:postcode":"35010",
    "sg:province":"AL",
    "wof:name":"River Road Baptist Church",
    "wof:placetype":"venue"
},
  "geometry": {"coordinates":[-85.927222,32.907146],"type":"Point"}
}