{
  "type": "Feature",
  "properties": {
    "iso:country":"US",
    "sg:address":"7995 US Hwy 72 Alt",
    "sg:city":"Madison",
    "sg:classifiers":[
        {
            "category":"Retail",
            "subcategory":"Repair Shop",
            "type":"Services"
        },
        {
            "category":"Wholesale",
            "subcategory":"Electrical",
            "type":"Manufacturing & Wholesale Goods"
        }
    ],
    "sg:phone":"+1 256 430 0333",
    "sg:postcode":"35758",
    "sg:province":"AL",
    "sg:tags":[
        "stove",
        "parts",
        "appliance",
        "range",
        "household"
    ],
    "wof:name":"A-1 Appliance Parts",
    "wof:placetype":"venue"
},
  "geometry": {"coordinates":[-86.717457,34.690199],"type":"Point"}
}