{
  "type": "Feature",
  "properties": {
    "addr:full":"15 Craig Dr Saraland AL 36571",
    "addr:housenumber":"15",
    "addr:postcode":"36571",
    "addr:street":"Craig Dr Saraland",
    "iso:country":"US",
    "sg:address":"15 Craig Dr",
    "sg:city":"Saraland",
    "sg:classifiers":[
        {
            "category":"Organizations",
            "subcategory":"Religious Organization",
            "type":"Services"
        }
    ],
    "sg:phone":"+1 251 679 6675",
    "sg:postcode":"36571",
    "sg:province":"AL",
    "wof:name":"Corporation of President of Th",
    "wof:placetype":"venue"
},
  "geometry": {"coordinates":[-88.072727,30.808049],"type":"Point"}
}