{
  "type": "Feature",
  "properties": {
    "iso:country":"US",
    "sg:address":"1004 S Main Ave",
    "sg:city":"Demopolis",
    "sg:classifiers":[
        {
            "category":"Freight",
            "type":"Transportation"
        }
    ],
    "sg:phone":"+1 334 289 2031",
    "sg:postcode":"36732",
    "sg:province":"AL",
    "wof:name":"Compton Ventures Inc",
    "wof:placetype":"venue"
},
  "geometry": {"coordinates":[-87.8391,32.506397],"type":"Point"}
}