{
  "type": "Feature",
  "properties": {
    "iso:country":"US",
    "sg:address":"1430 44th Ave SW",
    "sg:city":"Lanett",
    "sg:classifiers":[
        {
            "category":"Retail",
            "subcategory":"Auto Repair",
            "type":"Services"
        }
    ],
    "sg:phone":"+1 334 576 6984",
    "sg:postcode":"36863",
    "sg:province":"AL",
    "sg:tags":[
        "carburetor",
        "general"
    ],
    "wof:name":"Shealey Carburetor",
    "wof:placetype":"venue"
},
  "geometry": {"coordinates":[-85.236846,32.853515],"type":"Point"}
}