{
  "type": "Feature",
  "properties": {
    "iso:country":"US",
    "sg:address":"402 Celtic Dr",
    "sg:city":"Madison",
    "sg:classifiers":[
        {
            "category":"Retail",
            "subcategory":"Repair Shop",
            "type":"Services"
        }
    ],
    "sg:phone":"+1 256 464 3288",
    "sg:postcode":"35758",
    "sg:province":"AL",
    "sg:tags":[
        "related"
    ],
    "wof:name":"Cutting Edge Repairs",
    "wof:placetype":"venue"
},
  "geometry": {"coordinates":[-86.744958,34.682083],"type":"Point"}
}