{
  "type": "Feature",
  "properties": {
    "iso:country":"US",
    "sg:address":"213 Greene St NE",
    "sg:city":"Huntsville",
    "sg:classifiers":[
        {
            "category":"Professional",
            "subcategory":"Lawyer & Legal Services",
            "type":"Services"
        }
    ],
    "sg:phone":"+1 256 536 0095",
    "sg:postcode":"35801",
    "sg:province":"AL",
    "sg:tags":[
        "attorney",
        "law"
    ],
    "sg:website":"www.feesburgess.com",
    "wof:name":"Fees & Burgess PC",
    "wof:placetype":"venue"
},
  "geometry": {"coordinates":[-86.58610899999999,34.734218],"type":"Point"}
}