{
  "type": "Feature",
  "properties": {
    "iso:country":"US",
    "sg:address":"208 Crescent Dr",
    "sg:city":"Dothan",
    "sg:classifiers":[
        {
            "category":"Professional",
            "subcategory":"Business Services",
            "type":"Services"
        }
    ],
    "sg:phone":"+1 334 702 4711",
    "sg:postcode":"36303",
    "sg:province":"AL",
    "sg:tags":[
        "paralegal"
    ],
    "wof:name":"R Rogers & Assoc",
    "wof:placetype":"venue"
},
  "geometry": {"coordinates":[-85.444022,31.233149],"type":"Point"}
}