{
  "type": "Feature",
  "properties": {
    "iso:country":"US",
    "sg:address":"105 Tudor Pl",
    "sg:city":"Madison",
    "sg:classifiers":[
        {
            "category":"Building & Trades",
            "subcategory":"Construction",
            "type":"Services"
        }
    ],
    "sg:phone":"+1 256 890 9181",
    "sg:postcode":"35758",
    "sg:province":"AL",
    "sg:tags":[
        "home",
        "builder"
    ],
    "wof:name":"Cooper Homes Inc",
    "wof:placetype":"venue"
},
  "geometry": {"coordinates":[-86.76225700000001,34.726735],"type":"Point"}
}