{
  "type": "Feature",
  "properties": {
    "addr:full":"225 Virginia Ave Auburn AL 36830",
    "addr:housenumber":"225",
    "addr:postcode":"36830",
    "addr:street":"Virginia Ave",
    "iso:country":"US",
    "sg:address":"225 Virginia Ave",
    "sg:city":"Auburn",
    "sg:classifiers":[
        {
            "category":"Building & Trades",
            "subcategory":"Construction",
            "type":"Services"
        }
    ],
    "sg:phone":"+1 334 319 2489",
    "sg:postcode":"36830",
    "sg:province":"AL",
    "sg:tags":[
        "general",
        "contractor"
    ],
    "wof:name":"HBS Inc",
    "wof:placetype":"venue"
},
  "geometry": {"coordinates":[-85.477187,32.593939],"type":"Point"}
}