{
  "type": "Feature",
  "properties": {
    "iso:country":"US",
    "sg:address":"707 Pinecrest Rd SE",
    "sg:city":"Huntsville",
    "sg:classifiers":[
        {
            "category":"Wholesale",
            "subcategory":"Machinery & Supplies",
            "type":"Manufacturing & Wholesale Goods"
        }
    ],
    "sg:phone":"+1 256 882 0410",
    "sg:postcode":"35802",
    "sg:province":"AL",
    "sg:tags":[
        "equipment",
        "industrial"
    ],
    "wof:name":"Digital Automation Inc",
    "wof:placetype":"venue"
},
  "geometry": {"coordinates":[-86.55379000000001,34.654611],"type":"Point"}
}