{
  "type": "Feature",
  "properties": {
    "addr:full":"1152 Temple Ave N Fayette AL 35555",
    "addr:housenumber":"1152",
    "addr:postcode":"35555",
    "addr:street":"Temple Ave N",
    "iso:country":"US",
    "sg:address":"1152 Temple Ave N",
    "sg:city":"Fayette",
    "sg:classifiers":[
        {
            "category":"Autos & Motor Vehicles",
            "subcategory":"Automobile Sales",
            "type":"Retail Goods"
        }
    ],
    "sg:phone":"+1 205 932 6971",
    "sg:postcode":"35555",
    "sg:province":"AL",
    "sg:tags":[
        "car",
        "dealer"
    ],
    "wof:name":"Canterbury Auto Sales",
    "wof:placetype":"venue"
},
  "geometry": {"coordinates":[-87.828875,33.699516],"type":"Point"}
}