{
  "type": "Feature",
  "properties": {
    "iso:country":"US",
    "sg:address":"21888 Cedar Ln",
    "sg:city":"Silverhill",
    "sg:classifiers":[
        {
            "category":"Building & Trades",
            "subcategory":"Construction",
            "type":"Services"
        }
    ],
    "sg:phone":"+1 251 945 1155",
    "sg:postcode":"36576",
    "sg:province":"AL",
    "sg:tags":[
        "contractor"
    ],
    "wof:name":"Giles Drywall",
    "wof:placetype":"venue"
},
  "geometry": {"coordinates":[-87.781898,30.542678],"type":"Point"}
}