{
  "type": "Feature",
  "properties": {
    "iso:country":"US",
    "sg:address":"12686 Chicago St",
    "sg:city":"Elberta",
    "sg:classifiers":[
        {
            "category":"Building & Trades",
            "subcategory":"Construction",
            "type":"Services"
        }
    ],
    "sg:phone":"+1 251 986 8443",
    "sg:postcode":"36530",
    "sg:province":"AL",
    "sg:tags":[
        "carpentry",
        "nonresidential",
        "contractor"
    ],
    "wof:name":"Dixie Woodworks",
    "wof:placetype":"venue"
},
  "geometry": {"coordinates":[-87.599772,30.409521],"type":"Point"}
}