{
  "type": "Feature",
  "properties": {
    "iso:country":"US",
    "sg:address":"1737 W 3rd St",
    "sg:city":"Montgomery",
    "sg:classifiers":[
        {
            "category":"Shopping",
            "subcategory":"Optical Goods",
            "type":"Retail Goods"
        }
    ],
    "sg:phone":"+1 334 264 6917",
    "sg:postcode":"36106",
    "sg:province":"AL",
    "wof:name":"Cates Optical Svc",
    "wof:placetype":"venue"
},
  "geometry": {"coordinates":[-86.285168,32.363633],"type":"Point"}
}