{
  "type": "Feature",
  "properties": {
    "iso:country":"US",
    "sg:address":"705 Brookland Curv",
    "sg:city":"Montgomery",
    "sg:classifiers":[
        {
            "category":"Shopping",
            "subcategory":"Computers & Home Electronics",
            "type":"Retail Goods"
        }
    ],
    "sg:phone":"+1 334 288 7576",
    "sg:postcode":"36117",
    "sg:province":"AL",
    "sg:tags":[
        "equipment",
        "dealer"
    ],
    "wof:name":"A T Computer & Staffing Svc",
    "wof:placetype":"venue"
},
  "geometry": {"coordinates":[-86.195351,32.406138],"type":"Point"}
}