{
  "type": "Feature",
  "properties": {
    "addr:full":"1925 Gunter Ave Guntersville AL 35976",
    "addr:housenumber":"1925",
    "addr:postcode":"35976",
    "addr:street":"Gunter Ave",
    "iso:country":"US",
    "sg:address":"1925 Gunter Ave",
    "sg:city":"Guntersville",
    "sg:classifiers":[
        {
            "category":"Government",
            "subcategory":"Office",
            "type":"Public Place"
        }
    ],
    "sg:phone":"+1 256 571 4120",
    "sg:postcode":"35976",
    "sg:province":"AL",
    "sg:tags":[
        "county",
        "resource"
    ],
    "wof:name":"Child Support Svc",
    "wof:placetype":"venue"
},
  "geometry": {"coordinates":[-86.31106200000001,34.339396],"type":"Point"}
}