{
  "type": "Feature",
  "properties": {
    "addr:full":"914 Ploof Dr Bessemer AL 35023",
    "addr:housenumber":"914",
    "addr:postcode":"35023",
    "addr:street":"Ploof Dr",
    "iso:country":"US",
    "sg:address":"914 Ploof Dr",
    "sg:city":"Bessemer",
    "sg:classifiers":[
        {
            "category":"Wholesale",
            "subcategory":"Machinery & Supplies",
            "type":"Manufacturing & Wholesale Goods"
        }
    ],
    "sg:phone":"+1 205 491 9969",
    "sg:postcode":"35023",
    "sg:province":"AL",
    "sg:tags":[
        "equipment",
        "mining"
    ],
    "wof:name":"National Mine Service",
    "wof:placetype":"venue"
},
  "geometry": {"coordinates":[-86.97568,33.438636],"type":"Point"}
}