{
  "type": "Feature",
  "properties": {
    "iso:country":"US",
    "sg:address":"454 Dexter Ave",
    "sg:city":"Montgomery",
    "sg:classifiers":[
        {
            "category":"Organizations",
            "subcategory":"Religious Organization",
            "type":"Services"
        }
    ],
    "sg:phone":"+1 334 263 3970",
    "sg:postcode":"36104",
    "sg:province":"AL",
    "sg:website":"www.dexterkingmemorial.org",
    "wof:name":"Dexter Avenue King Memorial",
    "wof:placetype":"venue"
},
  "geometry": {"coordinates":[-86.303083,32.37754],"type":"Point"}
}