{
  "type": "Feature",
  "properties": {
    "addr:full":"3904 Richard Arrington Jr Blvd N Birmingham AL 35234",
    "addr:housenumber":"3904",
    "addr:postcode":"35234",
    "addr:street":"Richard Arrington Jr Blvd N",
    "iso:country":"US",
    "sg:address":"3904 Richard Arrington Jr Blvd N",
    "sg:city":"Birmingham",
    "sg:classifiers":[
        {
            "category":"Manufacturing",
            "subcategory":"Metals",
            "type":"Manufacturing & Wholesale Goods"
        },
        {
            "category":"Building & Trades",
            "subcategory":"Construction",
            "type":"Services"
        },
        {
            "category":"Manufacturing",
            "subcategory":"Building Materials",
            "type":"Manufacturing & Wholesale Goods"
        }
    ],
    "sg:phone":"+1 205 591 5555",
    "sg:postcode":"35234",
    "sg:province":"AL",
    "sg:tags":[
        "sheet",
        "specialty",
        "work",
        "heating",
        "system",
        "fabricator",
        "contractor",
        "air conditioning"
    ],
    "wof:name":"Red Sullivans Conditioned Air Service, Inc",
    "wof:placetype":"venue"
},
  "geometry": {"coordinates":[-86.781837,33.538849],"type":"Point"}
}