{
  "type": "Feature",
  "properties": {
    "iso:country":"US",
    "sg:address":"3410 Co Rd 44",
    "sg:city":"Eldridge",
    "sg:classifiers":[
        {
            "category":"Building & Trades",
            "subcategory":"Cleaning & Sanitation",
            "type":"Services"
        }
    ],
    "sg:phone":"+1 205 487 4498",
    "sg:postcode":"35554",
    "sg:province":"AL",
    "sg:tags":[
        "maintenance"
    ],
    "wof:name":"Stovall Cleaning Service",
    "wof:placetype":"venue"
},
  "geometry": {"coordinates":[-87.661512,33.836456],"type":"Point"}
}