{
  "type": "Feature",
  "properties": {
    "iso:country":"US",
    "sg:address":"400 N 12th St",
    "sg:city":"Gadsden",
    "sg:classifiers":[
        {
            "category":"Food & Beverages",
            "subcategory":"Groceries & Convenience Stores",
            "type":"Retail Goods"
        }
    ],
    "sg:phone":"+1 256 546 6004",
    "sg:postcode":"35901",
    "sg:province":"AL",
    "wof:name":"Texico Foodmart",
    "wof:placetype":"venue"
},
  "geometry": {"coordinates":[-86.022475,34.024184],"type":"Point"}
}