{
  "type": "Feature",
  "properties": {
    "iso:country":"US",
    "sg:address":"9735 State Rte 51",
    "sg:city":"Opelika",
    "sg:classifiers":[
        {
            "category":"Retail",
            "subcategory":"Auto Repair",
            "type":"Services"
        }
    ],
    "sg:phone":"+1 334 745 5550",
    "sg:postcode":"36804",
    "sg:province":"AL",
    "sg:tags":[
        "general"
    ],
    "wof:name":"Stringfellow Auto Service",
    "wof:placetype":"venue"
},
  "geometry": {"coordinates":[-85.382923,32.518054],"type":"Point"}
}