{
  "type": "Feature",
  "properties": {
    "addr:full":"602 Cahaba Valley Cir Pelham AL 35124",
    "addr:housenumber":"602",
    "addr:postcode":"35124",
    "addr:street":"Cahaba Valley Cir",
    "iso:country":"US",
    "sg:address":"602 Cahaba Valley Cir",
    "sg:city":"Pelham",
    "sg:classifiers":[
        {
            "category":"Wholesale",
            "subcategory":"Medical Equipment & Supplies",
            "type":"Manufacturing & Wholesale Goods"
        }
    ],
    "sg:phone":"+1 205 985 8800",
    "sg:postcode":"35124",
    "sg:province":"AL",
    "wof:name":"Pss",
    "wof:placetype":"venue"
},
  "geometry": {"coordinates":[-86.787187,33.341303],"type":"Point"}
}