{
  "type": "Feature",
  "properties": {
    "iso:country":"US",
    "sg:address":"2311 Highland Ave S",
    "sg:city":"Birmingham",
    "sg:classifiers":[
        {
            "category":"Organizations",
            "subcategory":"Professional Association",
            "type":"Services"
        }
    ],
    "sg:phone":"+1 205 930 5122",
    "sg:postcode":"35205",
    "sg:province":"AL",
    "sg:tags":[
        "trade"
    ],
    "wof:name":"American Family Business Inst",
    "wof:placetype":"venue"
},
  "geometry": {"coordinates":[-86.788521,33.502815],"type":"Point"}
}