{
  "type": "Feature",
  "properties": {
    "iso:country":"US",
    "sg:address":"1222 14th Ave S",
    "sg:city":"Birmingham",
    "sg:classifiers":[
        {
            "category":"Personal",
            "type":"Services"
        }
    ],
    "sg:phone":"+1 205 933 0970",
    "sg:postcode":"35205",
    "sg:province":"AL",
    "sg:tags":[
        "control",
        "weight"
    ],
    "wof:name":"Bariatric Weight Loss Clinic",
    "wof:placetype":"venue"
},
  "geometry": {"coordinates":[-86.805873,33.493707],"type":"Point"}
}