{
  "type": "Feature",
  "properties": {
    "iso:country":"US",
    "sg:address":"540 E Broad St",
    "sg:city":"Eufaula",
    "sg:classifiers":[
        {
            "category":"Government",
            "subcategory":"Post Office",
            "type":"Public Place"
        }
    ],
    "sg:phone":"+1 334 687 3550",
    "sg:postcode":"36027",
    "sg:province":"AL",
    "sg:tags":[
        "postal",
        "us"
    ],
    "wof:name":"Eufaula Main Office",
    "wof:placetype":"venue"
},
  "geometry": {"coordinates":[-85.13824099999999,31.893299],"type":"Point"}
}