{
  "type": "Feature",
  "properties": {
    "iso:country":"US",
    "sg:address":"514 Washington Ave",
    "sg:city":"Montgomery",
    "sg:classifiers":[
        {
            "category":"Organizations",
            "subcategory":"Professional Association",
            "type":"Services"
        }
    ],
    "sg:phone":"+1 334 264 7827",
    "sg:postcode":"36104",
    "sg:province":"AL",
    "wof:name":"Alabama Sheriff's Assn",
    "wof:placetype":"venue"
},
  "geometry": {"coordinates":[-86.301351,32.376416],"type":"Point"}
}