{
  "type": "Feature",
  "properties": {
    "addr:full":"2062 Columbiana Rd Birmingham AL 35216",
    "addr:housenumber":"2062",
    "addr:postcode":"35216",
    "addr:street":"Columbiana Rd",
    "iso:country":"US",
    "sg:address":"2062 Columbiana Rd",
    "sg:city":"Birmingham",
    "sg:classifiers":[
        {
            "category":"Professional",
            "subcategory":"Lawyer & Legal Services",
            "type":"Services"
        }
    ],
    "sg:phone":"+1 205 824 7767",
    "sg:postcode":"35216",
    "sg:province":"AL",
    "wof:name":"Firm McCallum Law",
    "wof:placetype":"venue"
},
  "geometry": {"coordinates":[-86.80879899999999,33.437444],"type":"Point"}
}