{
  "type": "Feature",
  "properties": {
    "iso:country":"US",
    "sg:address":"417 Mallon St",
    "sg:city":"Dothan",
    "sg:classifiers":[
        {
            "category":"Education",
            "subcategory":"Library",
            "type":"Public Place"
        }
    ],
    "sg:phone":"+1 334 793 5876",
    "sg:postcode":"36303",
    "sg:province":"AL",
    "wof:name":"Dollie Robinson Library",
    "wof:placetype":"venue"
},
  "geometry": {"coordinates":[-85.38594500000001,31.236626],"type":"Point"}
}