{
  "type": "Feature",
  "properties": {
    "iso:country":"US",
    "sg:address":"806 Brookside Dr",
    "sg:city":"Opp",
    "sg:classifiers":[
        {
            "category":"Wholesale",
            "subcategory":"Computers",
            "type":"Manufacturing & Wholesale Goods"
        }
    ],
    "sg:phone":"+1 334 493 0516",
    "sg:postcode":"36467",
    "sg:province":"AL",
    "wof:name":"Charles Matheny Co",
    "wof:placetype":"venue"
},
  "geometry": {"coordinates":[-86.25136999999999,31.294693],"type":"Point"}
}