{
  "type": "Feature",
  "properties": {
    "iso:country":"US",
    "sg:address":"721 McKenzie St",
    "sg:city":"Foley",
    "sg:classifiers":[
        {
            "category":"Food & Beverages",
            "subcategory":"Bakery",
            "type":"Retail Goods"
        }
    ],
    "sg:phone":"+1 251 943 6025",
    "sg:postcode":"36535",
    "sg:province":"AL",
    "wof:name":"Earth Grains Inc",
    "wof:placetype":"venue"
},
  "geometry": {"coordinates":[-87.68382800000001,30.412731],"type":"Point"}
}