{
  "type": "Feature",
  "properties": {
    "iso:country":"US",
    "sg:address":"20929 US Hwy 43",
    "sg:city":"Northport",
    "sg:classifiers":[
        {
            "category":"Professional",
            "type":"Services"
        }
    ],
    "sg:phone":"+1 205 333 0675",
    "sg:postcode":"35475",
    "sg:province":"AL",
    "wof:name":"Davis & Son",
    "wof:placetype":"venue"
},
  "geometry": {"coordinates":[-87.648802,33.519924],"type":"Point"}
}