{
  "type": "Feature",
  "properties": {
    "addr:full":"14296 Bone Camp Rd Coker AL 35452",
    "addr:housenumber":"14296",
    "addr:postcode":"35452",
    "addr:street":"Bone Camp Rd",
    "iso:country":"US",
    "sg:address":"14296 Bone Camp Rd",
    "sg:city":"Coker",
    "sg:classifiers":[
        {
            "category":"Building & Trades",
            "subcategory":"Construction",
            "type":"Services"
        }
    ],
    "sg:phone":"+1 205 339 7849",
    "sg:postcode":"35452",
    "sg:province":"AL",
    "sg:tags":[
        "excavating",
        "contractor"
    ],
    "wof:name":"Black Warrior Excavating Inc",
    "wof:placetype":"venue"
},
  "geometry": {"coordinates":[-87.667067,33.37151],"type":"Point"}
}