{
  "type": "Feature",
  "properties": {
    "iso:country":"US",
    "sg:address":"6200 Bell Rd Ct",
    "sg:city":"Montgomery",
    "sg:classifiers":[
        {
            "category":"Professional",
            "type":"Services"
        }
    ],
    "sg:phone":"+1 334 277 3141",
    "sg:postcode":"36117",
    "sg:province":"AL",
    "wof:name":"Gnac Services",
    "wof:placetype":"venue"
},
  "geometry": {"coordinates":[-86.188279,32.376601],"type":"Point"}
}