{
  "type": "Feature",
  "properties": {
    "addr:full":"1002 Hoke Ave Dolomite AL 35061",
    "addr:housenumber":"1002",
    "addr:postcode":"35061",
    "addr:street":"Hoke Ave",
    "iso:country":"US",
    "sg:address":"1002 Hoke Ave",
    "sg:city":"Dolomite",
    "sg:classifiers":[
        {
            "category":"Building & Trades",
            "subcategory":"Equipment Rental",
            "type":"Services"
        }
    ],
    "sg:phone":"+1 205 744 9170",
    "sg:postcode":"35061",
    "sg:province":"AL",
    "wof:name":"Safety-Kleen",
    "wof:placetype":"venue"
},
  "geometry": {"coordinates":[-86.958006,33.4601],"type":"Point"}
}