{
  "type": "Feature",
  "properties": {
    "iso:country":"US",
    "sg:address":"206 Dauphin St",
    "sg:city":"Enterprise",
    "sg:classifiers":[
        {
            "category":"Building & Trades",
            "subcategory":"Construction",
            "type":"Services"
        }
    ],
    "sg:phone":"+1 334 393 8242",
    "sg:postcode":"36330",
    "sg:province":"AL",
    "sg:tags":[
        "nonresidential"
    ],
    "wof:name":"Jpd Enterprises Inc",
    "wof:placetype":"venue"
},
  "geometry": {"coordinates":[-85.859009,31.328923],"type":"Point"}
}