{
  "type": "Feature",
  "properties": {
    "iso:country":"US",
    "sg:address":"2705 University Dr NW",
    "sg:city":"Huntsville",
    "sg:classifiers":[
        {
            "category":"Building & Trades",
            "subcategory":"Equipment Rental",
            "type":"Services"
        }
    ],
    "sg:phone":"+1 256 534 3434",
    "sg:postcode":"35816",
    "sg:province":"AL",
    "wof:name":"Rent-A-Center",
    "wof:placetype":"venue"
},
  "geometry": {"coordinates":[-86.608456,34.736516],"type":"Point"}
}