{
  "type": "Feature",
  "properties": {
    "addr:full":"1 Castle Down Dr Huntsville AL 35802",
    "addr:housenumber":"1",
    "addr:postcode":"35802",
    "addr:street":"Castle Down Dr",
    "iso:country":"US",
    "sg:address":"1 Castle Down Dr",
    "sg:city":"Huntsville",
    "sg:classifiers":[
        {
            "category":"Social Services",
            "subcategory":"Adult Care",
            "type":"Services"
        }
    ],
    "sg:phone":"+1 256 650 5700",
    "sg:postcode":"35802",
    "sg:province":"AL",
    "sg:tags":[
        "residential",
        "skilled",
        "nursing",
        "facility"
    ],
    "wof:name":"Carlton Cove Inc",
    "wof:placetype":"venue"
},
  "geometry": {"coordinates":[-86.515041,34.669891],"type":"Point"}
}