{
  "type": "Feature",
  "properties": {
    "addr:full":"5332 Atlanta Hwy Montgomery AL 36109",
    "addr:housenumber":"5332",
    "addr:postcode":"36109",
    "addr:street":"Atlanta Hwy",
    "iso:country":"US",
    "sg:address":"5332 Atlanta Hwy",
    "sg:city":"Montgomery",
    "sg:classifiers":[
        {
            "category":"Personal",
            "subcategory":"Beauty Salon",
            "type":"Services"
        }
    ],
    "sg:phone":"+1 334 279 6370",
    "sg:postcode":"36109",
    "sg:province":"AL",
    "wof:name":"U S Haircutters",
    "wof:placetype":"venue"
},
  "geometry": {"coordinates":[-86.21811700000001,32.381696],"type":"Point"}
}