{
  "type": "Feature",
  "properties": {
    "iso:country":"US",
    "sg:address":"100 Co Rd 87",
    "sg:city":"Calera",
    "sg:classifiers":[
        {
            "category":"Restaurant",
            "type":"Food & Drink"
        }
    ],
    "sg:phone":"+1 205 621 6887",
    "sg:postcode":"35040",
    "sg:province":"AL",
    "sg:tags":[
        "eating"
    ],
    "wof:name":"Bob Sykes Bbq",
    "wof:placetype":"venue"
},
  "geometry": {"coordinates":[-86.77669,33.167408],"type":"Point"}
}