{
  "type": "Feature",
  "properties": {
    "iso:country":"US",
    "sg:address":"126 Corporate Way",
    "sg:city":"Pelham",
    "sg:classifiers":[
        {
            "category":"Wholesale",
            "subcategory":"Construction Materials",
            "type":"Manufacturing & Wholesale Goods"
        }
    ],
    "sg:phone":"+1 205 664 1664",
    "sg:postcode":"35124",
    "sg:province":"AL",
    "wof:name":"Clopay Building Products Co",
    "wof:placetype":"venue"
},
  "geometry": {"coordinates":[-86.80298000000001,33.313618],"type":"Point"}
}