{
  "type": "Feature",
  "properties": {
    "iso:country":"US",
    "sg:address":"201 Magnolia St",
    "sg:city":"Valley",
    "sg:classifiers":[
        {
            "category":"Professional",
            "subcategory":"Computer Services",
            "type":"Services"
        }
    ],
    "sg:phone":"+1 334 756 4609",
    "sg:postcode":"36854",
    "sg:province":"AL",
    "sg:tags":[
        "programing",
        "custom"
    ],
    "wof:name":"Duncan Services",
    "wof:placetype":"venue"
},
  "geometry": {"coordinates":[-85.191553,32.793962],"type":"Point"}
}