{
  "type": "Feature",
  "properties": {
    "iso:country":"US",
    "sg:address":"4102 Cloverdale Dr NW",
    "sg:city":"Huntsville",
    "sg:classifiers":[
        {
            "category":"Building & Trades",
            "subcategory":"Pest Control",
            "type":"Services"
        }
    ],
    "sg:phone":"+1 256 430 4313",
    "sg:postcode":"35805",
    "sg:province":"AL",
    "wof:name":"Rocket City Pest Control",
    "wof:placetype":"venue"
},
  "geometry": {"coordinates":[-86.630214,34.722262],"type":"Point"}
}