{
  "type": "Feature",
  "properties": {
    "iso:country":"US",
    "sg:address":"1957 Cedar Bend Rd N",
    "sg:city":"Gadsden",
    "sg:classifiers":[
        {
            "category":"Social Services",
            "subcategory":"Child Care",
            "type":"Services"
        }
    ],
    "sg:phone":"+1 256 442 6043",
    "sg:postcode":"35907",
    "sg:province":"AL",
    "sg:tags":[
        "kindergarten",
        "academic",
        "school",
        "day"
    ],
    "wof:name":"Southside Day School Inc",
    "wof:placetype":"venue"
},
  "geometry": {"coordinates":[-86.03954,33.920308],"type":"Point"}
}