{
  "type": "Feature",
  "properties": {
    "addr:full":"225 Main St Attalla AL 35954",
    "addr:housenumber":"225",
    "addr:postcode":"35954",
    "addr:street":"Main St",
    "iso:country":"US",
    "sg:address":"225 Main St",
    "sg:city":"Attalla",
    "sg:classifiers":[
        {
            "category":"Government",
            "subcategory":"Office",
            "type":"Public Place"
        }
    ],
    "sg:phone":"+1 256 538 8968",
    "sg:postcode":"35954",
    "sg:province":"AL",
    "sg:tags":[
        "city"
    ],
    "wof:name":"Town of Ridgeville",
    "wof:placetype":"venue"
},
  "geometry": {"coordinates":[-86.104812,34.054961],"type":"Point"}
}