{
  "type": "Feature",
  "properties": {
    "iso:country":"US",
    "sg:address":"1623 Lee Hwy",
    "sg:city":"Athens",
    "sg:classifiers":[
        {
            "category":"Real Estate",
            "subcategory":"Real Estate Agent",
            "type":"Services"
        }
    ],
    "sg:phone":"+1 256 232 3410",
    "sg:postcode":"35611",
    "sg:province":"AL",
    "sg:tags":[
        "investment"
    ],
    "wof:name":"O'Bakana Investments",
    "wof:placetype":"venue"
},
  "geometry": {"coordinates":[-86.992653,34.790613],"type":"Point"}
}