{
  "type": "Feature",
  "properties": {
    "iso:country":"US",
    "sg:address":"5089 Co Rd 434",
    "sg:city":"Trinity",
    "sg:classifiers":[
        {
            "category":"Autos & Motor Vehicles",
            "subcategory":"Auto Supplies",
            "type":"Retail Goods"
        }
    ],
    "sg:phone":"+1 256 974 3287",
    "sg:postcode":"35673",
    "sg:province":"AL",
    "sg:tags":[
        "automobile",
        "parts"
    ],
    "wof:name":"A & A Jeep Parts & Sales",
    "wof:placetype":"venue"
},
  "geometry": {"coordinates":[-87.15929800000001,34.548922],"type":"Point"}
}