{
  "type": "Feature",
  "properties": {
    "addr:full":"2501 6th St Tuscaloosa AL 35401",
    "addr:housenumber":"2501",
    "addr:postcode":"35401",
    "addr:street":"6Th St",
    "iso:country":"US",
    "sg:address":"2501 6th St",
    "sg:city":"Tuscaloosa",
    "sg:classifiers":[
        {
            "category":"Professional",
            "subcategory":"Research",
            "type":"Services"
        }
    ],
    "sg:phone":"+1 205 391 9900",
    "sg:postcode":"35401",
    "sg:province":"AL",
    "sg:tags":[
        "environmental",
        "ecological"
    ],
    "wof:name":"Patton Geological & Environ",
    "wof:placetype":"venue"
},
  "geometry": {"coordinates":[-87.57062999999999,33.208095],"type":"Point"}
}