{
  "type": "Feature",
  "properties": {
    "iso:country":"US",
    "sg:address":"3228 Lorna Rd",
    "sg:city":"Birmingham",
    "sg:classifiers":[
        {
            "category":"Manufacturing",
            "subcategory":"Tools & Machinery",
            "type":"Manufacturing & Wholesale Goods"
        }
    ],
    "sg:phone":"+1 205 942 7722",
    "sg:postcode":"35216",
    "sg:province":"AL",
    "sg:tags":[
        "physician",
        "surgeon"
    ],
    "wof:name":"ADMEA",
    "wof:placetype":"venue"
},
  "geometry": {"coordinates":[-86.799699,33.395807],"type":"Point"}
}