{
  "type": "Feature",
  "properties": {
    "iso:country":"US",
    "sg:address":"300 Hughes Rd",
    "sg:city":"Madison",
    "sg:classifiers":[
        {
            "category":"Food & Beverages",
            "subcategory":"Dairy",
            "type":"Retail Goods"
        },
        {
            "category":"Restaurant",
            "type":"Food & Drink"
        }
    ],
    "sg:phone":"+1 256 461 1317",
    "sg:postcode":"35758",
    "sg:province":"AL",
    "sg:tags":[
        "product",
        "parlor",
        "ice",
        "cream"
    ],
    "wof:name":"Kaleidoscoops",
    "wof:placetype":"venue"
},
  "geometry": {"coordinates":[-86.74212,34.706555],"type":"Point"}
}