{
  "type": "Feature",
  "properties": {
    "iso:country":"US",
    "sg:address":"1874 Co Rd 74",
    "sg:city":"Florence",
    "sg:classifiers":[
        {
            "category":"Building & Trades",
            "subcategory":"Landscaping Services",
            "type":"Services"
        }
    ],
    "sg:phone":"+1 256 764 2232",
    "sg:postcode":"35633",
    "sg:province":"AL",
    "sg:tags":[
        "tree"
    ],
    "wof:name":"Ace Tree Svc",
    "wof:placetype":"venue"
},
  "geometry": {"coordinates":[-87.86327199999999,34.938458],"type":"Point"}
}