{
  "type": "Feature",
  "properties": {
    "iso:country":"US",
    "sg:address":"1205 19th St N",
    "sg:city":"Birmingham",
    "sg:classifiers":[
        {
            "category":"Professional",
            "subcategory":"Lawyer & Legal Services",
            "type":"Services"
        }
    ],
    "sg:phone":"+1 205 251 2520",
    "sg:postcode":"35234",
    "sg:province":"AL",
    "sg:tags":[
        "attorney",
        "criminal",
        "duo",
        "personal",
        "divorce",
        "drug",
        "charge",
        "injury",
        "dwi",
        "law"
    ],
    "sg:website":"http://www.rdrlaw.net",
    "wof:name":"Rolando Rankin",
    "wof:placetype":"venue"
},
  "geometry": {"coordinates":[-86.815366,33.525932],"type":"Point"}
}