{
  "type": "Feature",
  "properties": {
    "addr:full":"1560 Mount Meigs Rd Montgomery AL 36107",
    "addr:housenumber":"1560",
    "addr:postcode":"36107",
    "addr:street":"Mount Meigs Rd",
    "iso:country":"US",
    "sg:address":"1560 Mount Meigs Rd",
    "sg:city":"Montgomery",
    "sg:classifiers":[
        {
            "category":"Utilities",
            "subcategory":"Telephone",
            "type":"Services"
        }
    ],
    "sg:phone":"+1 334 265 5042",
    "sg:postcode":"36107",
    "sg:province":"AL",
    "sg:tags":[
        "communications"
    ],
    "wof:name":"Alltel Mobile Comm Inc",
    "wof:placetype":"venue"
},
  "geometry": {"coordinates":[-86.286697,32.375006],"type":"Point"}
}