{
  "type": "Feature",
  "properties": {
    "addr:full":"600 Riverview Dr Cropwell AL 35054",
    "addr:housenumber":"600",
    "addr:postcode":"35054",
    "addr:street":"Riverview Dr Cropwell",
    "iso:country":"US",
    "sg:address":"600 Riverview Dr",
    "sg:city":"Cropwell",
    "sg:classifiers":[
        {
            "category":"Organizations",
            "subcategory":"Religious Organization",
            "type":"Services"
        }
    ],
    "sg:phone":"+1 205 525 5885",
    "sg:postcode":"35054",
    "sg:province":"AL",
    "wof:name":"Just Jesus Ministries Inc",
    "wof:placetype":"venue"
},
  "geometry": {"coordinates":[-86.311871,33.490461],"type":"Point"}
}