{
  "type": "Feature",
  "properties": {
    "addr:full":"845 Shelby St Montevallo AL 35115",
    "addr:housenumber":"845",
    "addr:postcode":"35115",
    "addr:street":"Shelby St",
    "iso:country":"US",
    "sg:address":"845 Shelby St",
    "sg:city":"Montevallo",
    "sg:classifiers":[
        {
            "category":"Building & Trades",
            "subcategory":"Plumbing",
            "type":"Services"
        }
    ],
    "sg:phone":"+1 205 665 0690",
    "sg:postcode":"35115",
    "sg:province":"AL",
    "sg:tags":[
        "plumbing",
        "contractor"
    ],
    "wof:name":"Shelnutt Svcs",
    "wof:placetype":"venue"
},
  "geometry": {"coordinates":[-86.865177,33.1009],"type":"Point"}
}