{
  "type": "Feature",
  "properties": {
    "addr:full":"696 Commerce St Prattville AL 36066",
    "addr:housenumber":"696",
    "addr:postcode":"36066",
    "addr:street":"Commerce St",
    "iso:country":"US",
    "sg:address":"696 Commerce St",
    "sg:city":"Prattville",
    "sg:classifiers":[
        {
            "category":"Building & Trades",
            "subcategory":"Construction",
            "type":"Services"
        }
    ],
    "sg:phone":"+1 334 358 9371",
    "sg:postcode":"36066",
    "sg:province":"AL",
    "sg:tags":[
        "steel",
        "fabrication",
        "welding"
    ],
    "wof:name":"Nationwide Steel Inc",
    "wof:placetype":"venue"
},
  "geometry": {"coordinates":[-86.419979,32.458306],"type":"Point"}
}