{
  "type": "Feature",
  "properties": {
    "iso:country":"US",
    "sg:address":"8711 Brook Ln",
    "sg:city":"Fairhope",
    "sg:classifiers":[
        {
            "category":"Professional",
            "subcategory":"Business Services",
            "type":"Services"
        }
    ],
    "sg:phone":"+1 251 928 8088",
    "sg:postcode":"36532",
    "sg:province":"AL",
    "wof:name":"Renaissance Interiors",
    "wof:placetype":"venue"
},
  "geometry": {"coordinates":[-87.874742,30.532245],"type":"Point"}
}