{
  "type": "Feature",
  "properties": {
    "iso:country":"US",
    "sg:address":"102 Micah Way",
    "sg:city":"Scottsboro",
    "sg:classifiers":[
        {
            "category":"Building & Trades",
            "subcategory":"Electrical",
            "type":"Services"
        }
    ],
    "sg:phone":"+1 256 574 4810",
    "sg:postcode":"35769",
    "sg:province":"AL",
    "sg:tags":[
        "electrical",
        "contractor"
    ],
    "wof:name":"Pruetts Contracting",
    "wof:placetype":"venue"
},
  "geometry": {"coordinates":[-86.012477,34.661984],"type":"Point"}
}