{
  "type": "Feature",
  "properties": {
    "iso:country":"US",
    "sg:address":"1620 S Broad St",
    "sg:city":"Mobile",
    "sg:classifiers":[
        {
            "category":"Government",
            "subcategory":"Office",
            "type":"Public Place"
        }
    ],
    "sg:phone":"+1 251 342 4892",
    "sg:postcode":"36605",
    "sg:province":"AL",
    "sg:tags":[
        "federal",
        "security"
    ],
    "wof:name":"Alabama Army National Guard",
    "wof:placetype":"venue"
},
  "geometry": {"coordinates":[-88.061925,30.6521],"type":"Point"}
}