{
  "type": "Feature",
  "properties": {
    "iso:country":"US",
    "sg:address":"162 Carver Ave",
    "sg:city":"Atmore",
    "sg:classifiers":[
        {
            "category":"Bars & Pubs",
            "type":"Food & Drink"
        }
    ],
    "sg:phone":"+1 251 368 4752",
    "sg:postcode":"36502",
    "sg:province":"FL",
    "sg:tags":[
        "drinking"
    ],
    "wof:name":"Flamingo Terrace Lounge",
    "wof:placetype":"venue"
},
  "geometry": {"coordinates":[-87.48244,31.032372],"type":"Point"}
}