{
  "type": "Feature",
  "properties": {
    "addr:full":"13214 Holtville Rd Deatsville AL 36022",
    "addr:housenumber":"13214",
    "addr:postcode":"36022",
    "addr:street":"Holtville Rd",
    "iso:country":"US",
    "sg:address":"13214 Holtville Rd",
    "sg:city":"Deatsville",
    "sg:classifiers":[
        {
            "category":"Organizations",
            "subcategory":"Religious Organization",
            "type":"Services"
        }
    ],
    "sg:phone":"+1 334 569 2482",
    "sg:postcode":"36022",
    "sg:province":"AL",
    "wof:name":"Shoal Creek Baptist Church",
    "wof:placetype":"venue"
},
  "geometry": {"coordinates":[-86.372928,32.648554],"type":"Point"}
}