{
  "type": "Feature",
  "properties": {
    "addr:full":"20644 Yarbrough Rd Athens AL 35613",
    "addr:postcode":"20644;35613",
    "addr:street":"Yarbrough Rd",
    "iso:country":"US",
    "sg:address":"20644 Yarbrough Rd",
    "sg:city":"Athens",
    "sg:classifiers":[
        {
            "category":"Retail",
            "subcategory":"Repair Shop",
            "type":"Services"
        },
        {
            "category":"Building & Trades",
            "subcategory":"Plumbing",
            "type":"Services"
        }
    ],
    "sg:phone":"+1 256 771 7546",
    "sg:postcode":"35613",
    "sg:province":"AL",
    "sg:tags":[
        "septic"
    ],
    "wof:name":"Bailey's Backhoe",
    "wof:placetype":"venue"
},
  "geometry": {"coordinates":[-86.912025,34.857833],"type":"Point"}
}