{
  "type": "Feature",
  "properties": {
    "iso:country":"US",
    "sg:address":"9400 Parkway E",
    "sg:city":"Birmingham",
    "sg:classifiers":[
        {
            "category":"Autos & Motor Vehicles",
            "subcategory":"Fuel & Gas Station",
            "type":"Retail Goods"
        }
    ],
    "sg:phone":"+1 205 833 3518",
    "sg:postcode":"35215",
    "sg:province":"AL",
    "wof:name":"Ron's Red Lane Exxon",
    "wof:placetype":"venue"
},
  "geometry": {"coordinates":[-86.696602,33.5914],"type":"Point"}
}