{
  "type": "Feature",
  "properties": {
    "iso:country":"US",
    "sg:address":"2608 US Hwy 31",
    "sg:city":"Decatur",
    "sg:classifiers":[
        {
            "category":"Shopping",
            "subcategory":"Used Merchandise",
            "type":"Retail Goods"
        }
    ],
    "sg:phone":"+1 256 340 9090",
    "sg:postcode":"35603",
    "sg:province":"AL",
    "wof:name":"Goodwill Store",
    "wof:placetype":"venue"
},
  "geometry": {"coordinates":[-86.973275,34.560876],"type":"Point"}
}