{
  "type": "Feature",
  "properties": {
    "addr:full":"27 Harris Ave Saraland AL 36571",
    "addr:housenumber":"27",
    "addr:postcode":"36571",
    "addr:street":"Harris Ave Saraland",
    "iso:country":"US",
    "sg:address":"27 Harris Ave",
    "sg:city":"Saraland",
    "sg:classifiers":[
        {
            "category":"Home & Garden",
            "subcategory":"Garden Supply",
            "type":"Retail Goods"
        }
    ],
    "sg:phone":"+1 251 675 1494",
    "sg:postcode":"36571",
    "sg:province":"AL",
    "sg:tags":[
        "equipment",
        "lawn",
        "repair"
    ],
    "wof:name":"Saraland Lawn & Garden Center",
    "wof:placetype":"venue"
},
  "geometry": {"coordinates":[-88.073063,30.823079],"type":"Point"}
}