{
  "type": "Feature",
  "properties": {
    "iso:country":"US",
    "sg:address":"2513 State Rte 20",
    "sg:city":"Decatur",
    "sg:classifiers":[
        {
            "category":"Freight",
            "type":"Transportation"
        }
    ],
    "sg:phone":"+1 256 350 1413",
    "sg:postcode":"35601",
    "sg:province":"AL",
    "sg:tags":[
        "long",
        "trucking"
    ],
    "wof:name":"A & R Transport Inc",
    "wof:placetype":"venue"
},
  "geometry": {"coordinates":[-87.034474,34.619333],"type":"Point"}
}