{
  "type": "Feature",
  "properties": {
    "iso:country":"US",
    "sg:address":"6921 Simpson St",
    "sg:city":"Northport",
    "sg:classifiers":[
        {
            "category":"Professional",
            "subcategory":"Advertising",
            "type":"Services"
        }
    ],
    "sg:phone":"+1 205 339 2267",
    "sg:postcode":"35473",
    "sg:province":"AL",
    "sg:tags":[
        "mail"
    ],
    "wof:name":"Bulk Mailing Svc",
    "wof:placetype":"venue"
},
  "geometry": {"coordinates":[-87.628919,33.238367],"type":"Point"}
}