{
  "type": "Feature",
  "properties": {
    "iso:country":"US",
    "sg:address":"5201 Elmore Rd",
    "sg:city":"Elmore",
    "sg:classifiers":[
        {
            "category":"Building & Trades",
            "subcategory":"Landscaping Services",
            "type":"Services"
        }
    ],
    "sg:phone":"+1 334 567 8101",
    "sg:postcode":"36025",
    "sg:province":"AL",
    "sg:tags":[
        "landscape",
        "contractor"
    ],
    "wof:name":"Carter Landscaping Inc",
    "wof:placetype":"venue"
},
  "geometry": {"coordinates":[-86.288502,32.549564],"type":"Point"}
}