{
  "type": "Feature",
  "properties": {
    "iso:country":"US",
    "sg:address":"998 Love Branch Rd",
    "sg:city":"Harvest",
    "sg:classifiers":[
        {
            "category":"Manufacturing",
            "subcategory":"Chemicals & Compounds",
            "type":"Manufacturing & Wholesale Goods"
        }
    ],
    "sg:phone":"+1 256 830 4117",
    "sg:postcode":"35749",
    "sg:province":"AL",
    "sg:tags":[
        "industrial",
        "gas",
        "mfg"
    ],
    "wof:name":"Airgas",
    "wof:placetype":"venue"
},
  "geometry": {"coordinates":[-86.78441599999999,34.854102],"type":"Point"}
}