{
  "type": "Feature",
  "properties": {
    "addr:full":"2664 US Hwy 72 Huntsville AL 35811",
    "addr:housenumber":"2664",
    "addr:postcode":"35811",
    "addr:street":"Us Hwy 72",
    "iso:country":"US",
    "sg:address":"2664 US Hwy 72",
    "sg:city":"Huntsville",
    "sg:classifiers":[
        {
            "category":"Building & Trades",
            "subcategory":"Plumbing",
            "type":"Services"
        }
    ],
    "sg:phone":"+1 256 851 8070",
    "sg:postcode":"35811",
    "sg:province":"AL",
    "sg:tags":[
        "conditioning",
        "air",
        "system",
        "contractor"
    ],
    "wof:name":"Ingram Heating & Air Cond",
    "wof:placetype":"venue"
},
  "geometry": {"coordinates":[-86.492751,34.768342],"type":"Point"}
}