{
  "type": "Feature",
  "properties": {
    "iso:country":"US",
    "sg:address":"2609 Cameron St",
    "sg:city":"Mobile",
    "sg:classifiers":[
        {
            "category":"Utilities",
            "subcategory":"Telephone",
            "type":"Services"
        }
    ],
    "sg:phone":"+1 251 479 1113",
    "sg:postcode":"36607",
    "sg:province":"AL",
    "sg:tags":[
        "communications"
    ],
    "wof:name":"Nationwide Telephone Consultan",
    "wof:placetype":"venue"
},
  "geometry": {"coordinates":[-88.102281,30.690258],"type":"Point"}
}