{
  "type": "Feature",
  "properties": {
    "iso:country":"US",
    "sg:address":"1590 Pelham Rd S",
    "sg:city":"Jacksonville",
    "sg:classifiers":[
        {
            "category":"Insurance",
            "subcategory":"Insurance Agent",
            "type":"Services"
        }
    ],
    "sg:phone":"+1 256 435 2242",
    "sg:postcode":"36265",
    "sg:province":"AL",
    "wof:name":"Calhoun County Insurance Ctr",
    "wof:placetype":"venue"
},
  "geometry": {"coordinates":[-85.760897,33.786252],"type":"Point"}
}