{
  "type": "Feature",
  "properties": {
    "iso:country":"US",
    "sg:address":"500 S Broad St",
    "sg:city":"Mobile",
    "sg:classifiers":[
        {
            "category":"Home & Garden",
            "subcategory":"Furniture",
            "type":"Retail Goods"
        }
    ],
    "sg:phone":"+1 251 433 5954",
    "sg:postcode":"36603",
    "sg:province":"AL",
    "sg:tags":[
        "new"
    ],
    "wof:name":"New Orleans Furniture Co",
    "wof:placetype":"venue"
},
  "geometry": {"coordinates":[-88.05416700000001,30.676933],"type":"Point"}
}