{
  "type": "Feature",
  "properties": {
    "addr:full":"500 2nd Ave S Clanton AL 35045",
    "addr:housenumber":"500",
    "addr:postcode":"35045",
    "addr:street":"2Nd Ave S",
    "iso:country":"US",
    "sg:address":"500 2nd Ave S",
    "sg:city":"Clanton",
    "sg:classifiers":[
        {
            "category":"Professional",
            "subcategory":"Lawyer & Legal Services",
            "type":"Services"
        }
    ],
    "sg:phone":"+1 205 755 2004",
    "sg:postcode":"35045",
    "sg:province":"AL",
    "sg:tags":[
        "attorney"
    ],
    "wof:name":"Jackson & Jackson",
    "wof:placetype":"venue"
},
  "geometry": {"coordinates":[-86.62794100000001,32.838164],"type":"Point"}
}