{
  "type": "Feature",
  "properties": {
    "iso:country":"US",
    "sg:address":"2863 Co Rd 81",
    "sg:city":"Selma",
    "sg:classifiers":[
        {
            "category":"Education",
            "subcategory":"School",
            "type":"Public Place"
        }
    ],
    "sg:phone":"+1 334 872 6417",
    "sg:postcode":"36703",
    "sg:province":"AL",
    "wof:name":"William R Martin Middle School",
    "wof:placetype":"venue"
},
  "geometry": {"coordinates":[-86.981013,32.493454],"type":"Point"}
}