{
  "type": "Feature",
  "properties": {
    "addr:full":"1695 E University Dr Auburn AL 36830",
    "addr:housenumber":"1695",
    "addr:postcode":"36830",
    "addr:street":"E University Dr",
    "iso:country":"US",
    "sg:address":"1695 E University Dr",
    "sg:city":"Auburn",
    "sg:classifiers":[
        {
            "category":"Health Services",
            "subcategory":"Doctor",
            "type":"Services"
        },
        {
            "category":"Personal",
            "subcategory":"Beauty Salon",
            "type":"Services"
        },
        {
            "category":"Personal",
            "subcategory":"Massage",
            "type":"Services"
        },
        {
            "category":"Personal",
            "subcategory":"Skin Care",
            "type":"Services"
        }
    ],
    "sg:phone":"+1 334 826 3060",
    "sg:postcode":"36830",
    "sg:province":"AL",
    "sg:tags":[
        "hair",
        "therapist",
        "replacement"
    ],
    "wof:name":"Fruition Salon & Hair Replacement",
    "wof:placetype":"venue"
},
  "geometry": {"coordinates":[-85.447641,32.612751],"type":"Point"}
}