{
  "type": "Feature",
  "properties": {
    "iso:country":"US",
    "sg:address":"20711 Elkton Rd",
    "sg:city":"Athens",
    "sg:classifiers":[
        {
            "category":"Shopping",
            "subcategory":"Used Merchandise",
            "type":"Retail Goods"
        }
    ],
    "sg:phone":"+1 256 233 3002",
    "sg:postcode":"35614",
    "sg:province":"AL",
    "sg:tags":[
        "shop",
        "consignment"
    ],
    "wof:name":"Magic Moments",
    "wof:placetype":"venue"
},
  "geometry": {"coordinates":[-86.934026,34.854323],"type":"Point"}
}