{
  "type": "Feature",
  "properties": {
    "addr:full":"10641 Thomas Rd Tuscaloosa AL 35405",
    "addr:housenumber":"10641",
    "addr:postcode":"35405",
    "addr:street":"Thomas Rd",
    "iso:country":"US",
    "sg:address":"10641 Thomas Rd",
    "sg:city":"Tuscaloosa",
    "sg:classifiers":[
        {
            "category":"Building & Trades",
            "subcategory":"Construction",
            "type":"Services"
        }
    ],
    "sg:phone":"+1 205 345 8849",
    "sg:postcode":"35405",
    "sg:province":"AL",
    "sg:tags":[
        "home",
        "builder"
    ],
    "wof:name":"Rice Construction Co",
    "wof:placetype":"venue"
},
  "geometry": {"coordinates":[-87.545254,33.080974],"type":"Point"}
}