{
  "type": "Feature",
  "properties": {
    "addr:full":"222 Co Rd 33 Pelham AL 35124",
    "addr:housenumber":"222;33",
    "addr:postcode":"35124",
    "addr:street":"Co Rd",
    "iso:country":"US",
    "sg:address":"222 Co Rd 33",
    "sg:city":"Pelham",
    "sg:classifiers":[
        {
            "category":"Travel",
            "subcategory":"Campground",
            "type":"Entertainment"
        }
    ],
    "sg:phone":"+1 205 664 8832",
    "sg:postcode":"35124",
    "sg:province":"AL",
    "wof:name":"Camp Groun Birmingham South",
    "wof:placetype":"venue"
},
  "geometry": {"coordinates":[-86.80390199999999,33.291719],"type":"Point"}
}