{
  "type": "Feature",
  "properties": {
    "iso:country":"US",
    "sg:address":"105 Beltline Rd",
    "sg:city":"Decatur",
    "sg:classifiers":[
        {
            "category":"Building & Trades",
            "subcategory":"Construction",
            "type":"Services"
        }
    ],
    "sg:phone":"+1 256 350 4123",
    "sg:postcode":"35601",
    "sg:province":"AL",
    "sg:tags":[
        "carpentry",
        "contractor"
    ],
    "wof:name":"Trinity Woodworks",
    "wof:placetype":"venue"
},
  "geometry": {"coordinates":[-87.031468,34.601956],"type":"Point"}
}