{
  "type": "Feature",
  "properties": {
    "iso:country":"US",
    "sg:address":"519 N Lawrence St",
    "sg:city":"Montgomery",
    "sg:classifiers":[
        {
            "category":"Wholesale",
            "subcategory":"Non-durable Goods",
            "type":"Manufacturing & Wholesale Goods"
        }
    ],
    "sg:phone":"+1 334 265 1890",
    "sg:postcode":"36104",
    "sg:province":"AL",
    "wof:name":"Jpw Distributors Inc",
    "wof:placetype":"venue"
},
  "geometry": {"coordinates":[-86.306576,32.384012],"type":"Point"}
}