{
  "type": "Feature",
  "properties": {
    "iso:country":"US",
    "sg:address":"14965 US Hwy 431",
    "sg:city":"Hazel Green",
    "sg:classifiers":[
        {
            "category":"Social Services",
            "subcategory":"Child Care",
            "type":"Services"
        }
    ],
    "sg:phone":"+1 256 828 9198",
    "sg:postcode":"35750",
    "sg:province":"TN",
    "wof:name":"Younger Years Daycare",
    "wof:placetype":"venue"
},
  "geometry": {"coordinates":[-86.570863,34.955549],"type":"Point"}
}