{
  "type": "Feature",
  "properties": {
    "iso:country":"US",
    "sg:address":"22 W Plateau Ave",
    "sg:city":"Satsuma",
    "sg:classifiers":[
        {
            "category":"Building & Trades",
            "subcategory":"Construction",
            "type":"Services"
        }
    ],
    "sg:phone":"+1 251 675 1409",
    "sg:postcode":"36572",
    "sg:province":"AL",
    "wof:name":"Overstreet Contracting Co Inc",
    "wof:placetype":"venue"
},
  "geometry": {"coordinates":[-88.056941,30.856935],"type":"Point"}
}