{
  "type": "Feature",
  "properties": {
    "iso:country":"US",
    "sg:address":"3800 Millbrae Dr",
    "sg:city":"Huntsville",
    "sg:classifiers":[
        {
            "category":"Professional",
            "subcategory":"Management & Consulting",
            "type":"Services"
        }
    ],
    "sg:phone":"+1 256 852 3355",
    "sg:postcode":"35810",
    "sg:province":"AL",
    "sg:tags":[
        "research"
    ],
    "wof:name":"Montgomery Resources",
    "wof:placetype":"venue"
},
  "geometry": {"coordinates":[-86.61333399999999,34.797497],"type":"Point"}
}