{
  "type": "Feature",
  "properties": {
    "iso:country":"US",
    "sg:address":"1050 Co Rd 148",
    "sg:city":"Centre",
    "sg:classifiers":[
        {
            "category":"Building & Trades",
            "subcategory":"Construction",
            "type":"Services"
        }
    ],
    "sg:phone":"+1 256 927 4582",
    "sg:postcode":"35960",
    "sg:province":"AL",
    "sg:tags":[
        "heavy"
    ],
    "wof:name":"Dean Construction",
    "wof:placetype":"venue"
},
  "geometry": {"coordinates":[-85.642771,34.137199],"type":"Point"}
}