{
  "type": "Feature",
  "properties": {
    "addr:full":"251 Cahaba Valley Rd Pelham AL 35124",
    "addr:housenumber":"251",
    "addr:postcode":"35124",
    "addr:street":"Cahaba Valley Rd",
    "iso:country":"US",
    "sg:address":"251 Cahaba Valley Rd",
    "sg:city":"Pelham",
    "sg:classifiers":[
        {
            "category":"Home & Garden",
            "subcategory":"Furniture",
            "type":"Retail Goods"
        }
    ],
    "sg:phone":"+1 205 733 1995",
    "sg:postcode":"35124",
    "sg:province":"AL",
    "wof:name":"Barrow's Fine Furniture",
    "wof:placetype":"venue"
},
  "geometry": {"coordinates":[-86.78919999999999,33.332654],"type":"Point"}
}