{
  "type": "Feature",
  "properties": {
    "iso:country":"US",
    "sg:address":"2200 Government St",
    "sg:city":"Mobile",
    "sg:classifiers":[
        {
            "category":"Professional",
            "subcategory":"Employment Agencies",
            "type":"Services"
        }
    ],
    "sg:phone":"+1 251 652 1391",
    "sg:postcode":"36606",
    "sg:province":"AL",
    "sg:tags":[
        "supply",
        "help",
        "contractor"
    ],
    "wof:name":"Workmaster Employment Service",
    "wof:placetype":"venue"
},
  "geometry": {"coordinates":[-88.092682,30.674383],"type":"Point"}
}