{
  "type": "Feature",
  "properties": {
    "iso:country":"US",
    "sg:address":"8360 US Hwy 31",
    "sg:city":"Calera",
    "sg:classifiers":[
        {
            "category":"Shopping",
            "type":"Retail Goods"
        }
    ],
    "sg:phone":"+1 205 668 3100",
    "sg:postcode":"35040",
    "sg:province":"AL",
    "sg:tags":[
        "pet",
        "shop"
    ],
    "wof:name":"Ed's Pet World",
    "wof:placetype":"venue"
},
  "geometry": {"coordinates":[-86.753197,33.101447],"type":"Point"}
}