{
  "type": "Feature",
  "properties": {
    "iso:country":"US",
    "sg:address":"6779 Twin Beach Rd",
    "sg:city":"Fairhope",
    "sg:classifiers":[
        {
            "category":"Building & Trades",
            "subcategory":"Plumbing",
            "type":"Services"
        }
    ],
    "sg:phone":"+1 251 928 5973",
    "sg:postcode":"36532",
    "sg:province":"AL",
    "sg:tags":[
        "contractor"
    ],
    "wof:name":"Pickett Plumbing",
    "wof:placetype":"venue"
},
  "geometry": {"coordinates":[-87.908735,30.501693],"type":"Point"}
}