{
  "type": "Feature",
  "properties": {
    "addr:full":"2700 Bessemer Rd Birmingham AL 35208",
    "addr:housenumber":"2700",
    "addr:postcode":"35208",
    "addr:street":"Bessemer Rd",
    "iso:country":"US",
    "sg:address":"2700 Bessemer Rd",
    "sg:city":"Birmingham",
    "sg:classifiers":[
        {
            "category":"Professional",
            "type":"Services"
        }
    ],
    "sg:phone":"+1 205 981 7433",
    "sg:postcode":"35208",
    "sg:province":"AL",
    "wof:name":"Doc & Cloochie",
    "wof:placetype":"venue"
},
  "geometry": {"coordinates":[-86.87016800000001,33.501835],"type":"Point"}
}