{
  "type": "Feature",
  "properties": {
    "iso:country":"US",
    "sg:address":"112 Chula Vista Dr",
    "sg:city":"Pell City",
    "sg:classifiers":[
        {
            "category":"Home & Garden",
            "subcategory":"Hardware",
            "type":"Retail Goods"
        }
    ],
    "sg:phone":"+1 205 884 4971",
    "sg:postcode":"35125",
    "sg:province":"AL",
    "sg:tags":[
        "saw"
    ],
    "wof:name":"Alabama Saw Co",
    "wof:placetype":"venue"
},
  "geometry": {"coordinates":[-86.361459,33.593968],"type":"Point"}
}