{
  "type": "Feature",
  "properties": {
    "addr:full":"13300 Airport Blvd Mobile AL 36608",
    "addr:housenumber":"13300",
    "addr:postcode":"36608",
    "addr:street":"Airport Blvd",
    "iso:country":"US",
    "sg:address":"13300 Airport Blvd",
    "sg:city":"Mobile",
    "sg:classifiers":[
        {
            "category":"Marine",
            "type":"Transportation"
        }
    ],
    "sg:phone":"+1 251 633 0691",
    "sg:postcode":"36608",
    "sg:province":"AL",
    "sg:tags":[
        "towing"
    ],
    "wof:name":"R M Towing Co Inc",
    "wof:placetype":"venue"
},
  "geometry": {"coordinates":[-88.38331100000001,30.638973],"type":"Point"}
}