{
  "type": "Feature",
  "properties": {
    "iso:country":"US",
    "sg:address":"1701 6th Ave SE",
    "sg:city":"Decatur",
    "sg:classifiers":[
        {
            "category":"Autos & Motor Vehicles",
            "subcategory":"Auto Supplies",
            "type":"Retail Goods"
        }
    ],
    "sg:phone":"+1 256 353 6621",
    "sg:postcode":"35601",
    "sg:province":"AL",
    "sg:tags":[
        "household",
        "appliance"
    ],
    "wof:name":"Goodyear",
    "wof:placetype":"venue"
},
  "geometry": {"coordinates":[-86.977525,34.578894],"type":"Point"}
}