{
  "type": "Feature",
  "properties": {
    "iso:country":"US",
    "sg:address":"618 Holcombe Ave",
    "sg:city":"Mobile",
    "sg:classifiers":[
        {
            "category":"Retail",
            "subcategory":"Repair Shop",
            "type":"Services"
        }
    ],
    "sg:phone":"+1 251 476 8335",
    "sg:postcode":"36606",
    "sg:province":"AL",
    "sg:tags":[
        "reupholstery",
        "furniture"
    ],
    "wof:name":"Slater Upholstry",
    "wof:placetype":"venue"
},
  "geometry": {"coordinates":[-88.089548,30.667227],"type":"Point"}
}