{
  "type": "Feature",
  "properties": {
    "iso:country":"US",
    "sg:address":"2174 Old Alton Rd",
    "sg:city":"Birmingham",
    "sg:classifiers":[
        {
            "category":"Building & Trades",
            "subcategory":"Landscaping Services",
            "type":"Services"
        }
    ],
    "sg:phone":"+1 205 969 2708",
    "sg:postcode":"35210",
    "sg:province":"AL",
    "sg:tags":[
        "landscape"
    ],
    "wof:name":"Greenway",
    "wof:placetype":"venue"
},
  "geometry": {"coordinates":[-86.648204,33.566981],"type":"Point"}
}