{
  "type": "Feature",
  "properties": {
    "iso:country":"US",
    "sg:address":"133 Downing Ridge",
    "sg:city":"Madison",
    "sg:classifiers":[
        {
            "category":"Professional",
            "subcategory":"Engineering",
            "type":"Services"
        }
    ],
    "sg:phone":"+1 256 837 0325",
    "sg:postcode":"35758",
    "sg:province":"AL",
    "sg:tags":[
        "analysis"
    ],
    "wof:name":"Summerfield Atlantic RES Ltd",
    "wof:placetype":"venue"
},
  "geometry": {"coordinates":[-86.742726,34.728547],"type":"Point"}
}