{
  "type": "Feature",
  "properties": {
    "iso:country":"US",
    "sg:address":"2203 10th Ct",
    "sg:city":"Phenix City",
    "sg:classifiers":[
        {
            "category":"Sports & Exercise",
            "subcategory":"Gym",
            "type":"Entertainment"
        }
    ],
    "sg:phone":"+1 334 297 4745",
    "sg:postcode":"36867",
    "sg:province":"AL",
    "sg:tags":[
        "fitness",
        "physical",
        "facility"
    ],
    "wof:name":"Cory Everson Fitness",
    "wof:placetype":"venue"
},
  "geometry": {"coordinates":[-85.007167,32.481509],"type":"Point"}
}