{
  "type": "Feature",
  "properties": {
    "iso:country":"US",
    "sg:address":"2604 Newby Rd SW",
    "sg:city":"Huntsville",
    "sg:classifiers":[
        {
            "category":"Manufacturing",
            "subcategory":"Tools & Machinery",
            "type":"Manufacturing & Wholesale Goods"
        }
    ],
    "sg:phone":"+1 256 837 2000",
    "sg:postcode":"35805",
    "sg:province":"AL",
    "sg:tags":[
        "thermocouple"
    ],
    "sg:website":"www.medtherm.com",
    "wof:name":"Medtherm Corp",
    "wof:placetype":"venue"
},
  "geometry": {"coordinates":[-86.59791199999999,34.712006],"type":"Point"}
}