{
  "type": "Feature",
  "properties": {
    "iso:country":"US",
    "sg:address":"1090 Coosa River Pkwy",
    "sg:city":"Wetumpka",
    "sg:classifiers":[
        {
            "category":"Manufacturing",
            "subcategory":"Wood Products",
            "type":"Manufacturing & Wholesale Goods"
        }
    ],
    "sg:phone":"+1 334 567 7561",
    "sg:postcode":"36092",
    "sg:province":"AL",
    "wof:name":"Survey Supply Co",
    "wof:placetype":"venue"
},
  "geometry": {"coordinates":[-86.217727,32.552831],"type":"Point"}
}