{
  "type": "Feature",
  "properties": {
    "addr:full":"315 S Sage Ave Mobile AL 36606",
    "addr:housenumber":"315",
    "addr:postcode":"36606",
    "addr:street":"S Sage Ave",
    "iso:country":"US",
    "sg:address":"315 S Sage Ave",
    "sg:city":"Mobile",
    "sg:classifiers":[
        {
            "category":"Professional",
            "subcategory":"Employment Agencies",
            "type":"Services"
        }
    ],
    "sg:phone":"+1 251 471 6777",
    "sg:postcode":"36606",
    "sg:province":"AL",
    "sg:tags":[
        "opportunity",
        "executive",
        "temporary",
        "placement"
    ],
    "sg:website":"www.clarkpersonnel.com",
    "wof:name":"Clark Personnel Svc",
    "wof:placetype":"venue"
},
  "geometry": {"coordinates":[-88.114378,30.672042],"type":"Point"}
}