{
  "type": "Feature",
  "properties": {
    "iso:country":"US",
    "sg:address":"3421 22nd St",
    "sg:city":"Northport",
    "sg:classifiers":[
        {
            "category":"Professional",
            "subcategory":"Management & Consulting",
            "type":"Services"
        }
    ],
    "sg:phone":"+1 205 339 7751",
    "sg:postcode":"35476",
    "sg:province":"AL",
    "sg:tags":[
        "retail",
        "direct",
        "sales"
    ],
    "wof:name":"McJenkins Enterprise",
    "wof:placetype":"venue"
},
  "geometry": {"coordinates":[-87.591841,33.231744],"type":"Point"}
}