{
  "type": "Feature",
  "properties": {
    "iso:country":"US",
    "sg:address":"5182 Greystone Way",
    "sg:city":"Birmingham",
    "sg:classifiers":[
        {
            "category":"Autos & Motor Vehicles",
            "subcategory":"Automobile Sales",
            "type":"Retail Goods"
        }
    ],
    "sg:phone":"+1 205 987 5853",
    "sg:postcode":"35242",
    "sg:province":"AL",
    "sg:tags":[
        "used"
    ],
    "wof:name":"Sutherlin Wholesale LLC",
    "wof:placetype":"venue"
},
  "geometry": {"coordinates":[-86.641046,33.434085],"type":"Point"}
}