{
  "type": "Feature",
  "properties": {
    "addr:full":"1880 E Main St Prattville AL 36066",
    "addr:housenumber":"1880",
    "addr:postcode":"36066",
    "addr:street":"E Main St",
    "iso:country":"US",
    "sg:address":"1880 E Main St",
    "sg:city":"Prattville",
    "sg:classifiers":[
        {
            "category":"Retail",
            "subcategory":"Portrait Studio",
            "type":"Services"
        }
    ],
    "sg:phone":"+1 334 365 2860",
    "sg:postcode":"36066",
    "sg:province":"AL",
    "wof:name":"Olan Mills Studios",
    "wof:placetype":"venue"
},
  "geometry": {"coordinates":[-86.420935,32.460437],"type":"Point"}
}