{
  "type": "Feature",
  "properties": {
    "iso:country":"US",
    "sg:address":"25 Commerce Ave",
    "sg:city":"Bessemer",
    "sg:classifiers":[
        {
            "category":"Building & Trades",
            "subcategory":"Construction",
            "type":"Services"
        }
    ],
    "sg:phone":"+1 205 497 4390",
    "sg:postcode":"35023",
    "sg:province":"AL",
    "sg:tags":[
        "contractor"
    ],
    "wof:name":"J & S Home Improvement & Found",
    "wof:placetype":"venue"
},
  "geometry": {"coordinates":[-86.976302,33.436621],"type":"Point"}
}