{
  "type": "Feature",
  "properties": {
    "iso:country":"US",
    "sg:address":"5431 18th Ave",
    "sg:city":"Tuscaloosa",
    "sg:classifiers":[
        {
            "category":"Wholesale",
            "subcategory":"Apparel",
            "type":"Manufacturing & Wholesale Goods"
        }
    ],
    "sg:phone":"+1 205 345 4761",
    "sg:postcode":"35405",
    "sg:province":"AL",
    "sg:tags":[
        "clothing"
    ],
    "wof:name":"Blondies Hats & Accesories",
    "wof:placetype":"venue"
},
  "geometry": {"coordinates":[-87.5602,33.158565],"type":"Point"}
}