{
  "type": "Feature",
  "properties": {
    "addr:full":"2305 Upper Wetumpka Rd Montgomery AL 36107",
    "addr:housenumber":"2305",
    "addr:postcode":"36107",
    "addr:street":"Upper Wetumpka Rd",
    "iso:country":"US",
    "sg:address":"2305 Upper Wetumpka Rd",
    "sg:city":"Montgomery",
    "sg:classifiers":[
        {
            "category":"Communications",
            "subcategory":"Radio Station",
            "type":"Services"
        }
    ],
    "sg:phone":"+1 334 834 3710",
    "sg:postcode":"36107",
    "sg:province":"AL",
    "wof:name":"W M G Y-Gospel",
    "wof:placetype":"venue"
},
  "geometry": {"coordinates":[-86.275499,32.392667],"type":"Point"}
}