{
  "type": "Feature",
  "properties": {
    "addr:full":"1603 Hickory St Mulga AL 35118",
    "addr:housenumber":"1603",
    "addr:postcode":"35118",
    "addr:street":"Hickory St",
    "iso:country":"US",
    "sg:address":"1603 Hickory St",
    "sg:city":"Mulga",
    "sg:classifiers":[
        {
            "category":"Organizations",
            "subcategory":"Religious Organization",
            "type":"Services"
        }
    ],
    "sg:phone":"+1 205 788 0056",
    "sg:postcode":"35118",
    "sg:province":"AL",
    "wof:name":"Restored Kingdon of God",
    "wof:placetype":"venue"
},
  "geometry": {"coordinates":[-86.99442000000001,33.560579],"type":"Point"}
}