{
  "type": "Feature",
  "properties": {
    "addr:full":"209 Augusta St Clanton AL 35045",
    "addr:housenumber":"209",
    "addr:postcode":"35045",
    "addr:street":"Augusta St",
    "iso:country":"US",
    "sg:address":"209 Augusta St",
    "sg:city":"Clanton",
    "sg:classifiers":[
        {
            "category":"Building & Trades",
            "subcategory":"Construction",
            "type":"Services"
        }
    ],
    "sg:phone":"+1 205 755 9543",
    "sg:postcode":"35045",
    "sg:province":"AL",
    "sg:tags":[
        "roofing",
        "contractor"
    ],
    "wof:name":"Randall W Edwards Construction",
    "wof:placetype":"venue"
},
  "geometry": {"coordinates":[-86.652046,32.834609],"type":"Point"}
}