{
  "type": "Feature",
  "properties": {
    "iso:country":"US",
    "sg:address":"1386 Ross Clark Cir",
    "sg:city":"Dothan",
    "sg:classifiers":[
        {
            "category":"Health Services",
            "subcategory":"Clinic",
            "type":"Services"
        }
    ],
    "sg:phone":"+1 334 886 9655",
    "sg:postcode":"36301",
    "sg:province":"AL",
    "sg:tags":[
        "home"
    ],
    "wof:name":"Southern Home Respiratory",
    "wof:placetype":"venue"
},
  "geometry": {"coordinates":[-85.36423600000001,31.20785],"type":"Point"}
}