{
  "type": "Feature",
  "properties": {
    "iso:country":"US",
    "sg:address":"104 Wilson Ave",
    "sg:city":"Eutaw",
    "sg:classifiers":[
        {
            "category":"Wholesale",
            "subcategory":"Construction Materials",
            "type":"Manufacturing & Wholesale Goods"
        }
    ],
    "sg:phone":"+1 205 372 2135",
    "sg:postcode":"35462",
    "sg:province":"AL",
    "sg:tags":[
        "timberland",
        "company",
        "timber"
    ],
    "wof:name":"Beeker Timber Co",
    "wof:placetype":"venue"
},
  "geometry": {"coordinates":[-87.89037,32.836899],"type":"Point"}
}