{
  "type": "Feature",
  "properties": {
    "addr:full":"1385 Enterprise Way NW Huntsville AL 35806",
    "addr:housenumber":"1385",
    "addr:postcode":"35806",
    "addr:street":"Enterprise Way Nw",
    "iso:country":"US",
    "sg:address":"1385 Enterprise Way NW",
    "sg:city":"Huntsville",
    "sg:classifiers":[
        {
            "category":"Travel",
            "subcategory":"Hotels & Motels",
            "type":"Entertainment"
        }
    ],
    "sg:phone":"+1 256 971 0921",
    "sg:postcode":"35806",
    "sg:province":"AL",
    "sg:tags":[
        "operation"
    ],
    "wof:name":"Fairfield Inn",
    "wof:placetype":"venue"
},
  "geometry": {"coordinates":[-86.68028,34.733479],"type":"Point"}
}