{
  "type": "Feature",
  "properties": {
    "iso:country":"US",
    "sg:address":"105 Vega Cir",
    "sg:city":"Daphne",
    "sg:classifiers":[
        {
            "category":"Real Estate",
            "subcategory":"Real Estate Agent",
            "type":"Services"
        }
    ],
    "sg:phone":"+1 251 942 2882",
    "sg:postcode":"36526",
    "sg:province":"AL",
    "wof:name":"Buyers Agent Realty",
    "wof:placetype":"venue"
},
  "geometry": {"coordinates":[-87.909785,30.638396],"type":"Point"}
}