{
  "type": "Feature",
  "properties": {
    "iso:country":"US",
    "sg:address":"1192 Co Rd 230",
    "sg:city":"Selma",
    "sg:classifiers":[
        {
            "category":"Communications",
            "type":"Services"
        }
    ],
    "sg:phone":"+1 334 872 2254",
    "sg:postcode":"36701",
    "sg:province":"AL",
    "sg:tags":[
        "communication"
    ],
    "wof:name":"Ope Services",
    "wof:placetype":"venue"
},
  "geometry": {"coordinates":[-87.076116,32.487583],"type":"Point"}
}