{
  "type": "Feature",
  "properties": {
    "iso:country":"US",
    "sg:address":"507 N Pine St",
    "sg:city":"Wetumpka",
    "sg:classifiers":[
        {
            "category":"Building & Trades",
            "subcategory":"Landscaping Services",
            "type":"Services"
        }
    ],
    "sg:phone":"+1 334 567 1961",
    "sg:postcode":"36092",
    "sg:province":"AL",
    "wof:name":"Quality Landscape Service",
    "wof:placetype":"venue"
},
  "geometry": {"coordinates":[-86.21713200000001,32.544591],"type":"Point"}
}