{
  "type": "Feature",
  "properties": {
    "iso:country":"US",
    "sg:address":"402 US Hwy 231",
    "sg:city":"Ozark",
    "sg:classifiers":[
        {
            "category":"Shopping",
            "subcategory":"Department Store",
            "type":"Retail Goods"
        }
    ],
    "sg:phone":"+1 334 774 9366",
    "sg:postcode":"36360",
    "sg:province":"AL",
    "wof:name":"Kmart",
    "wof:placetype":"venue"
},
  "geometry": {"coordinates":[-85.65333699999999,31.444477],"type":"Point"}
}