{
  "type": "Feature",
  "properties": {
    "iso:country":"US",
    "sg:address":"94 Blue Bird Ln",
    "sg:city":"Pell City",
    "sg:classifiers":[
        {
            "category":"Building & Trades",
            "subcategory":"Construction",
            "type":"Services"
        }
    ],
    "sg:phone":"+1 205 338 4456",
    "sg:postcode":"35125",
    "sg:province":"AL",
    "sg:tags":[
        "house"
    ],
    "wof:name":"Howell Construction",
    "wof:placetype":"venue"
},
  "geometry": {"coordinates":[-86.326451,33.623835],"type":"Point"}
}