{
  "type": "Feature",
  "properties": {
    "iso:country":"US",
    "sg:address":"722 Browns Ferry St",
    "sg:city":"Athens",
    "sg:classifiers":[
        {
            "category":"Organizations",
            "subcategory":"Religious Organization",
            "type":"Services"
        }
    ],
    "sg:phone":"+1 256 233 4229",
    "sg:postcode":"35611",
    "sg:province":"AL",
    "wof:name":"Trinity Congregation Church",
    "wof:placetype":"venue"
},
  "geometry": {"coordinates":[-86.978265,34.7981],"type":"Point"}
}