{
  "type": "Feature",
  "properties": {
    "iso:country":"US",
    "sg:address":"5269 Dresden Rd",
    "sg:city":"Birmingham",
    "sg:classifiers":[
        {
            "category":"Building & Trades",
            "subcategory":"Construction",
            "type":"Services"
        }
    ],
    "sg:phone":"+1 205 365 2415",
    "sg:postcode":"35210",
    "sg:province":"AL",
    "sg:tags":[
        "concrete",
        "contractor"
    ],
    "wof:name":"Enterprise Construction",
    "wof:placetype":"venue"
},
  "geometry": {"coordinates":[-86.69710499999999,33.525151],"type":"Point"}
}