{
  "type": "Feature",
  "properties": {
    "addr:full":"820 US Hwy 231 Troy AL 36079",
    "addr:housenumber":"820",
    "addr:postcode":"36079",
    "addr:street":"Us Hwy 231",
    "iso:country":"US",
    "sg:address":"820 US Hwy 231",
    "sg:city":"Troy",
    "sg:classifiers":[
        {
            "category":"Real Estate",
            "subcategory":"Real Estate Agent",
            "type":"Services"
        }
    ],
    "sg:phone":"+1 334 566 5335",
    "sg:postcode":"36079",
    "sg:province":"AL",
    "wof:name":"Real Estate Assoc Of Alabama",
    "wof:placetype":"venue"
},
  "geometry": {"coordinates":[-85.99112599999999,31.833239],"type":"Point"}
}