{
  "type": "Feature",
  "properties": {
    "iso:country":"US",
    "sg:address":"1211 Newell Pkwy",
    "sg:city":"Montgomery",
    "sg:classifiers":[
        {
            "category":"Professional",
            "subcategory":"Engineering",
            "type":"Services"
        }
    ],
    "sg:phone":"+1 334 260 9174",
    "sg:postcode":"36110",
    "sg:province":"AL",
    "sg:tags":[
        "engineer"
    ],
    "wof:name":"Christian Testing Laboratories",
    "wof:placetype":"venue"
},
  "geometry": {"coordinates":[-86.261431,32.413619],"type":"Point"}
}