{
  "type": "Feature",
  "properties": {
    "iso:country":"US",
    "sg:address":"25299 Canal Rd",
    "sg:city":"Orange Beach",
    "sg:classifiers":[
        {
            "category":"Shopping",
            "subcategory":"Pharmacy",
            "type":"Retail Goods"
        }
    ],
    "sg:phone":"+1 251 981 2255",
    "sg:postcode":"36561",
    "sg:province":"AL",
    "wof:name":"Orange Beach Pharmacy",
    "wof:placetype":"venue"
},
  "geometry": {"coordinates":[-87.592126,30.29043],"type":"Point"}
}