{
  "type": "Feature",
  "properties": {
    "iso:country":"US",
    "sg:address":"2501 W Jefferson St",
    "sg:city":"Anniston",
    "sg:classifiers":[
        {
            "category":"Organizations",
            "subcategory":"Religious Organization",
            "type":"Services"
        }
    ],
    "sg:phone":"+1 256 237 2307",
    "sg:postcode":"36201",
    "sg:province":"AL",
    "sg:tags":[
        "church"
    ],
    "wof:name":"First Wesleyan Church",
    "wof:placetype":"venue"
},
  "geometry": {"coordinates":[-85.86062099999999,33.649663],"type":"Point"}
}