{
  "type": "Feature",
  "properties": {
    "addr:full":"3000 McClellan Blvd Anniston AL 36207",
    "addr:housenumber":"3000",
    "addr:postcode":"36207",
    "addr:street":"Mcclellan Blvd",
    "iso:country":"US",
    "sg:address":"3000 McClellan Blvd",
    "sg:city":"Anniston",
    "sg:classifiers":[
        {
            "category":"Autos & Motor Vehicles",
            "subcategory":"Auto Supplies",
            "type":"Retail Goods"
        }
    ],
    "sg:phone":"+1 256 237 0034",
    "sg:postcode":"36207",
    "sg:province":"AL",
    "sg:tags":[
        "tire"
    ],
    "wof:name":"Discount Tire World",
    "wof:placetype":"venue"
},
  "geometry": {"coordinates":[-85.824803,33.681597],"type":"Point"}
}