{
  "type": "Feature",
  "properties": {
    "addr:full":"1584 Paul Colburn Rd Fayette AL 35555",
    "addr:housenumber":"1584",
    "addr:postcode":"35555",
    "addr:street":"Paul Colburn Rd",
    "iso:country":"US",
    "sg:address":"1584 Paul Colburn Rd",
    "sg:city":"Fayette",
    "sg:classifiers":[
        {
            "category":"Building & Trades",
            "subcategory":"Construction",
            "type":"Services"
        }
    ],
    "sg:phone":"+1 205 932 5609",
    "sg:postcode":"35555",
    "sg:province":"AL",
    "sg:tags":[
        "contractor"
    ],
    "wof:name":"Dozier Gutter",
    "wof:placetype":"venue"
},
  "geometry": {"coordinates":[-87.881794,33.815993],"type":"Point"}
}