{
  "type": "Feature",
  "properties": {
    "iso:country":"US",
    "sg:address":"10121 Airport Blvd",
    "sg:city":"Mobile",
    "sg:classifiers":[
        {
            "category":"Professional",
            "subcategory":"Accounting & Tax Preparation",
            "type":"Services"
        }
    ],
    "sg:phone":"+1 251 776 7340",
    "sg:postcode":"36608",
    "sg:province":"AL",
    "sg:tags":[
        "accountant"
    ],
    "wof:name":"Jerome C Olsen PC",
    "wof:placetype":"venue"
},
  "geometry": {"coordinates":[-88.278175,30.670638],"type":"Point"}
}