{
  "type": "Feature",
  "properties": {
    "iso:country":"US",
    "sg:address":"1405 7th St SE",
    "sg:city":"Decatur",
    "sg:classifiers":[
        {
            "category":"Health Services",
            "subcategory":"Doctor",
            "type":"Services"
        }
    ],
    "sg:phone":"+1 256 355 6414",
    "sg:postcode":"35601",
    "sg:province":"AL",
    "sg:tags":[
        "physician",
        "surgeon"
    ],
    "wof:name":"Surgical Associates",
    "wof:placetype":"venue"
},
  "geometry": {"coordinates":[-86.968818,34.591101],"type":"Point"}
}