{
  "type": "Feature",
  "properties": {
    "iso:country":"US",
    "sg:address":"171 County Lake Rd",
    "sg:city":"New Market",
    "sg:classifiers":[
        {
            "category":"Social Services",
            "subcategory":"Child Care",
            "type":"Services"
        },
        {
            "category":"Organizations",
            "subcategory":"Religious Organization",
            "type":"Services"
        }
    ],
    "sg:phone":"+1 256 379 2813",
    "sg:postcode":"35761",
    "sg:province":"AL",
    "sg:tags":[
        "baptist",
        "church"
    ],
    "sg:website":"www.locustgrove.com",
    "wof:name":"Grove Locust Baptist Church",
    "wof:placetype":"venue"
},
  "geometry": {"coordinates":[-86.458255,34.8433],"type":"Point"}
}