{
  "type": "Feature",
  "properties": {
    "iso:country":"US",
    "sg:address":"1060 US Hwy 31",
    "sg:city":"Alabaster",
    "sg:classifiers":[
        {
            "category":"Manufacturing",
            "subcategory":"Chemicals & Compounds",
            "type":"Manufacturing & Wholesale Goods"
        }
    ],
    "sg:phone":"+1 205 664 3133",
    "sg:postcode":"35007",
    "sg:province":"AL",
    "sg:tags":[
        "mfg",
        "plastic"
    ],
    "wof:name":"Polyvinyl Concepts Inc",
    "wof:placetype":"venue"
},
  "geometry": {"coordinates":[-86.814166,33.254187],"type":"Point"}
}