{
  "type": "Feature",
  "properties": {
    "iso:country":"US",
    "sg:address":"701 Saundra Ln NE",
    "sg:city":"Cullman",
    "sg:classifiers":[
        {
            "category":"Building & Trades",
            "subcategory":"Construction",
            "type":"Services"
        }
    ],
    "sg:phone":"+1 256 739 1859",
    "sg:postcode":"35055",
    "sg:province":"AL",
    "sg:tags":[
        "general",
        "contractor"
    ],
    "wof:name":"Kent Construction",
    "wof:placetype":"venue"
},
  "geometry": {"coordinates":[-86.837117,34.192171],"type":"Point"}
}