{
  "type": "Feature",
  "properties": {
    "iso:country":"US",
    "sg:address":"1004 Co Rd 261",
    "sg:city":"Fort Payne",
    "sg:classifiers":[
        {
            "category":"Professional",
            "subcategory":"Accounting & Tax Preparation",
            "type":"Services"
        }
    ],
    "sg:phone":"+1 256 845 5576",
    "sg:postcode":"35967",
    "sg:province":"AL",
    "sg:tags":[
        "return"
    ],
    "wof:name":"Griggs Tax Service",
    "wof:placetype":"venue"
},
  "geometry": {"coordinates":[-85.675538,34.406245],"type":"Point"}
}