{
  "type": "Feature",
  "properties": {
    "addr:full":"3136 Norwood Blvd Birmingham AL 35234",
    "addr:housenumber":"3136",
    "addr:postcode":"35234",
    "addr:street":"Norwood Blvd",
    "iso:country":"US",
    "sg:address":"3136 Norwood Blvd",
    "sg:city":"Birmingham",
    "sg:classifiers":[
        {
            "category":"Education",
            "subcategory":"School",
            "type":"Public Place"
        }
    ],
    "sg:phone":"+1 205 231 3620",
    "sg:postcode":"35234",
    "sg:province":"AL",
    "wof:name":"Norwood Elementary School",
    "wof:placetype":"venue"
},
  "geometry": {"coordinates":[-86.80063199999999,33.539817],"type":"Point"}
}