{
  "type": "Feature",
  "properties": {
    "addr:full":"914 Pike Rd Pike Road AL 36064",
    "addr:housenumber":"914",
    "addr:postcode":"36064",
    "addr:street":"Pike Rd Pike Road",
    "iso:country":"US",
    "sg:address":"914 Pike Rd",
    "sg:city":"Pike Road",
    "sg:classifiers":[
        {
            "category":"Professional",
            "type":"Services"
        }
    ],
    "sg:phone":"+1 334 288 1850",
    "sg:postcode":"36064",
    "sg:province":"AL",
    "wof:name":"Howell Grassing Inc",
    "wof:placetype":"venue"
},
  "geometry": {"coordinates":[-86.094897,32.355449],"type":"Point"}
}