{
  "type": "Feature",
  "properties": {
    "iso:country":"US",
    "sg:address":"7853 Crestwood Blvd",
    "sg:city":"Birmingham",
    "sg:classifiers":[
        {
            "category":"Insurance",
            "subcategory":"Hazard Insurance",
            "type":"Services"
        }
    ],
    "sg:phone":"+1 205 956 6812",
    "sg:postcode":"35212",
    "sg:province":"AL",
    "sg:website":"http://www.statefarm.com",
    "wof:name":"State Farm Insurance Companies",
    "wof:placetype":"venue"
},
  "geometry": {"coordinates":[-86.741249,33.530514],"type":"Point"}
}