{
  "type": "Feature",
  "properties": {
    "addr:full":"368 Fob James Dr Valley AL 36854",
    "addr:housenumber":"368",
    "addr:postcode":"36854",
    "addr:street":"Fob James Dr",
    "iso:country":"US",
    "sg:address":"368 Fob James Dr",
    "sg:city":"Valley",
    "sg:classifiers":[
        {
            "category":"Retail",
            "subcategory":"Auto Repair",
            "type":"Services"
        }
    ],
    "sg:phone":"+1 334 756 5700",
    "sg:postcode":"36854",
    "sg:province":"AL",
    "sg:tags":[
        "transmission"
    ],
    "wof:name":"Keith's Transmission & Auto",
    "wof:placetype":"venue"
},
  "geometry": {"coordinates":[-85.191411,32.817536],"type":"Point"}
}