{
  "type": "Feature",
  "properties": {
    "iso:country":"US",
    "sg:address":"8770 Moores Mill Rd",
    "sg:city":"Meridianville",
    "sg:classifiers":[
        {
            "category":"Farming",
            "subcategory":"Livestock Farm",
            "type":"Manufacturing & Wholesale Goods"
        }
    ],
    "sg:phone":"+1 256 828 0167",
    "sg:postcode":"35759",
    "sg:province":"AL",
    "sg:tags":[
        "beef",
        "feedlot",
        "cattle"
    ],
    "wof:name":"Joe Pierce",
    "wof:placetype":"venue"
},
  "geometry": {"coordinates":[-86.517921,34.886096],"type":"Point"}
}