{
  "type": "Feature",
  "properties": {
    "iso:country":"US",
    "sg:address":"301 Columbus St",
    "sg:city":"Montgomery",
    "sg:classifiers":[
        {
            "category":"Museum",
            "type":"Entertainment"
        }
    ],
    "sg:phone":"+1 334 240 4500",
    "sg:postcode":"36104",
    "sg:province":"AL",
    "sg:tags":[
        "building",
        "rental",
        "preservation",
        "historical"
    ],
    "sg:website":"www.oldalabamatown.com",
    "wof:name":"Old Alabama Town",
    "wof:placetype":"venue"
},
  "geometry": {"coordinates":[-86.303947,32.382115],"type":"Point"}
}