{
  "type": "Feature",
  "properties": {
    "iso:country":"US",
    "sg:address":"1069 Lakeview Cres",
    "sg:city":"Birmingham",
    "sg:classifiers":[
        {
            "category":"Professional",
            "subcategory":"Research",
            "type":"Services"
        }
    ],
    "sg:phone":"+1 205 930 0408",
    "sg:postcode":"35205",
    "sg:province":"AL",
    "sg:tags":[
        "nonphysical",
        "consulting",
        "management",
        "commercial",
        "s"
    ],
    "wof:name":"Ginter & Rucks Associates",
    "wof:placetype":"venue"
},
  "geometry": {"coordinates":[-86.779797,33.51092],"type":"Point"}
}