{
  "type": "Feature",
  "properties": {
    "iso:country":"US",
    "sg:address":"5492 US Hwy 280",
    "sg:city":"Birmingham",
    "sg:classifiers":[
        {
            "category":"Food & Beverages",
            "subcategory":"Groceries & Convenience Stores",
            "type":"Retail Goods"
        }
    ],
    "sg:phone":"+1 205 981 0994",
    "sg:postcode":"35242",
    "sg:province":"AL",
    "wof:name":"Cowboys 280",
    "wof:placetype":"venue"
},
  "geometry": {"coordinates":[-86.666242,33.4153],"type":"Point"}
}