{
  "type": "Feature",
  "properties": {
    "iso:country":"US",
    "sg:address":"28252 State Hwy 75",
    "sg:city":"Oneonta",
    "sg:classifiers":[
        {
            "category":"Retail",
            "subcategory":"Animal Services",
            "type":"Services"
        }
    ],
    "sg:phone":"+1 205 274 7387",
    "sg:postcode":"35121",
    "sg:province":"AL",
    "sg:tags":[
        "pet",
        "grooming",
        "washing"
    ],
    "wof:name":"Pets First Grooming",
    "wof:placetype":"venue"
},
  "geometry": {"coordinates":[-86.487047,33.940103],"type":"Point"}
}