{
  "type": "Feature",
  "properties": {
    "iso:country":"US",
    "sg:address":"3561 Mayfair Rd",
    "sg:city":"Montgomery",
    "sg:classifiers":[
        {
            "category":"Professional",
            "subcategory":"Business Services",
            "type":"Services"
        }
    ],
    "sg:phone":"+1 334 396 4863",
    "sg:postcode":"36109",
    "sg:province":"AL",
    "wof:name":"Structured Solutions LLC",
    "wof:placetype":"venue"
},
  "geometry": {"coordinates":[-86.25342999999999,32.392197],"type":"Point"}
}