{
  "type": "Feature",
  "properties": {
    "iso:country":"US",
    "sg:address":"420 N Water St",
    "sg:city":"Mobile",
    "sg:classifiers":[
        {
            "category":"Autos & Motor Vehicles",
            "subcategory":"Fuel & Gas Station",
            "type":"Retail Goods"
        }
    ],
    "sg:phone":"+1 251 433 7976",
    "sg:postcode":"36602",
    "sg:province":"AL",
    "sg:tags":[
        "station",
        "gasoline",
        "oil"
    ],
    "wof:name":"Clark's Exxon 21",
    "wof:placetype":"venue"
},
  "geometry": {"coordinates":[-88.045573,30.699623],"type":"Point"}
}