{
  "type": "Feature",
  "properties": {
    "iso:country":"US",
    "sg:address":"7620 Memorial Pkwy SW",
    "sg:city":"Huntsville",
    "sg:classifiers":[
        {
            "category":"Freight",
            "type":"Transportation"
        }
    ],
    "sg:phone":"+1 256 883 6201",
    "sg:postcode":"35802",
    "sg:province":"AL",
    "sg:tags":[
        "storage",
        "rental"
    ],
    "wof:name":"Sentry Self Storage LTD",
    "wof:placetype":"venue"
},
  "geometry": {"coordinates":[-86.572039,34.664742],"type":"Point"}
}