{
  "type": "Feature",
  "properties": {
    "iso:country":"US",
    "sg:address":"1301 Skyland Blvd E",
    "sg:city":"Tuscaloosa",
    "sg:classifiers":[
        {
            "category":"Banks & Credit Unions",
            "subcategory":"Bank",
            "type":"Services"
        }
    ],
    "sg:phone":"+1 205 391 2800",
    "sg:postcode":"35405",
    "sg:province":"AL",
    "wof:name":"South Trust Bank",
    "wof:placetype":"venue"
},
  "geometry": {"coordinates":[-87.51712499999999,33.168439],"type":"Point"}
}