{
  "type": "Feature",
  "properties": {
    "addr:full":"4508 20th Ave Valley AL 36854",
    "addr:housenumber":"4508",
    "addr:postcode":"36854",
    "addr:street":"20Th Ave",
    "iso:country":"US",
    "sg:address":"4508 20th Ave",
    "sg:city":"Valley",
    "sg:classifiers":[
        {
            "category":"Professional",
            "subcategory":"Business Services",
            "type":"Services"
        }
    ],
    "sg:phone":"+1 334 756 0587",
    "sg:postcode":"36854",
    "sg:province":"AL",
    "sg:tags":[
        "embroidery"
    ],
    "wof:name":"Designs R Us",
    "wof:placetype":"venue"
},
  "geometry": {"coordinates":[-85.17456199999999,32.826847],"type":"Point"}
}