{
  "type": "Feature",
  "properties": {
    "addr:full":"4171 N Spring Valley Dr Mobile AL 36693",
    "addr:housenumber":"4171",
    "addr:postcode":"36693",
    "addr:street":"N Spring Valley Dr",
    "iso:country":"US",
    "sg:address":"4171 N Spring Valley Dr",
    "sg:city":"Mobile",
    "sg:classifiers":[
        {
            "category":"Professional",
            "type":"Services"
        }
    ],
    "sg:phone":"+1 251 824 4287",
    "sg:postcode":"36693",
    "sg:province":"AL",
    "wof:name":"Jelco L L C",
    "wof:placetype":"venue"
},
  "geometry": {"coordinates":[-88.134674,30.63778],"type":"Point"}
}