{
  "type": "Feature",
  "properties": {
    "addr:full":"3316 Mayflower Ln Gadsden AL 35907",
    "addr:housenumber":"3316",
    "addr:postcode":"35907",
    "addr:street":"Mayflower Ln",
    "iso:country":"US",
    "sg:address":"3316 Mayflower Ln",
    "sg:city":"Gadsden",
    "sg:classifiers":[
        {
            "category":"Professional",
            "type":"Services"
        }
    ],
    "sg:phone":"+1 256 413 3343",
    "sg:postcode":"35907",
    "sg:province":"AL",
    "wof:name":"Blinds Brothers of Wylie",
    "wof:placetype":"venue"
},
  "geometry": {"coordinates":[-86.016518,33.916269],"type":"Point"}
}