{
  "type": "Feature",
  "properties": {
    "iso:country":"US",
    "sg:address":"1616 Upper Wetumpka Rd",
    "sg:city":"Montgomery",
    "sg:classifiers":[
        {
            "category":"Autos & Motor Vehicles",
            "subcategory":"Automobile Sales",
            "type":"Retail Goods"
        }
    ],
    "sg:phone":"+1 334 832 1453",
    "sg:postcode":"36107",
    "sg:province":"AL",
    "wof:name":"Combs Motors Inc",
    "wof:placetype":"venue"
},
  "geometry": {"coordinates":[-86.285661,32.384555],"type":"Point"}
}