{
  "type": "Feature",
  "properties": {
    "iso:country":"US",
    "sg:address":"2110 Dauphin Island Pkwy",
    "sg:city":"Mobile",
    "sg:classifiers":[
        {
            "category":"Restaurant",
            "type":"Food & Drink"
        }
    ],
    "sg:phone":"+1 251 478 3337",
    "sg:postcode":"36605",
    "sg:province":"AL",
    "wof:name":"Seafood Po'Boys",
    "wof:placetype":"venue"
},
  "geometry": {"coordinates":[-88.088832,30.626822],"type":"Point"}
}