{
  "type": "Feature",
  "properties": {
    "iso:country":"US",
    "sg:address":"292 Christopher St SW",
    "sg:city":"Cullman",
    "sg:classifiers":[
        {
            "category":"Real Estate",
            "subcategory":"Real Estate Agent",
            "type":"Services"
        }
    ],
    "sg:phone":"+1 256 775 4640",
    "sg:postcode":"35055",
    "sg:province":"AL",
    "wof:name":"Voigt Ramey & Ramey Inc",
    "wof:placetype":"venue"
},
  "geometry": {"coordinates":[-86.83577,34.143718],"type":"Point"}
}