{
  "type": "Feature",
  "properties": {
    "addr:full":"1831 Charlanda Dr Mobile AL 36695",
    "addr:housenumber":"1831",
    "addr:postcode":"36695",
    "addr:street":"Charlanda Dr",
    "iso:country":"US",
    "sg:address":"1831 Charlanda Dr",
    "sg:city":"Mobile",
    "sg:classifiers":[
        {
            "category":"Organizations",
            "subcategory":"Community Association",
            "type":"Services"
        }
    ],
    "sg:phone":"+1 251 633 6853",
    "sg:postcode":"36695",
    "sg:province":"AL",
    "wof:name":"Ancient & Accepted Scotti",
    "wof:placetype":"venue"
},
  "geometry": {"coordinates":[-88.208293,30.653312],"type":"Point"}
}