{
  "type": "Feature",
  "properties": {
    "iso:country":"US",
    "sg:address":"317 Shelton Beach Rd",
    "sg:city":"Saraland",
    "sg:classifiers":[
        {
            "category":"Real Estate",
            "subcategory":"Real Estate Agent",
            "type":"Services"
        }
    ],
    "sg:phone":"+1 251 675 3999",
    "sg:postcode":"36571",
    "sg:province":"AL",
    "wof:name":"Beth Pierce Real Estate",
    "wof:placetype":"venue"
},
  "geometry": {"coordinates":[-88.080645,30.820026],"type":"Point"}
}