{
  "type": "Feature",
  "properties": {
    "iso:country":"US",
    "sg:address":"501 6th St S",
    "sg:city":"Birmingham",
    "sg:classifiers":[
        {
            "category":"Utilities",
            "subcategory":"Refuse",
            "type":"Services"
        }
    ],
    "sg:phone":"+1 205 250 5212",
    "sg:postcode":"35233",
    "sg:province":"AL",
    "sg:tags":[
        "system"
    ],
    "wof:name":"AMM Corp",
    "wof:placetype":"venue"
},
  "geometry": {"coordinates":[-86.819937,33.497844],"type":"Point"}
}