{
  "type": "Feature",
  "properties": {
    "addr:full":"2189 Parkway Lake Dr Birmingham AL 35244",
    "addr:housenumber":"2189",
    "addr:postcode":"35244",
    "addr:street":"Parkway Lake Dr",
    "iso:country":"US",
    "sg:address":"2189 Parkway Lake Dr",
    "sg:city":"Birmingham",
    "sg:classifiers":[
        {
            "category":"Wholesale",
            "subcategory":"Groceries",
            "type":"Manufacturing & Wholesale Goods"
        }
    ],
    "sg:phone":"+1 205 988 5233",
    "sg:postcode":"35244",
    "sg:province":"AL",
    "sg:tags":[
        "food",
        "broker",
        "general"
    ],
    "sg:website":"www.acosta.com",
    "wof:name":"Acosta Sales & Marketing Co",
    "wof:placetype":"venue"
},
  "geometry": {"coordinates":[-86.79150300000001,33.35941],"type":"Point"}
}