{
  "type": "Feature",
  "properties": {
    "iso:country":"US",
    "sg:address":"600 S Court St",
    "sg:city":"Montgomery",
    "sg:classifiers":[
        {
            "category":"Real Estate",
            "subcategory":"Developer",
            "type":"Services"
        }
    ],
    "sg:phone":"+1 334 269 4777",
    "sg:postcode":"36104",
    "sg:province":"AL",
    "wof:name":"Diversified Developers",
    "wof:placetype":"venue"
},
  "geometry": {"coordinates":[-86.308749,32.368237],"type":"Point"}
}