{
  "type": "Feature",
  "properties": {
    "iso:country":"US",
    "sg:address":"776 Venable Rd",
    "sg:city":"Wetumpka",
    "sg:classifiers":[
        {
            "category":"Building & Trades",
            "subcategory":"Construction",
            "type":"Services"
        }
    ],
    "sg:phone":"+1 334 567 2803",
    "sg:postcode":"36092",
    "sg:province":"AL",
    "sg:tags":[
        "floor",
        "laying",
        "contractor"
    ],
    "wof:name":"W & W Floor Co",
    "wof:placetype":"venue"
},
  "geometry": {"coordinates":[-86.107282,32.630178],"type":"Point"}
}