{
  "type": "Feature",
  "properties": {
    "addr:full":"121 N 20th St Opelika AL 36801",
    "addr:housenumber":"121",
    "addr:postcode":"36801",
    "addr:street":"N 20Th St",
    "iso:country":"US",
    "sg:address":"121 N 20th St",
    "sg:city":"Opelika",
    "sg:classifiers":[
        {
            "category":"Health Services",
            "subcategory":"Doctor",
            "type":"Services"
        }
    ],
    "sg:phone":"+1 334 749 1268",
    "sg:postcode":"36801",
    "sg:province":"AL",
    "wof:name":"Woodall Keith DMD Prof Corp",
    "wof:placetype":"venue"
},
  "geometry": {"coordinates":[-85.40397,32.637817],"type":"Point"}
}