{
  "type": "Feature",
  "properties": {
    "addr:full":"315 3rd Ave E Bessemer AL 35020",
    "addr:housenumber":"315",
    "addr:postcode":"35020",
    "addr:street":"3Rd Ave E Bessemer",
    "iso:country":"US",
    "sg:address":"315 3rd Ave E",
    "sg:city":"Bessemer",
    "sg:classifiers":[
        {
            "category":"Organizations",
            "subcategory":"Religious Organization",
            "type":"Services"
        }
    ],
    "sg:phone":"+1 205 428 6500",
    "sg:postcode":"35020",
    "sg:province":"AL",
    "wof:name":"First Bptst Chrch Jnsboro Hght",
    "wof:placetype":"venue"
},
  "geometry": {"coordinates":[-86.952461,33.377558],"type":"Point"}
}