{
  "type": "Feature",
  "properties": {
    "iso:country":"US",
    "sg:address":"216 Dove St",
    "sg:city":"Birmingham",
    "sg:classifiers":[
        {
            "category":"Manufacturing",
            "subcategory":"Tools & Machinery",
            "type":"Manufacturing & Wholesale Goods"
        }
    ],
    "sg:phone":"+1 205 849 5488",
    "sg:postcode":"35217",
    "sg:province":"AL",
    "sg:tags":[
        "machine",
        "shop"
    ],
    "wof:name":"Foster Machine & Mfg Co",
    "wof:placetype":"venue"
},
  "geometry": {"coordinates":[-86.770351,33.58992],"type":"Point"}
}