{
  "type": "Feature",
  "properties": {
    "iso:country":"US",
    "sg:address":"1552 Co Rd 45",
    "sg:city":"Ranburne",
    "sg:classifiers":[
        {
            "category":"Farming",
            "subcategory":"Poultry Farm",
            "type":"Manufacturing & Wholesale Goods"
        }
    ],
    "sg:phone":"+1 256 568 7740",
    "sg:postcode":"36273",
    "sg:province":"AL",
    "wof:name":"Billy Gibbs",
    "wof:placetype":"venue"
},
  "geometry": {"coordinates":[-85.364251,33.511425],"type":"Point"}
}