{
  "type": "Feature",
  "properties": {
    "addr:full":"2205 McKenzie St Foley AL 36535",
    "addr:housenumber":"2205",
    "addr:postcode":"36535",
    "addr:street":"Mckenzie St",
    "iso:country":"US",
    "sg:address":"2205 McKenzie St",
    "sg:city":"Foley",
    "sg:classifiers":[
        {
            "category":"Insurance",
            "subcategory":"Insurance Agent",
            "type":"Services"
        }
    ],
    "sg:phone":"+1 251 970 3805",
    "sg:postcode":"36535",
    "sg:province":"AL",
    "wof:name":"American General Life",
    "wof:placetype":"venue"
},
  "geometry": {"coordinates":[-87.68339,30.379494],"type":"Point"}
}