{
  "type": "Feature",
  "properties": {
    "addr:full":"960 State Rte 36 Hartselle AL 35640",
    "addr:housenumber":"960",
    "addr:postcode":"35640",
    "addr:street":"State Rte 36",
    "iso:country":"US",
    "sg:address":"960 State Rte 36",
    "sg:city":"Hartselle",
    "sg:classifiers":[
        {
            "category":"Shopping",
            "subcategory":"Bicycles & Sporting Goods",
            "type":"Retail Goods"
        }
    ],
    "sg:phone":"+1 256 751 0933",
    "sg:postcode":"35640",
    "sg:province":"AL",
    "sg:tags":[
        "equipment",
        "playground"
    ],
    "sg:website":"www.bigtoptoys.net",
    "wof:name":"Big Top Toys",
    "wof:placetype":"venue"
},
  "geometry": {"coordinates":[-86.864842,34.4482],"type":"Point"}
}