{
  "type": "Feature",
  "properties": {
    "iso:country":"US",
    "sg:address":"10015 Blackwell Nursery Rd",
    "sg:city":"Semmes",
    "sg:classifiers":[
        {
            "category":"Building & Trades",
            "subcategory":"Landscaping Services",
            "type":"Services"
        }
    ],
    "sg:phone":"+1 251 649 3194",
    "sg:postcode":"36575",
    "sg:province":"AL",
    "sg:tags":[
        "landscape",
        "contractor"
    ],
    "wof:name":"Guaranteed TLC",
    "wof:placetype":"venue"
},
  "geometry": {"coordinates":[-88.30186500000001,30.785267],"type":"Point"}
}