{
  "type": "Feature",
  "properties": {
    "iso:country":"US",
    "sg:address":"351 N Ann St",
    "sg:city":"Mobile",
    "sg:classifiers":[
        {
            "category":"Organizations",
            "subcategory":"Religious Organization",
            "type":"Services"
        }
    ],
    "sg:phone":"+1 251 694 9463",
    "sg:postcode":"36603",
    "sg:province":"AL",
    "sg:tags":[
        "church"
    ],
    "wof:name":"Spiritual Impact Christian Ctr",
    "wof:placetype":"venue"
},
  "geometry": {"coordinates":[-88.06443,30.698128],"type":"Point"}
}