{
  "type": "Feature",
  "properties": {
    "addr:full":"717 N Main St Enterprise AL 36330",
    "addr:housenumber":"717",
    "addr:postcode":"36330",
    "addr:street":"N Main St",
    "iso:country":"US",
    "sg:address":"717 N Main St",
    "sg:city":"Enterprise",
    "sg:classifiers":[
        {
            "category":"Autos & Motor Vehicles",
            "subcategory":"Auto Supplies",
            "type":"Retail Goods"
        }
    ],
    "sg:phone":"+1 334 347 8809",
    "sg:postcode":"36330",
    "sg:province":"AL",
    "wof:name":"Hutto Radiator Shop",
    "wof:placetype":"venue"
},
  "geometry": {"coordinates":[-85.861825,31.324306],"type":"Point"}
}