{
  "type": "Feature",
  "properties": {
    "addr:full":"3096 Brookhill Dr Birmingham AL 35242",
    "addr:housenumber":"3096",
    "addr:postcode":"35242",
    "addr:street":"Brookhill Dr",
    "iso:country":"US",
    "sg:address":"3096 Brookhill Dr",
    "sg:city":"Birmingham",
    "sg:classifiers":[
        {
            "category":"Manufacturing",
            "subcategory":"Printing",
            "type":"Manufacturing & Wholesale Goods"
        }
    ],
    "sg:phone":"+1 205 980 9292",
    "sg:postcode":"35242",
    "sg:province":"AL",
    "sg:tags":[
        "publisher"
    ],
    "sg:website":"www.birminghamhomesearch.com",
    "wof:name":"Homes & Land Magazine",
    "wof:placetype":"venue"
},
  "geometry": {"coordinates":[-86.69882699999999,33.404297],"type":"Point"}
}