{
  "type": "Feature",
  "properties": {
    "addr:full":"1720 Cherokee Ave SW Cullman AL 35055",
    "addr:housenumber":"1720",
    "addr:postcode":"35055",
    "addr:street":"Cherokee Ave Sw",
    "iso:country":"US",
    "sg:address":"1720 Cherokee Ave SW",
    "sg:city":"Cullman",
    "sg:classifiers":[
        {
            "category":"Restaurant",
            "type":"Food & Drink"
        }
    ],
    "sg:phone":"+1 256 775 1277",
    "sg:postcode":"35055",
    "sg:province":"AL",
    "sg:tags":[
        "eating"
    ],
    "wof:name":"Ryans",
    "wof:placetype":"venue"
},
  "geometry": {"coordinates":[-86.84669,34.145469],"type":"Point"}
}