{
  "type": "Feature",
  "properties": {
    "addr:full":"35809 State Rte 17 Butler AL 36904",
    "addr:housenumber":"35809",
    "addr:postcode":"36904",
    "addr:street":"State Rte 17",
    "iso:country":"US",
    "sg:address":"35809 State Rte 17",
    "sg:city":"Butler",
    "sg:classifiers":[
        {
            "category":"Freight",
            "type":"Transportation"
        }
    ],
    "sg:phone":"+1 205 459 5494",
    "sg:postcode":"36904",
    "sg:province":"AL",
    "sg:tags":[
        "operator",
        "local",
        "trucking"
    ],
    "wof:name":"Thomas Trucking LLC",
    "wof:placetype":"venue"
},
  "geometry": {"coordinates":[-88.177785,32.150731],"type":"Point"}
}