{
  "type": "Feature",
  "properties": {
    "iso:country":"US",
    "sg:address":"9 41st St S",
    "sg:city":"Birmingham",
    "sg:classifiers":[
        {
            "category":"Utilities",
            "subcategory":"Refuse",
            "type":"Services"
        }
    ],
    "sg:phone":"+1 205 595 6980",
    "sg:postcode":"35222",
    "sg:province":"AL",
    "sg:tags":[
        "system"
    ],
    "wof:name":"Visy Recycling",
    "wof:placetype":"venue"
},
  "geometry": {"coordinates":[-86.77511699999999,33.52572],"type":"Point"}
}