{
  "type": "Feature",
  "properties": {
    "iso:country":"US",
    "sg:address":"1535 Montgomery Hwy",
    "sg:city":"Birmingham",
    "sg:classifiers":[
        {
            "category":"Real Estate",
            "subcategory":"Developer",
            "type":"Services"
        }
    ],
    "sg:phone":"+1 205 822 6030",
    "sg:postcode":"35216",
    "sg:province":"AL",
    "sg:tags":[
        "operation"
    ],
    "sg:website":"www.daysinn.com",
    "wof:name":"Days Inn",
    "wof:placetype":"venue"
},
  "geometry": {"coordinates":[-86.806265,33.411763],"type":"Point"}
}