{
  "type": "Feature",
  "properties": {
    "iso:country":"US",
    "sg:address":"120 8th Ave SW",
    "sg:city":"Childersburg",
    "sg:classifiers":[
        {
            "category":"Insurance",
            "subcategory":"Insurance Agent",
            "type":"Services"
        }
    ],
    "sg:phone":"+1 256 378 6306",
    "sg:postcode":"35044",
    "sg:province":"AL",
    "wof:name":"Wright & Sprayberry Insurance",
    "wof:placetype":"venue"
},
  "geometry": {"coordinates":[-86.355094,33.277967],"type":"Point"}
}