{
  "type": "Feature",
  "properties": {
    "addr:full":"200 Owen Ave Bessemer AL 35020",
    "addr:housenumber":"200",
    "addr:postcode":"35020",
    "addr:street":"Owen Ave",
    "iso:country":"US",
    "sg:address":"200 Owen Ave",
    "sg:city":"Bessemer",
    "sg:classifiers":[
        {
            "category":"Professional",
            "subcategory":"Business Services",
            "type":"Services"
        }
    ],
    "sg:phone":"+1 205 424 0293",
    "sg:postcode":"35020",
    "sg:province":"AL",
    "wof:name":"Michaels Interior Design",
    "wof:placetype":"venue"
},
  "geometry": {"coordinates":[-86.959048,33.379056],"type":"Point"}
}