{
  "type": "Feature",
  "properties": {
    "addr:full":"7601 Airport Blvd Mobile AL 36608",
    "addr:housenumber":"7601",
    "addr:postcode":"36608",
    "addr:street":"Airport Blvd",
    "iso:country":"US",
    "sg:address":"7601 Airport Blvd",
    "sg:city":"Mobile",
    "sg:classifiers":[
        {
            "category":"Manufacturing",
            "subcategory":"Buildings",
            "type":"Manufacturing & Wholesale Goods"
        }
    ],
    "sg:phone":"+1 251 639 1416",
    "sg:postcode":"36608",
    "sg:province":"AL",
    "sg:tags":[
        "mobile",
        "home",
        "mfg"
    ],
    "wof:name":"Shel Ter Co",
    "wof:placetype":"venue"
},
  "geometry": {"coordinates":[-88.220545,30.685103],"type":"Point"}
}