{
  "type": "Feature",
  "properties": {
    "iso:country":"US",
    "sg:address":"303 N Carlisle St",
    "sg:city":"Albertville",
    "sg:classifiers":[
        {
            "category":"Building & Trades",
            "subcategory":"Construction",
            "type":"Services"
        }
    ],
    "sg:phone":"+1 256 891 1116",
    "sg:postcode":"35950",
    "sg:province":"AL",
    "sg:tags":[
        "contractor"
    ],
    "wof:name":"Kelgraco Inc",
    "wof:placetype":"venue"
},
  "geometry": {"coordinates":[-86.206282,34.271547],"type":"Point"}
}