{
  "type": "Feature",
  "properties": {
    "iso:country":"US",
    "sg:address":"210 Oxmoor Cir",
    "sg:city":"Birmingham",
    "sg:classifiers":[
        {
            "category":"Freight",
            "type":"Transportation"
        }
    ],
    "sg:phone":"+1 205 940 9799",
    "sg:postcode":"35209",
    "sg:province":"AL",
    "sg:tags":[
        "courier"
    ],
    "wof:name":"Bevmark Distributors",
    "wof:placetype":"venue"
},
  "geometry": {"coordinates":[-86.836376,33.452794],"type":"Point"}
}