{
  "type": "Feature",
  "properties": {
    "iso:country":"US",
    "sg:address":"29348 Perdido Beach Blvd",
    "sg:city":"Orange Beach",
    "sg:classifiers":[
        {
            "category":"Real Estate",
            "subcategory":"Real Estate Operator",
            "type":"Services"
        }
    ],
    "sg:phone":"+1 251 981 7099",
    "sg:postcode":"36561",
    "sg:province":"AL",
    "sg:tags":[
        "condominium"
    ],
    "wof:name":"Gulf Condo Rentals Inc",
    "wof:placetype":"venue"
},
  "geometry": {"coordinates":[-87.519077,30.281353],"type":"Point"}
}