{
  "type": "Feature",
  "properties": {
    "addr:full":"7070 Aaron Aronov Dr Fairfield AL 35064",
    "addr:housenumber":"7070",
    "addr:postcode":"35064",
    "addr:street":"Aaron Aronov Dr",
    "iso:country":"US",
    "sg:address":"7070 Aaron Aronov Dr",
    "sg:city":"Fairfield",
    "sg:classifiers":[
        {
            "category":"Personal",
            "subcategory":"Beauty Salon",
            "type":"Services"
        }
    ],
    "sg:phone":"+1 205 781 0666",
    "sg:postcode":"35064",
    "sg:province":"AL",
    "sg:tags":[
        "shop"
    ],
    "wof:name":"Top Perfect Nails",
    "wof:placetype":"venue"
},
  "geometry": {"coordinates":[-86.919405,33.46956],"type":"Point"}
}