{
  "type": "Feature",
  "properties": {
    "addr:full":"1906 Garber St Tuscaloosa AL 35404",
    "addr:housenumber":"1906",
    "addr:postcode":"35404",
    "addr:street":"Garber St",
    "iso:country":"US",
    "sg:address":"1906 Garber St",
    "sg:city":"Tuscaloosa",
    "sg:classifiers":[
        {
            "category":"Autos & Motor Vehicles",
            "subcategory":"Automobile Sales",
            "type":"Retail Goods"
        }
    ],
    "sg:phone":"+1 205 554 1659",
    "sg:postcode":"35404",
    "sg:province":"AL",
    "sg:tags":[
        "used"
    ],
    "wof:name":"Efua Auto Sales",
    "wof:placetype":"venue"
},
  "geometry": {"coordinates":[-87.492544,33.236946],"type":"Point"}
}