{
  "type": "Feature",
  "properties": {
    "iso:country":"US",
    "sg:address":"28800 Comstock Rd",
    "sg:city":"Elberta",
    "sg:classifiers":[
        {
            "category":"Professional",
            "subcategory":"Business Services",
            "type":"Services"
        }
    ],
    "sg:phone":"+1 251 986 8194",
    "sg:postcode":"36530",
    "sg:province":"AL",
    "sg:tags":[
        "welcome"
    ],
    "wof:name":"Mat Welcome",
    "wof:placetype":"venue"
},
  "geometry": {"coordinates":[-87.528244,30.458398],"type":"Point"}
}