{
  "type": "Feature",
  "properties": {
    "iso:country":"US",
    "sg:address":"3005 River Brook Ln",
    "sg:city":"Birmingham",
    "sg:classifiers":[
        {
            "category":"Building & Trades",
            "subcategory":"Construction",
            "type":"Services"
        }
    ],
    "sg:phone":"+1 205 991 9215",
    "sg:postcode":"35242",
    "sg:province":"AL",
    "sg:tags":[
        "general",
        "contractor"
    ],
    "wof:name":"Caleb Construction",
    "wof:placetype":"venue"
},
  "geometry": {"coordinates":[-86.725188,33.418534],"type":"Point"}
}