{
  "type": "Feature",
  "properties": {
    "iso:country":"US",
    "sg:address":"601 Co Rd 78",
    "sg:city":"Selma",
    "sg:classifiers":[
        {
            "category":"Manufacturing",
            "subcategory":"Paper Products",
            "type":"Manufacturing & Wholesale Goods"
        }
    ],
    "sg:phone":"+1 334 872 3481",
    "sg:postcode":"36703",
    "sg:province":"AL",
    "sg:tags":[
        "mfg"
    ],
    "wof:name":"International Paper Co",
    "wof:placetype":"venue"
},
  "geometry": {"coordinates":[-86.878986,32.427192],"type":"Point"}
}