{
  "type": "Feature",
  "properties": {
    "addr:full":"605 Columbia Hwy Dothan AL 36301",
    "addr:housenumber":"605",
    "addr:postcode":"36301",
    "addr:street":"Columbia Hwy",
    "iso:country":"US",
    "sg:address":"605 Columbia Hwy",
    "sg:city":"Dothan",
    "sg:classifiers":[
        {
            "category":"Recreation",
            "subcategory":"Amusement Park",
            "type":"Entertainment"
        }
    ],
    "sg:phone":"+1 334 792 5131",
    "sg:postcode":"36301",
    "sg:province":"AL",
    "wof:name":"Crimsom Heart Skatepark LLC",
    "wof:placetype":"venue"
},
  "geometry": {"coordinates":[-85.381809,31.221417],"type":"Point"}
}