{
  "type": "Feature",
  "properties": {
    "iso:country":"US",
    "sg:address":"1011 Pine St",
    "sg:city":"Thomasville",
    "sg:classifiers":[
        {
            "category":"Social Services",
            "subcategory":"Child Care",
            "type":"Services"
        }
    ],
    "sg:phone":"+1 334 636 4615",
    "sg:postcode":"36784",
    "sg:province":"AL",
    "sg:tags":[
        "kindergarten",
        "academic",
        "school"
    ],
    "wof:name":"Jack Jill Kindergarten",
    "wof:placetype":"venue"
},
  "geometry": {"coordinates":[-87.745682,31.886612],"type":"Point"}
}