{
  "type": "Feature",
  "properties": {
    "addr:full":"2362 Willowdale St Mobile AL 36605",
    "addr:housenumber":"2362",
    "addr:postcode":"36605",
    "addr:street":"Willowdale St",
    "iso:country":"US",
    "sg:address":"2362 Willowdale St",
    "sg:city":"Mobile",
    "sg:classifiers":[
        {
            "category":"Professional",
            "type":"Services"
        }
    ],
    "sg:phone":"+1 251 471 3481",
    "sg:postcode":"36605",
    "sg:province":"AL",
    "wof:name":"Littlepage Phillippi LLC",
    "wof:placetype":"venue"
},
  "geometry": {"coordinates":[-88.087067,30.623012],"type":"Point"}
}