{
  "type": "Feature",
  "properties": {
    "iso:country":"US",
    "sg:address":"760 Chestnut St",
    "sg:city":"Gadsden",
    "sg:classifiers":[
        {
            "category":"Health Services",
            "subcategory":"Doctor",
            "type":"Services"
        }
    ],
    "sg:phone":"+1 256 543 1100",
    "sg:postcode":"35901",
    "sg:province":"AL",
    "sg:tags":[
        "physician",
        "surgeon"
    ],
    "wof:name":"Kenny E Smith MD",
    "wof:placetype":"venue"
},
  "geometry": {"coordinates":[-86.011476,34.013991],"type":"Point"}
}