{
  "type": "Feature",
  "properties": {
    "iso:country":"US",
    "sg:address":"107 Danforth Dr",
    "sg:city":"Harvest",
    "sg:classifiers":[
        {
            "category":"Autos & Motor Vehicles",
            "subcategory":"Automobile Sales",
            "type":"Retail Goods"
        }
    ],
    "sg:phone":"+1 256 655 3115",
    "sg:postcode":"35749",
    "sg:province":"AL",
    "sg:tags":[
        "used"
    ],
    "wof:name":"Wls Imports Inc",
    "wof:placetype":"venue"
},
  "geometry": {"coordinates":[-86.671674,34.819509],"type":"Point"}
}