{
  "type": "Feature",
  "properties": {
    "addr:full":"489 Co Rd 643 Ranburne AL 36273",
    "addr:housenumber":"489",
    "addr:postcode":"36273",
    "addr:street":"Co Rd 643 Ranburne",
    "iso:country":"US",
    "sg:address":"489 Co Rd 643",
    "sg:city":"Ranburne",
    "sg:classifiers":[
        {
            "category":"Retail",
            "subcategory":"Auto Repair",
            "type":"Services"
        }
    ],
    "sg:phone":"+1 256 568 7223",
    "sg:postcode":"36273",
    "sg:province":"AL",
    "sg:tags":[
        "body",
        "automotive",
        "painting",
        "automobile"
    ],
    "wof:name":"S & S Automotive",
    "wof:placetype":"venue"
},
  "geometry": {"coordinates":[-85.31482099999999,33.513942],"type":"Point"}
}