{
  "type": "Feature",
  "properties": {
    "addr:full":"1201 Co Rd 1508 Cullman AL 35058",
    "addr:housenumber":"1201;1508",
    "addr:postcode":"35058",
    "addr:street":"Co Rd",
    "iso:country":"US",
    "sg:address":"1201 Co Rd 1508",
    "sg:city":"Cullman",
    "sg:classifiers":[
        {
            "category":"Wholesale",
            "subcategory":"Non-durable Goods",
            "type":"Manufacturing & Wholesale Goods"
        }
    ],
    "sg:phone":"+1 256 796 7882",
    "sg:postcode":"35058",
    "sg:province":"AL",
    "wof:name":"JC Advertising",
    "wof:placetype":"venue"
},
  "geometry": {"coordinates":[-86.744203,34.240272],"type":"Point"}
}