{
  "type": "Feature",
  "properties": {
    "iso:country":"US",
    "sg:address":"1558 Hurtel St",
    "sg:city":"Mobile",
    "sg:classifiers":[
        {
            "category":"Personal",
            "subcategory":"Beauty Salon",
            "type":"Services"
        }
    ],
    "sg:phone":"+1 251 479 6990",
    "sg:postcode":"36605",
    "sg:province":"AL",
    "sg:tags":[
        "shop"
    ],
    "wof:name":"Charitas Touch",
    "wof:placetype":"venue"
},
  "geometry": {"coordinates":[-88.076561,30.656694],"type":"Point"}
}