{
  "type": "Feature",
  "properties": {
    "iso:country":"US",
    "sg:address":"1729 5th Ave N",
    "sg:city":"Birmingham",
    "sg:classifiers":[
        {
            "category":"Government",
            "subcategory":"Office",
            "type":"Public Place"
        }
    ],
    "sg:phone":"+1 205 278 1970",
    "sg:postcode":"35203",
    "sg:province":"AL",
    "wof:name":"Honorable Inge P Johnson",
    "wof:placetype":"venue"
},
  "geometry": {"coordinates":[-86.811301,33.516497],"type":"Point"}
}