{
  "type": "Feature",
  "properties": {
    "iso:country":"US",
    "sg:address":"621 Boll Weevil Cir",
    "sg:city":"Enterprise",
    "sg:classifiers":[
        {
            "category":"Food & Beverages",
            "subcategory":"Specialty",
            "type":"Retail Goods"
        },
        {
            "category":"Home & Garden",
            "subcategory":"Home Furnishings",
            "type":"Retail Goods"
        }
    ],
    "sg:phone":"+1 334 347 7057",
    "sg:postcode":"36330",
    "sg:province":"AL",
    "sg:tags":[
        "gourmet",
        "shop",
        "kitchenware"
    ],
    "wof:name":"Pure Imagination Inc",
    "wof:placetype":"venue"
},
  "geometry": {"coordinates":[-85.864113,31.333332],"type":"Point"}
}