{
  "type": "Feature",
  "properties": {
    "iso:country":"US",
    "sg:address":"1125 Hollingsworth Dr",
    "sg:city":"Wellington",
    "sg:classifiers":[
        {
            "category":"Personal",
            "subcategory":"Beauty Salon",
            "type":"Services"
        }
    ],
    "sg:phone":"+1 256 492 8007",
    "sg:postcode":"36279",
    "sg:province":"AL",
    "wof:name":"Hair Affair Styling Salon",
    "wof:placetype":"venue"
},
  "geometry": {"coordinates":[-85.905132,33.900301],"type":"Point"}
}