{
  "type": "Feature",
  "properties": {
    "addr:full":"1125 Hollingsworth Dr Wellington AL 36279",
    "addr:housenumber":"1125",
    "addr:postcode":"36279",
    "addr:street":"Hollingsworth Dr",
    "iso:country":"US",
    "sg:address":"1125 Hollingsworth Dr",
    "sg:city":"Wellington",
    "sg:classifiers":[
        {
            "category":"Personal",
            "subcategory":"Beauty Salon",
            "type":"Services"
        }
    ],
    "sg:phone":"+1 256 492 8007",
    "sg:postcode":"36279",
    "sg:province":"AL",
    "wof:name":"Hair Affair Styling Salon",
    "wof:placetype":"venue"
},
  "geometry": {"coordinates":[-85.90513199999999,33.900301],"type":"Point"}
}