{
  "type": "Feature",
  "properties": {
    "addr:full":"1323 Weaver St Selma AL 36703",
    "addr:housenumber":"1323",
    "addr:postcode":"36703",
    "addr:street":"Weaver St",
    "iso:country":"US",
    "sg:address":"1323 Weaver St",
    "sg:city":"Selma",
    "sg:classifiers":[
        {
            "category":"Organizations",
            "subcategory":"Religious Organization",
            "type":"Services"
        }
    ],
    "sg:phone":"+1 334 872 2562",
    "sg:postcode":"36703",
    "sg:province":"AL",
    "sg:tags":[
        "church"
    ],
    "wof:name":"Bethelham Baptist Church",
    "wof:placetype":"venue"
},
  "geometry": {"coordinates":[-87.00805099999999,32.41634],"type":"Point"}
}