{
  "type": "Feature",
  "properties": {
    "iso:country":"US",
    "sg:address":"2111 E University Dr",
    "sg:city":"Auburn",
    "sg:classifiers":[
        {
            "category":"Cinema",
            "subcategory":"Movie Theater",
            "type":"Entertainment"
        }
    ],
    "sg:phone":"+1 334 826 8826",
    "sg:postcode":"36830",
    "sg:province":"AL",
    "sg:tags":[
        "motion",
        "picture"
    ],
    "wof:name":"Carmike Cinemas",
    "wof:placetype":"venue"
},
  "geometry": {"coordinates":[-85.452254,32.628436],"type":"Point"}
}