{
  "type": "Feature",
  "properties": {
    "iso:country":"US",
    "sg:address":"720 Oak Circle Dr E",
    "sg:city":"Mobile",
    "sg:classifiers":[
        {
            "category":"Professional",
            "subcategory":"Business Services",
            "type":"Services"
        }
    ],
    "sg:phone":"+1 251 662 8300",
    "sg:postcode":"36609",
    "sg:province":"AL",
    "sg:tags":[
        "paging",
        "signaling"
    ],
    "wof:name":"Allpage Inc",
    "wof:placetype":"venue"
},
  "geometry": {"coordinates":[-88.154933,30.651569],"type":"Point"}
}