{
  "type": "Feature",
  "properties": {
    "addr:full":"125 Deerbrook Rd Pell City AL 35125",
    "addr:housenumber":"125",
    "addr:postcode":"35125",
    "addr:street":"Deerbrook Rd",
    "iso:country":"US",
    "sg:address":"125 Deerbrook Rd",
    "sg:city":"Pell City",
    "sg:classifiers":[
        {
            "category":"Organizations",
            "subcategory":"Religious Organization",
            "type":"Services"
        }
    ],
    "sg:phone":"+1 205 884 1463",
    "sg:postcode":"35125",
    "sg:province":"AL",
    "wof:name":"Harvest Home Intl Outreach",
    "wof:placetype":"venue"
},
  "geometry": {"coordinates":[-86.316249,33.647888],"type":"Point"}
}