{
  "type": "Feature",
  "properties": {
    "addr:full":"4040 Balmoral Dr SW Huntsville AL 35801",
    "addr:housenumber":"4040",
    "addr:postcode":"35801",
    "addr:street":"Balmoral Dr Sw",
    "iso:country":"US",
    "sg:address":"4040 Balmoral Dr SW",
    "sg:city":"Huntsville",
    "sg:classifiers":[
        {
            "category":"Banks & Credit Unions",
            "subcategory":"Bank",
            "type":"Services"
        }
    ],
    "sg:phone":"+1 256 536 5626",
    "sg:postcode":"35801",
    "sg:province":"AL",
    "sg:tags":[
        "loan",
        "real estate"
    ],
    "sg:website":"www.worthingtonmortgage.com",
    "wof:name":"Worthington Mortgage Group",
    "wof:placetype":"venue"
},
  "geometry": {"coordinates":[-86.579494,34.696265],"type":"Point"}
}