{
  "type": "Feature",
  "properties": {
    "iso:country":"US",
    "sg:address":"8631 Plantation Ridge Rd",
    "sg:city":"Montgomery",
    "sg:classifiers":[
        {
            "category":"Professional",
            "subcategory":"Management & Consulting",
            "type":"Services"
        }
    ],
    "sg:phone":"+1 334 396 5514",
    "sg:postcode":"36116",
    "sg:province":"AL",
    "sg:tags":[
        "marketing",
        "program"
    ],
    "wof:name":"Sternenberg Marketing",
    "wof:placetype":"venue"
},
  "geometry": {"coordinates":[-86.16515699999999,32.334782],"type":"Point"}
}