{
  "type": "Feature",
  "properties": {
    "iso:country":"US",
    "sg:address":"5503 Roy Dr",
    "sg:city":"Helena",
    "sg:classifiers":[
        {
            "category":"Retail",
            "subcategory":"Auto Repair",
            "type":"Services"
        }
    ],
    "sg:phone":"+1 205 663 1303",
    "sg:postcode":"35080",
    "sg:province":"AL",
    "sg:tags":[
        "repairing",
        "automobile"
    ],
    "wof:name":"Tom's Auto Svc",
    "wof:placetype":"venue"
},
  "geometry": {"coordinates":[-86.845789,33.287705],"type":"Point"}
}