{
  "type": "Feature",
  "properties": {
    "iso:country":"US",
    "sg:address":"2821 Eastern Blvd",
    "sg:city":"Montgomery",
    "sg:classifiers":[
        {
            "category":"Banks & Credit Unions",
            "subcategory":"Investment Brokerage",
            "type":"Services"
        }
    ],
    "sg:phone":"+1 334 271 3991",
    "sg:postcode":"36116",
    "sg:province":"AL",
    "sg:tags":[
        "security"
    ],
    "wof:name":"Winton Blount III & Assoc",
    "wof:placetype":"venue"
},
  "geometry": {"coordinates":[-86.225225,32.341819],"type":"Point"}
}