{
  "type": "Feature",
  "properties": {
    "iso:country":"US",
    "sg:address":"204 Saint Nicholas Ave",
    "sg:city":"Brewton",
    "sg:classifiers":[
        {
            "category":"Autos & Motor Vehicles",
            "subcategory":"Fuel & Gas Station",
            "type":"Retail Goods"
        }
    ],
    "sg:phone":"+1 251 867 9397",
    "sg:postcode":"36426",
    "sg:province":"AL",
    "wof:name":"C&D Grocery",
    "wof:placetype":"venue"
},
  "geometry": {"coordinates":[-87.07349600000001,31.105063],"type":"Point"}
}