{
  "type": "Feature",
  "properties": {
    "iso:country":"US",
    "sg:address":"133 Rockway Rd",
    "sg:city":"Birmingham",
    "sg:classifiers":[
        {
            "category":"Professional",
            "subcategory":"Advertising",
            "type":"Services"
        }
    ],
    "sg:phone":"+1 205 870 5730",
    "sg:postcode":"35209",
    "sg:province":"AL",
    "sg:tags":[
        "mail",
        "direct"
    ],
    "wof:name":"Custom Mail Services Inc",
    "wof:placetype":"venue"
},
  "geometry": {"coordinates":[-86.805464,33.458839],"type":"Point"}
}