{
  "type": "Feature",
  "properties": {
    "iso:country":"US",
    "sg:address":"200 S Quintard Ave",
    "sg:city":"Anniston",
    "sg:classifiers":[
        {
            "category":"Banks & Credit Unions",
            "subcategory":"Bank",
            "type":"Services"
        }
    ],
    "sg:phone":"+1 256 237 1684",
    "sg:postcode":"36201",
    "sg:province":"AL",
    "wof:name":"America's First Credit Union",
    "wof:placetype":"venue"
},
  "geometry": {"coordinates":[-85.82608999999999,33.643497],"type":"Point"}
}