{
  "type": "Feature",
  "properties": {
    "iso:country":"US",
    "sg:address":"900 Merchant Walk",
    "sg:city":"Huntsville",
    "sg:classifiers":[
        {
            "category":"Health Services",
            "subcategory":"Doctor",
            "type":"Services"
        }
    ],
    "sg:phone":"+1 256 519 8972",
    "sg:postcode":"35801",
    "sg:province":"AL",
    "sg:tags":[
        "clinic"
    ],
    "wof:name":"South Parkway Chiropractic",
    "wof:placetype":"venue"
},
  "geometry": {"coordinates":[-86.588383,34.713401],"type":"Point"}
}