{
  "type": "Feature",
  "properties": {
    "addr:full":"1796 Hwy 77 Gadsden AL 35907",
    "addr:housenumber":"1796",
    "addr:postcode":"35907",
    "addr:street":"Hwy 77",
    "iso:country":"US",
    "sg:address":"1796 Hwy 77",
    "sg:city":"Gadsden",
    "sg:classifiers":[
        {
            "category":"Shopping",
            "subcategory":"Clothing, Apparel, & Fashions",
            "type":"Retail Goods"
        }
    ],
    "sg:phone":"+1 256 442 1058",
    "sg:postcode":"35907",
    "sg:province":"AL",
    "sg:tags":[
        "personal"
    ],
    "wof:name":"Ultimate Tan & Treasures",
    "wof:placetype":"venue"
},
  "geometry": {"coordinates":[-86.023878,33.929196],"type":"Point"}
}