{
  "type": "Feature",
  "properties": {
    "addr:full":"1119 Willow Run Rd Birmingham AL 35209",
    "addr:housenumber":"1119",
    "addr:postcode":"35209",
    "addr:street":"Willow Run Rd",
    "iso:country":"US",
    "sg:address":"1119 Willow Run Rd",
    "sg:city":"Birmingham",
    "sg:classifiers":[
        {
            "category":"Real Estate",
            "subcategory":"Real Estate Operator",
            "type":"Services"
        }
    ],
    "sg:phone":"+1 205 870 4535",
    "sg:postcode":"35209",
    "sg:province":"AL",
    "sg:tags":[
        "apartment"
    ],
    "wof:name":"Magnolia Park",
    "wof:placetype":"venue"
},
  "geometry": {"coordinates":[-86.80664299999999,33.4806],"type":"Point"}
}