{
  "type": "Feature",
  "properties": {
    "iso:country":"US",
    "sg:address":"1455 Co Rd 87",
    "sg:city":"Russellville",
    "sg:classifiers":[
        {
            "category":"Wholesale",
            "subcategory":"Farm Supplies",
            "type":"Manufacturing & Wholesale Goods"
        }
    ],
    "sg:phone":"+1 256 332 9650",
    "sg:postcode":"35654",
    "sg:province":"AL",
    "sg:tags":[
        "feed"
    ],
    "wof:name":"Channell Farms Inc",
    "wof:placetype":"venue"
},
  "geometry": {"coordinates":[-87.582897,34.491061],"type":"Point"}
}