{
  "type": "Feature",
  "properties": {
    "iso:country":"US",
    "sg:address":"1109 Old Talladega Hwy",
    "sg:city":"Sylacauga",
    "sg:classifiers":[
        {
            "category":"Insurance",
            "subcategory":"Insurance Agent",
            "type":"Services"
        }
    ],
    "sg:phone":"+1 256 245 3052",
    "sg:postcode":"35150",
    "sg:province":"AL",
    "wof:name":"Alfa Insurance Corp",
    "wof:placetype":"venue"
},
  "geometry": {"coordinates":[-86.24380600000001,33.183336],"type":"Point"}
}