{
  "type": "Feature",
  "properties": {
    "iso:country":"US",
    "sg:address":"203 E Lee St",
    "sg:city":"Enterprise",
    "sg:classifiers":[
        {
            "category":"Professional",
            "type":"Services"
        }
    ],
    "sg:phone":"+1 334 347 9861",
    "sg:postcode":"36330",
    "sg:province":"AL",
    "wof:name":"Professional Aviation Training",
    "wof:placetype":"venue"
},
  "geometry": {"coordinates":[-85.852147,31.317076],"type":"Point"}
}