{
  "type": "Feature",
  "properties": {
    "iso:country":"US",
    "sg:address":"1337 Springville Rd",
    "sg:city":"Birmingham",
    "sg:classifiers":[
        {
            "category":"Organizations",
            "subcategory":"Religious Organization",
            "type":"Services"
        }
    ],
    "sg:phone":"+1 205 856 8963",
    "sg:postcode":"35215",
    "sg:province":"AL",
    "sg:tags":[
        "church"
    ],
    "wof:name":"LDS Church",
    "wof:placetype":"venue"
},
  "geometry": {"coordinates":[-86.672857,33.617497],"type":"Point"}
}