{
  "type": "Feature",
  "properties": {
    "iso:country":"US",
    "sg:address":"103 Kirkland St",
    "sg:city":"Abbeville",
    "sg:classifiers":[
        {
            "category":"Restaurant",
            "type":"Food & Drink"
        }
    ],
    "sg:phone":"+1 334 585 0312",
    "sg:postcode":"36310",
    "sg:province":"AL",
    "sg:tags":[
        "barbecue"
    ],
    "wof:name":"Jimmy's Barbecue",
    "wof:placetype":"venue"
},
  "geometry": {"coordinates":[-85.30249,31.523421],"type":"Point"}
}