{
  "type": "Feature",
  "properties": {
    "iso:country":"US",
    "sg:address":"70 Greenview Dr",
    "sg:city":"Scottsboro",
    "sg:classifiers":[
        {
            "category":"Retail",
            "subcategory":"Portrait Studio",
            "type":"Services"
        }
    ],
    "sg:phone":"+1 256 259 4375",
    "sg:postcode":"35768",
    "sg:province":"AL",
    "sg:tags":[
        "photo"
    ],
    "wof:name":"Wj Photography",
    "wof:placetype":"venue"
},
  "geometry": {"coordinates":[-86.00224900000001,34.697077],"type":"Point"}
}