{
  "type": "Feature",
  "properties": {
    "addr:full":"2837 Pelham Pkwy Pelham AL 35124",
    "addr:housenumber":"2837",
    "addr:postcode":"35124",
    "addr:street":"Pelham Pkwy",
    "iso:country":"US",
    "sg:address":"2837 Pelham Pkwy",
    "sg:city":"Pelham",
    "sg:classifiers":[
        {
            "category":"Restaurant",
            "type":"Food & Drink"
        }
    ],
    "sg:phone":"+1 205 664 0640",
    "sg:postcode":"35124",
    "sg:province":"AL",
    "wof:name":"Scotty's Place",
    "wof:placetype":"venue"
},
  "geometry": {"coordinates":[-86.80654699999999,33.304261],"type":"Point"}
}