{
  "type": "Feature",
  "properties": {
    "iso:country":"US",
    "sg:address":"114 E Azalea Ave",
    "sg:city":"Foley",
    "sg:classifiers":[
        {
            "category":"Insurance",
            "subcategory":"Insurance Agent",
            "type":"Services"
        }
    ],
    "sg:phone":"+1 251 943 3904",
    "sg:postcode":"36535",
    "sg:province":"AL",
    "wof:name":"Thrivent Financial-Lutherans",
    "wof:placetype":"venue"
},
  "geometry": {"coordinates":[-87.682823,30.39939],"type":"Point"}
}