{
  "type": "Feature",
  "properties": {
    "iso:country":"US",
    "sg:address":"681 Tick Duckett Rd",
    "sg:city":"Albertville",
    "sg:classifiers":[
        {
            "category":"Professional",
            "subcategory":"Business Services",
            "type":"Services"
        }
    ],
    "sg:phone":"+1 256 878 7327",
    "sg:postcode":"35951",
    "sg:province":"AL",
    "wof:name":"L & T Enterprises Inc",
    "wof:placetype":"venue"
},
  "geometry": {"coordinates":[-86.12215,34.367819],"type":"Point"}
}