{
  "type": "Feature",
  "properties": {
    "addr:full":"736 McFarland Blvd Northport AL 35476",
    "addr:housenumber":"736",
    "addr:postcode":"35476",
    "addr:street":"Mcfarland Blvd",
    "iso:country":"US",
    "sg:address":"736 McFarland Blvd",
    "sg:city":"Northport",
    "sg:classifiers":[
        {
            "category":"Shopping",
            "type":"Retail Goods"
        }
    ],
    "sg:phone":"+1 205 339 3370",
    "sg:postcode":"35476",
    "sg:province":"AL",
    "sg:tags":[
        "medical",
        "hospital",
        "supply"
    ],
    "wof:name":"Home Med Inc",
    "wof:placetype":"venue"
},
  "geometry": {"coordinates":[-87.563125,33.237191],"type":"Point"}
}