{
  "type": "Feature",
  "properties": {
    "addr:full":"950 Parkway Dr SE Leeds AL 35094",
    "addr:housenumber":"950",
    "addr:postcode":"35094",
    "addr:street":"Parkway Dr Se",
    "iso:country":"US",
    "sg:address":"950 Parkway Dr SE",
    "sg:city":"Leeds",
    "sg:classifiers":[
        {
            "category":"Retail",
            "subcategory":"Auto Repair",
            "type":"Services"
        }
    ],
    "sg:phone":"+1 205 702 4000",
    "sg:postcode":"35094",
    "sg:province":"AL",
    "sg:tags":[
        "repairing",
        "automobile"
    ],
    "wof:name":"Greenway Custom Paint & Body",
    "wof:placetype":"venue"
},
  "geometry": {"coordinates":[-86.53976299999999,33.542676],"type":"Point"}
}