{
  "type": "Feature",
  "properties": {
    "iso:country":"US",
    "sg:address":"2300 Center Hills Dr",
    "sg:city":"Opelika",
    "sg:classifiers":[
        {
            "category":"Social Services",
            "type":"Services"
        }
    ],
    "sg:phone":"+1 334 742 2112",
    "sg:postcode":"36801",
    "sg:province":"AL",
    "sg:tags":[
        "organization",
        "welfare"
    ],
    "wof:name":"Lee-Scan",
    "wof:placetype":"venue"
},
  "geometry": {"coordinates":[-85.41063200000001,32.626052],"type":"Point"}
}