{
  "type": "Feature",
  "properties": {
    "addr:full":"1000 Glenn Hearn Blvd SW Huntsville AL 35824",
    "addr:housenumber":"1000",
    "addr:postcode":"35824",
    "addr:street":"Glenn Hearn Blvd Sw",
    "iso:country":"US",
    "sg:address":"1000 Glenn Hearn Blvd SW",
    "sg:city":"Huntsville",
    "sg:classifiers":[
        {
            "category":"Wholesale",
            "subcategory":"Machinery & Supplies",
            "type":"Manufacturing & Wholesale Goods"
        }
    ],
    "sg:phone":"+1 256 772 2004",
    "sg:postcode":"35824",
    "sg:province":"AL",
    "sg:tags":[
        "aircraft",
        "avionics"
    ],
    "wof:name":"C-Cubed Avionics",
    "wof:placetype":"venue"
},
  "geometry": {"coordinates":[-86.773734,34.648485],"type":"Point"}
}