{
  "type": "Feature",
  "properties": {
    "iso:country":"US",
    "sg:address":"90 Kay Ave",
    "sg:city":"Trussville",
    "sg:classifiers":[
        {
            "category":"Professional",
            "subcategory":"Management & Consulting",
            "type":"Services"
        }
    ],
    "sg:phone":"+1 205 802 7811",
    "sg:postcode":"35173",
    "sg:province":"AL",
    "wof:name":"On Track Accounting",
    "wof:placetype":"venue"
},
  "geometry": {"coordinates":[-86.61493,33.617815],"type":"Point"}
}