{
  "type": "Feature",
  "properties": {
    "iso:country":"US",
    "sg:address":"513 Vassar St",
    "sg:city":"Dothan",
    "sg:classifiers":[
        {
            "category":"Personal",
            "subcategory":"Beauty Salon",
            "type":"Services"
        }
    ],
    "sg:phone":"+1 334 677 1166",
    "sg:postcode":"36301",
    "sg:province":"AL",
    "wof:name":"Nancy Hair & Nails Shop",
    "wof:placetype":"venue"
},
  "geometry": {"coordinates":[-85.384143,31.208866],"type":"Point"}
}