{
  "type": "Feature",
  "properties": {
    "iso:country":"US",
    "sg:address":"306 N Goldthwaite St",
    "sg:city":"Montgomery",
    "sg:classifiers":[
        {
            "category":"Retail",
            "subcategory":"Auto Repair",
            "type":"Services"
        }
    ],
    "sg:phone":"+1 334 263 2111",
    "sg:postcode":"36104",
    "sg:province":"AL",
    "sg:tags":[
        "transmission"
    ],
    "wof:name":"Harlow's Transmission Svc",
    "wof:placetype":"venue"
},
  "geometry": {"coordinates":[-86.315208,32.377617],"type":"Point"}
}