{
  "type": "Feature",
  "properties": {
    "iso:country":"US",
    "sg:address":"3956 Barrancas Key Dr",
    "sg:city":"Orange Beach",
    "sg:classifiers":[
        {
            "category":"Building & Trades",
            "subcategory":"Cleaning & Sanitation",
            "type":"Services"
        }
    ],
    "sg:phone":"+1 251 980 6344",
    "sg:postcode":"36561",
    "sg:province":"AL",
    "sg:tags":[
        "maintenance"
    ],
    "wof:name":"Enhanced Home Services",
    "wof:placetype":"venue"
},
  "geometry": {"coordinates":[-87.53436,30.28322],"type":"Point"}
}