{
  "type": "Feature",
  "properties": {
    "addr:full":"500 Gene Reed Rd Birmingham AL 35215",
    "addr:housenumber":"500",
    "addr:postcode":"35215",
    "addr:street":"Gene Reed Rd",
    "iso:country":"US",
    "sg:address":"500 Gene Reed Rd",
    "sg:city":"Birmingham",
    "sg:classifiers":[
        {
            "category":"Professional",
            "subcategory":"Accounting & Tax Preparation",
            "type":"Services"
        }
    ],
    "sg:phone":"+1 205 838 2300",
    "sg:postcode":"35215",
    "sg:province":"AL",
    "sg:tags":[
        "accountant"
    ],
    "wof:name":"Owens Jerry",
    "wof:placetype":"venue"
},
  "geometry": {"coordinates":[-86.697197,33.597801],"type":"Point"}
}