{
  "type": "Feature",
  "properties": {
    "iso:country":"US",
    "sg:address":"2954 Spring Hill Ave",
    "sg:city":"Mobile",
    "sg:classifiers":[
        {
            "category":"Retail",
            "subcategory":"Laundry & Dry Cleaning",
            "type":"Services"
        }
    ],
    "sg:phone":"+1 251 479 7791",
    "sg:postcode":"36607",
    "sg:province":"AL",
    "sg:tags":[
        "garment",
        "agent",
        "cleaners"
    ],
    "wof:name":"Dixie Service Cleaners MBL GA",
    "wof:placetype":"venue"
},
  "geometry": {"coordinates":[-88.110119,30.699427],"type":"Point"}
}