{
  "type": "Feature",
  "properties": {
    "iso:country":"US",
    "sg:address":"522 W 2nd St",
    "sg:city":"Muscle Shoals",
    "sg:classifiers":[
        {
            "category":"Professional",
            "subcategory":"Advertising",
            "type":"Services"
        }
    ],
    "sg:phone":"+1 256 383 2112",
    "sg:postcode":"35661",
    "sg:province":"AL",
    "sg:tags":[
        "counselor"
    ],
    "wof:name":"Sound Advertising",
    "wof:placetype":"venue"
},
  "geometry": {"coordinates":[-87.703523,34.75994],"type":"Point"}
}