{
  "type": "Feature",
  "properties": {
    "iso:country":"US",
    "sg:address":"107 E Northside St",
    "sg:city":"Tuskegee",
    "sg:classifiers":[
        {
            "category":"Shopping",
            "subcategory":"Gifts & Souvenirs",
            "type":"Retail Goods"
        },
        {
            "category":"Shopping",
            "subcategory":"Clothing, Apparel, & Fashions",
            "type":"Retail Goods"
        }
    ],
    "sg:phone":"+1 334 727 4225",
    "sg:postcode":"36083",
    "sg:province":"AL",
    "sg:tags":[
        "shop"
    ],
    "wof:name":"Ala's Unique Boutique",
    "wof:placetype":"venue"
},
  "geometry": {"coordinates":[-85.690816,32.424718],"type":"Point"}
}