{
  "type": "Feature",
  "properties": {
    "addr:full":"3133 Bell Rd Montgomery AL 36116",
    "addr:housenumber":"3133",
    "addr:postcode":"36116",
    "addr:street":"Bell Rd",
    "iso:country":"US",
    "sg:address":"3133 Bell Rd",
    "sg:city":"Montgomery",
    "sg:classifiers":[
        {
            "category":"Restaurant",
            "type":"Food & Drink"
        }
    ],
    "sg:phone":"+1 334 277 8710",
    "sg:postcode":"36116",
    "sg:province":"AL",
    "sg:tags":[
        "eating"
    ],
    "wof:name":"Ruddles Pub",
    "wof:placetype":"venue"
},
  "geometry": {"coordinates":[-86.196265,32.337588],"type":"Point"}
}