{
  "type": "Feature",
  "properties": {
    "addr:full":"12844 US Hwy 431 Guntersville AL 35976",
    "addr:housenumber":"12844",
    "addr:postcode":"35976",
    "addr:street":"Us Hwy 431",
    "iso:country":"US",
    "sg:address":"12844 US Hwy 431",
    "sg:city":"Guntersville",
    "sg:classifiers":[
        {
            "category":"Banks & Credit Unions",
            "subcategory":"Bank",
            "type":"Services"
        }
    ],
    "sg:phone":"+1 256 582 4774",
    "sg:postcode":"35976",
    "sg:province":"AL",
    "sg:tags":[
        "cashing",
        "check"
    ],
    "wof:name":"Quicloans",
    "wof:placetype":"venue"
},
  "geometry": {"coordinates":[-86.29541399999999,34.307913],"type":"Point"}
}