{
  "type": "Feature",
  "properties": {
    "addr:full":"608 Cherry St Eufaula AL 36027",
    "addr:housenumber":"608",
    "addr:postcode":"36027",
    "addr:street":"Cherry St",
    "iso:country":"US",
    "sg:address":"608 Cherry St",
    "sg:city":"Eufaula",
    "sg:classifiers":[
        {
            "category":"Retail",
            "subcategory":"Photofinishing",
            "type":"Services"
        }
    ],
    "sg:phone":"+1 334 687 7457",
    "sg:postcode":"36027",
    "sg:province":"AL",
    "sg:tags":[
        "laboratory"
    ],
    "wof:name":"Billy Andrew Photography",
    "wof:placetype":"venue"
},
  "geometry": {"coordinates":[-85.156499,31.895648],"type":"Point"}
}