{
  "type": "Feature",
  "properties": {
    "addr:full":"1117 John J Egan Dr Birmingham AL 35204",
    "addr:housenumber":"1117",
    "addr:postcode":"35204",
    "addr:street":"John J Egan Dr",
    "iso:country":"US",
    "sg:address":"1117 John J Egan Dr",
    "sg:city":"Birmingham",
    "sg:classifiers":[
        {
            "category":"Professional",
            "subcategory":"Business Services",
            "type":"Services"
        }
    ],
    "sg:phone":"+1 205 326 6266",
    "sg:postcode":"35204",
    "sg:province":"AL",
    "wof:name":"Clays Retail Sales",
    "wof:placetype":"venue"
},
  "geometry": {"coordinates":[-86.833772,33.540324],"type":"Point"}
}