{
  "type": "Feature",
  "properties": {
    "iso:country":"US",
    "sg:address":"3100 Sunview Dr",
    "sg:city":"Birmingham",
    "sg:classifiers":[
        {
            "category":"Personal",
            "subcategory":"Beauty Salon",
            "type":"Services"
        }
    ],
    "sg:phone":"+1 205 969 0788",
    "sg:postcode":"35243",
    "sg:province":"AL",
    "sg:tags":[
        "hair",
        "studio"
    ],
    "wof:name":"Batton Hair Studio",
    "wof:placetype":"venue"
},
  "geometry": {"coordinates":[-86.733318,33.461455],"type":"Point"}
}