{
  "type": "Feature",
  "properties": {
    "iso:country":"US",
    "sg:address":"123 Wall St",
    "sg:city":"Gadsden",
    "sg:classifiers":[
        {
            "category":"Retail",
            "subcategory":"Animal Services",
            "type":"Services"
        }
    ],
    "sg:phone":"+1 256 547 7074",
    "sg:postcode":"35904",
    "sg:province":"AL",
    "wof:name":"Pet Paws Grooming",
    "wof:placetype":"venue"
},
  "geometry": {"coordinates":[-86.045632,34.019631],"type":"Point"}
}