{
  "type": "Feature",
  "properties": {
    "iso:country":"US",
    "sg:address":"1606 Rainbow Dr",
    "sg:city":"Gadsden",
    "sg:classifiers":[
        {
            "category":"Restaurant",
            "type":"Food & Drink"
        }
    ],
    "sg:phone":"+1 256 547 9817",
    "sg:postcode":"35901",
    "sg:province":"AL",
    "wof:name":"Top O The River",
    "wof:placetype":"venue"
},
  "geometry": {"coordinates":[-86.004299,33.988857],"type":"Point"}
}