{
  "type": "Feature",
  "properties": {
    "addr:full":"9795 Corner School Rd Warrior AL 35180",
    "addr:housenumber":"9795",
    "addr:postcode":"35180",
    "addr:street":"Corner School Rd",
    "iso:country":"US",
    "sg:address":"9795 Corner School Rd",
    "sg:city":"Warrior",
    "sg:classifiers":[
        {
            "category":"Farming",
            "subcategory":"Farm",
            "type":"Manufacturing & Wholesale Goods"
        }
    ],
    "sg:phone":"+1 205 647 6884",
    "sg:postcode":"35180",
    "sg:province":"AL",
    "sg:tags":[
        "crop",
        "general"
    ],
    "wof:name":"Wakefield Farms",
    "wof:placetype":"venue"
},
  "geometry": {"coordinates":[-86.94072799999999,33.793394],"type":"Point"}
}