{
  "type": "Feature",
  "properties": {
    "iso:country":"US",
    "sg:address":"102 W Northside St",
    "sg:city":"Tuskegee",
    "sg:classifiers":[
        {
            "category":"Banks & Credit Unions",
            "subcategory":"Bank",
            "type":"Services"
        }
    ],
    "sg:phone":"+1 334 724 9312",
    "sg:postcode":"36083",
    "sg:province":"AL",
    "sg:tags":[
        "loan"
    ],
    "wof:name":"Tuskegee Loan Co Inc",
    "wof:placetype":"venue"
},
  "geometry": {"coordinates":[-85.691523,32.424114],"type":"Point"}
}