{
  "type": "Feature",
  "properties": {
    "iso:country":"US",
    "sg:address":"515 2nd Ave NW",
    "sg:city":"Arab",
    "sg:classifiers":[
        {
            "category":"Organizations",
            "subcategory":"Religious Organization",
            "type":"Services"
        }
    ],
    "sg:phone":"+1 256 586 7652",
    "sg:postcode":"35016",
    "sg:province":"AL",
    "wof:name":"New Life Tabernacle Upc",
    "wof:placetype":"venue"
},
  "geometry": {"coordinates":[-86.50145000000001,34.319433],"type":"Point"}
}