{
  "type": "Feature",
  "properties": {
    "iso:country":"US",
    "sg:address":"11295 State Rte 157",
    "sg:city":"Florence",
    "sg:classifiers":[
        {
            "category":"Restaurant",
            "type":"Food & Drink"
        }
    ],
    "sg:phone":"+1 256 767 2272",
    "sg:postcode":"35633",
    "sg:province":"AL",
    "sg:tags":[
        "eating"
    ],
    "wof:name":"Cloverdale Grille",
    "wof:placetype":"venue"
},
  "geometry": {"coordinates":[-87.77978,34.947316],"type":"Point"}
}