{
  "type": "Feature",
  "properties": {
    "iso:country":"US",
    "sg:address":"1366 Main St",
    "sg:city":"Sumiton",
    "sg:classifiers":[
        {
            "category":"Real Estate",
            "subcategory":"Surveying",
            "type":"Services"
        }
    ],
    "sg:phone":"+1 205 648 9351",
    "sg:postcode":"35148",
    "sg:province":"AL",
    "sg:tags":[
        "surveyor"
    ],
    "wof:name":"Land-Tec Surveying Co",
    "wof:placetype":"venue"
},
  "geometry": {"coordinates":[-87.047867,33.755269],"type":"Point"}
}