{
  "type": "Feature",
  "properties": {
    "addr:full":"1205 S 8th St Lanett AL 36863",
    "addr:housenumber":"1205",
    "addr:postcode":"36863",
    "addr:street":"S 8Th St",
    "iso:country":"US",
    "sg:address":"1205 S 8th St",
    "sg:city":"Lanett",
    "sg:classifiers":[
        {
            "category":"Organizations",
            "subcategory":"Religious Organization",
            "type":"Services"
        }
    ],
    "sg:phone":"+1 334 644 4396",
    "sg:postcode":"36863",
    "sg:province":"AL",
    "wof:name":"West Side Baptist Church",
    "wof:placetype":"venue"
},
  "geometry": {"coordinates":[-85.200367,32.862435],"type":"Point"}
}