{
  "type": "Feature",
  "properties": {
    "iso:country":"US",
    "sg:address":"722 Moffett Rd",
    "sg:city":"Dothan",
    "sg:classifiers":[
        {
            "category":"Communications",
            "subcategory":"Film & Video Production",
            "type":"Services"
        }
    ],
    "sg:phone":"+1 334 678 9526",
    "sg:postcode":"36301",
    "sg:province":"AL",
    "sg:tags":[
        "taping"
    ],
    "wof:name":"In Focus",
    "wof:placetype":"venue"
},
  "geometry": {"coordinates":[-85.409232,31.133822],"type":"Point"}
}