{
  "type": "Feature",
  "properties": {
    "iso:country":"US",
    "sg:address":"515 E Laurel Ave",
    "sg:city":"Foley",
    "sg:classifiers":[
        {
            "category":"Food & Beverages",
            "subcategory":"Groceries & Convenience Stores",
            "type":"Retail Goods"
        }
    ],
    "sg:phone":"+1 251 943 2405",
    "sg:postcode":"36535",
    "sg:province":"AL",
    "wof:name":"Easy Stop",
    "wof:placetype":"venue"
},
  "geometry": {"coordinates":[-87.674791,30.406572],"type":"Point"}
}