{
  "type": "Feature",
  "properties": {
    "iso:country":"US",
    "sg:address":"1016 S Valley Ave",
    "sg:city":"Collinsville",
    "sg:classifiers":[
        {
            "category":"Shopping",
            "subcategory":"Used Merchandise",
            "type":"Retail Goods"
        },
        {
            "category":"Professional",
            "subcategory":"Business Services",
            "type":"Services"
        }
    ],
    "sg:phone":"+1 256 524 2536",
    "sg:postcode":"35961",
    "sg:province":"AL",
    "sg:tags":[
        "flea",
        "market"
    ],
    "sg:website":"www.collinsvilletradeday.com",
    "wof:name":"Collinsville Trade Day No 1",
    "wof:placetype":"venue"
},
  "geometry": {"coordinates":[-85.868635,34.252774],"type":"Point"}
}