{
  "type": "Feature",
  "properties": {
    "iso:country":"US",
    "sg:address":"1931 Highland Ave",
    "sg:city":"Montgomery",
    "sg:classifiers":[
        {
            "category":"Education",
            "subcategory":"Special Training",
            "type":"Public Place"
        }
    ],
    "sg:phone":"+1 334 832 7369",
    "sg:postcode":"36107",
    "sg:province":"AL",
    "wof:name":"Wing of Faith Learning Center",
    "wof:placetype":"venue"
},
  "geometry": {"coordinates":[-86.282135,32.372309],"type":"Point"}
}