{
  "type": "Feature",
  "properties": {
    "iso:country":"US",
    "sg:address":"5331 Perimeter Pkwy",
    "sg:city":"Montgomery",
    "sg:classifiers":[
        {
            "category":"Manufacturing",
            "subcategory":"Chemicals & Compounds",
            "type":"Manufacturing & Wholesale Goods"
        }
    ],
    "sg:phone":"+1 334 288 1288",
    "sg:postcode":"36116",
    "sg:province":"AL",
    "sg:tags":[
        "miller",
        "drug"
    ],
    "sg:website":"www.proethic.com",
    "wof:name":"Pro Ethic Laboratories",
    "wof:placetype":"venue"
},
  "geometry": {"coordinates":[-86.20677499999999,32.299827],"type":"Point"}
}