{
  "type": "Feature",
  "properties": {
    "addr:full":"175 Ag Science Dr Brewton AL 36426",
    "addr:postcode":"36426",
    "addr:street":"Science Dr",
    "iso:country":"US",
    "sg:address":"175 Ag Science Dr",
    "sg:city":"Brewton",
    "sg:classifiers":[
        {
            "category":"Education",
            "subcategory":"College",
            "type":"Public Place"
        }
    ],
    "sg:phone":"+1 251 809 1801",
    "sg:postcode":"36426",
    "sg:province":"AL",
    "sg:tags":[
        "university"
    ],
    "wof:name":"Auburn University",
    "wof:placetype":"venue"
},
  "geometry": {"coordinates":[-87.10109799999999,31.088422],"type":"Point"}
}