{
  "type": "Feature",
  "properties": {
    "addr:full":"4356 Old Shell Rd Mobile AL 36608",
    "addr:housenumber":"4356",
    "addr:postcode":"36608",
    "addr:street":"Old Shell Rd",
    "iso:country":"US",
    "sg:address":"4356 Old Shell Rd",
    "sg:city":"Mobile",
    "sg:classifiers":[
        {
            "category":"Manufacturing",
            "subcategory":"Apparel",
            "type":"Manufacturing & Wholesale Goods"
        }
    ],
    "sg:phone":"+1 251 342 6131",
    "sg:postcode":"36608",
    "sg:province":"AL",
    "sg:tags":[
        "sewing",
        "contractor"
    ],
    "wof:name":"Sew N Shop",
    "wof:placetype":"venue"
},
  "geometry": {"coordinates":[-88.14216999999999,30.697756],"type":"Point"}
}