{
  "type": "Feature",
  "properties": {
    "iso:country":"US",
    "sg:address":"3493 Government Blvd",
    "sg:city":"Mobile",
    "sg:classifiers":[
        {
            "category":"Retail",
            "subcategory":"Repair Shop",
            "type":"Services"
        }
    ],
    "sg:phone":"+1 251 661 3345",
    "sg:postcode":"36693",
    "sg:province":"AL",
    "sg:tags":[
        "refinishing",
        "furniture"
    ],
    "wof:name":"C & S Refinishing & Restoring",
    "wof:placetype":"venue"
},
  "geometry": {"coordinates":[-88.125611,30.650045],"type":"Point"}
}