{
  "type": "Feature",
  "properties": {
    "iso:country":"US",
    "sg:address":"79967 US Hwy 278",
    "sg:city":"Blountsville",
    "sg:classifiers":[
        {
            "category":"Building & Trades",
            "subcategory":"Construction",
            "type":"Services"
        }
    ],
    "sg:phone":"+1 205 429 3814",
    "sg:postcode":"35031",
    "sg:province":"AL",
    "sg:tags":[
        "house"
    ],
    "wof:name":"Custom Building",
    "wof:placetype":"venue"
},
  "geometry": {"coordinates":[-86.504635,34.163154],"type":"Point"}
}