{
  "type": "Feature",
  "properties": {
    "iso:country":"US",
    "sg:address":"6814 Deer Foot Dr",
    "sg:city":"Pinson",
    "sg:classifiers":[
        {
            "category":"Real Estate",
            "subcategory":"Architect",
            "type":"Services"
        }
    ],
    "sg:phone":"+1 205 681 8362",
    "sg:postcode":"35126",
    "sg:province":"AL",
    "sg:website":"www.drhorton.com",
    "wof:name":"D R Horton",
    "wof:placetype":"venue"
},
  "geometry": {"coordinates":[-86.606392,33.699147],"type":"Point"}
}