{
  "type": "Feature",
  "properties": {
    "iso:country":"US",
    "sg:address":"10695 US Hwy 98",
    "sg:city":"Fairhope",
    "sg:classifiers":[
        {
            "category":"Building & Trades",
            "subcategory":"Construction",
            "type":"Services"
        }
    ],
    "sg:phone":"+1 251 928 2958",
    "sg:postcode":"36532",
    "sg:province":"AL",
    "sg:tags":[
        "pile",
        "driving",
        "contractor"
    ],
    "wof:name":"Robert J Barlow Inc",
    "wof:placetype":"venue"
},
  "geometry": {"coordinates":[-87.84036,30.419639],"type":"Point"}
}