{
  "type": "Feature",
  "properties": {
    "iso:country":"US",
    "sg:address":"123 S Hamburg Ave",
    "sg:city":"Butler",
    "sg:classifiers":[
        {
            "category":"Government",
            "subcategory":"Office",
            "type":"Public Place"
        },
        {
            "category":"Social Services",
            "type":"Services"
        }
    ],
    "sg:phone":"+1 205 459 5911",
    "sg:postcode":"36904",
    "sg:province":"AL",
    "sg:tags":[
        "notification",
        "executive",
        "emergency"
    ],
    "wof:name":"E 911 Communications District",
    "wof:placetype":"venue"
},
  "geometry": {"coordinates":[-88.222474,32.089767],"type":"Point"}
}