{
  "type": "Feature",
  "properties": {
    "iso:country":"US",
    "sg:address":"4756 Old Shell Rd",
    "sg:city":"Mobile",
    "sg:classifiers":[
        {
            "category":"Professional",
            "subcategory":"Management & Consulting",
            "type":"Services"
        }
    ],
    "sg:phone":"+1 251 343 0169",
    "sg:postcode":"36608",
    "sg:province":"AL",
    "sg:tags":[
        "business"
    ],
    "wof:name":"Chamlee Consulting Inc",
    "wof:placetype":"venue"
},
  "geometry": {"coordinates":[-88.15222300000001,30.693175],"type":"Point"}
}