{
  "type": "Feature",
  "properties": {
    "addr:full":"1612 US Hwy 78 Oxford AL 36203",
    "addr:housenumber":"1612",
    "addr:postcode":"36203",
    "addr:street":"Us Hwy 78",
    "iso:country":"US",
    "sg:address":"1612 US Hwy 78",
    "sg:city":"Oxford",
    "sg:classifiers":[
        {
            "category":"Health Services",
            "subcategory":"Doctor",
            "type":"Services"
        }
    ],
    "sg:phone":"+1 256 835 4756",
    "sg:postcode":"36203",
    "sg:province":"AL",
    "sg:tags":[
        "physician",
        "medical",
        "surgeon"
    ],
    "wof:name":"Patient First Healthcare",
    "wof:placetype":"venue"
},
  "geometry": {"coordinates":[-85.87538000000001,33.594653],"type":"Point"}
}