{
  "type": "Feature",
  "properties": {
    "iso:country":"US",
    "sg:address":"4124 3rd Ave S",
    "sg:city":"Birmingham",
    "sg:classifiers":[
        {
            "category":"Personal",
            "subcategory":"Beauty Salon",
            "type":"Services"
        }
    ],
    "sg:phone":"+1 205 592 6133",
    "sg:postcode":"35222",
    "sg:province":"AL",
    "sg:tags":[
        "shop"
    ],
    "wof:name":"Infinite Artistry Hair & Nail",
    "wof:placetype":"venue"
},
  "geometry": {"coordinates":[-86.77279,33.524237],"type":"Point"}
}