{
  "type": "Feature",
  "properties": {
    "iso:country":"US",
    "sg:address":"101 E Grubbs St",
    "sg:city":"Enterprise",
    "sg:classifiers":[
        {
            "category":"Education",
            "subcategory":"Library",
            "type":"Public Place"
        }
    ],
    "sg:phone":"+1 334 347 2636",
    "sg:postcode":"36330",
    "sg:province":"AL",
    "sg:website":"www.enterprise-pub-library.net",
    "wof:name":"Enterprise Public Library",
    "wof:placetype":"venue"
},
  "geometry": {"coordinates":[-85.85329,31.313626],"type":"Point"}
}