{
  "type": "Feature",
  "properties": {
    "addr:full":"303 Walker St Gurley AL 35748",
    "addr:housenumber":"303",
    "addr:postcode":"35748",
    "addr:street":"Walker St",
    "iso:country":"US",
    "sg:address":"303 Walker St",
    "sg:city":"Gurley",
    "sg:classifiers":[
        {
            "category":"Organizations",
            "subcategory":"Religious Organization",
            "type":"Services"
        }
    ],
    "sg:phone":"+1 256 776 2244",
    "sg:postcode":"35748",
    "sg:province":"AL",
    "wof:name":"Gurley Church Of Christ",
    "wof:placetype":"venue"
},
  "geometry": {"coordinates":[-86.369491,34.695804],"type":"Point"}
}