{
  "type": "Feature",
  "properties": {
    "addr:full":"519 Paul Jeffcoat Rd Gordon AL 36343",
    "addr:housenumber":"519",
    "addr:postcode":"36343",
    "addr:street":"Paul Jeffcoat Rd",
    "iso:country":"US",
    "sg:address":"519 Paul Jeffcoat Rd",
    "sg:city":"Gordon",
    "sg:classifiers":[
        {
            "category":"Farming",
            "subcategory":"Farm",
            "type":"Manufacturing & Wholesale Goods"
        }
    ],
    "sg:phone":"+1 334 522 3766",
    "sg:postcode":"36343",
    "sg:province":"AL",
    "wof:name":"George Jeffcoat Farms",
    "wof:placetype":"venue"
},
  "geometry": {"coordinates":[-85.09419800000001,31.110931],"type":"Point"}
}