{
  "type": "Feature",
  "properties": {
    "addr:full":"67859 State Rte 17 Detroit AL 35552",
    "addr:housenumber":"67859",
    "addr:postcode":"35552",
    "addr:street":"State Rte 17",
    "iso:country":"US",
    "sg:address":"67859 State Rte 17",
    "sg:city":"Detroit",
    "sg:classifiers":[
        {
            "category":"Autos & Motor Vehicles",
            "subcategory":"Fuel & Gas Station",
            "type":"Retail Goods"
        }
    ],
    "sg:phone":"+1 205 273 4551",
    "sg:postcode":"35552",
    "sg:province":"AL",
    "sg:tags":[
        "oil"
    ],
    "wof:name":"Shell",
    "wof:placetype":"venue"
},
  "geometry": {"coordinates":[-88.138289,34.053861],"type":"Point"}
}