{
  "type": "Feature",
  "properties": {
    "iso:country":"US",
    "sg:address":"495 Woodcreek Ln",
    "sg:city":"Pell City",
    "sg:classifiers":[
        {
            "category":"Farming",
            "subcategory":"Livestock Farm",
            "type":"Manufacturing & Wholesale Goods"
        }
    ],
    "sg:phone":"+1 205 640 7737",
    "sg:postcode":"35128",
    "sg:province":"AL",
    "sg:tags":[
        "specialty",
        "animal"
    ],
    "wof:name":"Wood Creek Apiary",
    "wof:placetype":"venue"
},
  "geometry": {"coordinates":[-86.454078,33.557046],"type":"Point"}
}