{
  "type": "Feature",
  "properties": {
    "iso:country":"US",
    "sg:address":"878 Pike Rd",
    "sg:city":"Pike Road",
    "sg:classifiers":[
        {
            "category":"Restaurant",
            "type":"Food & Drink"
        }
    ],
    "sg:phone":"+1 334 271 0177",
    "sg:postcode":"36064",
    "sg:province":"AL",
    "sg:tags":[
        "eating"
    ],
    "wof:name":"Steaks Devine",
    "wof:placetype":"venue"
},
  "geometry": {"coordinates":[-86.094898,32.356033],"type":"Point"}
}