{
  "type": "Feature",
  "properties": {
    "addr:full":"1113 30th Ave Northport AL 35476",
    "addr:housenumber":"1113",
    "addr:postcode":"35476",
    "addr:street":"30Th Ave",
    "iso:country":"US",
    "sg:address":"1113 30th Ave",
    "sg:city":"Northport",
    "sg:classifiers":[
        {
            "category":"Retail",
            "subcategory":"Auto Repair",
            "type":"Services"
        }
    ],
    "sg:phone":"+1 205 750 0403",
    "sg:postcode":"35476",
    "sg:province":"AL",
    "sg:tags":[
        "repairing",
        "automobile"
    ],
    "wof:name":"Auto Tech",
    "wof:placetype":"venue"
},
  "geometry": {"coordinates":[-87.585831,33.224025],"type":"Point"}
}