{
  "type": "Feature",
  "properties": {
    "iso:country":"US",
    "sg:address":"285 Co Rd 104",
    "sg:city":"Prattville",
    "sg:classifiers":[
        {
            "category":"Travel",
            "subcategory":"Travel Agent",
            "type":"Entertainment"
        }
    ],
    "sg:phone":"+1 334 365 2421",
    "sg:postcode":"36066",
    "sg:province":"AL",
    "sg:tags":[
        "operator",
        "tour"
    ],
    "wof:name":"Yellow Hammer Tours",
    "wof:placetype":"venue"
},
  "geometry": {"coordinates":[-86.435233,32.565447],"type":"Point"}
}