{
  "type": "Feature",
  "properties": {
    "iso:country":"US",
    "sg:address":"1751 Riverside Dr",
    "sg:city":"Mobile",
    "sg:classifiers":[
        {
            "category":"Food & Beverages",
            "subcategory":"Groceries & Convenience Stores",
            "type":"Retail Goods"
        }
    ],
    "sg:phone":"+1 251 479 9262",
    "sg:postcode":"36605",
    "sg:province":"AL",
    "wof:name":"M J's Express",
    "wof:placetype":"venue"
},
  "geometry": {"coordinates":[-88.080723,30.605042],"type":"Point"}
}