{
  "type": "Feature",
  "properties": {
    "iso:country":"US",
    "sg:address":"1301 Commerce St",
    "sg:city":"Birmingham",
    "sg:classifiers":[
        {
            "category":"Wholesale",
            "subcategory":"Hardware",
            "type":"Manufacturing & Wholesale Goods"
        }
    ],
    "sg:phone":"+1 205 841 9959",
    "sg:postcode":"35217",
    "sg:province":"AL",
    "sg:tags":[
        "equipment",
        "refrigeration",
        "merchandising",
        "w"
    ],
    "wof:name":"Young Sales Inc",
    "wof:placetype":"venue"
},
  "geometry": {"coordinates":[-86.785645,33.566747],"type":"Point"}
}