{
  "type": "Feature",
  "properties": {
    "iso:country":"US",
    "sg:address":"47155 State Rte 59",
    "sg:city":"Bay Minette",
    "sg:classifiers":[
        {
            "category":"Retail",
            "subcategory":"Auto Repair",
            "type":"Services"
        }
    ],
    "sg:phone":"+1 251 937 7104",
    "sg:postcode":"36507",
    "sg:province":"AL",
    "sg:tags":[
        "repairing",
        "automobile"
    ],
    "wof:name":"Parmer's Service Ctr",
    "wof:placetype":"venue"
},
  "geometry": {"coordinates":[-87.78812600000001,30.912478],"type":"Point"}
}