{
  "type": "Feature",
  "properties": {
    "iso:country":"US",
    "sg:address":"1114 Alabama Ave",
    "sg:city":"Selma",
    "sg:classifiers":[
        {
            "category":"Personal",
            "subcategory":"Beauty Salon",
            "type":"Services"
        }
    ],
    "sg:phone":"+1 334 872 2020",
    "sg:postcode":"36703",
    "sg:province":"AL",
    "sg:tags":[
        "shop"
    ],
    "wof:name":"Hair Styles Unlimited",
    "wof:placetype":"venue"
},
  "geometry": {"coordinates":[-87.01896499999999,32.408075],"type":"Point"}
}