{
  "type": "Feature",
  "properties": {
    "addr:full":"1891 Heartline Rd Bankston AL 35542",
    "addr:housenumber":"1891",
    "addr:postcode":"35542",
    "addr:street":"Heartline Rd",
    "iso:country":"US",
    "sg:address":"1891 Heartline Rd",
    "sg:city":"Bankston",
    "sg:classifiers":[
        {
            "category":"Shopping",
            "subcategory":"Clothing, Apparel, & Fashions",
            "type":"Retail Goods"
        }
    ],
    "sg:phone":"+1 205 932 5401",
    "sg:postcode":"35542",
    "sg:province":"AL",
    "sg:tags":[
        "family"
    ],
    "wof:name":"Garys Tees",
    "wof:placetype":"venue"
},
  "geometry": {"coordinates":[-87.69194299999999,33.703741],"type":"Point"}
}