{
  "type": "Feature",
  "properties": {
    "iso:country":"US",
    "sg:address":"1005 Oak Lawn Dr",
    "sg:city":"Birmingham",
    "sg:classifiers":[
        {
            "category":"Building & Trades",
            "subcategory":"Construction",
            "type":"Services"
        }
    ],
    "sg:phone":"+1 205 822 4544",
    "sg:postcode":"35216",
    "sg:province":"AL",
    "sg:tags":[
        "concrete",
        "contractor"
    ],
    "wof:name":"Concrete Construction",
    "wof:placetype":"venue"
},
  "geometry": {"coordinates":[-86.78612,33.439719],"type":"Point"}
}