{
  "type": "Feature",
  "properties": {
    "addr:full":"21033 Logan Dr Mc Calla AL 35111",
    "addr:housenumber":"21033",
    "addr:postcode":"35111",
    "addr:street":"Logan Dr",
    "iso:country":"US",
    "sg:address":"21033 Logan Dr",
    "sg:city":"Mc Calla",
    "sg:classifiers":[
        {
            "category":"Building & Trades",
            "subcategory":"Construction",
            "type":"Services"
        }
    ],
    "sg:phone":"+1 205 477 5343",
    "sg:postcode":"35111",
    "sg:province":"AL",
    "sg:tags":[
        "house"
    ],
    "wof:name":"M&M Builders",
    "wof:placetype":"venue"
},
  "geometry": {"coordinates":[-87.141453,33.285269],"type":"Point"}
}