{
  "type": "Feature",
  "properties": {
    "addr:full":"295 Reeves Ln SW Bessemer AL 35022",
    "addr:housenumber":"295",
    "addr:postcode":"35022",
    "addr:street":"Reeves Ln Sw",
    "iso:country":"US",
    "sg:address":"295 Reeves Ln SW",
    "sg:city":"Bessemer",
    "sg:classifiers":[
        {
            "category":"Shopping",
            "subcategory":"Hobbies, Toys, & Games",
            "type":"Retail Goods"
        }
    ],
    "sg:phone":"+1 205 428 7145",
    "sg:postcode":"35022",
    "sg:province":"AL",
    "sg:tags":[
        "material"
    ],
    "wof:name":"Weaver Ceramics",
    "wof:placetype":"venue"
},
  "geometry": {"coordinates":[-86.980323,33.370235],"type":"Point"}
}