{
  "type": "Feature",
  "properties": {
    "iso:country":"US",
    "sg:address":"1319 Co Rd 77",
    "sg:city":"Lafayette",
    "sg:classifiers":[
        {
            "category":"Retail",
            "subcategory":"Auto Rental",
            "type":"Services"
        }
    ],
    "sg:phone":"+1 334 864 8764",
    "sg:postcode":"36862",
    "sg:province":"AL",
    "sg:tags":[
        "truck",
        "trailer",
        "utility"
    ],
    "wof:name":"U-Haul",
    "wof:placetype":"venue"
},
  "geometry": {"coordinates":[-85.37594,32.846506],"type":"Point"}
}