{
  "type": "Feature",
  "properties": {
    "addr:full":"12196 E State Highway 52 Hartford AL 36344",
    "addr:housenumber":"12196",
    "addr:postcode":"36344",
    "addr:street":"E State Highway 52",
    "iso:country":"US",
    "sg:address":"12196 E State Highway 52",
    "sg:city":"Hartford",
    "sg:classifiers":[
        {
            "category":"Building & Trades",
            "subcategory":"Landscaping Services",
            "type":"Services"
        },
        {
            "category":"Health Services",
            "subcategory":"Nursing And Care Facility",
            "type":"Services"
        },
        {
            "category":"Social Services",
            "subcategory":"Adult Care",
            "type":"Services"
        }
    ],
    "sg:phone":"+1 334 588 2306",
    "sg:postcode":"36344",
    "sg:province":"AL",
    "sg:tags":[
        "living",
        "assisted",
        "rest",
        "elder",
        "homes-institutional",
        "home",
        "aged"
    ],
    "wof:name":"Hartford Retirement Village Inc",
    "wof:placetype":"venue"
},
  "geometry": {"coordinates":[-85.73760299999999,31.09342],"type":"Point"}
}