{
  "type": "Feature",
  "properties": {
    "addr:full":"139 N Tallassee St Dadeville AL 36853",
    "addr:housenumber":"139",
    "addr:postcode":"36853",
    "addr:street":"N Tallassee St",
    "iso:country":"US",
    "sg:address":"139 N Tallassee St",
    "sg:city":"Dadeville",
    "sg:classifiers":[
        {
            "category":"Personal",
            "type":"Services"
        }
    ],
    "sg:phone":"+1 256 825 0535",
    "sg:postcode":"36853",
    "sg:province":"AL",
    "wof:name":"Bahama Tanning Salon",
    "wof:placetype":"venue"
},
  "geometry": {"coordinates":[-85.764596,32.830837],"type":"Point"}
}