{
  "type": "Feature",
  "properties": {
    "iso:country":"US",
    "sg:address":"6870 US Hwy 29",
    "sg:city":"Opelika",
    "sg:classifiers":[
        {
            "category":"Building & Trades",
            "subcategory":"Plumbing",
            "type":"Services"
        }
    ],
    "sg:phone":"+1 334 749 9986",
    "sg:postcode":"36804",
    "sg:province":"AL",
    "sg:tags":[
        "plumbing",
        "contractor"
    ],
    "wof:name":"B & G Backhoe & Trenching Inc",
    "wof:placetype":"venue"
},
  "geometry": {"coordinates":[-85.259131,32.704008],"type":"Point"}
}