{
  "type": "Feature",
  "properties": {
    "addr:full":"1176 Kent Rd Oneonta AL 35121",
    "addr:housenumber":"1176",
    "addr:postcode":"35121",
    "addr:street":"Kent Rd",
    "iso:country":"US",
    "sg:address":"1176 Kent Rd",
    "sg:city":"Oneonta",
    "sg:classifiers":[
        {
            "category":"Professional",
            "subcategory":"Employment Agencies",
            "type":"Services"
        }
    ],
    "sg:phone":"+1 205 466 7461",
    "sg:postcode":"35121",
    "sg:province":"AL",
    "sg:tags":[
        "help",
        "supply"
    ],
    "wof:name":"Fallin Farms",
    "wof:placetype":"venue"
},
  "geometry": {"coordinates":[-86.422737,34.051066],"type":"Point"}
}