{
  "type": "Feature",
  "properties": {
    "iso:country":"US",
    "sg:address":"768 Camp Ney A Ti Rd",
    "sg:city":"Guntersville",
    "sg:classifiers":[
        {
            "category":"Travel",
            "subcategory":"Campground",
            "type":"Entertainment"
        }
    ],
    "sg:phone":"+1 256 582 2437",
    "sg:postcode":"35976",
    "sg:province":"AL",
    "sg:tags":[
        "camp"
    ],
    "sg:website":"www.nayati.org",
    "wof:name":"Alabama Christian Youth Camp",
    "wof:placetype":"venue"
},
  "geometry": {"coordinates":[-86.232854,34.456113],"type":"Point"}
}