{
  "type": "Feature",
  "properties": {
    "iso:country":"US",
    "sg:address":"1961 1st Ave",
    "sg:city":"Opelika",
    "sg:classifiers":[
        {
            "category":"Shopping",
            "subcategory":"Pharmacy",
            "type":"Retail Goods"
        }
    ],
    "sg:phone":"+1 334 745 3881",
    "sg:postcode":"36801",
    "sg:province":"AL",
    "sg:tags":[
        "drug",
        "store"
    ],
    "wof:name":"Adams Pharmacy & Home Care",
    "wof:placetype":"venue"
},
  "geometry": {"coordinates":[-85.403123,32.635245],"type":"Point"}
}