{
  "type": "Feature",
  "properties": {
    "iso:country":"US",
    "sg:address":"1217 Noble St",
    "sg:city":"Anniston",
    "sg:classifiers":[
        {
            "category":"Professional",
            "subcategory":"Lawyer & Legal Services",
            "type":"Services"
        }
    ],
    "sg:phone":"+1 256 237 8815",
    "sg:postcode":"36201",
    "sg:province":"AL",
    "sg:tags":[
        "attorney"
    ],
    "wof:name":"Moeller Law Firm",
    "wof:placetype":"venue"
},
  "geometry": {"coordinates":[-85.82971,33.659967],"type":"Point"}
}