{
  "type": "Feature",
  "properties": {
    "addr:full":"400 Celtic Dr Madison AL 35758",
    "addr:housenumber":"400",
    "addr:postcode":"35758",
    "addr:street":"Celtic Dr",
    "iso:country":"US",
    "sg:address":"400 Celtic Dr",
    "sg:city":"Madison",
    "sg:classifiers":[
        {
            "category":"Building & Trades",
            "subcategory":"Construction",
            "type":"Services"
        }
    ],
    "sg:phone":"+1 256 772 8490",
    "sg:postcode":"35758",
    "sg:province":"AL",
    "sg:tags":[
        "marking",
        "maintenance",
        "parking"
    ],
    "sg:website":"www.ci.madison.al.us",
    "wof:name":"Madison Public Works Dept",
    "wof:placetype":"venue"
},
  "geometry": {"coordinates":[-86.74495899999999,34.682024],"type":"Point"}
}