{
  "type": "Feature",
  "properties": {
    "iso:country":"US",
    "sg:address":"324 Tuscaloosa Ave",
    "sg:city":"Berry",
    "sg:classifiers":[
        {
            "category":"Organizations",
            "subcategory":"Religious Organization",
            "type":"Services"
        }
    ],
    "sg:phone":"+1 205 689 4644",
    "sg:postcode":"35546",
    "sg:province":"AL",
    "sg:tags":[
        "clergy"
    ],
    "wof:name":"E T Sargent",
    "wof:placetype":"venue"
},
  "geometry": {"coordinates":[-87.601079,33.657552],"type":"Point"}
}