{
  "type": "Feature",
  "properties": {
    "addr:full":"637 Maple St Fairfield AL 35064",
    "addr:housenumber":"637",
    "addr:postcode":"35064",
    "addr:street":"Maple St",
    "iso:country":"US",
    "sg:address":"637 Maple St",
    "sg:city":"Fairfield",
    "sg:classifiers":[
        {
            "category":"Building & Trades",
            "subcategory":"Cleaning & Sanitation",
            "type":"Services"
        }
    ],
    "sg:phone":"+1 205 781 3877",
    "sg:postcode":"35064",
    "sg:province":"AL",
    "sg:tags":[
        "maintenance"
    ],
    "wof:name":"Mr Clean Cleaning Svc",
    "wof:placetype":"venue"
},
  "geometry": {"coordinates":[-86.90645000000001,33.489394],"type":"Point"}
}