{
  "type": "Feature",
  "properties": {
    "iso:country":"US",
    "sg:address":"421 Deese Rd",
    "sg:city":"Ozark",
    "sg:classifiers":[
        {
            "category":"Retail",
            "subcategory":"Veterinary Services",
            "type":"Services"
        }
    ],
    "sg:phone":"+1 334 774 5940",
    "sg:postcode":"36360",
    "sg:province":"AL",
    "sg:tags":[
        "veterinarian"
    ],
    "wof:name":"Ozark Veterinary Clinic",
    "wof:placetype":"venue"
},
  "geometry": {"coordinates":[-85.638615,31.439607],"type":"Point"}
}