{
  "type": "Feature",
  "properties": {
    "iso:country":"US",
    "sg:address":"828 12th St N",
    "sg:city":"Bessemer",
    "sg:classifiers":[
        {
            "category":"Shopping",
            "subcategory":"Used Merchandise",
            "type":"Retail Goods"
        }
    ],
    "sg:phone":"+1 205 428 6167",
    "sg:postcode":"35020",
    "sg:province":"AL",
    "wof:name":"Veterans Thrift Store",
    "wof:placetype":"venue"
},
  "geometry": {"coordinates":[-86.966455,33.398312],"type":"Point"}
}