{
  "type": "Feature",
  "properties": {
    "iso:country":"US",
    "sg:address":"3508 N Jackson Hwy",
    "sg:city":"Sheffield",
    "sg:classifiers":[
        {
            "category":"Manufacturing",
            "subcategory":"Signs",
            "type":"Manufacturing & Wholesale Goods"
        }
    ],
    "sg:phone":"+1 256 383 3115",
    "sg:postcode":"35660",
    "sg:province":"AL",
    "sg:tags":[
        "advertising",
        "specialty"
    ],
    "wof:name":"Tri State Signs & Label",
    "wof:placetype":"venue"
},
  "geometry": {"coordinates":[-87.674984,34.767427],"type":"Point"}
}