{
  "type": "Feature",
  "properties": {
    "addr:full":"3508 N Jackson Hwy Sheffield AL 35660",
    "addr:housenumber":"3508",
    "addr:postcode":"35660",
    "addr:street":"N Jackson Hwy",
    "iso:country":"US",
    "sg:address":"3508 N Jackson Hwy",
    "sg:city":"Sheffield",
    "sg:classifiers":[
        {
            "category":"Manufacturing",
            "subcategory":"Signs",
            "type":"Manufacturing & Wholesale Goods"
        }
    ],
    "sg:phone":"+1 256 383 3115",
    "sg:postcode":"35660",
    "sg:province":"AL",
    "sg:tags":[
        "advertising",
        "specialty"
    ],
    "wof:name":"Tri State Signs & Label",
    "wof:placetype":"venue"
},
  "geometry": {"coordinates":[-87.67498399999999,34.767427],"type":"Point"}
}