{
  "type": "Feature",
  "properties": {
    "iso:country":"US",
    "sg:address":"160 Augusta Trl",
    "sg:city":"Cullman",
    "sg:classifiers":[
        {
            "category":"Recreation",
            "type":"Entertainment"
        }
    ],
    "sg:phone":"+1 256 739 0711",
    "sg:postcode":"35057",
    "sg:province":"AL",
    "sg:tags":[
        "course",
        "golf"
    ],
    "wof:name":"Terri Pines Country Club",
    "wof:placetype":"venue"
},
  "geometry": {"coordinates":[-86.896342,34.227861],"type":"Point"}
}