{
  "type": "Feature",
  "properties": {
    "iso:country":"US",
    "sg:address":"10887 US Hwy 98",
    "sg:city":"Fairhope",
    "sg:classifiers":[
        {
            "category":"Professional",
            "type":"Services"
        }
    ],
    "sg:phone":"+1 251 928 4444",
    "sg:postcode":"36532",
    "sg:province":"AL",
    "wof:name":"Comtech Services",
    "wof:placetype":"venue"
},
  "geometry": {"coordinates":[-87.831766,30.42054],"type":"Point"}
}