{
  "type": "Feature",
  "properties": {
    "addr:full":"296 Cahaba Valley Pkwy N Pelham AL 35124",
    "addr:housenumber":"296",
    "addr:postcode":"35124",
    "addr:street":"Cahaba Valley Pkwy N",
    "iso:country":"US",
    "sg:address":"296 Cahaba Valley Pkwy N",
    "sg:city":"Pelham",
    "sg:classifiers":[
        {
            "category":"Building & Trades",
            "subcategory":"Electrical",
            "type":"Services"
        }
    ],
    "sg:phone":"+1 205 733 8848",
    "sg:postcode":"35124",
    "sg:province":"AL",
    "sg:tags":[
        "electrical",
        "electric",
        "contractor"
    ],
    "wof:name":"Wayne J Griffin Electric Inc",
    "wof:placetype":"venue"
},
  "geometry": {"coordinates":[-86.784774,33.343174],"type":"Point"}
}