{
  "type": "Feature",
  "properties": {
    "addr:full":"224 7th St S Clanton AL 35045",
    "addr:housenumber":"224",
    "addr:postcode":"35045",
    "addr:street":"7Th St S",
    "iso:country":"US",
    "sg:address":"224 7th St S",
    "sg:city":"Clanton",
    "sg:classifiers":[
        {
            "category":"Banks & Credit Unions",
            "subcategory":"Bank",
            "type":"Services"
        }
    ],
    "sg:phone":"+1 205 755 0390",
    "sg:postcode":"35045",
    "sg:province":"AL",
    "sg:tags":[
        "financing"
    ],
    "wof:name":"Key Finance Co Inc",
    "wof:placetype":"venue"
},
  "geometry": {"coordinates":[-86.629075,32.835527],"type":"Point"}
}