{
  "type": "Feature",
  "properties": {
    "addr:full":"1024 Co Rd 351 Crane Hill AL 35053",
    "addr:housenumber":"1024;351",
    "addr:postcode":"35053",
    "addr:street":"Co Rd;Crane Hill",
    "iso:country":"US",
    "sg:address":"1024 Co Rd 351",
    "sg:city":"Crane Hill",
    "sg:classifiers":[
        {
            "category":"Farming",
            "subcategory":"Livestock Farm",
            "type":"Manufacturing & Wholesale Goods"
        }
    ],
    "sg:phone":"+1 256 747 6402",
    "sg:postcode":"35053",
    "sg:province":"AL",
    "sg:tags":[
        "beef",
        "feedlot",
        "cattle"
    ],
    "wof:name":"Kenneth Phillips",
    "wof:placetype":"venue"
},
  "geometry": {"coordinates":[-87.06438799999999,34.081716],"type":"Point"}
}