{
  "type": "Feature",
  "properties": {
    "iso:country":"US",
    "sg:address":"14 Bolton Dr",
    "sg:city":"Montgomery",
    "sg:classifiers":[
        {
            "category":"Retail",
            "subcategory":"Auto Repair",
            "type":"Services"
        }
    ],
    "sg:phone":"+1 334 284 6452",
    "sg:postcode":"36105",
    "sg:province":"AL",
    "sg:tags":[
        "general"
    ],
    "wof:name":"Means Auto Repair",
    "wof:placetype":"venue"
},
  "geometry": {"coordinates":[-86.307593,32.319481],"type":"Point"}
}