{
  "type": "Feature",
  "properties": {
    "addr:full":"2629 2nd Ave N Birmingham AL 35203",
    "addr:housenumber":"2629",
    "addr:postcode":"35203",
    "addr:street":"2Nd Ave N",
    "iso:country":"US",
    "sg:address":"2629 2nd Ave N",
    "sg:city":"Birmingham",
    "sg:classifiers":[
        {
            "category":"Retail",
            "subcategory":"Repair Shop",
            "type":"Services"
        }
    ],
    "sg:phone":"+1 205 251 9233",
    "sg:postcode":"35203",
    "sg:province":"AL",
    "wof:name":"Wade Furniture Refinishing",
    "wof:placetype":"venue"
},
  "geometry": {"coordinates":[-86.796999,33.51971],"type":"Point"}
}