{
  "type": "Feature",
  "properties": {
    "iso:country":"US",
    "sg:address":"108 S 5th St",
    "sg:city":"Gadsden",
    "sg:classifiers":[
        {
            "category":"Insurance",
            "subcategory":"Insurance Agent",
            "type":"Services"
        }
    ],
    "sg:phone":"+1 256 546 2811",
    "sg:postcode":"35901",
    "sg:province":"AL",
    "sg:website":"www.kerrywilson.com",
    "wof:name":"Kerry Wilson Insurance",
    "wof:placetype":"venue"
},
  "geometry": {"coordinates":[-86.005152,34.01285],"type":"Point"}
}