{
  "type": "Feature",
  "properties": {
    "addr:full":"9695 Fairway Dr Foley AL 36535",
    "addr:housenumber":"9695",
    "addr:postcode":"36535",
    "addr:street":"Fairway Dr",
    "iso:country":"US",
    "sg:address":"9695 Fairway Dr",
    "sg:city":"Foley",
    "sg:classifiers":[
        {
            "category":"Travel",
            "subcategory":"Travel Agent",
            "type":"Entertainment"
        }
    ],
    "sg:phone":"+1 251 955 1353",
    "sg:postcode":"36535",
    "sg:province":"AL",
    "sg:tags":[
        "agency"
    ],
    "wof:name":"Cruizin Co",
    "wof:placetype":"venue"
},
  "geometry": {"coordinates":[-87.644651,30.369183],"type":"Point"}
}