{
  "type": "Feature",
  "properties": {
    "addr:full":"3605 8th Ave SW Huntsville AL 35805",
    "addr:housenumber":"3605",
    "addr:postcode":"35805",
    "addr:street":"8Th Ave Sw",
    "iso:country":"US",
    "sg:address":"3605 8th Ave SW",
    "sg:city":"Huntsville",
    "sg:classifiers":[
        {
            "category":"Building & Trades",
            "subcategory":"Electrical",
            "type":"Services"
        }
    ],
    "sg:phone":"+1 256 536 4375",
    "sg:postcode":"35805",
    "sg:province":"AL",
    "sg:tags":[
        "electric",
        "contractor"
    ],
    "sg:website":"www.stewartelectricinc.com",
    "wof:name":"Stewart Electric Co",
    "wof:placetype":"venue"
},
  "geometry": {"coordinates":[-86.615866,34.716825],"type":"Point"}
}