{
  "type": "Feature",
  "properties": {
    "iso:country":"US",
    "sg:address":"501 S 6th St",
    "sg:city":"Lanett",
    "sg:classifiers":[
        {
            "category":"Organizations",
            "subcategory":"Professional Association",
            "type":"Services"
        }
    ],
    "sg:phone":"+1 334 644 2200",
    "sg:postcode":"36863",
    "sg:province":"AL",
    "wof:name":"Alcoholics Anonymous",
    "wof:placetype":"venue"
},
  "geometry": {"coordinates":[-85.194267,32.864382],"type":"Point"}
}