{
  "type": "Feature",
  "properties": {
    "addr:full":"3312 Huntsville Rd Florence AL 35630",
    "addr:housenumber":"3312",
    "addr:postcode":"35630",
    "addr:street":"Huntsville Rd",
    "iso:country":"US",
    "sg:address":"3312 Huntsville Rd",
    "sg:city":"Florence",
    "sg:classifiers":[
        {
            "category":"Wholesale",
            "subcategory":"Fruits & Vegetables",
            "type":"Manufacturing & Wholesale Goods"
        }
    ],
    "sg:phone":"+1 256 766 5891",
    "sg:postcode":"35630",
    "sg:province":"AL",
    "wof:name":"O K Produce",
    "wof:placetype":"venue"
},
  "geometry": {"coordinates":[-87.637612,34.81723],"type":"Point"}
}