{
  "type": "Feature",
  "properties": {
    "iso:country":"US",
    "sg:address":"300 41st St S",
    "sg:city":"Birmingham",
    "sg:classifiers":[
        {
            "category":"Food & Beverages",
            "subcategory":"Groceries & Convenience Stores",
            "type":"Retail Goods"
        },
        {
            "category":"Autos & Motor Vehicles",
            "subcategory":"Fuel & Gas Station",
            "type":"Retail Goods"
        }
    ],
    "sg:phone":"+1 205 595 1405",
    "sg:postcode":"35222",
    "sg:province":"AL",
    "sg:tags":[
        "oil"
    ],
    "wof:name":"Amoco Food Shop 231",
    "wof:placetype":"venue"
},
  "geometry": {"coordinates":[-86.77354699999999,33.523232],"type":"Point"}
}