{
  "type": "Feature",
  "properties": {
    "addr:full":"827 Cadillac Ave Dauphin Island AL 36528",
    "addr:housenumber":"827",
    "addr:postcode":"36528",
    "addr:street":"Cadillac Ave",
    "iso:country":"US",
    "sg:address":"827 Cadillac Ave",
    "sg:city":"Dauphin Island",
    "sg:classifiers":[
        {
            "category":"Organizations",
            "subcategory":"Religious Organization",
            "type":"Services"
        }
    ],
    "sg:phone":"+1 251 861 2352",
    "sg:postcode":"36528",
    "sg:province":"AL",
    "sg:tags":[
        "church"
    ],
    "wof:name":"St Edmund By The Sea Church",
    "wof:placetype":"venue"
},
  "geometry": {"coordinates":[-88.10941800000001,30.255272],"type":"Point"}
}