{
  "type": "Feature",
  "properties": {
    "addr:full":"203 E Ross St Jackson AL 36545",
    "addr:housenumber":"203",
    "addr:postcode":"36545",
    "addr:street":"E Ross St",
    "iso:country":"US",
    "sg:address":"203 E Ross St",
    "sg:city":"Jackson",
    "sg:classifiers":[
        {
            "category":"Retail",
            "subcategory":"Funeral Services",
            "type":"Services"
        }
    ],
    "sg:phone":"+1 251 246 3168",
    "sg:postcode":"36545",
    "sg:province":"AL",
    "sg:tags":[
        "director"
    ],
    "wof:name":"Jackson Funeral Home",
    "wof:placetype":"venue"
},
  "geometry": {"coordinates":[-87.89481600000001,31.499066],"type":"Point"}
}