{
  "type": "Feature",
  "properties": {
    "iso:country":"US",
    "sg:address":"3233 Executive Park Cir",
    "sg:city":"Mobile",
    "sg:classifiers":[
        {
            "category":"Autos & Motor Vehicles",
            "subcategory":"Automobile Sales",
            "type":"Retail Goods"
        },
        {
            "category":"Professional",
            "subcategory":"Research",
            "type":"Services"
        }
    ],
    "sg:phone":"+1 251 472 8300",
    "sg:postcode":"36606",
    "sg:province":"AL",
    "sg:tags":[
        "car",
        "dealer",
        "noncommercial",
        "organization"
    ],
    "sg:website":"www.discoveryalliance.com",
    "wof:name":"Discovery Alliance Inc",
    "wof:placetype":"venue"
},
  "geometry": {"coordinates":[-88.122056,30.663314],"type":"Point"}
}