{
  "type": "Feature",
  "properties": {
    "addr:full":"129 Wheeler Rd Camden AL 36726",
    "addr:housenumber":"129",
    "addr:postcode":"36726",
    "addr:street":"Wheeler Rd",
    "iso:country":"US",
    "sg:address":"129 Wheeler Rd",
    "sg:city":"Camden",
    "sg:classifiers":[
        {
            "category":"Social Services",
            "subcategory":"Child Care",
            "type":"Services"
        }
    ],
    "sg:phone":"+1 334 682 5936",
    "sg:postcode":"36726",
    "sg:province":"AL",
    "wof:name":"Bright Eyes Day Care",
    "wof:placetype":"venue"
},
  "geometry": {"coordinates":[-87.367558,31.998606],"type":"Point"}
}