{
  "type": "Feature",
  "properties": {
    "addr:full":"101 N Memorial Dr Prattville AL 36067",
    "addr:housenumber":"101",
    "addr:postcode":"36067",
    "addr:street":"N Memorial Dr",
    "iso:country":"US",
    "sg:address":"101 N Memorial Dr",
    "sg:city":"Prattville",
    "sg:classifiers":[
        {
            "category":"Autos & Motor Vehicles",
            "subcategory":"Fuel & Gas Station",
            "type":"Retail Goods"
        }
    ],
    "sg:phone":"+1 334 365 2362",
    "sg:postcode":"36067",
    "sg:province":"AL",
    "sg:tags":[
        "oil"
    ],
    "wof:name":"Herrod's Chevron",
    "wof:placetype":"venue"
},
  "geometry": {"coordinates":[-86.450942,32.464683],"type":"Point"}
}