{
  "type": "Feature",
  "properties": {
    "iso:country":"US",
    "sg:address":"3051 Busby Rd",
    "sg:city":"Mobile",
    "sg:classifiers":[
        {
            "category":"Building & Trades",
            "subcategory":"Construction",
            "type":"Services"
        }
    ],
    "sg:phone":"+1 251 633 5603",
    "sg:postcode":"36695",
    "sg:province":"AL",
    "sg:tags":[
        "contractor"
    ],
    "wof:name":"Busbys Home Maintenance",
    "wof:placetype":"venue"
},
  "geometry": {"coordinates":[-88.326008,30.629046],"type":"Point"}
}