{
  "type": "Feature",
  "properties": {
    "iso:country":"US",
    "sg:address":"11281 Co Rd 35",
    "sg:city":"Fayette",
    "sg:classifiers":[
        {
            "category":"Organizations",
            "subcategory":"Religious Organization",
            "type":"Services"
        }
    ],
    "sg:phone":"+1 205 932 4699",
    "sg:postcode":"35555",
    "sg:province":"AL",
    "sg:tags":[
        "church"
    ],
    "wof:name":"Unity Grove Baptist Church",
    "wof:placetype":"venue"
},
  "geometry": {"coordinates":[-87.740309,33.558273],"type":"Point"}
}