{
  "type": "Feature",
  "properties": {
    "iso:country":"US",
    "sg:address":"141 First St",
    "sg:city":"Prattville",
    "sg:classifiers":[
        {
            "category":"Manufacturing",
            "subcategory":"Printing",
            "type":"Manufacturing & Wholesale Goods"
        }
    ],
    "sg:phone":"+1 334 491 6397",
    "sg:postcode":"36067",
    "sg:province":"AL",
    "sg:tags":[
        "newspaper"
    ],
    "wof:name":"Prattville Autauga Gazette",
    "wof:placetype":"venue"
},
  "geometry": {"coordinates":[-86.47266500000001,32.458283],"type":"Point"}
}