{
  "type": "Feature",
  "properties": {
    "addr:full":"200 N Royal St Mobile AL 36602",
    "addr:housenumber":"200",
    "addr:postcode":"36602",
    "addr:street":"N Royal St",
    "iso:country":"US",
    "sg:address":"200 N Royal St",
    "sg:city":"Mobile",
    "sg:classifiers":[
        {
            "category":"Government",
            "subcategory":"Police Station",
            "type":"Public Place"
        }
    ],
    "sg:phone":"+1 251 438 3674",
    "sg:postcode":"36602",
    "sg:province":"AL",
    "sg:tags":[
        "federal"
    ],
    "wof:name":"Federal Bureau-Investigation",
    "wof:placetype":"venue"
},
  "geometry": {"coordinates":[-88.04259399999999,30.696371],"type":"Point"}
}