{
  "type": "Feature",
  "properties": {
    "iso:country":"US",
    "sg:address":"616 Church St NE",
    "sg:city":"Decatur",
    "sg:classifiers":[
        {
            "category":"Restaurant",
            "type":"Food & Drink"
        }
    ],
    "sg:phone":"+1 256 353 2061",
    "sg:postcode":"35601",
    "sg:province":"AL",
    "sg:tags":[
        "eating"
    ],
    "wof:name":"Melvin Company",
    "wof:placetype":"venue"
},
  "geometry": {"coordinates":[-86.9769,34.60816],"type":"Point"}
}