{
  "type": "Feature",
  "properties": {
    "addr:full":"6500 Amber Hills Rd Trussville AL 35173",
    "addr:housenumber":"6500",
    "addr:postcode":"35173",
    "addr:street":"Amber Hills Rd",
    "iso:country":"US",
    "sg:address":"6500 Amber Hills Rd",
    "sg:city":"Trussville",
    "sg:classifiers":[
        {
            "category":"Manufacturing",
            "subcategory":"Glass & Minerals",
            "type":"Manufacturing & Wholesale Goods"
        }
    ],
    "sg:phone":"+1 205 951 7274",
    "sg:postcode":"35173",
    "sg:province":"AL",
    "sg:tags":[
        "ready",
        "concrete",
        "mfg"
    ],
    "wof:name":"Shelby Concrete Inc",
    "wof:placetype":"venue"
},
  "geometry": {"coordinates":[-86.612402,33.5582],"type":"Point"}
}