{
  "type": "Feature",
  "properties": {
    "iso:country":"US",
    "sg:address":"454 Stillwell Dr",
    "sg:city":"Union Grove",
    "sg:classifiers":[
        {
            "category":"Building & Trades",
            "subcategory":"Construction",
            "type":"Services"
        }
    ],
    "sg:phone":"+1 256 498 3532",
    "sg:postcode":"35175",
    "sg:province":"AL",
    "sg:tags":[
        "new",
        "industrial",
        "renovation",
        "for"
    ],
    "wof:name":"Native American Contracting",
    "wof:placetype":"venue"
},
  "geometry": {"coordinates":[-86.514372,34.43762],"type":"Point"}
}