{
  "type": "Feature",
  "properties": {
    "iso:country":"US",
    "sg:address":"3251 Browns Rd",
    "sg:city":"Millbrook",
    "sg:classifiers":[
        {
            "category":"Organizations",
            "subcategory":"Religious Organization",
            "type":"Services"
        }
    ],
    "sg:phone":"+1 334 285 7509",
    "sg:postcode":"36054",
    "sg:province":"AL",
    "sg:tags":[
        "church"
    ],
    "wof:name":"Millbrook Church of Nazarene",
    "wof:placetype":"venue"
},
  "geometry": {"coordinates":[-86.370406,32.503641],"type":"Point"}
}