{
  "type": "Feature",
  "properties": {
    "iso:country":"US",
    "sg:address":"1409 Kathy Ln SW",
    "sg:city":"Decatur",
    "sg:classifiers":[
        {
            "category":"Food & Beverages",
            "subcategory":"Specialty",
            "type":"Retail Goods"
        }
    ],
    "sg:phone":"+1 256 353 6744",
    "sg:postcode":"35601",
    "sg:province":"AL",
    "wof:name":"Shaklee Distributor",
    "wof:placetype":"venue"
},
  "geometry": {"coordinates":[-87.02322100000001,34.584255],"type":"Point"}
}