{
  "type": "Feature",
  "properties": {
    "addr:full":"303 Stonecroft Cir Helena AL 35080",
    "addr:housenumber":"303",
    "addr:postcode":"35080",
    "addr:street":"Stonecroft Cir",
    "iso:country":"US",
    "sg:address":"303 Stonecroft Cir",
    "sg:city":"Helena",
    "sg:classifiers":[
        {
            "category":"Food & Beverages",
            "subcategory":"Groceries & Convenience Stores",
            "type":"Retail Goods"
        }
    ],
    "sg:phone":"+1 205 664 4775",
    "sg:postcode":"35080",
    "sg:province":"AL",
    "wof:name":"W H Johnson Corporation",
    "wof:placetype":"venue"
},
  "geometry": {"coordinates":[-86.85782500000001,33.275975],"type":"Point"}
}