{
  "type": "Feature",
  "properties": {
    "iso:country":"US",
    "sg:address":"303 Stonecroft Cir",
    "sg:city":"Helena",
    "sg:classifiers":[
        {
            "category":"Food & Beverages",
            "subcategory":"Groceries & Convenience Stores",
            "type":"Retail Goods"
        }
    ],
    "sg:phone":"+1 205 664 4775",
    "sg:postcode":"35080",
    "sg:province":"AL",
    "wof:name":"W H Johnson Corporation",
    "wof:placetype":"venue"
},
  "geometry": {"coordinates":[-86.857825,33.275975],"type":"Point"}
}