{
  "type": "Feature",
  "properties": {
    "iso:country":"US",
    "sg:address":"461 US Hwy 278",
    "sg:city":"Cullman",
    "sg:classifiers":[
        {
            "category":"Retail",
            "subcategory":"Funeral Services",
            "type":"Services"
        }
    ],
    "sg:phone":"+1 256 734 3144",
    "sg:postcode":"35055",
    "sg:province":"AL",
    "sg:tags":[
        "director",
        "home"
    ],
    "wof:name":"Williams-Mc Cracken Funeral HM",
    "wof:placetype":"venue"
},
  "geometry": {"coordinates":[-86.795197,34.182978],"type":"Point"}
}