{
  "type": "Feature",
  "properties": {
    "addr:full":"3847 Riverview Dr Birmingham AL 35243",
    "addr:housenumber":"3847",
    "addr:postcode":"35243",
    "addr:street":"Riverview Dr",
    "iso:country":"US",
    "sg:address":"3847 Riverview Dr",
    "sg:city":"Birmingham",
    "sg:classifiers":[
        {
            "category":"Professional",
            "subcategory":"Accounting & Tax Preparation",
            "type":"Services"
        }
    ],
    "sg:phone":"+1 205 967 3311",
    "sg:postcode":"35243",
    "sg:province":"AL",
    "wof:name":"Stanford Lowry CPA",
    "wof:placetype":"venue"
},
  "geometry": {"coordinates":[-86.70984900000001,33.477029],"type":"Point"}
}