{
  "type": "Feature",
  "properties": {
    "iso:country":"US",
    "sg:address":"268 Co Rd 623",
    "sg:city":"Enterprise",
    "sg:phone":"+1 334 347 4635",
    "sg:postcode":"36330",
    "sg:province":"AL",
    "sg:tags":[
        "farm",
        "corn",
        "beef",
        "feedlot",
        "cattle"
    ],
    "wof:name":"Lazy H Farm",
    "wof:placetype":"venue"
},
  "geometry": {"coordinates":[-85.87817800000001,31.283],"type":"Point"}
}