{
  "type": "Feature",
  "properties": {
    "iso:country":"US",
    "sg:address":"1790 Bethel Rd",
    "sg:city":"Decatur",
    "sg:classifiers":[
        {
            "category":"Retail",
            "subcategory":"Portrait Studio",
            "type":"Services"
        }
    ],
    "sg:phone":"+1 256 340 3637",
    "sg:postcode":"35603",
    "sg:province":"AL",
    "sg:tags":[
        "photographer",
        "photo"
    ],
    "wof:name":"Southern Touch Family Portrait",
    "wof:placetype":"venue"
},
  "geometry": {"coordinates":[-86.89518099999999,34.517181],"type":"Point"}
}