{
  "type": "Feature",
  "properties": {
    "iso:country":"US",
    "sg:address":"3213 Dauphin St",
    "sg:city":"Mobile",
    "sg:classifiers":[
        {
            "category":"Health Services",
            "subcategory":"Doctor",
            "type":"Services"
        }
    ],
    "sg:phone":"+1 251 479 9538",
    "sg:postcode":"36606",
    "sg:province":"AL",
    "sg:tags":[
        "physician",
        "surgeon"
    ],
    "wof:name":"Dermatology Center",
    "wof:placetype":"venue"
},
  "geometry": {"coordinates":[-88.11888999999999,30.689496],"type":"Point"}
}