{
  "type": "Feature",
  "properties": {
    "addr:full":"1110 Poplar Ridge Rd New Hope AL 35760",
    "addr:housenumber":"1110",
    "addr:postcode":"35760",
    "addr:street":"Poplar Ridge Rd New",
    "iso:country":"US",
    "sg:address":"1110 Poplar Ridge Rd",
    "sg:city":"New Hope",
    "sg:classifiers":[
        {
            "category":"Farming",
            "subcategory":"Livestock Farm",
            "type":"Manufacturing & Wholesale Goods"
        }
    ],
    "sg:phone":"+1 256 723 4159",
    "sg:postcode":"35760",
    "sg:province":"AL",
    "sg:tags":[
        "beef",
        "feedlot",
        "cattle"
    ],
    "wof:name":"Charles Moon",
    "wof:placetype":"venue"
},
  "geometry": {"coordinates":[-86.365177,34.578741],"type":"Point"}
}