{
  "type": "Feature",
  "properties": {
    "iso:country":"US",
    "sg:address":"3808 Mcfarland Blvd E",
    "sg:city":"Tuscaloosa",
    "sg:classifiers":[
        {
            "category":"Restaurant",
            "type":"Food & Drink"
        }
    ],
    "sg:menulink":"http://www.allmenus.com/al/tuscaloosa/166706-burger-king/menu/",
    "sg:phone":"+1 205 553 3616",
    "sg:postcode":"35405",
    "sg:province":"AL",
    "sg:tags":[
        "burger",
        "american"
    ],
    "wof:name":"Burger King",
    "wof:placetype":"venue"
},
  "geometry": {"coordinates":[-87.52478000000001,33.17372],"type":"Point"}
}