{
  "type": "Feature",
  "properties": {
    "addr:full":"2809 Gus Grissom Dr NW Huntsville AL 35810",
    "addr:housenumber":"2809",
    "addr:postcode":"35810",
    "addr:street":"Gus Grissom Dr Nw",
    "iso:country":"US",
    "sg:address":"2809 Gus Grissom Dr NW",
    "sg:city":"Huntsville",
    "sg:classifiers":[
        {
            "category":"Building & Trades",
            "subcategory":"Cleaning & Sanitation",
            "type":"Services"
        }
    ],
    "sg:phone":"+1 256 852 3891",
    "sg:postcode":"35810",
    "sg:province":"AL",
    "sg:tags":[
        "janitor"
    ],
    "wof:name":"Niebo's Commercial Janitor",
    "wof:placetype":"venue"
},
  "geometry": {"coordinates":[-86.61624399999999,34.754137],"type":"Point"}
}