{
  "type": "Feature",
  "properties": {
    "addr:full":"7401 Crestwood Blvd Birmingham AL 35210",
    "addr:housenumber":"7401",
    "addr:postcode":"35210",
    "addr:street":"Crestwood Blvd",
    "iso:country":"US",
    "sg:address":"7401 Crestwood Blvd",
    "sg:city":"Birmingham",
    "sg:classifiers":[
        {
            "category":"Restaurant",
            "type":"Food & Drink"
        }
    ],
    "sg:menulink":"http://www.allmenus.com/al/birmingham/8510-hooters/menu/",
    "sg:phone":"+1 205 591 4668",
    "sg:postcode":"35210",
    "sg:province":"AL",
    "sg:tags":[
        "american",
        "wing"
    ],
    "wof:name":"Hooters",
    "wof:placetype":"venue"
},
  "geometry": {"coordinates":[-86.72354199999999,33.530197],"type":"Point"}
}