{
  "type": "Feature",
  "properties": {
    "iso:country":"US",
    "sg:address":"2212 Old Big Cove Rd",
    "sg:city":"Owens Cross Roads",
    "sg:classifiers":[
        {
            "category":"Professional",
            "subcategory":"Business Services",
            "type":"Services"
        }
    ],
    "sg:phone":"+1 256 518 9336",
    "sg:postcode":"35763",
    "sg:province":"AL",
    "wof:name":"Mables Accessory",
    "wof:placetype":"venue"
},
  "geometry": {"coordinates":[-86.496042,34.622768],"type":"Point"}
}