{
  "type": "Feature",
  "properties": {
    "addr:full":"102 N Leland Dr Florence AL 35630",
    "addr:housenumber":"102",
    "addr:postcode":"35630",
    "addr:street":"N Leland Dr",
    "iso:country":"US",
    "sg:address":"102 N Leland Dr",
    "sg:city":"Florence",
    "sg:classifiers":[
        {
            "category":"Organizations",
            "subcategory":"Religious Organization",
            "type":"Services"
        }
    ],
    "sg:phone":"+1 256 766 4514",
    "sg:postcode":"35630",
    "sg:province":"AL",
    "wof:name":"Eastwood Church Of Christ",
    "wof:placetype":"venue"
},
  "geometry": {"coordinates":[-87.629012,34.821587],"type":"Point"}
}