{
  "type": "Feature",
  "properties": {
    "iso:country":"US",
    "sg:address":"425 1st St SW",
    "sg:city":"Fayette",
    "sg:classifiers":[
        {
            "category":"Organizations",
            "subcategory":"Religious Organization",
            "type":"Services"
        }
    ],
    "sg:phone":"+1 205 932 4517",
    "sg:postcode":"35555",
    "sg:province":"AL",
    "sg:tags":[
        "church"
    ],
    "wof:name":"St James CME Church",
    "wof:placetype":"venue"
},
  "geometry": {"coordinates":[-87.836702,33.684556],"type":"Point"}
}