{
  "type": "Feature",
  "properties": {
    "addr:full":"511 Carroll Ave S Russellville AL 35653",
    "addr:housenumber":"511",
    "addr:postcode":"35653",
    "addr:street":"Carroll Ave S Russellville",
    "iso:country":"US",
    "sg:address":"511 Carroll Ave S",
    "sg:city":"Russellville",
    "sg:classifiers":[
        {
            "category":"Railroad",
            "type":"Transportation"
        }
    ],
    "sg:phone":"+1 205 486 2414",
    "sg:postcode":"35653",
    "sg:province":"AL",
    "sg:tags":[
        "operator",
        "line"
    ],
    "wof:name":"Southern Railway",
    "wof:placetype":"venue"
},
  "geometry": {"coordinates":[-87.73029699999999,34.5002],"type":"Point"}
}