{
  "type": "Feature",
  "properties": {
    "iso:country":"US",
    "sg:address":"3070 Green Valley Rd",
    "sg:city":"Birmingham",
    "sg:classifiers":[
        {
            "category":"Professional",
            "subcategory":"Management & Consulting",
            "type":"Services"
        }
    ],
    "sg:phone":"+1 205 271 1487",
    "sg:postcode":"35243",
    "sg:province":"AL",
    "sg:tags":[
        "consultant",
        "energy",
        "conservation"
    ],
    "wof:name":"Horton Controls Inc",
    "wof:placetype":"venue"
},
  "geometry": {"coordinates":[-86.73563799999999,33.46037],"type":"Point"}
}