{
  "type": "Feature",
  "properties": {
    "addr:full":"801 Davison Ave Muscle Shoals AL 35661",
    "addr:housenumber":"801",
    "addr:postcode":"35661",
    "addr:street":"Davison Ave",
    "iso:country":"US",
    "sg:address":"801 Davison Ave",
    "sg:city":"Muscle Shoals",
    "sg:classifiers":[
        {
            "category":"Building & Trades",
            "subcategory":"Pest Control",
            "type":"Services"
        }
    ],
    "sg:phone":"+1 256 381 1311",
    "sg:postcode":"35661",
    "sg:province":"AL",
    "wof:name":"Bugbusters",
    "wof:placetype":"venue"
},
  "geometry": {"coordinates":[-87.659689,34.747979],"type":"Point"}
}