{
  "type": "Feature",
  "properties": {
    "iso:country":"US",
    "sg:address":"80 Johnson Dr",
    "sg:city":"Chelsea",
    "sg:classifiers":[
        {
            "category":"Shopping",
            "subcategory":"Discount & Variety Stores",
            "type":"Retail Goods"
        }
    ],
    "sg:phone":"+1 205 678 8197",
    "sg:postcode":"35043",
    "sg:province":"AL",
    "wof:name":"J & J Junk Sale",
    "wof:placetype":"venue"
},
  "geometry": {"coordinates":[-86.610782,33.346328],"type":"Point"}
}