{
  "type": "Feature",
  "properties": {
    "iso:country":"US",
    "sg:address":"503 3rd St SE",
    "sg:city":"Fayette",
    "sg:classifiers":[
        {
            "category":"Home & Garden",
            "subcategory":"Building Materials",
            "type":"Retail Goods"
        }
    ],
    "sg:phone":"+1 205 932 4110",
    "sg:postcode":"35555",
    "sg:province":"AL",
    "sg:tags":[
        "lumber"
    ],
    "wof:name":"Arthur Lumber Co",
    "wof:placetype":"venue"
},
  "geometry": {"coordinates":[-87.823702,33.681892],"type":"Point"}
}