{
  "type": "Feature",
  "properties": {
    "iso:country":"US",
    "sg:address":"13 Avenue W",
    "sg:city":"Birmingham",
    "sg:classifiers":[
        {
            "category":"Organizations",
            "subcategory":"Religious Organization",
            "type":"Services"
        }
    ],
    "sg:phone":"+1 205 798 6981",
    "sg:postcode":"35214",
    "sg:province":"AL",
    "sg:tags":[
        "church"
    ],
    "wof:name":"Israel Missionary Communiyy",
    "wof:placetype":"venue"
},
  "geometry": {"coordinates":[-86.878778,33.535653],"type":"Point"}
}