{
  "type": "Feature",
  "properties": {
    "iso:country":"US",
    "sg:address":"7 Grove St",
    "sg:city":"Headland",
    "sg:classifiers":[
        {
            "category":"Shopping",
            "subcategory":"Jewelry",
            "type":"Retail Goods"
        }
    ],
    "sg:phone":"+1 334 693 9795",
    "sg:postcode":"36345",
    "sg:province":"AL",
    "sg:tags":[
        "jeweler"
    ],
    "wof:name":"John's Jewelry",
    "wof:placetype":"venue"
},
  "geometry": {"coordinates":[-85.341904,31.352712],"type":"Point"}
}