{
  "type": "Feature",
  "properties": {
    "iso:country":"US",
    "sg:address":"17008 US Hwy 98 Alt",
    "sg:city":"Point Clear",
    "sg:classifiers":[
        {
            "category":"Government",
            "subcategory":"Post Office",
            "type":"Public Place"
        }
    ],
    "sg:phone":"+1 251 928 5132",
    "sg:postcode":"36532",
    "sg:province":"AL",
    "sg:tags":[
        "postal",
        "us"
    ],
    "wof:name":"US Post Office",
    "wof:placetype":"venue"
},
  "geometry": {"coordinates":[-87.86089,30.42492],"type":"Point"}
}