{
  "type": "Feature",
  "properties": {
    "iso:country":"US",
    "sg:address":"3 Westchester Ct",
    "sg:city":"Birmingham",
    "sg:classifiers":[
        {
            "category":"Building & Trades",
            "subcategory":"Cleaning & Sanitation",
            "type":"Services"
        }
    ],
    "sg:phone":"+1 205 853 3719",
    "sg:postcode":"35215",
    "sg:province":"AL",
    "sg:tags":[
        "janitor"
    ],
    "wof:name":"Clean It Out",
    "wof:placetype":"venue"
},
  "geometry": {"coordinates":[-86.685933,33.663379],"type":"Point"}
}