{
  "type": "Feature",
  "properties": {
    "addr:full":"577 Hughes Rd Madison AL 35758",
    "addr:housenumber":"577",
    "addr:postcode":"35758",
    "addr:street":"Hughes Rd",
    "iso:country":"US",
    "sg:address":"577 Hughes Rd",
    "sg:city":"Madison",
    "sg:classifiers":[
        {
            "category":"Health Services",
            "subcategory":"Doctor",
            "type":"Services"
        }
    ],
    "sg:phone":"+1 256 461 8607",
    "sg:postcode":"35758",
    "sg:province":"AL",
    "wof:name":"Mooris Jeffrey S DDS",
    "wof:placetype":"venue"
},
  "geometry": {"coordinates":[-86.741651,34.71768],"type":"Point"}
}