{
  "type": "Feature",
  "properties": {
    "iso:country":"US",
    "sg:address":"2419 Mallard Dr",
    "sg:city":"Birmingham",
    "sg:classifiers":[
        {
            "category":"Professional",
            "subcategory":"Business Services",
            "type":"Services"
        }
    ],
    "sg:phone":"+1 205 988 9878",
    "sg:postcode":"35216",
    "sg:province":"AL",
    "wof:name":"Henrys Interiors Inc",
    "wof:placetype":"venue"
},
  "geometry": {"coordinates":[-86.77566,33.388993],"type":"Point"}
}