{
  "type": "Feature",
  "properties": {
    "iso:country":"US",
    "sg:address":"1711 Pepperell Pkwy",
    "sg:city":"Opelika",
    "sg:classifiers":[
        {
            "category":"Health Services",
            "subcategory":"Doctor",
            "type":"Services"
        }
    ],
    "sg:phone":"+1 334 745 7098",
    "sg:postcode":"36801",
    "sg:province":"AL",
    "sg:tags":[
        "medical"
    ],
    "wof:name":"K V Klinner Jr MD",
    "wof:placetype":"venue"
},
  "geometry": {"coordinates":[-85.396994,32.638885],"type":"Point"}
}