{
  "type": "Feature",
  "properties": {
    "iso:country":"US",
    "sg:address":"3062 Hartford Hwy",
    "sg:city":"Dothan",
    "sg:classifiers":[
        {
            "category":"Building & Trades",
            "subcategory":"Cleaning & Sanitation",
            "type":"Services"
        }
    ],
    "sg:phone":"+1 334 678 2331",
    "sg:postcode":"36305",
    "sg:province":"AL",
    "sg:tags":[
        "maintenance"
    ],
    "wof:name":"Homemaid",
    "wof:placetype":"venue"
},
  "geometry": {"coordinates":[-85.43932,31.198008],"type":"Point"}
}