{
  "type": "Feature",
  "properties": {
    "addr:full":"800 Watterson Curv Trussville AL 35173",
    "addr:housenumber":"800",
    "addr:postcode":"35173",
    "addr:street":"Watterson Curv",
    "iso:country":"US",
    "sg:address":"800 Watterson Curv",
    "sg:city":"Trussville",
    "sg:classifiers":[
        {
            "category":"Shopping",
            "subcategory":"Mobile Phones",
            "type":"Retail Goods"
        }
    ],
    "sg:phone":"+1 205 661 0444",
    "sg:postcode":"35173",
    "sg:province":"AL",
    "sg:website":"www.dcsdampers.com",
    "wof:name":"Dcs Dampers",
    "wof:placetype":"venue"
},
  "geometry": {"coordinates":[-86.611189,33.614221],"type":"Point"}
}