{
  "type": "Feature",
  "properties": {
    "addr:full":"860 Grove St Montgomery AL 36104",
    "addr:housenumber":"860",
    "addr:postcode":"36104",
    "addr:street":"Grove St",
    "iso:country":"US",
    "sg:address":"860 Grove St",
    "sg:city":"Montgomery",
    "sg:classifiers":[
        {
            "category":"Utilities",
            "subcategory":"Mobile Phone",
            "type":"Services"
        }
    ],
    "sg:phone":"+1 334 265 8637",
    "sg:postcode":"36104",
    "sg:province":"AL",
    "sg:tags":[
        "telephone",
        "cellular"
    ],
    "wof:name":"Cell Ministries",
    "wof:placetype":"venue"
},
  "geometry": {"coordinates":[-86.296567,32.369596],"type":"Point"}
}