{
  "type": "Feature",
  "properties": {
    "addr:full":"360 Southern Hills Dr Calera AL 35040",
    "addr:housenumber":"360",
    "addr:postcode":"35040",
    "addr:street":"Southern Hills Dr",
    "iso:country":"US",
    "sg:address":"360 Southern Hills Dr",
    "sg:city":"Calera",
    "sg:classifiers":[
        {
            "category":"Professional",
            "subcategory":"Business Services",
            "type":"Services"
        }
    ],
    "sg:phone":"+1 205 668 1131",
    "sg:postcode":"35040",
    "sg:province":"AL",
    "sg:tags":[
        "plant",
        "design",
        "maintenance"
    ],
    "wof:name":"Tropical Interiors",
    "wof:placetype":"venue"
},
  "geometry": {"coordinates":[-86.76617,33.144403],"type":"Point"}
}