{
  "type": "Feature",
  "properties": {
    "addr:full":"600 Baptist Line Rd Aliceville AL 35442",
    "addr:housenumber":"600",
    "addr:postcode":"35442",
    "addr:street":"Baptist Line Rd",
    "iso:country":"US",
    "sg:address":"600 Baptist Line Rd",
    "sg:city":"Aliceville",
    "sg:classifiers":[
        {
            "category":"Manufacturing",
            "subcategory":"Lumber",
            "type":"Manufacturing & Wholesale Goods"
        }
    ],
    "sg:phone":"+1 205 373 3717",
    "sg:postcode":"35442",
    "sg:province":"AL",
    "sg:tags":[
        "planing",
        "mills",
        "sawmill"
    ],
    "sg:website":"www.buchananhardwoods.com",
    "wof:name":"Buchanan Lumber",
    "wof:placetype":"venue"
},
  "geometry": {"coordinates":[-88.16007999999999,33.121119],"type":"Point"}
}