{
  "type": "Feature",
  "properties": {
    "iso:country":"US",
    "sg:address":"6694 US Hwy 431",
    "sg:city":"Owens Cross Rds",
    "sg:classifiers":[
        {
            "category":"Restaurant",
            "type":"Food & Drink"
        }
    ],
    "sg:phone":"+1 256 533 4384",
    "sg:postcode":"35763",
    "sg:province":"AL",
    "wof:name":"Taco Bell",
    "wof:placetype":"venue"
},
  "geometry": {"coordinates":[-86.482585,34.657538],"type":"Point"}
}