{
  "type": "Feature",
  "properties": {
    "iso:country":"US",
    "sg:address":"507 7th St S",
    "sg:city":"Clanton",
    "sg:classifiers":[
        {
            "category":"Retail",
            "subcategory":"Self-service Laundry",
            "type":"Services"
        }
    ],
    "sg:phone":"+1 205 755 9807",
    "sg:postcode":"35045",
    "sg:province":"AL",
    "wof:name":"Suds R-Us",
    "wof:placetype":"venue"
},
  "geometry": {"coordinates":[-86.628122,32.832632],"type":"Point"}
}