{
  "type": "Feature",
  "properties": {
    "addr:full":"9995 Holtville Rd Wetumpka AL 36092",
    "addr:housenumber":"9995",
    "addr:postcode":"36092",
    "addr:street":"Holtville Rd",
    "iso:country":"US",
    "sg:address":"9995 Holtville Rd",
    "sg:city":"Wetumpka",
    "sg:classifiers":[
        {
            "category":"Restaurant",
            "type":"Food & Drink"
        }
    ],
    "sg:menulink":"http://www.allmenus.com/al/deatsville/121106-subway/menu/",
    "sg:phone":"+1 334 569 0606",
    "sg:postcode":"36092",
    "sg:province":"AL",
    "sg:tags":[
        "american",
        "sandwich"
    ],
    "wof:name":"Subway",
    "wof:placetype":"venue"
},
  "geometry": {"coordinates":[-86.31979,32.635754],"type":"Point"}
}