{
  "type": "Feature",
  "properties": {
    "iso:country":"US",
    "sg:address":"1301 Decatur Hwy",
    "sg:city":"Gardendale",
    "sg:classifiers":[
        {
            "category":"Restaurant",
            "type":"Food & Drink"
        }
    ],
    "sg:phone":"+1 205 631 8408",
    "sg:postcode":"35071",
    "sg:province":"AL",
    "wof:name":"Burger King",
    "wof:placetype":"venue"
},
  "geometry": {"coordinates":[-86.8125,33.66002],"type":"Point"}
}