{
  "type": "Feature",
  "properties": {
    "iso:country":"US",
    "sg:address":"599 Oak Dr E",
    "sg:city":"Trussville",
    "sg:classifiers":[
        {
            "category":"Transit Center",
            "subcategory":"Freight",
            "type":"Transportation"
        }
    ],
    "sg:phone":"+1 205 661 2732",
    "sg:postcode":"35173",
    "sg:province":"AL",
    "sg:tags":[
        "trucking-light",
        "hauling"
    ],
    "wof:name":"Southerland Hauling Inc",
    "wof:placetype":"venue"
},
  "geometry": {"coordinates":[-86.600601,33.613541],"type":"Point"}
}