{
  "type": "Feature",
  "properties": {
    "iso:country":"US",
    "sg:address":"334 State Rte 36",
    "sg:city":"Hartselle",
    "sg:classifiers":[
        {
            "category":"Food & Beverages",
            "subcategory":"Fruits & Vegetables",
            "type":"Retail Goods"
        }
    ],
    "sg:phone":"+1 256 773 9479",
    "sg:postcode":"35640",
    "sg:province":"AL",
    "sg:tags":[
        "produce"
    ],
    "wof:name":"Reeves Peach Farm",
    "wof:placetype":"venue"
},
  "geometry": {"coordinates":[-86.88731300000001,34.448596],"type":"Point"}
}