{
  "type": "Feature",
  "properties": {
    "addr:full":"1401 Government St Mobile AL 36604",
    "addr:housenumber":"1401",
    "addr:postcode":"36604",
    "addr:street":"Government St",
    "iso:country":"US",
    "sg:address":"1401 Government St",
    "sg:city":"Mobile",
    "sg:classifiers":[
        {
            "category":"Organizations",
            "subcategory":"Religious Organization",
            "type":"Services"
        }
    ],
    "sg:phone":"+1 251 471 2334",
    "sg:postcode":"36604",
    "sg:province":"AL",
    "sg:tags":[
        "nondenominational",
        "church"
    ],
    "wof:name":"Living Word Christian Center",
    "wof:placetype":"venue"
},
  "geometry": {"coordinates":[-88.06952200000001,30.6814],"type":"Point"}
}