{
  "type": "Feature",
  "properties": {
    "iso:country":"US",
    "sg:address":"2209 E Broad St",
    "sg:city":"Gadsden",
    "sg:classifiers":[
        {
            "category":"Real Estate",
            "subcategory":"Developer",
            "type":"Services"
        }
    ],
    "sg:phone":"+1 256 492 0755",
    "sg:postcode":"35903",
    "sg:province":"AL",
    "sg:tags":[
        "cemetery"
    ],
    "wof:name":"Crestwood Marketing",
    "wof:placetype":"venue"
},
  "geometry": {"coordinates":[-85.968975,33.988616],"type":"Point"}
}