{
  "type": "Feature",
  "properties": {
    "iso:country":"US",
    "sg:address":"1966 Government St",
    "sg:city":"Mobile",
    "sg:classifiers":[
        {
            "category":"Restaurant",
            "type":"Food & Drink"
        }
    ],
    "sg:menulink":"http://www.allmenus.com/al/mobile/174938-popeyes-chicken--biscuits/menu/",
    "sg:phone":"+1 251 479 0076",
    "sg:postcode":"36606",
    "sg:province":"AL",
    "sg:tags":[
        "american",
        "wing"
    ],
    "wof:name":"Popeyes Chicken & Biscuits",
    "wof:placetype":"venue"
},
  "geometry": {"coordinates":[-88.08592400000001,30.676369],"type":"Point"}
}