{
  "type": "Feature",
  "properties": {
    "iso:country":"US",
    "sg:address":"516 19th St N",
    "sg:city":"Bessemer",
    "sg:classifiers":[
        {
            "category":"Social Services",
            "subcategory":"Job Training",
            "type":"Services"
        }
    ],
    "sg:phone":"+1 205 481 1556",
    "sg:postcode":"35020",
    "sg:province":"AL",
    "sg:tags":[
        "career",
        "counseling",
        "vocational"
    ],
    "wof:name":"Heritage Center",
    "wof:placetype":"venue"
},
  "geometry": {"coordinates":[-86.956112,33.403918],"type":"Point"}
}