{
  "type": "Feature",
  "properties": {
    "addr:full":"105 Sunnywood Cir Columbiana AL 35051",
    "addr:housenumber":"105",
    "addr:postcode":"35051",
    "addr:street":"Sunnywood Cir",
    "iso:country":"US",
    "sg:address":"105 Sunnywood Cir",
    "sg:city":"Columbiana",
    "sg:classifiers":[
        {
            "category":"Building & Trades",
            "subcategory":"Plumbing",
            "type":"Services"
        }
    ],
    "sg:phone":"+1 205 669 9942",
    "sg:postcode":"35051",
    "sg:province":"AL",
    "sg:tags":[
        "contractor"
    ],
    "wof:name":"South Shelby Heating Cooling",
    "wof:placetype":"venue"
},
  "geometry": {"coordinates":[-86.595176,33.167086],"type":"Point"}
}