{
  "type": "Feature",
  "properties": {
    "addr:full":"10068 Downing St Semmes AL 36575",
    "addr:housenumber":"10068",
    "addr:postcode":"36575",
    "addr:street":"Downing St",
    "iso:country":"US",
    "sg:address":"10068 Downing St",
    "sg:city":"Semmes",
    "sg:classifiers":[
        {
            "category":"Building & Trades",
            "subcategory":"Construction",
            "type":"Services"
        }
    ],
    "sg:phone":"+1 251 680 3232",
    "sg:postcode":"36575",
    "sg:province":"AL",
    "sg:tags":[
        "house"
    ],
    "wof:name":"A A A Mobile Home LLC",
    "wof:placetype":"venue"
},
  "geometry": {"coordinates":[-88.279612,30.766421],"type":"Point"}
}