{
  "type": "Feature",
  "properties": {
    "iso:country":"US",
    "sg:address":"576 Plummer Rd NW",
    "sg:city":"Huntsville",
    "sg:classifiers":[
        {
            "category":"Personal",
            "subcategory":"Beauty Salon",
            "type":"Services"
        }
    ],
    "sg:phone":"+1 256 746 8033",
    "sg:postcode":"35806",
    "sg:province":"AL",
    "wof:name":"Epiphany Beauty Salon",
    "wof:placetype":"venue"
},
  "geometry": {"coordinates":[-86.670087,34.771549],"type":"Point"}
}