{
  "type": "Feature",
  "properties": {
    "iso:country":"US",
    "sg:address":"5767 Co Rd 10",
    "sg:city":"Montevallo",
    "sg:classifiers":[
        {
            "category":"Food & Beverages",
            "subcategory":"Groceries & Convenience Stores",
            "type":"Retail Goods"
        }
    ],
    "sg:phone":"+1 205 665 1964",
    "sg:postcode":"35115",
    "sg:province":"AL",
    "wof:name":"Barts Country Store",
    "wof:placetype":"venue"
},
  "geometry": {"coordinates":[-86.92659500000001,33.15331],"type":"Point"}
}