{
  "type": "Feature",
  "properties": {
    "addr:full":"401 N Lafayette St Lafayette AL 36862",
    "addr:housenumber":"401",
    "addr:postcode":"36862",
    "addr:street":"N Lafayette St",
    "iso:country":"US",
    "sg:address":"401 N Lafayette St",
    "sg:city":"Lafayette",
    "sg:classifiers":[
        {
            "category":"Insurance",
            "subcategory":"Insurance Agent",
            "type":"Services"
        }
    ],
    "sg:phone":"+1 334 864 8772",
    "sg:postcode":"36862",
    "sg:province":"AL",
    "wof:name":"State Farm Insurance",
    "wof:placetype":"venue"
},
  "geometry": {"coordinates":[-85.398768,32.91717],"type":"Point"}
}