{
  "type": "Feature",
  "properties": {
    "iso:country":"US",
    "sg:address":"499 Co Rd 820",
    "sg:city":"Selma",
    "sg:classifiers":[
        {
            "category":"Retail",
            "subcategory":"Repair Shop",
            "type":"Services"
        },
        {
            "category":"Shopping",
            "subcategory":"Bicycles & Sporting Goods",
            "type":"Retail Goods"
        }
    ],
    "sg:phone":"+1 334 872 6231",
    "sg:postcode":"36701",
    "sg:province":"AL",
    "sg:tags":[
        "gunsmith",
        "gun",
        "sm",
        "mfg"
    ],
    "wof:name":"Walker Arms Co Inc",
    "wof:placetype":"venue"
},
  "geometry": {"coordinates":[-87.101161,32.440526],"type":"Point"}
}