{
  "type": "Feature",
  "properties": {
    "iso:country":"US",
    "sg:address":"541 Larkin Ln",
    "sg:city":"Montgomery",
    "sg:classifiers":[
        {
            "category":"Organizations",
            "subcategory":"Community Association",
            "type":"Services"
        }
    ],
    "sg:phone":"+1 334 272 3812",
    "sg:postcode":"36109",
    "sg:province":"AL",
    "wof:name":"Kappa Kappa Iota",
    "wof:placetype":"venue"
},
  "geometry": {"coordinates":[-86.239375,32.371657],"type":"Point"}
}