{
  "type": "Feature",
  "properties": {
    "addr:full":"3014 Danville Rd SW Decatur AL 35603",
    "addr:housenumber":"3014",
    "addr:postcode":"35603",
    "addr:street":"Danville Rd Sw",
    "iso:country":"US",
    "sg:address":"3014 Danville Rd SW",
    "sg:city":"Decatur",
    "sg:classifiers":[
        {
            "category":"Organizations",
            "subcategory":"Religious Organization",
            "type":"Services"
        }
    ],
    "sg:phone":"+1 256 355 9381",
    "sg:postcode":"35603",
    "sg:province":"AL",
    "wof:name":"Saint Luke Untd Methdst Church",
    "wof:placetype":"venue"
},
  "geometry": {"coordinates":[-87.02052999999999,34.54603],"type":"Point"}
}