{
  "type": "Feature",
  "properties": {
    "iso:country":"US",
    "sg:address":"25 S Court St",
    "sg:city":"Montgomery",
    "sg:classifiers":[
        {
            "category":"Professional",
            "subcategory":"Lawyer & Legal Services",
            "type":"Services"
        }
    ],
    "sg:phone":"+1 334 834 5700",
    "sg:postcode":"36104",
    "sg:province":"AL",
    "sg:tags":[
        "attorney"
    ],
    "wof:name":"Nelson & Teague LLC",
    "wof:placetype":"venue"
},
  "geometry": {"coordinates":[-86.308934,32.377338],"type":"Point"}
}