{
  "type": "Feature",
  "properties": {
    "iso:country":"US",
    "sg:address":"3271 Windwood Dr",
    "sg:city":"Montgomery",
    "sg:classifiers":[
        {
            "category":"Building & Trades",
            "subcategory":"Construction",
            "type":"Services"
        }
    ],
    "sg:phone":"+1 334 288 8610",
    "sg:postcode":"36116",
    "sg:province":"AL",
    "sg:tags":[
        "general",
        "contractor"
    ],
    "wof:name":"Crafts For Better Homes",
    "wof:placetype":"venue"
},
  "geometry": {"coordinates":[-86.264209,32.319082],"type":"Point"}
}