{
  "type": "Feature",
  "properties": {
    "addr:full":"467 Daleville Ave Daleville AL 36322",
    "addr:housenumber":"467",
    "addr:postcode":"36322",
    "addr:street":"Daleville Ave",
    "iso:country":"US",
    "sg:address":"467 Daleville Ave",
    "sg:city":"Daleville",
    "sg:classifiers":[
        {
            "category":"Organizations",
            "subcategory":"Professional Association",
            "type":"Services"
        }
    ],
    "sg:phone":"+1 334 598 6361",
    "sg:postcode":"36322",
    "sg:province":"AL",
    "sg:tags":[
        "business",
        "trade"
    ],
    "wof:name":"Iam Federal Credit Union",
    "wof:placetype":"venue"
},
  "geometry": {"coordinates":[-85.71055699999999,31.321044],"type":"Point"}
}