{
  "type": "Feature",
  "properties": {
    "iso:country":"US",
    "sg:address":"412 Hamric Dr E",
    "sg:city":"Oxford",
    "sg:classifiers":[
        {
            "category":"Retail",
            "subcategory":"Laundry & Dry Cleaning",
            "type":"Services"
        }
    ],
    "sg:phone":"+1 256 831 2326",
    "sg:postcode":"36203",
    "sg:province":"AL",
    "sg:tags":[
        "garment",
        "plant",
        "agent",
        "drycleaning"
    ],
    "wof:name":"Marvel Cleaners",
    "wof:placetype":"venue"
},
  "geometry": {"coordinates":[-85.83099199999999,33.60865],"type":"Point"}
}