{
  "type": "Feature",
  "properties": {
    "iso:country":"US",
    "sg:address":"826 Bradley St SW",
    "sg:city":"Decatur",
    "sg:classifiers":[
        {
            "category":"Food & Beverages",
            "subcategory":"Groceries & Convenience Stores",
            "type":"Retail Goods"
        }
    ],
    "sg:phone":"+1 256 351 7919",
    "sg:postcode":"35601",
    "sg:province":"AL",
    "wof:name":"LA Hacienda",
    "wof:placetype":"venue"
},
  "geometry": {"coordinates":[-86.999147,34.571268],"type":"Point"}
}