{
  "type": "Feature",
  "properties": {
    "addr:full":"120 7th Ct SW Graysville AL 35073",
    "addr:housenumber":"120",
    "addr:postcode":"35073",
    "addr:street":"7Th Ct Sw",
    "iso:country":"US",
    "sg:address":"120 7th Ct SW",
    "sg:city":"Graysville",
    "sg:classifiers":[
        {
            "category":"Shopping",
            "subcategory":"Department Store",
            "type":"Retail Goods"
        }
    ],
    "sg:phone":"+1 205 674 7306",
    "sg:postcode":"35073",
    "sg:province":"AL",
    "sg:tags":[
        "shop"
    ],
    "wof:name":"Bargain Post",
    "wof:placetype":"venue"
},
  "geometry": {"coordinates":[-86.974209,33.621054],"type":"Point"}
}