{
  "type": "Feature",
  "properties": {
    "addr:full":"1018 Madison Ave Montgomery AL 36104",
    "addr:housenumber":"1018",
    "addr:postcode":"36104",
    "addr:street":"Madison Ave",
    "iso:country":"US",
    "sg:address":"1018 Madison Ave",
    "sg:city":"Montgomery",
    "sg:classifiers":[
        {
            "category":"Organizations",
            "subcategory":"Membership Organization",
            "type":"Services"
        },
        {
            "category":"Education",
            "subcategory":"Special Training",
            "type":"Public Place"
        }
    ],
    "sg:phone":"+1 334 241 2787",
    "sg:postcode":"36104",
    "sg:province":"AL",
    "sg:tags":[
        "school",
        "instruction",
        "art"
    ],
    "wof:name":"Armory Learning Arts Center",
    "wof:placetype":"venue"
},
  "geometry": {"coordinates":[-86.29533000000001,32.380322],"type":"Point"}
}