{
  "type": "Feature",
  "properties": {
    "iso:country":"US",
    "sg:address":"4408 5th Ave S",
    "sg:city":"Birmingham",
    "sg:classifiers":[
        {
            "category":"Wholesale",
            "subcategory":"Vending Machines",
            "type":"Manufacturing & Wholesale Goods"
        }
    ],
    "sg:phone":"+1 205 591 7026",
    "sg:postcode":"35222",
    "sg:province":"AL",
    "sg:tags":[
        "operator"
    ],
    "wof:name":"General Amusement Mus Eqp Svc",
    "wof:placetype":"venue"
},
  "geometry": {"coordinates":[-86.766386,33.525437],"type":"Point"}
}