{
  "type": "Feature",
  "properties": {
    "iso:country":"US",
    "sg:address":"6493 Atlanta Hwy",
    "sg:city":"Montgomery",
    "sg:classifiers":[
        {
            "category":"Restaurant",
            "type":"Food & Drink"
        }
    ],
    "sg:menulink":"http://www.allmenus.com/al/montgomery/190255-mcdonalds/menu/",
    "sg:postcode":"36117",
    "sg:province":"AL",
    "sg:tags":[
        "burger",
        "american"
    ],
    "wof:name":"McDonald's",
    "wof:placetype":"venue"
},
  "geometry": {"coordinates":[-86.186941,32.382418],"type":"Point"}
}