{
  "type": "Feature",
  "properties": {
    "iso:country":"US",
    "sg:address":"1032 Stephens St",
    "sg:city":"Montgomery",
    "sg:classifiers":[
        {
            "category":"Organizations",
            "subcategory":"Religious Organization",
            "type":"Services"
        }
    ],
    "sg:phone":"+1 334 269 5988",
    "sg:postcode":"36108",
    "sg:province":"AL",
    "sg:tags":[
        "church"
    ],
    "wof:name":"Mt Zion Primitive Baptst Chrch",
    "wof:placetype":"venue"
},
  "geometry": {"coordinates":[-86.323503,32.35517],"type":"Point"}
}