{
  "type": "Feature",
  "properties": {
    "iso:country":"US",
    "sg:address":"3473 State Rte 53",
    "sg:city":"Huntsville",
    "sg:classifiers":[
        {
            "category":"Manufacturing",
            "subcategory":"Electronics",
            "type":"Manufacturing & Wholesale Goods"
        }
    ],
    "sg:phone":"+1 256 859 2464",
    "sg:postcode":"35806",
    "sg:province":"AL",
    "sg:tags":[
        "mfg",
        "boards",
        "circuit",
        "printed"
    ],
    "wof:name":"Patel Electronics Co Inc",
    "wof:placetype":"venue"
},
  "geometry": {"coordinates":[-86.662131,34.78496],"type":"Point"}
}