{
  "type": "Feature",
  "properties": {
    "iso:country":"US",
    "sg:address":"10400 Co Rd 95",
    "sg:city":"Elberta",
    "sg:classifiers":[
        {
            "category":"Freight",
            "type":"Transportation"
        }
    ],
    "sg:phone":"+1 251 986 8392",
    "sg:postcode":"36530",
    "sg:province":"AL",
    "sg:tags":[
        "commercial",
        "storage"
    ],
    "wof:name":"Josephine Self Storage",
    "wof:placetype":"venue"
},
  "geometry": {"coordinates":[-87.547587,30.370237],"type":"Point"}
}