{
  "type": "Feature",
  "properties": {
    "iso:country":"US",
    "sg:address":"5906 Provost Ave",
    "sg:city":"Montgomery",
    "sg:classifiers":[
        {
            "category":"Professional",
            "subcategory":"Accounting & Tax Preparation",
            "type":"Services"
        }
    ],
    "sg:phone":"+1 334 286 4833",
    "sg:postcode":"36116",
    "sg:province":"AL",
    "sg:tags":[
        "return",
        "filing"
    ],
    "wof:name":"Fast Tax Cash",
    "wof:placetype":"venue"
},
  "geometry": {"coordinates":[-86.223668,32.310714],"type":"Point"}
}