{
  "type": "Feature",
  "properties": {
    "iso:country":"US",
    "sg:address":"169 Silverleaf Dr",
    "sg:city":"Pelham",
    "sg:classifiers":[
        {
            "category":"Building & Trades",
            "subcategory":"Landscaping Services",
            "type":"Services"
        }
    ],
    "sg:phone":"+1 205 663 6570",
    "sg:postcode":"35124",
    "sg:province":"AL",
    "sg:tags":[
        "cutting",
        "grass",
        "cleanup"
    ],
    "wof:name":"Forever Green",
    "wof:placetype":"venue"
},
  "geometry": {"coordinates":[-86.782905,33.288387],"type":"Point"}
}