{
  "type": "Feature",
  "properties": {
    "iso:country":"US",
    "sg:address":"1302 5th Ave SE",
    "sg:city":"Decatur",
    "sg:classifiers":[
        {
            "category":"Personal",
            "subcategory":"Beauty Salon",
            "type":"Services"
        }
    ],
    "sg:phone":"+1 256 355 2750",
    "sg:postcode":"35601",
    "sg:province":"AL",
    "sg:tags":[
        "shop"
    ],
    "wof:name":"Fashion Aire Beauty Salon",
    "wof:placetype":"venue"
},
  "geometry": {"coordinates":[-86.981618,34.586],"type":"Point"}
}