{
  "type": "Feature",
  "properties": {
    "iso:country":"US",
    "sg:address":"1331 Whirlaway Cir",
    "sg:city":"Helena",
    "sg:classifiers":[
        {
            "category":"Shopping",
            "type":"Retail Goods"
        }
    ],
    "sg:phone":"+1 205 663 9790",
    "sg:postcode":"35080",
    "sg:province":"AL",
    "sg:tags":[
        "wheel",
        "chair",
        "scooter"
    ],
    "wof:name":"Sparkle Systems Inc",
    "wof:placetype":"venue"
},
  "geometry": {"coordinates":[-86.829026,33.2801],"type":"Point"}
}