{
  "type": "Feature",
  "properties": {
    "addr:full":"612 Tracy St Gadsden AL 35901",
    "addr:housenumber":"612",
    "addr:postcode":"35901",
    "addr:street":"Tracy St",
    "iso:country":"US",
    "sg:address":"612 Tracy St",
    "sg:city":"Gadsden",
    "sg:classifiers":[
        {
            "category":"Education",
            "subcategory":"School",
            "type":"Public Place"
        }
    ],
    "sg:phone":"+1 256 547 6341",
    "sg:postcode":"35901",
    "sg:province":"AL",
    "sg:website":"www.gcs.k12.al.us",
    "wof:name":"Disque Middle School",
    "wof:placetype":"venue"
},
  "geometry": {"coordinates":[-86.011488,34.005167],"type":"Point"}
}