{
  "type": "Feature",
  "properties": {
    "addr:full":"9865 Gallops Creek Dr Wilmer AL 36587",
    "addr:housenumber":"9865",
    "addr:postcode":"36587",
    "addr:street":"Gallops Creek Dr",
    "iso:country":"US",
    "sg:address":"9865 Gallops Creek Dr",
    "sg:city":"Wilmer",
    "sg:classifiers":[
        {
            "category":"Shopping",
            "subcategory":"Computers & Home Electronics",
            "type":"Retail Goods"
        }
    ],
    "sg:phone":"+1 251 649 7329",
    "sg:postcode":"36587",
    "sg:province":"AL",
    "wof:name":"Sunbelt Electronic",
    "wof:placetype":"venue"
},
  "geometry": {"coordinates":[-88.26951200000001,30.86261],"type":"Point"}
}