{
  "type": "Feature",
  "properties": {
    "addr:full":"1121 9th Ave SW Bessemer AL 35022",
    "addr:housenumber":"1121",
    "addr:postcode":"35022",
    "addr:street":"9Th Ave Sw",
    "iso:country":"US",
    "sg:address":"1121 9th Ave SW",
    "sg:city":"Bessemer",
    "sg:classifiers":[
        {
            "category":"Bars & Pubs",
            "type":"Food & Drink"
        }
    ],
    "sg:phone":"+1 205 425 4445",
    "sg:postcode":"35022",
    "sg:province":"AL",
    "sg:tags":[
        "drinking"
    ],
    "wof:name":"Sharkyz",
    "wof:placetype":"venue"
},
  "geometry": {"coordinates":[-86.99678,33.368261],"type":"Point"}
}