{
  "type": "Feature",
  "properties": {
    "iso:country":"US",
    "sg:address":"117 Gristmill Rd NE",
    "sg:city":"Huntsville",
    "sg:classifiers":[
        {
            "category":"Professional",
            "subcategory":"Computer Services",
            "type":"Services"
        }
    ],
    "sg:phone":"+1 256 859 6141",
    "sg:postcode":"35811",
    "sg:province":"AL",
    "sg:tags":[
        "development",
        "software"
    ],
    "wof:name":"Inovative Technologies Inc",
    "wof:placetype":"venue"
},
  "geometry": {"coordinates":[-86.548967,34.809235],"type":"Point"}
}