{
  "type": "Feature",
  "properties": {
    "iso:country":"US",
    "sg:address":"2536 Central Pkwy SW",
    "sg:city":"Decatur",
    "sg:classifiers":[
        {
            "category":"Building & Trades",
            "subcategory":"Construction",
            "type":"Services"
        }
    ],
    "sg:phone":"+1 256 340 0707",
    "sg:postcode":"35601",
    "sg:province":"AL",
    "sg:tags":[
        "asbestos",
        "removal"
    ],
    "wof:name":"Thermal Abatement Inc",
    "wof:placetype":"venue"
},
  "geometry": {"coordinates":[-86.982271,34.564949],"type":"Point"}
}