{
  "type": "Feature",
  "properties": {
    "addr:full":"307 Thompson Ln Hazel Green AL 35750",
    "addr:housenumber":"307",
    "addr:postcode":"35750",
    "addr:street":"Thompson Ln",
    "iso:country":"US",
    "sg:address":"307 Thompson Ln",
    "sg:city":"Hazel Green",
    "sg:classifiers":[
        {
            "category":"Building & Trades",
            "subcategory":"Landscaping Services",
            "type":"Services"
        }
    ],
    "sg:phone":"+1 256 859 8383",
    "sg:postcode":"35750",
    "sg:province":"AL",
    "sg:tags":[
        "lawn",
        "maintenance",
        "grounds"
    ],
    "wof:name":"Turf Techs",
    "wof:placetype":"venue"
},
  "geometry": {"coordinates":[-86.50925700000001,34.964656],"type":"Point"}
}