{
  "type": "Feature",
  "properties": {
    "iso:country":"US",
    "sg:address":"307 Thompson Ln",
    "sg:city":"Hazel Green",
    "sg:classifiers":[
        {
            "category":"Building & Trades",
            "subcategory":"Landscaping Services",
            "type":"Services"
        }
    ],
    "sg:phone":"+1 256 859 8383",
    "sg:postcode":"35750",
    "sg:province":"AL",
    "sg:tags":[
        "lawn",
        "maintenance",
        "grounds"
    ],
    "wof:name":"Turf Techs",
    "wof:placetype":"venue"
},
  "geometry": {"coordinates":[-86.509257,34.964656],"type":"Point"}
}