{
  "type": "Feature",
  "properties": {
    "iso:country":"US",
    "sg:address":"6605 Chestnut Rd",
    "sg:city":"Quinton",
    "sg:classifiers":[
        {
            "category":"Home & Garden",
            "subcategory":"Building Materials",
            "type":"Retail Goods"
        }
    ],
    "sg:phone":"+1 205 674 5861",
    "sg:postcode":"35130",
    "sg:province":"AL",
    "sg:tags":[
        "installs",
        "garage",
        "overhead",
        "door"
    ],
    "wof:name":"West Alabama Doors Inc",
    "wof:placetype":"venue"
},
  "geometry": {"coordinates":[-87.063353,33.641484],"type":"Point"}
}