{
  "type": "Feature",
  "properties": {
    "iso:country":"US",
    "sg:address":"303 Upper Kingston Rd",
    "sg:city":"Prattville",
    "sg:classifiers":[
        {
            "category":"Organizations",
            "subcategory":"Religious Organization",
            "type":"Services"
        }
    ],
    "sg:phone":"+1 334 361 6655",
    "sg:postcode":"36067",
    "sg:province":"AL",
    "wof:name":"Spring Hill AME Zion Church",
    "wof:placetype":"venue"
},
  "geometry": {"coordinates":[-86.475213,32.466005],"type":"Point"}
}