{
  "type": "Feature",
  "properties": {
    "addr:full":"161 W Main St Prattville AL 36067",
    "addr:housenumber":"161",
    "addr:postcode":"36067",
    "addr:street":"W Main St",
    "iso:country":"US",
    "sg:address":"161 W Main St",
    "sg:city":"Prattville",
    "sg:classifiers":[
        {
            "category":"Retail",
            "subcategory":"Laundry & Dry Cleaning",
            "type":"Services"
        },
        {
            "category":"Shopping",
            "subcategory":"Clothing, Apparel, & Fashions",
            "type":"Retail Goods"
        }
    ],
    "sg:phone":"+1 334 365 4149",
    "sg:postcode":"36067",
    "sg:province":"AL",
    "sg:tags":[
        "alteration"
    ],
    "wof:name":"Patsy's Pins & Needles",
    "wof:placetype":"venue"
},
  "geometry": {"coordinates":[-86.474148,32.459721],"type":"Point"}
}