{
  "type": "Feature",
  "properties": {
    "iso:country":"US",
    "sg:address":"7419 US Hwy 431",
    "sg:city":"Albertville",
    "sg:classifiers":[
        {
            "category":"Health Services",
            "subcategory":"Optometrist",
            "type":"Services"
        }
    ],
    "sg:phone":"+1 256 878 0125",
    "sg:postcode":"35950",
    "sg:province":"AL",
    "wof:name":"Eye Care Assoc Inc",
    "wof:placetype":"venue"
},
  "geometry": {"coordinates":[-86.207994,34.277183],"type":"Point"}
}