{
  "type": "Feature",
  "properties": {
    "addr:full":"1204 Posey Ave NW Huntsville AL 35816",
    "addr:housenumber":"1204",
    "addr:postcode":"35816",
    "addr:street":"Posey Ave Nw",
    "iso:country":"US",
    "sg:address":"1204 Posey Ave NW",
    "sg:city":"Huntsville",
    "sg:classifiers":[
        {
            "category":"Bars & Pubs",
            "type":"Food & Drink"
        }
    ],
    "sg:phone":"+1 256 534 5970",
    "sg:postcode":"35816",
    "sg:province":"AL",
    "sg:tags":[
        "lounge",
        "cocktail"
    ],
    "wof:name":"Club Ozz",
    "wof:placetype":"venue"
},
  "geometry": {"coordinates":[-86.601169,34.738383],"type":"Point"}
}