{
  "type": "Feature",
  "properties": {
    "addr:full":"3527 Tanglecreek Cir Birmingham AL 35243",
    "addr:housenumber":"3527",
    "addr:postcode":"35243",
    "addr:street":"Tanglecreek Cir",
    "iso:country":"US",
    "sg:address":"3527 Tanglecreek Cir",
    "sg:city":"Birmingham",
    "sg:classifiers":[
        {
            "category":"Health Services",
            "subcategory":"Doctor",
            "type":"Services"
        }
    ],
    "sg:phone":"+1 205 968 0874",
    "sg:postcode":"35243",
    "sg:province":"AL",
    "sg:tags":[
        "medical"
    ],
    "wof:name":"John W Bowers M D",
    "wof:placetype":"venue"
},
  "geometry": {"coordinates":[-86.765608,33.443578],"type":"Point"}
}