{
  "type": "Feature",
  "properties": {
    "addr:full":"62 Rollins Ln Anniston AL 36203",
    "addr:housenumber":"62",
    "addr:postcode":"36203",
    "addr:street":"Rollins Ln",
    "iso:country":"US",
    "sg:address":"62 Rollins Ln",
    "sg:city":"Anniston",
    "sg:classifiers":[
        {
            "category":"Building & Trades",
            "subcategory":"Plumbing",
            "type":"Services"
        }
    ],
    "sg:phone":"+1 256 835 3109",
    "sg:postcode":"36203",
    "sg:province":"AL",
    "sg:tags":[
        "conditioning",
        "air",
        "system",
        "contractor"
    ],
    "wof:name":"Jay Rollins Heating & AC",
    "wof:placetype":"venue"
},
  "geometry": {"coordinates":[-85.826944,33.577398],"type":"Point"}
}