{
  "type": "Feature",
  "properties": {
    "addr:full":"1421 Shades Crest Rd Birmingham AL 35226",
    "addr:housenumber":"1421",
    "addr:postcode":"35226",
    "addr:street":"Shades Crest Rd",
    "iso:country":"US",
    "sg:address":"1421 Shades Crest Rd",
    "sg:city":"Birmingham",
    "sg:classifiers":[
        {
            "category":"Professional",
            "subcategory":"Business Services",
            "type":"Services"
        }
    ],
    "sg:phone":"+1 205 824 6051",
    "sg:postcode":"35226",
    "sg:province":"AL",
    "wof:name":"Rp Design LLC",
    "wof:placetype":"venue"
},
  "geometry": {"coordinates":[-86.818444,33.43889],"type":"Point"}
}