{
  "type": "Feature",
  "properties": {
    "iso:country":"US",
    "sg:address":"1016 Riverchase Pkwy W",
    "sg:city":"Birmingham",
    "sg:classifiers":[
        {
            "category":"Building & Trades",
            "subcategory":"Construction",
            "type":"Services"
        }
    ],
    "sg:phone":"+1 205 987 7895",
    "sg:postcode":"35244",
    "sg:province":"AL",
    "sg:tags":[
        "home",
        "general",
        "family",
        "contractor"
    ],
    "wof:name":"Good Sense Homes Inc",
    "wof:placetype":"venue"
},
  "geometry": {"coordinates":[-86.815701,33.346219],"type":"Point"}
}