{
  "type": "Feature",
  "properties": {
    "iso:country":"US",
    "sg:address":"4421 Atlanta Hwy",
    "sg:city":"Montgomery",
    "sg:classifiers":[
        {
            "category":"Health Services",
            "subcategory":"Doctor",
            "type":"Services"
        }
    ],
    "sg:phone":"+1 334 272 2906",
    "sg:postcode":"36109",
    "sg:province":"AL",
    "sg:tags":[
        "dentist"
    ],
    "wof:name":"C Ronald Elijah DDS",
    "wof:placetype":"venue"
},
  "geometry": {"coordinates":[-86.229253,32.3818],"type":"Point"}
}