{
  "type": "Feature",
  "properties": {
    "addr:full":"555 Sparkman Dr NW Huntsville AL 35816",
    "addr:housenumber":"555",
    "addr:postcode":"35816",
    "addr:street":"Sparkman Dr Nw",
    "iso:country":"US",
    "sg:address":"555 Sparkman Dr NW",
    "sg:city":"Huntsville",
    "sg:classifiers":[
        {
            "category":"Social Services",
            "type":"Services"
        }
    ],
    "sg:phone":"+1 256 830 2155",
    "sg:postcode":"35816",
    "sg:province":"AL",
    "wof:name":"Volunteers of America Inc",
    "wof:placetype":"venue"
},
  "geometry": {"coordinates":[-86.644066,34.732298],"type":"Point"}
}