{
  "type": "Feature",
  "properties": {
    "iso:country":"US",
    "sg:address":"3401 Industrial Dr",
    "sg:city":"Montgomery",
    "sg:classifiers":[
        {
            "category":"Autos & Motor Vehicles",
            "subcategory":"Auto Supplies",
            "type":"Retail Goods"
        }
    ],
    "sg:phone":"+1 334 263 3101",
    "sg:postcode":"36108",
    "sg:province":"AL",
    "wof:name":"Kenworth Of Montgomery",
    "wof:placetype":"venue"
},
  "geometry": {"coordinates":[-86.377068,32.381698],"type":"Point"}
}