{
  "type": "Feature",
  "properties": {
    "addr:full":"101 Lyon Ln Birmingham AL 35211",
    "addr:housenumber":"101",
    "addr:postcode":"35211",
    "addr:street":"Lyon Ln",
    "iso:country":"US",
    "sg:address":"101 Lyon Ln",
    "sg:city":"Birmingham",
    "sg:classifiers":[
        {
            "category":"Building & Trades",
            "subcategory":"Construction",
            "type":"Services"
        }
    ],
    "sg:phone":"+1 205 942 9700",
    "sg:postcode":"35211",
    "sg:province":"AL",
    "sg:tags":[
        "metal",
        "contractor"
    ],
    "wof:name":"R B Atkins & Associates Inc",
    "wof:placetype":"venue"
},
  "geometry": {"coordinates":[-86.856326,33.442487],"type":"Point"}
}