{
  "type": "Feature",
  "properties": {
    "addr:full":"733 Railroad St Hurtsboro AL 36860",
    "addr:housenumber":"733",
    "addr:postcode":"36860",
    "addr:street":"Railroad St",
    "iso:country":"US",
    "sg:address":"733 Railroad St",
    "sg:city":"Hurtsboro",
    "sg:classifiers":[
        {
            "category":"Education",
            "subcategory":"School",
            "type":"Public Place"
        }
    ],
    "sg:phone":"+1 334 667 7471",
    "sg:postcode":"36860",
    "sg:province":"AL",
    "wof:name":"Russell Elementary School",
    "wof:placetype":"venue"
},
  "geometry": {"coordinates":[-85.409756,32.240965],"type":"Point"}
}