{
  "type": "Feature",
  "properties": {
    "iso:country":"US",
    "sg:address":"4855 Whitesburg Dr S",
    "sg:city":"Huntsville",
    "sg:classifiers":[
        {
            "category":"Cafe",
            "type":"Food & Drink"
        }
    ],
    "sg:menulink":"http://www.allmenus.com/al/huntsville/54905-tellinis-cafe--grill/menu/",
    "sg:phone":"+1 256 881 9155",
    "sg:postcode":"35802",
    "sg:province":"AL",
    "sg:tags":[
        "italian"
    ],
    "wof:name":"Tellinis Cafe & Grill",
    "wof:placetype":"venue"
},
  "geometry": {"coordinates":[-86.56815899999999,34.692515],"type":"Point"}
}