{
  "type": "Feature",
  "properties": {
    "iso:country":"US",
    "sg:address":"14195 Ripley Rd",
    "sg:city":"Athens",
    "sg:classifiers":[
        {
            "category":"Wholesale",
            "subcategory":"Machinery & Supplies",
            "type":"Manufacturing & Wholesale Goods"
        }
    ],
    "sg:phone":"+1 256 232 5533",
    "sg:postcode":"35611",
    "sg:province":"AL",
    "sg:tags":[
        "equipment",
        "establishment"
    ],
    "wof:name":"Baugher Enterprises Inc",
    "wof:placetype":"venue"
},
  "geometry": {"coordinates":[-87.070695,34.754106],"type":"Point"}
}