{
  "type": "Feature",
  "properties": {
    "addr:full":"100 Blacksher Ct Mobile AL 36606",
    "addr:housenumber":"100",
    "addr:postcode":"36606",
    "addr:street":"Blacksher Ct",
    "iso:country":"US",
    "sg:address":"100 Blacksher Ct",
    "sg:city":"Mobile",
    "sg:classifiers":[
        {
            "category":"Building & Trades",
            "subcategory":"Construction",
            "type":"Services"
        }
    ],
    "sg:phone":"+1 251 479 9139",
    "sg:postcode":"36606",
    "sg:province":"AL",
    "sg:tags":[
        "hanging",
        "contractor"
    ],
    "wof:name":"Chapman Painting CL",
    "wof:placetype":"venue"
},
  "geometry": {"coordinates":[-88.11162299999999,30.68397],"type":"Point"}
}