{
  "type": "Feature",
  "properties": {
    "addr:full":"1025 Douglas Ave Brewton AL 36426",
    "addr:housenumber":"1025",
    "addr:postcode":"36426",
    "addr:street":"Douglas Ave",
    "iso:country":"US",
    "sg:address":"1025 Douglas Ave",
    "sg:city":"Brewton",
    "sg:classifiers":[
        {
            "category":"Shopping",
            "subcategory":"Beauty & Cosmetics",
            "type":"Retail Goods"
        },
        {
            "category":"Retail",
            "subcategory":"Photofinishing",
            "type":"Services"
        },
        {
            "category":"Shopping",
            "subcategory":"Pharmacy",
            "type":"Retail Goods"
        }
    ],
    "sg:phone":"+1 251 743 4854",
    "sg:postcode":"36426",
    "sg:province":"AL",
    "sg:tags":[
        "equipment",
        "photo",
        "finishing",
        "perfume",
        "supply"
    ],
    "wof:name":"Rite Aid",
    "wof:placetype":"venue"
},
  "geometry": {"coordinates":[-87.06217599999999,31.13847],"type":"Point"}
}