{
  "type": "Feature",
  "properties": {
    "iso:country":"US",
    "sg:address":"6545 US Hwy 31",
    "sg:city":"Verbena",
    "sg:classifiers":[
        {
            "category":"Food & Beverages",
            "subcategory":"Groceries & Convenience Stores",
            "type":"Retail Goods"
        }
    ],
    "sg:phone":"+1 205 755 4301",
    "sg:postcode":"36091",
    "sg:province":"AL",
    "wof:name":"Sandys Bent & Dent Grocery",
    "wof:placetype":"venue"
},
  "geometry": {"coordinates":[-86.511917,32.754602],"type":"Point"}
}