{
  "type": "Feature",
  "properties": {
    "addr:full":"4025 Old Leeds Cir Birmingham AL 35213",
    "addr:housenumber":"4025",
    "addr:postcode":"35213",
    "addr:street":"Old Leeds Cir",
    "iso:country":"US",
    "sg:address":"4025 Old Leeds Cir",
    "sg:city":"Birmingham",
    "sg:classifiers":[
        {
            "category":"Manufacturing",
            "subcategory":"Chemicals & Compounds",
            "type":"Manufacturing & Wholesale Goods"
        },
        {
            "category":"Home & Garden",
            "subcategory":"Home Furnishings",
            "type":"Retail Goods"
        },
        {
            "category":"Professional",
            "subcategory":"Art Services",
            "type":"Services"
        },
        {
            "category":"Home & Garden",
            "subcategory":"Furniture",
            "type":"Retail Goods"
        }
    ],
    "sg:phone":"+1 205 870 8195",
    "sg:postcode":"35213",
    "sg:province":"AL",
    "sg:tags":[
        "product",
        "designer",
        "house",
        "decorator",
        "wicker",
        "interior",
        "store"
    ],
    "wof:name":"Iron Art Inc",
    "wof:placetype":"venue"
},
  "geometry": {"coordinates":[-86.733515,33.496967],"type":"Point"}
}