{
  "type": "Feature",
  "properties": {
    "addr:full":"121 S Ross St Auburn AL 36830",
    "addr:housenumber":"121",
    "addr:postcode":"36830",
    "addr:street":"S Ross St",
    "iso:country":"US",
    "sg:address":"121 S Ross St",
    "sg:city":"Auburn",
    "sg:classifiers":[
        {
            "category":"Personal",
            "subcategory":"Beauty Salon",
            "type":"Services"
        }
    ],
    "sg:phone":"+1 334 821 7147",
    "sg:postcode":"36830",
    "sg:province":"AL",
    "sg:tags":[
        "shop"
    ],
    "wof:name":"Hair It Is",
    "wof:placetype":"venue"
},
  "geometry": {"coordinates":[-85.47492099999999,32.606513],"type":"Point"}
}