{
  "type": "Feature",
  "properties": {
    "iso:country":"US",
    "sg:address":"12985 Saddlebrook Cir",
    "sg:city":"Fairhope",
    "sg:classifiers":[
        {
            "category":"Professional",
            "type":"Services"
        }
    ],
    "sg:phone":"+1 251 928 1670",
    "sg:postcode":"36532",
    "sg:province":"AL",
    "sg:tags":[
        "establishment"
    ],
    "wof:name":"Luxury Asset Exchange Inc",
    "wof:placetype":"venue"
},
  "geometry": {"coordinates":[-87.843432,30.404584],"type":"Point"}
}