{
  "type": "Feature",
  "properties": {
    "iso:country":"US",
    "sg:address":"5570 County Line Rd",
    "sg:city":"Leighton",
    "sg:classifiers":[
        {
            "category":"Shopping",
            "subcategory":"Used Merchandise",
            "type":"Retail Goods"
        }
    ],
    "sg:phone":"+1 256 446 5162",
    "sg:postcode":"35646",
    "sg:province":"AL",
    "sg:tags":[
        "antique"
    ],
    "wof:name":"White Oak Antiques Inc",
    "wof:placetype":"venue"
},
  "geometry": {"coordinates":[-87.528546,34.662009],"type":"Point"}
}