{
  "type": "Feature",
  "properties": {
    "iso:country":"US",
    "sg:address":"357 Forest Ave",
    "sg:city":"Luverne",
    "sg:classifiers":[
        {
            "category":"Insurance",
            "subcategory":"Insurance Agent",
            "type":"Services"
        }
    ],
    "sg:phone":"+1 334 335 3354",
    "sg:postcode":"36049",
    "sg:province":"AL",
    "wof:name":"Alfa Insurance Corp",
    "wof:placetype":"venue"
},
  "geometry": {"coordinates":[-86.263837,31.713047],"type":"Point"}
}