{
  "type": "Feature",
  "properties": {
    "iso:country":"US",
    "sg:address":"4031 Airport Blvd",
    "sg:city":"Mobile",
    "sg:classifiers":[
        {
            "category":"Professional",
            "type":"Services"
        }
    ],
    "sg:phone":"+1 251 380 0853",
    "sg:postcode":"36608",
    "sg:province":"AL",
    "wof:name":"Jennifer L Fanks",
    "wof:placetype":"venue"
},
  "geometry": {"coordinates":[-88.151544,30.675891],"type":"Point"}
}