{
  "type": "Feature",
  "properties": {
    "iso:country":"US",
    "sg:address":"443 Co Rd 92",
    "sg:city":"Graham",
    "sg:classifiers":[
        {
            "category":"Professional",
            "type":"Services"
        }
    ],
    "sg:phone":"+1 256 568 7505",
    "sg:postcode":"36263",
    "sg:province":"AL",
    "wof:name":"Lovvorn Power Systems LLC",
    "wof:placetype":"venue"
},
  "geometry": {"coordinates":[-85.377776,33.457439],"type":"Point"}
}