{
  "type": "Feature",
  "properties": {
    "iso:country":"US",
    "sg:address":"9190 Old Hwy 9",
    "sg:city":"Cedar Bluff",
    "sg:classifiers":[
        {
            "category":"Building & Trades",
            "subcategory":"Plumbing",
            "type":"Services"
        }
    ],
    "sg:phone":"+1 256 779 8638",
    "sg:postcode":"35959",
    "sg:province":"AL",
    "sg:tags":[
        "septic"
    ],
    "wof:name":"Pee Wee's Pumping Svc",
    "wof:placetype":"venue"
},
  "geometry": {"coordinates":[-85.59971400000001,34.221471],"type":"Point"}
}