{
  "type": "Feature",
  "properties": {
    "addr:full":"33600 State Rte 22 Verbena AL 36091",
    "addr:housenumber":"33600",
    "addr:postcode":"36091",
    "addr:street":"State Rte 22 Verbena",
    "iso:country":"US",
    "sg:address":"33600 State Rte 22",
    "sg:city":"Verbena",
    "sg:classifiers":[
        {
            "category":"Wholesale",
            "subcategory":"Farm Supplies",
            "type":"Manufacturing & Wholesale Goods"
        }
    ],
    "sg:phone":"+1 205 755 6887",
    "sg:postcode":"36091",
    "sg:province":"AL",
    "sg:tags":[
        "raw",
        "product",
        "material"
    ],
    "wof:name":"Verbena Pecan Company",
    "wof:placetype":"venue"
},
  "geometry": {"coordinates":[-86.50966099999999,32.772412],"type":"Point"}
}