{
  "type": "Feature",
  "properties": {
    "addr:full":"5484 Amber Hills Rd Birmingham AL 35210",
    "addr:housenumber":"5484",
    "addr:postcode":"35210",
    "addr:street":"Amber Hills Rd",
    "iso:country":"US",
    "sg:address":"5484 Amber Hills Rd",
    "sg:city":"Birmingham",
    "sg:classifiers":[
        {
            "category":"Building & Trades",
            "subcategory":"Plumbing",
            "type":"Services"
        }
    ],
    "sg:phone":"+1 205 956 8906",
    "sg:postcode":"35210",
    "sg:province":"AL",
    "sg:tags":[
        "plumbing",
        "contractor"
    ],
    "wof:name":"Best Plumbing & Drain Svc",
    "wof:placetype":"venue"
},
  "geometry": {"coordinates":[-86.640198,33.566912],"type":"Point"}
}