{
  "type": "Feature",
  "properties": {
    "iso:country":"US",
    "sg:address":"307 N Main St",
    "sg:city":"Enterprise",
    "sg:classifiers":[
        {
            "category":"Organizations",
            "subcategory":"Religious Organization",
            "type":"Services"
        }
    ],
    "sg:phone":"+1 334 393 4471",
    "sg:postcode":"36330",
    "sg:province":"AL",
    "wof:name":"Christian Mission Bargain Ctr",
    "wof:placetype":"venue"
},
  "geometry": {"coordinates":[-85.856455,31.31723],"type":"Point"}
}