{
  "type": "Feature",
  "properties": {
    "iso:country":"US",
    "sg:address":"123 Grice St",
    "sg:city":"Brewton",
    "sg:classifiers":[
        {
            "category":"Building & Trades",
            "subcategory":"Construction",
            "type":"Services"
        }
    ],
    "sg:phone":"+1 251 867 2903",
    "sg:postcode":"36426",
    "sg:province":"AL",
    "sg:tags":[
        "house",
        "light"
    ],
    "wof:name":"Sr Scott Builders",
    "wof:placetype":"venue"
},
  "geometry": {"coordinates":[-87.060215,31.090149],"type":"Point"}
}