{
  "type": "Feature",
  "properties": {
    "iso:country":"US",
    "sg:address":"1694 Montgomery Hwy",
    "sg:city":"Vestavia",
    "sg:classifiers":[
        {
            "category":"Coffee & Tea",
            "type":"Food & Drink"
        },
        {
            "category":"Restaurant",
            "type":"Food & Drink"
        }
    ],
    "sg:phone":"+1 205 978 5599",
    "sg:postcode":"35216",
    "sg:province":"AL",
    "sg:tags":[
        "espresso"
    ],
    "wof:name":"Smokey Joes",
    "wof:placetype":"venue"
},
  "geometry": {"coordinates":[-86.80661000000001,33.388435],"type":"Point"}
}