{
  "type": "Feature",
  "properties": {
    "iso:country":"US",
    "sg:address":"14304 Rockhouse Rd",
    "sg:city":"Brookwood",
    "sg:classifiers":[
        {
            "category":"Professional",
            "subcategory":"Business Services",
            "type":"Services"
        }
    ],
    "sg:phone":"+1 205 477 4082",
    "sg:postcode":"35444",
    "sg:province":"AL",
    "sg:tags":[
        "transcribing",
        "disc"
    ],
    "wof:name":"C & C Transcription Svc",
    "wof:placetype":"venue"
},
  "geometry": {"coordinates":[-87.162992,33.309031],"type":"Point"}
}