{
  "type": "Feature",
  "properties": {
    "addr:full":"8857 Clubhouse Cir Pinson AL 35126",
    "addr:housenumber":"8857",
    "addr:postcode":"35126",
    "addr:street":"Clubhouse Cir",
    "iso:country":"US",
    "sg:address":"8857 Clubhouse Cir",
    "sg:city":"Pinson",
    "sg:classifiers":[
        {
            "category":"Manufacturing",
            "subcategory":"Printing",
            "type":"Manufacturing & Wholesale Goods"
        }
    ],
    "sg:phone":"+1 205 833 0011",
    "sg:postcode":"35126",
    "sg:province":"AL",
    "sg:tags":[
        "lithographic",
        "printer",
        "commercial"
    ],
    "wof:name":"Ellis Printing Inc",
    "wof:placetype":"venue"
},
  "geometry": {"coordinates":[-86.61051500000001,33.76175],"type":"Point"}
}