{
  "type": "Feature",
  "properties": {
    "addr:full":"3500 Main St Adamsville AL 35005",
    "addr:housenumber":"3500",
    "addr:postcode":"35005",
    "addr:street":"Main St",
    "iso:country":"US",
    "sg:address":"3500 Main St",
    "sg:city":"Adamsville",
    "sg:classifiers":[
        {
            "category":"Banks & Credit Unions",
            "subcategory":"Bank",
            "type":"Services"
        },
        {
            "category":"Banks & Credit Unions",
            "subcategory":"Financial Services",
            "type":"Services"
        }
    ],
    "sg:phone":"+1 205 743 2011",
    "sg:postcode":"35005",
    "sg:province":"AL",
    "sg:tags":[
        "commercial",
        "loan",
        "saving",
        "mortgage"
    ],
    "sg:website":"https://www.wachovia.com/?DCMP=KNL-CPS-DS-Directory-0703&HBX_PK=Banks&HBX_OU=71",
    "wof:name":"Wachovia Bank",
    "wof:placetype":"venue"
},
  "geometry": {"coordinates":[-86.935952,33.587284],"type":"Point"}
}