{
  "type": "Feature",
  "properties": {
    "iso:country":"US",
    "sg:address":"237 Oxmoor Cir Ste 101",
    "sg:city":"Birmingham",
    "sg:classifiers":[
        {
            "category":"Professional",
            "subcategory":"Detective & Security Services",
            "type":"Services"
        }
    ],
    "sg:phone":"+1 205 945 0003",
    "sg:postcode":"35209",
    "sg:province":"AL",
    "sg:tags":[
        "control",
        "television",
        "monitoring",
        "consultant",
        "system",
        "equipment",
        "systems-closed",
        "circuit",
        "telecasting"
    ],
    "sg:website":"http://www.alscaninc.com",
    "wof:name":"Alscan Inc",
    "wof:placetype":"venue"
},
  "geometry": {"coordinates":[-86.83603100000001,33.453083],"type":"Point"}
}