{
  "type": "Feature",
  "properties": {
    "addr:full":"301 N Walston Bridge Rd Jasper AL 35504",
    "addr:housenumber":"301",
    "addr:postcode":"35504",
    "addr:street":"N Walston Bridge Rd",
    "iso:country":"US",
    "sg:address":"301 N Walston Bridge Rd",
    "sg:city":"Jasper",
    "sg:classifiers":[
        {
            "category":"Government",
            "subcategory":"Office",
            "type":"Public Place"
        }
    ],
    "sg:phone":"+1 205 221 7840",
    "sg:postcode":"35504",
    "sg:province":"AL",
    "sg:tags":[
        "state",
        "program"
    ],
    "wof:name":"Vocational Rehabilitation Svc",
    "wof:placetype":"venue"
},
  "geometry": {"coordinates":[-87.256895,33.850472],"type":"Point"}
}