{
  "type": "Feature",
  "properties": {
    "iso:country":"US",
    "sg:address":"801 E Tennessee St",
    "sg:city":"Florence",
    "sg:classifiers":[
        {
            "category":"Autos & Motor Vehicles",
            "subcategory":"Automobile Sales",
            "type":"Retail Goods"
        }
    ],
    "sg:phone":"+1 256 766 5520",
    "sg:postcode":"35630",
    "sg:province":"AL",
    "sg:tags":[
        "used"
    ],
    "wof:name":"Jenkins Auto Sales LLC",
    "wof:placetype":"venue"
},
  "geometry": {"coordinates":[-87.66552799999999,34.804615],"type":"Point"}
}