{
  "type": "Feature",
  "properties": {
    "addr:full":"1208 Kentucky Ave Stevenson AL 35772",
    "addr:housenumber":"1208",
    "addr:postcode":"35772",
    "addr:street":"Kentucky Ave",
    "iso:country":"US",
    "sg:address":"1208 Kentucky Ave",
    "sg:city":"Stevenson",
    "sg:classifiers":[
        {
            "category":"Shopping",
            "type":"Retail Goods"
        }
    ],
    "sg:phone":"+1 256 437 1005",
    "sg:postcode":"35772",
    "sg:province":"AL",
    "sg:tags":[
        "candle"
    ],
    "wof:name":"Log Cabin Candles",
    "wof:placetype":"venue"
},
  "geometry": {"coordinates":[-85.82545500000001,34.85627],"type":"Point"}
}