{
  "type": "Feature",
  "properties": {
    "iso:country":"US",
    "sg:address":"2001 Brae Trl",
    "sg:city":"Birmingham",
    "sg:classifiers":[
        {
            "category":"Farming",
            "subcategory":"Farm",
            "type":"Manufacturing & Wholesale Goods"
        }
    ],
    "sg:phone":"+1 205 991 3915",
    "sg:postcode":"35242",
    "sg:province":"AL",
    "wof:name":"Greystone Farms Owners Assn",
    "wof:placetype":"venue"
},
  "geometry": {"coordinates":[-86.647437,33.416779],"type":"Point"}
}