{
  "type": "Feature",
  "properties": {
    "addr:full":"1129 Talucah Rd Valhermoso Spgs AL 35775",
    "addr:housenumber":"1129",
    "addr:postcode":"35775",
    "addr:street":"Talucah Rd;Spgs",
    "iso:country":"US",
    "sg:address":"1129 Talucah Rd",
    "sg:city":"Valhermoso Spgs",
    "sg:classifiers":[
        {
            "category":"Organizations",
            "subcategory":"Religious Organization",
            "type":"Services"
        }
    ],
    "sg:phone":"+1 256 778 9519",
    "sg:postcode":"35775",
    "sg:province":"AL",
    "sg:tags":[
        "church"
    ],
    "wof:name":"Mt Pleasant Missionary Baptist",
    "wof:placetype":"venue"
},
  "geometry": {"coordinates":[-86.686533,34.542778],"type":"Point"}
}