{
  "type": "Feature",
  "properties": {
    "addr:full":"651 Fiber St NW Huntsville AL 35801",
    "addr:housenumber":"651",
    "addr:postcode":"35801",
    "addr:street":"Fiber St Nw",
    "iso:country":"US",
    "sg:address":"651 Fiber St NW",
    "sg:city":"Huntsville",
    "sg:classifiers":[
        {
            "category":"Building & Trades",
            "subcategory":"Plumbing",
            "type":"Services"
        }
    ],
    "sg:phone":"+1 256 536 0204",
    "sg:postcode":"35801",
    "sg:province":"AL",
    "sg:tags":[
        "contractor"
    ],
    "wof:name":"Stanley Jones Corp",
    "wof:placetype":"venue"
},
  "geometry": {"coordinates":[-86.597317,34.736535],"type":"Point"}
}