{
  "type": "Feature",
  "properties": {
    "iso:country":"US",
    "sg:address":"3700 1st Ave N",
    "sg:city":"Birmingham",
    "sg:classifiers":[
        {
            "category":"Wholesale",
            "subcategory":"Stationery",
            "type":"Manufacturing & Wholesale Goods"
        }
    ],
    "sg:phone":"+1 205 328 2626",
    "sg:postcode":"35222",
    "sg:province":"AL",
    "sg:tags":[
        "packaging",
        "material"
    ],
    "sg:website":"www.citypaper2.com",
    "wof:name":"City Ad Specialties",
    "wof:placetype":"venue"
},
  "geometry": {"coordinates":[-86.780676,33.526368],"type":"Point"}
}