{
  "type": "Feature",
  "properties": {
    "addr:full":"5 N Pointe Pkwy Enterprise AL 36330",
    "addr:housenumber":"5",
    "addr:postcode":"36330",
    "addr:street":"N Pointe Pkwy Enterprise",
    "iso:country":"US",
    "sg:address":"5 N Pointe Pkwy",
    "sg:city":"Enterprise",
    "sg:classifiers":[
        {
            "category":"Restaurant",
            "type":"Food & Drink"
        }
    ],
    "sg:menulink":"http://www.allmenus.com/al/enterprise/121025-subway/menu/",
    "sg:phone":"+1 334 347 3373",
    "sg:postcode":"36330",
    "sg:province":"AL",
    "sg:tags":[
        "american",
        "sandwich"
    ],
    "wof:name":"Subway",
    "wof:placetype":"venue"
},
  "geometry": {"coordinates":[-85.85658100000001,31.337453],"type":"Point"}
}