{
  "type": "Feature",
  "properties": {
    "iso:country":"US",
    "sg:address":"308 Dekalb St",
    "sg:city":"Marion",
    "sg:classifiers":[
        {
            "category":"Education",
            "subcategory":"Library",
            "type":"Public Place"
        }
    ],
    "sg:phone":"+1 334 683 5184",
    "sg:postcode":"36756",
    "sg:province":"AL",
    "wof:name":"Bowling Library",
    "wof:placetype":"venue"
},
  "geometry": {"coordinates":[-87.324817,32.631064],"type":"Point"}
}