{
  "type": "Feature",
  "properties": {
    "iso:country":"US",
    "sg:address":"501 5th St SW",
    "sg:city":"Cullman",
    "sg:classifiers":[
        {
            "category":"Professional",
            "subcategory":"Accounting & Tax Preparation",
            "type":"Services"
        }
    ],
    "sg:phone":"+1 256 739 0312",
    "sg:postcode":"35055",
    "sg:province":"AL",
    "sg:tags":[
        "accountant"
    ],
    "wof:name":"Warren Avertt Kimbrough Marino",
    "wof:placetype":"venue"
},
  "geometry": {"coordinates":[-86.845672,34.171425],"type":"Point"}
}