{
  "type": "Feature",
  "properties": {
    "iso:country":"US",
    "sg:address":"602 Cox Creek Pkwy",
    "sg:city":"Florence",
    "sg:classifiers":[
        {
            "category":"Food & Beverages",
            "subcategory":"Groceries & Convenience Stores",
            "type":"Retail Goods"
        }
    ],
    "sg:phone":"+1 256 760 5221",
    "sg:postcode":"35630",
    "sg:province":"AL",
    "wof:name":"Cowboy's",
    "wof:placetype":"venue"
},
  "geometry": {"coordinates":[-87.659376,34.843971],"type":"Point"}
}