{
  "type": "Feature",
  "properties": {
    "iso:country":"US",
    "sg:address":"675 Co Rd 406",
    "sg:city":"Thorsby",
    "sg:classifiers":[
        {
            "category":"Building & Trades",
            "subcategory":"Construction",
            "type":"Services"
        }
    ],
    "sg:phone":"+1 205 280 0067",
    "sg:postcode":"35045",
    "sg:province":"AL",
    "sg:tags":[
        "concrete",
        "contractor"
    ],
    "wof:name":"Southern Oak Construction",
    "wof:placetype":"venue"
},
  "geometry": {"coordinates":[-86.693869,32.847416],"type":"Point"}
}