{
  "type": "Feature",
  "properties": {
    "addr:full":"501 Alexandria Rd SW Jacksonville AL 36265",
    "addr:housenumber":"501",
    "addr:postcode":"36265",
    "addr:street":"Alexandria Rd Sw",
    "iso:country":"US",
    "sg:address":"501 Alexandria Rd SW",
    "sg:city":"Jacksonville",
    "sg:classifiers":[
        {
            "category":"Government",
            "subcategory":"Office",
            "type":"Public Place"
        }
    ],
    "sg:phone":"+1 256 435 8115",
    "sg:postcode":"36265",
    "sg:province":"AL",
    "sg:tags":[
        "dept",
        "recreation",
        "parks"
    ],
    "wof:name":"Parks & Recreation",
    "wof:placetype":"venue"
},
  "geometry": {"coordinates":[-85.771976,33.813279],"type":"Point"}
}