{
  "type": "Feature",
  "properties": {
    "iso:country":"US",
    "sg:address":"3100 Masters Dr SE",
    "sg:city":"Owens Cross Rds",
    "sg:classifiers":[
        {
            "category":"Social Services",
            "subcategory":"Job Training",
            "type":"Services"
        }
    ],
    "sg:phone":"+1 256 534 9639",
    "sg:postcode":"35763",
    "sg:province":"AL",
    "sg:tags":[
        "career",
        "counseling",
        "vocational"
    ],
    "wof:name":"John W Mc Kinney III",
    "wof:placetype":"venue"
},
  "geometry": {"coordinates":[-86.477294,34.662617],"type":"Point"}
}