{
  "type": "Feature",
  "properties": {
    "iso:country":"US",
    "sg:address":"115 Division Rd",
    "sg:city":"Montgomery",
    "sg:classifiers":[
        {
            "category":"Utilities",
            "subcategory":"Refuse",
            "type":"Services"
        }
    ],
    "sg:phone":"+1 334 240 4526",
    "sg:postcode":"36104",
    "sg:province":"AL",
    "sg:tags":[
        "system"
    ],
    "wof:name":"Municipal Landfill",
    "wof:placetype":"venue"
},
  "geometry": {"coordinates":[-86.321756,32.406866],"type":"Point"}
}