{
  "type": "Feature",
  "properties": {
    "iso:country":"US",
    "sg:address":"2435 Lower Wetumpka Rd",
    "sg:city":"Montgomery",
    "sg:classifiers":[
        {
            "category":"Retail",
            "subcategory":"Auto Rental",
            "type":"Services"
        }
    ],
    "sg:phone":"+1 334 269 2202",
    "sg:postcode":"36110",
    "sg:province":"AL",
    "sg:tags":[
        "passenger",
        "car"
    ],
    "wof:name":"Coyote Ugly",
    "wof:placetype":"venue"
},
  "geometry": {"coordinates":[-86.289772,32.40627],"type":"Point"}
}