{
  "type": "Feature",
  "properties": {
    "addr:full":"6543 Moores Mill Rd Huntsville AL 35811",
    "addr:housenumber":"6543",
    "addr:postcode":"35811",
    "addr:street":"Moores Mill Rd",
    "iso:country":"US",
    "sg:address":"6543 Moores Mill Rd",
    "sg:city":"Huntsville",
    "sg:classifiers":[
        {
            "category":"Retail",
            "subcategory":"Auto Repair",
            "type":"Services"
        }
    ],
    "sg:phone":"+1 256 852 6929",
    "sg:postcode":"35811",
    "sg:province":"AL",
    "sg:tags":[
        "body",
        "wheel",
        "axle",
        "alignment"
    ],
    "wof:name":"Dale's Body Shop",
    "wof:placetype":"venue"
},
  "geometry": {"coordinates":[-86.53590199999999,34.817615],"type":"Point"}
}