{
  "type": "Feature",
  "properties": {
    "addr:full":"1610 Goins Rd Childersburg AL 35044",
    "addr:housenumber":"1610",
    "addr:postcode":"35044",
    "addr:street":"Goins Rd",
    "iso:country":"US",
    "sg:address":"1610 Goins Rd",
    "sg:city":"Childersburg",
    "sg:classifiers":[
        {
            "category":"Professional",
            "type":"Services"
        }
    ],
    "sg:phone":"+1 256 378 3201",
    "sg:postcode":"35044",
    "sg:province":"AL",
    "sg:tags":[
        "establishment"
    ],
    "wof:name":"JWG Inc",
    "wof:placetype":"venue"
},
  "geometry": {"coordinates":[-86.42537400000001,33.195799],"type":"Point"}
}