{
  "type": "Feature",
  "properties": {
    "iso:country":"US",
    "sg:address":"2305 Shady Grove Ln SW",
    "sg:city":"Decatur",
    "sg:classifiers":[
        {
            "category":"Autos & Motor Vehicles",
            "subcategory":"Fuel & Gas Station",
            "type":"Retail Goods"
        }
    ],
    "sg:phone":"+1 256 353 0163",
    "sg:postcode":"35603",
    "sg:province":"AL",
    "sg:tags":[
        "station",
        "gasoline"
    ],
    "wof:name":"Mojos Deli & Texaco",
    "wof:placetype":"venue"
},
  "geometry": {"coordinates":[-87.05312,34.566689],"type":"Point"}
}