{
  "type": "Feature",
  "properties": {
    "iso:country":"US",
    "sg:address":"4969 Luker Rd SW",
    "sg:city":"Decatur",
    "sg:classifiers":[
        {
            "category":"Building & Trades",
            "subcategory":"Construction",
            "type":"Services"
        }
    ],
    "sg:phone":"+1 256 306 9093",
    "sg:postcode":"35603",
    "sg:province":"AL",
    "sg:tags":[
        "house"
    ],
    "wof:name":"Ajs Painting & Home Imprvs",
    "wof:placetype":"venue"
},
  "geometry": {"coordinates":[-86.96516200000001,34.505955],"type":"Point"}
}