{
  "type": "Feature",
  "properties": {
    "iso:country":"US",
    "sg:address":"367 Scott Rd",
    "sg:city":"Alexander City",
    "sg:classifiers":[
        {
            "category":"Sports & Exercise",
            "subcategory":"Race Track",
            "type":"Entertainment"
        },
        {
            "category":"Retail",
            "subcategory":"Animal Services",
            "type":"Services"
        }
    ],
    "sg:phone":"+1 256 234 6111",
    "sg:postcode":"35010",
    "sg:province":"AL",
    "sg:tags":[
        "washing",
        "pet",
        "or",
        "grooming",
        "racing",
        "operation"
    ],
    "wof:name":"Charlene's Pet Grooming",
    "wof:placetype":"venue"
},
  "geometry": {"coordinates":[-85.933007,32.940373],"type":"Point"}
}