{
  "type": "Feature",
  "properties": {
    "addr:full":"2929 Pinehaven Dr Birmingham AL 35223",
    "addr:housenumber":"2929",
    "addr:postcode":"35223",
    "addr:street":"Pinehaven Dr",
    "iso:country":"US",
    "sg:address":"2929 Pinehaven Dr",
    "sg:city":"Birmingham",
    "sg:classifiers":[
        {
            "category":"Professional",
            "subcategory":"Business Services",
            "type":"Services"
        }
    ],
    "sg:phone":"+1 205 907 3404",
    "sg:postcode":"35223",
    "sg:province":"AL",
    "wof:name":"Sharp Minds LLC",
    "wof:placetype":"venue"
},
  "geometry": {"coordinates":[-86.759913,33.486733],"type":"Point"}
}