{
  "type": "Feature",
  "properties": {
    "iso:country":"US",
    "sg:address":"1101 Jackson Ave",
    "sg:city":"Tuscaloosa",
    "sg:classifiers":[
        {
            "category":"Government",
            "subcategory":"Office",
            "type":"Public Place"
        }
    ],
    "sg:phone":"+1 205 345 4131",
    "sg:postcode":"35401",
    "sg:province":"AL",
    "sg:tags":[
        "county",
        "program",
        "health"
    ],
    "wof:name":"Tuscaloosa County Health Dept",
    "wof:placetype":"venue"
},
  "geometry": {"coordinates":[-87.532927,33.203255],"type":"Point"}
}