{
  "type": "Feature",
  "properties": {
    "addr:full":"2495 Co Rd 67 Selma AL 36701",
    "addr:housenumber":"2495;67",
    "addr:postcode":"36701",
    "addr:street":"Co Rd",
    "iso:country":"US",
    "sg:address":"2495 Co Rd 67",
    "sg:city":"Selma",
    "sg:classifiers":[
        {
            "category":"Shopping",
            "type":"Retail Goods"
        }
    ],
    "sg:phone":"+1 334 874 4188",
    "sg:postcode":"36701",
    "sg:province":"AL",
    "sg:tags":[
        "trophy",
        "or",
        "plaque"
    ],
    "wof:name":"Quality Trophies and Plaques",
    "wof:placetype":"venue"
},
  "geometry": {"coordinates":[-86.949563,32.300659],"type":"Point"}
}