{
  "type": "Feature",
  "properties": {
    "iso:country":"US",
    "sg:address":"1604 Exeter Ave",
    "sg:city":"Bessemer",
    "sg:classifiers":[
        {
            "category":"Restaurant",
            "type":"Food & Drink"
        }
    ],
    "sg:phone":"+1 205 425 3595",
    "sg:postcode":"35020",
    "sg:province":"AL",
    "sg:tags":[
        "eating"
    ],
    "wof:name":"Lotta Papa",
    "wof:placetype":"venue"
},
  "geometry": {"coordinates":[-86.946066,33.395057],"type":"Point"}
}