{
  "type": "Feature",
  "properties": {
    "addr:full":"13370 Ave B Wilmer AL 36587",
    "addr:housenumber":"13370",
    "addr:postcode":"36587",
    "addr:street":"Ave B",
    "iso:country":"US",
    "sg:address":"13370 Ave B",
    "sg:city":"Wilmer",
    "sg:classifiers":[
        {
            "category":"Organizations",
            "subcategory":"Religious Organization",
            "type":"Services"
        }
    ],
    "sg:phone":"+1 251 649 1800",
    "sg:postcode":"36587",
    "sg:province":"AL",
    "sg:tags":[
        "church"
    ],
    "wof:name":"Wilmer United Methodist Church",
    "wof:placetype":"venue"
},
  "geometry": {"coordinates":[-88.359398,30.825158],"type":"Point"}
}