{
  "type": "Feature",
  "properties": {
    "addr:full":"5732 US Hwy 431 Brownsboro AL 35741",
    "addr:housenumber":"5732",
    "addr:postcode":"35741",
    "addr:street":"Us Hwy 431",
    "iso:country":"US",
    "sg:address":"5732 US Hwy 431",
    "sg:city":"Brownsboro",
    "sg:classifiers":[
        {
            "category":"Shopping",
            "subcategory":"Clothing, Apparel, & Fashions",
            "type":"Retail Goods"
        }
    ],
    "sg:phone":"+1 256 534 3232",
    "sg:postcode":"35741",
    "sg:province":"AL",
    "wof:name":"Primarily Purple",
    "wof:placetype":"venue"
},
  "geometry": {"coordinates":[-86.500973,34.687692],"type":"Point"}
}