{
  "type": "Feature",
  "properties": {
    "iso:country":"US",
    "sg:address":"760 Skyland Blvd",
    "sg:city":"Tuscaloosa",
    "sg:classifiers":[
        {
            "category":"Restaurant",
            "type":"Food & Drink"
        }
    ],
    "sg:phone":"+1 205 469 7447",
    "sg:postcode":"35405",
    "sg:province":"AL",
    "sg:website":"www.goldenrulebbq.com",
    "wof:name":"Golden Rule BBQ-Tuscaloosa",
    "wof:placetype":"venue"
},
  "geometry": {"coordinates":[-87.549239,33.165255],"type":"Point"}
}