{
  "type": "Feature",
  "properties": {
    "addr:full":"1545 Blessing Rd Albertville AL 35957",
    "addr:housenumber":"1545",
    "addr:postcode":"35957",
    "addr:street":"Blessing Rd",
    "iso:country":"US",
    "sg:address":"1545 Blessing Rd",
    "sg:city":"Albertville",
    "sg:classifiers":[
        {
            "category":"Building & Trades",
            "subcategory":"Construction",
            "type":"Services"
        }
    ],
    "sg:phone":"+1 256 878 6315",
    "sg:postcode":"35957",
    "sg:province":"AL",
    "sg:tags":[
        "concrete",
        "contractor"
    ],
    "wof:name":"Ralph Minor & Sons Concrete",
    "wof:placetype":"venue"
},
  "geometry": {"coordinates":[-86.133667,34.259729],"type":"Point"}
}