{
  "type": "Feature",
  "properties": {
    "iso:country":"US",
    "sg:address":"3360 Lake Ter",
    "sg:city":"Millbrook",
    "sg:classifiers":[
        {
            "category":"Health Services",
            "subcategory":"Clinic",
            "type":"Services"
        }
    ],
    "sg:phone":"+1 334 290 3470",
    "sg:postcode":"36054",
    "sg:province":"AL",
    "sg:tags":[
        "kidney",
        "dialysis",
        "center"
    ],
    "wof:name":"Physicians Dialysis Inc",
    "wof:placetype":"venue"
},
  "geometry": {"coordinates":[-86.367329,32.479799],"type":"Point"}
}