{
  "type": "Feature",
  "properties": {
    "iso:country":"US",
    "sg:address":"162 Liberty Rd",
    "sg:city":"Tallassee",
    "sg:classifiers":[
        {
            "category":"Building & Trades",
            "subcategory":"Construction",
            "type":"Services"
        }
    ],
    "sg:phone":"+1 334 514 4347",
    "sg:postcode":"36078",
    "sg:province":"AL",
    "sg:tags":[
        "house"
    ],
    "wof:name":"Nabors Construction",
    "wof:placetype":"venue"
},
  "geometry": {"coordinates":[-86.004286,32.525083],"type":"Point"}
}