{
  "type": "Feature",
  "properties": {
    "iso:country":"US",
    "sg:address":"8434 Wire Rd",
    "sg:city":"Cottondale",
    "sg:classifiers":[
        {
            "category":"Building & Trades",
            "subcategory":"Construction",
            "type":"Services"
        }
    ],
    "sg:phone":"+1 205 556 6942",
    "sg:postcode":"35453",
    "sg:province":"AL",
    "sg:tags":[
        "contractor"
    ],
    "wof:name":"Browning Roofing",
    "wof:placetype":"venue"
},
  "geometry": {"coordinates":[-87.42751199999999,33.169318],"type":"Point"}
}