{
  "type": "Feature",
  "properties": {
    "iso:country":"US",
    "sg:address":"1726 N Wood Ave",
    "sg:city":"Florence",
    "sg:classifiers":[
        {
            "category":"Retail",
            "subcategory":"Repair Shop",
            "type":"Services"
        },
        {
            "category":"Building & Trades",
            "subcategory":"Plumbing",
            "type":"Services"
        }
    ],
    "sg:phone":"+1 256 766 0715",
    "sg:postcode":"35630",
    "sg:province":"AL",
    "sg:tags":[
        "appliance",
        "contractor"
    ],
    "wof:name":"A OK Appliance Repair",
    "wof:placetype":"venue"
},
  "geometry": {"coordinates":[-87.68260600000001,34.824829],"type":"Point"}
}