{
  "type": "Feature",
  "properties": {
    "iso:country":"US",
    "sg:address":"3751 Industrial Park Dr",
    "sg:city":"Mobile",
    "sg:classifiers":[
        {
            "category":"Professional",
            "subcategory":"Business Services",
            "type":"Services"
        }
    ],
    "sg:phone":"+1 251 660 7555",
    "sg:postcode":"36693",
    "sg:province":"AL",
    "wof:name":"David E Upchurch",
    "wof:placetype":"venue"
},
  "geometry": {"coordinates":[-88.128688,30.634714],"type":"Point"}
}