{
  "type": "Feature",
  "properties": {
    "addr:full":"1410 Co Rd 66 Woodland AL 36280",
    "addr:housenumber":"1410;66",
    "addr:postcode":"36280",
    "addr:street":"Co Rd",
    "iso:country":"US",
    "sg:address":"1410 Co Rd 66",
    "sg:city":"Woodland",
    "sg:classifiers":[
        {
            "category":"Manufacturing",
            "subcategory":"Glass & Minerals",
            "type":"Manufacturing & Wholesale Goods"
        }
    ],
    "sg:phone":"+1 256 363 2655",
    "sg:postcode":"36280",
    "sg:province":"AL",
    "sg:tags":[
        "excavation",
        "concrete",
        "product",
        "mfg",
        "contractor"
    ],
    "wof:name":"Wortham Excavating",
    "wof:placetype":"venue"
},
  "geometry": {"coordinates":[-85.500185,33.3984],"type":"Point"}
}