{
  "type": "Feature",
  "properties": {
    "iso:country":"US",
    "sg:address":"4608 Avenue W",
    "sg:city":"Birmingham",
    "sg:classifiers":[
        {
            "category":"Restaurant",
            "type":"Food & Drink"
        }
    ],
    "sg:menulink":"http://www.allmenus.com/al/birmingham/87581-little-caesars-pizza/menu/",
    "sg:phone":"+1 205 781 4004",
    "sg:postcode":"35208",
    "sg:province":"AL",
    "sg:tags":[
        "american",
        "pizza"
    ],
    "wof:name":"Little Caesar's Pizza",
    "wof:placetype":"venue"
},
  "geometry": {"coordinates":[-86.876519,33.496711],"type":"Point"}
}