{
  "type": "Feature",
  "properties": {
    "iso:country":"US",
    "sg:address":"212 US Hwy 43",
    "sg:city":"Saraland",
    "sg:classifiers":[
        {
            "category":"Shopping",
            "subcategory":"Gifts & Souvenirs",
            "type":"Retail Goods"
        }
    ],
    "sg:phone":"+1 251 675 7007",
    "sg:postcode":"36571",
    "sg:province":"AL",
    "sg:tags":[
        "cards",
        "greeting"
    ],
    "wof:name":"Bead Shack The",
    "wof:placetype":"venue"
},
  "geometry": {"coordinates":[-88.068395,30.829751],"type":"Point"}
}