{
  "type": "Feature",
  "properties": {
    "iso:country":"US",
    "sg:address":"500 Columbus St E",
    "sg:city":"Fayette",
    "sg:classifiers":[
        {
            "category":"Retail",
            "subcategory":"Auto Repair",
            "type":"Services"
        }
    ],
    "sg:phone":"+1 205 932 7922",
    "sg:postcode":"35555",
    "sg:province":"AL",
    "sg:tags":[
        "repairing",
        "automobile",
        "general"
    ],
    "wof:name":"S & S Auto Repair Shop",
    "wof:placetype":"venue"
},
  "geometry": {"coordinates":[-87.82517300000001,33.68428],"type":"Point"}
}