{
  "type": "Feature",
  "properties": {
    "addr:full":"8018 Co Rd 24 Clanton AL 35045",
    "addr:housenumber":"8018;24",
    "addr:postcode":"35045",
    "addr:street":"Co Rd",
    "iso:country":"US",
    "sg:address":"8018 Co Rd 24",
    "sg:city":"Clanton",
    "sg:classifiers":[
        {
            "category":"Building & Trades",
            "subcategory":"Construction",
            "type":"Services"
        }
    ],
    "sg:phone":"+1 205 755 5533",
    "sg:postcode":"35045",
    "sg:province":"AL",
    "sg:tags":[
        "roofing",
        "contractor"
    ],
    "wof:name":"A Plus Metal Works",
    "wof:placetype":"venue"
},
  "geometry": {"coordinates":[-86.589747,32.748763],"type":"Point"}
}