{
  "type": "Feature",
  "properties": {
    "addr:full":"557 Stage Rd Auburn AL 36830",
    "addr:housenumber":"557",
    "addr:postcode":"36830",
    "addr:street":"Stage Rd",
    "iso:country":"US",
    "sg:address":"557 Stage Rd",
    "sg:city":"Auburn",
    "sg:classifiers":[
        {
            "category":"Shopping",
            "subcategory":"Computers & Home Electronics",
            "type":"Retail Goods"
        }
    ],
    "sg:phone":"+1 334 821 4300",
    "sg:postcode":"36830",
    "sg:province":"AL",
    "sg:tags":[
        "software"
    ],
    "wof:name":"RUR Group Inc",
    "wof:placetype":"venue"
},
  "geometry": {"coordinates":[-85.46885899999999,32.613552],"type":"Point"}
}