{
  "type": "Feature",
  "properties": {
    "iso:country":"US",
    "sg:address":"1018 Fir St",
    "sg:city":"Dothan",
    "sg:classifiers":[
        {
            "category":"Building & Trades",
            "subcategory":"Construction",
            "type":"Services"
        }
    ],
    "sg:phone":"+1 334 794 6822",
    "sg:postcode":"36303",
    "sg:province":"AL",
    "sg:tags":[
        "roofing",
        "contractor"
    ],
    "wof:name":"Robinson Roofing & Remodeling",
    "wof:placetype":"venue"
},
  "geometry": {"coordinates":[-85.39437,31.238504],"type":"Point"}
}