{
  "type": "Feature",
  "properties": {
    "iso:country":"US",
    "sg:address":"2700 Highway 280 S 208W",
    "sg:city":"Birmingham",
    "sg:classifiers":[
        {
            "category":"Professional",
            "subcategory":"Employment Agencies",
            "type":"Services"
        }
    ],
    "sg:phone":"+1 205 870 8474",
    "sg:postcode":"35223",
    "sg:province":"AL",
    "sg:tags":[
        "opportunity"
    ],
    "wof:name":"Esi Executive Solutions Inc",
    "wof:placetype":"venue"
},
  "geometry": {"coordinates":[-86.77340700000001,33.47833],"type":"Point"}
}