{
  "type": "Feature",
  "properties": {
    "iso:country":"US",
    "sg:address":"9125 Parkway E",
    "sg:city":"Birmingham",
    "sg:classifiers":[
        {
            "category":"Restaurant",
            "type":"Food & Drink"
        }
    ],
    "sg:phone":"+1 205 838 1818",
    "sg:postcode":"35206",
    "sg:province":"AL",
    "sg:tags":[
        "eating"
    ],
    "wof:name":"Good Taste Chinese Buffet",
    "wof:placetype":"venue"
},
  "geometry": {"coordinates":[-86.70362799999999,33.584973],"type":"Point"}
}