{
  "type": "Feature",
  "properties": {
    "addr:full":"134 Sandy Ct Prattville AL 36067",
    "addr:housenumber":"134",
    "addr:postcode":"36067",
    "addr:street":"Sandy Ct",
    "iso:country":"US",
    "sg:address":"134 Sandy Ct",
    "sg:city":"Prattville",
    "sg:classifiers":[
        {
            "category":"Government",
            "subcategory":"Office",
            "type":"Public Place"
        }
    ],
    "sg:phone":"+1 334 361 3701",
    "sg:postcode":"36067",
    "sg:province":"AL",
    "sg:tags":[
        "executive",
        "local"
    ],
    "wof:name":"Autauga County Commission Off",
    "wof:placetype":"venue"
},
  "geometry": {"coordinates":[-86.46923700000001,32.470553],"type":"Point"}
}