{
  "type": "Feature",
  "properties": {
    "iso:country":"US",
    "sg:address":"9248 Parkway E",
    "sg:city":"Birmingham",
    "sg:classifiers":[
        {
            "category":"Professional",
            "subcategory":"Accounting & Tax Preparation",
            "type":"Services"
        }
    ],
    "sg:phone":"+1 205 838 0456",
    "sg:postcode":"35206",
    "sg:province":"AL",
    "sg:tags":[
        "bookkeeping",
        "return",
        "representative",
        "preparation-business",
        "taxes-consultants"
    ],
    "sg:website":"http://www.jacksonhewitt.com/",
    "wof:name":"Jackson Hewitt Tax Service",
    "wof:placetype":"venue"
},
  "geometry": {"coordinates":[-86.698846,33.588413],"type":"Point"}
}