{
  "type": "Feature",
  "properties": {
    "iso:country":"US",
    "sg:address":"2520 4th Ave S",
    "sg:city":"Birmingham",
    "sg:classifiers":[
        {
            "category":"Restaurant",
            "type":"Food & Drink"
        }
    ],
    "sg:phone":"+1 205 328 6072",
    "sg:postcode":"35233",
    "sg:province":"AL",
    "sg:tags":[
        "catering"
    ],
    "wof:name":"Char-House Foods",
    "wof:placetype":"venue"
},
  "geometry": {"coordinates":[-86.794103,33.512911],"type":"Point"}
}