{
  "type": "Feature",
  "properties": {
    "addr:full":"3400 Skyway Dr Auburn AL 36830",
    "addr:housenumber":"3400",
    "addr:postcode":"36830",
    "addr:street":"Skyway Dr",
    "iso:country":"US",
    "sg:address":"3400 Skyway Dr",
    "sg:city":"Auburn",
    "sg:classifiers":[
        {
            "category":"Utilities",
            "subcategory":"Natural Gas",
            "type":"Services"
        }
    ],
    "sg:phone":"+1 334 887 4800",
    "sg:postcode":"36830",
    "sg:province":"AL",
    "sg:tags":[
        "company"
    ],
    "sg:website":"www.energen.com",
    "wof:name":"Alabama Gas Corp",
    "wof:placetype":"venue"
},
  "geometry": {"coordinates":[-85.429444,32.614109],"type":"Point"}
}