{
  "type": "Feature",
  "properties": {
    "addr:full":"109 Industrial Park Dr Pelham AL 35124",
    "addr:housenumber":"109",
    "addr:postcode":"35124",
    "addr:street":"Industrial Park Dr",
    "iso:country":"US",
    "sg:address":"109 Industrial Park Dr",
    "sg:city":"Pelham",
    "sg:classifiers":[
        {
            "category":"Professional",
            "subcategory":"Management & Consulting",
            "type":"Services"
        }
    ],
    "sg:phone":"+1 205 408 3040",
    "sg:postcode":"35124",
    "sg:province":"AL",
    "wof:name":"Consolidated Services",
    "wof:placetype":"venue"
},
  "geometry": {"coordinates":[-86.81333100000001,33.296593],"type":"Point"}
}