{
  "type": "Feature",
  "properties": {
    "iso:country":"US",
    "sg:address":"13565 Co Rd 8",
    "sg:city":"Woodville",
    "sg:classifiers":[
        {
            "category":"Building & Trades",
            "subcategory":"Construction",
            "type":"Services"
        }
    ],
    "sg:phone":"+1 256 776 9192",
    "sg:postcode":"35776",
    "sg:province":"AL",
    "sg:tags":[
        "hanging",
        "contractor"
    ],
    "wof:name":"Spectrum Painting Co",
    "wof:placetype":"venue"
},
  "geometry": {"coordinates":[-86.273902,34.626692],"type":"Point"}
}