{
  "type": "Feature",
  "properties": {
    "iso:country":"US",
    "sg:address":"1505 Country Club Dr SW",
    "sg:city":"Jacksonville",
    "sg:classifiers":[
        {
            "category":"Recreation",
            "type":"Entertainment"
        }
    ],
    "sg:phone":"+1 256 435 3114",
    "sg:postcode":"36265",
    "sg:province":"AL",
    "sg:tags":[
        "shop",
        "course",
        "membership",
        "golf",
        "pro"
    ],
    "wof:name":"Stoney Brook Golf Course",
    "wof:placetype":"venue"
},
  "geometry": {"coordinates":[-85.773218,33.785582],"type":"Point"}
}