{
  "type": "Feature",
  "properties": {
    "iso:country":"US",
    "sg:address":"3608 Lakeside Dr",
    "sg:city":"Birmingham",
    "sg:classifiers":[
        {
            "category":"Freight",
            "type":"Transportation"
        }
    ],
    "sg:phone":"+1 205 967 8263",
    "sg:postcode":"35243",
    "sg:province":"AL",
    "wof:name":"James R Murphy LLC",
    "wof:placetype":"venue"
},
  "geometry": {"coordinates":[-86.718294,33.44756],"type":"Point"}
}