{
  "type": "Feature",
  "properties": {
    "addr:full":"55 1st Ave SW Lafayette AL 36862",
    "addr:housenumber":"55",
    "addr:postcode":"36862",
    "addr:street":"1St Ave Sw",
    "iso:country":"US",
    "sg:address":"55 1st Ave SW",
    "sg:city":"Lafayette",
    "sg:classifiers":[
        {
            "category":"Retail",
            "subcategory":"Laundry & Dry Cleaning",
            "type":"Services"
        }
    ],
    "sg:phone":"+1 334 864 9413",
    "sg:postcode":"36862",
    "sg:province":"AL",
    "sg:tags":[
        "cleaners"
    ],
    "wof:name":"Sunshine Cleaners",
    "wof:placetype":"venue"
},
  "geometry": {"coordinates":[-85.401708,32.898967],"type":"Point"}
}