{
  "type": "Feature",
  "properties": {
    "iso:country":"US",
    "sg:address":"402 Dr Martin L King Jr Ave",
    "sg:city":"Mobile",
    "sg:classifiers":[
        {
            "category":"Retail",
            "subcategory":"Funeral Services",
            "type":"Services"
        }
    ],
    "sg:phone":"+1 251 432 3665",
    "sg:postcode":"36603",
    "sg:province":"AL",
    "sg:tags":[
        "director"
    ],
    "wof:name":"Lovett's Funeral Chapel",
    "wof:placetype":"venue"
},
  "geometry": {"coordinates":[-88.054852,30.696465],"type":"Point"}
}