{
  "type": "Feature",
  "properties": {
    "iso:country":"US",
    "sg:address":"2504 Airport Rd",
    "sg:city":"Anniston",
    "sg:classifiers":[
        {
            "category":"Airport",
            "type":"Transportation"
        }
    ],
    "sg:phone":"+1 256 831 4410",
    "sg:postcode":"36203",
    "sg:province":"AL",
    "wof:name":"Anniston Metropolitan Airport",
    "wof:placetype":"venue"
},
  "geometry": {"coordinates":[-85.889542,33.587123],"type":"Point"}
}