{
  "type": "Feature",
  "properties": {
    "iso:country":"US",
    "sg:address":"5744 Willow Lake Dr",
    "sg:city":"Birmingham",
    "sg:classifiers":[
        {
            "category":"Building & Trades",
            "subcategory":"Construction",
            "type":"Services"
        }
    ],
    "sg:phone":"+1 205 531 9639",
    "sg:postcode":"35244",
    "sg:province":"AL",
    "sg:tags":[
        "finishing",
        "deck"
    ],
    "wof:name":"Chantaz Contracting Co",
    "wof:placetype":"venue"
},
  "geometry": {"coordinates":[-86.878793,33.338889],"type":"Point"}
}