{
  "type": "Feature",
  "properties": {
    "iso:country":"US",
    "sg:address":"105 N Gilmer Ave",
    "sg:city":"Lanett",
    "sg:classifiers":[
        {
            "category":"Retail",
            "subcategory":"Auto Repair",
            "type":"Services"
        }
    ],
    "sg:phone":"+1 334 644 7355",
    "sg:postcode":"36863",
    "sg:province":"AL",
    "sg:tags":[
        "repairing",
        "automotive",
        "automobile",
        "general"
    ],
    "wof:name":"David's Automotive Repair",
    "wof:placetype":"venue"
},
  "geometry": {"coordinates":[-85.186799,32.869295],"type":"Point"}
}