{
  "type": "Feature",
  "properties": {
    "iso:country":"US",
    "sg:address":"7441 Co Rd 48",
    "sg:city":"Lafayette",
    "sg:classifiers":[
        {
            "category":"Travel",
            "subcategory":"Travel Agent",
            "type":"Entertainment"
        }
    ],
    "sg:phone":"+1 334 864 7006",
    "sg:postcode":"36862",
    "sg:province":"AL",
    "sg:tags":[
        "operator",
        "tour"
    ],
    "wof:name":"Fun Cruises & Tours Corp",
    "wof:placetype":"venue"
},
  "geometry": {"coordinates":[-85.533619,32.889883],"type":"Point"}
}