{
  "type": "Feature",
  "properties": {
    "addr:full":"88125 US Hwy 278 Altoona AL 35952",
    "addr:postcode":"88125;35952",
    "addr:street":"Us Hwy 278",
    "iso:country":"US",
    "sg:address":"88125 US Hwy 278",
    "sg:city":"Altoona",
    "sg:classifiers":[
        {
            "category":"Wholesale",
            "subcategory":"Auto Parts",
            "type":"Manufacturing & Wholesale Goods"
        }
    ],
    "sg:phone":"+1 205 466 5300",
    "sg:postcode":"35952",
    "sg:province":"AL",
    "wof:name":"Snead Wholesale Tire",
    "wof:placetype":"venue"
},
  "geometry": {"coordinates":[-86.381271,34.11068],"type":"Point"}
}