{
  "type": "Feature",
  "properties": {
    "iso:country":"US",
    "sg:address":"401 Madison St",
    "sg:city":"Huntsville",
    "sg:classifiers":[
        {
            "category":"Professional",
            "subcategory":"Lawyer & Legal Services",
            "type":"Services"
        }
    ],
    "sg:phone":"+1 256 539 8880",
    "sg:postcode":"35801",
    "sg:province":"AL",
    "sg:tags":[
        "attorney"
    ],
    "wof:name":"John C Taylor",
    "wof:placetype":"venue"
},
  "geometry": {"coordinates":[-86.58401,34.727855],"type":"Point"}
}