{
  "type": "Feature",
  "properties": {
    "iso:country":"US",
    "sg:address":"1413 Dale Cir SE",
    "sg:city":"Huntsville",
    "sg:classifiers":[
        {
            "category":"Professional",
            "subcategory":"Business Services",
            "type":"Services"
        }
    ],
    "sg:phone":"+1 256 539 5700",
    "sg:postcode":"35801",
    "sg:province":"AL",
    "sg:tags":[
        "interior",
        "decorating"
    ],
    "wof:name":"Decorating Den Interiors",
    "wof:placetype":"venue"
},
  "geometry": {"coordinates":[-86.564107,34.720792],"type":"Point"}
}