{
  "type": "Feature",
  "properties": {
    "iso:country":"US",
    "sg:address":"3000 Ivy Ave SW",
    "sg:city":"Huntsville",
    "sg:classifiers":[
        {
            "category":"Real Estate",
            "subcategory":"Real Estate Operator",
            "type":"Services"
        }
    ],
    "sg:phone":"+1 256 534 2263",
    "sg:postcode":"35805",
    "sg:province":"AL",
    "sg:tags":[
        "apartment"
    ],
    "wof:name":"Mill Stream Apartments",
    "wof:placetype":"venue"
},
  "geometry": {"coordinates":[-86.607118,34.705411],"type":"Point"}
}