{
  "type": "Feature",
  "properties": {
    "iso:country":"US",
    "sg:address":"2390 Ross Clark Cir",
    "sg:city":"Dothan",
    "sg:classifiers":[
        {
            "category":"Utilities",
            "subcategory":"Natural Gas",
            "type":"Services"
        }
    ],
    "sg:phone":"+1 334 794 0567",
    "sg:postcode":"36301",
    "sg:province":"AL",
    "sg:tags":[
        "company"
    ],
    "wof:name":"Southeast Alabama Gas District",
    "wof:placetype":"venue"
},
  "geometry": {"coordinates":[-85.411733,31.196459],"type":"Point"}
}