{
  "type": "Feature",
  "properties": {
    "iso:country":"US",
    "sg:address":"960 2nd St",
    "sg:city":"Cherokee",
    "sg:classifiers":[
        {
            "category":"Organizations",
            "subcategory":"Community Association",
            "type":"Services"
        }
    ],
    "sg:phone":"+1 256 359 6555",
    "sg:postcode":"35616",
    "sg:province":"AL",
    "sg:tags":[
        "fraternal"
    ],
    "wof:name":"Vertagreen Masonic Lodge",
    "wof:placetype":"venue"
},
  "geometry": {"coordinates":[-87.97369,34.757229],"type":"Point"}
}