{
  "type": "Feature",
  "properties": {
    "iso:country":"US",
    "sg:address":"7355 Theodore Dawes Rd",
    "sg:city":"Theodore",
    "sg:classifiers":[
        {
            "category":"Professional",
            "subcategory":"Business Services",
            "type":"Services"
        }
    ],
    "sg:phone":"+1 251 653 9794",
    "sg:postcode":"36582",
    "sg:province":"AL",
    "wof:name":"Cash Express Theodore LLC",
    "wof:placetype":"venue"
},
  "geometry": {"coordinates":[-88.218914,30.567816],"type":"Point"}
}