{
  "type": "Feature",
  "properties": {
    "addr:full":"335 Co Rd 232 Florence AL 35633",
    "addr:housenumber":"335",
    "addr:postcode":"35633",
    "addr:street":"Co Rd 232",
    "iso:country":"US",
    "sg:address":"335 Co Rd 232",
    "sg:city":"Florence",
    "sg:phone":"+1 256 767 1327",
    "sg:postcode":"35633",
    "sg:province":"AL",
    "sg:tags":[
        "farm",
        "corn",
        "cotton"
    ],
    "wof:name":"David McIntyre",
    "wof:placetype":"venue"
},
  "geometry": {"coordinates":[-87.73847499999999,34.834751],"type":"Point"}
}