{
  "type": "Feature",
  "properties": {
    "iso:country":"US",
    "sg:address":"502 2nd Ave S",
    "sg:city":"Clanton",
    "sg:classifiers":[
        {
            "category":"Professional",
            "subcategory":"Accounting & Tax Preparation",
            "type":"Services"
        }
    ],
    "sg:phone":"+1 205 755 0655",
    "sg:postcode":"35045",
    "sg:province":"AL",
    "sg:tags":[
        "accountant"
    ],
    "wof:name":"Hull & Russell",
    "wof:placetype":"venue"
},
  "geometry": {"coordinates":[-86.62799200000001,32.838223],"type":"Point"}
}