{
  "type": "Feature",
  "properties": {
    "addr:full":"60 N Broad St Mobile AL 36602",
    "addr:housenumber":"60",
    "addr:postcode":"36602",
    "addr:street":"N Broad St",
    "iso:country":"US",
    "sg:address":"60 N Broad St",
    "sg:city":"Mobile",
    "sg:classifiers":[
        {
            "category":"Retail",
            "subcategory":"Auto Repair",
            "type":"Services"
        }
    ],
    "sg:phone":"+1 251 438 9393",
    "sg:postcode":"36602",
    "sg:province":"AL",
    "sg:tags":[
        "repairing",
        "automobile",
        "general"
    ],
    "wof:name":"Hutchins Carburetor Service",
    "wof:placetype":"venue"
},
  "geometry": {"coordinates":[-88.055069,30.689381],"type":"Point"}
}