{
  "type": "Feature",
  "properties": {
    "iso:country":"US",
    "sg:address":"158 Rayfield Dr",
    "sg:city":"Huntsville",
    "sg:classifiers":[
        {
            "category":"Retail",
            "subcategory":"Auto Repair",
            "type":"Services"
        }
    ],
    "sg:phone":"+1 256 859 5665",
    "sg:postcode":"35811",
    "sg:province":"AL",
    "sg:tags":[
        "transmission"
    ],
    "wof:name":"Towry Transmission Repair",
    "wof:placetype":"venue"
},
  "geometry": {"coordinates":[-86.509852,34.787096],"type":"Point"}
}