{
  "type": "Feature",
  "properties": {
    "iso:country":"US",
    "sg:address":"506 N Pine St",
    "sg:city":"Foley",
    "sg:classifiers":[
        {
            "category":"Organizations",
            "subcategory":"Religious Organization",
            "type":"Services"
        }
    ],
    "sg:phone":"+1 251 943 2173",
    "sg:postcode":"36535",
    "sg:province":"AL",
    "sg:tags":[
        "church"
    ],
    "wof:name":"St Paul's Episcopal Church",
    "wof:placetype":"venue"
},
  "geometry": {"coordinates":[-87.687129,30.411089],"type":"Point"}
}