{
  "type": "Feature",
  "properties": {
    "iso:country":"US",
    "sg:address":"1904 Shirt Tail Bend Rd",
    "sg:city":"New Hope",
    "sg:classifiers":[
        {
            "category":"Professional",
            "subcategory":"Research",
            "type":"Services"
        }
    ],
    "sg:phone":"+1 256 723 2255",
    "sg:postcode":"35760",
    "sg:province":"AL",
    "sg:tags":[
        "environmental",
        "ecological"
    ],
    "sg:website":"www.geotechinc.org",
    "wof:name":"Geo Tech Inc",
    "wof:placetype":"venue"
},
  "geometry": {"coordinates":[-86.35227,34.505204],"type":"Point"}
}