{
  "type": "Feature",
  "properties": {
    "iso:country":"US",
    "sg:address":"365 Rice Hill Rd",
    "sg:city":"Empire",
    "sg:classifiers":[
        {
            "category":"Food & Beverages",
            "subcategory":"Groceries & Convenience Stores",
            "type":"Retail Goods"
        }
    ],
    "sg:phone":"+1 205 608 3621",
    "sg:postcode":"35063",
    "sg:province":"AL",
    "sg:tags":[
        "eating"
    ],
    "wof:name":"Quincy Family Restaurant",
    "wof:placetype":"venue"
},
  "geometry": {"coordinates":[-87.024046,33.781152],"type":"Point"}
}