{
  "type": "Feature",
  "properties": {
    "addr:city":"Hoover",
    "addr:full":"3530 Lorna Rd Hoover, Al 35216-5902",
    "addr:house_number":"3530",
    "addr:housenumber":"3530",
    "addr:phone":"+1 205-682-8019",
    "addr:postcode":"35216-5902",
    "addr:road":"Lorna Rd",
    "addr:state":"AL",
    "addr:street":"Lorna Rd",
    "iso:country":"US",
    "sg:address":"3530 Lorna Rd",
    "sg:city":"Birmingham",
    "sg:classifiers":[
        {
            "category":"Recreation",
            "type":"Entertainment"
        }
    ],
    "sg:phone":"+1 205 682 8019",
    "sg:postcode":"35216",
    "sg:province":"AL",
    "sg:tags":[
        "parks"
    ],
    "wof:airports":[
        102527725
    ],
    "wof:name":"Aldridge Gardens",
    "wof:placetype":"venue"
},
  "geometry": {"coordinates":[-86.79432,33.38533],"type":"Point"}
}