{
  "type": "Feature",
  "properties": {
    "addr:full":"3530 Lorna Rd Birmingham AL 35216",
    "addr:housenumber":"3530",
    "addr:postcode":"35216",
    "addr:street":"Lorna Rd",
    "iso:country":"US",
    "sg:address":"3530 Lorna Rd",
    "sg:city":"Birmingham",
    "sg:classifiers":[
        {
            "category":"Recreation",
            "type":"Entertainment"
        }
    ],
    "sg:phone":"+1 205 682 8019",
    "sg:postcode":"35216",
    "sg:province":"AL",
    "sg:tags":[
        "parks"
    ],
    "wof:name":"Aldridge Gardens",
    "wof:placetype":"venue"
},
  "geometry": {"coordinates":[-86.794127,33.384911],"type":"Point"}
}