{
  "type": "Feature",
  "properties": {
    "iso:country":"US",
    "sg:address":"3865 Gulf Shores Pkwy",
    "sg:city":"Gulf Shores",
    "sg:classifiers":[
        {
            "category":"Shopping",
            "subcategory":"Computers & Home Electronics",
            "type":"Retail Goods"
        }
    ],
    "sg:phone":"+1 251 968 8060",
    "sg:postcode":"36542",
    "sg:province":"AL",
    "sg:tags":[
        "audio"
    ],
    "wof:name":"Innovative Audio Video LLC",
    "wof:placetype":"venue"
},
  "geometry": {"coordinates":[-87.683252,30.306127],"type":"Point"}
}