{
  "type": "Feature",
  "properties": {
    "iso:country":"US",
    "sg:address":"3141 Lorna Rd",
    "sg:city":"Birmingham",
    "sg:classifiers":[
        {
            "category":"Banks & Credit Unions",
            "subcategory":"Bank",
            "type":"Services"
        }
    ],
    "sg:phone":"+1 205 823 6355",
    "sg:postcode":"35216",
    "sg:province":"AL",
    "sg:tags":[
        "loan",
        "real estate"
    ],
    "wof:name":"Mainstreet Funding Corp",
    "wof:placetype":"venue"
},
  "geometry": {"coordinates":[-86.803358,33.400065],"type":"Point"}
}