{
  "type": "Feature",
  "properties": {
    "iso:country":"US",
    "sg:address":"1901 Coliseum Pkwy",
    "sg:city":"Montgomery",
    "sg:classifiers":[
        {
            "category":"Restaurant",
            "type":"Food & Drink"
        }
    ],
    "sg:menulink":"http://www.allmenus.com/al/montgomery/231567-sonic/menu/",
    "sg:phone":"+1 334 272 2886",
    "sg:postcode":"36110",
    "sg:province":"AL",
    "sg:tags":[
        "burger",
        "american"
    ],
    "wof:name":"Sonic",
    "wof:placetype":"venue"
},
  "geometry": {"coordinates":[-86.27262500000001,32.420547],"type":"Point"}
}