{
  "type": "Feature",
  "properties": {
    "iso:country":"US",
    "sg:address":"1546 Grist Rd",
    "sg:city":"Selma",
    "sg:classifiers":[
        {
            "category":"Government",
            "subcategory":"Office",
            "type":"Public Place"
        }
    ],
    "sg:phone":"+1 334 872 5846",
    "sg:postcode":"36701",
    "sg:province":"AL",
    "sg:tags":[
        "state",
        "park"
    ],
    "wof:name":"Paul M Grist State Park",
    "wof:placetype":"venue"
},
  "geometry": {"coordinates":[-86.991302,32.597889],"type":"Point"}
}