{
  "type": "Feature",
  "properties": {
    "iso:country":"US",
    "sg:address":"614 22nd St N",
    "sg:city":"Bessemer",
    "sg:classifiers":[
        {
            "category":"Real Estate",
            "subcategory":"Real Estate Operator",
            "type":"Services"
        }
    ],
    "sg:phone":"+1 205 481 9638",
    "sg:postcode":"35020",
    "sg:province":"AL",
    "sg:tags":[
        "apartment"
    ],
    "wof:name":"Bessemer Housing Authority",
    "wof:placetype":"venue"
},
  "geometry": {"coordinates":[-86.954369,33.407811],"type":"Point"}
}