{
  "type": "Feature",
  "properties": {
    "addr:full":"48412 US Hwy 78 Lincoln AL 35096",
    "addr:postcode":"48412;35096",
    "addr:street":"Us Hwy 78",
    "iso:country":"US",
    "sg:address":"48412 US Hwy 78",
    "sg:city":"Lincoln",
    "sg:classifiers":[
        {
            "category":"Freight",
            "type":"Transportation"
        }
    ],
    "sg:phone":"+1 205 763 1400",
    "sg:postcode":"35096",
    "sg:province":"AL",
    "sg:tags":[
        "general"
    ],
    "wof:name":"Lincoln Storage",
    "wof:placetype":"venue"
},
  "geometry": {"coordinates":[-86.107069,33.604998],"type":"Point"}
}