{
  "type": "Feature",
  "properties": {
    "addr:full":"2508 16th St N Birmingham AL 35204",
    "addr:housenumber":"2508",
    "addr:postcode":"35204",
    "addr:street":"16Th St N",
    "iso:country":"US",
    "sg:address":"2508 16th St N",
    "sg:city":"Birmingham",
    "sg:classifiers":[
        {
            "category":"Professional",
            "type":"Services"
        }
    ],
    "sg:phone":"+1 205 222 2165",
    "sg:postcode":"35204",
    "sg:province":"AL",
    "wof:name":"Christion and Sons Inc",
    "wof:placetype":"venue"
},
  "geometry": {"coordinates":[-86.830332,33.542395],"type":"Point"}
}