{
  "type": "Feature",
  "properties": {
    "iso:country":"US",
    "sg:address":"1920 Culver Rd",
    "sg:city":"Tuscaloosa",
    "sg:classifiers":[
        {
            "category":"Home & Garden",
            "subcategory":"Building Materials",
            "type":"Retail Goods"
        }
    ],
    "sg:phone":"+1 205 345 3515",
    "sg:postcode":"35401",
    "sg:province":"AL",
    "sg:tags":[
        "lumber"
    ],
    "wof:name":"Friday Lumber Co Inc",
    "wof:placetype":"venue"
},
  "geometry": {"coordinates":[-87.596555,33.196612],"type":"Point"}
}