{
  "type": "Feature",
  "properties": {
    "addr:full":"142 Brooks Blvd Brewton AL 36426",
    "addr:housenumber":"142",
    "addr:postcode":"36426",
    "addr:street":"Brooks Blvd",
    "iso:country":"US",
    "sg:address":"142 Brooks Blvd",
    "sg:city":"Brewton",
    "sg:classifiers":[
        {
            "category":"Freight",
            "type":"Transportation"
        }
    ],
    "sg:phone":"+1 251 867 7597",
    "sg:postcode":"36426",
    "sg:province":"AL",
    "sg:tags":[
        "special"
    ],
    "wof:name":"A-1 Storage",
    "wof:placetype":"venue"
},
  "geometry": {"coordinates":[-87.08541200000001,31.150715],"type":"Point"}
}