{
  "type": "Feature",
  "properties": {
    "iso:country":"US",
    "sg:address":"1202 Decator St",
    "sg:city":"Dothan",
    "sg:classifiers":[
        {
            "category":"Building & Trades",
            "subcategory":"Construction",
            "type":"Services"
        }
    ],
    "sg:phone":"+1 334 792 1742",
    "sg:postcode":"36301",
    "sg:province":"AL",
    "sg:tags":[
        "hanging",
        "contractor"
    ],
    "wof:name":"Danny McArdle Painting",
    "wof:placetype":"venue"
},
  "geometry": {"coordinates":[-85.41208,31.217037],"type":"Point"}
}