{
  "type": "Feature",
  "properties": {
    "iso:country":"US",
    "sg:address":"28190 N Main St",
    "sg:city":"Daphne",
    "sg:classifiers":[
        {
            "category":"Banks & Credit Unions",
            "subcategory":"Bank",
            "type":"Services"
        }
    ],
    "sg:phone":"+1 251 621 5761",
    "sg:postcode":"36526",
    "sg:province":"AL",
    "sg:tags":[
        "loan",
        "real estate"
    ],
    "wof:name":"Equisouth Mortgage Inc",
    "wof:placetype":"venue"
},
  "geometry": {"coordinates":[-87.910564,30.640142],"type":"Point"}
}