{
  "type": "Feature",
  "properties": {
    "iso:country":"US",
    "sg:address":"427 W Patton Ave",
    "sg:city":"Montgomery",
    "sg:classifiers":[
        {
            "category":"Building & Trades",
            "subcategory":"Construction",
            "type":"Services"
        }
    ],
    "sg:phone":"+1 334 284 2100",
    "sg:postcode":"36105",
    "sg:province":"AL",
    "sg:tags":[
        "house"
    ],
    "wof:name":"Sweazer Const",
    "wof:placetype":"venue"
},
  "geometry": {"coordinates":[-86.314842,32.333962],"type":"Point"}
}