{
  "type": "Feature",
  "properties": {
    "addr:full":"766 E Glenn Ave Auburn AL 36830",
    "addr:housenumber":"766",
    "addr:postcode":"36830",
    "addr:street":"E Glenn Ave",
    "iso:country":"US",
    "sg:address":"766 E Glenn Ave",
    "sg:city":"Auburn",
    "sg:classifiers":[
        {
            "category":"Insurance",
            "subcategory":"Insurance Agent",
            "type":"Services"
        }
    ],
    "sg:phone":"+1 334 887 8502",
    "sg:postcode":"36830",
    "sg:province":"AL",
    "wof:name":"Alfa Insurance Corp",
    "wof:placetype":"venue"
},
  "geometry": {"coordinates":[-85.467034,32.608931],"type":"Point"}
}