{
  "type": "Feature",
  "properties": {
    "iso:country":"US",
    "sg:address":"1 Office Park Cir",
    "sg:city":"Birmingham",
    "sg:classifiers":[
        {
            "category":"Professional",
            "subcategory":"Management & Consulting",
            "type":"Services"
        }
    ],
    "sg:phone":"+1 205 879 1241",
    "sg:postcode":"35223",
    "sg:province":"AL",
    "wof:name":"Jackson Hospitality Services",
    "wof:placetype":"venue"
},
  "geometry": {"coordinates":[-86.769579,33.478837],"type":"Point"}
}