{
  "type": "Feature",
  "properties": {
    "addr:full":"850 Lincoln St SW Birmingham AL 35211",
    "addr:housenumber":"850",
    "addr:postcode":"35211",
    "addr:street":"Lincoln St Sw",
    "iso:country":"US",
    "sg:address":"850 Lincoln St SW",
    "sg:city":"Birmingham",
    "sg:classifiers":[
        {
            "category":"Restaurant",
            "type":"Food & Drink"
        }
    ],
    "sg:phone":"+1 205 297 9192",
    "sg:postcode":"35211",
    "sg:province":"AL",
    "sg:tags":[
        "eating"
    ],
    "wof:name":"Simply Divine Catering Service",
    "wof:placetype":"venue"
},
  "geometry": {"coordinates":[-86.83360500000001,33.486799],"type":"Point"}
}