{
  "type": "Feature",
  "properties": {
    "iso:country":"US",
    "sg:address":"784 N Jefferson St",
    "sg:city":"Athens",
    "sg:classifiers":[
        {
            "category":"Retail",
            "subcategory":"Repair Shop",
            "type":"Services"
        }
    ],
    "sg:phone":"+1 256 232 1150",
    "sg:postcode":"35611",
    "sg:province":"AL",
    "sg:tags":[
        "refrigeration",
        "electrical"
    ],
    "wof:name":"Presnell Appliance",
    "wof:placetype":"venue"
},
  "geometry": {"coordinates":[-86.971747,34.810432],"type":"Point"}
}