{
  "type": "Feature",
  "properties": {
    "iso:country":"US",
    "sg:address":"1475 Weatherbrook Ln",
    "sg:city":"Anniston",
    "sg:classifiers":[
        {
            "category":"Wholesale",
            "subcategory":"Durable Goods & Equipment",
            "type":"Manufacturing & Wholesale Goods"
        }
    ],
    "sg:phone":"+1 256 435 1467",
    "sg:postcode":"36206",
    "sg:province":"AL",
    "wof:name":"Medders Auto Core Supply",
    "wof:placetype":"venue"
},
  "geometry": {"coordinates":[-85.746348,33.758379],"type":"Point"}
}