{
  "type": "Feature",
  "properties": {
    "iso:country":"US",
    "sg:address":"3050 State Rte 14",
    "sg:city":"Auburn",
    "sg:classifiers":[
        {
            "category":"Food & Beverages",
            "subcategory":"Groceries & Convenience Stores",
            "type":"Retail Goods"
        }
    ],
    "sg:phone":"+1 334 887 3555",
    "sg:postcode":"36832",
    "sg:province":"AL",
    "wof:name":"GND Petro Chem",
    "wof:placetype":"venue"
},
  "geometry": {"coordinates":[-85.543447,32.600423],"type":"Point"}
}