{
  "type": "Feature",
  "properties": {
    "iso:country":"US",
    "sg:address":"3190 Leeman Ferry Rd SW",
    "sg:city":"Huntsville",
    "sg:classifiers":[
        {
            "category":"Shopping",
            "subcategory":"Bicycles & Sporting Goods",
            "type":"Retail Goods"
        }
    ],
    "sg:phone":"+1 256 650 0257",
    "sg:postcode":"35801",
    "sg:province":"AL",
    "sg:tags":[
        "equipment",
        "tennis",
        "supply"
    ],
    "wof:name":"Dinosaur Tennis Com",
    "wof:placetype":"venue"
},
  "geometry": {"coordinates":[-86.591951,34.69504],"type":"Point"}
}