{
  "type": "Feature",
  "properties": {
    "iso:country":"US",
    "sg:address":"400 S Christine Ave",
    "sg:city":"Anniston",
    "sg:classifiers":[
        {
            "category":"Organizations",
            "subcategory":"Religious Organization",
            "type":"Services"
        }
    ],
    "sg:phone":"+1 256 237 9596",
    "sg:postcode":"36207",
    "sg:province":"AL",
    "wof:name":"Smith Tabernacle CME Church",
    "wof:placetype":"venue"
},
  "geometry": {"coordinates":[-85.822728,33.641828],"type":"Point"}
}