{
  "type": "Feature",
  "properties": {
    "iso:country":"US",
    "sg:address":"4394 State Rte 157",
    "sg:city":"Florence",
    "sg:classifiers":[
        {
            "category":"Shopping",
            "subcategory":"Bicycles & Sporting Goods",
            "type":"Retail Goods"
        }
    ],
    "sg:phone":"+1 256 766 7043",
    "sg:postcode":"35633",
    "sg:province":"AL",
    "sg:tags":[
        "p",
        "mfg",
        "trimming"
    ],
    "wof:name":"M & J Sporting Goods Inc",
    "wof:placetype":"venue"
},
  "geometry": {"coordinates":[-87.691644,34.86956],"type":"Point"}
}