{
  "type": "Feature",
  "properties": {
    "iso:country":"US",
    "sg:address":"189 Old Springs Rd",
    "sg:city":"Springville",
    "sg:classifiers":[
        {
            "category":"Building & Trades",
            "subcategory":"Construction",
            "type":"Services"
        }
    ],
    "sg:phone":"+1 205 467 7332",
    "sg:postcode":"35146",
    "sg:province":"AL",
    "sg:tags":[
        "house"
    ],
    "wof:name":"Bama Home Improvement Co",
    "wof:placetype":"venue"
},
  "geometry": {"coordinates":[-86.450484,33.777718],"type":"Point"}
}