{
  "type": "Feature",
  "properties": {
    "addr:full":"5847 Brewbaker Blvd Montgomery AL 36116",
    "addr:housenumber":"5847",
    "addr:postcode":"36116",
    "addr:street":"Brewbaker Blvd",
    "iso:country":"US",
    "sg:address":"5847 Brewbaker Blvd",
    "sg:city":"Montgomery",
    "sg:classifiers":[
        {
            "category":"Professional",
            "subcategory":"Management & Consulting",
            "type":"Services"
        }
    ],
    "sg:phone":"+1 334 201 5447",
    "sg:postcode":"36116",
    "sg:province":"AL",
    "sg:tags":[
        "support",
        "administrative"
    ],
    "wof:name":"Timely Tasks",
    "wof:placetype":"venue"
},
  "geometry": {"coordinates":[-86.215627,32.315193],"type":"Point"}
}