{
  "type": "Feature",
  "properties": {
    "iso:country":"US",
    "sg:address":"2660 N Brindlee Mountain Pkwy",
    "sg:city":"Arab",
    "sg:classifiers":[
        {
            "category":"Home & Garden",
            "subcategory":"Household Appliances",
            "type":"Retail Goods"
        }
    ],
    "sg:phone":"+1 256 586 4775",
    "sg:postcode":"35016",
    "sg:province":"AL",
    "wof:name":"Bobs Appliance Sales & Svc",
    "wof:placetype":"venue"
},
  "geometry": {"coordinates":[-86.507979,34.362039],"type":"Point"}
}