{
  "type": "Feature",
  "properties": {
    "iso:country":"US",
    "sg:address":"22410 Choctaw Ln",
    "sg:city":"Athens",
    "sg:classifiers":[
        {
            "category":"Professional",
            "subcategory":"Engineering",
            "type":"Services"
        }
    ],
    "sg:phone":"+1 256 232 3836",
    "sg:postcode":"35613",
    "sg:province":"AL",
    "wof:name":"Igou Engineering",
    "wof:placetype":"venue"
},
  "geometry": {"coordinates":[-86.923472,34.769097],"type":"Point"}
}