{
  "type": "Feature",
  "properties": {
    "iso:country":"US",
    "sg:address":"310 S Atlanta Ave",
    "sg:city":"Sheffield",
    "sg:classifiers":[
        {
            "category":"Shopping",
            "type":"Retail Goods"
        },
        {
            "category":"Wholesale",
            "subcategory":"Durable Goods & Equipment",
            "type":"Manufacturing & Wholesale Goods"
        }
    ],
    "sg:phone":"+1 256 383 7782",
    "sg:postcode":"35660",
    "sg:province":"AL",
    "sg:tags":[
        "professional",
        "church",
        "supply"
    ],
    "wof:name":"Sparks Christian Books & Supls",
    "wof:placetype":"venue"
},
  "geometry": {"coordinates":[-87.695364,34.755534],"type":"Point"}
}