{
  "type": "Feature",
  "properties": {
    "addr:full":"1811 Co Rd 57 Prattville AL 36067",
    "addr:housenumber":"1811;57",
    "addr:postcode":"36067",
    "addr:street":"Co Rd",
    "iso:country":"US",
    "sg:address":"1811 Co Rd 57",
    "sg:city":"Prattville",
    "sg:classifiers":[
        {
            "category":"Social Services",
            "subcategory":"Child Care",
            "type":"Services"
        }
    ],
    "sg:phone":"+1 334 361 8009",
    "sg:postcode":"36067",
    "sg:province":"AL",
    "wof:name":"Just 4 Kids Learning Ctr",
    "wof:placetype":"venue"
},
  "geometry": {"coordinates":[-86.54723199999999,32.555946],"type":"Point"}
}