{
  "type": "Feature",
  "properties": {
    "iso:country":"US",
    "sg:address":"1831 James Ave",
    "sg:city":"Montgomery",
    "sg:classifiers":[
        {
            "category":"Building & Trades",
            "subcategory":"Construction",
            "type":"Services"
        }
    ],
    "sg:phone":"+1 334 263 5599",
    "sg:postcode":"36107",
    "sg:province":"AL",
    "sg:tags":[
        "contractor"
    ],
    "wof:name":"Consolacon",
    "wof:placetype":"venue"
},
  "geometry": {"coordinates":[-86.281867,32.377945],"type":"Point"}
}