{
  "type": "Feature",
  "properties": {
    "iso:country":"US",
    "sg:address":"555 Edgil Rd",
    "sg:city":"Jasper",
    "sg:classifiers":[
        {
            "category":"Building & Trades",
            "subcategory":"Construction",
            "type":"Services"
        }
    ],
    "sg:phone":"+1 205 302 0882",
    "sg:postcode":"35503",
    "sg:province":"AL",
    "sg:tags":[
        "residential"
    ],
    "wof:name":"Breeds Construction",
    "wof:placetype":"venue"
},
  "geometry": {"coordinates":[-87.36698800000001,33.904548],"type":"Point"}
}