{
  "type": "Feature",
  "properties": {
    "iso:country":"US",
    "sg:address":"8 Norwood Cir",
    "sg:city":"Birmingham",
    "sg:classifiers":[
        {
            "category":"Restaurant",
            "type":"Food & Drink"
        }
    ],
    "sg:phone":"+1 205 254 3921",
    "sg:postcode":"35234",
    "sg:province":"AL",
    "sg:tags":[
        "caterer"
    ],
    "wof:name":"Unique Catering",
    "wof:placetype":"venue"
},
  "geometry": {"coordinates":[-86.795325,33.538167],"type":"Point"}
}