{
  "type": "Feature",
  "properties": {
    "iso:country":"US",
    "sg:address":"875 Baker Dr",
    "sg:city":"Altoona",
    "sg:phone":"+1 205 466 7747",
    "sg:postcode":"35952",
    "sg:province":"AL",
    "sg:tags":[
        "farm",
        "corn",
        "soybean"
    ],
    "wof:name":"Howard Holmes",
    "wof:placetype":"venue"
},
  "geometry": {"coordinates":[-86.389571,34.122078],"type":"Point"}
}