{
  "type": "Feature",
  "properties": {
    "addr:full":"431 Main Ave Northport AL 35476",
    "addr:housenumber":"431",
    "addr:postcode":"35476",
    "addr:street":"Main Ave",
    "iso:country":"US",
    "sg:address":"431 Main Ave",
    "sg:city":"Northport",
    "sg:classifiers":[
        {
            "category":"Shopping",
            "type":"Retail Goods"
        }
    ],
    "sg:phone":"+1 205 752 4422",
    "sg:postcode":"35476",
    "sg:province":"AL",
    "sg:tags":[
        "merchandise"
    ],
    "wof:name":"Renaissance Art Gallery",
    "wof:placetype":"venue"
},
  "geometry": {"coordinates":[-87.578322,33.218656],"type":"Point"}
}