{
  "type": "Feature",
  "properties": {
    "iso:country":"US",
    "sg:address":"4679 Birmingport Rd",
    "sg:city":"Mulga",
    "sg:classifiers":[
        {
            "category":"Organizations",
            "subcategory":"Religious Organization",
            "type":"Services"
        }
    ],
    "sg:phone":"+1 205 786 5359",
    "sg:postcode":"35118",
    "sg:province":"AL",
    "wof:name":"Maytown Baptist Church",
    "wof:placetype":"venue"
},
  "geometry": {"coordinates":[-87.00294,33.527831],"type":"Point"}
}