{
  "type": "Feature",
  "properties": {
    "iso:country":"US",
    "sg:address":"601 Village Green Dr E",
    "sg:city":"Mobile",
    "sg:classifiers":[
        {
            "category":"Real Estate",
            "subcategory":"Real Estate Operator",
            "type":"Services"
        }
    ],
    "sg:phone":"+1 251 661 3970",
    "sg:postcode":"36609",
    "sg:province":"AL",
    "sg:tags":[
        "apartment"
    ],
    "wof:name":"Cedar Trace Apartments",
    "wof:placetype":"venue"
},
  "geometry": {"coordinates":[-88.142503,30.658281],"type":"Point"}
}