{
  "type": "Feature",
  "properties": {
    "iso:country":"US",
    "sg:address":"1679 Center Point Pkwy",
    "sg:city":"Birmingham",
    "sg:classifiers":[
        {
            "category":"Utilities",
            "subcategory":"Mobile Phone",
            "type":"Services"
        }
    ],
    "sg:phone":"+1 205 520 2050",
    "sg:postcode":"35215",
    "sg:province":"AL",
    "sg:tags":[
        "telephone",
        "cellular"
    ],
    "wof:name":"Cingular Wireless",
    "wof:placetype":"venue"
},
  "geometry": {"coordinates":[-86.684679,33.631678],"type":"Point"}
}