{
  "type": "Feature",
  "properties": {
    "iso:country":"US",
    "sg:address":"5356 State Rte 67",
    "sg:city":"Somerville",
    "sg:classifiers":[
        {
            "category":"Autos & Motor Vehicles",
            "subcategory":"Fuel & Gas Station",
            "type":"Retail Goods"
        }
    ],
    "sg:phone":"+1 256 778 9200",
    "sg:postcode":"35670",
    "sg:province":"AL",
    "sg:tags":[
        "station",
        "gasoline"
    ],
    "wof:name":"Exxon",
    "wof:placetype":"venue"
},
  "geometry": {"coordinates":[-86.75544499999999,34.445669],"type":"Point"}
}