{
  "type": "Feature",
  "properties": {
    "iso:country":"US",
    "sg:address":"4188 Alden Dr",
    "sg:city":"Mobile",
    "sg:classifiers":[
        {
            "category":"Professional",
            "type":"Services"
        }
    ],
    "sg:phone":"+1 251 643 1818",
    "sg:postcode":"36693",
    "sg:province":"AL",
    "wof:name":"Darrells Exotics",
    "wof:placetype":"venue"
},
  "geometry": {"coordinates":[-88.136003,30.620141],"type":"Point"}
}