{
  "type": "Feature",
  "properties": {
    "iso:country":"US",
    "sg:address":"151 Taylor Pt",
    "sg:city":"Eclectic",
    "sg:classifiers":[
        {
            "category":"Building & Trades",
            "subcategory":"Construction",
            "type":"Services"
        }
    ],
    "sg:phone":"+1 334 541 3756",
    "sg:postcode":"36024",
    "sg:province":"AL",
    "sg:tags":[
        "maker",
        "cabinet"
    ],
    "wof:name":"Allen's Cabinet Inc",
    "wof:placetype":"venue"
},
  "geometry": {"coordinates":[-85.93638199999999,32.696441],"type":"Point"}
}