{
  "type": "Feature",
  "properties": {
    "iso:country":"US",
    "sg:address":"68 Neel School Rd",
    "sg:city":"Danville",
    "sg:classifiers":[
        {
            "category":"Shopping",
            "type":"Retail Goods"
        }
    ],
    "sg:phone":"+1 256 773 4420",
    "sg:postcode":"35619",
    "sg:province":"AL",
    "sg:tags":[
        "fire",
        "repair",
        "equipment"
    ],
    "wof:name":"10-70 Fire Equipment & Service",
    "wof:placetype":"venue"
},
  "geometry": {"coordinates":[-87.059611,34.468964],"type":"Point"}
}