{
  "type": "Feature",
  "properties": {
    "iso:country":"US",
    "sg:address":"16659 Thompson Rd",
    "sg:city":"Loxley",
    "sg:classifiers":[
        {
            "category":"Wholesale",
            "subcategory":"Machinery & Supplies",
            "type":"Manufacturing & Wholesale Goods"
        }
    ],
    "sg:phone":"+1 251 947 4720",
    "sg:postcode":"36551",
    "sg:province":"AL",
    "sg:tags":[
        "tool"
    ],
    "wof:name":"Toolhawk Aircraft A & P Tool",
    "wof:placetype":"venue"
},
  "geometry": {"coordinates":[-87.738338,30.581808],"type":"Point"}
}