{
  "type": "Feature",
  "properties": {
    "iso:country":"US",
    "sg:address":"116 Red Oak Ln",
    "sg:city":"Eufaula",
    "sg:classifiers":[
        {
            "category":"Professional",
            "type":"Services"
        },
        {
            "category":"Professional",
            "subcategory":"Business Services",
            "type":"Services"
        }
    ],
    "sg:phone":"+1 334 355 0380",
    "sg:postcode":"36027",
    "sg:province":"AL",
    "sg:tags":[
        "establishment",
        "design"
    ],
    "wof:name":"Forerunner Fishers Tech Inc",
    "wof:placetype":"venue"
},
  "geometry": {"coordinates":[-85.161502,31.840381],"type":"Point"}
}