{
  "type": "Feature",
  "properties": {
    "addr:full":"1762 52nd St Birmingham AL 35208",
    "addr:housenumber":"1762",
    "addr:postcode":"35208",
    "addr:street":"52Nd St",
    "iso:country":"US",
    "sg:address":"1762 52nd St",
    "sg:city":"Birmingham",
    "sg:classifiers":[
        {
            "category":"Restaurant",
            "type":"Food & Drink"
        }
    ],
    "sg:phone":"+1 205 923 3873",
    "sg:postcode":"35208",
    "sg:province":"AL",
    "sg:tags":[
        "eating"
    ],
    "wof:name":"Traceys Treats & Sweets",
    "wof:placetype":"venue"
},
  "geometry": {"coordinates":[-86.884242,33.482143],"type":"Point"}
}