{
  "type": "Feature",
  "properties": {
    "iso:country":"US",
    "sg:address":"212 North St W",
    "sg:city":"Talladega",
    "sg:classifiers":[
        {
            "category":"Professional",
            "subcategory":"Lawyer & Legal Services",
            "type":"Services"
        }
    ],
    "sg:phone":"+1 256 362 0081",
    "sg:postcode":"35160",
    "sg:province":"AL",
    "sg:tags":[
        "attorney"
    ],
    "wof:name":"Wooten Thornton Carpenter",
    "wof:placetype":"venue"
},
  "geometry": {"coordinates":[-86.103591,33.435251],"type":"Point"}
}