{
  "type": "Feature",
  "properties": {
    "addr:full":"18655 Cape Fear Blvd Foley AL 36535",
    "addr:housenumber":"18655",
    "addr:postcode":"36535",
    "addr:street":"Cape Fear Blvd",
    "iso:country":"US",
    "sg:address":"18655 Cape Fear Blvd",
    "sg:city":"Foley",
    "sg:classifiers":[
        {
            "category":"Arts & Performance",
            "subcategory":"Theater",
            "type":"Entertainment"
        }
    ],
    "sg:phone":"+1 251 971 1880",
    "sg:postcode":"36535",
    "sg:province":"AL",
    "sg:tags":[
        "entertainer"
    ],
    "wof:name":"Dave Mc Cormick & The Blue Bnd",
    "wof:placetype":"venue"
},
  "geometry": {"coordinates":[-87.708037,30.387549],"type":"Point"}
}