{
  "type": "Feature",
  "properties": {
    "iso:country":"US",
    "sg:address":"1263 Old Talladega Hwy",
    "sg:city":"Sylacauga",
    "sg:classifiers":[
        {
            "category":"Health Services",
            "subcategory":"Nursing And Care Facility",
            "type":"Services"
        }
    ],
    "sg:phone":"+1 256 249 0066",
    "sg:postcode":"35150",
    "sg:province":"AL",
    "sg:tags":[
        "hospice"
    ],
    "wof:name":"Faith Hospice",
    "wof:placetype":"venue"
},
  "geometry": {"coordinates":[-86.243437,33.184131],"type":"Point"}
}