{
  "type": "Feature",
  "properties": {
    "iso:country":"US",
    "sg:address":"12 St James Rd",
    "sg:city":"Pittsview",
    "sg:classifiers":[
        {
            "category":"Organizations",
            "subcategory":"Religious Organization",
            "type":"Services"
        }
    ],
    "sg:phone":"+1 334 855 3465",
    "sg:postcode":"36871",
    "sg:province":"AL",
    "sg:tags":[
        "church"
    ],
    "wof:name":"St James Baptist Church",
    "wof:placetype":"venue"
},
  "geometry": {"coordinates":[-85.085188,32.155129],"type":"Point"}
}