{
  "type": "Feature",
  "properties": {
    "addr:full":"402 Airport Rd Clanton AL 35045",
    "addr:housenumber":"402",
    "addr:postcode":"35045",
    "addr:street":"Airport Rd",
    "iso:country":"US",
    "sg:address":"402 Airport Rd",
    "sg:city":"Clanton",
    "sg:classifiers":[
        {
            "category":"Personal",
            "subcategory":"Barber",
            "type":"Services"
        }
    ],
    "sg:phone":"+1 205 755 0915",
    "sg:postcode":"35045",
    "sg:province":"AL",
    "wof:name":"Kutter's Korner",
    "wof:placetype":"venue"
},
  "geometry": {"coordinates":[-86.61918900000001,32.846561],"type":"Point"}
}