{
  "type": "Feature",
  "properties": {
    "iso:country":"US",
    "sg:address":"8251 3 Notch Rd",
    "sg:city":"Mobile",
    "sg:classifiers":[
        {
            "category":"Education",
            "subcategory":"School",
            "type":"Public Place"
        }
    ],
    "sg:phone":"+1 251 221 1529",
    "sg:postcode":"36619",
    "sg:province":"AL",
    "sg:website":"www.schoolinsites.com",
    "wof:name":"Meadowlake Elementary School",
    "wof:placetype":"venue"
},
  "geometry": {"coordinates":[-88.170835,30.590193],"type":"Point"}
}