{
  "type": "Feature",
  "properties": {
    "iso:country":"US",
    "sg:address":"31525 Tara Blvd W",
    "sg:city":"Spanish Fort",
    "sg:classifiers":[
        {
            "category":"Building & Trades",
            "subcategory":"Plumbing",
            "type":"Services"
        }
    ],
    "sg:phone":"+1 251 621 9189",
    "sg:postcode":"36527",
    "sg:province":"AL",
    "sg:tags":[
        "contractor"
    ],
    "wof:name":"Dismukes Plumbing",
    "wof:placetype":"venue"
},
  "geometry": {"coordinates":[-87.895205,30.688622],"type":"Point"}
}