{
  "type": "Feature",
  "properties": {
    "addr:full":"101 Baker Ave Clanton AL 35045",
    "addr:housenumber":"101",
    "addr:postcode":"35045",
    "addr:street":"Baker Ave",
    "iso:country":"US",
    "sg:address":"101 Baker Ave",
    "sg:city":"Clanton",
    "sg:classifiers":[
        {
            "category":"Health Services",
            "subcategory":"Doctor",
            "type":"Services"
        }
    ],
    "sg:phone":"+1 205 755 1231",
    "sg:postcode":"35045",
    "sg:province":"AL",
    "sg:tags":[
        "dentist"
    ],
    "wof:name":"Baker & Baker",
    "wof:placetype":"venue"
},
  "geometry": {"coordinates":[-86.62076399999999,32.860597],"type":"Point"}
}