{
  "type": "Feature",
  "properties": {
    "addr:full":"2900 Valley Rd Birmingham AL 35203",
    "addr:housenumber":"2900",
    "addr:postcode":"35203",
    "addr:street":"Valley Rd",
    "iso:country":"US",
    "sg:address":"2900 Valley Rd",
    "sg:city":"Birmingham",
    "sg:classifiers":[
        {
            "category":"Building & Trades",
            "subcategory":"Locksmith",
            "type":"Services"
        }
    ],
    "sg:phone":"+1 205 453 1894",
    "sg:postcode":"35203",
    "sg:province":"AL",
    "sg:tags":[
        "key"
    ],
    "wof:name":"All Day & Night 24 7 Locksmith",
    "wof:placetype":"venue"
},
  "geometry": {"coordinates":[-86.781452,33.614772],"type":"Point"}
}