{
  "type": "Feature",
  "properties": {
    "iso:country":"US",
    "sg:address":"110 S Market St",
    "sg:city":"Scottsboro",
    "sg:classifiers":[
        {
            "category":"Shopping",
            "subcategory":"Gifts & Souvenirs",
            "type":"Retail Goods"
        }
    ],
    "sg:phone":"+1 256 574 5652",
    "sg:postcode":"35768",
    "sg:province":"AL",
    "wof:name":"Ginas Jewelry & Gifts",
    "wof:placetype":"venue"
},
  "geometry": {"coordinates":[-86.033269,34.673493],"type":"Point"}
}