{
  "type": "Feature",
  "properties": {
    "addr:full":"3612 Jonquil Dr NW Huntsville AL 35810",
    "addr:housenumber":"3612",
    "addr:postcode":"35810",
    "addr:street":"Jonquil Dr Nw",
    "iso:country":"US",
    "sg:address":"3612 Jonquil Dr NW",
    "sg:city":"Huntsville",
    "sg:classifiers":[
        {
            "category":"Professional",
            "subcategory":"Business Services",
            "type":"Services"
        }
    ],
    "sg:phone":"+1 256 852 7373",
    "sg:postcode":"35810",
    "sg:province":"AL",
    "wof:name":"Calvin Ledet",
    "wof:placetype":"venue"
},
  "geometry": {"coordinates":[-86.641599,34.77507],"type":"Point"}
}