{
  "type": "Feature",
  "properties": {
    "iso:country":"US",
    "sg:address":"3144 Old Columbiana Rd",
    "sg:city":"Birmingham",
    "sg:classifiers":[
        {
            "category":"Professional",
            "subcategory":"Accounting & Tax Preparation",
            "type":"Services"
        }
    ],
    "sg:phone":"+1 205 979 3839",
    "sg:postcode":"35226",
    "sg:province":"AL",
    "wof:name":"Brinton A Owen CPA",
    "wof:placetype":"venue"
},
  "geometry": {"coordinates":[-86.807795,33.404421],"type":"Point"}
}