{
  "type": "Feature",
  "properties": {
    "iso:country":"US",
    "sg:address":"4533 Valleydale Rd",
    "sg:city":"Birmingham",
    "sg:classifiers":[
        {
            "category":"Shopping",
            "subcategory":"Books",
            "type":"Retail Goods"
        }
    ],
    "sg:phone":"+1 205 995 5580",
    "sg:postcode":"35242",
    "sg:province":"AL",
    "wof:name":"Snoozys College Bookstore",
    "wof:placetype":"venue"
},
  "geometry": {"coordinates":[-86.73731,33.38467],"type":"Point"}
}