{
  "type": "Feature",
  "properties": {
    "iso:country":"US",
    "sg:address":"666 Old Winchester Rd",
    "sg:city":"New Market",
    "sg:classifiers":[
        {
            "category":"Retail",
            "subcategory":"Repair Shop",
            "type":"Services"
        }
    ],
    "sg:phone":"+1 256 379 3575",
    "sg:postcode":"35761",
    "sg:province":"AL",
    "wof:name":"Winchester Small Engines",
    "wof:placetype":"venue"
},
  "geometry": {"coordinates":[-86.39966099999999,34.972244],"type":"Point"}
}