{
  "type": "Feature",
  "properties": {
    "iso:country":"US",
    "sg:address":"699 Gallatin St SW",
    "sg:city":"Huntsville",
    "sg:classifiers":[
        {
            "category":"Health Services",
            "subcategory":"Nursing And Care Facility",
            "type":"Services"
        },
        {
            "category":"Insurance",
            "subcategory":"Insurance Agent",
            "type":"Services"
        }
    ],
    "sg:phone":"+1 256 864 4100",
    "sg:postcode":"35801",
    "sg:province":"AL",
    "sg:tags":[
        "manage",
        "accident"
    ],
    "wof:name":"First Community Health Plan",
    "wof:placetype":"venue"
},
  "geometry": {"coordinates":[-86.58322699999999,34.724142],"type":"Point"}
}