{
  "type": "Feature",
  "properties": {
    "addr:full":"3410 Old Selma Rd Montgomery AL 36108",
    "addr:housenumber":"3410",
    "addr:postcode":"36108",
    "addr:street":"Old Selma Rd",
    "iso:country":"US",
    "sg:address":"3410 Old Selma Rd",
    "sg:city":"Montgomery",
    "sg:classifiers":[
        {
            "category":"Organizations",
            "subcategory":"Religious Organization",
            "type":"Services"
        }
    ],
    "sg:phone":"+1 334 263 0701",
    "sg:postcode":"36108",
    "sg:province":"AL",
    "sg:tags":[
        "church"
    ],
    "wof:name":"Greater Bible Way Temple",
    "wof:placetype":"venue"
},
  "geometry": {"coordinates":[-86.378441,32.352616],"type":"Point"}
}