{
  "type": "Feature",
  "properties": {
    "iso:country":"US",
    "sg:address":"417 Buttercup Ln",
    "sg:city":"Montevallo",
    "sg:classifiers":[
        {
            "category":"Building & Trades",
            "subcategory":"Construction",
            "type":"Services"
        }
    ],
    "sg:phone":"+1 205 665 2301",
    "sg:postcode":"35115",
    "sg:province":"AL",
    "wof:name":"Byrd Contractors Inc",
    "wof:placetype":"venue"
},
  "geometry": {"coordinates":[-86.800809,33.161544],"type":"Point"}
}