{
  "type": "Feature",
  "properties": {
    "iso:country":"US",
    "sg:address":"8272 State Rte 59",
    "sg:city":"Foley",
    "sg:classifiers":[
        {
            "category":"Restaurant",
            "type":"Food & Drink"
        }
    ],
    "sg:phone":"+1 251 943 8730",
    "sg:postcode":"36535",
    "sg:province":"AL",
    "sg:tags":[
        "eating"
    ],
    "wof:name":"Two Jays",
    "wof:placetype":"venue"
},
  "geometry": {"coordinates":[-87.683348,30.348544],"type":"Point"}
}