{
  "type": "Feature",
  "properties": {
    "iso:country":"US",
    "sg:address":"510 Airport Dr",
    "sg:city":"Foley",
    "sg:classifiers":[
        {
            "category":"Airport",
            "type":"Transportation"
        }
    ],
    "sg:phone":"+1 251 943 5214",
    "sg:postcode":"36535",
    "sg:province":"AL",
    "wof:name":"JLS Aviation",
    "wof:placetype":"venue"
},
  "geometry": {"coordinates":[-87.70347099999999,30.428918],"type":"Point"}
}