{
  "type": "Feature",
  "properties": {
    "iso:country":"US",
    "sg:address":"1723 2nd Ave",
    "sg:city":"Tuscaloosa",
    "sg:classifiers":[
        {
            "category":"Professional",
            "subcategory":"Management & Consulting",
            "type":"Services"
        }
    ],
    "sg:phone":"+1 205 752 0047",
    "sg:postcode":"35401",
    "sg:province":"AL",
    "sg:tags":[
        "consultant"
    ],
    "wof:name":"Geo Consultants LLC",
    "wof:placetype":"venue"
},
  "geometry": {"coordinates":[-87.538111,33.194848],"type":"Point"}
}