{
  "type": "Feature",
  "properties": {
    "addr:full":"1120 17th Ave Calera AL 35040",
    "addr:housenumber":"1120",
    "addr:postcode":"35040",
    "addr:street":"17Th Ave",
    "iso:country":"US",
    "sg:address":"1120 17th Ave",
    "sg:city":"Calera",
    "sg:classifiers":[
        {
            "category":"Personal",
            "subcategory":"Beauty Salon",
            "type":"Services"
        }
    ],
    "sg:phone":"+1 205 668 2828",
    "sg:postcode":"35040",
    "sg:province":"AL",
    "wof:name":"Hair Studio & More",
    "wof:placetype":"venue"
},
  "geometry": {"coordinates":[-86.751975,33.102055],"type":"Point"}
}