{
  "type": "Feature",
  "properties": {
    "addr:full":"9709 Parkway E Birmingham AL 35215",
    "addr:housenumber":"9709",
    "addr:postcode":"35215",
    "addr:street":"Parkway E",
    "iso:country":"US",
    "sg:address":"9709 Parkway E",
    "sg:city":"Birmingham",
    "sg:classifiers":[
        {
            "category":"Health Services",
            "subcategory":"Doctor",
            "type":"Services"
        }
    ],
    "sg:phone":"+1 205 836 1199",
    "sg:postcode":"35215",
    "sg:province":"AL",
    "sg:tags":[
        "practice",
        "family"
    ],
    "wof:name":"Trinity Medical Clinics At Center Point-Family Medicine",
    "wof:placetype":"venue"
},
  "geometry": {"coordinates":[-86.69179,33.600411],"type":"Point"}
}