{
  "type": "Feature",
  "properties": {
    "iso:country":"US",
    "sg:address":"608 Gardner Dr SE",
    "sg:city":"Jacksonville",
    "sg:classifiers":[
        {
            "category":"Shopping",
            "subcategory":"Gifts & Souvenirs",
            "type":"Retail Goods"
        }
    ],
    "sg:phone":"+1 256 435 3330",
    "sg:postcode":"36265",
    "sg:province":"AL",
    "sg:tags":[
        "shop"
    ],
    "wof:name":"M & E Gift Hut & Variety Shop",
    "wof:placetype":"venue"
},
  "geometry": {"coordinates":[-85.75114000000001,33.810986],"type":"Point"}
}