{
  "type": "Feature",
  "properties": {
    "iso:country":"US",
    "sg:address":"2501 Greenwood Dr SE",
    "sg:city":"Decatur",
    "sg:classifiers":[
        {
            "category":"Freight",
            "type":"Transportation"
        }
    ],
    "sg:phone":"+1 256 353 1159",
    "sg:postcode":"35601",
    "sg:province":"AL",
    "sg:tags":[
        "arrangement"
    ],
    "wof:name":"Advantage Transportation Inc",
    "wof:placetype":"venue"
},
  "geometry": {"coordinates":[-86.945968,34.578402],"type":"Point"}
}