{
  "type": "Feature",
  "properties": {
    "iso:country":"US",
    "sg:address":"133 Moss Hill Ln",
    "sg:city":"Calera",
    "sg:classifiers":[
        {
            "category":"Professional",
            "type":"Services"
        }
    ],
    "sg:phone":"+1 205 482 2226",
    "sg:postcode":"35040",
    "sg:province":"AL",
    "wof:name":"Alabama Utility Services Inc",
    "wof:placetype":"venue"
},
  "geometry": {"coordinates":[-86.77193200000001,33.14289],"type":"Point"}
}