{
  "type": "Feature",
  "properties": {
    "iso:country":"US",
    "sg:address":"3065 Brookhill Dr",
    "sg:city":"Birmingham",
    "sg:classifiers":[
        {
            "category":"Shopping",
            "subcategory":"Computers & Home Electronics",
            "type":"Retail Goods"
        }
    ],
    "sg:phone":"+1 205 991 8020",
    "sg:postcode":"35242",
    "sg:province":"AL",
    "sg:tags":[
        "software"
    ],
    "wof:name":"Computer Works Inc",
    "wof:placetype":"venue"
},
  "geometry": {"coordinates":[-86.701587,33.402566],"type":"Point"}
}