{
  "type": "Feature",
  "properties": {
    "addr:full":"125 N Broadnax St Dadeville AL 36853",
    "addr:housenumber":"125",
    "addr:postcode":"36853",
    "addr:street":"N Broadnax St",
    "iso:country":"US",
    "sg:address":"125 N Broadnax St",
    "sg:city":"Dadeville",
    "sg:classifiers":[
        {
            "category":"Professional",
            "subcategory":"Employment Agencies",
            "type":"Services"
        }
    ],
    "sg:phone":"+1 256 825 1081",
    "sg:postcode":"36853",
    "sg:province":"AL",
    "wof:name":"Tallapoosa County Bd Registar",
    "wof:placetype":"venue"
},
  "geometry": {"coordinates":[-85.76360200000001,32.831141],"type":"Point"}
}