{
  "type": "Feature",
  "properties": {
    "addr:full":"19576 State Rte 117 Ider AL 35981",
    "addr:housenumber":"19576",
    "addr:postcode":"35981",
    "addr:street":"State Rte 117 Ider",
    "iso:country":"US",
    "sg:address":"19576 State Rte 117",
    "sg:city":"Ider",
    "sg:classifiers":[
        {
            "category":"Wholesale",
            "subcategory":"Machinery & Supplies",
            "type":"Manufacturing & Wholesale Goods"
        }
    ],
    "sg:phone":"+1 256 657 5750",
    "sg:postcode":"35981",
    "sg:province":"AL",
    "sg:tags":[
        "feed",
        "equipment",
        "industrial"
    ],
    "wof:name":"Wootten AG & Landscape",
    "wof:placetype":"venue"
},
  "geometry": {"coordinates":[-85.667619,34.692716],"type":"Point"}
}