{
  "type": "Feature",
  "properties": {
    "addr:full":"3714 Hargrove Rd E Tuscaloosa AL 35405",
    "addr:housenumber":"3714",
    "addr:postcode":"35405",
    "addr:street":"Hargrove Rd E",
    "iso:country":"US",
    "sg:address":"3714 Hargrove Rd E",
    "sg:city":"Tuscaloosa",
    "sg:classifiers":[
        {
            "category":"Wholesale",
            "subcategory":"Machinery & Supplies",
            "type":"Manufacturing & Wholesale Goods"
        }
    ],
    "sg:phone":"+1 205 556 0208",
    "sg:postcode":"35405",
    "sg:province":"AL",
    "sg:tags":[
        "fire",
        "department",
        "equipment"
    ],
    "wof:name":"Tuscaloosa Fire Equipment",
    "wof:placetype":"venue"
},
  "geometry": {"coordinates":[-87.489515,33.172595],"type":"Point"}
}