{
  "type": "Feature",
  "properties": {
    "iso:country":"US",
    "sg:address":"625 Madison Ave",
    "sg:city":"Montgomery",
    "sg:classifiers":[
        {
            "category":"Restaurant",
            "type":"Food & Drink"
        }
    ],
    "sg:menulink":"http://www.allmenus.com/al/montgomery/173911-wendys/menu/",
    "sg:phone":"+1 334 264 7103",
    "sg:postcode":"36104",
    "sg:province":"AL",
    "sg:tags":[
        "burger",
        "american",
        "soup"
    ],
    "wof:name":"Wendy's",
    "wof:placetype":"venue"
},
  "geometry": {"coordinates":[-86.301087,32.380015],"type":"Point"}
}