{
  "type": "Feature",
  "properties": {
    "addr:full":"1106 S Quintard Ave Anniston AL 36201",
    "addr:housenumber":"1106",
    "addr:postcode":"36201",
    "addr:street":"S Quintard Ave",
    "iso:country":"US",
    "sg:address":"1106 S Quintard Ave",
    "sg:city":"Anniston",
    "sg:classifiers":[
        {
            "category":"Banks & Credit Unions",
            "subcategory":"Bank",
            "type":"Services"
        }
    ],
    "sg:phone":"+1 256 435 2028",
    "sg:postcode":"36201",
    "sg:province":"AL",
    "sg:tags":[
        "loan"
    ],
    "wof:name":"Columbus Finance Co",
    "wof:placetype":"venue"
},
  "geometry": {"coordinates":[-85.82552099999999,33.633021],"type":"Point"}
}