{
  "type": "Feature",
  "properties": {
    "addr:full":"12891 Dickens Ln Madison AL 35756",
    "addr:housenumber":"12891",
    "addr:postcode":"35756",
    "addr:street":"Dickens Ln",
    "iso:country":"US",
    "sg:address":"12891 Dickens Ln",
    "sg:city":"Madison",
    "sg:classifiers":[
        {
            "category":"Building & Trades",
            "subcategory":"Landscaping Services",
            "type":"Services"
        }
    ],
    "sg:phone":"+1 256 233 2803",
    "sg:postcode":"35756",
    "sg:province":"AL",
    "sg:tags":[
        "landscape",
        "contractor"
    ],
    "wof:name":"Landscape Images Inc",
    "wof:placetype":"venue"
},
  "geometry": {"coordinates":[-86.788344,34.742169],"type":"Point"}
}