{
  "type": "Feature",
  "properties": {
    "iso:country":"US",
    "sg:address":"510 Emery Dr W",
    "sg:city":"Birmingham",
    "sg:classifiers":[
        {
            "category":"Professional",
            "subcategory":"Engineering",
            "type":"Services"
        }
    ],
    "sg:phone":"+1 205 982 9806",
    "sg:postcode":"35244",
    "sg:province":"AL",
    "sg:tags":[
        "engineer"
    ],
    "sg:website":"www.garylowen.com",
    "wof:name":"Gary L Owen & Assoc Inc",
    "wof:placetype":"venue"
},
  "geometry": {"coordinates":[-86.846877,33.352033],"type":"Point"}
}