{
  "type": "Feature",
  "properties": {
    "iso:country":"US",
    "sg:address":"110 Clinic St",
    "sg:city":"New Market",
    "sg:classifiers":[
        {
            "category":"Health Services",
            "subcategory":"Doctor",
            "type":"Services"
        }
    ],
    "sg:phone":"+1 256 379 2101",
    "sg:postcode":"35761",
    "sg:province":"AL",
    "sg:tags":[
        "medical"
    ],
    "wof:name":"New Market Clinic",
    "wof:placetype":"venue"
},
  "geometry": {"coordinates":[-86.42854,34.906624],"type":"Point"}
}