{
  "type": "Feature",
  "properties": {
    "iso:country":"US",
    "sg:address":"637 Boll Weevil Cir",
    "sg:city":"Enterprise",
    "sg:classifiers":[
        {
            "category":"Restaurant",
            "type":"Food & Drink"
        }
    ],
    "sg:phone":"+1 334 308 1550",
    "sg:postcode":"36330",
    "sg:province":"AL",
    "wof:name":"Waffle House",
    "wof:placetype":"venue"
},
  "geometry": {"coordinates":[-85.86004699999999,31.334055],"type":"Point"}
}