{
  "type": "Feature",
  "properties": {
    "addr:full":"300 W Brunson St Enterprise AL 36330",
    "addr:housenumber":"300",
    "addr:postcode":"36330",
    "addr:street":"W Brunson St",
    "iso:country":"US",
    "sg:address":"300 W Brunson St",
    "sg:city":"Enterprise",
    "sg:classifiers":[
        {
            "category":"Professional",
            "type":"Services"
        }
    ],
    "sg:phone":"+1 334 393 3437",
    "sg:postcode":"36330",
    "sg:province":"AL",
    "wof:name":"Hamilton Camira",
    "wof:placetype":"venue"
},
  "geometry": {"coordinates":[-85.858745,31.315949],"type":"Point"}
}