{
  "type": "Feature",
  "properties": {
    "addr:full":"1304 Lane Ave Fultondale AL 35068",
    "addr:housenumber":"1304",
    "addr:postcode":"35068",
    "addr:street":"Lane Ave",
    "iso:country":"US",
    "sg:address":"1304 Lane Ave",
    "sg:city":"Fultondale",
    "sg:classifiers":[
        {
            "category":"Shopping",
            "type":"Retail Goods"
        }
    ],
    "sg:phone":"+1 205 841 2423",
    "sg:postcode":"35068",
    "sg:province":"AL",
    "sg:tags":[
        "merchandise"
    ],
    "wof:name":"Brian Green",
    "wof:placetype":"venue"
},
  "geometry": {"coordinates":[-86.801247,33.608862],"type":"Point"}
}