{
  "type": "Feature",
  "properties": {
    "iso:country":"US",
    "sg:address":"2926 Una St",
    "sg:city":"Birmingham",
    "sg:classifiers":[
        {
            "category":"Real Estate",
            "subcategory":"Real Estate Operator",
            "type":"Services"
        }
    ],
    "sg:phone":"+1 205 674 0222",
    "sg:postcode":"35214",
    "sg:province":"AL",
    "sg:tags":[
        "mobile",
        "home",
        "community"
    ],
    "wof:name":"Forestdale Mobile Home Comm",
    "wof:placetype":"venue"
},
  "geometry": {"coordinates":[-86.892853,33.611583],"type":"Point"}
}