{
  "type": "Feature",
  "properties": {
    "addr:full":"1214 Gilmer Ave Tallassee AL 36078",
    "addr:housenumber":"1214",
    "addr:postcode":"36078",
    "addr:street":"Gilmer Ave",
    "iso:country":"US",
    "sg:address":"1214 Gilmer Ave",
    "sg:city":"Tallassee",
    "sg:classifiers":[
        {
            "category":"Manufacturing",
            "subcategory":"Signs",
            "type":"Manufacturing & Wholesale Goods"
        }
    ],
    "sg:phone":"+1 334 283 4398",
    "sg:postcode":"36078",
    "sg:province":"AL",
    "wof:name":"Brantley's Sign Svc",
    "wof:placetype":"venue"
},
  "geometry": {"coordinates":[-85.911868,32.547095],"type":"Point"}
}