{
  "type": "Feature",
  "properties": {
    "iso:country":"US",
    "sg:address":"4750 Woodmere Blvd",
    "sg:city":"Montgomery",
    "sg:classifiers":[
        {
            "category":"Professional",
            "type":"Services"
        }
    ],
    "sg:phone":"+1 334 264 3322",
    "sg:postcode":"36106",
    "sg:province":"AL",
    "sg:tags":[
        "establishment"
    ],
    "wof:name":"Outside Ideas",
    "wof:placetype":"venue"
},
  "geometry": {"coordinates":[-86.225611,32.355677],"type":"Point"}
}