{
  "type": "Feature",
  "properties": {
    "iso:country":"US",
    "sg:address":"21332 State Rte 59",
    "sg:city":"Robertsdale",
    "sg:classifiers":[
        {
            "category":"Insurance",
            "subcategory":"Insurance Agent",
            "type":"Services"
        }
    ],
    "sg:phone":"+1 251 947 7761",
    "sg:postcode":"36567",
    "sg:province":"AL",
    "wof:name":"Alfa Insurance Corp",
    "wof:placetype":"venue"
},
  "geometry": {"coordinates":[-87.708304,30.536048],"type":"Point"}
}