{
  "type": "Feature",
  "properties": {
    "iso:country":"US",
    "sg:address":"601 S Main St",
    "sg:city":"Citronelle",
    "sg:classifiers":[
        {
            "category":"Real Estate",
            "subcategory":"Real Estate Operator",
            "type":"Services"
        }
    ],
    "sg:phone":"+1 251 866 7541",
    "sg:postcode":"36522",
    "sg:province":"AL",
    "sg:tags":[
        "apartment"
    ],
    "wof:name":"Treetops Apartments",
    "wof:placetype":"venue"
},
  "geometry": {"coordinates":[-88.230266,31.08135],"type":"Point"}
}