{
  "type": "Feature",
  "properties": {
    "addr:full":"101 Sardis Dr Boaz AL 35956",
    "addr:housenumber":"101",
    "addr:postcode":"35956",
    "addr:street":"Sardis Dr",
    "iso:country":"US",
    "sg:address":"101 Sardis Dr",
    "sg:city":"Boaz",
    "sg:classifiers":[
        {
            "category":"Home & Garden",
            "subcategory":"Carpets & Floor Coverings",
            "type":"Retail Goods"
        }
    ],
    "sg:phone":"+1 256 593 7822",
    "sg:postcode":"35956",
    "sg:province":"AL",
    "sg:tags":[
        "dealer",
        "rug"
    ],
    "wof:name":"Millers Carpet & Tile",
    "wof:placetype":"venue"
},
  "geometry": {"coordinates":[-86.13886100000001,34.170863],"type":"Point"}
}