{
  "type": "Feature",
  "properties": {
    "addr:full":"3201 Airport Blvd Mobile AL 36608",
    "addr:housenumber":"3201",
    "addr:postcode":"36608",
    "addr:street":"Airport Blvd",
    "iso:country":"US",
    "sg:address":"3201 Airport Blvd",
    "sg:city":"Mobile",
    "sg:classifiers":[
        {
            "category":"Retail",
            "subcategory":"Photofinishing",
            "type":"Services"
        }
    ],
    "sg:phone":"+1 251 450 0717",
    "sg:postcode":"36608",
    "sg:province":"AL",
    "sg:tags":[
        "laboratory"
    ],
    "wof:name":"Qualex Inc",
    "wof:placetype":"venue"
},
  "geometry": {"coordinates":[-88.120026,30.676118],"type":"Point"}
}