{
  "type": "Feature",
  "properties": {
    "addr:full":"32485 US Hwy 90 Seminole AL 36574",
    "addr:housenumber":"32485",
    "addr:postcode":"36574",
    "addr:street":"Us Hwy 90",
    "iso:country":"US",
    "sg:address":"32485 US Hwy 90",
    "sg:city":"Seminole",
    "sg:classifiers":[
        {
            "category":"Shopping",
            "subcategory":"Used Merchandise",
            "type":"Retail Goods"
        }
    ],
    "sg:phone":"+1 251 946 2284",
    "sg:postcode":"36574",
    "sg:province":"AL",
    "sg:tags":[
        "pawnbroker"
    ],
    "wof:name":"Gulf Coast Communications",
    "wof:placetype":"venue"
},
  "geometry": {"coordinates":[-87.473793,30.515147],"type":"Point"}
}