{
  "type": "Feature",
  "properties": {
    "addr:full":"2100 3rd Ave S Jasper AL 35501",
    "addr:housenumber":"2100",
    "addr:postcode":"35501",
    "addr:street":"3Rd Ave S",
    "iso:country":"US",
    "sg:address":"2100 3rd Ave S",
    "sg:city":"Jasper",
    "sg:classifiers":[
        {
            "category":"Building & Trades",
            "subcategory":"Construction",
            "type":"Services"
        }
    ],
    "sg:phone":"+1 205 384 9100",
    "sg:postcode":"35501",
    "sg:province":"AL",
    "sg:tags":[
        "home",
        "builder"
    ],
    "wof:name":"Alabama Home Construction",
    "wof:placetype":"venue"
},
  "geometry": {"coordinates":[-87.277458,33.831118],"type":"Point"}
}