{
  "type": "Feature",
  "properties": {
    "iso:country":"US",
    "sg:address":"4209 University Blvd E",
    "sg:city":"Tuscaloosa",
    "sg:classifiers":[
        {
            "category":"Cinema",
            "subcategory":"Movie Rental",
            "type":"Entertainment"
        }
    ],
    "sg:phone":"+1 205 553 8538",
    "sg:postcode":"35404",
    "sg:province":"AL",
    "sg:tags":[
        "video",
        "tape"
    ],
    "wof:name":"Movie Gallery",
    "wof:placetype":"venue"
},
  "geometry": {"coordinates":[-87.48029200000001,33.197816],"type":"Point"}
}