{
  "type": "Feature",
  "properties": {
    "addr:full":"20451 US Hwy 43 Mt Vernon AL 36560",
    "addr:postcode":"20451;36560",
    "addr:street":"Us Hwy 43",
    "iso:country":"US",
    "sg:address":"20451 US Hwy 43",
    "sg:city":"Mt Vernon",
    "sg:classifiers":[
        {
            "category":"Utilities",
            "subcategory":"Natural Gas",
            "type":"Services"
        }
    ],
    "sg:phone":"+1 251 829 6250",
    "sg:postcode":"36560",
    "sg:province":"AL",
    "wof:name":"Florida Gas Transmission Co",
    "wof:placetype":"venue"
},
  "geometry": {"coordinates":[-88.00944800000001,31.111778],"type":"Point"}
}