{
  "type": "Feature",
  "properties": {
    "iso:country":"US",
    "sg:address":"256 E Washington St",
    "sg:city":"Abbeville",
    "sg:classifiers":[
        {
            "category":"Wholesale",
            "subcategory":"Farm Supplies",
            "type":"Manufacturing & Wholesale Goods"
        }
    ],
    "sg:phone":"+1 334 585 5413",
    "sg:postcode":"36310",
    "sg:province":"AL",
    "sg:tags":[
        "feed"
    ],
    "wof:name":"Mc Coy's Farm & Garden Ctr",
    "wof:placetype":"venue"
},
  "geometry": {"coordinates":[-85.242706,31.570889],"type":"Point"}
}