{
  "type": "Feature",
  "properties": {
    "iso:country":"US",
    "sg:address":"133 Sundance Trl",
    "sg:city":"Alabaster",
    "sg:classifiers":[
        {
            "category":"Professional",
            "subcategory":"Detective & Security Services",
            "type":"Services"
        }
    ],
    "sg:phone":"+1 205 281 8238",
    "sg:postcode":"35007",
    "sg:province":"AL",
    "sg:tags":[
        "car"
    ],
    "wof:name":"ADT Security Employee",
    "wof:placetype":"venue"
},
  "geometry": {"coordinates":[-86.830232,33.255056],"type":"Point"}
}