{
  "type": "Feature",
  "properties": {
    "addr:full":"108 Co Rd 412 Killen AL 35645",
    "addr:housenumber":"108",
    "addr:postcode":"35645",
    "addr:street":"Co Rd 412",
    "iso:country":"US",
    "sg:address":"108 Co Rd 412",
    "sg:city":"Killen",
    "sg:classifiers":[
        {
            "category":"Professional",
            "subcategory":"Business Services",
            "type":"Services"
        }
    ],
    "sg:phone":"+1 256 757 7050",
    "sg:postcode":"35645",
    "sg:province":"AL",
    "wof:name":"Delphi Group LLC",
    "wof:placetype":"venue"
},
  "geometry": {"coordinates":[-87.44728600000001,34.818431],"type":"Point"}
}