{
  "type": "Feature",
  "properties": {
    "addr:full":"202 Ida Moody Rd Scottsboro AL 35769",
    "addr:housenumber":"202",
    "addr:postcode":"35769",
    "addr:street":"Ida Moody Rd",
    "iso:country":"US",
    "sg:address":"202 Ida Moody Rd",
    "sg:city":"Scottsboro",
    "sg:classifiers":[
        {
            "category":"Education",
            "subcategory":"School",
            "type":"Public Place"
        }
    ],
    "sg:phone":"+1 256 259 4181",
    "sg:postcode":"35769",
    "sg:province":"AL",
    "wof:name":"Nelson Head Start",
    "wof:placetype":"venue"
},
  "geometry": {"coordinates":[-86.05351400000001,34.624104],"type":"Point"}
}