{
  "type": "Feature",
  "properties": {
    "addr:full":"2408 7th Ave S Birmingham AL 35233",
    "addr:housenumber":"2408",
    "addr:postcode":"35233",
    "addr:street":"7Th Ave S",
    "iso:country":"US",
    "sg:address":"2408 7th Ave S",
    "sg:city":"Birmingham",
    "sg:classifiers":[
        {
            "category":"Shopping",
            "subcategory":"Used Merchandise",
            "type":"Retail Goods"
        }
    ],
    "sg:phone":"+1 205 252 5549",
    "sg:postcode":"35233",
    "sg:province":"AL",
    "sg:tags":[
        "antique"
    ],
    "wof:name":"Antiques & Garden's",
    "wof:placetype":"venue"
},
  "geometry": {"coordinates":[-86.79312899999999,33.509145],"type":"Point"}
}