{
  "type": "Feature",
  "properties": {
    "iso:country":"US",
    "sg:address":"1600 7th Ave S",
    "sg:city":"Birmingham",
    "sg:classifiers":[
        {
            "category":"Health Services",
            "subcategory":"Hospital",
            "type":"Services"
        },
        {
            "category":"Health Services",
            "subcategory":"Doctor",
            "type":"Services"
        }
    ],
    "sg:phone":"+1 205 939 9193",
    "sg:postcode":"35233",
    "sg:province":"AL",
    "sg:tags":[
        "physician",
        "surgeon",
        "psychiatric"
    ],
    "wof:name":"Children's Behavioral Health",
    "wof:placetype":"venue"
},
  "geometry": {"coordinates":[-86.80674999999999,33.502595],"type":"Point"}
}