{
  "type": "Feature",
  "properties": {
    "addr:full":"28 Phillips Ct Empire AL 35148",
    "addr:housenumber":"28",
    "addr:postcode":"35148",
    "addr:street":"Phillips Ct",
    "iso:country":"US",
    "sg:address":"28 Phillips Ct",
    "sg:city":"Empire",
    "sg:classifiers":[
        {
            "category":"Building & Trades",
            "subcategory":"Construction",
            "type":"Services"
        }
    ],
    "sg:phone":"+1 205 648 4679",
    "sg:postcode":"35148",
    "sg:province":"AL",
    "sg:tags":[
        "concrete",
        "contractor"
    ],
    "wof:name":"Phillips Concrete Service",
    "wof:placetype":"venue"
},
  "geometry": {"coordinates":[-87.030683,33.768118],"type":"Point"}
}