{
  "type": "Feature",
  "properties": {
    "addr:full":"427 Leighton Ave Anniston AL 36207",
    "addr:housenumber":"427",
    "addr:postcode":"36207",
    "addr:street":"Leighton Ave",
    "iso:country":"US",
    "sg:address":"427 Leighton Ave",
    "sg:city":"Anniston",
    "sg:classifiers":[
        {
            "category":"Retail",
            "subcategory":"Car Wash",
            "type":"Services"
        }
    ],
    "sg:phone":"+1 256 235 0760",
    "sg:postcode":"36207",
    "sg:province":"AL",
    "sg:tags":[
        "carwash",
        "automobile",
        "detail",
        "clean"
    ],
    "wof:name":"S & B Clean Up Shop",
    "wof:placetype":"venue"
},
  "geometry": {"coordinates":[-85.824905,33.649921],"type":"Point"}
}