{
  "type": "Feature",
  "properties": {
    "addr:full":"183 Woody Cir New Hope AL 35760",
    "addr:housenumber":"183",
    "addr:postcode":"35760",
    "addr:street":"Woody Cir",
    "iso:country":"US",
    "sg:address":"183 Woody Cir",
    "sg:city":"New Hope",
    "sg:classifiers":[
        {
            "category":"Farming",
            "subcategory":"Farm",
            "type":"Manufacturing & Wholesale Goods"
        }
    ],
    "sg:phone":"+1 256 723 2808",
    "sg:postcode":"35760",
    "sg:province":"AL",
    "sg:tags":[
        "crop",
        "general"
    ],
    "wof:name":"F&W Farms",
    "wof:placetype":"venue"
},
  "geometry": {"coordinates":[-86.365962,34.574535],"type":"Point"}
}