{
  "type": "Feature",
  "properties": {
    "iso:country":"US",
    "sg:address":"520 Lookout Dr",
    "sg:city":"Arab",
    "sg:classifiers":[
        {
            "category":"Building & Trades",
            "subcategory":"Landscaping Services",
            "type":"Services"
        }
    ],
    "sg:phone":"+1 256 586 0683",
    "sg:postcode":"35016",
    "sg:province":"AL",
    "sg:tags":[
        "landscape"
    ],
    "wof:name":"Bradley Landscaping",
    "wof:placetype":"venue"
},
  "geometry": {"coordinates":[-86.440336,34.307923],"type":"Point"}
}