{
  "type": "Feature",
  "properties": {
    "iso:country":"US",
    "sg:address":"9140 Cox Gap Rd",
    "sg:city":"Boaz",
    "sg:classifiers":[
        {
            "category":"Retail",
            "subcategory":"Auto Repair",
            "type":"Services"
        }
    ],
    "sg:phone":"+1 256 593 9440",
    "sg:postcode":"35956",
    "sg:province":"AL",
    "sg:tags":[
        "truck"
    ],
    "wof:name":"Speedy Diesel Svc",
    "wof:placetype":"venue"
},
  "geometry": {"coordinates":[-86.139619,34.168066],"type":"Point"}
}