{
  "type": "Feature",
  "properties": {
    "iso:country":"US",
    "sg:address":"8006 Madison Pike",
    "sg:city":"Madison",
    "sg:classifiers":[
        {
            "category":"Organizations",
            "subcategory":"Religious Organization",
            "type":"Services"
        }
    ],
    "sg:phone":"+1 256 772 0090",
    "sg:postcode":"35758",
    "sg:province":"AL",
    "sg:tags":[
        "church"
    ],
    "wof:name":"Real Ministries",
    "wof:placetype":"venue"
},
  "geometry": {"coordinates":[-86.719895,34.706389],"type":"Point"}
}