{
  "type": "Feature",
  "properties": {
    "iso:country":"US",
    "sg:address":"2804 Lurleen B Wallace Blvd",
    "sg:city":"Northport",
    "sg:classifiers":[
        {
            "category":"Health Services",
            "subcategory":"Clinic",
            "type":"Services"
        }
    ],
    "sg:phone":"+1 205 330 8889",
    "sg:postcode":"35476",
    "sg:province":"AL",
    "wof:name":"Care First Home Health",
    "wof:placetype":"venue"
},
  "geometry": {"coordinates":[-87.57668,33.235558],"type":"Point"}
}