{
  "type": "Feature",
  "properties": {
    "iso:country":"US",
    "sg:address":"41306 State Rte 75",
    "sg:city":"Geraldine",
    "sg:classifiers":[
        {
            "category":"Banks & Credit Unions",
            "subcategory":"Bank",
            "type":"Services"
        }
    ],
    "sg:phone":"+1 256 659 5555",
    "sg:postcode":"35974",
    "sg:province":"AL",
    "sg:tags":[
        "cashing",
        "check"
    ],
    "wof:name":"Fast Cash",
    "wof:placetype":"venue"
},
  "geometry": {"coordinates":[-86.00237300000001,34.365672],"type":"Point"}
}