{
  "type": "Feature",
  "properties": {
    "iso:country":"US",
    "sg:address":"305 E Stewart Ave",
    "sg:city":"Opp",
    "sg:classifiers":[
        {
            "category":"Education",
            "subcategory":"School",
            "type":"Public Place"
        }
    ],
    "sg:phone":"+1 334 493 3173",
    "sg:postcode":"36467",
    "sg:province":"AL",
    "wof:name":"Opp Superintendent",
    "wof:placetype":"venue"
},
  "geometry": {"coordinates":[-86.250694,31.28616],"type":"Point"}
}