{
  "type": "Feature",
  "properties": {
    "iso:country":"US",
    "sg:address":"475 Mount Zion Rd",
    "sg:city":"Madison",
    "sg:classifiers":[
        {
            "category":"Professional",
            "subcategory":"Business Services",
            "type":"Services"
        }
    ],
    "sg:phone":"+1 256 837 0672",
    "sg:postcode":"35757",
    "sg:province":"AL",
    "wof:name":"Pack Enterprises Pack Ent",
    "wof:placetype":"venue"
},
  "geometry": {"coordinates":[-86.729069,34.786654],"type":"Point"}
}