{
  "type": "Feature",
  "properties": {
    "addr:full":"505 Energy Center Blvd Northport AL 35473",
    "addr:housenumber":"505",
    "addr:postcode":"35473",
    "addr:street":"Energy Center Blvd",
    "iso:country":"US",
    "sg:address":"505 Energy Center Blvd",
    "sg:city":"Northport",
    "sg:classifiers":[
        {
            "category":"Professional",
            "subcategory":"Accounting & Tax Preparation",
            "type":"Services"
        }
    ],
    "sg:phone":"+1 205 349 3840",
    "sg:postcode":"35473",
    "sg:province":"AL",
    "sg:tags":[
        "accountant"
    ],
    "wof:name":"Le Croy Hunter & Co",
    "wof:placetype":"venue"
},
  "geometry": {"coordinates":[-87.551858,33.240199],"type":"Point"}
}