{
  "type": "Feature",
  "properties": {
    "iso:country":"US",
    "sg:address":"2823 Lower Wetumpka Rd",
    "sg:city":"Montgomery",
    "sg:classifiers":[
        {
            "category":"Retail",
            "subcategory":"Self-service Laundry",
            "type":"Services"
        }
    ],
    "sg:phone":"+1 334 517 9971",
    "sg:postcode":"36110",
    "sg:province":"AL",
    "sg:tags":[
        "coin",
        "power"
    ],
    "wof:name":"S & S Laundry",
    "wof:placetype":"venue"
},
  "geometry": {"coordinates":[-86.285653,32.416469],"type":"Point"}
}