{
  "type": "Feature",
  "properties": {
    "iso:country":"US",
    "sg:address":"1403 Dale Cir SE",
    "sg:city":"Huntsville",
    "sg:classifiers":[
        {
            "category":"Building & Trades",
            "subcategory":"Landscaping Services",
            "type":"Services"
        }
    ],
    "sg:phone":"+1 256 536 0666",
    "sg:postcode":"35801",
    "sg:province":"AL",
    "sg:tags":[
        "landscape"
    ],
    "wof:name":"Scenic Landscapes Inc",
    "wof:placetype":"venue"
},
  "geometry": {"coordinates":[-86.564115,34.720576],"type":"Point"}
}