{
  "type": "Feature",
  "properties": {
    "iso:country":"US",
    "sg:address":"205 Oak Hill Rd",
    "sg:city":"Jasper",
    "sg:classifiers":[
        {
            "category":"Health Services",
            "subcategory":"Optometrist",
            "type":"Services"
        }
    ],
    "sg:phone":"+1 205 302 0110",
    "sg:postcode":"35504",
    "sg:province":"AL",
    "wof:name":"Wesley Optometry",
    "wof:placetype":"venue"
},
  "geometry": {"coordinates":[-87.286844,33.854463],"type":"Point"}
}