{
  "type": "Feature",
  "properties": {
    "addr:full":"7452 Pineapple Hwy Greenville AL 36037",
    "addr:housenumber":"7452",
    "addr:postcode":"36037",
    "addr:street":"Pineapple Hwy",
    "iso:country":"US",
    "sg:address":"7452 Pineapple Hwy",
    "sg:city":"Greenville",
    "sg:classifiers":[
        {
            "category":"Farming",
            "subcategory":"Farm",
            "type":"Manufacturing & Wholesale Goods"
        }
    ],
    "sg:phone":"+1 334 382 5109",
    "sg:postcode":"36037",
    "sg:province":"AL",
    "sg:tags":[
        "crop",
        "general"
    ],
    "wof:name":"Sims Farm Co Randal Sims",
    "wof:placetype":"venue"
},
  "geometry": {"coordinates":[-86.74594500000001,31.824365],"type":"Point"}
}