{
  "type": "Feature",
  "properties": {
    "addr:full":"132 1st Ave NW Vernon AL 35555",
    "addr:housenumber":"132",
    "addr:postcode":"35555",
    "addr:street":"1St Ave Nw",
    "iso:country":"US",
    "sg:address":"132 1st Ave NW",
    "sg:city":"Vernon",
    "sg:classifiers":[
        {
            "category":"Insurance",
            "subcategory":"Insurance Agent",
            "type":"Services"
        }
    ],
    "sg:phone":"+1 205 695 6773",
    "sg:postcode":"35555",
    "sg:province":"AL",
    "wof:name":"Alfa Insurance Claims",
    "wof:placetype":"venue"
},
  "geometry": {"coordinates":[-88.110511,33.758049],"type":"Point"}
}