{
  "type": "Feature",
  "properties": {
    "iso:country":"US",
    "sg:address":"867 McQuillen St",
    "sg:city":"Mobile",
    "sg:classifiers":[
        {
            "category":"Organizations",
            "subcategory":"Religious Organization",
            "type":"Services"
        }
    ],
    "sg:phone":"+1 251 694 6900",
    "sg:postcode":"36603",
    "sg:province":"AL",
    "sg:tags":[
        "church"
    ],
    "wof:name":"Christ Overcoming Holiness Chr",
    "wof:placetype":"venue"
},
  "geometry": {"coordinates":[-88.055609,30.66378],"type":"Point"}
}