{
  "type": "Feature",
  "properties": {
    "iso:country":"US",
    "sg:address":"22453 Sea Cliff Dr",
    "sg:city":"Fairhope",
    "sg:classifiers":[
        {
            "category":"Real Estate",
            "subcategory":"Real Estate Agent",
            "type":"Services"
        }
    ],
    "sg:phone":"+1 251 928 8363",
    "sg:postcode":"36559",
    "sg:province":"AL",
    "wof:name":"C B Smith Properties Inc",
    "wof:placetype":"venue"
},
  "geometry": {"coordinates":[-87.899613,30.552916],"type":"Point"}
}