{
  "type": "Feature",
  "properties": {
    "addr:full":"2336 Whitesburg Dr S Huntsville AL 35801",
    "addr:housenumber":"2336",
    "addr:postcode":"35801",
    "addr:street":"Whitesburg Dr S",
    "iso:country":"US",
    "sg:address":"2336 Whitesburg Dr S",
    "sg:city":"Huntsville",
    "sg:classifiers":[
        {
            "category":"Shopping",
            "subcategory":"Jewelry",
            "type":"Retail Goods"
        }
    ],
    "sg:phone":"+1 256 536 5858",
    "sg:postcode":"35801",
    "sg:province":"AL",
    "sg:tags":[
        "precious",
        "metal",
        "mfg"
    ],
    "wof:name":"Emmett Blevins Jewelers",
    "wof:placetype":"venue"
},
  "geometry": {"coordinates":[-86.575534,34.714046],"type":"Point"}
}