{
  "type": "Feature",
  "properties": {
    "addr:full":"811 S RR Ave Opelika AL 36801",
    "addr:housenumber":"811",
    "addr:postcode":"36801",
    "addr:street":"S Rr Ave",
    "iso:country":"US",
    "sg:address":"811 S RR Ave",
    "sg:city":"Opelika",
    "sg:classifiers":[
        {
            "category":"Manufacturing",
            "subcategory":"Apparel",
            "type":"Manufacturing & Wholesale Goods"
        }
    ],
    "sg:phone":"+1 334 741 9073",
    "sg:postcode":"36801",
    "sg:province":"AL",
    "sg:tags":[
        "coat"
    ],
    "wof:name":"Opelika Coffee Co",
    "wof:placetype":"venue"
},
  "geometry": {"coordinates":[-85.380121,32.647321],"type":"Point"}
}