{
  "type": "Feature",
  "properties": {
    "iso:country":"US",
    "sg:address":"334 S Northington St",
    "sg:city":"Prattville",
    "sg:classifiers":[
        {
            "category":"Wholesale",
            "subcategory":"Drugs",
            "type":"Manufacturing & Wholesale Goods"
        }
    ],
    "sg:phone":"+1 334 365 1149",
    "sg:postcode":"36067",
    "sg:province":"AL",
    "wof:name":"Glenco",
    "wof:placetype":"venue"
},
  "geometry": {"coordinates":[-86.467534,32.458347],"type":"Point"}
}