{
  "type": "Feature",
  "properties": {
    "iso:country":"US",
    "sg:address":"312 4th Ave",
    "sg:city":"Tuscumbia",
    "sg:classifiers":[
        {
            "category":"Autos & Motor Vehicles",
            "subcategory":"Automobile Sales",
            "type":"Retail Goods"
        }
    ],
    "sg:phone":"+1 256 389 3933",
    "sg:postcode":"35674",
    "sg:province":"AL",
    "sg:tags":[
        "car",
        "dealer"
    ],
    "wof:name":"Wayne Motors LLC",
    "wof:placetype":"venue"
},
  "geometry": {"coordinates":[-87.72715599999999,34.71377],"type":"Point"}
}