{
  "type": "Feature",
  "properties": {
    "iso:country":"US",
    "sg:address":"3700 Bob Wallace Ave SW",
    "sg:city":"Huntsville",
    "sg:classifiers":[
        {
            "category":"Organizations",
            "subcategory":"Religious Organization",
            "type":"Services"
        }
    ],
    "sg:phone":"+1 256 883 0397",
    "sg:postcode":"35805",
    "sg:province":"AL",
    "wof:name":"Jeff Tankersley Rev",
    "wof:placetype":"venue"
},
  "geometry": {"coordinates":[-86.616769,34.712897],"type":"Point"}
}