{
  "type": "Feature",
  "properties": {
    "iso:country":"US",
    "sg:address":"3301 Veterans Dr",
    "sg:city":"Florence",
    "sg:phone":"+1 256 760 9199",
    "sg:postcode":"35630",
    "sg:province":"AL",
    "sg:tags":[
        "equipment",
        "commercial"
    ],
    "wof:name":"Create-A-Cake",
    "wof:placetype":"venue"
},
  "geometry": {"coordinates":[-87.63416100000001,34.81065],"type":"Point"}
}