{
  "type": "Feature",
  "properties": {
    "addr:full":"507 Limestone Rd Dothan AL 36301",
    "addr:housenumber":"507",
    "addr:postcode":"36301",
    "addr:street":"Limestone Rd",
    "iso:country":"US",
    "sg:address":"507 Limestone Rd",
    "sg:city":"Dothan",
    "sg:classifiers":[
        {
            "category":"Building & Trades",
            "subcategory":"Construction",
            "type":"Services"
        }
    ],
    "sg:phone":"+1 334 671 1076",
    "sg:postcode":"36301",
    "sg:province":"AL",
    "sg:tags":[
        "contracting",
        "general"
    ],
    "wof:name":"Arrowstone Construction Inc",
    "wof:placetype":"venue"
},
  "geometry": {"coordinates":[-85.411326,31.129941],"type":"Point"}
}