{
  "type": "Feature",
  "properties": {
    "iso:country":"US",
    "sg:address":"210 Washington St S",
    "sg:city":"Livingston",
    "sg:classifiers":[
        {
            "category":"Professional",
            "subcategory":"Computer Services",
            "type":"Services"
        }
    ],
    "sg:phone":"+1 205 652 4800",
    "sg:postcode":"35470",
    "sg:province":"AL",
    "sg:tags":[
        "internet"
    ],
    "sg:website":"www.sumternet.com",
    "wof:name":"Sumter Net",
    "wof:placetype":"venue"
},
  "geometry": {"coordinates":[-88.188365,32.583878],"type":"Point"}
}