{
  "type": "Feature",
  "properties": {
    "addr:full":"3201 10th Ave Tuscaloosa AL 35401",
    "addr:housenumber":"3201",
    "addr:postcode":"35401",
    "addr:street":"10Th Ave",
    "iso:country":"US",
    "sg:address":"3201 10th Ave",
    "sg:city":"Tuscaloosa",
    "sg:classifiers":[
        {
            "category":"Retail",
            "subcategory":"Laundry & Dry Cleaning",
            "type":"Services"
        }
    ],
    "sg:phone":"+1 205 752 0666",
    "sg:postcode":"35401",
    "sg:province":"AL",
    "sg:tags":[
        "cleaners"
    ],
    "wof:name":"Thomas Cleaners",
    "wof:placetype":"venue"
},
  "geometry": {"coordinates":[-87.551664,33.182078],"type":"Point"}
}