{
  "type": "Feature",
  "properties": {
    "iso:country":"US",
    "sg:address":"1308 Red Rock Cir",
    "sg:city":"Pleasant Grove",
    "sg:classifiers":[
        {
            "category":"Social Services",
            "type":"Services"
        }
    ],
    "sg:phone":"+1 205 253 0937",
    "sg:postcode":"35127",
    "sg:province":"AL",
    "sg:tags":[
        "p",
        "training",
        "education",
        "diversity",
        "supplemental"
    ],
    "wof:name":"S & A Recovery Consultants Inc",
    "wof:placetype":"venue"
},
  "geometry": {"coordinates":[-86.984018,33.466567],"type":"Point"}
}