{
  "type": "Feature",
  "properties": {
    "addr:full":"2505 Highland Ave Montgomery AL 36107",
    "addr:housenumber":"2505",
    "addr:postcode":"36107",
    "addr:street":"Highland Ave",
    "iso:country":"US",
    "sg:address":"2505 Highland Ave",
    "sg:city":"Montgomery",
    "sg:classifiers":[
        {
            "category":"Personal",
            "subcategory":"Beauty Salon",
            "type":"Services"
        }
    ],
    "sg:phone":"+1 334 263 1177",
    "sg:postcode":"36107",
    "sg:province":"AL",
    "sg:tags":[
        "shop"
    ],
    "wof:name":"Enchantment Beauty Salon & Btq",
    "wof:placetype":"venue"
},
  "geometry": {"coordinates":[-86.274393,32.372435],"type":"Point"}
}