{
  "type": "Feature",
  "properties": {
    "iso:country":"US",
    "sg:address":"2409 Mahaska Dr",
    "sg:city":"Birmingham",
    "sg:classifiers":[
        {
            "category":"Shopping",
            "subcategory":"Used Merchandise",
            "type":"Retail Goods"
        }
    ],
    "sg:phone":"+1 205 763 7881",
    "sg:postcode":"35244",
    "sg:province":"AL",
    "wof:name":"Curtlin Antique",
    "wof:placetype":"venue"
},
  "geometry": {"coordinates":[-86.758304,33.379358],"type":"Point"}
}