{
  "type": "Feature",
  "properties": {
    "iso:country":"US",
    "sg:address":"2601 McKenzie St",
    "sg:city":"Foley",
    "sg:classifiers":[
        {
            "category":"Shopping",
            "subcategory":"Gifts & Souvenirs",
            "type":"Retail Goods"
        }
    ],
    "sg:phone":"+1 251 971 6464",
    "sg:postcode":"36535",
    "sg:province":"AL",
    "wof:name":"AM Cafe Jewelry Company Inc",
    "wof:placetype":"venue"
},
  "geometry": {"coordinates":[-87.68305100000001,30.372063],"type":"Point"}
}