{
  "type": "Feature",
  "properties": {
    "iso:country":"US",
    "sg:address":"2604 Hough Rd",
    "sg:city":"Florence",
    "sg:classifiers":[
        {
            "category":"Health Services",
            "subcategory":"Doctor",
            "type":"Services"
        }
    ],
    "sg:phone":"+1 256 764 9955",
    "sg:postcode":"35630",
    "sg:province":"AL",
    "wof:name":"Knight Harlan R DMD",
    "wof:placetype":"venue"
},
  "geometry": {"coordinates":[-87.63373199999999,34.83493],"type":"Point"}
}