{
  "type": "Feature",
  "properties": {
    "addr:full":"3045 Eastaboga Rd Talladega AL 35160",
    "addr:housenumber":"3045",
    "addr:postcode":"35160",
    "addr:street":"Eastaboga Rd",
    "iso:country":"US",
    "sg:address":"3045 Eastaboga Rd",
    "sg:city":"Talladega",
    "sg:classifiers":[
        {
            "category":"Recreation",
            "type":"Entertainment"
        },
        {
            "category":"Farming",
            "subcategory":"Fish & Marine Products",
            "type":"Manufacturing & Wholesale Goods"
        }
    ],
    "sg:phone":"+1 256 761 1085",
    "sg:postcode":"35160",
    "sg:province":"AL",
    "sg:tags":[
        "club",
        "membership",
        "preserves",
        "hunting",
        "fishing"
    ],
    "wof:name":"M & H Sporting Clays & Quail P",
    "wof:placetype":"venue"
},
  "geometry": {"coordinates":[-86.037795,33.492481],"type":"Point"}
}