{
  "type": "Feature",
  "properties": {
    "addr:full":"155 Lagrange Rd Russellville AL 35653",
    "addr:housenumber":"155",
    "addr:postcode":"35653",
    "addr:street":"Lagrange Rd",
    "iso:country":"US",
    "sg:address":"155 Lagrange Rd",
    "sg:city":"Russellville",
    "sg:classifiers":[
        {
            "category":"Real Estate",
            "subcategory":"Real Estate Agent",
            "type":"Services"
        }
    ],
    "sg:phone":"+1 256 332 3766",
    "sg:postcode":"35653",
    "sg:province":"AL",
    "wof:name":"Rogers Realties",
    "wof:placetype":"venue"
},
  "geometry": {"coordinates":[-87.71607299999999,34.526075],"type":"Point"}
}