{
  "type": "Feature",
  "properties": {
    "iso:country":"US",
    "sg:address":"723 2nd Ave NE",
    "sg:city":"Cullman",
    "sg:classifiers":[
        {
            "category":"Restaurant",
            "type":"Food & Drink"
        }
    ],
    "sg:phone":"+1 256 734 0069",
    "sg:postcode":"35055",
    "sg:province":"AL",
    "sg:tags":[
        "eating"
    ],
    "wof:name":"Hardees",
    "wof:placetype":"venue"
},
  "geometry": {"coordinates":[-86.84578999999999,34.184188],"type":"Point"}
}