{
  "type": "Feature",
  "properties": {
    "iso:country":"US",
    "sg:address":"219 Forest Rd",
    "sg:city":"Bessemer",
    "sg:classifiers":[
        {
            "category":"Restaurant",
            "type":"Food & Drink"
        }
    ],
    "sg:menulink":"http://www.allmenus.com/al/birmingham/156334-krystal-burgers/menu/",
    "sg:phone":"+1 205 497 4079",
    "sg:postcode":"35023",
    "sg:province":"AL",
    "sg:tags":[
        "burger",
        "chicken",
        "american"
    ],
    "wof:name":"Krystal Burgers",
    "wof:placetype":"venue"
},
  "geometry": {"coordinates":[-86.985966,33.450456],"type":"Point"}
}