{
  "type": "Feature",
  "properties": {
    "iso:country":"US",
    "sg:address":"112 40th St N",
    "sg:city":"Birmingham",
    "sg:classifiers":[
        {
            "category":"Government",
            "subcategory":"Fire Station",
            "type":"Public Place"
        }
    ],
    "sg:phone":"+1 205 591 9111",
    "sg:postcode":"35222",
    "sg:province":"AL",
    "sg:tags":[
        "protection"
    ],
    "wof:name":"American Fire Protection",
    "wof:placetype":"venue"
},
  "geometry": {"coordinates":[-86.77852,33.529682],"type":"Point"}
}