{
  "type": "Feature",
  "properties": {
    "addr:full":"4325 44th Ave N Birmingham AL 35217",
    "addr:housenumber":"4325",
    "addr:postcode":"35217",
    "addr:street":"44Th Ave N",
    "iso:country":"US",
    "sg:address":"4325 44th Ave N",
    "sg:city":"Birmingham",
    "sg:classifiers":[
        {
            "category":"Building & Trades",
            "subcategory":"Landscaping Services",
            "type":"Services"
        }
    ],
    "sg:phone":"+1 205 849 5556",
    "sg:postcode":"35217",
    "sg:province":"AL",
    "wof:name":"Curb Appeal Lawn Svc",
    "wof:placetype":"venue"
},
  "geometry": {"coordinates":[-86.771709,33.565086],"type":"Point"}
}