{
  "type": "Feature",
  "properties": {
    "addr:full":"1680 Montgomery Hwy Vestavia AL 35216",
    "addr:housenumber":"1680",
    "addr:postcode":"35216",
    "addr:street":"Montgomery Hwy Vestavia",
    "iso:country":"US",
    "sg:address":"1680 Montgomery Hwy",
    "sg:city":"Vestavia",
    "sg:classifiers":[
        {
            "category":"Health Services",
            "subcategory":"Doctor",
            "type":"Services"
        },
        {
            "category":"Health Services",
            "subcategory":"Clinic",
            "type":"Services"
        }
    ],
    "sg:phone":"+1 205 979 0888",
    "sg:postcode":"35216",
    "sg:province":"AL",
    "sg:tags":[
        "physician",
        "family",
        "practice",
        "surgeons",
        "manipulative",
        "osteopathic",
        "treatment",
        "medicine",
        "surgeon",
        "internal"
    ],
    "sg:website":"http://www.americanfamilycare.com",
    "wof:name":"American Family Care Medical",
    "wof:placetype":"venue"
},
  "geometry": {"coordinates":[-86.806541,33.391369],"type":"Point"}
}