{
  "type": "Feature",
  "properties": {
    "iso:country":"US",
    "sg:address":"118 Ledyard Dr",
    "sg:city":"Montgomery",
    "sg:classifiers":[
        {
            "category":"Professional",
            "subcategory":"Management & Consulting",
            "type":"Services"
        }
    ],
    "sg:phone":"+1 334 279 8755",
    "sg:postcode":"36109",
    "sg:province":"AL",
    "sg:tags":[
        "business"
    ],
    "wof:name":"Davis Agricultural Consulting",
    "wof:placetype":"venue"
},
  "geometry": {"coordinates":[-86.229946,32.379008],"type":"Point"}
}