{
  "type": "Feature",
  "properties": {
    "addr:full":"1740 Cleburn Ave SW Birmingham AL 35211",
    "addr:housenumber":"1740",
    "addr:postcode":"35211",
    "addr:street":"Cleburn Ave Sw",
    "iso:country":"US",
    "sg:address":"1740 Cleburn Ave SW",
    "sg:city":"Birmingham",
    "sg:classifiers":[
        {
            "category":"Social Services",
            "subcategory":"Child Care",
            "type":"Services"
        }
    ],
    "sg:phone":"+1 205 925 9399",
    "sg:postcode":"35211",
    "sg:province":"AL",
    "sg:tags":[
        "organization",
        "religious",
        "day"
    ],
    "wof:name":"New Hope Christian School",
    "wof:placetype":"venue"
},
  "geometry": {"coordinates":[-86.861681,33.478362],"type":"Point"}
}