{
  "type": "Feature",
  "properties": {
    "addr:full":"4380 Co Rd 61 Houston AL 35572",
    "addr:housenumber":"4380;61",
    "addr:postcode":"35572",
    "addr:street":"Co Rd",
    "iso:country":"US",
    "sg:address":"4380 Co Rd 61",
    "sg:city":"Houston",
    "sg:classifiers":[
        {
            "category":"Recreation",
            "subcategory":"Marina",
            "type":"Entertainment"
        }
    ],
    "sg:phone":"+1 205 489 5488",
    "sg:postcode":"35572",
    "sg:province":"AL",
    "wof:name":"Yellow Creek Marina",
    "wof:placetype":"venue"
},
  "geometry": {"coordinates":[-87.27236600000001,34.093197],"type":"Point"}
}