{
  "type": "Feature",
  "properties": {
    "iso:country":"US",
    "sg:address":"2605 Banks Ave",
    "sg:city":"Mobile",
    "sg:classifiers":[
        {
            "category":"Retail",
            "subcategory":"Repair Shop",
            "type":"Services"
        }
    ],
    "sg:phone":"+1 251 452 8684",
    "sg:postcode":"36617",
    "sg:province":"AL",
    "sg:tags":[
        "welding"
    ],
    "wof:name":"Bunns Welding Shop",
    "wof:placetype":"venue"
},
  "geometry": {"coordinates":[-88.10581999999999,30.728012],"type":"Point"}
}