{
  "type": "Feature",
  "properties": {
    "iso:country":"US",
    "sg:address":"1155 Government St",
    "sg:city":"Mobile",
    "sg:classifiers":[
        {
            "category":"Professional",
            "subcategory":"Lawyer & Legal Services",
            "type":"Services"
        }
    ],
    "sg:phone":"+1 251 432 1330",
    "sg:postcode":"36604",
    "sg:province":"AL",
    "wof:name":"Whitfield J George Jr",
    "wof:placetype":"venue"
},
  "geometry": {"coordinates":[-88.062055,30.683608],"type":"Point"}
}