{
  "type": "Feature",
  "properties": {
    "iso:country":"US",
    "sg:address":"230 N Cotton St",
    "sg:city":"Andalusia",
    "sg:classifiers":[
        {
            "category":"Retail",
            "subcategory":"Funeral Services",
            "type":"Services"
        }
    ],
    "sg:phone":"+1 334 222 4093",
    "sg:postcode":"36420",
    "sg:province":"AL",
    "wof:name":"Marshall-Hammond Funeral Home",
    "wof:placetype":"venue"
},
  "geometry": {"coordinates":[-86.48202000000001,31.312022],"type":"Point"}
}