{
  "type": "Feature",
  "properties": {
    "iso:country":"US",
    "sg:address":"17892 Pennsylvania St",
    "sg:city":"Robertsdale",
    "sg:classifiers":[
        {
            "category":"Professional",
            "type":"Services"
        }
    ],
    "sg:phone":"+1 251 929 1313",
    "sg:postcode":"36567",
    "sg:province":"AL",
    "wof:name":"Minnies",
    "wof:placetype":"venue"
},
  "geometry": {"coordinates":[-87.716853,30.552919],"type":"Point"}
}