{
  "type": "Feature",
  "properties": {
    "iso:country":"US",
    "sg:address":"200 Alabama Ave",
    "sg:city":"Muscle Shoals",
    "sg:classifiers":[
        {
            "category":"Health Services",
            "subcategory":"Nursing And Care Facility",
            "type":"Services"
        }
    ],
    "sg:phone":"+1 256 381 4330",
    "sg:postcode":"35661",
    "sg:province":"AL",
    "sg:tags":[
        "skilled"
    ],
    "wof:name":"Sunbridge Care/Rehab For Muscl",
    "wof:placetype":"venue"
},
  "geometry": {"coordinates":[-87.63832,34.743829],"type":"Point"}
}