{
  "type": "Feature",
  "properties": {
    "iso:country":"US",
    "sg:address":"175 Co Rd 564",
    "sg:city":"Town Creek",
    "sg:classifiers":[
        {
            "category":"Retail",
            "subcategory":"Repair Shop",
            "type":"Services"
        }
    ],
    "sg:phone":"+1 256 476 3034",
    "sg:postcode":"35672",
    "sg:province":"AL",
    "wof:name":"J & W Home Repair",
    "wof:placetype":"venue"
},
  "geometry": {"coordinates":[-87.41412,34.49416],"type":"Point"}
}