{
  "type": "Feature",
  "properties": {
    "iso:country":"US",
    "sg:address":"6001 Old Shell Rd",
    "sg:city":"Mobile",
    "sg:classifiers":[
        {
            "category":"Real Estate",
            "subcategory":"Real Estate Operator",
            "type":"Services"
        }
    ],
    "sg:phone":"+1 251 342 3024",
    "sg:postcode":"36608",
    "sg:province":"AL",
    "sg:tags":[
        "apartment"
    ],
    "wof:name":"Robin Wood Apartments",
    "wof:placetype":"venue"
},
  "geometry": {"coordinates":[-88.181025,30.690026],"type":"Point"}
}