{
  "type": "Feature",
  "properties": {
    "iso:country":"US",
    "sg:address":"221 S Cedar Ave",
    "sg:city":"Demopolis",
    "sg:classifiers":[
        {
            "category":"Professional",
            "subcategory":"Accounting & Tax Preparation",
            "type":"Services"
        }
    ],
    "sg:phone":"+1 334 289 2290",
    "sg:postcode":"36732",
    "sg:province":"AL",
    "sg:tags":[
        "accountant"
    ],
    "wof:name":"Sue N Manning CPA",
    "wof:placetype":"venue"
},
  "geometry": {"coordinates":[-87.835123,32.515088],"type":"Point"}
}