{
  "type": "Feature",
  "properties": {
    "iso:country":"US",
    "sg:address":"10000 Memorial Pkwy SW",
    "sg:city":"Huntsville",
    "sg:classifiers":[
        {
            "category":"Banks & Credit Unions",
            "subcategory":"Bank",
            "type":"Services"
        }
    ],
    "sg:phone":"+1 256 429 1222",
    "sg:postcode":"35803",
    "sg:province":"AL",
    "sg:website":"www.southtrust.com",
    "wof:name":"South Trust Bank",
    "wof:placetype":"venue"
},
  "geometry": {"coordinates":[-86.566936,34.64314],"type":"Point"}
}