{
  "type": "Feature",
  "properties": {
    "iso:country":"US",
    "sg:address":"2816 3rd St E",
    "sg:city":"Tuscaloosa",
    "sg:classifiers":[
        {
            "category":"Building & Trades",
            "subcategory":"Construction",
            "type":"Services"
        }
    ],
    "sg:phone":"+1 205 554 0546",
    "sg:postcode":"35404",
    "sg:province":"AL",
    "sg:tags":[
        "house"
    ],
    "wof:name":"Butler Construction",
    "wof:placetype":"venue"
},
  "geometry": {"coordinates":[-87.499986,33.213214],"type":"Point"}
}