{
  "type": "Feature",
  "properties": {
    "addr:full":"9985 Holtville Rd Wetumpka AL 36092",
    "addr:housenumber":"9985",
    "addr:postcode":"36092",
    "addr:street":"Holtville Rd",
    "iso:country":"US",
    "sg:address":"9985 Holtville Rd",
    "sg:city":"Wetumpka",
    "sg:classifiers":[
        {
            "category":"Autos & Motor Vehicles",
            "subcategory":"Fuel & Gas Station",
            "type":"Retail Goods"
        }
    ],
    "sg:phone":"+1 334 569 2202",
    "sg:postcode":"36092",
    "sg:province":"AL",
    "sg:tags":[
        "station",
        "gasoline"
    ],
    "wof:name":"Slapout Petro",
    "wof:placetype":"venue"
},
  "geometry": {"coordinates":[-86.318515,32.635448],"type":"Point"}
}