{
  "type": "Feature",
  "properties": {
    "addr:full":"2204 Scott St Guntersville AL 35976",
    "addr:housenumber":"2204",
    "addr:postcode":"35976",
    "addr:street":"Scott St",
    "iso:country":"US",
    "sg:address":"2204 Scott St",
    "sg:city":"Guntersville",
    "sg:classifiers":[
        {
            "category":"Travel",
            "subcategory":"Hotels & Motels",
            "type":"Entertainment"
        }
    ],
    "sg:phone":"+1 256 505 0133",
    "sg:postcode":"35976",
    "sg:province":"AL",
    "sg:tags":[
        "operation"
    ],
    "wof:name":"Bed & Brakfast Lk Guntersville",
    "wof:placetype":"venue"
},
  "geometry": {"coordinates":[-86.293289,34.362351],"type":"Point"}
}