{
  "type": "Feature",
  "properties": {
    "addr:full":"2092 Myrtlewood Dr Montgomery AL 36111",
    "addr:housenumber":"2092",
    "addr:postcode":"36111",
    "addr:street":"Myrtlewood Dr",
    "iso:country":"US",
    "sg:address":"2092 Myrtlewood Dr",
    "sg:city":"Montgomery",
    "sg:classifiers":[
        {
            "category":"Professional",
            "subcategory":"Business Services",
            "type":"Services"
        }
    ],
    "sg:phone":"+1 334 264 7737",
    "sg:postcode":"36111",
    "sg:province":"AL",
    "wof:name":"Freestyle Inc",
    "wof:placetype":"venue"
},
  "geometry": {"coordinates":[-86.275064,32.349416],"type":"Point"}
}