{
  "type": "Feature",
  "properties": {
    "addr:full":"1852 Beltline Rd SW Decatur AL 35601",
    "addr:housenumber":"1852",
    "addr:postcode":"35601",
    "addr:street":"Beltline Rd Sw",
    "iso:country":"US",
    "sg:address":"1852 Beltline Rd SW",
    "sg:city":"Decatur",
    "sg:classifiers":[
        {
            "category":"Health Services",
            "subcategory":"Doctor",
            "type":"Services"
        }
    ],
    "sg:phone":"+1 256 353 9988",
    "sg:postcode":"35601",
    "sg:province":"AL",
    "sg:tags":[
        "physician",
        "surgeon"
    ],
    "wof:name":"Alabama Occupational Health",
    "wof:placetype":"venue"
},
  "geometry": {"coordinates":[-87.01621400000001,34.574973],"type":"Point"}
}