{
  "type": "Feature",
  "properties": {
    "iso:country":"US",
    "sg:address":"116 McKinney Rd",
    "sg:city":"Gurley",
    "sg:classifiers":[
        {
            "category":"Building & Trades",
            "subcategory":"Construction",
            "type":"Services"
        }
    ],
    "sg:phone":"+1 256 653 6726",
    "sg:postcode":"35748",
    "sg:province":"AL",
    "sg:tags":[
        "roofing",
        "contractor"
    ],
    "wof:name":"A-N-A Svc",
    "wof:placetype":"venue"
},
  "geometry": {"coordinates":[-86.360405,34.656989],"type":"Point"}
}