{
  "type": "Feature",
  "properties": {
    "iso:country":"US",
    "sg:address":"322 Todd Cir",
    "sg:city":"Albertville",
    "sg:classifiers":[
        {
            "category":"Building & Trades",
            "subcategory":"Plumbing",
            "type":"Services"
        }
    ],
    "sg:phone":"+1 256 878 8934",
    "sg:postcode":"35950",
    "sg:province":"AL",
    "sg:tags":[
        "conditioning",
        "air",
        "system",
        "contractor"
    ],
    "wof:name":"Morrow Heating & Air Cond",
    "wof:placetype":"venue"
},
  "geometry": {"coordinates":[-86.217688,34.26447],"type":"Point"}
}