{
  "type": "Feature",
  "properties": {
    "addr:full":"4017 Ave I Birmingham AL 35218",
    "addr:housenumber":"4017",
    "addr:postcode":"35218",
    "addr:street":"Ave I",
    "iso:country":"US",
    "sg:address":"4017 Ave I",
    "sg:city":"Birmingham",
    "sg:classifiers":[
        {
            "category":"Home & Garden",
            "subcategory":"Building Materials",
            "type":"Retail Goods"
        }
    ],
    "sg:phone":"+1 205 788 4500",
    "sg:postcode":"35218",
    "sg:province":"AL",
    "wof:name":"Auto Color Co Inc",
    "wof:placetype":"venue"
},
  "geometry": {"coordinates":[-86.90351,33.493435],"type":"Point"}
}