{
  "type": "Feature",
  "properties": {
    "iso:country":"US",
    "sg:address":"2117 Bessemer Rd",
    "sg:city":"Birmingham",
    "sg:classifiers":[
        {
            "category":"Autos & Motor Vehicles",
            "subcategory":"Automobile Sales",
            "type":"Retail Goods"
        }
    ],
    "sg:phone":"+1 205 781 0526",
    "sg:postcode":"35208",
    "sg:province":"AL",
    "wof:name":"Motown Auto Sales",
    "wof:placetype":"venue"
},
  "geometry": {"coordinates":[-86.88057999999999,33.493876],"type":"Point"}
}