{
  "type": "Feature",
  "properties": {
    "addr:full":"5266 Grantswood Rd Birmingham AL 35210",
    "addr:housenumber":"5266",
    "addr:postcode":"35210",
    "addr:street":"Grantswood Rd",
    "iso:country":"US",
    "sg:address":"5266 Grantswood Rd",
    "sg:city":"Birmingham",
    "sg:classifiers":[
        {
            "category":"Professional",
            "subcategory":"Management & Consulting",
            "type":"Services"
        }
    ],
    "sg:phone":"+1 205 951 3554",
    "sg:postcode":"35210",
    "sg:province":"AL",
    "sg:tags":[
        "insurance"
    ],
    "sg:website":"www.deanconsulting.com",
    "wof:name":"Dean Consulting Inc",
    "wof:placetype":"venue"
},
  "geometry": {"coordinates":[-86.65408100000001,33.531138],"type":"Point"}
}