{
  "type": "Feature",
  "properties": {
    "addr:full":"1687 Center Point Pkwy Birmingham AL 35215",
    "addr:housenumber":"1687",
    "addr:postcode":"35215",
    "addr:street":"Center Point Pkwy",
    "iso:country":"US",
    "sg:address":"1687 Center Point Pkwy",
    "sg:city":"Birmingham",
    "sg:classifiers":[
        {
            "category":"Shopping",
            "subcategory":"Discount & Variety Stores",
            "type":"Retail Goods"
        },
        {
            "category":"Shopping",
            "subcategory":"Department Store",
            "type":"Retail Goods"
        }
    ],
    "sg:phone":"+1 205 815 0132",
    "sg:postcode":"35215",
    "sg:province":"AL",
    "sg:tags":[
        "shop"
    ],
    "wof:name":"Dollar General",
    "wof:placetype":"venue"
},
  "geometry": {"coordinates":[-86.684704,33.63153],"type":"Point"}
}