{
  "type": "Feature",
  "properties": {
    "iso:country":"US",
    "sg:address":"292 Tallapoosa St",
    "sg:city":"Alexander City",
    "sg:classifiers":[
        {
            "category":"Autos & Motor Vehicles",
            "subcategory":"Auto Supplies",
            "type":"Retail Goods"
        }
    ],
    "sg:phone":"+1 256 234 6301",
    "sg:postcode":"35010",
    "sg:province":"AL",
    "sg:tags":[
        "automobile",
        "parts"
    ],
    "wof:name":"Rogers Automotive Supply",
    "wof:placetype":"venue"
},
  "geometry": {"coordinates":[-85.950382,32.943869],"type":"Point"}
}