{
  "type": "Feature",
  "properties": {
    "iso:country":"US",
    "sg:address":"17550 US Hwy 11",
    "sg:city":"Vance",
    "sg:classifiers":[
        {
            "category":"Building & Trades",
            "subcategory":"Landscaping Services",
            "type":"Services"
        }
    ],
    "sg:phone":"+1 205 507 9187",
    "sg:postcode":"35490",
    "sg:province":"AL",
    "sg:tags":[
        "landscape",
        "contractor"
    ],
    "wof:name":"Superior Maintenance Co",
    "wof:placetype":"venue"
},
  "geometry": {"coordinates":[-87.269174,33.172905],"type":"Point"}
}