{
  "type": "Feature",
  "properties": {
    "addr:full":"1001 S Franklin Dr Troy AL 36081",
    "addr:housenumber":"1001",
    "addr:postcode":"36081",
    "addr:street":"S Franklin Dr",
    "iso:country":"US",
    "sg:address":"1001 S Franklin Dr",
    "sg:city":"Troy",
    "sg:classifiers":[
        {
            "category":"Health Services",
            "subcategory":"Clinic",
            "type":"Services"
        }
    ],
    "sg:phone":"+1 334 566 7266",
    "sg:postcode":"36081",
    "sg:province":"AL",
    "sg:tags":[
        "kidney",
        "dialysis",
        "center"
    ],
    "wof:name":"Fresenius Usa Inc",
    "wof:placetype":"venue"
},
  "geometry": {"coordinates":[-85.947321,31.783012],"type":"Point"}
}