{
  "type": "Feature",
  "properties": {
    "iso:country":"US",
    "sg:address":"909 Fisher St SW",
    "sg:city":"Cullman",
    "sg:classifiers":[
        {
            "category":"Insurance",
            "subcategory":"Insurance Agent",
            "type":"Services"
        }
    ],
    "sg:phone":"+1 256 734 4640",
    "sg:postcode":"35055",
    "sg:province":"AL",
    "wof:name":"State Farm Insurance",
    "wof:placetype":"venue"
},
  "geometry": {"coordinates":[-86.844606,34.145724],"type":"Point"}
}