{
  "type": "Feature",
  "properties": {
    "iso:country":"US",
    "sg:address":"19 Anderson Rd",
    "sg:city":"Saraland",
    "sg:classifiers":[
        {
            "category":"Retail",
            "subcategory":"Repair Shop",
            "type":"Services"
        }
    ],
    "sg:phone":"+1 251 679 9993",
    "sg:postcode":"36571",
    "sg:province":"AL",
    "sg:tags":[
        "furniture"
    ],
    "wof:name":"Saraland Upholstery",
    "wof:placetype":"venue"
},
  "geometry": {"coordinates":[-88.06473200000001,30.821055],"type":"Point"}
}