{
  "type": "Feature",
  "properties": {
    "iso:country":"US",
    "sg:address":"106 S 6th St",
    "sg:city":"Gadsden",
    "sg:classifiers":[
        {
            "category":"Shopping",
            "subcategory":"Gifts & Souvenirs",
            "type":"Retail Goods"
        }
    ],
    "sg:phone":"+1 256 546 1251",
    "sg:postcode":"35901",
    "sg:province":"AL",
    "wof:name":"Pleasure Treasures",
    "wof:placetype":"venue"
},
  "geometry": {"coordinates":[-86.007892,34.011418],"type":"Point"}
}