{
  "type": "Feature",
  "properties": {
    "iso:country":"US",
    "sg:address":"6802 Old Greensboro Rd",
    "sg:city":"Tuscaloosa",
    "sg:classifiers":[
        {
            "category":"Real Estate",
            "subcategory":"Real Estate Operator",
            "type":"Services"
        }
    ],
    "sg:phone":"+1 205 366 9500",
    "sg:postcode":"35405",
    "sg:province":"AL",
    "sg:tags":[
        "apartment"
    ],
    "wof:name":"Winding Creek Apartments",
    "wof:placetype":"venue"
},
  "geometry": {"coordinates":[-87.547385,33.145815],"type":"Point"}
}