{
  "type": "Feature",
  "properties": {
    "iso:country":"US",
    "sg:address":"108 Kay Ave",
    "sg:city":"Trussville",
    "sg:classifiers":[
        {
            "category":"Autos & Motor Vehicles",
            "subcategory":"Automobile Sales",
            "type":"Retail Goods"
        }
    ],
    "sg:phone":"+1 205 655 8812",
    "sg:postcode":"35173",
    "sg:province":"AL",
    "wof:name":"K Auto Sales",
    "wof:placetype":"venue"
},
  "geometry": {"coordinates":[-86.614998,33.618007],"type":"Point"}
}