{
  "type": "Feature",
  "properties": {
    "iso:country":"US",
    "sg:address":"110 Sherman Brunson Rd",
    "sg:city":"Pansey",
    "sg:classifiers":[
        {
            "category":"Organizations",
            "subcategory":"Religious Organization",
            "type":"Services"
        }
    ],
    "sg:phone":"+1 334 522 3404",
    "sg:postcode":"36370",
    "sg:province":"AL",
    "sg:tags":[
        "church"
    ],
    "wof:name":"Pleasant Hill Baptist Past",
    "wof:placetype":"venue"
},
  "geometry": {"coordinates":[-85.172834,31.089436],"type":"Point"}
}