{
  "type": "Feature",
  "properties": {
    "iso:country":"US",
    "sg:address":"1537 Jean St",
    "sg:city":"Montgomery",
    "sg:classifiers":[
        {
            "category":"Building & Trades",
            "subcategory":"Construction",
            "type":"Services"
        }
    ],
    "sg:phone":"+1 334 262 8859",
    "sg:postcode":"36107",
    "sg:province":"AL",
    "sg:tags":[
        "new",
        "dwelling",
        "renovation"
    ],
    "wof:name":"Jerry Kyser Builder Inc",
    "wof:placetype":"venue"
},
  "geometry": {"coordinates":[-86.273174,32.361915],"type":"Point"}
}