{
  "type": "Feature",
  "properties": {
    "iso:country":"US",
    "sg:address":"20988 State Rte 59",
    "sg:city":"Robertsdale",
    "sg:classifiers":[
        {
            "category":"Autos & Motor Vehicles",
            "subcategory":"Automobile Sales",
            "type":"Retail Goods"
        },
        {
            "category":"Autos & Motor Vehicles",
            "subcategory":"Motorcycle Sales",
            "type":"Retail Goods"
        }
    ],
    "sg:phone":"+1 251 947 4735",
    "sg:postcode":"36567",
    "sg:province":"AL",
    "sg:tags":[
        "car",
        "golf",
        "cart"
    ],
    "wof:name":"Taylor's Golf Cart Sales & Svc",
    "wof:placetype":"venue"
},
  "geometry": {"coordinates":[-87.708303,30.527909],"type":"Point"}
}