{
  "type": "Feature",
  "properties": {
    "iso:country":"US",
    "sg:address":"1529 Carraway Blvd",
    "sg:city":"Birmingham",
    "sg:classifiers":[
        {
            "category":"Health Services",
            "subcategory":"Doctor",
            "type":"Services"
        }
    ],
    "sg:phone":"+1 205 323 8588",
    "sg:postcode":"35234",
    "sg:province":"AL",
    "sg:tags":[
        "physician",
        "surgeon"
    ],
    "wof:name":"Alabama Cardiovascular Group",
    "wof:placetype":"venue"
},
  "geometry": {"coordinates":[-86.808921,33.535417],"type":"Point"}
}