{
  "type": "Feature",
  "properties": {
    "iso:country":"US",
    "sg:address":"2214 Ross Clark Cir",
    "sg:city":"Dothan",
    "sg:classifiers":[
        {
            "category":"Retail",
            "subcategory":"Portrait Studio",
            "type":"Services"
        }
    ],
    "sg:phone":"+1 334 673 2373",
    "sg:postcode":"36301",
    "sg:province":"AL",
    "wof:name":"Olan Mills Studios",
    "wof:placetype":"venue"
},
  "geometry": {"coordinates":[-85.401617,31.19075],"type":"Point"}
}