{
  "type": "Feature",
  "properties": {
    "addr:full":"321 Park St Demopolis AL 36732",
    "addr:housenumber":"321",
    "addr:postcode":"36732",
    "addr:street":"Park St",
    "iso:country":"US",
    "sg:address":"321 Park St",
    "sg:city":"Demopolis",
    "sg:classifiers":[
        {
            "category":"Professional",
            "subcategory":"Accounting & Tax Preparation",
            "type":"Services"
        }
    ],
    "sg:phone":"+1 334 289 2583",
    "sg:postcode":"36732",
    "sg:province":"AL",
    "wof:name":"Watson McCory & Associates",
    "wof:placetype":"venue"
},
  "geometry": {"coordinates":[-87.834017,32.510262],"type":"Point"}
}