{
  "type": "Feature",
  "properties": {
    "addr:full":"204 E Main St Mobile AL 36610",
    "addr:housenumber":"204",
    "addr:postcode":"36610",
    "addr:street":"E Main St",
    "iso:country":"US",
    "sg:address":"204 E Main St",
    "sg:city":"Mobile",
    "sg:classifiers":[
        {
            "category":"Social Services",
            "type":"Services"
        }
    ],
    "sg:phone":"+1 251 456 2251",
    "sg:postcode":"36610",
    "sg:province":"AL",
    "wof:name":"Prichard Plateau Community Svc",
    "wof:placetype":"venue"
},
  "geometry": {"coordinates":[-88.07962999999999,30.731046],"type":"Point"}
}