{
  "type": "Feature",
  "properties": {
    "addr:full":"529 Boll Weevil Cir Enterprise AL 36330",
    "addr:housenumber":"529",
    "addr:postcode":"36330",
    "addr:street":"Boll Weevil Cir Enterprise",
    "iso:country":"US",
    "sg:address":"529 Boll Weevil Cir",
    "sg:city":"Enterprise",
    "sg:classifiers":[
        {
            "category":"Arts & Performance",
            "subcategory":"Theater",
            "type":"Entertainment"
        }
    ],
    "sg:phone":"+1 334 393 7922",
    "sg:postcode":"36330",
    "sg:province":"AL",
    "sg:tags":[
        "bureau"
    ],
    "wof:name":"Superkala Records",
    "wof:placetype":"venue"
},
  "geometry": {"coordinates":[-85.86922,31.332436],"type":"Point"}
}