{
  "type": "Feature",
  "properties": {
    "iso:country":"US",
    "sg:address":"628 Main St",
    "sg:city":"Montevallo",
    "sg:classifiers":[
        {
            "category":"Restaurant",
            "type":"Food & Drink"
        }
    ],
    "sg:phone":"+1 205 665 4331",
    "sg:postcode":"35115",
    "sg:province":"AL",
    "wof:name":"Greg Winslett Restaurant",
    "wof:placetype":"venue"
},
  "geometry": {"coordinates":[-86.863223,33.100085],"type":"Point"}
}