{
  "type": "Feature",
  "properties": {
    "addr:full":"104 Bessemer Super Hwy Birmingham AL 35228",
    "addr:housenumber":"104",
    "addr:postcode":"35228",
    "addr:street":"Super Hwy",
    "iso:country":"US",
    "sg:address":"104 Bessemer Super Hwy",
    "sg:city":"Birmingham",
    "sg:classifiers":[
        {
            "category":"Restaurant",
            "type":"Food & Drink"
        }
    ],
    "sg:menulink":"http://www.allmenus.com/al/birmingham/173897-wendys/menu/",
    "sg:phone":"+1 205 923 4327",
    "sg:postcode":"35228",
    "sg:province":"AL",
    "sg:tags":[
        "burger",
        "american",
        "soup"
    ],
    "wof:name":"Wendy's",
    "wof:placetype":"venue"
},
  "geometry": {"coordinates":[-86.91213399999999,33.462786],"type":"Point"}
}