{
  "type": "Feature",
  "properties": {
    "addr:full":"1604 Co Rd 130 Berry AL 35546",
    "addr:housenumber":"1604;130",
    "addr:postcode":"35546",
    "addr:street":"Co Rd;Berry",
    "iso:country":"US",
    "sg:address":"1604 Co Rd 130",
    "sg:city":"Berry",
    "sg:classifiers":[
        {
            "category":"Manufacturing",
            "subcategory":"Lumber",
            "type":"Manufacturing & Wholesale Goods"
        }
    ],
    "sg:phone":"+1 205 689 4388",
    "sg:postcode":"35546",
    "sg:province":"AL",
    "sg:tags":[
        "logging"
    ],
    "wof:name":"Ray L Clark Log Contractor",
    "wof:placetype":"venue"
},
  "geometry": {"coordinates":[-87.605971,33.685135],"type":"Point"}
}