{
  "type": "Feature",
  "properties": {
    "iso:country":"US",
    "sg:address":"4319 Maplewood Dr",
    "sg:city":"Trussville",
    "sg:classifiers":[
        {
            "category":"Wholesale",
            "subcategory":"Construction Materials",
            "type":"Manufacturing & Wholesale Goods"
        }
    ],
    "sg:phone":"+1 205 655 8057",
    "sg:postcode":"35173",
    "sg:province":"AL",
    "wof:name":"Unimin Corporation",
    "wof:placetype":"venue"
},
  "geometry": {"coordinates":[-86.591774,33.630598],"type":"Point"}
}