{
  "type": "Feature",
  "properties": {
    "iso:country":"US",
    "sg:address":"647 Brothers Ave",
    "sg:city":"Wilsonville",
    "sg:classifiers":[
        {
            "category":"Building & Trades",
            "subcategory":"Construction",
            "type":"Services"
        }
    ],
    "sg:phone":"+1 205 670 0446",
    "sg:postcode":"35186",
    "sg:province":"AL",
    "sg:tags":[
        "general",
        "contractor"
    ],
    "wof:name":"Flanagan Construction Co",
    "wof:placetype":"venue"
},
  "geometry": {"coordinates":[-86.473957,33.22419],"type":"Point"}
}