{
  "type": "Feature",
  "properties": {
    "addr:full":"1309 7th Ave Phenix City AL 36867",
    "addr:housenumber":"1309",
    "addr:postcode":"36867",
    "addr:street":"7Th Ave Phenix City Al",
    "iso:country":"US",
    "sg:address":"1309 7th Ave",
    "sg:city":"Phenix City",
    "sg:classifiers":[
        {
            "category":"Health Services",
            "subcategory":"Chiropractor",
            "type":"Services"
        }
    ],
    "sg:phone":"+1 334 298 0029",
    "sg:postcode":"36867",
    "sg:province":"AL",
    "wof:name":"Rud Chiropractic",
    "wof:placetype":"venue"
},
  "geometry": {"coordinates":[-85.002302,32.471058],"type":"Point"}
}