{
  "type": "Feature",
  "properties": {
    "iso:country":"US",
    "sg:address":"520 Lasalle St",
    "sg:city":"Rainbow City",
    "sg:classifiers":[
        {
            "category":"Health Services",
            "subcategory":"Nursing And Care Facility",
            "type":"Services"
        }
    ],
    "sg:phone":"+1 256 442 0102",
    "sg:postcode":"35906",
    "sg:province":"AL",
    "sg:tags":[
        "intermediate"
    ],
    "wof:name":"The Meadows of Rainbow City",
    "wof:placetype":"venue"
},
  "geometry": {"coordinates":[-86.048084,33.97071],"type":"Point"}
}