{
  "type": "Feature",
  "properties": {
    "iso:country":"US",
    "sg:address":"322 N Main St",
    "sg:city":"Hackleburg",
    "sg:classifiers":[
        {
            "category":"Autos & Motor Vehicles",
            "subcategory":"Auto Supplies",
            "type":"Retail Goods"
        }
    ],
    "sg:phone":"+1 205 935 2381",
    "sg:postcode":"35564",
    "sg:province":"AL",
    "sg:tags":[
        "tire"
    ],
    "wof:name":"Yielding and Supply",
    "wof:placetype":"venue"
},
  "geometry": {"coordinates":[-87.82879699999999,34.279709],"type":"Point"}
}