{
  "type": "Feature",
  "properties": {
    "iso:country":"US",
    "sg:address":"955 Downtowner Blvd",
    "sg:city":"Mobile",
    "sg:classifiers":[
        {
            "category":"Wholesale",
            "subcategory":"Durable Goods & Equipment",
            "type":"Manufacturing & Wholesale Goods"
        }
    ],
    "sg:phone":"+1 251 343 0065",
    "sg:postcode":"36609",
    "sg:province":"AL",
    "sg:tags":[
        "representative",
        "manufacturer"
    ],
    "sg:website":"www.surline.com",
    "wof:name":"Surline & Assoc",
    "wof:placetype":"venue"
},
  "geometry": {"coordinates":[-88.140281,30.669759],"type":"Point"}
}