{
  "type": "Feature",
  "properties": {
    "addr:full":"2224 1st Ave N Birmingham AL 35203",
    "addr:housenumber":"2224",
    "addr:postcode":"35203",
    "addr:street":"1St Ave N",
    "iso:country":"US",
    "sg:address":"2224 1st Ave N",
    "sg:city":"Birmingham",
    "sg:classifiers":[
        {
            "category":"Building & Trades",
            "subcategory":"Electrical",
            "type":"Services"
        }
    ],
    "sg:phone":"+1 205 856 1054",
    "sg:postcode":"35203",
    "sg:province":"AL",
    "sg:tags":[
        "electrician"
    ],
    "wof:name":"Stephens Electric",
    "wof:placetype":"venue"
},
  "geometry": {"coordinates":[-86.80256799999999,33.51594],"type":"Point"}
}