{
  "type": "Feature",
  "properties": {
    "iso:country":"US",
    "sg:address":"158 Co Rd 414",
    "sg:city":"Opelika",
    "sg:classifiers":[
        {
            "category":"Building & Trades",
            "subcategory":"Construction",
            "type":"Services"
        }
    ],
    "sg:phone":"+1 334 749 9365",
    "sg:postcode":"36804",
    "sg:province":"AL",
    "sg:tags":[
        "coping",
        "plastering",
        "tiling",
        "pool",
        "swimming"
    ],
    "wof:name":"Murphy's Pool & Spas",
    "wof:placetype":"venue"
},
  "geometry": {"coordinates":[-85.386658,32.543156],"type":"Point"}
}