{
  "type": "Feature",
  "properties": {
    "iso:country":"US",
    "sg:address":"140 Co Rd 1749",
    "sg:city":"Holly Pond",
    "sg:classifiers":[
        {
            "category":"Shopping",
            "subcategory":"Bicycles & Sporting Goods",
            "type":"Retail Goods"
        }
    ],
    "sg:phone":"+1 256 796 2699",
    "sg:postcode":"35083",
    "sg:province":"AL",
    "wof:name":"Cox Golf",
    "wof:placetype":"venue"
},
  "geometry": {"coordinates":[-86.550403,34.224592],"type":"Point"}
}