{
  "type": "Feature",
  "properties": {
    "addr:full":"251 Ingate St Mobile AL 36607",
    "addr:housenumber":"251",
    "addr:postcode":"36607",
    "addr:street":"Ingate St",
    "iso:country":"US",
    "sg:address":"251 Ingate St",
    "sg:city":"Mobile",
    "sg:classifiers":[
        {
            "category":"Shopping",
            "subcategory":"Discount & Variety Stores",
            "type":"Retail Goods"
        }
    ],
    "sg:phone":"+1 251 472 2009",
    "sg:postcode":"36607",
    "sg:province":"AL",
    "sg:tags":[
        "merchandise",
        "general"
    ],
    "wof:name":"Reid Business Supply Inc",
    "wof:placetype":"venue"
},
  "geometry": {"coordinates":[-88.120949,30.702175],"type":"Point"}
}