{
  "type": "Feature",
  "properties": {
    "addr:full":"3758 Government Blvd Mobile AL 36693",
    "addr:housenumber":"3758",
    "addr:postcode":"36693",
    "addr:street":"Government Blvd",
    "iso:country":"US",
    "sg:address":"3758 Government Blvd",
    "sg:city":"Mobile",
    "sg:classifiers":[
        {
            "category":"Bars & Pubs",
            "type":"Food & Drink"
        }
    ],
    "sg:phone":"+1 251 666 9922",
    "sg:postcode":"36693",
    "sg:province":"AL",
    "sg:tags":[
        "lounge",
        "cocktail"
    ],
    "wof:name":"Jack O'Diamonds",
    "wof:placetype":"venue"
},
  "geometry": {"coordinates":[-88.12932000000001,30.647699],"type":"Point"}
}