{
  "type": "Feature",
  "properties": {
    "addr:full":"2409 Acton Rd Birmingham AL 35243",
    "addr:housenumber":"2409",
    "addr:postcode":"35243",
    "addr:street":"Acton Rd",
    "iso:country":"US",
    "sg:address":"2409 Acton Rd",
    "sg:city":"Birmingham",
    "sg:classifiers":[
        {
            "category":"Cafe",
            "type":"Food & Drink"
        }
    ],
    "sg:menulink":"http://www.allmenus.com/al/birmingham/255329-mandarin-cafe/menu/",
    "sg:phone":"+1 205 823 2365",
    "sg:postcode":"35243",
    "sg:province":"AL",
    "sg:tags":[
        "asian",
        "chinese"
    ],
    "wof:name":"Mandarin Cafe",
    "wof:placetype":"venue"
},
  "geometry": {"coordinates":[-86.764509,33.410165],"type":"Point"}
}