{
  "type": "Feature",
  "properties": {
    "addr:full":"145 S Court St Prattville AL 36067",
    "addr:housenumber":"145",
    "addr:postcode":"36067",
    "addr:street":"S Court St",
    "iso:country":"US",
    "sg:address":"145 S Court St",
    "sg:city":"Prattville",
    "sg:classifiers":[
        {
            "category":"Shopping",
            "subcategory":"Used Merchandise",
            "type":"Retail Goods"
        }
    ],
    "sg:phone":"+1 334 358 0058",
    "sg:postcode":"36067",
    "sg:province":"AL",
    "sg:tags":[
        "flea",
        "market"
    ],
    "wof:name":"Antique & Flea Market",
    "wof:placetype":"venue"
},
  "geometry": {"coordinates":[-86.47537199999999,32.461878],"type":"Point"}
}