{
  "type": "Feature",
  "properties": {
    "iso:country":"US",
    "sg:address":"4755 Quarterstaff Rd",
    "sg:city":"Birmingham",
    "sg:classifiers":[
        {
            "category":"Professional",
            "subcategory":"Business Services",
            "type":"Services"
        }
    ],
    "sg:phone":"+1 205 967 1308",
    "sg:postcode":"35223",
    "sg:province":"AL",
    "wof:name":"Underhill Enterprises Inc",
    "wof:placetype":"venue"
},
  "geometry": {"coordinates":[-86.702427,33.504953],"type":"Point"}
}