{
  "type": "Feature",
  "properties": {
    "addr:full":"6630 Moffett Rd Mobile AL 36618",
    "addr:housenumber":"6630",
    "addr:postcode":"36618",
    "addr:street":"Moffett Rd",
    "iso:country":"US",
    "sg:address":"6630 Moffett Rd",
    "sg:city":"Mobile",
    "sg:classifiers":[
        {
            "category":"Autos & Motor Vehicles",
            "subcategory":"Automobile Sales",
            "type":"Retail Goods"
        }
    ],
    "sg:phone":"+1 251 645 8403",
    "sg:postcode":"36618",
    "sg:province":"AL",
    "sg:tags":[
        "car",
        "dealer"
    ],
    "wof:name":"Moffet Road Auto Sales",
    "wof:placetype":"venue"
},
  "geometry": {"coordinates":[-88.19514599999999,30.751586],"type":"Point"}
}