{
  "type": "Feature",
  "properties": {
    "addr:full":"6700 Martin Luther King Jr Blvd Tuscaloosa AL 35401",
    "addr:housenumber":"6700",
    "addr:postcode":"35401",
    "addr:street":"Martin Luther King Jr Blvd",
    "iso:country":"US",
    "sg:address":"6700 Martin Luther King Jr Blvd",
    "sg:city":"Tuscaloosa",
    "sg:phone":"+1 205 758 7990",
    "sg:postcode":"35401",
    "sg:province":"AL",
    "sg:tags":[
        "petroleum"
    ],
    "wof:name":"Hicks Petroleum Distributors",
    "wof:placetype":"venue"
},
  "geometry": {"coordinates":[-87.62178900000001,33.148091],"type":"Point"}
}