{
  "type": "Feature",
  "properties": {
    "iso:country":"US",
    "sg:address":"204 Starmont Ln",
    "sg:city":"Gallion",
    "sg:classifiers":[
        {
            "category":"Shopping",
            "subcategory":"Bicycles & Sporting Goods",
            "type":"Retail Goods"
        }
    ],
    "sg:phone":"+1 334 289 9179",
    "sg:postcode":"36732",
    "sg:province":"AL",
    "wof:name":"Bow Up Bait Shop",
    "wof:placetype":"venue"
},
  "geometry": {"coordinates":[-87.79548699999999,32.459887],"type":"Point"}
}