{
  "type": "Feature",
  "properties": {
    "iso:country":"US",
    "sg:address":"107 Walter Davis Dr",
    "sg:city":"Birmingham",
    "sg:classifiers":[
        {
            "category":"Food & Beverages",
            "subcategory":"Groceries & Convenience Stores",
            "type":"Retail Goods"
        }
    ],
    "sg:phone":"+1 205 942 8911",
    "sg:postcode":"35209",
    "sg:province":"AL",
    "wof:name":"United Way Community Food Bank",
    "wof:placetype":"venue"
},
  "geometry": {"coordinates":[-86.837401,33.475994],"type":"Point"}
}