{
  "type": "Feature",
  "properties": {
    "iso:country":"US",
    "sg:address":"503 W College St",
    "sg:city":"Florence",
    "sg:classifiers":[
        {
            "category":"Health Services",
            "subcategory":"Doctor",
            "type":"Services"
        }
    ],
    "sg:phone":"+1 256 718 0388",
    "sg:postcode":"35630",
    "sg:province":"AL",
    "sg:tags":[
        "physician",
        "surgeon"
    ],
    "wof:name":"Sockwell Clinic",
    "wof:placetype":"venue"
},
  "geometry": {"coordinates":[-87.68084399999999,34.796819],"type":"Point"}
}