{
  "type": "Feature",
  "properties": {
    "iso:country":"US",
    "sg:address":"618 Walnut Cir",
    "sg:city":"Jasper",
    "sg:classifiers":[
        {
            "category":"Home & Garden",
            "subcategory":"Garden Supply",
            "type":"Retail Goods"
        }
    ],
    "sg:phone":"+1 205 384 9742",
    "sg:postcode":"35501",
    "sg:province":"AL",
    "wof:name":"Alabama Tree Surgery",
    "wof:placetype":"venue"
},
  "geometry": {"coordinates":[-87.320352,33.791214],"type":"Point"}
}