{
  "type": "Feature",
  "properties": {
    "iso:country":"US",
    "sg:address":"1000 22nd St SW",
    "sg:city":"Birmingham",
    "sg:classifiers":[
        {
            "category":"Building & Trades",
            "subcategory":"Landscaping Services",
            "type":"Services"
        }
    ],
    "sg:phone":"+1 205 923 3350",
    "sg:postcode":"35211",
    "sg:province":"AL",
    "sg:tags":[
        "landscape"
    ],
    "wof:name":"Wilson Landscape",
    "wof:placetype":"venue"
},
  "geometry": {"coordinates":[-86.871609,33.47813],"type":"Point"}
}