{
  "type": "Feature",
  "properties": {
    "iso:country":"US",
    "sg:address":"728 27th St SW",
    "sg:city":"Birmingham",
    "sg:classifiers":[
        {
            "category":"Building & Trades",
            "subcategory":"Plumbing",
            "type":"Services"
        }
    ],
    "sg:phone":"+1 205 923 9886",
    "sg:postcode":"35211",
    "sg:province":"AL",
    "sg:tags":[
        "contractor"
    ],
    "wof:name":"Ervin Plumbing",
    "wof:placetype":"venue"
},
  "geometry": {"coordinates":[-86.877788,33.477172],"type":"Point"}
}