{
  "type": "Feature",
  "properties": {
    "iso:country":"US",
    "sg:address":"58 1st Ave SW",
    "sg:city":"Lafayette",
    "sg:classifiers":[
        {
            "category":"Social Services",
            "type":"Services"
        }
    ],
    "sg:phone":"+1 334 864 4372",
    "sg:postcode":"36862",
    "sg:province":"AL",
    "sg:tags":[
        "probation"
    ],
    "wof:name":"Chambers Probation & Parole",
    "wof:placetype":"venue"
},
  "geometry": {"coordinates":[-85.402102,32.899118],"type":"Point"}
}