{
  "type": "Feature",
  "properties": {
    "iso:country":"US",
    "sg:address":"310 Co Rd 71",
    "sg:city":"Thorsby",
    "sg:classifiers":[
        {
            "category":"Insurance",
            "subcategory":"Insurance Agent",
            "type":"Services"
        }
    ],
    "sg:phone":"+1 205 646 1141",
    "sg:postcode":"35171",
    "sg:province":"AL",
    "wof:name":"Cotton States Inc",
    "wof:placetype":"venue"
},
  "geometry": {"coordinates":[-86.727889,32.93382],"type":"Point"}
}