{
  "type": "Feature",
  "properties": {
    "iso:country":"US",
    "sg:address":"401 Adams Ave",
    "sg:city":"Montgomery",
    "sg:classifiers":[
        {
            "category":"Professional",
            "subcategory":"Lawyer & Legal Services",
            "type":"Services"
        }
    ],
    "sg:phone":"+1 334 956 7607",
    "sg:postcode":"36104",
    "sg:province":"AL",
    "sg:tags":[
        "attorney"
    ],
    "wof:name":"George R Parker",
    "wof:placetype":"venue"
},
  "geometry": {"coordinates":[-86.302381,32.375298],"type":"Point"}
}