{
  "type": "Feature",
  "properties": {
    "addr:full":"314 N 11th St Opelika AL 36801",
    "addr:housenumber":"314",
    "addr:postcode":"36801",
    "addr:street":"N 11Th St",
    "iso:country":"US",
    "sg:address":"314 N 11th St",
    "sg:city":"Opelika",
    "sg:classifiers":[
        {
            "category":"Building & Trades",
            "subcategory":"Construction",
            "type":"Services"
        }
    ],
    "sg:phone":"+1 334 737 3939",
    "sg:postcode":"36801",
    "sg:province":"AL",
    "sg:tags":[
        "house"
    ],
    "wof:name":"Quality Construction",
    "wof:placetype":"venue"
},
  "geometry": {"coordinates":[-85.38649700000001,32.649194],"type":"Point"}
}