{
  "type": "Feature",
  "properties": {
    "addr:full":"361 Lakeview Dr Sterrett AL 35147",
    "addr:housenumber":"361",
    "addr:postcode":"35147",
    "addr:street":"Lakeview Dr Sterrett",
    "iso:country":"US",
    "sg:address":"361 Lakeview Dr",
    "sg:city":"Sterrett",
    "sg:classifiers":[
        {
            "category":"Farming",
            "subcategory":"Berry Farm",
            "type":"Manufacturing & Wholesale Goods"
        }
    ],
    "sg:phone":"+1 205 672 2526",
    "sg:postcode":"35147",
    "sg:province":"AL",
    "sg:tags":[
        "crop"
    ],
    "wof:name":"Irvin R Balch",
    "wof:placetype":"venue"
},
  "geometry": {"coordinates":[-86.45887,33.492116],"type":"Point"}
}