{
  "type": "Feature",
  "properties": {
    "iso:country":"US",
    "sg:address":"169 Hunter Ridge Rd",
    "sg:city":"Scottsboro",
    "sg:classifiers":[
        {
            "category":"Professional",
            "type":"Services"
        }
    ],
    "sg:phone":"+1 256 575 2588",
    "sg:postcode":"35768",
    "sg:province":"AL",
    "wof:name":"Billy Eakin",
    "wof:placetype":"venue"
},
  "geometry": {"coordinates":[-86.11908200000001,34.686247],"type":"Point"}
}