{
  "type": "Feature",
  "properties": {
    "iso:country":"US",
    "sg:address":"4819 Main St",
    "sg:city":"Brighton",
    "sg:classifiers":[
        {
            "category":"Organizations",
            "subcategory":"Religious Organization",
            "type":"Services"
        }
    ],
    "sg:phone":"+1 205 426 2547",
    "sg:postcode":"35020",
    "sg:province":"AL",
    "sg:tags":[
        "church"
    ],
    "wof:name":"Friendship Baptist Church",
    "wof:placetype":"venue"
},
  "geometry": {"coordinates":[-86.94810099999999,33.431681],"type":"Point"}
}