{
  "type": "Feature",
  "properties": {
    "iso:country":"US",
    "sg:address":"2367 Jordan Rd",
    "sg:city":"Huntsville",
    "sg:classifiers":[
        {
            "category":"Organizations",
            "subcategory":"Religious Organization",
            "type":"Services"
        }
    ],
    "sg:phone":"+1 256 852 5817",
    "sg:postcode":"35811",
    "sg:province":"AL",
    "wof:name":"Sam Gulley Rev",
    "wof:placetype":"venue"
},
  "geometry": {"coordinates":[-86.486605,34.772442],"type":"Point"}
}