{
  "type": "Feature",
  "properties": {
    "addr:full":"931 7th Ave N Birmingham AL 35203",
    "addr:housenumber":"931",
    "addr:postcode":"35203",
    "addr:street":"7Th Ave N",
    "iso:country":"US",
    "sg:address":"931 7th Ave N",
    "sg:city":"Birmingham",
    "sg:classifiers":[
        {
            "category":"Retail",
            "subcategory":"Car Wash",
            "type":"Services"
        }
    ],
    "sg:phone":"+1 205 323 4358",
    "sg:postcode":"35203",
    "sg:province":"AL",
    "sg:tags":[
        "repair",
        "truck",
        "detail",
        "clean",
        "automobile"
    ],
    "sg:website":"http://clickserve.dartsearch.net/link/click?lid=43000000313869077&ds_s_kwgid=58000000006820725&ds_e_matchtype={MatchType}&ds_e_kwdid={OrderItemId}&ds_e_adid={AdId}&ds_url_v=2",
    "wof:name":"Birmingham Auto Clean",
    "wof:placetype":"venue"
},
  "geometry": {"coordinates":[-86.82447999999999,33.513359],"type":"Point"}
}