{
  "type": "Feature",
  "properties": {
    "addr:full":"1739 Abel Rd Delta AL 36258",
    "addr:housenumber":"1739",
    "addr:postcode":"36258",
    "addr:street":"Abel Rd",
    "iso:country":"US",
    "sg:address":"1739 Abel Rd",
    "sg:city":"Delta",
    "sg:classifiers":[
        {
            "category":"Farming",
            "subcategory":"Livestock Farm",
            "type":"Manufacturing & Wholesale Goods"
        }
    ],
    "sg:phone":"+1 256 488 5313",
    "sg:postcode":"36258",
    "sg:province":"AL",
    "sg:tags":[
        "beef",
        "feedlot",
        "cattle"
    ],
    "wof:name":"Herbert Buttram",
    "wof:placetype":"venue"
},
  "geometry": {"coordinates":[-85.757733,33.488802],"type":"Point"}
}