{
  "type": "Feature",
  "properties": {
    "addr:full":"2113 Allendale Rd Montgomery AL 36111",
    "addr:housenumber":"2113",
    "addr:postcode":"36111",
    "addr:street":"Allendale Rd",
    "iso:country":"US",
    "sg:address":"2113 Allendale Rd",
    "sg:city":"Montgomery",
    "sg:classifiers":[
        {
            "category":"Wholesale",
            "subcategory":"Scrap",
            "type":"Manufacturing & Wholesale Goods"
        }
    ],
    "sg:phone":"+1 334 395 9906",
    "sg:postcode":"36111",
    "sg:province":"AL",
    "sg:tags":[
        "metal",
        "iron"
    ],
    "wof:name":"Sunbelt International Trading",
    "wof:placetype":"venue"
},
  "geometry": {"coordinates":[-86.275462,32.345989],"type":"Point"}
}