{
  "type": "Feature",
  "properties": {
    "iso:country":"US",
    "sg:address":"106 5th St SE",
    "sg:city":"Aliceville",
    "sg:classifiers":[
        {
            "category":"Health Services",
            "subcategory":"Doctor",
            "type":"Services"
        }
    ],
    "sg:phone":"+1 205 373 8726",
    "sg:postcode":"35442",
    "sg:province":"AL",
    "sg:tags":[
        "dentist"
    ],
    "wof:name":"James E Gunnells DDS",
    "wof:placetype":"venue"
},
  "geometry": {"coordinates":[-88.14661700000001,33.124938],"type":"Point"}
}