{
  "type": "Feature",
  "properties": {
    "iso:country":"US",
    "sg:address":"920 Meridian St N",
    "sg:city":"Huntsville",
    "sg:classifiers":[
        {
            "category":"Personal",
            "subcategory":"Barber",
            "type":"Services"
        }
    ],
    "sg:phone":"+1 256 534 9208",
    "sg:postcode":"35801",
    "sg:province":"AL",
    "sg:tags":[
        "shop"
    ],
    "wof:name":"Freeman & Battle Barber Shop",
    "wof:placetype":"venue"
},
  "geometry": {"coordinates":[-86.585215,34.741982],"type":"Point"}
}