{
  "type": "Feature",
  "properties": {
    "addr:full":"17950 Co Rd 68 Loxley AL 36551",
    "addr:housenumber":"17950;68",
    "addr:postcode":"36551",
    "addr:street":"Co Rd",
    "iso:country":"US",
    "sg:address":"17950 Co Rd 68",
    "sg:city":"Loxley",
    "sg:classifiers":[
        {
            "category":"Retail",
            "subcategory":"Repair Shop",
            "type":"Services"
        }
    ],
    "sg:phone":"+1 251 964 5957",
    "sg:postcode":"36551",
    "sg:province":"AL",
    "sg:tags":[
        "upholsterer"
    ],
    "wof:name":"Loxley Upholstery Shop",
    "wof:placetype":"venue"
},
  "geometry": {"coordinates":[-87.71766100000001,30.633012],"type":"Point"}
}