{
  "type": "Feature",
  "properties": {
    "iso:country":"US",
    "sg:address":"3702 Greensboro Ave",
    "sg:city":"Tuscaloosa",
    "sg:classifiers":[
        {
            "category":"Retail",
            "subcategory":"Auto Repair",
            "type":"Services"
        }
    ],
    "sg:phone":"+1 205 758 4761",
    "sg:postcode":"35405",
    "sg:province":"AL",
    "sg:tags":[
        "wrecker"
    ],
    "wof:name":"Fred Robertson Wrecker Service",
    "wof:placetype":"venue"
},
  "geometry": {"coordinates":[-87.547716,33.175405],"type":"Point"}
}