{
  "type": "Feature",
  "properties": {
    "iso:country":"US",
    "sg:address":"790 Montgomery Hwy",
    "sg:city":"Birmingham",
    "sg:classifiers":[
        {
            "category":"Restaurant",
            "type":"Food & Drink"
        }
    ],
    "sg:menulink":"http://www.allmenus.com/al/birmingham/92014-firehouse-subs/menu/",
    "sg:phone":"+1 205 979 5753",
    "sg:postcode":"35216",
    "sg:province":"AL",
    "sg:tags":[
        "wrap",
        "american",
        "sandwich"
    ],
    "wof:name":"Firehouse Subs",
    "wof:placetype":"venue"
},
  "geometry": {"coordinates":[-86.79119,33.444573],"type":"Point"}
}