{
  "type": "Feature",
  "properties": {
    "addr:full":"107 Brookville Dr Harvest AL 35749",
    "addr:housenumber":"107",
    "addr:postcode":"35749",
    "addr:street":"Brookville Dr",
    "iso:country":"US",
    "sg:address":"107 Brookville Dr",
    "sg:city":"Harvest",
    "sg:classifiers":[
        {
            "category":"Professional",
            "type":"Services"
        }
    ],
    "sg:phone":"+1 256 830 6860",
    "sg:postcode":"35749",
    "sg:province":"AL",
    "wof:name":"Tillman Trim & Deck",
    "wof:placetype":"venue"
},
  "geometry": {"coordinates":[-86.781691,34.779429],"type":"Point"}
}