{
  "type": "Feature",
  "properties": {
    "iso:country":"US",
    "sg:address":"9476 State Rte 22",
    "sg:city":"Maplesville",
    "sg:classifiers":[
        {
            "category":"Insurance",
            "subcategory":"Insurance Agent",
            "type":"Services"
        }
    ],
    "sg:phone":"+1 334 366 5700",
    "sg:postcode":"36750",
    "sg:province":"AL",
    "wof:name":"Alfa Insurance Corp",
    "wof:placetype":"venue"
},
  "geometry": {"coordinates":[-86.871275,32.788499],"type":"Point"}
}