{
  "type": "Feature",
  "properties": {
    "iso:country":"US",
    "sg:address":"12610 Jefferson Dr",
    "sg:city":"Duncanville",
    "sg:classifiers":[
        {
            "category":"Building & Trades",
            "subcategory":"Electrical",
            "type":"Services"
        }
    ],
    "sg:phone":"+1 205 345 7477",
    "sg:postcode":"35456",
    "sg:province":"AL",
    "sg:tags":[
        "equipment",
        "maintain",
        "telecommunication",
        "install"
    ],
    "wof:name":"Channell Communications Inc",
    "wof:placetype":"venue"
},
  "geometry": {"coordinates":[-87.47669999999999,33.120855],"type":"Point"}
}