{
  "type": "Feature",
  "properties": {
    "addr:full":"1207 Main St Daphne AL 36526",
    "addr:housenumber":"1207",
    "addr:postcode":"36526",
    "addr:street":"Main St",
    "iso:country":"US",
    "sg:address":"1207 Main St",
    "sg:city":"Daphne",
    "sg:classifiers":[
        {
            "category":"Health Services",
            "subcategory":"Health Practitioner",
            "type":"Services"
        }
    ],
    "sg:phone":"+1 251 621 6865",
    "sg:postcode":"36526",
    "sg:province":"AL",
    "sg:tags":[
        "therapist",
        "physical"
    ],
    "wof:name":"Progressive Rehab Svc",
    "wof:placetype":"venue"
},
  "geometry": {"coordinates":[-87.90267299999999,30.594997],"type":"Point"}
}