{
  "type": "Feature",
  "properties": {
    "addr:full":"9 Office Park Cir Mountain Brook AL 35223",
    "addr:postcode":"35223",
    "addr:street":"Park Cir",
    "iso:country":"US",
    "sg:address":"9 Office Park Cir",
    "sg:city":"Mountain Brook",
    "sg:classifiers":[
        {
            "category":"Organizations",
            "subcategory":"Non-profit Organization",
            "type":"Services"
        }
    ],
    "sg:phone":"+1 205 871 5000",
    "sg:postcode":"35223",
    "sg:province":"AL",
    "sg:tags":[
        "fund",
        "counselor",
        "raising"
    ],
    "wof:name":"Fund Raising Svc Inc",
    "wof:placetype":"venue"
},
  "geometry": {"coordinates":[-86.76952300000001,33.478772],"type":"Point"}
}