{
  "type": "Feature",
  "properties": {
    "iso:country":"US",
    "sg:address":"610 7th St",
    "sg:city":"Florala",
    "sg:classifiers":[
        {
            "category":"Utilities",
            "subcategory":"Refuse",
            "type":"Services"
        }
    ],
    "sg:phone":"+1 334 858 4841",
    "sg:postcode":"36442",
    "sg:province":"AL",
    "sg:tags":[
        "garbage",
        "collection"
    ],
    "wof:name":"C & L Garbage Co",
    "wof:placetype":"venue"
},
  "geometry": {"coordinates":[-86.330033,31.008793],"type":"Point"}
}