{
  "type": "Feature",
  "properties": {
    "addr:full":"8731 2nd Ave N Birmingham AL 35206",
    "addr:housenumber":"8731",
    "addr:postcode":"35206",
    "addr:street":"2Nd Ave N",
    "iso:country":"US",
    "sg:address":"8731 2nd Ave N",
    "sg:city":"Birmingham",
    "sg:classifiers":[
        {
            "category":"Professional",
            "subcategory":"Art Services",
            "type":"Services"
        }
    ],
    "sg:phone":"+1 205 807 2071",
    "sg:postcode":"35206",
    "sg:province":"AL",
    "sg:tags":[
        "graphic",
        "designer"
    ],
    "wof:name":"Linda's Graphics",
    "wof:placetype":"venue"
},
  "geometry": {"coordinates":[-86.719982,33.579533],"type":"Point"}
}