{
  "type": "Feature",
  "properties": {
    "iso:country":"US",
    "sg:address":"9 Park St",
    "sg:city":"Headland",
    "sg:classifiers":[
        {
            "category":"Government",
            "subcategory":"Office",
            "type":"Public Place"
        }
    ],
    "sg:phone":"+1 334 693 3363",
    "sg:postcode":"36345",
    "sg:province":"AL",
    "sg:tags":[
        "govt",
        "city"
    ],
    "wof:name":"Headland City Water Dept",
    "wof:placetype":"venue"
},
  "geometry": {"coordinates":[-85.341928,31.351555],"type":"Point"}
}