{
  "type": "Feature",
  "properties": {
    "iso:country":"US",
    "sg:address":"601 12th St",
    "sg:city":"Phenix City",
    "sg:classifiers":[
        {
            "category":"Government",
            "subcategory":"Office",
            "type":"Public Place"
        }
    ],
    "sg:phone":"+1 334 448 2707",
    "sg:postcode":"36867",
    "sg:province":"AL",
    "sg:tags":[
        "village"
    ],
    "wof:name":"Phenix City Personnel",
    "wof:placetype":"venue"
},
  "geometry": {"coordinates":[-85.000822,32.469076],"type":"Point"}
}