{
  "type": "Feature",
  "properties": {
    "iso:country":"US",
    "sg:address":"402 W Powell St",
    "sg:city":"Dothan",
    "sg:classifiers":[
        {
            "category":"Organizations",
            "subcategory":"Religious Organization",
            "type":"Services"
        }
    ],
    "sg:phone":"+1 334 671 2882",
    "sg:postcode":"36303",
    "sg:province":"AL",
    "wof:name":"Ordinary People Society",
    "wof:placetype":"venue"
},
  "geometry": {"coordinates":[-85.396825,31.230398],"type":"Point"}
}