{
  "type": "Feature",
  "properties": {
    "iso:country":"US",
    "sg:address":"7751 State Rte 253",
    "sg:city":"Guin",
    "sg:classifiers":[
        {
            "category":"Retail",
            "subcategory":"Animal Services",
            "type":"Services"
        }
    ],
    "sg:phone":"+1 205 468 2306",
    "sg:postcode":"35563",
    "sg:province":"AL",
    "wof:name":"Wruff Cut",
    "wof:placetype":"venue"
},
  "geometry": {"coordinates":[-87.837152,34.041174],"type":"Point"}
}