{
  "type": "Feature",
  "properties": {
    "iso:country":"US",
    "sg:address":"3935 Crosshaven Dr",
    "sg:city":"Birmingham",
    "sg:classifiers":[
        {
            "category":"Food & Beverages",
            "subcategory":"Groceries & Convenience Stores",
            "type":"Retail Goods"
        }
    ],
    "sg:phone":"+1 205 967 2233",
    "sg:postcode":"35243",
    "sg:province":"AL",
    "wof:name":"Cahaba Heights Exxcon",
    "wof:placetype":"venue"
},
  "geometry": {"coordinates":[-86.731186,33.462562],"type":"Point"}
}