{
  "type": "Feature",
  "properties": {
    "iso:country":"US",
    "sg:address":"369 S College St",
    "sg:city":"Auburn",
    "sg:classifiers":[
        {
            "category":"Organizations",
            "subcategory":"Professional Association",
            "type":"Services"
        }
    ],
    "sg:phone":"+1 334 821 5148",
    "sg:postcode":"36830",
    "sg:province":"AL",
    "wof:name":"Alabama Nurserymen's Assn",
    "wof:placetype":"venue"
},
  "geometry": {"coordinates":[-85.481695,32.600724],"type":"Point"}
}