{
  "type": "Feature",
  "properties": {
    "iso:country":"US",
    "sg:address":"1624 S Eufaula Ave",
    "sg:city":"Eufaula",
    "sg:classifiers":[
        {
            "category":"Autos & Motor Vehicles",
            "subcategory":"Automobile Sales",
            "type":"Retail Goods"
        }
    ],
    "sg:phone":"+1 334 687 4088",
    "sg:postcode":"36027",
    "sg:province":"AL",
    "sg:tags":[
        "car",
        "used",
        "dealer"
    ],
    "wof:name":"Dewayne's Auto Sales",
    "wof:placetype":"venue"
},
  "geometry": {"coordinates":[-85.153851,31.873456],"type":"Point"}
}