{
  "type": "Feature",
  "properties": {
    "iso:country":"US",
    "sg:address":"2411 US Hwy 31",
    "sg:city":"Bay Minette",
    "sg:classifiers":[
        {
            "category":"Health Services",
            "subcategory":"Nursing And Care Facility",
            "type":"Services"
        }
    ],
    "sg:phone":"+1 251 580 2660",
    "sg:postcode":"36507",
    "sg:province":"AL",
    "sg:tags":[
        "living",
        "assisted"
    ],
    "wof:name":"Azalea Pl Asssted Lving Fcilty",
    "wof:placetype":"venue"
},
  "geometry": {"coordinates":[-87.775021,30.841909],"type":"Point"}
}