{
  "type": "Feature",
  "properties": {
    "iso:country":"US",
    "sg:address":"302 3rd St SW",
    "sg:city":"Attalla",
    "sg:classifiers":[
        {
            "category":"Restaurant",
            "type":"Food & Drink"
        }
    ],
    "sg:phone":"+1 256 538 5632",
    "sg:postcode":"35954",
    "sg:province":"AL",
    "sg:tags":[
        "eating"
    ],
    "wof:name":"Jacks Hamburgers 93",
    "wof:placetype":"venue"
},
  "geometry": {"coordinates":[-86.097394,34.015499],"type":"Point"}
}