{
  "type": "Feature",
  "properties": {
    "iso:country":"US",
    "sg:address":"7880 Madison Pike",
    "sg:city":"Madison",
    "sg:classifiers":[
        {
            "category":"Health Services",
            "subcategory":"Optometrist",
            "type":"Services"
        }
    ],
    "sg:phone":"+1 256 772 8711",
    "sg:postcode":"35758",
    "sg:province":"AL",
    "wof:name":"Eye Care Assoc Inc",
    "wof:placetype":"venue"
},
  "geometry": {"coordinates":[-86.713838,34.707498],"type":"Point"}
}