{
  "type": "Feature",
  "properties": {
    "addr:full":"4717 University Dr NW Huntsville AL 35816",
    "addr:housenumber":"4717",
    "addr:postcode":"35816",
    "addr:street":"University Dr Nw",
    "iso:country":"US",
    "sg:address":"4717 University Dr NW",
    "sg:city":"Huntsville",
    "sg:classifiers":[
        {
            "category":"Professional",
            "subcategory":"Employment Agencies",
            "type":"Services"
        }
    ],
    "sg:phone":"+1 256 721 0513",
    "sg:postcode":"35816",
    "sg:province":"AL",
    "sg:tags":[
        "help",
        "supply"
    ],
    "wof:name":"SOS Temporary Services",
    "wof:placetype":"venue"
},
  "geometry": {"coordinates":[-86.648223,34.735758],"type":"Point"}
}