{
  "type": "Feature",
  "properties": {
    "iso:country":"US",
    "sg:address":"64 Main St W",
    "sg:city":"Rainsville",
    "sg:classifiers":[
        {
            "category":"Personal",
            "subcategory":"Beauty Salon",
            "type":"Services"
        }
    ],
    "sg:phone":"+1 256 638 7099",
    "sg:postcode":"35986",
    "sg:province":"AL",
    "sg:tags":[
        "manicuring"
    ],
    "wof:name":"Rainsville Nails",
    "wof:placetype":"venue"
},
  "geometry": {"coordinates":[-85.848911,34.494992],"type":"Point"}
}