{
  "type": "Feature",
  "properties": {
    "iso:country":"US",
    "sg:address":"1541 Pine Ridge Rd",
    "sg:city":"Montgomery",
    "sg:classifiers":[
        {
            "category":"Professional",
            "subcategory":"Engineering",
            "type":"Services"
        }
    ],
    "sg:phone":"+1 334 213 1157",
    "sg:postcode":"36109",
    "sg:province":"AL",
    "wof:name":"High Point Inc",
    "wof:placetype":"venue"
},
  "geometry": {"coordinates":[-86.251847,32.400453],"type":"Point"}
}