{
  "type": "Feature",
  "properties": {
    "iso:country":"US",
    "sg:address":"314 Pawnee Trl SE",
    "sg:city":"Huntsville",
    "sg:classifiers":[
        {
            "category":"Education",
            "subcategory":"Special Training",
            "type":"Public Place"
        }
    ],
    "sg:phone":"+1 256 881 0171",
    "sg:postcode":"35803",
    "sg:province":"AL",
    "wof:name":"Joyce M Beason",
    "wof:placetype":"venue"
},
  "geometry": {"coordinates":[-86.56379,34.626179],"type":"Point"}
}