{
  "type": "Feature",
  "properties": {
    "iso:country":"US",
    "sg:address":"133 Hope Dr",
    "sg:city":"Daphne",
    "sg:classifiers":[
        {
            "category":"Cinema",
            "subcategory":"Movie Theater",
            "type":"Entertainment"
        }
    ],
    "sg:phone":"+1 251 626 0306",
    "sg:postcode":"36526",
    "sg:province":"AL",
    "sg:tags":[
        "operations",
        "lessor",
        "broke"
    ],
    "wof:name":"Eastern Shore Cinema",
    "wof:placetype":"venue"
},
  "geometry": {"coordinates":[-87.884268,30.643995],"type":"Point"}
}