{
  "type": "Feature",
  "properties": {
    "addr:full":"636 15th St E Tuscaloosa AL 35401",
    "addr:housenumber":"636",
    "addr:postcode":"35401",
    "addr:street":"15Th St",
    "iso:country":"US",
    "sg:address":"636 15th St E",
    "sg:city":"Tuscaloosa",
    "sg:classifiers":[
        {
            "category":"Manufacturing",
            "subcategory":"Printing",
            "type":"Manufacturing & Wholesale Goods"
        }
    ],
    "sg:phone":"+1 205 750 0690",
    "sg:postcode":"35401",
    "sg:province":"AL",
    "sg:tags":[
        "screen"
    ],
    "wof:name":"TNT T-Shirts",
    "wof:placetype":"venue"
},
  "geometry": {"coordinates":[-87.528336,33.197501],"type":"Point"}
}