{
  "type": "Feature",
  "properties": {
    "iso:country":"US",
    "sg:address":"4621 Round Forest Dr",
    "sg:city":"Birmingham",
    "sg:classifiers":[
        {
            "category":"Wholesale",
            "subcategory":"Machinery & Supplies",
            "type":"Manufacturing & Wholesale Goods"
        }
    ],
    "sg:phone":"+1 205 879 2063",
    "sg:postcode":"35213",
    "sg:province":"AL",
    "sg:tags":[
        "equipment",
        "industrial"
    ],
    "wof:name":"Southwood Machinery Inc",
    "wof:placetype":"venue"
},
  "geometry": {"coordinates":[-86.70307,33.518463],"type":"Point"}
}