{
  "type": "Feature",
  "properties": {
    "iso:country":"US",
    "sg:address":"408 Dora St",
    "sg:city":"Albertville",
    "sg:classifiers":[
        {
            "category":"Retail",
            "subcategory":"Auto Repair",
            "type":"Services"
        }
    ],
    "sg:phone":"+1 256 891 3317",
    "sg:postcode":"35950",
    "sg:province":"AL",
    "sg:tags":[
        "body"
    ],
    "wof:name":"Alliance Mobile Headliner Svc",
    "wof:placetype":"venue"
},
  "geometry": {"coordinates":[-86.208045,34.262127],"type":"Point"}
}