{
  "type": "Feature",
  "properties": {
    "iso:country":"US",
    "sg:address":"553 Cold Springs Rd",
    "sg:city":"Deatsville",
    "sg:phone":"+1 334 285 4759",
    "sg:postcode":"36022",
    "sg:province":"AL",
    "sg:tags":[
        "farm",
        "cotton"
    ],
    "wof:name":"Huston J Gibbons",
    "wof:placetype":"venue"
},
  "geometry": {"coordinates":[-86.35969900000001,32.610954],"type":"Point"}
}