{
  "type": "Feature",
  "properties": {
    "iso:country":"US",
    "sg:address":"111 4th St S",
    "sg:city":"Oneonta",
    "sg:classifiers":[
        {
            "category":"Retail",
            "subcategory":"Auto Repair",
            "type":"Services"
        }
    ],
    "sg:phone":"+1 205 625 3839",
    "sg:postcode":"35121",
    "sg:province":"AL",
    "sg:tags":[
        "body",
        "automobile",
        "painting"
    ],
    "wof:name":"Gibson & Box Auto Body Repair",
    "wof:placetype":"venue"
},
  "geometry": {"coordinates":[-86.472929,33.945889],"type":"Point"}
}