{
  "type": "Feature",
  "properties": {
    "iso:country":"US",
    "sg:address":"100 Riverbend Dr",
    "sg:city":"Mobile",
    "sg:classifiers":[
        {
            "category":"Organizations",
            "subcategory":"Community Association",
            "type":"Services"
        }
    ],
    "sg:phone":"+1 251 476 1838",
    "sg:postcode":"36605",
    "sg:province":"AL",
    "sg:tags":[
        "condominium"
    ],
    "wof:name":"River Landing Club Owners Assn",
    "wof:placetype":"venue"
},
  "geometry": {"coordinates":[-88.097563,30.624247],"type":"Point"}
}