{
  "type": "Feature",
  "properties": {
    "addr:full":"628 2nd St Muscle Shoals AL 35661",
    "addr:housenumber":"628",
    "addr:postcode":"35661",
    "addr:street":"2Nd St",
    "iso:country":"US",
    "sg:address":"628 2nd St",
    "sg:city":"Muscle Shoals",
    "sg:classifiers":[
        {
            "category":"Restaurant",
            "type":"Food & Drink"
        }
    ],
    "sg:phone":"+1 256 386 0088",
    "sg:postcode":"35661",
    "sg:province":"AL",
    "sg:tags":[
        "eating"
    ],
    "wof:name":"Coralee's Family Restaurants",
    "wof:placetype":"venue"
},
  "geometry": {"coordinates":[-87.673224,34.759589],"type":"Point"}
}