{
  "type": "Feature",
  "properties": {
    "addr:full":"2838 Yellow Leaf Rd Clanton AL 35045",
    "addr:housenumber":"2838",
    "addr:postcode":"35045",
    "addr:street":"Yellow Leaf Rd",
    "iso:country":"US",
    "sg:address":"2838 Yellow Leaf Rd",
    "sg:city":"Clanton",
    "sg:classifiers":[
        {
            "category":"Recreation",
            "type":"Entertainment"
        }
    ],
    "sg:phone":"+1 205 755 5896",
    "sg:postcode":"35045",
    "sg:province":"AL",
    "sg:tags":[
        "club",
        "membership"
    ],
    "wof:name":"National Exchange Club",
    "wof:placetype":"venue"
},
  "geometry": {"coordinates":[-86.641032,32.86739],"type":"Point"}
}