{
  "type": "Feature",
  "properties": {
    "iso:country":"US",
    "sg:address":"3719 Dauphin St",
    "sg:city":"Mobile",
    "sg:classifiers":[
        {
            "category":"Health Services",
            "subcategory":"Doctor",
            "type":"Services"
        }
    ],
    "sg:phone":"+1 251 414 5665",
    "sg:postcode":"36608",
    "sg:province":"AL",
    "sg:tags":[
        "physician",
        "surgeon",
        "medical"
    ],
    "wof:name":"Radiation Therapy-Oncology PC",
    "wof:placetype":"venue"
},
  "geometry": {"coordinates":[-88.1434,30.685375],"type":"Point"}
}