{
  "type": "Feature",
  "properties": {
    "iso:country":"US",
    "sg:address":"106 Lee St NE",
    "sg:city":"Decatur",
    "sg:classifiers":[
        {
            "category":"Professional",
            "subcategory":"Lawyer & Legal Services",
            "type":"Services"
        }
    ],
    "sg:phone":"+1 256 350 2252",
    "sg:postcode":"35601",
    "sg:province":"AL",
    "sg:tags":[
        "attorney"
    ],
    "wof:name":"Yarbrough Law Firm",
    "wof:placetype":"venue"
},
  "geometry": {"coordinates":[-86.986913,34.607755],"type":"Point"}
}