{
  "type": "Feature",
  "properties": {
    "iso:country":"US",
    "sg:address":"101 Pollard St",
    "sg:city":"Montgomery",
    "sg:classifiers":[
        {
            "category":"Wholesale",
            "subcategory":"Machinery & Supplies",
            "type":"Manufacturing & Wholesale Goods"
        }
    ],
    "sg:phone":"+1 334 263 2524",
    "sg:postcode":"36104",
    "sg:province":"AL",
    "sg:tags":[
        "bearing"
    ],
    "wof:name":"Bearings & Drives Inc",
    "wof:placetype":"venue"
},
  "geometry": {"coordinates":[-86.30737,32.384166],"type":"Point"}
}