{
  "type": "Feature",
  "properties": {
    "iso:country":"US",
    "sg:address":"2119 3rd Ave N",
    "sg:city":"Birmingham",
    "sg:classifiers":[
        {
            "category":"Professional",
            "subcategory":"Secretarial Services",
            "type":"Services"
        }
    ],
    "sg:phone":"+1 205 324 2333",
    "sg:postcode":"35203",
    "sg:province":"AL",
    "sg:tags":[
        "reporting",
        "court"
    ],
    "wof:name":"Edmondson Reporting & Video",
    "wof:placetype":"venue"
},
  "geometry": {"coordinates":[-86.804323,33.517426],"type":"Point"}
}