{
  "type": "Feature",
  "properties": {
    "addr:full":"1010 Riveria Ave SE Huntsville AL 35802",
    "addr:housenumber":"1010",
    "addr:postcode":"35802",
    "addr:street":"Riveria Ave Se",
    "iso:country":"US",
    "sg:address":"1010 Riveria Ave SE",
    "sg:city":"Huntsville",
    "sg:classifiers":[
        {
            "category":"Professional",
            "subcategory":"Lawyer & Legal Services",
            "type":"Services"
        }
    ],
    "sg:phone":"+1 256 880 0171",
    "sg:postcode":"35802",
    "sg:province":"AL",
    "sg:tags":[
        "attorney"
    ],
    "wof:name":"Robert Willisson",
    "wof:placetype":"venue"
},
  "geometry": {"coordinates":[-86.540766,34.665924],"type":"Point"}
}