{
  "type": "Feature",
  "properties": {
    "iso:country":"US",
    "sg:address":"54 Dalraida Rd",
    "sg:city":"Montgomery",
    "sg:classifiers":[
        {
            "category":"Retail",
            "subcategory":"Repair Shop",
            "type":"Services"
        }
    ],
    "sg:phone":"+1 334 271 2540",
    "sg:postcode":"36109",
    "sg:province":"AL",
    "sg:tags":[
        "lock",
        "locksmith"
    ],
    "wof:name":"Alabama Locksmith & Security",
    "wof:placetype":"venue"
},
  "geometry": {"coordinates":[-86.245755,32.383645],"type":"Point"}
}