{
  "type": "Feature",
  "properties": {
    "iso:country":"US",
    "sg:address":"1248 Conception Street Rd",
    "sg:city":"Mobile",
    "sg:classifiers":[
        {
            "category":"Building & Trades",
            "subcategory":"Equipment Rental",
            "type":"Services"
        }
    ],
    "sg:phone":"+1 251 452 2241",
    "sg:postcode":"36610",
    "sg:province":"AL",
    "sg:tags":[
        "crane"
    ],
    "wof:name":"Equipment Rental & Contractors",
    "wof:placetype":"venue"
},
  "geometry": {"coordinates":[-88.063948,30.717588],"type":"Point"}
}