{
  "type": "Feature",
  "properties": {
    "iso:country":"US",
    "sg:address":"695 Wooden Bridge Dr",
    "sg:city":"Auburn",
    "sg:classifiers":[
        {
            "category":"Health Services",
            "subcategory":"Doctor",
            "type":"Services"
        }
    ],
    "sg:phone":"+1 334 501 1561",
    "sg:postcode":"36830",
    "sg:province":"AL",
    "sg:tags":[
        "clinic"
    ],
    "wof:name":"Great Starts Of Alabama",
    "wof:placetype":"venue"
},
  "geometry": {"coordinates":[-85.472848,32.574014],"type":"Point"}
}