{
  "type": "Feature",
  "properties": {
    "iso:country":"US",
    "sg:address":"3312 26th St N",
    "sg:city":"Birmingham",
    "sg:classifiers":[
        {
            "category":"Personal",
            "subcategory":"Beauty Salon",
            "type":"Services"
        }
    ],
    "sg:phone":"+1 205 252 0253",
    "sg:postcode":"35207",
    "sg:province":"AL",
    "wof:name":"Ethridge Brothers",
    "wof:placetype":"venue"
},
  "geometry": {"coordinates":[-86.819478,33.555065],"type":"Point"}
}