{
  "type": "Feature",
  "properties": {
    "iso:country":"US",
    "sg:address":"3026 E Meighan Blvd",
    "sg:city":"Gadsden",
    "sg:classifiers":[
        {
            "category":"Travel",
            "subcategory":"Hotels & Motels",
            "type":"Entertainment"
        }
    ],
    "sg:phone":"+1 256 494 5345",
    "sg:postcode":"35903",
    "sg:province":"AL",
    "sg:tags":[
        "resort"
    ],
    "sg:website":"www.yearroundvacation.com",
    "wof:name":"Festiva Resorts",
    "wof:placetype":"venue"
},
  "geometry": {"coordinates":[-85.951648,33.974425],"type":"Point"}
}