{
  "type": "Feature",
  "properties": {
    "addr:full":"3026 E Meighan Blvd Gadsden AL 35903",
    "addr:housenumber":"3026",
    "addr:postcode":"35903",
    "addr:street":"E Meighan Blvd",
    "iso:country":"US",
    "sg:address":"3026 E Meighan Blvd",
    "sg:city":"Gadsden",
    "sg:classifiers":[
        {
            "category":"Travel",
            "subcategory":"Hotels & Motels",
            "type":"Entertainment"
        }
    ],
    "sg:phone":"+1 256 494 5345",
    "sg:postcode":"35903",
    "sg:province":"AL",
    "sg:tags":[
        "resort"
    ],
    "sg:website":"www.yearroundvacation.com",
    "wof:name":"Festiva Resorts",
    "wof:placetype":"venue"
},
  "geometry": {"coordinates":[-85.95164800000001,33.974425],"type":"Point"}
}