{
  "type": "Feature",
  "properties": {
    "iso:country":"US",
    "sg:address":"565 US Hwy 431",
    "sg:city":"Boaz",
    "sg:classifiers":[
        {
            "category":"Utilities",
            "subcategory":"Telephone",
            "type":"Services"
        },
        {
            "category":"Shopping",
            "subcategory":"Computers & Home Electronics",
            "type":"Retail Goods"
        }
    ],
    "sg:phone":"+1 256 840 1400",
    "sg:postcode":"35957",
    "sg:province":"AL",
    "sg:tags":[
        "equipment",
        "satellite",
        "system",
        "cable",
        "communications"
    ],
    "wof:name":"East Alabama Electronic Inc",
    "wof:placetype":"venue"
},
  "geometry": {"coordinates":[-86.149075,34.19486],"type":"Point"}
}