{
  "type": "Feature",
  "properties": {
    "iso:country":"US",
    "sg:address":"506 Douglas Ave",
    "sg:city":"Brewton",
    "sg:classifiers":[
        {
            "category":"Shopping",
            "subcategory":"Clothing, Apparel, & Fashions",
            "type":"Retail Goods"
        }
    ],
    "sg:phone":"+1 251 867 8185",
    "sg:postcode":"36426",
    "sg:province":"AL",
    "sg:tags":[
        "personal"
    ],
    "wof:name":"Miss Pats Place",
    "wof:placetype":"venue"
},
  "geometry": {"coordinates":[-87.068541,31.113],"type":"Point"}
}