{
  "type": "Feature",
  "properties": {
    "addr:full":"1950 Sand Rock Ave Leesburg AL 35983",
    "addr:housenumber":"1950",
    "addr:postcode":"35983",
    "addr:street":"Sand Rock Ave",
    "iso:country":"US",
    "sg:address":"1950 Sand Rock Ave",
    "sg:city":"Leesburg",
    "sg:classifiers":[
        {
            "category":"Social Services",
            "subcategory":"Child Care",
            "type":"Services"
        }
    ],
    "sg:phone":"+1 256 523 5630",
    "sg:postcode":"35983",
    "sg:province":"AL",
    "sg:tags":[
        "day"
    ],
    "wof:name":"Headstart",
    "wof:placetype":"venue"
},
  "geometry": {"coordinates":[-85.76069,34.220878],"type":"Point"}
}