{
  "type": "Feature",
  "properties": {
    "iso:country":"US",
    "sg:address":"4496 State Rte 71",
    "sg:city":"Dutton",
    "sg:classifiers":[
        {
            "category":"Government",
            "subcategory":"Post Office",
            "type":"Public Place"
        }
    ],
    "sg:phone":"+1 256 228 3796",
    "sg:postcode":"35744",
    "sg:province":"AL",
    "sg:tags":[
        "postal",
        "us"
    ],
    "wof:name":"US Post Office",
    "wof:placetype":"venue"
},
  "geometry": {"coordinates":[-85.915775,34.611097],"type":"Point"}
}