{
  "type": "Feature",
  "properties": {
    "addr:full":"220 Ruth Rd NW Arab AL 35016",
    "addr:housenumber":"220",
    "addr:postcode":"35016",
    "addr:street":"Ruth Rd Nw",
    "iso:country":"US",
    "sg:address":"220 Ruth Rd NW",
    "sg:city":"Arab",
    "sg:classifiers":[
        {
            "category":"Shopping",
            "subcategory":"Used Merchandise",
            "type":"Retail Goods"
        }
    ],
    "sg:phone":"+1 256 586 4169",
    "sg:postcode":"35016",
    "sg:province":"AL",
    "sg:tags":[
        "antique"
    ],
    "wof:name":"Kelly Supply Gifts & Antiques",
    "wof:placetype":"venue"
},
  "geometry": {"coordinates":[-86.509484,34.355833],"type":"Point"}
}