{
  "type": "Feature",
  "properties": {
    "iso:country":"US",
    "sg:address":"2237 Bessemer Rd",
    "sg:city":"Birmingham",
    "sg:classifiers":[
        {
            "category":"Shopping",
            "subcategory":"Shoes",
            "type":"Retail Goods"
        }
    ],
    "sg:phone":"+1 205 788 9111",
    "sg:postcode":"35208",
    "sg:province":"AL",
    "sg:tags":[
        "athletic"
    ],
    "sg:website":"www.footlocker.com",
    "wof:name":"Foot Locker",
    "wof:placetype":"venue"
},
  "geometry": {"coordinates":[-86.87830099999999,33.495596],"type":"Point"}
}