{
  "type": "Feature",
  "properties": {
    "addr:full":"9148 Fairhope Ave Fairhope AL 36532",
    "addr:housenumber":"9148",
    "addr:postcode":"36532",
    "addr:street":"Fairhope Ave",
    "iso:country":"US",
    "sg:address":"9148 Fairhope Ave",
    "sg:city":"Fairhope",
    "sg:classifiers":[
        {
            "category":"Professional",
            "subcategory":"Accounting & Tax Preparation",
            "type":"Services"
        }
    ],
    "sg:phone":"+1 251 929 0381",
    "sg:postcode":"36532",
    "sg:province":"AL",
    "sg:tags":[
        "return",
        "filing"
    ],
    "wof:name":"Accounting Tax & Technology",
    "wof:placetype":"venue"
},
  "geometry": {"coordinates":[-87.86626,30.523582],"type":"Point"}
}