{
  "type": "Feature",
  "properties": {
    "addr:full":"4216 US Hwy 31 Decatur AL 35603",
    "addr:housenumber":"4216",
    "addr:postcode":"35603",
    "addr:street":"Us Hwy 31",
    "iso:country":"US",
    "sg:address":"4216 US Hwy 31",
    "sg:city":"Decatur",
    "sg:classifiers":[
        {
            "category":"Government",
            "subcategory":"Office",
            "type":"Public Place"
        }
    ],
    "sg:phone":"+1 256 552 0911",
    "sg:postcode":"35603",
    "sg:province":"AL",
    "wof:name":"E-911 Board",
    "wof:placetype":"venue"
},
  "geometry": {"coordinates":[-86.970952,34.525117],"type":"Point"}
}