{
  "type": "Feature",
  "properties": {
    "iso:country":"US",
    "sg:address":"601 1st Ave SW",
    "sg:city":"Cullman",
    "sg:classifiers":[
        {
            "category":"Social Services",
            "type":"Services"
        }
    ],
    "sg:phone":"+1 256 775 4656",
    "sg:postcode":"35055",
    "sg:province":"AL",
    "wof:name":"Substance Abuse",
    "wof:placetype":"venue"
},
  "geometry": {"coordinates":[-86.840856,34.172267],"type":"Point"}
}