{
  "type": "Feature",
  "properties": {
    "iso:country":"US",
    "sg:address":"14510 Forest Dr",
    "sg:city":"Tuscaloosa",
    "sg:classifiers":[
        {
            "category":"Building & Trades",
            "subcategory":"Landscaping Services",
            "type":"Services"
        }
    ],
    "sg:phone":"+1 205 758 1141",
    "sg:postcode":"35405",
    "sg:province":"AL",
    "sg:tags":[
        "tree"
    ],
    "wof:name":"Triple J Tree Svc",
    "wof:placetype":"venue"
},
  "geometry": {"coordinates":[-87.534158,33.064069],"type":"Point"}
}