{
  "type": "Feature",
  "properties": {
    "addr:full":"14510 Forest Dr Tuscaloosa AL 35405",
    "addr:housenumber":"14510",
    "addr:postcode":"35405",
    "addr:street":"Forest Dr",
    "iso:country":"US",
    "sg:address":"14510 Forest Dr",
    "sg:city":"Tuscaloosa",
    "sg:classifiers":[
        {
            "category":"Building & Trades",
            "subcategory":"Landscaping Services",
            "type":"Services"
        }
    ],
    "sg:phone":"+1 205 758 1141",
    "sg:postcode":"35405",
    "sg:province":"AL",
    "sg:tags":[
        "tree"
    ],
    "wof:name":"Triple J Tree Svc",
    "wof:placetype":"venue"
},
  "geometry": {"coordinates":[-87.53415800000001,33.064069],"type":"Point"}
}