{
  "type": "Feature",
  "properties": {
    "addr:full":"2006 Franklin St SE Huntsville AL 35801",
    "addr:housenumber":"2006",
    "addr:postcode":"35801",
    "addr:street":"Franklin St Se",
    "iso:country":"US",
    "sg:address":"2006 Franklin St SE",
    "sg:city":"Huntsville",
    "sg:classifiers":[
        {
            "category":"Organizations",
            "subcategory":"Non-profit Organization",
            "type":"Services"
        }
    ],
    "sg:phone":"+1 256 534 1996",
    "sg:postcode":"35801",
    "sg:province":"AL",
    "sg:tags":[
        "alternative",
        "abortion"
    ],
    "wof:name":"Choose Life-Save-A-Life",
    "wof:placetype":"venue"
},
  "geometry": {"coordinates":[-86.576916,34.718755],"type":"Point"}
}