{
  "type": "Feature",
  "properties": {
    "iso:country":"US",
    "sg:address":"2603 Highland Ave",
    "sg:city":"Montgomery",
    "sg:classifiers":[
        {
            "category":"Building & Trades",
            "subcategory":"Plumbing",
            "type":"Services"
        }
    ],
    "sg:phone":"+1 334 264 1217",
    "sg:postcode":"36107",
    "sg:province":"AL",
    "sg:tags":[
        "contractor"
    ],
    "wof:name":"Ihs Services",
    "wof:placetype":"venue"
},
  "geometry": {"coordinates":[-86.273285,32.372447],"type":"Point"}
}