{
  "type": "Feature",
  "properties": {
    "iso:country":"US",
    "sg:address":"1219 Almon St Ste A",
    "sg:city":"Heflin",
    "sg:classifiers":[
        {
            "category":"Personal",
            "subcategory":"Beauty Salon",
            "type":"Services"
        }
    ],
    "sg:phone":"+1 256 463 2775",
    "sg:postcode":"36264",
    "sg:province":"AL",
    "wof:name":"Salon On Almon",
    "wof:placetype":"venue"
},
  "geometry": {"coordinates":[-85.59261100000001,33.633262],"type":"Point"}
}