{
  "type": "Feature",
  "properties": {
    "addr:full":"12330 Viewpoint Rd Northport AL 35475",
    "addr:housenumber":"12330",
    "addr:postcode":"35475",
    "addr:street":"Viewpoint Rd",
    "iso:country":"US",
    "sg:address":"12330 Viewpoint Rd",
    "sg:city":"Northport",
    "sg:classifiers":[
        {
            "category":"Retail",
            "subcategory":"Auto Repair",
            "type":"Services"
        }
    ],
    "sg:phone":"+1 205 339 3634",
    "sg:postcode":"35475",
    "sg:province":"AL",
    "sg:tags":[
        "body",
        "shop"
    ],
    "wof:name":"Griffins Body Masters",
    "wof:placetype":"venue"
},
  "geometry": {"coordinates":[-87.607398,33.349189],"type":"Point"}
}