{
  "type": "Feature",
  "properties": {
    "iso:country":"US",
    "sg:address":"1603 Brentwood",
    "sg:city":"Muscle Shoals",
    "sg:classifiers":[
        {
            "category":"Building & Trades",
            "subcategory":"Construction",
            "type":"Services"
        }
    ],
    "sg:phone":"+1 256 386 7946",
    "sg:postcode":"35661",
    "sg:province":"AL",
    "sg:tags":[
        "retail",
        "pool",
        "swimming"
    ],
    "wof:name":"Rainbow Pools Inc",
    "wof:placetype":"venue"
},
  "geometry": {"coordinates":[-87.64788299999999,34.725281],"type":"Point"}
}