{
  "type": "Feature",
  "properties": {
    "iso:country":"US",
    "sg:address":"315 15th St",
    "sg:city":"Tuscaloosa",
    "sg:classifiers":[
        {
            "category":"Personal",
            "subcategory":"Barber",
            "type":"Services"
        }
    ],
    "sg:phone":"+1 205 759 3234",
    "sg:postcode":"35401",
    "sg:province":"AL",
    "wof:name":"Don's Barber & Styling Shop",
    "wof:placetype":"venue"
},
  "geometry": {"coordinates":[-87.539135,33.198326],"type":"Point"}
}