{
  "type": "Feature",
  "properties": {
    "iso:country":"US",
    "sg:address":"6885 Doc Owens Rd",
    "sg:city":"Dora",
    "sg:classifiers":[
        {
            "category":"Shopping",
            "type":"Retail Goods"
        }
    ],
    "sg:phone":"+1 205 648 3171",
    "sg:postcode":"35062",
    "sg:province":"AL",
    "sg:tags":[
        "cosmetic",
        "perfume"
    ],
    "wof:name":"Mary Kay Cosmetics",
    "wof:placetype":"venue"
},
  "geometry": {"coordinates":[-87.02133600000001,33.712417],"type":"Point"}
}