{
  "type": "Feature",
  "properties": {
    "iso:country":"US",
    "sg:address":"8571 Three Mile Rd",
    "sg:city":"Irvington",
    "sg:classifiers":[
        {
            "category":"Social Services",
            "subcategory":"Adult Care",
            "type":"Services"
        }
    ],
    "sg:phone":"+1 251 824 9875",
    "sg:postcode":"36544",
    "sg:province":"AL",
    "sg:tags":[
        "home",
        "residential"
    ],
    "wof:name":"Mackey's Home",
    "wof:placetype":"venue"
},
  "geometry": {"coordinates":[-88.242673,30.457984],"type":"Point"}
}