{
  "type": "Feature",
  "properties": {
    "iso:country":"US",
    "sg:address":"803 26 Ave",
    "sg:city":"Phenix City",
    "sg:classifiers":[
        {
            "category":"Building & Trades",
            "subcategory":"Landscaping Services",
            "type":"Services"
        }
    ],
    "sg:phone":"+1 334 297 0458",
    "sg:postcode":"36869",
    "sg:province":"AL",
    "wof:name":"C & M Lawn Service",
    "wof:placetype":"venue"
},
  "geometry": {"coordinates":[-85.029446,32.477677],"type":"Point"}
}