{
  "type": "Feature",
  "properties": {
    "iso:country":"US",
    "sg:address":"101 E Brunson St",
    "sg:city":"Enterprise",
    "sg:classifiers":[
        {
            "category":"Health Services",
            "subcategory":"Doctor",
            "type":"Services"
        }
    ],
    "sg:phone":"+1 334 393 3686",
    "sg:postcode":"36330",
    "sg:province":"AL",
    "sg:tags":[
        "medical"
    ],
    "wof:name":"Mockler Karen J MD",
    "wof:placetype":"venue"
},
  "geometry": {"coordinates":[-85.853059,31.319402],"type":"Point"}
}