{
  "type": "Feature",
  "properties": {
    "iso:country":"US",
    "sg:address":"2610 Cone Dr",
    "sg:city":"Birmingham",
    "sg:classifiers":[
        {
            "category":"Building & Trades",
            "subcategory":"Construction",
            "type":"Services"
        }
    ],
    "sg:phone":"+1 205 841 6010",
    "sg:postcode":"35217",
    "sg:province":"AL",
    "sg:tags":[
        "contractor"
    ],
    "wof:name":"B & H Contracting Inc",
    "wof:placetype":"venue"
},
  "geometry": {"coordinates":[-86.78130299999999,33.623901],"type":"Point"}
}