{
  "type": "Feature",
  "properties": {
    "iso:country":"US",
    "sg:address":"2300 Washington St NW",
    "sg:city":"Huntsville",
    "sg:classifiers":[
        {
            "category":"Building & Trades",
            "subcategory":"Construction",
            "type":"Services"
        }
    ],
    "sg:phone":"+1 256 539 7006",
    "sg:postcode":"35811",
    "sg:province":"AL",
    "sg:tags":[
        "masonry",
        "contractor"
    ],
    "wof:name":"Southern Masonry",
    "wof:placetype":"venue"
},
  "geometry": {"coordinates":[-86.588436,34.753044],"type":"Point"}
}