{
  "type": "Feature",
  "properties": {
    "iso:country":"US",
    "sg:address":"127 Hayden St",
    "sg:city":"New Hope",
    "sg:classifiers":[
        {
            "category":"Building & Trades",
            "subcategory":"Construction",
            "type":"Services"
        }
    ],
    "sg:phone":"+1 256 723 5703",
    "sg:postcode":"35760",
    "sg:province":"AL",
    "sg:tags":[
        "general",
        "contractor"
    ],
    "wof:name":"Cedar Creek Construction",
    "wof:placetype":"venue"
},
  "geometry": {"coordinates":[-86.39557499999999,34.538762],"type":"Point"}
}