{
  "type": "Feature",
  "properties": {
    "addr:full":"154 N Haardt Dr Montgomery AL 36105",
    "addr:housenumber":"154",
    "addr:postcode":"36105",
    "addr:street":"N Haardt Dr",
    "iso:country":"US",
    "sg:address":"154 N Haardt Dr",
    "sg:city":"Montgomery",
    "sg:classifiers":[
        {
            "category":"Recreation",
            "type":"Entertainment"
        }
    ],
    "sg:phone":"+1 334 262 9473",
    "sg:postcode":"36105",
    "sg:province":"AL",
    "wof:name":"Pdp Travel Agency",
    "wof:placetype":"venue"
},
  "geometry": {"coordinates":[-86.31426999999999,32.345748],"type":"Point"}
}