{
  "type": "Feature",
  "properties": {
    "addr:full":"1376 Swallow Ln Birmingham AL 35213",
    "addr:housenumber":"1376",
    "addr:postcode":"35213",
    "addr:street":"Swallow Ln",
    "iso:country":"US",
    "sg:address":"1376 Swallow Ln",
    "sg:city":"Birmingham",
    "sg:classifiers":[
        {
            "category":"Professional",
            "subcategory":"Management & Consulting",
            "type":"Services"
        }
    ],
    "sg:phone":"+1 205 956 0611",
    "sg:postcode":"35213",
    "sg:province":"AL",
    "sg:tags":[
        "business"
    ],
    "wof:name":"Tre Consulting LLC",
    "wof:placetype":"venue"
},
  "geometry": {"coordinates":[-86.72507400000001,33.517452],"type":"Point"}
}