{
  "type": "Feature",
  "properties": {
    "iso:country":"US",
    "sg:address":"19226 Co Rd 12 S",
    "sg:city":"Foley",
    "sg:classifiers":[
        {
            "category":"Building & Trades",
            "subcategory":"Electrical",
            "type":"Services"
        }
    ],
    "sg:phone":"+1 251 970 3509",
    "sg:postcode":"36535",
    "sg:province":"AL",
    "sg:tags":[
        "electric",
        "contractor"
    ],
    "wof:name":"Coastline Electrical Co",
    "wof:placetype":"venue"
},
  "geometry": {"coordinates":[-87.696387,30.355559],"type":"Point"}
}