{
  "type": "Feature",
  "properties": {
    "iso:country":"US",
    "sg:address":"1172 Grier Rd",
    "sg:city":"Wetumpka",
    "sg:classifiers":[
        {
            "category":"Professional",
            "subcategory":"Management & Consulting",
            "type":"Services"
        }
    ],
    "sg:phone":"+1 334 514 9383",
    "sg:postcode":"36092",
    "sg:province":"AL",
    "wof:name":"William Hamrick",
    "wof:placetype":"venue"
},
  "geometry": {"coordinates":[-86.19299599999999,32.616238],"type":"Point"}
}