{
  "type": "Feature",
  "properties": {
    "iso:country":"US",
    "sg:address":"2001 US Hwy 31",
    "sg:city":"Hartselle",
    "sg:classifiers":[
        {
            "category":"Autos & Motor Vehicles",
            "subcategory":"Fuel & Gas Station",
            "type":"Retail Goods"
        }
    ],
    "sg:phone":"+1 256 751 3755",
    "sg:postcode":"35640",
    "sg:province":"AL",
    "sg:tags":[
        "oil"
    ],
    "wof:name":"Southside Shell Foodmart",
    "wof:placetype":"venue"
},
  "geometry": {"coordinates":[-86.958274,34.472179],"type":"Point"}
}