{
  "type": "Feature",
  "properties": {
    "iso:country":"US",
    "sg:address":"2463 Redmill Saragossa Rd",
    "sg:city":"Jasper",
    "sg:classifiers":[
        {
            "category":"Food & Beverages",
            "subcategory":"Groceries & Convenience Stores",
            "type":"Retail Goods"
        }
    ],
    "sg:phone":"+1 205 295 2285",
    "sg:postcode":"35503",
    "sg:province":"AL",
    "wof:name":"Nauvoo Corner Stop",
    "wof:placetype":"venue"
},
  "geometry": {"coordinates":[-87.37145700000001,33.890107],"type":"Point"}
}