{
  "type": "Feature",
  "properties": {
    "iso:country":"US",
    "sg:address":"501 River Falls St",
    "sg:city":"Andalusia",
    "sg:classifiers":[
        {
            "category":"Autos & Motor Vehicles",
            "subcategory":"Auto Supplies",
            "type":"Retail Goods"
        }
    ],
    "sg:phone":"+1 334 222 1438",
    "sg:postcode":"36420",
    "sg:province":"AL",
    "sg:tags":[
        "tire"
    ],
    "wof:name":"Radford's Tire Ctr",
    "wof:placetype":"venue"
},
  "geometry": {"coordinates":[-86.491098,31.313012],"type":"Point"}
}