{
  "type": "Feature",
  "properties": {
    "addr:full":"676 Dean Cir Tallassee AL 36078",
    "addr:housenumber":"676",
    "addr:postcode":"36078",
    "addr:street":"Dean Cir",
    "iso:country":"US",
    "sg:address":"676 Dean Cir",
    "sg:city":"Tallassee",
    "sg:classifiers":[
        {
            "category":"Retail",
            "subcategory":"Repair Shop",
            "type":"Services"
        }
    ],
    "sg:phone":"+1 334 283 6759",
    "sg:postcode":"36078",
    "sg:province":"AL",
    "sg:tags":[
        "upholsterer"
    ],
    "wof:name":"Coach Kraft Upholstery",
    "wof:placetype":"venue"
},
  "geometry": {"coordinates":[-85.918142,32.621071],"type":"Point"}
}