{
  "type": "Feature",
  "properties": {
    "iso:country":"US",
    "sg:address":"210 Camp Ground Rd",
    "sg:city":"Brownsboro",
    "sg:classifiers":[
        {
            "category":"Building & Trades",
            "subcategory":"Landscaping Services",
            "type":"Services"
        }
    ],
    "sg:phone":"+1 256 518 9836",
    "sg:postcode":"35741",
    "sg:province":"AL",
    "sg:tags":[
        "landscape",
        "contractor"
    ],
    "wof:name":"Classic Landscapes Inc",
    "wof:placetype":"venue"
},
  "geometry": {"coordinates":[-86.500078,34.682128],"type":"Point"}
}