{
  "type": "Feature",
  "properties": {
    "iso:country":"US",
    "sg:address":"1012 23rd St",
    "sg:city":"Phenix City",
    "sg:classifiers":[
        {
            "category":"Building & Trades",
            "subcategory":"Construction",
            "type":"Services"
        }
    ],
    "sg:phone":"+1 334 297 6363",
    "sg:postcode":"36867",
    "sg:province":"AL",
    "sg:tags":[
        "house"
    ],
    "wof:name":"Camelot Construction LLC",
    "wof:placetype":"venue"
},
  "geometry": {"coordinates":[-85.007033,32.482668],"type":"Point"}
}