{
  "type": "Feature",
  "properties": {
    "iso:country":"US",
    "sg:address":"115 US Hwy 72 E",
    "sg:city":"Athens",
    "sg:classifiers":[
        {
            "category":"Home & Garden",
            "subcategory":"Carpets & Floor Coverings",
            "type":"Retail Goods"
        }
    ],
    "sg:phone":"+1 256 232 5172",
    "sg:postcode":"35611",
    "sg:province":"AL",
    "wof:name":"Carpet Shop",
    "wof:placetype":"venue"
},
  "geometry": {"coordinates":[-86.968981,34.789886],"type":"Point"}
}