{
  "type": "Feature",
  "properties": {
    "addr:full":"4141 Pleasant Valley Rd Jacksonville AL 36265",
    "addr:housenumber":"4141",
    "addr:postcode":"36265",
    "addr:street":"Pleasant Valley Rd",
    "iso:country":"US",
    "sg:address":"4141 Pleasant Valley Rd",
    "sg:city":"Jacksonville",
    "sg:classifiers":[
        {
            "category":"Education",
            "subcategory":"School",
            "type":"Public Place"
        }
    ],
    "sg:phone":"+1 256 741 6700",
    "sg:postcode":"36265",
    "sg:province":"AL",
    "wof:name":"Pleasant Valley High School",
    "wof:placetype":"venue"
},
  "geometry": {"coordinates":[-85.81481700000001,33.885352],"type":"Point"}
}