{
  "type": "Feature",
  "properties": {
    "addr:full":"141 Gateway Plz Greenville AL 36037",
    "addr:housenumber":"141",
    "addr:postcode":"36037",
    "addr:street":"Gateway Plz",
    "iso:country":"US",
    "sg:address":"141 Gateway Plz",
    "sg:city":"Greenville",
    "sg:classifiers":[
        {
            "category":"Shopping",
            "type":"Retail Goods"
        }
    ],
    "sg:phone":"+1 334 383 9419",
    "sg:postcode":"36037",
    "sg:province":"AL",
    "sg:tags":[
        "telephone",
        "cellular"
    ],
    "wof:name":"Unicel",
    "wof:placetype":"venue"
},
  "geometry": {"coordinates":[-86.636599,31.850049],"type":"Point"}
}