{
  "type": "Feature",
  "properties": {
    "iso:country":"US",
    "sg:address":"529 19th St",
    "sg:city":"Tuscaloosa",
    "sg:classifiers":[
        {
            "category":"Real Estate",
            "subcategory":"Real Estate Operator",
            "type":"Services"
        }
    ],
    "sg:phone":"+1 205 752 3232",
    "sg:postcode":"35401",
    "sg:province":"AL",
    "sg:tags":[
        "apartment"
    ],
    "wof:name":"A Stones Throw Apartments",
    "wof:placetype":"venue"
},
  "geometry": {"coordinates":[-87.544366,33.194555],"type":"Point"}
}