{
  "type": "Feature",
  "properties": {
    "iso:country":"US",
    "sg:address":"3105 Drake Ave SW",
    "sg:city":"Huntsville",
    "sg:classifiers":[
        {
            "category":"Food & Beverages",
            "subcategory":"Groceries & Convenience Stores",
            "type":"Retail Goods"
        }
    ],
    "sg:phone":"+1 256 881 1400",
    "sg:postcode":"35805",
    "sg:province":"AL",
    "wof:name":"Corner Store The",
    "wof:placetype":"venue"
},
  "geometry": {"coordinates":[-86.607432,34.69804],"type":"Point"}
}