{
  "type": "Feature",
  "properties": {
    "iso:country":"US",
    "sg:address":"717 N Park Ave",
    "sg:city":"Dothan",
    "sg:classifiers":[
        {
            "category":"Building & Trades",
            "subcategory":"Construction",
            "type":"Services"
        }
    ],
    "sg:phone":"+1 334 702 0370",
    "sg:postcode":"36303",
    "sg:province":"AL",
    "sg:tags":[
        "hanging",
        "contractor"
    ],
    "wof:name":"McNemar S Painting Wc",
    "wof:placetype":"venue"
},
  "geometry": {"coordinates":[-85.409065,31.2353],"type":"Point"}
}