{
  "type": "Feature",
  "properties": {
    "iso:country":"US",
    "sg:address":"120 Holly Oak Ln",
    "sg:city":"Huntsville",
    "sg:classifiers":[
        {
            "category":"Manufacturing",
            "subcategory":"Metals",
            "type":"Manufacturing & Wholesale Goods"
        }
    ],
    "sg:phone":"+1 256 858 6541",
    "sg:postcode":"35811",
    "sg:province":"AL",
    "sg:tags":[
        "ornamental",
        "work",
        "bronze"
    ],
    "wof:name":"Impressions Of Life",
    "wof:placetype":"venue"
},
  "geometry": {"coordinates":[-86.530473,34.816876],"type":"Point"}
}