{
  "type": "Feature",
  "properties": {
    "iso:country":"US",
    "sg:address":"1713 Dauphine Dr",
    "sg:city":"Tuscaloosa",
    "sg:classifiers":[
        {
            "category":"Building & Trades",
            "subcategory":"Plumbing",
            "type":"Services"
        }
    ],
    "sg:phone":"+1 205 366 3585",
    "sg:postcode":"35406",
    "sg:province":"AL",
    "sg:tags":[
        "mechanical",
        "contractor"
    ],
    "wof:name":"Combustion Technologies",
    "wof:placetype":"venue"
},
  "geometry": {"coordinates":[-87.55903,33.224846],"type":"Point"}
}