{
  "type": "Feature",
  "properties": {
    "addr:full":"406 5th St N Oneonta AL 35121",
    "addr:housenumber":"406",
    "addr:postcode":"35121",
    "addr:street":"5Th St N",
    "iso:country":"US",
    "sg:address":"406 5th St N",
    "sg:city":"Oneonta",
    "sg:classifiers":[
        {
            "category":"Utilities",
            "subcategory":"Mobile Phone",
            "type":"Services"
        }
    ],
    "sg:phone":"+1 205 274 2900",
    "sg:postcode":"35121",
    "sg:province":"AL",
    "sg:tags":[
        "telephone",
        "cellular"
    ],
    "wof:name":"Wireless Digital LLC",
    "wof:placetype":"venue"
},
  "geometry": {"coordinates":[-86.474548,33.950211],"type":"Point"}
}