{
  "type": "Feature",
  "properties": {
    "addr:full":"103 Woodland Trl Madison AL 35758",
    "addr:housenumber":"103",
    "addr:postcode":"35758",
    "addr:street":"Woodland Trl",
    "iso:country":"US",
    "sg:address":"103 Woodland Trl",
    "sg:city":"Madison",
    "sg:classifiers":[
        {
            "category":"Professional",
            "type":"Services"
        }
    ],
    "sg:phone":"+1 256 830 1337",
    "sg:postcode":"35758",
    "sg:province":"AL",
    "wof:name":"Fancy That",
    "wof:placetype":"venue"
},
  "geometry": {"coordinates":[-86.732981,34.740302],"type":"Point"}
}