{
  "type": "Feature",
  "properties": {
    "addr:full":"1800 John Rogers Dr Birmingham AL 35210",
    "addr:housenumber":"1800",
    "addr:postcode":"35210",
    "addr:street":"John Rogers Dr",
    "iso:country":"US",
    "sg:address":"1800 John Rogers Dr",
    "sg:city":"Birmingham",
    "sg:classifiers":[
        {
            "category":"Social Services",
            "subcategory":"Child Care",
            "type":"Services"
        }
    ],
    "sg:phone":"+1 205 838 1033",
    "sg:postcode":"35210",
    "sg:province":"AL",
    "sg:tags":[
        "day"
    ],
    "sg:website":"www.guidinglight.org",
    "wof:name":"Guiding Light Church",
    "wof:placetype":"venue"
},
  "geometry": {"coordinates":[-86.66871399999999,33.56435],"type":"Point"}
}