{
  "type": "Feature",
  "properties": {
    "addr:full":"6501 Interstate Ln Cottondale AL 35453",
    "addr:housenumber":"6501",
    "addr:postcode":"35453",
    "addr:street":"Interstate Ln",
    "iso:country":"US",
    "sg:address":"6501 Interstate Ln",
    "sg:city":"Cottondale",
    "sg:classifiers":[
        {
            "category":"Restaurant",
            "type":"Food & Drink"
        }
    ],
    "sg:menulink":"http://www.allmenus.com/al/tuscaloosa/190150-mcdonalds/menu/",
    "sg:postcode":"35453",
    "sg:province":"AL",
    "sg:tags":[
        "burger",
        "american"
    ],
    "wof:name":"McDonald's",
    "wof:placetype":"venue"
},
  "geometry": {"coordinates":[-87.44798400000001,33.176148],"type":"Point"}
}