{
  "type": "Feature",
  "properties": {
    "addr:full":"24820 Canal Rd Orange Beach AL 36561",
    "addr:housenumber":"24820",
    "addr:postcode":"36561",
    "addr:street":"Canal Rd",
    "iso:country":"US",
    "sg:address":"24820 Canal Rd",
    "sg:city":"Orange Beach",
    "sg:classifiers":[
        {
            "category":"Professional",
            "subcategory":"Business Services",
            "type":"Services"
        }
    ],
    "sg:phone":"+1 251 989 9033",
    "sg:postcode":"36561",
    "sg:province":"AL",
    "sg:tags":[
        "interior",
        "consultant",
        "design",
        "decorator"
    ],
    "wof:name":"Merrill Miller's Interiors",
    "wof:placetype":"venue"
},
  "geometry": {"coordinates":[-87.61953,30.290195],"type":"Point"}
}