{
  "type": "Feature",
  "properties": {
    "iso:country":"US",
    "sg:address":"585 Valley View Rd",
    "sg:city":"Pelham",
    "sg:classifiers":[
        {
            "category":"Professional",
            "subcategory":"Art Services",
            "type":"Services"
        }
    ],
    "sg:phone":"+1 205 987 1771",
    "sg:postcode":"35124",
    "sg:province":"AL",
    "sg:tags":[
        "photographer"
    ],
    "wof:name":"Snow  Chuck Photography Inc",
    "wof:placetype":"venue"
},
  "geometry": {"coordinates":[-86.749426,33.360085],"type":"Point"}
}