{
  "type": "Feature",
  "properties": {
    "addr:full":"416 S Wintzell Ave Bayou La Batre AL 36509",
    "addr:housenumber":"416",
    "addr:postcode":"36509",
    "addr:street":"S Wintzell Ave Bayou La",
    "iso:country":"US",
    "sg:address":"416 S Wintzell Ave",
    "sg:city":"Bayou La Batre",
    "sg:classifiers":[
        {
            "category":"Food & Beverages",
            "subcategory":"Groceries & Convenience Stores",
            "type":"Retail Goods"
        }
    ],
    "sg:phone":"+1 251 824 2213",
    "sg:postcode":"36509",
    "sg:province":"AL",
    "sg:tags":[
        "grocer"
    ],
    "wof:name":"Greer's",
    "wof:placetype":"venue"
},
  "geometry": {"coordinates":[-88.24839900000001,30.402103],"type":"Point"}
}