{
  "type": "Feature",
  "properties": {
    "iso:country":"US",
    "sg:address":"5951 Greenwood Pkwy",
    "sg:city":"Bessemer",
    "sg:classifiers":[
        {
            "category":"Shopping",
            "type":"Retail Goods"
        }
    ],
    "sg:phone":"+1 205 428 1478",
    "sg:postcode":"35022",
    "sg:province":"AL",
    "sg:tags":[
        "cosmetic",
        "perfume"
    ],
    "wof:name":"Gulf States Beauty Supply Co",
    "wof:placetype":"venue"
},
  "geometry": {"coordinates":[-86.92237,33.343114],"type":"Point"}
}