{
  "type": "Feature",
  "properties": {
    "iso:country":"US",
    "sg:address":"3625 9th Ave N",
    "sg:city":"Birmingham",
    "sg:classifiers":[
        {
            "category":"Organizations",
            "subcategory":"Labor Organization",
            "type":"Services"
        }
    ],
    "sg:phone":"+1 205 595 5295",
    "sg:postcode":"35222",
    "sg:province":"AL",
    "wof:name":"Birmingham Plumbers Local 91",
    "wof:placetype":"venue"
},
  "geometry": {"coordinates":[-86.785398,33.535331],"type":"Point"}
}