{
  "type": "Feature",
  "properties": {
    "addr:full":"2660 10th Ave S Birmingham AL 35205",
    "addr:housenumber":"2660",
    "addr:postcode":"35205",
    "addr:street":"10Th Ave S",
    "iso:country":"US",
    "sg:address":"2660 10th Ave S",
    "sg:city":"Birmingham",
    "sg:classifiers":[
        {
            "category":"Health Services",
            "subcategory":"Doctor",
            "type":"Services"
        }
    ],
    "sg:phone":"+1 205 313 2650",
    "sg:postcode":"35205",
    "sg:province":"AL",
    "sg:tags":[
        "medical"
    ],
    "wof:name":"Endocrinolgy & Inter Med Assoc",
    "wof:placetype":"venue"
},
  "geometry": {"coordinates":[-86.788664,33.506266],"type":"Point"}
}