{
  "type": "Feature",
  "properties": {
    "iso:country":"US",
    "sg:address":"501 2nd Ave N",
    "sg:city":"Clanton",
    "sg:classifiers":[
        {
            "category":"Government",
            "subcategory":"Office",
            "type":"Public Place"
        }
    ],
    "sg:phone":"+1 205 755 3820",
    "sg:postcode":"35045",
    "sg:province":"AL",
    "wof:name":"Chilton County Registrars",
    "wof:placetype":"venue"
},
  "geometry": {"coordinates":[-86.628993,32.840058],"type":"Point"}
}