{
  "type": "Feature",
  "properties": {
    "iso:country":"US",
    "sg:address":"103 Colonial Cir",
    "sg:city":"Alabaster",
    "sg:classifiers":[
        {
            "category":"Professional",
            "subcategory":"Art Services",
            "type":"Services"
        }
    ],
    "sg:phone":"+1 205 685 1545",
    "sg:postcode":"35007",
    "sg:province":"AL",
    "sg:tags":[
        "graphic",
        "designer"
    ],
    "wof:name":"Ad South Graphic Designers",
    "wof:placetype":"venue"
},
  "geometry": {"coordinates":[-86.836617,33.259507],"type":"Point"}
}