{
  "type": "Feature",
  "properties": {
    "iso:country":"US",
    "sg:address":"155 Vulcan Rd",
    "sg:city":"Homewood",
    "sg:classifiers":[
        {
            "category":"Travel",
            "subcategory":"Hotels & Motels",
            "type":"Entertainment"
        }
    ],
    "sg:phone":"+1 205 945 9600",
    "sg:postcode":"35209",
    "sg:province":"AL",
    "wof:name":"Dada Hotel",
    "wof:placetype":"venue"
},
  "geometry": {"coordinates":[-86.826835,33.464804],"type":"Point"}
}