{
  "type": "Feature",
  "properties": {
    "iso:country":"US",
    "sg:address":"3246 US Hwy 80",
    "sg:city":"Selma",
    "sg:classifiers":[
        {
            "category":"Organizations",
            "subcategory":"Religious Organization",
            "type":"Services"
        }
    ],
    "sg:phone":"+1 334 872 3418",
    "sg:postcode":"36701",
    "sg:province":"AL",
    "wof:name":"Joy Baptist Temple",
    "wof:placetype":"venue"
},
  "geometry": {"coordinates":[-86.99680499999999,32.366529],"type":"Point"}
}