{
  "type": "Feature",
  "properties": {
    "addr:full":"520 15th St Tuscaloosa AL 35401",
    "addr:housenumber":"520",
    "addr:postcode":"35401",
    "addr:street":"15Th St",
    "iso:country":"US",
    "sg:address":"520 15th St",
    "sg:city":"Tuscaloosa",
    "sg:classifiers":[
        {
            "category":"Wholesale",
            "subcategory":"Sporting Goods",
            "type":"Manufacturing & Wholesale Goods"
        }
    ],
    "sg:phone":"+1 205 758 2505",
    "sg:postcode":"35401",
    "sg:province":"AL",
    "sg:tags":[
        "apparel",
        "bowling",
        "accessory"
    ],
    "wof:name":"Mc Corveys Pro Shop",
    "wof:placetype":"venue"
},
  "geometry": {"coordinates":[-87.541642,33.198823],"type":"Point"}
}