{
  "type": "Feature",
  "properties": {
    "iso:country":"US",
    "sg:address":"2630 Co Rd 1371",
    "sg:city":"Vinemont",
    "sg:classifiers":[
        {
            "category":"Retail",
            "subcategory":"Laundry & Dry Cleaning",
            "type":"Services"
        },
        {
            "category":"Shopping",
            "subcategory":"Clothing, Apparel, & Fashions",
            "type":"Retail Goods"
        }
    ],
    "sg:phone":"+1 256 736 5914",
    "sg:postcode":"35179",
    "sg:province":"AL",
    "sg:tags":[
        "alteration"
    ],
    "wof:name":"Kathy's Alterations",
    "wof:placetype":"venue"
},
  "geometry": {"coordinates":[-86.863868,34.287643],"type":"Point"}
}