{
  "type": "Feature",
  "properties": {
    "addr:full":"1145 3rd Ave W Birmingham AL 35204",
    "addr:housenumber":"1145",
    "addr:postcode":"35204",
    "addr:street":"3Rd Ave W",
    "iso:country":"US",
    "sg:address":"1145 3rd Ave W",
    "sg:city":"Birmingham",
    "sg:classifiers":[
        {
            "category":"Restaurant",
            "type":"Food & Drink"
        }
    ],
    "sg:menulink":"http://www.allmenus.com/al/birmingham/13099-churchs-chicken/menu/",
    "sg:phone":"+1 205 780 4740",
    "sg:postcode":"35204",
    "sg:province":"AL",
    "sg:tags":[
        "chicken",
        "wing"
    ],
    "wof:name":"Church's Chicken",
    "wof:placetype":"venue"
},
  "geometry": {"coordinates":[-86.85577499999999,33.505183],"type":"Point"}
}