{
  "type": "Feature",
  "properties": {
    "addr:full":"1753 Jefferson Ave SW Birmingham AL 35211",
    "addr:housenumber":"1753",
    "addr:postcode":"35211",
    "addr:street":"Jefferson Ave Sw",
    "iso:country":"US",
    "sg:address":"1753 Jefferson Ave SW",
    "sg:city":"Birmingham",
    "sg:classifiers":[
        {
            "category":"Professional",
            "subcategory":"Accounting & Tax Preparation",
            "type":"Services"
        }
    ],
    "sg:phone":"+1 205 923 3622",
    "sg:postcode":"35211",
    "sg:province":"AL",
    "wof:name":"H & R Block",
    "wof:placetype":"venue"
},
  "geometry": {"coordinates":[-86.86382399999999,33.479358],"type":"Point"}
}