{
  "type": "Feature",
  "properties": {
    "addr:full":"2209 36th Ave N Birmingham AL 35207",
    "addr:housenumber":"2209",
    "addr:postcode":"35207",
    "addr:street":"36Th Ave N",
    "iso:country":"US",
    "sg:address":"2209 36th Ave N",
    "sg:city":"Birmingham",
    "sg:classifiers":[
        {
            "category":"Shopping",
            "type":"Retail Goods"
        }
    ],
    "sg:phone":"+1 205 251 8875",
    "sg:postcode":"35207",
    "sg:province":"AL",
    "sg:tags":[
        "merchandise"
    ],
    "wof:name":"A&B Detail Shop",
    "wof:placetype":"venue"
},
  "geometry": {"coordinates":[-86.82605599999999,33.555937],"type":"Point"}
}