{
  "type": "Feature",
  "properties": {
    "iso:country":"US",
    "sg:address":"320 Paul W Bryant Dr",
    "sg:city":"Tuscaloosa",
    "sg:classifiers":[
        {
            "category":"Travel",
            "subcategory":"Hotels & Motels",
            "type":"Entertainment"
        }
    ],
    "sg:phone":"+1 205 752 3200",
    "sg:postcode":"35401",
    "sg:province":"AL",
    "sg:tags":[
        "operation",
        "eating",
        "drinking"
    ],
    "wof:name":"Four Points Hotel",
    "wof:placetype":"venue"
},
  "geometry": {"coordinates":[-87.542075,33.20603],"type":"Point"}
}