{
  "type": "Feature",
  "properties": {
    "addr:full":"4821 Moffett Rd Mobile AL 36618",
    "addr:housenumber":"4821",
    "addr:postcode":"36618",
    "addr:street":"Moffett Rd",
    "iso:country":"US",
    "sg:address":"4821 Moffett Rd",
    "sg:city":"Mobile",
    "sg:classifiers":[
        {
            "category":"Shopping",
            "subcategory":"Discount & Variety Stores",
            "type":"Retail Goods"
        },
        {
            "category":"Shopping",
            "subcategory":"Department Store",
            "type":"Retail Goods"
        }
    ],
    "sg:phone":"+1 251 344 6302",
    "sg:postcode":"36618",
    "sg:province":"AL",
    "sg:tags":[
        "shop"
    ],
    "wof:name":"Dollar General",
    "wof:placetype":"venue"
},
  "geometry": {"coordinates":[-88.154008,30.720022],"type":"Point"}
}