{
  "type": "Feature",
  "properties": {
    "iso:country":"US",
    "sg:address":"417 19th St N",
    "sg:city":"Birmingham",
    "sg:classifiers":[
        {
            "category":"Shopping",
            "subcategory":"Used Merchandise",
            "type":"Retail Goods"
        }
    ],
    "sg:phone":"+1 205 788 5500",
    "sg:postcode":"35203",
    "sg:province":"AL",
    "wof:name":"A JS Bargain Shop",
    "wof:placetype":"venue"
},
  "geometry": {"coordinates":[-86.809127,33.51686],"type":"Point"}
}