{
  "type": "Feature",
  "properties": {
    "addr:full":"137 E Main St Albertville AL 35950",
    "addr:housenumber":"137",
    "addr:postcode":"35950",
    "addr:street":"E Main St",
    "iso:country":"US",
    "sg:address":"137 E Main St",
    "sg:city":"Albertville",
    "sg:classifiers":[
        {
            "category":"Wholesale",
            "subcategory":"Durable Goods & Equipment",
            "type":"Manufacturing & Wholesale Goods"
        }
    ],
    "sg:phone":"+1 256 878 1765",
    "sg:postcode":"35950",
    "sg:province":"AL",
    "sg:tags":[
        "exporter"
    ],
    "wof:name":"Centro Ayuda Al Immigrante",
    "wof:placetype":"venue"
},
  "geometry": {"coordinates":[-86.208298,34.267727],"type":"Point"}
}