{
  "type": "Feature",
  "properties": {
    "iso:country":"US",
    "sg:address":"13874 Roberts Rd",
    "sg:city":"Chunchula",
    "sg:classifiers":[
        {
            "category":"Building & Trades",
            "subcategory":"Construction",
            "type":"Services"
        }
    ],
    "sg:phone":"+1 251 679 1240",
    "sg:postcode":"36521",
    "sg:province":"AL",
    "sg:tags":[
        "dry wall",
        "contractor"
    ],
    "wof:name":"Baetje Drywall",
    "wof:placetype":"venue"
},
  "geometry": {"coordinates":[-88.129247,30.979318],"type":"Point"}
}