{
  "type": "Feature",
  "properties": {
    "addr:full":"135 Catoma St Montgomery AL 36104",
    "addr:housenumber":"135",
    "addr:postcode":"36104",
    "addr:street":"Catoma St",
    "iso:country":"US",
    "sg:address":"135 Catoma St",
    "sg:city":"Montgomery",
    "sg:classifiers":[
        {
            "category":"Government",
            "subcategory":"Post Office",
            "type":"Public Place"
        }
    ],
    "sg:phone":"+1 334 000 1111",
    "sg:postcode":"36104",
    "sg:province":"AL",
    "wof:name":"US Post Office",
    "wof:placetype":"venue"
},
  "geometry": {"coordinates":[-86.311194,32.373971],"type":"Point"}
}