{
  "type": "Feature",
  "properties": {
    "iso:country":"US",
    "sg:address":"6662 State Rte 75",
    "sg:city":"Pinson",
    "sg:classifiers":[
        {
            "category":"Food & Beverages",
            "subcategory":"Groceries & Convenience Stores",
            "type":"Retail Goods"
        }
    ],
    "sg:phone":"+1 205 681 7440",
    "sg:postcode":"35126",
    "sg:province":"AL",
    "wof:name":"Food Giant 6",
    "wof:placetype":"venue"
},
  "geometry": {"coordinates":[-86.679766,33.697344],"type":"Point"}
}