{
  "type": "Feature",
  "properties": {
    "iso:country":"US",
    "sg:address":"42171 Portobello Rd",
    "sg:city":"Birmingham",
    "sg:classifiers":[
        {
            "category":"Professional",
            "subcategory":"Employment Agencies",
            "type":"Services"
        }
    ],
    "sg:phone":"+1 205 981 2348",
    "sg:postcode":"35242",
    "sg:province":"AL",
    "wof:name":"Alabama Medical Careers",
    "wof:placetype":"venue"
},
  "geometry": {"coordinates":[-86.692528,33.4326],"type":"Point"}
}