{
  "type": "Feature",
  "properties": {
    "iso:country":"US",
    "sg:address":"1106 Kingsbury Ave",
    "sg:city":"Birmingham",
    "sg:classifiers":[
        {
            "category":"Retail",
            "subcategory":"Animal Services",
            "type":"Services"
        }
    ],
    "sg:phone":"+1 205 879 7484",
    "sg:postcode":"35213",
    "sg:province":"AL",
    "wof:name":"4 Legged Care Pet Service",
    "wof:placetype":"venue"
},
  "geometry": {"coordinates":[-86.736073,33.512406],"type":"Point"}
}