{
  "type": "Feature",
  "properties": {
    "iso:country":"US",
    "sg:address":"23072 State Rte 75",
    "sg:city":"Sylvania",
    "sg:classifiers":[
        {
            "category":"Restaurant",
            "type":"Food & Drink"
        }
    ],
    "sg:phone":"+1 256 638 9200",
    "sg:postcode":"35988",
    "sg:province":"AL",
    "wof:name":"Quail's Nest Restaurant",
    "wof:placetype":"venue"
},
  "geometry": {"coordinates":[-85.79692,34.565342],"type":"Point"}
}