{
  "type": "Feature",
  "properties": {
    "iso:country":"US",
    "sg:address":"518 Daleville Ave",
    "sg:city":"Daleville",
    "sg:classifiers":[
        {
            "category":"Shopping",
            "type":"Retail Goods"
        }
    ],
    "sg:phone":"+1 334 598 4620",
    "sg:postcode":"36322",
    "sg:province":"AL",
    "sg:tags":[
        "art",
        "gallery",
        "dealer"
    ],
    "wof:name":"R & R Gallaries",
    "wof:placetype":"venue"
},
  "geometry": {"coordinates":[-85.71056299999999,31.320978],"type":"Point"}
}