{
  "type": "Feature",
  "properties": {
    "iso:country":"US",
    "sg:address":"8903 State Rte 20",
    "sg:city":"Florence",
    "sg:classifiers":[
        {
            "category":"Building & Trades",
            "subcategory":"Equipment Rental",
            "type":"Services"
        }
    ],
    "sg:phone":"+1 256 767 7232",
    "sg:postcode":"35633",
    "sg:province":"AL",
    "sg:tags":[
        "yard"
    ],
    "wof:name":"U-Haul Co",
    "wof:placetype":"venue"
},
  "geometry": {"coordinates":[-87.77233699999999,34.870893],"type":"Point"}
}