{
  "type": "Feature",
  "properties": {
    "addr:full":"5963 Idlemoore Ct Theodore AL 36582",
    "addr:housenumber":"5963",
    "addr:postcode":"36582",
    "addr:street":"Idlemoore Ct",
    "iso:country":"US",
    "sg:address":"5963 Idlemoore Ct",
    "sg:city":"Theodore",
    "sg:classifiers":[
        {
            "category":"Professional",
            "subcategory":"Business Services",
            "type":"Services"
        }
    ],
    "sg:phone":"+1 251 432 7446",
    "sg:postcode":"36582",
    "sg:province":"AL",
    "sg:tags":[
        "painter",
        "sign"
    ],
    "wof:name":"Suncoast Signs & Graphics",
    "wof:placetype":"venue"
},
  "geometry": {"coordinates":[-88.21386,30.565323],"type":"Point"}
}