{
  "type": "Feature",
  "properties": {
    "iso:country":"US",
    "sg:address":"107 Kirkland St",
    "sg:city":"Abbeville",
    "sg:classifiers":[
        {
            "category":"Food & Beverages",
            "subcategory":"Bakery",
            "type":"Retail Goods"
        }
    ],
    "sg:phone":"+1 334 585 3239",
    "sg:postcode":"36310",
    "sg:province":"AL",
    "sg:tags":[
        "baker"
    ],
    "wof:name":"D & D Donut & Bake Shop",
    "wof:placetype":"venue"
},
  "geometry": {"coordinates":[-85.302178,31.524088],"type":"Point"}
}