{
  "type": "Feature",
  "properties": {
    "iso:country":"US",
    "sg:address":"4017 Sewall Dr SW",
    "sg:city":"Huntsville",
    "sg:classifiers":[
        {
            "category":"Professional",
            "type":"Services"
        }
    ],
    "sg:phone":"+1 256 882 3709",
    "sg:postcode":"35805",
    "sg:province":"AL",
    "wof:name":"Wesley Hawkins",
    "wof:placetype":"venue"
},
  "geometry": {"coordinates":[-86.60656,34.693147],"type":"Point"}
}