{
  "type": "Feature",
  "properties": {
    "iso:country":"US",
    "sg:address":"7863 Schillinger Park W",
    "sg:city":"Mobile",
    "sg:classifiers":[
        {
            "category":"Professional",
            "subcategory":"Business Services",
            "type":"Services"
        },
        {
            "category":"Wholesale",
            "subcategory":"Electrical",
            "type":"Manufacturing & Wholesale Goods"
        }
    ],
    "sg:phone":"+1 251 607 0426",
    "sg:postcode":"36608",
    "sg:province":"AL",
    "sg:tags":[
        "television"
    ],
    "wof:name":"Gesotec Automation LLC",
    "wof:placetype":"venue"
},
  "geometry": {"coordinates":[-88.226036,30.685109],"type":"Point"}
}