{
  "type": "Feature",
  "properties": {
    "addr:full":"2728 Lakeland Trl Birmingham AL 35243",
    "addr:housenumber":"2728",
    "addr:postcode":"35243",
    "addr:street":"Lakeland Trl",
    "iso:country":"US",
    "sg:address":"2728 Lakeland Trl",
    "sg:city":"Birmingham",
    "sg:classifiers":[
        {
            "category":"Retail",
            "subcategory":"Car Wash",
            "type":"Services"
        }
    ],
    "sg:phone":"+1 205 967 3657",
    "sg:postcode":"35243",
    "sg:province":"AL",
    "sg:tags":[
        "carwash"
    ],
    "wof:name":"Supreme Car Wash LLC",
    "wof:placetype":"venue"
},
  "geometry": {"coordinates":[-86.7403,33.418523],"type":"Point"}
}