{
  "type": "Feature",
  "properties": {
    "iso:country":"US",
    "sg:address":"2270 Pleasant Springs Dr",
    "sg:city":"Tuskegee",
    "sg:classifiers":[
        {
            "category":"Professional",
            "subcategory":"Lawyer & Legal Services",
            "type":"Services"
        }
    ],
    "sg:phone":"+1 334 727 6513",
    "sg:postcode":"36083",
    "sg:province":"AL",
    "sg:tags":[
        "attorney"
    ],
    "wof:name":"Linda W Henderson",
    "wof:placetype":"venue"
},
  "geometry": {"coordinates":[-85.756893,32.421828],"type":"Point"}
}