{
  "type": "Feature",
  "properties": {
    "addr:full":"7321 52nd St Tuscaloosa AL 35401",
    "addr:housenumber":"7321",
    "addr:postcode":"35401",
    "addr:street":"52Nd St",
    "iso:country":"US",
    "sg:address":"7321 52nd St",
    "sg:city":"Tuscaloosa",
    "sg:classifiers":[
        {
            "category":"Retail",
            "subcategory":"Repair Shop",
            "type":"Services"
        }
    ],
    "sg:phone":"+1 205 345 7085",
    "sg:postcode":"35401",
    "sg:province":"AL",
    "wof:name":"White Septic",
    "wof:placetype":"venue"
},
  "geometry": {"coordinates":[-87.63521,33.16718],"type":"Point"}
}