{
  "type": "Feature",
  "properties": {
    "addr:full":"1015 Snow St Oxford AL 36203",
    "addr:housenumber":"1015",
    "addr:postcode":"36203",
    "addr:street":"Snow St",
    "iso:country":"US",
    "sg:address":"1015 Snow St",
    "sg:city":"Oxford",
    "sg:classifiers":[
        {
            "category":"Shopping",
            "subcategory":"Clothing, Apparel, & Fashions",
            "type":"Retail Goods"
        }
    ],
    "sg:phone":"+1 256 835 1090",
    "sg:postcode":"36203",
    "sg:province":"AL",
    "sg:tags":[
        "shop",
        "bridal",
        "ware",
        "formal"
    ],
    "wof:name":"Special Occassions",
    "wof:placetype":"venue"
},
  "geometry": {"coordinates":[-85.816868,33.614957],"type":"Point"}
}