{
  "type": "Feature",
  "properties": {
    "iso:country":"US",
    "sg:address":"1650 Co Rd 147",
    "sg:city":"Town Creek",
    "sg:classifiers":[
        {
            "category":"Retail",
            "subcategory":"Repair Shop",
            "type":"Services"
        }
    ],
    "sg:phone":"+1 256 685 2892",
    "sg:postcode":"35672",
    "sg:province":"AL",
    "sg:tags":[
        "supply"
    ],
    "wof:name":"Nichols Small Engines",
    "wof:placetype":"venue"
},
  "geometry": {"coordinates":[-87.396242,34.585132],"type":"Point"}
}