{
  "type": "Feature",
  "properties": {
    "addr:full":"970 Oak St Mobile AL 36604",
    "addr:housenumber":"970",
    "addr:postcode":"36604",
    "addr:street":"Oak St",
    "iso:country":"US",
    "sg:address":"970 Oak St",
    "sg:city":"Mobile",
    "sg:classifiers":[
        {
            "category":"Building & Trades",
            "subcategory":"Plumbing",
            "type":"Services"
        }
    ],
    "sg:phone":"+1 251 432 3291",
    "sg:postcode":"36604",
    "sg:province":"AL",
    "sg:tags":[
        "contractor"
    ],
    "wof:name":"Reliable Plumbing Company",
    "wof:placetype":"venue"
},
  "geometry": {"coordinates":[-88.05946900000001,30.690037],"type":"Point"}
}