{
  "type": "Feature",
  "properties": {
    "addr:full":"44 Golden Pond Rd Alexander City AL 35010",
    "addr:housenumber":"44",
    "addr:postcode":"35010",
    "addr:street":"Golden Pond Rd",
    "iso:country":"US",
    "sg:address":"44 Golden Pond Rd",
    "sg:city":"Alexander City",
    "sg:classifiers":[
        {
            "category":"Farming",
            "subcategory":"Farm",
            "type":"Manufacturing & Wholesale Goods"
        }
    ],
    "sg:phone":"+1 256 234 7266",
    "sg:postcode":"35010",
    "sg:province":"AL",
    "sg:tags":[
        "crop",
        "general"
    ],
    "wof:name":"Rainwater James Edward Farm",
    "wof:placetype":"venue"
},
  "geometry": {"coordinates":[-86.006799,32.864148],"type":"Point"}
}