{
  "type": "Feature",
  "properties": {
    "iso:country":"US",
    "sg:address":"4320 Marthaler Ln",
    "sg:city":"Leighton",
    "sg:phone":"+1 256 446 8968",
    "sg:postcode":"35646",
    "sg:province":"AL",
    "sg:tags":[
        "farm",
        "crop",
        "cotton"
    ],
    "wof:name":"Underwood Inc",
    "wof:placetype":"venue"
},
  "geometry": {"coordinates":[-87.564784,34.735531],"type":"Point"}
}