{
  "type": "Feature",
  "properties": {
    "iso:country":"US",
    "sg:address":"6395 State Rte 19",
    "sg:city":"Vina",
    "sg:classifiers":[
        {
            "category":"Home & Garden",
            "subcategory":"Furniture",
            "type":"Retail Goods"
        }
    ],
    "sg:phone":"+1 256 356 8605",
    "sg:postcode":"35593",
    "sg:province":"AL",
    "sg:tags":[
        "cabinet"
    ],
    "wof:name":"Tiffan Door Co",
    "wof:placetype":"venue"
},
  "geometry": {"coordinates":[-88.062806,34.376869],"type":"Point"}
}