{
  "type": "Feature",
  "properties": {
    "addr:full":"1000 W Main St Dothan AL 36301",
    "addr:housenumber":"1000",
    "addr:postcode":"36301",
    "addr:street":"W Main St",
    "iso:country":"US",
    "sg:address":"1000 W Main St",
    "sg:city":"Dothan",
    "sg:classifiers":[
        {
            "category":"Cinema",
            "subcategory":"Movie Rental",
            "type":"Entertainment"
        }
    ],
    "sg:phone":"+1 334 794 7453",
    "sg:postcode":"36301",
    "sg:province":"AL",
    "sg:tags":[
        "leasing",
        "video",
        "disc",
        "tape"
    ],
    "wof:name":"Movie Galleries Outlet",
    "wof:placetype":"venue"
},
  "geometry": {"coordinates":[-85.404394,31.226194],"type":"Point"}
}