{
  "type": "Feature",
  "properties": {
    "iso:country":"US",
    "sg:address":"701 Owens St",
    "sg:city":"Mobile",
    "sg:classifiers":[
        {
            "category":"Health Services",
            "subcategory":"Health Practitioner",
            "type":"Services"
        }
    ],
    "sg:phone":"+1 251 457 6149",
    "sg:postcode":"36610",
    "sg:province":"AL",
    "sg:tags":[
        "nutritionist"
    ],
    "wof:name":"Mothers & Babies Nutrition",
    "wof:placetype":"venue"
},
  "geometry": {"coordinates":[-88.098751,30.725851],"type":"Point"}
}