{
  "type": "Feature",
  "properties": {
    "addr:full":"701 Owens St Mobile AL 36610",
    "addr:housenumber":"701",
    "addr:postcode":"36610",
    "addr:street":"Owens St",
    "iso:country":"US",
    "sg:address":"701 Owens St",
    "sg:city":"Mobile",
    "sg:classifiers":[
        {
            "category":"Health Services",
            "subcategory":"Health Practitioner",
            "type":"Services"
        }
    ],
    "sg:phone":"+1 251 457 6149",
    "sg:postcode":"36610",
    "sg:province":"AL",
    "sg:tags":[
        "nutritionist"
    ],
    "wof:name":"Mothers & Babies Nutrition",
    "wof:placetype":"venue"
},
  "geometry": {"coordinates":[-88.09875099999999,30.725851],"type":"Point"}
}