{
  "type": "Feature",
  "properties": {
    "iso:country":"US",
    "sg:address":"1620 2nd Ave SW",
    "sg:city":"Cullman",
    "sg:classifiers":[
        {
            "category":"Restaurant",
            "type":"Food & Drink"
        }
    ],
    "sg:phone":"+1 256 734 6958",
    "sg:postcode":"35055",
    "sg:province":"AL",
    "sg:tags":[
        "eating"
    ],
    "wof:name":"KFC",
    "wof:placetype":"venue"
},
  "geometry": {"coordinates":[-86.823644,34.139633],"type":"Point"}
}