{
  "type": "Feature",
  "properties": {
    "iso:country":"US",
    "sg:address":"8841 Helena Rd",
    "sg:city":"Pelham",
    "sg:classifiers":[
        {
            "category":"Professional",
            "subcategory":"Management & Consulting",
            "type":"Services"
        }
    ],
    "sg:phone":"+1 205 989 0007",
    "sg:postcode":"35124",
    "sg:province":"AL",
    "sg:tags":[
        "consultant",
        "educational"
    ],
    "wof:name":"College 123",
    "wof:placetype":"venue"
},
  "geometry": {"coordinates":[-86.80657600000001,33.339498],"type":"Point"}
}