{
  "type": "Feature",
  "properties": {
    "iso:country":"US",
    "sg:address":"108 Market St E",
    "sg:city":"Athens",
    "sg:classifiers":[
        {
            "category":"Shopping",
            "type":"Retail Goods"
        }
    ],
    "sg:phone":"+1 256 771 0400",
    "sg:postcode":"35611",
    "sg:province":"AL",
    "sg:tags":[
        "art",
        "gallery",
        "dealer"
    ],
    "wof:name":"Sassy's Fraz",
    "wof:placetype":"venue"
},
  "geometry": {"coordinates":[-86.969779,34.803179],"type":"Point"}
}