{
  "type": "Feature",
  "properties": {
    "iso:country":"US",
    "sg:address":"249 S 6th St",
    "sg:city":"Gadsden",
    "sg:classifiers":[
        {
            "category":"Health Services",
            "subcategory":"Optometrist",
            "type":"Services"
        }
    ],
    "sg:phone":"+1 256 546 4647",
    "sg:postcode":"35901",
    "sg:province":"AL",
    "sg:tags":[
        "optical",
        "good"
    ],
    "wof:name":"Hartzog G Delton Dr",
    "wof:placetype":"venue"
},
  "geometry": {"coordinates":[-86.00771400000001,34.012537],"type":"Point"}
}