{
  "type": "Feature",
  "properties": {
    "addr:full":"8850 Baptist Camp Rd Elberta AL 36530",
    "addr:housenumber":"8850",
    "addr:postcode":"36530",
    "addr:street":"Baptist Camp Rd",
    "iso:country":"US",
    "sg:address":"8850 Baptist Camp Rd",
    "sg:city":"Elberta",
    "sg:classifiers":[
        {
            "category":"Farming",
            "subcategory":"Livestock Farm",
            "type":"Manufacturing & Wholesale Goods"
        }
    ],
    "sg:phone":"+1 251 987 5426",
    "sg:postcode":"36530",
    "sg:province":"AL",
    "sg:tags":[
        "beef",
        "feedlot",
        "cattle"
    ],
    "wof:name":"Joe Good",
    "wof:placetype":"venue"
},
  "geometry": {"coordinates":[-87.591211,30.351998],"type":"Point"}
}