{
  "type": "Feature",
  "properties": {
    "iso:country":"US",
    "sg:address":"112 Main St W",
    "sg:city":"Rainsville",
    "sg:classifiers":[
        {
            "category":"Shopping",
            "subcategory":"Pharmacy",
            "type":"Retail Goods"
        }
    ],
    "sg:phone":"+1 256 638 6667",
    "sg:postcode":"35986",
    "sg:province":"AL",
    "wof:name":"Pharmacy Partners",
    "wof:placetype":"venue"
},
  "geometry": {"coordinates":[-85.848449,34.494688],"type":"Point"}
}