{
  "type": "Feature",
  "properties": {
    "addr:full":"110 S Bryant St Abbeville AL 36310",
    "addr:housenumber":"110",
    "addr:postcode":"36310",
    "addr:street":"S Bryant St",
    "iso:country":"US",
    "sg:address":"110 S Bryant St",
    "sg:city":"Abbeville",
    "sg:classifiers":[
        {
            "category":"Social Services",
            "subcategory":"Child Care",
            "type":"Services"
        }
    ],
    "sg:phone":"+1 334 585 2745",
    "sg:postcode":"36310",
    "sg:province":"AL",
    "sg:tags":[
        "day"
    ],
    "wof:name":"J&M Day Care",
    "wof:placetype":"venue"
},
  "geometry": {"coordinates":[-85.24217299999999,31.563632],"type":"Point"}
}