{
  "type": "Feature",
  "properties": {
    "iso:country":"US",
    "sg:address":"450 Cane Creek Farm Rd",
    "sg:city":"Alexandria",
    "sg:classifiers":[
        {
            "category":"Real Estate",
            "subcategory":"Developer",
            "type":"Services"
        }
    ],
    "sg:phone":"+1 256 820 4058",
    "sg:postcode":"36250",
    "sg:province":"AL",
    "sg:tags":[
        "cemetery"
    ],
    "sg:website":"www.maplegrovecemetery.com",
    "wof:name":"Maple Grove Cemetery & Chapel",
    "wof:placetype":"venue"
},
  "geometry": {"coordinates":[-85.890199,33.739852],"type":"Point"}
}