{
  "type": "Feature",
  "properties": {
    "iso:country":"US",
    "sg:address":"4329 Windsong Trl",
    "sg:city":"Trussville",
    "sg:classifiers":[
        {
            "category":"Health Services",
            "subcategory":"Medical Lab",
            "type":"Services"
        }
    ],
    "sg:phone":"+1 205 655 8271",
    "sg:postcode":"35173",
    "sg:province":"AL",
    "sg:tags":[
        "laboratory",
        "dental"
    ],
    "wof:name":"Osborn Dental Lab",
    "wof:placetype":"venue"
},
  "geometry": {"coordinates":[-86.557586,33.631723],"type":"Point"}
}