{
  "type": "Feature",
  "properties": {
    "iso:country":"US",
    "sg:address":"200 N Royal St",
    "sg:city":"Mobile",
    "sg:classifiers":[
        {
            "category":"Government",
            "subcategory":"Police Station",
            "type":"Public Place"
        }
    ],
    "sg:phone":"+1 334 438 3674",
    "sg:postcode":"36602",
    "sg:province":"AL",
    "sg:tags":[
        "investigation",
        "bureau"
    ],
    "wof:name":"FBI",
    "wof:placetype":"venue"
},
  "geometry": {"coordinates":[-88.04259399999999,30.696371],"type":"Point"}
}