{
  "type": "Feature",
  "properties": {
    "iso:country":"US",
    "sg:address":"411 S Montgomery Ave",
    "sg:city":"Sheffield",
    "sg:classifiers":[
        {
            "category":"Wholesale",
            "subcategory":"Plants",
            "type":"Manufacturing & Wholesale Goods"
        }
    ],
    "sg:phone":"+1 256 389 9424",
    "sg:postcode":"35660",
    "sg:province":"AL",
    "sg:tags":[
        "silk",
        "flower"
    ],
    "wof:name":"Smith Wholesale Floral Co Inc",
    "wof:placetype":"venue"
},
  "geometry": {"coordinates":[-87.698697,34.753614],"type":"Point"}
}