{
  "type": "Feature",
  "properties": {
    "iso:country":"US",
    "sg:address":"401 14th St SE",
    "sg:city":"Decatur",
    "sg:classifiers":[
        {
            "category":"Personal",
            "subcategory":"Beauty Salon",
            "type":"Services"
        }
    ],
    "sg:phone":"+1 256 355 2272",
    "sg:postcode":"35601",
    "sg:province":"AL",
    "wof:name":"Salon Bleu Tammy",
    "wof:placetype":"venue"
},
  "geometry": {"coordinates":[-86.983109,34.578159],"type":"Point"}
}