{
  "type": "Feature",
  "properties": {
    "iso:country":"US",
    "sg:address":"1515 Dartmouth Ave",
    "sg:city":"Bessemer",
    "sg:classifiers":[
        {
            "category":"Social Services",
            "subcategory":"Child Care",
            "type":"Services"
        }
    ],
    "sg:phone":"+1 205 426 6058",
    "sg:postcode":"35020",
    "sg:province":"AL",
    "sg:tags":[
        "day"
    ],
    "wof:name":"Moore Family Daycare",
    "wof:placetype":"venue"
},
  "geometry": {"coordinates":[-86.948195,33.394512],"type":"Point"}
}