{
  "type": "Feature",
  "properties": {
    "addr:full":"1821 11th Ave S Birmingham AL 35205",
    "addr:housenumber":"1821",
    "addr:postcode":"35205",
    "addr:street":"11Th Ave S",
    "iso:country":"US",
    "sg:address":"1821 11th Ave S",
    "sg:city":"Birmingham",
    "sg:classifiers":[
        {
            "category":"Government",
            "subcategory":"Post Office",
            "type":"Public Place"
        }
    ],
    "sg:phone":"+1 205 939 0168",
    "sg:postcode":"35205",
    "sg:province":"AL",
    "sg:tags":[
        "postal",
        "us"
    ],
    "wof:name":"South Highland Station",
    "wof:placetype":"venue"
},
  "geometry": {"coordinates":[-86.794645,33.500717],"type":"Point"}
}