{
  "type": "Feature",
  "properties": {
    "iso:country":"US",
    "sg:address":"256 US Hwy 278",
    "sg:city":"Cullman",
    "sg:classifiers":[
        {
            "category":"Utilities",
            "subcategory":"Cable",
            "type":"Services"
        }
    ],
    "sg:phone":"+1 256 734 3000",
    "sg:postcode":"35055",
    "sg:province":"AL",
    "sg:tags":[
        "television"
    ],
    "wof:name":"Adelphia",
    "wof:placetype":"venue"
},
  "geometry": {"coordinates":[-86.838443,34.177051],"type":"Point"}
}