{
  "type": "Feature",
  "properties": {
    "iso:country":"US",
    "sg:address":"1640 Cresthill Rd",
    "sg:city":"Birmingham",
    "sg:classifiers":[
        {
            "category":"Building & Trades",
            "subcategory":"Construction",
            "type":"Services"
        }
    ],
    "sg:phone":"+1 205 229 3980",
    "sg:postcode":"35213",
    "sg:province":"AL",
    "sg:tags":[
        "contractor"
    ],
    "wof:name":"Sandoval Roofing",
    "wof:placetype":"venue"
},
  "geometry": {"coordinates":[-86.727981,33.528005],"type":"Point"}
}