{
  "type": "Feature",
  "properties": {
    "iso:country":"US",
    "sg:address":"730 Glover Ave",
    "sg:city":"Enterprise",
    "sg:classifiers":[
        {
            "category":"Insurance",
            "subcategory":"Insurance Agent",
            "type":"Services"
        },
        {
            "category":"Insurance",
            "subcategory":"Hazard Insurance",
            "type":"Services"
        }
    ],
    "sg:phone":"+1 334 347 9133",
    "sg:postcode":"36330",
    "sg:province":"AL",
    "sg:tags":[
        "auto"
    ],
    "sg:website":"http://www.ypad.com/business-profile.cfm/state/AL/city/Enterprise/ppid/3620",
    "wof:name":"Cotton States Insurance Agency",
    "wof:placetype":"venue"
},
  "geometry": {"coordinates":[-85.835348,31.320995],"type":"Point"}
}