{
  "type": "Feature",
  "properties": {
    "iso:country":"US",
    "sg:address":"7717 Melvin Rd",
    "sg:city":"Gilbertown",
    "sg:classifiers":[
        {
            "category":"Shopping",
            "type":"Retail Goods"
        }
    ],
    "sg:phone":"+1 251 843 5597",
    "sg:postcode":"36908",
    "sg:province":"AL",
    "sg:tags":[
        "sales"
    ],
    "wof:name":"Trent Johnson Merchandising",
    "wof:placetype":"venue"
},
  "geometry": {"coordinates":[-88.440235,31.922358],"type":"Point"}
}