{
  "type": "Feature",
  "properties": {
    "addr:full":"31888 State Hwy 75 Oneonta AL 35121",
    "addr:housenumber":"31888",
    "addr:postcode":"35121",
    "addr:street":"State Hwy 75",
    "iso:country":"US",
    "sg:address":"31888 State Hwy 75",
    "sg:city":"Oneonta",
    "sg:classifiers":[
        {
            "category":"Home & Garden",
            "subcategory":"Mobile Homes",
            "type":"Retail Goods"
        }
    ],
    "sg:phone":"+1 205 625 6930",
    "sg:postcode":"35121",
    "sg:province":"AL",
    "wof:name":"Alabama Mobile Home Brks LLC",
    "wof:placetype":"venue"
},
  "geometry": {"coordinates":[-86.441818,33.982039],"type":"Point"}
}