{
  "type": "Feature",
  "properties": {
    "iso:country":"US",
    "sg:address":"12141 Airport Blvd",
    "sg:city":"Mobile",
    "sg:classifiers":[
        {
            "category":"Wholesale",
            "subcategory":"Plants",
            "type":"Manufacturing & Wholesale Goods"
        }
    ],
    "sg:phone":"+1 251 634 1637",
    "sg:postcode":"36608",
    "sg:province":"AL",
    "sg:tags":[
        "supply"
    ],
    "wof:name":"Reeves Wholesale Nursery",
    "wof:placetype":"venue"
},
  "geometry": {"coordinates":[-88.35815,30.635227],"type":"Point"}
}