{
  "type": "Feature",
  "properties": {
    "iso:country":"US",
    "sg:address":"3079 Pelham Pkwy",
    "sg:city":"Pelham",
    "sg:classifiers":[
        {
            "category":"Restaurant",
            "type":"Food & Drink"
        }
    ],
    "sg:phone":"+1 205 663 7818",
    "sg:postcode":"35124",
    "sg:province":"AL",
    "wof:name":"Fran's Restaurant",
    "wof:placetype":"venue"
},
  "geometry": {"coordinates":[-86.811311,33.291137],"type":"Point"}
}