{
  "type": "Feature",
  "properties": {
    "addr:full":"320 Crossbrook Trl Chelsea AL 35043",
    "addr:housenumber":"320",
    "addr:postcode":"35043",
    "addr:street":"Crossbrook Trl",
    "iso:country":"US",
    "sg:address":"320 Crossbrook Trl",
    "sg:city":"Chelsea",
    "sg:classifiers":[
        {
            "category":"Building & Trades",
            "subcategory":"Construction",
            "type":"Services"
        }
    ],
    "sg:phone":"+1 205 678 2228",
    "sg:postcode":"35043",
    "sg:province":"AL",
    "sg:tags":[
        "residential"
    ],
    "wof:name":"Bedwell Development Corp",
    "wof:placetype":"venue"
},
  "geometry": {"coordinates":[-86.652664,33.303696],"type":"Point"}
}