{
  "type": "Feature",
  "properties": {
    "iso:country":"US",
    "sg:address":"1113 Bluefield Ave SE",
    "sg:city":"Huntsville",
    "sg:classifiers":[
        {
            "category":"Organizations",
            "subcategory":"Religious Organization",
            "type":"Services"
        }
    ],
    "sg:phone":"+1 256 536 7271",
    "sg:postcode":"35801",
    "sg:province":"AL",
    "wof:name":"Doctrinal Bible Church Inc",
    "wof:placetype":"venue"
},
  "geometry": {"coordinates":[-86.569861,34.724596],"type":"Point"}
}