{
  "type": "Feature",
  "properties": {
    "iso:country":"US",
    "sg:address":"210 N Elm St",
    "sg:city":"Tuskegee",
    "sg:classifiers":[
        {
            "category":"Government",
            "subcategory":"Office",
            "type":"Public Place"
        }
    ],
    "sg:phone":"+1 334 724 2552",
    "sg:postcode":"36083",
    "sg:province":"AL",
    "wof:name":"Macon County Probate Tag Ofc",
    "wof:placetype":"venue"
},
  "geometry": {"coordinates":[-85.691984,32.423635],"type":"Point"}
}