{
  "type": "Feature",
  "properties": {
    "iso:country":"US",
    "sg:address":"740 Lucy's Trl",
    "sg:city":"Wetumpka",
    "sg:classifiers":[
        {
            "category":"Organizations",
            "subcategory":"Community Association",
            "type":"Services"
        }
    ],
    "sg:phone":"+1 334 514 6047",
    "sg:postcode":"36093",
    "sg:province":"AL",
    "wof:name":"Pippas Woods Homeowners Assn",
    "wof:placetype":"venue"
},
  "geometry": {"coordinates":[-86.160283,32.455658],"type":"Point"}
}