{
  "type": "Feature",
  "properties": {
    "iso:country":"US",
    "sg:address":"6955 Co Rd 114",
    "sg:city":"Brundidge",
    "sg:classifiers":[
        {
            "category":"Farming",
            "subcategory":"Poultry Farm",
            "type":"Manufacturing & Wholesale Goods"
        }
    ],
    "sg:phone":"+1 334 735 3471",
    "sg:postcode":"36346",
    "sg:province":"AL",
    "sg:tags":[
        "chicken"
    ],
    "wof:name":"George Dismukes",
    "wof:placetype":"venue"
},
  "geometry": {"coordinates":[-85.862999,31.584691],"type":"Point"}
}