{
  "type": "Feature",
  "properties": {
    "iso:country":"US",
    "sg:address":"2657 Shady Grove Rd",
    "sg:city":"Adamsville",
    "sg:classifiers":[
        {
            "category":"Government",
            "subcategory":"Fire Station",
            "type":"Public Place"
        }
    ],
    "sg:phone":"+1 205 674 1200",
    "sg:postcode":"35005",
    "sg:province":"AL",
    "sg:tags":[
        "protection"
    ],
    "wof:name":"Shady Grove Fire Dept",
    "wof:placetype":"venue"
},
  "geometry": {"coordinates":[-87.00410100000001,33.588257],"type":"Point"}
}