{
  "type": "Feature",
  "properties": {
    "addr:full":"1820 Shellbrook Dr NW Huntsville AL 35806",
    "addr:housenumber":"1820",
    "addr:postcode":"35806",
    "addr:street":"Shellbrook Dr Nw",
    "iso:country":"US",
    "sg:address":"1820 Shellbrook Dr NW",
    "sg:city":"Huntsville",
    "sg:classifiers":[
        {
            "category":"Farming",
            "subcategory":"Fish & Marine Products",
            "type":"Manufacturing & Wholesale Goods"
        }
    ],
    "sg:phone":"+1 256 895 9169",
    "sg:postcode":"35806",
    "sg:province":"AL",
    "sg:tags":[
        "management"
    ],
    "wof:name":"Rocky Mountain Elk Founda",
    "wof:placetype":"venue"
},
  "geometry": {"coordinates":[-86.688569,34.75888],"type":"Point"}
}