{
  "type": "Feature",
  "properties": {
    "iso:country":"US",
    "sg:address":"8330 State Rte 59",
    "sg:city":"Foley",
    "sg:classifiers":[
        {
            "category":"Shopping",
            "subcategory":"Used Merchandise",
            "type":"Retail Goods"
        }
    ],
    "sg:phone":"+1 251 968 3694",
    "sg:postcode":"36535",
    "sg:province":"AL",
    "sg:tags":[
        "shop",
        "consignment"
    ],
    "wof:name":"Carolyns Consignment",
    "wof:placetype":"venue"
},
  "geometry": {"coordinates":[-87.683347,30.346023],"type":"Point"}
}