{
  "type": "Feature",
  "properties": {
    "iso:country":"US",
    "sg:address":"4681 Appaloosa Dr",
    "sg:city":"Birmingham",
    "sg:classifiers":[
        {
            "category":"Manufacturing",
            "subcategory":"Leather Goods",
            "type":"Manufacturing & Wholesale Goods"
        }
    ],
    "sg:phone":"+1 205 956 4444",
    "sg:postcode":"35210",
    "sg:province":"AL",
    "sg:tags":[
        "mfg"
    ],
    "wof:name":"Porkys Leather",
    "wof:placetype":"venue"
},
  "geometry": {"coordinates":[-86.66139200000001,33.545087],"type":"Point"}
}