{
  "type": "Feature",
  "properties": {
    "iso:country":"US",
    "sg:address":"200 Kuderna Acres",
    "sg:city":"Auburn",
    "sg:classifiers":[
        {
            "category":"Shopping",
            "subcategory":"Clothing, Apparel, & Fashions",
            "type":"Retail Goods"
        }
    ],
    "sg:phone":"+1 334 887 1002",
    "sg:postcode":"36832",
    "sg:province":"AL",
    "sg:tags":[
        "t"
    ],
    "wof:name":"Owl Bay Outfitters",
    "wof:placetype":"venue"
},
  "geometry": {"coordinates":[-85.53843000000001,32.569189],"type":"Point"}
}