{
  "type": "Feature",
  "properties": {
    "iso:country":"US",
    "sg:address":"2503 S 11th St",
    "sg:city":"Gadsden",
    "sg:classifiers":[
        {
            "category":"Building & Trades",
            "subcategory":"Plumbing",
            "type":"Services"
        }
    ],
    "sg:phone":"+1 256 546 6262",
    "sg:postcode":"35904",
    "sg:province":"AL",
    "sg:tags":[
        "conditioning",
        "contractor",
        "system",
        "air"
    ],
    "wof:name":"A/C Stevens & Heating",
    "wof:placetype":"venue"
},
  "geometry": {"coordinates":[-86.041704,33.996464],"type":"Point"}
}