{
  "type": "Feature",
  "properties": {
    "addr:full":"1145 Dale Rd Eufaula AL 36027",
    "addr:housenumber":"1145",
    "addr:postcode":"36027",
    "addr:street":"Dale Rd",
    "iso:country":"US",
    "sg:address":"1145 Dale Rd",
    "sg:city":"Eufaula",
    "sg:classifiers":[
        {
            "category":"Utilities",
            "subcategory":"Electric",
            "type":"Services"
        }
    ],
    "sg:phone":"+1 334 687 4391",
    "sg:postcode":"36027",
    "sg:province":"AL",
    "wof:name":"Alabama Power Company",
    "wof:placetype":"venue"
},
  "geometry": {"coordinates":[-85.154652,31.876177],"type":"Point"}
}