{
  "type": "Feature",
  "properties": {
    "iso:country":"US",
    "sg:address":"921 1st St SW",
    "sg:city":"Childersburg",
    "sg:classifiers":[
        {
            "category":"Retail",
            "subcategory":"Laundry & Dry Cleaning",
            "type":"Services"
        }
    ],
    "sg:phone":"+1 256 378 7811",
    "sg:postcode":"35044",
    "sg:province":"AL",
    "sg:tags":[
        "drycleaning"
    ],
    "wof:name":"Taylor Cleaning Service",
    "wof:placetype":"venue"
},
  "geometry": {"coordinates":[-86.356064,33.277976],"type":"Point"}
}