{
  "type": "Feature",
  "properties": {
    "iso:country":"US",
    "sg:address":"295 W Valley Ave",
    "sg:city":"Birmingham",
    "sg:phone":"+1 205 942 8333",
    "sg:postcode":"35209",
    "sg:province":"AL",
    "wof:name":"Campesino Western Wear",
    "wof:placetype":"venue"
},
  "geometry": {"coordinates":[-86.831481,33.468344],"type":"Point"}
}