{
  "type": "Feature",
  "properties": {
    "iso:country":"US",
    "sg:address":"650 Fussy Hill Rd",
    "sg:city":"New Market",
    "sg:classifiers":[
        {
            "category":"Building & Trades",
            "subcategory":"Construction",
            "type":"Services"
        }
    ],
    "sg:phone":"+1 256 379 2611",
    "sg:postcode":"35761",
    "sg:province":"AL",
    "sg:tags":[
        "house"
    ],
    "wof:name":"Five Star Home Improvement",
    "wof:placetype":"venue"
},
  "geometry": {"coordinates":[-86.41771,34.844026],"type":"Point"}
}