{
  "type": "Feature",
  "properties": {
    "iso:country":"US",
    "sg:address":"559 Fairhope Ave",
    "sg:city":"Fairhope",
    "sg:classifiers":[
        {
            "category":"Professional",
            "subcategory":"Lawyer & Legal Services",
            "type":"Services"
        }
    ],
    "sg:phone":"+1 251 990 5454",
    "sg:postcode":"36532",
    "sg:province":"AL",
    "sg:tags":[
        "attorney"
    ],
    "wof:name":"John W Beck Law Offices",
    "wof:placetype":"venue"
},
  "geometry": {"coordinates":[-87.89907100000001,30.522956],"type":"Point"}
}