{
  "type": "Feature",
  "properties": {
    "iso:country":"US",
    "sg:address":"743 Pike Rd",
    "sg:city":"Pike Road",
    "sg:classifiers":[
        {
            "category":"Professional",
            "subcategory":"Business Services",
            "type":"Services"
        }
    ],
    "sg:phone":"+1 334 279 7882",
    "sg:postcode":"36064",
    "sg:province":"AL",
    "sg:tags":[
        "pressure",
        "steam",
        "cleaning"
    ],
    "wof:name":"Johnny Tatum Jr",
    "wof:placetype":"venue"
},
  "geometry": {"coordinates":[-86.095084,32.358224],"type":"Point"}
}