{
  "type": "Feature",
  "properties": {
    "iso:country":"US",
    "sg:address":"630 Glover Ave",
    "sg:city":"Enterprise",
    "sg:classifiers":[
        {
            "category":"Travel",
            "subcategory":"Hotels & Motels",
            "type":"Entertainment"
        }
    ],
    "sg:phone":"+1 334 347 6262",
    "sg:postcode":"36330",
    "sg:province":"AL",
    "sg:tags":[
        "operation"
    ],
    "sg:website":"www.ramada.com",
    "wof:name":"Ramada Inn",
    "wof:placetype":"venue"
},
  "geometry": {"coordinates":[-85.83876600000001,31.320442],"type":"Point"}
}