{
  "type": "Feature",
  "properties": {
    "iso:country":"US",
    "sg:address":"717 Saundra Cir NE",
    "sg:city":"Cullman",
    "sg:classifiers":[
        {
            "category":"Shopping",
            "subcategory":"Computers & Home Electronics",
            "type":"Retail Goods"
        }
    ],
    "sg:phone":"+1 256 734 8053",
    "sg:postcode":"35055",
    "sg:province":"AL",
    "sg:tags":[
        "equipment",
        "electronic",
        "supply"
    ],
    "wof:name":"Stereo Center",
    "wof:placetype":"venue"
},
  "geometry": {"coordinates":[-86.838375,34.191664],"type":"Point"}
}