{
  "type": "Feature",
  "properties": {
    "addr:full":"2011 Carl Jones Rd Moody AL 35004",
    "addr:housenumber":"2011",
    "addr:postcode":"35004",
    "addr:street":"Carl Jones Rd",
    "iso:country":"US",
    "sg:address":"2011 Carl Jones Rd",
    "sg:city":"Moody",
    "sg:classifiers":[
        {
            "category":"Building & Trades",
            "subcategory":"Plumbing",
            "type":"Services"
        }
    ],
    "sg:phone":"+1 205 369 3371",
    "sg:postcode":"35004",
    "sg:province":"AL",
    "sg:tags":[
        "contractor"
    ],
    "wof:name":"Warrens Heating & Cooling LLC",
    "wof:placetype":"venue"
},
  "geometry": {"coordinates":[-86.506308,33.569276],"type":"Point"}
}