{
  "type": "Feature",
  "properties": {
    "iso:country":"US",
    "sg:address":"3388 Morgan Mill Rd",
    "sg:city":"Brantley",
    "sg:classifiers":[
        {
            "category":"Farming",
            "subcategory":"Farm",
            "type":"Manufacturing & Wholesale Goods"
        }
    ],
    "sg:phone":"+1 334 897 6697",
    "sg:postcode":"36009",
    "sg:province":"AL",
    "sg:tags":[
        "crop",
        "general"
    ],
    "wof:name":"Keith Danley Farm",
    "wof:placetype":"venue"
},
  "geometry": {"coordinates":[-86.213024,31.482691],"type":"Point"}
}