{
  "type": "Feature",
  "properties": {
    "addr:full":"2301 Rainbow Dr Gadsden AL 35901",
    "addr:housenumber":"2301",
    "addr:postcode":"35901",
    "addr:street":"Rainbow Dr",
    "iso:country":"US",
    "sg:address":"2301 Rainbow Dr",
    "sg:city":"Gadsden",
    "sg:classifiers":[
        {
            "category":"Health Services",
            "subcategory":"Nursing And Care Facility",
            "type":"Services"
        }
    ],
    "sg:phone":"+1 256 543 3467",
    "sg:postcode":"35901",
    "sg:province":"AL",
    "sg:tags":[
        "home",
        "convalescent"
    ],
    "wof:name":"Mc Guffey Health Care Ctr",
    "wof:placetype":"venue"
},
  "geometry": {"coordinates":[-86.02020899999999,33.97079],"type":"Point"}
}