{
  "type": "Feature",
  "properties": {
    "iso:country":"US",
    "sg:address":"2316 Memorial Pkwy SW",
    "sg:city":"Huntsville",
    "sg:phone":"+1 256 539 7766",
    "sg:postcode":"35801",
    "sg:province":"AL",
    "sg:website":"http://russellbrosautoelectric.com",
    "wof:name":"Russell Brothers Auto Electric",
    "wof:placetype":"venue"
},
  "geometry": {"coordinates":[-86.59169,34.715698],"type":"Point"}
}