{
  "type": "Feature",
  "properties": {
    "iso:country":"US",
    "sg:address":"2610 University Blvd",
    "sg:city":"Tuscaloosa",
    "sg:classifiers":[
        {
            "category":"Shopping",
            "subcategory":"Gifts & Souvenirs",
            "type":"Retail Goods"
        }
    ],
    "sg:phone":"+1 205 758 4634",
    "sg:postcode":"35401",
    "sg:province":"AL",
    "sg:tags":[
        "shop"
    ],
    "wof:name":"Bun-Lam Enterprises",
    "wof:placetype":"venue"
},
  "geometry": {"coordinates":[-87.572295,33.208856],"type":"Point"}
}