{
  "type": "Feature",
  "properties": {
    "addr:full":"9120 US Hwy 280 Alexander City AL 35010",
    "addr:housenumber":"9120",
    "addr:postcode":"35010",
    "addr:street":"Us Hwy 280",
    "iso:country":"US",
    "sg:address":"9120 US Hwy 280",
    "sg:city":"Alexander City",
    "sg:classifiers":[
        {
            "category":"Autos & Motor Vehicles",
            "subcategory":"Fuel & Gas Station",
            "type":"Retail Goods"
        }
    ],
    "sg:phone":"+1 256 825 6065",
    "sg:postcode":"35010",
    "sg:province":"AL",
    "sg:tags":[
        "station",
        "gasoline"
    ],
    "wof:name":"Riverbend Gas & Grocery",
    "wof:placetype":"venue"
},
  "geometry": {"coordinates":[-85.883999,32.89835],"type":"Point"}
}