{
  "type": "Feature",
  "properties": {
    "iso:country":"US",
    "sg:address":"8224 Old Federal Rd",
    "sg:city":"Montgomery",
    "sg:classifiers":[
        {
            "category":"Insurance",
            "subcategory":"Title Insurance",
            "type":"Services"
        }
    ],
    "sg:phone":"+1 334 279 9070",
    "sg:postcode":"36117",
    "sg:province":"AL",
    "sg:website":"www.securitylandtitleinc.com",
    "wof:name":"Security Land Title Inc",
    "wof:placetype":"venue"
},
  "geometry": {"coordinates":[-86.170067,32.341673],"type":"Point"}
}