{
  "type": "Feature",
  "properties": {
    "iso:country":"US",
    "sg:address":"1900 Avalon Ave",
    "sg:city":"Muscle Shoals",
    "sg:classifiers":[
        {
            "category":"Education",
            "subcategory":"School",
            "type":"Public Place"
        }
    ],
    "sg:phone":"+1 256 389 2682",
    "sg:postcode":"35661",
    "sg:province":"AL",
    "sg:website":"www.mscs.k12.al.us",
    "wof:name":"Muscle Schoals High School",
    "wof:placetype":"venue"
},
  "geometry": {"coordinates":[-87.641471,34.744331],"type":"Point"}
}