{
  "type": "Feature",
  "properties": {
    "iso:country":"US",
    "sg:address":"175 Distribution Dr",
    "sg:city":"Homewood",
    "sg:classifiers":[
        {
            "category":"Home & Garden",
            "subcategory":"Building Materials",
            "type":"Retail Goods"
        }
    ],
    "sg:phone":"+1 205 942 6203",
    "sg:postcode":"35209",
    "sg:province":"AL",
    "sg:tags":[
        "insulation",
        "heat"
    ],
    "wof:name":"IDI Distributors",
    "wof:placetype":"venue"
},
  "geometry": {"coordinates":[-86.84523,33.444961],"type":"Point"}
}