{
  "type": "Feature",
  "properties": {
    "addr:full":"1110 Way Thru the Woods Decatur AL 35603",
    "addr:housenumber":"1110",
    "addr:postcode":"35603",
    "addr:street":"Way Thru;Woods",
    "iso:country":"US",
    "sg:address":"1110 Way Thru the Woods",
    "sg:city":"Decatur",
    "sg:classifiers":[
        {
            "category":"Utilities",
            "subcategory":"Telephone",
            "type":"Services"
        }
    ],
    "sg:phone":"+1 256 340 9806",
    "sg:postcode":"35603",
    "sg:province":"AL",
    "sg:tags":[
        "communications"
    ],
    "wof:name":"Worldsites",
    "wof:placetype":"venue"
},
  "geometry": {"coordinates":[-87.00102699999999,34.55288],"type":"Point"}
}