{
  "type": "Feature",
  "properties": {
    "iso:country":"US",
    "sg:address":"1006 Oxmoor Rd",
    "sg:city":"Birmingham",
    "sg:classifiers":[
        {
            "category":"Restaurant",
            "type":"Food & Drink"
        }
    ],
    "sg:phone":"+1 205 870 4733",
    "sg:postcode":"35209",
    "sg:province":"AL",
    "sg:tags":[
        "eating"
    ],
    "wof:name":"Juliano's Italian Restaurant",
    "wof:placetype":"venue"
},
  "geometry": {"coordinates":[-86.80758400000001,33.473929],"type":"Point"}
}