{
  "type": "Feature",
  "properties": {
    "iso:country":"US",
    "sg:address":"9142 Coosada Rd",
    "sg:city":"Coosada",
    "sg:classifiers":[
        {
            "category":"Building & Trades",
            "subcategory":"Construction",
            "type":"Services"
        }
    ],
    "sg:phone":"+1 334 285 1460",
    "sg:postcode":"36020",
    "sg:province":"AL",
    "sg:tags":[
        "general",
        "contractor"
    ],
    "wof:name":"R & R Contractors LLC",
    "wof:placetype":"venue"
},
  "geometry": {"coordinates":[-86.313493,32.49827],"type":"Point"}
}