{
  "type": "Feature",
  "properties": {
    "addr:full":"100 Telegraph Rd Mobile AL 36611",
    "addr:housenumber":"100",
    "addr:postcode":"36611",
    "addr:street":"Telegraph Rd",
    "iso:country":"US",
    "sg:address":"100 Telegraph Rd",
    "sg:city":"Mobile",
    "sg:classifiers":[
        {
            "category":"Autos & Motor Vehicles",
            "subcategory":"Fuel & Gas Station",
            "type":"Retail Goods"
        }
    ],
    "sg:phone":"+1 251 456 4369",
    "sg:postcode":"36611",
    "sg:province":"AL",
    "sg:tags":[
        "grocery",
        "station",
        "gasoline"
    ],
    "wof:name":"Texaco",
    "wof:placetype":"venue"
},
  "geometry": {"coordinates":[-88.07388899999999,30.761224],"type":"Point"}
}