{
  "type": "Feature",
  "properties": {
    "iso:country":"US",
    "sg:address":"1602 Spring Dr",
    "sg:city":"Opelika",
    "sg:classifiers":[
        {
            "category":"Professional",
            "subcategory":"Business Services",
            "type":"Services"
        }
    ],
    "sg:phone":"+1 334 742 0890",
    "sg:postcode":"36801",
    "sg:province":"AL",
    "sg:tags":[
        "notary"
    ],
    "wof:name":"Lori Conner",
    "wof:placetype":"venue"
},
  "geometry": {"coordinates":[-85.428316,32.634015],"type":"Point"}
}