{
  "type": "Feature",
  "properties": {
    "iso:country":"US",
    "sg:address":"2464 W Main St",
    "sg:city":"Dothan",
    "sg:classifiers":[
        {
            "category":"Shopping",
            "subcategory":"Optical Goods",
            "type":"Retail Goods"
        },
        {
            "category":"Health Services",
            "subcategory":"Optometrist",
            "type":"Services"
        }
    ],
    "sg:phone":"+1 334 792 2020",
    "sg:postcode":"36301",
    "sg:province":"AL",
    "wof:name":"20/20 Eye Care",
    "wof:placetype":"venue"
},
  "geometry": {"coordinates":[-85.425034,31.228427],"type":"Point"}
}