{
  "type": "Feature",
  "properties": {
    "addr:full":"180 Roma Dr Madison AL 35758",
    "addr:housenumber":"180",
    "addr:postcode":"35758",
    "addr:street":"Roma Dr",
    "iso:country":"US",
    "sg:address":"180 Roma Dr",
    "sg:city":"Madison",
    "sg:classifiers":[
        {
            "category":"Social Services",
            "subcategory":"Child Care",
            "type":"Services"
        },
        {
            "category":"Education",
            "subcategory":"School",
            "type":"Public Place"
        }
    ],
    "sg:phone":"+1 256 830 0773",
    "sg:postcode":"35758",
    "sg:province":"AL",
    "sg:tags":[
        "kindergarten",
        "academic"
    ],
    "wof:name":"Joy Of Learning Montessori",
    "wof:placetype":"venue"
},
  "geometry": {"coordinates":[-86.738651,34.751068],"type":"Point"}
}