{
  "type": "Feature",
  "properties": {
    "iso:country":"US",
    "sg:address":"2025 Danville Park Dr SW",
    "sg:city":"Decatur",
    "sg:classifiers":[
        {
            "category":"Real Estate",
            "subcategory":"Real Estate Operator",
            "type":"Services"
        }
    ],
    "sg:phone":"+1 256 353 8919",
    "sg:postcode":"35603",
    "sg:province":"AL",
    "sg:tags":[
        "apartment"
    ],
    "sg:website":"http://www.danvilleparkapts.com",
    "wof:name":"Danville Park Office Complex",
    "wof:placetype":"venue"
},
  "geometry": {"coordinates":[-87.018405,34.566119],"type":"Point"}
}