{
  "type": "Feature",
  "properties": {
    "iso:country":"US",
    "sg:address":"1227 Headland Ave",
    "sg:city":"Dothan",
    "sg:classifiers":[
        {
            "category":"Social Services",
            "type":"Services"
        }
    ],
    "sg:phone":"+1 334 792 8453",
    "sg:postcode":"36303",
    "sg:province":"AL",
    "sg:tags":[
        "organization",
        "welfare"
    ],
    "wof:name":"Habitat For Humanity",
    "wof:placetype":"venue"
},
  "geometry": {"coordinates":[-85.39127499999999,31.24805],"type":"Point"}
}