{
  "type": "Feature",
  "properties": {
    "iso:country":"US",
    "sg:address":"24303 Co Rd 21",
    "sg:city":"Talladega",
    "sg:classifiers":[
        {
            "category":"Shopping",
            "subcategory":"Clothing, Apparel, & Fashions",
            "type":"Retail Goods"
        }
    ],
    "sg:phone":"+1 256 362 7703",
    "sg:postcode":"35160",
    "sg:province":"AL",
    "sg:tags":[
        "feed",
        "western"
    ],
    "wof:name":"Red Barn Country Store",
    "wof:placetype":"venue"
},
  "geometry": {"coordinates":[-86.18614700000001,33.344237],"type":"Point"}
}