{
  "type": "Feature",
  "properties": {
    "iso:country":"US",
    "sg:address":"124 16th St S",
    "sg:city":"Birmingham",
    "sg:classifiers":[
        {
            "category":"Wholesale",
            "subcategory":"Chemicals & Plastics",
            "type":"Manufacturing & Wholesale Goods"
        }
    ],
    "sg:phone":"+1 205 323 1626",
    "sg:postcode":"35233",
    "sg:province":"AL",
    "sg:tags":[
        "dry",
        "repair",
        "fire",
        "ice",
        "dioxide",
        "carbon"
    ],
    "wof:name":"Knox Fire Extinguisher",
    "wof:placetype":"venue"
},
  "geometry": {"coordinates":[-86.80908100000001,33.508403],"type":"Point"}
}