{
  "type": "Feature",
  "properties": {
    "iso:country":"US",
    "sg:address":"191 Hidden Creek Pkwy",
    "sg:city":"Pelham",
    "sg:classifiers":[
        {
            "category":"Building & Trades",
            "subcategory":"Construction",
            "type":"Services"
        }
    ],
    "sg:phone":"+1 205 621 1647",
    "sg:postcode":"35124",
    "sg:province":"AL",
    "sg:tags":[
        "house"
    ],
    "wof:name":"Wilkins Construction",
    "wof:placetype":"venue"
},
  "geometry": {"coordinates":[-86.805155,33.28939],"type":"Point"}
}