{
  "type": "Feature",
  "properties": {
    "addr:full":"1004 Pike Rd Birmingham AL 35218",
    "addr:housenumber":"1004",
    "addr:postcode":"35218",
    "addr:street":"Pike Rd",
    "iso:country":"US",
    "sg:address":"1004 Pike Rd",
    "sg:city":"Birmingham",
    "sg:classifiers":[
        {
            "category":"Retail",
            "subcategory":"Photofinishing",
            "type":"Services"
        }
    ],
    "sg:phone":"+1 205 785 2500",
    "sg:postcode":"35218",
    "sg:province":"AL",
    "sg:tags":[
        "laboratory"
    ],
    "wof:name":"Superior Photo Service",
    "wof:placetype":"venue"
},
  "geometry": {"coordinates":[-86.901526,33.495362],"type":"Point"}
}