{
  "type": "Feature",
  "properties": {
    "iso:country":"US",
    "sg:address":"2600 Riverchase Galleria",
    "sg:city":"Birmingham",
    "sg:classifiers":[
        {
            "category":"Shopping",
            "subcategory":"Department Store",
            "type":"Retail Goods"
        }
    ],
    "sg:phone":"+1 205 868 2601",
    "sg:postcode":"35244",
    "sg:province":"AL",
    "wof:name":"Richs-Macys",
    "wof:placetype":"venue"
},
  "geometry": {"coordinates":[-86.811602,33.380325],"type":"Point"}
}