{
  "type": "Feature",
  "properties": {
    "addr:full":"7777 Spanish Fort Blvd Spanish Fort AL 36527",
    "addr:housenumber":"7777",
    "addr:postcode":"36527",
    "addr:street":"Spanish Fort Blvd",
    "iso:country":"US",
    "sg:address":"7777 Spanish Fort Blvd",
    "sg:city":"Spanish Fort",
    "sg:classifiers":[
        {
            "category":"Building & Trades",
            "subcategory":"Construction",
            "type":"Services"
        }
    ],
    "sg:phone":"+1 251 626 6691",
    "sg:postcode":"36527",
    "sg:province":"AL",
    "sg:tags":[
        "contractor"
    ],
    "wof:name":"Creel Insulation",
    "wof:placetype":"venue"
},
  "geometry": {"coordinates":[-87.889712,30.671098],"type":"Point"}
}