{
  "type": "Feature",
  "properties": {
    "iso:country":"US",
    "sg:address":"3855 Narrow Lane Rd",
    "sg:city":"Montgomery",
    "sg:classifiers":[
        {
            "category":"Autos & Motor Vehicles",
            "subcategory":"Fuel & Gas Station",
            "type":"Retail Goods"
        }
    ],
    "sg:phone":"+1 334 288 5115",
    "sg:postcode":"36111",
    "sg:province":"AL",
    "sg:tags":[
        "station",
        "gasoline"
    ],
    "wof:name":"Amoco",
    "wof:placetype":"venue"
},
  "geometry": {"coordinates":[-86.282146,32.334326],"type":"Point"}
}