{
  "type": "Feature",
  "properties": {
    "iso:country":"US",
    "sg:address":"1600 W 16th St",
    "sg:city":"Anniston",
    "sg:classifiers":[
        {
            "category":"Manufacturing",
            "subcategory":"Wood Products",
            "type":"Manufacturing & Wholesale Goods"
        }
    ],
    "sg:phone":"+1 256 237 2875",
    "sg:postcode":"36201",
    "sg:province":"AL",
    "sg:website":"www.boozerbeam.com",
    "wof:name":"Boozer Laminated Beam Co",
    "wof:placetype":"venue"
},
  "geometry": {"coordinates":[-85.853675,33.664604],"type":"Point"}
}