{
  "type": "Feature",
  "properties": {
    "iso:country":"US",
    "sg:address":"1712 Curtis Rd",
    "sg:city":"Atmore",
    "sg:classifiers":[
        {
            "category":"Manufacturing",
            "subcategory":"Printing",
            "type":"Manufacturing & Wholesale Goods"
        }
    ],
    "sg:phone":"+1 251 446 9061",
    "sg:postcode":"36502",
    "sg:province":"AL",
    "sg:tags":[
        "newspaper"
    ],
    "wof:name":"Andrea Weekly",
    "wof:placetype":"venue"
},
  "geometry": {"coordinates":[-87.505653,31.099571],"type":"Point"}
}