{
  "type": "Feature",
  "properties": {
    "addr:full":"202 2nd Ave SE Fayette AL 35555",
    "addr:housenumber":"202",
    "addr:postcode":"35555",
    "addr:street":"2Nd Ave Se",
    "iso:country":"US",
    "sg:address":"202 2nd Ave SE",
    "sg:city":"Fayette",
    "sg:classifiers":[
        {
            "category":"Professional",
            "subcategory":"Accounting & Tax Preparation",
            "type":"Services"
        }
    ],
    "sg:phone":"+1 205 932 3648",
    "sg:postcode":"35555",
    "sg:province":"AL",
    "sg:tags":[
        "prep"
    ],
    "wof:name":"H & R Block",
    "wof:placetype":"venue"
},
  "geometry": {"coordinates":[-87.829065,33.684086],"type":"Point"}
}