{
  "type": "Feature",
  "properties": {
    "iso:country":"US",
    "sg:address":"1265 Highland Dr",
    "sg:city":"Elba",
    "sg:classifiers":[
        {
            "category":"Manufacturing",
            "subcategory":"Signs",
            "type":"Manufacturing & Wholesale Goods"
        }
    ],
    "sg:phone":"+1 334 897 2710",
    "sg:postcode":"36323",
    "sg:province":"AL",
    "sg:tags":[
        "specialty",
        "mfg"
    ],
    "wof:name":"Maddox Promotions & Awards",
    "wof:placetype":"venue"
},
  "geometry": {"coordinates":[-86.078339,31.428913],"type":"Point"}
}