{
  "type": "Feature",
  "properties": {
    "addr:full":"523 W Grand Ave Rainbow City AL 35906",
    "addr:housenumber":"523",
    "addr:postcode":"35906",
    "addr:street":"W Grand Ave",
    "iso:country":"US",
    "sg:address":"523 W Grand Ave",
    "sg:city":"Rainbow City",
    "sg:classifiers":[
        {
            "category":"Organizations",
            "subcategory":"Religious Organization",
            "type":"Services"
        }
    ],
    "sg:phone":"+1 256 442 8686",
    "sg:postcode":"35906",
    "sg:province":"AL",
    "wof:name":"Coosa Valley Baptist Church",
    "wof:placetype":"venue"
},
  "geometry": {"coordinates":[-86.04988299999999,33.969716],"type":"Point"}
}