{
  "type": "Feature",
  "properties": {
    "iso:country":"US",
    "sg:address":"567 Belview St",
    "sg:city":"Bessemer",
    "sg:classifiers":[
        {
            "category":"Home & Garden",
            "subcategory":"Furniture",
            "type":"Retail Goods"
        }
    ],
    "sg:phone":"+1 205 425 2133",
    "sg:postcode":"35020",
    "sg:province":"AL",
    "sg:tags":[
        "builder",
        "cabinet"
    ],
    "wof:name":"Ken Ross Cabinets",
    "wof:placetype":"venue"
},
  "geometry": {"coordinates":[-86.969916,33.369979],"type":"Point"}
}