{
  "type": "Feature",
  "properties": {
    "iso:country":"US",
    "sg:address":"6495 Atlanta Hwy",
    "sg:city":"Montgomery",
    "sg:classifiers":[
        {
            "category":"Personal",
            "subcategory":"Beauty Salon",
            "type":"Services"
        }
    ],
    "sg:phone":"+1 334 260 0801",
    "sg:postcode":"36117",
    "sg:province":"AL",
    "wof:name":"Smart Style Family Hair Salon",
    "wof:placetype":"venue"
},
  "geometry": {"coordinates":[-86.186367,32.382418],"type":"Point"}
}