{
  "type": "Feature",
  "properties": {
    "addr:full":"9945 Dominion Dr S Mobile AL 36695",
    "addr:housenumber":"9945",
    "addr:postcode":"36695",
    "addr:street":"Dominion Dr S",
    "iso:country":"US",
    "sg:address":"9945 Dominion Dr S",
    "sg:city":"Mobile",
    "sg:classifiers":[
        {
            "category":"Professional",
            "subcategory":"Management & Consulting",
            "type":"Services"
        }
    ],
    "sg:phone":"+1 251 776 7620",
    "sg:postcode":"36695",
    "sg:province":"AL",
    "sg:tags":[
        "business"
    ],
    "wof:name":"Business Support & Consulting",
    "wof:placetype":"venue"
},
  "geometry": {"coordinates":[-88.279976,30.667323],"type":"Point"}
}