{
  "type": "Feature",
  "properties": {
    "addr:full":"1705 Broad Ave Lanett AL 36863",
    "addr:housenumber":"1705",
    "addr:postcode":"36863",
    "addr:street":"Broad Ave",
    "iso:country":"US",
    "sg:address":"1705 Broad Ave",
    "sg:city":"Lanett",
    "sg:classifiers":[
        {
            "category":"Restaurant",
            "type":"Food & Drink"
        }
    ],
    "sg:menulink":"http://www.allmenus.com/al/langdale/231555-sonic/menu/",
    "sg:phone":"+1 334 644 5191",
    "sg:postcode":"36863",
    "sg:province":"AL",
    "sg:tags":[
        "burger",
        "american"
    ],
    "wof:name":"Sonic",
    "wof:placetype":"venue"
},
  "geometry": {"coordinates":[-85.19159999999999,32.854324],"type":"Point"}
}