{
  "type": "Feature",
  "properties": {
    "addr:full":"10880 Pelican Bay Dr Theodore AL 36582",
    "addr:housenumber":"10880",
    "addr:postcode":"36582",
    "addr:street":"Pelican Bay Dr",
    "iso:country":"US",
    "sg:address":"10880 Pelican Bay Dr",
    "sg:city":"Theodore",
    "sg:classifiers":[
        {
            "category":"Professional",
            "subcategory":"Computer Services",
            "type":"Services"
        }
    ],
    "sg:phone":"+1 251 973 2778",
    "sg:postcode":"36582",
    "sg:province":"AL",
    "sg:tags":[
        "datum"
    ],
    "wof:name":"Abco Tech",
    "wof:placetype":"venue"
},
  "geometry": {"coordinates":[-88.12175499999999,30.464663],"type":"Point"}
}