{
  "type": "Feature",
  "properties": {
    "iso:country":"US",
    "sg:address":"2360 Havens Rd",
    "sg:city":"Semmes",
    "sg:classifiers":[
        {
            "category":"Manufacturing",
            "subcategory":"Metals",
            "type":"Manufacturing & Wholesale Goods"
        }
    ],
    "sg:phone":"+1 251 649 3621",
    "sg:postcode":"36575",
    "sg:province":"AL",
    "sg:tags":[
        "fabrication"
    ],
    "wof:name":"Raefab",
    "wof:placetype":"venue"
},
  "geometry": {"coordinates":[-88.297757,30.743187],"type":"Point"}
}