{
  "type": "Feature",
  "properties": {
    "addr:full":"3401 N Jackson Hwy Sheffield AL 35660",
    "addr:housenumber":"3401",
    "addr:postcode":"35660",
    "addr:street":"N Jackson Hwy",
    "iso:country":"US",
    "sg:address":"3401 N Jackson Hwy",
    "sg:city":"Sheffield",
    "sg:classifiers":[
        {
            "category":"Shopping",
            "subcategory":"Department Store",
            "type":"Retail Goods"
        }
    ],
    "sg:phone":"+1 256 383 7894",
    "sg:postcode":"35660",
    "sg:province":"AL",
    "wof:name":"Barbara Holt Thrift Shop",
    "wof:placetype":"venue"
},
  "geometry": {"coordinates":[-87.676436,34.76642],"type":"Point"}
}