{
  "type": "Feature",
  "properties": {
    "iso:country":"US",
    "sg:address":"3401 N Jackson Hwy",
    "sg:city":"Sheffield",
    "sg:classifiers":[
        {
            "category":"Shopping",
            "subcategory":"Department Store",
            "type":"Retail Goods"
        }
    ],
    "sg:phone":"+1 256 383 7894",
    "sg:postcode":"35660",
    "sg:province":"AL",
    "wof:name":"Barbara Holt Thrift Shop",
    "wof:placetype":"venue"
},
  "geometry": {"coordinates":[-87.676436,34.76642],"type":"Point"}
}