{
  "type": "Feature",
  "properties": {
    "addr:full":"308 Dogwood Ave Anniston AL 36201",
    "addr:housenumber":"308",
    "addr:postcode":"36201",
    "addr:street":"Dogwood Ave",
    "iso:country":"US",
    "sg:address":"308 Dogwood Ave",
    "sg:city":"Anniston",
    "sg:classifiers":[
        {
            "category":"Wholesale",
            "subcategory":"Non-durable Goods",
            "type":"Manufacturing & Wholesale Goods"
        }
    ],
    "sg:phone":"+1 256 235 2593",
    "sg:postcode":"36201",
    "sg:province":"AL",
    "wof:name":"Southern Charm Lite",
    "wof:placetype":"venue"
},
  "geometry": {"coordinates":[-85.835892,33.69131],"type":"Point"}
}