{
  "type": "Feature",
  "properties": {
    "addr:full":"6900 March Rd Theodore AL 36582",
    "addr:housenumber":"6900",
    "addr:postcode":"36582",
    "addr:street":"March Rd",
    "iso:country":"US",
    "sg:address":"6900 March Rd",
    "sg:city":"Theodore",
    "sg:classifiers":[
        {
            "category":"Shopping",
            "subcategory":"Used Merchandise",
            "type":"Retail Goods"
        }
    ],
    "sg:phone":"+1 251 957 3297",
    "sg:postcode":"36582",
    "sg:province":"AL",
    "wof:name":"Horse Farm Antiques & Gifts",
    "wof:placetype":"venue"
},
  "geometry": {"coordinates":[-88.284693,30.546235],"type":"Point"}
}