{
  "type": "Feature",
  "properties": {
    "iso:country":"US",
    "sg:address":"6889 Horse Creek Blvd",
    "sg:city":"Cordova",
    "sg:classifiers":[
        {
            "category":"Retail",
            "subcategory":"Repair Shop",
            "type":"Services"
        }
    ],
    "sg:phone":"+1 205 483 9800",
    "sg:postcode":"35550",
    "sg:province":"AL",
    "sg:tags":[
        "switch",
        "contact",
        "electrical"
    ],
    "wof:name":"Electro Mechanical Devices",
    "wof:placetype":"venue"
},
  "geometry": {"coordinates":[-87.168781,33.755237],"type":"Point"}
}