{
  "type": "Feature",
  "properties": {
    "iso:country":"US",
    "sg:address":"101 Co Rd 47",
    "sg:city":"Columbiana",
    "sg:classifiers":[
        {
            "category":"Shopping",
            "subcategory":"Clothing, Apparel, & Fashions",
            "type":"Retail Goods"
        }
    ],
    "sg:phone":"+1 205 669 2388",
    "sg:postcode":"35051",
    "sg:province":"AL",
    "sg:tags":[
        "alteration"
    ],
    "wof:name":"Aunt B's Alterations",
    "wof:placetype":"venue"
},
  "geometry": {"coordinates":[-86.60715,33.187533],"type":"Point"}
}