{
  "type": "Feature",
  "properties": {
    "iso:country":"US",
    "sg:address":"1600 26th Ave",
    "sg:city":"Tuscaloosa",
    "sg:classifiers":[
        {
            "category":"Government",
            "subcategory":"Jail",
            "type":"Public Place"
        }
    ],
    "sg:phone":"+1 205 349 4511",
    "sg:postcode":"35401",
    "sg:province":"AL",
    "sg:tags":[
        "correctional",
        "institution"
    ],
    "wof:name":"County Jail",
    "wof:placetype":"venue"
},
  "geometry": {"coordinates":[-87.566239,33.198236],"type":"Point"}
}