{
  "type": "Feature",
  "properties": {
    "addr:full":"208 Bolvin Cir Albertville AL 35950",
    "addr:housenumber":"208",
    "addr:postcode":"35950",
    "addr:street":"Bolvin Cir",
    "iso:country":"US",
    "sg:address":"208 Bolvin Cir",
    "sg:city":"Albertville",
    "sg:classifiers":[
        {
            "category":"Building & Trades",
            "subcategory":"Landscaping Services",
            "type":"Services"
        }
    ],
    "sg:phone":"+1 256 878 3867",
    "sg:postcode":"35950",
    "sg:province":"AL",
    "wof:name":"Forever Green Nursery",
    "wof:placetype":"venue"
},
  "geometry": {"coordinates":[-86.197001,34.257976],"type":"Point"}
}