{
  "type": "Feature",
  "properties": {
    "addr:full":"4200 Curry Station Rd Munford AL 36268",
    "addr:housenumber":"4200",
    "addr:postcode":"36268",
    "addr:street":"Curry Station Rd",
    "iso:country":"US",
    "sg:address":"4200 Curry Station Rd",
    "sg:city":"Munford",
    "sg:classifiers":[
        {
            "category":"Building & Trades",
            "subcategory":"Plumbing",
            "type":"Services"
        }
    ],
    "sg:phone":"+1 256 362 1515",
    "sg:postcode":"36268",
    "sg:province":"AL",
    "sg:tags":[
        "conditioning",
        "air",
        "system",
        "contractor"
    ],
    "wof:name":"Quality Heating & AC",
    "wof:placetype":"venue"
},
  "geometry": {"coordinates":[-86.009522,33.541907],"type":"Point"}
}