{
  "type": "Feature",
  "properties": {
    "addr:full":"7671 Parker Rd Fairhope AL 36532",
    "addr:housenumber":"7671",
    "addr:postcode":"36532",
    "addr:street":"Parker Rd",
    "iso:country":"US",
    "sg:address":"7671 Parker Rd",
    "sg:city":"Fairhope",
    "sg:classifiers":[
        {
            "category":"Professional",
            "subcategory":"Employment Agencies",
            "type":"Services"
        }
    ],
    "sg:phone":"+1 251 990 3700",
    "sg:postcode":"36532",
    "sg:province":"AL",
    "sg:tags":[
        "help",
        "supply"
    ],
    "wof:name":"White Diamond Express LLC",
    "wof:placetype":"venue"
},
  "geometry": {"coordinates":[-87.8914,30.556547],"type":"Point"}
}