{
  "type": "Feature",
  "properties": {
    "addr:full":"54708 State Rte 17 Sulligent AL 35586",
    "addr:housenumber":"54708",
    "addr:postcode":"35586",
    "addr:street":"State Rte 17 Sulligent",
    "iso:country":"US",
    "sg:address":"54708 State Rte 17",
    "sg:city":"Sulligent",
    "sg:classifiers":[
        {
            "category":"Organizations",
            "subcategory":"Religious Organization",
            "type":"Services"
        }
    ],
    "sg:phone":"+1 205 698 9806",
    "sg:postcode":"35586",
    "sg:province":"AL",
    "sg:tags":[
        "church"
    ],
    "wof:name":"First Assembly Of God",
    "wof:placetype":"venue"
},
  "geometry": {"coordinates":[-88.12933700000001,33.893151],"type":"Point"}
}