{
  "type": "Feature",
  "properties": {
    "iso:country":"US",
    "sg:address":"909 E 2nd St",
    "sg:city":"Sheffield",
    "sg:classifiers":[
        {
            "category":"Professional",
            "subcategory":"Lawyer & Legal Services",
            "type":"Services"
        }
    ],
    "sg:phone":"+1 256 381 3917",
    "sg:postcode":"35660",
    "sg:province":"AL",
    "sg:tags":[
        "attorney"
    ],
    "wof:name":"Nathan P Johnson",
    "wof:placetype":"venue"
},
  "geometry": {"coordinates":[-87.68420999999999,34.759705],"type":"Point"}
}