{
  "type": "Feature",
  "properties": {
    "addr:full":"1315 Tower Rd Vernon AL 35592",
    "addr:housenumber":"1315",
    "addr:postcode":"35592",
    "addr:street":"Tower Rd",
    "iso:country":"US",
    "sg:address":"1315 Tower Rd",
    "sg:city":"Vernon",
    "sg:classifiers":[
        {
            "category":"Organizations",
            "subcategory":"Religious Organization",
            "type":"Services"
        }
    ],
    "sg:phone":"+1 205 695 7471",
    "sg:postcode":"35592",
    "sg:province":"AL",
    "wof:name":"United Baptist Church",
    "wof:placetype":"venue"
},
  "geometry": {"coordinates":[-88.129239,33.763711],"type":"Point"}
}