{
  "type": "Feature",
  "properties": {
    "iso:country":"US",
    "sg:address":"130 S Seale Rd",
    "sg:city":"Phenix City",
    "sg:classifiers":[
        {
            "category":"Restaurant",
            "type":"Food & Drink"
        }
    ],
    "sg:phone":"+1 334 291 5127",
    "sg:postcode":"36869",
    "sg:province":"AL",
    "sg:tags":[
        "eating"
    ],
    "wof:name":"Gus's Diner",
    "wof:placetype":"venue"
},
  "geometry": {"coordinates":[-85.039913,32.417445],"type":"Point"}
}