{
  "type": "Feature",
  "properties": {
    "addr:full":"909 Plantation Blvd Fairhope AL 36532",
    "addr:housenumber":"909",
    "addr:postcode":"36532",
    "addr:street":"Plantation Blvd",
    "iso:country":"US",
    "sg:address":"909 Plantation Blvd",
    "sg:city":"Fairhope",
    "sg:classifiers":[
        {
            "category":"Building & Trades",
            "subcategory":"Construction",
            "type":"Services"
        }
    ],
    "sg:phone":"+1 251 929 0531",
    "sg:postcode":"36532",
    "sg:province":"AL",
    "sg:tags":[
        "general",
        "contractor"
    ],
    "wof:name":"Don Gordon Construction Inc",
    "wof:placetype":"venue"
},
  "geometry": {"coordinates":[-87.885561,30.526227],"type":"Point"}
}