{
  "type": "Feature",
  "properties": {
    "iso:country":"US",
    "sg:address":"115 Ce-Lee Dr NW",
    "sg:city":"Huntsville",
    "sg:classifiers":[
        {
            "category":"Professional",
            "subcategory":"Computer Services",
            "type":"Services"
        }
    ],
    "sg:phone":"+1 256 721 0707",
    "sg:postcode":"35806",
    "sg:province":"AL",
    "sg:tags":[
        "design",
        "system"
    ],
    "wof:name":"Telint Inc",
    "wof:placetype":"venue"
},
  "geometry": {"coordinates":[-86.71203,34.767344],"type":"Point"}
}