{
  "type": "Feature",
  "properties": {
    "addr:full":"119 Johnson Ave S Talladega AL 35160",
    "addr:housenumber":"119",
    "addr:postcode":"35160",
    "addr:street":"Johnson Ave S Talladega",
    "iso:country":"US",
    "sg:address":"119 Johnson Ave S",
    "sg:city":"Talladega",
    "sg:classifiers":[
        {
            "category":"Home & Garden",
            "subcategory":"Carpets & Floor Coverings",
            "type":"Retail Goods"
        }
    ],
    "sg:phone":"+1 256 362 2970",
    "sg:postcode":"35160",
    "sg:province":"AL",
    "sg:tags":[
        "mobile",
        "real estate",
        "h"
    ],
    "wof:name":"Stephens Realty Co",
    "wof:placetype":"venue"
},
  "geometry": {"coordinates":[-86.09459099999999,33.437438],"type":"Point"}
}