{
  "type": "Feature",
  "properties": {
    "iso:country":"US",
    "sg:address":"6982 Parc Brook Ln",
    "sg:city":"Trussville",
    "sg:classifiers":[
        {
            "category":"Professional",
            "subcategory":"Business Services",
            "type":"Services"
        }
    ],
    "sg:phone":"+1 205 655 8902",
    "sg:postcode":"35173",
    "sg:province":"AL",
    "wof:name":"Precision Trim LLC",
    "wof:placetype":"venue"
},
  "geometry": {"coordinates":[-86.587525,33.633946],"type":"Point"}
}