{
  "type": "Feature",
  "properties": {
    "iso:country":"US",
    "sg:address":"1000 Ventana Rd",
    "sg:city":"Columbiana",
    "sg:classifiers":[
        {
            "category":"Farming",
            "subcategory":"Dairy Farm",
            "type":"Manufacturing & Wholesale Goods"
        }
    ],
    "sg:phone":"+1 205 669 1286",
    "sg:postcode":"35051",
    "sg:province":"AL",
    "wof:name":"Rosser Dairy Farms",
    "wof:placetype":"venue"
},
  "geometry": {"coordinates":[-86.667368,33.17377],"type":"Point"}
}