{
  "type": "Feature",
  "properties": {
    "iso:country":"US",
    "sg:address":"4705 Chippewa Ln",
    "sg:city":"Pelham",
    "sg:classifiers":[
        {
            "category":"Wholesale",
            "subcategory":"Machinery & Supplies",
            "type":"Manufacturing & Wholesale Goods"
        }
    ],
    "sg:phone":"+1 205 988 3006",
    "sg:postcode":"35124",
    "sg:province":"AL",
    "wof:name":"Telecommunication Dvsfd Inc",
    "wof:placetype":"venue"
},
  "geometry": {"coordinates":[-86.796823,33.33768],"type":"Point"}
}