{
  "type": "Feature",
  "properties": {
    "addr:full":"1177 Irby Cir Union Grove AL 35175",
    "addr:housenumber":"1177",
    "addr:postcode":"35175",
    "addr:street":"Irby Cir",
    "iso:country":"US",
    "sg:address":"1177 Irby Cir",
    "sg:city":"Union Grove",
    "sg:classifiers":[
        {
            "category":"Building & Trades",
            "subcategory":"Construction",
            "type":"Services"
        }
    ],
    "sg:phone":"+1 256 498 0480",
    "sg:postcode":"35175",
    "sg:province":"AL",
    "sg:tags":[
        "dry wall",
        "contractor"
    ],
    "wof:name":"Williams Drywall",
    "wof:placetype":"venue"
},
  "geometry": {"coordinates":[-86.54559999999999,34.448861],"type":"Point"}
}