{
  "type": "Feature",
  "properties": {
    "addr:full":"1905 Montgomery Hwy Dothan AL 36303",
    "addr:housenumber":"1905",
    "addr:postcode":"36303",
    "addr:street":"Montgomery Hwy",
    "iso:country":"US",
    "sg:address":"1905 Montgomery Hwy",
    "sg:city":"Dothan",
    "sg:classifiers":[
        {
            "category":"Restaurant",
            "type":"Food & Drink"
        }
    ],
    "sg:phone":"+1 334 671 8244",
    "sg:postcode":"36303",
    "sg:province":"AL",
    "sg:tags":[
        "eating"
    ],
    "wof:name":"Pats Diner",
    "wof:placetype":"venue"
},
  "geometry": {"coordinates":[-85.411964,31.239752],"type":"Point"}
}