{
  "type": "Feature",
  "properties": {
    "iso:country":"US",
    "sg:address":"3240 State Rte 53",
    "sg:city":"Huntsville",
    "sg:classifiers":[
        {
            "category":"Retail",
            "subcategory":"Auto Repair",
            "type":"Services"
        }
    ],
    "sg:phone":"+1 256 852 3239",
    "sg:postcode":"35806",
    "sg:province":"AL",
    "sg:tags":[
        "automotive",
        "general"
    ],
    "wof:name":"Rice Automobile Repair",
    "wof:placetype":"venue"
},
  "geometry": {"coordinates":[-86.657044,34.778967],"type":"Point"}
}