{
  "type": "Feature",
  "properties": {
    "iso:country":"US",
    "sg:address":"2890 S Valley Rd",
    "sg:city":"Gadsden",
    "sg:classifiers":[
        {
            "category":"Professional",
            "type":"Services"
        }
    ],
    "sg:phone":"+1 256 442 3162",
    "sg:postcode":"35907",
    "sg:province":"AL",
    "wof:name":"Dales Notary Service",
    "wof:placetype":"venue"
},
  "geometry": {"coordinates":[-86.010381,33.913853],"type":"Point"}
}