{
  "type": "Feature",
  "properties": {
    "iso:country":"US",
    "sg:address":"626 Alabama Ave",
    "sg:city":"Selma",
    "sg:classifiers":[
        {
            "category":"Professional",
            "subcategory":"Lawyer & Legal Services",
            "type":"Services"
        }
    ],
    "sg:phone":"+1 334 877 1011",
    "sg:postcode":"36701",
    "sg:province":"AL",
    "sg:tags":[
        "attorney"
    ],
    "wof:name":"Jeffrey C Robinson Law Offices",
    "wof:placetype":"venue"
},
  "geometry": {"coordinates":[-87.024479,32.405785],"type":"Point"}
}