{
  "type": "Feature",
  "properties": {
    "addr:full":"1892 Ben Elmore Rd Gordo AL 35466",
    "addr:housenumber":"1892",
    "addr:postcode":"35466",
    "addr:street":"Ben Elmore Rd",
    "iso:country":"US",
    "sg:address":"1892 Ben Elmore Rd",
    "sg:city":"Gordo",
    "sg:classifiers":[
        {
            "category":"Professional",
            "type":"Services"
        }
    ],
    "sg:phone":"+1 205 364 0316",
    "sg:postcode":"35466",
    "sg:province":"AL",
    "wof:name":"Jeffrey P Belcher",
    "wof:placetype":"venue"
},
  "geometry": {"coordinates":[-87.881676,33.317572],"type":"Point"}
}