{
  "type": "Feature",
  "properties": {
    "iso:country":"US",
    "sg:address":"11541 Old Moffat Rd",
    "sg:city":"Wilmer",
    "sg:classifiers":[
        {
            "category":"Organizations",
            "subcategory":"Religious Organization",
            "type":"Services"
        }
    ],
    "sg:phone":"+1 251 645 4700",
    "sg:postcode":"36587",
    "sg:province":"AL",
    "sg:tags":[
        "church"
    ],
    "wof:name":"First United Pentecostal Chr",
    "wof:placetype":"venue"
},
  "geometry": {"coordinates":[-88.315772,30.797479],"type":"Point"}
}