{
  "type": "Feature",
  "properties": {
    "iso:country":"US",
    "sg:address":"21790 State Rte 59",
    "sg:city":"Robertsdale",
    "sg:classifiers":[
        {
            "category":"Restaurant",
            "type":"Food & Drink"
        }
    ],
    "sg:phone":"+1 251 947 4801",
    "sg:postcode":"36567",
    "sg:province":"AL",
    "wof:name":"Country Cookin 2",
    "wof:placetype":"venue"
},
  "geometry": {"coordinates":[-87.70827300000001,30.538435],"type":"Point"}
}