{
  "type": "Feature",
  "properties": {
    "iso:country":"US",
    "sg:address":"70644 State Rte 9",
    "sg:city":"Goodwater",
    "sg:classifiers":[
        {
            "category":"Manufacturing",
            "subcategory":"Metals",
            "type":"Manufacturing & Wholesale Goods"
        }
    ],
    "sg:phone":"+1 256 839 6688",
    "sg:postcode":"35072",
    "sg:province":"AL",
    "sg:tags":[
        "mfg",
        "equipment",
        "industrial",
        "metalwork",
        "structural"
    ],
    "wof:name":"Graves Farm",
    "wof:placetype":"venue"
},
  "geometry": {"coordinates":[-86.024438,33.089062],"type":"Point"}
}