{
  "type": "Feature",
  "properties": {
    "addr:full":"210 N Main St Tuscumbia AL 35674",
    "addr:housenumber":"210",
    "addr:postcode":"35674",
    "addr:street":"N Main St",
    "iso:country":"US",
    "sg:address":"210 N Main St",
    "sg:city":"Tuscumbia",
    "sg:classifiers":[
        {
            "category":"Professional",
            "subcategory":"Lawyer & Legal Services",
            "type":"Services"
        }
    ],
    "sg:phone":"+1 256 383 2435",
    "sg:postcode":"35674",
    "sg:province":"AL",
    "sg:tags":[
        "attorney"
    ],
    "wof:name":"Black & Houghston",
    "wof:placetype":"venue"
},
  "geometry": {"coordinates":[-87.703497,34.732597],"type":"Point"}
}