{
  "type": "Feature",
  "properties": {
    "iso:country":"US",
    "sg:address":"92 Co Rd 507",
    "sg:city":"Moulton",
    "sg:classifiers":[
        {
            "category":"Building & Trades",
            "subcategory":"Construction",
            "type":"Services"
        }
    ],
    "sg:phone":"+1 256 508 9893",
    "sg:postcode":"35650",
    "sg:province":"AL",
    "sg:tags":[
        "carpentry",
        "contractor"
    ],
    "wof:name":"Smith Construction",
    "wof:placetype":"venue"
},
  "geometry": {"coordinates":[-87.336637,34.550692],"type":"Point"}
}