{
  "type": "Feature",
  "properties": {
    "addr:full":"911 Miller Blvd Madison AL 35758",
    "addr:housenumber":"911",
    "addr:postcode":"35758",
    "addr:street":"Miller Blvd",
    "iso:country":"US",
    "sg:address":"911 Miller Blvd",
    "sg:city":"Madison",
    "sg:classifiers":[
        {
            "category":"Personal",
            "type":"Services"
        }
    ],
    "sg:phone":"+1 256 461 4264",
    "sg:postcode":"35758",
    "sg:province":"AL",
    "sg:tags":[
        "treatment",
        "scalp"
    ],
    "wof:name":"International Institute",
    "wof:placetype":"venue"
},
  "geometry": {"coordinates":[-86.71977200000001,34.70867],"type":"Point"}
}