{
  "type": "Feature",
  "properties": {
    "iso:country":"US",
    "sg:address":"102 S Main St",
    "sg:city":"Linden",
    "sg:classifiers":[
        {
            "category":"Home & Garden",
            "subcategory":"Furniture",
            "type":"Retail Goods"
        }
    ],
    "sg:phone":"+1 334 295 8787",
    "sg:postcode":"36748",
    "sg:province":"AL",
    "wof:name":"Larry Walters Furniture & Appl",
    "wof:placetype":"venue"
},
  "geometry": {"coordinates":[-87.798041,32.306231],"type":"Point"}
}