{
  "type": "Feature",
  "properties": {
    "iso:country":"US",
    "sg:address":"2328 2nd Ave N",
    "sg:city":"Birmingham",
    "sg:classifiers":[
        {
            "category":"Professional",
            "subcategory":"Lawyer & Legal Services",
            "type":"Services"
        }
    ],
    "sg:phone":"+1 205 323 2521",
    "sg:postcode":"35203",
    "sg:province":"AL",
    "wof:name":"Broderick S Black",
    "wof:placetype":"venue"
},
  "geometry": {"coordinates":[-86.801161,33.517878],"type":"Point"}
}