{
  "type": "Feature",
  "properties": {
    "addr:full":"188 Co Rd 182 Dawson AL 35963",
    "addr:housenumber":"188;182",
    "addr:postcode":"35963",
    "addr:street":"Co Rd",
    "iso:country":"US",
    "sg:address":"188 Co Rd 182",
    "sg:city":"Dawson",
    "sg:classifiers":[
        {
            "category":"Building & Trades",
            "subcategory":"Construction",
            "type":"Services"
        }
    ],
    "sg:phone":"+1 256 659 2399",
    "sg:postcode":"35963",
    "sg:province":"AL",
    "sg:tags":[
        "house"
    ],
    "wof:name":"L & B Construction Inc",
    "wof:placetype":"venue"
},
  "geometry": {"coordinates":[-85.931724,34.345623],"type":"Point"}
}