{
  "type": "Feature",
  "properties": {
    "iso:country":"US",
    "sg:address":"7819 1st Ave N",
    "sg:city":"Birmingham",
    "sg:classifiers":[
        {
            "category":"Retail",
            "subcategory":"Repair Shop",
            "type":"Services"
        }
    ],
    "sg:phone":"+1 205 836 0139",
    "sg:postcode":"35206",
    "sg:province":"AL",
    "sg:tags":[
        "electrical"
    ],
    "wof:name":"East Lake Cycle Shop",
    "wof:placetype":"venue"
},
  "geometry": {"coordinates":[-86.726868,33.564426],"type":"Point"}
}