{
  "type": "Feature",
  "properties": {
    "iso:country":"US",
    "sg:address":"447 Rogers Rd",
    "sg:city":"Oneonta",
    "sg:classifiers":[
        {
            "category":"Insurance",
            "subcategory":"Insurance Agent",
            "type":"Services"
        }
    ],
    "sg:phone":"+1 205 625 6430",
    "sg:postcode":"35121",
    "sg:province":"AL",
    "wof:name":"Mc Waters & Assoc",
    "wof:placetype":"venue"
},
  "geometry": {"coordinates":[-86.417232,33.922055],"type":"Point"}
}