{
  "type": "Feature",
  "properties": {
    "addr:full":"1800 Crawford Rd Opelika AL 36804",
    "addr:housenumber":"1800",
    "addr:postcode":"36804",
    "addr:street":"Crawford Rd",
    "iso:country":"US",
    "sg:address":"1800 Crawford Rd",
    "sg:city":"Opelika",
    "sg:classifiers":[
        {
            "category":"Banks & Credit Unions",
            "subcategory":"Bank",
            "type":"Services"
        }
    ],
    "sg:phone":"+1 334 705 8268",
    "sg:postcode":"36804",
    "sg:province":"AL",
    "sg:website":"www.royalfederal.com",
    "wof:name":"Royal Federal Credit Union",
    "wof:placetype":"venue"
},
  "geometry": {"coordinates":[-85.337935,32.600135],"type":"Point"}
}