{
  "type": "Feature",
  "properties": {
    "iso:country":"US",
    "sg:address":"5563 7th St",
    "sg:city":"Satsuma",
    "sg:classifiers":[
        {
            "category":"Personal",
            "subcategory":"Beauty Salon",
            "type":"Services"
        }
    ],
    "sg:phone":"+1 251 679 8080",
    "sg:postcode":"36572",
    "sg:province":"AL",
    "sg:tags":[
        "shop"
    ],
    "wof:name":"Mustard Seed Hair Studio",
    "wof:placetype":"venue"
},
  "geometry": {"coordinates":[-88.062434,30.85288],"type":"Point"}
}