{
  "type": "Feature",
  "properties": {
    "iso:country":"US",
    "sg:address":"1776 Independence Ct",
    "sg:city":"Birmingham",
    "sg:classifiers":[
        {
            "category":"Professional",
            "subcategory":"Accounting & Tax Preparation",
            "type":"Services"
        }
    ],
    "sg:phone":"+1 205 870 4850",
    "sg:postcode":"35216",
    "sg:province":"AL",
    "sg:tags":[
        "firm"
    ],
    "wof:name":"Turpin Tommy & Associates CPA",
    "wof:placetype":"venue"
},
  "geometry": {"coordinates":[-86.779017,33.460775],"type":"Point"}
}