{
  "type": "Feature",
  "properties": {
    "iso:country":"US",
    "sg:address":"700 Tuskegee Ave",
    "sg:city":"Dothan",
    "sg:classifiers":[
        {
            "category":"Social Services",
            "type":"Services"
        }
    ],
    "sg:phone":"+1 334 673 2310",
    "sg:postcode":"36303",
    "sg:province":"AL",
    "wof:name":"Tyshauwns Day Care",
    "wof:placetype":"venue"
},
  "geometry": {"coordinates":[-85.381281,31.23039],"type":"Point"}
}