{
  "type": "Feature",
  "properties": {
    "iso:country":"US",
    "sg:address":"27243 Parker Ln",
    "sg:city":"Daphne",
    "sg:classifiers":[
        {
            "category":"Building & Trades",
            "subcategory":"Construction",
            "type":"Services"
        }
    ],
    "sg:phone":"+1 251 621 0432",
    "sg:postcode":"36526",
    "sg:province":"AL",
    "sg:tags":[
        "contractor"
    ],
    "wof:name":"Wc Gafford Roofing & Repair",
    "wof:placetype":"venue"
},
  "geometry": {"coordinates":[-87.897031,30.621558],"type":"Point"}
}