{
  "type": "Feature",
  "properties": {
    "addr:full":"1602 Dandridge St SW Decatur AL 35601",
    "addr:housenumber":"1602",
    "addr:postcode":"35601",
    "addr:street":"Dandridge St Sw",
    "iso:country":"US",
    "sg:address":"1602 Dandridge St SW",
    "sg:city":"Decatur",
    "sg:classifiers":[
        {
            "category":"Professional",
            "subcategory":"Business Services",
            "type":"Services"
        }
    ],
    "sg:phone":"+1 256 353 3619",
    "sg:postcode":"35601",
    "sg:province":"AL",
    "sg:tags":[
        "auto",
        "repair"
    ],
    "wof:name":"Larsen Enterprises Inc",
    "wof:placetype":"venue"
},
  "geometry": {"coordinates":[-87.009332,34.588788],"type":"Point"}
}