{
  "type": "Feature",
  "properties": {
    "addr:full":"614 16th St Phenix City AL 36867",
    "addr:housenumber":"614",
    "addr:postcode":"36867",
    "addr:street":"16Th St Phenix",
    "iso:country":"US",
    "sg:address":"614 16th St",
    "sg:city":"Phenix City",
    "sg:classifiers":[
        {
            "category":"Restaurant",
            "type":"Food & Drink"
        }
    ],
    "sg:phone":"+1 334 297 1509",
    "sg:postcode":"36867",
    "sg:province":"AL",
    "wof:name":"Booth's Corner Cafe",
    "wof:placetype":"venue"
},
  "geometry": {"coordinates":[-85.002205,32.474633],"type":"Point"}
}