{
  "type": "Feature",
  "properties": {
    "iso:country":"US",
    "sg:address":"1541 Cooper Hill Rd",
    "sg:city":"Birmingham",
    "sg:classifiers":[
        {
            "category":"Building & Trades",
            "subcategory":"Construction",
            "type":"Services"
        }
    ],
    "sg:phone":"+1 205 951 2108",
    "sg:postcode":"35210",
    "sg:province":"AL",
    "sg:tags":[
        "home",
        "family",
        "contractor"
    ],
    "wof:name":"Grayson Construction Co",
    "wof:placetype":"venue"
},
  "geometry": {"coordinates":[-86.726645,33.524176],"type":"Point"}
}