{
  "type": "Feature",
  "properties": {
    "addr:full":"6721 Tung Ave W Theodore AL 36582",
    "addr:housenumber":"6721",
    "addr:postcode":"36582",
    "addr:street":"Tung Ave W",
    "iso:country":"US",
    "sg:address":"6721 Tung Ave W",
    "sg:city":"Theodore",
    "sg:classifiers":[
        {
            "category":"Professional",
            "subcategory":"Business Services",
            "type":"Services"
        }
    ],
    "sg:phone":"+1 251 653 1035",
    "sg:postcode":"36582",
    "sg:province":"AL",
    "wof:name":"Mike Tillman Enterprises LLC",
    "wof:placetype":"venue"
},
  "geometry": {"coordinates":[-88.19904,30.53813],"type":"Point"}
}