{
  "type": "Feature",
  "properties": {
    "addr:full":"907 E Park Ave Enterprise AL 36330",
    "addr:housenumber":"907",
    "addr:postcode":"36330",
    "addr:street":"E Park Ave",
    "iso:country":"US",
    "sg:address":"907 E Park Ave",
    "sg:city":"Enterprise",
    "sg:classifiers":[
        {
            "category":"Professional",
            "type":"Services"
        }
    ],
    "sg:phone":"+1 334 348 2395",
    "sg:postcode":"36330",
    "sg:province":"AL",
    "wof:name":"Leslie Boots",
    "wof:placetype":"venue"
},
  "geometry": {"coordinates":[-85.83953,31.308304],"type":"Point"}
}