{
  "type": "Feature",
  "properties": {
    "iso:country":"US",
    "sg:address":"1712 12th Ave N",
    "sg:city":"Bessemer",
    "sg:classifiers":[
        {
            "category":"Shopping",
            "subcategory":"Computers & Home Electronics",
            "type":"Retail Goods"
        }
    ],
    "sg:phone":"+1 205 426 1116",
    "sg:postcode":"35020",
    "sg:province":"AL",
    "sg:tags":[
        "radio",
        "television",
        "electronic",
        "store"
    ],
    "wof:name":"Stereo Zone",
    "wof:placetype":"venue"
},
  "geometry": {"coordinates":[-86.966219,33.407165],"type":"Point"}
}