{
  "type": "Feature",
  "properties": {
    "iso:country":"US",
    "sg:address":"2106 Halcyon Blvd",
    "sg:city":"Montgomery",
    "sg:classifiers":[
        {
            "category":"Building & Trades",
            "subcategory":"Landscaping Services",
            "type":"Services"
        }
    ],
    "sg:phone":"+1 334 213 3233",
    "sg:postcode":"36117",
    "sg:province":"AL",
    "sg:tags":[
        "lawn",
        "maintenance",
        "grounds"
    ],
    "wof:name":"Reliable Lawn Care",
    "wof:placetype":"venue"
},
  "geometry": {"coordinates":[-86.16661000000001,32.346147],"type":"Point"}
}