{
  "type": "Feature",
  "properties": {
    "iso:country":"US",
    "sg:address":"1993 Lakemont Dr",
    "sg:city":"Birmingham",
    "sg:classifiers":[
        {
            "category":"Professional",
            "subcategory":"Engineering",
            "type":"Services"
        }
    ],
    "sg:phone":"+1 205 426 7771",
    "sg:postcode":"35244",
    "sg:province":"AL",
    "wof:name":"Plant & Process Engineering",
    "wof:placetype":"venue"
},
  "geometry": {"coordinates":[-86.885762,33.321814],"type":"Point"}
}