{
  "type": "Feature",
  "properties": {
    "iso:country":"US",
    "sg:address":"917 3rd St SW",
    "sg:city":"Attalla",
    "sg:classifiers":[
        {
            "category":"Retail",
            "subcategory":"Auto Repair",
            "type":"Services"
        }
    ],
    "sg:phone":"+1 256 538 9109",
    "sg:postcode":"35954",
    "sg:province":"AL",
    "sg:tags":[
        "repairing",
        "automobile"
    ],
    "wof:name":"Attalla Auto Svc",
    "wof:placetype":"venue"
},
  "geometry": {"coordinates":[-86.110222,34.007007],"type":"Point"}
}