{
  "type": "Feature",
  "properties": {
    "iso:country":"US",
    "sg:address":"2405 Meridian St N",
    "sg:city":"Huntsville",
    "sg:classifiers":[
        {
            "category":"Professional",
            "subcategory":"Accounting & Tax Preparation",
            "type":"Services"
        }
    ],
    "sg:phone":"+1 256 534 0273",
    "sg:postcode":"35811",
    "sg:province":"AL",
    "sg:tags":[
        "financial",
        "investment"
    ],
    "wof:name":"Quillin Financial Services",
    "wof:placetype":"venue"
},
  "geometry": {"coordinates":[-86.579902,34.754914],"type":"Point"}
}