{
  "type": "Feature",
  "properties": {
    "iso:country":"US",
    "sg:address":"1474 S Union Ave",
    "sg:city":"Ozark",
    "sg:classifiers":[
        {
            "category":"Freight",
            "type":"Transportation"
        },
        {
            "category":"Building & Trades",
            "subcategory":"Equipment Rental",
            "type":"Services"
        }
    ],
    "sg:phone":"+1 334 774 4413",
    "sg:postcode":"36360",
    "sg:province":"AL",
    "sg:tags":[
        "commercial",
        "storage"
    ],
    "wof:name":"Rental Center The",
    "wof:placetype":"venue"
},
  "geometry": {"coordinates":[-85.62327,31.432029],"type":"Point"}
}