{
  "type": "Feature",
  "properties": {
    "addr:full":"1425 Montgomery Hwy Birmingham AL 35216",
    "addr:housenumber":"1425",
    "addr:postcode":"35216",
    "addr:street":"Montgomery Hwy",
    "iso:country":"US",
    "sg:address":"1425 Montgomery Hwy",
    "sg:city":"Birmingham",
    "sg:classifiers":[
        {
            "category":"Shopping",
            "subcategory":"Books",
            "type":"Retail Goods"
        }
    ],
    "sg:phone":"+1 205 978 0600",
    "sg:postcode":"35216",
    "sg:province":"AL",
    "sg:tags":[
        "comic"
    ],
    "wof:name":"Kingdom Comics Inc",
    "wof:placetype":"venue"
},
  "geometry": {"coordinates":[-86.801717,33.418365],"type":"Point"}
}