{
  "type": "Feature",
  "properties": {
    "iso:country":"US",
    "sg:address":"1104 Valley Rd",
    "sg:city":"Jasper",
    "sg:classifiers":[
        {
            "category":"Professional",
            "subcategory":"Business Services",
            "type":"Services"
        }
    ],
    "sg:phone":"+1 205 384 4850",
    "sg:postcode":"35501",
    "sg:province":"AL",
    "wof:name":"Cain Sales Inc",
    "wof:placetype":"venue"
},
  "geometry": {"coordinates":[-87.258088,33.839689],"type":"Point"}
}