{
  "type": "Feature",
  "properties": {
    "iso:country":"US",
    "sg:address":"4027 Sewall Dr SW",
    "sg:city":"Huntsville",
    "sg:classifiers":[
        {
            "category":"Retail",
            "subcategory":"Laundry & Dry Cleaning",
            "type":"Services"
        }
    ],
    "sg:phone":"+1 256 882 6334",
    "sg:postcode":"35805",
    "sg:province":"AL",
    "sg:tags":[
        "house"
    ],
    "wof:name":"Total Carpet Care",
    "wof:placetype":"venue"
},
  "geometry": {"coordinates":[-86.60728400000001,34.693151],"type":"Point"}
}