{
  "type": "Feature",
  "properties": {
    "iso:country":"US",
    "sg:address":"37924 US Hwy 11",
    "sg:city":"Valley Head",
    "sg:classifiers":[
        {
            "category":"Personal",
            "subcategory":"Tanning Parlor",
            "type":"Services"
        }
    ],
    "sg:phone":"+1 256 635 6740",
    "sg:postcode":"35989",
    "sg:province":"AL",
    "sg:tags":[
        "salon"
    ],
    "wof:name":"Head Shed",
    "wof:placetype":"venue"
},
  "geometry": {"coordinates":[-85.628181,34.579836],"type":"Point"}
}