{
  "type": "Feature",
  "properties": {
    "iso:country":"US",
    "sg:address":"2841 Deatsville Hwy",
    "sg:city":"Deatsville",
    "sg:classifiers":[
        {
            "category":"Building & Trades",
            "subcategory":"Construction",
            "type":"Services"
        }
    ],
    "sg:phone":"+1 334 290 0374",
    "sg:postcode":"36022",
    "sg:province":"AL",
    "sg:tags":[
        "fencing",
        "contractor"
    ],
    "wof:name":"Fishermans Fencing",
    "wof:placetype":"venue"
},
  "geometry": {"coordinates":[-86.394221,32.550382],"type":"Point"}
}