{
  "type": "Feature",
  "properties": {
    "addr:full":"2930 Main St Millbrook AL 36054",
    "addr:housenumber":"2930",
    "addr:postcode":"36054",
    "addr:street":"Main St",
    "iso:country":"US",
    "sg:address":"2930 Main St",
    "sg:city":"Millbrook",
    "sg:classifiers":[
        {
            "category":"Wholesale",
            "subcategory":"Machinery & Supplies",
            "type":"Manufacturing & Wholesale Goods"
        }
    ],
    "sg:phone":"+1 334 290 1801",
    "sg:postcode":"36054",
    "sg:province":"AL",
    "sg:tags":[
        "equipment",
        "industrial"
    ],
    "wof:name":"K Industrial Supply",
    "wof:placetype":"venue"
},
  "geometry": {"coordinates":[-86.36049199999999,32.472175],"type":"Point"}
}