{
  "type": "Feature",
  "properties": {
    "iso:country":"US",
    "sg:address":"539 Miller Cir",
    "sg:city":"Pelham",
    "sg:classifiers":[
        {
            "category":"Insurance",
            "subcategory":"Insurance Agent",
            "type":"Services"
        }
    ],
    "sg:phone":"+1 205 991 2893",
    "sg:postcode":"35124",
    "sg:province":"AL",
    "sg:tags":[
        "surplus"
    ],
    "wof:name":"Allied Underwriting Inc",
    "wof:placetype":"venue"
},
  "geometry": {"coordinates":[-86.740996,33.36717],"type":"Point"}
}