{
  "type": "Feature",
  "properties": {
    "iso:country":"US",
    "sg:address":"217 W Grand Ave",
    "sg:city":"Rainbow City",
    "sg:classifiers":[
        {
            "category":"Retail",
            "subcategory":"Veterinary Services",
            "type":"Services"
        }
    ],
    "sg:phone":"+1 256 442 2967",
    "sg:postcode":"35906",
    "sg:province":"AL",
    "wof:name":"Animal Health Care",
    "wof:placetype":"venue"
},
  "geometry": {"coordinates":[-86.044333,33.959709],"type":"Point"}
}