{
  "type": "Feature",
  "properties": {
    "iso:country":"US",
    "sg:address":"301 W Inez Rd Ste 10",
    "sg:city":"Dothan",
    "sg:classifiers":[
        {
            "category":"Personal",
            "subcategory":"Nail Salon",
            "type":"Services"
        }
    ],
    "sg:phone":"+1 334 677 8448",
    "sg:postcode":"36301",
    "sg:province":"AL",
    "wof:name":"Nail Depot Ii",
    "wof:placetype":"venue"
},
  "geometry": {"coordinates":[-85.40203099999999,31.177231],"type":"Point"}
}