{
  "type": "Feature",
  "properties": {
    "iso:country":"US",
    "sg:address":"43020 White House Fork Rd Exd",
    "sg:city":"Bay Minette",
    "sg:classifiers":[
        {
            "category":"Organizations",
            "subcategory":"Religious Organization",
            "type":"Services"
        }
    ],
    "sg:phone":"+1 251 580 0406",
    "sg:postcode":"36507",
    "sg:province":"AL",
    "sg:tags":[
        "church"
    ],
    "wof:name":"Revelation Pentecostal Church",
    "wof:placetype":"venue"
},
  "geometry": {"coordinates":[-87.801637,30.851041],"type":"Point"}
}