{
  "type": "Feature",
  "properties": {
    "iso:country":"US",
    "sg:address":"22520 US Hwy 431",
    "sg:city":"Guntersville",
    "sg:classifiers":[
        {
            "category":"Organizations",
            "subcategory":"Religious Organization",
            "type":"Services"
        }
    ],
    "sg:phone":"+1 256 582 2734",
    "sg:postcode":"35976",
    "sg:province":"AL",
    "sg:tags":[
        "church"
    ],
    "wof:name":"Henryville United Methodist",
    "wof:placetype":"venue"
},
  "geometry": {"coordinates":[-86.262374,34.424052],"type":"Point"}
}