{
  "type": "Feature",
  "properties": {
    "iso:country":"US",
    "sg:address":"313 Iota Ave S",
    "sg:city":"Birmingham",
    "sg:classifiers":[
        {
            "category":"Organizations",
            "subcategory":"Religious Organization",
            "type":"Services"
        }
    ],
    "sg:phone":"+1 205 324 8083",
    "sg:postcode":"35205",
    "sg:province":"AL",
    "wof:name":"New Mt Zion Baptist Church",
    "wof:placetype":"venue"
},
  "geometry": {"coordinates":[-86.828413,33.499784],"type":"Point"}
}