{
  "type": "Feature",
  "properties": {
    "iso:country":"US",
    "sg:address":"2067 Co Rd 70",
    "sg:city":"Moulton",
    "sg:classifiers":[
        {
            "category":"Recreation",
            "type":"Entertainment"
        }
    ],
    "sg:phone":"+1 256 292 3262",
    "sg:postcode":"35650",
    "sg:province":"AL",
    "sg:tags":[
        "amusement"
    ],
    "wof:name":"Arthur Hawsey",
    "wof:placetype":"venue"
},
  "geometry": {"coordinates":[-87.303815,34.332035],"type":"Point"}
}