{
  "type": "Feature",
  "properties": {
    "addr:full":"3004 Mc Gehee Rd Montgomery AL 36111",
    "addr:housenumber":"3004",
    "addr:postcode":"36111",
    "addr:street":"Mc Gehee Rd",
    "iso:country":"US",
    "sg:address":"3004 Mc Gehee Rd",
    "sg:city":"Montgomery",
    "sg:classifiers":[
        {
            "category":"Food & Beverages",
            "subcategory":"Bakery",
            "type":"Retail Goods"
        }
    ],
    "sg:phone":"+1 334 284 8800",
    "sg:postcode":"36111",
    "sg:province":"AL",
    "sg:tags":[
        "cookie",
        "cracker"
    ],
    "wof:name":"Cookies By Design",
    "wof:placetype":"venue"
},
  "geometry": {"coordinates":[-86.258827,32.337647],"type":"Point"}
}