{
  "type": "Feature",
  "properties": {
    "iso:country":"US",
    "sg:address":"375 Mill Rd",
    "sg:city":"Madison",
    "sg:classifiers":[
        {
            "category":"Manufacturing",
            "subcategory":"Chemicals & Compounds",
            "type":"Manufacturing & Wholesale Goods"
        }
    ],
    "sg:phone":"+1 256 325 9697",
    "sg:postcode":"35758",
    "sg:province":"AL",
    "sg:tags":[
        "record",
        "immunization"
    ],
    "wof:name":"Records For A Lifetime Inc",
    "wof:placetype":"venue"
},
  "geometry": {"coordinates":[-86.75321,34.699583],"type":"Point"}
}