{
  "type": "Feature",
  "properties": {
    "iso:country":"US",
    "sg:address":"3022 State Rte 69",
    "sg:city":"Cullman",
    "sg:classifiers":[
        {
            "category":"Wholesale",
            "subcategory":"Construction Materials",
            "type":"Manufacturing & Wholesale Goods"
        }
    ],
    "sg:phone":"+1 256 287 2453",
    "sg:postcode":"35077",
    "sg:province":"AL",
    "sg:tags":[
        "timberland",
        "company",
        "timber"
    ],
    "wof:name":"C & L Land Co",
    "wof:placetype":"venue"
},
  "geometry": {"coordinates":[-86.911467,34.023306],"type":"Point"}
}