{
  "type": "Feature",
  "properties": {
    "iso:country":"US",
    "sg:address":"877 Miami Pl",
    "sg:city":"Birmingham",
    "sg:classifiers":[
        {
            "category":"Professional",
            "subcategory":"Business Services",
            "type":"Services"
        }
    ],
    "sg:phone":"+1 205 798 4385",
    "sg:postcode":"35214",
    "sg:province":"AL",
    "wof:name":"Hall Enterprises",
    "wof:placetype":"venue"
},
  "geometry": {"coordinates":[-86.87504,33.563919],"type":"Point"}
}