{
  "type": "Feature",
  "properties": {
    "addr:full":"12561 US Hwy 280 Jacksons Gap AL 36861",
    "addr:housenumber":"12561",
    "addr:postcode":"36861",
    "addr:street":"Us Hwy 280",
    "iso:country":"US",
    "sg:address":"12561 US Hwy 280",
    "sg:city":"Jacksons Gap",
    "sg:classifiers":[
        {
            "category":"Banks & Credit Unions",
            "subcategory":"Bank",
            "type":"Services"
        }
    ],
    "sg:phone":"+1 256 825 9256",
    "sg:postcode":"36861",
    "sg:province":"AL",
    "wof:name":"Bank Of Dadeville",
    "wof:placetype":"venue"
},
  "geometry": {"coordinates":[-85.82734000000001,32.883213],"type":"Point"}
}