{
  "type": "Feature",
  "properties": {
    "iso:country":"US",
    "sg:address":"3156 Pelham Pkwy",
    "sg:city":"Pelham",
    "sg:classifiers":[
        {
            "category":"Organizations",
            "subcategory":"Non-profit Organization",
            "type":"Services"
        }
    ],
    "sg:phone":"+1 205 685 9535",
    "sg:postcode":"35124",
    "sg:province":"AL",
    "sg:tags":[
        "info",
        "addiction",
        "abuse",
        "treatment",
        "drug"
    ],
    "wof:name":"Chilton-Shelby Mental Health",
    "wof:placetype":"venue"
},
  "geometry": {"coordinates":[-86.810558,33.286327],"type":"Point"}
}