{
  "type": "Feature",
  "properties": {
    "addr:full":"10705 Co Rd 121 Valley Head AL 35989",
    "addr:housenumber":"10705;121",
    "addr:postcode":"35989",
    "addr:street":"Co Rd;Valley Head",
    "iso:country":"US",
    "sg:address":"10705 Co Rd 121",
    "sg:city":"Valley Head",
    "sg:classifiers":[
        {
            "category":"Retail",
            "subcategory":"Repair Shop",
            "type":"Services"
        }
    ],
    "sg:phone":"+1 256 657 3328",
    "sg:postcode":"35989",
    "sg:province":"AL",
    "sg:tags":[
        "industrial",
        "machinery",
        "welding",
        "mfg"
    ],
    "wof:name":"High Point Machine Shop",
    "wof:placetype":"venue"
},
  "geometry": {"coordinates":[-85.686066,34.568898],"type":"Point"}
}