{
  "type": "Feature",
  "properties": {
    "iso:country":"US",
    "sg:address":"5156 US Hwy 78",
    "sg:city":"Oxford",
    "sg:classifiers":[
        {
            "category":"Professional",
            "subcategory":"Management & Consulting",
            "type":"Services"
        }
    ],
    "sg:phone":"+1 256 832 1030",
    "sg:postcode":"36203",
    "sg:province":"AL",
    "sg:tags":[
        "consultant",
        "publishing"
    ],
    "wof:name":"Sky Publishing",
    "wof:placetype":"venue"
},
  "geometry": {"coordinates":[-85.933255,33.597063],"type":"Point"}
}