{
  "type": "Feature",
  "properties": {
    "addr:full":"1406 E Pushmataha St Butler AL 36904",
    "addr:housenumber":"1406",
    "addr:postcode":"36904",
    "addr:street":"E Pushmataha St",
    "iso:country":"US",
    "sg:address":"1406 E Pushmataha St",
    "sg:city":"Butler",
    "sg:classifiers":[
        {
            "category":"Health Services",
            "subcategory":"Clinic",
            "type":"Services"
        }
    ],
    "sg:phone":"+1 205 459 7024",
    "sg:postcode":"36904",
    "sg:province":"AL",
    "sg:tags":[
        "specialty",
        "outpatient"
    ],
    "wof:name":"Rehab Advantage",
    "wof:placetype":"venue"
},
  "geometry": {"coordinates":[-88.20649400000001,32.08983],"type":"Point"}
}