{
  "type": "Feature",
  "properties": {
    "iso:country":"US",
    "sg:address":"1000 Blackwell Dairy Rd",
    "sg:city":"Jasper",
    "sg:classifiers":[
        {
            "category":"Organizations",
            "subcategory":"Religious Organization",
            "type":"Services"
        }
    ],
    "sg:phone":"+1 205 302 0601",
    "sg:postcode":"35504",
    "sg:province":"AL",
    "wof:name":"Friendship Independent Church",
    "wof:placetype":"venue"
},
  "geometry": {"coordinates":[-87.227283,33.856296],"type":"Point"}
}