{
  "type": "Feature",
  "properties": {
    "addr:full":"3829 2nd Ave Tuscaloosa AL 35405",
    "addr:housenumber":"3829",
    "addr:postcode":"35405",
    "addr:street":"2Nd Ave",
    "iso:country":"US",
    "sg:address":"3829 2nd Ave",
    "sg:city":"Tuscaloosa",
    "sg:classifiers":[
        {
            "category":"Building & Trades",
            "subcategory":"Cleaning & Sanitation",
            "type":"Services"
        }
    ],
    "sg:phone":"+1 205 758 2959",
    "sg:postcode":"35405",
    "sg:province":"AL",
    "sg:tags":[
        "maintenance"
    ],
    "wof:name":"Hurst Building Services LLC",
    "wof:placetype":"venue"
},
  "geometry": {"coordinates":[-87.539186,33.173215],"type":"Point"}
}