{
  "type": "Feature",
  "properties": {
    "iso:country":"US",
    "sg:address":"5401 Candlewood Dr",
    "sg:city":"Northport",
    "sg:classifiers":[
        {
            "category":"Building & Trades",
            "subcategory":"Construction",
            "type":"Services"
        }
    ],
    "sg:phone":"+1 205 339 6264",
    "sg:postcode":"35473",
    "sg:province":"AL",
    "sg:tags":[
        "residential",
        "nonresidential"
    ],
    "wof:name":"Candlewood Construction",
    "wof:placetype":"venue"
},
  "geometry": {"coordinates":[-87.61048599999999,33.259556],"type":"Point"}
}