{
  "type": "Feature",
  "properties": {
    "iso:country":"US",
    "sg:address":"106 N McCleskey St",
    "sg:city":"Boaz",
    "sg:classifiers":[
        {
            "category":"Health Services",
            "subcategory":"Chiropractor",
            "type":"Services"
        }
    ],
    "sg:phone":"+1 256 593 6363",
    "sg:postcode":"35957",
    "sg:province":"AL",
    "wof:name":"Galloway Chiropractic Ctr",
    "wof:placetype":"venue"
},
  "geometry": {"coordinates":[-86.156763,34.19915],"type":"Point"}
}