{
  "type": "Feature",
  "properties": {
    "iso:country":"US",
    "sg:address":"1734 Co Rd 339",
    "sg:city":"Russellville",
    "sg:classifiers":[
        {
            "category":"Retail",
            "subcategory":"Auto Repair",
            "type":"Services"
        }
    ],
    "sg:phone":"+1 256 331 0119",
    "sg:postcode":"35654",
    "sg:province":"AL",
    "sg:tags":[
        "general"
    ],
    "wof:name":"Turners Automotive",
    "wof:placetype":"venue"
},
  "geometry": {"coordinates":[-87.530411,34.470943],"type":"Point"}
}