{
  "type": "Feature",
  "properties": {
    "iso:country":"US",
    "sg:address":"2486 Co Rd 85",
    "sg:city":"Clanton",
    "sg:classifiers":[
        {
            "category":"Building & Trades",
            "subcategory":"Construction",
            "type":"Services"
        }
    ],
    "sg:phone":"+1 205 755 3271",
    "sg:postcode":"35046",
    "sg:province":"AL",
    "sg:tags":[
        "general",
        "contractor"
    ],
    "wof:name":"RTM Construction",
    "wof:placetype":"venue"
},
  "geometry": {"coordinates":[-86.585618,32.833733],"type":"Point"}
}