{
  "type": "Feature",
  "properties": {
    "iso:country":"US",
    "sg:address":"5601 Oporto Madrid Blvd S",
    "sg:city":"Birmingham",
    "sg:classifiers":[
        {
            "category":"Arena",
            "subcategory":"Sports Club",
            "type":"Entertainment"
        }
    ],
    "sg:phone":"+1 205 956 9011",
    "sg:postcode":"35210",
    "sg:province":"AL",
    "sg:tags":[
        "athletic",
        "fields",
        "stadium"
    ],
    "wof:name":"Lawson Field Stadium",
    "wof:placetype":"venue"
},
  "geometry": {"coordinates":[-86.71952,33.537023],"type":"Point"}
}