{
  "type": "Feature",
  "properties": {
    "iso:country":"US",
    "sg:address":"144 1st St S",
    "sg:city":"Alabaster",
    "sg:classifiers":[
        {
            "category":"Professional",
            "subcategory":"Accounting & Tax Preparation",
            "type":"Services"
        }
    ],
    "sg:phone":"+1 205 663 7987",
    "sg:postcode":"35007",
    "sg:province":"AL",
    "sg:tags":[
        "accountant"
    ],
    "wof:name":"Harry Harrison CPA",
    "wof:placetype":"venue"
},
  "geometry": {"coordinates":[-86.80403,33.228545],"type":"Point"}
}