{
  "type": "Feature",
  "properties": {
    "iso:country":"US",
    "sg:address":"215 Abingdon Ave NW",
    "sg:city":"Huntsville",
    "sg:classifiers":[
        {
            "category":"Social Services",
            "type":"Services"
        }
    ],
    "sg:phone":"+1 256 534 6060",
    "sg:postcode":"35801",
    "sg:province":"AL",
    "sg:tags":[
        "youth",
        "organization",
        "center"
    ],
    "sg:website":"www.bgchsv.com",
    "wof:name":"Boys & Girls Club Learning Ctr",
    "wof:placetype":"venue"
},
  "geometry": {"coordinates":[-86.58732500000001,34.74545],"type":"Point"}
}