{
  "type": "Feature",
  "properties": {
    "iso:country":"US",
    "sg:address":"7555 State Rte 69",
    "sg:city":"Cullman",
    "sg:classifiers":[
        {
            "category":"Government",
            "subcategory":"Fire Station",
            "type":"Public Place"
        }
    ],
    "sg:phone":"+1 256 796 5000",
    "sg:postcode":"35058",
    "sg:province":"AL",
    "sg:tags":[
        "department"
    ],
    "wof:name":"Fairview Fire Dept",
    "wof:placetype":"venue"
},
  "geometry": {"coordinates":[-86.686487,34.245847],"type":"Point"}
}