{
  "type": "Feature",
  "properties": {
    "iso:country":"US",
    "sg:address":"3060 Friendship Rd",
    "sg:city":"Arab",
    "sg:phone":"+1 256 586 5311",
    "sg:postcode":"35016",
    "sg:province":"AL",
    "sg:tags":[
        "farm",
        "field",
        "crop"
    ],
    "wof:name":"James White",
    "wof:placetype":"venue"
},
  "geometry": {"coordinates":[-86.46986200000001,34.366807],"type":"Point"}
}