{
  "type": "Feature",
  "properties": {
    "addr:full":"4885 Coosada Rd Coosada AL 36020",
    "addr:housenumber":"4885",
    "addr:postcode":"36020",
    "addr:street":"Coosada Rd",
    "iso:country":"US",
    "sg:address":"4885 Coosada Rd",
    "sg:city":"Coosada",
    "sg:classifiers":[
        {
            "category":"Organizations",
            "subcategory":"Religious Organization",
            "type":"Services"
        }
    ],
    "sg:phone":"+1 334 285 1412",
    "sg:postcode":"36020",
    "sg:province":"AL",
    "sg:tags":[
        "church"
    ],
    "wof:name":"Jackson Chapel AME Zion Church",
    "wof:placetype":"venue"
},
  "geometry": {"coordinates":[-86.347855,32.493783],"type":"Point"}
}