{
  "type": "Feature",
  "properties": {
    "addr:full":"5955 Highway 72 E Gurley AL 35748",
    "addr:housenumber":"5955",
    "addr:postcode":"35748",
    "addr:street":"Highway 72 E Gurley",
    "iso:country":"US",
    "sg:address":"5955 Highway 72 E",
    "sg:city":"Gurley",
    "sg:classifiers":[
        {
            "category":"Restaurant",
            "type":"Food & Drink"
        }
    ],
    "sg:menulink":"http://www.allmenus.com/al/gurley/121050-subway/menu/",
    "sg:phone":"+1 256 776 2232",
    "sg:postcode":"35748",
    "sg:province":"AL",
    "sg:tags":[
        "american",
        "sandwich"
    ],
    "wof:name":"Subway",
    "wof:placetype":"venue"
},
  "geometry": {"coordinates":[-86.38699800000001,34.701089],"type":"Point"}
}