{
  "type": "Feature",
  "properties": {
    "addr:full":"602 Clift Dr Madison AL 35758",
    "addr:housenumber":"602",
    "addr:postcode":"35758",
    "addr:street":"Clift Dr",
    "iso:country":"US",
    "sg:address":"602 Clift Dr",
    "sg:city":"Madison",
    "sg:classifiers":[
        {
            "category":"Organizations",
            "subcategory":"Labor Organization",
            "type":"Services"
        }
    ],
    "sg:phone":"+1 256 464 5139",
    "sg:postcode":"35758",
    "sg:province":"AL",
    "wof:name":"I A M A W District Lodge 75",
    "wof:placetype":"venue"
},
  "geometry": {"coordinates":[-86.737162,34.700252],"type":"Point"}
}