{
  "type": "Feature",
  "properties": {
    "iso:country":"US",
    "sg:address":"2518 Jarvis St SW",
    "sg:city":"Decatur",
    "sg:classifiers":[
        {
            "category":"Professional",
            "subcategory":"Computer Services",
            "type":"Services"
        }
    ],
    "sg:phone":"+1 256 353 0473",
    "sg:postcode":"35603",
    "sg:province":"AL",
    "sg:tags":[
        "related"
    ],
    "wof:name":"Tro Associates Inc",
    "wof:placetype":"venue"
},
  "geometry": {"coordinates":[-87.03399,34.578409],"type":"Point"}
}