{
  "type": "Feature",
  "properties": {
    "iso:country":"US",
    "sg:address":"1516 Tallapoosa St",
    "sg:city":"Alexander City",
    "sg:classifiers":[
        {
            "category":"Building & Trades",
            "subcategory":"Landscaping Services",
            "type":"Services"
        }
    ],
    "sg:phone":"+1 256 329 1901",
    "sg:postcode":"35010",
    "sg:province":"AL",
    "sg:tags":[
        "garden",
        "supply",
        "contractor",
        "planning",
        "architect",
        "landscape"
    ],
    "wof:name":"Hill Top Nursery & Landscaping",
    "wof:placetype":"venue"
},
  "geometry": {"coordinates":[-85.939521,32.948178],"type":"Point"}
}