{
  "type": "Feature",
  "properties": {
    "iso:country":"US",
    "sg:address":"2370 Hillcrest Rd",
    "sg:city":"Mobile",
    "sg:classifiers":[
        {
            "category":"Retail",
            "subcategory":"Laundry & Dry Cleaning",
            "type":"Services"
        }
    ],
    "sg:phone":"+1 251 660 2408",
    "sg:postcode":"36695",
    "sg:province":"AL",
    "sg:tags":[
        "curtain",
        "drapery",
        "cleaners"
    ],
    "wof:name":"Omni Clean",
    "wof:placetype":"venue"
},
  "geometry": {"coordinates":[-88.190911,30.63725],"type":"Point"}
}