{
  "type": "Feature",
  "properties": {
    "iso:country":"US",
    "sg:address":"9120 Airport Blvd",
    "sg:city":"Mobile",
    "sg:classifiers":[
        {
            "category":"Food & Beverages",
            "subcategory":"Meat & Fish",
            "type":"Retail Goods"
        }
    ],
    "sg:phone":"+1 251 633 3285",
    "sg:postcode":"36608",
    "sg:province":"AL",
    "wof:name":"West Mobile Seafood",
    "wof:placetype":"venue"
},
  "geometry": {"coordinates":[-88.266728,30.671778],"type":"Point"}
}