{
  "type": "Feature",
  "properties": {
    "iso:country":"US",
    "sg:address":"281 Lyon Ln",
    "sg:city":"Birmingham",
    "sg:classifiers":[
        {
            "category":"Building & Trades",
            "subcategory":"Construction",
            "type":"Services"
        }
    ],
    "sg:phone":"+1 205 943 0071",
    "sg:postcode":"35211",
    "sg:province":"AL",
    "sg:tags":[
        "company",
        "holding"
    ],
    "wof:name":"H & P Holding Corporation",
    "wof:placetype":"venue"
},
  "geometry": {"coordinates":[-86.85208,33.442484],"type":"Point"}
}