{
  "type": "Feature",
  "properties": {
    "addr:full":"915 US Hwy 98 Daphne AL 36526",
    "addr:housenumber":"915",
    "addr:postcode":"36526",
    "addr:street":"Us Hwy 98",
    "iso:country":"US",
    "sg:address":"915 US Hwy 98",
    "sg:city":"Daphne",
    "sg:classifiers":[
        {
            "category":"Building & Trades",
            "subcategory":"Equipment Rental",
            "type":"Services"
        }
    ],
    "sg:phone":"+1 251 626 8244",
    "sg:postcode":"36526",
    "sg:province":"AL",
    "sg:tags":[
        "yard"
    ],
    "wof:name":"DRC Rental Ctr",
    "wof:placetype":"venue"
},
  "geometry": {"coordinates":[-87.88919300000001,30.545536],"type":"Point"}
}