{
  "type": "Feature",
  "properties": {
    "iso:country":"US",
    "sg:address":"5900 8th St S",
    "sg:city":"Bessemer",
    "sg:classifiers":[
        {
            "category":"Organizations",
            "subcategory":"Religious Organization",
            "type":"Services"
        }
    ],
    "sg:phone":"+1 205 424 8600",
    "sg:postcode":"35020",
    "sg:province":"AL",
    "sg:tags":[
        "church"
    ],
    "wof:name":"Greater Highway Church",
    "wof:placetype":"venue"
},
  "geometry": {"coordinates":[-86.923217,33.426519],"type":"Point"}
}