{
  "type": "Feature",
  "properties": {
    "addr:full":"1008 S Bell St Dothan AL 36301",
    "addr:housenumber":"1008",
    "addr:postcode":"36301",
    "addr:street":"S Bell St",
    "iso:country":"US",
    "sg:address":"1008 S Bell St",
    "sg:city":"Dothan",
    "sg:classifiers":[
        {
            "category":"Personal",
            "subcategory":"Beauty Salon",
            "type":"Services"
        }
    ],
    "sg:phone":"+1 334 671 0131",
    "sg:postcode":"36301",
    "sg:province":"AL",
    "wof:name":"Perfect Divas",
    "wof:placetype":"venue"
},
  "geometry": {"coordinates":[-85.399137,31.206684],"type":"Point"}
}