{
  "type": "Feature",
  "properties": {
    "iso:country":"US",
    "sg:address":"22095 Compton Rd",
    "sg:city":"Athens",
    "sg:classifiers":[
        {
            "category":"Manufacturing",
            "subcategory":"Printing",
            "type":"Manufacturing & Wholesale Goods"
        }
    ],
    "sg:phone":"+1 256 233 3276",
    "sg:postcode":"35613",
    "sg:province":"AL",
    "sg:tags":[
        "commercial",
        "lithographic"
    ],
    "wof:name":"M-Press Printing Co",
    "wof:placetype":"venue"
},
  "geometry": {"coordinates":[-86.928525,34.832862],"type":"Point"}
}