{
  "type": "Feature",
  "properties": {
    "addr:full":"2964 Pelham Pkwy Pelham AL 35124",
    "addr:housenumber":"2964",
    "addr:postcode":"35124",
    "addr:street":"Pelham Pkwy",
    "iso:country":"US",
    "sg:address":"2964 Pelham Pkwy",
    "sg:city":"Pelham",
    "sg:classifiers":[
        {
            "category":"Banks & Credit Unions",
            "subcategory":"Bank",
            "type":"Services"
        }
    ],
    "sg:phone":"+1 205 663 0723",
    "sg:postcode":"35124",
    "sg:province":"AL",
    "wof:name":"Regions",
    "wof:placetype":"venue"
},
  "geometry": {"coordinates":[-86.81164,33.296484],"type":"Point"}
}