{
  "type": "Feature",
  "properties": {
    "iso:country":"US",
    "sg:address":"522 Colony Rd",
    "sg:city":"Hanceville",
    "sg:classifiers":[
        {
            "category":"Organizations",
            "subcategory":"Religious Organization",
            "type":"Services"
        }
    ],
    "sg:phone":"+1 256 287 2150",
    "sg:postcode":"35077",
    "sg:province":"AL",
    "wof:name":"Fairview Baptist Church",
    "wof:placetype":"venue"
},
  "geometry": {"coordinates":[-86.887663,33.944341],"type":"Point"}
}