{
  "type": "Feature",
  "properties": {
    "iso:country":"US",
    "sg:address":"2018 Womack Rd",
    "sg:city":"Birmingham",
    "sg:classifiers":[
        {
            "category":"Building & Trades",
            "subcategory":"Construction",
            "type":"Services"
        }
    ],
    "sg:phone":"+1 205 956 9810",
    "sg:postcode":"35210",
    "sg:province":"AL",
    "sg:tags":[
        "welder"
    ],
    "wof:name":"N L Barnes Inc",
    "wof:placetype":"venue"
},
  "geometry": {"coordinates":[-86.619181,33.561655],"type":"Point"}
}