{
  "type": "Feature",
  "properties": {
    "addr:full":"1572 Mill Sq Alexander City AL 35010",
    "addr:housenumber":"1572",
    "addr:postcode":"35010",
    "addr:street":"Mill Sq",
    "iso:country":"US",
    "sg:address":"1572 Mill Sq",
    "sg:city":"Alexander City",
    "sg:classifiers":[
        {
            "category":"Wholesale",
            "subcategory":"Medical Equipment & Supplies",
            "type":"Manufacturing & Wholesale Goods"
        },
        {
            "category":"Health Services",
            "subcategory":"Doctor",
            "type":"Services"
        }
    ],
    "sg:phone":"+1 256 329 8401",
    "sg:postcode":"35010",
    "sg:province":"AL",
    "sg:tags":[
        "dental"
    ],
    "wof:name":"Tooth Masters",
    "wof:placetype":"venue"
},
  "geometry": {"coordinates":[-85.971504,32.935547],"type":"Point"}
}