{
  "type": "Feature",
  "properties": {
    "iso:country":"US",
    "sg:address":"2720 7th Ave S",
    "sg:city":"Birmingham",
    "sg:classifiers":[
        {
            "category":"Wholesale",
            "subcategory":"Electrical",
            "type":"Manufacturing & Wholesale Goods"
        }
    ],
    "sg:phone":"+1 205 870 0274",
    "sg:postcode":"35233",
    "sg:province":"AL",
    "sg:tags":[
        "control"
    ],
    "sg:website":"www.controlandpower.com",
    "wof:name":"Control & Power Inc",
    "wof:placetype":"venue"
},
  "geometry": {"coordinates":[-86.79001,33.510641],"type":"Point"}
}