{
  "type": "Feature",
  "properties": {
    "iso:country":"US",
    "sg:address":"1410 Emory Folmar Blvd",
    "sg:city":"Montgomery",
    "sg:classifiers":[
        {
            "category":"Wholesale",
            "subcategory":"Construction Materials",
            "type":"Manufacturing & Wholesale Goods"
        }
    ],
    "sg:phone":"+1 334 272 8121",
    "sg:postcode":"36110",
    "sg:province":"AL",
    "sg:tags":[
        "brick",
        "common",
        "face"
    ],
    "wof:name":"Capital Brick Co",
    "wof:placetype":"venue"
},
  "geometry": {"coordinates":[-86.258965,32.415089],"type":"Point"}
}