{
  "type": "Feature",
  "properties": {
    "iso:country":"US",
    "sg:address":"2149 Jefferson St",
    "sg:city":"Auburn",
    "sg:classifiers":[
        {
            "category":"Building & Trades",
            "subcategory":"Construction",
            "type":"Services"
        }
    ],
    "sg:phone":"+1 334 887 2367",
    "sg:postcode":"36830",
    "sg:province":"AL",
    "sg:tags":[
        "house"
    ],
    "wof:name":"Crast A Tindal",
    "wof:placetype":"venue"
},
  "geometry": {"coordinates":[-85.439964,32.579115],"type":"Point"}
}