{
  "type": "Feature",
  "properties": {
    "iso:country":"US",
    "sg:address":"900 S Court St",
    "sg:city":"Montgomery",
    "sg:classifiers":[
        {
            "category":"Organizations",
            "subcategory":"Religious Organization",
            "type":"Services"
        }
    ],
    "sg:phone":"+1 334 264 0251",
    "sg:postcode":"36104",
    "sg:province":"AL",
    "sg:tags":[
        "church"
    ],
    "wof:name":"Strait Gate Christian Center",
    "wof:placetype":"venue"
},
  "geometry": {"coordinates":[-86.308657,32.363459],"type":"Point"}
}