{
  "type": "Feature",
  "properties": {
    "iso:country":"US",
    "sg:address":"1293 Hueytown Rd",
    "sg:city":"Bessemer",
    "sg:classifiers":[
        {
            "category":"Restaurant",
            "type":"Food & Drink"
        }
    ],
    "sg:phone":"+1 205 491 2120",
    "sg:postcode":"35023",
    "sg:province":"AL",
    "sg:tags":[
        "tea",
        "eating",
        "rooms"
    ],
    "wof:name":"Candle Lite Tea Room",
    "wof:placetype":"venue"
},
  "geometry": {"coordinates":[-86.994158,33.441943],"type":"Point"}
}