{
  "type": "Feature",
  "properties": {
    "addr:full":"250 N Water St Mobile AL 36602",
    "addr:housenumber":"250",
    "addr:postcode":"36602",
    "addr:street":"N Water St",
    "iso:country":"US",
    "sg:address":"250 N Water St",
    "sg:city":"Mobile",
    "sg:classifiers":[
        {
            "category":"Government",
            "subcategory":"Office",
            "type":"Public Place"
        }
    ],
    "sg:phone":"+1 251 433 1151",
    "sg:postcode":"36602",
    "sg:province":"AL",
    "wof:name":"Foreign Trade Relations Comm",
    "wof:placetype":"venue"
},
  "geometry": {"coordinates":[-88.04114800000001,30.697076],"type":"Point"}
}