{
  "type": "Feature",
  "properties": {
    "addr:full":"3625 5th Ave S Birmingham AL 35222",
    "addr:housenumber":"3625",
    "addr:postcode":"35222",
    "addr:street":"5Th Ave S",
    "iso:country":"US",
    "sg:address":"3625 5th Ave S",
    "sg:city":"Birmingham",
    "sg:classifiers":[
        {
            "category":"Communications",
            "subcategory":"Film & Video Production",
            "type":"Services"
        }
    ],
    "sg:phone":"+1 205 595 5220",
    "sg:postcode":"35222",
    "sg:province":"AL",
    "sg:tags":[
        "motion"
    ],
    "wof:name":"Transmedia Music",
    "wof:placetype":"venue"
},
  "geometry": {"coordinates":[-86.778357,33.519033],"type":"Point"}
}