{
  "type": "Feature",
  "properties": {
    "iso:country":"US",
    "sg:address":"2120 Diane Cir",
    "sg:city":"Alabaster",
    "sg:classifiers":[
        {
            "category":"Professional",
            "subcategory":"Business Services",
            "type":"Services"
        }
    ],
    "sg:phone":"+1 205 621 4797",
    "sg:postcode":"35007",
    "sg:province":"AL",
    "wof:name":"Arant Enterprises Inc",
    "wof:placetype":"venue"
},
  "geometry": {"coordinates":[-86.815829,33.206537],"type":"Point"}
}