{
  "type": "Feature",
  "properties": {
    "iso:country":"US",
    "sg:address":"572 Holcombe Ave",
    "sg:city":"Mobile",
    "sg:classifiers":[
        {
            "category":"Real Estate",
            "subcategory":"Real Estate Agent",
            "type":"Services"
        }
    ],
    "sg:phone":"+1 251 476 1113",
    "sg:postcode":"36606",
    "sg:province":"AL",
    "sg:tags":[
        "appraiser"
    ],
    "wof:name":"Thomas Bealle Assoc Inc",
    "wof:placetype":"venue"
},
  "geometry": {"coordinates":[-88.089522,30.672759],"type":"Point"}
}