{
  "type": "Feature",
  "properties": {
    "iso:country":"US",
    "sg:address":"28960 US Hwy 98",
    "sg:city":"Daphne",
    "sg:classifiers":[
        {
            "category":"Restaurant",
            "type":"Food & Drink"
        }
    ],
    "sg:phone":"+1 251 626 2623",
    "sg:postcode":"36526",
    "sg:province":"AL",
    "sg:tags":[
        "eating"
    ],
    "wof:name":"El Rancho Mexican Restaurant",
    "wof:placetype":"venue"
},
  "geometry": {"coordinates":[-87.912403,30.64942],"type":"Point"}
}