{
  "type": "Feature",
  "properties": {
    "iso:country":"US",
    "sg:address":"5012 Holmes Ave NW",
    "sg:city":"Huntsville",
    "sg:classifiers":[
        {
            "category":"Professional",
            "subcategory":"Management & Consulting",
            "type":"Services"
        }
    ],
    "sg:phone":"+1 256 837 4484",
    "sg:postcode":"35816",
    "sg:province":"AL",
    "sg:tags":[
        "business"
    ],
    "wof:name":"Jackson Coy Consulting",
    "wof:placetype":"venue"
},
  "geometry": {"coordinates":[-86.647559,34.730495],"type":"Point"}
}