{
  "type": "Feature",
  "properties": {
    "addr:full":"15095 US Hwy 278 W Attalla AL 35954",
    "addr:postcode":"15095;35954",
    "addr:street":"Us Hwy 278 W Attalla",
    "iso:country":"US",
    "sg:address":"15095 US Hwy 278 W",
    "sg:city":"Attalla",
    "sg:classifiers":[
        {
            "category":"Organizations",
            "subcategory":"Religious Organization",
            "type":"Services"
        }
    ],
    "sg:phone":"+1 256 538 2101",
    "sg:postcode":"35954",
    "sg:province":"AL",
    "sg:tags":[
        "church"
    ],
    "wof:name":"Visions Temple Church",
    "wof:placetype":"venue"
},
  "geometry": {"coordinates":[-86.129503,34.040305],"type":"Point"}
}