{
  "type": "Feature",
  "properties": {
    "iso:country":"US",
    "sg:address":"4164 Troy Hwy",
    "sg:city":"Montgomery",
    "sg:classifiers":[
        {
            "category":"Building & Trades",
            "subcategory":"Cleaning & Sanitation",
            "type":"Services"
        }
    ],
    "sg:phone":"+1 334 281 7754",
    "sg:postcode":"36116",
    "sg:province":"AL",
    "sg:tags":[
        "janitor",
        "maintenance"
    ],
    "sg:website":"www.pfmi.net",
    "wof:name":"Professional Facilities Mgmt",
    "wof:placetype":"venue"
},
  "geometry": {"coordinates":[-86.233669,32.319292],"type":"Point"}
}