{
  "type": "Feature",
  "properties": {
    "addr:full":"205 E Lee St Enterprise AL 36330",
    "addr:housenumber":"205",
    "addr:postcode":"36330",
    "addr:street":"E Lee St",
    "iso:country":"US",
    "sg:address":"205 E Lee St",
    "sg:city":"Enterprise",
    "sg:classifiers":[
        {
            "category":"Wholesale",
            "subcategory":"Medical Equipment & Supplies",
            "type":"Manufacturing & Wholesale Goods"
        }
    ],
    "sg:phone":"+1 334 347 6767",
    "sg:postcode":"36330",
    "sg:province":"AL",
    "sg:tags":[
        "physician",
        "surgeon"
    ],
    "wof:name":"Southern Medical Eqpt Corp",
    "wof:placetype":"venue"
},
  "geometry": {"coordinates":[-85.852462,31.316825],"type":"Point"}
}