{
  "type": "Feature",
  "properties": {
    "addr:full":"117 Main St Grove Hill AL 36451",
    "addr:housenumber":"117",
    "addr:postcode":"36451",
    "addr:street":"Main St;Hill",
    "iso:country":"US",
    "sg:address":"117 Main St",
    "sg:city":"Grove Hill",
    "sg:classifiers":[
        {
            "category":"Professional",
            "subcategory":"Lawyer & Legal Services",
            "type":"Services"
        }
    ],
    "sg:phone":"+1 251 275 4949",
    "sg:postcode":"36451",
    "sg:province":"AL",
    "sg:tags":[
        "attorney"
    ],
    "wof:name":"Spencer B Walker",
    "wof:placetype":"venue"
},
  "geometry": {"coordinates":[-87.77759500000001,31.708738],"type":"Point"}
}