{
  "type": "Feature",
  "properties": {
    "iso:country":"US",
    "sg:address":"3690 State Rte 20",
    "sg:city":"Florence",
    "sg:classifiers":[
        {
            "category":"Shopping",
            "subcategory":"Bicycles & Sporting Goods",
            "type":"Retail Goods"
        }
    ],
    "sg:phone":"+1 256 764 3098",
    "sg:postcode":"35630",
    "sg:province":"AL",
    "wof:name":"Box Excavating & Paving",
    "wof:placetype":"venue"
},
  "geometry": {"coordinates":[-87.72219,34.814255],"type":"Point"}
}