{
  "type": "Feature",
  "properties": {
    "addr:full":"69 College St Gilbertown AL 36908",
    "addr:housenumber":"69",
    "addr:postcode":"36908",
    "addr:street":"College",
    "iso:country":"US",
    "sg:address":"69 College St",
    "sg:city":"Gilbertown",
    "sg:classifiers":[
        {
            "category":"Real Estate",
            "subcategory":"Real Estate Operator",
            "type":"Services"
        }
    ],
    "sg:phone":"+1 251 843 5836",
    "sg:postcode":"36908",
    "sg:province":"AL",
    "sg:tags":[
        "apartment"
    ],
    "wof:name":"Park Towne Apartments",
    "wof:placetype":"venue"
},
  "geometry": {"coordinates":[-88.316827,31.875147],"type":"Point"}
}