{
  "type": "Feature",
  "properties": {
    "addr:full":"111 Canal St Mobile AL 36603",
    "addr:housenumber":"111",
    "addr:postcode":"36603",
    "addr:street":"Canal St",
    "iso:country":"US",
    "sg:address":"111 Canal St",
    "sg:city":"Mobile",
    "sg:classifiers":[
        {
            "category":"Government",
            "subcategory":"Office",
            "type":"Public Place"
        }
    ],
    "sg:phone":"+1 251 574 3324",
    "sg:postcode":"36603",
    "sg:province":"AL",
    "wof:name":"Community Svc",
    "wof:placetype":"venue"
},
  "geometry": {"coordinates":[-88.04080500000001,30.683188],"type":"Point"}
}