{
  "type": "Feature",
  "properties": {
    "iso:country":"US",
    "sg:address":"15337 US Hwy 31",
    "sg:city":"Hope Hull",
    "sg:classifiers":[
        {
            "category":"Freight",
            "type":"Transportation"
        }
    ],
    "sg:phone":"+1 334 284 3863",
    "sg:postcode":"36043",
    "sg:province":"AL",
    "sg:tags":[
        "operator",
        "local",
        "trucking"
    ],
    "wof:name":"Tommy Gray",
    "wof:placetype":"venue"
},
  "geometry": {"coordinates":[-86.372465,32.154573],"type":"Point"}
}