{
  "type": "Feature",
  "properties": {
    "iso:country":"US",
    "sg:address":"6541 W Andrews Ave",
    "sg:city":"Ozark",
    "sg:classifiers":[
        {
            "category":"Retail",
            "subcategory":"Auto Rental",
            "type":"Services"
        }
    ],
    "sg:phone":"+1 334 774 1732",
    "sg:postcode":"36360",
    "sg:province":"AL",
    "sg:tags":[
        "renting",
        "truck",
        "leasing"
    ],
    "wof:name":"U-Haul Co",
    "wof:placetype":"venue"
},
  "geometry": {"coordinates":[-85.70043099999999,31.385322],"type":"Point"}
}