{
  "type": "Feature",
  "properties": {
    "addr:full":"400 Limestone St NE Russellville AL 35653",
    "addr:housenumber":"400",
    "addr:postcode":"35653",
    "addr:street":"Limestone St Ne",
    "iso:country":"US",
    "sg:address":"400 Limestone St NE",
    "sg:city":"Russellville",
    "sg:classifiers":[
        {
            "category":"Organizations",
            "subcategory":"Religious Organization",
            "type":"Services"
        }
    ],
    "sg:phone":"+1 256 332 5451",
    "sg:postcode":"35653",
    "sg:province":"AL",
    "sg:tags":[
        "church"
    ],
    "wof:name":"Eastside Church Of Christ",
    "wof:placetype":"venue"
},
  "geometry": {"coordinates":[-87.725098,34.507352],"type":"Point"}
}