{
  "type": "Feature",
  "properties": {
    "addr:full":"14369 Blackburn Rd Athens AL 35611",
    "addr:housenumber":"14369",
    "addr:postcode":"35611",
    "addr:street":"Blackburn Rd",
    "iso:country":"US",
    "sg:address":"14369 Blackburn Rd",
    "sg:city":"Athens",
    "sg:classifiers":[
        {
            "category":"Retail",
            "subcategory":"Auto Repair",
            "type":"Services"
        },
        {
            "category":"Wholesale",
            "subcategory":"Auto Parts",
            "type":"Manufacturing & Wholesale Goods"
        }
    ],
    "sg:phone":"+1 256 233 2677",
    "sg:postcode":"35611",
    "sg:province":"AL",
    "sg:tags":[
        "transmission",
        "automobile",
        "rebuilt",
        "used",
        "general"
    ],
    "wof:name":"Pitts Auto Parts",
    "wof:placetype":"venue"
},
  "geometry": {"coordinates":[-87.05466800000001,34.762635],"type":"Point"}
}