{
  "type": "Feature",
  "properties": {
    "iso:country":"US",
    "sg:address":"3430 Atlanta Hwy",
    "sg:city":"Montgomery",
    "sg:classifiers":[
        {
            "category":"Restaurant",
            "type":"Food & Drink"
        }
    ],
    "sg:menulink":"http://www.allmenus.com/al/montgomery/231569-sonic/menu/",
    "sg:phone":"+1 334 396 6708",
    "sg:postcode":"36109",
    "sg:province":"AL",
    "sg:tags":[
        "burger",
        "american"
    ],
    "wof:name":"Sonic",
    "wof:placetype":"venue"
},
  "geometry": {"coordinates":[-86.258456,32.38496],"type":"Point"}
}