{
  "type": "Feature",
  "properties": {
    "iso:country":"US",
    "sg:address":"543 Tuscaloosa Ave SW",
    "sg:city":"Birmingham",
    "sg:classifiers":[
        {
            "category":"Retail",
            "subcategory":"Auto Repair",
            "type":"Services"
        }
    ],
    "sg:phone":"+1 205 781 3718",
    "sg:postcode":"35211",
    "sg:province":"AL",
    "sg:tags":[
        "transmission",
        "automotive",
        "general"
    ],
    "wof:name":"Hatcher Ron Auto & Transm Ctr",
    "wof:placetype":"venue"
},
  "geometry": {"coordinates":[-86.842069,33.500453],"type":"Point"}
}