{
  "type": "Feature",
  "properties": {
    "iso:country":"US",
    "sg:address":"2260 Pike Rd",
    "sg:city":"Pike Road",
    "sg:classifiers":[
        {
            "category":"Local Transit",
            "type":"Transportation"
        }
    ],
    "sg:phone":"+1 334 260 5583",
    "sg:postcode":"36064",
    "sg:province":"AL",
    "sg:tags":[
        "limousine"
    ],
    "wof:name":"Capitol Coach",
    "wof:placetype":"venue"
},
  "geometry": {"coordinates":[-86.094555,32.332237],"type":"Point"}
}