{
  "type": "Feature",
  "properties": {
    "addr:full":"39225 US Hwy 280 Sylacauga AL 35150",
    "addr:postcode":"39225;35150",
    "addr:street":"Us Hwy 280",
    "iso:country":"US",
    "sg:address":"39225 US Hwy 280",
    "sg:city":"Sylacauga",
    "sg:classifiers":[
        {
            "category":"Wholesale",
            "subcategory":"Farm Supplies",
            "type":"Manufacturing & Wholesale Goods"
        }
    ],
    "sg:phone":"+1 256 249 2527",
    "sg:postcode":"35150",
    "sg:province":"AL",
    "sg:tags":[
        "feed"
    ],
    "wof:name":"Oak Grove Feed & Tack LLC",
    "wof:placetype":"venue"
},
  "geometry": {"coordinates":[-86.307813,33.195216],"type":"Point"}
}