{
  "type": "Feature",
  "properties": {
    "iso:country":"US",
    "sg:address":"203 US Hwy 80",
    "sg:city":"Demopolis",
    "sg:classifiers":[
        {
            "category":"Health Services",
            "subcategory":"Doctor",
            "type":"Services"
        }
    ],
    "sg:phone":"+1 334 289 1517",
    "sg:postcode":"36732",
    "sg:province":"AL",
    "sg:tags":[
        "physician",
        "surgeon"
    ],
    "wof:name":"Fitz-Gerald & Perret Clinic",
    "wof:placetype":"venue"
},
  "geometry": {"coordinates":[-87.836148,32.503543],"type":"Point"}
}