{
  "type": "Feature",
  "properties": {
    "iso:country":"US",
    "sg:address":"2302 Seaton Pl",
    "sg:city":"Montgomery",
    "sg:classifiers":[
        {
            "category":"Organizations",
            "subcategory":"Professional Association",
            "type":"Services"
        }
    ],
    "sg:phone":"+1 334 271 1536",
    "sg:postcode":"36116",
    "sg:province":"AL",
    "wof:name":"Alabama Medical Directors Asso",
    "wof:placetype":"venue"
},
  "geometry": {"coordinates":[-86.173073,32.337625],"type":"Point"}
}