{
  "type": "Feature",
  "properties": {
    "addr:full":"560 Mountain Dr Springville AL 35146",
    "addr:housenumber":"560",
    "addr:postcode":"35146",
    "addr:street":"Mountain Dr",
    "iso:country":"US",
    "sg:address":"560 Mountain Dr",
    "sg:city":"Springville",
    "sg:classifiers":[
        {
            "category":"Organizations",
            "subcategory":"Religious Organization",
            "type":"Services"
        }
    ],
    "sg:phone":"+1 205 467 9770",
    "sg:postcode":"35146",
    "sg:province":"AL",
    "wof:name":"Solid Rock Baptist Church",
    "wof:placetype":"venue"
},
  "geometry": {"coordinates":[-86.460413,33.777095],"type":"Point"}
}