{
  "type": "Feature",
  "properties": {
    "addr:full":"524 E 24th Ave Gulf Shores AL 36542",
    "addr:housenumber":"524",
    "addr:postcode":"36542",
    "addr:street":"E 24Th Ave",
    "iso:country":"US",
    "sg:address":"524 E 24th Ave",
    "sg:city":"Gulf Shores",
    "sg:classifiers":[
        {
            "category":"Wholesale",
            "subcategory":"Seafood",
            "type":"Manufacturing & Wholesale Goods"
        }
    ],
    "sg:phone":"+1 251 968 2511",
    "sg:postcode":"36542",
    "sg:province":"AL",
    "wof:name":"Tropic Star Seafood Inc",
    "wof:placetype":"venue"
},
  "geometry": {"coordinates":[-87.677699,30.278049],"type":"Point"}
}