{
  "type": "Feature",
  "properties": {
    "iso:country":"US",
    "sg:address":"323 Airport Rd",
    "sg:city":"Auburn",
    "sg:classifiers":[
        {
            "category":"Utilities",
            "subcategory":"Mobile Phone",
            "type":"Services"
        }
    ],
    "sg:phone":"+1 334 826 9190",
    "sg:postcode":"36830",
    "sg:province":"AL",
    "sg:tags":[
        "telephone",
        "cellular"
    ],
    "wof:name":"Cingular Wireless",
    "wof:placetype":"venue"
},
  "geometry": {"coordinates":[-85.440005,32.613346],"type":"Point"}
}