{
  "type": "Feature",
  "properties": {
    "addr:full":"13745 US Hwy 411 Odenville AL 35120",
    "addr:housenumber":"13745",
    "addr:postcode":"35120",
    "addr:street":"Us Hwy 411",
    "iso:country":"US",
    "sg:address":"13745 US Hwy 411",
    "sg:city":"Odenville",
    "sg:classifiers":[
        {
            "category":"Social Services",
            "subcategory":"Child Care",
            "type":"Services"
        }
    ],
    "sg:phone":"+1 205 629 0203",
    "sg:postcode":"35120",
    "sg:province":"AL",
    "wof:name":"Calvary Community Day Care",
    "wof:placetype":"venue"
},
  "geometry": {"coordinates":[-86.40721600000001,33.676519],"type":"Point"}
}