{
  "type": "Feature",
  "properties": {
    "iso:country":"US",
    "sg:address":"112 Hayden St",
    "sg:city":"New Hope",
    "sg:classifiers":[
        {
            "category":"Shopping",
            "type":"Retail Goods"
        }
    ],
    "sg:phone":"+1 256 723 7793",
    "sg:postcode":"35760",
    "sg:province":"AL",
    "sg:tags":[
        "equipment",
        "telephone",
        "supply"
    ],
    "wof:name":"Triad Inc",
    "wof:placetype":"venue"
},
  "geometry": {"coordinates":[-86.395682,34.53808],"type":"Point"}
}