{
  "type": "Feature",
  "properties": {
    "addr:full":"780 Brookwood Vlg Birmingham AL 35209",
    "addr:housenumber":"780",
    "addr:postcode":"35209",
    "addr:street":"Brookwood Vlg",
    "iso:country":"US",
    "sg:address":"780 Brookwood Vlg",
    "sg:city":"Birmingham",
    "sg:classifiers":[
        {
            "category":"Restaurant",
            "type":"Food & Drink"
        }
    ],
    "sg:menulink":"http://www.allmenus.com/al/birmingham/179536-chick-fil-a/menu/",
    "sg:phone":"+1 205 871 1398",
    "sg:postcode":"35209",
    "sg:province":"AL",
    "sg:tags":[
        "wrap",
        "soup",
        "american",
        "sandwich",
        "salad"
    ],
    "wof:name":"Chick-fil-A",
    "wof:placetype":"venue"
},
  "geometry": {"coordinates":[-86.775211,33.467982],"type":"Point"}
}