{
  "type": "Feature",
  "properties": {
    "iso:country":"US",
    "sg:address":"2174 Pelham Pkwy",
    "sg:city":"Pelham",
    "sg:classifiers":[
        {
            "category":"Autos & Motor Vehicles",
            "subcategory":"Auto Supplies",
            "type":"Retail Goods"
        },
        {
            "category":"Retail",
            "subcategory":"Auto Repair",
            "type":"Services"
        }
    ],
    "sg:phone":"+1 205 982 1984",
    "sg:postcode":"35124",
    "sg:province":"AL",
    "sg:tags":[
        "clutch",
        "automobile",
        "brake",
        "equipment-service",
        "diagnostic",
        "air conditioning"
    ],
    "sg:website":"http://www.TheGarageInPelham.com",
    "wof:name":"The Garage",
    "wof:placetype":"venue"
},
  "geometry": {"coordinates":[-86.792441,33.338138],"type":"Point"}
}