{
  "type": "Feature",
  "properties": {
    "iso:country":"US",
    "sg:address":"1025 US Hwy 331",
    "sg:city":"Opp",
    "sg:classifiers":[
        {
            "category":"Wholesale",
            "subcategory":"Stationery",
            "type":"Manufacturing & Wholesale Goods"
        }
    ],
    "sg:phone":"+1 334 493 7943",
    "sg:postcode":"36467",
    "sg:province":"AL",
    "sg:tags":[
        "paper"
    ],
    "wof:name":"International Paper",
    "wof:placetype":"venue"
},
  "geometry": {"coordinates":[-86.249055,31.267407],"type":"Point"}
}