{
  "type": "Feature",
  "properties": {
    "iso:country":"US",
    "sg:address":"24955 US Hwy 31",
    "sg:city":"Jemison",
    "sg:classifiers":[
        {
            "category":"Education",
            "subcategory":"School",
            "type":"Public Place"
        }
    ],
    "sg:phone":"+1 205 688 2335",
    "sg:postcode":"35085",
    "sg:province":"AL",
    "wof:name":"Jemison Headstart Ctr",
    "wof:placetype":"venue"
},
  "geometry": {"coordinates":[-86.745923,32.962481],"type":"Point"}
}