{
  "type": "Feature",
  "properties": {
    "iso:country":"US",
    "sg:address":"5648 Dalphon Rd",
    "sg:city":"Montgomery",
    "sg:classifiers":[
        {
            "category":"Autos & Motor Vehicles",
            "subcategory":"Automobile Sales",
            "type":"Retail Goods"
        }
    ],
    "sg:phone":"+1 334 263 7783",
    "sg:postcode":"36117",
    "sg:province":"AL",
    "sg:tags":[
        "car",
        "dealer"
    ],
    "wof:name":"Reinhardt Motors Inc",
    "wof:placetype":"venue"
},
  "geometry": {"coordinates":[-86.207118,32.37842],"type":"Point"}
}