{
  "type": "Feature",
  "properties": {
    "iso:country":"US",
    "sg:address":"8006 Madison Pike",
    "sg:city":"Madison",
    "sg:classifiers":[
        {
            "category":"Wholesale",
            "subcategory":"Stationery",
            "type":"Manufacturing & Wholesale Goods"
        }
    ],
    "sg:phone":"+1 256 325 3305",
    "sg:postcode":"35758",
    "sg:province":"AL",
    "sg:tags":[
        "school",
        "supply"
    ],
    "wof:name":"Creative Learning Connection",
    "wof:placetype":"venue"
},
  "geometry": {"coordinates":[-86.71989499999999,34.706389],"type":"Point"}
}