{
  "type": "Feature",
  "properties": {
    "iso:country":"US",
    "sg:address":"145 N Chalkville Rd",
    "sg:city":"Trussville",
    "sg:classifiers":[
        {
            "category":"Health Services",
            "subcategory":"Doctor",
            "type":"Services"
        }
    ],
    "sg:phone":"+1 205 661 3737",
    "sg:postcode":"35173",
    "sg:province":"AL",
    "wof:name":"Jordan Michele MD PC",
    "wof:placetype":"venue"
},
  "geometry": {"coordinates":[-86.60904600000001,33.623755],"type":"Point"}
}