{
  "type": "Feature",
  "properties": {
    "iso:country":"US",
    "sg:address":"1712 Baker Holly Rd",
    "sg:city":"Clanton",
    "sg:classifiers":[
        {
            "category":"Recreation",
            "type":"Entertainment"
        }
    ],
    "sg:phone":"+1 205 755 3053",
    "sg:postcode":"35045",
    "sg:province":"AL",
    "sg:tags":[
        "club",
        "membership"
    ],
    "wof:name":"Shur Shot Inc",
    "wof:placetype":"venue"
},
  "geometry": {"coordinates":[-86.640457,32.817805],"type":"Point"}
}