{
  "type": "Feature",
  "properties": {
    "addr:full":"1115 Ann St Montgomery AL 36107",
    "addr:housenumber":"1115",
    "addr:postcode":"36107",
    "addr:street":"Ann St",
    "iso:country":"US",
    "sg:address":"1115 Ann St",
    "sg:city":"Montgomery",
    "sg:classifiers":[
        {
            "category":"Autos & Motor Vehicles",
            "subcategory":"Fuel & Gas Station",
            "type":"Retail Goods"
        }
    ],
    "sg:phone":"+1 334 262 5178",
    "sg:postcode":"36107",
    "sg:province":"AL",
    "sg:tags":[
        "oil"
    ],
    "wof:name":"Ann Street Amoco",
    "wof:placetype":"venue"
},
  "geometry": {"coordinates":[-86.27101399999999,32.368115],"type":"Point"}
}