{
  "type": "Feature",
  "properties": {
    "iso:country":"US",
    "sg:address":"7542 Wall Triana Hwy A",
    "sg:city":"Madison",
    "sg:classifiers":[
        {
            "category":"Arts & Performance",
            "subcategory":"Dance",
            "type":"Entertainment"
        }
    ],
    "sg:phone":"+1 256 772 2088",
    "sg:postcode":"35757",
    "sg:province":"AL",
    "sg:tags":[
        "instruction",
        "dancing"
    ],
    "wof:name":"Studio J Dance",
    "wof:placetype":"venue"
},
  "geometry": {"coordinates":[-86.749123,34.807513],"type":"Point"}
}