{
  "type": "Feature",
  "properties": {
    "iso:country":"US",
    "sg:address":"4569 Spearman Rd",
    "sg:city":"Pinson",
    "sg:classifiers":[
        {
            "category":"Professional",
            "subcategory":"Secretarial Services",
            "type":"Services"
        }
    ],
    "sg:phone":"+1 205 680 0881",
    "sg:postcode":"35126",
    "sg:province":"AL",
    "sg:tags":[
        "reporting"
    ],
    "wof:name":"Hudson Legal Secretarial Svcs",
    "wof:placetype":"venue"
},
  "geometry": {"coordinates":[-86.670477,33.68276],"type":"Point"}
}