{
  "type": "Feature",
  "properties": {
    "addr:full":"400 Bell St Enterprise AL 36330",
    "addr:housenumber":"400",
    "addr:postcode":"36330",
    "addr:street":"Bell St",
    "iso:country":"US",
    "sg:address":"400 Bell St",
    "sg:city":"Enterprise",
    "sg:classifiers":[
        {
            "category":"Professional",
            "type":"Services"
        }
    ],
    "sg:phone":"+1 334 308 1193",
    "sg:postcode":"36330",
    "sg:province":"AL",
    "wof:name":"Jones John",
    "wof:placetype":"venue"
},
  "geometry": {"coordinates":[-85.85247200000001,31.305386],"type":"Point"}
}