{
  "type": "Feature",
  "properties": {
    "iso:country":"US",
    "sg:address":"3261 Brook Highland Trce",
    "sg:city":"Birmingham",
    "sg:classifiers":[
        {
            "category":"Education",
            "subcategory":"Special Training",
            "type":"Public Place"
        }
    ],
    "sg:phone":"+1 205 995 1140",
    "sg:postcode":"35242",
    "sg:province":"AL",
    "sg:tags":[
        "tutoring"
    ],
    "wof:name":"Club Z In Home Tutoring Svc",
    "wof:placetype":"venue"
},
  "geometry": {"coordinates":[-86.67315499999999,33.430747],"type":"Point"}
}