{
  "type": "Feature",
  "properties": {
    "addr:full":"1415 Louisville St Montgomery AL 36104",
    "addr:housenumber":"1415",
    "addr:postcode":"36104",
    "addr:street":"Louisville St",
    "iso:country":"US",
    "sg:address":"1415 Louisville St",
    "sg:city":"Montgomery",
    "sg:classifiers":[
        {
            "category":"Home & Garden",
            "subcategory":"Building Materials",
            "type":"Retail Goods"
        }
    ],
    "sg:phone":"+1 334 834 5290",
    "sg:postcode":"36104",
    "sg:province":"AL",
    "sg:tags":[
        "wood",
        "preservative"
    ],
    "wof:name":"Koppers Industries",
    "wof:placetype":"venue"
},
  "geometry": {"coordinates":[-86.317757,32.397398],"type":"Point"}
}