{
  "type": "Feature",
  "properties": {
    "iso:country":"US",
    "sg:address":"1375 Heflin Ave W",
    "sg:city":"Birmingham",
    "sg:classifiers":[
        {
            "category":"Social Services",
            "subcategory":"Child Care",
            "type":"Services"
        },
        {
            "category":"Education",
            "subcategory":"Preschool",
            "type":"Public Place"
        },
        {
            "category":"Education",
            "subcategory":"School",
            "type":"Public Place"
        }
    ],
    "sg:phone":"+1 205 798 5430",
    "sg:postcode":"35214",
    "sg:province":"AL",
    "sg:tags":[
        "elementary",
        "day"
    ],
    "wof:name":"Beary Best of Care Christian Academy the",
    "wof:placetype":"venue"
},
  "geometry": {"coordinates":[-86.898201,33.563702],"type":"Point"}
}