{
  "type": "Feature",
  "properties": {
    "iso:country":"US",
    "sg:address":"620 Oliver Rd",
    "sg:city":"Montgomery",
    "sg:classifiers":[
        {
            "category":"Retail",
            "subcategory":"Repair Shop",
            "type":"Services"
        }
    ],
    "sg:phone":"+1 334 244 1104",
    "sg:postcode":"36117",
    "sg:province":"AL",
    "sg:tags":[
        "upholsterer"
    ],
    "wof:name":"Upholstery By Troy",
    "wof:placetype":"venue"
},
  "geometry": {"coordinates":[-86.206841,32.397231],"type":"Point"}
}