{
  "type": "Feature",
  "properties": {
    "addr:full":"3805 Tree Crossings Pkwy Birmingham AL 35244",
    "addr:housenumber":"3805",
    "addr:postcode":"35244",
    "addr:street":"Tree Crossings Pkwy",
    "iso:country":"US",
    "sg:address":"3805 Tree Crossings Pkwy",
    "sg:city":"Birmingham",
    "sg:classifiers":[
        {
            "category":"Travel",
            "subcategory":"Travel Agent",
            "type":"Entertainment"
        }
    ],
    "sg:phone":"+1 205 739 0480",
    "sg:postcode":"35244",
    "sg:province":"AL",
    "sg:tags":[
        "agency"
    ],
    "wof:name":"Going Places Travel Agency",
    "wof:placetype":"venue"
},
  "geometry": {"coordinates":[-86.83752699999999,33.357394],"type":"Point"}
}