{
  "type": "Feature",
  "properties": {
    "addr:full":"81 Church St Birmingham AL 35213",
    "addr:housenumber":"81",
    "addr:postcode":"35213",
    "addr:street":"Church St",
    "iso:country":"US",
    "sg:address":"81 Church St",
    "sg:city":"Birmingham",
    "sg:classifiers":[
        {
            "category":"Shopping",
            "subcategory":"Jewelry",
            "type":"Retail Goods"
        }
    ],
    "sg:phone":"+1 205 879 5153",
    "sg:postcode":"35213",
    "sg:province":"AL",
    "sg:tags":[
        "repair"
    ],
    "wof:name":"Denman & Crosby",
    "wof:placetype":"venue"
},
  "geometry": {"coordinates":[-86.756199,33.50282],"type":"Point"}
}