{
  "type": "Feature",
  "properties": {
    "addr:full":"500 State Rte 75 Albertville AL 35951",
    "addr:housenumber":"500",
    "addr:postcode":"35951",
    "addr:street":"State Rte 75",
    "iso:country":"US",
    "sg:address":"500 State Rte 75",
    "sg:city":"Albertville",
    "sg:classifiers":[
        {
            "category":"Building & Trades",
            "subcategory":"Construction",
            "type":"Services"
        }
    ],
    "sg:phone":"+1 256 891 3985",
    "sg:postcode":"35951",
    "sg:province":"AL",
    "sg:tags":[
        "resurfacing",
        "floor",
        "laying",
        "refinishing",
        "contractor"
    ],
    "wof:name":"Quality Floor Covering Supply",
    "wof:placetype":"venue"
},
  "geometry": {"coordinates":[-86.19952600000001,34.279061],"type":"Point"}
}