{
  "type": "Feature",
  "properties": {
    "addr:full":"15089 Court St Moulton AL 35650",
    "addr:housenumber":"15089",
    "addr:postcode":"35650",
    "addr:street":"Court St",
    "iso:country":"US",
    "sg:address":"15089 Court St",
    "sg:city":"Moulton",
    "sg:classifiers":[
        {
            "category":"Government",
            "subcategory":"Office",
            "type":"Public Place"
        }
    ],
    "sg:phone":"+1 256 974 5871",
    "sg:postcode":"35650",
    "sg:province":"AL",
    "sg:tags":[
        "security"
    ],
    "wof:name":"Det 1co L 115 Sig",
    "wof:placetype":"venue"
},
  "geometry": {"coordinates":[-87.27493699999999,34.483456],"type":"Point"}
}