{
  "type": "Feature",
  "properties": {
    "iso:country":"US",
    "sg:address":"806 N Section St",
    "sg:city":"Fairhope",
    "sg:classifiers":[
        {
            "category":"Real Estate",
            "subcategory":"Real Estate Agent",
            "type":"Services"
        }
    ],
    "sg:phone":"+1 251 990 3067",
    "sg:postcode":"36532",
    "sg:province":"AL",
    "sg:tags":[
        "appraiser"
    ],
    "wof:name":"R L Farmer & Co Inc",
    "wof:placetype":"venue"
},
  "geometry": {"coordinates":[-87.898533,30.541432],"type":"Point"}
}