{
  "type": "Feature",
  "properties": {
    "addr:full":"447 S Oates St Dothan AL 36301",
    "addr:housenumber":"447",
    "addr:postcode":"36301",
    "addr:street":"S Oates St",
    "iso:country":"US",
    "sg:address":"447 S Oates St",
    "sg:city":"Dothan",
    "sg:classifiers":[
        {
            "category":"Shopping",
            "subcategory":"Clothing, Apparel, & Fashions",
            "type":"Retail Goods"
        }
    ],
    "sg:phone":"+1 334 792 4336",
    "sg:postcode":"36301",
    "sg:province":"AL",
    "wof:name":"C & A Fashions",
    "wof:placetype":"venue"
},
  "geometry": {"coordinates":[-85.39295300000001,31.218786],"type":"Point"}
}