{
  "type": "Feature",
  "properties": {
    "addr:full":"6880 Ridgewood Dr Pinson AL 35126",
    "addr:housenumber":"6880",
    "addr:postcode":"35126",
    "addr:street":"Ridgewood Dr",
    "iso:country":"US",
    "sg:address":"6880 Ridgewood Dr",
    "sg:city":"Pinson",
    "sg:classifiers":[
        {
            "category":"Building & Trades",
            "subcategory":"Construction",
            "type":"Services"
        }
    ],
    "sg:phone":"+1 205 680 9090",
    "sg:postcode":"35126",
    "sg:province":"AL",
    "sg:tags":[
        "house"
    ],
    "wof:name":"Forsythe Construction Inc",
    "wof:placetype":"venue"
},
  "geometry": {"coordinates":[-86.651657,33.70159],"type":"Point"}
}