{
  "type": "Feature",
  "properties": {
    "iso:country":"US",
    "sg:address":"3368 Green Valley Rd",
    "sg:city":"Gadsden",
    "sg:classifiers":[
        {
            "category":"Building & Trades",
            "subcategory":"Construction",
            "type":"Services"
        }
    ],
    "sg:phone":"+1 256 442 2699",
    "sg:postcode":"35907",
    "sg:province":"AL",
    "sg:tags":[
        "contractor"
    ],
    "wof:name":"Scott Gober Construction Comp",
    "wof:placetype":"venue"
},
  "geometry": {"coordinates":[-86.021108,33.877747],"type":"Point"}
}