{
  "type": "Feature",
  "properties": {
    "addr:full":"272 Snow Dr Homewood AL 35209",
    "addr:housenumber":"272",
    "addr:postcode":"35209",
    "addr:street":"Snow Dr",
    "iso:country":"US",
    "sg:address":"272 Snow Dr",
    "sg:city":"Homewood",
    "sg:classifiers":[
        {
            "category":"Professional",
            "subcategory":"Management & Consulting",
            "type":"Services"
        }
    ],
    "sg:phone":"+1 205 945 8087",
    "sg:postcode":"35209",
    "sg:province":"AL",
    "sg:tags":[
        "employment",
        "screening"
    ],
    "wof:name":"ICA Investigations Corp",
    "wof:placetype":"venue"
},
  "geometry": {"coordinates":[-86.836505,33.445256],"type":"Point"}
}