{
  "type": "Feature",
  "properties": {
    "addr:full":"63 Academy Blvd Monroeville AL 36460",
    "addr:housenumber":"63",
    "addr:postcode":"36460",
    "addr:street":"Academy Blvd",
    "iso:country":"US",
    "sg:address":"63 Academy Blvd",
    "sg:city":"Monroeville",
    "sg:classifiers":[
        {
            "category":"Building & Trades",
            "subcategory":"Pest Control",
            "type":"Services"
        }
    ],
    "sg:phone":"+1 251 743 2719",
    "sg:postcode":"36460",
    "sg:province":"AL",
    "wof:name":"Monroe Pest Control",
    "wof:placetype":"venue"
},
  "geometry": {"coordinates":[-87.329403,31.526289],"type":"Point"}
}