{
  "type": "Feature",
  "properties": {
    "iso:country":"US",
    "sg:address":"2020 Sharon Blvd",
    "sg:city":"Dora",
    "sg:classifiers":[
        {
            "category":"Shopping",
            "subcategory":"Used Merchandise",
            "type":"Retail Goods"
        }
    ],
    "sg:phone":"+1 205 648 3542",
    "sg:postcode":"35062",
    "sg:province":"AL",
    "wof:name":"Jessica & Us Inc",
    "wof:placetype":"venue"
},
  "geometry": {"coordinates":[-87.082894,33.735817],"type":"Point"}
}