{
  "type": "Feature",
  "properties": {
    "addr:full":"758 Hurricane Rd New Market AL 35761",
    "addr:housenumber":"758",
    "addr:postcode":"35761",
    "addr:street":"Hurricane Rd",
    "iso:country":"US",
    "sg:address":"758 Hurricane Rd",
    "sg:city":"New Market",
    "sg:classifiers":[
        {
            "category":"Retail",
            "subcategory":"Laundry & Dry Cleaning",
            "type":"Services"
        }
    ],
    "sg:phone":"+1 256 379 3933",
    "sg:postcode":"35761",
    "sg:province":"AL",
    "wof:name":"Pro Clean",
    "wof:placetype":"venue"
},
  "geometry": {"coordinates":[-86.404599,34.906337],"type":"Point"}
}