{
  "type": "Feature",
  "properties": {
    "addr:full":"504 22nd St S Irondale AL 35210",
    "addr:housenumber":"504",
    "addr:postcode":"35210",
    "addr:street":"22Nd St S",
    "iso:country":"US",
    "sg:address":"504 22nd St S",
    "sg:city":"Irondale",
    "sg:classifiers":[
        {
            "category":"Professional",
            "type":"Services"
        }
    ],
    "sg:phone":"+1 205 956 1224",
    "sg:postcode":"35210",
    "sg:province":"AL",
    "sg:tags":[
        "establishment"
    ],
    "wof:name":"H S Enterprises",
    "wof:placetype":"venue"
},
  "geometry": {"coordinates":[-86.701746,33.536237],"type":"Point"}
}