{
  "type": "Feature",
  "properties": {
    "iso:country":"US",
    "sg:address":"3439 Colonnade Pkwy Ste 400 - 500",
    "sg:city":"Birmingham",
    "sg:classifiers":[
        {
            "category":"Personal",
            "subcategory":"Tanning Parlor",
            "type":"Services"
        },
        {
            "category":"Personal",
            "subcategory":"Beauty Salon",
            "type":"Services"
        },
        {
            "category":"Personal",
            "subcategory":"Skin Care",
            "type":"Services"
        },
        {
            "category":"Personal",
            "subcategory":"Nail Salon",
            "type":"Services"
        }
    ],
    "sg:phone":"+1 205 977 9306",
    "sg:postcode":"35243",
    "sg:province":"AL",
    "sg:tags":[
        "hair",
        "stylist"
    ],
    "sg:website":"http://theladyfingerssalon.com",
    "wof:name":"Lady Fingers Salon",
    "wof:placetype":"venue"
},
  "geometry": {"coordinates":[-86.72963,33.437012],"type":"Point"}
}