{
  "type": "Feature",
  "properties": {
    "iso:country":"US",
    "sg:address":"234 Oxmoor Cir",
    "sg:city":"Birmingham",
    "sg:classifiers":[
        {
            "category":"Building & Trades",
            "subcategory":"Cleaning & Sanitation",
            "type":"Services"
        }
    ],
    "sg:phone":"+1 205 982 0883",
    "sg:postcode":"35209",
    "sg:province":"AL",
    "sg:tags":[
        "janitor"
    ],
    "wof:name":"Fikes Of Alabama",
    "wof:placetype":"venue"
},
  "geometry": {"coordinates":[-86.837149,33.453064],"type":"Point"}
}