{
  "type": "Feature",
  "properties": {
    "iso:country":"US",
    "sg:address":"109 Dothan Rd",
    "sg:city":"Abbeville",
    "sg:classifiers":[
        {
            "category":"Shopping",
            "subcategory":"Optical Goods",
            "type":"Retail Goods"
        }
    ],
    "sg:phone":"+1 334 585 9626",
    "sg:postcode":"36310",
    "sg:province":"AL",
    "wof:name":"Daniel Murray Od",
    "wof:placetype":"venue"
},
  "geometry": {"coordinates":[-85.253265,31.558062],"type":"Point"}
}