{
  "type": "Feature",
  "properties": {
    "iso:country":"US",
    "sg:address":"1011 Meridian St N",
    "sg:city":"Huntsville",
    "sg:classifiers":[
        {
            "category":"Retail",
            "subcategory":"Auto Repair",
            "type":"Services"
        }
    ],
    "sg:phone":"+1 256 551 0701",
    "sg:postcode":"35801",
    "sg:province":"AL",
    "sg:tags":[
        "repairing",
        "automobile"
    ],
    "wof:name":"Aala-Tech Automotive",
    "wof:placetype":"venue"
},
  "geometry": {"coordinates":[-86.585033,34.742779],"type":"Point"}
}