{
  "type": "Feature",
  "properties": {
    "iso:country":"US",
    "sg:address":"2913 Cullman Ave",
    "sg:city":"Birmingham",
    "sg:classifiers":[
        {
            "category":"Building & Trades",
            "subcategory":"Construction",
            "type":"Services"
        }
    ],
    "sg:phone":"+1 205 965 5317",
    "sg:postcode":"35208",
    "sg:province":"AL",
    "sg:tags":[
        "house"
    ],
    "wof:name":"Pickens Home Repair",
    "wof:placetype":"venue"
},
  "geometry": {"coordinates":[-86.86993099999999,33.503316],"type":"Point"}
}