{
  "type": "Feature",
  "properties": {
    "iso:country":"US",
    "sg:address":"1205 Evergreen Rd",
    "sg:city":"Falkville",
    "sg:classifiers":[
        {
            "category":"Food & Beverages",
            "subcategory":"Bakery",
            "type":"Retail Goods"
        }
    ],
    "sg:phone":"+1 256 462 3988",
    "sg:postcode":"35622",
    "sg:province":"AL",
    "wof:name":"Dutch Oven Bakery",
    "wof:placetype":"venue"
},
  "geometry": {"coordinates":[-87.01542499999999,34.337393],"type":"Point"}
}