{
  "type": "Feature",
  "properties": {
    "iso:country":"US",
    "sg:address":"3849 Valley Head Rd",
    "sg:city":"Birmingham",
    "sg:classifiers":[
        {
            "category":"Professional",
            "subcategory":"Business Services",
            "type":"Services"
        }
    ],
    "sg:phone":"+1 205 970 0876",
    "sg:postcode":"35223",
    "sg:province":"AL",
    "wof:name":"Sound Logic Studios LLC",
    "wof:placetype":"venue"
},
  "geometry": {"coordinates":[-86.722812,33.490736],"type":"Point"}
}