{
  "type": "Feature",
  "properties": {
    "iso:country":"US",
    "sg:address":"1011 Lurleen B Wallace Blvd",
    "sg:city":"Northport",
    "sg:classifiers":[
        {
            "category":"Food & Beverages",
            "subcategory":"Bakery",
            "type":"Retail Goods"
        }
    ],
    "sg:phone":"+1 205 344 5373",
    "sg:postcode":"35476",
    "sg:province":"AL",
    "wof:name":"Flowers Discount Bakery Store",
    "wof:placetype":"venue"
},
  "geometry": {"coordinates":[-87.576707,33.224548],"type":"Point"}
}