{
  "type": "Feature",
  "properties": {
    "addr:full":"18036 State Rte 251 Athens AL 35613",
    "addr:housenumber":"18036",
    "addr:postcode":"35613",
    "addr:street":"State Rte 251",
    "iso:country":"US",
    "sg:address":"18036 State Rte 251",
    "sg:city":"Athens",
    "sg:phone":"+1 256 232 8234",
    "sg:postcode":"35613",
    "sg:province":"AL",
    "sg:tags":[
        "farm",
        "wheat",
        "cotton"
    ],
    "wof:name":"Mark Craig",
    "wof:placetype":"venue"
},
  "geometry": {"coordinates":[-86.882193,34.838576],"type":"Point"}
}