{
  "type": "Feature",
  "properties": {
    "iso:country":"US",
    "sg:address":"628 S Wood Ave",
    "sg:city":"Florence",
    "sg:classifiers":[
        {
            "category":"Utilities",
            "subcategory":"Telephone",
            "type":"Services"
        }
    ],
    "sg:phone":"+1 256 766 7391",
    "sg:postcode":"35630",
    "sg:province":"AL",
    "sg:tags":[
        "company"
    ],
    "wof:name":"MCI",
    "wof:placetype":"venue"
},
  "geometry": {"coordinates":[-87.670041,34.796062],"type":"Point"}
}