{
  "type": "Feature",
  "properties": {
    "addr:full":"232 Pine Ridge Rd Madison AL 35758",
    "addr:housenumber":"232",
    "addr:postcode":"35758",
    "addr:street":"Pine Ridge Rd",
    "iso:country":"US",
    "sg:address":"232 Pine Ridge Rd",
    "sg:city":"Madison",
    "sg:classifiers":[
        {
            "category":"Professional",
            "subcategory":"Business Services",
            "type":"Services"
        }
    ],
    "sg:phone":"+1 256 464 9593",
    "sg:postcode":"35758",
    "sg:province":"AL",
    "sg:tags":[
        "landscape"
    ],
    "wof:name":"Home Sweet Home",
    "wof:placetype":"venue"
},
  "geometry": {"coordinates":[-86.72845599999999,34.698758],"type":"Point"}
}