{
  "type": "Feature",
  "properties": {
    "iso:country":"US",
    "sg:address":"985 Carlton Rd",
    "sg:city":"Scottsboro",
    "sg:classifiers":[
        {
            "category":"Travel",
            "subcategory":"Hotels & Motels",
            "type":"Entertainment"
        }
    ],
    "sg:phone":"+1 256 505 0722",
    "sg:postcode":"35769",
    "sg:province":"AL",
    "sg:tags":[
        "operation"
    ],
    "wof:name":"Ivy Creek Inn",
    "wof:placetype":"venue"
},
  "geometry": {"coordinates":[-86.221555,34.486288],"type":"Point"}
}