{
  "type": "Feature",
  "properties": {
    "iso:country":"US",
    "sg:address":"8301 Bailey Cove Rd SE",
    "sg:city":"Huntsville",
    "sg:classifiers":[
        {
            "category":"Wholesale",
            "subcategory":"Computers",
            "type":"Manufacturing & Wholesale Goods"
        }
    ],
    "sg:phone":"+1 256 881 6817",
    "sg:postcode":"35802",
    "sg:province":"AL",
    "sg:tags":[
        "communications",
        "datum"
    ],
    "wof:name":"Central Datacom",
    "wof:placetype":"venue"
},
  "geometry": {"coordinates":[-86.53954400000001,34.657137],"type":"Point"}
}