{
  "type": "Feature",
  "properties": {
    "iso:country":"US",
    "sg:address":"565 Houston St",
    "sg:city":"Mobile",
    "sg:classifiers":[
        {
            "category":"Retail",
            "subcategory":"Auto Repair",
            "type":"Services"
        }
    ],
    "sg:phone":"+1 251 479 7002",
    "sg:postcode":"36606",
    "sg:province":"AL",
    "sg:tags":[
        "body"
    ],
    "wof:name":"Webb Paint & Body Shop",
    "wof:placetype":"venue"
},
  "geometry": {"coordinates":[-88.081272,30.671326],"type":"Point"}
}