{
  "type": "Feature",
  "properties": {
    "iso:country":"US",
    "sg:address":"660 Saint Anthony St",
    "sg:city":"Mobile",
    "sg:classifiers":[
        {
            "category":"Organizations",
            "subcategory":"Religious Organization",
            "type":"Services"
        }
    ],
    "sg:phone":"+1 251 432 2906",
    "sg:postcode":"36603",
    "sg:province":"AL",
    "sg:tags":[
        "church"
    ],
    "wof:name":"Science Of Life Missionary Chr",
    "wof:placetype":"venue"
},
  "geometry": {"coordinates":[-88.052521,30.692064],"type":"Point"}
}