{
  "type": "Feature",
  "properties": {
    "iso:country":"US",
    "sg:address":"5901 University Dr NW",
    "sg:city":"Huntsville",
    "sg:classifiers":[
        {
            "category":"Shopping",
            "subcategory":"Clothing, Apparel, & Fashions",
            "type":"Retail Goods"
        }
    ],
    "sg:phone":"+1 256 890 4288",
    "sg:postcode":"35806",
    "sg:province":"AL",
    "sg:tags":[
        "consignment"
    ],
    "wof:name":"Kids Closet Of Huntsville",
    "wof:placetype":"venue"
},
  "geometry": {"coordinates":[-86.66525300000001,34.740631],"type":"Point"}
}