{
  "type": "Feature",
  "properties": {
    "addr:full":"200 1st Ave E Oneonta AL 35121",
    "addr:housenumber":"200",
    "addr:postcode":"35121",
    "addr:street":"1St Ave E",
    "iso:country":"US",
    "sg:address":"200 1st Ave E",
    "sg:city":"Oneonta",
    "sg:classifiers":[
        {
            "category":"Personal",
            "type":"Services"
        }
    ],
    "sg:phone":"+1 205 274 2936",
    "sg:postcode":"35121",
    "sg:province":"AL",
    "sg:tags":[
        "wear",
        "formal"
    ],
    "wof:name":"Elegant Touch",
    "wof:placetype":"venue"
},
  "geometry": {"coordinates":[-86.474773,33.945815],"type":"Point"}
}