{
  "type": "Feature",
  "properties": {
    "iso:country":"US",
    "sg:address":"2146 Highland Ave S",
    "sg:city":"Birmingham",
    "sg:classifiers":[
        {
            "category":"Professional",
            "subcategory":"Lawyer & Legal Services",
            "type":"Services"
        }
    ],
    "sg:phone":"+1 205 212 9410",
    "sg:postcode":"35205",
    "sg:province":"AL",
    "sg:tags":[
        "attorney"
    ],
    "wof:name":"Denson Law Firm",
    "wof:placetype":"venue"
},
  "geometry": {"coordinates":[-86.790994,33.500282],"type":"Point"}
}