{
  "type": "Feature",
  "properties": {
    "iso:country":"US",
    "sg:address":"10842 State Rte 25",
    "sg:city":"Calera",
    "sg:classifiers":[
        {
            "category":"Shopping",
            "subcategory":"Discount & Variety Stores",
            "type":"Retail Goods"
        }
    ],
    "sg:phone":"+1 205 668 9543",
    "sg:postcode":"35040",
    "sg:province":"AL",
    "wof:name":"Hope Enterprise Variety Store",
    "wof:placetype":"venue"
},
  "geometry": {"coordinates":[-86.75167,33.103098],"type":"Point"}
}