{
  "type": "Feature",
  "properties": {
    "iso:country":"US",
    "sg:address":"12375 US Hwy 72",
    "sg:city":"Rogersville",
    "sg:classifiers":[
        {
            "category":"Shopping",
            "type":"Retail Goods"
        }
    ],
    "sg:phone":"+1 256 247 9480",
    "sg:postcode":"35652",
    "sg:province":"AL",
    "sg:tags":[
        "merchandise"
    ],
    "wof:name":"Gina Dees Country Store",
    "wof:placetype":"venue"
},
  "geometry": {"coordinates":[-87.368135,34.84281],"type":"Point"}
}