{
  "type": "Feature",
  "properties": {
    "iso:country":"US",
    "sg:address":"200 Cahaba Park Cir",
    "sg:city":"Birmingham",
    "sg:classifiers":[
        {
            "category":"Professional",
            "subcategory":"Business Services",
            "type":"Services"
        },
        {
            "category":"Professional",
            "subcategory":"Management & Consulting",
            "type":"Services"
        }
    ],
    "sg:phone":"+1 205 980 8979",
    "sg:postcode":"35242",
    "sg:province":"AL",
    "wof:name":"Business Development Group",
    "wof:placetype":"venue"
},
  "geometry": {"coordinates":[-86.706164,33.429498],"type":"Point"}
}