{
  "type": "Feature",
  "properties": {
    "addr:full":"817 McKenzie St Foley AL 36535",
    "addr:housenumber":"817",
    "addr:postcode":"36535",
    "addr:street":"Mckenzie St",
    "iso:country":"US",
    "sg:address":"817 McKenzie St",
    "sg:city":"Foley",
    "sg:classifiers":[
        {
            "category":"Food & Beverages",
            "subcategory":"Fruits & Vegetables",
            "type":"Retail Goods"
        }
    ],
    "sg:phone":"+1 251 943 8181",
    "sg:postcode":"36535",
    "sg:province":"AL",
    "sg:tags":[
        "produce"
    ],
    "wof:name":"Foley Farm Market & Cafe",
    "wof:placetype":"venue"
},
  "geometry": {"coordinates":[-87.683814,30.414364],"type":"Point"}
}