{
  "type": "Feature",
  "properties": {
    "addr:full":"103 E 22nd St Anniston AL 36201",
    "addr:housenumber":"103",
    "addr:postcode":"36201",
    "addr:street":"E 22Nd St",
    "iso:country":"US",
    "sg:address":"103 E 22nd St",
    "sg:city":"Anniston",
    "sg:classifiers":[
        {
            "category":"Real Estate",
            "subcategory":"Real Estate Agent",
            "type":"Services"
        }
    ],
    "sg:phone":"+1 256 236 1188",
    "sg:postcode":"36201",
    "sg:province":"AL",
    "sg:tags":[
        "management"
    ],
    "wof:name":"J Brittain Assoc",
    "wof:placetype":"venue"
},
  "geometry": {"coordinates":[-85.82756000000001,33.673023],"type":"Point"}
}