{
  "type": "Feature",
  "properties": {
    "iso:country":"US",
    "sg:address":"199 Oak St",
    "sg:city":"Brundidge",
    "sg:classifiers":[
        {
            "category":"Professional",
            "type":"Services"
        }
    ],
    "sg:phone":"+1 334 735 2470",
    "sg:postcode":"36010",
    "sg:province":"AL",
    "wof:name":"McKinney Angelesa",
    "wof:placetype":"venue"
},
  "geometry": {"coordinates":[-85.815651,31.718218],"type":"Point"}
}