{
  "type": "Feature",
  "properties": {
    "iso:country":"US",
    "sg:address":"800 Huron St",
    "sg:city":"Birmingham",
    "sg:classifiers":[
        {
            "category":"Organizations",
            "subcategory":"Religious Organization",
            "type":"Services"
        }
    ],
    "sg:phone":"+1 205 788 6921",
    "sg:postcode":"35224",
    "sg:province":"AL",
    "wof:name":"Wylam Presbyterian Church",
    "wof:placetype":"venue"
},
  "geometry": {"coordinates":[-86.921015,33.504214],"type":"Point"}
}