{
  "type": "Feature",
  "properties": {
    "addr:full":"108 Hilltop Business Center Dr Pelham AL 35124",
    "addr:housenumber":"108",
    "addr:postcode":"35124",
    "addr:street":"Hilltop Business Center Dr",
    "iso:country":"US",
    "sg:address":"108 Hilltop Business Center Dr",
    "sg:city":"Pelham",
    "sg:classifiers":[
        {
            "category":"Professional",
            "subcategory":"Detective & Security Services",
            "type":"Services"
        }
    ],
    "sg:phone":"+1 205 942 9431",
    "sg:postcode":"35124",
    "sg:province":"AL",
    "sg:tags":[
        "car"
    ],
    "wof:name":"Alliance Services LLC",
    "wof:placetype":"venue"
},
  "geometry": {"coordinates":[-86.795404,33.335965],"type":"Point"}
}