{
  "type": "Feature",
  "properties": {
    "addr:full":"6560 McClellan Blvd Anniston AL 36206",
    "addr:housenumber":"6560",
    "addr:postcode":"36206",
    "addr:street":"Mcclellan Blvd",
    "iso:country":"US",
    "sg:address":"6560 McClellan Blvd",
    "sg:city":"Anniston",
    "sg:classifiers":[
        {
            "category":"Shopping",
            "subcategory":"Optical Goods",
            "type":"Retail Goods"
        }
    ],
    "sg:phone":"+1 256 820 2460",
    "sg:postcode":"36206",
    "sg:province":"AL",
    "wof:name":"Wal-Mart Vision Ctr",
    "wof:placetype":"venue"
},
  "geometry": {"coordinates":[-85.798039,33.732437],"type":"Point"}
}