{
  "type": "Feature",
  "properties": {
    "iso:country":"US",
    "sg:address":"207 N Catherine St",
    "sg:city":"Mobile",
    "sg:classifiers":[
        {
            "category":"Utilities",
            "subcategory":"Water",
            "type":"Services"
        }
    ],
    "sg:phone":"+1 251 694 3100",
    "sg:postcode":"36604",
    "sg:province":"AL",
    "sg:tags":[
        "company",
        "sewage"
    ],
    "sg:website":"www.mawss.com",
    "wof:name":"Mobile Area Water & Sewer Syst",
    "wof:placetype":"venue"
},
  "geometry": {"coordinates":[-88.072878,30.695581],"type":"Point"}
}