{
  "type": "Feature",
  "properties": {
    "iso:country":"US",
    "sg:address":"4907 Bridgehampton Rd",
    "sg:city":"Owens Cross Roads",
    "sg:classifiers":[
        {
            "category":"Farming",
            "subcategory":"Farm",
            "type":"Manufacturing & Wholesale Goods"
        }
    ],
    "sg:phone":"+1 256 519 8077",
    "sg:postcode":"35763",
    "sg:province":"AL",
    "sg:tags":[
        "crop",
        "general"
    ],
    "wof:name":"Jerry Belt",
    "wof:placetype":"venue"
},
  "geometry": {"coordinates":[-86.484655,34.632523],"type":"Point"}
}