{
  "type": "Feature",
  "properties": {
    "iso:country":"US",
    "sg:address":"651 Pike Rd",
    "sg:city":"Pike Road",
    "sg:classifiers":[
        {
            "category":"Professional",
            "type":"Services"
        }
    ],
    "sg:phone":"+1 334 260 7765",
    "sg:postcode":"36064",
    "sg:province":"AL",
    "sg:tags":[
        "establishment"
    ],
    "wof:name":"Time & Space",
    "wof:placetype":"venue"
},
  "geometry": {"coordinates":[-86.095942,32.359547],"type":"Point"}
}