{
  "type": "Feature",
  "properties": {
    "iso:country":"US",
    "sg:address":"4055 Co Rd 28",
    "sg:city":"Columbiana",
    "sg:classifiers":[
        {
            "category":"Building & Trades",
            "subcategory":"Construction",
            "type":"Services"
        }
    ],
    "sg:phone":"+1 205 669 6848",
    "sg:postcode":"35051",
    "sg:province":"AL",
    "sg:tags":[
        "excavation",
        "contractor"
    ],
    "wof:name":"Blankenship Excavating",
    "wof:placetype":"venue"
},
  "geometry": {"coordinates":[-86.542972,33.161254],"type":"Point"}
}