{
  "type": "Feature",
  "properties": {
    "addr:full":"4055 Co Rd 28 Columbiana AL 35051",
    "addr:housenumber":"4055;28",
    "addr:postcode":"35051",
    "addr:street":"Co Rd",
    "iso:country":"US",
    "sg:address":"4055 Co Rd 28",
    "sg:city":"Columbiana",
    "sg:classifiers":[
        {
            "category":"Building & Trades",
            "subcategory":"Construction",
            "type":"Services"
        }
    ],
    "sg:phone":"+1 205 669 6848",
    "sg:postcode":"35051",
    "sg:province":"AL",
    "sg:tags":[
        "excavation",
        "contractor"
    ],
    "wof:name":"Blankenship Excavating",
    "wof:placetype":"venue"
},
  "geometry": {"coordinates":[-86.54297200000001,33.161254],"type":"Point"}
}