{
  "type": "Feature",
  "properties": {
    "iso:country":"US",
    "sg:address":"2732 Central Ave",
    "sg:city":"Birmingham",
    "sg:classifiers":[
        {
            "category":"Shopping",
            "subcategory":"Party Supplies",
            "type":"Retail Goods"
        },
        {
            "category":"Building & Trades",
            "subcategory":"Equipment Rental",
            "type":"Services"
        }
    ],
    "sg:phone":"+1 205 871 2125",
    "sg:postcode":"35209",
    "sg:province":"AL",
    "sg:tags":[
        "yard",
        "store"
    ],
    "sg:website":"http://www.huffrental.com",
    "wof:name":"Huff Rental",
    "wof:placetype":"venue"
},
  "geometry": {"coordinates":[-86.79494699999999,33.480322],"type":"Point"}
}