{
  "type": "Feature",
  "properties": {
    "addr:full":"1650 Mann Dr Birmingham AL 35214",
    "addr:housenumber":"1650",
    "addr:postcode":"35214",
    "addr:street":"Mann Dr",
    "iso:country":"US",
    "sg:address":"1650 Mann Dr",
    "sg:city":"Birmingham",
    "sg:classifiers":[
        {
            "category":"Building & Trades",
            "subcategory":"Locksmith",
            "type":"Services"
        }
    ],
    "sg:phone":"+1 205 216 1148",
    "sg:postcode":"35214",
    "sg:province":"AL",
    "sg:tags":[
        "key"
    ],
    "wof:name":"All Good Locksmith",
    "wof:placetype":"venue"
},
  "geometry": {"coordinates":[-86.880779,33.572554],"type":"Point"}
}