{
  "type": "Feature",
  "properties": {
    "addr:full":"7801 Old Hwy 20 Leighton AL 35646",
    "addr:housenumber":"7801",
    "addr:postcode":"35646",
    "addr:street":"Old Hwy 20 Leighton",
    "iso:country":"US",
    "sg:address":"7801 Old Hwy 20",
    "sg:city":"Leighton",
    "sg:classifiers":[
        {
            "category":"Organizations",
            "subcategory":"Religious Organization",
            "type":"Services"
        }
    ],
    "sg:phone":"+1 256 446 6388",
    "sg:postcode":"35646",
    "sg:province":"AL",
    "sg:tags":[
        "church"
    ],
    "wof:name":"Emmanuel Christian Ctr",
    "wof:placetype":"venue"
},
  "geometry": {"coordinates":[-87.5419,34.698536],"type":"Point"}
}