{
  "type": "Feature",
  "properties": {
    "iso:country":"US",
    "sg:address":"221 Broad St",
    "sg:city":"Gadsden",
    "sg:classifiers":[
        {
            "category":"Health Services",
            "subcategory":"Optometrist",
            "type":"Services"
        }
    ],
    "sg:phone":"+1 256 547 7537",
    "sg:postcode":"35901",
    "sg:province":"AL",
    "wof:name":"Momans Eyecare",
    "wof:placetype":"venue"
},
  "geometry": {"coordinates":[-86.001725,34.012249],"type":"Point"}
}