{
  "type": "Feature",
  "properties": {
    "addr:full":"2468 Jamestown Dr Birmingham AL 35226",
    "addr:housenumber":"2468",
    "addr:postcode":"35226",
    "addr:street":"Jamestown Dr",
    "iso:country":"US",
    "sg:address":"2468 Jamestown Dr",
    "sg:city":"Birmingham",
    "sg:classifiers":[
        {
            "category":"Professional",
            "type":"Services"
        }
    ],
    "sg:phone":"+1 205 975 5400",
    "sg:postcode":"35226",
    "sg:province":"AL",
    "wof:name":"Highland Grounds Services Inc",
    "wof:placetype":"venue"
},
  "geometry": {"coordinates":[-86.839703,33.390586],"type":"Point"}
}