{
  "type": "Feature",
  "properties": {
    "iso:country":"US",
    "sg:address":"33226 US Hwy 431",
    "sg:city":"Roanoke",
    "sg:classifiers":[
        {
            "category":"Retail",
            "subcategory":"Repair Shop",
            "type":"Services"
        }
    ],
    "sg:phone":"+1 334 863 4046",
    "sg:postcode":"36274",
    "sg:province":"AL",
    "wof:name":"Smith TV Repair",
    "wof:placetype":"venue"
},
  "geometry": {"coordinates":[-85.34571,33.099503],"type":"Point"}
}