{
  "type": "Feature",
  "properties": {
    "iso:country":"US",
    "sg:address":"1575 Co Rd 7",
    "sg:city":"Bremen",
    "sg:classifiers":[
        {
            "category":"Freight",
            "type":"Transportation"
        }
    ],
    "sg:phone":"+1 256 287 2719",
    "sg:postcode":"35033",
    "sg:province":"AL",
    "sg:tags":[
        "trucking"
    ],
    "wof:name":"S & S Trucking",
    "wof:placetype":"venue"
},
  "geometry": {"coordinates":[-86.95441700000001,33.884074],"type":"Point"}
}