{
  "type": "Feature",
  "properties": {
    "iso:country":"US",
    "sg:address":"4654 Co Rd 17",
    "sg:city":"Helena",
    "sg:classifiers":[
        {
            "category":"Food & Beverages",
            "subcategory":"Groceries & Convenience Stores",
            "type":"Retail Goods"
        }
    ],
    "sg:phone":"+1 205 663 9448",
    "sg:postcode":"35080",
    "sg:province":"AL",
    "wof:name":"Balam Country Store",
    "wof:placetype":"venue"
},
  "geometry": {"coordinates":[-86.85272,33.281412],"type":"Point"}
}