{
  "type": "Feature",
  "properties": {
    "iso:country":"US",
    "sg:address":"10562 Vance Blocton Rd",
    "sg:city":"Vance",
    "sg:classifiers":[
        {
            "category":"Professional",
            "type":"Services"
        }
    ],
    "sg:phone":"+1 205 562 9188",
    "sg:postcode":"35490",
    "sg:province":"AL",
    "sg:tags":[
        "establishment"
    ],
    "wof:name":"LA Michoacana No 2",
    "wof:placetype":"venue"
},
  "geometry": {"coordinates":[-87.233138,33.174478],"type":"Point"}
}