{
  "type": "Feature",
  "properties": {
    "iso:country":"US",
    "sg:address":"11 Midtown Park W",
    "sg:city":"Mobile",
    "sg:classifiers":[
        {
            "category":"Professional",
            "subcategory":"Management & Consulting",
            "type":"Services"
        }
    ],
    "sg:phone":"+1 251 478 6100",
    "sg:postcode":"36606",
    "sg:province":"AL",
    "sg:tags":[
        "golf",
        "promotion",
        "tourism"
    ],
    "wof:name":"Fairways Golf Co Inc",
    "wof:placetype":"venue"
},
  "geometry": {"coordinates":[-88.122074,30.687942],"type":"Point"}
}