{
  "type": "Feature",
  "properties": {
    "addr:full":"2491 Eastern Blvd Montgomery AL 36117",
    "addr:housenumber":"2491",
    "addr:postcode":"36117",
    "addr:street":"Eastern Blvd",
    "iso:country":"US",
    "sg:address":"2491 Eastern Blvd",
    "sg:city":"Montgomery",
    "sg:classifiers":[
        {
            "category":"Travel",
            "subcategory":"Hotels & Motels",
            "type":"Entertainment"
        }
    ],
    "sg:phone":"+1 334 279 1204",
    "sg:postcode":"36117",
    "sg:province":"AL",
    "sg:tags":[
        "operation"
    ],
    "wof:name":"Extended Stay America Inc",
    "wof:placetype":"venue"
},
  "geometry": {"coordinates":[-86.221552,32.348394],"type":"Point"}
}