{
  "type": "Feature",
  "properties": {
    "iso:country":"US",
    "sg:address":"2408 Canterbury Rd",
    "sg:city":"Birmingham",
    "sg:classifiers":[
        {
            "category":"Professional",
            "subcategory":"Business Services",
            "type":"Services"
        }
    ],
    "sg:phone":"+1 205 879 2714",
    "sg:postcode":"35223",
    "sg:province":"AL",
    "sg:tags":[
        "interior",
        "consulting",
        "providing",
        "decorator"
    ],
    "wof:name":"Timeless Interiors Inc",
    "wof:placetype":"venue"
},
  "geometry": {"coordinates":[-86.772536,33.483584],"type":"Point"}
}