{
  "type": "Feature",
  "properties": {
    "iso:country":"US",
    "sg:address":"211 Sparkman St NW",
    "sg:city":"Hartselle",
    "sg:classifiers":[
        {
            "category":"Health Services",
            "subcategory":"Health Practitioner",
            "type":"Services"
        }
    ],
    "sg:phone":"+1 256 751 0046",
    "sg:postcode":"35640",
    "sg:province":"AL",
    "sg:tags":[
        "psychologist"
    ],
    "wof:name":"Parapsychology Research",
    "wof:placetype":"venue"
},
  "geometry": {"coordinates":[-86.935487,34.445074],"type":"Point"}
}