{
  "type": "Feature",
  "properties": {
    "iso:country":"US",
    "sg:address":"313 Franklin St SE",
    "sg:city":"Huntsville",
    "sg:classifiers":[
        {
            "category":"Real Estate",
            "subcategory":"Architect",
            "type":"Services"
        }
    ],
    "sg:phone":"+1 256 551 0991",
    "sg:postcode":"35801",
    "sg:province":"AL",
    "sg:website":"www.jeffthomasarchitects.com",
    "wof:name":"Jeff Thomas Architects",
    "wof:placetype":"venue"
},
  "geometry": {"coordinates":[-86.583618,34.729404],"type":"Point"}
}