{
  "type": "Feature",
  "properties": {
    "addr:full":"4146 Carmichael Ct Montgomery AL 36106",
    "addr:housenumber":"4146",
    "addr:postcode":"36106",
    "addr:street":"Carmichael Ct",
    "iso:country":"US",
    "sg:address":"4146 Carmichael Ct",
    "sg:city":"Montgomery",
    "sg:classifiers":[
        {
            "category":"Social Services",
            "type":"Services"
        }
    ],
    "sg:phone":"+1 334 409 0210",
    "sg:postcode":"36106",
    "sg:province":"AL",
    "wof:name":"Associated Psychologist",
    "wof:placetype":"venue"
},
  "geometry": {"coordinates":[-86.237514,32.356697],"type":"Point"}
}