{
  "type": "Feature",
  "properties": {
    "iso:country":"US",
    "sg:address":"213 Co Rd 14",
    "sg:city":"Flat Rock",
    "sg:classifiers":[
        {
            "category":"Organizations",
            "subcategory":"Religious Organization",
            "type":"Services"
        }
    ],
    "sg:phone":"+1 256 632 6124",
    "sg:postcode":"35966",
    "sg:province":"AL",
    "sg:tags":[
        "church"
    ],
    "wof:name":"Caperton's Chapel Baptist Chr",
    "wof:placetype":"venue"
},
  "geometry": {"coordinates":[-85.770669,34.820132],"type":"Point"}
}