{
  "type": "Feature",
  "properties": {
    "addr:full":"5130 Airport Rd Millbrook AL 36054",
    "addr:housenumber":"5130",
    "addr:postcode":"36054",
    "addr:street":"Airport Rd",
    "iso:country":"US",
    "sg:address":"5130 Airport Rd",
    "sg:city":"Millbrook",
    "sg:classifiers":[
        {
            "category":"Professional",
            "subcategory":"Engineering",
            "type":"Services"
        }
    ],
    "sg:phone":"+1 334 857 2734",
    "sg:postcode":"36054",
    "sg:province":"AL",
    "sg:tags":[
        "consulting",
        "software",
        "engineer"
    ],
    "wof:name":"Funtional Systems Analysts Inc",
    "wof:placetype":"venue"
},
  "geometry": {"coordinates":[-86.34935,32.506231],"type":"Point"}
}