{
  "type": "Feature",
  "properties": {
    "addr:full":"5700 E Lake Blvd Birmingham AL 35217",
    "addr:housenumber":"5700",
    "addr:postcode":"35217",
    "addr:street":"E Lake Blvd",
    "iso:country":"US",
    "sg:address":"5700 E Lake Blvd",
    "sg:city":"Birmingham",
    "sg:classifiers":[
        {
            "category":"Military Area",
            "type":"Public Place"
        },
        {
            "category":"Government",
            "subcategory":"Office",
            "type":"Public Place"
        }
    ],
    "sg:phone":"+1 205 849 7376",
    "sg:postcode":"35217",
    "sg:province":"AL",
    "sg:tags":[
        "government-state",
        "force",
        "armed",
        "recruiting"
    ],
    "sg:website":"http://www.depts.ttu.edu",
    "wof:name":"Alabama Army National Guard Recruiting",
    "wof:placetype":"venue"
},
  "geometry": {"coordinates":[-86.75196200000001,33.571891],"type":"Point"}
}