{
  "type": "Feature",
  "properties": {
    "iso:country":"US",
    "sg:address":"523 Spencer Dr NW",
    "sg:city":"Huntsville",
    "sg:classifiers":[
        {
            "category":"Professional",
            "subcategory":"Computer Services",
            "type":"Services"
        }
    ],
    "sg:phone":"+1 256 721 9311",
    "sg:postcode":"35806",
    "sg:province":"AL",
    "sg:tags":[
        "graphics"
    ],
    "wof:name":"SCR Information Controls",
    "wof:placetype":"venue"
},
  "geometry": {"coordinates":[-86.663618,34.724431],"type":"Point"}
}