{
  "type": "Feature",
  "properties": {
    "addr:full":"11407 Crestfield Dr SE Huntsville AL 35803",
    "addr:housenumber":"11407",
    "addr:postcode":"35803",
    "addr:street":"Crestfield Dr Se",
    "iso:country":"US",
    "sg:address":"11407 Crestfield Dr SE",
    "sg:city":"Huntsville",
    "sg:classifiers":[
        {
            "category":"Building & Trades",
            "subcategory":"Construction",
            "type":"Services"
        }
    ],
    "sg:phone":"+1 256 880 0980",
    "sg:postcode":"35803",
    "sg:province":"AL",
    "sg:tags":[
        "hanging",
        "contractor"
    ],
    "wof:name":"Karen Drake Backgrounds",
    "wof:placetype":"venue"
},
  "geometry": {"coordinates":[-86.558615,34.631825],"type":"Point"}
}