{
  "type": "Feature",
  "properties": {
    "addr:full":"17081 US Hwy 29 Brewton AL 36426",
    "addr:postcode":"17081;36426",
    "addr:street":"Us Hwy 29",
    "iso:country":"US",
    "sg:address":"17081 US Hwy 29",
    "sg:city":"Brewton",
    "sg:classifiers":[
        {
            "category":"Organizations",
            "subcategory":"Religious Organization",
            "type":"Services"
        }
    ],
    "sg:phone":"+1 251 867 8251",
    "sg:postcode":"36426",
    "sg:province":"AL",
    "sg:tags":[
        "church"
    ],
    "wof:name":"Second Bethlehem Baptist Chr",
    "wof:placetype":"venue"
},
  "geometry": {"coordinates":[-86.81272300000001,31.162201],"type":"Point"}
}