{
  "type": "Feature",
  "properties": {
    "iso:country":"US",
    "sg:address":"2708 Forrest Ave",
    "sg:city":"Gadsden",
    "sg:classifiers":[
        {
            "category":"Retail",
            "subcategory":"Auto Rental",
            "type":"Services"
        }
    ],
    "sg:phone":"+1 256 549 0039",
    "sg:postcode":"35904",
    "sg:province":"AL",
    "sg:tags":[
        "truck",
        "leasing"
    ],
    "wof:name":"U-Haul",
    "wof:placetype":"venue"
},
  "geometry": {"coordinates":[-86.047025,34.018749],"type":"Point"}
}