{
  "type": "Feature",
  "properties": {
    "iso:country":"US",
    "sg:address":"45 Marco Dr",
    "sg:city":"Decatur",
    "sg:phone":"+1 256 355 5560",
    "sg:postcode":"35603",
    "sg:province":"AL",
    "wof:name":"Jw Steakhouse",
    "wof:placetype":"venue"
},
  "geometry": {"coordinates":[-86.901208,34.530976],"type":"Point"}
}