{
  "type": "Feature",
  "properties": {
    "addr:full":"224 Holmes Ave NE Huntsville AL 35801",
    "addr:housenumber":"224",
    "addr:postcode":"35801",
    "addr:street":"Holmes Ave Ne",
    "iso:country":"US",
    "sg:address":"224 Holmes Ave NE",
    "sg:city":"Huntsville",
    "sg:classifiers":[
        {
            "category":"Real Estate",
            "subcategory":"Architect",
            "type":"Services"
        }
    ],
    "sg:phone":"+1 256 533 7510",
    "sg:postcode":"35801",
    "sg:province":"AL",
    "wof:name":"Bill Peters Architects",
    "wof:placetype":"venue"
},
  "geometry": {"coordinates":[-86.58532599999999,34.732987],"type":"Point"}
}