{
  "type": "Feature",
  "properties": {
    "iso:country":"US",
    "sg:address":"3213 Colesbury Dr",
    "sg:city":"Birmingham",
    "sg:classifiers":[
        {
            "category":"Professional",
            "subcategory":"Management & Consulting",
            "type":"Services"
        }
    ],
    "sg:phone":"+1 205 979 3492",
    "sg:postcode":"35226",
    "sg:province":"AL",
    "wof:name":"Davis Mktg",
    "wof:placetype":"venue"
},
  "geometry": {"coordinates":[-86.827014,33.391221],"type":"Point"}
}