{
  "type": "Feature",
  "properties": {
    "addr:full":"1383 Wolf Creek Rd N Pell City AL 35125",
    "addr:housenumber":"1383",
    "addr:postcode":"35125",
    "addr:street":"Wolf Creek Rd N",
    "iso:country":"US",
    "sg:address":"1383 Wolf Creek Rd N",
    "sg:city":"Pell City",
    "sg:classifiers":[
        {
            "category":"Professional",
            "subcategory":"Business Services",
            "type":"Services"
        }
    ],
    "sg:phone":"+1 205 338 3171",
    "sg:postcode":"35125",
    "sg:province":"AL",
    "wof:name":"2 ADM Financial Enterprises In",
    "wof:placetype":"venue"
},
  "geometry": {"coordinates":[-86.30583799999999,33.602554],"type":"Point"}
}