{
  "type": "Feature",
  "properties": {
    "addr:full":"708 Stevens Ave NE Huntsville AL 35801",
    "addr:housenumber":"708",
    "addr:postcode":"35801",
    "addr:street":"Stevens Ave Ne",
    "iso:country":"US",
    "sg:address":"708 Stevens Ave NE",
    "sg:city":"Huntsville",
    "sg:classifiers":[
        {
            "category":"Shopping",
            "subcategory":"Jewelry",
            "type":"Retail Goods"
        }
    ],
    "sg:phone":"+1 256 539 2247",
    "sg:postcode":"35801",
    "sg:province":"AL",
    "wof:name":"A Touch Of Mink",
    "wof:placetype":"venue"
},
  "geometry": {"coordinates":[-86.575462,34.744899],"type":"Point"}
}