{
  "type": "Feature",
  "properties": {
    "iso:country":"US",
    "sg:address":"902 S Brundidge St",
    "sg:city":"Troy",
    "sg:classifiers":[
        {
            "category":"Shopping",
            "type":"Retail Goods"
        }
    ],
    "sg:phone":"+1 334 566 4560",
    "sg:postcode":"36081",
    "sg:province":"AL",
    "sg:tags":[
        "monument"
    ],
    "wof:name":"Pinckard Vault & Marble Works",
    "wof:placetype":"venue"
},
  "geometry": {"coordinates":[-85.966407,31.796162],"type":"Point"}
}