{
  "type": "Feature",
  "properties": {
    "iso:country":"US",
    "sg:address":"635 Underwood Ave",
    "sg:city":"Oneonta",
    "sg:classifiers":[
        {
            "category":"Building & Trades",
            "subcategory":"Plumbing",
            "type":"Services"
        }
    ],
    "sg:phone":"+1 205 274 4770",
    "sg:postcode":"35121",
    "sg:province":"AL",
    "sg:tags":[
        "heating",
        "contractor"
    ],
    "wof:name":"Air Duct Industries",
    "wof:placetype":"venue"
},
  "geometry": {"coordinates":[-86.463985,33.942965],"type":"Point"}
}