{
  "type": "Feature",
  "properties": {
    "iso:country":"US",
    "sg:address":"24825 Canal Rd",
    "sg:city":"Orange Beach",
    "sg:classifiers":[
        {
            "category":"Real Estate",
            "subcategory":"Real Estate Agent",
            "type":"Services"
        }
    ],
    "sg:phone":"+1 251 974 2531",
    "sg:postcode":"36561",
    "sg:province":"AL",
    "wof:name":"Malcom Bond",
    "wof:placetype":"venue"
},
  "geometry": {"coordinates":[-87.619532,30.290195],"type":"Point"}
}