{
  "type": "Feature",
  "properties": {
    "iso:country":"US",
    "sg:address":"2623 Montgomery Hwy",
    "sg:city":"Dothan",
    "sg:classifiers":[
        {
            "category":"Professional",
            "subcategory":"Management & Consulting",
            "type":"Services"
        }
    ],
    "sg:phone":"+1 334 671 7007",
    "sg:postcode":"36303",
    "sg:province":"AL",
    "sg:tags":[
        "consultant",
        "educational"
    ],
    "wof:name":"Pearson Professional Ctr",
    "wof:placetype":"venue"
},
  "geometry": {"coordinates":[-85.420346,31.244948],"type":"Point"}
}