{
  "type": "Feature",
  "properties": {
    "iso:country":"US",
    "sg:address":"3180 Wall Triana Hwy",
    "sg:city":"Huntsville",
    "sg:classifiers":[
        {
            "category":"Utilities",
            "subcategory":"Fuel Oil & Lpg",
            "type":"Services"
        }
    ],
    "sg:phone":"+1 256 461 0076",
    "sg:postcode":"35824",
    "sg:province":"AL",
    "sg:tags":[
        "propane",
        "retail"
    ],
    "wof:name":"Amerigas",
    "wof:placetype":"venue"
},
  "geometry": {"coordinates":[-86.754064,34.656556],"type":"Point"}
}