{
  "type": "Feature",
  "properties": {
    "iso:country":"US",
    "sg:address":"1108 Ashville Rd NE",
    "sg:city":"Leeds",
    "sg:classifiers":[
        {
            "category":"Professional",
            "type":"Services"
        }
    ],
    "sg:phone":"+1 205 699 6647",
    "sg:postcode":"35094",
    "sg:province":"AL",
    "sg:tags":[
        "establishment"
    ],
    "wof:name":"Guardian Systems Inc",
    "wof:placetype":"venue"
},
  "geometry": {"coordinates":[-86.53417399999999,33.553631],"type":"Point"}
}