{
  "type": "Feature",
  "properties": {
    "addr:full":"921 10th Ave Phenix City AL 36867",
    "addr:housenumber":"921",
    "addr:postcode":"36867",
    "addr:street":"10Th Ave Phenix City Al",
    "iso:country":"US",
    "sg:address":"921 10th Ave",
    "sg:city":"Phenix City",
    "sg:classifiers":[
        {
            "category":"Organizations",
            "subcategory":"Religious Organization",
            "type":"Services"
        }
    ],
    "sg:phone":"+1 334 297 0103",
    "sg:postcode":"36867",
    "sg:province":"AL",
    "sg:tags":[
        "church"
    ],
    "wof:name":"Gaines Chapel AME Church Inc",
    "wof:placetype":"venue"
},
  "geometry": {"coordinates":[-85.006032,32.462862],"type":"Point"}
}