{
  "type": "Feature",
  "properties": {
    "iso:country":"US",
    "sg:address":"2500 Center Point Pkwy Ste 100",
    "sg:city":"Birmingham",
    "sg:classifiers":[
        {
            "category":"Health Services",
            "subcategory":"Dentist",
            "type":"Services"
        }
    ],
    "sg:phone":"+1 205 854 7448",
    "sg:postcode":"35215",
    "sg:province":"AL",
    "wof:name":"Winchester David R DMD Dntst",
    "wof:placetype":"venue"
},
  "geometry": {"coordinates":[-86.68319700000001,33.651001],"type":"Point"}
}