{
  "type": "Feature",
  "properties": {
    "iso:country":"US",
    "sg:address":"908 US Hwy 72 E",
    "sg:city":"Athens",
    "sg:classifiers":[
        {
            "category":"Autos & Motor Vehicles",
            "subcategory":"Auto Supplies",
            "type":"Retail Goods"
        }
    ],
    "sg:phone":"+1 256 232 7696",
    "sg:postcode":"35611",
    "sg:province":"AL",
    "sg:tags":[
        "repair"
    ],
    "wof:name":"Bumper To Bumper Parts & Svc",
    "wof:placetype":"venue"
},
  "geometry": {"coordinates":[-86.963465,34.788267],"type":"Point"}
}