{
  "type": "Feature",
  "properties": {
    "iso:country":"US",
    "sg:address":"325 N 3rd St",
    "sg:city":"Gadsden",
    "sg:classifiers":[
        {
            "category":"Shopping",
            "subcategory":"Discount & Variety Stores",
            "type":"Retail Goods"
        }
    ],
    "sg:phone":"+1 256 547 9556",
    "sg:postcode":"35901",
    "sg:province":"AL",
    "wof:name":"Bargain Town",
    "wof:placetype":"venue"
},
  "geometry": {"coordinates":[-85.999297,34.016316],"type":"Point"}
}