{
  "type": "Feature",
  "properties": {
    "iso:country":"US",
    "sg:address":"320 Bexar Ave W",
    "sg:city":"Hamilton",
    "sg:classifiers":[
        {
            "category":"Banks & Credit Unions",
            "subcategory":"Bank",
            "type":"Services"
        }
    ],
    "sg:phone":"+1 205 921 7886",
    "sg:postcode":"35570",
    "sg:province":"AL",
    "wof:name":"South Trust Bank",
    "wof:placetype":"venue"
},
  "geometry": {"coordinates":[-87.994919,34.14413],"type":"Point"}
}