{
  "type": "Feature",
  "properties": {
    "addr:full":"601 Montgomery Hwy Birmingham AL 35216",
    "addr:housenumber":"601",
    "addr:postcode":"35216",
    "addr:street":"Montgomery Hwy",
    "iso:country":"US",
    "sg:address":"601 Montgomery Hwy",
    "sg:city":"Birmingham",
    "sg:classifiers":[
        {
            "category":"Restaurant",
            "type":"Food & Drink"
        }
    ],
    "sg:menulink":"http://www.allmenus.com/al/birmingham/152194-honeybaked-ham/menu/",
    "sg:phone":"+1 205 823 4700",
    "sg:postcode":"35216",
    "sg:province":"AL",
    "sg:tags":[
        "american"
    ],
    "wof:name":"The HoneyBaked Ham Company",
    "wof:placetype":"venue"
},
  "geometry": {"coordinates":[-86.78931799999999,33.449118],"type":"Point"}
}