{
  "type": "Feature",
  "properties": {
    "addr:full":"2544 Valley Rd Birmingham AL 35217",
    "addr:housenumber":"2544",
    "addr:postcode":"35217",
    "addr:street":"Valley Rd",
    "iso:country":"US",
    "sg:address":"2544 Valley Rd",
    "sg:city":"Birmingham",
    "sg:classifiers":[
        {
            "category":"Freight",
            "type":"Transportation"
        }
    ],
    "sg:phone":"+1 205 849 0742",
    "sg:postcode":"35217",
    "sg:province":"AL",
    "wof:name":"Bawilliam",
    "wof:placetype":"venue"
},
  "geometry": {"coordinates":[-86.77402499999999,33.623906],"type":"Point"}
}