{
  "type": "Feature",
  "properties": {
    "addr:full":"224 41st Ave N Birmingham AL 35207",
    "addr:housenumber":"224",
    "addr:postcode":"35207",
    "addr:street":"41St Ave N",
    "iso:country":"US",
    "sg:address":"224 41st Ave N",
    "sg:city":"Birmingham",
    "sg:classifiers":[
        {
            "category":"Food & Beverages",
            "subcategory":"Groceries & Convenience Stores",
            "type":"Retail Goods"
        }
    ],
    "sg:phone":"+1 205 323 2177",
    "sg:postcode":"35207",
    "sg:province":"AL",
    "wof:name":"Flying J Travel Plaza",
    "wof:placetype":"venue"
},
  "geometry": {"coordinates":[-86.831497,33.5616],"type":"Point"}
}