{
  "type": "Feature",
  "properties": {
    "iso:country":"US",
    "sg:address":"5224 Siloam Rd",
    "sg:city":"Cuba",
    "sg:classifiers":[
        {
            "category":"Recreation",
            "type":"Entertainment"
        }
    ],
    "sg:phone":"+1 205 392 5875",
    "sg:postcode":"36907",
    "sg:province":"AL",
    "sg:tags":[
        "club",
        "membership"
    ],
    "wof:name":"Siloam Community Club Inc",
    "wof:placetype":"venue"
},
  "geometry": {"coordinates":[-88.287899,32.414982],"type":"Point"}
}