{
  "type": "Feature",
  "properties": {
    "iso:country":"US",
    "sg:address":"2555 Dauphinwood Dr",
    "sg:city":"Mobile",
    "sg:classifiers":[
        {
            "category":"Home & Garden",
            "subcategory":"Carpets & Floor Coverings",
            "type":"Retail Goods"
        }
    ],
    "sg:phone":"+1 251 478 6389",
    "sg:postcode":"36606",
    "sg:province":"AL",
    "sg:tags":[
        "material"
    ],
    "wof:name":"Hilliard & Sons Inc",
    "wof:placetype":"venue"
},
  "geometry": {"coordinates":[-88.102342,30.685494],"type":"Point"}
}