{
  "type": "Feature",
  "properties": {
    "addr:full":"800 11th St Birmingham AL 35228",
    "addr:housenumber":"800",
    "addr:postcode":"35228",
    "addr:street":"11Th St",
    "iso:country":"US",
    "sg:address":"800 11th St",
    "sg:city":"Birmingham",
    "sg:classifiers":[
        {
            "category":"Restaurant",
            "type":"Food & Drink"
        }
    ],
    "sg:phone":"+1 205 933 6422",
    "sg:postcode":"35228",
    "sg:province":"AL",
    "wof:name":"Waffle House",
    "wof:placetype":"venue"
},
  "geometry": {"coordinates":[-86.94630100000001,33.455247],"type":"Point"}
}