{
  "type": "Feature",
  "properties": {
    "iso:country":"US",
    "sg:address":"222 Brassell St",
    "sg:city":"Montgomery",
    "sg:classifiers":[
        {
            "category":"Social Services",
            "type":"Services"
        }
    ],
    "sg:phone":"+1 334 834 5812",
    "sg:postcode":"36104",
    "sg:province":"AL",
    "wof:name":"Health Services Wic Progra",
    "wof:placetype":"venue"
},
  "geometry": {"coordinates":[-86.295179,32.373977],"type":"Point"}
}