{
  "type": "Feature",
  "properties": {
    "iso:country":"US",
    "sg:address":"921 Co Rd 359",
    "sg:city":"Leesburg",
    "sg:classifiers":[
        {
            "category":"Health Services",
            "subcategory":"Health Practitioner",
            "type":"Services"
        }
    ],
    "sg:phone":"+1 256 526 7077",
    "sg:postcode":"35983",
    "sg:province":"AL",
    "wof:name":"TLC Rhblitation Physcl Therapy",
    "wof:placetype":"venue"
},
  "geometry": {"coordinates":[-85.733828,34.192475],"type":"Point"}
}