{
  "type": "Feature",
  "properties": {
    "addr:full":"118 Franklin St NE Russellville AL 35653",
    "addr:housenumber":"118",
    "addr:postcode":"35653",
    "addr:street":"Franklin St Ne",
    "iso:country":"US",
    "sg:address":"118 Franklin St NE",
    "sg:city":"Russellville",
    "sg:classifiers":[
        {
            "category":"Professional",
            "type":"Services"
        }
    ],
    "sg:phone":"+1 256 332 2133",
    "sg:postcode":"35653",
    "sg:province":"AL",
    "wof:name":"El Quetzal Buena Vista",
    "wof:placetype":"venue"
},
  "geometry": {"coordinates":[-87.729418,34.50553],"type":"Point"}
}