{
  "type": "Feature",
  "properties": {
    "addr:full":"4966 Catherine Dr Montgomery AL 36116",
    "addr:housenumber":"4966",
    "addr:postcode":"36116",
    "addr:street":"Catherine Dr",
    "iso:country":"US",
    "sg:address":"4966 Catherine Dr",
    "sg:city":"Montgomery",
    "sg:classifiers":[
        {
            "category":"Wholesale",
            "subcategory":"Hardware",
            "type":"Manufacturing & Wholesale Goods"
        }
    ],
    "sg:phone":"+1 334 288 7573",
    "sg:postcode":"36116",
    "sg:province":"AL",
    "sg:tags":[
        "fastener"
    ],
    "wof:name":"Golden Rule Fasteners Inc",
    "wof:placetype":"venue"
},
  "geometry": {"coordinates":[-86.23515999999999,32.321754],"type":"Point"}
}