{
  "type": "Feature",
  "properties": {
    "addr:full":"620 Fox Run Pkwy Opelika AL 36801",
    "addr:housenumber":"620",
    "addr:postcode":"36801",
    "addr:street":"Fox Run Pkwy Opelika",
    "iso:country":"US",
    "sg:address":"620 Fox Run Pkwy",
    "sg:city":"Opelika",
    "sg:classifiers":[
        {
            "category":"Manufacturing",
            "subcategory":"Rubber & Plastics",
            "type":"Manufacturing & Wholesale Goods"
        }
    ],
    "sg:phone":"+1 334 742 0005",
    "sg:postcode":"36801",
    "sg:province":"AL",
    "sg:tags":[
        "product"
    ],
    "sg:website":"www.jssusa.us",
    "wof:name":"Janson Seals & Sleeves Inc",
    "wof:placetype":"venue"
},
  "geometry": {"coordinates":[-85.35495400000001,32.64591],"type":"Point"}
}