{
  "type": "Feature",
  "properties": {
    "iso:country":"US",
    "sg:address":"13815 State Rte 216",
    "sg:city":"Cottondale",
    "sg:classifiers":[
        {
            "category":"Building & Trades",
            "subcategory":"Plumbing",
            "type":"Services"
        }
    ],
    "sg:phone":"+1 205 554 1786",
    "sg:postcode":"35453",
    "sg:province":"AL",
    "sg:tags":[
        "plumbing",
        "heating",
        "air"
    ],
    "wof:name":"P & M Plumbing",
    "wof:placetype":"venue"
},
  "geometry": {"coordinates":[-87.398951,33.25112],"type":"Point"}
}