{
  "type": "Feature",
  "properties": {
    "addr:full":"100 W Troy St Dothan AL 36303",
    "addr:housenumber":"100",
    "addr:postcode":"36303",
    "addr:street":"W Troy St",
    "iso:country":"US",
    "sg:address":"100 W Troy St",
    "sg:city":"Dothan",
    "sg:classifiers":[
        {
            "category":"Government",
            "subcategory":"Court House",
            "type":"Public Place"
        }
    ],
    "sg:phone":"+1 334 792 3583",
    "sg:postcode":"36303",
    "sg:province":"AL",
    "sg:tags":[
        "legal"
    ],
    "wof:name":"Attorneys Executive Off For US",
    "wof:placetype":"venue"
},
  "geometry": {"coordinates":[-85.39358799999999,31.225213],"type":"Point"}
}