{
  "type": "Feature",
  "properties": {
    "iso:country":"US",
    "sg:address":"30617 US Hwy 72",
    "sg:city":"Madison",
    "sg:classifiers":[
        {
            "category":"Personal",
            "subcategory":"Beauty Salon",
            "type":"Services"
        }
    ],
    "sg:phone":"+1 256 216 5533",
    "sg:postcode":"35756",
    "sg:province":"AL",
    "sg:tags":[
        "shop"
    ],
    "wof:name":"Perm-U-2 Hair Gallery",
    "wof:placetype":"venue"
},
  "geometry": {"coordinates":[-86.788023,34.748148],"type":"Point"}
}