{
  "type": "Feature",
  "properties": {
    "iso:country":"US",
    "sg:address":"620 Oliver Rd",
    "sg:city":"Montgomery",
    "sg:classifiers":[
        {
            "category":"Education",
            "subcategory":"Special Training",
            "type":"Public Place"
        }
    ],
    "sg:phone":"+1 334 265 5656",
    "sg:postcode":"36117",
    "sg:province":"AL",
    "wof:name":"Beckys Book House",
    "wof:placetype":"venue"
},
  "geometry": {"coordinates":[-86.206841,32.397231],"type":"Point"}
}