{
  "type": "Feature",
  "properties": {
    "addr:full":"18701 Co Rd 8 Florence AL 35633",
    "addr:housenumber":"18701;8",
    "addr:postcode":"35633",
    "addr:street":"Co Rd",
    "iso:country":"US",
    "sg:address":"18701 Co Rd 8",
    "sg:city":"Florence",
    "sg:classifiers":[
        {
            "category":"Home & Garden",
            "subcategory":"Furniture",
            "type":"Retail Goods"
        }
    ],
    "sg:phone":"+1 256 764 5588",
    "sg:postcode":"35633",
    "sg:province":"AL",
    "sg:tags":[
        "cabinet"
    ],
    "wof:name":"Moore's Cabinet Shop",
    "wof:placetype":"venue"
},
  "geometry": {"coordinates":[-87.75778699999999,34.942036],"type":"Point"}
}