{
  "type": "Feature",
  "properties": {
    "iso:country":"US",
    "sg:address":"150 Co Rd 255",
    "sg:city":"Town Creek",
    "sg:classifiers":[
        {
            "category":"Professional",
            "subcategory":"Business Services",
            "type":"Services"
        }
    ],
    "sg:phone":"+1 256 685 2855",
    "sg:postcode":"35672",
    "sg:province":"AL",
    "wof:name":"4-A Bail Bonds Inc",
    "wof:placetype":"venue"
},
  "geometry": {"coordinates":[-87.42583500000001,34.59427],"type":"Point"}
}