{
  "type": "Feature",
  "properties": {
    "iso:country":"US",
    "sg:address":"8539 W Renfroe Rd",
    "sg:city":"Talladega",
    "sg:classifiers":[
        {
            "category":"Recreation",
            "subcategory":"Marina",
            "type":"Entertainment"
        }
    ],
    "sg:phone":"+1 256 268 5855",
    "sg:postcode":"35160",
    "sg:province":"AL",
    "wof:name":"Marina Bay",
    "wof:placetype":"venue"
},
  "geometry": {"coordinates":[-86.246416,33.452279],"type":"Point"}
}