{
  "type": "Feature",
  "properties": {
    "iso:country":"US",
    "sg:address":"109 Alexandria Pkwy",
    "sg:city":"Alexandria",
    "sg:classifiers":[
        {
            "category":"Wholesale",
            "subcategory":"Construction Materials",
            "type":"Manufacturing & Wholesale Goods"
        }
    ],
    "sg:phone":"+1 256 820 7974",
    "sg:postcode":"36250",
    "sg:province":"AL",
    "wof:name":"Norandex / Reynolds",
    "wof:placetype":"venue"
},
  "geometry": {"coordinates":[-85.895813,33.7735],"type":"Point"}
}