{
  "type": "Feature",
  "properties": {
    "addr:full":"1510 4th Ave SE Decatur AL 35601",
    "addr:housenumber":"1510",
    "addr:postcode":"35601",
    "addr:street":"4Th Ave Se",
    "iso:country":"US",
    "sg:address":"1510 4th Ave SE",
    "sg:city":"Decatur",
    "sg:classifiers":[
        {
            "category":"Autos & Motor Vehicles",
            "subcategory":"Auto Supplies",
            "type":"Retail Goods"
        }
    ],
    "sg:phone":"+1 256 351 6850",
    "sg:postcode":"35601",
    "sg:province":"AL",
    "sg:tags":[
        "wheel",
        "cover"
    ],
    "wof:name":"Meals On Wheels",
    "wof:placetype":"venue"
},
  "geometry": {"coordinates":[-86.98296999999999,34.582697],"type":"Point"}
}