{
  "type": "Feature",
  "properties": {
    "addr:full":"660 Co Rd 10 Auburn AL 36830",
    "addr:housenumber":"660;10",
    "addr:postcode":"36830",
    "addr:street":"Co Rd",
    "iso:country":"US",
    "sg:address":"660 Co Rd 10",
    "sg:city":"Auburn",
    "sg:classifiers":[
        {
            "category":"Building & Trades",
            "subcategory":"Electrical",
            "type":"Services"
        }
    ],
    "sg:phone":"+1 334 826 0198",
    "sg:postcode":"36830",
    "sg:province":"AL",
    "sg:tags":[
        "electric",
        "contractor"
    ],
    "wof:name":"FSC Electrical Construction",
    "wof:placetype":"venue"
},
  "geometry": {"coordinates":[-85.50812000000001,32.53829],"type":"Point"}
}