{
  "type": "Feature",
  "properties": {
    "addr:full":"500 Pelham Rd S Jacksonville AL 36265",
    "addr:housenumber":"500",
    "addr:postcode":"36265",
    "addr:street":"Pelham Rd",
    "iso:country":"US",
    "sg:address":"500 Pelham Rd S",
    "sg:city":"Jacksonville",
    "sg:classifiers":[
        {
            "category":"Shopping",
            "subcategory":"Discount & Variety Stores",
            "type":"Retail Goods"
        }
    ],
    "sg:phone":"+1 205 435 3600",
    "sg:postcode":"36265",
    "sg:province":"AL",
    "wof:name":"Freds",
    "wof:placetype":"venue"
},
  "geometry": {"coordinates":[-85.761186,33.800652],"type":"Point"}
}