{
  "type": "Feature",
  "properties": {
    "addr:full":"2701 W Montgomery Rd Tuskegee Inst AL 36088",
    "addr:housenumber":"2701",
    "addr:postcode":"36088",
    "addr:street":"W Montgomery Rd",
    "iso:country":"US",
    "sg:address":"2701 W Montgomery Rd",
    "sg:city":"Tuskegee Inst",
    "sg:classifiers":[
        {
            "category":"Organizations",
            "subcategory":"Religious Organization",
            "type":"Services"
        }
    ],
    "sg:phone":"+1 334 727 2390",
    "sg:postcode":"36088",
    "sg:province":"AL",
    "sg:tags":[
        "church"
    ],
    "wof:name":"Bowen United Methodist Church",
    "wof:placetype":"venue"
},
  "geometry": {"coordinates":[-85.715535,32.412211],"type":"Point"}
}