{
  "type": "Feature",
  "properties": {
    "iso:country":"US",
    "sg:address":"237 Bessemer Super Hwy",
    "sg:city":"Birmingham",
    "sg:classifiers":[
        {
            "category":"Building & Trades",
            "subcategory":"Pest Control",
            "type":"Services"
        }
    ],
    "sg:phone":"+1 205 929 9995",
    "sg:postcode":"35228",
    "sg:province":"AL",
    "sg:tags":[
        "exterminating"
    ],
    "wof:name":"Alabama Exterminators Inc",
    "wof:placetype":"venue"
},
  "geometry": {"coordinates":[-86.914407,33.460911],"type":"Point"}
}