{
  "type": "Feature",
  "properties": {
    "iso:country":"US",
    "sg:address":"114 Hunters Hill Trl",
    "sg:city":"Toney",
    "sg:classifiers":[
        {
            "category":"Building & Trades",
            "subcategory":"Plumbing",
            "type":"Services"
        }
    ],
    "sg:phone":"+1 256 851 6919",
    "sg:postcode":"35773",
    "sg:province":"AL",
    "sg:tags":[
        "contractor"
    ],
    "wof:name":"Cool Advice",
    "wof:placetype":"venue"
},
  "geometry": {"coordinates":[-86.770522,34.890054],"type":"Point"}
}