{
  "type": "Feature",
  "properties": {
    "iso:country":"US",
    "sg:address":"207 1st Ave",
    "sg:city":"Troy",
    "sg:classifiers":[
        {
            "category":"Recreation",
            "type":"Entertainment"
        }
    ],
    "sg:phone":"+1 334 566 2620",
    "sg:postcode":"36081",
    "sg:province":"AL",
    "sg:tags":[
        "club",
        "membership"
    ],
    "wof:name":"National Exchange Club",
    "wof:placetype":"venue"
},
  "geometry": {"coordinates":[-85.960634,31.788556],"type":"Point"}
}