{
  "type": "Feature",
  "properties": {
    "iso:country":"US",
    "sg:address":"111 Southmoore Cir",
    "sg:city":"Anniston",
    "sg:classifiers":[
        {
            "category":"Professional",
            "type":"Services"
        }
    ],
    "sg:phone":"+1 256 835 9997",
    "sg:postcode":"36203",
    "sg:province":"AL",
    "wof:name":"Pro Script Svc",
    "wof:placetype":"venue"
},
  "geometry": {"coordinates":[-85.828309,33.573817],"type":"Point"}
}