{
  "type": "Feature",
  "properties": {
    "iso:country":"US",
    "sg:address":"2904 Greensport Rd",
    "sg:city":"Ashville",
    "sg:classifiers":[
        {
            "category":"Farming",
            "subcategory":"Livestock Farm",
            "type":"Manufacturing & Wholesale Goods"
        }
    ],
    "sg:phone":"+1 205 594 5354",
    "sg:postcode":"35953",
    "sg:province":"AL",
    "sg:tags":[
        "beef",
        "feedlot",
        "cattle"
    ],
    "wof:name":"Fitzgerald Yarbrough Farm",
    "wof:placetype":"venue"
},
  "geometry": {"coordinates":[-86.205762,33.816038],"type":"Point"}
}