{
  "type": "Feature",
  "properties": {
    "iso:country":"US",
    "sg:address":"5798 US Hwy 31",
    "sg:city":"Calera",
    "sg:classifiers":[
        {
            "category":"Organizations",
            "subcategory":"Religious Organization",
            "type":"Services"
        }
    ],
    "sg:phone":"+1 205 668 3053",
    "sg:postcode":"35040",
    "sg:province":"AL",
    "sg:tags":[
        "church"
    ],
    "wof:name":"New Mt Moriah Baptist",
    "wof:placetype":"venue"
},
  "geometry": {"coordinates":[-86.751019,33.137504],"type":"Point"}
}