{
  "type": "Feature",
  "properties": {
    "iso:country":"US",
    "sg:address":"69574 Main St",
    "sg:city":"Blountsville",
    "sg:classifiers":[
        {
            "category":"Communications",
            "type":"Services"
        }
    ],
    "sg:phone":"+1 205 429 4596",
    "sg:postcode":"35031",
    "sg:province":"AL",
    "wof:name":"Haymaker Communications Inc",
    "wof:placetype":"venue"
},
  "geometry": {"coordinates":[-86.586787,34.088991],"type":"Point"}
}