{
  "type": "Feature",
  "properties": {
    "addr:full":"445 Moulton St E Decatur AL 35601",
    "addr:housenumber":"445",
    "addr:postcode":"35601",
    "addr:street":"Moulton St E",
    "iso:country":"US",
    "sg:address":"445 Moulton St E",
    "sg:city":"Decatur",
    "sg:classifiers":[
        {
            "category":"Professional",
            "subcategory":"Business Services",
            "type":"Services"
        }
    ],
    "sg:phone":"+1 256 353 8405",
    "sg:postcode":"35601",
    "sg:province":"AL",
    "sg:tags":[
        "drafting"
    ],
    "wof:name":"Southern Synergy Inc",
    "wof:placetype":"venue"
},
  "geometry": {"coordinates":[-86.980559,34.603783],"type":"Point"}
}