{
  "type": "Feature",
  "properties": {
    "iso:country":"US",
    "sg:address":"3932 Crosshaven Dr",
    "sg:city":"Birmingham",
    "sg:classifiers":[
        {
            "category":"Professional",
            "subcategory":"Management & Consulting",
            "type":"Services"
        }
    ],
    "sg:phone":"+1 205 298 1740",
    "sg:postcode":"35243",
    "sg:province":"AL",
    "sg:tags":[
        "business"
    ],
    "wof:name":"Adkins Services LLC",
    "wof:placetype":"venue"
},
  "geometry": {"coordinates":[-86.731316,33.462264],"type":"Point"}
}