{
  "type": "Feature",
  "properties": {
    "iso:country":"US",
    "sg:address":"1001 Pineview Rd",
    "sg:city":"Birmingham",
    "sg:classifiers":[
        {
            "category":"Organizations",
            "subcategory":"Religious Organization",
            "type":"Services"
        }
    ],
    "sg:phone":"+1 205 929 0800",
    "sg:postcode":"35228",
    "sg:province":"AL",
    "wof:name":"Bethany Refuge Cmnty Church",
    "wof:placetype":"venue"
},
  "geometry": {"coordinates":[-86.898704,33.471691],"type":"Point"}
}