{
  "type": "Feature",
  "properties": {
    "iso:country":"US",
    "sg:address":"198 Old Hwy 231 N",
    "sg:city":"Troy",
    "sg:classifiers":[
        {
            "category":"Autos & Motor Vehicles",
            "subcategory":"Fuel & Gas Station",
            "type":"Retail Goods"
        }
    ],
    "sg:phone":"+1 334 566 1189",
    "sg:postcode":"36081",
    "sg:province":"AL",
    "sg:tags":[
        "station"
    ],
    "wof:name":"Shopper Stop & Shell",
    "wof:placetype":"venue"
},
  "geometry": {"coordinates":[-85.997168,31.854114],"type":"Point"}
}