{
  "type": "Feature",
  "properties": {
    "iso:country":"US",
    "sg:address":"434 E Beach Blvd",
    "sg:city":"Gulf Shores",
    "sg:classifiers":[
        {
            "category":"Restaurant",
            "type":"Food & Drink"
        }
    ],
    "sg:phone":"+1 251 948 9191",
    "sg:postcode":"36542",
    "sg:province":"AL",
    "wof:name":"Duck's Diner",
    "wof:placetype":"venue"
},
  "geometry": {"coordinates":[-87.679181,30.249661],"type":"Point"}
}