{
  "type": "Feature",
  "properties": {
    "addr:full":"1340 N 3 Notch St Troy AL 36081",
    "addr:housenumber":"1340;3",
    "addr:postcode":"36081",
    "addr:street":"N;Notch St",
    "iso:country":"US",
    "sg:address":"1340 N 3 Notch St",
    "sg:city":"Troy",
    "sg:classifiers":[
        {
            "category":"Health Services",
            "subcategory":"Doctor",
            "type":"Services"
        }
    ],
    "sg:phone":"+1 334 808 8940",
    "sg:postcode":"36081",
    "sg:province":"AL",
    "sg:tags":[
        "osteopathic"
    ],
    "wof:name":"Dragsten E Virginia MD",
    "wof:placetype":"venue"
},
  "geometry": {"coordinates":[-85.960362,31.823601],"type":"Point"}
}