{
  "type": "Feature",
  "properties": {
    "iso:country":"US",
    "sg:address":"601 S Quintard Ave",
    "sg:city":"Anniston",
    "sg:classifiers":[
        {
            "category":"Shopping",
            "subcategory":"Music",
            "type":"Retail Goods"
        }
    ],
    "sg:phone":"+1 256 235 2323",
    "sg:postcode":"36201",
    "sg:province":"AL",
    "wof:name":"City of Anniston CD",
    "wof:placetype":"venue"
},
  "geometry": {"coordinates":[-85.825468,33.638408],"type":"Point"}
}