{
  "type": "Feature",
  "properties": {
    "addr:full":"107 Knight Ave Roanoke AL 36274",
    "addr:housenumber":"107",
    "addr:postcode":"36274",
    "addr:street":"Knight Ave",
    "iso:country":"US",
    "sg:address":"107 Knight Ave",
    "sg:city":"Roanoke",
    "sg:classifiers":[
        {
            "category":"Personal",
            "subcategory":"Beauty Salon",
            "type":"Services"
        }
    ],
    "sg:phone":"+1 334 863 4779",
    "sg:postcode":"36274",
    "sg:province":"AL",
    "wof:name":"Fabulous Beauty Salon",
    "wof:placetype":"venue"
},
  "geometry": {"coordinates":[-85.372873,33.153485],"type":"Point"}
}