{
  "type": "Feature",
  "properties": {
    "addr:full":"6594 Wall Triana Hwy Madison AL 35757",
    "addr:housenumber":"6594",
    "addr:postcode":"35757",
    "addr:street":"Wall Triana Hwy",
    "iso:country":"US",
    "sg:address":"6594 Wall Triana Hwy",
    "sg:city":"Madison",
    "sg:classifiers":[
        {
            "category":"Professional",
            "subcategory":"Engineering",
            "type":"Services"
        }
    ],
    "sg:phone":"+1 256 830 5006",
    "sg:postcode":"35757",
    "sg:province":"AL",
    "sg:tags":[
        "civil"
    ],
    "wof:name":"Tom B Turner P E",
    "wof:placetype":"venue"
},
  "geometry": {"coordinates":[-86.749363,34.774474],"type":"Point"}
}