{
  "type": "Feature",
  "properties": {
    "iso:country":"US",
    "sg:address":"3213 10th St",
    "sg:city":"Tuscaloosa",
    "sg:classifiers":[
        {
            "category":"Recreation",
            "type":"Entertainment"
        }
    ],
    "sg:phone":"+1 205 344 6646",
    "sg:postcode":"35401",
    "sg:province":"AL",
    "sg:tags":[
        "club",
        "membership"
    ],
    "wof:name":"Club 750",
    "wof:placetype":"venue"
},
  "geometry": {"coordinates":[-87.577758,33.201249],"type":"Point"}
}