{
  "type": "Feature",
  "properties": {
    "addr:full":"1255 Springhill Ave Mobile AL 36604",
    "addr:housenumber":"1255",
    "addr:postcode":"36604",
    "addr:street":"Springhill Ave",
    "iso:country":"US",
    "sg:address":"1255 Springhill Ave",
    "sg:city":"Mobile",
    "sg:classifiers":[
        {
            "category":"Health Services",
            "subcategory":"Doctor",
            "type":"Services"
        }
    ],
    "sg:phone":"+1 251 433 1146",
    "sg:postcode":"36604",
    "sg:province":"AL",
    "sg:tags":[
        "physician",
        "surgeon"
    ],
    "wof:name":"Carmel Health Network",
    "wof:placetype":"venue"
},
  "geometry": {"coordinates":[-88.065079,30.692632],"type":"Point"}
}