{
  "type": "Feature",
  "properties": {
    "iso:country":"US",
    "sg:address":"3760 State Rte 89",
    "sg:city":"Minter",
    "sg:classifiers":[
        {
            "category":"Recreation",
            "type":"Entertainment"
        }
    ],
    "sg:phone":"+1 334 872 3582",
    "sg:postcode":"36761",
    "sg:province":"AL",
    "sg:tags":[
        "club",
        "membership"
    ],
    "wof:name":"Riverdale Hunting Club",
    "wof:placetype":"venue"
},
  "geometry": {"coordinates":[-87.041426,32.104538],"type":"Point"}
}