{
  "type": "Feature",
  "properties": {
    "iso:country":"US",
    "sg:address":"4321 University Dr NW",
    "sg:city":"Huntsville",
    "sg:classifiers":[
        {
            "category":"Wholesale",
            "subcategory":"Furniture",
            "type":"Manufacturing & Wholesale Goods"
        }
    ],
    "sg:phone":"+1 256 722 8000",
    "sg:postcode":"35816",
    "sg:province":"AL",
    "wof:name":"Alabama Business Furnishings",
    "wof:placetype":"venue"
},
  "geometry": {"coordinates":[-86.635363,34.735005],"type":"Point"}
}