{
  "type": "Feature",
  "properties": {
    "iso:country":"US",
    "sg:address":"6281 Hudson Pl",
    "sg:city":"Birmingham",
    "sg:classifiers":[
        {
            "category":"Organizations",
            "subcategory":"Religious Organization",
            "type":"Services"
        }
    ],
    "sg:phone":"+1 205 426 0444",
    "sg:postcode":"35228",
    "sg:province":"AL",
    "sg:tags":[
        "church"
    ],
    "wof:name":"Bonner Temple AME",
    "wof:placetype":"venue"
},
  "geometry": {"coordinates":[-86.931547,33.428664],"type":"Point"}
}