{
  "type": "Feature",
  "properties": {
    "iso:country":"US",
    "sg:address":"6904 Providence Park Dr",
    "sg:city":"Mobile",
    "sg:classifiers":[
        {
            "category":"Health Services",
            "subcategory":"Health Practitioner",
            "type":"Services"
        }
    ],
    "sg:phone":"+1 251 639 2090",
    "sg:postcode":"36695",
    "sg:province":"AL",
    "sg:tags":[
        "therapist",
        "specialty",
        "outpatient",
        "physical"
    ],
    "wof:name":"Providence Rehab & Wellness",
    "wof:placetype":"venue"
},
  "geometry": {"coordinates":[-88.206901,30.677945],"type":"Point"}
}