{
  "type": "Feature",
  "properties": {
    "addr:full":"5475 Bay la Launch Ave Orange Beach AL 36561",
    "addr:housenumber":"5475",
    "addr:postcode":"36561",
    "addr:street":"Bay La Launch Ave",
    "iso:country":"US",
    "sg:address":"5475 Bay la Launch Ave",
    "sg:city":"Orange Beach",
    "sg:classifiers":[
        {
            "category":"Recreation",
            "type":"Entertainment"
        }
    ],
    "sg:phone":"+1 251 946 9000",
    "sg:postcode":"36561",
    "sg:province":"AL",
    "sg:website":"www.dolphincruise.com",
    "wof:name":"Sky High Parasail",
    "wof:placetype":"venue"
},
  "geometry": {"coordinates":[-87.52584899999999,30.306296],"type":"Point"}
}