{
  "type": "Feature",
  "properties": {
    "addr:full":"14391 US Hwy 43 Northport AL 35475",
    "addr:housenumber":"14391",
    "addr:postcode":"35475",
    "addr:street":"Us Hwy 43",
    "iso:country":"US",
    "sg:address":"14391 US Hwy 43",
    "sg:city":"Northport",
    "sg:classifiers":[
        {
            "category":"Shopping",
            "subcategory":"Bicycles & Sporting Goods",
            "type":"Retail Goods"
        }
    ],
    "sg:phone":"+1 205 339 2229",
    "sg:postcode":"35475",
    "sg:province":"AL",
    "sg:tags":[
        "gun",
        "gunsmith"
    ],
    "wof:name":"Wild Woods Hardware & Gun Shop",
    "wof:placetype":"venue"
},
  "geometry": {"coordinates":[-87.606346,33.33037],"type":"Point"}
}