{
  "type": "Feature",
  "properties": {
    "iso:country":"US",
    "sg:address":"1600 Alabama Ave",
    "sg:city":"Jasper",
    "sg:classifiers":[
        {
            "category":"Professional",
            "subcategory":"Lawyer & Legal Services",
            "type":"Services"
        }
    ],
    "sg:phone":"+1 205 221 4646",
    "sg:postcode":"35501",
    "sg:province":"AL",
    "sg:tags":[
        "attorney"
    ],
    "wof:name":"Bevill & Bevill Law Firm",
    "wof:placetype":"venue"
},
  "geometry": {"coordinates":[-87.27463,33.835412],"type":"Point"}
}