{
  "type": "Feature",
  "properties": {
    "iso:country":"US",
    "sg:address":"2828 Norwood Blvd",
    "sg:city":"Birmingham",
    "sg:classifiers":[
        {
            "category":"Professional",
            "type":"Services"
        }
    ],
    "sg:phone":"+1 205 322 2681",
    "sg:postcode":"35234",
    "sg:province":"AL",
    "wof:name":"Dubs & Beat",
    "wof:placetype":"venue"
},
  "geometry": {"coordinates":[-86.806644,33.539121],"type":"Point"}
}