{
  "type": "Feature",
  "properties": {
    "iso:country":"US",
    "sg:address":"3626 Moffett Rd",
    "sg:city":"Mobile",
    "sg:classifiers":[
        {
            "category":"Retail",
            "subcategory":"Auto Repair",
            "type":"Services"
        }
    ],
    "sg:phone":"+1 251 344 7545",
    "sg:postcode":"36618",
    "sg:province":"AL",
    "sg:tags":[
        "repairing",
        "automobile"
    ],
    "wof:name":"Southern Auto Repair",
    "wof:placetype":"venue"
},
  "geometry": {"coordinates":[-88.125587,30.709193],"type":"Point"}
}