{
  "type": "Feature",
  "properties": {
    "iso:country":"US",
    "sg:address":"665 S Conception St",
    "sg:city":"Mobile",
    "sg:classifiers":[
        {
            "category":"Bars & Pubs",
            "type":"Food & Drink"
        }
    ],
    "sg:phone":"+1 251 694 7978",
    "sg:postcode":"36603",
    "sg:province":"AL",
    "sg:tags":[
        "lounge",
        "cocktail"
    ],
    "wof:name":"Johnson's Lounge",
    "wof:placetype":"venue"
},
  "geometry": {"coordinates":[-88.043096,30.676146],"type":"Point"}
}