{
  "type": "Feature",
  "properties": {
    "iso:country":"US",
    "sg:address":"405 Roebuck Dr",
    "sg:city":"Birmingham",
    "sg:classifiers":[
        {
            "category":"Building & Trades",
            "subcategory":"Pest Control",
            "type":"Services"
        }
    ],
    "sg:phone":"+1 205 836 8431",
    "sg:postcode":"35215",
    "sg:province":"AL",
    "wof:name":"Southern Termite Control",
    "wof:placetype":"venue"
},
  "geometry": {"coordinates":[-86.69813000000001,33.60022],"type":"Point"}
}