{
  "type": "Feature",
  "properties": {
    "iso:country":"US",
    "sg:address":"609 Co Rd 368",
    "sg:city":"Albertville",
    "sg:classifiers":[
        {
            "category":"Building & Trades",
            "subcategory":"Construction",
            "type":"Services"
        }
    ],
    "sg:phone":"+1 256 659 6262",
    "sg:postcode":"35951",
    "sg:province":"AL",
    "sg:tags":[
        "contractor"
    ],
    "wof:name":"Hills Siding",
    "wof:placetype":"venue"
},
  "geometry": {"coordinates":[-86.089609,34.398792],"type":"Point"}
}