{
  "type": "Feature",
  "properties": {
    "iso:country":"US",
    "sg:address":"6324 Whitesburg Dr S",
    "sg:city":"Huntsville",
    "sg:classifiers":[
        {
            "category":"Building & Trades",
            "subcategory":"Landscaping Services",
            "type":"Services"
        }
    ],
    "sg:phone":"+1 256 797 8061",
    "sg:postcode":"35802",
    "sg:province":"AL",
    "sg:tags":[
        "tree"
    ],
    "wof:name":"Tree Techs",
    "wof:placetype":"venue"
},
  "geometry": {"coordinates":[-86.568201,34.679705],"type":"Point"}
}