{
  "type": "Feature",
  "properties": {
    "addr:full":"812 Regal Dr SW Huntsville AL 35801",
    "addr:housenumber":"812",
    "addr:postcode":"35801",
    "addr:street":"Regal Dr Sw",
    "iso:country":"US",
    "sg:address":"812 Regal Dr SW",
    "sg:city":"Huntsville",
    "sg:classifiers":[
        {
            "category":"Shopping",
            "subcategory":"Clothing, Apparel, & Fashions",
            "type":"Retail Goods"
        }
    ],
    "sg:phone":"+1 256 551 9006",
    "sg:postcode":"35801",
    "sg:province":"AL",
    "wof:name":"Madison Avenue Bridal & Formal",
    "wof:placetype":"venue"
},
  "geometry": {"coordinates":[-86.587462,34.709027],"type":"Point"}
}