{
  "type": "Feature",
  "properties": {
    "iso:country":"US",
    "sg:address":"9029 Co Rd 22",
    "sg:city":"Montevallo",
    "sg:classifiers":[
        {
            "category":"Wholesale",
            "subcategory":"Machinery & Supplies",
            "type":"Manufacturing & Wholesale Goods"
        }
    ],
    "sg:phone":"+1 205 668 1450",
    "sg:postcode":"35115",
    "sg:province":"AL",
    "sg:tags":[
        "equipment",
        "excavating",
        "industrial"
    ],
    "wof:name":"J & K Supply Co",
    "wof:placetype":"venue"
},
  "geometry": {"coordinates":[-86.790127,33.145951],"type":"Point"}
}