{
  "type": "Feature",
  "properties": {
    "iso:country":"US",
    "sg:address":"126 Fred Atkinson Rd",
    "sg:city":"Huntsville",
    "sg:classifiers":[
        {
            "category":"Shopping",
            "subcategory":"Hobbies, Toys, & Games",
            "type":"Retail Goods"
        }
    ],
    "sg:phone":"+1 256 837 7687",
    "sg:postcode":"35806",
    "sg:province":"AL",
    "sg:tags":[
        "product",
        "ceramic"
    ],
    "wof:name":"Precious Prints By Kristi",
    "wof:placetype":"venue"
},
  "geometry": {"coordinates":[-86.70339,34.781827],"type":"Point"}
}