{
  "type": "Feature",
  "properties": {
    "iso:country":"US",
    "sg:address":"749 E Thach Ave",
    "sg:city":"Auburn",
    "sg:classifiers":[
        {
            "category":"Education",
            "subcategory":"Library",
            "type":"Public Place"
        }
    ],
    "sg:phone":"+1 334 887 4997",
    "sg:postcode":"36830",
    "sg:province":"AL",
    "wof:name":"City Of Auburn Library",
    "wof:placetype":"venue"
},
  "geometry": {"coordinates":[-85.464901,32.604564],"type":"Point"}
}