{
  "type": "Feature",
  "properties": {
    "addr:full":"27480 State Rte 69 Jasper AL 35504",
    "addr:housenumber":"27480",
    "addr:postcode":"35504",
    "addr:street":"State Rte 69",
    "iso:country":"US",
    "sg:address":"27480 State Rte 69",
    "sg:city":"Jasper",
    "sg:classifiers":[
        {
            "category":"Organizations",
            "subcategory":"Religious Organization",
            "type":"Services"
        }
    ],
    "sg:phone":"+1 205 387 7956",
    "sg:postcode":"35504",
    "sg:province":"AL",
    "wof:name":"Boldo First Baptist Church",
    "wof:placetype":"venue"
},
  "geometry": {"coordinates":[-87.183837,33.852868],"type":"Point"}
}