{
  "type": "Feature",
  "properties": {
    "iso:country":"US",
    "sg:address":"2500 Ermine Dr",
    "sg:city":"Huntsville",
    "sg:classifiers":[
        {
            "category":"Professional",
            "subcategory":"Management & Consulting",
            "type":"Services"
        }
    ],
    "sg:phone":"+1 256 851 1809",
    "sg:postcode":"35810",
    "sg:province":"AL",
    "wof:name":"Adr Inc",
    "wof:placetype":"venue"
},
  "geometry": {"coordinates":[-86.605451,34.753012],"type":"Point"}
}