{
  "type": "Feature",
  "properties": {
    "addr:full":"2527 Co Rd 85 Deatsville AL 36022",
    "addr:housenumber":"2527;85",
    "addr:postcode":"36022",
    "addr:street":"Co Rd",
    "iso:country":"US",
    "sg:address":"2527 Co Rd 85",
    "sg:city":"Deatsville",
    "sg:classifiers":[
        {
            "category":"Wholesale",
            "subcategory":"Machinery & Supplies",
            "type":"Manufacturing & Wholesale Goods"
        }
    ],
    "sg:phone":"+1 334 358 2160",
    "sg:postcode":"36022",
    "sg:province":"AL",
    "sg:tags":[
        "equipment",
        "veterinarian"
    ],
    "wof:name":"Sunbelt Veterinary Supply Inc",
    "wof:placetype":"venue"
},
  "geometry": {"coordinates":[-86.43239699999999,32.600526],"type":"Point"}
}