{
  "type": "Feature",
  "properties": {
    "iso:country":"US",
    "sg:address":"740 S Cotton St",
    "sg:city":"Andalusia",
    "sg:classifiers":[
        {
            "category":"Shopping",
            "subcategory":"Jewelry",
            "type":"Retail Goods"
        }
    ],
    "sg:phone":"+1 334 222 0380",
    "sg:postcode":"36420",
    "sg:province":"AL",
    "sg:tags":[
        "jeweler"
    ],
    "wof:name":"Riley's Fine Jewelry",
    "wof:placetype":"venue"
},
  "geometry": {"coordinates":[-86.479241,31.298316],"type":"Point"}
}