{
  "type": "Feature",
  "properties": {
    "iso:country":"US",
    "sg:address":"4585 Ceasarville Rd",
    "sg:city":"Wetumpka",
    "sg:classifiers":[
        {
            "category":"Retail",
            "subcategory":"Auto Repair",
            "type":"Services"
        }
    ],
    "sg:phone":"+1 334 569 3747",
    "sg:postcode":"36092",
    "sg:province":"AL",
    "wof:name":"Grace Auto & Forklift Repair",
    "wof:placetype":"venue"
},
  "geometry": {"coordinates":[-86.318572,32.620291],"type":"Point"}
}