{
  "type": "Feature",
  "properties": {
    "iso:country":"US",
    "sg:address":"506 Broad St",
    "sg:city":"Gadsden",
    "sg:classifiers":[
        {
            "category":"Shopping",
            "subcategory":"Hobbies, Toys, & Games",
            "type":"Retail Goods"
        }
    ],
    "sg:phone":"+1 256 546 1503",
    "sg:postcode":"35901",
    "sg:province":"AL",
    "sg:tags":[
        "doll"
    ],
    "wof:name":"Dolls2go.Com Inc",
    "wof:placetype":"venue"
},
  "geometry": {"coordinates":[-86.006288,34.014267],"type":"Point"}
}