{
  "type": "Feature",
  "properties": {
    "addr:full":"1037 Gardner St Gadsden AL 35901",
    "addr:housenumber":"1037",
    "addr:postcode":"35901",
    "addr:street":"Gardner St",
    "iso:country":"US",
    "sg:address":"1037 Gardner St",
    "sg:city":"Gadsden",
    "sg:classifiers":[
        {
            "category":"Social Services",
            "subcategory":"Child Care",
            "type":"Services"
        }
    ],
    "sg:phone":"+1 256 547 0292",
    "sg:postcode":"35901",
    "sg:province":"AL",
    "sg:tags":[
        "day"
    ],
    "wof:name":"Sheades Daycare",
    "wof:placetype":"venue"
},
  "geometry": {"coordinates":[-86.016358,34.020325],"type":"Point"}
}