{
  "type": "Feature",
  "properties": {
    "iso:country":"US",
    "sg:address":"2908 W Main St",
    "sg:city":"Mobile",
    "sg:classifiers":[
        {
            "category":"Wholesale",
            "subcategory":"Scrap",
            "type":"Manufacturing & Wholesale Goods"
        }
    ],
    "sg:phone":"+1 251 452 8715",
    "sg:postcode":"36612",
    "sg:province":"AL",
    "sg:tags":[
        "disposal",
        "tire"
    ],
    "wof:name":"Mobile Tire Recyclers",
    "wof:placetype":"venue"
},
  "geometry": {"coordinates":[-88.104226,30.750191],"type":"Point"}
}