{
  "type": "Feature",
  "properties": {
    "addr:full":"8554 US Hwy 72 Alt Madison AL 35758",
    "addr:housenumber":"8554",
    "addr:postcode":"35758",
    "addr:street":"Us Hwy 72 Alt",
    "iso:country":"US",
    "sg:address":"8554 US Hwy 72 Alt",
    "sg:city":"Madison",
    "sg:classifiers":[
        {
            "category":"Shopping",
            "subcategory":"Used Merchandise",
            "type":"Retail Goods"
        }
    ],
    "sg:phone":"+1 256 864 0008",
    "sg:postcode":"35758",
    "sg:province":"AL",
    "sg:tags":[
        "shop",
        "thrift"
    ],
    "wof:name":"Thrift Shop",
    "wof:placetype":"venue"
},
  "geometry": {"coordinates":[-86.73844099999999,34.682134],"type":"Point"}
}