{
  "type": "Feature",
  "properties": {
    "addr:full":"902 East St Moulton AL 35650",
    "addr:housenumber":"902",
    "addr:postcode":"35650",
    "addr:street":"East St",
    "iso:country":"US",
    "sg:address":"902 East St",
    "sg:city":"Moulton",
    "sg:classifiers":[
        {
            "category":"Professional",
            "subcategory":"Business Services",
            "type":"Services"
        }
    ],
    "sg:phone":"+1 256 974 0279",
    "sg:postcode":"35650",
    "sg:province":"AL",
    "wof:name":"Fire Dept",
    "wof:placetype":"venue"
},
  "geometry": {"coordinates":[-87.288843,34.483512],"type":"Point"}
}