{
  "type": "Feature",
  "properties": {
    "iso:country":"US",
    "sg:address":"3502 Cottonwood Dr",
    "sg:city":"Montgomery",
    "sg:classifiers":[
        {
            "category":"Building & Trades",
            "subcategory":"Electrical",
            "type":"Services"
        }
    ],
    "sg:phone":"+1 334 887 8171",
    "sg:postcode":"36109",
    "sg:province":"AL",
    "sg:tags":[
        "electrical",
        "contractor"
    ],
    "wof:name":"Charter Communications",
    "wof:placetype":"venue"
},
  "geometry": {"coordinates":[-86.253666,32.380708],"type":"Point"}
}