{
  "type": "Feature",
  "properties": {
    "addr:full":"3276 Bel Air Mall Mobile AL 36606",
    "addr:housenumber":"3276",
    "addr:postcode":"36606",
    "addr:street":"Bel Air Mall",
    "iso:country":"US",
    "sg:address":"3276 Bel Air Mall",
    "sg:city":"Mobile",
    "sg:classifiers":[
        {
            "category":"Shopping",
            "subcategory":"Clothing, Apparel, & Fashions",
            "type":"Retail Goods"
        }
    ],
    "sg:phone":"+1 251 476 5190",
    "sg:postcode":"36606",
    "sg:province":"AL",
    "wof:name":"Lerner New York",
    "wof:placetype":"venue"
},
  "geometry": {"coordinates":[-88.12366,30.673479],"type":"Point"}
}