{
  "type": "Feature",
  "properties": {
    "iso:country":"US",
    "sg:address":"1876 Data Dr",
    "sg:city":"Birmingham",
    "sg:classifiers":[
        {
            "category":"Health Services",
            "subcategory":"Doctor",
            "type":"Services"
        }
    ],
    "sg:phone":"+1 205 444 5618",
    "sg:postcode":"35244",
    "sg:province":"AL",
    "sg:tags":[
        "dentist"
    ],
    "wof:name":"DDS",
    "wof:placetype":"venue"
},
  "geometry": {"coordinates":[-86.796033,33.372482],"type":"Point"}
}