{
  "type": "Feature",
  "properties": {
    "addr:full":"1703 Pelham Rd S Jacksonville AL 36265",
    "addr:housenumber":"1703",
    "addr:postcode":"36265",
    "addr:street":"Pelham Rd",
    "iso:country":"US",
    "sg:address":"1703 Pelham Rd S",
    "sg:city":"Jacksonville",
    "sg:classifiers":[
        {
            "category":"Government",
            "subcategory":"Office",
            "type":"Public Place"
        }
    ],
    "sg:phone":"+1 256 435 3521",
    "sg:postcode":"36265",
    "sg:province":"AL",
    "sg:tags":[
        "protection",
        "police"
    ],
    "wof:name":"Alabama State Troopers",
    "wof:placetype":"venue"
},
  "geometry": {"coordinates":[-85.761737,33.782015],"type":"Point"}
}