{
  "type": "Feature",
  "properties": {
    "addr:full":"1516 Quintard Ave Anniston AL 36201",
    "addr:housenumber":"1516",
    "addr:postcode":"36201",
    "addr:street":"Quintard Ave",
    "iso:country":"US",
    "sg:address":"1516 Quintard Ave",
    "sg:city":"Anniston",
    "sg:classifiers":[
        {
            "category":"Insurance",
            "subcategory":"Insurance Agent",
            "type":"Services"
        }
    ],
    "sg:phone":"+1 256 237 8700",
    "sg:postcode":"36201",
    "sg:province":"AL",
    "wof:name":"Alfa Insurance Corp",
    "wof:placetype":"venue"
},
  "geometry": {"coordinates":[-85.826937,33.664838],"type":"Point"}
}