{
  "type": "Feature",
  "properties": {
    "iso:country":"US",
    "sg:address":"3474 Roy Webb Rd",
    "sg:city":"Jacksonville",
    "sg:classifiers":[
        {
            "category":"Building & Trades",
            "subcategory":"Plumbing",
            "type":"Services"
        }
    ],
    "sg:phone":"+1 256 447 1894",
    "sg:postcode":"36265",
    "sg:province":"AL",
    "sg:tags":[
        "contractor"
    ],
    "wof:name":"Phillips Sons Htg A Conditiong",
    "wof:placetype":"venue"
},
  "geometry": {"coordinates":[-85.743105,33.885326],"type":"Point"}
}