{
  "type": "Feature",
  "properties": {
    "addr:full":"2000 Quintard Ave Anniston AL 36201",
    "addr:housenumber":"2000",
    "addr:postcode":"36201",
    "addr:street":"Quintard Ave",
    "iso:country":"US",
    "sg:address":"2000 Quintard Ave",
    "sg:city":"Anniston",
    "sg:classifiers":[
        {
            "category":"Restaurant",
            "type":"Food & Drink"
        }
    ],
    "sg:menulink":"http://www.allmenus.com/al/anniston/198614-kfc---kentucky-fried-chicken/menu/",
    "sg:phone":"+1 256 235 2234",
    "sg:postcode":"36201",
    "sg:province":"AL",
    "sg:tags":[
        "american",
        "chicken"
    ],
    "wof:name":"KFC - Kentucky Fried Chicken",
    "wof:placetype":"venue"
},
  "geometry": {"coordinates":[-85.826813,33.670336],"type":"Point"}
}