{
  "type": "Feature",
  "properties": {
    "iso:country":"US",
    "sg:address":"5100 Main St",
    "sg:city":"Brighton",
    "sg:classifiers":[
        {
            "category":"Building & Trades",
            "subcategory":"Plumbing",
            "type":"Services"
        }
    ],
    "sg:phone":"+1 205 426 8270",
    "sg:postcode":"35020",
    "sg:province":"AL",
    "sg:tags":[
        "plumbing",
        "contractor"
    ],
    "wof:name":"Design Plumbing Co",
    "wof:placetype":"venue"
},
  "geometry": {"coordinates":[-86.93638300000001,33.443351],"type":"Point"}
}