{
  "type": "Feature",
  "properties": {
    "iso:country":"US",
    "sg:address":"200 Cahaba Park Cir",
    "sg:city":"Birmingham",
    "sg:classifiers":[
        {
            "category":"Banks & Credit Unions",
            "subcategory":"Bank",
            "type":"Services"
        }
    ],
    "sg:phone":"+1 205 591 5055",
    "sg:postcode":"35242",
    "sg:province":"AL",
    "sg:tags":[
        "loan",
        "real estate"
    ],
    "sg:website":"www.homesouth.com",
    "wof:name":"Homesouth Mortgage Svc Inc",
    "wof:placetype":"venue"
},
  "geometry": {"coordinates":[-86.706164,33.429498],"type":"Point"}
}