{
  "type": "Feature",
  "properties": {
    "iso:country":"US",
    "sg:address":"1016 Cole Dr SE",
    "sg:city":"Huntsville",
    "sg:classifiers":[
        {
            "category":"Retail",
            "subcategory":"Auto Rental",
            "type":"Services"
        }
    ],
    "sg:phone":"+1 256 881 4736",
    "sg:postcode":"35802",
    "sg:province":"AL",
    "sg:tags":[
        "mobile",
        "home",
        "leasing"
    ],
    "wof:name":"Glenn'Ll Inc",
    "wof:placetype":"venue"
},
  "geometry": {"coordinates":[-86.557946,34.670655],"type":"Point"}
}