{
  "type": "Feature",
  "properties": {
    "addr:full":"1404 S Brundidge St Troy AL 36081",
    "addr:housenumber":"1404",
    "addr:postcode":"36081",
    "addr:street":"S Brundidge St",
    "iso:country":"US",
    "sg:address":"1404 S Brundidge St",
    "sg:city":"Troy",
    "sg:classifiers":[
        {
            "category":"Shopping",
            "subcategory":"Bicycles & Sporting Goods",
            "type":"Retail Goods"
        }
    ],
    "sg:phone":"+1 334 566 0022",
    "sg:postcode":"36081",
    "sg:province":"AL",
    "sg:tags":[
        "archery",
        "hunting",
        "supply"
    ],
    "wof:name":"Troy Sportshop LLC",
    "wof:placetype":"venue"
},
  "geometry": {"coordinates":[-85.96407499999999,31.787235],"type":"Point"}
}