{
  "type": "Feature",
  "properties": {
    "iso:country":"US",
    "sg:address":"2729 Eastern Blvd",
    "sg:city":"Montgomery",
    "sg:classifiers":[
        {
            "category":"Insurance",
            "subcategory":"Insurance Agent",
            "type":"Services"
        }
    ],
    "sg:phone":"+1 334 213 7440",
    "sg:postcode":"36117",
    "sg:province":"AL",
    "wof:name":"State Farm Insurance",
    "wof:placetype":"venue"
},
  "geometry": {"coordinates":[-86.222121,32.347771],"type":"Point"}
}