{
  "type": "Feature",
  "properties": {
    "iso:country":"US",
    "sg:address":"851 Goodyear Ave",
    "sg:city":"Gadsden",
    "sg:classifiers":[
        {
            "category":"Health Services",
            "subcategory":"Clinic",
            "type":"Services"
        }
    ],
    "sg:phone":"+1 256 543 3367",
    "sg:postcode":"35903",
    "sg:province":"AL",
    "wof:name":"Meridan Occupatnl Healthcare",
    "wof:placetype":"venue"
},
  "geometry": {"coordinates":[-85.97744,34.009331],"type":"Point"}
}