{
  "type": "Feature",
  "properties": {
    "iso:country":"US",
    "sg:address":"215 Gault Ave N",
    "sg:city":"Fort Payne",
    "sg:classifiers":[
        {
            "category":"Shopping",
            "subcategory":"Used Merchandise",
            "type":"Retail Goods"
        }
    ],
    "sg:phone":"+1 256 997 0945",
    "sg:postcode":"35967",
    "sg:province":"AL",
    "sg:tags":[
        "antique"
    ],
    "wof:name":"Locklear Sports & Antiques",
    "wof:placetype":"venue"
},
  "geometry": {"coordinates":[-85.72220299999999,34.441575],"type":"Point"}
}