{
  "type": "Feature",
  "properties": {
    "iso:country":"US",
    "sg:address":"1419 14th St S",
    "sg:city":"Birmingham",
    "sg:classifiers":[
        {
            "category":"Professional",
            "subcategory":"Computer Services",
            "type":"Services"
        }
    ],
    "sg:phone":"+1 205 939 3565",
    "sg:postcode":"35205",
    "sg:province":"AL",
    "sg:tags":[
        "programing",
        "custom"
    ],
    "wof:name":"Great New Day",
    "wof:placetype":"venue"
},
  "geometry": {"coordinates":[-86.803186,33.494316],"type":"Point"}
}