{
  "type": "Feature",
  "properties": {
    "iso:country":"US",
    "sg:address":"1223 N 3 Notch St",
    "sg:city":"Troy",
    "sg:classifiers":[
        {
            "category":"Professional",
            "subcategory":"Business Services",
            "type":"Services"
        }
    ],
    "sg:phone":"+1 334 566 4050",
    "sg:postcode":"36081",
    "sg:province":"AL",
    "wof:name":"AT&T",
    "wof:placetype":"venue"
},
  "geometry": {"coordinates":[-85.96283699999999,31.821091],"type":"Point"}
}