{
  "type": "Feature",
  "properties": {
    "iso:country":"US",
    "sg:address":"412 N Alice St",
    "sg:city":"Dothan",
    "sg:classifiers":[
        {
            "category":"Professional",
            "type":"Services"
        }
    ],
    "sg:phone":"+1 334 699 2020",
    "sg:postcode":"36303",
    "sg:province":"AL",
    "sg:tags":[
        "establishment"
    ],
    "wof:name":"Afro Dothan Inc",
    "wof:placetype":"venue"
},
  "geometry": {"coordinates":[-85.3971,31.229079],"type":"Point"}
}