{
  "type": "Feature",
  "properties": {
    "iso:country":"US",
    "sg:address":"19519 Co Rd 26",
    "sg:city":"Oneonta",
    "sg:classifiers":[
        {
            "category":"Wholesale",
            "subcategory":"Non-durable Goods",
            "type":"Manufacturing & Wholesale Goods"
        }
    ],
    "sg:phone":"+1 205 466 7473",
    "sg:postcode":"35121",
    "sg:province":"AL",
    "wof:name":"O K Litter Service Inc",
    "wof:placetype":"venue"
},
  "geometry": {"coordinates":[-86.457838,34.04287],"type":"Point"}
}