{
  "type": "Feature",
  "properties": {
    "addr:full":"457 Flint Hill Rd Bessemer AL 35022",
    "addr:housenumber":"457",
    "addr:postcode":"35022",
    "addr:street":"Flint Hill Rd",
    "iso:country":"US",
    "sg:address":"457 Flint Hill Rd",
    "sg:city":"Bessemer",
    "sg:classifiers":[
        {
            "category":"Real Estate",
            "subcategory":"Real Estate Operator",
            "type":"Services"
        }
    ],
    "sg:phone":"+1 205 426 6394",
    "sg:postcode":"35022",
    "sg:province":"AL",
    "sg:tags":[
        "apartment"
    ],
    "wof:name":"Green Isle Apartments-Bessemer",
    "wof:placetype":"venue"
},
  "geometry": {"coordinates":[-86.997384,33.355651],"type":"Point"}
}