{
  "type": "Feature",
  "properties": {
    "iso:country":"US",
    "sg:address":"602 Ludmor Rd",
    "sg:city":"Dothan",
    "sg:classifiers":[
        {
            "category":"Building & Trades",
            "subcategory":"Landscaping Services",
            "type":"Services"
        }
    ],
    "sg:phone":"+1 334 692 3823",
    "sg:postcode":"36303",
    "sg:province":"AL",
    "wof:name":"Simmons Mowing Service",
    "wof:placetype":"venue"
},
  "geometry": {"coordinates":[-85.511153,31.247105],"type":"Point"}
}