{
  "type": "Feature",
  "properties": {
    "iso:country":"US",
    "sg:address":"13321 Moffett Rd",
    "sg:city":"Wilmer",
    "sg:classifiers":[
        {
            "category":"Shopping",
            "subcategory":"Gifts & Souvenirs",
            "type":"Retail Goods"
        }
    ],
    "sg:phone":"+1 251 645 3130",
    "sg:postcode":"36587",
    "sg:province":"AL",
    "sg:tags":[
        "shop"
    ],
    "wof:name":"Cherry Berry Gifts & Baskets",
    "wof:placetype":"venue"
},
  "geometry": {"coordinates":[-88.351846,30.820258],"type":"Point"}
}