{
  "type": "Feature",
  "properties": {
    "iso:country":"US",
    "sg:address":"1015 Co Rd 183",
    "sg:city":"Moulton",
    "sg:classifiers":[
        {
            "category":"Freight",
            "type":"Transportation"
        }
    ],
    "sg:phone":"+1 256 974 4204",
    "sg:postcode":"35650",
    "sg:province":"AL",
    "wof:name":"A P Express",
    "wof:placetype":"venue"
},
  "geometry": {"coordinates":[-87.240257,34.428664],"type":"Point"}
}