{
  "type": "Feature",
  "properties": {
    "iso:country":"US",
    "sg:address":"1835 Old Shell Rd",
    "sg:city":"Mobile",
    "sg:classifiers":[
        {
            "category":"Insurance",
            "subcategory":"Insurance Agent",
            "type":"Services"
        }
    ],
    "sg:phone":"+1 251 470 5915",
    "sg:postcode":"36607",
    "sg:province":"AL",
    "sg:tags":[
        "processing"
    ],
    "wof:name":"Medical Claims Assistance",
    "wof:placetype":"venue"
},
  "geometry": {"coordinates":[-88.085629,30.687616],"type":"Point"}
}