{
  "type": "Feature",
  "properties": {
    "iso:country":"US",
    "sg:address":"1004 Shady Brook Dr",
    "sg:city":"Mobile",
    "sg:classifiers":[
        {
            "category":"Building & Trades",
            "subcategory":"Construction",
            "type":"Services"
        }
    ],
    "sg:phone":"+1 251 478 3128",
    "sg:postcode":"36606",
    "sg:province":"AL",
    "sg:tags":[
        "residential"
    ],
    "wof:name":"Three Bears Developement LLC",
    "wof:placetype":"venue"
},
  "geometry": {"coordinates":[-88.120023,30.657347],"type":"Point"}
}