{
  "type": "Feature",
  "properties": {
    "addr:full":"1000 Main St Daphne AL 36526",
    "addr:housenumber":"1000",
    "addr:postcode":"36526",
    "addr:street":"Main St",
    "iso:country":"US",
    "sg:address":"1000 Main St",
    "sg:city":"Daphne",
    "sg:classifiers":[
        {
            "category":"Education",
            "subcategory":"School",
            "type":"Public Place"
        }
    ],
    "sg:phone":"+1 251 626 0277",
    "sg:postcode":"36526",
    "sg:province":"AL",
    "wof:name":"Daphne Elementary Schl S Cmps",
    "wof:placetype":"venue"
},
  "geometry": {"coordinates":[-87.90278000000001,30.591027],"type":"Point"}
}