{
  "type": "Feature",
  "properties": {
    "addr:full":"1207 1st Ave Selma AL 36703",
    "addr:housenumber":"1207",
    "addr:postcode":"36703",
    "addr:street":"1St Ave",
    "iso:country":"US",
    "sg:address":"1207 1st Ave",
    "sg:city":"Selma",
    "sg:classifiers":[
        {
            "category":"Organizations",
            "subcategory":"Religious Organization",
            "type":"Services"
        }
    ],
    "sg:phone":"+1 334 875 3494",
    "sg:postcode":"36703",
    "sg:province":"AL",
    "wof:name":"Grtr Stpauls Missionary Baptst",
    "wof:placetype":"venue"
},
  "geometry": {"coordinates":[-87.019975,32.422307],"type":"Point"}
}