{
  "type": "Feature",
  "properties": {
    "iso:country":"US",
    "sg:address":"3245 Montgomery Hwy",
    "sg:city":"Dothan",
    "sg:classifiers":[
        {
            "category":"Communications",
            "subcategory":"Radio Station",
            "type":"Services"
        }
    ],
    "sg:phone":"+1 334 712 1182",
    "sg:postcode":"36303",
    "sg:province":"AL",
    "sg:tags":[
        "company",
        "broadcasting"
    ],
    "wof:name":"Country",
    "wof:placetype":"venue"
},
  "geometry": {"coordinates":[-85.42918899999999,31.253116],"type":"Point"}
}