{
  "type": "Feature",
  "properties": {
    "iso:country":"US",
    "sg:address":"1317 Virginia Blvd NW",
    "sg:city":"Huntsville",
    "sg:classifiers":[
        {
            "category":"Manufacturing",
            "subcategory":"Tools & Machinery",
            "type":"Manufacturing & Wholesale Goods"
        }
    ],
    "sg:phone":"+1 256 533 1369",
    "sg:postcode":"35801",
    "sg:province":"AL",
    "sg:tags":[
        "instrument",
        "optical",
        "lense"
    ],
    "sg:website":"www.opti-matrix.com",
    "wof:name":"Opti-Matrix",
    "wof:placetype":"venue"
},
  "geometry": {"coordinates":[-86.58641299999999,34.748293],"type":"Point"}
}