{
  "type": "Feature",
  "properties": {
    "iso:country":"US",
    "sg:address":"1722 Pine St",
    "sg:city":"Montgomery",
    "sg:classifiers":[
        {
            "category":"Health Services",
            "subcategory":"Medical Lab",
            "type":"Services"
        }
    ],
    "sg:phone":"+1 334 262 9536",
    "sg:postcode":"36106",
    "sg:province":"AL",
    "sg:tags":[
        "laboratory"
    ],
    "wof:name":"Laboratory Corporation America",
    "wof:placetype":"venue"
},
  "geometry": {"coordinates":[-86.285822,32.366472],"type":"Point"}
}