{
  "type": "Feature",
  "properties": {
    "iso:country":"US",
    "sg:address":"4927 Altadena South Dr",
    "sg:city":"Birmingham",
    "sg:classifiers":[
        {
            "category":"Food & Beverages",
            "subcategory":"Groceries & Convenience Stores",
            "type":"Retail Goods"
        }
    ],
    "sg:phone":"+1 205 995 5777",
    "sg:postcode":"35244",
    "sg:province":"AL",
    "wof:name":"Modi International Inc",
    "wof:placetype":"venue"
},
  "geometry": {"coordinates":[-86.738115,33.389893],"type":"Point"}
}