{
  "type": "Feature",
  "properties": {
    "iso:country":"US",
    "sg:address":"133 Co Rd 38",
    "sg:city":"Horton",
    "sg:classifiers":[
        {
            "category":"Retail",
            "subcategory":"Auto Repair",
            "type":"Services"
        }
    ],
    "sg:phone":"+1 205 429 3482",
    "sg:postcode":"35980",
    "sg:province":"AL",
    "sg:tags":[
        "transmission"
    ],
    "wof:name":"Phillips Transmission",
    "wof:placetype":"venue"
},
  "geometry": {"coordinates":[-86.461711,34.133142],"type":"Point"}
}