{
  "type": "Feature",
  "properties": {
    "addr:full":"510 Cherokee Rd Alexander City AL 35010",
    "addr:housenumber":"510",
    "addr:postcode":"35010",
    "addr:street":"Cherokee Rd",
    "iso:country":"US",
    "sg:address":"510 Cherokee Rd",
    "sg:city":"Alexander City",
    "sg:classifiers":[
        {
            "category":"Autos & Motor Vehicles",
            "subcategory":"Auto Supplies",
            "type":"Retail Goods"
        }
    ],
    "sg:phone":"+1 256 234 3761",
    "sg:postcode":"35010",
    "sg:province":"AL",
    "sg:tags":[
        "tire"
    ],
    "wof:name":"Firestone Tire & Auto Ctr",
    "wof:placetype":"venue"
},
  "geometry": {"coordinates":[-85.953019,32.937664],"type":"Point"}
}