{
  "type": "Feature",
  "properties": {
    "addr:full":"1291 Priebes Mill Rd Oxford AL 36203",
    "addr:housenumber":"1291",
    "addr:postcode":"36203",
    "addr:street":"Priebes Mill Rd",
    "iso:country":"US",
    "sg:address":"1291 Priebes Mill Rd",
    "sg:city":"Oxford",
    "sg:classifiers":[
        {
            "category":"Autos & Motor Vehicles",
            "subcategory":"Boat Sales",
            "type":"Retail Goods"
        }
    ],
    "sg:phone":"+1 256 835 9199",
    "sg:postcode":"36203",
    "sg:province":"AL",
    "wof:name":"Choccolocco Canoe & Kayak",
    "wof:placetype":"venue"
},
  "geometry": {"coordinates":[-85.93848300000001,33.569845],"type":"Point"}
}