{
  "type": "Feature",
  "properties": {
    "iso:country":"US",
    "sg:address":"5920 Cinnamon Ct",
    "sg:city":"Mobile",
    "sg:classifiers":[
        {
            "category":"Shopping",
            "subcategory":"Bicycles & Sporting Goods",
            "type":"Retail Goods"
        }
    ],
    "sg:phone":"+1 251 665 0167",
    "sg:postcode":"36693",
    "sg:province":"AL",
    "wof:name":"Marvin Barnes",
    "wof:placetype":"venue"
},
  "geometry": {"coordinates":[-88.180408,30.630815],"type":"Point"}
}