{
  "type": "Feature",
  "properties": {
    "iso:country":"US",
    "sg:address":"500 Trillium Dr",
    "sg:city":"Eclectic",
    "sg:classifiers":[
        {
            "category":"Building & Trades",
            "subcategory":"Construction",
            "type":"Services"
        }
    ],
    "sg:phone":"+1 334 857 3298",
    "sg:postcode":"36024",
    "sg:province":"AL",
    "sg:tags":[
        "house"
    ],
    "wof:name":"Blackwell Construction Company",
    "wof:placetype":"venue"
},
  "geometry": {"coordinates":[-85.97944099999999,32.737035],"type":"Point"}
}