{
  "type": "Feature",
  "properties": {
    "iso:country":"US",
    "sg:address":"112 Saraland Blvd S",
    "sg:city":"Saraland",
    "sg:classifiers":[
        {
            "category":"Insurance",
            "subcategory":"Insurance Agent",
            "type":"Services"
        }
    ],
    "sg:phone":"+1 251 675 5556",
    "sg:postcode":"36571",
    "sg:province":"AL",
    "wof:name":"Farmers Insurance Group",
    "wof:placetype":"venue"
},
  "geometry": {"coordinates":[-88.07025299999999,30.818712],"type":"Point"}
}