{
  "type": "Feature",
  "properties": {
    "iso:country":"US",
    "sg:address":"2507 Pentelope Dr SE",
    "sg:city":"Huntsville",
    "sg:classifiers":[
        {
            "category":"Professional",
            "subcategory":"Computer Services",
            "type":"Services"
        }
    ],
    "sg:phone":"+1 256 533 4363",
    "sg:postcode":"35803",
    "sg:province":"AL",
    "sg:tags":[
        "related"
    ],
    "wof:name":"Z Shop",
    "wof:placetype":"venue"
},
  "geometry": {"coordinates":[-86.531508,34.626341],"type":"Point"}
}