{
  "type": "Feature",
  "properties": {
    "addr:full":"9105 Hokes Bluff Rd Centre AL 35960",
    "addr:postcode":"9105;35960",
    "addr:street":"Hokes Bluff Rd",
    "iso:country":"US",
    "sg:address":"9105 Hokes Bluff Rd",
    "sg:city":"Centre",
    "sg:classifiers":[
        {
            "category":"Building & Trades",
            "subcategory":"Construction",
            "type":"Services"
        }
    ],
    "sg:phone":"+1 256 927 5718",
    "sg:postcode":"35960",
    "sg:province":"AL",
    "sg:tags":[
        "nonresidential"
    ],
    "wof:name":"Ashley Garage",
    "wof:placetype":"venue"
},
  "geometry": {"coordinates":[-85.670345,34.138608],"type":"Point"}
}