{
  "type": "Feature",
  "properties": {
    "addr:full":"208 E Laurel St Scottsboro AL 35768",
    "addr:housenumber":"208",
    "addr:postcode":"35768",
    "addr:street":"E Laurel St",
    "iso:country":"US",
    "sg:address":"208 E Laurel St",
    "sg:city":"Scottsboro",
    "sg:classifiers":[
        {
            "category":"Education",
            "subcategory":"Special Training",
            "type":"Public Place"
        }
    ],
    "sg:phone":"+1 256 574 0100",
    "sg:postcode":"35768",
    "sg:province":"AL",
    "sg:tags":[
        "school",
        "language"
    ],
    "wof:name":"Espanol Tutoring Ctr LL",
    "wof:placetype":"venue"
},
  "geometry": {"coordinates":[-86.033174,34.672792],"type":"Point"}
}