{
  "type": "Feature",
  "properties": {
    "addr:full":"525 E Broad St Eufaula AL 36027",
    "addr:housenumber":"525",
    "addr:postcode":"36027",
    "addr:street":"E Broad St",
    "iso:country":"US",
    "sg:address":"525 E Broad St",
    "sg:city":"Eufaula",
    "sg:classifiers":[
        {
            "category":"Health Services",
            "subcategory":"Doctor",
            "type":"Services"
        }
    ],
    "sg:phone":"+1 334 687 4827",
    "sg:postcode":"36027",
    "sg:province":"AL",
    "sg:tags":[
        "medical"
    ],
    "wof:name":"Moses M Jones MD",
    "wof:placetype":"venue"
},
  "geometry": {"coordinates":[-85.138503,31.892912],"type":"Point"}
}