{
  "type": "Feature",
  "properties": {
    "addr:full":"308 1st St Lanett AL 36863",
    "addr:housenumber":"308",
    "addr:postcode":"36863",
    "addr:street":"1St St",
    "iso:country":"US",
    "sg:address":"308 1st St",
    "sg:city":"Lanett",
    "sg:classifiers":[
        {
            "category":"Home & Garden",
            "subcategory":"Furniture",
            "type":"Retail Goods"
        }
    ],
    "sg:phone":"+1 334 644 3639",
    "sg:postcode":"36863",
    "sg:province":"AL",
    "sg:tags":[
        "mattress"
    ],
    "wof:name":"Nations Discount Mattress",
    "wof:placetype":"venue"
},
  "geometry": {"coordinates":[-85.190878,32.868088],"type":"Point"}
}