{
  "type": "Feature",
  "properties": {
    "addr:full":"15620 Howells Ferry Rd Wilmer AL 36587",
    "addr:postcode":"15620;36587",
    "addr:street":"Howells Ferry Rd",
    "iso:country":"US",
    "sg:address":"15620 Howells Ferry Rd",
    "sg:city":"Wilmer",
    "sg:classifiers":[
        {
            "category":"Farming",
            "subcategory":"Farm",
            "type":"Manufacturing & Wholesale Goods"
        }
    ],
    "sg:phone":"+1 251 649 4263",
    "sg:postcode":"36587",
    "sg:province":"AL",
    "sg:tags":[
        "crop",
        "general"
    ],
    "wof:name":"Anthony Cecchi",
    "wof:placetype":"venue"
},
  "geometry": {"coordinates":[-88.41481899999999,30.785615],"type":"Point"}
}