{
  "type": "Feature",
  "properties": {
    "iso:country":"US",
    "sg:address":"151 N Foster St",
    "sg:city":"Dothan",
    "sg:classifiers":[
        {
            "category":"Food & Beverages",
            "subcategory":"Bakery",
            "type":"Retail Goods"
        }
    ],
    "sg:phone":"+1 334 702 9111",
    "sg:postcode":"36303",
    "sg:province":"AL",
    "wof:name":"River Nile Bakery & Eatery",
    "wof:placetype":"venue"
},
  "geometry": {"coordinates":[-85.39228,31.224351],"type":"Point"}
}