{
  "type": "Feature",
  "properties": {
    "iso:country":"US",
    "sg:address":"1400 Gunter Ave",
    "sg:city":"Guntersville",
    "sg:classifiers":[
        {
            "category":"Food & Beverages",
            "subcategory":"Groceries & Convenience Stores",
            "type":"Retail Goods"
        }
    ],
    "sg:phone":"+1 256 582 0880",
    "sg:postcode":"35976",
    "sg:province":"AL",
    "sg:tags":[
        "grocer"
    ],
    "wof:name":"Naivad's C & S",
    "wof:placetype":"venue"
},
  "geometry": {"coordinates":[-86.303372,34.346335],"type":"Point"}
}