{
  "type": "Feature",
  "properties": {
    "addr:full":"35 N Main St Arab AL 35016",
    "addr:housenumber":"35",
    "addr:postcode":"35016",
    "addr:street":"N Main St",
    "iso:country":"US",
    "sg:address":"35 N Main St",
    "sg:city":"Arab",
    "sg:classifiers":[
        {
            "category":"Restaurant",
            "type":"Food & Drink"
        }
    ],
    "sg:phone":"+1 256 931 2335",
    "sg:postcode":"35016",
    "sg:province":"AL",
    "sg:tags":[
        "eating"
    ],
    "wof:name":"Grumpys",
    "wof:placetype":"venue"
},
  "geometry": {"coordinates":[-86.495857,34.31729],"type":"Point"}
}