{
  "type": "Feature",
  "properties": {
    "iso:country":"US",
    "sg:address":"15315 US Hwy 43",
    "sg:city":"Russellville",
    "sg:classifiers":[
        {
            "category":"Banks & Credit Unions",
            "subcategory":"Bank",
            "type":"Services"
        }
    ],
    "sg:phone":"+1 256 331 0600",
    "sg:postcode":"35653",
    "sg:province":"AL",
    "wof:name":"First Metro Bank",
    "wof:placetype":"venue"
},
  "geometry": {"coordinates":[-87.717579,34.513245],"type":"Point"}
}