{
  "type": "Feature",
  "properties": {
    "iso:country":"US",
    "sg:address":"5700 Walnut Grove Rd",
    "sg:city":"Birmingham",
    "sg:classifiers":[
        {
            "category":"Building & Trades",
            "subcategory":"Construction",
            "type":"Services"
        }
    ],
    "sg:phone":"+1 205 681 0512",
    "sg:postcode":"35215",
    "sg:province":"AL",
    "sg:tags":[
        "hanging",
        "contractor"
    ],
    "wof:name":"Dynamic Painting and Dctg",
    "wof:placetype":"venue"
},
  "geometry": {"coordinates":[-86.709159,33.671268],"type":"Point"}
}