{
  "type": "Feature",
  "properties": {
    "iso:country":"US",
    "sg:address":"5371 State Rte 67",
    "sg:city":"Somerville",
    "sg:classifiers":[
        {
            "category":"Personal",
            "subcategory":"Beauty Salon",
            "type":"Services"
        }
    ],
    "sg:phone":"+1 256 778 7255",
    "sg:postcode":"35670",
    "sg:province":"AL",
    "sg:tags":[
        "shop"
    ],
    "wof:name":"Graffiti II",
    "wof:placetype":"venue"
},
  "geometry": {"coordinates":[-86.755077,34.445279],"type":"Point"}
}