{
  "type": "Feature",
  "properties": {
    "iso:country":"US",
    "sg:address":"3651 Government Blvd",
    "sg:city":"Mobile",
    "sg:classifiers":[
        {
            "category":"Travel",
            "subcategory":"Hotels & Motels",
            "type":"Entertainment"
        }
    ],
    "sg:phone":"+1 251 666 7751",
    "sg:postcode":"36693",
    "sg:province":"AL",
    "wof:name":"Rest Inn",
    "wof:placetype":"venue"
},
  "geometry": {"coordinates":[-88.130573,30.646108],"type":"Point"}
}