{
  "type": "Feature",
  "properties": {
    "iso:country":"US",
    "sg:address":"959 Chestnut St",
    "sg:city":"Roanoke",
    "sg:classifiers":[
        {
            "category":"Food & Beverages",
            "subcategory":"Groceries & Convenience Stores",
            "type":"Retail Goods"
        }
    ],
    "sg:phone":"+1 334 863 2314",
    "sg:postcode":"36274",
    "sg:province":"AL",
    "sg:tags":[
        "grocer"
    ],
    "wof:name":"Bob & Myras Meats & Groceries",
    "wof:placetype":"venue"
},
  "geometry": {"coordinates":[-85.380032,33.135068],"type":"Point"}
}