{
  "type": "Feature",
  "properties": {
    "iso:country":"US",
    "sg:address":"618 Azalea Rd",
    "sg:city":"Mobile",
    "sg:classifiers":[
        {
            "category":"Manufacturing",
            "subcategory":"Metals",
            "type":"Manufacturing & Wholesale Goods"
        }
    ],
    "sg:phone":"+1 251 662 1170",
    "sg:postcode":"36609",
    "sg:province":"AL",
    "sg:tags":[
        "fiber",
        "optics",
        "system"
    ],
    "wof:name":"Southern Light",
    "wof:placetype":"venue"
},
  "geometry": {"coordinates":[-88.147263,30.656382],"type":"Point"}
}