{
  "type": "Feature",
  "properties": {
    "iso:country":"US",
    "sg:address":"1601 E 2nd St",
    "sg:city":"Sheffield",
    "sg:classifiers":[
        {
            "category":"Professional",
            "subcategory":"Computer Services",
            "type":"Services"
        }
    ],
    "sg:phone":"+1 256 389 9066",
    "sg:postcode":"35660",
    "sg:province":"AL",
    "sg:tags":[
        "repair"
    ],
    "sg:website":"www.advmicro.net",
    "wof:name":"Advanced Micro Svc",
    "wof:placetype":"venue"
},
  "geometry": {"coordinates":[-87.674641,34.759536],"type":"Point"}
}