{
  "type": "Feature",
  "properties": {
    "iso:country":"US",
    "sg:address":"244 S 5th St",
    "sg:city":"Gadsden",
    "sg:classifiers":[
        {
            "category":"Personal",
            "subcategory":"Beauty Salon",
            "type":"Services"
        }
    ],
    "sg:phone":"+1 256 546 0022",
    "sg:postcode":"35901",
    "sg:province":"AL",
    "sg:tags":[
        "full",
        "jewelry",
        "cosmetic"
    ],
    "wof:name":"Facets",
    "wof:placetype":"venue"
},
  "geometry": {"coordinates":[-86.006604,34.010736],"type":"Point"}
}