{
  "type": "Feature",
  "properties": {
    "iso:country":"US",
    "sg:address":"1400 Quintard Ave",
    "sg:city":"Anniston",
    "sg:classifiers":[
        {
            "category":"Retail",
            "subcategory":"Laundry & Dry Cleaning",
            "type":"Services"
        }
    ],
    "sg:phone":"+1 256 238 8145",
    "sg:postcode":"36201",
    "sg:province":"AL",
    "sg:tags":[
        "cleaners",
        "cleaner"
    ],
    "wof:name":"Concord Custom Cleaners 6119",
    "wof:placetype":"venue"
},
  "geometry": {"coordinates":[-85.826855,33.663427],"type":"Point"}
}