{
  "type": "Feature",
  "properties": {
    "iso:country":"US",
    "sg:address":"1843 Highway 36 E",
    "sg:city":"Hartselle",
    "sg:classifiers":[
        {
            "category":"Food & Beverages",
            "subcategory":"Groceries & Convenience Stores",
            "type":"Retail Goods"
        }
    ],
    "sg:phone":"+1 256 773 1977",
    "sg:postcode":"35640",
    "sg:province":"AL",
    "wof:name":"Kenny's Grocery",
    "wof:placetype":"venue"
},
  "geometry": {"coordinates":[-86.843746,34.447643],"type":"Point"}
}