{
  "type": "Feature",
  "properties": {
    "iso:country":"US",
    "sg:address":"1095 Industrial Pkwy",
    "sg:city":"Saraland",
    "sg:classifiers":[
        {
            "category":"Personal",
            "subcategory":"Beauty Salon",
            "type":"Services"
        }
    ],
    "sg:phone":"+1 251 679 1448",
    "sg:postcode":"36571",
    "sg:province":"AL",
    "sg:tags":[
        "shop"
    ],
    "wof:name":"Regal Nails",
    "wof:placetype":"venue"
},
  "geometry": {"coordinates":[-88.10042199999999,30.802013],"type":"Point"}
}