{
  "type": "Feature",
  "properties": {
    "iso:country":"US",
    "sg:address":"28170 N Main St",
    "sg:city":"Daphne",
    "sg:classifiers":[
        {
            "category":"Professional",
            "subcategory":"Business Services",
            "type":"Services"
        },
        {
            "category":"Building & Trades",
            "subcategory":"Equipment Rental",
            "type":"Services"
        }
    ],
    "sg:phone":"+1 251 626 9109",
    "sg:postcode":"36526",
    "sg:province":"AL",
    "sg:tags":[
        "leasing",
        "audio",
        "presentation"
    ],
    "wof:name":"Media Services LLC",
    "wof:placetype":"venue"
},
  "geometry": {"coordinates":[-87.910565,30.640107],"type":"Point"}
}