{
  "type": "Feature",
  "properties": {
    "iso:country":"US",
    "sg:address":"366 Cox Creek Pkwy",
    "sg:city":"Florence",
    "sg:classifiers":[
        {
            "category":"Shopping",
            "subcategory":"Hobbies, Toys, & Games",
            "type":"Retail Goods"
        }
    ],
    "sg:phone":"+1 256 740 0655",
    "sg:postcode":"35630",
    "sg:province":"AL",
    "sg:tags":[
        "supply"
    ],
    "wof:name":"EB Games",
    "wof:placetype":"venue"
},
  "geometry": {"coordinates":[-87.63154400000001,34.836867],"type":"Point"}
}