{
  "type": "Feature",
  "properties": {
    "iso:country":"US",
    "sg:address":"192 Co Rd 611",
    "sg:city":"Smiths",
    "sg:classifiers":[
        {
            "category":"Professional",
            "type":"Services"
        }
    ],
    "sg:phone":"+1 334 298 2063",
    "sg:postcode":"36877",
    "sg:province":"AL",
    "wof:name":"Clarkco Inc",
    "wof:placetype":"venue"
},
  "geometry": {"coordinates":[-85.036828,32.552988],"type":"Point"}
}