{
  "type": "Feature",
  "properties": {
    "addr:full":"679 State Rte 17 Silas AL 36919",
    "addr:housenumber":"679",
    "addr:postcode":"36919",
    "addr:street":"State Rte 17 Silas",
    "iso:country":"US",
    "sg:address":"679 State Rte 17",
    "sg:city":"Silas",
    "sg:classifiers":[
        {
            "category":"Food & Beverages",
            "subcategory":"Liquor & Beverages",
            "type":"Retail Goods"
        }
    ],
    "sg:phone":"+1 251 542 9965",
    "sg:postcode":"36919",
    "sg:province":"AL",
    "wof:name":"B & S Package Store",
    "wof:placetype":"venue"
},
  "geometry": {"coordinates":[-88.29702899999999,31.713634],"type":"Point"}
}