{
  "type": "Feature",
  "properties": {
    "iso:country":"US",
    "sg:address":"323 Lonnie Dr",
    "sg:city":"Muscle Shoals",
    "sg:classifiers":[
        {
            "category":"Wholesale",
            "subcategory":"Vending Machines",
            "type":"Manufacturing & Wholesale Goods"
        }
    ],
    "sg:phone":"+1 256 718 1078",
    "sg:postcode":"35661",
    "sg:province":"AL",
    "sg:tags":[
        "operator"
    ],
    "wof:name":"M&K Amusements LLC",
    "wof:placetype":"venue"
},
  "geometry": {"coordinates":[-87.631516,34.725187],"type":"Point"}
}