{
  "type": "Feature",
  "properties": {
    "addr:full":"409 S Cedar Ave Demopolis AL 36732",
    "addr:housenumber":"409",
    "addr:postcode":"36732",
    "addr:street":"S Cedar Ave",
    "iso:country":"US",
    "sg:address":"409 S Cedar Ave",
    "sg:city":"Demopolis",
    "sg:classifiers":[
        {
            "category":"Retail",
            "subcategory":"Laundry & Dry Cleaning",
            "type":"Services"
        }
    ],
    "sg:phone":"+1 334 289 0750",
    "sg:postcode":"36732",
    "sg:province":"AL",
    "sg:tags":[
        "cleaners"
    ],
    "wof:name":"Lily White Cleaners Inc",
    "wof:placetype":"venue"
},
  "geometry": {"coordinates":[-87.835291,32.513182],"type":"Point"}
}