{
  "type": "Feature",
  "properties": {
    "iso:country":"US",
    "sg:address":"3909 McGregor Ct",
    "sg:city":"Mobile",
    "sg:classifiers":[
        {
            "category":"Shopping",
            "subcategory":"Gifts & Souvenirs",
            "type":"Retail Goods"
        }
    ],
    "sg:phone":"+1 251 342 1205",
    "sg:postcode":"36608",
    "sg:province":"AL",
    "wof:name":"Glazed Bayou",
    "wof:placetype":"venue"
},
  "geometry": {"coordinates":[-88.145974,30.695344],"type":"Point"}
}