{
  "type": "Feature",
  "properties": {
    "iso:country":"US",
    "sg:address":"725 Big Nance St",
    "sg:city":"Moulton",
    "sg:classifiers":[
        {
            "category":"Shopping",
            "type":"Retail Goods"
        }
    ],
    "sg:phone":"+1 256 974 1116",
    "sg:postcode":"35650",
    "sg:province":"AL",
    "sg:tags":[
        "plumbing",
        "p",
        "merchandise"
    ],
    "wof:name":"Electrical Outlet",
    "wof:placetype":"venue"
},
  "geometry": {"coordinates":[-87.293666,34.481383],"type":"Point"}
}