{
  "type": "Feature",
  "properties": {
    "iso:country":"US",
    "sg:address":"9 Eastview Dr",
    "sg:city":"Madison",
    "sg:classifiers":[
        {
            "category":"Organizations",
            "subcategory":"Religious Organization",
            "type":"Services"
        }
    ],
    "sg:phone":"+1 256 772 4463",
    "sg:postcode":"35758",
    "sg:province":"AL",
    "sg:tags":[
        "church"
    ],
    "wof:name":"Crosspointe Church",
    "wof:placetype":"venue"
},
  "geometry": {"coordinates":[-86.706854,34.721014],"type":"Point"}
}