{
  "type": "Feature",
  "properties": {
    "addr:full":"602 US Hwy 231 Wetumpka AL 36093",
    "addr:housenumber":"602",
    "addr:postcode":"36093",
    "addr:street":"Us Hwy 231 Wetumpka",
    "iso:country":"US",
    "sg:address":"602 US Hwy 231",
    "sg:city":"Wetumpka",
    "sg:classifiers":[
        {
            "category":"Autos & Motor Vehicles",
            "subcategory":"Fuel & Gas Station",
            "type":"Retail Goods"
        }
    ],
    "sg:phone":"+1 334 567 7061",
    "sg:postcode":"36093",
    "sg:province":"AL",
    "sg:tags":[
        "oil"
    ],
    "wof:name":"Riverside Shell Svc Station",
    "wof:placetype":"venue"
},
  "geometry": {"coordinates":[-86.19807900000001,32.45749],"type":"Point"}
}