{
  "type": "Feature",
  "properties": {
    "addr:full":"3516 Cheshire Dr Birmingham AL 35242",
    "addr:housenumber":"3516",
    "addr:postcode":"35242",
    "addr:street":"Cheshire Dr",
    "iso:country":"US",
    "sg:address":"3516 Cheshire Dr",
    "sg:city":"Birmingham",
    "sg:classifiers":[
        {
            "category":"Wholesale",
            "subcategory":"Construction Materials",
            "type":"Manufacturing & Wholesale Goods"
        }
    ],
    "sg:phone":"+1 205 444 1344",
    "sg:postcode":"35242",
    "sg:province":"AL",
    "sg:tags":[
        "tank",
        "system",
        "septic"
    ],
    "wof:name":"GPM Environmental Inc",
    "wof:placetype":"venue"
},
  "geometry": {"coordinates":[-86.695368,33.400917],"type":"Point"}
}