{
  "type": "Feature",
  "properties": {
    "iso:country":"US",
    "sg:address":"3155 Dauphin St",
    "sg:city":"Mobile",
    "sg:classifiers":[
        {
            "category":"Retail",
            "subcategory":"Funeral Services",
            "type":"Services"
        }
    ],
    "sg:phone":"+1 251 479 4547",
    "sg:postcode":"36606",
    "sg:province":"AL",
    "sg:tags":[
        "director"
    ],
    "wof:name":"Radney Funeral Homes",
    "wof:placetype":"venue"
},
  "geometry": {"coordinates":[-88.117999,30.689565],"type":"Point"}
}