{
  "type": "Feature",
  "properties": {
    "iso:country":"US",
    "sg:address":"900 Palmer Ave",
    "sg:city":"Brighton",
    "sg:classifiers":[
        {
            "category":"Arts & Performance",
            "subcategory":"Theater",
            "type":"Entertainment"
        }
    ],
    "sg:phone":"+1 205 426 8560",
    "sg:postcode":"35020",
    "sg:province":"AL",
    "sg:tags":[
        "theatrical",
        "producer"
    ],
    "wof:name":"Chip Records & Save",
    "wof:placetype":"venue"
},
  "geometry": {"coordinates":[-86.930955,33.444333],"type":"Point"}
}