{
  "type": "Feature",
  "properties": {
    "addr:full":"1505 S White Ave Bay Minette AL 36507",
    "addr:housenumber":"1505",
    "addr:postcode":"36507",
    "addr:street":"S White Ave",
    "iso:country":"US",
    "sg:address":"1505 S White Ave",
    "sg:city":"Bay Minette",
    "sg:classifiers":[
        {
            "category":"Building & Trades",
            "subcategory":"Electrical",
            "type":"Services"
        }
    ],
    "sg:phone":"+1 251 937 6443",
    "sg:postcode":"36507",
    "sg:province":"AL",
    "sg:tags":[
        "electrical",
        "contractor"
    ],
    "wof:name":"Bay Electrical",
    "wof:placetype":"venue"
},
  "geometry": {"coordinates":[-87.767897,30.866447],"type":"Point"}
}