{
  "type": "Feature",
  "properties": {
    "iso:country":"US",
    "sg:address":"1704 Crawford Rd",
    "sg:city":"Phenix City",
    "sg:classifiers":[
        {
            "category":"Home & Garden",
            "subcategory":"Furniture",
            "type":"Retail Goods"
        }
    ],
    "sg:phone":"+1 334 291 7909",
    "sg:postcode":"36867",
    "sg:province":"AL",
    "sg:tags":[
        "cabinet"
    ],
    "wof:name":"J & J Cabinet Shop",
    "wof:placetype":"venue"
},
  "geometry": {"coordinates":[-85.02188599999999,32.474634],"type":"Point"}
}