{
  "type": "Feature",
  "properties": {
    "addr:full":"333 Franklin St SE Huntsville AL 35801",
    "addr:housenumber":"333",
    "addr:postcode":"35801",
    "addr:street":"Franklin St Se",
    "iso:country":"US",
    "sg:address":"333 Franklin St SE",
    "sg:city":"Huntsville",
    "sg:classifiers":[
        {
            "category":"Real Estate",
            "subcategory":"Real Estate Agent",
            "type":"Services"
        }
    ],
    "sg:phone":"+1 256 533 6705",
    "sg:postcode":"35801",
    "sg:province":"AL",
    "sg:tags":[
        "appraiser"
    ],
    "wof:name":"Appraisal Group",
    "wof:placetype":"venue"
},
  "geometry": {"coordinates":[-86.58373,34.729572],"type":"Point"}
}