{
  "type": "Feature",
  "properties": {
    "iso:country":"US",
    "sg:address":"45 Wright Ln",
    "sg:city":"Sylacauga",
    "sg:classifiers":[
        {
            "category":"Retail",
            "subcategory":"Repair Shop",
            "type":"Services"
        }
    ],
    "sg:phone":"+1 256 245 0700",
    "sg:postcode":"35150",
    "sg:province":"AL",
    "sg:tags":[
        "blacksmith"
    ],
    "wof:name":"Jan RG Hill Blacksmith Shop",
    "wof:placetype":"venue"
},
  "geometry": {"coordinates":[-86.325781,33.230329],"type":"Point"}
}