{
  "type": "Feature",
  "properties": {
    "iso:country":"US",
    "sg:address":"7611 Lake Rd S",
    "sg:city":"Mobile",
    "sg:classifiers":[
        {
            "category":"Government",
            "subcategory":"Office",
            "type":"Public Place"
        }
    ],
    "sg:phone":"+1 251 443 7982",
    "sg:postcode":"36605",
    "sg:province":"AL",
    "wof:name":"State Docks",
    "wof:placetype":"venue"
},
  "geometry": {"coordinates":[-88.091994,30.537811],"type":"Point"}
}