{
  "type": "Feature",
  "properties": {
    "addr:full":"12561 Mary Ann Beach Rd Fairhope AL 36532",
    "addr:housenumber":"12561",
    "addr:postcode":"36532",
    "addr:street":"Mary Ann Beach Rd",
    "iso:country":"US",
    "sg:address":"12561 Mary Ann Beach Rd",
    "sg:city":"Fairhope",
    "sg:classifiers":[
        {
            "category":"Building & Trades",
            "subcategory":"Landscaping Services",
            "type":"Services"
        }
    ],
    "sg:phone":"+1 251 928 7744",
    "sg:postcode":"36532",
    "sg:province":"AL",
    "sg:tags":[
        "landscape",
        "contractor"
    ],
    "wof:name":"Jubilee Landscape Inc",
    "wof:placetype":"venue"
},
  "geometry": {"coordinates":[-87.852439,30.407872],"type":"Point"}
}