{
  "type": "Feature",
  "properties": {
    "iso:country":"US",
    "sg:address":"9765 S Main St",
    "sg:city":"Wilsonville",
    "sg:classifiers":[
        {
            "category":"Retail",
            "subcategory":"Auto Repair",
            "type":"Services"
        }
    ],
    "sg:phone":"+1 205 670 0320",
    "sg:postcode":"35186",
    "sg:province":"AL",
    "sg:tags":[
        "repairing",
        "automobile"
    ],
    "wof:name":"Revis Auto Svc",
    "wof:placetype":"venue"
},
  "geometry": {"coordinates":[-86.485058,33.231663],"type":"Point"}
}