{
  "type": "Feature",
  "properties": {
    "addr:full":"15 Lynn Dr Florence AL 35633",
    "addr:housenumber":"15",
    "addr:postcode":"35633",
    "addr:street":"Lynn Dr",
    "iso:country":"US",
    "sg:address":"15 Lynn Dr",
    "sg:city":"Florence",
    "sg:classifiers":[
        {
            "category":"Professional",
            "subcategory":"Management & Consulting",
            "type":"Services"
        }
    ],
    "sg:phone":"+1 256 768 7897",
    "sg:postcode":"35633",
    "sg:province":"AL",
    "wof:name":"Hester Cnsulting Envmtl Servic",
    "wof:placetype":"venue"
},
  "geometry": {"coordinates":[-87.807969,34.911081],"type":"Point"}
}