{
  "type": "Feature",
  "properties": {
    "iso:country":"US",
    "sg:address":"2008 Rainbow Dr",
    "sg:city":"Gadsden",
    "sg:classifiers":[
        {
            "category":"Personal",
            "subcategory":"Beauty Salon",
            "type":"Services"
        }
    ],
    "sg:phone":"+1 256 546 7009",
    "sg:postcode":"35901",
    "sg:province":"AL",
    "sg:tags":[
        "shop"
    ],
    "wof:name":"First Impressions Hair Salon",
    "wof:placetype":"venue"
},
  "geometry": {"coordinates":[-86.015616,33.974439],"type":"Point"}
}