{
  "type": "Feature",
  "properties": {
    "iso:country":"US",
    "sg:address":"808 W Burdeshaw St",
    "sg:city":"Dothan",
    "sg:classifiers":[
        {
            "category":"Wholesale",
            "subcategory":"Medical Equipment & Supplies",
            "type":"Manufacturing & Wholesale Goods"
        }
    ],
    "sg:phone":"+1 334 671 3035",
    "sg:postcode":"36303",
    "sg:province":"AL",
    "sg:tags":[
        "physician",
        "surgeon"
    ],
    "wof:name":"Diabetic Resource Specialists",
    "wof:placetype":"venue"
},
  "geometry": {"coordinates":[-85.405233,31.228254],"type":"Point"}
}