{
  "type": "Feature",
  "properties": {
    "addr:full":"4604 Gary Ave Fairfield AL 35064",
    "addr:housenumber":"4604",
    "addr:postcode":"35064",
    "addr:street":"Gary Ave",
    "iso:country":"US",
    "sg:address":"4604 Gary Ave",
    "sg:city":"Fairfield",
    "sg:classifiers":[
        {
            "category":"Professional",
            "subcategory":"Advertising",
            "type":"Services"
        }
    ],
    "sg:phone":"+1 205 786 2111",
    "sg:postcode":"35064",
    "sg:province":"AL",
    "sg:tags":[
        "counselor"
    ],
    "wof:name":"Bill Barrow Advertising",
    "wof:placetype":"venue"
},
  "geometry": {"coordinates":[-86.915577,33.490932],"type":"Point"}
}