{
  "type": "Feature",
  "properties": {
    "addr:full":"1701 Pepperell Pkwy Opelika AL 36801",
    "addr:housenumber":"1701",
    "addr:postcode":"36801",
    "addr:street":"Pepperell Pkwy Opelika",
    "iso:country":"US",
    "sg:address":"1701 Pepperell Pkwy",
    "sg:city":"Opelika",
    "sg:classifiers":[
        {
            "category":"Retail",
            "subcategory":"Car Wash",
            "type":"Services"
        }
    ],
    "sg:phone":"+1 334 745 5001",
    "sg:postcode":"36801",
    "sg:province":"AL",
    "sg:tags":[
        "polishing",
        "washing"
    ],
    "wof:name":"Goo Goo Car Wash",
    "wof:placetype":"venue"
},
  "geometry": {"coordinates":[-85.39715700000001,32.638906],"type":"Point"}
}