{
  "type": "Feature",
  "properties": {
    "iso:country":"US",
    "sg:address":"180 E Glen Rd",
    "sg:city":"Alexandria",
    "sg:classifiers":[
        {
            "category":"Organizations",
            "subcategory":"Community Association",
            "type":"Services"
        }
    ],
    "sg:phone":"+1 256 820 9319",
    "sg:postcode":"36250",
    "sg:province":"AL",
    "wof:name":"Free Accpted Msons Jcksonville",
    "wof:placetype":"venue"
},
  "geometry": {"coordinates":[-85.86292400000001,33.761848],"type":"Point"}
}