{
  "type": "Feature",
  "properties": {
    "addr:full":"3384 Norman Bridge Rd Montgomery AL 36105",
    "addr:housenumber":"3384",
    "addr:postcode":"36105",
    "addr:street":"Norman Bridge Rd",
    "iso:country":"US",
    "sg:address":"3384 Norman Bridge Rd",
    "sg:city":"Montgomery",
    "sg:classifiers":[
        {
            "category":"Personal",
            "subcategory":"Barber",
            "type":"Services"
        }
    ],
    "sg:phone":"+1 334 263 0055",
    "sg:postcode":"36105",
    "sg:province":"AL",
    "sg:tags":[
        "shop"
    ],
    "wof:name":"Roots of Soul Barbershop",
    "wof:placetype":"venue"
},
  "geometry": {"coordinates":[-86.299728,32.346801],"type":"Point"}
}