{
  "type": "Feature",
  "properties": {
    "addr:full":"7681 Stonewall Rd Opelika AL 36801",
    "addr:housenumber":"7681",
    "addr:postcode":"36801",
    "addr:street":"Stonewall Rd",
    "iso:country":"US",
    "sg:address":"7681 Stonewall Rd",
    "sg:city":"Opelika",
    "sg:classifiers":[
        {
            "category":"Farming",
            "subcategory":"Farm",
            "type":"Manufacturing & Wholesale Goods"
        }
    ],
    "sg:phone":"+1 334 821 9670",
    "sg:postcode":"36801",
    "sg:province":"AL",
    "sg:tags":[
        "crop",
        "general"
    ],
    "wof:name":"Pp Farm",
    "wof:placetype":"venue"
},
  "geometry": {"coordinates":[-85.487979,32.688988],"type":"Point"}
}