{
  "type": "Feature",
  "properties": {
    "addr:full":"2891 Glen Gate Dr Bessemer AL 35022",
    "addr:housenumber":"2891",
    "addr:postcode":"35022",
    "addr:street":"Glen Gate Dr",
    "iso:country":"US",
    "sg:address":"2891 Glen Gate Dr",
    "sg:city":"Bessemer",
    "sg:classifiers":[
        {
            "category":"Building & Trades",
            "subcategory":"Construction",
            "type":"Services"
        }
    ],
    "sg:phone":"+1 205 426 5813",
    "sg:postcode":"35022",
    "sg:province":"AL",
    "sg:tags":[
        "house"
    ],
    "wof:name":"Lenox Homes Inc",
    "wof:placetype":"venue"
},
  "geometry": {"coordinates":[-86.931197,33.290218],"type":"Point"}
}