{
  "type": "Feature",
  "properties": {
    "iso:country":"US",
    "sg:address":"4521 US Hwy 80",
    "sg:city":"Phenix City",
    "sg:classifiers":[
        {
            "category":"Travel",
            "subcategory":"Hotels & Motels",
            "type":"Entertainment"
        }
    ],
    "sg:phone":"+1 334 298 9098",
    "sg:postcode":"36870",
    "sg:province":"AL",
    "sg:tags":[
        "operation"
    ],
    "wof:name":"Crawford Motor Inn",
    "wof:placetype":"venue"
},
  "geometry": {"coordinates":[-85.191433,32.456582],"type":"Point"}
}