{
  "type": "Feature",
  "properties": {
    "iso:country":"US",
    "sg:address":"4733 Overwood Cir",
    "sg:city":"Birmingham",
    "sg:classifiers":[
        {
            "category":"Building & Trades",
            "subcategory":"Construction",
            "type":"Services"
        }
    ],
    "sg:phone":"+1 205 965 6641",
    "sg:postcode":"35222",
    "sg:province":"AL",
    "sg:tags":[
        "house"
    ],
    "wof:name":"Artisan Builders LLC",
    "wof:placetype":"venue"
},
  "geometry": {"coordinates":[-86.759488,33.518816],"type":"Point"}
}