{
  "type": "Feature",
  "properties": {
    "iso:country":"US",
    "sg:address":"603 Hutchinson Ave",
    "sg:city":"Bay Minette",
    "sg:classifiers":[
        {
            "category":"Manufacturing",
            "subcategory":"Toys & Sporting Goods",
            "type":"Manufacturing & Wholesale Goods"
        }
    ],
    "sg:phone":"+1 251 937 5648",
    "sg:postcode":"36507",
    "sg:province":"AL",
    "sg:tags":[
        "mfg"
    ],
    "wof:name":"Orion Products",
    "wof:placetype":"venue"
},
  "geometry": {"coordinates":[-87.797765,30.875469],"type":"Point"}
}