{
  "type": "Feature",
  "properties": {
    "addr:full":"1400 21st Way S Birmingham AL 35205",
    "addr:housenumber":"1400",
    "addr:postcode":"35205",
    "addr:street":"21St Way S",
    "iso:country":"US",
    "sg:address":"1400 21st Way S",
    "sg:city":"Birmingham",
    "sg:classifiers":[
        {
            "category":"Professional",
            "subcategory":"Lawyer & Legal Services",
            "type":"Services"
        }
    ],
    "sg:phone":"+1 205 918 0025",
    "sg:postcode":"35205",
    "sg:province":"AL",
    "wof:name":"Richard R Newton Attorney",
    "wof:placetype":"venue"
},
  "geometry": {"coordinates":[-86.789699,33.498004],"type":"Point"}
}