{
  "type": "Feature",
  "properties": {
    "iso:country":"US",
    "sg:address":"792 Commerce Dr",
    "sg:city":"Alexander City",
    "sg:classifiers":[
        {
            "category":"Shopping",
            "type":"Retail Goods"
        }
    ],
    "sg:phone":"+1 256 329 8008",
    "sg:postcode":"35010",
    "sg:province":"AL",
    "sg:tags":[
        "merchandise"
    ],
    "wof:name":"Ebanr Banner Systems LLC",
    "wof:placetype":"venue"
},
  "geometry": {"coordinates":[-85.968906,32.936793],"type":"Point"}
}