{
  "type": "Feature",
  "properties": {
    "iso:country":"US",
    "sg:address":"1843 Mara Dr NE",
    "sg:city":"Birmingham",
    "sg:classifiers":[
        {
            "category":"Food & Beverages",
            "subcategory":"Meat & Fish",
            "type":"Retail Goods"
        }
    ],
    "sg:phone":"+1 205 815 3282",
    "sg:postcode":"35215",
    "sg:province":"AL",
    "wof:name":"Port City Seafood Market",
    "wof:placetype":"venue"
},
  "geometry": {"coordinates":[-86.675379,33.637667],"type":"Point"}
}