{
  "type": "Feature",
  "properties": {
    "addr:full":"1843 Mara Dr NE Birmingham AL 35215",
    "addr:housenumber":"1843",
    "addr:postcode":"35215",
    "addr:street":"Mara Dr Ne",
    "iso:country":"US",
    "sg:address":"1843 Mara Dr NE",
    "sg:city":"Birmingham",
    "sg:classifiers":[
        {
            "category":"Food & Beverages",
            "subcategory":"Meat & Fish",
            "type":"Retail Goods"
        }
    ],
    "sg:phone":"+1 205 815 3282",
    "sg:postcode":"35215",
    "sg:province":"AL",
    "wof:name":"Port City Seafood Market",
    "wof:placetype":"venue"
},
  "geometry": {"coordinates":[-86.67537900000001,33.637667],"type":"Point"}
}