{
  "type": "Feature",
  "properties": {
    "iso:country":"US",
    "sg:address":"1910 3rd Ave N",
    "sg:city":"Bessemer",
    "sg:classifiers":[
        {
            "category":"Home & Garden",
            "subcategory":"Furniture",
            "type":"Retail Goods"
        }
    ],
    "sg:phone":"+1 205 425 1611",
    "sg:postcode":"35020",
    "sg:province":"AL",
    "sg:tags":[
        "household",
        "appliance"
    ],
    "wof:name":"Ward-Mclure Furniture Co (del)",
    "wof:placetype":"venue"
},
  "geometry": {"coordinates":[-86.95276800000001,33.403631],"type":"Point"}
}