{
  "type": "Feature",
  "properties": {
    "iso:country":"US",
    "sg:address":"106 E 2nd St",
    "sg:city":"Tuscumbia",
    "sg:classifiers":[
        {
            "category":"Insurance",
            "subcategory":"Insurance Agent",
            "type":"Services"
        }
    ],
    "sg:phone":"+1 256 383 6780",
    "sg:postcode":"35674",
    "sg:province":"AL",
    "wof:name":"Alfa Insurance Corp",
    "wof:placetype":"venue"
},
  "geometry": {"coordinates":[-87.70215399999999,34.735315],"type":"Point"}
}