{
  "type": "Feature",
  "properties": {
    "iso:country":"US",
    "sg:address":"104 Market Center Dr",
    "sg:city":"Alabaster",
    "sg:classifiers":[
        {
            "category":"Retail",
            "subcategory":"Laundry & Dry Cleaning",
            "type":"Services"
        }
    ],
    "sg:phone":"+1 205 620 0192",
    "sg:postcode":"35007",
    "sg:province":"AL",
    "sg:tags":[
        "drycleaning",
        "plant",
        "drop"
    ],
    "wof:name":"Classic Cleaners",
    "wof:placetype":"venue"
},
  "geometry": {"coordinates":[-86.818668,33.23838],"type":"Point"}
}