{
  "type": "Feature",
  "properties": {
    "iso:country":"US",
    "sg:address":"29943 US Hwy 72",
    "sg:city":"Madison",
    "sg:classifiers":[
        {
            "category":"Retail",
            "subcategory":"Auto Repair",
            "type":"Services"
        }
    ],
    "sg:phone":"+1 256 325 5114",
    "sg:postcode":"35756",
    "sg:province":"AL",
    "sg:tags":[
        "body",
        "automobile",
        "painting"
    ],
    "wof:name":"Eagle Collision of Madison",
    "wof:placetype":"venue"
},
  "geometry": {"coordinates":[-86.799376,34.749125],"type":"Point"}
}