{
  "type": "Feature",
  "properties": {
    "iso:country":"US",
    "sg:address":"3725 Gulf Shores Pkwy",
    "sg:city":"Gulf Shores",
    "sg:classifiers":[
        {
            "category":"Autos & Motor Vehicles",
            "subcategory":"Motorcycle Sales",
            "type":"Retail Goods"
        }
    ],
    "sg:phone":"+1 251 981 8666",
    "sg:postcode":"36542",
    "sg:province":"AL",
    "sg:tags":[
        "scooter"
    ],
    "wof:name":"Fast Eddie's Cycles",
    "wof:placetype":"venue"
},
  "geometry": {"coordinates":[-87.683248,30.30511],"type":"Point"}
}