{
  "type": "Feature",
  "properties": {
    "addr:full":"250 River Run Alexander City AL 35010",
    "addr:housenumber":"250",
    "addr:postcode":"35010",
    "addr:street":"River Run",
    "iso:country":"US",
    "sg:address":"250 River Run",
    "sg:city":"Alexander City",
    "sg:classifiers":[
        {
            "category":"Recreation",
            "subcategory":"Marina",
            "type":"Entertainment"
        }
    ],
    "sg:phone":"+1 256 234 2022",
    "sg:postcode":"35010",
    "sg:province":"AL",
    "sg:tags":[
        "operation",
        "boat"
    ],
    "wof:name":"River North Marina",
    "wof:placetype":"venue"
},
  "geometry": {"coordinates":[-85.884221,32.892791],"type":"Point"}
}