{
  "type": "Feature",
  "properties": {
    "iso:country":"US",
    "sg:address":"1713 Creighton Ave SE",
    "sg:city":"Decatur",
    "sg:classifiers":[
        {
            "category":"Retail",
            "subcategory":"Repair Shop",
            "type":"Services"
        }
    ],
    "sg:phone":"+1 256 350 0079",
    "sg:postcode":"35601",
    "sg:province":"AL",
    "sg:tags":[
        "tool",
        "parts"
    ],
    "wof:name":"Power Tool Supply & Repair",
    "wof:placetype":"venue"
},
  "geometry": {"coordinates":[-86.980727,34.578394],"type":"Point"}
}