{
  "type": "Feature",
  "properties": {
    "iso:country":"US",
    "sg:address":"106 W Washington St",
    "sg:city":"Athens",
    "sg:classifiers":[
        {
            "category":"Building & Trades",
            "subcategory":"Construction",
            "type":"Services"
        }
    ],
    "sg:phone":"+1 256 230 1144",
    "sg:postcode":"35611",
    "sg:province":"AL",
    "sg:tags":[
        "kitchen",
        "installation",
        "cabinet"
    ],
    "wof:name":"Bath & Kitchen Shop",
    "wof:placetype":"venue"
},
  "geometry": {"coordinates":[-86.971035,34.802433],"type":"Point"}
}