{
  "type": "Feature",
  "properties": {
    "iso:country":"US",
    "sg:address":"5181 Washington Ferry Rd",
    "sg:city":"Montgomery",
    "sg:classifiers":[
        {
            "category":"Building & Trades",
            "subcategory":"Construction",
            "type":"Services"
        }
    ],
    "sg:phone":"+1 334 262 4350",
    "sg:postcode":"36108",
    "sg:province":"AL",
    "sg:tags":[
        "contractor"
    ],
    "wof:name":"Carter Construction Co",
    "wof:placetype":"venue"
},
  "geometry": {"coordinates":[-86.413033,32.397341],"type":"Point"}
}