{
  "type": "Feature",
  "properties": {
    "addr:full":"209 W Berry Ave Foley AL 36535",
    "addr:housenumber":"209",
    "addr:postcode":"36535",
    "addr:street":"W Berry Ave",
    "iso:country":"US",
    "sg:address":"209 W Berry Ave",
    "sg:city":"Foley",
    "sg:classifiers":[
        {
            "category":"Organizations",
            "subcategory":"Religious Organization",
            "type":"Services"
        }
    ],
    "sg:phone":"+1 251 943 8499",
    "sg:postcode":"36535",
    "sg:province":"AL",
    "sg:tags":[
        "church"
    ],
    "wof:name":"Foley Apostolic Church",
    "wof:placetype":"venue"
},
  "geometry": {"coordinates":[-87.686027,30.418262],"type":"Point"}
}