{
  "type": "Feature",
  "properties": {
    "iso:country":"US",
    "sg:address":"900 S Beltline Hwy",
    "sg:city":"Mobile",
    "sg:classifiers":[
        {
            "category":"Travel",
            "subcategory":"Hotels & Motels",
            "type":"Entertainment"
        }
    ],
    "sg:phone":"+1 251 344 5500",
    "sg:postcode":"36609",
    "sg:province":"AL",
    "sg:tags":[
        "operation"
    ],
    "wof:name":"Family Inns",
    "wof:placetype":"venue"
},
  "geometry": {"coordinates":[-88.128468,30.674668],"type":"Point"}
}