{
  "type": "Feature",
  "properties": {
    "addr:full":"101 Kyser Blvd Madison AL 35758",
    "addr:housenumber":"101",
    "addr:postcode":"35758",
    "addr:street":"Kyser Blvd",
    "iso:country":"US",
    "sg:address":"101 Kyser Blvd",
    "sg:city":"Madison",
    "sg:classifiers":[
        {
            "category":"Autos & Motor Vehicles",
            "subcategory":"Fuel & Gas Station",
            "type":"Retail Goods"
        }
    ],
    "sg:phone":"+1 256 464 0738",
    "sg:postcode":"35758",
    "sg:province":"AL",
    "sg:tags":[
        "oil"
    ],
    "wof:name":"Bud's",
    "wof:placetype":"venue"
},
  "geometry": {"coordinates":[-86.751481,34.689313],"type":"Point"}
}