{
  "type": "Feature",
  "properties": {
    "addr:full":"273 Cahaba Valley Pkwy Pelham AL 35124",
    "addr:housenumber":"273",
    "addr:postcode":"35124",
    "addr:street":"Cahaba Valley Pkwy",
    "iso:country":"US",
    "sg:address":"273 Cahaba Valley Pkwy",
    "sg:city":"Pelham",
    "sg:classifiers":[
        {
            "category":"Banks & Credit Unions",
            "subcategory":"Financial Services",
            "type":"Services"
        }
    ],
    "sg:phone":"+1 205 988 5919",
    "sg:postcode":"35124",
    "sg:province":"AL",
    "sg:tags":[
        "furniture"
    ],
    "sg:website":"www.ofusa.com",
    "wof:name":"Office Furniture USA",
    "wof:placetype":"venue"
},
  "geometry": {"coordinates":[-86.78332399999999,33.338749],"type":"Point"}
}