{
  "type": "Feature",
  "properties": {
    "iso:country":"US",
    "sg:address":"4116 Libby Dr",
    "sg:city":"Mobile",
    "sg:classifiers":[
        {
            "category":"Professional",
            "subcategory":"Accounting & Tax Preparation",
            "type":"Services"
        }
    ],
    "sg:phone":"+1 251 662 0016",
    "sg:postcode":"36693",
    "sg:province":"AL",
    "sg:tags":[
        "accountant"
    ],
    "wof:name":"E W Greer & Co",
    "wof:placetype":"venue"
},
  "geometry": {"coordinates":[-88.15208699999999,30.646357],"type":"Point"}
}