{
  "type": "Feature",
  "properties": {
    "addr:full":"21193 Co Rd 27 Fairhope AL 36532",
    "addr:housenumber":"21193;27",
    "addr:postcode":"36532",
    "addr:street":"Co Rd",
    "iso:country":"US",
    "sg:address":"21193 Co Rd 27",
    "sg:city":"Fairhope",
    "sg:classifiers":[
        {
            "category":"Shopping",
            "subcategory":"Used Merchandise",
            "type":"Retail Goods"
        }
    ],
    "sg:phone":"+1 251 928 6490",
    "sg:postcode":"36532",
    "sg:province":"AL",
    "sg:tags":[
        "antique"
    ],
    "wof:name":"Heirloom Antiques LLC",
    "wof:placetype":"venue"
},
  "geometry": {"coordinates":[-87.85244400000001,30.535982],"type":"Point"}
}