{
  "type": "Feature",
  "properties": {
    "iso:country":"US",
    "sg:address":"7871 Morris Hill Rd",
    "sg:city":"Semmes",
    "sg:classifiers":[
        {
            "category":"Retail",
            "subcategory":"Auto Repair",
            "type":"Services"
        }
    ],
    "sg:phone":"+1 251 649 5673",
    "sg:postcode":"36575",
    "sg:province":"AL",
    "sg:tags":[
        "body",
        "automobile",
        "top",
        "upholstery"
    ],
    "wof:name":"A R S Custom Auto Trim",
    "wof:placetype":"venue"
},
  "geometry": {"coordinates":[-88.221985,30.749462],"type":"Point"}
}