{
  "type": "Feature",
  "properties": {
    "addr:full":"756 Sullivan Ave Mobile AL 36606",
    "addr:housenumber":"756",
    "addr:postcode":"36606",
    "addr:street":"Sullivan Ave",
    "iso:country":"US",
    "sg:address":"756 Sullivan Ave",
    "sg:city":"Mobile",
    "sg:classifiers":[
        {
            "category":"Health Services",
            "subcategory":"Doctor",
            "type":"Services"
        }
    ],
    "sg:phone":"+1 251 471 2846",
    "sg:postcode":"36606",
    "sg:province":"AL",
    "sg:tags":[
        "medical"
    ],
    "wof:name":"Henri Rathle MD",
    "wof:placetype":"venue"
},
  "geometry": {"coordinates":[-88.10875299999999,30.664798],"type":"Point"}
}