{
  "type": "Feature",
  "properties": {
    "addr:full":"1195 W South Blvd Montgomery AL 36105",
    "addr:housenumber":"1195",
    "addr:postcode":"36105",
    "addr:street":"W South Blvd",
    "iso:country":"US",
    "sg:address":"1195 W South Blvd",
    "sg:city":"Montgomery",
    "sg:classifiers":[
        {
            "category":"Restaurant",
            "type":"Food & Drink"
        }
    ],
    "sg:menulink":"http://www.allmenus.com/al/hope-hull/173905-wendys/menu/",
    "sg:phone":"+1 334 284 4531",
    "sg:postcode":"36105",
    "sg:province":"AL",
    "sg:tags":[
        "burger",
        "american",
        "soup"
    ],
    "wof:name":"Wendy's",
    "wof:placetype":"venue"
},
  "geometry": {"coordinates":[-86.341773,32.328335],"type":"Point"}
}