{
  "type": "Feature",
  "properties": {
    "addr:full":"2 20th St N Ste 950 Birmingham AL 35203",
    "addr:housenumber":"2",
    "addr:postcode":"35203",
    "addr:street":"20Th St N Ste 950",
    "iso:country":"US",
    "sg:address":"2 20th St N Ste 950",
    "sg:city":"Birmingham",
    "sg:classifiers":[
        {
            "category":"Professional",
            "subcategory":"Employment Agencies",
            "type":"Services"
        }
    ],
    "sg:phone":"+1 205 972 1394",
    "sg:postcode":"35203",
    "sg:province":"AL",
    "sg:tags":[
        "opportunity"
    ],
    "wof:name":"Murse Professional Search Grou",
    "wof:placetype":"venue"
},
  "geometry": {"coordinates":[-86.804817,33.513199],"type":"Point"}
}