{
  "type": "Feature",
  "properties": {
    "iso:country":"US",
    "sg:address":"2101 Highland Ave S",
    "sg:city":"Birmingham",
    "sg:classifiers":[
        {
            "category":"Professional",
            "subcategory":"Lawyer & Legal Services",
            "type":"Services"
        }
    ],
    "sg:phone":"+1 205 870 3767",
    "sg:postcode":"35205",
    "sg:province":"AL",
    "sg:tags":[
        "attorney"
    ],
    "wof:name":"Austill Lewis & Simms",
    "wof:placetype":"venue"
},
  "geometry": {"coordinates":[-86.792918,33.499919],"type":"Point"}
}