{
  "type": "Feature",
  "properties": {
    "iso:country":"US",
    "sg:address":"3925 9th Ave",
    "sg:city":"Birmingham",
    "sg:classifiers":[
        {
            "category":"Food & Beverages",
            "subcategory":"Groceries & Convenience Stores",
            "type":"Retail Goods"
        }
    ],
    "sg:phone":"+1 205 785 1314",
    "sg:postcode":"35224",
    "sg:province":"AL",
    "wof:name":"Wylam Junction",
    "wof:placetype":"venue"
},
  "geometry": {"coordinates":[-86.91578,33.503935],"type":"Point"}
}