{
  "type": "Feature",
  "properties": {
    "iso:country":"US",
    "sg:address":"1059 S Ann St",
    "sg:city":"Mobile",
    "sg:classifiers":[
        {
            "category":"Organizations",
            "subcategory":"Religious Organization",
            "type":"Services"
        }
    ],
    "sg:phone":"+1 251 432 0700",
    "sg:postcode":"36605",
    "sg:province":"AL",
    "sg:tags":[
        "church"
    ],
    "wof:name":"Harvest Temple Church Of God",
    "wof:placetype":"venue"
},
  "geometry": {"coordinates":[-88.06786,30.666308],"type":"Point"}
}