{
  "type": "Feature",
  "properties": {
    "iso:country":"US",
    "sg:address":"1021 US Hwy 431",
    "sg:city":"Anniston",
    "sg:classifiers":[
        {
            "category":"Shopping",
            "type":"Retail Goods"
        }
    ],
    "sg:phone":"+1 256 237 7639",
    "sg:postcode":"36206",
    "sg:province":"AL",
    "sg:tags":[
        "merchandise"
    ],
    "wof:name":"Aquarium",
    "wof:placetype":"venue"
},
  "geometry": {"coordinates":[-85.831578,33.702832],"type":"Point"}
}