{
  "type": "Feature",
  "properties": {
    "iso:country":"US",
    "sg:address":"3013 Mitt Lary Rd",
    "sg:city":"Northport",
    "sg:classifiers":[
        {
            "category":"Building & Trades",
            "subcategory":"Equipment Rental",
            "type":"Services"
        }
    ],
    "sg:phone":"+1 205 333 8879",
    "sg:postcode":"35475",
    "sg:province":"AL",
    "sg:tags":[
        "leasing"
    ],
    "wof:name":"Jerry Fikes",
    "wof:placetype":"venue"
},
  "geometry": {"coordinates":[-87.57834200000001,33.302076],"type":"Point"}
}