{
  "type": "Feature",
  "properties": {
    "iso:country":"US",
    "sg:address":"233 Montclair Loop",
    "sg:city":"Daphne",
    "sg:classifiers":[
        {
            "category":"Professional",
            "subcategory":"Engineering",
            "type":"Services"
        }
    ],
    "sg:phone":"+1 251 626 6072",
    "sg:postcode":"36526",
    "sg:province":"AL",
    "wof:name":"ADB Surveying & Engineering Co",
    "wof:placetype":"venue"
},
  "geometry": {"coordinates":[-87.87464799999999,30.633468],"type":"Point"}
}