{
  "type": "Feature",
  "properties": {
    "addr:full":"1222 Jordan Ln NW Huntsville AL 35816",
    "addr:housenumber":"1222",
    "addr:postcode":"35816",
    "addr:street":"Jordan Ln Nw",
    "iso:country":"US",
    "sg:address":"1222 Jordan Ln NW",
    "sg:city":"Huntsville",
    "sg:classifiers":[
        {
            "category":"Food & Beverages",
            "subcategory":"Groceries & Convenience Stores",
            "type":"Retail Goods"
        }
    ],
    "sg:phone":"+1 256 536 1445",
    "sg:postcode":"35816",
    "sg:province":"AL",
    "wof:name":"La Colonial Tienda Mexicana",
    "wof:placetype":"venue"
},
  "geometry": {"coordinates":[-86.62809,34.740601],"type":"Point"}
}