{
  "type": "Feature",
  "properties": {
    "iso:country":"US",
    "sg:address":"111 E 3rd St",
    "sg:city":"Tuscumbia",
    "sg:classifiers":[
        {
            "category":"Insurance",
            "subcategory":"Insurance Agent",
            "type":"Services"
        }
    ],
    "sg:phone":"+1 256 381 1334",
    "sg:postcode":"35674",
    "sg:province":"AL",
    "wof:name":"State Farm Insurance",
    "wof:placetype":"venue"
},
  "geometry": {"coordinates":[-87.702232,34.734448],"type":"Point"}
}