{
  "type": "Feature",
  "properties": {
    "iso:country":"US",
    "sg:address":"475 Pine Grove Rd",
    "sg:city":"Madison",
    "sg:classifiers":[
        {
            "category":"Professional",
            "type":"Services"
        }
    ],
    "sg:phone":"+1 256 837 2351",
    "sg:postcode":"35757",
    "sg:province":"AL",
    "wof:name":"Dana Alicia & Paul",
    "wof:placetype":"venue"
},
  "geometry": {"coordinates":[-86.757233,34.794033],"type":"Point"}
}