{
  "type": "Feature",
  "properties": {
    "iso:country":"US",
    "sg:address":"32485 US Hwy 90",
    "sg:city":"Seminole",
    "sg:classifiers":[
        {
            "category":"Shopping",
            "subcategory":"Used Merchandise",
            "type":"Retail Goods"
        },
        {
            "category":"Banks & Credit Unions",
            "subcategory":"Bank",
            "type":"Services"
        }
    ],
    "sg:phone":"+1 251 946 2575",
    "sg:postcode":"36574",
    "sg:province":"AL",
    "sg:tags":[
        "loan"
    ],
    "wof:name":"Florabama Title Loans Inc",
    "wof:placetype":"venue"
},
  "geometry": {"coordinates":[-87.473793,30.515147],"type":"Point"}
}