{
  "type": "Feature",
  "properties": {
    "addr:full":"11009 Crestfield Dr SE Huntsville AL 35803",
    "addr:housenumber":"11009",
    "addr:postcode":"35803",
    "addr:street":"Crestfield Dr Se",
    "iso:country":"US",
    "sg:address":"11009 Crestfield Dr SE",
    "sg:city":"Huntsville",
    "sg:classifiers":[
        {
            "category":"Professional",
            "subcategory":"Business Services",
            "type":"Services"
        }
    ],
    "sg:phone":"+1 256 881 2907",
    "sg:postcode":"35803",
    "sg:province":"AL",
    "wof:name":"Ralph Hood Inc",
    "wof:placetype":"venue"
},
  "geometry": {"coordinates":[-86.560839,34.640094],"type":"Point"}
}