{
  "type": "Feature",
  "properties": {
    "iso:country":"US",
    "sg:address":"4414 10th Ave S",
    "sg:city":"Birmingham",
    "sg:classifiers":[
        {
            "category":"Professional",
            "subcategory":"Research",
            "type":"Services"
        },
        {
            "category":"Building & Trades",
            "subcategory":"Electrical",
            "type":"Services"
        }
    ],
    "sg:phone":"+1 205 592 6225",
    "sg:postcode":"35222",
    "sg:province":"AL",
    "sg:tags":[
        "control",
        "vibration",
        "system",
        "controls",
        "regulator",
        "measurement"
    ],
    "wof:name":"Bruel & Kjaer North America Inc",
    "wof:placetype":"venue"
},
  "geometry": {"coordinates":[-86.764242,33.513651],"type":"Point"}
}