{
  "type": "Feature",
  "properties": {
    "iso:country":"US",
    "sg:address":"87 White Frost Dr",
    "sg:city":"Montgomery",
    "sg:classifiers":[
        {
            "category":"Real Estate",
            "subcategory":"Real Estate Operator",
            "type":"Services"
        }
    ],
    "sg:phone":"+1 334 288 1470",
    "sg:postcode":"36116",
    "sg:province":"AL",
    "sg:tags":[
        "mobile",
        "home",
        "community"
    ],
    "wof:name":"Montgomery Regency Mobile Home",
    "wof:placetype":"venue"
},
  "geometry": {"coordinates":[-86.229449,32.318768],"type":"Point"}
}