{
  "type": "Feature",
  "properties": {
    "iso:country":"US",
    "sg:address":"623 Main St",
    "sg:city":"Montevallo",
    "sg:classifiers":[
        {
            "category":"Shopping",
            "subcategory":"Jewelry",
            "type":"Retail Goods"
        }
    ],
    "sg:phone":"+1 205 665 7296",
    "sg:postcode":"35115",
    "sg:province":"AL",
    "wof:name":"Lacey Jewelry & Gifts",
    "wof:placetype":"venue"
},
  "geometry": {"coordinates":[-86.863267,33.10024],"type":"Point"}
}