{
  "type": "Feature",
  "properties": {
    "addr:full":"915 US Hwy 31 Atmore AL 36502",
    "addr:housenumber":"915",
    "addr:postcode":"36502",
    "addr:street":"Us Hwy 31",
    "iso:country":"US",
    "sg:address":"915 US Hwy 31",
    "sg:city":"Atmore",
    "sg:classifiers":[
        {
            "category":"Shopping",
            "type":"Retail Goods"
        }
    ],
    "sg:phone":"+1 251 368 1309",
    "sg:postcode":"36502",
    "sg:province":"AL",
    "sg:tags":[
        "merchandise"
    ],
    "wof:name":"Mr Green Jeans Garden Center",
    "wof:placetype":"venue"
},
  "geometry": {"coordinates":[-87.595535,31.001098],"type":"Point"}
}