{
  "type": "Feature",
  "properties": {
    "iso:country":"US",
    "sg:address":"4040 Dean Rd",
    "sg:city":"Pinson",
    "sg:classifiers":[
        {
            "category":"Building & Trades",
            "subcategory":"Construction",
            "type":"Services"
        }
    ],
    "sg:phone":"+1 205 681 7341",
    "sg:postcode":"35126",
    "sg:province":"AL",
    "sg:tags":[
        "industrial"
    ],
    "wof:name":"Thomason Building",
    "wof:placetype":"venue"
},
  "geometry": {"coordinates":[-86.69205100000001,33.772361],"type":"Point"}
}