{
  "type": "Feature",
  "properties": {
    "iso:country":"US",
    "sg:address":"1391 Schillinger Rd S",
    "sg:city":"Mobile",
    "sg:classifiers":[
        {
            "category":"Mining & Drilling",
            "type":"Manufacturing & Wholesale Goods"
        }
    ],
    "sg:phone":"+1 251 639 9614",
    "sg:postcode":"36695",
    "sg:province":"AL",
    "sg:tags":[
        "oil",
        "gas",
        "producer"
    ],
    "wof:name":"My Mart Max Oil",
    "wof:placetype":"venue"
},
  "geometry": {"coordinates":[-88.225099,30.65742],"type":"Point"}
}