{
  "type": "Feature",
  "properties": {
    "iso:country":"US",
    "sg:address":"2304 Appletree Ct NE",
    "sg:city":"Huntsville",
    "sg:classifiers":[
        {
            "category":"Professional",
            "type":"Services"
        }
    ],
    "sg:phone":"+1 256 532 3132",
    "sg:postcode":"35801",
    "sg:province":"AL",
    "wof:name":"Rw Glatzau",
    "wof:placetype":"venue"
},
  "geometry": {"coordinates":[-86.549132,34.74316],"type":"Point"}
}