{
  "type": "Feature",
  "properties": {
    "addr:full":"1501 4th Ave SW Bessemer AL 35022",
    "addr:housenumber":"1501",
    "addr:postcode":"35022",
    "addr:street":"4Th Ave Sw",
    "iso:country":"US",
    "sg:address":"1501 4th Ave SW",
    "sg:city":"Bessemer",
    "sg:classifiers":[
        {
            "category":"Organizations",
            "subcategory":"Community Association",
            "type":"Services"
        }
    ],
    "sg:phone":"+1 205 426 1211",
    "sg:postcode":"35022",
    "sg:province":"AL",
    "wof:name":"Earl S Usher Bssemer Area YMCA",
    "wof:placetype":"venue"
},
  "geometry": {"coordinates":[-86.99176300000001,33.356132],"type":"Point"}
}