{
  "type": "Feature",
  "properties": {
    "addr:full":"2834 Pelham Pkwy Pelham AL 35124",
    "addr:housenumber":"2834",
    "addr:postcode":"35124",
    "addr:street":"Pelham Pkwy",
    "iso:country":"US",
    "sg:address":"2834 Pelham Pkwy",
    "sg:city":"Pelham",
    "sg:classifiers":[
        {
            "category":"Shopping",
            "subcategory":"Clothing, Apparel, & Fashions",
            "type":"Retail Goods"
        }
    ],
    "sg:phone":"+1 205 685 1334",
    "sg:postcode":"35124",
    "sg:province":"AL",
    "wof:name":"Nurses Ink Uniforms",
    "wof:placetype":"venue"
},
  "geometry": {"coordinates":[-86.807636,33.303115],"type":"Point"}
}