{
  "type": "Feature",
  "properties": {
    "iso:country":"US",
    "sg:address":"1803 Paint Rock Rd",
    "sg:city":"New Hope",
    "sg:classifiers":[
        {
            "category":"Building & Trades",
            "subcategory":"Construction",
            "type":"Services"
        }
    ],
    "sg:phone":"+1 256 723 2511",
    "sg:postcode":"35760",
    "sg:province":"AL",
    "sg:tags":[
        "contractor"
    ],
    "wof:name":"Stapler Painting & Drywall",
    "wof:placetype":"venue"
},
  "geometry": {"coordinates":[-86.327675,34.53371],"type":"Point"}
}