{
  "type": "Feature",
  "properties": {
    "addr:full":"106 Burke Ave SE Attalla AL 35954",
    "addr:housenumber":"106",
    "addr:postcode":"35954",
    "addr:street":"Burke Ave Se Attalla",
    "iso:country":"US",
    "sg:address":"106 Burke Ave SE",
    "sg:city":"Attalla",
    "sg:classifiers":[
        {
            "category":"Government",
            "subcategory":"Office",
            "type":"Public Place"
        }
    ],
    "sg:phone":"+1 256 538 9331",
    "sg:postcode":"35954",
    "sg:province":"AL",
    "sg:tags":[
        "national",
        "guard"
    ],
    "wof:name":"Alabama National Guard",
    "wof:placetype":"venue"
},
  "geometry": {"coordinates":[-86.104266,33.994528],"type":"Point"}
}