{
  "type": "Feature",
  "properties": {
    "iso:country":"US",
    "sg:address":"2662 Spring Hill Ave",
    "sg:city":"Mobile",
    "sg:classifiers":[
        {
            "category":"Restaurant",
            "type":"Food & Drink"
        }
    ],
    "sg:menulink":"http://www.allmenus.com/al/mobile/244310-gone-fishin/menu/",
    "sg:phone":"+1 251 479 5972",
    "sg:postcode":"36607",
    "sg:province":"AL",
    "sg:tags":[
        "american"
    ],
    "wof:name":"Gone Fishin'",
    "wof:placetype":"venue"
},
  "geometry": {"coordinates":[-88.10279800000001,30.696462],"type":"Point"}
}