{
  "type": "Feature",
  "properties": {
    "iso:country":"US",
    "sg:address":"200 Hospital Ave",
    "sg:city":"Ozark",
    "sg:classifiers":[
        {
            "category":"Health Services",
            "subcategory":"Doctor",
            "type":"Services"
        }
    ],
    "sg:phone":"+1 334 774 2630",
    "sg:postcode":"36360",
    "sg:province":"AL",
    "sg:tags":[
        "clinic"
    ],
    "wof:name":"Gambro Healthcare",
    "wof:placetype":"venue"
},
  "geometry": {"coordinates":[-85.63104300000001,31.450959],"type":"Point"}
}