{
  "type": "Feature",
  "properties": {
    "addr:full":"410 Parks Ave Scottsboro AL 35768",
    "addr:housenumber":"410",
    "addr:postcode":"35768",
    "addr:street":"Parks Ave",
    "iso:country":"US",
    "sg:address":"410 Parks Ave",
    "sg:city":"Scottsboro",
    "sg:classifiers":[
        {
            "category":"Insurance",
            "subcategory":"Hazard Insurance",
            "type":"Services"
        },
        {
            "category":"Professional",
            "subcategory":"Business Services",
            "type":"Services"
        }
    ],
    "sg:phone":"+1 256 574 5355",
    "sg:postcode":"35768",
    "sg:province":"AL",
    "sg:tags":[
        "bond"
    ],
    "wof:name":"Brock Bonding Company",
    "wof:placetype":"venue"
},
  "geometry": {"coordinates":[-86.04074900000001,34.666158],"type":"Point"}
}