{
  "type": "Feature",
  "properties": {
    "addr:full":"1701 Mcfarland Blvd E Tuscaloosa AL 35404",
    "addr:housenumber":"1701",
    "addr:postcode":"35404",
    "addr:street":"Mcfarland Blvd E",
    "iso:country":"US",
    "sg:address":"1701 Mcfarland Blvd E",
    "sg:city":"Tuscaloosa",
    "sg:classifiers":[
        {
            "category":"Restaurant",
            "type":"Food & Drink"
        }
    ],
    "sg:menulink":"http://www.allmenus.com/al/tuscaloosa/254959-taco-casa/menu/",
    "sg:phone":"+1 205 556 5674",
    "sg:postcode":"35404",
    "sg:province":"AL",
    "wof:name":"Taco Casa",
    "wof:placetype":"venue"
},
  "geometry": {"coordinates":[-87.525903,33.194982],"type":"Point"}
}