{
  "type": "Feature",
  "properties": {
    "addr:full":"205 Ashwood Cir Trussville AL 35173",
    "addr:housenumber":"205",
    "addr:postcode":"35173",
    "addr:street":"Ashwood Cir",
    "iso:country":"US",
    "sg:address":"205 Ashwood Cir",
    "sg:city":"Trussville",
    "sg:classifiers":[
        {
            "category":"Manufacturing",
            "subcategory":"Soap",
            "type":"Manufacturing & Wholesale Goods"
        }
    ],
    "sg:phone":"+1 205 655 4760",
    "sg:postcode":"35173",
    "sg:province":"AL",
    "sg:tags":[
        "detergent",
        "mfg"
    ],
    "wof:name":"Country Scents",
    "wof:placetype":"venue"
},
  "geometry": {"coordinates":[-86.623064,33.620751],"type":"Point"}
}