{
  "type": "Feature",
  "properties": {
    "iso:country":"US",
    "sg:address":"1050 Convalescent Rd",
    "sg:city":"Vernon",
    "sg:classifiers":[
        {
            "category":"Health Services",
            "subcategory":"Nursing And Care Facility",
            "type":"Services"
        }
    ],
    "sg:phone":"+1 205 695 9313",
    "sg:postcode":"35592",
    "sg:province":"AL",
    "wof:name":"Care Center Of Vernon",
    "wof:placetype":"venue"
},
  "geometry": {"coordinates":[-88.16298999999999,33.719542],"type":"Point"}
}