{
  "type": "Feature",
  "properties": {
    "addr:full":"7500 Memorial Pkwy SW Huntsville AL 35802",
    "addr:housenumber":"7500",
    "addr:postcode":"35802",
    "addr:street":"Memorial Pkwy Sw",
    "iso:country":"US",
    "sg:address":"7500 Memorial Pkwy SW",
    "sg:city":"Huntsville",
    "sg:classifiers":[
        {
            "category":"Real Estate",
            "subcategory":"Real Estate Agent",
            "type":"Services"
        }
    ],
    "sg:phone":"+1 256 880 7779",
    "sg:postcode":"35802",
    "sg:province":"AL",
    "wof:name":"Chief Waters Realty Co",
    "wof:placetype":"venue"
},
  "geometry": {"coordinates":[-86.57364800000001,34.669683],"type":"Point"}
}