{
  "type": "Feature",
  "properties": {
    "iso:country":"US",
    "sg:address":"151 Cindy Ln",
    "sg:city":"Birmingham",
    "sg:classifiers":[
        {
            "category":"Professional",
            "subcategory":"Business Services",
            "type":"Services"
        }
    ],
    "sg:phone":"+1 205 791 6841",
    "sg:postcode":"35214",
    "sg:province":"AL",
    "wof:name":"All Four Seasons Enterprises",
    "wof:placetype":"venue"
},
  "geometry": {"coordinates":[-86.894761,33.561241],"type":"Point"}
}