{
  "type": "Feature",
  "properties": {
    "iso:country":"US",
    "sg:address":"9095 Little River Rd",
    "sg:city":"Bayou La Batre",
    "sg:classifiers":[
        {
            "category":"Autos & Motor Vehicles",
            "subcategory":"Boat Sales",
            "type":"Retail Goods"
        }
    ],
    "sg:phone":"+1 251 824 4331",
    "sg:postcode":"36509",
    "sg:province":"AL",
    "sg:tags":[
        "marine",
        "supply"
    ],
    "wof:name":"Hebert Marine Supplies",
    "wof:placetype":"venue"
},
  "geometry": {"coordinates":[-88.256534,30.406956],"type":"Point"}
}