{
  "type": "Feature",
  "properties": {
    "addr:full":"3231 Warrior Valley Rd Altoona AL 35952",
    "addr:housenumber":"3231",
    "addr:postcode":"35952",
    "addr:street":"Warrior Valley Rd",
    "iso:country":"US",
    "sg:address":"3231 Warrior Valley Rd",
    "sg:city":"Altoona",
    "sg:classifiers":[
        {
            "category":"Organizations",
            "subcategory":"Religious Organization",
            "type":"Services"
        }
    ],
    "sg:phone":"+1 205 589 2548",
    "sg:postcode":"35952",
    "sg:province":"AL",
    "sg:tags":[
        "church"
    ],
    "wof:name":"Mt Pisgah Baptist Church",
    "wof:placetype":"venue"
},
  "geometry": {"coordinates":[-86.317723,34.000916],"type":"Point"}
}