{
  "type": "Feature",
  "properties": {
    "iso:country":"US",
    "sg:address":"700 N Iroquois Ave",
    "sg:city":"Dothan",
    "sg:classifiers":[
        {
            "category":"Professional",
            "type":"Services"
        }
    ],
    "sg:phone":"+1 334 794 4526",
    "sg:postcode":"36303",
    "sg:province":"AL",
    "wof:name":"Bridlewood Llc",
    "wof:placetype":"venue"
},
  "geometry": {"coordinates":[-85.41602399999999,31.236759],"type":"Point"}
}