{
  "type": "Feature",
  "properties": {
    "iso:country":"US",
    "sg:address":"5835 State Rte 36",
    "sg:city":"Danville",
    "sg:classifiers":[
        {
            "category":"Shopping",
            "subcategory":"Department Store",
            "type":"Retail Goods"
        }
    ],
    "sg:phone":"+1 256 751 9030",
    "sg:postcode":"35619",
    "sg:province":"AL",
    "sg:tags":[
        "shop"
    ],
    "wof:name":"Dollar General",
    "wof:placetype":"venue"
},
  "geometry": {"coordinates":[-87.089359,34.414869],"type":"Point"}
}