{
  "type": "Feature",
  "properties": {
    "iso:country":"US",
    "sg:address":"103 4th St N",
    "sg:city":"Oneonta",
    "sg:classifiers":[
        {
            "category":"Professional",
            "subcategory":"Lawyer & Legal Services",
            "type":"Services"
        }
    ],
    "sg:phone":"+1 205 625 6255",
    "sg:postcode":"35121",
    "sg:province":"AL",
    "sg:tags":[
        "attorney"
    ],
    "wof:name":"Steven D King",
    "wof:placetype":"venue"
},
  "geometry": {"coordinates":[-86.47366700000001,33.946924],"type":"Point"}
}