{
  "type": "Feature",
  "properties": {
    "iso:country":"US",
    "sg:address":"850 Blackburn Dr",
    "sg:city":"Mobile",
    "sg:classifiers":[
        {
            "category":"Restaurant",
            "type":"Food & Drink"
        }
    ],
    "sg:phone":"+1 251 633 2373",
    "sg:postcode":"36608",
    "sg:province":"AL",
    "wof:name":"Mother Mary's Family Rstrnt",
    "wof:placetype":"venue"
},
  "geometry": {"coordinates":[-88.260913,30.672518],"type":"Point"}
}