{
  "type": "Feature",
  "properties": {
    "iso:country":"US",
    "sg:address":"9550 Clebourne Rd",
    "sg:city":"Chunchula",
    "sg:classifiers":[
        {
            "category":"Building & Trades",
            "subcategory":"Equipment Rental",
            "type":"Services"
        }
    ],
    "sg:phone":"+1 251 649 6222",
    "sg:postcode":"36521",
    "sg:province":"AL",
    "wof:name":"Simmons Spacewalks",
    "wof:placetype":"venue"
},
  "geometry": {"coordinates":[-88.271508,30.904307],"type":"Point"}
}