{
  "type": "Feature",
  "properties": {
    "iso:country":"US",
    "sg:address":"48 Medical Park Dr E",
    "sg:city":"Birmingham",
    "sg:classifiers":[
        {
            "category":"Health Services",
            "subcategory":"Doctor",
            "type":"Services"
        }
    ],
    "sg:phone":"+1 205 838 3407",
    "sg:postcode":"35235",
    "sg:province":"AL",
    "sg:tags":[
        "dermatologist"
    ],
    "wof:name":"Robbins Courtney M MD",
    "wof:placetype":"venue"
},
  "geometry": {"coordinates":[-86.665892,33.594331],"type":"Point"}
}