{
  "type": "Feature",
  "properties": {
    "iso:country":"US",
    "sg:address":"8919 State Rte 119",
    "sg:city":"Alabaster",
    "sg:classifiers":[
        {
            "category":"Retail",
            "subcategory":"Animal Services",
            "type":"Services"
        }
    ],
    "sg:phone":"+1 205 663 2198",
    "sg:postcode":"35007",
    "sg:province":"AL",
    "sg:tags":[
        "pet",
        "grooming",
        "washing"
    ],
    "wof:name":"Ms Kristy's Pet Grooming",
    "wof:placetype":"venue"
},
  "geometry": {"coordinates":[-86.829229,33.209965],"type":"Point"}
}