{
  "type": "Feature",
  "properties": {
    "addr:full":"14733 Tom Johnson Rd Coden AL 36523",
    "addr:housenumber":"14733",
    "addr:postcode":"36523",
    "addr:street":"Tom Johnson Rd",
    "iso:country":"US",
    "sg:address":"14733 Tom Johnson Rd",
    "sg:city":"Coden",
    "sg:classifiers":[
        {
            "category":"Wholesale",
            "subcategory":"Seafood",
            "type":"Manufacturing & Wholesale Goods"
        }
    ],
    "sg:phone":"+1 251 824 4925",
    "sg:postcode":"36523",
    "sg:province":"AL",
    "wof:name":"Capt Collier Seafood",
    "wof:placetype":"venue"
},
  "geometry": {"coordinates":[-88.238505,30.383113],"type":"Point"}
}