{
  "type": "Feature",
  "properties": {
    "addr:full":"15132 US Hwy 72 Rogersville AL 35652",
    "addr:postcode":"15132;35652",
    "addr:street":"Us Hwy 72",
    "iso:country":"US",
    "sg:address":"15132 US Hwy 72",
    "sg:city":"Rogersville",
    "sg:classifiers":[
        {
            "category":"Social Services",
            "type":"Services"
        }
    ],
    "sg:phone":"+1 256 247 1222",
    "sg:postcode":"35652",
    "sg:province":"AL",
    "sg:tags":[
        "information",
        "abuse",
        "treatment",
        "center"
    ],
    "wof:name":"Substance Abuse Council",
    "wof:placetype":"venue"
},
  "geometry": {"coordinates":[-87.317925,34.83082],"type":"Point"}
}