{
  "type": "Feature",
  "properties": {
    "iso:country":"US",
    "sg:address":"616 Gay Rd",
    "sg:city":"Bessemer",
    "sg:classifiers":[
        {
            "category":"Building & Trades",
            "subcategory":"Construction",
            "type":"Services"
        }
    ],
    "sg:phone":"+1 205 497 0236",
    "sg:postcode":"35023",
    "sg:province":"AL",
    "sg:tags":[
        "hanging",
        "contractor"
    ],
    "wof:name":"Shugrue Painting Inc",
    "wof:placetype":"venue"
},
  "geometry": {"coordinates":[-87.026882,33.470269],"type":"Point"}
}