{
  "type": "Feature",
  "properties": {
    "addr:full":"1141 Huffman Rd Birmingham AL 35215",
    "addr:housenumber":"1141",
    "addr:postcode":"35215",
    "addr:street":"Huffman Rd",
    "iso:country":"US",
    "sg:address":"1141 Huffman Rd",
    "sg:city":"Birmingham",
    "sg:classifiers":[
        {
            "category":"Shopping",
            "subcategory":"Computers & Home Electronics",
            "type":"Retail Goods"
        }
    ],
    "sg:phone":"+1 205 815 5334",
    "sg:postcode":"35215",
    "sg:province":"AL",
    "sg:tags":[
        "store"
    ],
    "wof:name":"Radio Shack",
    "wof:placetype":"venue"
},
  "geometry": {"coordinates":[-86.687578,33.61269],"type":"Point"}
}