{
  "type": "Feature",
  "properties": {
    "iso:country":"US",
    "sg:address":"166 Commerce St",
    "sg:city":"Montgomery",
    "sg:classifiers":[
        {
            "category":"Professional",
            "subcategory":"Lawyer & Legal Services",
            "type":"Services"
        }
    ],
    "sg:phone":"+1 334 262 3300",
    "sg:postcode":"36104",
    "sg:province":"AL",
    "sg:tags":[
        "attorney"
    ],
    "wof:name":"Slate Kennedy Attorneys At Law",
    "wof:placetype":"venue"
},
  "geometry": {"coordinates":[-86.311173,32.379406],"type":"Point"}
}