{
  "type": "Feature",
  "properties": {
    "iso:country":"US",
    "sg:address":"3405 28th Pl N",
    "sg:city":"Birmingham",
    "sg:classifiers":[
        {
            "category":"Manufacturing",
            "subcategory":"Tools & Machinery",
            "type":"Manufacturing & Wholesale Goods"
        }
    ],
    "sg:phone":"+1 205 251 4469",
    "sg:postcode":"35207",
    "sg:province":"AL",
    "sg:tags":[
        "machine",
        "shop"
    ],
    "wof:name":"Curtis Machine Co Inc",
    "wof:placetype":"venue"
},
  "geometry": {"coordinates":[-86.81572799999999,33.557411],"type":"Point"}
}