{
  "type": "Feature",
  "properties": {
    "iso:country":"US",
    "sg:address":"710 Leighton Ave",
    "sg:city":"Anniston",
    "sg:classifiers":[
        {
            "category":"Building & Trades",
            "subcategory":"Construction",
            "type":"Services"
        },
        {
            "category":"Education",
            "subcategory":"School",
            "type":"Public Place"
        }
    ],
    "sg:phone":"+1 256 235 2836",
    "sg:postcode":"36207",
    "sg:province":"AL",
    "sg:tags":[
        "company"
    ],
    "wof:name":"E B Construction Anniston Ofc",
    "wof:placetype":"venue"
},
  "geometry": {"coordinates":[-85.825068,33.6532],"type":"Point"}
}