{
  "type": "Feature",
  "properties": {
    "addr:full":"5811 Rime Village Birmingham AL 35216",
    "addr:housenumber":"5811",
    "addr:postcode":"35216",
    "addr:street":"Rime Village",
    "iso:country":"US",
    "sg:address":"5811 Rime Village",
    "sg:city":"Birmingham",
    "sg:classifiers":[
        {
            "category":"Arts & Performance",
            "subcategory":"Theater",
            "type":"Entertainment"
        }
    ],
    "sg:phone":"+1 205 529 3086",
    "sg:postcode":"35216",
    "sg:province":"AL",
    "sg:tags":[
        "group"
    ],
    "wof:name":"Espen Entertainment",
    "wof:placetype":"venue"
},
  "geometry": {"coordinates":[-86.791456,33.380245],"type":"Point"}
}