{
  "type": "Feature",
  "properties": {
    "iso:country":"US",
    "sg:address":"300 Willow Dr",
    "sg:city":"Bessemer",
    "sg:classifiers":[
        {
            "category":"Manufacturing",
            "subcategory":"Printing",
            "type":"Manufacturing & Wholesale Goods"
        }
    ],
    "sg:phone":"+1 205 491 7863",
    "sg:postcode":"35023",
    "sg:province":"AL",
    "sg:tags":[
        "lithographic",
        "commercial"
    ],
    "wof:name":"Printers Technical Services",
    "wof:placetype":"venue"
},
  "geometry": {"coordinates":[-86.991021,33.437689],"type":"Point"}
}