{
  "type": "Feature",
  "properties": {
    "iso:country":"US",
    "sg:address":"1130 Pelham Rd S",
    "sg:city":"Jacksonville",
    "sg:classifiers":[
        {
            "category":"Restaurant",
            "type":"Food & Drink"
        }
    ],
    "sg:phone":"+1 256 782 0919",
    "sg:postcode":"36265",
    "sg:province":"AL",
    "sg:tags":[
        "drive"
    ],
    "wof:name":"Sonic Drive-In",
    "wof:placetype":"venue"
},
  "geometry": {"coordinates":[-85.761073,33.791903],"type":"Point"}
}