{
  "type": "Feature",
  "properties": {
    "iso:country":"US",
    "sg:address":"136 1st Ave NW",
    "sg:city":"Vernon",
    "sg:classifiers":[
        {
            "category":"Restaurant",
            "type":"Food & Drink"
        }
    ],
    "sg:phone":"+1 205 695 7091",
    "sg:postcode":"35555",
    "sg:province":"AL",
    "sg:tags":[
        "out"
    ],
    "wof:name":"Pizza To Go",
    "wof:placetype":"venue"
},
  "geometry": {"coordinates":[-88.110441,33.75804],"type":"Point"}
}