{
  "type": "Feature",
  "properties": {
    "iso:country":"US",
    "sg:address":"108 Bibb St",
    "sg:city":"Montgomery",
    "sg:classifiers":[
        {
            "category":"Education",
            "subcategory":"Special Training",
            "type":"Public Place"
        }
    ],
    "sg:phone":"+1 334 263 0178",
    "sg:postcode":"36104",
    "sg:province":"AL",
    "sg:tags":[
        "instruction",
        "music"
    ],
    "wof:name":"House Of The Arts Inc",
    "wof:placetype":"venue"
},
  "geometry": {"coordinates":[-86.310671,32.37906],"type":"Point"}
}