{
  "type": "Feature",
  "properties": {
    "addr:full":"1319 Eastern Blvd Montgomery AL 36117",
    "addr:housenumber":"1319",
    "addr:postcode":"36117",
    "addr:street":"Eastern Blvd",
    "iso:country":"US",
    "sg:address":"1319 Eastern Blvd",
    "sg:city":"Montgomery",
    "sg:classifiers":[
        {
            "category":"Food & Beverages",
            "subcategory":"Groceries & Convenience Stores",
            "type":"Retail Goods"
        }
    ],
    "sg:phone":"+1 334 396 4145",
    "sg:postcode":"36117",
    "sg:province":"AL",
    "wof:name":"Racetrac Petroleum Inc",
    "wof:placetype":"venue"
},
  "geometry": {"coordinates":[-86.216515,32.357479],"type":"Point"}
}