{
  "type": "Feature",
  "properties": {
    "iso:country":"US",
    "sg:address":"2524 Dauphin Island Pkwy",
    "sg:city":"Mobile",
    "sg:classifiers":[
        {
            "category":"Shopping",
            "subcategory":"Crafts & Fabrics",
            "type":"Retail Goods"
        }
    ],
    "sg:phone":"+1 251 478 5644",
    "sg:postcode":"36605",
    "sg:province":"AL",
    "sg:tags":[
        "sewing"
    ],
    "wof:name":"Lace Heaven Inc",
    "wof:placetype":"venue"
},
  "geometry": {"coordinates":[-88.078717,30.620128],"type":"Point"}
}