{
  "type": "Feature",
  "properties": {
    "addr:full":"814 E Academy St Troy AL 36081",
    "addr:housenumber":"814",
    "addr:postcode":"36081",
    "addr:street":"E Academy St",
    "iso:country":"US",
    "sg:address":"814 E Academy St",
    "sg:city":"Troy",
    "sg:classifiers":[
        {
            "category":"Professional",
            "subcategory":"Business Services",
            "type":"Services"
        }
    ],
    "sg:phone":"+1 334 566 2849",
    "sg:postcode":"36081",
    "sg:province":"AL",
    "sg:tags":[
        "recording",
        "arts"
    ],
    "wof:name":"Double A&M Recording",
    "wof:placetype":"venue"
},
  "geometry": {"coordinates":[-85.96179100000001,31.809101],"type":"Point"}
}