{
  "type": "Feature",
  "properties": {
    "iso:country":"US",
    "sg:address":"109 N 26th St",
    "sg:city":"Gadsden",
    "sg:classifiers":[
        {
            "category":"Retail",
            "subcategory":"Auto Repair",
            "type":"Services"
        }
    ],
    "sg:phone":"+1 256 547 1032",
    "sg:postcode":"35904",
    "sg:province":"AL",
    "sg:tags":[
        "automotive"
    ],
    "wof:name":"Putman Front End Service",
    "wof:placetype":"venue"
},
  "geometry": {"coordinates":[-86.04364700000001,34.019274],"type":"Point"}
}