{
  "type": "Feature",
  "properties": {
    "iso:country":"US",
    "sg:address":"1530 Tower Dr NE",
    "sg:city":"Arab",
    "sg:classifiers":[
        {
            "category":"Wholesale",
            "subcategory":"Stationery",
            "type":"Manufacturing & Wholesale Goods"
        },
        {
            "category":"Professional",
            "subcategory":"Management & Consulting",
            "type":"Services"
        }
    ],
    "sg:phone":"+1 256 586 2044",
    "sg:postcode":"35016",
    "sg:province":"AL",
    "sg:tags":[
        "packaging",
        "material"
    ],
    "wof:name":"Marketing Images Inc",
    "wof:placetype":"venue"
},
  "geometry": {"coordinates":[-86.463554,34.346213],"type":"Point"}
}