{
  "type": "Feature",
  "properties": {
    "addr:full":"1380 Geneva Hwy Enterprise AL 36330",
    "addr:housenumber":"1380",
    "addr:postcode":"36330",
    "addr:street":"Geneva Hwy Enterprise",
    "iso:country":"US",
    "sg:address":"1380 Geneva Hwy",
    "sg:city":"Enterprise",
    "sg:classifiers":[
        {
            "category":"Building & Trades",
            "subcategory":"Construction",
            "type":"Services"
        }
    ],
    "sg:phone":"+1 334 347 3021",
    "sg:postcode":"36330",
    "sg:province":"AL",
    "sg:tags":[
        "general",
        "contractor"
    ],
    "wof:name":"Trawick Construction",
    "wof:placetype":"venue"
},
  "geometry": {"coordinates":[-85.864379,31.293763],"type":"Point"}
}