{
  "type": "Feature",
  "properties": {
    "iso:country":"US",
    "sg:address":"1716 Catherine Ct",
    "sg:city":"Auburn",
    "sg:classifiers":[
        {
            "category":"Social Services",
            "type":"Services"
        }
    ],
    "sg:phone":"+1 334 502 0060",
    "sg:postcode":"36830",
    "sg:province":"AL",
    "sg:website":"www.lcydc.org",
    "wof:name":"Lee County Youth Dev Ctr",
    "wof:placetype":"venue"
},
  "geometry": {"coordinates":[-85.449292,32.613776],"type":"Point"}
}