{
  "type": "Feature",
  "properties": {
    "addr:full":"1500 Old Hwy 78 E Jasper AL 35501",
    "addr:housenumber":"1500",
    "addr:postcode":"35501",
    "addr:street":"Old Hwy 78 E",
    "iso:country":"US",
    "sg:address":"1500 Old Hwy 78 E",
    "sg:city":"Jasper",
    "sg:classifiers":[
        {
            "category":"Autos & Motor Vehicles",
            "subcategory":"Automobile Sales",
            "type":"Retail Goods"
        }
    ],
    "sg:phone":"+1 205 221 6280",
    "sg:postcode":"35501",
    "sg:province":"AL",
    "sg:tags":[
        "car",
        "used",
        "truck",
        "dealer",
        "new"
    ],
    "wof:name":"Jasper Honda Chrysler Dodge",
    "wof:placetype":"venue"
},
  "geometry": {"coordinates":[-87.567976,33.90377],"type":"Point"}
}