{
  "type": "Feature",
  "properties": {
    "iso:country":"US",
    "sg:address":"449 Caroline St",
    "sg:city":"Montgomery",
    "sg:classifiers":[
        {
            "category":"Retail",
            "subcategory":"Car Wash",
            "type":"Services"
        }
    ],
    "sg:phone":"+1 334 265 2930",
    "sg:postcode":"36104",
    "sg:province":"AL",
    "sg:tags":[
        "automobile",
        "detail",
        "clean"
    ],
    "wof:name":"John's Detail",
    "wof:placetype":"venue"
},
  "geometry": {"coordinates":[-86.31344,32.371402],"type":"Point"}
}