{
  "type": "Feature",
  "properties": {
    "iso:country":"US",
    "sg:address":"772 Gantts Ln",
    "sg:city":"Sylacauga",
    "sg:classifiers":[
        {
            "category":"Wholesale",
            "subcategory":"Construction Materials",
            "type":"Manufacturing & Wholesale Goods"
        }
    ],
    "sg:phone":"+1 256 245 6408",
    "sg:postcode":"35150",
    "sg:province":"AL",
    "wof:name":"Martin Marietta Aggregates",
    "wof:placetype":"venue"
},
  "geometry": {"coordinates":[-86.29062500000001,33.144784],"type":"Point"}
}