{
  "type": "Feature",
  "properties": {
    "addr:full":"416 Cahaba Park Cir Birmingham AL 35242",
    "addr:housenumber":"416",
    "addr:postcode":"35242",
    "addr:street":"Cahaba Park Cir",
    "iso:country":"US",
    "sg:address":"416 Cahaba Park Cir",
    "sg:city":"Birmingham",
    "sg:classifiers":[
        {
            "category":"Manufacturing",
            "subcategory":"Printing",
            "type":"Manufacturing & Wholesale Goods"
        }
    ],
    "sg:phone":"+1 205 991 8288",
    "sg:postcode":"35242",
    "sg:province":"AL",
    "sg:tags":[
        "lithographic",
        "commercial",
        "photocopying"
    ],
    "wof:name":"Pete Petroff & Associates Inc",
    "wof:placetype":"venue"
},
  "geometry": {"coordinates":[-86.707004,33.428389],"type":"Point"}
}