{
  "type": "Feature",
  "properties": {
    "iso:country":"US",
    "sg:address":"4004 Mc Ewen Dr NW",
    "sg:city":"Huntsville",
    "sg:classifiers":[
        {
            "category":"Personal",
            "type":"Services"
        }
    ],
    "sg:phone":"+1 256 859 6650",
    "sg:postcode":"35810",
    "sg:province":"AL",
    "wof:name":"Any Time Sitter Service",
    "wof:placetype":"venue"
},
  "geometry": {"coordinates":[-86.625836,34.76294],"type":"Point"}
}