{
  "type": "Feature",
  "properties": {
    "addr:full":"6417 Hillcrest Park Ct Mobile AL 36695",
    "addr:housenumber":"6417",
    "addr:postcode":"36695",
    "addr:street":"Hillcrest Park Ct",
    "iso:country":"US",
    "sg:address":"6417 Hillcrest Park Ct",
    "sg:city":"Mobile",
    "sg:classifiers":[
        {
            "category":"Professional",
            "subcategory":"Employment Agencies",
            "type":"Services"
        }
    ],
    "sg:phone":"+1 251 634 1129",
    "sg:postcode":"36695",
    "sg:province":"AL",
    "sg:tags":[
        "help",
        "supply"
    ],
    "wof:name":"Manpower",
    "wof:placetype":"venue"
},
  "geometry": {"coordinates":[-88.191001,30.66217],"type":"Point"}
}