{
  "type": "Feature",
  "properties": {
    "iso:country":"US",
    "sg:address":"975 Sharon Blvd",
    "sg:city":"Dora",
    "sg:classifiers":[
        {
            "category":"Government",
            "subcategory":"Post Office",
            "type":"Public Place"
        }
    ],
    "sg:phone":"+1 205 648 6650",
    "sg:postcode":"35062",
    "sg:province":"AL",
    "sg:website":"www.usps.gov",
    "wof:name":"US Post Office",
    "wof:placetype":"venue"
},
  "geometry": {"coordinates":[-87.07323700000001,33.746121],"type":"Point"}
}