{
  "type": "Feature",
  "properties": {
    "iso:country":"US",
    "sg:address":"3653 S Chelsea Dr",
    "sg:city":"Mobile",
    "sg:classifiers":[
        {
            "category":"Food & Beverages",
            "subcategory":"Fruits & Vegetables",
            "type":"Retail Goods"
        }
    ],
    "sg:phone":"+1 251 342 4079",
    "sg:postcode":"36608",
    "sg:province":"AL",
    "wof:name":"Superior Produce Co Inc",
    "wof:placetype":"venue"
},
  "geometry": {"coordinates":[-88.138454,30.707336],"type":"Point"}
}