{
  "type": "Feature",
  "properties": {
    "iso:country":"US",
    "sg:address":"428 Madison St",
    "sg:city":"Alexander City",
    "sg:classifiers":[
        {
            "category":"Banks & Credit Unions",
            "subcategory":"Bank",
            "type":"Services"
        }
    ],
    "sg:phone":"+1 256 329 7459",
    "sg:postcode":"35010",
    "sg:province":"AL",
    "wof:name":"Aliant Bank",
    "wof:placetype":"venue"
},
  "geometry": {"coordinates":[-85.952853,32.939878],"type":"Point"}
}