{
  "type": "Feature",
  "properties": {
    "addr:full":"117 North St E Talladega AL 35160",
    "addr:housenumber":"117",
    "addr:postcode":"35160",
    "addr:street":"North St;Talladega",
    "iso:country":"US",
    "sg:address":"117 North St E",
    "sg:city":"Talladega",
    "sg:classifiers":[
        {
            "category":"Professional",
            "subcategory":"Lawyer & Legal Services",
            "type":"Services"
        }
    ],
    "sg:phone":"+1 256 362 6670",
    "sg:postcode":"35160",
    "sg:province":"AL",
    "sg:tags":[
        "attorney"
    ],
    "wof:name":"Love Love & Love",
    "wof:placetype":"venue"
},
  "geometry": {"coordinates":[-86.101373,33.435736],"type":"Point"}
}