{
  "type": "Feature",
  "properties": {
    "addr:full":"3465 Co Rd 34 Hartford AL 36344",
    "addr:housenumber":"3465;34",
    "addr:postcode":"36344",
    "addr:street":"Co Rd",
    "iso:country":"US",
    "sg:address":"3465 Co Rd 34",
    "sg:city":"Hartford",
    "sg:phone":"+1 334 588 3954",
    "sg:postcode":"36344",
    "sg:province":"AL",
    "sg:tags":[
        "farm",
        "field",
        "crop"
    ],
    "wof:name":"Kenneth Sallas",
    "wof:placetype":"venue"
},
  "geometry": {"coordinates":[-85.781824,31.105827],"type":"Point"}
}