{
  "type": "Feature",
  "properties": {
    "iso:country":"US",
    "sg:address":"46 E Patton Ave",
    "sg:city":"Montgomery",
    "sg:classifiers":[
        {
            "category":"Professional",
            "subcategory":"Management & Consulting",
            "type":"Services"
        }
    ],
    "sg:phone":"+1 334 288 5754",
    "sg:postcode":"36105",
    "sg:province":"AL",
    "sg:tags":[
        "consultant"
    ],
    "wof:name":"Gmp Consultants",
    "wof:placetype":"venue"
},
  "geometry": {"coordinates":[-86.306428,32.334049],"type":"Point"}
}