{
  "type": "Feature",
  "properties": {
    "iso:country":"US",
    "sg:address":"513 Henson St",
    "sg:city":"Birmingham",
    "sg:classifiers":[
        {
            "category":"Building & Trades",
            "subcategory":"Construction",
            "type":"Services"
        }
    ],
    "sg:phone":"+1 205 923 1046",
    "sg:postcode":"35228",
    "sg:province":"AL",
    "sg:tags":[
        "house"
    ],
    "wof:name":"Wj Construction",
    "wof:placetype":"venue"
},
  "geometry": {"coordinates":[-86.90513,33.461669],"type":"Point"}
}