{
  "type": "Feature",
  "properties": {
    "iso:country":"US",
    "sg:address":"2700 19th St N",
    "sg:city":"Bessemer",
    "sg:classifiers":[
        {
            "category":"Building & Trades",
            "subcategory":"Construction",
            "type":"Services"
        }
    ],
    "sg:phone":"+1 205 491 6321",
    "sg:postcode":"35023",
    "sg:province":"AL",
    "sg:tags":[
        "bathroom",
        "remodeling",
        "kitchen"
    ],
    "wof:name":"Odoms Cabinets and Tops Inc",
    "wof:placetype":"venue"
},
  "geometry": {"coordinates":[-86.984785,33.421388],"type":"Point"}
}