{
  "type": "Feature",
  "properties": {
    "addr:full":"5161 Atlanta Hwy Montgomery AL 36109",
    "addr:housenumber":"5161",
    "addr:postcode":"36109",
    "addr:street":"Atlanta Hwy",
    "iso:country":"US",
    "sg:address":"5161 Atlanta Hwy",
    "sg:city":"Montgomery",
    "sg:classifiers":[
        {
            "category":"Personal",
            "type":"Services"
        }
    ],
    "sg:phone":"+1 334 277 9727",
    "sg:postcode":"36109",
    "sg:province":"AL",
    "wof:name":"Tropic Tan LLC",
    "wof:placetype":"venue"
},
  "geometry": {"coordinates":[-86.223956,32.381729],"type":"Point"}
}