{
  "type": "Feature",
  "properties": {
    "iso:country":"US",
    "sg:address":"25 Eufaula Ave",
    "sg:city":"Clayton",
    "sg:classifiers":[
        {
            "category":"Wholesale",
            "subcategory":"Farm Supplies",
            "type":"Manufacturing & Wholesale Goods"
        }
    ],
    "sg:phone":"+1 334 775 3491",
    "sg:postcode":"36016",
    "sg:province":"AL",
    "sg:tags":[
        "feed"
    ],
    "wof:name":"Home & Farm Supply Co",
    "wof:placetype":"venue"
},
  "geometry": {"coordinates":[-85.448251,31.878068],"type":"Point"}
}