{
  "type": "Feature",
  "properties": {
    "iso:country":"US",
    "sg:address":"73 Market Pl",
    "sg:city":"Montgomery",
    "sg:classifiers":[
        {
            "category":"Personal",
            "subcategory":"Beauty Salon",
            "type":"Services"
        }
    ],
    "sg:phone":"+1 334 244 2026",
    "sg:postcode":"36117",
    "sg:province":"AL",
    "sg:tags":[
        "shop"
    ],
    "wof:name":"Tammy Cox",
    "wof:placetype":"venue"
},
  "geometry": {"coordinates":[-86.188278,32.380376],"type":"Point"}
}