{
  "type": "Feature",
  "properties": {
    "iso:country":"US",
    "sg:address":"30388 Ardmore Ave",
    "sg:city":"Ardmore",
    "sg:classifiers":[
        {
            "category":"Shopping",
            "subcategory":"Used Merchandise",
            "type":"Retail Goods"
        }
    ],
    "sg:phone":"+1 256 423 3619",
    "sg:postcode":"35739",
    "sg:province":"AL",
    "sg:tags":[
        "shop",
        "consignment"
    ],
    "wof:name":"Eva's Treasure Chest",
    "wof:placetype":"venue"
},
  "geometry": {"coordinates":[-86.846481,34.989752],"type":"Point"}
}