{
  "type": "Feature",
  "properties": {
    "addr:full":"505 S Decatur St Montgomery AL 36104",
    "addr:housenumber":"505",
    "addr:postcode":"36104",
    "addr:street":"S Decatur St",
    "iso:country":"US",
    "sg:address":"505 S Decatur St",
    "sg:city":"Montgomery",
    "sg:classifiers":[
        {
            "category":"Retail",
            "subcategory":"Laundry & Dry Cleaning",
            "type":"Services"
        }
    ],
    "sg:phone":"+1 334 262 5286",
    "sg:postcode":"36104",
    "sg:province":"AL",
    "sg:tags":[
        "cleaners"
    ],
    "wof:name":"Capital City Laundry-Cleaners",
    "wof:placetype":"venue"
},
  "geometry": {"coordinates":[-86.3021,32.370271],"type":"Point"}
}