{
  "type": "Feature",
  "properties": {
    "iso:country":"US",
    "sg:address":"1285 Co Rd 1583",
    "sg:city":"Cullman",
    "sg:classifiers":[
        {
            "category":"Building & Trades",
            "subcategory":"Construction",
            "type":"Services"
        }
    ],
    "sg:phone":"+1 256 796 7622",
    "sg:postcode":"35058",
    "sg:province":"AL",
    "sg:tags":[
        "excavating",
        "contractor"
    ],
    "wof:name":"C & M Dirt Works",
    "wof:placetype":"venue"
},
  "geometry": {"coordinates":[-86.66816799999999,34.250915],"type":"Point"}
}