{
  "type": "Feature",
  "properties": {
    "iso:country":"US",
    "sg:address":"1325 Noble St",
    "sg:city":"Anniston",
    "sg:classifiers":[
        {
            "category":"Professional",
            "subcategory":"Business Services",
            "type":"Services"
        }
    ],
    "sg:phone":"+1 256 238 9299",
    "sg:postcode":"36201",
    "sg:province":"AL",
    "wof:name":"Bond James Bond Inc",
    "wof:placetype":"venue"
},
  "geometry": {"coordinates":[-85.829714,33.661172],"type":"Point"}
}