{
  "type": "Feature",
  "properties": {
    "iso:country":"US",
    "sg:address":"603 S Jefferson St",
    "sg:city":"Athens",
    "sg:classifiers":[
        {
            "category":"Food & Beverages",
            "subcategory":"Groceries & Convenience Stores",
            "type":"Retail Goods"
        }
    ],
    "sg:phone":"+1 256 232 4622",
    "sg:postcode":"35611",
    "sg:province":"AL",
    "sg:tags":[
        "grocer"
    ],
    "sg:website":"www.kroger.com",
    "wof:name":"Kroger",
    "wof:placetype":"venue"
},
  "geometry": {"coordinates":[-86.972362,34.79866],"type":"Point"}
}