{
  "type": "Feature",
  "properties": {
    "addr:full":"6517 Co Rd 39 Silas AL 36919",
    "addr:housenumber":"6517;39",
    "addr:postcode":"36919",
    "addr:street":"Co Rd",
    "iso:country":"US",
    "sg:address":"6517 Co Rd 39",
    "sg:city":"Silas",
    "sg:classifiers":[
        {
            "category":"Farming",
            "subcategory":"Livestock Farm",
            "type":"Manufacturing & Wholesale Goods"
        }
    ],
    "sg:phone":"+1 251 542 9567",
    "sg:postcode":"36919",
    "sg:province":"AL",
    "sg:tags":[
        "beef",
        "feedlot",
        "cattle"
    ],
    "wof:name":"Louis Dyess",
    "wof:placetype":"venue"
},
  "geometry": {"coordinates":[-88.453658,31.814875],"type":"Point"}
}