{
  "type": "Feature",
  "properties": {
    "iso:country":"US",
    "sg:address":"7047 Old Madison Pike NW",
    "sg:city":"Huntsville",
    "sg:classifiers":[
        {
            "category":"Manufacturing",
            "subcategory":"Aerospace",
            "type":"Manufacturing & Wholesale Goods"
        }
    ],
    "sg:phone":"+1 256 837 8040",
    "sg:postcode":"35806",
    "sg:province":"AL",
    "sg:tags":[
        "airplane",
        "fastener"
    ],
    "wof:name":"Aerospace Products SE Inc",
    "wof:placetype":"venue"
},
  "geometry": {"coordinates":[-86.683188,34.713249],"type":"Point"}
}