{
  "type": "Feature",
  "properties": {
    "iso:country":"US",
    "sg:address":"3055 Lorna Rd",
    "sg:city":"Birmingham",
    "sg:classifiers":[
        {
            "category":"Professional",
            "subcategory":"Computer Services",
            "type":"Services"
        }
    ],
    "sg:phone":"+1 205 822 7353",
    "sg:postcode":"35216",
    "sg:province":"AL",
    "sg:tags":[
        "internet"
    ],
    "wof:name":"Collegiate Internet Co",
    "wof:placetype":"venue"
},
  "geometry": {"coordinates":[-86.804957,33.406309],"type":"Point"}
}