{
  "type": "Feature",
  "properties": {
    "addr:full":"7500 Memorial Pkwy SW Huntsville AL 35802",
    "addr:housenumber":"7500",
    "addr:postcode":"35802",
    "addr:street":"Memorial Pkwy Sw",
    "iso:country":"US",
    "sg:address":"7500 Memorial Pkwy SW",
    "sg:city":"Huntsville",
    "sg:classifiers":[
        {
            "category":"Personal",
            "subcategory":"Tanning Parlor",
            "type":"Services"
        },
        {
            "category":"Health Services",
            "subcategory":"Health Practitioner",
            "type":"Services"
        }
    ],
    "sg:phone":"+1 256 883 9200",
    "sg:postcode":"35802",
    "sg:province":"AL",
    "sg:tags":[
        "salon"
    ],
    "wof:name":"A Main Street/Pure Tan Salon",
    "wof:placetype":"venue"
},
  "geometry": {"coordinates":[-86.57364800000001,34.669683],"type":"Point"}
}