{
  "type": "Feature",
  "properties": {
    "iso:country":"US",
    "sg:address":"971 Hadwen St",
    "sg:city":"Gadsden",
    "sg:classifiers":[
        {
            "category":"Building & Trades",
            "subcategory":"Landscaping Services",
            "type":"Services"
        }
    ],
    "sg:phone":"+1 256 547 6546",
    "sg:postcode":"35901",
    "sg:province":"AL",
    "wof:name":"L/B Landscape/Lawn Care",
    "wof:placetype":"venue"
},
  "geometry": {"coordinates":[-85.964212,34.033026],"type":"Point"}
}