{
  "type": "Feature",
  "properties": {
    "addr:full":"1909 Montgomery Hwy Kinsey AL 36303",
    "addr:housenumber":"1909",
    "addr:postcode":"36303",
    "addr:street":"Montgomery Hwy Kinsey",
    "iso:country":"US",
    "sg:address":"1909 Montgomery Hwy",
    "sg:city":"Kinsey",
    "sg:classifiers":[
        {
            "category":"Banks & Credit Unions",
            "subcategory":"Bank",
            "type":"Services"
        }
    ],
    "sg:phone":"+1 334 699 5737",
    "sg:postcode":"36303",
    "sg:province":"AL",
    "sg:tags":[
        "loan",
        "real estate"
    ],
    "wof:name":"Coast 2 Coast Lending",
    "wof:placetype":"venue"
},
  "geometry": {"coordinates":[-85.411918,31.23973],"type":"Point"}
}