{
  "type": "Feature",
  "properties": {
    "iso:country":"US",
    "sg:address":"11594 Memorial Pkwy SW",
    "sg:city":"Huntsville",
    "sg:classifiers":[
        {
            "category":"Restaurant",
            "type":"Food & Drink"
        }
    ],
    "sg:menulink":"http://www.allmenus.com/al/huntsville/103444-ruby-tuesdays/menu/",
    "sg:phone":"+1 256 883 3105",
    "sg:postcode":"35803",
    "sg:province":"AL",
    "sg:tags":[
        "burger",
        "american"
    ],
    "wof:name":"Ruby Tuesdays",
    "wof:placetype":"venue"
},
  "geometry": {"coordinates":[-86.567269,34.618192],"type":"Point"}
}