{
  "type": "Feature",
  "properties": {
    "iso:country":"US",
    "sg:address":"429 Hagwood Cir",
    "sg:city":"Trafford",
    "sg:classifiers":[
        {
            "category":"Building & Trades",
            "subcategory":"Construction",
            "type":"Services"
        }
    ],
    "sg:phone":"+1 205 681 0710",
    "sg:postcode":"35172",
    "sg:province":"AL",
    "sg:tags":[
        "contractor"
    ],
    "wof:name":"Hill Drywall Co",
    "wof:placetype":"venue"
},
  "geometry": {"coordinates":[-86.662515,33.832339],"type":"Point"}
}