{
  "type": "Feature",
  "properties": {
    "iso:country":"US",
    "sg:address":"60 S Mountain Dr",
    "sg:city":"Decatur",
    "sg:classifiers":[
        {
            "category":"Organizations",
            "subcategory":"Religious Organization",
            "type":"Services"
        }
    ],
    "sg:phone":"+1 256 355 3004",
    "sg:postcode":"35603",
    "sg:province":"AL",
    "sg:website":"www.elhm.org",
    "wof:name":"Edwin L Hodges Ministries",
    "wof:placetype":"venue"
},
  "geometry": {"coordinates":[-87.087655,34.572344],"type":"Point"}
}