{
  "type": "Feature",
  "properties": {
    "addr:full":"1225 Florence Blvd Florence AL 35634",
    "addr:housenumber":"1225",
    "addr:postcode":"35634",
    "addr:street":"Florence Blvd",
    "iso:country":"US",
    "sg:address":"1225 Florence Blvd",
    "sg:city":"Florence",
    "sg:classifiers":[
        {
            "category":"Real Estate",
            "subcategory":"Real Estate Services",
            "type":"Services"
        }
    ],
    "sg:phone":"+1 256 764 9093",
    "sg:postcode":"35634",
    "sg:province":"AL",
    "sg:tags":[
        "company",
        "title"
    ],
    "wof:name":"Titlemax Of Florence",
    "wof:placetype":"venue"
},
  "geometry": {"coordinates":[-87.66397600000001,34.815135],"type":"Point"}
}