{
  "type": "Feature",
  "properties": {
    "iso:country":"US",
    "sg:address":"5940 Co Rd 818",
    "sg:city":"Logan",
    "sg:classifiers":[
        {
            "category":"Farming",
            "subcategory":"Livestock Farm",
            "type":"Manufacturing & Wholesale Goods"
        }
    ],
    "sg:phone":"+1 256 747 6542",
    "sg:postcode":"35098",
    "sg:province":"AL",
    "sg:tags":[
        "beef",
        "feedlot",
        "cattle"
    ],
    "wof:name":"Jerry Quattlebaum",
    "wof:placetype":"venue"
},
  "geometry": {"coordinates":[-87.029803,34.130046],"type":"Point"}
}