{
  "type": "Feature",
  "properties": {
    "iso:country":"US",
    "sg:address":"3115 E Riviere du Chien Loop",
    "sg:city":"Mobile",
    "sg:classifiers":[
        {
            "category":"Real Estate",
            "subcategory":"Architect",
            "type":"Services"
        }
    ],
    "sg:phone":"+1 251 661 5570",
    "sg:postcode":"36693",
    "sg:province":"AL",
    "wof:name":"Slater & Slater Architects",
    "wof:placetype":"venue"
},
  "geometry": {"coordinates":[-88.11685,30.609137],"type":"Point"}
}