{
  "type": "Feature",
  "properties": {
    "iso:country":"US",
    "sg:address":"1101 Rayfield Dr",
    "sg:city":"Birmingham",
    "sg:classifiers":[
        {
            "category":"Arts & Performance",
            "subcategory":"Theater",
            "type":"Entertainment"
        }
    ],
    "sg:phone":"+1 205 925 5997",
    "sg:postcode":"35228",
    "sg:province":"AL",
    "sg:tags":[
        "group"
    ],
    "wof:name":"Curtis Bell",
    "wof:placetype":"venue"
},
  "geometry": {"coordinates":[-86.89867,33.464048],"type":"Point"}
}