{
  "type": "Feature",
  "properties": {
    "iso:country":"US",
    "sg:address":"337 Valley Ave",
    "sg:city":"Birmingham",
    "sg:classifiers":[
        {
            "category":"Bars & Pubs",
            "type":"Food & Drink"
        }
    ],
    "sg:menulink":"http://www.allmenus.com/al/birmingham/54109-full-moon-bar-b-que/menu/",
    "sg:phone":"+1 205 945 9997",
    "sg:postcode":"35209",
    "sg:province":"AL",
    "sg:tags":[
        "barbecue",
        "american"
    ],
    "wof:name":"Full Moon Bar B Que",
    "wof:placetype":"venue"
},
  "geometry": {"coordinates":[-86.82210600000001,33.471873],"type":"Point"}
}