{
  "type": "Feature",
  "properties": {
    "addr:full":"19125 S 3rd St Citronelle AL 36522",
    "addr:housenumber":"19125",
    "addr:postcode":"36522",
    "addr:street":"S 3Rd St",
    "iso:country":"US",
    "sg:address":"19125 S 3rd St",
    "sg:city":"Citronelle",
    "sg:classifiers":[
        {
            "category":"Food & Beverages",
            "subcategory":"Groceries & Convenience Stores",
            "type":"Retail Goods"
        }
    ],
    "sg:phone":"+1 251 866 3727",
    "sg:postcode":"36522",
    "sg:province":"AL",
    "wof:name":"Discount Mart",
    "wof:placetype":"venue"
},
  "geometry": {"coordinates":[-88.23818199999999,31.088145],"type":"Point"}
}