{
  "type": "Feature",
  "properties": {
    "iso:country":"US",
    "sg:address":"831 Blackburn Dr",
    "sg:city":"Mobile",
    "sg:classifiers":[
        {
            "category":"Autos & Motor Vehicles",
            "subcategory":"Automobile Sales",
            "type":"Retail Goods"
        }
    ],
    "sg:phone":"+1 251 666 1216",
    "sg:postcode":"36608",
    "sg:province":"AL",
    "sg:tags":[
        "used"
    ],
    "wof:name":"Frank Clements Clean Cars",
    "wof:placetype":"venue"
},
  "geometry": {"coordinates":[-88.260767,30.672637],"type":"Point"}
}