{
  "type": "Feature",
  "properties": {
    "iso:country":"US",
    "sg:address":"26 Sweetheart Ln",
    "sg:city":"Oxford",
    "sg:classifiers":[
        {
            "category":"Retail",
            "subcategory":"Car Wash",
            "type":"Services"
        }
    ],
    "sg:phone":"+1 256 835 0023",
    "sg:postcode":"36203",
    "sg:province":"AL",
    "sg:tags":[
        "automotive",
        "detailing"
    ],
    "wof:name":"Ultimate Detail",
    "wof:placetype":"venue"
},
  "geometry": {"coordinates":[-85.870581,33.589651],"type":"Point"}
}