{
  "type": "Feature",
  "properties": {
    "iso:country":"US",
    "sg:address":"8275 State Rte 59",
    "sg:city":"Foley",
    "sg:classifiers":[
        {
            "category":"Personal",
            "subcategory":"Beauty Salon",
            "type":"Services"
        }
    ],
    "sg:phone":"+1 251 943 8345",
    "sg:postcode":"36535",
    "sg:province":"AL",
    "wof:name":"Custom Touch Salon",
    "wof:placetype":"venue"
},
  "geometry": {"coordinates":[-87.682979,30.348519],"type":"Point"}
}