{
  "type": "Feature",
  "properties": {
    "addr:full":"12447 Co Rd 33 Lexington AL 35648",
    "addr:housenumber":"12447;33",
    "addr:postcode":"35648",
    "addr:street":"Co Rd",
    "iso:country":"US",
    "sg:address":"12447 Co Rd 33",
    "sg:city":"Lexington",
    "sg:classifiers":[
        {
            "category":"Building & Trades",
            "subcategory":"Construction",
            "type":"Services"
        }
    ],
    "sg:phone":"+1 256 757 8966",
    "sg:postcode":"35648",
    "sg:province":"AL",
    "sg:tags":[
        "contractor"
    ],
    "wof:name":"Hatcher Insulation",
    "wof:placetype":"venue"
},
  "geometry": {"coordinates":[-87.443208,34.951222],"type":"Point"}
}