{
  "type": "Feature",
  "properties": {
    "iso:country":"US",
    "sg:address":"5901 Atlanta Hwy",
    "sg:city":"Montgomery",
    "sg:classifiers":[
        {
            "category":"Shopping",
            "subcategory":"Hobbies, Toys, & Games",
            "type":"Retail Goods"
        }
    ],
    "sg:phone":"+1 334 215 1842",
    "sg:postcode":"36117",
    "sg:province":"AL",
    "sg:tags":[
        "craft",
        "supply"
    ],
    "sg:website":"www.hobbylobby.com",
    "wof:name":"Hobby Lobby Creative Ctr",
    "wof:placetype":"venue"
},
  "geometry": {"coordinates":[-86.197028,32.382251],"type":"Point"}
}