{
  "type": "Feature",
  "properties": {
    "iso:country":"US",
    "sg:address":"7320 1st Ave N",
    "sg:city":"Birmingham",
    "sg:classifiers":[
        {
            "category":"Shopping",
            "type":"Retail Goods"
        }
    ],
    "sg:phone":"+1 205 833 1323",
    "sg:postcode":"35206",
    "sg:province":"AL",
    "sg:tags":[
        "cosmetic",
        "perfume"
    ],
    "wof:name":"Hair Express",
    "wof:placetype":"venue"
},
  "geometry": {"coordinates":[-86.732207,33.557901],"type":"Point"}
}