{
  "type": "Feature",
  "properties": {
    "addr:full":"324 Church St Mobile AL 36610",
    "addr:housenumber":"324",
    "addr:postcode":"36610",
    "addr:street":"Church St",
    "iso:country":"US",
    "sg:address":"324 Church St",
    "sg:city":"Mobile",
    "sg:classifiers":[
        {
            "category":"Organizations",
            "subcategory":"Religious Organization",
            "type":"Services"
        }
    ],
    "sg:phone":"+1 251 330 0251",
    "sg:postcode":"36610",
    "sg:province":"AL",
    "wof:name":"New Christian Sprng Missionary",
    "wof:placetype":"venue"
},
  "geometry": {"coordinates":[-88.085949,30.734516],"type":"Point"}
}