{
  "type": "Feature",
  "properties": {
    "iso:country":"US",
    "sg:address":"117 Crabapple Ln",
    "sg:city":"Birmingham",
    "sg:classifiers":[
        {
            "category":"Professional",
            "subcategory":"Business Services",
            "type":"Services"
        }
    ],
    "sg:phone":"+1 205 271 0375",
    "sg:postcode":"35214",
    "sg:province":"AL",
    "wof:name":"Mid South Safety Services",
    "wof:placetype":"venue"
},
  "geometry": {"coordinates":[-86.891789,33.556836],"type":"Point"}
}