{
  "type": "Feature",
  "properties": {
    "addr:full":"1803 26 Ave Phenix City AL 36867",
    "addr:housenumber":"1803",
    "addr:postcode":"36867",
    "addr:street":"26 Ave Phenix City Al",
    "iso:country":"US",
    "sg:address":"1803 26 Ave",
    "sg:city":"Phenix City",
    "sg:classifiers":[
        {
            "category":"Real Estate",
            "subcategory":"Real Estate Agent",
            "type":"Services"
        }
    ],
    "sg:phone":"+1 334 732 1500",
    "sg:postcode":"36867",
    "sg:province":"AL",
    "wof:name":"ABC Realty Svc Inc",
    "wof:placetype":"venue"
},
  "geometry": {"coordinates":[-85.02944599999999,32.477677],"type":"Point"}
}