{
  "type": "Feature",
  "properties": {
    "iso:country":"US",
    "sg:address":"1228 Josephine St",
    "sg:city":"Prattville",
    "sg:classifiers":[
        {
            "category":"Health Services",
            "subcategory":"Health Practitioner",
            "type":"Services"
        }
    ],
    "sg:phone":"+1 334 358 3990",
    "sg:postcode":"36066",
    "sg:province":"AL",
    "wof:name":"Reflexology By Paula",
    "wof:placetype":"venue"
},
  "geometry": {"coordinates":[-86.442345,32.458523],"type":"Point"}
}