{
  "type": "Feature",
  "properties": {
    "iso:country":"US",
    "sg:address":"2117 Oakwood Ave NW",
    "sg:city":"Huntsville",
    "sg:classifiers":[
        {
            "category":"Organizations",
            "subcategory":"Religious Organization",
            "type":"Services"
        }
    ],
    "sg:phone":"+1 256 536 4673",
    "sg:postcode":"35810",
    "sg:province":"AL",
    "sg:tags":[
        "church"
    ],
    "wof:name":"Fellowship Of Faith Bapt Chr",
    "wof:placetype":"venue"
},
  "geometry": {"coordinates":[-86.60109300000001,34.749322],"type":"Point"}
}