{
  "type": "Feature",
  "properties": {
    "addr:full":"1034 Overhill Dr Alexander City AL 35010",
    "addr:housenumber":"1034",
    "addr:postcode":"35010",
    "addr:street":"Overhill Dr",
    "iso:country":"US",
    "sg:address":"1034 Overhill Dr",
    "sg:city":"Alexander City",
    "sg:classifiers":[
        {
            "category":"Retail",
            "subcategory":"Auto Repair",
            "type":"Services"
        }
    ],
    "sg:phone":"+1 256 234 6304",
    "sg:postcode":"35010",
    "sg:province":"AL",
    "sg:tags":[
        "general"
    ],
    "wof:name":"Dark Garage",
    "wof:placetype":"venue"
},
  "geometry": {"coordinates":[-85.977532,32.932417],"type":"Point"}
}