{
  "type": "Feature",
  "properties": {
    "addr:full":"4000 Bessemer Ave SW Birmingham AL 35221",
    "addr:housenumber":"4000",
    "addr:postcode":"35221",
    "addr:street":"Bessemer Ave Sw",
    "iso:country":"US",
    "sg:address":"4000 Bessemer Ave SW",
    "sg:city":"Birmingham",
    "sg:classifiers":[
        {
            "category":"Food & Beverages",
            "subcategory":"Bakery",
            "type":"Retail Goods"
        }
    ],
    "sg:phone":"+1 205 426 6486",
    "sg:postcode":"35221",
    "sg:province":"AL",
    "sg:tags":[
        "store",
        "thrift"
    ],
    "wof:name":"Dolly Madison",
    "wof:placetype":"venue"
},
  "geometry": {"coordinates":[-86.900414,33.453368],"type":"Point"}
}