{
  "type": "Feature",
  "properties": {
    "iso:country":"US",
    "sg:address":"103 Rainbow Industrial Blvd",
    "sg:city":"Rainbow City",
    "sg:classifiers":[
        {
            "category":"Manufacturing",
            "subcategory":"Motor Vehicles & Parts",
            "type":"Manufacturing & Wholesale Goods"
        }
    ],
    "sg:phone":"+1 256 442 6773",
    "sg:postcode":"35906",
    "sg:province":"AL",
    "sg:tags":[
        "cylinder",
        "head"
    ],
    "wof:name":"Alabama Cylinder Head Exchange",
    "wof:placetype":"venue"
},
  "geometry": {"coordinates":[-86.056343,33.979062],"type":"Point"}
}