{
  "type": "Feature",
  "properties": {
    "iso:country":"US",
    "sg:address":"8810 Bridlewood Dr SE",
    "sg:city":"Huntsville",
    "sg:classifiers":[
        {
            "category":"Professional",
            "type":"Services"
        }
    ],
    "sg:phone":"+1 256 881 5600",
    "sg:postcode":"35802",
    "sg:province":"AL",
    "wof:name":"Concept Exploration & Dev",
    "wof:placetype":"venue"
},
  "geometry": {"coordinates":[-86.550377,34.650573],"type":"Point"}
}