{
  "type": "Feature",
  "properties": {
    "addr:full":"2937 7th Ave S Ste 100 Birmingham AL 35233",
    "addr:housenumber":"2937",
    "addr:postcode":"35233",
    "addr:street":"7Th Ave S Ste 100",
    "iso:country":"US",
    "sg:address":"2937 7th Ave S Ste 100",
    "sg:city":"Birmingham",
    "sg:classifiers":[
        {
            "category":"Professional",
            "subcategory":"Accounting & Tax Preparation",
            "type":"Services"
        }
    ],
    "sg:phone":"+1 205 251 2441",
    "sg:postcode":"35233",
    "sg:province":"AL",
    "sg:tags":[
        "bookkeeping",
        "return",
        "preparation-business"
    ],
    "wof:name":"Sarah Mcclure Tax Consultant",
    "wof:placetype":"venue"
},
  "geometry": {"coordinates":[-86.786992,33.511973],"type":"Point"}
}