{
  "type": "Feature",
  "properties": {
    "iso:country":"US",
    "sg:address":"2320 Rock Springs Rd",
    "sg:city":"Warrior",
    "sg:classifiers":[
        {
            "category":"Building & Trades",
            "subcategory":"Construction",
            "type":"Services"
        }
    ],
    "sg:phone":"+1 205 647 5176",
    "sg:postcode":"35180",
    "sg:province":"AL",
    "sg:tags":[
        "mfg",
        "kitchen",
        "cabinet",
        "wood",
        "contractor",
        "carpentry"
    ],
    "wof:name":"Carpentry Contractor",
    "wof:placetype":"venue"
},
  "geometry": {"coordinates":[-86.804901,33.889594],"type":"Point"}
}