{
  "type": "Feature",
  "properties": {
    "iso:country":"US",
    "sg:address":"1480 Honeycutt Rd",
    "sg:city":"Remlap",
    "sg:classifiers":[
        {
            "category":"Shopping",
            "subcategory":"Florist",
            "type":"Retail Goods"
        }
    ],
    "sg:phone":"+1 205 681 9004",
    "sg:postcode":"35133",
    "sg:province":"AL",
    "wof:name":"Marys Flowers & Gifts",
    "wof:placetype":"venue"
},
  "geometry": {"coordinates":[-86.64183,33.877176],"type":"Point"}
}