{
  "type": "Feature",
  "properties": {
    "iso:country":"US",
    "sg:address":"1216 Wilmer Ave",
    "sg:city":"Anniston",
    "sg:classifiers":[
        {
            "category":"Banks & Credit Unions",
            "subcategory":"Bank",
            "type":"Services"
        }
    ],
    "sg:phone":"+1 256 236 1260",
    "sg:postcode":"36201",
    "sg:province":"AL",
    "wof:name":"First Educators Credit Union",
    "wof:placetype":"venue"
},
  "geometry": {"coordinates":[-85.828544,33.660844],"type":"Point"}
}