{
  "type": "Feature",
  "properties": {
    "addr:full":"1216 Wilmer Ave Anniston AL 36201",
    "addr:housenumber":"1216",
    "addr:postcode":"36201",
    "addr:street":"Wilmer Ave",
    "iso:country":"US",
    "sg:address":"1216 Wilmer Ave",
    "sg:city":"Anniston",
    "sg:classifiers":[
        {
            "category":"Banks & Credit Unions",
            "subcategory":"Bank",
            "type":"Services"
        }
    ],
    "sg:phone":"+1 256 236 1260",
    "sg:postcode":"36201",
    "sg:province":"AL",
    "wof:name":"First Educators Credit Union",
    "wof:placetype":"venue"
},
  "geometry": {"coordinates":[-85.82854399999999,33.660844],"type":"Point"}
}