{
  "type": "Feature",
  "properties": {
    "iso:country":"US",
    "sg:address":"1915 Goodwater Rd",
    "sg:city":"Alexander City",
    "sg:classifiers":[
        {
            "category":"Utilities",
            "subcategory":"Water",
            "type":"Services"
        }
    ],
    "sg:phone":"+1 256 839 6171",
    "sg:postcode":"35010",
    "sg:province":"AL",
    "sg:tags":[
        "company",
        "sewage"
    ],
    "wof:name":"Hackneyville Water Authority",
    "wof:placetype":"venue"
},
  "geometry": {"coordinates":[-85.969074,33.059378],"type":"Point"}
}