{
  "type": "Feature",
  "properties": {
    "iso:country":"US",
    "sg:address":"22 N Elm Ave",
    "sg:city":"Sylacauga",
    "sg:classifiers":[
        {
            "category":"Shopping",
            "subcategory":"Florist",
            "type":"Retail Goods"
        }
    ],
    "sg:phone":"+1 256 249 8100",
    "sg:postcode":"35150",
    "sg:province":"AL",
    "wof:name":"Garden Gate",
    "wof:placetype":"venue"
},
  "geometry": {"coordinates":[-86.257807,33.168911],"type":"Point"}
}