{
  "type": "Feature",
  "properties": {
    "iso:country":"US",
    "sg:address":"2376 Co Rd 711",
    "sg:city":"Enterprise",
    "sg:classifiers":[
        {
            "category":"Professional",
            "subcategory":"Business Services",
            "type":"Services"
        }
    ],
    "sg:phone":"+1 334 347 2591",
    "sg:postcode":"36330",
    "sg:province":"AL",
    "wof:name":"Progressive Services",
    "wof:placetype":"venue"
},
  "geometry": {"coordinates":[-85.859691,31.267943],"type":"Point"}
}