{
  "type": "Feature",
  "properties": {
    "addr:full":"3205 24th St Northport AL 35476",
    "addr:housenumber":"3205",
    "addr:postcode":"35476",
    "addr:street":"24Th St",
    "iso:country":"US",
    "sg:address":"3205 24th St",
    "sg:city":"Northport",
    "sg:classifiers":[
        {
            "category":"Building & Trades",
            "subcategory":"Construction",
            "type":"Services"
        }
    ],
    "sg:phone":"+1 205 339 6873",
    "sg:postcode":"35476",
    "sg:province":"AL",
    "sg:tags":[
        "hanging",
        "contractor"
    ],
    "wof:name":"Benny Sutton Paint Contractors",
    "wof:placetype":"venue"
},
  "geometry": {"coordinates":[-87.58782600000001,33.233521],"type":"Point"}
}