{
  "type": "Feature",
  "properties": {
    "addr:full":"1062 Co Rd 625 Mentone AL 35984",
    "addr:housenumber":"1062;625",
    "addr:postcode":"35984",
    "addr:street":"Co Rd",
    "iso:country":"US",
    "sg:address":"1062 Co Rd 625",
    "sg:city":"Mentone",
    "sg:classifiers":[
        {
            "category":"Professional",
            "subcategory":"Management & Consulting",
            "type":"Services"
        }
    ],
    "sg:phone":"+1 256 634 4193",
    "sg:postcode":"35984",
    "sg:province":"AL",
    "sg:tags":[
        "personal",
        "retail",
        "direct",
        "sales"
    ],
    "wof:name":"Partyponycom",
    "wof:placetype":"venue"
},
  "geometry": {"coordinates":[-85.580305,34.502502],"type":"Point"}
}