{
  "type": "Feature",
  "properties": {
    "addr:full":"224 N Washington St Livingston AL 35470",
    "addr:housenumber":"224",
    "addr:postcode":"35470",
    "addr:street":"N Washington St",
    "iso:country":"US",
    "sg:address":"224 N Washington St",
    "sg:city":"Livingston",
    "sg:classifiers":[
        {
            "category":"Retail",
            "subcategory":"Laundry & Dry Cleaning",
            "type":"Services"
        }
    ],
    "sg:phone":"+1 205 652 4200",
    "sg:postcode":"35470",
    "sg:province":"AL",
    "sg:tags":[
        "drycleaning",
        "plant"
    ],
    "wof:name":"Fashion Cleaners",
    "wof:placetype":"venue"
},
  "geometry": {"coordinates":[-88.183027,32.597372],"type":"Point"}
}