{
  "type": "Feature",
  "properties": {
    "addr:full":"1601 Magnolia Rd Lanett AL 36863",
    "addr:housenumber":"1601",
    "addr:postcode":"36863",
    "addr:street":"Magnolia Rd",
    "iso:country":"US",
    "sg:address":"1601 Magnolia Rd",
    "sg:city":"Lanett",
    "sg:classifiers":[
        {
            "category":"Organizations",
            "subcategory":"Religious Organization",
            "type":"Services"
        }
    ],
    "sg:phone":"+1 334 576 3451",
    "sg:postcode":"36863",
    "sg:province":"AL",
    "sg:tags":[
        "church"
    ],
    "wof:name":"Mt Herman Baptist Church",
    "wof:placetype":"venue"
},
  "geometry": {"coordinates":[-85.203751,32.846678],"type":"Point"}
}