{
  "type": "Feature",
  "properties": {
    "addr:full":"6215 Bon Secour Hwy Bon Secour AL 36511",
    "addr:housenumber":"6215",
    "addr:postcode":"36511",
    "addr:street":"Bon Secour Hwy Bon Secour",
    "iso:country":"US",
    "sg:address":"6215 Bon Secour Hwy",
    "sg:city":"Bon Secour",
    "sg:classifiers":[
        {
            "category":"Building & Trades",
            "subcategory":"Construction",
            "type":"Services"
        }
    ],
    "sg:phone":"+1 251 949 7821",
    "sg:postcode":"36511",
    "sg:province":"AL",
    "sg:tags":[
        "heavy"
    ],
    "wof:name":"Discount Marine Construction",
    "wof:placetype":"venue"
},
  "geometry": {"coordinates":[-87.731916,30.314417],"type":"Point"}
}