{
  "type": "Feature",
  "properties": {
    "iso:country":"US",
    "sg:address":"4575 Headland Ave",
    "sg:city":"Dothan",
    "sg:classifiers":[
        {
            "category":"Building & Trades",
            "subcategory":"Construction",
            "type":"Services"
        }
    ],
    "sg:phone":"+1 334 792 3886",
    "sg:postcode":"36303",
    "sg:province":"AL",
    "sg:tags":[
        "contractor"
    ],
    "wof:name":"Williams Masonry Inc",
    "wof:placetype":"venue"
},
  "geometry": {"coordinates":[-85.377309,31.29076],"type":"Point"}
}