{
  "type": "Feature",
  "properties": {
    "iso:country":"US",
    "sg:address":"5440 Zeigler Blvd",
    "sg:city":"Mobile",
    "sg:classifiers":[
        {
            "category":"Personal",
            "subcategory":"Barber",
            "type":"Services"
        }
    ],
    "sg:phone":"+1 251 344 5324",
    "sg:postcode":"36608",
    "sg:province":"AL",
    "sg:tags":[
        "shop"
    ],
    "wof:name":"Joes Hoof Shop",
    "wof:placetype":"venue"
},
  "geometry": {"coordinates":[-88.158762,30.709519],"type":"Point"}
}