{
  "type": "Feature",
  "properties": {
    "addr:full":"3146 Leeman Ferry Rd SW Huntsville AL 35801",
    "addr:housenumber":"3146",
    "addr:postcode":"35801",
    "addr:street":"Leeman Ferry Rd Sw",
    "iso:country":"US",
    "sg:address":"3146 Leeman Ferry Rd SW",
    "sg:city":"Huntsville",
    "sg:classifiers":[
        {
            "category":"Restaurant",
            "type":"Food & Drink"
        }
    ],
    "sg:phone":"+1 256 883 6364",
    "sg:postcode":"35801",
    "sg:province":"AL",
    "wof:name":"Mc Donald's",
    "wof:placetype":"venue"
},
  "geometry": {"coordinates":[-86.59206500000001,34.693264],"type":"Point"}
}