{
  "type": "Feature",
  "properties": {
    "iso:country":"US",
    "sg:address":"1930 Winchester Rd NE",
    "sg:city":"Huntsville",
    "sg:classifiers":[
        {
            "category":"Shopping",
            "type":"Retail Goods"
        }
    ],
    "sg:phone":"+1 256 679 7919",
    "sg:postcode":"35811",
    "sg:province":"AL",
    "sg:tags":[
        "merchandise"
    ],
    "wof:name":"Twenty First Century Fireworks",
    "wof:placetype":"venue"
},
  "geometry": {"coordinates":[-86.50225500000001,34.813517],"type":"Point"}
}