{
  "type": "Feature",
  "properties": {
    "iso:country":"US",
    "sg:address":"3607 Old Shell Rd",
    "sg:city":"Mobile",
    "sg:classifiers":[
        {
            "category":"Personal",
            "type":"Services"
        }
    ],
    "sg:phone":"+1 251 341 0927",
    "sg:postcode":"36608",
    "sg:province":"AL",
    "wof:name":"Garrett Williamson",
    "wof:placetype":"venue"
},
  "geometry": {"coordinates":[-88.124291,30.698658],"type":"Point"}
}