{
  "type": "Feature",
  "properties": {
    "iso:country":"US",
    "sg:address":"3 Moss Oak Ct",
    "sg:city":"Fairhope",
    "sg:classifiers":[
        {
            "category":"Building & Trades",
            "subcategory":"Construction",
            "type":"Services"
        }
    ],
    "sg:phone":"+1 251 990 4976",
    "sg:postcode":"36532",
    "sg:province":"AL",
    "sg:tags":[
        "house"
    ],
    "wof:name":"C&R Turner Homes Inc",
    "wof:placetype":"venue"
},
  "geometry": {"coordinates":[-87.914131,30.517455],"type":"Point"}
}