{
  "type": "Feature",
  "properties": {
    "iso:country":"US",
    "sg:address":"1256 Sangster Rd",
    "sg:city":"Gadsden",
    "sg:classifiers":[
        {
            "category":"Professional",
            "type":"Services"
        }
    ],
    "sg:phone":"+1 256 546 4963",
    "sg:postcode":"35901",
    "sg:province":"AL",
    "wof:name":"Thomas J McGlaughn Region",
    "wof:placetype":"venue"
},
  "geometry": {"coordinates":[-86.023074,33.972355],"type":"Point"}
}