{
  "type": "Feature",
  "properties": {
    "iso:country":"US",
    "sg:address":"2401 15th Ave N Ste 140",
    "sg:city":"Birmingham",
    "sg:classifiers":[
        {
            "category":"Health Services",
            "subcategory":"Doctor",
            "type":"Services"
        }
    ],
    "sg:phone":"+1 205 502 4400",
    "sg:postcode":"35234",
    "sg:province":"AL",
    "sg:tags":[
        "physician",
        "family",
        "practice",
        "surgeons",
        "medicine"
    ],
    "wof:name":"Andrew Dewitt Md Inc",
    "wof:placetype":"venue"
},
  "geometry": {"coordinates":[-86.81154600000001,33.533852],"type":"Point"}
}