{
  "type": "Feature",
  "properties": {
    "iso:country":"US",
    "sg:address":"22 S Florida St Suite C",
    "sg:city":"Mobile",
    "sg:classifiers":[
        {
            "category":"Retail",
            "subcategory":"Repair Shop",
            "type":"Services"
        },
        {
            "category":"Home & Garden",
            "subcategory":"Building Materials",
            "type":"Retail Goods"
        },
        {
            "category":"Building & Trades",
            "subcategory":"Construction",
            "type":"Services"
        },
        {
            "category":"Building & Trades",
            "subcategory":"Electrical",
            "type":"Services"
        }
    ],
    "sg:phone":"+1 251 473 7888",
    "sg:postcode":"36606",
    "sg:province":"AL",
    "sg:tags":[
        "industrial",
        "electrician",
        "electric",
        "improvement",
        "generators-electric-service",
        "contractors-commercial",
        "maintenance"
    ],
    "sg:website":"http://www.mrelectric.com",
    "wof:name":"Mr. Electric Of South Alabama",
    "wof:placetype":"venue"
},
  "geometry": {"coordinates":[-88.100351,30.686959],"type":"Point"}
}