{
  "type": "Feature",
  "properties": {
    "addr:full":"12 N Lawrence St Mobile AL 36602",
    "addr:housenumber":"12",
    "addr:postcode":"36602",
    "addr:street":"N Lawrence St",
    "iso:country":"US",
    "sg:address":"12 N Lawrence St",
    "sg:city":"Mobile",
    "sg:classifiers":[
        {
            "category":"Professional",
            "subcategory":"Lawyer & Legal Services",
            "type":"Services"
        }
    ],
    "sg:phone":"+1 251 432 3801",
    "sg:postcode":"36602",
    "sg:province":"AL",
    "sg:tags":[
        "attorney"
    ],
    "wof:name":"Richard Yelverton",
    "wof:placetype":"venue"
},
  "geometry": {"coordinates":[-88.04823500000001,30.69058],"type":"Point"}
}