{
  "type": "Feature",
  "properties": {
    "iso:country":"US",
    "sg:address":"911 N Alston St",
    "sg:city":"Foley",
    "sg:classifiers":[
        {
            "category":"Professional",
            "subcategory":"Engineering",
            "type":"Services"
        }
    ],
    "sg:phone":"+1 251 943 7115",
    "sg:postcode":"36535",
    "sg:province":"AL",
    "wof:name":"South Paw Construction",
    "wof:placetype":"venue"
},
  "geometry": {"coordinates":[-87.685372,30.416441],"type":"Point"}
}