{
  "type": "Feature",
  "properties": {
    "iso:country":"US",
    "sg:address":"800 Faust Ave",
    "sg:city":"Ozark",
    "sg:classifiers":[
        {
            "category":"Education",
            "subcategory":"School",
            "type":"Public Place"
        }
    ],
    "sg:phone":"+1 334 774 4919",
    "sg:postcode":"36360",
    "sg:province":"AL",
    "wof:name":"Joseph W Lsnby Elementary Schl",
    "wof:placetype":"venue"
},
  "geometry": {"coordinates":[-85.628742,31.471529],"type":"Point"}
}