{
  "type": "Feature",
  "properties": {
    "addr:full":"5112 Gary Ave Fairfield AL 35064",
    "addr:housenumber":"5112",
    "addr:postcode":"35064",
    "addr:street":"Gary Ave",
    "iso:country":"US",
    "sg:address":"5112 Gary Ave",
    "sg:city":"Fairfield",
    "sg:classifiers":[
        {
            "category":"Shopping",
            "subcategory":"Gifts & Souvenirs",
            "type":"Retail Goods"
        }
    ],
    "sg:phone":"+1 205 783 0403",
    "sg:postcode":"35064",
    "sg:province":"AL",
    "wof:name":"Nefertiti Imporium",
    "wof:placetype":"venue"
},
  "geometry": {"coordinates":[-86.915784,33.487028],"type":"Point"}
}