{
  "type": "Feature",
  "properties": {
    "iso:country":"US",
    "sg:address":"24742 US Hwy 31",
    "sg:city":"Jemison",
    "sg:classifiers":[
        {
            "category":"Organizations",
            "subcategory":"Religious Organization",
            "type":"Services"
        }
    ],
    "sg:phone":"+1 205 688 2787",
    "sg:postcode":"35085",
    "sg:province":"AL",
    "sg:tags":[
        "church"
    ],
    "wof:name":"Cross Roads Community Church",
    "wof:placetype":"venue"
},
  "geometry": {"coordinates":[-86.744372,32.960863],"type":"Point"}
}