{
  "type": "Feature",
  "properties": {
    "iso:country":"US",
    "sg:address":"100 Worthington Way",
    "sg:city":"Trussville",
    "sg:classifiers":[
        {
            "category":"Professional",
            "subcategory":"Business Services",
            "type":"Services"
        }
    ],
    "sg:phone":"+1 205 661 0269",
    "sg:postcode":"35173",
    "sg:province":"AL",
    "wof:name":"Open Door Home Inspection Inc",
    "wof:placetype":"venue"
},
  "geometry": {"coordinates":[-86.605938,33.638059],"type":"Point"}
}