{
  "type": "Feature",
  "properties": {
    "addr:full":"619 Saraland Blvd S Saraland AL 36571",
    "addr:housenumber":"619",
    "addr:postcode":"36571",
    "addr:street":"Saraland Blvd S Saraland",
    "iso:country":"US",
    "sg:address":"619 Saraland Blvd S",
    "sg:city":"Saraland",
    "sg:classifiers":[
        {
            "category":"Restaurant",
            "type":"Food & Drink"
        }
    ],
    "sg:menulink":"http://www.allmenus.com/al/mobile/231592-sonic/menu/",
    "sg:phone":"+1 251 675 7404",
    "sg:postcode":"36571",
    "sg:province":"AL",
    "sg:tags":[
        "burger",
        "american"
    ],
    "wof:name":"Sonic",
    "wof:placetype":"venue"
},
  "geometry": {"coordinates":[-88.071563,30.807822],"type":"Point"}
}