{
  "type": "Feature",
  "properties": {
    "iso:country":"US",
    "sg:address":"871 78th St S",
    "sg:city":"Birmingham",
    "sg:classifiers":[
        {
            "category":"Shopping",
            "subcategory":"Gifts & Souvenirs",
            "type":"Retail Goods"
        }
    ],
    "sg:phone":"+1 205 836 8290",
    "sg:postcode":"35206",
    "sg:province":"AL",
    "wof:name":"Johnsies Unique Gifts",
    "wof:placetype":"venue"
},
  "geometry": {"coordinates":[-86.711942,33.557112],"type":"Point"}
}