{
  "type": "Feature",
  "properties": {
    "addr:full":"507 Holmes Ave NE Huntsville AL 35801",
    "addr:housenumber":"507",
    "addr:postcode":"35801",
    "addr:street":"Holmes Ave Ne",
    "iso:country":"US",
    "sg:address":"507 Holmes Ave NE",
    "sg:city":"Huntsville",
    "sg:classifiers":[
        {
            "category":"Health Services",
            "subcategory":"Doctor",
            "type":"Services"
        }
    ],
    "sg:phone":"+1 256 539 0545",
    "sg:postcode":"35801",
    "sg:province":"AL",
    "sg:tags":[
        "medical"
    ],
    "wof:name":"Donald S Huber Dr",
    "wof:placetype":"venue"
},
  "geometry": {"coordinates":[-86.58201099999999,34.736057],"type":"Point"}
}