{
  "type": "Feature",
  "properties": {
    "iso:country":"US",
    "sg:address":"1030 Airport Rd W",
    "sg:city":"Fort Payne",
    "sg:classifiers":[
        {
            "category":"Freight",
            "type":"Transportation"
        }
    ],
    "sg:phone":"+1 256 845 5578",
    "sg:postcode":"35968",
    "sg:province":"AL",
    "sg:tags":[
        "broker",
        "trucking"
    ],
    "wof:name":"Trius Transportation Co",
    "wof:placetype":"venue"
},
  "geometry": {"coordinates":[-85.743196,34.449878],"type":"Point"}
}