{
  "type": "Feature",
  "properties": {
    "addr:full":"151 Powell Chapel Rd Falkville AL 35622",
    "addr:housenumber":"151",
    "addr:postcode":"35622",
    "addr:street":"Powell Chapel Rd",
    "iso:country":"US",
    "sg:address":"151 Powell Chapel Rd",
    "sg:city":"Falkville",
    "sg:classifiers":[
        {
            "category":"Autos & Motor Vehicles",
            "subcategory":"Automobile Sales",
            "type":"Retail Goods"
        }
    ],
    "sg:phone":"+1 256 734 3355",
    "sg:postcode":"35622",
    "sg:province":"AL",
    "sg:tags":[
        "used"
    ],
    "wof:name":"Auto Sales",
    "wof:placetype":"venue"
},
  "geometry": {"coordinates":[-86.91862500000001,34.320654],"type":"Point"}
}