{
  "type": "Feature",
  "properties": {
    "iso:country":"US",
    "sg:address":"6736 Airport Rd",
    "sg:city":"Elmore",
    "sg:classifiers":[
        {
            "category":"Professional",
            "subcategory":"Lawyer & Legal Services",
            "type":"Services"
        }
    ],
    "sg:phone":"+1 334 285 8100",
    "sg:postcode":"36025",
    "sg:province":"AL",
    "wof:name":"Sherry Albertson Attorney",
    "wof:placetype":"venue"
},
  "geometry": {"coordinates":[-86.335114,32.527108],"type":"Point"}
}