{
  "type": "Feature",
  "properties": {
    "addr:full":"3960 Cresthaven Rd Mobile AL 36609",
    "addr:housenumber":"3960",
    "addr:postcode":"36609",
    "addr:street":"Cresthaven Rd",
    "iso:country":"US",
    "sg:address":"3960 Cresthaven Rd",
    "sg:city":"Mobile",
    "sg:classifiers":[
        {
            "category":"Retail",
            "subcategory":"Laundry & Dry Cleaning",
            "type":"Services"
        }
    ],
    "sg:phone":"+1 251 343 2829",
    "sg:postcode":"36609",
    "sg:province":"AL",
    "sg:tags":[
        "power"
    ],
    "wof:name":"Azalea-Cresthaven Laundry Mat",
    "wof:placetype":"venue"
},
  "geometry": {"coordinates":[-88.15172099999999,30.663706],"type":"Point"}
}