{
  "type": "Feature",
  "properties": {
    "iso:country":"US",
    "sg:address":"1900 Country Club Rd SE",
    "sg:city":"Decatur",
    "sg:classifiers":[
        {
            "category":"Health Services",
            "subcategory":"Dentist",
            "type":"Services"
        }
    ],
    "sg:phone":"+1 256 350 3172",
    "sg:postcode":"35601",
    "sg:province":"AL",
    "wof:name":"Stanley Pat Dr Dntst Res",
    "wof:placetype":"venue"
},
  "geometry": {"coordinates":[-86.97187,34.576099],"type":"Point"}
}