{
  "type": "Feature",
  "properties": {
    "iso:country":"US",
    "sg:address":"1015 Lay Dam Rd",
    "sg:city":"Clanton",
    "sg:classifiers":[
        {
            "category":"Insurance",
            "subcategory":"Insurance Agent",
            "type":"Services"
        }
    ],
    "sg:phone":"+1 205 755 3375",
    "sg:postcode":"35045",
    "sg:province":"AL",
    "wof:name":"Liberty National Insurance Co",
    "wof:placetype":"venue"
},
  "geometry": {"coordinates":[-86.622662,32.856107],"type":"Point"}
}