{
  "type": "Feature",
  "properties": {
    "addr:full":"1758 Park Pl Montgomery AL 36106",
    "addr:housenumber":"1758",
    "addr:postcode":"36106",
    "addr:street":"Park Pl",
    "iso:country":"US",
    "sg:address":"1758 Park Pl",
    "sg:city":"Montgomery",
    "sg:classifiers":[
        {
            "category":"Health Services",
            "subcategory":"Doctor",
            "type":"Services"
        }
    ],
    "sg:phone":"+1 334 264 9191",
    "sg:postcode":"36106",
    "sg:province":"AL",
    "sg:tags":[
        "physician",
        "surgeon"
    ],
    "wof:name":"Cardiology Associates",
    "wof:placetype":"venue"
},
  "geometry": {"coordinates":[-86.284857,32.368547],"type":"Point"}
}