{
  "type": "Feature",
  "properties": {
    "iso:country":"US",
    "sg:address":"1911 S 11th St",
    "sg:city":"Gadsden",
    "sg:classifiers":[
        {
            "category":"Organizations",
            "subcategory":"Religious Organization",
            "type":"Services"
        }
    ],
    "sg:phone":"+1 256 546 2625",
    "sg:postcode":"35904",
    "sg:province":"AL",
    "wof:name":"Victory Baptist Church",
    "wof:placetype":"venue"
},
  "geometry": {"coordinates":[-86.032405,33.996105],"type":"Point"}
}