{
  "type": "Feature",
  "properties": {
    "iso:country":"US",
    "sg:address":"934 US Hwy 43",
    "sg:city":"Winfield",
    "sg:classifiers":[
        {
            "category":"Personal",
            "subcategory":"Tanning Parlor",
            "type":"Services"
        },
        {
            "category":"Personal",
            "type":"Services"
        }
    ],
    "sg:phone":"+1 205 487 3686",
    "sg:postcode":"35594",
    "sg:province":"AL",
    "sg:tags":[
        "salon"
    ],
    "wof:name":"Naomi's Tanning Salon",
    "wof:placetype":"venue"
},
  "geometry": {"coordinates":[-87.823505,33.859546],"type":"Point"}
}