{
  "type": "Feature",
  "properties": {
    "addr:full":"190 Lime Quarry Rd Madison AL 35758",
    "addr:housenumber":"190",
    "addr:postcode":"35758",
    "addr:street":"Lime Quarry Rd",
    "iso:country":"US",
    "sg:address":"190 Lime Quarry Rd",
    "sg:city":"Madison",
    "sg:classifiers":[
        {
            "category":"Professional",
            "subcategory":"Detective & Security Services",
            "type":"Services"
        }
    ],
    "sg:phone":"+1 256 464 9292",
    "sg:postcode":"35758",
    "sg:province":"AL",
    "sg:tags":[
        "guard",
        "patrol"
    ],
    "wof:name":"Securitas Security Svc USA Inc",
    "wof:placetype":"venue"
},
  "geometry": {"coordinates":[-86.748589,34.676442],"type":"Point"}
}