{
  "type": "Feature",
  "properties": {
    "iso:country":"US",
    "sg:address":"7445 Moffett Rd",
    "sg:city":"Mobile",
    "sg:classifiers":[
        {
            "category":"Home & Garden",
            "subcategory":"Mobile Homes",
            "type":"Retail Goods"
        }
    ],
    "sg:phone":"+1 251 645 0645",
    "sg:postcode":"36618",
    "sg:province":"AL",
    "wof:name":"Ron's Used Mobile Homes",
    "wof:placetype":"venue"
},
  "geometry": {"coordinates":[-88.2192,30.756454],"type":"Point"}
}