{
  "type": "Feature",
  "properties": {
    "addr:full":"811 Baltimore Hill Rd Huntsville AL 35810",
    "addr:housenumber":"811",
    "addr:postcode":"35810",
    "addr:street":"Baltimore Hill Rd",
    "iso:country":"US",
    "sg:address":"811 Baltimore Hill Rd",
    "sg:city":"Huntsville",
    "sg:classifiers":[
        {
            "category":"Retail",
            "subcategory":"Auto Repair",
            "type":"Services"
        }
    ],
    "sg:phone":"+1 256 852 7715",
    "sg:postcode":"35810",
    "sg:province":"AL",
    "sg:tags":[
        "general"
    ],
    "wof:name":"Morris Auto Repair",
    "wof:placetype":"venue"
},
  "geometry": {"coordinates":[-86.538388,34.836298],"type":"Point"}
}