{
  "type": "Feature",
  "properties": {
    "addr:full":"707 8th St W Jasper AL 35501",
    "addr:housenumber":"707",
    "addr:postcode":"35501",
    "addr:street":"8Th St W",
    "iso:country":"US",
    "sg:address":"707 8th St W",
    "sg:city":"Jasper",
    "sg:classifiers":[
        {
            "category":"Farming",
            "subcategory":"Livestock Farm",
            "type":"Manufacturing & Wholesale Goods"
        }
    ],
    "sg:phone":"+1 205 221 7791",
    "sg:postcode":"35501",
    "sg:province":"AL",
    "sg:tags":[
        "animal",
        "general"
    ],
    "wof:name":"Sunlight Farm",
    "wof:placetype":"venue"
},
  "geometry": {"coordinates":[-87.28361200000001,33.844163],"type":"Point"}
}