{
  "type": "Feature",
  "properties": {
    "iso:country":"US",
    "sg:address":"212 N Main St",
    "sg:city":"Enterprise",
    "sg:classifiers":[
        {
            "category":"Restaurant",
            "type":"Food & Drink"
        }
    ],
    "sg:phone":"+1 334 347 6622",
    "sg:postcode":"36330",
    "sg:province":"AL",
    "sg:tags":[
        "eating"
    ],
    "wof:name":"Annie Cafe",
    "wof:placetype":"venue"
},
  "geometry": {"coordinates":[-85.854765,31.315341],"type":"Point"}
}