{
  "type": "Feature",
  "properties": {
    "iso:country":"US",
    "sg:address":"1722 Friendship Rd",
    "sg:city":"Arab",
    "sg:classifiers":[
        {
            "category":"Building & Trades",
            "subcategory":"Electrical",
            "type":"Services"
        }
    ],
    "sg:phone":"+1 256 586 7190",
    "sg:postcode":"35016",
    "sg:province":"AL",
    "sg:tags":[
        "electrical",
        "contractor"
    ],
    "wof:name":"Daniel Electric",
    "wof:placetype":"venue"
},
  "geometry": {"coordinates":[-86.47350900000001,34.352266],"type":"Point"}
}