{
  "type": "Feature",
  "properties": {
    "iso:country":"US",
    "sg:address":"5600 Girby Rd",
    "sg:city":"Mobile",
    "sg:classifiers":[
        {
            "category":"Social Services",
            "type":"Services"
        }
    ],
    "sg:phone":"+1 251 660 5722",
    "sg:postcode":"36693",
    "sg:province":"AL",
    "sg:tags":[
        "clinic",
        "specialty",
        "outpatient"
    ],
    "wof:name":"Child & Adolescents Program",
    "wof:placetype":"venue"
},
  "geometry": {"coordinates":[-88.167379,30.618387],"type":"Point"}
}