{
  "type": "Feature",
  "properties": {
    "addr:full":"3315 Governors Dr SW Huntsville AL 35805",
    "addr:housenumber":"3315",
    "addr:postcode":"35805",
    "addr:street":"Governors Dr Sw",
    "iso:country":"US",
    "sg:address":"3315 Governors Dr SW",
    "sg:city":"Huntsville",
    "sg:classifiers":[
        {
            "category":"Autos & Motor Vehicles",
            "subcategory":"Fuel & Gas Station",
            "type":"Retail Goods"
        },
        {
            "category":"Food & Beverages",
            "subcategory":"Groceries & Convenience Stores",
            "type":"Retail Goods"
        }
    ],
    "sg:phone":"+1 256 533 3290",
    "sg:postcode":"35805",
    "sg:province":"AL",
    "wof:name":"Shell Food Mart",
    "wof:placetype":"venue"
},
  "geometry": {"coordinates":[-86.610693,34.720119],"type":"Point"}
}