{
  "type": "Feature",
  "properties": {
    "iso:country":"US",
    "sg:address":"4515 Coosada Ferry Rd",
    "sg:city":"Montgomery",
    "sg:classifiers":[
        {
            "category":"Professional",
            "subcategory":"Business Services",
            "type":"Services"
        }
    ],
    "sg:phone":"+1 334 269 2158",
    "sg:postcode":"36110",
    "sg:province":"AL",
    "wof:name":"Capitol City Recovery",
    "wof:placetype":"venue"
},
  "geometry": {"coordinates":[-86.29193100000001,32.457002],"type":"Point"}
}