{
  "type": "Feature",
  "properties": {
    "addr:full":"192 Co Rd 352 Salem AL 36874",
    "addr:housenumber":"192;352",
    "addr:postcode":"36874",
    "addr:street":"Co Rd",
    "iso:country":"US",
    "sg:address":"192 Co Rd 352",
    "sg:city":"Salem",
    "sg:classifiers":[
        {
            "category":"Freight",
            "type":"Transportation"
        }
    ],
    "sg:phone":"+1 334 502 6181",
    "sg:postcode":"36874",
    "sg:province":"AL",
    "wof:name":"A&A Moving",
    "wof:placetype":"venue"
},
  "geometry": {"coordinates":[-85.137187,32.677657],"type":"Point"}
}