{
  "type": "Feature",
  "properties": {
    "iso:country":"US",
    "sg:address":"850 Brandy Cir",
    "sg:city":"Birmingham",
    "sg:classifiers":[
        {
            "category":"Organizations",
            "subcategory":"Religious Organization",
            "type":"Services"
        }
    ],
    "sg:phone":"+1 205 798 3181",
    "sg:postcode":"35214",
    "sg:province":"AL",
    "wof:name":"Liberty Baptist Church",
    "wof:placetype":"venue"
},
  "geometry": {"coordinates":[-86.87678099999999,33.563408],"type":"Point"}
}