{
  "type": "Feature",
  "properties": {
    "iso:country":"US",
    "sg:address":"4123 Ross Clark Cir",
    "sg:city":"Dothan",
    "sg:classifiers":[
        {
            "category":"Autos & Motor Vehicles",
            "subcategory":"Automobile Sales",
            "type":"Retail Goods"
        }
    ],
    "sg:phone":"+1 334 673 3556",
    "sg:postcode":"36303",
    "sg:province":"AL",
    "sg:tags":[
        "used"
    ],
    "wof:name":"Hertz",
    "wof:placetype":"venue"
},
  "geometry": {"coordinates":[-85.39753899999999,31.253495],"type":"Point"}
}