{
  "type": "Feature",
  "properties": {
    "iso:country":"US",
    "sg:address":"4809 Northwood Lake Dr W",
    "sg:city":"Northport",
    "sg:classifiers":[
        {
            "category":"Professional",
            "type":"Services"
        }
    ],
    "sg:phone":"+1 205 339 2186",
    "sg:postcode":"35473",
    "sg:province":"AL",
    "wof:name":"Richard A Krause",
    "wof:placetype":"venue"
},
  "geometry": {"coordinates":[-87.58608700000001,33.255252],"type":"Point"}
}