{
  "type": "Feature",
  "properties": {
    "addr:full":"206 Coosa St W Talladega AL 35160",
    "addr:housenumber":"206",
    "addr:postcode":"35160",
    "addr:street":"Coosa St W Talladega",
    "iso:country":"US",
    "sg:address":"206 Coosa St W",
    "sg:city":"Talladega",
    "sg:classifiers":[
        {
            "category":"Home & Garden",
            "subcategory":"Home Furnishings",
            "type":"Retail Goods"
        }
    ],
    "sg:phone":"+1 256 362 3348",
    "sg:postcode":"35160",
    "sg:province":"AL",
    "sg:tags":[
        "lamp",
        "shades"
    ],
    "wof:name":"Townsend's Lamps & Gifts",
    "wof:placetype":"venue"
},
  "geometry": {"coordinates":[-86.104021,33.437462],"type":"Point"}
}