{
  "type": "Feature",
  "properties": {
    "iso:country":"US",
    "sg:address":"1121 Gulf Shores Pkwy",
    "sg:city":"Gulf Shores",
    "sg:classifiers":[
        {
            "category":"Restaurant",
            "type":"Food & Drink"
        }
    ],
    "sg:phone":"+1 251 968 2777",
    "sg:postcode":"36542",
    "sg:province":"AL",
    "wof:name":"Jake's Steakhouse",
    "wof:placetype":"venue"
},
  "geometry": {"coordinates":[-87.688557,30.260077],"type":"Point"}
}