{
  "type": "Feature",
  "properties": {
    "iso:country":"US",
    "sg:address":"5058 Dawes Ln Exd",
    "sg:city":"Theodore",
    "sg:classifiers":[
        {
            "category":"Retail",
            "subcategory":"Auto Repair",
            "type":"Services"
        }
    ],
    "sg:phone":"+1 251 602 1892",
    "sg:postcode":"36582",
    "sg:province":"AL",
    "sg:tags":[
        "wrecker"
    ],
    "wof:name":"Petra Towing & Recovery",
    "wof:placetype":"venue"
},
  "geometry": {"coordinates":[-88.250039,30.588321],"type":"Point"}
}