{
  "type": "Feature",
  "properties": {
    "iso:country":"US",
    "sg:address":"108 14th St SW",
    "sg:city":"Decatur",
    "sg:classifiers":[
        {
            "category":"Manufacturing",
            "subcategory":"Printing",
            "type":"Manufacturing & Wholesale Goods"
        }
    ],
    "sg:phone":"+1 256 353 8000",
    "sg:postcode":"35601",
    "sg:province":"AL",
    "sg:tags":[
        "commercial",
        "lithographic",
        "mfg"
    ],
    "wof:name":"Copy Cat Printing Inc",
    "wof:placetype":"venue"
},
  "geometry": {"coordinates":[-86.987364,34.578063],"type":"Point"}
}