{
  "type": "Feature",
  "properties": {
    "addr:full":"124 Hardin Rd Falkville AL 35622",
    "addr:housenumber":"124",
    "addr:postcode":"35622",
    "addr:street":"Hardin Rd",
    "iso:country":"US",
    "sg:address":"124 Hardin Rd",
    "sg:city":"Falkville",
    "sg:classifiers":[
        {
            "category":"Farming",
            "subcategory":"Farm",
            "type":"Manufacturing & Wholesale Goods"
        }
    ],
    "sg:phone":"+1 256 462 3859",
    "sg:postcode":"35622",
    "sg:province":"AL",
    "sg:tags":[
        "crop",
        "general"
    ],
    "wof:name":"Higdon Farms",
    "wof:placetype":"venue"
},
  "geometry": {"coordinates":[-87.02703099999999,34.343896],"type":"Point"}
}