{
  "type": "Feature",
  "properties": {
    "iso:country":"US",
    "sg:address":"2435 Montgomery Hwy",
    "sg:city":"Dothan",
    "sg:classifiers":[
        {
            "category":"Food & Beverages",
            "subcategory":"Liquor & Beverages",
            "type":"Retail Goods"
        }
    ],
    "sg:phone":"+1 334 792 8745",
    "sg:postcode":"36303",
    "sg:province":"AL",
    "wof:name":"Alabama State ABC Stores",
    "wof:placetype":"venue"
},
  "geometry": {"coordinates":[-85.41811300000001,31.242789],"type":"Point"}
}