{
  "type": "Feature",
  "properties": {
    "addr:full":"401 N Main Ave Demopolis AL 36732",
    "addr:housenumber":"401",
    "addr:postcode":"36732",
    "addr:street":"N Main Ave",
    "iso:country":"US",
    "sg:address":"401 N Main Ave",
    "sg:city":"Demopolis",
    "sg:classifiers":[
        {
            "category":"Organizations",
            "subcategory":"Religious Organization",
            "type":"Services"
        }
    ],
    "sg:phone":"+1 334 289 3363",
    "sg:postcode":"36732",
    "sg:province":"AL",
    "sg:tags":[
        "church"
    ],
    "wof:name":"Trinity Episcopal Church",
    "wof:placetype":"venue"
},
  "geometry": {"coordinates":[-87.83882199999999,32.520496],"type":"Point"}
}