{
  "type": "Feature",
  "properties": {
    "iso:country":"US",
    "sg:address":"311 Mendel Pkwy E",
    "sg:city":"Montgomery",
    "sg:classifiers":[
        {
            "category":"Shopping",
            "type":"Retail Goods"
        }
    ],
    "sg:phone":"+1 334 272 4535",
    "sg:postcode":"36117",
    "sg:province":"AL",
    "sg:tags":[
        "system",
        "alarm",
        "security",
        "signal"
    ],
    "wof:name":"Silent Sentry Electronic Sec",
    "wof:placetype":"venue"
},
  "geometry": {"coordinates":[-86.201579,32.379096],"type":"Point"}
}