{
  "type": "Feature",
  "properties": {
    "iso:country":"US",
    "sg:address":"6570 State Rte 69",
    "sg:city":"Tuscaloosa",
    "sg:classifiers":[
        {
            "category":"Personal",
            "subcategory":"Beauty Salon",
            "type":"Services"
        }
    ],
    "sg:phone":"+1 205 758 6245",
    "sg:postcode":"35405",
    "sg:province":"AL",
    "sg:tags":[
        "manicuring"
    ],
    "wof:name":"Nail Club",
    "wof:placetype":"venue"
},
  "geometry": {"coordinates":[-87.54533600000001,33.148115],"type":"Point"}
}