{
  "type": "Feature",
  "properties": {
    "iso:country":"US",
    "sg:address":"3994 Co Rd 30",
    "sg:city":"Sardis",
    "sg:classifiers":[
        {
            "category":"Organizations",
            "subcategory":"Religious Organization",
            "type":"Services"
        }
    ],
    "sg:phone":"+1 334 877 0126",
    "sg:postcode":"36775",
    "sg:province":"AL",
    "sg:tags":[
        "church"
    ],
    "wof:name":"New Mt Lebanon Baptist Church",
    "wof:placetype":"venue"
},
  "geometry": {"coordinates":[-87.04363,32.282723],"type":"Point"}
}