{
  "type": "Feature",
  "properties": {
    "addr:full":"3324 Co Rd 37 Camp Hill AL 36850",
    "addr:housenumber":"3324;37",
    "addr:postcode":"36850",
    "addr:street":"Co Rd",
    "iso:country":"US",
    "sg:address":"3324 Co Rd 37",
    "sg:city":"Camp Hill",
    "sg:classifiers":[
        {
            "category":"Building & Trades",
            "subcategory":"Construction",
            "type":"Services"
        }
    ],
    "sg:phone":"+1 256 896 2203",
    "sg:postcode":"36850",
    "sg:province":"AL",
    "sg:tags":[
        "sewer",
        "contractor"
    ],
    "wof:name":"Culebra Mfg Co",
    "wof:placetype":"venue"
},
  "geometry": {"coordinates":[-85.547241,32.831856],"type":"Point"}
}