{
  "type": "Feature",
  "properties": {
    "iso:country":"US",
    "sg:address":"3201 Portia Ln",
    "sg:city":"Birmingham",
    "sg:classifiers":[
        {
            "category":"Community Center",
            "type":"Public Place"
        }
    ],
    "sg:phone":"+1 205 978 8667",
    "sg:postcode":"35216",
    "sg:province":"AL",
    "sg:tags":[
        "medical"
    ],
    "wof:name":"Brookwood Medical Center",
    "wof:placetype":"venue"
},
  "geometry": {"coordinates":[-86.795563,33.40036],"type":"Point"}
}