{
  "type": "Feature",
  "properties": {
    "addr:full":"1210 Dale Dr SE Huntsville AL 35801",
    "addr:housenumber":"1210",
    "addr:postcode":"35801",
    "addr:street":"Dale Dr Se",
    "iso:country":"US",
    "sg:address":"1210 Dale Dr SE",
    "sg:city":"Huntsville",
    "sg:classifiers":[
        {
            "category":"Retail",
            "subcategory":"Portrait Studio",
            "type":"Services"
        }
    ],
    "sg:phone":"+1 256 658 2530",
    "sg:postcode":"35801",
    "sg:province":"AL",
    "sg:tags":[
        "photographer"
    ],
    "wof:name":"Flashback Photography",
    "wof:placetype":"venue"
},
  "geometry": {"coordinates":[-86.564071,34.724988],"type":"Point"}
}