{
  "type": "Feature",
  "properties": {
    "addr:full":"3150 Tine Ave Montgomery AL 36108",
    "addr:postcode":"3150;36108",
    "addr:street":"Tine Ave",
    "iso:country":"US",
    "sg:address":"3150 Tine Ave",
    "sg:city":"Montgomery",
    "sg:classifiers":[
        {
            "category":"Freight",
            "type":"Transportation"
        }
    ],
    "sg:phone":"+1 334 265 0964",
    "sg:postcode":"36108",
    "sg:province":"AL",
    "sg:tags":[
        "grocery",
        "general"
    ],
    "wof:name":"Petrey Warehouse",
    "wof:placetype":"venue"
},
  "geometry": {"coordinates":[-86.348771,32.356112],"type":"Point"}
}