{
  "type": "Feature",
  "properties": {
    "addr:full":"1420 S Skyline Dr Jasper AL 35501",
    "addr:housenumber":"1420",
    "addr:postcode":"35501",
    "addr:street":"S Skyline Dr",
    "iso:country":"US",
    "sg:address":"1420 S Skyline Dr",
    "sg:city":"Jasper",
    "sg:classifiers":[
        {
            "category":"Retail",
            "subcategory":"Auto Repair",
            "type":"Services"
        }
    ],
    "sg:phone":"+1 205 387 0607",
    "sg:postcode":"35501",
    "sg:province":"AL",
    "sg:tags":[
        "wrecker"
    ],
    "wof:name":"Williams Garage & Wrecker Svc",
    "wof:placetype":"venue"
},
  "geometry": {"coordinates":[-87.31384199999999,33.842245],"type":"Point"}
}