{
  "type": "Feature",
  "properties": {
    "addr:full":"1701 Holt Rd NE Tuscaloosa AL 35404",
    "addr:housenumber":"1701",
    "addr:postcode":"35404",
    "addr:street":"Holt Rd Ne",
    "iso:country":"US",
    "sg:address":"1701 Holt Rd NE",
    "sg:city":"Tuscaloosa",
    "sg:classifiers":[
        {
            "category":"Wholesale",
            "subcategory":"Non-durable Goods",
            "type":"Manufacturing & Wholesale Goods"
        }
    ],
    "sg:phone":"+1 205 553 9686",
    "sg:postcode":"35404",
    "sg:province":"AL",
    "wof:name":"Moletec Corporation",
    "wof:placetype":"venue"
},
  "geometry": {"coordinates":[-87.505932,33.235248],"type":"Point"}
}