{
  "type": "Feature",
  "properties": {
    "addr:full":"1500 1st Ave N Unit 44 Birmingham AL 35203",
    "addr:housenumber":"1500;44",
    "addr:postcode":"35203",
    "addr:street":"1St Ave N Unit",
    "iso:country":"US",
    "sg:address":"1500 1st Ave N Unit 44",
    "sg:city":"Birmingham",
    "sg:classifiers":[
        {
            "category":"Food & Beverages",
            "subcategory":"Specialty",
            "type":"Retail Goods"
        }
    ],
    "sg:phone":"+1 205 250 8040",
    "sg:postcode":"35203",
    "sg:province":"AL",
    "sg:tags":[
        "supplement",
        "vitamin"
    ],
    "sg:website":"http://www.hcsupplements.com",
    "wof:name":"Healthcare Supplements Inc",
    "wof:placetype":"venue"
},
  "geometry": {"coordinates":[-86.81265,33.511142],"type":"Point"}
}