{
  "type": "Feature",
  "properties": {
    "iso:country":"US",
    "sg:address":"2511 2nd Ave NE",
    "sg:city":"Fayette",
    "sg:classifiers":[
        {
            "category":"Building & Trades",
            "subcategory":"Plumbing",
            "type":"Services"
        }
    ],
    "sg:phone":"+1 205 932 6112",
    "sg:postcode":"35555",
    "sg:province":"AL",
    "sg:tags":[
        "conditioning",
        "air",
        "system",
        "contractor"
    ],
    "wof:name":"Mark's Heating & Cooling",
    "wof:placetype":"venue"
},
  "geometry": {"coordinates":[-87.81387,33.718593],"type":"Point"}
}