{
  "type": "Feature",
  "properties": {
    "iso:country":"US",
    "sg:address":"1315 E Park Ave",
    "sg:city":"Enterprise",
    "sg:classifiers":[
        {
            "category":"Mining & Drilling",
            "type":"Manufacturing & Wholesale Goods"
        }
    ],
    "sg:phone":"+1 334 347 3024",
    "sg:postcode":"36330",
    "sg:province":"AL",
    "sg:tags":[
        "oil",
        "gas",
        "producer"
    ],
    "wof:name":"Southwest Georgia Oil Co",
    "wof:placetype":"venue"
},
  "geometry": {"coordinates":[-85.832225,31.307846],"type":"Point"}
}