{
  "type": "Feature",
  "properties": {
    "iso:country":"US",
    "sg:address":"7066 Willow Rd",
    "sg:city":"Ider",
    "sg:classifiers":[
        {
            "category":"Autos & Motor Vehicles",
            "subcategory":"Automobile Sales",
            "type":"Retail Goods"
        }
    ],
    "sg:phone":"+1 256 632 6098",
    "sg:postcode":"35981",
    "sg:province":"AL",
    "sg:tags":[
        "new",
        "used",
        "car"
    ],
    "wof:name":"Williamson Motors",
    "wof:placetype":"venue"
},
  "geometry": {"coordinates":[-85.688292,34.716039],"type":"Point"}
}