{
  "type": "Feature",
  "properties": {
    "iso:country":"US",
    "sg:address":"1951 Market St",
    "sg:city":"Millbrook",
    "sg:classifiers":[
        {
            "category":"Home & Garden",
            "subcategory":"Furniture",
            "type":"Retail Goods"
        }
    ],
    "sg:phone":"+1 334 290 1809",
    "sg:postcode":"36054",
    "sg:province":"AL",
    "sg:tags":[
        "mattress"
    ],
    "wof:name":"Mr Sandman",
    "wof:placetype":"venue"
},
  "geometry": {"coordinates":[-86.383345,32.458281],"type":"Point"}
}