{
  "type": "Feature",
  "properties": {
    "addr:full":"485 Westchester Dr Birmingham AL 35215",
    "addr:housenumber":"485",
    "addr:postcode":"35215",
    "addr:street":"Westchester Dr",
    "iso:country":"US",
    "sg:address":"485 Westchester Dr",
    "sg:city":"Birmingham",
    "sg:classifiers":[
        {
            "category":"Retail",
            "subcategory":"Car Wash",
            "type":"Services"
        }
    ],
    "sg:phone":"+1 205 266 4127",
    "sg:postcode":"35215",
    "sg:province":"AL",
    "sg:tags":[
        "carwash"
    ],
    "wof:name":"At Home Car Wash",
    "wof:placetype":"venue"
},
  "geometry": {"coordinates":[-86.698629,33.663326],"type":"Point"}
}