{
  "type": "Feature",
  "properties": {
    "addr:full":"2018 E 2nd St Montgomery AL 36106",
    "addr:housenumber":"2018",
    "addr:postcode":"36106",
    "addr:street":"E 2Nd St",
    "iso:country":"US",
    "sg:address":"2018 E 2nd St",
    "sg:city":"Montgomery",
    "sg:classifiers":[
        {
            "category":"Personal",
            "type":"Services"
        }
    ],
    "sg:phone":"+1 334 956 8700",
    "sg:postcode":"36106",
    "sg:province":"AL",
    "sg:tags":[
        "therapist",
        "massage"
    ],
    "wof:name":"Gwen's A Southern Spa",
    "wof:placetype":"venue"
},
  "geometry": {"coordinates":[-86.281845,32.363975],"type":"Point"}
}