{
  "type": "Feature",
  "properties": {
    "addr:full":"7121 Airport Blvd Mobile AL 36608",
    "addr:housenumber":"7121",
    "addr:postcode":"36608",
    "addr:street":"Airport Blvd",
    "iso:country":"US",
    "sg:address":"7121 Airport Blvd",
    "sg:city":"Mobile",
    "sg:classifiers":[
        {
            "category":"Health Services",
            "subcategory":"Chiropractor",
            "type":"Services"
        }
    ],
    "sg:phone":"+1 251 342 8833",
    "sg:postcode":"36608",
    "sg:province":"AL",
    "wof:name":"Airport Boulevard Chiropractic",
    "wof:placetype":"venue"
},
  "geometry": {"coordinates":[-88.208575,30.686522],"type":"Point"}
}