{
  "type": "Feature",
  "properties": {
    "addr:full":"8500 Bay View Dr Foley AL 36535",
    "addr:housenumber":"8500",
    "addr:postcode":"36535",
    "addr:street":"Bay View Dr",
    "iso:country":"US",
    "sg:address":"8500 Bay View Dr",
    "sg:city":"Foley",
    "sg:classifiers":[
        {
            "category":"Professional",
            "subcategory":"Art Services",
            "type":"Services"
        }
    ],
    "sg:phone":"+1 251 955 1231",
    "sg:postcode":"36535",
    "sg:province":"AL",
    "sg:tags":[
        "commercial",
        "design"
    ],
    "wof:name":"Architectural Illustration",
    "wof:placetype":"venue"
},
  "geometry": {"coordinates":[-87.604465,30.346311],"type":"Point"}
}