{
  "type": "Feature",
  "properties": {
    "iso:country":"US",
    "sg:address":"2217 Cahaba Valley Dr",
    "sg:city":"Birmingham",
    "sg:classifiers":[
        {
            "category":"Professional",
            "subcategory":"Lawyer & Legal Services",
            "type":"Services"
        }
    ],
    "sg:phone":"+1 205 663 0444",
    "sg:postcode":"35242",
    "sg:province":"AL",
    "wof:name":"Dry Ice Blasting Services Inc",
    "wof:placetype":"venue"
},
  "geometry": {"coordinates":[-86.672255,33.41612],"type":"Point"}
}