{
  "type": "Feature",
  "properties": {
    "iso:country":"US",
    "sg:address":"4799 Old Birmingham Hwy",
    "sg:city":"Jasper",
    "sg:classifiers":[
        {
            "category":"Building & Trades",
            "subcategory":"Construction",
            "type":"Services"
        }
    ],
    "sg:phone":"+1 205 221 8446",
    "sg:postcode":"35501",
    "sg:province":"AL",
    "sg:tags":[
        "home",
        "builder"
    ],
    "wof:name":"Walker County Homebuilders",
    "wof:placetype":"venue"
},
  "geometry": {"coordinates":[-87.214426,33.820205],"type":"Point"}
}