{
  "type": "Feature",
  "properties": {
    "addr:full":"44100 Pine Grove Rd Bay Minette AL 36507",
    "addr:housenumber":"44100",
    "addr:postcode":"36507",
    "addr:street":"Pine Grove Rd",
    "iso:country":"US",
    "sg:address":"44100 Pine Grove Rd",
    "sg:city":"Bay Minette",
    "sg:classifiers":[
        {
            "category":"Real Estate",
            "subcategory":"Real Estate Operator",
            "type":"Services"
        },
        {
            "category":"Building & Trades",
            "subcategory":"Construction",
            "type":"Services"
        }
    ],
    "sg:phone":"+1 251 937 9495",
    "sg:postcode":"36507",
    "sg:province":"AL",
    "sg:tags":[
        "house",
        "apartment",
        "nonresidential"
    ],
    "wof:name":"Robinson Construction Company",
    "wof:placetype":"venue"
},
  "geometry": {"coordinates":[-87.750979,30.869472],"type":"Point"}
}