{
  "type": "Feature",
  "properties": {
    "addr:full":"3730 4th Ter N Birmingham AL 35222",
    "addr:housenumber":"3730",
    "addr:postcode":"35222",
    "addr:street":"4Th Ter N",
    "iso:country":"US",
    "sg:address":"3730 4th Ter N",
    "sg:city":"Birmingham",
    "sg:classifiers":[
        {
            "category":"Building & Trades",
            "subcategory":"Construction",
            "type":"Services"
        }
    ],
    "sg:phone":"+1 205 599 9930",
    "sg:postcode":"35222",
    "sg:province":"AL",
    "sg:tags":[
        "layer",
        "contractor",
        "laying",
        "floor",
        "carpet"
    ],
    "wof:name":"Flooring Creations Inc",
    "wof:placetype":"venue"
},
  "geometry": {"coordinates":[-86.784818,33.528269],"type":"Point"}
}