{
  "type": "Feature",
  "properties": {
    "iso:country":"US",
    "sg:address":"401 George Wallace Dr",
    "sg:city":"Gadsden",
    "sg:classifiers":[
        {
            "category":"Utilities",
            "subcategory":"Telephone",
            "type":"Services"
        }
    ],
    "sg:phone":"+1 256 546 5320",
    "sg:postcode":"35903",
    "sg:province":"AL",
    "sg:tags":[
        "communications"
    ],
    "wof:name":"Cingular Wireless",
    "wof:placetype":"venue"
},
  "geometry": {"coordinates":[-85.99624,34.003669],"type":"Point"}
}