{
  "type": "Feature",
  "properties": {
    "iso:country":"US",
    "sg:address":"1822 Doublehead Rd",
    "sg:city":"Roanoke",
    "sg:classifiers":[
        {
            "category":"Building & Trades",
            "subcategory":"Electrical",
            "type":"Services"
        }
    ],
    "sg:phone":"+1 334 863 7725",
    "sg:postcode":"36274",
    "sg:province":"AL",
    "sg:tags":[
        "electrician"
    ],
    "wof:name":"Cain Communications Inc",
    "wof:placetype":"venue"
},
  "geometry": {"coordinates":[-85.388807,33.116342],"type":"Point"}
}