{
  "type": "Feature",
  "properties": {
    "iso:country":"US",
    "sg:address":"5778 Chelsea Rd",
    "sg:city":"Columbiana",
    "sg:classifiers":[
        {
            "category":"Organizations",
            "subcategory":"Religious Organization",
            "type":"Services"
        }
    ],
    "sg:phone":"+1 205 669 0839",
    "sg:postcode":"35051",
    "sg:province":"AL",
    "sg:tags":[
        "church"
    ],
    "wof:name":"New Bethesda Baptist Church",
    "wof:placetype":"venue"
},
  "geometry": {"coordinates":[-86.62147400000001,33.264539],"type":"Point"}
}