{
  "type": "Feature",
  "properties": {
    "addr:full":"407 Conti St Mobile AL 36602",
    "addr:housenumber":"407",
    "addr:postcode":"36602",
    "addr:street":"Conti St",
    "iso:country":"US",
    "sg:address":"407 Conti St",
    "sg:city":"Mobile",
    "sg:classifiers":[
        {
            "category":"Professional",
            "subcategory":"Lawyer & Legal Services",
            "type":"Services"
        }
    ],
    "sg:phone":"+1 251 438 9100",
    "sg:postcode":"36602",
    "sg:province":"AL",
    "sg:tags":[
        "attorney"
    ],
    "wof:name":"Frank H Kruse",
    "wof:placetype":"venue"
},
  "geometry": {"coordinates":[-88.046764,30.689412],"type":"Point"}
}