{
  "type": "Feature",
  "properties": {
    "addr:full":"4985 Tulip Ave Mobile AL 36619",
    "addr:housenumber":"4985",
    "addr:postcode":"36619",
    "addr:street":"Tulip Ave",
    "iso:country":"US",
    "sg:address":"4985 Tulip Ave",
    "sg:city":"Mobile",
    "sg:classifiers":[
        {
            "category":"Personal",
            "subcategory":"Beauty Salon",
            "type":"Services"
        }
    ],
    "sg:phone":"+1 251 661 6276",
    "sg:postcode":"36619",
    "sg:province":"AL",
    "sg:tags":[
        "shop"
    ],
    "wof:name":"By Cindy",
    "wof:placetype":"venue"
},
  "geometry": {"coordinates":[-88.194121,30.58729],"type":"Point"}
}