{
  "type": "Feature",
  "properties": {
    "iso:country":"US",
    "sg:address":"216 S 4th St",
    "sg:city":"Gadsden",
    "sg:classifiers":[
        {
            "category":"Wholesale",
            "subcategory":"Electrical",
            "type":"Manufacturing & Wholesale Goods"
        }
    ],
    "sg:phone":"+1 256 878 2510",
    "sg:postcode":"35901",
    "sg:province":"AL",
    "sg:tags":[
        "alarm",
        "burglar",
        "system"
    ],
    "sg:website":"www.telesystemsinc.net",
    "wof:name":"Tele-Systems Inc",
    "wof:placetype":"venue"
},
  "geometry": {"coordinates":[-86.004203,34.011124],"type":"Point"}
}