{
  "type": "Feature",
  "properties": {
    "iso:country":"US",
    "sg:address":"1016 20th St S",
    "sg:city":"Birmingham",
    "sg:classifiers":[
        {
            "category":"Bars & Pubs",
            "type":"Food & Drink"
        }
    ],
    "sg:phone":"+1 205 241 8000",
    "sg:postcode":"35205",
    "sg:province":"AL",
    "sg:tags":[
        "drinking"
    ],
    "wof:name":"Banana Joe's",
    "wof:placetype":"venue"
},
  "geometry": {"coordinates":[-86.796944,33.501466],"type":"Point"}
}