{
  "type": "Feature",
  "properties": {
    "addr:full":"105 Gossom Switch Rd Wetumpka AL 36092",
    "addr:housenumber":"105",
    "addr:postcode":"36092",
    "addr:street":"Gossom Switch Rd",
    "iso:country":"US",
    "sg:address":"105 Gossom Switch Rd",
    "sg:city":"Wetumpka",
    "sg:classifiers":[
        {
            "category":"Government",
            "subcategory":"Office",
            "type":"Public Place"
        }
    ],
    "sg:phone":"+1 334 567 2264",
    "sg:postcode":"36092",
    "sg:province":"AL",
    "sg:tags":[
        "use",
        "land",
        "commodity",
        "related",
        "program",
        "administers"
    ],
    "wof:name":"Farm Service Agency",
    "wof:placetype":"venue"
},
  "geometry": {"coordinates":[-86.226761,32.54169],"type":"Point"}
}