{
  "type": "Feature",
  "properties": {
    "iso:country":"US",
    "sg:address":"1558 Montgomery Hwy",
    "sg:city":"Dothan",
    "sg:classifiers":[
        {
            "category":"Manufacturing",
            "subcategory":"Glass & Minerals",
            "type":"Manufacturing & Wholesale Goods"
        }
    ],
    "sg:phone":"+1 334 793 7746",
    "sg:postcode":"36303",
    "sg:province":"AL",
    "sg:tags":[
        "product",
        "mfg"
    ],
    "wof:name":"A Touch of Glass",
    "wof:placetype":"venue"
},
  "geometry": {"coordinates":[-85.405011,31.239063],"type":"Point"}
}