{
  "type": "Feature",
  "properties": {
    "addr:full":"1535 Lille St Birmingham AL 35214",
    "addr:postcode":"1535;35214",
    "addr:street":"Lille St",
    "iso:country":"US",
    "sg:address":"1535 Lille St",
    "sg:city":"Birmingham",
    "sg:classifiers":[
        {
            "category":"Retail",
            "subcategory":"Veterinary Services",
            "type":"Services"
        }
    ],
    "sg:phone":"+1 205 798 8892",
    "sg:postcode":"35214",
    "sg:province":"AL",
    "wof:name":"Metro Animal Doctors",
    "wof:placetype":"venue"
},
  "geometry": {"coordinates":[-86.889431,33.571709],"type":"Point"}
}