{
  "type": "Feature",
  "properties": {
    "iso:country":"US",
    "sg:address":"2531 Bell Rd",
    "sg:city":"Montgomery",
    "sg:classifiers":[
        {
            "category":"Insurance",
            "subcategory":"Insurance Agent",
            "type":"Services"
        }
    ],
    "sg:phone":"+1 334 277 1109",
    "sg:postcode":"36117",
    "sg:province":"AL",
    "wof:name":"State Farm Insurance",
    "wof:placetype":"venue"
},
  "geometry": {"coordinates":[-86.19444900000001,32.344605],"type":"Point"}
}