{
  "type": "Feature",
  "properties": {
    "addr:full":"116 Washington St NE Huntsville AL 35801",
    "addr:housenumber":"116",
    "addr:postcode":"35801",
    "addr:street":"Washington St Ne",
    "iso:country":"US",
    "sg:address":"116 Washington St NE",
    "sg:city":"Huntsville",
    "sg:classifiers":[
        {
            "category":"Recreation",
            "type":"Entertainment"
        }
    ],
    "sg:phone":"+1 205 532 3914",
    "sg:postcode":"35801",
    "sg:province":"AL",
    "sg:tags":[
        "club",
        "membership"
    ],
    "wof:name":"Oxygen",
    "wof:placetype":"venue"
},
  "geometry": {"coordinates":[-86.586151,34.732464],"type":"Point"}
}