{
  "type": "Feature",
  "properties": {
    "iso:country":"US",
    "sg:address":"423 Main Ave",
    "sg:city":"Northport",
    "sg:classifiers":[
        {
            "category":"Home & Garden",
            "subcategory":"Household Appliances",
            "type":"Retail Goods"
        }
    ],
    "sg:phone":"+1 205 345 1660",
    "sg:postcode":"35476",
    "sg:province":"AL",
    "sg:tags":[
        "cleaners",
        "vacuum"
    ],
    "wof:name":"Rainbow West Alabama",
    "wof:placetype":"venue"
},
  "geometry": {"coordinates":[-87.57835,33.218746],"type":"Point"}
}