{
  "type": "Feature",
  "properties": {
    "iso:country":"US",
    "sg:address":"1930 Radcliff Rd",
    "sg:city":"Saraland",
    "sg:classifiers":[
        {
            "category":"Building & Trades",
            "subcategory":"Construction",
            "type":"Services"
        }
    ],
    "sg:phone":"+1 251 679 9196",
    "sg:postcode":"36571",
    "sg:province":"AL",
    "sg:tags":[
        "hanging",
        "contractor"
    ],
    "wof:name":"Jimmy Rodgers Paint Co Inc",
    "wof:placetype":"venue"
},
  "geometry": {"coordinates":[-88.124171,30.895398],"type":"Point"}
}