{
  "type": "Feature",
  "properties": {
    "iso:country":"US",
    "sg:address":"2900 Pinson Valley Pkwy",
    "sg:city":"Birmingham",
    "sg:classifiers":[
        {
            "category":"Food & Beverages",
            "subcategory":"Dairy",
            "type":"Retail Goods"
        }
    ],
    "sg:phone":"+1 205 849 8514",
    "sg:postcode":"35217",
    "sg:province":"AL",
    "sg:tags":[
        "product"
    ],
    "wof:name":"Dairy Fresh Milk & Ice Cream",
    "wof:placetype":"venue"
},
  "geometry": {"coordinates":[-86.738444,33.619228],"type":"Point"}
}