{
  "type": "Feature",
  "properties": {
    "iso:country":"US",
    "sg:address":"2220 Bessemer Rd",
    "sg:city":"Birmingham",
    "sg:classifiers":[
        {
            "category":"Building & Trades",
            "subcategory":"Construction",
            "type":"Services"
        }
    ],
    "sg:phone":"+1 205 786 6750",
    "sg:postcode":"35208",
    "sg:province":"AL",
    "sg:tags":[
        "contractor"
    ],
    "wof:name":"Domit Enterprise",
    "wof:placetype":"venue"
},
  "geometry": {"coordinates":[-86.878044,33.495925],"type":"Point"}
}