{
  "type": "Feature",
  "properties": {
    "iso:country":"US",
    "sg:address":"1007 Goodyear Ave",
    "sg:city":"Gadsden",
    "sg:classifiers":[
        {
            "category":"Health Services",
            "subcategory":"Doctor",
            "type":"Services"
        }
    ],
    "sg:phone":"+1 256 494 4033",
    "sg:postcode":"35903",
    "sg:province":"AL",
    "sg:tags":[
        "medical"
    ],
    "wof:name":"Imaging Specialists",
    "wof:placetype":"venue"
},
  "geometry": {"coordinates":[-85.971035,34.009362],"type":"Point"}
}