{
  "type": "Feature",
  "properties": {
    "iso:country":"US",
    "sg:address":"551 State Rte 30",
    "sg:city":"Eufaula",
    "sg:classifiers":[
        {
            "category":"Building & Trades",
            "subcategory":"Cleaning & Sanitation",
            "type":"Services"
        }
    ],
    "sg:phone":"+1 334 616 0482",
    "sg:postcode":"36027",
    "sg:province":"AL",
    "sg:tags":[
        "maintenance"
    ],
    "wof:name":"Sparkle & Shine Pressure Wshg",
    "wof:placetype":"venue"
},
  "geometry": {"coordinates":[-85.210064,31.869673],"type":"Point"}
}