{
  "type": "Feature",
  "properties": {
    "iso:country":"US",
    "sg:address":"3765 Government Blvd",
    "sg:city":"Mobile",
    "sg:classifiers":[
        {
            "category":"Professional",
            "subcategory":"Employment Agencies",
            "type":"Services"
        }
    ],
    "sg:phone":"+1 251 643 7070",
    "sg:postcode":"36693",
    "sg:province":"AL",
    "wof:name":"Bridge Staffing Inc",
    "wof:placetype":"venue"
},
  "geometry": {"coordinates":[-88.133853,30.642741],"type":"Point"}
}