{
  "type": "Feature",
  "properties": {
    "addr:full":"4491 US Hwy 80 Phenix City AL 36870",
    "addr:housenumber":"4491",
    "addr:postcode":"36870",
    "addr:street":"Us Hwy 80 Phenix City Al",
    "iso:country":"US",
    "sg:address":"4491 US Hwy 80",
    "sg:city":"Phenix City",
    "sg:classifiers":[
        {
            "category":"Autos & Motor Vehicles",
            "subcategory":"Auto Supplies",
            "type":"Retail Goods"
        }
    ],
    "sg:phone":"+1 334 298 3733",
    "sg:postcode":"36870",
    "sg:province":"AL",
    "sg:tags":[
        "wheel",
        "cover"
    ],
    "wof:name":"Wheels & Tracks",
    "wof:placetype":"venue"
},
  "geometry": {"coordinates":[-85.18792500000001,32.456714],"type":"Point"}
}