{
  "type": "Feature",
  "properties": {
    "iso:country":"US",
    "sg:address":"2320 Highland Ave S",
    "sg:city":"Birmingham",
    "sg:classifiers":[
        {
            "category":"Professional",
            "subcategory":"Accounting & Tax Preparation",
            "type":"Services"
        }
    ],
    "sg:phone":"+1 205 933 6855",
    "sg:postcode":"35205",
    "sg:province":"AL",
    "wof:name":"Browder & Associates PC",
    "wof:placetype":"venue"
},
  "geometry": {"coordinates":[-86.78851299999999,33.50297],"type":"Point"}
}