{
  "type": "Feature",
  "properties": {
    "iso:country":"US",
    "sg:address":"800 Wellman Ave NE",
    "sg:city":"Huntsville",
    "sg:classifiers":[
        {
            "category":"Restaurant",
            "type":"Food & Drink"
        }
    ],
    "sg:phone":"+1 256 534 0122",
    "sg:postcode":"35801",
    "sg:province":"AL",
    "sg:tags":[
        "eating"
    ],
    "wof:name":"Thai Garden Restaurant Inc",
    "wof:placetype":"venue"
},
  "geometry": {"coordinates":[-86.574267,34.737667],"type":"Point"}
}