{
  "type": "Feature",
  "properties": {
    "addr:full":"749 N Court St Montgomery AL 36104",
    "addr:housenumber":"749",
    "addr:postcode":"36104",
    "addr:street":"N Court",
    "iso:country":"US",
    "sg:address":"749 N Court St",
    "sg:city":"Montgomery",
    "sg:classifiers":[
        {
            "category":"Wholesale",
            "subcategory":"Scrap",
            "type":"Manufacturing & Wholesale Goods"
        }
    ],
    "sg:phone":"+1 334 265 6771",
    "sg:postcode":"36104",
    "sg:province":"AL",
    "sg:tags":[
        "metal",
        "iron"
    ],
    "wof:name":"Sabel Industries Inc",
    "wof:placetype":"venue"
},
  "geometry": {"coordinates":[-86.309318,32.387032],"type":"Point"}
}