{
  "type": "Feature",
  "properties": {
    "addr:full":"2880 Dauphin St Mobile AL 36606",
    "addr:housenumber":"2880",
    "addr:postcode":"36606",
    "addr:street":"Dauphin St",
    "iso:country":"US",
    "sg:address":"2880 Dauphin St",
    "sg:city":"Mobile",
    "sg:classifiers":[
        {
            "category":"Health Services",
            "subcategory":"Doctor",
            "type":"Services"
        },
        {
            "category":"Health Services",
            "subcategory":"Optometrist",
            "type":"Services"
        },
        {
            "category":"Wholesale",
            "subcategory":"Medical Equipment & Supplies",
            "type":"Manufacturing & Wholesale Goods"
        },
        {
            "category":"Health Services",
            "subcategory":"Health Practitioner",
            "type":"Services"
        },
        {
            "category":"Shopping",
            "subcategory":"Optician",
            "type":"Retail Goods"
        }
    ],
    "sg:phone":"+1 251 473 1900",
    "sg:postcode":"36606",
    "sg:province":"AL",
    "sg:tags":[
        "plastic",
        "optometry",
        "audiologists",
        "immunology",
        "physician",
        "reconstructive",
        "allergy",
        "surgeons",
        "hearing",
        "otorhinolaryngology",
        "assistive",
        "ophthalmology",
        "optical",
        "device",
        "nose",
        "optometrists-od-pediatric",
        "throat",
        "aid",
        "surgeon",
        "ear"
    ],
    "sg:website":"http://pmg.md",
    "wof:name":"Premier Medical Group",
    "wof:placetype":"venue"
},
  "geometry": {"coordinates":[-88.111261,30.689],"type":"Point"}
}