{
  "type": "Feature",
  "properties": {
    "iso:country":"US",
    "sg:address":"6966 US Hwy 431",
    "sg:city":"Owens Cross Roads",
    "sg:classifiers":[
        {
            "category":"Restaurant",
            "type":"Food & Drink"
        }
    ],
    "sg:phone":"+1 256 539 6477",
    "sg:postcode":"35763",
    "sg:province":"AL",
    "sg:tags":[
        "eating"
    ],
    "wof:name":"El Olmeze Restaurant",
    "wof:placetype":"venue"
},
  "geometry": {"coordinates":[-86.477835,34.648809],"type":"Point"}
}