{
  "type": "Feature",
  "properties": {
    "iso:country":"US",
    "sg:address":"4032 Parkway Dr",
    "sg:city":"Florence",
    "sg:classifiers":[
        {
            "category":"Manufacturing",
            "subcategory":"Wood Products",
            "type":"Manufacturing & Wholesale Goods"
        }
    ],
    "sg:phone":"+1 256 764 4613",
    "sg:postcode":"35630",
    "sg:province":"AL",
    "sg:tags":[
        "item",
        "craft",
        "from",
        "mfg"
    ],
    "wof:name":"Fiberex",
    "wof:placetype":"venue"
},
  "geometry": {"coordinates":[-87.65639299999999,34.860053],"type":"Point"}
}