{
  "type": "Feature",
  "properties": {
    "addr:full":"5109 Overlook Rd Mobile AL 36618",
    "addr:housenumber":"5109",
    "addr:postcode":"36618",
    "addr:street":"Overlook Rd",
    "iso:country":"US",
    "sg:address":"5109 Overlook Rd",
    "sg:city":"Mobile",
    "sg:classifiers":[
        {
            "category":"Social Services",
            "subcategory":"Child Care",
            "type":"Services"
        }
    ],
    "sg:phone":"+1 251 342 9025",
    "sg:postcode":"36618",
    "sg:province":"AL",
    "sg:tags":[
        "day"
    ],
    "wof:name":"Overlook Kiddie Kare Inc",
    "wof:placetype":"venue"
},
  "geometry": {"coordinates":[-88.161804,30.719551],"type":"Point"}
}