{
  "type": "Feature",
  "properties": {
    "addr:full":"1901 Melba Dr Dothan AL 36301",
    "addr:housenumber":"1901",
    "addr:postcode":"36301",
    "addr:street":"Melba Dr",
    "iso:country":"US",
    "sg:address":"1901 Melba Dr",
    "sg:city":"Dothan",
    "sg:classifiers":[
        {
            "category":"Health Services",
            "subcategory":"Doctor",
            "type":"Services"
        }
    ],
    "sg:phone":"+1 334 794 6611",
    "sg:postcode":"36301",
    "sg:province":"AL",
    "sg:tags":[
        "physician",
        "surgeon"
    ],
    "wof:name":"Southern Clinic PC",
    "wof:placetype":"venue"
},
  "geometry": {"coordinates":[-85.36486600000001,31.2148],"type":"Point"}
}