{
  "type": "Feature",
  "properties": {
    "addr:full":"6601 Wellborne Dr S Mobile AL 36695",
    "addr:housenumber":"6601",
    "addr:postcode":"36695",
    "addr:street":"Wellborne Dr S",
    "iso:country":"US",
    "sg:address":"6601 Wellborne Dr S",
    "sg:city":"Mobile",
    "sg:classifiers":[
        {
            "category":"Food & Beverages",
            "subcategory":"Groceries & Convenience Stores",
            "type":"Retail Goods"
        }
    ],
    "sg:phone":"+1 251 479 2445",
    "sg:postcode":"36695",
    "sg:province":"AL",
    "wof:name":"Stop Super 3",
    "wof:placetype":"venue"
},
  "geometry": {"coordinates":[-88.196118,30.621905],"type":"Point"}
}