{
  "type": "Feature",
  "properties": {
    "iso:country":"US",
    "sg:address":"3995 Cottage Hill Rd",
    "sg:city":"Mobile",
    "sg:classifiers":[
        {
            "category":"Farming",
            "subcategory":"Livestock Farm",
            "type":"Manufacturing & Wholesale Goods"
        }
    ],
    "sg:phone":"+1 251 660 7766",
    "sg:postcode":"36609",
    "sg:province":"AL",
    "sg:tags":[
        "animal",
        "general"
    ],
    "wof:name":"Pelican Oaks Ranch LLC",
    "wof:placetype":"venue"
},
  "geometry": {"coordinates":[-88.139854,30.653039],"type":"Point"}
}