{
  "type": "Feature",
  "properties": {
    "addr:full":"717 State Rte 67 Decatur AL 35603",
    "addr:housenumber":"717",
    "addr:postcode":"35603",
    "addr:street":"State Rte 67",
    "iso:country":"US",
    "sg:address":"717 State Rte 67",
    "sg:city":"Decatur",
    "sg:classifiers":[
        {
            "category":"Restaurant",
            "type":"Food & Drink"
        }
    ],
    "sg:phone":"+1 256 353 2242",
    "sg:postcode":"35603",
    "sg:province":"AL",
    "sg:tags":[
        "eating"
    ],
    "wof:name":"Los Charros Mexican Resturant",
    "wof:placetype":"venue"
},
  "geometry": {"coordinates":[-86.887533,34.519704],"type":"Point"}
}