{
  "type": "Feature",
  "properties": {
    "iso:country":"US",
    "sg:address":"195 Blake Dr",
    "sg:city":"Double Springs",
    "sg:classifiers":[
        {
            "category":"Social Services",
            "type":"Services"
        }
    ],
    "sg:phone":"+1 205 489 2251",
    "sg:postcode":"35553",
    "sg:province":"AL",
    "sg:tags":[
        "probation"
    ],
    "wof:name":"Juvenile Probation Office",
    "wof:placetype":"venue"
},
  "geometry": {"coordinates":[-87.398648,34.146208],"type":"Point"}
}