{
  "type": "Feature",
  "properties": {
    "iso:country":"US",
    "sg:address":"5414 Trace Ridge Ln",
    "sg:city":"Birmingham",
    "sg:classifiers":[
        {
            "category":"Personal",
            "subcategory":"Beauty Salon",
            "type":"Services"
        }
    ],
    "sg:phone":"+1 205 982 2828",
    "sg:postcode":"35244",
    "sg:province":"AL",
    "sg:tags":[
        "shop"
    ],
    "wof:name":"Event Solutions of Alabama",
    "wof:placetype":"venue"
},
  "geometry": {"coordinates":[-86.831889,33.356126],"type":"Point"}
}