{
  "type": "Feature",
  "properties": {
    "iso:country":"US",
    "sg:address":"2709 Spring Hill Ave",
    "sg:city":"Mobile",
    "sg:classifiers":[
        {
            "category":"Wholesale",
            "subcategory":"Seafood",
            "type":"Manufacturing & Wholesale Goods"
        }
    ],
    "sg:phone":"+1 251 478 2868",
    "sg:postcode":"36607",
    "sg:province":"AL",
    "wof:name":"Springhill Seafood",
    "wof:placetype":"venue"
},
  "geometry": {"coordinates":[-88.10370899999999,30.696761],"type":"Point"}
}