{
  "type": "Feature",
  "properties": {
    "iso:country":"US",
    "sg:address":"12021 Memorial Pkwy SW",
    "sg:city":"Huntsville",
    "sg:classifiers":[
        {
            "category":"Health Services",
            "subcategory":"Medical Lab",
            "type":"Services"
        }
    ],
    "sg:phone":"+1 256 882 1701",
    "sg:postcode":"35803",
    "sg:province":"AL",
    "sg:tags":[
        "laboratory",
        "dental"
    ],
    "wof:name":"Key Dental Laboratory",
    "wof:placetype":"venue"
},
  "geometry": {"coordinates":[-86.56608,34.610758],"type":"Point"}
}