{
  "type": "Feature",
  "properties": {
    "addr:full":"4503 Norris Mill Rd SW Decatur AL 35603",
    "addr:housenumber":"4503",
    "addr:postcode":"35603",
    "addr:street":"Norris Mill Rd Sw",
    "iso:country":"US",
    "sg:address":"4503 Norris Mill Rd SW",
    "sg:city":"Decatur",
    "sg:classifiers":[
        {
            "category":"Building & Trades",
            "subcategory":"Plumbing",
            "type":"Services"
        }
    ],
    "sg:phone":"+1 256 350 5545",
    "sg:postcode":"35603",
    "sg:province":"AL",
    "sg:tags":[
        "conditioning",
        "air",
        "system",
        "contractor"
    ],
    "wof:name":"Bill Hall Heating & Air Cond",
    "wof:placetype":"venue"
},
  "geometry": {"coordinates":[-86.98308,34.52105],"type":"Point"}
}