{
  "type": "Feature",
  "properties": {
    "addr:full":"516 35th St N Birmingham AL 35222",
    "addr:housenumber":"516",
    "addr:postcode":"35222",
    "addr:street":"35Th St N",
    "iso:country":"US",
    "sg:address":"516 35th St N",
    "sg:city":"Birmingham",
    "sg:classifiers":[
        {
            "category":"Freight",
            "type":"Transportation"
        },
        {
            "category":"Building & Trades",
            "subcategory":"Plumbing",
            "type":"Services"
        }
    ],
    "sg:phone":"+1 205 324 8808",
    "sg:postcode":"35222",
    "sg:province":"AL",
    "sg:tags":[
        "delivery",
        "contractor"
    ],
    "wof:name":"America 1 Air Delivery Inc",
    "wof:placetype":"venue"
},
  "geometry": {"coordinates":[-86.786484,33.531203],"type":"Point"}
}