{
  "type": "Feature",
  "properties": {
    "addr:full":"900 Skyland Blvd E Tuscaloosa AL 35405",
    "addr:housenumber":"900",
    "addr:postcode":"35405",
    "addr:street":"Skyland Blvd E",
    "iso:country":"US",
    "sg:address":"900 Skyland Blvd E",
    "sg:city":"Tuscaloosa",
    "sg:classifiers":[
        {
            "category":"Shopping",
            "subcategory":"Clothing, Apparel, & Fashions",
            "type":"Retail Goods"
        }
    ],
    "sg:phone":"+1 205 345 3514",
    "sg:postcode":"35405",
    "sg:province":"AL",
    "sg:tags":[
        "wear"
    ],
    "wof:name":"Kidz Fashion",
    "wof:placetype":"venue"
},
  "geometry": {"coordinates":[-87.52233099999999,33.168237],"type":"Point"}
}