{
  "type": "Feature",
  "properties": {
    "iso:country":"US",
    "sg:address":"19416 River Landing Rd",
    "sg:city":"Seminole",
    "sg:classifiers":[
        {
            "category":"Health Services",
            "subcategory":"Medical Lab",
            "type":"Services"
        }
    ],
    "sg:phone":"+1 251 946 3221",
    "sg:postcode":"36574",
    "sg:province":"AL",
    "sg:tags":[
        "laboratory",
        "dental"
    ],
    "wof:name":"Coastal Dental Ceramics",
    "wof:placetype":"venue"
},
  "geometry": {"coordinates":[-87.447359,30.508097],"type":"Point"}
}