{
  "type": "Feature",
  "properties": {
    "addr:full":"205 Millstone Ln Madison AL 35758",
    "addr:housenumber":"205",
    "addr:postcode":"35758",
    "addr:street":"Millstone Ln",
    "iso:country":"US",
    "sg:address":"205 Millstone Ln",
    "sg:city":"Madison",
    "sg:classifiers":[
        {
            "category":"Utilities",
            "subcategory":"Telephone",
            "type":"Services"
        }
    ],
    "sg:phone":"+1 256 772 5717",
    "sg:postcode":"35758",
    "sg:province":"AL",
    "sg:tags":[
        "motion",
        "communications"
    ],
    "wof:name":"Visible Pulse",
    "wof:placetype":"venue"
},
  "geometry": {"coordinates":[-86.736983,34.710102],"type":"Point"}
}