{
  "type": "Feature",
  "properties": {
    "iso:country":"US",
    "sg:address":"2910 Morgan Rd",
    "sg:city":"Bessemer",
    "sg:classifiers":[
        {
            "category":"Cinema",
            "subcategory":"Movie Rental",
            "type":"Entertainment"
        }
    ],
    "sg:phone":"+1 205 424 1191",
    "sg:postcode":"35022",
    "sg:province":"AL",
    "sg:tags":[
        "game",
        "rent"
    ],
    "wof:name":"Movie Gallery",
    "wof:placetype":"venue"
},
  "geometry": {"coordinates":[-86.917626,33.336979],"type":"Point"}
}