{
  "type": "Feature",
  "properties": {
    "iso:country":"US",
    "sg:address":"1011 W Fort Williams St",
    "sg:city":"Sylacauga",
    "sg:classifiers":[
        {
            "category":"Insurance",
            "subcategory":"Insurance Agent",
            "type":"Services"
        }
    ],
    "sg:phone":"+1 256 245 4392",
    "sg:postcode":"35150",
    "sg:province":"AL",
    "wof:name":"Alfa Insurance Corp",
    "wof:placetype":"venue"
},
  "geometry": {"coordinates":[-86.266533,33.167293],"type":"Point"}
}