{
  "type": "Feature",
  "properties": {
    "iso:country":"US",
    "sg:address":"1600 Lee Boy Rd",
    "sg:city":"Newton",
    "sg:classifiers":[
        {
            "category":"Professional",
            "subcategory":"Computer Services",
            "type":"Services"
        }
    ],
    "sg:phone":"+1 334 692 5079",
    "sg:postcode":"36352",
    "sg:province":"AL",
    "sg:tags":[
        "datum"
    ],
    "wof:name":"Firepoint Productions",
    "wof:placetype":"venue"
},
  "geometry": {"coordinates":[-85.624397,31.257938],"type":"Point"}
}