{
  "type": "Feature",
  "properties": {
    "iso:country":"US",
    "sg:address":"602 Pelham Rd S",
    "sg:city":"Jacksonville",
    "sg:classifiers":[
        {
            "category":"Restaurant",
            "type":"Food & Drink"
        }
    ],
    "sg:phone":"+1 256 435 1450",
    "sg:postcode":"36265",
    "sg:province":"AL",
    "wof:name":"Taco Bell",
    "wof:placetype":"venue"
},
  "geometry": {"coordinates":[-85.761218,33.799767],"type":"Point"}
}