{
  "type": "Feature",
  "properties": {
    "iso:country":"US",
    "sg:address":"2519 Main St",
    "sg:city":"Daphne",
    "sg:classifiers":[
        {
            "category":"Professional",
            "subcategory":"Management & Consulting",
            "type":"Services"
        }
    ],
    "sg:phone":"+1 251 626 2856",
    "sg:postcode":"36526",
    "sg:province":"AL",
    "wof:name":"Lott Family Management Inc",
    "wof:placetype":"venue"
},
  "geometry": {"coordinates":[-87.907768,30.617601],"type":"Point"}
}