{
  "type": "Feature",
  "properties": {
    "iso:country":"US",
    "sg:address":"513 Regent Dr",
    "sg:city":"Alabaster",
    "sg:classifiers":[
        {
            "category":"Retail",
            "subcategory":"Repair Shop",
            "type":"Services"
        },
        {
            "category":"Wholesale",
            "subcategory":"Furniture",
            "type":"Manufacturing & Wholesale Goods"
        }
    ],
    "sg:phone":"+1 205 664 5719",
    "sg:postcode":"35007",
    "sg:province":"AL",
    "sg:tags":[
        "installs",
        "commercial",
        "cabinet"
    ],
    "wof:name":"GNI Installations Inc",
    "wof:placetype":"venue"
},
  "geometry": {"coordinates":[-86.803844,33.241805],"type":"Point"}
}