{
  "type": "Feature",
  "properties": {
    "addr:full":"229 1st Ave E Oneonta AL 35121",
    "addr:housenumber":"229",
    "addr:postcode":"35121",
    "addr:street":"1St Ave E",
    "iso:country":"US",
    "sg:address":"229 1st Ave E",
    "sg:city":"Oneonta",
    "sg:classifiers":[
        {
            "category":"Shopping",
            "subcategory":"Gifts & Souvenirs",
            "type":"Retail Goods"
        }
    ],
    "sg:phone":"+1 205 625 6598",
    "sg:postcode":"35121",
    "sg:province":"AL",
    "sg:tags":[
        "shop"
    ],
    "wof:name":"Touch Of Country",
    "wof:placetype":"venue"
},
  "geometry": {"coordinates":[-86.47499500000001,33.945459],"type":"Point"}
}