{
  "type": "Feature",
  "properties": {
    "iso:country":"US",
    "sg:address":"2981 Grants Mill Rd",
    "sg:city":"Leeds",
    "sg:classifiers":[
        {
            "category":"Wholesale",
            "subcategory":"Non-durable Goods",
            "type":"Manufacturing & Wholesale Goods"
        }
    ],
    "sg:phone":"+1 205 956 7158",
    "sg:postcode":"35094",
    "sg:province":"AL",
    "sg:tags":[
        "tropical",
        "fish"
    ],
    "wof:name":"Blue Springs Hatchery",
    "wof:placetype":"venue"
},
  "geometry": {"coordinates":[-86.64089,33.48826],"type":"Point"}
}