{
  "type": "Feature",
  "properties": {
    "addr:full":"5652 Crestwood Blvd Birmingham AL 35212",
    "addr:housenumber":"5652",
    "addr:postcode":"35212",
    "addr:street":"Crestwood Blvd",
    "iso:country":"US",
    "sg:address":"5652 Crestwood Blvd",
    "sg:city":"Birmingham",
    "sg:classifiers":[
        {
            "category":"Personal",
            "type":"Services"
        }
    ],
    "sg:phone":"+1 205 599 3338",
    "sg:postcode":"35212",
    "sg:province":"AL",
    "wof:name":"Trott & Company",
    "wof:placetype":"venue"
},
  "geometry": {"coordinates":[-86.74482500000001,33.529614],"type":"Point"}
}