{
  "type": "Feature",
  "properties": {
    "iso:country":"US",
    "sg:address":"7656 US Hwy 231",
    "sg:city":"Wetumpka",
    "sg:classifiers":[
        {
            "category":"Shopping",
            "subcategory":"Bicycles & Sporting Goods",
            "type":"Retail Goods"
        }
    ],
    "sg:phone":"+1 334 567 7092",
    "sg:postcode":"36092",
    "sg:province":"AL",
    "wof:name":"Wetumpka Fish & Game",
    "wof:placetype":"venue"
},
  "geometry": {"coordinates":[-86.19004700000001,32.547827],"type":"Point"}
}