{
  "type": "Feature",
  "properties": {
    "iso:country":"US",
    "sg:address":"557 W Main St",
    "sg:city":"Dothan",
    "sg:classifiers":[
        {
            "category":"Shopping",
            "subcategory":"Used Merchandise",
            "type":"Retail Goods"
        }
    ],
    "sg:phone":"+1 334 702 4712",
    "sg:postcode":"36301",
    "sg:province":"AL",
    "wof:name":"CSS Thrift Store",
    "wof:placetype":"venue"
},
  "geometry": {"coordinates":[-85.399079,31.224852],"type":"Point"}
}