{
  "type": "Feature",
  "properties": {
    "iso:country":"US",
    "sg:address":"966 US Hwy 231",
    "sg:city":"Wetumpka",
    "sg:classifiers":[
        {
            "category":"Wholesale",
            "subcategory":"Toys & Hobbies",
            "type":"Manufacturing & Wholesale Goods"
        },
        {
            "category":"Restaurant",
            "type":"Food & Drink"
        }
    ],
    "sg:phone":"+1 334 514 4928",
    "sg:postcode":"36093",
    "sg:province":"AL",
    "sg:tags":[
        "firework",
        "eating",
        "merchandise"
    ],
    "wof:name":"Big Daddy's Fireworks",
    "wof:placetype":"venue"
},
  "geometry": {"coordinates":[-86.190423,32.465218],"type":"Point"}
}