{
  "type": "Feature",
  "properties": {
    "addr:full":"108 Hickory Point Dr Helena AL 35080",
    "addr:housenumber":"108",
    "addr:postcode":"35080",
    "addr:street":"Hickory Point Dr",
    "iso:country":"US",
    "sg:address":"108 Hickory Point Dr",
    "sg:city":"Helena",
    "sg:classifiers":[
        {
            "category":"Building & Trades",
            "subcategory":"Landscaping Services",
            "type":"Services"
        }
    ],
    "sg:phone":"+1 205 621 0448",
    "sg:postcode":"35080",
    "sg:province":"AL",
    "wof:name":"Prime Landscape Services LLC",
    "wof:placetype":"venue"
},
  "geometry": {"coordinates":[-86.840104,33.270992],"type":"Point"}
}