{
  "type": "Feature",
  "properties": {
    "iso:country":"US",
    "sg:address":"720 39th St S",
    "sg:city":"Birmingham",
    "sg:classifiers":[
        {
            "category":"Professional",
            "subcategory":"Art Services",
            "type":"Services"
        }
    ],
    "sg:phone":"+1 205 978 1726",
    "sg:postcode":"35222",
    "sg:province":"AL",
    "sg:tags":[
        "photographer"
    ],
    "wof:name":"Big Swede Production Inc",
    "wof:placetype":"venue"
},
  "geometry": {"coordinates":[-86.774045,33.51662],"type":"Point"}
}