{
  "type": "Feature",
  "properties": {
    "iso:country":"US",
    "sg:address":"2366 White St",
    "sg:city":"Mobile",
    "sg:classifiers":[
        {
            "category":"Building & Trades",
            "subcategory":"Construction",
            "type":"Services"
        }
    ],
    "sg:phone":"+1 251 471 1698",
    "sg:postcode":"36605",
    "sg:province":"AL",
    "sg:tags":[
        "contractor"
    ],
    "wof:name":"Acme Insulators",
    "wof:placetype":"venue"
},
  "geometry": {"coordinates":[-88.101784,30.641405],"type":"Point"}
}