{
  "type": "Feature",
  "properties": {
    "iso:country":"US",
    "sg:address":"1627 Opelika Rd",
    "sg:city":"Auburn",
    "sg:classifiers":[
        {
            "category":"Professional",
            "subcategory":"Detective & Security Services",
            "type":"Services"
        }
    ],
    "sg:phone":"+1 334 466 0940",
    "sg:postcode":"36830",
    "sg:province":"AL",
    "sg:tags":[
        "car",
        "guard",
        "patrol"
    ],
    "wof:name":"Control Security Service Inc",
    "wof:placetype":"venue"
},
  "geometry": {"coordinates":[-85.447875,32.624182],"type":"Point"}
}