{
  "type": "Feature",
  "properties": {
    "iso:country":"US",
    "sg:address":"11437 Memorial Pkwy SW",
    "sg:city":"Huntsville",
    "sg:classifiers":[
        {
            "category":"Restaurant",
            "type":"Food & Drink"
        }
    ],
    "sg:menulink":"http://www.allmenus.com/al/huntsville/55639-subway/menu/",
    "sg:phone":"+1 256 881 8006",
    "sg:postcode":"35803",
    "sg:province":"AL",
    "sg:tags":[
        "american",
        "sandwich"
    ],
    "wof:name":"Subway",
    "wof:placetype":"venue"
},
  "geometry": {"coordinates":[-86.566855,34.62934],"type":"Point"}
}