{
  "type": "Feature",
  "properties": {
    "addr:full":"1605 AL-21 Monroeville AL 36460",
    "addr:housenumber":"1605",
    "addr:postcode":"36460",
    "addr:street":"Al-21",
    "iso:country":"US",
    "sg:address":"1605 AL-21",
    "sg:city":"Monroeville",
    "sg:classifiers":[
        {
            "category":"Restaurant",
            "type":"Food & Drink"
        }
    ],
    "sg:menulink":"http://www.allmenus.com/al/monroeville/72777-pizza-hut/menu/",
    "sg:phone":"+1 251 575 2088",
    "sg:postcode":"36460",
    "sg:province":"AL",
    "sg:tags":[
        "american",
        "pizza"
    ],
    "wof:name":"Pizza Hut",
    "wof:placetype":"venue"
},
  "geometry": {"coordinates":[-87.307832,31.541717],"type":"Point"}
}