{
  "type": "Feature",
  "properties": {
    "addr:full":"24711 Co Rd 20 Elberta AL 36530",
    "addr:housenumber":"24711;20",
    "addr:postcode":"36530",
    "addr:street":"Co Rd",
    "iso:country":"US",
    "sg:address":"24711 Co Rd 20",
    "sg:city":"Elberta",
    "sg:classifiers":[
        {
            "category":"Travel",
            "subcategory":"Campground",
            "type":"Entertainment"
        }
    ],
    "sg:phone":"+1 251 987 5131",
    "sg:postcode":"36530",
    "sg:province":"AL",
    "sg:tags":[
        "trailer"
    ],
    "wof:name":"Wolf Bay Plantations Inc",
    "wof:placetype":"venue"
},
  "geometry": {"coordinates":[-87.603278,30.370407],"type":"Point"}
}