{
  "type": "Feature",
  "properties": {
    "iso:country":"US",
    "sg:address":"34 S Monterey St",
    "sg:city":"Mobile",
    "sg:classifiers":[
        {
            "category":"Professional",
            "subcategory":"Business Services",
            "type":"Services"
        }
    ],
    "sg:phone":"+1 251 473 6328",
    "sg:postcode":"36604",
    "sg:province":"AL",
    "wof:name":"Tam Williams Design Inc",
    "wof:placetype":"venue"
},
  "geometry": {"coordinates":[-88.076868,30.686091],"type":"Point"}
}