{
  "type": "Feature",
  "properties": {
    "iso:country":"US",
    "sg:address":"124 Chapel Rd",
    "sg:city":"Wetumpka",
    "sg:classifiers":[
        {
            "category":"Education",
            "subcategory":"School",
            "type":"Public Place"
        }
    ],
    "sg:phone":"+1 334 567 1215",
    "sg:postcode":"36092",
    "sg:province":"AL",
    "wof:name":"It",
    "wof:placetype":"venue"
},
  "geometry": {"coordinates":[-86.225627,32.548852],"type":"Point"}
}