{
  "type": "Feature",
  "properties": {
    "iso:country":"US",
    "sg:address":"3119 Wesley Way",
    "sg:city":"Dothan",
    "sg:classifiers":[
        {
            "category":"Personal",
            "subcategory":"Beauty Salon",
            "type":"Services"
        }
    ],
    "sg:phone":"+1 334 671 7797",
    "sg:postcode":"36305",
    "sg:province":"AL",
    "sg:tags":[
        "shop"
    ],
    "wof:name":"Upper Cuts",
    "wof:placetype":"venue"
},
  "geometry": {"coordinates":[-85.432315,31.221111],"type":"Point"}
}