{
  "type": "Feature",
  "properties": {
    "addr:full":"306 Dekalb St Marion AL 36756",
    "addr:housenumber":"306",
    "addr:postcode":"36756",
    "addr:street":"Dekalb St",
    "iso:country":"US",
    "sg:address":"306 Dekalb St",
    "sg:city":"Marion",
    "sg:classifiers":[
        {
            "category":"Education",
            "subcategory":"Library",
            "type":"Public Place"
        }
    ],
    "sg:phone":"+1 334 683 5182",
    "sg:postcode":"36756",
    "sg:province":"AL",
    "wof:name":"Bowling Library Judson",
    "wof:placetype":"venue"
},
  "geometry": {"coordinates":[-87.324817,32.631064],"type":"Point"}
}