{
  "type": "Feature",
  "properties": {
    "iso:country":"US",
    "sg:address":"408 E Laurel St",
    "sg:city":"Scottsboro",
    "sg:classifiers":[
        {
            "category":"Banks & Credit Unions",
            "subcategory":"Bank",
            "type":"Services"
        }
    ],
    "sg:phone":"+1 256 259 1999",
    "sg:postcode":"35768",
    "sg:province":"AL",
    "wof:name":"North Jackson Bank",
    "wof:placetype":"venue"
},
  "geometry": {"coordinates":[-86.030382,34.672731],"type":"Point"}
}