{
  "type": "Feature",
  "properties": {
    "addr:full":"305 Seminole Dr SW Huntsville AL 35805",
    "addr:housenumber":"305",
    "addr:postcode":"35805",
    "addr:street":"Seminole Dr Sw",
    "iso:country":"US",
    "sg:address":"305 Seminole Dr SW",
    "sg:city":"Huntsville",
    "sg:classifiers":[
        {
            "category":"Organizations",
            "subcategory":"Religious Organization",
            "type":"Services"
        }
    ],
    "sg:phone":"+1 256 534 1402",
    "sg:postcode":"35805",
    "sg:province":"AL",
    "sg:tags":[
        "church"
    ],
    "wof:name":"Salvation Army",
    "wof:placetype":"venue"
},
  "geometry": {"coordinates":[-86.597893,34.721209],"type":"Point"}
}