{
  "type": "Feature",
  "properties": {
    "addr:full":"10419 Padgett Switch Rd Irvington AL 36544",
    "addr:housenumber":"10419",
    "addr:postcode":"36544",
    "addr:street":"Padgett Switch Rd",
    "iso:country":"US",
    "sg:address":"10419 Padgett Switch Rd",
    "sg:city":"Irvington",
    "sg:classifiers":[
        {
            "category":"Building & Trades",
            "subcategory":"Landscaping Services",
            "type":"Services"
        }
    ],
    "sg:phone":"+1 251 957 3098",
    "sg:postcode":"36544",
    "sg:province":"AL",
    "wof:name":"Louie Landscaper",
    "wof:placetype":"venue"
},
  "geometry": {"coordinates":[-88.21699,30.487382],"type":"Point"}
}