{
  "type": "Feature",
  "properties": {
    "iso:country":"US",
    "sg:address":"3820 Valley Ford Rd",
    "sg:city":"Adger",
    "sg:classifiers":[
        {
            "category":"Wholesale",
            "subcategory":"Electrical",
            "type":"Manufacturing & Wholesale Goods"
        }
    ],
    "sg:phone":"+1 205 428 2447",
    "sg:postcode":"35006",
    "sg:province":"AL",
    "sg:tags":[
        "alarm",
        "burglar",
        "system"
    ],
    "wof:name":"Bhips Alarm Svc",
    "wof:placetype":"venue"
},
  "geometry": {"coordinates":[-87.091457,33.390548],"type":"Point"}
}