{
  "type": "Feature",
  "properties": {
    "addr:full":"2901 2nd Ave S Birmingham AL 35233",
    "addr:housenumber":"2901",
    "addr:postcode":"35233",
    "addr:street":"2Nd Ave S",
    "iso:country":"US",
    "sg:address":"2901 2nd Ave S",
    "sg:city":"Birmingham",
    "sg:phone":"+1 205 323 0047",
    "sg:postcode":"35233",
    "sg:province":"AL",
    "wof:name":"Amani Raha",
    "wof:placetype":"venue"
},
  "geometry": {"coordinates":[-86.790916,33.516762],"type":"Point"}
}