{
  "type": "Feature",
  "properties": {
    "addr:full":"646 Scottsville Rd Brent AL 35034",
    "addr:housenumber":"646",
    "addr:postcode":"35034",
    "addr:street":"Scottsville Rd",
    "iso:country":"US",
    "sg:address":"646 Scottsville Rd",
    "sg:city":"Brent",
    "sg:classifiers":[
        {
            "category":"Organizations",
            "subcategory":"Religious Organization",
            "type":"Services"
        }
    ],
    "sg:phone":"+1 205 926 5009",
    "sg:postcode":"35034",
    "sg:province":"AL",
    "wof:name":"Real Truth Holiness Church",
    "wof:placetype":"venue"
},
  "geometry": {"coordinates":[-87.17090899999999,32.938561],"type":"Point"}
}