{
  "type": "Feature",
  "properties": {
    "iso:country":"US",
    "sg:address":"5320 Lansdowne Dr",
    "sg:city":"Mobile",
    "sg:classifiers":[
        {
            "category":"Organizations",
            "subcategory":"Religious Organization",
            "type":"Services"
        }
    ],
    "sg:phone":"+1 251 661 5253",
    "sg:postcode":"36693",
    "sg:province":"AL",
    "wof:name":"Saint Luis Mssnary Bptst Chrch",
    "wof:placetype":"venue"
},
  "geometry": {"coordinates":[-88.164941,30.612001],"type":"Point"}
}