{
  "type": "Feature",
  "properties": {
    "iso:country":"US",
    "sg:address":"103 W 3rd St",
    "sg:city":"Sylacauga",
    "sg:classifiers":[
        {
            "category":"Shopping",
            "subcategory":"Jewelry",
            "type":"Retail Goods"
        }
    ],
    "sg:phone":"+1 256 245 2157",
    "sg:postcode":"35150",
    "sg:province":"AL",
    "sg:tags":[
        "jeweler"
    ],
    "wof:name":"Stacey's Jewelry",
    "wof:placetype":"venue"
},
  "geometry": {"coordinates":[-86.252241,33.171515],"type":"Point"}
}