{
  "type": "Feature",
  "properties": {
    "iso:country":"US",
    "sg:address":"112 N Main St",
    "sg:city":"Boaz",
    "sg:classifiers":[
        {
            "category":"Home & Garden",
            "subcategory":"Hardware",
            "type":"Retail Goods"
        }
    ],
    "sg:phone":"+1 256 593 5812",
    "sg:postcode":"35957",
    "sg:province":"AL",
    "wof:name":"Hunt & Wright Hardware Company",
    "wof:placetype":"venue"
},
  "geometry": {"coordinates":[-86.16587699999999,34.199509],"type":"Point"}
}