{
  "type": "Feature",
  "properties": {
    "iso:country":"US",
    "sg:address":"15222 Freemans Bend Rd",
    "sg:city":"Northport",
    "sg:classifiers":[
        {
            "category":"Manufacturing",
            "subcategory":"Printing",
            "type":"Manufacturing & Wholesale Goods"
        }
    ],
    "sg:phone":"+1 205 752 3381",
    "sg:postcode":"35475",
    "sg:province":"AL",
    "sg:tags":[
        "newspaper",
        "publisher",
        "publishing"
    ],
    "sg:website":"www.bninews.com",
    "wof:name":"Boone Newspapers Inc",
    "wof:placetype":"venue"
},
  "geometry": {"coordinates":[-87.57867,33.35619],"type":"Point"}
}