{
  "type": "Feature",
  "properties": {
    "iso:country":"US",
    "sg:address":"1121 Dawes Rd",
    "sg:city":"Mobile",
    "sg:classifiers":[
        {
            "category":"Personal",
            "type":"Services"
        }
    ],
    "sg:phone":"+1 251 533 1831",
    "sg:postcode":"36695",
    "sg:province":"AL",
    "sg:tags":[
        "therapist",
        "massage"
    ],
    "wof:name":"Best Lil Wrap",
    "wof:placetype":"venue"
},
  "geometry": {"coordinates":[-88.23526699999999,30.670629],"type":"Point"}
}