{
  "type": "Feature",
  "properties": {
    "addr:full":"2513 31st St SW Birmingham AL 35221",
    "addr:housenumber":"2513",
    "addr:postcode":"35221",
    "addr:street":"31St St Sw",
    "iso:country":"US",
    "sg:address":"2513 31st St SW",
    "sg:city":"Birmingham",
    "sg:classifiers":[
        {
            "category":"Building & Trades",
            "subcategory":"Construction",
            "type":"Services"
        }
    ],
    "sg:phone":"+1 205 923 2115",
    "sg:postcode":"35221",
    "sg:province":"AL",
    "sg:tags":[
        "general"
    ],
    "wof:name":"H & H Unlimited Inc",
    "wof:placetype":"venue"
},
  "geometry": {"coordinates":[-86.882775,33.458959],"type":"Point"}
}