{
  "type": "Feature",
  "properties": {
    "iso:country":"US",
    "sg:address":"4 Office Park Cir",
    "sg:city":"Birmingham",
    "sg:classifiers":[
        {
            "category":"Insurance",
            "subcategory":"Hazard Insurance",
            "type":"Services"
        },
        {
            "category":"Professional",
            "subcategory":"Accounting & Tax Preparation",
            "type":"Services"
        }
    ],
    "sg:phone":"+1 205 871 5560",
    "sg:postcode":"35223",
    "sg:province":"AL",
    "sg:tags":[
        "profit",
        "sharing",
        "pension",
        "plan"
    ],
    "wof:name":"Ronald C Denson",
    "wof:placetype":"venue"
},
  "geometry": {"coordinates":[-86.76958399999999,33.478913],"type":"Point"}
}