{
  "type": "Feature",
  "properties": {
    "addr:full":"214 S 3rd St Gadsden AL 35901",
    "addr:housenumber":"214",
    "addr:postcode":"35901",
    "addr:street":"S 3Rd St",
    "iso:country":"US",
    "sg:address":"214 S 3rd St",
    "sg:city":"Gadsden",
    "sg:classifiers":[
        {
            "category":"Autos & Motor Vehicles",
            "subcategory":"Automobile Sales",
            "type":"Retail Goods"
        }
    ],
    "sg:phone":"+1 256 546 2000",
    "sg:postcode":"35901",
    "sg:province":"AL",
    "sg:tags":[
        "car",
        "dealer"
    ],
    "wof:name":"Dale Hicks Auto Sales",
    "wof:placetype":"venue"
},
  "geometry": {"coordinates":[-86.002734,34.011218],"type":"Point"}
}