{
  "type": "Feature",
  "properties": {
    "iso:country":"US",
    "sg:address":"1356 W Gulf Field Dr",
    "sg:city":"Mobile",
    "sg:classifiers":[
        {
            "category":"Freight",
            "type":"Transportation"
        }
    ],
    "sg:phone":"+1 251 478 1393",
    "sg:postcode":"36605",
    "sg:province":"AL",
    "wof:name":"Ryder Logistics",
    "wof:placetype":"venue"
},
  "geometry": {"coordinates":[-88.083236,30.644537],"type":"Point"}
}