{
  "type": "Feature",
  "properties": {
    "iso:country":"US",
    "sg:address":"2101 6th Ave N",
    "sg:city":"Birmingham",
    "sg:classifiers":[
        {
            "category":"Utilities",
            "subcategory":"Telephone",
            "type":"Services"
        }
    ],
    "sg:phone":"+1 205 326 3465",
    "sg:postcode":"35203",
    "sg:province":"AL",
    "sg:tags":[
        "communications"
    ],
    "wof:name":"T C G Teleport of Alabama",
    "wof:placetype":"venue"
},
  "geometry": {"coordinates":[-86.80614300000001,33.520547],"type":"Point"}
}