{
  "type": "Feature",
  "properties": {
    "iso:country":"US",
    "sg:address":"114 Mill Creek Rd",
    "sg:city":"Crossville",
    "sg:classifiers":[
        {
            "category":"Manufacturing",
            "subcategory":"Furniture",
            "type":"Manufacturing & Wholesale Goods"
        }
    ],
    "sg:phone":"+1 256 528 6459",
    "sg:postcode":"35962",
    "sg:province":"AL",
    "wof:name":"Deluxe Furniture Mfg",
    "wof:placetype":"venue"
},
  "geometry": {"coordinates":[-85.99787999999999,34.284293],"type":"Point"}
}