{
  "type": "Feature",
  "properties": {
    "iso:country":"US",
    "sg:address":"332 Co Rd 617",
    "sg:city":"Enterprise",
    "sg:classifiers":[
        {
            "category":"Building & Trades",
            "subcategory":"Construction",
            "type":"Services"
        }
    ],
    "sg:phone":"+1 334 393 4700",
    "sg:postcode":"36330",
    "sg:province":"AL",
    "sg:tags":[
        "contractor"
    ],
    "wof:name":"Moss Fence Contractors",
    "wof:placetype":"venue"
},
  "geometry": {"coordinates":[-85.949411,31.255716],"type":"Point"}
}