{
  "type": "Feature",
  "properties": {
    "iso:country":"US",
    "sg:address":"2700 13th St",
    "sg:city":"Birmingham",
    "sg:classifiers":[
        {
            "category":"Manufacturing",
            "subcategory":"Textiles",
            "type":"Manufacturing & Wholesale Goods"
        }
    ],
    "sg:phone":"+1 205 785 5130",
    "sg:postcode":"35208",
    "sg:province":"AL",
    "sg:tags":[
        "mfg",
        "woven",
        "rug",
        "tufted",
        "carpet"
    ],
    "wof:name":"Mohawk Industries Inc",
    "wof:placetype":"venue"
},
  "geometry": {"coordinates":[-86.871242,33.515164],"type":"Point"}
}