{
  "type": "Feature",
  "properties": {
    "iso:country":"US",
    "sg:address":"6271 Spanish Trail Ct",
    "sg:city":"Theodore",
    "sg:classifiers":[
        {
            "category":"Retail",
            "subcategory":"Repair Shop",
            "type":"Services"
        }
    ],
    "sg:phone":"+1 251 653 2211",
    "sg:postcode":"36582",
    "sg:province":"AL",
    "sg:tags":[
        "upholsterer"
    ],
    "wof:name":"A 1 Custom Upholstery",
    "wof:placetype":"venue"
},
  "geometry": {"coordinates":[-88.211217,30.560944],"type":"Point"}
}