{
  "type": "Feature",
  "properties": {
    "iso:country":"US",
    "sg:address":"1691 Center Point Pkwy",
    "sg:city":"Birmingham",
    "sg:classifiers":[
        {
            "category":"Home & Garden",
            "subcategory":"Furniture",
            "type":"Retail Goods"
        }
    ],
    "sg:phone":"+1 205 853 2830",
    "sg:postcode":"35215",
    "sg:province":"AL",
    "wof:name":"Braswell Ed Furn Cntrpoint Inc",
    "wof:placetype":"venue"
},
  "geometry": {"coordinates":[-86.684716,33.631456],"type":"Point"}
}