{
  "type": "Feature",
  "properties": {
    "iso:country":"US",
    "sg:address":"3738 Sandfort Rd",
    "sg:city":"Phenix City",
    "sg:classifiers":[
        {
            "category":"Building & Trades",
            "subcategory":"Construction",
            "type":"Services"
        }
    ],
    "sg:phone":"+1 334 297 3747",
    "sg:postcode":"36869",
    "sg:province":"AL",
    "sg:tags":[
        "gas",
        "line",
        "installation",
        "repair"
    ],
    "wof:name":"Hammock Plumbing Co",
    "wof:placetype":"venue"
},
  "geometry": {"coordinates":[-85.043528,32.4424],"type":"Point"}
}