{
  "type": "Feature",
  "properties": {
    "iso:country":"US",
    "sg:address":"3459 Warrior River Rd",
    "sg:city":"Bessemer",
    "sg:classifiers":[
        {
            "category":"Shopping",
            "subcategory":"Gifts & Souvenirs",
            "type":"Retail Goods"
        }
    ],
    "sg:phone":"+1 205 497 0041",
    "sg:postcode":"35023",
    "sg:province":"AL",
    "sg:tags":[
        "repair"
    ],
    "wof:name":"Operable Walls of Al",
    "wof:placetype":"venue"
},
  "geometry": {"coordinates":[-87.021147,33.459409],"type":"Point"}
}