{
  "type": "Feature",
  "properties": {
    "iso:country":"US",
    "sg:address":"109 E Mill St",
    "sg:city":"Hartford",
    "sg:classifiers":[
        {
            "category":"Home & Garden",
            "subcategory":"Garden Supply",
            "type":"Retail Goods"
        }
    ],
    "sg:phone":"+1 334 588 0945",
    "sg:postcode":"36344",
    "sg:province":"AL",
    "sg:tags":[
        "machinery"
    ],
    "wof:name":"Snapper Pro Equipment Co Inc",
    "wof:placetype":"venue"
},
  "geometry": {"coordinates":[-85.69671200000001,31.102155],"type":"Point"}
}