{
  "type": "Feature",
  "properties": {
    "iso:country":"US",
    "sg:address":"663 Cox Creek Pkwy",
    "sg:city":"Florence",
    "sg:classifiers":[
        {
            "category":"Organizations",
            "subcategory":"Religious Organization",
            "type":"Services"
        }
    ],
    "sg:phone":"+1 256 764 7810",
    "sg:postcode":"35630",
    "sg:province":"AL",
    "wof:name":"Parkway Community Church",
    "wof:placetype":"venue"
},
  "geometry": {"coordinates":[-87.656916,34.843837],"type":"Point"}
}