{
  "type": "Feature",
  "properties": {
    "iso:country":"US",
    "sg:address":"300 Aplin Rd",
    "sg:city":"Atmore",
    "sg:classifiers":[
        {
            "category":"Farming",
            "subcategory":"Farm",
            "type":"Manufacturing & Wholesale Goods"
        }
    ],
    "sg:phone":"+1 251 368 5658",
    "sg:postcode":"36502",
    "sg:province":"FL",
    "sg:tags":[
        "crop",
        "general"
    ],
    "wof:name":"Joes Plant Shack",
    "wof:placetype":"venue"
},
  "geometry": {"coordinates":[-87.525911,31.126872],"type":"Point"}
}