{
  "type": "Feature",
  "properties": {
    "iso:country":"US",
    "sg:address":"208 N Main St",
    "sg:city":"Columbiana",
    "sg:classifiers":[
        {
            "category":"Recreation",
            "type":"Entertainment"
        }
    ],
    "sg:phone":"+1 205 669 4946",
    "sg:postcode":"35051",
    "sg:province":"AL",
    "wof:name":"City Recreation Ctr",
    "wof:placetype":"venue"
},
  "geometry": {"coordinates":[-86.60716,33.182022],"type":"Point"}
}