{
  "type": "Feature",
  "properties": {
    "addr:full":"3829 9th Ave N Bessemer AL 35020",
    "addr:housenumber":"3829",
    "addr:postcode":"35020",
    "addr:street":"9Th Ave N",
    "iso:country":"US",
    "sg:address":"3829 9th Ave N",
    "sg:city":"Bessemer",
    "sg:classifiers":[
        {
            "category":"Personal",
            "subcategory":"Beauty Salon",
            "type":"Services"
        }
    ],
    "sg:phone":"+1 205 481 1890",
    "sg:postcode":"35020",
    "sg:province":"AL",
    "wof:name":"It's Yours",
    "wof:placetype":"venue"
},
  "geometry": {"coordinates":[-86.94937299999999,33.420797],"type":"Point"}
}