{
  "type": "Feature",
  "properties": {
    "iso:country":"US",
    "sg:address":"1684 S Eufaula Ave",
    "sg:city":"Eufaula",
    "sg:classifiers":[
        {
            "category":"Personal",
            "subcategory":"Beauty Salon",
            "type":"Services"
        }
    ],
    "sg:phone":"+1 334 687 1081",
    "sg:postcode":"36027",
    "sg:province":"AL",
    "sg:tags":[
        "shop"
    ],
    "wof:name":"Darcy Railey",
    "wof:placetype":"venue"
},
  "geometry": {"coordinates":[-85.155058,31.872251],"type":"Point"}
}