{
  "type": "Feature",
  "properties": {
    "iso:country":"US",
    "sg:address":"4 Bigger St",
    "sg:city":"Monroeville",
    "sg:classifiers":[
        {
            "category":"Utilities",
            "subcategory":"Fuel Oil & Lpg",
            "type":"Services"
        }
    ],
    "sg:phone":"+1 251 575 9136",
    "sg:postcode":"36460",
    "sg:province":"AL",
    "sg:tags":[
        "propane",
        "gas"
    ],
    "wof:name":"D-Gas",
    "wof:placetype":"venue"
},
  "geometry": {"coordinates":[-87.327187,31.52129],"type":"Point"}
}