{
  "type": "Feature",
  "properties": {
    "iso:country":"US",
    "sg:address":"102 Mc Swean Dr",
    "sg:city":"Abbeville",
    "sg:classifiers":[
        {
            "category":"Professional",
            "subcategory":"Management & Consulting",
            "type":"Services"
        }
    ],
    "sg:phone":"+1 334 585 2438",
    "sg:postcode":"36310",
    "sg:province":"AL",
    "sg:tags":[
        "consultant",
        "educational"
    ],
    "wof:name":"Thomas Mc Coy",
    "wof:placetype":"venue"
},
  "geometry": {"coordinates":[-85.25587,31.556627],"type":"Point"}
}