{
  "type": "Feature",
  "properties": {
    "iso:country":"US",
    "sg:address":"33605 US Hwy 280",
    "sg:city":"Childersburg",
    "sg:classifiers":[
        {
            "category":"Shopping",
            "type":"Retail Goods"
        }
    ],
    "sg:phone":"+1 256 378 7000",
    "sg:postcode":"35044",
    "sg:province":"AL",
    "sg:tags":[
        "supply",
        "sales",
        "hearing",
        "equipment",
        "impaired",
        "aid"
    ],
    "wof:name":"Advanced Hearing Care",
    "wof:placetype":"venue"
},
  "geometry": {"coordinates":[-86.353104,33.267527],"type":"Point"}
}