{
  "type": "Feature",
  "properties": {
    "iso:country":"US",
    "sg:address":"350 Old Hwy 231 N",
    "sg:city":"Troy",
    "sg:classifiers":[
        {
            "category":"Cinema",
            "subcategory":"Movie Theater",
            "type":"Entertainment"
        }
    ],
    "sg:phone":"+1 334 808 4225",
    "sg:postcode":"36081",
    "sg:province":"AL",
    "wof:name":"Continental Cinema 5",
    "wof:placetype":"venue"
},
  "geometry": {"coordinates":[-85.997452,31.854519],"type":"Point"}
}