{
  "type": "Feature",
  "properties": {
    "iso:country":"US",
    "sg:address":"1118 N Wilson Ave",
    "sg:city":"Mobile",
    "sg:classifiers":[
        {
            "category":"Organizations",
            "subcategory":"Religious Organization",
            "type":"Services"
        }
    ],
    "sg:phone":"+1 251 457 7701",
    "sg:postcode":"36610",
    "sg:province":"AL",
    "sg:tags":[
        "church"
    ],
    "wof:name":"Rivers Living Water Ministry",
    "wof:placetype":"venue"
},
  "geometry": {"coordinates":[-88.078861,30.744927],"type":"Point"}
}