{
  "type": "Feature",
  "properties": {
    "iso:country":"US",
    "sg:address":"1800 Ford Rd",
    "sg:city":"Muscle Shoals",
    "sg:classifiers":[
        {
            "category":"Building & Trades",
            "subcategory":"Construction",
            "type":"Services"
        }
    ],
    "sg:phone":"+1 256 386 0096",
    "sg:postcode":"35661",
    "sg:province":"AL",
    "sg:tags":[
        "contracting",
        "painting",
        "painter"
    ],
    "wof:name":"Ray Co Management Inc",
    "wof:placetype":"venue"
},
  "geometry": {"coordinates":[-87.603919,34.767204],"type":"Point"}
}