{
  "type": "Feature",
  "properties": {
    "iso:country":"US",
    "sg:address":"330 Hillside Rd",
    "sg:city":"Montgomery",
    "sg:classifiers":[
        {
            "category":"Real Estate",
            "subcategory":"Surveying",
            "type":"Services"
        }
    ],
    "sg:phone":"+1 334 272 0222",
    "sg:postcode":"36109",
    "sg:province":"AL",
    "sg:tags":[
        "surveyor"
    ],
    "wof:name":"Wilford Land Surveying",
    "wof:placetype":"venue"
},
  "geometry": {"coordinates":[-86.233683,32.385723],"type":"Point"}
}