{
  "type": "Feature",
  "properties": {
    "iso:country":"US",
    "sg:address":"1647 Riderwood Trl",
    "sg:city":"Birmingham",
    "sg:classifiers":[
        {
            "category":"Health Services",
            "subcategory":"Clinic",
            "type":"Services"
        }
    ],
    "sg:phone":"+1 205 979 5042",
    "sg:postcode":"35214",
    "sg:province":"AL",
    "wof:name":"Health & More Inc",
    "wof:placetype":"venue"
},
  "geometry": {"coordinates":[-86.89749399999999,33.57287],"type":"Point"}
}