{
  "type": "Feature",
  "properties": {
    "iso:country":"US",
    "sg:address":"572 Azalea Rd",
    "sg:city":"Mobile",
    "sg:classifiers":[
        {
            "category":"Real Estate",
            "subcategory":"Surveying",
            "type":"Services"
        }
    ],
    "sg:phone":"+1 251 661 7691",
    "sg:postcode":"36609",
    "sg:province":"AL",
    "sg:tags":[
        "engineering"
    ],
    "wof:name":"Neal Gibson & Associates",
    "wof:placetype":"venue"
},
  "geometry": {"coordinates":[-88.148616,30.657545],"type":"Point"}
}