{
  "type": "Feature",
  "properties": {
    "iso:country":"US",
    "sg:address":"3656 Susan Moore Rd",
    "sg:city":"Blountsville",
    "sg:classifiers":[
        {
            "category":"Autos & Motor Vehicles",
            "subcategory":"Automobile Sales",
            "type":"Retail Goods"
        }
    ],
    "sg:phone":"+1 205 466 7366",
    "sg:postcode":"35031",
    "sg:province":"AL",
    "sg:tags":[
        "used"
    ],
    "wof:name":"Johnson Motors",
    "wof:placetype":"venue"
},
  "geometry": {"coordinates":[-86.435454,34.084803],"type":"Point"}
}