{
  "type": "Feature",
  "properties": {
    "iso:country":"US",
    "sg:address":"1201 7th St SE",
    "sg:city":"Decatur",
    "sg:classifiers":[
        {
            "category":"Health Services",
            "subcategory":"Doctor",
            "type":"Services"
        }
    ],
    "sg:phone":"+1 256 340 0872",
    "sg:postcode":"35601",
    "sg:province":"AL",
    "sg:tags":[
        "physician",
        "surgeon"
    ],
    "wof:name":"Apollo MD",
    "wof:placetype":"venue"
},
  "geometry": {"coordinates":[-86.972748,34.591179],"type":"Point"}
}