{
  "type": "Feature",
  "properties": {
    "iso:country":"US",
    "sg:address":"2260 Co Rd 95",
    "sg:city":"Ranburne",
    "sg:classifiers":[
        {
            "category":"Farming",
            "subcategory":"Poultry Farm",
            "type":"Manufacturing & Wholesale Goods"
        }
    ],
    "sg:phone":"+1 256 748 4311",
    "sg:postcode":"36273",
    "sg:province":"AL",
    "sg:tags":[
        "chicken"
    ],
    "wof:name":"Roger Langley Poultry Farm",
    "wof:placetype":"venue"
},
  "geometry": {"coordinates":[-85.343074,33.580298],"type":"Point"}
}