{
  "type": "Feature",
  "properties": {
    "iso:country":"US",
    "sg:address":"2152 Cobbs Ford Rd",
    "sg:city":"Prattville",
    "sg:classifiers":[
        {
            "category":"Bars & Pubs",
            "subcategory":"Nightclub",
            "type":"Food & Drink"
        }
    ],
    "sg:phone":"+1 334 285 5500",
    "sg:postcode":"36066",
    "sg:province":"AL",
    "sg:tags":[
        "club",
        "night"
    ],
    "wof:name":"Club BTS",
    "wof:placetype":"venue"
},
  "geometry": {"coordinates":[-86.410389,32.459729],"type":"Point"}
}