{
  "type": "Feature",
  "properties": {
    "addr:full":"3900 Wilmer Rd Wilmer AL 36587",
    "addr:housenumber":"3900",
    "addr:postcode":"36587",
    "addr:street":"Wilmer Rd",
    "iso:country":"US",
    "sg:address":"3900 Wilmer Rd",
    "sg:city":"Wilmer",
    "sg:classifiers":[
        {
            "category":"Building & Trades",
            "subcategory":"Construction",
            "type":"Services"
        }
    ],
    "sg:phone":"+1 251 645 3192",
    "sg:postcode":"36587",
    "sg:province":"AL",
    "sg:tags":[
        "general",
        "contractor"
    ],
    "wof:name":"SAW Construction Inc",
    "wof:placetype":"venue"
},
  "geometry": {"coordinates":[-88.37406300000001,30.771013],"type":"Point"}
}