{
  "type": "Feature",
  "properties": {
    "iso:country":"US",
    "sg:address":"210 Co Rd 757",
    "sg:city":"Cullman",
    "sg:classifiers":[
        {
            "category":"Freight",
            "type":"Transportation"
        }
    ],
    "sg:phone":"+1 256 734 8766",
    "sg:postcode":"35055",
    "sg:province":"AL",
    "wof:name":"First Horizon Logistics Inc",
    "wof:placetype":"venue"
},
  "geometry": {"coordinates":[-86.716493,34.172152],"type":"Point"}
}