{
  "type": "Feature",
  "properties": {
    "addr:full":"52 Medical Park Dr E Ste 305 Birmingham AL 35235",
    "addr:housenumber":"52",
    "addr:postcode":"35235",
    "addr:street":"Medical Park Dr E Ste 305",
    "iso:country":"US",
    "sg:address":"52 Medical Park Dr E Ste 305",
    "sg:city":"Birmingham",
    "sg:classifiers":[
        {
            "category":"Health Services",
            "subcategory":"Hospital",
            "type":"Services"
        }
    ],
    "sg:phone":"+1 205 838 3888",
    "sg:postcode":"35235",
    "sg:province":"AL",
    "wof:name":"Outpatient Services East",
    "wof:placetype":"venue"
},
  "geometry": {"coordinates":[-86.665604,33.594601],"type":"Point"}
}