{
  "type": "Feature",
  "properties": {
    "iso:country":"US",
    "sg:address":"3618 Pepperell Pkwy",
    "sg:city":"Opelika",
    "sg:classifiers":[
        {
            "category":"Shopping",
            "subcategory":"Clothing, Apparel, & Fashions",
            "type":"Retail Goods"
        }
    ],
    "sg:phone":"+1 334 749 8803",
    "sg:postcode":"36801",
    "sg:province":"AL",
    "wof:name":"Fashion Bug",
    "wof:placetype":"venue"
},
  "geometry": {"coordinates":[-85.431753,32.633242],"type":"Point"}
}