{
  "type": "Feature",
  "properties": {
    "iso:country":"US",
    "sg:address":"1515 N Wood Ave",
    "sg:city":"Florence",
    "sg:classifiers":[
        {
            "category":"Banks & Credit Unions",
            "subcategory":"Bank",
            "type":"Services"
        }
    ],
    "sg:phone":"+1 256 767 8031",
    "sg:postcode":"35630",
    "sg:province":"AL",
    "sg:tags":[
        "cashing",
        "check"
    ],
    "wof:name":"Advance America",
    "wof:placetype":"venue"
},
  "geometry": {"coordinates":[-87.681864,34.821665],"type":"Point"}
}