{
  "type": "Feature",
  "properties": {
    "addr:full":"907 3rd Ave SE Decatur AL 35601",
    "addr:housenumber":"907",
    "addr:postcode":"35601",
    "addr:street":"3Rd Ave Se",
    "iso:country":"US",
    "sg:address":"907 3rd Ave SE",
    "sg:city":"Decatur",
    "sg:classifiers":[
        {
            "category":"Building & Trades",
            "subcategory":"Plumbing",
            "type":"Services"
        }
    ],
    "sg:phone":"+1 256 355 9062",
    "sg:postcode":"35601",
    "sg:province":"AL",
    "sg:tags":[
        "conditioning",
        "air",
        "system",
        "contractor"
    ],
    "wof:name":"Cathcart Service Inc",
    "wof:placetype":"venue"
},
  "geometry": {"coordinates":[-86.98414200000001,34.593264],"type":"Point"}
}