{
  "type": "Feature",
  "properties": {
    "addr:full":"8981 Helena Rd Pelham AL 35124",
    "addr:housenumber":"8981",
    "addr:postcode":"35124",
    "addr:street":"Helena Rd",
    "iso:country":"US",
    "sg:address":"8981 Helena Rd",
    "sg:city":"Pelham",
    "sg:classifiers":[
        {
            "category":"Banks & Credit Unions",
            "subcategory":"Investment Brokerage",
            "type":"Services"
        }
    ],
    "sg:phone":"+1 205 678 9525",
    "sg:postcode":"35124",
    "sg:province":"AL",
    "wof:name":"About Investments",
    "wof:placetype":"venue"
},
  "geometry": {"coordinates":[-86.799667,33.34455],"type":"Point"}
}