{
  "type": "Feature",
  "properties": {
    "iso:country":"US",
    "sg:address":"676 Wilson Blvd",
    "sg:city":"Axis",
    "sg:classifiers":[
        {
            "category":"Building & Trades",
            "subcategory":"Cleaning & Sanitation",
            "type":"Services"
        }
    ],
    "sg:phone":"+1 251 675 5789",
    "sg:postcode":"36505",
    "sg:province":"AL",
    "sg:tags":[
        "maintenance"
    ],
    "wof:name":"Harris Cleaning Svc",
    "wof:placetype":"venue"
},
  "geometry": {"coordinates":[-88.02142499999999,30.926897],"type":"Point"}
}