{
  "type": "Feature",
  "properties": {
    "iso:country":"US",
    "sg:address":"690 State Rte 14",
    "sg:city":"Greensboro",
    "sg:classifiers":[
        {
            "category":"Manufacturing",
            "subcategory":"Paper Products",
            "type":"Manufacturing & Wholesale Goods"
        }
    ],
    "sg:phone":"+1 334 624 3873",
    "sg:postcode":"36744",
    "sg:province":"AL",
    "wof:name":"International Paper Co",
    "wof:placetype":"venue"
},
  "geometry": {"coordinates":[-87.593768,32.698996],"type":"Point"}
}