{
  "type": "Feature",
  "properties": {
    "addr:full":"7727 Theodore Dawes Rd Theodore AL 36582",
    "addr:housenumber":"7727",
    "addr:postcode":"36582",
    "addr:street":"Theodore Dawes Rd",
    "iso:country":"US",
    "sg:address":"7727 Theodore Dawes Rd",
    "sg:city":"Theodore",
    "sg:classifiers":[
        {
            "category":"Building & Trades",
            "subcategory":"Construction",
            "type":"Services"
        }
    ],
    "sg:phone":"+1 251 653 1120",
    "sg:postcode":"36582",
    "sg:province":"AL",
    "sg:tags":[
        "contractor"
    ],
    "wof:name":"ICM of Mobile",
    "wof:placetype":"venue"
},
  "geometry": {"coordinates":[-88.224476,30.572489],"type":"Point"}
}