{
  "type": "Feature",
  "properties": {
    "iso:country":"US",
    "sg:address":"3139 Sycamore Ln",
    "sg:city":"Mobile",
    "sg:classifiers":[
        {
            "category":"Travel",
            "subcategory":"Hotels & Motels",
            "type":"Entertainment"
        }
    ],
    "sg:phone":"+1 251 479 7684",
    "sg:postcode":"36607",
    "sg:province":"AL",
    "sg:tags":[
        "operation"
    ],
    "wof:name":"Crichton Lodging",
    "wof:placetype":"venue"
},
  "geometry": {"coordinates":[-88.11941400000001,30.700496],"type":"Point"}
}