{
  "type": "Feature",
  "properties": {
    "addr:full":"170 Jenkins Rd New Hope AL 35760",
    "addr:housenumber":"170",
    "addr:postcode":"35760",
    "addr:street":"Jenkins Rd New",
    "iso:country":"US",
    "sg:address":"170 Jenkins Rd",
    "sg:city":"New Hope",
    "sg:classifiers":[
        {
            "category":"Professional",
            "subcategory":"Computer Services",
            "type":"Services"
        }
    ],
    "sg:phone":"+1 256 725 4411",
    "sg:postcode":"35760",
    "sg:province":"AL",
    "sg:tags":[
        "related"
    ],
    "wof:name":"PC& You",
    "wof:placetype":"venue"
},
  "geometry": {"coordinates":[-86.395458,34.592755],"type":"Point"}
}