{
  "type": "Feature",
  "properties": {
    "iso:country":"US",
    "sg:address":"2804 Tallahatta Springs Rd",
    "sg:city":"Thomasville",
    "sg:classifiers":[
        {
            "category":"Building & Trades",
            "subcategory":"Construction",
            "type":"Services"
        }
    ],
    "sg:phone":"+1 334 636 5392",
    "sg:postcode":"36784",
    "sg:province":"AL",
    "sg:tags":[
        "clearing",
        "land",
        "leveling"
    ],
    "wof:name":"Hi Track Dozer Svc Inc",
    "wof:placetype":"venue"
},
  "geometry": {"coordinates":[-87.77032699999999,31.90929],"type":"Point"}
}