{
  "type": "Feature",
  "properties": {
    "iso:country":"US",
    "sg:address":"2410 McPhillips",
    "sg:city":"Daphne",
    "sg:classifiers":[
        {
            "category":"Freight",
            "type":"Transportation"
        }
    ],
    "sg:phone":"+1 251 626 9148",
    "sg:postcode":"36526",
    "sg:province":"AL",
    "sg:tags":[
        "contractor"
    ],
    "wof:name":"Sarah Hearn Trucking Inc",
    "wof:placetype":"venue"
},
  "geometry": {"coordinates":[-87.901375,30.614435],"type":"Point"}
}