{
  "type": "Feature",
  "properties": {
    "iso:country":"US",
    "sg:address":"6087 Steeple Chase Dr",
    "sg:city":"Pinson",
    "sg:classifiers":[
        {
            "category":"Building & Trades",
            "subcategory":"Plumbing",
            "type":"Services"
        }
    ],
    "sg:phone":"+1 205 681 0514",
    "sg:postcode":"35126",
    "sg:province":"AL",
    "sg:tags":[
        "contractor"
    ],
    "wof:name":"Bos Plumbing & Service Inc",
    "wof:placetype":"venue"
},
  "geometry": {"coordinates":[-86.61739,33.687058],"type":"Point"}
}