{
  "type": "Feature",
  "properties": {
    "addr:full":"4261 Osage Dr Birmingham AL 35217",
    "addr:housenumber":"4261",
    "addr:postcode":"35217",
    "addr:street":"Osage Dr",
    "iso:country":"US",
    "sg:address":"4261 Osage Dr",
    "sg:city":"Birmingham",
    "sg:classifiers":[
        {
            "category":"Freight",
            "type":"Transportation"
        }
    ],
    "sg:phone":"+1 205 849 5476",
    "sg:postcode":"35217",
    "sg:province":"AL",
    "sg:tags":[
        "broker",
        "trucking"
    ],
    "wof:name":"Best Way Logistics",
    "wof:placetype":"venue"
},
  "geometry": {"coordinates":[-86.745789,33.631555],"type":"Point"}
}