{
  "type": "Feature",
  "properties": {
    "iso:country":"US",
    "sg:address":"2623 Alta Vista Cir",
    "sg:city":"Birmingham",
    "sg:classifiers":[
        {
            "category":"Manufacturing",
            "subcategory":"Printing",
            "type":"Manufacturing & Wholesale Goods"
        }
    ],
    "sg:phone":"+1 205 967 8608",
    "sg:postcode":"35243",
    "sg:province":"AL",
    "sg:tags":[
        "publishes",
        "book"
    ],
    "wof:name":"Story Time Publications Inc",
    "wof:placetype":"venue"
},
  "geometry": {"coordinates":[-86.749859,33.41722],"type":"Point"}
}