{
  "type": "Feature",
  "properties": {
    "iso:country":"US",
    "sg:address":"2502 Arrowood Cir",
    "sg:city":"Birmingham",
    "sg:classifiers":[
        {
            "category":"Professional",
            "type":"Services"
        }
    ],
    "sg:phone":"+1 205 798 9755",
    "sg:postcode":"35214",
    "sg:province":"AL",
    "wof:name":"Felicia Butler",
    "wof:placetype":"venue"
},
  "geometry": {"coordinates":[-86.903509,33.587517],"type":"Point"}
}