{
  "type": "Feature",
  "properties": {
    "iso:country":"US",
    "sg:address":"2920 Marti Ln",
    "sg:city":"Montgomery",
    "sg:classifiers":[
        {
            "category":"Health Services",
            "subcategory":"Doctor",
            "type":"Services"
        }
    ],
    "sg:phone":"+1 334 613 0626",
    "sg:postcode":"36116",
    "sg:province":"AL",
    "wof:name":"Kent D Hill DDS",
    "wof:placetype":"venue"
},
  "geometry": {"coordinates":[-86.254668,32.326797],"type":"Point"}
}