{
  "type": "Feature",
  "properties": {
    "addr:full":"1846 State Rte 14 Prattville AL 36066",
    "addr:housenumber":"1846",
    "addr:postcode":"36066",
    "addr:street":"State Rte 14",
    "iso:country":"US",
    "sg:address":"1846 State Rte 14",
    "sg:city":"Prattville",
    "sg:classifiers":[
        {
            "category":"Autos & Motor Vehicles",
            "subcategory":"Fuel & Gas Station",
            "type":"Retail Goods"
        }
    ],
    "sg:phone":"+1 334 361 8037",
    "sg:postcode":"36066",
    "sg:province":"AL",
    "sg:tags":[
        "convenience",
        "station",
        "gasoline",
        "store"
    ],
    "wof:name":"Shop-A-Snak Food Mart",
    "wof:placetype":"venue"
},
  "geometry": {"coordinates":[-86.418082,32.482856],"type":"Point"}
}