{
  "type": "Feature",
  "properties": {
    "iso:country":"US",
    "sg:address":"102 Martin Luther King Blvd",
    "sg:city":"Union Springs",
    "sg:classifiers":[
        {
            "category":"Autos & Motor Vehicles",
            "subcategory":"Fuel & Gas Station",
            "type":"Retail Goods"
        },
        {
            "category":"Wholesale",
            "subcategory":"Auto Parts",
            "type":"Manufacturing & Wholesale Goods"
        }
    ],
    "sg:phone":"+1 334 738 5469",
    "sg:postcode":"36089",
    "sg:province":"AL",
    "sg:tags":[
        "station",
        "gasoline",
        "oil"
    ],
    "wof:name":"Union Springs Phillips 66",
    "wof:placetype":"venue"
},
  "geometry": {"coordinates":[-85.713537,32.14333],"type":"Point"}
}