{
  "type": "Feature",
  "properties": {
    "iso:country":"US",
    "sg:address":"21270 Co Rd 27",
    "sg:city":"Fairhope",
    "sg:classifiers":[
        {
            "category":"Building & Trades",
            "subcategory":"Landscaping Services",
            "type":"Services"
        }
    ],
    "sg:phone":"+1 251 928 6406",
    "sg:postcode":"36532",
    "sg:province":"AL",
    "sg:tags":[
        "landscape"
    ],
    "wof:name":"Rezner Pottery & Landscaping",
    "wof:placetype":"venue"
},
  "geometry": {"coordinates":[-87.852307,30.532044],"type":"Point"}
}