{
  "type": "Feature",
  "properties": {
    "iso:country":"US",
    "sg:address":"101 S Royal Ave",
    "sg:city":"Florence",
    "sg:classifiers":[
        {
            "category":"Manufacturing",
            "subcategory":"Metals",
            "type":"Manufacturing & Wholesale Goods"
        }
    ],
    "sg:phone":"+1 256 764 2323",
    "sg:postcode":"35630",
    "sg:province":"AL",
    "sg:tags":[
        "fabricator",
        "sheet"
    ],
    "wof:name":"Stanfield's Tin Shop",
    "wof:placetype":"venue"
},
  "geometry": {"coordinates":[-87.656842,34.802234],"type":"Point"}
}