{
  "type": "Feature",
  "properties": {
    "addr:full":"745 Woodall Rd Decatur AL 35601",
    "addr:housenumber":"745",
    "addr:postcode":"35601",
    "addr:street":"Woodall Rd",
    "iso:country":"US",
    "sg:address":"745 Woodall Rd",
    "sg:city":"Decatur",
    "sg:classifiers":[
        {
            "category":"Manufacturing",
            "subcategory":"Tools & Machinery",
            "type":"Manufacturing & Wholesale Goods"
        }
    ],
    "sg:phone":"+1 256 355 9198",
    "sg:postcode":"35601",
    "sg:province":"AL",
    "sg:tags":[
        "industrial",
        "mfg",
        "contractor",
        "trade"
    ],
    "wof:name":"Wilson Machine & Welding Inc",
    "wof:placetype":"venue"
},
  "geometry": {"coordinates":[-87.052792,34.598515],"type":"Point"}
}