{
  "type": "Feature",
  "properties": {
    "iso:country":"US",
    "sg:address":"3550 20th Ave",
    "sg:city":"Valley",
    "sg:classifiers":[
        {
            "category":"Restaurant",
            "type":"Food & Drink"
        }
    ],
    "sg:phone":"+1 334 768 2901",
    "sg:postcode":"36854",
    "sg:province":"AL",
    "wof:name":"Hardee's",
    "wof:placetype":"venue"
},
  "geometry": {"coordinates":[-85.156611,32.788043],"type":"Point"}
}