{
  "type": "Feature",
  "properties": {
    "iso:country":"US",
    "sg:address":"7139 State Rte 119",
    "sg:city":"Montevallo",
    "sg:classifiers":[
        {
            "category":"Building & Trades",
            "subcategory":"Pest Control",
            "type":"Services"
        }
    ],
    "sg:phone":"+1 205 663 7123",
    "sg:postcode":"35115",
    "sg:province":"AL",
    "wof:name":"Coverall Pest Control",
    "wof:placetype":"venue"
},
  "geometry": {"coordinates":[-86.82280900000001,33.184732],"type":"Point"}
}