{
  "type": "Feature",
  "properties": {
    "iso:country":"US",
    "sg:address":"3060 Leeman Ferry Rd SW",
    "sg:city":"Huntsville",
    "sg:classifiers":[
        {
            "category":"Shopping",
            "type":"Retail Goods"
        },
        {
            "category":"Manufacturing",
            "subcategory":"Apparel",
            "type":"Manufacturing & Wholesale Goods"
        }
    ],
    "sg:phone":"+1 256 882 1603",
    "sg:postcode":"35801",
    "sg:province":"AL",
    "sg:tags":[
        "flag",
        "banner",
        "merchandise"
    ],
    "wof:name":"Flag & Banner Center",
    "wof:placetype":"venue"
},
  "geometry": {"coordinates":[-86.591724,34.702367],"type":"Point"}
}