{
  "type": "Feature",
  "properties": {
    "iso:country":"US",
    "sg:address":"1955 Lookout Cir",
    "sg:city":"Gadsden",
    "sg:classifiers":[
        {
            "category":"Building & Trades",
            "subcategory":"Electrical",
            "type":"Services"
        }
    ],
    "sg:phone":"+1 256 546 4103",
    "sg:postcode":"35904",
    "sg:province":"AL",
    "sg:tags":[
        "electric",
        "contractor"
    ],
    "wof:name":"J L Means Electric",
    "wof:placetype":"venue"
},
  "geometry": {"coordinates":[-86.02117800000001,34.04362],"type":"Point"}
}