{
  "type": "Feature",
  "properties": {
    "addr:full":"4120 Wall St Montgomery AL 36106",
    "addr:housenumber":"4120",
    "addr:postcode":"36106",
    "addr:street":"Wall St",
    "iso:country":"US",
    "sg:address":"4120 Wall St",
    "sg:city":"Montgomery",
    "sg:classifiers":[
        {
            "category":"Wholesale",
            "subcategory":"Computers",
            "type":"Manufacturing & Wholesale Goods"
        }
    ],
    "sg:phone":"+1 334 263 0506",
    "sg:postcode":"36106",
    "sg:province":"AL",
    "wof:name":"Contact Network Inc",
    "wof:placetype":"venue"
},
  "geometry": {"coordinates":[-86.233493,32.359789],"type":"Point"}
}