{
  "type": "Feature",
  "properties": {
    "iso:country":"US",
    "sg:address":"22 Southern Hills St",
    "sg:city":"Calera",
    "sg:classifiers":[
        {
            "category":"Professional",
            "subcategory":"Computer Services",
            "type":"Services"
        }
    ],
    "sg:phone":"+1 205 668 2050",
    "sg:postcode":"35040",
    "sg:province":"AL",
    "sg:tags":[
        "electrical",
        "related",
        "contractor"
    ],
    "wof:name":"Digital Design Inc",
    "wof:placetype":"venue"
},
  "geometry": {"coordinates":[-86.76613,33.143645],"type":"Point"}
}