{
  "type": "Feature",
  "properties": {
    "addr:full":"15179 McCulley Mill Rd Athens AL 35613",
    "addr:postcode":"15179;35613",
    "addr:street":"Mcculley Mill Rd",
    "iso:country":"US",
    "sg:address":"15179 McCulley Mill Rd",
    "sg:city":"Athens",
    "sg:classifiers":[
        {
            "category":"Farming",
            "subcategory":"Livestock Farm",
            "type":"Manufacturing & Wholesale Goods"
        }
    ],
    "sg:phone":"+1 256 232 5364",
    "sg:postcode":"35613",
    "sg:province":"AL",
    "sg:tags":[
        "beef",
        "feedlot",
        "cattle"
    ],
    "wof:name":"James Bailey",
    "wof:placetype":"venue"
},
  "geometry": {"coordinates":[-86.863885,34.776645],"type":"Point"}
}