{
  "type": "Feature",
  "properties": {
    "iso:country":"US",
    "sg:address":"4925 Madison Cir",
    "sg:city":"Northport",
    "sg:classifiers":[
        {
            "category":"Health Services",
            "subcategory":"Clinic",
            "type":"Services"
        }
    ],
    "sg:phone":"+1 205 339 0735",
    "sg:postcode":"35475",
    "sg:province":"AL",
    "wof:name":"T & S Medical",
    "wof:placetype":"venue"
},
  "geometry": {"coordinates":[-87.603344,33.301041],"type":"Point"}
}