{
  "type": "Feature",
  "properties": {
    "iso:country":"US",
    "sg:address":"1371 Bessemer Rd",
    "sg:city":"Birmingham",
    "sg:classifiers":[
        {
            "category":"Restaurant",
            "type":"Food & Drink"
        }
    ],
    "sg:phone":"+1 205 923 2422",
    "sg:postcode":"35208",
    "sg:province":"AL",
    "sg:tags":[
        "eating"
    ],
    "wof:name":"Top That Grill II",
    "wof:placetype":"venue"
},
  "geometry": {"coordinates":[-86.894251,33.481035],"type":"Point"}
}