{
  "type": "Feature",
  "properties": {
    "addr:full":"481 Azalea Way Birmingham AL 35215",
    "addr:housenumber":"481",
    "addr:postcode":"35215",
    "addr:street":"Azalea Way",
    "iso:country":"US",
    "sg:address":"481 Azalea Way",
    "sg:city":"Birmingham",
    "sg:classifiers":[
        {
            "category":"Professional",
            "type":"Services"
        }
    ],
    "sg:phone":"+1 205 815 0697",
    "sg:postcode":"35215",
    "sg:province":"AL",
    "wof:name":"Quantex Inc",
    "wof:placetype":"venue"
},
  "geometry": {"coordinates":[-86.695505,33.608439],"type":"Point"}
}