{
  "type": "Feature",
  "properties": {
    "iso:country":"US",
    "sg:address":"1570 S Phillips Rd",
    "sg:city":"Lanett",
    "sg:classifiers":[
        {
            "category":"Utilities",
            "subcategory":"Telephone",
            "type":"Services"
        }
    ],
    "sg:phone":"+1 706 645 8671",
    "sg:postcode":"36863",
    "sg:province":"AL",
    "sg:tags":[
        "communications",
        "radiotelephone",
        "communication"
    ],
    "wof:name":"Interstate Telephone Company",
    "wof:placetype":"venue"
},
  "geometry": {"coordinates":[-85.23168099999999,32.848583],"type":"Point"}
}