{
  "type": "Feature",
  "properties": {
    "iso:country":"US",
    "sg:address":"1106 Winston Dr",
    "sg:city":"Athens",
    "sg:classifiers":[
        {
            "category":"Professional",
            "subcategory":"Engineering",
            "type":"Services"
        }
    ],
    "sg:phone":"+1 256 777 6443",
    "sg:postcode":"35611",
    "sg:province":"AL",
    "wof:name":"Bullington Engineering Inc",
    "wof:placetype":"venue"
},
  "geometry": {"coordinates":[-86.955704,34.795684],"type":"Point"}
}