{
  "type": "Feature",
  "properties": {
    "iso:country":"US",
    "sg:address":"1013 Way Thru the Woods",
    "sg:city":"Decatur",
    "sg:classifiers":[
        {
            "category":"Arts & Performance",
            "subcategory":"Theater",
            "type":"Entertainment"
        }
    ],
    "sg:phone":"+1 256 350 2760",
    "sg:postcode":"35603",
    "sg:province":"AL",
    "sg:tags":[
        "group"
    ],
    "wof:name":"Clown Express",
    "wof:placetype":"venue"
},
  "geometry": {"coordinates":[-87.007052,34.546946],"type":"Point"}
}