{
  "type": "Feature",
  "properties": {
    "addr:full":"2145 S College St Auburn AL 36832",
    "addr:housenumber":"2145",
    "addr:postcode":"36832",
    "addr:street":"S College St",
    "iso:country":"US",
    "sg:address":"2145 S College St",
    "sg:city":"Auburn",
    "sg:classifiers":[
        {
            "category":"Building & Trades",
            "subcategory":"Plumbing",
            "type":"Services"
        }
    ],
    "sg:phone":"+1 334 821 4328",
    "sg:postcode":"36832",
    "sg:province":"AL",
    "sg:tags":[
        "heat",
        "pump"
    ],
    "wof:name":"Mechanical Services",
    "wof:placetype":"venue"
},
  "geometry": {"coordinates":[-85.509934,32.551902],"type":"Point"}
}