{
  "type": "Feature",
  "properties": {
    "iso:country":"US",
    "sg:address":"355 Cedar Ridge Dr",
    "sg:city":"Wetumpka",
    "sg:classifiers":[
        {
            "category":"Professional",
            "subcategory":"Management & Consulting",
            "type":"Services"
        }
    ],
    "sg:phone":"+1 334 567 1028",
    "sg:postcode":"36093",
    "sg:province":"AL",
    "sg:tags":[
        "business"
    ],
    "wof:name":"Industrial Saftey and Maint",
    "wof:placetype":"venue"
},
  "geometry": {"coordinates":[-86.10332099999999,32.46927],"type":"Point"}
}