{
  "type": "Feature",
  "properties": {
    "iso:country":"US",
    "sg:address":"610 Chapelwood Dr",
    "sg:city":"Dothan",
    "sg:classifiers":[
        {
            "category":"Professional",
            "type":"Services"
        }
    ],
    "sg:phone":"+1 334 702 3161",
    "sg:postcode":"36305",
    "sg:province":"AL",
    "wof:name":"Matt Whitehead",
    "wof:placetype":"venue"
},
  "geometry": {"coordinates":[-85.463465,31.225667],"type":"Point"}
}