{
  "type": "Feature",
  "properties": {
    "iso:country":"US",
    "sg:address":"221 Jefferson Ave E",
    "sg:city":"Oneonta",
    "sg:classifiers":[
        {
            "category":"Professional",
            "subcategory":"Advertising",
            "type":"Services"
        }
    ],
    "sg:phone":"+1 205 274 9327",
    "sg:postcode":"35121",
    "sg:province":"AL",
    "sg:tags":[
        "distributing",
        "sample"
    ],
    "wof:name":"Hidden Valley Farms",
    "wof:placetype":"venue"
},
  "geometry": {"coordinates":[-86.472883,33.943307],"type":"Point"}
}