{
  "type": "Feature",
  "properties": {
    "addr:full":"4412 4th Ave S Birmingham AL 35222",
    "addr:housenumber":"4412",
    "addr:postcode":"35222",
    "addr:street":"4Th Ave S",
    "iso:country":"US",
    "sg:address":"4412 4th Ave S",
    "sg:city":"Birmingham",
    "sg:classifiers":[
        {
            "category":"Shopping",
            "subcategory":"Discount & Variety Stores",
            "type":"Retail Goods"
        },
        {
            "category":"Shopping",
            "subcategory":"Department Store",
            "type":"Retail Goods"
        }
    ],
    "sg:phone":"+1 205 591 3709",
    "sg:postcode":"35222",
    "sg:province":"AL",
    "sg:tags":[
        "shop"
    ],
    "wof:name":"Family Dollar Stores",
    "wof:placetype":"venue"
},
  "geometry": {"coordinates":[-86.76624200000001,33.526371],"type":"Point"}
}