{
  "type": "Feature",
  "properties": {
    "addr:full":"770 Middle St Fairhope AL 36532",
    "addr:housenumber":"770",
    "addr:postcode":"36532",
    "addr:street":"Middle St",
    "iso:country":"US",
    "sg:address":"770 Middle St",
    "sg:city":"Fairhope",
    "sg:classifiers":[
        {
            "category":"Health Services",
            "subcategory":"Doctor",
            "type":"Services"
        }
    ],
    "sg:phone":"+1 251 928 1191",
    "sg:postcode":"36532",
    "sg:province":"AL",
    "sg:tags":[
        "physician",
        "medical",
        "surgeon"
    ],
    "wof:name":"Family Practice Assoc Montrose",
    "wof:placetype":"venue"
},
  "geometry": {"coordinates":[-87.88782,30.513714],"type":"Point"}
}