{
  "type": "Feature",
  "properties": {
    "iso:country":"US",
    "sg:address":"1051 S McDonough St",
    "sg:city":"Montgomery",
    "sg:classifiers":[
        {
            "category":"Professional",
            "subcategory":"Lawyer & Legal Services",
            "type":"Services"
        }
    ],
    "sg:phone":"+1 334 265 0505",
    "sg:postcode":"36104",
    "sg:province":"AL",
    "wof:name":"Hollifield & Hollifield",
    "wof:placetype":"venue"
},
  "geometry": {"coordinates":[-86.304368,32.36388],"type":"Point"}
}