{
  "type": "Feature",
  "properties": {
    "iso:country":"US",
    "sg:address":"308 Chewalca Dr",
    "sg:city":"Rainbow City",
    "sg:classifiers":[
        {
            "category":"Home & Garden",
            "subcategory":"Carpets & Floor Coverings",
            "type":"Retail Goods"
        }
    ],
    "sg:phone":"+1 256 413 7877",
    "sg:postcode":"35906",
    "sg:province":"AL",
    "wof:name":"Knights Flooring",
    "wof:placetype":"venue"
},
  "geometry": {"coordinates":[-86.043281,33.961646],"type":"Point"}
}