{
  "type": "Feature",
  "properties": {
    "iso:country":"US",
    "sg:address":"16282 Hardy Rd",
    "sg:city":"Athens",
    "sg:classifiers":[
        {
            "category":"Professional",
            "subcategory":"Computer Services",
            "type":"Services"
        }
    ],
    "sg:phone":"+1 256 729 8407",
    "sg:postcode":"35611",
    "sg:province":"AL",
    "sg:tags":[
        "programing",
        "custom"
    ],
    "wof:name":"Computer Design & Redimensions",
    "wof:placetype":"venue"
},
  "geometry": {"coordinates":[-87.152093,34.799895],"type":"Point"}
}