{
  "type": "Feature",
  "properties": {
    "addr:full":"607 14th St SE Decatur AL 35601",
    "addr:housenumber":"607",
    "addr:postcode":"35601",
    "addr:street":"14Th St Se",
    "iso:country":"US",
    "sg:address":"607 14th St SE",
    "sg:city":"Decatur",
    "sg:classifiers":[
        {
            "category":"Cinema",
            "subcategory":"Movie Theater",
            "type":"Entertainment"
        }
    ],
    "sg:phone":"+1 256 350 0935",
    "sg:postcode":"35601",
    "sg:province":"AL",
    "wof:name":"Carmike 8",
    "wof:placetype":"venue"
},
  "geometry": {"coordinates":[-86.978769,34.57834],"type":"Point"}
}