{
  "type": "Feature",
  "properties": {
    "iso:country":"US",
    "sg:address":"3100 Independence Dr",
    "sg:city":"Birmingham",
    "sg:classifiers":[
        {
            "category":"Professional",
            "subcategory":"Lawyer & Legal Services",
            "type":"Services"
        }
    ],
    "sg:phone":"+1 205 870 7744",
    "sg:postcode":"35209",
    "sg:province":"AL",
    "sg:tags":[
        "attorney"
    ],
    "wof:name":"Bobby Lott Jr Law Office",
    "wof:placetype":"venue"
},
  "geometry": {"coordinates":[-86.787376,33.47472],"type":"Point"}
}