{
  "type": "Feature",
  "properties": {
    "iso:country":"US",
    "sg:address":"210 N Elm St",
    "sg:city":"Tuskegee",
    "sg:classifiers":[
        {
            "category":"Social Services",
            "type":"Services"
        }
    ],
    "sg:phone":"+1 334 727 9523",
    "sg:postcode":"36083",
    "sg:province":"AL",
    "sg:tags":[
        "organization",
        "welfare"
    ],
    "wof:name":"Macon County Retired & Senior",
    "wof:placetype":"venue"
},
  "geometry": {"coordinates":[-85.691984,32.423635],"type":"Point"}
}