{
  "type": "Feature",
  "properties": {
    "iso:country":"US",
    "sg:address":"1202 Old Oak Rd",
    "sg:city":"Birmingham",
    "sg:classifiers":[
        {
            "category":"Professional",
            "type":"Services"
        }
    ],
    "sg:phone":"+1 205 853 5825",
    "sg:postcode":"35235",
    "sg:province":"AL",
    "wof:name":"Bob Guice",
    "wof:placetype":"venue"
},
  "geometry": {"coordinates":[-86.665725,33.611779],"type":"Point"}
}