{
  "type": "Feature",
  "properties": {
    "addr:full":"1811 W Main St Dothan AL 36301",
    "addr:housenumber":"1811",
    "addr:postcode":"36301",
    "addr:street":"W Main St",
    "iso:country":"US",
    "sg:address":"1811 W Main St",
    "sg:city":"Dothan",
    "sg:classifiers":[
        {
            "category":"Professional",
            "subcategory":"Lawyer & Legal Services",
            "type":"Services"
        }
    ],
    "sg:phone":"+1 334 793 6543",
    "sg:postcode":"36301",
    "sg:province":"AL",
    "wof:name":"Charles Finney",
    "wof:placetype":"venue"
},
  "geometry": {"coordinates":[-85.417446,31.228066],"type":"Point"}
}