{
  "type": "Feature",
  "properties": {
    "iso:country":"US",
    "sg:address":"1335 Gunter Ave",
    "sg:city":"Guntersville",
    "sg:classifiers":[
        {
            "category":"Retail",
            "subcategory":"Animal Services",
            "type":"Services"
        }
    ],
    "sg:phone":"+1 256 582 1900",
    "sg:postcode":"35976",
    "sg:province":"AL",
    "sg:tags":[
        "pet",
        "grooming",
        "washing"
    ],
    "wof:name":"Petals & Paws",
    "wof:placetype":"venue"
},
  "geometry": {"coordinates":[-86.302306,34.347195],"type":"Point"}
}