{
  "type": "Feature",
  "properties": {
    "iso:country":"US",
    "sg:address":"5039 English Turn",
    "sg:city":"Birmingham",
    "sg:classifiers":[
        {
            "category":"Shopping",
            "subcategory":"Clothing, Apparel, & Fashions",
            "type":"Retail Goods"
        }
    ],
    "sg:phone":"+1 205 995 8711",
    "sg:postcode":"35242",
    "sg:province":"AL",
    "wof:name":"Fashion Consulting By Joan",
    "wof:placetype":"venue"
},
  "geometry": {"coordinates":[-86.635874,33.419775],"type":"Point"}
}