{
  "type": "Feature",
  "properties": {
    "iso:country":"US",
    "sg:address":"3120 29th Ave N",
    "sg:city":"Birmingham",
    "sg:classifiers":[
        {
            "category":"Organizations",
            "subcategory":"Religious Organization",
            "type":"Services"
        }
    ],
    "sg:phone":"+1 205 324 8400",
    "sg:postcode":"35207",
    "sg:province":"AL",
    "wof:name":"Mount Pleasant Pbc Church Inc",
    "wof:placetype":"venue"
},
  "geometry": {"coordinates":[-86.804732,33.552057],"type":"Point"}
}