{
  "type": "Feature",
  "properties": {
    "iso:country":"US",
    "sg:address":"2527 Danville Rd SW",
    "sg:city":"Decatur",
    "sg:classifiers":[
        {
            "category":"Social Services",
            "subcategory":"Child Care",
            "type":"Services"
        }
    ],
    "sg:phone":"+1 256 353 8280",
    "sg:postcode":"35603",
    "sg:province":"AL",
    "wof:name":"Decatur Baptist Child Care Ctr",
    "wof:placetype":"venue"
},
  "geometry": {"coordinates":[-87.017907,34.561054],"type":"Point"}
}