{
  "type": "Feature",
  "properties": {
    "addr:full":"514 E Lafayette St Dadeville AL 36853",
    "addr:housenumber":"514",
    "addr:postcode":"36853",
    "addr:street":"E Lafayette St",
    "iso:country":"US",
    "sg:address":"514 E Lafayette St",
    "sg:city":"Dadeville",
    "sg:classifiers":[
        {
            "category":"Professional",
            "type":"Services"
        }
    ],
    "sg:phone":"+1 256 825 0148",
    "sg:postcode":"36853",
    "sg:province":"AL",
    "wof:name":"Vision Athletic Apparel Inc",
    "wof:placetype":"venue"
},
  "geometry": {"coordinates":[-85.75767999999999,32.833495],"type":"Point"}
}