{
  "type": "Feature",
  "properties": {
    "iso:country":"US",
    "sg:address":"195 W Valley Ave",
    "sg:city":"Birmingham",
    "sg:classifiers":[
        {
            "category":"Personal",
            "subcategory":"Beauty Salon",
            "type":"Services"
        }
    ],
    "sg:phone":"+1 205 290 0440",
    "sg:postcode":"35209",
    "sg:province":"AL",
    "sg:tags":[
        "shop"
    ],
    "wof:name":"Nail First",
    "wof:placetype":"venue"
},
  "geometry": {"coordinates":[-86.83741499999999,33.46501],"type":"Point"}
}