{
  "type": "Feature",
  "properties": {
    "iso:country":"US",
    "sg:address":"484 Bachelor Rd",
    "sg:city":"Atmore",
    "sg:classifiers":[
        {
            "category":"Retail",
            "subcategory":"Veterinary Services",
            "type":"Services"
        }
    ],
    "sg:phone":"+1 251 368 8668",
    "sg:postcode":"36502",
    "sg:province":"AL",
    "wof:name":"Lee Veterinary Clinic PC",
    "wof:placetype":"venue"
},
  "geometry": {"coordinates":[-87.42637,31.005225],"type":"Point"}
}