{
  "type": "Feature",
  "properties": {
    "addr:full":"449 Dalton Dr Birmingham AL 35215",
    "addr:housenumber":"449",
    "addr:postcode":"35215",
    "addr:street":"Dalton Dr",
    "iso:country":"US",
    "sg:address":"449 Dalton Dr",
    "sg:city":"Birmingham",
    "sg:classifiers":[
        {
            "category":"Autos & Motor Vehicles",
            "subcategory":"Automobile Sales",
            "type":"Retail Goods"
        }
    ],
    "sg:phone":"+1 205 838 1477",
    "sg:postcode":"35215",
    "sg:province":"AL",
    "sg:tags":[
        "used"
    ],
    "wof:name":"Duke Tim Auto Sales Inc",
    "wof:placetype":"venue"
},
  "geometry": {"coordinates":[-86.700237,33.59522],"type":"Point"}
}