{
  "type": "Feature",
  "properties": {
    "iso:country":"US",
    "sg:address":"2202 Virginia Ave",
    "sg:city":"Muscle Shoals",
    "sg:classifiers":[
        {
            "category":"Building & Trades",
            "subcategory":"Construction",
            "type":"Services"
        }
    ],
    "sg:phone":"+1 256 383 3762",
    "sg:postcode":"35661",
    "sg:province":"AL",
    "sg:tags":[
        "floor",
        "laying",
        "contractor"
    ],
    "wof:name":"Vaughn Flooring Contractors",
    "wof:placetype":"venue"
},
  "geometry": {"coordinates":[-87.638554,34.750237],"type":"Point"}
}