{
  "type": "Feature",
  "properties": {
    "iso:country":"US",
    "sg:address":"2806 Dartmouth Ave",
    "sg:city":"Bessemer",
    "sg:classifiers":[
        {
            "category":"Retail",
            "subcategory":"Auto Repair",
            "type":"Services"
        }
    ],
    "sg:phone":"+1 205 425 0470",
    "sg:postcode":"35020",
    "sg:province":"AL",
    "sg:tags":[
        "repairing",
        "automobile"
    ],
    "wof:name":"D & R Auto Repair",
    "wof:placetype":"venue"
},
  "geometry": {"coordinates":[-86.935801,33.410087],"type":"Point"}
}