{
  "type": "Feature",
  "properties": {
    "addr:full":"186 5th Ave NW Graysville AL 35073",
    "addr:housenumber":"186",
    "addr:postcode":"35073",
    "addr:street":"5Th Ave Nw Graysville",
    "iso:country":"US",
    "sg:address":"186 5th Ave NW",
    "sg:city":"Graysville",
    "sg:classifiers":[
        {
            "category":"Freight",
            "type":"Transportation"
        }
    ],
    "sg:phone":"+1 205 674 0720",
    "sg:postcode":"35073",
    "sg:province":"AL",
    "sg:tags":[
        "operator",
        "local",
        "trucking"
    ],
    "wof:name":"Drake Trucking",
    "wof:placetype":"venue"
},
  "geometry": {"coordinates":[-86.976636,33.635027],"type":"Point"}
}