{
  "type": "Feature",
  "properties": {
    "iso:country":"US",
    "sg:address":"107 E College St",
    "sg:city":"Florence",
    "sg:classifiers":[
        {
            "category":"Professional",
            "subcategory":"Lawyer & Legal Services",
            "type":"Services"
        }
    ],
    "sg:phone":"+1 256 232 0202",
    "sg:postcode":"35630",
    "sg:province":"AL",
    "sg:tags":[
        "attorney"
    ],
    "wof:name":"Sherrill Batts & Shipman",
    "wof:placetype":"venue"
},
  "geometry": {"coordinates":[-87.67411300000001,34.799858],"type":"Point"}
}