{
  "type": "Feature",
  "properties": {
    "iso:country":"US",
    "sg:address":"7308 Cottage Hill Rd",
    "sg:city":"Mobile",
    "sg:classifiers":[
        {
            "category":"Real Estate",
            "subcategory":"Real Estate Agent",
            "type":"Services"
        }
    ],
    "sg:phone":"+1 251 633 9910",
    "sg:postcode":"36695",
    "sg:province":"AL",
    "wof:name":"Danny Blight Realty",
    "wof:placetype":"venue"
},
  "geometry": {"coordinates":[-88.213229,30.636581],"type":"Point"}
}