{
  "type": "Feature",
  "properties": {
    "addr:full":"1314 Polaris Dr Mobile AL 36693",
    "addr:housenumber":"1314",
    "addr:postcode":"36693",
    "addr:street":"Polaris Dr",
    "iso:country":"US",
    "sg:address":"1314 Polaris Dr",
    "sg:city":"Mobile",
    "sg:classifiers":[
        {
            "category":"Building & Trades",
            "subcategory":"Construction",
            "type":"Services"
        }
    ],
    "sg:phone":"+1 251 604 4967",
    "sg:postcode":"36693",
    "sg:province":"AL",
    "sg:tags":[
        "home",
        "improvement"
    ],
    "wof:name":"W C Construction Co",
    "wof:placetype":"venue"
},
  "geometry": {"coordinates":[-88.155674,30.631592],"type":"Point"}
}