{
  "type": "Feature",
  "properties": {
    "iso:country":"US",
    "sg:address":"120 Wynn Dr NW",
    "sg:city":"Huntsville",
    "sg:classifiers":[
        {
            "category":"Professional",
            "subcategory":"Computer Services",
            "type":"Services"
        }
    ],
    "sg:phone":"+1 256 704 0604",
    "sg:postcode":"35805",
    "sg:province":"AL",
    "sg:tags":[
        "internet"
    ],
    "wof:name":"Dealnews Com",
    "wof:placetype":"venue"
},
  "geometry": {"coordinates":[-86.653791,34.716336],"type":"Point"}
}