{
  "type": "Feature",
  "properties": {
    "iso:country":"US",
    "sg:address":"5900 23rd Ave",
    "sg:city":"Valley",
    "sg:classifiers":[
        {
            "category":"Retail",
            "subcategory":"Repair Shop",
            "type":"Services"
        }
    ],
    "sg:phone":"+1 334 756 7315",
    "sg:postcode":"36854",
    "sg:province":"AL",
    "sg:tags":[
        "television",
        "radio"
    ],
    "wof:name":"Stodghill TV Svc",
    "wof:placetype":"venue"
},
  "geometry": {"coordinates":[-85.173771,32.814431],"type":"Point"}
}