{
  "type": "Feature",
  "properties": {
    "iso:country":"US",
    "sg:address":"1340 Highpoint Ter",
    "sg:city":"Birmingham",
    "sg:classifiers":[
        {
            "category":"Professional",
            "subcategory":"Lawyer & Legal Services",
            "type":"Services"
        }
    ],
    "sg:phone":"+1 205 520 5030",
    "sg:postcode":"35235",
    "sg:province":"AL",
    "wof:name":"Alford Margie Attorney",
    "wof:placetype":"venue"
},
  "geometry": {"coordinates":[-86.665802,33.613098],"type":"Point"}
}