{
  "type": "Feature",
  "properties": {
    "addr:full":"1809 Indian Creek Cir Birmingham AL 35243",
    "addr:housenumber":"1809",
    "addr:postcode":"35243",
    "addr:street":"Indian Creek Cir",
    "iso:country":"US",
    "sg:address":"1809 Indian Creek Cir",
    "sg:city":"Birmingham",
    "sg:classifiers":[
        {
            "category":"Health Services",
            "subcategory":"Doctor",
            "type":"Services"
        }
    ],
    "sg:phone":"+1 205 967 5752",
    "sg:postcode":"35243",
    "sg:province":"AL",
    "sg:tags":[
        "medical"
    ],
    "wof:name":"Vulcan Anesthesia Service",
    "wof:placetype":"venue"
},
  "geometry": {"coordinates":[-86.763662,33.451642],"type":"Point"}
}