{
  "type": "Feature",
  "properties": {
    "iso:country":"US",
    "sg:address":"6240 Robinhood Ln NW",
    "sg:city":"Huntsville",
    "sg:classifiers":[
        {
            "category":"Real Estate",
            "subcategory":"Real Estate Operator",
            "type":"Services"
        }
    ],
    "sg:phone":"+1 256 722 9501",
    "sg:postcode":"35806",
    "sg:province":"AL",
    "sg:tags":[
        "apartment"
    ],
    "wof:name":"Research Park Apartments",
    "wof:placetype":"venue"
},
  "geometry": {"coordinates":[-86.658285,34.714339],"type":"Point"}
}