{
  "type": "Feature",
  "properties": {
    "addr:full":"6240 Robinhood Ln NW Huntsville AL 35806",
    "addr:housenumber":"6240",
    "addr:postcode":"35806",
    "addr:street":"Robinhood Ln Nw",
    "iso:country":"US",
    "sg:address":"6240 Robinhood Ln NW",
    "sg:city":"Huntsville",
    "sg:classifiers":[
        {
            "category":"Real Estate",
            "subcategory":"Real Estate Operator",
            "type":"Services"
        }
    ],
    "sg:phone":"+1 256 722 9501",
    "sg:postcode":"35806",
    "sg:province":"AL",
    "sg:tags":[
        "apartment"
    ],
    "wof:name":"Research Park Apartments",
    "wof:placetype":"venue"
},
  "geometry": {"coordinates":[-86.65828500000001,34.714339],"type":"Point"}
}