{
  "type": "Feature",
  "properties": {
    "addr:full":"3045 Independence Dr Birmingham AL 35209",
    "addr:housenumber":"3045",
    "addr:postcode":"35209",
    "addr:street":"Independence Dr",
    "iso:country":"US",
    "sg:address":"3045 Independence Dr",
    "sg:city":"Birmingham",
    "sg:classifiers":[
        {
            "category":"Insurance",
            "subcategory":"Insurance Agent",
            "type":"Services"
        },
        {
            "category":"Insurance",
            "subcategory":"Hazard Insurance",
            "type":"Services"
        },
        {
            "category":"Insurance",
            "subcategory":"Title Insurance",
            "type":"Services"
        },
        {
            "category":"Insurance",
            "subcategory":"Life Insurance",
            "type":"Services"
        }
    ],
    "sg:phone":"+1 205 870 9643",
    "sg:postcode":"35209",
    "sg:province":"AL",
    "sg:tags":[
        "business",
        "auto",
        "commercial",
        "homeowner",
        "motorcycle",
        "renter"
    ],
    "wof:name":"Allstate Insurance Company - Richard Reid",
    "wof:placetype":"venue"
},
  "geometry": {"coordinates":[-86.787239,33.476551],"type":"Point"}
}