{
  "type": "Feature",
  "properties": {
    "iso:country":"US",
    "sg:address":"1203 Posey Ave NW",
    "sg:city":"Huntsville",
    "sg:classifiers":[
        {
            "category":"Home & Garden",
            "subcategory":"Furniture",
            "type":"Retail Goods"
        }
    ],
    "sg:phone":"+1 256 551 9078",
    "sg:postcode":"35816",
    "sg:province":"AL",
    "sg:tags":[
        "cabinet"
    ],
    "wof:name":"Woodwerx Custom Cabinets",
    "wof:placetype":"venue"
},
  "geometry": {"coordinates":[-86.601309,34.738325],"type":"Point"}
}