{
  "type": "Feature",
  "properties": {
    "iso:country":"US",
    "sg:address":"300 Flightline Dr",
    "sg:city":"Dothan",
    "sg:classifiers":[
        {
            "category":"Professional",
            "subcategory":"Engineering",
            "type":"Services"
        }
    ],
    "sg:phone":"+1 334 983 4541",
    "sg:postcode":"36303",
    "sg:province":"AL",
    "sg:tags":[
        "mechanical"
    ],
    "wof:name":"Alabama Jet Center",
    "wof:placetype":"venue"
},
  "geometry": {"coordinates":[-85.450649,31.315722],"type":"Point"}
}