{
  "type": "Feature",
  "properties": {
    "iso:country":"US",
    "sg:address":"200 Finney Rd SW",
    "sg:city":"Huntsville",
    "sg:classifiers":[
        {
            "category":"Manufacturing",
            "subcategory":"Metals",
            "type":"Manufacturing & Wholesale Goods"
        },
        {
            "category":"Manufacturing",
            "subcategory":"Watercraft",
            "type":"Manufacturing & Wholesale Goods"
        }
    ],
    "sg:phone":"+1 256 772 0164",
    "sg:postcode":"35824",
    "sg:province":"AL",
    "sg:tags":[
        "supply",
        "equipment",
        "part",
        "distributor",
        "rebuilt",
        "marine",
        "boat"
    ],
    "sg:website":"www.thmarine.com",
    "wof:name":"T-H Marine Supplies Inc Mfg",
    "wof:placetype":"venue"
},
  "geometry": {"coordinates":[-86.752138,34.642829],"type":"Point"}
}