{
  "type": "Feature",
  "properties": {
    "addr:full":"4000 Fieldcrest Dr Montgomery AL 36111",
    "addr:housenumber":"4000",
    "addr:postcode":"36111",
    "addr:street":"Fieldcrest Dr",
    "iso:country":"US",
    "sg:address":"4000 Fieldcrest Dr",
    "sg:city":"Montgomery",
    "sg:classifiers":[
        {
            "category":"Health Services",
            "subcategory":"Nursing And Care Facility",
            "type":"Services"
        }
    ],
    "sg:phone":"+1 334 284 0370",
    "sg:postcode":"36111",
    "sg:province":"AL",
    "sg:tags":[
        "living",
        "retirement",
        "community"
    ],
    "wof:name":"Caravita Village",
    "wof:placetype":"venue"
},
  "geometry": {"coordinates":[-86.25137599999999,32.3311],"type":"Point"}
}