{
  "type": "Feature",
  "properties": {
    "iso:country":"US",
    "sg:address":"1961 Woodridge Rd",
    "sg:city":"Tuscaloosa",
    "sg:classifiers":[
        {
            "category":"Professional",
            "type":"Services"
        }
    ],
    "sg:phone":"+1 205 752 8721",
    "sg:postcode":"35406",
    "sg:province":"AL",
    "sg:tags":[
        "establishment"
    ],
    "wof:name":"Specialties Of The House",
    "wof:placetype":"venue"
},
  "geometry": {"coordinates":[-87.53248,33.233966],"type":"Point"}
}