{
  "type": "Feature",
  "properties": {
    "iso:country":"US",
    "sg:address":"1 Moulton Pl",
    "sg:city":"Mobile",
    "sg:classifiers":[
        {
            "category":"Professional",
            "subcategory":"Business Services",
            "type":"Services"
        }
    ],
    "sg:phone":"+1 251 344 9640",
    "sg:postcode":"36608",
    "sg:province":"AL",
    "wof:name":"Atlas LLC",
    "wof:placetype":"venue"
},
  "geometry": {"coordinates":[-88.13019799999999,30.699178],"type":"Point"}
}