{
  "type": "Feature",
  "properties": {
    "iso:country":"US",
    "sg:address":"22916 US Hwy 98",
    "sg:city":"Fairhope",
    "sg:classifiers":[
        {
            "category":"Building & Trades",
            "subcategory":"Pest Control",
            "type":"Services"
        }
    ],
    "sg:phone":"+1 251 929 1921",
    "sg:postcode":"36532",
    "sg:province":"AL",
    "wof:name":"Havard Pest Control",
    "wof:placetype":"venue"
},
  "geometry": {"coordinates":[-87.89392599999999,30.559129],"type":"Point"}
}