{
  "type": "Feature",
  "properties": {
    "iso:country":"US",
    "sg:address":"74 Kenny Clay Rd",
    "sg:city":"Somerville",
    "sg:classifiers":[
        {
            "category":"Shopping",
            "subcategory":"Gifts & Souvenirs",
            "type":"Retail Goods"
        }
    ],
    "sg:phone":"+1 256 301 0065",
    "sg:postcode":"35670",
    "sg:province":"AL",
    "sg:tags":[
        "shop"
    ],
    "wof:name":"Zone",
    "wof:placetype":"venue"
},
  "geometry": {"coordinates":[-86.714908,34.512685],"type":"Point"}
}