{
  "type": "Feature",
  "properties": {
    "iso:country":"US",
    "sg:address":"2525 US Hwy 431",
    "sg:city":"Boaz",
    "sg:classifiers":[
        {
            "category":"Health Services",
            "subcategory":"Doctor",
            "type":"Services"
        }
    ],
    "sg:phone":"+1 256 593 2221",
    "sg:postcode":"35957",
    "sg:province":"AL",
    "sg:tags":[
        "medical"
    ],
    "wof:name":"Emanuel Carlos C MD Facc",
    "wof:placetype":"venue"
},
  "geometry": {"coordinates":[-86.15955200000001,34.221861],"type":"Point"}
}