{
  "type": "Feature",
  "properties": {
    "addr:full":"6458 Belle Bayou Dr Theodore AL 36582",
    "addr:housenumber":"6458",
    "addr:postcode":"36582",
    "addr:street":"Belle Bayou Dr",
    "iso:country":"US",
    "sg:address":"6458 Belle Bayou Dr",
    "sg:city":"Theodore",
    "sg:classifiers":[
        {
            "category":"Building & Trades",
            "subcategory":"Electrical",
            "type":"Services"
        }
    ],
    "sg:phone":"+1 251 443 6558",
    "sg:postcode":"36582",
    "sg:province":"AL",
    "sg:tags":[
        "electrical",
        "contractor"
    ],
    "wof:name":"Collings Electric",
    "wof:placetype":"venue"
},
  "geometry": {"coordinates":[-88.10881999999999,30.556634],"type":"Point"}
}