{
  "type": "Feature",
  "properties": {
    "addr:full":"14077 Tanner Williams Rd Wilmer AL 36587",
    "addr:housenumber":"14077",
    "addr:postcode":"36587",
    "addr:street":"Tanner Williams Rd",
    "iso:country":"US",
    "sg:address":"14077 Tanner Williams Rd",
    "sg:city":"Wilmer",
    "sg:classifiers":[
        {
            "category":"Retail",
            "subcategory":"Repair Shop",
            "type":"Services"
        }
    ],
    "sg:phone":"+1 251 649 7185",
    "sg:postcode":"36587",
    "sg:province":"AL",
    "wof:name":"Sullivan Clyde Piano Service",
    "wof:placetype":"venue"
},
  "geometry": {"coordinates":[-88.368925,30.723966],"type":"Point"}
}