{
  "type": "Feature",
  "properties": {
    "iso:country":"US",
    "sg:address":"1424 Co Rd 28",
    "sg:city":"Crossville",
    "sg:classifiers":[
        {
            "category":"Farming",
            "subcategory":"Livestock Farm",
            "type":"Manufacturing & Wholesale Goods"
        }
    ],
    "sg:phone":"+1 256 659 6462",
    "sg:postcode":"35962",
    "sg:province":"AL",
    "sg:tags":[
        "hog",
        "or",
        "feedlot"
    ],
    "wof:name":"H&A Farms",
    "wof:placetype":"venue"
},
  "geometry": {"coordinates":[-86.021419,34.342456],"type":"Point"}
}