{
  "type": "Feature",
  "properties": {
    "addr:full":"500 N 10th St Opelika AL 36801",
    "addr:housenumber":"500",
    "addr:postcode":"36801",
    "addr:street":"N 10Th St",
    "iso:country":"US",
    "sg:address":"500 N 10th St",
    "sg:city":"Opelika",
    "sg:classifiers":[
        {
            "category":"Organizations",
            "subcategory":"Religious Organization",
            "type":"Services"
        }
    ],
    "sg:phone":"+1 334 745 5181",
    "sg:postcode":"36801",
    "sg:province":"AL",
    "sg:tags":[
        "church"
    ],
    "wof:name":"Church Of Christ",
    "wof:placetype":"venue"
},
  "geometry": {"coordinates":[-85.38749,32.652096],"type":"Point"}
}