{
  "type": "Feature",
  "properties": {
    "iso:country":"US",
    "sg:address":"404 Glover St",
    "sg:city":"Albertville",
    "sg:classifiers":[
        {
            "category":"Building & Trades",
            "subcategory":"Construction",
            "type":"Services"
        }
    ],
    "sg:phone":"+1 256 878 3878",
    "sg:postcode":"35950",
    "sg:province":"AL",
    "sg:tags":[
        "nonresidential",
        "contractor"
    ],
    "wof:name":"Andrew Gregg Contracting",
    "wof:placetype":"venue"
},
  "geometry": {"coordinates":[-86.20443899999999,34.274247],"type":"Point"}
}