{
  "type": "Feature",
  "properties": {
    "iso:country":"US",
    "sg:address":"406 Antler Dr",
    "sg:city":"Enterprise",
    "sg:classifiers":[
        {
            "category":"Wholesale",
            "subcategory":"Plants",
            "type":"Manufacturing & Wholesale Goods"
        }
    ],
    "sg:phone":"+1 334 393 4383",
    "sg:postcode":"36330",
    "sg:province":"AL",
    "sg:tags":[
        "supply"
    ],
    "wof:name":"Aretha Flowers",
    "wof:placetype":"venue"
},
  "geometry": {"coordinates":[-85.815485,31.326266],"type":"Point"}
}