{
  "type": "Feature",
  "properties": {
    "iso:country":"US",
    "sg:address":"205 Executive Park Dr",
    "sg:city":"Dothan",
    "sg:classifiers":[
        {
            "category":"Health Services",
            "subcategory":"Doctor",
            "type":"Services"
        }
    ],
    "sg:phone":"+1 334 793 7674",
    "sg:postcode":"36303",
    "sg:province":"AL",
    "sg:tags":[
        "dentist"
    ],
    "wof:name":"Hand William G DMD PC",
    "wof:placetype":"venue"
},
  "geometry": {"coordinates":[-85.427486,31.251569],"type":"Point"}
}