{
  "type": "Feature",
  "properties": {
    "addr:full":"3450 US Hwy 72 Killen AL 35645",
    "addr:housenumber":"3450",
    "addr:postcode":"35645",
    "addr:street":"Us Hwy 72",
    "iso:country":"US",
    "sg:address":"3450 US Hwy 72",
    "sg:city":"Killen",
    "sg:classifiers":[
        {
            "category":"Museum",
            "type":"Entertainment"
        }
    ],
    "sg:phone":"+1 256 757 9229",
    "sg:postcode":"35645",
    "sg:province":"AL",
    "wof:name":"Pettus Museum",
    "wof:placetype":"venue"
},
  "geometry": {"coordinates":[-87.508557,34.859533],"type":"Point"}
}