{
  "type": "Feature",
  "properties": {
    "iso:country":"US",
    "sg:address":"105 Clinton St SE",
    "sg:city":"Jacksonville",
    "sg:classifiers":[
        {
            "category":"Shopping",
            "subcategory":"Beauty & Cosmetics",
            "type":"Retail Goods"
        }
    ],
    "sg:phone":"+1 256 435 4840",
    "sg:postcode":"36265",
    "sg:province":"AL",
    "sg:tags":[
        "perfume"
    ],
    "wof:name":"Merle Norman Cosmetics",
    "wof:placetype":"venue"
},
  "geometry": {"coordinates":[-85.761324,33.814332],"type":"Point"}
}