{
  "type": "Feature",
  "properties": {
    "iso:country":"US",
    "sg:address":"1601 9th Ave S",
    "sg:city":"Birmingham",
    "sg:classifiers":[
        {
            "category":"Restaurant",
            "type":"Food & Drink"
        }
    ],
    "sg:menulink":"http://www.allmenus.com/al/birmingham/163446-rallys/menu/",
    "sg:phone":"+1 205 424 3226",
    "sg:postcode":"35205",
    "sg:province":"AL",
    "sg:tags":[
        "sandwich",
        "dog",
        "burger",
        "hot",
        "wrap",
        "american"
    ],
    "wof:name":"Rally's",
    "wof:placetype":"venue"
},
  "geometry": {"coordinates":[-86.80377799999999,33.500669],"type":"Point"}
}