{
  "type": "Feature",
  "properties": {
    "iso:country":"US",
    "sg:address":"8151 Zeigler Blvd",
    "sg:city":"Mobile",
    "sg:classifiers":[
        {
            "category":"Manufacturing",
            "subcategory":"Glass & Minerals",
            "type":"Manufacturing & Wholesale Goods"
        }
    ],
    "sg:phone":"+1 251 639 9514",
    "sg:postcode":"36608",
    "sg:province":"AL",
    "sg:tags":[
        "ready"
    ],
    "wof:name":"Bayou Concrete",
    "wof:placetype":"venue"
},
  "geometry": {"coordinates":[-88.232594,30.704973],"type":"Point"}
}