{
  "type": "Feature",
  "properties": {
    "addr:full":"210 6th St N Clanton AL 35045",
    "addr:housenumber":"210",
    "addr:postcode":"35045",
    "addr:street":"6Th St N",
    "iso:country":"US",
    "sg:address":"210 6th St N",
    "sg:city":"Clanton",
    "sg:classifiers":[
        {
            "category":"Organizations",
            "subcategory":"Religious Organization",
            "type":"Services"
        }
    ],
    "sg:phone":"+1 205 755 3840",
    "sg:postcode":"35045",
    "sg:province":"AL",
    "sg:website":"www.clantonfirstbaptist.org",
    "wof:name":"First Baptist Church",
    "wof:placetype":"venue"
},
  "geometry": {"coordinates":[-86.630465,32.840498],"type":"Point"}
}