{
  "type": "Feature",
  "properties": {
    "iso:country":"US",
    "sg:address":"300 Dove St",
    "sg:city":"Birmingham",
    "sg:classifiers":[
        {
            "category":"Recreation",
            "type":"Entertainment"
        }
    ],
    "sg:phone":"+1 205 841 3658",
    "sg:postcode":"35217",
    "sg:province":"AL",
    "sg:tags":[
        "amusement"
    ],
    "wof:name":"Tours-A-Plenty",
    "wof:placetype":"venue"
},
  "geometry": {"coordinates":[-86.771151,33.58965],"type":"Point"}
}