{
  "type": "Feature",
  "properties": {
    "iso:country":"US",
    "sg:address":"839 Three Cedars Rd",
    "sg:city":"Ohatchee",
    "sg:classifiers":[
        {
            "category":"Building & Trades",
            "subcategory":"Construction",
            "type":"Services"
        }
    ],
    "sg:phone":"+1 256 892 7000",
    "sg:postcode":"36271",
    "sg:province":"AL",
    "sg:tags":[
        "concrete",
        "contractor"
    ],
    "wof:name":"Alpha Concrete & Grading",
    "wof:placetype":"venue"
},
  "geometry": {"coordinates":[-86.039509,33.757998],"type":"Point"}
}