{
  "type": "Feature",
  "properties": {
    "iso:country":"US",
    "sg:address":"214 Richeson St NW",
    "sg:city":"Russellville",
    "sg:classifiers":[
        {
            "category":"Professional",
            "subcategory":"Accounting & Tax Preparation",
            "type":"Services"
        }
    ],
    "sg:phone":"+1 256 332 0854",
    "sg:postcode":"35653",
    "sg:province":"AL",
    "sg:tags":[
        "return"
    ],
    "wof:name":"Richardson Consultant",
    "wof:placetype":"venue"
},
  "geometry": {"coordinates":[-87.728316,34.515632],"type":"Point"}
}