{
  "type": "Feature",
  "properties": {
    "iso:country":"US",
    "sg:address":"716 Davis St",
    "sg:city":"Elba",
    "sg:classifiers":[
        {
            "category":"Professional",
            "subcategory":"Business Services",
            "type":"Services"
        }
    ],
    "sg:phone":"+1 334 897 5506",
    "sg:postcode":"36323",
    "sg:province":"AL",
    "wof:name":"Dubose Appraisals",
    "wof:placetype":"venue"
},
  "geometry": {"coordinates":[-86.068692,31.413818],"type":"Point"}
}