{
  "type": "Feature",
  "properties": {
    "iso:country":"US",
    "sg:address":"142 W Jeff Davis Ave",
    "sg:city":"Montgomery",
    "sg:classifiers":[
        {
            "category":"Organizations",
            "subcategory":"Religious Organization",
            "type":"Services"
        }
    ],
    "sg:phone":"+1 334 263 4435",
    "sg:postcode":"36104",
    "sg:province":"AL",
    "sg:tags":[
        "church"
    ],
    "wof:name":"New Mount Olive Missionry Bapt",
    "wof:placetype":"venue"
},
  "geometry": {"coordinates":[-86.311258,32.36628],"type":"Point"}
}