{
  "type": "Feature",
  "properties": {
    "iso:country":"US",
    "sg:address":"204 Hillwood Dr",
    "sg:city":"Alabaster",
    "sg:classifiers":[
        {
            "category":"Manufacturing",
            "subcategory":"Metals",
            "type":"Manufacturing & Wholesale Goods"
        }
    ],
    "sg:phone":"+1 205 516 3227",
    "sg:postcode":"35007",
    "sg:province":"AL",
    "sg:tags":[
        "steel",
        "die",
        "tool",
        "alloy"
    ],
    "wof:name":"Zayler Tooling & Manufacturing",
    "wof:placetype":"venue"
},
  "geometry": {"coordinates":[-86.809067,33.260518],"type":"Point"}
}