{
  "type": "Feature",
  "properties": {
    "addr:full":"2522 Brookline Dr NW Huntsville AL 35810",
    "addr:housenumber":"2522",
    "addr:postcode":"35810",
    "addr:street":"Brookline Dr Nw",
    "iso:country":"US",
    "sg:address":"2522 Brookline Dr NW",
    "sg:city":"Huntsville",
    "sg:classifiers":[
        {
            "category":"Building & Trades",
            "subcategory":"Cleaning & Sanitation",
            "type":"Services"
        }
    ],
    "sg:phone":"+1 256 859 2558",
    "sg:postcode":"35810",
    "sg:province":"AL",
    "sg:tags":[
        "residential",
        "commercial",
        "janitorial"
    ],
    "wof:name":"Trinis Janitorial Service",
    "wof:placetype":"venue"
},
  "geometry": {"coordinates":[-86.627304,34.757355],"type":"Point"}
}