{
  "type": "Feature",
  "properties": {
    "iso:country":"US",
    "sg:address":"214 Seville St",
    "sg:city":"Florence",
    "sg:classifiers":[
        {
            "category":"Home & Garden",
            "subcategory":"Furniture",
            "type":"Retail Goods"
        }
    ],
    "sg:phone":"+1 256 764 6593",
    "sg:postcode":"35630",
    "sg:province":"AL",
    "wof:name":"Royal Furniture",
    "wof:placetype":"venue"
},
  "geometry": {"coordinates":[-87.627524,34.832608],"type":"Point"}
}