{
  "type": "Feature",
  "properties": {
    "addr:full":"710 20th St N Birmingham AL 35203",
    "addr:housenumber":"710",
    "addr:postcode":"35203",
    "addr:street":"20Th St N",
    "iso:country":"US",
    "sg:address":"710 20th St N",
    "sg:city":"Birmingham",
    "sg:classifiers":[
        {
            "category":"Professional",
            "type":"Services"
        }
    ],
    "sg:phone":"+1 205 787 5320",
    "sg:postcode":"35203",
    "sg:province":"AL",
    "wof:name":"Bernard Kincaid",
    "wof:placetype":"venue"
},
  "geometry": {"coordinates":[-86.81116900000001,33.520986],"type":"Point"}
}