{
  "type": "Feature",
  "properties": {
    "iso:country":"US",
    "sg:address":"1228 Audubon Rd",
    "sg:city":"Montgomery",
    "sg:classifiers":[
        {
            "category":"Building & Trades",
            "subcategory":"Cleaning & Sanitation",
            "type":"Services"
        }
    ],
    "sg:phone":"+1 334 284 7618",
    "sg:postcode":"36111",
    "sg:province":"AL",
    "sg:tags":[
        "maintenance"
    ],
    "wof:name":"T & T Cleaning Services",
    "wof:placetype":"venue"
},
  "geometry": {"coordinates":[-86.287359,32.327688],"type":"Point"}
}