{
  "type": "Feature",
  "properties": {
    "addr:full":"2315 Bob Wallace Ave SW Huntsville AL 35805",
    "addr:housenumber":"2315",
    "addr:postcode":"35805",
    "addr:street":"Bob Wallace Ave Sw",
    "iso:country":"US",
    "sg:address":"2315 Bob Wallace Ave SW",
    "sg:city":"Huntsville",
    "sg:classifiers":[
        {
            "category":"Government",
            "subcategory":"Office",
            "type":"Public Place"
        }
    ],
    "sg:phone":"+1 256 534 6868",
    "sg:postcode":"35805",
    "sg:province":"AL",
    "wof:name":"National Children Advocacy Ctr",
    "wof:placetype":"venue"
},
  "geometry": {"coordinates":[-86.594759,34.711183],"type":"Point"}
}