{
  "type": "Feature",
  "properties": {
    "iso:country":"US",
    "sg:address":"3658 Airport Blvd",
    "sg:city":"Mobile",
    "sg:classifiers":[
        {
            "category":"Shopping",
            "type":"Retail Goods"
        },
        {
            "category":"Shopping",
            "subcategory":"Clothing, Apparel, & Fashions",
            "type":"Retail Goods"
        }
    ],
    "sg:phone":"+1 251 304 0950",
    "sg:postcode":"36608",
    "sg:province":"AL",
    "sg:tags":[
        "baby",
        "infant",
        "accessory",
        "furniture",
        "supply"
    ],
    "wof:name":"Babies R Us",
    "wof:placetype":"venue"
},
  "geometry": {"coordinates":[-88.133876,30.676066],"type":"Point"}
}