{
  "type": "Feature",
  "properties": {
    "iso:country":"US",
    "sg:address":"2839 7th Ave S",
    "sg:city":"Birmingham",
    "sg:classifiers":[
        {
            "category":"Cafe",
            "type":"Food & Drink"
        }
    ],
    "sg:menulink":"http://www.allmenus.com/al/birmingham/53750-bombay-cafe/menu/",
    "sg:phone":"+1 204 322 1930",
    "sg:postcode":"35233",
    "sg:province":"AL",
    "sg:tags":[
        "american"
    ],
    "wof:name":"Bombay Cafe",
    "wof:placetype":"venue"
},
  "geometry": {"coordinates":[-86.78840700000001,33.511305],"type":"Point"}
}