{
  "type": "Feature",
  "properties": {
    "addr:full":"328 Washington St S Livingston AL 35470",
    "addr:housenumber":"328",
    "addr:postcode":"35470",
    "addr:street":"Washington St S",
    "iso:country":"US",
    "sg:address":"328 Washington St S",
    "sg:city":"Livingston",
    "sg:classifiers":[
        {
            "category":"Professional",
            "subcategory":"Lawyer & Legal Services",
            "type":"Services"
        }
    ],
    "sg:phone":"+1 205 652 2701",
    "sg:postcode":"35470",
    "sg:province":"AL",
    "sg:tags":[
        "attorney"
    ],
    "wof:name":"Robert M Seale",
    "wof:placetype":"venue"
},
  "geometry": {"coordinates":[-88.18923599999999,32.582734],"type":"Point"}
}