{
  "type": "Feature",
  "properties": {
    "iso:country":"US",
    "sg:address":"7545 US Hwy 72 Alt",
    "sg:city":"Madison",
    "sg:classifiers":[
        {
            "category":"Building & Trades",
            "subcategory":"Construction",
            "type":"Services"
        }
    ],
    "sg:phone":"+1 256 837 0999",
    "sg:postcode":"35758",
    "sg:province":"AL",
    "sg:tags":[
        "house"
    ],
    "wof:name":"Woodland Homes of Huntsville",
    "wof:placetype":"venue"
},
  "geometry": {"coordinates":[-86.70052,34.697038],"type":"Point"}
}