{
  "type": "Feature",
  "properties": {
    "iso:country":"US",
    "sg:address":"2409 State Rte 79",
    "sg:city":"Guntersville",
    "sg:classifiers":[
        {
            "category":"Social Services",
            "subcategory":"Child Care",
            "type":"Services"
        }
    ],
    "sg:phone":"+1 256 582 5776",
    "sg:postcode":"35976",
    "sg:province":"AL",
    "sg:tags":[
        "day"
    ],
    "wof:name":"Bright Beginners Nursery Sch",
    "wof:placetype":"venue"
},
  "geometry": {"coordinates":[-86.235877,34.455879],"type":"Point"}
}