{
  "type": "Feature",
  "properties": {
    "addr:full":"1188 Powder Plant Rd Bessemer AL 35022",
    "addr:housenumber":"1188",
    "addr:postcode":"35022",
    "addr:street":"Powder Plant Rd",
    "iso:country":"US",
    "sg:address":"1188 Powder Plant Rd",
    "sg:city":"Bessemer",
    "sg:classifiers":[
        {
            "category":"Manufacturing",
            "subcategory":"Glass & Minerals",
            "type":"Manufacturing & Wholesale Goods"
        },
        {
            "category":"Building & Trades",
            "subcategory":"Construction",
            "type":"Services"
        }
    ],
    "sg:phone":"+1 205 425 2111",
    "sg:postcode":"35022",
    "sg:province":"AL",
    "sg:tags":[
        "concrete",
        "central",
        "contractor"
    ],
    "wof:name":"Bama Concrete Products Co Inc",
    "wof:placetype":"venue"
},
  "geometry": {"coordinates":[-87.01034900000001,33.368155],"type":"Point"}
}