{
  "type": "Feature",
  "properties": {
    "iso:country":"US",
    "sg:address":"1355 14th Ave S",
    "sg:city":"Birmingham",
    "sg:classifiers":[
        {
            "category":"Building & Trades",
            "subcategory":"Cleaning & Sanitation",
            "type":"Services"
        }
    ],
    "sg:phone":"+1 205 934 2666",
    "sg:postcode":"35205",
    "sg:province":"AL",
    "wof:name":"Merceys Closet",
    "wof:placetype":"venue"
},
  "geometry": {"coordinates":[-86.803804,33.493521],"type":"Point"}
}