{
  "type": "Feature",
  "properties": {
    "iso:country":"US",
    "sg:address":"6601 1st Ave N",
    "sg:city":"Birmingham",
    "sg:classifiers":[
        {
            "category":"Autos & Motor Vehicles",
            "subcategory":"Fuel & Gas Station",
            "type":"Retail Goods"
        }
    ],
    "sg:phone":"+1 205 836 0833",
    "sg:postcode":"35206",
    "sg:province":"AL",
    "sg:tags":[
        "station",
        "gasoline"
    ],
    "wof:name":"Amoco",
    "wof:placetype":"venue"
},
  "geometry": {"coordinates":[-86.740026,33.550112],"type":"Point"}
}