{
  "type": "Feature",
  "properties": {
    "iso:country":"US",
    "sg:address":"1127 S Quintard Ave",
    "sg:city":"Anniston",
    "sg:classifiers":[
        {
            "category":"Retail",
            "subcategory":"Car Wash",
            "type":"Services"
        }
    ],
    "sg:phone":"+1 256 237 7855",
    "sg:postcode":"36201",
    "sg:province":"AL",
    "sg:tags":[
        "polishing",
        "washing"
    ],
    "wof:name":"Tite Wash 2",
    "wof:placetype":"venue"
},
  "geometry": {"coordinates":[-85.825491,33.633291],"type":"Point"}
}