{
  "type": "Feature",
  "properties": {
    "iso:country":"US",
    "sg:address":"1446 Sutton Bridge Rd",
    "sg:city":"Rainbow City",
    "sg:classifiers":[
        {
            "category":"Social Services",
            "subcategory":"Job Training",
            "type":"Services"
        }
    ],
    "sg:phone":"+1 256 413 3181",
    "sg:postcode":"35906",
    "sg:province":"AL",
    "sg:tags":[
        "retardation",
        "disabled",
        "mental",
        "dev"
    ],
    "wof:name":"Regional 310 Authority",
    "wof:placetype":"venue"
},
  "geometry": {"coordinates":[-86.043323,33.984111],"type":"Point"}
}