{
  "type": "Feature",
  "properties": {
    "iso:country":"US",
    "sg:address":"1568 Allens Cross Rd",
    "sg:city":"Union Grove",
    "sg:classifiers":[
        {
            "category":"Farming",
            "subcategory":"Livestock Farm",
            "type":"Manufacturing & Wholesale Goods"
        }
    ],
    "sg:phone":"+1 256 498 2038",
    "sg:postcode":"35175",
    "sg:province":"AL",
    "sg:tags":[
        "feedlot",
        "field",
        "crop",
        "beef",
        "cattle"
    ],
    "wof:name":"J Brand",
    "wof:placetype":"venue"
},
  "geometry": {"coordinates":[-86.531576,34.440493],"type":"Point"}
}