{
  "type": "Feature",
  "properties": {
    "addr:full":"9911 Blackwell Nursery Rd S Semmes AL 36575",
    "addr:housenumber":"9911",
    "addr:postcode":"36575",
    "addr:street":"Blackwell Nursery Rd",
    "iso:country":"US",
    "sg:address":"9911 Blackwell Nursery Rd S",
    "sg:city":"Semmes",
    "sg:classifiers":[
        {
            "category":"Place Of Worship",
            "subcategory":"Church",
            "type":"Public Place"
        },
        {
            "category":"Place Of Worship",
            "type":"Public Place"
        },
        {
            "category":"Place Of Worship",
            "subcategory":"Shrine",
            "type":"Public Place"
        }
    ],
    "sg:phone":"+1 251 645 6838",
    "sg:postcode":"36575",
    "sg:province":"AL",
    "sg:tags":[
        "churches-baptist-general",
        "churches-baptist-free",
        "churches-baptist"
    ],
    "sg:website":"http://www.baycityfwb.com",
    "wof:name":"Bay City Free Will Baptist Church",
    "wof:placetype":"venue"
},
  "geometry": {"coordinates":[-88.276743,30.778699],"type":"Point"}
}