{
  "type": "Feature",
  "properties": {
    "iso:country":"US",
    "sg:address":"2770 Southside Dr",
    "sg:city":"Tuscaloosa",
    "sg:classifiers":[
        {
            "category":"Freight",
            "type":"Transportation"
        }
    ],
    "sg:phone":"+1 205 752 3711",
    "sg:postcode":"35401",
    "sg:province":"AL",
    "sg:tags":[
        "arrangement"
    ],
    "wof:name":"Airborne",
    "wof:placetype":"venue"
},
  "geometry": {"coordinates":[-87.559592,33.186491],"type":"Point"}
}