{
  "type": "Feature",
  "properties": {
    "iso:country":"US",
    "sg:address":"489 Mudd St",
    "sg:city":"Eastaboga",
    "sg:classifiers":[
        {
            "category":"Freight",
            "type":"Transportation"
        }
    ],
    "sg:phone":"+1 256 835 4894",
    "sg:postcode":"36260",
    "sg:province":"AL",
    "wof:name":"Straightline Transportation",
    "wof:placetype":"venue"
},
  "geometry": {"coordinates":[-86.021096,33.607541],"type":"Point"}
}