{
  "type": "Feature",
  "properties": {
    "addr:full":"102 Timberwind Dr New Market AL 35761",
    "addr:housenumber":"102",
    "addr:postcode":"35761",
    "addr:street":"Timberwind Dr",
    "iso:country":"US",
    "sg:address":"102 Timberwind Dr",
    "sg:city":"New Market",
    "sg:classifiers":[
        {
            "category":"Professional",
            "type":"Services"
        }
    ],
    "sg:phone":"+1 256 828 5269",
    "sg:postcode":"35761",
    "sg:province":"AL",
    "wof:name":"Bart J Darwin",
    "wof:placetype":"venue"
},
  "geometry": {"coordinates":[-86.504378,34.894],"type":"Point"}
}