{
  "type": "Feature",
  "properties": {
    "iso:country":"US",
    "sg:address":"5612 Smith Rd",
    "sg:city":"Pell City",
    "sg:classifiers":[
        {
            "category":"Insurance",
            "subcategory":"Hazard Insurance",
            "type":"Services"
        }
    ],
    "sg:phone":"+1 205 338 2800",
    "sg:postcode":"35128",
    "sg:province":"AL",
    "sg:tags":[
        "bond"
    ],
    "wof:name":"Harmon's Bonding Co",
    "wof:placetype":"venue"
},
  "geometry": {"coordinates":[-86.259638,33.523586],"type":"Point"}
}