{
  "type": "Feature",
  "properties": {
    "addr:full":"1720 Cong W L Dickinson Dr Montgomery AL 36109",
    "addr:housenumber":"1720",
    "addr:postcode":"36109",
    "addr:street":"Cong W L Dickinson Dr",
    "iso:country":"US",
    "sg:address":"1720 Cong W L Dickinson Dr",
    "sg:city":"Montgomery",
    "sg:classifiers":[
        {
            "category":"Government",
            "subcategory":"Office",
            "type":"Public Place"
        }
    ],
    "sg:phone":"+1 334 271 7200",
    "sg:postcode":"36109",
    "sg:province":"AL",
    "sg:tags":[
        "state",
        "security"
    ],
    "wof:name":"Adjutant General",
    "wof:placetype":"venue"
},
  "geometry": {"coordinates":[-86.261932,32.407615],"type":"Point"}
}