{
  "type": "Feature",
  "properties": {
    "iso:country":"US",
    "sg:address":"598 N High St",
    "sg:city":"Tuscumbia",
    "sg:classifiers":[
        {
            "category":"Education",
            "subcategory":"School",
            "type":"Public Place"
        }
    ],
    "sg:phone":"+1 256 389 2920",
    "sg:postcode":"35674",
    "sg:province":"AL",
    "wof:name":"Deshler Middle School",
    "wof:placetype":"venue"
},
  "geometry": {"coordinates":[-87.697826,34.73719],"type":"Point"}
}