{
  "type": "Feature",
  "properties": {
    "addr:full":"598 N High St Tuscumbia AL 35674",
    "addr:housenumber":"598",
    "addr:postcode":"35674",
    "addr:street":"N High St",
    "iso:country":"US",
    "sg:address":"598 N High St",
    "sg:city":"Tuscumbia",
    "sg:classifiers":[
        {
            "category":"Education",
            "subcategory":"School",
            "type":"Public Place"
        }
    ],
    "sg:phone":"+1 256 389 2920",
    "sg:postcode":"35674",
    "sg:province":"AL",
    "wof:name":"Deshler Middle School",
    "wof:placetype":"venue"
},
  "geometry": {"coordinates":[-87.69782600000001,34.73719],"type":"Point"}
}