{
  "type": "Feature",
  "properties": {
    "addr:full":"2900 Morgan Rd Bessemer AL 35022",
    "addr:housenumber":"2900",
    "addr:postcode":"35022",
    "addr:street":"Morgan Rd",
    "iso:country":"US",
    "sg:address":"2900 Morgan Rd",
    "sg:city":"Bessemer",
    "sg:classifiers":[
        {
            "category":"Food & Beverages",
            "subcategory":"Groceries & Convenience Stores",
            "type":"Retail Goods"
        }
    ],
    "sg:phone":"+1 205 424 2433",
    "sg:postcode":"35022",
    "sg:province":"AL",
    "sg:tags":[
        "convenient"
    ],
    "wof:name":"Johnson Food Mart Inc",
    "wof:placetype":"venue"
},
  "geometry": {"coordinates":[-86.917564,33.336847],"type":"Point"}
}