{
  "type": "Feature",
  "properties": {
    "addr:full":"14031 S Wintzell Ave Bayou La Batre AL 36509",
    "addr:housenumber":"14031",
    "addr:postcode":"36509",
    "addr:street":"S Wintzell Ave Bayou La",
    "iso:country":"US",
    "sg:address":"14031 S Wintzell Ave",
    "sg:city":"Bayou La Batre",
    "sg:classifiers":[
        {
            "category":"Restaurant",
            "type":"Food & Drink"
        }
    ],
    "sg:menulink":"http://www.allmenus.com/al/bayou-la-batre/72838-pizza-hut/menu/",
    "sg:phone":"+1 251 824 3177",
    "sg:postcode":"36509",
    "sg:province":"AL",
    "sg:tags":[
        "american",
        "pizza"
    ],
    "wof:name":"Pizza Hut",
    "wof:placetype":"venue"
},
  "geometry": {"coordinates":[-88.246933,30.398005],"type":"Point"}
}