{
  "type": "Feature",
  "properties": {
    "iso:country":"US",
    "sg:address":"1251 Old Birmingham Hwy",
    "sg:city":"Sylacauga",
    "sg:phone":"+1 256 245 5478",
    "sg:postcode":"35150",
    "sg:province":"AL",
    "sg:tags":[
        "oil"
    ],
    "sg:website":"www.allenoil.com",
    "wof:name":"Allen Oil Co Of Sylacauga",
    "wof:placetype":"venue"
},
  "geometry": {"coordinates":[-86.271124,33.172449],"type":"Point"}
}