{
  "type": "Feature",
  "properties": {
    "addr:full":"9076 Madison Blvd Madison AL 35758",
    "addr:housenumber":"9076",
    "addr:postcode":"35758",
    "addr:street":"Madison Blvd",
    "iso:country":"US",
    "sg:address":"9076 Madison Blvd",
    "sg:city":"Madison",
    "sg:classifiers":[
        {
            "category":"Wholesale",
            "subcategory":"Machinery & Supplies",
            "type":"Manufacturing & Wholesale Goods"
        }
    ],
    "sg:phone":"+1 256 464 5675",
    "sg:postcode":"35758",
    "sg:province":"AL",
    "sg:tags":[
        "equipment",
        "establishment"
    ],
    "wof:name":"Sally Beauty Supply",
    "wof:placetype":"venue"
},
  "geometry": {"coordinates":[-86.756488,34.674899],"type":"Point"}
}