{
  "type": "Feature",
  "properties": {
    "iso:country":"US",
    "sg:address":"2312 Harrison St",
    "sg:city":"Tuscaloosa",
    "sg:classifiers":[
        {
            "category":"Recreation",
            "type":"Entertainment"
        }
    ],
    "sg:phone":"+1 205 758 4101",
    "sg:postcode":"35401",
    "sg:province":"AL",
    "sg:tags":[
        "club",
        "membership"
    ],
    "wof:name":"Sawyerville Hunting",
    "wof:placetype":"venue"
},
  "geometry": {"coordinates":[-87.54113,33.188688],"type":"Point"}
}