{
  "type": "Feature",
  "properties": {
    "iso:country":"US",
    "sg:address":"22 Sandusky Ln",
    "sg:city":"Gadsden",
    "sg:classifiers":[
        {
            "category":"Building & Trades",
            "subcategory":"Construction",
            "type":"Services"
        }
    ],
    "sg:phone":"+1 256 543 8443",
    "sg:postcode":"35904",
    "sg:province":"AL",
    "sg:tags":[
        "contractor"
    ],
    "wof:name":"Carl Smith Siding",
    "wof:placetype":"venue"
},
  "geometry": {"coordinates":[-86.051429,34.025814],"type":"Point"}
}