{
  "type": "Feature",
  "properties": {
    "addr:full":"3603 Pebble Creek Ln Dothan AL 36303",
    "addr:housenumber":"3603",
    "addr:postcode":"36303",
    "addr:street":"Pebble Creek Ln",
    "iso:country":"US",
    "sg:address":"3603 Pebble Creek Ln",
    "sg:city":"Dothan",
    "sg:classifiers":[
        {
            "category":"Professional",
            "subcategory":"Business Services",
            "type":"Services"
        }
    ],
    "sg:phone":"+1 334 673 1239",
    "sg:postcode":"36303",
    "sg:province":"AL",
    "wof:name":"Sloop Enterprises Inc",
    "wof:placetype":"venue"
},
  "geometry": {"coordinates":[-85.44957700000001,31.259211],"type":"Point"}
}