{
  "type": "Feature",
  "properties": {
    "addr:full":"106 Cooper St Union Springs AL 36089",
    "addr:housenumber":"106",
    "addr:postcode":"36089",
    "addr:street":"Cooper St",
    "iso:country":"US",
    "sg:address":"106 Cooper St",
    "sg:city":"Union Springs",
    "sg:classifiers":[
        {
            "category":"Manufacturing",
            "subcategory":"Lumber",
            "type":"Manufacturing & Wholesale Goods"
        }
    ],
    "sg:phone":"+1 334 738 3040",
    "sg:postcode":"36089",
    "sg:province":"AL",
    "sg:tags":[
        "government"
    ],
    "wof:name":"Forestry Commission",
    "wof:placetype":"venue"
},
  "geometry": {"coordinates":[-85.71062499999999,32.144352],"type":"Point"}
}