{
  "type": "Feature",
  "properties": {
    "iso:country":"US",
    "sg:address":"4731 Campanella Dr S",
    "sg:city":"Theodore",
    "sg:classifiers":[
        {
            "category":"Building & Trades",
            "subcategory":"Construction",
            "type":"Services"
        }
    ],
    "sg:phone":"+1 251 653 5203",
    "sg:postcode":"36582",
    "sg:province":"AL",
    "sg:tags":[
        "floor",
        "laying",
        "contractor"
    ],
    "wof:name":"R Evans Carpet Installer",
    "wof:placetype":"venue"
},
  "geometry": {"coordinates":[-88.15142400000001,30.535215],"type":"Point"}
}