{
  "type": "Feature",
  "properties": {
    "addr:full":"208 W Powell St Dothan AL 36303",
    "addr:housenumber":"208",
    "addr:postcode":"36303",
    "addr:street":"W Powell St",
    "iso:country":"US",
    "sg:address":"208 W Powell St",
    "sg:city":"Dothan",
    "sg:classifiers":[
        {
            "category":"Autos & Motor Vehicles",
            "subcategory":"Automobile Sales",
            "type":"Retail Goods"
        }
    ],
    "sg:phone":"+1 334 393 6880",
    "sg:postcode":"36303",
    "sg:province":"AL",
    "sg:tags":[
        "car",
        "dealer"
    ],
    "wof:name":"Dothan Motor Co",
    "wof:placetype":"venue"
},
  "geometry": {"coordinates":[-85.395528,31.230368],"type":"Point"}
}