{
  "type": "Feature",
  "properties": {
    "iso:country":"US",
    "sg:address":"3421 S Shades Crest Rd",
    "sg:city":"Birmingham",
    "sg:classifiers":[
        {
            "category":"Sports & Exercise",
            "subcategory":"Gym",
            "type":"Entertainment"
        }
    ],
    "sg:phone":"+1 205 982 6262",
    "sg:postcode":"35244",
    "sg:province":"AL",
    "sg:tags":[
        "club",
        "health",
        "studio",
        "gymnasium"
    ],
    "wof:name":"Curves For Women",
    "wof:placetype":"venue"
},
  "geometry": {"coordinates":[-86.872776,33.34054],"type":"Point"}
}