{
  "type": "Feature",
  "properties": {
    "iso:country":"US",
    "sg:address":"439 Saint Nicholas Ave",
    "sg:city":"Brewton",
    "sg:classifiers":[
        {
            "category":"Home & Garden",
            "subcategory":"Household Appliances",
            "type":"Retail Goods"
        },
        {
            "category":"Building & Trades",
            "subcategory":"Construction",
            "type":"Services"
        },
        {
            "category":"Building & Trades",
            "subcategory":"Electrical",
            "type":"Services"
        }
    ],
    "sg:phone":"+1 251 867 9255",
    "sg:postcode":"36426",
    "sg:province":"AL",
    "sg:tags":[
        "repair",
        "electrician",
        "system",
        "specialty",
        "pump",
        "heating",
        "contractor",
        "heat",
        "air conditioning"
    ],
    "wof:name":"Air Refrigeration & Contracting LLC",
    "wof:placetype":"venue"
},
  "geometry": {"coordinates":[-87.07357,31.112217],"type":"Point"}
}