{
  "type": "Feature",
  "properties": {
    "addr:full":"1204 Regency Blvd SE Decatur AL 35601",
    "addr:housenumber":"1204",
    "addr:postcode":"35601",
    "addr:street":"Regency Blvd Se",
    "iso:country":"US",
    "sg:address":"1204 Regency Blvd SE",
    "sg:city":"Decatur",
    "sg:classifiers":[
        {
            "category":"Communications",
            "type":"Services"
        }
    ],
    "sg:phone":"+1 256 355 2616",
    "sg:postcode":"35601",
    "sg:province":"AL",
    "wof:name":"Pointe Mallard Estates",
    "wof:placetype":"venue"
},
  "geometry": {"coordinates":[-86.944771,34.586704],"type":"Point"}
}