{
  "type": "Feature",
  "properties": {
    "iso:country":"US",
    "sg:address":"4030 Morris Ave",
    "sg:city":"Birmingham",
    "sg:classifiers":[
        {
            "category":"Retail",
            "subcategory":"Auto Repair",
            "type":"Services"
        }
    ],
    "sg:phone":"+1 205 591 5086",
    "sg:postcode":"35222",
    "sg:province":"AL",
    "sg:tags":[
        "repairing",
        "automobile"
    ],
    "wof:name":"Beasley Auto & Truck Repair",
    "wof:placetype":"venue"
},
  "geometry": {"coordinates":[-86.778242,33.526681],"type":"Point"}
}