{
  "type": "Feature",
  "properties": {
    "iso:country":"US",
    "sg:address":"201 Gilliam St",
    "sg:city":"Abbeville",
    "sg:classifiers":[
        {
            "category":"Professional",
            "type":"Services"
        }
    ],
    "sg:phone":"+1 334 585 6378",
    "sg:postcode":"36310",
    "sg:province":"AL",
    "sg:tags":[
        "establishment"
    ],
    "wof:name":"Abbeville Intermediate Lunc",
    "wof:placetype":"venue"
},
  "geometry": {"coordinates":[-85.240167,31.563421],"type":"Point"}
}