{
  "type": "Feature",
  "properties": {
    "iso:country":"US",
    "sg:address":"507 Green Springs Ave S",
    "sg:city":"Birmingham",
    "sg:classifiers":[
        {
            "category":"Communications",
            "subcategory":"Television Station",
            "type":"Services"
        }
    ],
    "sg:phone":"+1 205 226 9944",
    "sg:postcode":"35205",
    "sg:province":"AL",
    "sg:tags":[
        "distributor",
        "program",
        "producer"
    ],
    "wof:name":"Barefoot Productions",
    "wof:placetype":"venue"
},
  "geometry": {"coordinates":[-86.817314,33.484904],"type":"Point"}
}