{
  "type": "Feature",
  "properties": {
    "iso:country":"US",
    "sg:address":"3511 Vistamont Cir S",
    "sg:city":"Gadsden",
    "sg:classifiers":[
        {
            "category":"Railroad",
            "type":"Transportation"
        }
    ],
    "sg:phone":"+1 256 442 8126",
    "sg:postcode":"35907",
    "sg:province":"AL",
    "sg:tags":[
        "operator",
        "line"
    ],
    "wof:name":"Federal Railroad ADM",
    "wof:placetype":"venue"
},
  "geometry": {"coordinates":[-86.01274100000001,33.932885],"type":"Point"}
}