{
  "type": "Feature",
  "properties": {
    "addr:full":"3192 Co Rd 203 Dothan AL 36301",
    "addr:housenumber":"3192",
    "addr:postcode":"203;36301",
    "addr:street":"Co Rd",
    "iso:country":"US",
    "sg:address":"3192 Co Rd 203",
    "sg:city":"Dothan",
    "sg:classifiers":[
        {
            "category":"Freight",
            "type":"Transportation"
        }
    ],
    "sg:phone":"+1 334 794 6551",
    "sg:postcode":"36301",
    "sg:province":"AL",
    "sg:tags":[
        "trucking"
    ],
    "wof:name":"K A Carroll Trucking",
    "wof:placetype":"venue"
},
  "geometry": {"coordinates":[-85.427252,31.154502],"type":"Point"}
}