{
  "type": "Feature",
  "properties": {
    "iso:country":"US",
    "sg:address":"6467 US Hwy 431",
    "sg:city":"Owens Cross Roads",
    "sg:classifiers":[
        {
            "category":"Retail",
            "subcategory":"Repair Shop",
            "type":"Services"
        }
    ],
    "sg:phone":"+1 256 518 9709",
    "sg:postcode":"35763",
    "sg:province":"AL",
    "wof:name":"Hampton Cove Tire & Auto Ctr",
    "wof:placetype":"venue"
},
  "geometry": {"coordinates":[-86.486021,34.664535],"type":"Point"}
}