{
  "type": "Feature",
  "properties": {
    "addr:full":"5821 Acacia Ct Montgomery AL 36117",
    "addr:housenumber":"5821",
    "addr:postcode":"36117",
    "addr:street":"Acacia Ct",
    "iso:country":"US",
    "sg:address":"5821 Acacia Ct",
    "sg:city":"Montgomery",
    "sg:classifiers":[
        {
            "category":"Professional",
            "subcategory":"Business Services",
            "type":"Services"
        }
    ],
    "sg:phone":"+1 334 277 0636",
    "sg:postcode":"36117",
    "sg:province":"AL",
    "sg:tags":[
        "computer"
    ],
    "wof:name":"Computer Business System",
    "wof:placetype":"venue"
},
  "geometry": {"coordinates":[-86.197429,32.40013],"type":"Point"}
}