{
  "type": "Feature",
  "properties": {
    "iso:country":"US",
    "sg:address":"1821 Sherman St SE",
    "sg:city":"Decatur",
    "sg:classifiers":[
        {
            "category":"Organizations",
            "subcategory":"Labor Organization",
            "type":"Services"
        }
    ],
    "sg:phone":"+1 256 353 4116",
    "sg:postcode":"35601",
    "sg:province":"AL",
    "wof:name":"United Fd & Coml Wkrs Local 8",
    "wof:placetype":"venue"
},
  "geometry": {"coordinates":[-86.963301,34.599337],"type":"Point"}
}