{
  "type": "Feature",
  "properties": {
    "iso:country":"US",
    "sg:address":"373 S Greeno Rd",
    "sg:city":"Fairhope",
    "sg:classifiers":[
        {
            "category":"Restaurant",
            "type":"Food & Drink"
        }
    ],
    "sg:menulink":"http://www.allmenus.com/al/fairhope/107367-waffle-house/menu/",
    "sg:phone":"+1 251 990 2996",
    "sg:postcode":"36532",
    "sg:province":"AL",
    "sg:tags":[
        "american"
    ],
    "wof:name":"Waffle House",
    "wof:placetype":"venue"
},
  "geometry": {"coordinates":[-87.88618099999999,30.515104],"type":"Point"}
}