{
  "type": "Feature",
  "properties": {
    "iso:country":"US",
    "sg:address":"3737 Government Blvd",
    "sg:city":"Mobile",
    "sg:classifiers":[
        {
            "category":"Professional",
            "subcategory":"Management & Consulting",
            "type":"Services"
        }
    ],
    "sg:phone":"+1 251 666 9221",
    "sg:postcode":"36693",
    "sg:province":"AL",
    "wof:name":"Phoenix Care Management Inc",
    "wof:placetype":"venue"
},
  "geometry": {"coordinates":[-88.13311,30.643594],"type":"Point"}
}