{
  "type": "Feature",
  "properties": {
    "iso:country":"US",
    "sg:address":"205 State St",
    "sg:city":"Mobile",
    "sg:classifiers":[
        {
            "category":"Professional",
            "subcategory":"Lawyer & Legal Services",
            "type":"Services"
        }
    ],
    "sg:phone":"+1 251 434 9912",
    "sg:postcode":"36603",
    "sg:province":"AL",
    "sg:tags":[
        "attorney"
    ],
    "wof:name":"Tommy W Patterson Atty At Law",
    "wof:placetype":"venue"
},
  "geometry": {"coordinates":[-88.04561200000001,30.695204],"type":"Point"}
}