{
  "type": "Feature",
  "properties": {
    "iso:country":"US",
    "sg:address":"409 N Main St",
    "sg:city":"Enterprise",
    "sg:classifiers":[
        {
            "category":"Health Services",
            "subcategory":"Doctor",
            "type":"Services"
        }
    ],
    "sg:phone":"+1 334 393 8252",
    "sg:postcode":"36330",
    "sg:province":"AL",
    "sg:tags":[
        "physician",
        "medical",
        "surgeon"
    ],
    "wof:name":"Eurology Clinic Lower Alabama",
    "wof:placetype":"venue"
},
  "geometry": {"coordinates":[-85.857202,31.318228],"type":"Point"}
}