{
  "type": "Feature",
  "properties": {
    "iso:country":"US",
    "sg:address":"1639 Kowaliga Rd",
    "sg:city":"Eclectic",
    "sg:classifiers":[
        {
            "category":"Organizations",
            "subcategory":"Religious Organization",
            "type":"Services"
        }
    ],
    "sg:phone":"+1 334 541 3051",
    "sg:postcode":"36024",
    "sg:province":"AL",
    "sg:tags":[
        "church"
    ],
    "wof:name":"Healing Waters Church Of God",
    "wof:placetype":"venue"
},
  "geometry": {"coordinates":[-86.049024,32.654042],"type":"Point"}
}