{
  "type": "Feature",
  "properties": {
    "iso:country":"US",
    "sg:address":"2310 Huntsville Rd",
    "sg:city":"Florence",
    "sg:classifiers":[
        {
            "category":"Professional",
            "subcategory":"Accounting & Tax Preparation",
            "type":"Services"
        }
    ],
    "sg:phone":"+1 256 766 9810",
    "sg:postcode":"35630",
    "sg:province":"AL",
    "sg:tags":[
        "return"
    ],
    "wof:name":"Briggs Tax Service",
    "wof:placetype":"venue"
},
  "geometry": {"coordinates":[-87.647042,34.810694],"type":"Point"}
}