{
  "type": "Feature",
  "properties": {
    "iso:country":"US",
    "sg:address":"17 Rambo Dr",
    "sg:city":"Saraland",
    "sg:classifiers":[
        {
            "category":"Personal",
            "subcategory":"Beauty Salon",
            "type":"Services"
        }
    ],
    "sg:phone":"+1 251 442 3500",
    "sg:postcode":"36571",
    "sg:province":"AL",
    "sg:tags":[
        "shop"
    ],
    "wof:name":"Salon Eclipse",
    "wof:placetype":"venue"
},
  "geometry": {"coordinates":[-88.067875,30.831008],"type":"Point"}
}