{
  "type": "Feature",
  "properties": {
    "addr:full":"296 Co Rd 68 W Deatsville AL 36022",
    "addr:housenumber":"296;68",
    "addr:postcode":"36022",
    "addr:street":"Co Rd;W Deatsville",
    "iso:country":"US",
    "sg:address":"296 Co Rd 68 W",
    "sg:city":"Deatsville",
    "sg:classifiers":[
        {
            "category":"Wholesale",
            "subcategory":"Home Furnishings",
            "type":"Manufacturing & Wholesale Goods"
        }
    ],
    "sg:phone":"+1 334 285 8585",
    "sg:postcode":"36022",
    "sg:province":"AL",
    "sg:tags":[
        "curtain",
        "drapery"
    ],
    "wof:name":"Lee Edwards & Assoc",
    "wof:placetype":"venue"
},
  "geometry": {"coordinates":[-86.513729,32.659307],"type":"Point"}
}