{
  "type": "Feature",
  "properties": {
    "iso:country":"US",
    "sg:address":"1050 Harborview Dr NE",
    "sg:city":"Decatur",
    "sg:classifiers":[
        {
            "category":"Real Estate",
            "subcategory":"Real Estate Operator",
            "type":"Services"
        }
    ],
    "sg:phone":"+1 256 355 1325",
    "sg:postcode":"35601",
    "sg:province":"AL",
    "sg:tags":[
        "apartment"
    ],
    "wof:name":"Rhodes Ferry Apartments",
    "wof:placetype":"venue"
},
  "geometry": {"coordinates":[-86.982682,34.614871],"type":"Point"}
}