{
  "type": "Feature",
  "properties": {
    "iso:country":"US",
    "sg:address":"1100 Sand Rock Rd",
    "sg:city":"Anniston",
    "sg:classifiers":[
        {
            "category":"Manufacturing",
            "subcategory":"Jewelry",
            "type":"Manufacturing & Wholesale Goods"
        }
    ],
    "sg:phone":"+1 256 831 2653",
    "sg:postcode":"36207",
    "sg:province":"AL",
    "sg:tags":[
        "precious",
        "metal",
        "mfg"
    ],
    "wof:name":"Lauren Chloe",
    "wof:placetype":"venue"
},
  "geometry": {"coordinates":[-85.795937,33.63379],"type":"Point"}
}