{
  "type": "Feature",
  "properties": {
    "iso:country":"US",
    "sg:address":"4850 Chana Creek Rd",
    "sg:city":"Tallassee",
    "sg:classifiers":[
        {
            "category":"Organizations",
            "subcategory":"Religious Organization",
            "type":"Services"
        }
    ],
    "sg:phone":"+1 334 541 2160",
    "sg:postcode":"36078",
    "sg:province":"AL",
    "wof:name":"Providnce Prmtive Bptst Church",
    "wof:placetype":"venue"
},
  "geometry": {"coordinates":[-85.955369,32.619312],"type":"Point"}
}