{
  "type": "Feature",
  "properties": {
    "addr:full":"400 W Fort Williams St Sylacauga AL 35150",
    "addr:housenumber":"400",
    "addr:postcode":"35150",
    "addr:street":"W Fort Williams St",
    "iso:country":"US",
    "sg:address":"400 W Fort Williams St",
    "sg:city":"Sylacauga",
    "sg:classifiers":[
        {
            "category":"Health Services",
            "subcategory":"Doctor",
            "type":"Services"
        }
    ],
    "sg:phone":"+1 256 249 0061",
    "sg:postcode":"35150",
    "sg:province":"AL",
    "sg:tags":[
        "physician",
        "surgeon"
    ],
    "wof:name":"Sylacauga Medical & Surg Clnc",
    "wof:placetype":"venue"
},
  "geometry": {"coordinates":[-86.257882,33.167339],"type":"Point"}
}