{
  "type": "Feature",
  "properties": {
    "iso:country":"US",
    "sg:address":"112 W Cottonwood Rd",
    "sg:city":"Dothan",
    "sg:classifiers":[
        {
            "category":"Banks & Credit Unions",
            "subcategory":"Bank",
            "type":"Services"
        },
        {
            "category":"Banks & Credit Unions",
            "subcategory":"Financial Services",
            "type":"Services"
        }
    ],
    "sg:phone":"+1 334 712 4397",
    "sg:postcode":"36301",
    "sg:province":"AL",
    "sg:tags":[
        "commercial",
        "loan",
        "saving",
        "mortgage"
    ],
    "sg:website":"https://www.wachovia.com/?DCMP=KNL-CPS-DS-Directory-0703&HBX_PK=Banks&HBX_OU=71",
    "wof:name":"Wachovia Bank",
    "wof:placetype":"venue"
},
  "geometry": {"coordinates":[-85.392099,31.208763],"type":"Point"}
}