{
  "type": "Feature",
  "properties": {
    "iso:country":"US",
    "sg:address":"221 Hillside Trl",
    "sg:city":"Gadsden",
    "sg:classifiers":[
        {
            "category":"Professional",
            "subcategory":"Management & Consulting",
            "type":"Services"
        }
    ],
    "sg:phone":"+1 256 442 1871",
    "sg:postcode":"35901",
    "sg:province":"AL",
    "sg:tags":[
        "business"
    ],
    "wof:name":"John D Mc Cord",
    "wof:placetype":"venue"
},
  "geometry": {"coordinates":[-86.026681,33.951725],"type":"Point"}
}