{
  "type": "Feature",
  "properties": {
    "iso:country":"US",
    "sg:address":"1557 Jackson Ferry Rd",
    "sg:city":"Montgomery",
    "sg:classifiers":[
        {
            "category":"Freight",
            "type":"Transportation"
        }
    ],
    "sg:phone":"+1 334 240 0918",
    "sg:postcode":"36104",
    "sg:province":"AL",
    "sg:tags":[
        "operator",
        "trucking"
    ],
    "sg:website":"www.service-transport.com",
    "wof:name":"Service Transport Inc",
    "wof:placetype":"venue"
},
  "geometry": {"coordinates":[-86.306752,32.405761],"type":"Point"}
}