{
  "type": "Feature",
  "properties": {
    "addr:full":"2830 N Broad St Selma AL 36701",
    "addr:housenumber":"2830",
    "addr:postcode":"36701",
    "addr:street":"N Broad St",
    "iso:country":"US",
    "sg:address":"2830 N Broad St",
    "sg:city":"Selma",
    "sg:classifiers":[
        {
            "category":"Shopping",
            "subcategory":"Jewelry",
            "type":"Retail Goods"
        }
    ],
    "sg:phone":"+1 334 872 4769",
    "sg:postcode":"36701",
    "sg:province":"AL",
    "sg:tags":[
        "repair"
    ],
    "wof:name":"Roys Fine Jewelry",
    "wof:placetype":"venue"
},
  "geometry": {"coordinates":[-87.024412,32.439347],"type":"Point"}
}