{
  "type": "Feature",
  "properties": {
    "addr:full":"2701 Andrews Rd Opelika AL 36801",
    "addr:housenumber":"2701",
    "addr:postcode":"36801",
    "addr:street":"Andrews Rd",
    "iso:country":"US",
    "sg:address":"2701 Andrews Rd",
    "sg:city":"Opelika",
    "sg:classifiers":[
        {
            "category":"Freight",
            "type":"Transportation"
        }
    ],
    "sg:phone":"+1 334 741 3955",
    "sg:postcode":"36801",
    "sg:province":"AL",
    "sg:tags":[
        "dry",
        "bulk",
        "trucking"
    ],
    "sg:website":"www.transportindustries.com",
    "wof:name":"Clarksville Refrigerated Lines",
    "wof:placetype":"venue"
},
  "geometry": {"coordinates":[-85.332719,32.69687],"type":"Point"}
}