{
  "type": "Feature",
  "properties": {
    "iso:country":"US",
    "sg:address":"903 Main Ave",
    "sg:city":"Northport",
    "sg:classifiers":[
        {
            "category":"Home & Garden",
            "subcategory":"Garden Supply",
            "type":"Retail Goods"
        }
    ],
    "sg:phone":"+1 205 366 8600",
    "sg:postcode":"35476",
    "sg:province":"AL",
    "wof:name":"Canebrake Gardens",
    "wof:placetype":"venue"
},
  "geometry": {"coordinates":[-87.579263,33.221253],"type":"Point"}
}