{
  "type": "Feature",
  "properties": {
    "addr:full":"110 Laurel Breeze Dr Enterprise AL 36330",
    "addr:housenumber":"110",
    "addr:postcode":"36330",
    "addr:street":"Laurel Breeze Dr",
    "iso:country":"US",
    "sg:address":"110 Laurel Breeze Dr",
    "sg:city":"Enterprise",
    "sg:classifiers":[
        {
            "category":"Building & Trades",
            "subcategory":"Plumbing",
            "type":"Services"
        }
    ],
    "sg:phone":"+1 334 347 3237",
    "sg:postcode":"36330",
    "sg:province":"AL",
    "sg:tags":[
        "plumbing",
        "contractor"
    ],
    "wof:name":"KIRK Donaldson Plumbing",
    "wof:placetype":"venue"
},
  "geometry": {"coordinates":[-85.866467,31.379383],"type":"Point"}
}