{
  "type": "Feature",
  "properties": {
    "iso:country":"US",
    "sg:address":"962 Wildfork Rd",
    "sg:city":"Frisco City",
    "sg:classifiers":[
        {
            "category":"Retail",
            "subcategory":"Auto Repair",
            "type":"Services"
        }
    ],
    "sg:phone":"+1 251 765 2163",
    "sg:postcode":"36445",
    "sg:province":"AL",
    "sg:tags":[
        "wrecker"
    ],
    "wof:name":"E & S Automotive Towing",
    "wof:placetype":"venue"
},
  "geometry": {"coordinates":[-87.349283,31.419983],"type":"Point"}
}