{
  "type": "Feature",
  "properties": {
    "iso:country":"US",
    "sg:address":"11729 US Hwy 72",
    "sg:city":"Athens",
    "sg:classifiers":[
        {
            "category":"Farming",
            "subcategory":"Farm & Veterinary Services",
            "type":"Manufacturing & Wholesale Goods"
        }
    ],
    "sg:phone":"+1 256 729 6409",
    "sg:postcode":"35611",
    "sg:province":"AL",
    "sg:tags":[
        "crop",
        "harvesting"
    ],
    "wof:name":"Brownsferry Cotton Farm",
    "wof:placetype":"venue"
},
  "geometry": {"coordinates":[-87.112322,34.795139],"type":"Point"}
}