{
  "type": "Feature",
  "properties": {
    "iso:country":"US",
    "sg:address":"3498 Bel Air Mall",
    "sg:city":"Mobile",
    "sg:classifiers":[
        {
            "category":"Retail",
            "subcategory":"Repair Shop",
            "type":"Services"
        },
        {
            "category":"Shopping",
            "subcategory":"Jewelry",
            "type":"Retail Goods"
        }
    ],
    "sg:phone":"+1 251 479 2824",
    "sg:postcode":"36606",
    "sg:province":"AL",
    "wof:name":"MD Watch Service Inc",
    "wof:placetype":"venue"
},
  "geometry": {"coordinates":[-88.122272,30.670036],"type":"Point"}
}