{
  "type": "Feature",
  "properties": {
    "addr:full":"3382 Woolfolk Rd Munford AL 36268",
    "addr:housenumber":"3382",
    "addr:postcode":"36268",
    "addr:street":"Woolfolk Rd",
    "iso:country":"US",
    "sg:address":"3382 Woolfolk Rd",
    "sg:city":"Munford",
    "sg:classifiers":[
        {
            "category":"Organizations",
            "subcategory":"Religious Organization",
            "type":"Services"
        }
    ],
    "sg:phone":"+1 256 315 0707",
    "sg:postcode":"36268",
    "sg:province":"AL",
    "sg:tags":[
        "church"
    ],
    "wof:name":"Grace Community Church",
    "wof:placetype":"venue"
},
  "geometry": {"coordinates":[-86.025783,33.404104],"type":"Point"}
}