{
  "type": "Feature",
  "properties": {
    "addr:full":"2524 Commerce Sq W Birmingham AL 35210",
    "addr:housenumber":"2524",
    "addr:postcode":"35210",
    "addr:street":"Commerce Sq W",
    "iso:country":"US",
    "sg:address":"2524 Commerce Sq W",
    "sg:city":"Birmingham",
    "sg:classifiers":[
        {
            "category":"Wholesale",
            "subcategory":"Wine & Distilled Alcoholic Beverages",
            "type":"Manufacturing & Wholesale Goods"
        }
    ],
    "sg:phone":"+1 205 540 6994",
    "sg:postcode":"35210",
    "sg:province":"AL",
    "wof:name":"Rush",
    "wof:placetype":"venue"
},
  "geometry": {"coordinates":[-86.69999300000001,33.541436],"type":"Point"}
}