{
  "type": "Feature",
  "properties": {
    "addr:full":"910 Somerville Rd NE Decatur AL 35601",
    "addr:housenumber":"910",
    "addr:postcode":"35601",
    "addr:street":"Somerville Rd Ne",
    "iso:country":"US",
    "sg:address":"910 Somerville Rd NE",
    "sg:city":"Decatur",
    "sg:classifiers":[
        {
            "category":"Education",
            "subcategory":"School",
            "type":"Public Place"
        }
    ],
    "sg:phone":"+1 256 552 3033",
    "sg:postcode":"35601",
    "sg:province":"AL",
    "wof:name":"Somerville Rd Elementary Schl",
    "wof:placetype":"venue"
},
  "geometry": {"coordinates":[-86.972311,34.605627],"type":"Point"}
}