{
  "type": "Feature",
  "properties": {
    "addr:full":"4739 State Rte 119 Montevallo AL 35115",
    "addr:housenumber":"4739",
    "addr:postcode":"35115",
    "addr:street":"State Rte 119",
    "iso:country":"US",
    "sg:address":"4739 State Rte 119",
    "sg:city":"Montevallo",
    "sg:classifiers":[
        {
            "category":"Real Estate",
            "subcategory":"Real Estate Agent",
            "type":"Services"
        }
    ],
    "sg:phone":"+1 205 665 7773",
    "sg:postcode":"35115",
    "sg:province":"AL",
    "wof:name":"Mikul & Assoc",
    "wof:placetype":"venue"
},
  "geometry": {"coordinates":[-86.822588,33.151258],"type":"Point"}
}