{
  "type": "Feature",
  "properties": {
    "addr:full":"6549 Atlanta Hwy Montgomery AL 36117",
    "addr:housenumber":"6549",
    "addr:postcode":"36117",
    "addr:street":"Atlanta Hwy",
    "iso:country":"US",
    "sg:address":"6549 Atlanta Hwy",
    "sg:city":"Montgomery",
    "sg:classifiers":[
        {
            "category":"Shopping",
            "subcategory":"Clothing, Apparel, & Fashions",
            "type":"Retail Goods"
        }
    ],
    "sg:phone":"+1 334 260 2181",
    "sg:postcode":"36117",
    "sg:province":"AL",
    "sg:website":"www.cato.com",
    "wof:name":"Cato",
    "wof:placetype":"venue"
},
  "geometry": {"coordinates":[-86.18446,32.38236],"type":"Point"}
}