{
  "type": "Feature",
  "properties": {
    "addr:full":"448 E Forest Dr Birmingham AL 35235",
    "addr:housenumber":"448",
    "addr:postcode":"35235",
    "addr:street":"E Forest Dr",
    "iso:country":"US",
    "sg:address":"448 E Forest Dr",
    "sg:city":"Birmingham",
    "sg:classifiers":[
        {
            "category":"Professional",
            "subcategory":"Engineering",
            "type":"Services"
        }
    ],
    "sg:phone":"+1 205 833 2011",
    "sg:postcode":"35235",
    "sg:province":"AL",
    "wof:name":"Mega Enterprises",
    "wof:placetype":"venue"
},
  "geometry": {"coordinates":[-86.653521,33.58967],"type":"Point"}
}