{
  "type": "Feature",
  "properties": {
    "iso:country":"US",
    "sg:address":"5560 Nevius Rd",
    "sg:city":"Mobile",
    "sg:classifiers":[
        {
            "category":"Health Services",
            "subcategory":"Doctor",
            "type":"Services"
        }
    ],
    "sg:phone":"+1 251 666 3737",
    "sg:postcode":"36619",
    "sg:province":"AL",
    "sg:tags":[
        "medical"
    ],
    "wof:name":"Mobile Family Care",
    "wof:placetype":"venue"
},
  "geometry": {"coordinates":[-88.171233,30.596734],"type":"Point"}
}