{
  "type": "Feature",
  "properties": {
    "iso:country":"US",
    "sg:address":"569 Houston St",
    "sg:city":"Mobile",
    "sg:classifiers":[
        {
            "category":"Professional",
            "type":"Services"
        }
    ],
    "sg:phone":"+1 251 476 7900",
    "sg:postcode":"36606",
    "sg:province":"AL",
    "wof:name":"House of Judah",
    "wof:placetype":"venue"
},
  "geometry": {"coordinates":[-88.081273,30.671397],"type":"Point"}
}