{
  "type": "Feature",
  "properties": {
    "iso:country":"US",
    "sg:address":"2570 Mall Rd",
    "sg:city":"Florence",
    "sg:classifiers":[
        {
            "category":"Personal",
            "subcategory":"Beauty Salon",
            "type":"Services"
        }
    ],
    "sg:phone":"+1 256 766 2930",
    "sg:postcode":"35630",
    "sg:province":"AL",
    "sg:tags":[
        "shop"
    ],
    "wof:name":"Cut & Curl Salon",
    "wof:placetype":"venue"
},
  "geometry": {"coordinates":[-87.638383,34.835775],"type":"Point"}
}