{
  "type": "Feature",
  "properties": {
    "iso:country":"US",
    "sg:address":"1731 17th Ave S",
    "sg:city":"Pell City",
    "sg:classifiers":[
        {
            "category":"Farming",
            "subcategory":"Livestock Farm",
            "type":"Manufacturing & Wholesale Goods"
        }
    ],
    "sg:phone":"+1 205 338 3156",
    "sg:postcode":"35128",
    "sg:province":"AL",
    "sg:tags":[
        "equine"
    ],
    "wof:name":"Spotted R Farm",
    "wof:placetype":"venue"
},
  "geometry": {"coordinates":[-86.279163,33.569955],"type":"Point"}
}