{
  "type": "Feature",
  "properties": {
    "iso:country":"US",
    "sg:address":"4013 Kinross Ln",
    "sg:city":"Birmingham",
    "sg:classifiers":[
        {
            "category":"Banks & Credit Unions",
            "subcategory":"Financial Services",
            "type":"Services"
        }
    ],
    "sg:phone":"+1 205 980 8479",
    "sg:postcode":"35242",
    "sg:province":"AL",
    "sg:tags":[
        "mortgage"
    ],
    "wof:name":"A Wimberly & Assoc Mortga",
    "wof:placetype":"venue"
},
  "geometry": {"coordinates":[-86.67188,33.435441],"type":"Point"}
}