{
  "type": "Feature",
  "properties": {
    "addr:full":"7600 US Hwy 72 Alt Madison AL 35758",
    "addr:housenumber":"7600",
    "addr:postcode":"35758",
    "addr:street":"Us Hwy 72 Alt",
    "iso:country":"US",
    "sg:address":"7600 US Hwy 72 Alt",
    "sg:city":"Madison",
    "sg:classifiers":[
        {
            "category":"Professional",
            "subcategory":"Accounting & Tax Preparation",
            "type":"Services"
        }
    ],
    "sg:phone":"+1 256 864 8580",
    "sg:postcode":"35758",
    "sg:province":"AL",
    "sg:tags":[
        "accountant"
    ],
    "wof:name":"Precision Payroll & Accounting",
    "wof:placetype":"venue"
},
  "geometry": {"coordinates":[-86.702472,34.696145],"type":"Point"}
}