{
  "type": "Feature",
  "properties": {
    "addr:full":"816 7th St N Clanton AL 35045",
    "addr:housenumber":"816",
    "addr:postcode":"35045",
    "addr:street":"7Th St N",
    "iso:country":"US",
    "sg:address":"816 7th St N",
    "sg:city":"Clanton",
    "sg:classifiers":[
        {
            "category":"Utilities",
            "subcategory":"Mobile Phone",
            "type":"Services"
        }
    ],
    "sg:phone":"+1 205 280 2571",
    "sg:postcode":"35045",
    "sg:province":"AL",
    "sg:tags":[
        "telephone",
        "cellular"
    ],
    "wof:name":"Blue Streak Electric Equp",
    "wof:placetype":"venue"
},
  "geometry": {"coordinates":[-86.63363,32.845639],"type":"Point"}
}