{
  "type": "Feature",
  "properties": {
    "iso:country":"US",
    "sg:address":"120 Industrial Dr",
    "sg:city":"Birmingham",
    "sg:classifiers":[
        {
            "category":"Wholesale",
            "subcategory":"Groceries",
            "type":"Manufacturing & Wholesale Goods"
        }
    ],
    "sg:phone":"+1 205 942 2869",
    "sg:postcode":"35211",
    "sg:province":"AL",
    "sg:tags":[
        "tea",
        "coffee"
    ],
    "wof:name":"S & D Coffee Inc",
    "wof:placetype":"venue"
},
  "geometry": {"coordinates":[-86.849746,33.455109],"type":"Point"}
}