{
  "type": "Feature",
  "properties": {
    "addr:full":"1917 Highway 58 Helena AL 35080",
    "addr:housenumber":"1917",
    "addr:postcode":"35080",
    "addr:street":"Highway 58",
    "iso:country":"US",
    "sg:address":"1917 Highway 58",
    "sg:city":"Helena",
    "sg:classifiers":[
        {
            "category":"Restaurant",
            "type":"Food & Drink"
        }
    ],
    "sg:phone":"+1 205 664 0688",
    "sg:postcode":"35080",
    "sg:province":"AL",
    "sg:tags":[
        "house",
        "steak",
        "barbecue"
    ],
    "wof:name":"Zou's Kitchen",
    "wof:placetype":"venue"
},
  "geometry": {"coordinates":[-86.85179599999999,33.273647],"type":"Point"}
}