{
  "type": "Feature",
  "properties": {
    "iso:country":"US",
    "sg:address":"645 Coliseum Blvd",
    "sg:city":"Montgomery",
    "sg:classifiers":[
        {
            "category":"Organizations",
            "subcategory":"Religious Organization",
            "type":"Services"
        }
    ],
    "sg:phone":"+1 334 272 2591",
    "sg:postcode":"36109",
    "sg:province":"AL",
    "wof:name":"All Saints Episcopal Church",
    "wof:placetype":"venue"
},
  "geometry": {"coordinates":[-86.258413,32.393946],"type":"Point"}
}