{
  "type": "Feature",
  "properties": {
    "addr:full":"319 Park Ave Birmingham AL 35226",
    "addr:housenumber":"319",
    "addr:postcode":"35226",
    "addr:street":"Park Ave",
    "iso:country":"US",
    "sg:address":"319 Park Ave",
    "sg:city":"Birmingham",
    "sg:classifiers":[
        {
            "category":"Professional",
            "type":"Services"
        }
    ],
    "sg:phone":"+1 205 823 8087",
    "sg:postcode":"35226",
    "sg:province":"AL",
    "wof:name":"Rachels Garden",
    "wof:placetype":"venue"
},
  "geometry": {"coordinates":[-86.855155,33.39196],"type":"Point"}
}