{
  "type": "Feature",
  "properties": {
    "addr:full":"2 S Dubois Ave Tallassee AL 36078",
    "addr:housenumber":"2",
    "addr:postcode":"36078",
    "addr:street":"S Dubois Ave",
    "iso:country":"US",
    "sg:address":"2 S Dubois Ave",
    "sg:city":"Tallassee",
    "sg:classifiers":[
        {
            "category":"Professional",
            "subcategory":"Lawyer & Legal Services",
            "type":"Services"
        }
    ],
    "sg:phone":"+1 334 283 6548",
    "sg:postcode":"36078",
    "sg:province":"AL",
    "sg:tags":[
        "attorney"
    ],
    "wof:name":"Bowles & Cottle",
    "wof:placetype":"venue"
},
  "geometry": {"coordinates":[-85.89478699999999,32.536104],"type":"Point"}
}