{
  "type": "Feature",
  "properties": {
    "addr:full":"207 Sanford Ave Eufaula AL 36027",
    "addr:housenumber":"207",
    "addr:postcode":"36027",
    "addr:street":"Sanford Ave",
    "iso:country":"US",
    "sg:address":"207 Sanford Ave",
    "sg:city":"Eufaula",
    "sg:classifiers":[
        {
            "category":"Retail",
            "subcategory":"Portrait Studio",
            "type":"Services"
        }
    ],
    "sg:phone":"+1 334 687 4356",
    "sg:postcode":"36027",
    "sg:province":"AL",
    "sg:tags":[
        "photo"
    ],
    "wof:name":"Precious Images",
    "wof:placetype":"venue"
},
  "geometry": {"coordinates":[-85.15062,31.895484],"type":"Point"}
}