{
  "type": "Feature",
  "properties": {
    "addr:full":"2800 9th St Northport AL 35476",
    "addr:housenumber":"2800",
    "addr:postcode":"35476",
    "addr:street":"9Th St",
    "iso:country":"US",
    "sg:address":"2800 9th St",
    "sg:city":"Northport",
    "sg:classifiers":[
        {
            "category":"Wholesale",
            "subcategory":"Auto Parts",
            "type":"Manufacturing & Wholesale Goods"
        }
    ],
    "sg:phone":"+1 205 758 2734",
    "sg:postcode":"35476",
    "sg:province":"AL",
    "sg:tags":[
        "automobile",
        "supply"
    ],
    "wof:name":"Automotive Industries",
    "wof:placetype":"venue"
},
  "geometry": {"coordinates":[-87.585858,33.222026],"type":"Point"}
}