{
  "type": "Feature",
  "properties": {
    "addr:full":"739 Oliver Rd Montgomery AL 36117",
    "addr:housenumber":"739",
    "addr:postcode":"36117",
    "addr:street":"Oliver Rd",
    "iso:country":"US",
    "sg:address":"739 Oliver Rd",
    "sg:city":"Montgomery",
    "sg:classifiers":[
        {
            "category":"Wholesale",
            "subcategory":"Machinery & Supplies",
            "type":"Manufacturing & Wholesale Goods"
        },
        {
            "category":"Home & Garden",
            "subcategory":"Hardware",
            "type":"Retail Goods"
        }
    ],
    "sg:phone":"+1 334 272 0500",
    "sg:postcode":"36117",
    "sg:province":"AL",
    "sg:tags":[
        "tool"
    ],
    "wof:name":"Newman Industrial Supply LLC",
    "wof:placetype":"venue"
},
  "geometry": {"coordinates":[-86.206811,32.399723],"type":"Point"}
}