{
  "type": "Feature",
  "properties": {
    "iso:country":"US",
    "sg:address":"2125 McCoy Ave",
    "sg:city":"Anniston",
    "sg:classifiers":[
        {
            "category":"Home & Garden",
            "subcategory":"Furniture",
            "type":"Retail Goods"
        }
    ],
    "sg:phone":"+1 256 236 1199",
    "sg:postcode":"36201",
    "sg:province":"AL",
    "sg:tags":[
        "top",
        "counter"
    ],
    "wof:name":"Dreamcast Concrete Products",
    "wof:placetype":"venue"
},
  "geometry": {"coordinates":[-85.835778,33.672608],"type":"Point"}
}