{
  "type": "Feature",
  "properties": {
    "iso:country":"US",
    "sg:address":"500 19th Ave SE",
    "sg:city":"Decatur",
    "sg:classifiers":[
        {
            "category":"Manufacturing",
            "subcategory":"Textiles",
            "type":"Manufacturing & Wholesale Goods"
        }
    ],
    "sg:phone":"+1 256 350 7002",
    "sg:postcode":"35601",
    "sg:province":"AL",
    "sg:tags":[
        "cord",
        "fabric",
        "tire"
    ],
    "wof:name":"Goodyear Tire & Rubber Co",
    "wof:placetype":"venue"
},
  "geometry": {"coordinates":[-86.96298299999999,34.598893],"type":"Point"}
}