{
  "type": "Feature",
  "properties": {
    "iso:country":"US",
    "sg:address":"12279 Buhl Cutoff Rd",
    "sg:city":"Buhl",
    "sg:classifiers":[
        {
            "category":"Shopping",
            "subcategory":"Florist",
            "type":"Retail Goods"
        }
    ],
    "sg:phone":"+1 205 339 8077",
    "sg:postcode":"35446",
    "sg:province":"AL",
    "wof:name":"Special Occassions By Janice",
    "wof:placetype":"venue"
},
  "geometry": {"coordinates":[-87.74893,33.265513],"type":"Point"}
}