{
  "type": "Feature",
  "properties": {
    "addr:full":"16096 State Rte 216 Brookwood AL 35444",
    "addr:housenumber":"16096",
    "addr:postcode":"35444",
    "addr:street":"State Rte 216",
    "iso:country":"US",
    "sg:address":"16096 State Rte 216",
    "sg:city":"Brookwood",
    "sg:classifiers":[
        {
            "category":"Social Services",
            "subcategory":"Child Care",
            "type":"Services"
        }
    ],
    "sg:phone":"+1 205 562 0002",
    "sg:postcode":"35444",
    "sg:province":"AL",
    "sg:tags":[
        "day"
    ],
    "wof:name":"Kreative Kids",
    "wof:placetype":"venue"
},
  "geometry": {"coordinates":[-87.316816,33.259726],"type":"Point"}
}