{
  "type": "Feature",
  "properties": {
    "iso:country":"US",
    "sg:address":"18708 US Hwy 31",
    "sg:city":"Cullman",
    "sg:classifiers":[
        {
            "category":"Health Services",
            "subcategory":"Doctor",
            "type":"Services"
        }
    ],
    "sg:phone":"+1 256 739 8600",
    "sg:postcode":"35058",
    "sg:province":"AL",
    "wof:name":"Carmen Duke Moss DMD",
    "wof:placetype":"venue"
},
  "geometry": {"coordinates":[-86.864528,34.237068],"type":"Point"}
}