{
  "type": "Feature",
  "properties": {
    "iso:country":"US",
    "sg:address":"150 N Section St",
    "sg:city":"Fairhope",
    "sg:classifiers":[
        {
            "category":"Autos & Motor Vehicles",
            "subcategory":"Auto Supplies",
            "type":"Retail Goods"
        }
    ],
    "sg:phone":"+1 251 928 2194",
    "sg:postcode":"36532",
    "sg:province":"AL",
    "sg:tags":[
        "automobile",
        "parts"
    ],
    "wof:name":"Service First Auto Inc",
    "wof:placetype":"venue"
},
  "geometry": {"coordinates":[-87.902932,30.526774],"type":"Point"}
}