{
  "type": "Feature",
  "properties": {
    "iso:country":"US",
    "sg:address":"490 Holliday Dr",
    "sg:city":"Oneonta",
    "sg:classifiers":[
        {
            "category":"Building & Trades",
            "subcategory":"Construction",
            "type":"Services"
        }
    ],
    "sg:phone":"+1 205 274 8933",
    "sg:postcode":"35121",
    "sg:province":"AL",
    "sg:tags":[
        "contractor"
    ],
    "wof:name":"Noland Weston Roofing",
    "wof:placetype":"venue"
},
  "geometry": {"coordinates":[-86.41167,33.897762],"type":"Point"}
}