{
  "type": "Feature",
  "properties": {
    "addr:full":"30 Leon Dr Dothan AL 36301",
    "addr:housenumber":"30",
    "addr:postcode":"36301",
    "addr:street":"Leon Dr",
    "iso:country":"US",
    "sg:address":"30 Leon Dr",
    "sg:city":"Dothan",
    "sg:classifiers":[
        {
            "category":"Manufacturing",
            "subcategory":"Signs",
            "type":"Manufacturing & Wholesale Goods"
        }
    ],
    "sg:phone":"+1 334 677 3782",
    "sg:postcode":"36301",
    "sg:province":"AL",
    "sg:tags":[
        "repair",
        "installation"
    ],
    "wof:name":"Vital Signs",
    "wof:placetype":"venue"
},
  "geometry": {"coordinates":[-85.403683,31.121359],"type":"Point"}
}