{
  "type": "Feature",
  "properties": {
    "addr:full":"1258 Perry Hill Rd Montgomery AL 36109",
    "addr:housenumber":"1258",
    "addr:postcode":"36109",
    "addr:street":"Perry Hill Rd",
    "iso:country":"US",
    "sg:address":"1258 Perry Hill Rd",
    "sg:city":"Montgomery",
    "sg:classifiers":[
        {
            "category":"Professional",
            "subcategory":"Accounting & Tax Preparation",
            "type":"Services"
        }
    ],
    "sg:phone":"+1 334 273 9586",
    "sg:postcode":"36109",
    "sg:province":"AL",
    "wof:name":"C&E Physicians Billing SE",
    "wof:placetype":"venue"
},
  "geometry": {"coordinates":[-86.244254,32.361583],"type":"Point"}
}