{
  "type": "Feature",
  "properties": {
    "iso:country":"US",
    "sg:address":"2200 Gateway Dr",
    "sg:city":"Opelika",
    "sg:classifiers":[
        {
            "category":"Professional",
            "subcategory":"Employment Agencies",
            "type":"Services"
        }
    ],
    "sg:phone":"+1 334 742 9111",
    "sg:postcode":"36801",
    "sg:province":"AL",
    "sg:tags":[
        "temporary",
        "help",
        "contractor"
    ],
    "sg:website":"www.kellyservices.com",
    "wof:name":"Kelly Services Inc",
    "wof:placetype":"venue"
},
  "geometry": {"coordinates":[-85.40513300000001,32.624589],"type":"Point"}
}