{
  "type": "Feature",
  "properties": {
    "iso:country":"US",
    "sg:address":"1455 Red Hat Rd",
    "sg:city":"Decatur",
    "sg:classifiers":[
        {
            "category":"Wholesale",
            "subcategory":"Durable Goods & Equipment",
            "type":"Manufacturing & Wholesale Goods"
        }
    ],
    "sg:phone":"+1 256 301 5200",
    "sg:postcode":"35601",
    "sg:province":"AL",
    "sg:tags":[
        "exporter"
    ],
    "wof:name":"Oci Chemical Corp",
    "wof:placetype":"venue"
},
  "geometry": {"coordinates":[-87.069964,34.643671],"type":"Point"}
}