{
  "type": "Feature",
  "properties": {
    "iso:country":"US",
    "sg:address":"616 Jackson St SE",
    "sg:city":"Decatur",
    "sg:classifiers":[
        {
            "category":"Building & Trades",
            "subcategory":"Construction",
            "type":"Services"
        }
    ],
    "sg:phone":"+1 256 350 4309",
    "sg:postcode":"35601",
    "sg:province":"AL",
    "sg:tags":[
        "general",
        "contractor"
    ],
    "wof:name":"Woodward Construction",
    "wof:placetype":"venue"
},
  "geometry": {"coordinates":[-86.977735,34.600746],"type":"Point"}
}