{
  "type": "Feature",
  "properties": {
    "iso:country":"US",
    "sg:address":"1705 Holt Rd NE",
    "sg:city":"Tuscaloosa",
    "sg:classifiers":[
        {
            "category":"Government",
            "subcategory":"Post Office",
            "type":"Public Place"
        }
    ],
    "sg:phone":"+1 205 553 6415",
    "sg:postcode":"35404",
    "sg:province":"AL",
    "sg:tags":[
        "postal",
        "us"
    ],
    "wof:name":"United States Postal Service",
    "wof:placetype":"venue"
},
  "geometry": {"coordinates":[-87.505917,33.235275],"type":"Point"}
}