{
  "type": "Feature",
  "properties": {
    "addr:full":"100 Handy L Davis Mobile AL 36610",
    "addr:housenumber":"100",
    "addr:postcode":"36610",
    "addr:street":"Handy L",
    "iso:country":"US",
    "sg:address":"100 Handy L Davis",
    "sg:city":"Mobile",
    "sg:classifiers":[
        {
            "category":"Restaurant",
            "type":"Food & Drink"
        }
    ],
    "sg:phone":"+1 251 533 1963",
    "sg:postcode":"36610",
    "sg:province":"AL",
    "sg:tags":[
        "franchise",
        "business"
    ],
    "wof:name":"A Rhemie Mart",
    "wof:placetype":"venue"
},
  "geometry": {"coordinates":[-88.07615699999999,30.735436],"type":"Point"}
}