{
  "type": "Feature",
  "properties": {
    "iso:country":"US",
    "sg:address":"1980 Suncrest Dr",
    "sg:city":"Prattville",
    "sg:classifiers":[
        {
            "category":"Wholesale",
            "subcategory":"Durable Goods & Equipment",
            "type":"Manufacturing & Wholesale Goods"
        }
    ],
    "sg:phone":"+1 334 361 9661",
    "sg:postcode":"36067",
    "sg:province":"AL",
    "sg:tags":[
        "training",
        "vocational"
    ],
    "wof:name":"Learning Labs Inc",
    "wof:placetype":"venue"
},
  "geometry": {"coordinates":[-86.524448,32.560071],"type":"Point"}
}