{
  "type": "Feature",
  "properties": {
    "addr:full":"15434 US Hwy 43 Russellville AL 35653",
    "addr:postcode":"15434;35653",
    "addr:street":"Us Hwy 43",
    "iso:country":"US",
    "sg:address":"15434 US Hwy 43",
    "sg:city":"Russellville",
    "sg:classifiers":[
        {
            "category":"Restaurant",
            "type":"Food & Drink"
        }
    ],
    "sg:phone":"+1 256 332 7194",
    "sg:postcode":"35653",
    "sg:province":"AL",
    "wof:name":"Captain D's Seafood",
    "wof:placetype":"venue"
},
  "geometry": {"coordinates":[-87.716942,34.515261],"type":"Point"}
}