{
  "type": "Feature",
  "properties": {
    "iso:country":"US",
    "sg:address":"4033 US Hwy 231",
    "sg:city":"Wetumpka",
    "sg:classifiers":[
        {
            "category":"Sports & Exercise",
            "subcategory":"Gym",
            "type":"Entertainment"
        }
    ],
    "sg:phone":"+1 334 514 4500",
    "sg:postcode":"36093",
    "sg:province":"AL",
    "sg:tags":[
        "fitness",
        "physical",
        "facility"
    ],
    "wof:name":"Curves For Women",
    "wof:placetype":"venue"
},
  "geometry": {"coordinates":[-86.216066,32.502224],"type":"Point"}
}