{
  "type": "Feature",
  "properties": {
    "iso:country":"US",
    "sg:address":"107 Woodhaven Ave",
    "sg:city":"Attalla",
    "sg:classifiers":[
        {
            "category":"Food & Beverages",
            "subcategory":"Bakery",
            "type":"Retail Goods"
        }
    ],
    "sg:phone":"+1 256 538 9843",
    "sg:postcode":"35954",
    "sg:province":"AL",
    "wof:name":"Cupboard",
    "wof:placetype":"venue"
},
  "geometry": {"coordinates":[-86.104072,34.025469],"type":"Point"}
}