{
  "type": "Feature",
  "properties": {
    "addr:full":"1682 Montgomery Hwy Birmingham AL 35216",
    "addr:housenumber":"1682",
    "addr:postcode":"35216",
    "addr:street":"Montgomery Hwy",
    "iso:country":"US",
    "sg:address":"1682 Montgomery Hwy",
    "sg:city":"Birmingham",
    "sg:classifiers":[
        {
            "category":"Health Services",
            "subcategory":"Health Practitioner",
            "type":"Services"
        }
    ],
    "sg:phone":"+1 205 421 0000",
    "sg:postcode":"35216",
    "sg:province":"AL",
    "wof:name":"AFLAC",
    "wof:placetype":"venue"
},
  "geometry": {"coordinates":[-86.80640699999999,33.391303],"type":"Point"}
}