{
  "type": "Feature",
  "properties": {
    "addr:full":"6531 State Rte 69 Tuscaloosa AL 35405",
    "addr:housenumber":"6531",
    "addr:postcode":"35405",
    "addr:street":"State Rte 69",
    "iso:country":"US",
    "sg:address":"6531 State Rte 69",
    "sg:city":"Tuscaloosa",
    "sg:classifiers":[
        {
            "category":"Personal",
            "subcategory":"Beauty Salon",
            "type":"Services"
        }
    ],
    "sg:phone":"+1 205 752 8009",
    "sg:postcode":"35405",
    "sg:province":"AL",
    "wof:name":"Solutions",
    "wof:placetype":"venue"
},
  "geometry": {"coordinates":[-87.545079,33.148432],"type":"Point"}
}