{
  "type": "Feature",
  "properties": {
    "iso:country":"US",
    "sg:address":"5815 Jones Valley Dr SE",
    "sg:city":"Huntsville",
    "sg:classifiers":[
        {
            "category":"Professional",
            "subcategory":"Management & Consulting",
            "type":"Services"
        }
    ],
    "sg:phone":"+1 256 426 4942",
    "sg:postcode":"35802",
    "sg:province":"AL",
    "sg:tags":[
        "business"
    ],
    "wof:name":"Vernor Kathryn",
    "wof:placetype":"venue"
},
  "geometry": {"coordinates":[-86.562279,34.682959],"type":"Point"}
}