{
  "type": "Feature",
  "properties": {
    "addr:full":"603 Dibble St Tuskegee AL 36083",
    "addr:housenumber":"603",
    "addr:postcode":"36083",
    "addr:street":"Dibble St",
    "iso:country":"US",
    "sg:address":"603 Dibble St",
    "sg:city":"Tuskegee",
    "sg:classifiers":[
        {
            "category":"Professional",
            "type":"Services"
        }
    ],
    "sg:phone":"+1 334 725 1247",
    "sg:postcode":"36083",
    "sg:province":"AL",
    "sg:tags":[
        "establishment"
    ],
    "wof:name":"Tuskegee Macon County",
    "wof:placetype":"venue"
},
  "geometry": {"coordinates":[-85.69653599999999,32.427808],"type":"Point"}
}