{
  "type": "Feature",
  "properties": {
    "iso:country":"US",
    "sg:address":"1556 Mill Sq",
    "sg:city":"Alexander City",
    "sg:classifiers":[
        {
            "category":"Home & Garden",
            "subcategory":"Furniture",
            "type":"Retail Goods"
        }
    ],
    "sg:phone":"+1 256 329 0000",
    "sg:postcode":"35010",
    "sg:province":"AL",
    "wof:name":"Farmers Furniture",
    "wof:placetype":"venue"
},
  "geometry": {"coordinates":[-85.971516,32.935383],"type":"Point"}
}