{
  "type": "Feature",
  "properties": {
    "addr:full":"4301 Linwood Dr S Birmingham AL 35222",
    "addr:housenumber":"4301",
    "addr:postcode":"35222",
    "addr:street":"Linwood Dr S",
    "iso:country":"US",
    "sg:address":"4301 Linwood Dr S",
    "sg:city":"Birmingham",
    "sg:classifiers":[
        {
            "category":"Organizations",
            "subcategory":"Membership Organization",
            "type":"Services"
        }
    ],
    "sg:phone":"+1 205 349 6644",
    "sg:postcode":"35222",
    "sg:province":"AL",
    "wof:name":"Birmingham Youth Hockey League",
    "wof:placetype":"venue"
},
  "geometry": {"coordinates":[-86.76583599999999,33.52158],"type":"Point"}
}