{
  "type": "Feature",
  "properties": {
    "iso:country":"US",
    "sg:address":"3928 Cypress Dr",
    "sg:city":"Birmingham",
    "sg:classifiers":[
        {
            "category":"Professional",
            "subcategory":"Advertising",
            "type":"Services"
        }
    ],
    "sg:phone":"+1 205 970 6635",
    "sg:postcode":"35243",
    "sg:province":"AL",
    "sg:tags":[
        "postal",
        "us"
    ],
    "wof:name":"River Run Carrier Annex",
    "wof:placetype":"venue"
},
  "geometry": {"coordinates":[-86.732364,33.461647],"type":"Point"}
}