{
  "type": "Feature",
  "properties": {
    "iso:country":"US",
    "sg:address":"3016 Forest Dr",
    "sg:city":"Fultondale",
    "sg:classifiers":[
        {
            "category":"Building & Trades",
            "subcategory":"Construction",
            "type":"Services"
        }
    ],
    "sg:phone":"+1 205 849 6621",
    "sg:postcode":"35068",
    "sg:province":"AL",
    "sg:tags":[
        "house"
    ],
    "wof:name":"Ed S Home Improvement &",
    "wof:placetype":"venue"
},
  "geometry": {"coordinates":[-86.828429,33.60704],"type":"Point"}
}