{
  "type": "Feature",
  "properties": {
    "iso:country":"US",
    "sg:address":"77 Cedar Ln",
    "sg:city":"Trussville",
    "sg:classifiers":[
        {
            "category":"Social Services",
            "subcategory":"Child Care",
            "type":"Services"
        }
    ],
    "sg:phone":"+1 205 655 3920",
    "sg:postcode":"35173",
    "sg:province":"AL",
    "sg:tags":[
        "day"
    ],
    "wof:name":"Just For Kids Childcare",
    "wof:placetype":"venue"
},
  "geometry": {"coordinates":[-86.610211,33.617989],"type":"Point"}
}