{
  "type": "Feature",
  "properties": {
    "addr:full":"310 Joseph St Bessemer AL 35020",
    "addr:housenumber":"310",
    "addr:postcode":"35020",
    "addr:street":"Joseph St",
    "iso:country":"US",
    "sg:address":"310 Joseph St",
    "sg:city":"Bessemer",
    "sg:classifiers":[
        {
            "category":"Manufacturing",
            "subcategory":"Building Materials",
            "type":"Manufacturing & Wholesale Goods"
        }
    ],
    "sg:phone":"+1 205 425 0544",
    "sg:postcode":"35020",
    "sg:province":"AL",
    "sg:tags":[
        "cabinet"
    ],
    "wof:name":"Lewis Cox Cabinets",
    "wof:placetype":"venue"
},
  "geometry": {"coordinates":[-86.955423,33.374313],"type":"Point"}
}