{
  "type": "Feature",
  "properties": {
    "addr:full":"2 N Florida St Mobile AL 36607",
    "addr:housenumber":"2",
    "addr:postcode":"36607",
    "addr:street":"N Florida St",
    "iso:country":"US",
    "sg:address":"2 N Florida St",
    "sg:city":"Mobile",
    "sg:classifiers":[
        {
            "category":"Health Services",
            "subcategory":"Chiropractor",
            "type":"Services"
        }
    ],
    "sg:phone":"+1 251 473 0373",
    "sg:postcode":"36607",
    "sg:province":"AL",
    "wof:name":"Harlow Chiropractic Clinic",
    "wof:placetype":"venue"
},
  "geometry": {"coordinates":[-88.100251,30.688024],"type":"Point"}
}