{
  "type": "Feature",
  "properties": {
    "addr:full":"2769 Zelda Rd Montgomery AL 36106",
    "addr:housenumber":"2769",
    "addr:postcode":"36106",
    "addr:street":"Zelda Rd",
    "iso:country":"US",
    "sg:address":"2769 Zelda Rd",
    "sg:city":"Montgomery",
    "sg:classifiers":[
        {
            "category":"Retail",
            "subcategory":"Auto Repair",
            "type":"Services"
        }
    ],
    "sg:phone":"+1 334 271 2278",
    "sg:postcode":"36106",
    "sg:province":"AL",
    "sg:tags":[
        "automotive",
        "tire",
        "general"
    ],
    "wof:name":"Big 10 Tires 82",
    "wof:placetype":"venue"
},
  "geometry": {"coordinates":[-86.26772200000001,32.364086],"type":"Point"}
}