{
  "type": "Feature",
  "properties": {
    "iso:country":"US",
    "sg:address":"2945 Smithfield Rd",
    "sg:city":"Atmore",
    "sg:classifiers":[
        {
            "category":"Retail",
            "subcategory":"Repair Shop",
            "type":"Services"
        }
    ],
    "sg:phone":"+1 251 294 5570",
    "sg:postcode":"36502",
    "sg:province":"AL",
    "sg:tags":[
        "welding"
    ],
    "wof:name":"Island Welding/Repar",
    "wof:placetype":"venue"
},
  "geometry": {"coordinates":[-87.481966,31.18043],"type":"Point"}
}