{
  "type": "Feature",
  "properties": {
    "iso:country":"US",
    "sg:address":"313 Cedar Hill Dr",
    "sg:city":"Birmingham",
    "sg:classifiers":[
        {
            "category":"Retail",
            "subcategory":"Auto Repair",
            "type":"Services"
        }
    ],
    "sg:phone":"+1 205 437 8867",
    "sg:postcode":"35242",
    "sg:province":"AL",
    "sg:tags":[
        "general"
    ],
    "wof:name":"S&C Auto Inc",
    "wof:placetype":"venue"
},
  "geometry": {"coordinates":[-86.684914,33.400541],"type":"Point"}
}