{
  "type": "Feature",
  "properties": {
    "addr:full":"1455 Arrowhead Rd Selma AL 36703",
    "addr:housenumber":"1455",
    "addr:postcode":"36703",
    "addr:street":"Arrowhead Rd",
    "iso:country":"US",
    "sg:address":"1455 Arrowhead Rd",
    "sg:city":"Selma",
    "sg:classifiers":[
        {
            "category":"Retail",
            "subcategory":"Repair Shop",
            "type":"Services"
        }
    ],
    "sg:phone":"+1 334 872 9988",
    "sg:postcode":"36703",
    "sg:province":"AL",
    "sg:tags":[
        "appliance"
    ],
    "wof:name":"Asap Appliance Svc & Parts",
    "wof:placetype":"venue"
},
  "geometry": {"coordinates":[-86.896754,32.424062],"type":"Point"}
}