{
  "type": "Feature",
  "properties": {
    "iso:country":"US",
    "sg:address":"2415 Schillinger Rd S",
    "sg:city":"Mobile",
    "sg:classifiers":[
        {
            "category":"Restaurant",
            "type":"Food & Drink"
        }
    ],
    "sg:phone":"+1 251 634 1378",
    "sg:postcode":"36695",
    "sg:province":"AL",
    "wof:name":"Mc Donald's",
    "wof:placetype":"venue"
},
  "geometry": {"coordinates":[-88.22464100000001,30.634385],"type":"Point"}
}