{
  "type": "Feature",
  "properties": {
    "addr:full":"217 Daryl St Livingston AL 35470",
    "addr:housenumber":"217",
    "addr:postcode":"35470",
    "addr:street":"Daryl St",
    "iso:country":"US",
    "sg:address":"217 Daryl St",
    "sg:city":"Livingston",
    "sg:classifiers":[
        {
            "category":"Organizations",
            "subcategory":"Professional Association",
            "type":"Services"
        }
    ],
    "sg:phone":"+1 205 652 1712",
    "sg:postcode":"35470",
    "sg:province":"AL",
    "wof:name":"Alabama Counseling Assn",
    "wof:placetype":"venue"
},
  "geometry": {"coordinates":[-88.201719,32.607469],"type":"Point"}
}