{
  "type": "Feature",
  "properties": {
    "addr:full":"612 Hamric Dr E Oxford AL 36203",
    "addr:housenumber":"612",
    "addr:postcode":"36203",
    "addr:street":"Hamric Dr E",
    "iso:country":"US",
    "sg:address":"612 Hamric Dr E",
    "sg:city":"Oxford",
    "sg:classifiers":[
        {
            "category":"Restaurant",
            "type":"Food & Drink"
        }
    ],
    "sg:menulink":"http://www.allmenus.com/al/anniston/84983-applebees/menu/",
    "sg:phone":"+1 256 835 2434",
    "sg:postcode":"36203",
    "sg:province":"AL",
    "sg:tags":[
        "burger",
        "american",
        "sandwich",
        "soup"
    ],
    "wof:name":"Applebee's",
    "wof:placetype":"venue"
},
  "geometry": {"coordinates":[-85.829508,33.608915],"type":"Point"}
}