{
  "type": "Feature",
  "properties": {
    "iso:country":"US",
    "sg:address":"21161 US Hwy 280",
    "sg:city":"Dadeville",
    "sg:classifiers":[
        {
            "category":"Retail",
            "subcategory":"Auto Repair",
            "type":"Services"
        }
    ],
    "sg:phone":"+1 256 825 5288",
    "sg:postcode":"36853",
    "sg:province":"AL",
    "sg:tags":[
        "repairing",
        "automobile"
    ],
    "wof:name":"Ed's Service Ctr",
    "wof:placetype":"venue"
},
  "geometry": {"coordinates":[-85.712357,32.814327],"type":"Point"}
}