{
  "type": "Feature",
  "properties": {
    "iso:country":"US",
    "sg:address":"184 Country Club Dr",
    "sg:city":"Daphne",
    "sg:classifiers":[
        {
            "category":"Retail",
            "subcategory":"Auto Repair",
            "type":"Services"
        }
    ],
    "sg:phone":"+1 251 943 2447",
    "sg:postcode":"36526",
    "sg:province":"AL",
    "sg:tags":[
        "automobile",
        "installation",
        "glass"
    ],
    "wof:name":"Novus Windshield Repair",
    "wof:placetype":"venue"
},
  "geometry": {"coordinates":[-87.898898,30.643407],"type":"Point"}
}