{
  "type": "Feature",
  "properties": {
    "iso:country":"US",
    "sg:address":"409 Columbia Hwy",
    "sg:city":"Dothan",
    "sg:classifiers":[
        {
            "category":"Food & Beverages",
            "subcategory":"Groceries & Convenience Stores",
            "type":"Retail Goods"
        }
    ],
    "sg:phone":"+1 334 794 5136",
    "sg:postcode":"36301",
    "sg:province":"AL",
    "sg:tags":[
        "grocer"
    ],
    "wof:name":"Main Street U-Sav Food",
    "wof:placetype":"venue"
},
  "geometry": {"coordinates":[-85.384888,31.221909],"type":"Point"}
}