{
  "type": "Feature",
  "properties": {
    "addr:full":"14015 US Hwy 43 Russellville AL 35653",
    "addr:housenumber":"14015",
    "addr:postcode":"35653",
    "addr:street":"Us Hwy 43",
    "iso:country":"US",
    "sg:address":"14015 US Hwy 43",
    "sg:city":"Russellville",
    "sg:classifiers":[
        {
            "category":"Banks & Credit Unions",
            "subcategory":"Bank",
            "type":"Services"
        }
    ],
    "sg:phone":"+1 256 332 5110",
    "sg:postcode":"35653",
    "sg:province":"AL",
    "wof:name":"Citizens Bank",
    "wof:placetype":"venue"
},
  "geometry": {"coordinates":[-87.721608,34.497653],"type":"Point"}
}