{
  "type": "Feature",
  "properties": {
    "iso:country":"US",
    "sg:address":"1921 Duval St",
    "sg:city":"Mobile",
    "sg:classifiers":[
        {
            "category":"Professional",
            "subcategory":"Accounting & Tax Preparation",
            "type":"Services"
        }
    ],
    "sg:phone":"+1 251 476 9420",
    "sg:postcode":"36606",
    "sg:province":"AL",
    "sg:tags":[
        "return",
        "filing"
    ],
    "wof:name":"Worldwide Tax Wireless Svc",
    "wof:placetype":"venue"
},
  "geometry": {"coordinates":[-88.084969,30.662985],"type":"Point"}
}