{
  "type": "Feature",
  "properties": {
    "iso:country":"US",
    "sg:address":"7560 Spencer Ln",
    "sg:city":"Helena",
    "sg:classifiers":[
        {
            "category":"Professional",
            "type":"Services"
        }
    ],
    "sg:phone":"+1 205 663 1911",
    "sg:postcode":"35080",
    "sg:province":"AL",
    "wof:name":"Charles L Dunn",
    "wof:placetype":"venue"
},
  "geometry": {"coordinates":[-86.846586,33.27948],"type":"Point"}
}