{
  "type": "Feature",
  "properties": {
    "iso:country":"US",
    "sg:address":"12 Trillium Cir",
    "sg:city":"Dothan",
    "sg:classifiers":[
        {
            "category":"Building & Trades",
            "subcategory":"Cleaning & Sanitation",
            "type":"Services"
        }
    ],
    "sg:phone":"+1 334 794 3836",
    "sg:postcode":"36301",
    "sg:province":"AL",
    "sg:tags":[
        "janitor"
    ],
    "wof:name":"Edward's Office Cleaning Svc",
    "wof:placetype":"venue"
},
  "geometry": {"coordinates":[-85.399826,31.186873],"type":"Point"}
}