{
  "type": "Feature",
  "properties": {
    "iso:country":"US",
    "sg:address":"2643 Montgomery Hwy",
    "sg:city":"Dothan",
    "sg:classifiers":[
        {
            "category":"Manufacturing",
            "subcategory":"Printing",
            "type":"Manufacturing & Wholesale Goods"
        }
    ],
    "sg:phone":"+1 334 793 1562",
    "sg:postcode":"36303",
    "sg:province":"AL",
    "sg:tags":[
        "print",
        "commercial",
        "lithographic",
        "typesetting"
    ],
    "wof:name":"Dothan Instant Printing LLC",
    "wof:placetype":"venue"
},
  "geometry": {"coordinates":[-85.42057200000001,31.245194],"type":"Point"}
}