{
  "type": "Feature",
  "properties": {
    "iso:country":"US",
    "sg:address":"520 Winfrey Rd",
    "sg:city":"Boaz",
    "sg:classifiers":[
        {
            "category":"Autos & Motor Vehicles",
            "subcategory":"Automobile Sales",
            "type":"Retail Goods"
        }
    ],
    "sg:phone":"+1 256 593 2966",
    "sg:postcode":"35957",
    "sg:province":"AL",
    "sg:tags":[
        "used"
    ],
    "wof:name":"Jeffs Auto Sales",
    "wof:placetype":"venue"
},
  "geometry": {"coordinates":[-86.27879900000001,34.18279],"type":"Point"}
}