{
  "type": "Feature",
  "properties": {
    "addr:full":"604 2nd St Muscle Shoals AL 35661",
    "addr:housenumber":"604",
    "addr:postcode":"35661",
    "addr:street":"2Nd St",
    "iso:country":"US",
    "sg:address":"604 2nd St",
    "sg:city":"Muscle Shoals",
    "sg:classifiers":[
        {
            "category":"Food & Beverages",
            "subcategory":"Groceries & Convenience Stores",
            "type":"Retail Goods"
        }
    ],
    "sg:phone":"+1 256 383 5245",
    "sg:postcode":"35661",
    "sg:province":"AL",
    "wof:name":"Quick Stop 106",
    "wof:placetype":"venue"
},
  "geometry": {"coordinates":[-87.67298,34.759586],"type":"Point"}
}