{
  "type": "Feature",
  "properties": {
    "addr:full":"925 Dozier Rd Montgomery AL 36117",
    "addr:housenumber":"925",
    "addr:postcode":"36117",
    "addr:street":"Dozier Rd",
    "iso:country":"US",
    "sg:address":"925 Dozier Rd",
    "sg:city":"Montgomery",
    "sg:classifiers":[
        {
            "category":"Retail",
            "subcategory":"Auto Repair",
            "type":"Services"
        }
    ],
    "sg:phone":"+1 334 396 0180",
    "sg:postcode":"36117",
    "sg:province":"AL",
    "sg:tags":[
        "body",
        "automobile",
        "painting"
    ],
    "wof:name":"Custom Rides Body & Repair",
    "wof:placetype":"venue"
},
  "geometry": {"coordinates":[-86.138203,32.413704],"type":"Point"}
}