{
  "type": "Feature",
  "properties": {
    "iso:country":"US",
    "sg:address":"661 Co Rd 781",
    "sg:city":"Cullman",
    "sg:phone":"+1 256 734 1235",
    "sg:postcode":"35055",
    "sg:province":"AL",
    "sg:tags":[
        "farm",
        "soybean"
    ],
    "wof:name":"Stisher Edsel Farm",
    "wof:placetype":"venue"
},
  "geometry": {"coordinates":[-86.70455200000001,34.16673],"type":"Point"}
}