{
  "type": "Feature",
  "properties": {
    "addr:full":"3042 Birmingham Hwy Montgomery AL 36108",
    "addr:housenumber":"3042",
    "addr:postcode":"36108",
    "addr:street":"Birmingham Hwy",
    "iso:country":"US",
    "sg:address":"3042 Birmingham Hwy",
    "sg:city":"Montgomery",
    "sg:classifiers":[
        {
            "category":"Wholesale",
            "subcategory":"Auto Parts",
            "type":"Manufacturing & Wholesale Goods"
        }
    ],
    "sg:phone":"+1 334 264 7364",
    "sg:postcode":"36108",
    "sg:province":"AL",
    "sg:tags":[
        "supply"
    ],
    "sg:website":"www.keystoneauto.com",
    "wof:name":"Keystone Automotive",
    "wof:placetype":"venue"
},
  "geometry": {"coordinates":[-86.36734800000001,32.364904],"type":"Point"}
}