{
  "type": "Feature",
  "properties": {
    "iso:country":"US",
    "sg:address":"1720 28th Ave S",
    "sg:city":"Birmingham",
    "sg:classifiers":[
        {
            "category":"Real Estate",
            "subcategory":"Real Estate Agent",
            "type":"Services"
        }
    ],
    "sg:phone":"+1 205 870 3550",
    "sg:postcode":"35209",
    "sg:province":"AL",
    "wof:name":"Avenue Of Homes Inc",
    "wof:placetype":"venue"
},
  "geometry": {"coordinates":[-86.793903,33.480472],"type":"Point"}
}