{
  "type": "Feature",
  "properties": {
    "iso:country":"US",
    "sg:address":"3306 32nd Pl N",
    "sg:city":"Birmingham",
    "sg:classifiers":[
        {
            "category":"Building & Trades",
            "subcategory":"Construction",
            "type":"Services"
        }
    ],
    "sg:phone":"+1 205 849 7857",
    "sg:postcode":"35207",
    "sg:province":"AL",
    "wof:name":"Blue & Black Patching",
    "wof:placetype":"venue"
},
  "geometry": {"coordinates":[-86.800624,33.557198],"type":"Point"}
}