{
  "type": "Feature",
  "properties": {
    "iso:country":"US",
    "sg:address":"3040 US Hwy 278",
    "sg:city":"Cullman",
    "sg:classifiers":[
        {
            "category":"Freight",
            "type":"Transportation"
        }
    ],
    "sg:phone":"+1 256 737 7441",
    "sg:postcode":"35057",
    "sg:province":"AL",
    "wof:name":"H&H Transportation LLC",
    "wof:placetype":"venue"
},
  "geometry": {"coordinates":[-86.919009,34.192234],"type":"Point"}
}