{
  "type": "Feature",
  "properties": {
    "addr:full":"2307 US Hwy 31 Hartselle AL 35640",
    "addr:housenumber":"2307",
    "addr:postcode":"35640",
    "addr:street":"Us Hwy 31",
    "iso:country":"US",
    "sg:address":"2307 US Hwy 31",
    "sg:city":"Hartselle",
    "sg:classifiers":[
        {
            "category":"Autos & Motor Vehicles",
            "subcategory":"Fuel & Gas Station",
            "type":"Retail Goods"
        }
    ],
    "sg:phone":"+1 256 773 8881",
    "sg:postcode":"35640",
    "sg:province":"AL",
    "sg:tags":[
        "automotive",
        "station",
        "gasoline",
        "repair"
    ],
    "wof:name":"Garnett Shell",
    "wof:placetype":"venue"
},
  "geometry": {"coordinates":[-86.915368,34.401966],"type":"Point"}
}