{
  "type": "Feature",
  "properties": {
    "addr:full":"1343 Bessemer Rd Birmingham AL 35208",
    "addr:housenumber":"1343",
    "addr:postcode":"35208",
    "addr:street":"Bessemer Rd",
    "iso:country":"US",
    "sg:address":"1343 Bessemer Rd",
    "sg:city":"Birmingham",
    "sg:classifiers":[
        {
            "category":"Building & Trades",
            "subcategory":"Equipment Rental",
            "type":"Services"
        }
    ],
    "sg:phone":"+1 205 923 4400",
    "sg:postcode":"35208",
    "sg:province":"AL",
    "sg:tags":[
        "appliance"
    ],
    "wof:name":"Aarons Sales & Lease Ownership",
    "wof:placetype":"venue"
},
  "geometry": {"coordinates":[-86.894876,33.480365],"type":"Point"}
}