{
  "type": "Feature",
  "properties": {
    "iso:country":"US",
    "sg:address":"328 E Samford Ave",
    "sg:city":"Auburn",
    "sg:classifiers":[
        {
            "category":"Organizations",
            "subcategory":"Community Association",
            "type":"Services"
        }
    ],
    "sg:phone":"+1 334 887 4932",
    "sg:postcode":"36830",
    "sg:province":"AL",
    "wof:name":"Auburn City Pool",
    "wof:placetype":"venue"
},
  "geometry": {"coordinates":[-85.475531,32.598739],"type":"Point"}
}