{
  "type": "Feature",
  "properties": {
    "iso:country":"US",
    "sg:address":"1740 S Oates St",
    "sg:city":"Dothan",
    "sg:classifiers":[
        {
            "category":"Restaurant",
            "type":"Food & Drink"
        }
    ],
    "sg:phone":"+1 334 794 4625",
    "sg:postcode":"36301",
    "sg:province":"AL",
    "sg:tags":[
        "style",
        "family"
    ],
    "wof:name":"Ray's Restaurant",
    "wof:placetype":"venue"
},
  "geometry": {"coordinates":[-85.39566600000001,31.204853],"type":"Point"}
}