{
  "type": "Feature",
  "properties": {
    "iso:country":"US",
    "sg:address":"2809 Corona Ave",
    "sg:city":"Jasper",
    "sg:classifiers":[
        {
            "category":"Home & Garden",
            "subcategory":"Carpets & Floor Coverings",
            "type":"Retail Goods"
        }
    ],
    "sg:phone":"+1 205 221 3666",
    "sg:postcode":"35501",
    "sg:province":"AL",
    "wof:name":"C&D Janitorial & Carpets",
    "wof:placetype":"venue"
},
  "geometry": {"coordinates":[-87.27176300000001,33.82341],"type":"Point"}
}