{
  "type": "Feature",
  "properties": {
    "addr:full":"3829 Lorna Rd Birmingham AL 35244",
    "addr:housenumber":"3829",
    "addr:postcode":"35244",
    "addr:street":"Lorna Rd",
    "iso:country":"US",
    "sg:address":"3829 Lorna Rd",
    "sg:city":"Birmingham",
    "sg:classifiers":[
        {
            "category":"Professional",
            "subcategory":"Accounting & Tax Preparation",
            "type":"Services"
        }
    ],
    "sg:phone":"+1 205 682 7911",
    "sg:postcode":"35244",
    "sg:province":"AL",
    "wof:name":"ACS Group",
    "wof:placetype":"venue"
},
  "geometry": {"coordinates":[-86.80610799999999,33.373314],"type":"Point"}
}