{
  "type": "Feature",
  "properties": {
    "iso:country":"US",
    "sg:address":"1245 S Eufaula Ave",
    "sg:city":"Eufaula",
    "sg:classifiers":[
        {
            "category":"Banks & Credit Unions",
            "subcategory":"Bank",
            "type":"Services"
        }
    ],
    "sg:phone":"+1 334 687 5400",
    "sg:postcode":"36027",
    "sg:province":"AL",
    "sg:tags":[
        "saving",
        "commercial"
    ],
    "wof:name":"Peoplessouth Bank",
    "wof:placetype":"venue"
},
  "geometry": {"coordinates":[-85.154657,31.872671],"type":"Point"}
}