{
  "type": "Feature",
  "properties": {
    "addr:full":"835 Odum Cir Gardendale AL 35071",
    "addr:housenumber":"835",
    "addr:postcode":"35071",
    "addr:street":"Odum Cir",
    "iso:country":"US",
    "sg:address":"835 Odum Cir",
    "sg:city":"Gardendale",
    "sg:classifiers":[
        {
            "category":"Restaurant",
            "type":"Food & Drink"
        }
    ],
    "sg:phone":"+1 205 608 2168",
    "sg:postcode":"35071",
    "sg:province":"AL",
    "wof:name":"Habaneros Mexican Grill",
    "wof:placetype":"venue"
},
  "geometry": {"coordinates":[-86.826857,33.648351],"type":"Point"}
}