{
  "type": "Feature",
  "properties": {
    "addr:full":"6737 Old Springville Rd Pinson AL 35126",
    "addr:housenumber":"6737",
    "addr:postcode":"35126",
    "addr:street":"Old Springville Rd",
    "iso:country":"US",
    "sg:address":"6737 Old Springville Rd",
    "sg:city":"Pinson",
    "sg:classifiers":[
        {
            "category":"Organizations",
            "subcategory":"Professional Association",
            "type":"Services"
        }
    ],
    "sg:phone":"+1 205 681 0298",
    "sg:postcode":"35126",
    "sg:province":"AL",
    "wof:name":"Clay Recreation Assn Inc",
    "wof:placetype":"venue"
},
  "geometry": {"coordinates":[-86.60356899999999,33.700546],"type":"Point"}
}