{
  "type": "Feature",
  "properties": {
    "iso:country":"US",
    "sg:address":"239 Irvin Dr",
    "sg:city":"Boaz",
    "sg:classifiers":[
        {
            "category":"Autos & Motor Vehicles",
            "subcategory":"Automobile Sales",
            "type":"Retail Goods"
        }
    ],
    "sg:phone":"+1 256 593 0465",
    "sg:postcode":"35956",
    "sg:province":"AL",
    "sg:tags":[
        "used"
    ],
    "wof:name":"Hubbard Auto Sales LLC",
    "wof:placetype":"venue"
},
  "geometry": {"coordinates":[-86.101157,34.134659],"type":"Point"}
}