{
  "type": "Feature",
  "properties": {
    "iso:country":"US",
    "sg:address":"108 N Randolph Ave",
    "sg:city":"Eufaula",
    "sg:classifiers":[
        {
            "category":"Professional",
            "subcategory":"Lawyer & Legal Services",
            "type":"Services"
        }
    ],
    "sg:phone":"+1 334 687 9007",
    "sg:postcode":"36027",
    "sg:province":"AL",
    "sg:tags":[
        "attorney"
    ],
    "wof:name":"Grubb Law Firm",
    "wof:placetype":"venue"
},
  "geometry": {"coordinates":[-85.144038,31.894557],"type":"Point"}
}