{
  "type": "Feature",
  "properties": {
    "addr:full":"871 Twin Forks Ave Auburn AL 36830",
    "addr:housenumber":"871",
    "addr:postcode":"36830",
    "addr:street":"Twin Forks Ave",
    "iso:country":"US",
    "sg:address":"871 Twin Forks Ave",
    "sg:city":"Auburn",
    "sg:classifiers":[
        {
            "category":"Health Services",
            "subcategory":"Nursing And Care Facility",
            "type":"Services"
        }
    ],
    "sg:phone":"+1 334 887 1061",
    "sg:postcode":"36830",
    "sg:province":"AL",
    "sg:tags":[
        "living",
        "assisted"
    ],
    "wof:name":"Morningside Assisted Living",
    "wof:placetype":"venue"
},
  "geometry": {"coordinates":[-85.464945,32.625039],"type":"Point"}
}