{
  "type": "Feature",
  "properties": {
    "iso:country":"US",
    "sg:address":"56 Henderson Ln",
    "sg:city":"Atmore",
    "sg:classifiers":[
        {
            "category":"Retail",
            "subcategory":"Repair Shop",
            "type":"Services"
        }
    ],
    "sg:phone":"+1 251 443 5455",
    "sg:postcode":"36502",
    "sg:province":"AL",
    "sg:tags":[
        "heavy",
        "equipment",
        "tractor"
    ],
    "wof:name":"Cobb Equipment Repair",
    "wof:placetype":"venue"
},
  "geometry": {"coordinates":[-87.500467,31.055991],"type":"Point"}
}