{
  "type": "Feature",
  "properties": {
    "iso:country":"US",
    "sg:address":"4501 Atlanta Hwy",
    "sg:city":"Montgomery",
    "sg:classifiers":[
        {
            "category":"Shopping",
            "subcategory":"Bicycles & Sporting Goods",
            "type":"Retail Goods"
        }
    ],
    "sg:phone":"+1 334 277 5288",
    "sg:postcode":"36109",
    "sg:province":"AL",
    "sg:tags":[
        "repair",
        "accessory"
    ],
    "sg:website":"www.cycleescape.com",
    "wof:name":"Cycle Escape",
    "wof:placetype":"venue"
},
  "geometry": {"coordinates":[-86.226102,32.381715],"type":"Point"}
}