{
  "type": "Feature",
  "properties": {
    "iso:country":"US",
    "sg:address":"3010 Ross Clark Cir",
    "sg:city":"Dothan",
    "sg:classifiers":[
        {
            "category":"Home & Garden",
            "subcategory":"Household Appliances",
            "type":"Retail Goods"
        }
    ],
    "sg:phone":"+1 334 673 9001",
    "sg:postcode":"36301",
    "sg:province":"AL",
    "sg:tags":[
        "electronics",
        "consumer"
    ],
    "wof:name":"Rex TV",
    "wof:placetype":"venue"
},
  "geometry": {"coordinates":[-85.43211,31.221489],"type":"Point"}
}