{
  "type": "Feature",
  "properties": {
    "iso:country":"US",
    "sg:address":"2201 Sherwood Pl",
    "sg:city":"Birmingham",
    "sg:classifiers":[
        {
            "category":"Home & Garden",
            "subcategory":"Furniture",
            "type":"Retail Goods"
        }
    ],
    "sg:phone":"+1 205 978 9691",
    "sg:postcode":"35226",
    "sg:province":"AL",
    "wof:name":"Donohoo Furniture",
    "wof:placetype":"venue"
},
  "geometry": {"coordinates":[-86.824575,33.428092],"type":"Point"}
}