{
  "type": "Feature",
  "properties": {
    "iso:country":"US",
    "sg:address":"404 Sequoya Dr",
    "sg:city":"Anniston",
    "sg:classifiers":[
        {
            "category":"Communications",
            "subcategory":"Radio Station",
            "type":"Services"
        }
    ],
    "sg:phone":"+1 256 820 3711",
    "sg:postcode":"36206",
    "sg:province":"AL",
    "sg:tags":[
        "broadcast"
    ],
    "wof:name":"Charis",
    "wof:placetype":"venue"
},
  "geometry": {"coordinates":[-85.865495,33.731138],"type":"Point"}
}