{
  "type": "Feature",
  "properties": {
    "iso:country":"US",
    "sg:address":"115 Polly Reed Rd",
    "sg:city":"Center Point",
    "sg:classifiers":[
        {
            "category":"Social Services",
            "subcategory":"Child Care",
            "type":"Services"
        }
    ],
    "sg:phone":"+1 205 324 1203",
    "sg:postcode":"35215",
    "sg:province":"AL",
    "sg:tags":[
        "day"
    ],
    "wof:name":"Aodr Kinderversity Daycare Center",
    "wof:placetype":"venue"
},
  "geometry": {"coordinates":[-86.683138,33.634706],"type":"Point"}
}