{
  "type": "Feature",
  "properties": {
    "iso:country":"US",
    "sg:address":"31 Inverness Center Pkwy",
    "sg:city":"Birmingham",
    "sg:classifiers":[
        {
            "category":"Wholesale",
            "subcategory":"Drugs",
            "type":"Manufacturing & Wholesale Goods"
        }
    ],
    "sg:phone":"+1 205 991 9870",
    "sg:postcode":"35242",
    "sg:province":"AL",
    "sg:tags":[
        "pharmaceutical",
        "product"
    ],
    "wof:name":"Centrix Pharmaceutical",
    "wof:placetype":"venue"
},
  "geometry": {"coordinates":[-86.703215,33.423919],"type":"Point"}
}