{
  "type": "Feature",
  "properties": {
    "addr:full":"503 Brown St Opp AL 36467",
    "addr:housenumber":"503",
    "addr:postcode":"36467",
    "addr:street":"Brown St Opp",
    "iso:country":"US",
    "sg:address":"503 Brown St",
    "sg:city":"Opp",
    "sg:classifiers":[
        {
            "category":"Education",
            "subcategory":"School",
            "type":"Public Place"
        }
    ],
    "sg:phone":"+1 334 493 6031",
    "sg:postcode":"36467",
    "sg:province":"AL",
    "sg:website":"www.oppcityschools.com",
    "wof:name":"South Highlands Elementary",
    "wof:placetype":"venue"
},
  "geometry": {"coordinates":[-86.259783,31.276544],"type":"Point"}
}