{
  "type": "Feature",
  "properties": {
    "iso:country":"US",
    "sg:address":"401 N 11th St",
    "sg:city":"Gadsden",
    "sg:classifiers":[
        {
            "category":"Home & Garden",
            "subcategory":"Building Materials",
            "type":"Retail Goods"
        }
    ],
    "sg:phone":"+1 256 546 2856",
    "sg:postcode":"35901",
    "sg:province":"AL",
    "wof:name":"Marvins Hardware",
    "wof:placetype":"venue"
},
  "geometry": {"coordinates":[-86.01696200000001,34.023127],"type":"Point"}
}