{
  "type": "Feature",
  "properties": {
    "iso:country":"US",
    "sg:address":"420 Lowell Dr SE",
    "sg:city":"Huntsville",
    "sg:classifiers":[
        {
            "category":"Personal",
            "subcategory":"Beauty Salon",
            "type":"Services"
        }
    ],
    "sg:phone":"+1 256 533 7145",
    "sg:postcode":"35801",
    "sg:province":"AL",
    "sg:tags":[
        "shop"
    ],
    "wof:name":"Fountain of Youth",
    "wof:placetype":"venue"
},
  "geometry": {"coordinates":[-86.577278,34.720998],"type":"Point"}
}