{
  "type": "Feature",
  "properties": {
    "iso:country":"US",
    "sg:address":"10745 US Hwy 431",
    "sg:city":"Albertville",
    "sg:classifiers":[
        {
            "category":"Banks & Credit Unions",
            "subcategory":"Bank",
            "type":"Services"
        }
    ],
    "sg:phone":"+1 256 891 1804",
    "sg:postcode":"35950",
    "sg:province":"AL",
    "sg:tags":[
        "cashing",
        "check"
    ],
    "wof:name":"A-1 Quick Cash Advance Co",
    "wof:placetype":"venue"
},
  "geometry": {"coordinates":[-86.260618,34.295583],"type":"Point"}
}