{
  "type": "Feature",
  "properties": {
    "iso:country":"US",
    "sg:address":"2003 Meridian St N",
    "sg:city":"Huntsville",
    "sg:classifiers":[
        {
            "category":"Autos & Motor Vehicles",
            "subcategory":"Fuel & Gas Station",
            "type":"Retail Goods"
        },
        {
            "category":"Food & Beverages",
            "subcategory":"Groceries & Convenience Stores",
            "type":"Retail Goods"
        }
    ],
    "sg:phone":"+1 256 533 6019",
    "sg:postcode":"35811",
    "sg:province":"AL",
    "wof:name":"Shell Food Mart",
    "wof:placetype":"venue"
},
  "geometry": {"coordinates":[-86.58303100000001,34.749196],"type":"Point"}
}