{
  "type": "Feature",
  "properties": {
    "addr:full":"820 Grove St Birmingham AL 35209",
    "addr:housenumber":"820",
    "addr:postcode":"35209",
    "addr:street":"Grove St",
    "iso:country":"US",
    "sg:address":"820 Grove St",
    "sg:city":"Birmingham",
    "sg:classifiers":[
        {
            "category":"Professional",
            "subcategory":"Accounting & Tax Preparation",
            "type":"Services"
        }
    ],
    "sg:phone":"+1 205 940 9933",
    "sg:postcode":"35209",
    "sg:province":"AL",
    "sg:tags":[
        "forensic"
    ],
    "wof:name":"Thomas Gber Frensic Acctg Svcs",
    "wof:placetype":"venue"
},
  "geometry": {"coordinates":[-86.82251599999999,33.456488],"type":"Point"}
}