{
  "type": "Feature",
  "properties": {
    "iso:country":"US",
    "sg:address":"9320 Silley Dean Rd",
    "sg:city":"Pinson",
    "sg:classifiers":[
        {
            "category":"Freight",
            "type":"Transportation"
        }
    ],
    "sg:phone":"+1 205 681 9398",
    "sg:postcode":"35126",
    "sg:province":"AL",
    "sg:tags":[
        "operator",
        "local",
        "trucking"
    ],
    "wof:name":"Goss Trucking Inc",
    "wof:placetype":"venue"
},
  "geometry": {"coordinates":[-86.675918,33.778187],"type":"Point"}
}