{
  "type": "Feature",
  "properties": {
    "iso:country":"US",
    "sg:address":"1113 Garland Dr",
    "sg:city":"Mobile",
    "sg:classifiers":[
        {
            "category":"Personal",
            "subcategory":"Beauty Salon",
            "type":"Services"
        }
    ],
    "sg:phone":"+1 251 343 3744",
    "sg:postcode":"36618",
    "sg:province":"AL",
    "sg:tags":[
        "shop"
    ],
    "wof:name":"Bananas Hair Cutting Studio",
    "wof:placetype":"venue"
},
  "geometry": {"coordinates":[-88.159896,30.715402],"type":"Point"}
}