{
  "type": "Feature",
  "properties": {
    "iso:country":"US",
    "sg:address":"2613 Goss St",
    "sg:city":"Birmingham",
    "sg:classifiers":[
        {
            "category":"Building & Trades",
            "subcategory":"Construction",
            "type":"Services"
        }
    ],
    "sg:phone":"+1 205 942 5022",
    "sg:postcode":"35211",
    "sg:province":"AL",
    "sg:tags":[
        "framing",
        "contractor"
    ],
    "wof:name":"Willie & Brothers Cnstr Co",
    "wof:placetype":"venue"
},
  "geometry": {"coordinates":[-86.87001600000001,33.427275],"type":"Point"}
}