{
  "type": "Feature",
  "properties": {
    "iso:country":"US",
    "sg:address":"1100 Forrest Ave",
    "sg:city":"Florence",
    "sg:classifiers":[
        {
            "category":"Wholesale",
            "subcategory":"Hardware",
            "type":"Manufacturing & Wholesale Goods"
        }
    ],
    "sg:phone":"+1 256 767 0260",
    "sg:postcode":"35630",
    "sg:province":"AL",
    "sg:tags":[
        "plumbing",
        "fixture",
        "supply"
    ],
    "sg:website":"www.southernpipe.com",
    "wof:name":"Southern Pipe & Supply Co",
    "wof:placetype":"venue"
},
  "geometry": {"coordinates":[-87.666497,34.8124],"type":"Point"}
}