{
  "type": "Feature",
  "properties": {
    "iso:country":"US",
    "sg:address":"12894 US Hwy 278",
    "sg:city":"Cullman",
    "sg:classifiers":[
        {
            "category":"Manufacturing",
            "subcategory":"Metals",
            "type":"Manufacturing & Wholesale Goods"
        }
    ],
    "sg:phone":"+1 256 747 2776",
    "sg:postcode":"35057",
    "sg:province":"AL",
    "sg:tags":[
        "steel"
    ],
    "wof:name":"Reid Building & Truss Co Inc",
    "wof:placetype":"venue"
},
  "geometry": {"coordinates":[-87.074344,34.201132],"type":"Point"}
}