{
  "type": "Feature",
  "properties": {
    "addr:full":"118 Lindsey Ave Butler AL 36904",
    "addr:housenumber":"118",
    "addr:postcode":"36904",
    "addr:street":"Lindsey Ave",
    "iso:country":"US",
    "sg:address":"118 Lindsey Ave",
    "sg:city":"Butler",
    "sg:classifiers":[
        {
            "category":"Retail",
            "subcategory":"Auto Repair",
            "type":"Services"
        }
    ],
    "sg:phone":"+1 205 459 3167",
    "sg:postcode":"36904",
    "sg:province":"AL",
    "sg:tags":[
        "repairing",
        "automobile"
    ],
    "wof:name":"B & S Auto Repair",
    "wof:placetype":"venue"
},
  "geometry": {"coordinates":[-88.237661,32.092472],"type":"Point"}
}