{
  "type": "Feature",
  "properties": {
    "addr:full":"19175 Odom Dr Citronelle AL 36522",
    "addr:postcode":"19175;36522",
    "addr:street":"Odom Dr",
    "iso:country":"US",
    "sg:address":"19175 Odom Dr",
    "sg:city":"Citronelle",
    "sg:classifiers":[
        {
            "category":"Autos & Motor Vehicles",
            "subcategory":"Automobile Sales",
            "type":"Retail Goods"
        }
    ],
    "sg:phone":"+1 251 866 7100",
    "sg:postcode":"36522",
    "sg:province":"AL",
    "sg:tags":[
        "used"
    ],
    "wof:name":"Cars",
    "wof:placetype":"venue"
},
  "geometry": {"coordinates":[-88.24091,31.090922],"type":"Point"}
}