{
  "type": "Feature",
  "properties": {
    "iso:country":"US",
    "sg:address":"835 Hale Rd",
    "sg:city":"Mobile",
    "sg:classifiers":[
        {
            "category":"Building & Trades",
            "subcategory":"Construction",
            "type":"Services"
        }
    ],
    "sg:phone":"+1 251 635 0058",
    "sg:postcode":"36608",
    "sg:province":"AL",
    "sg:tags":[
        "contractor"
    ],
    "wof:name":"Smileys Paint & Drywall",
    "wof:placetype":"venue"
},
  "geometry": {"coordinates":[-88.26771599999999,30.672532],"type":"Point"}
}