{
  "type": "Feature",
  "properties": {
    "iso:country":"US",
    "sg:address":"711 N Main St",
    "sg:city":"Atmore",
    "sg:classifiers":[
        {
            "category":"Building & Trades",
            "subcategory":"Pest Control",
            "type":"Services"
        }
    ],
    "sg:phone":"+1 251 446 3133",
    "sg:postcode":"36502",
    "sg:province":"AL",
    "wof:name":"Baldwin Gulf Coast Pest Cntrl",
    "wof:placetype":"venue"
},
  "geometry": {"coordinates":[-87.493191,31.035366],"type":"Point"}
}