{
  "type": "Feature",
  "properties": {
    "iso:country":"US",
    "sg:address":"2304 27th Ave",
    "sg:city":"Northport",
    "sg:classifiers":[
        {
            "category":"Restaurant",
            "type":"Food & Drink"
        }
    ],
    "sg:phone":"+1 205 333 6245",
    "sg:postcode":"35476",
    "sg:province":"AL",
    "sg:tags":[
        "eating"
    ],
    "wof:name":"Archibalds Bbq 2",
    "wof:placetype":"venue"
},
  "geometry": {"coordinates":[-87.583668,33.234413],"type":"Point"}
}