{
  "type": "Feature",
  "properties": {
    "iso:country":"US",
    "sg:address":"5115 Narrow Lane Rd",
    "sg:city":"Montgomery",
    "sg:classifiers":[
        {
            "category":"Wholesale",
            "subcategory":"Construction Materials",
            "type":"Manufacturing & Wholesale Goods"
        }
    ],
    "sg:phone":"+1 334 284 4260",
    "sg:postcode":"36116",
    "sg:province":"AL",
    "sg:tags":[
        "lumber",
        "sales"
    ],
    "wof:name":"Conway Co",
    "wof:placetype":"venue"
},
  "geometry": {"coordinates":[-86.276844,32.303475],"type":"Point"}
}