{
  "type": "Feature",
  "properties": {
    "addr:full":"2244 Center Point Pkwy Birmingham AL 35215",
    "addr:housenumber":"2244",
    "addr:postcode":"35215",
    "addr:street":"Center Point Pkwy",
    "iso:country":"US",
    "sg:address":"2244 Center Point Pkwy",
    "sg:city":"Birmingham",
    "sg:classifiers":[
        {
            "category":"Banks & Credit Unions",
            "subcategory":"Bank",
            "type":"Services"
        }
    ],
    "sg:phone":"+1 205 854 3732",
    "sg:postcode":"35215",
    "sg:province":"AL",
    "sg:tags":[
        "loan",
        "real estate"
    ],
    "wof:name":"American Home Lending",
    "wof:placetype":"venue"
},
  "geometry": {"coordinates":[-86.683903,33.643716],"type":"Point"}
}