{
  "type": "Feature",
  "properties": {
    "addr:full":"128 River Oaks Dr Madison AL 35758",
    "addr:housenumber":"128",
    "addr:postcode":"35758",
    "addr:street":"River Oaks Dr",
    "iso:country":"US",
    "sg:address":"128 River Oaks Dr",
    "sg:city":"Madison",
    "sg:classifiers":[
        {
            "category":"Building & Trades",
            "subcategory":"Construction",
            "type":"Services"
        }
    ],
    "sg:phone":"+1 256 430 6883",
    "sg:postcode":"35758",
    "sg:province":"AL",
    "sg:tags":[
        "house"
    ],
    "wof:name":"His Valreginald Master Builder",
    "wof:placetype":"venue"
},
  "geometry": {"coordinates":[-86.70421399999999,34.731297],"type":"Point"}
}