{
  "type": "Feature",
  "properties": {
    "iso:country":"US",
    "sg:address":"128 River Oaks Dr",
    "sg:city":"Madison",
    "sg:classifiers":[
        {
            "category":"Building & Trades",
            "subcategory":"Construction",
            "type":"Services"
        }
    ],
    "sg:phone":"+1 256 430 6883",
    "sg:postcode":"35758",
    "sg:province":"AL",
    "sg:tags":[
        "house"
    ],
    "wof:name":"His Valreginald Master Builder",
    "wof:placetype":"venue"
},
  "geometry": {"coordinates":[-86.704214,34.731297],"type":"Point"}
}