{
  "type": "Feature",
  "properties": {
    "iso:country":"US",
    "sg:address":"2100 Longleaf Trl",
    "sg:city":"Birmingham",
    "sg:classifiers":[
        {
            "category":"Wholesale",
            "subcategory":"Medical Equipment & Supplies",
            "type":"Manufacturing & Wholesale Goods"
        }
    ],
    "sg:phone":"+1 205 706 7130",
    "sg:postcode":"35243",
    "sg:province":"AL",
    "sg:tags":[
        "for"
    ],
    "wof:name":"Advanced Imaging Solutions Inc",
    "wof:placetype":"venue"
},
  "geometry": {"coordinates":[-86.757688,33.42136],"type":"Point"}
}