{
  "type": "Feature",
  "properties": {
    "addr:full":"103 Court St Grove Hill AL 36451",
    "addr:housenumber":"103",
    "addr:postcode":"36451",
    "addr:street":"Court St;Hill",
    "iso:country":"US",
    "sg:address":"103 Court St",
    "sg:city":"Grove Hill",
    "sg:classifiers":[
        {
            "category":"Professional",
            "subcategory":"Lawyer & Legal Services",
            "type":"Services"
        }
    ],
    "sg:phone":"+1 334 636 4943",
    "sg:postcode":"36451",
    "sg:province":"AL",
    "sg:tags":[
        "attorney"
    ],
    "wof:name":"Wilson & Drinkard",
    "wof:placetype":"venue"
},
  "geometry": {"coordinates":[-87.778098,31.708768],"type":"Point"}
}