{
  "type": "Feature",
  "properties": {
    "addr:full":"1160 Huffman Rd Birmingham AL 35215",
    "addr:housenumber":"1160",
    "addr:postcode":"35215",
    "addr:street":"Huffman Rd",
    "iso:country":"US",
    "sg:address":"1160 Huffman Rd",
    "sg:city":"Birmingham",
    "sg:classifiers":[
        {
            "category":"Health Services",
            "subcategory":"Doctor",
            "type":"Services"
        }
    ],
    "sg:phone":"+1 205 856 5500",
    "sg:postcode":"35215",
    "sg:province":"AL",
    "sg:tags":[
        "physician",
        "surgeon"
    ],
    "wof:name":"Henry L Darnell Jr Family Prac",
    "wof:placetype":"venue"
},
  "geometry": {"coordinates":[-86.687608,33.612257],"type":"Point"}
}