{
  "type": "Feature",
  "properties": {
    "addr:full":"4200 Washington Ferry Rd Montgomery AL 36108",
    "addr:housenumber":"4200",
    "addr:postcode":"36108",
    "addr:street":"Washington Ferry Rd",
    "iso:country":"US",
    "sg:address":"4200 Washington Ferry Rd",
    "sg:city":"Montgomery",
    "sg:classifiers":[
        {
            "category":"Manufacturing",
            "subcategory":"Building Materials",
            "type":"Manufacturing & Wholesale Goods"
        }
    ],
    "sg:phone":"+1 334 263 4839",
    "sg:postcode":"36108",
    "sg:province":"AL",
    "wof:name":"Stake Supply",
    "wof:placetype":"venue"
},
  "geometry": {"coordinates":[-86.382514,32.392285],"type":"Point"}
}