{
  "type": "Feature",
  "properties": {
    "addr:full":"2287 Landline Rd Selma AL 36701",
    "addr:housenumber":"2287",
    "addr:postcode":"36701",
    "addr:street":"Landline Rd",
    "iso:country":"US",
    "sg:address":"2287 Landline Rd",
    "sg:city":"Selma",
    "sg:classifiers":[
        {
            "category":"Building & Trades",
            "subcategory":"Pest Control",
            "type":"Services"
        }
    ],
    "sg:phone":"+1 334 874 8247",
    "sg:postcode":"36701",
    "sg:province":"AL",
    "wof:name":"Selma Pest Control Inc",
    "wof:placetype":"venue"
},
  "geometry": {"coordinates":[-87.08326700000001,32.416263],"type":"Point"}
}