{
  "type": "Feature",
  "properties": {
    "iso:country":"US",
    "sg:address":"412 Wilderness Rd",
    "sg:city":"Pelham",
    "sg:classifiers":[
        {
            "category":"Building & Trades",
            "subcategory":"Construction",
            "type":"Services"
        }
    ],
    "sg:phone":"+1 205 620 5538",
    "sg:postcode":"35124",
    "sg:province":"AL",
    "sg:tags":[
        "residential"
    ],
    "wof:name":"PSM Construction Co Inc",
    "wof:placetype":"venue"
},
  "geometry": {"coordinates":[-86.806605,33.314887],"type":"Point"}
}