{
  "type": "Feature",
  "properties": {
    "iso:country":"US",
    "sg:address":"2916 18th St S",
    "sg:city":"Birmingham",
    "sg:classifiers":[
        {
            "category":"Restaurant",
            "type":"Food & Drink"
        }
    ],
    "sg:menulink":"http://www.allmenus.com/al/birmingham/254738-savages-bakery/menu/",
    "sg:phone":"+1 205 871 4901",
    "sg:postcode":"35209",
    "sg:province":"AL",
    "wof:name":"Savage's Bakery",
    "wof:placetype":"venue"
},
  "geometry": {"coordinates":[-86.791751,33.478813],"type":"Point"}
}