{
  "type": "Feature",
  "properties": {
    "iso:country":"US",
    "sg:address":"2206 Lancelot Dr SW",
    "sg:city":"Decatur",
    "sg:classifiers":[
        {
            "category":"Building & Trades",
            "subcategory":"Construction",
            "type":"Services"
        }
    ],
    "sg:phone":"+1 256 350 8319",
    "sg:postcode":"35603",
    "sg:province":"AL",
    "sg:tags":[
        "house"
    ],
    "wof:name":"C&C Const Inc",
    "wof:placetype":"venue"
},
  "geometry": {"coordinates":[-87.025072,34.554855],"type":"Point"}
}