{
  "type": "Feature",
  "properties": {
    "iso:country":"US",
    "sg:address":"100 Frankfurt Cir",
    "sg:city":"Birmingham",
    "sg:classifiers":[
        {
            "category":"Restaurant",
            "type":"Food & Drink"
        }
    ],
    "sg:menulink":"http://www.allmenus.com/al/hoover/55607-subway/menu/",
    "sg:phone":"+1 205 942 6500",
    "sg:postcode":"35211",
    "sg:province":"AL",
    "sg:tags":[
        "american",
        "sandwich"
    ],
    "wof:name":"Subway",
    "wof:placetype":"venue"
},
  "geometry": {"coordinates":[-86.861351,33.436372],"type":"Point"}
}