{
  "type": "Feature",
  "properties": {
    "addr:full":"669 1st St SW Alabaster AL 35007",
    "addr:housenumber":"669",
    "addr:postcode":"35007",
    "addr:street":"1St St Sw",
    "iso:country":"US",
    "sg:address":"669 1st St SW",
    "sg:city":"Alabaster",
    "sg:classifiers":[
        {
            "category":"Cinema",
            "subcategory":"Movie Rental",
            "type":"Entertainment"
        }
    ],
    "sg:phone":"+1 205 621 4440",
    "sg:postcode":"35007",
    "sg:province":"AL",
    "sg:tags":[
        "leasing",
        "video",
        "disc",
        "tape"
    ],
    "wof:name":"Blockbuster Video",
    "wof:placetype":"venue"
},
  "geometry": {"coordinates":[-86.819138,33.237187],"type":"Point"}
}