{
  "type": "Feature",
  "properties": {
    "addr:full":"475 E Main St Prattville AL 36067",
    "addr:housenumber":"475",
    "addr:postcode":"36067",
    "addr:street":"E Main St",
    "iso:country":"US",
    "sg:address":"475 E Main St",
    "sg:city":"Prattville",
    "sg:classifiers":[
        {
            "category":"Farming",
            "subcategory":"Livestock Farm",
            "type":"Manufacturing & Wholesale Goods"
        }
    ],
    "sg:phone":"+1 334 365 5082",
    "sg:postcode":"36067",
    "sg:province":"AL",
    "sg:tags":[
        "specialty",
        "animal"
    ],
    "wof:name":"Harlan Sprague Dawley Inc",
    "wof:placetype":"venue"
},
  "geometry": {"coordinates":[-86.464089,32.459371],"type":"Point"}
}