{
  "type": "Feature",
  "properties": {
    "addr:full":"7028 Eastchase Pkwy Montgomery AL 36117",
    "addr:housenumber":"7028",
    "addr:postcode":"36117",
    "addr:street":"Eastchase Pkwy",
    "iso:country":"US",
    "sg:address":"7028 Eastchase Pkwy",
    "sg:city":"Montgomery",
    "sg:classifiers":[
        {
            "category":"Restaurant",
            "type":"Food & Drink"
        }
    ],
    "sg:menulink":"http://www.allmenus.com/al/montgomery/89451-moes-southwest-grill/menu/",
    "sg:phone":"+1 334 356 3333",
    "sg:postcode":"36117",
    "sg:province":"AL",
    "sg:tags":[
        "mexican"
    ],
    "wof:name":"Moe's Southwest Grill",
    "wof:placetype":"venue"
},
  "geometry": {"coordinates":[-86.169319,32.357694],"type":"Point"}
}