{
  "type": "Feature",
  "properties": {
    "iso:country":"US",
    "sg:address":"1313 Grants Mill Rd",
    "sg:city":"Birmingham",
    "sg:classifiers":[
        {
            "category":"Autos & Motor Vehicles",
            "subcategory":"Automobile Sales",
            "type":"Retail Goods"
        },
        {
            "category":"Retail",
            "subcategory":"Auto Repair",
            "type":"Services"
        }
    ],
    "sg:phone":"+1 205 957 1313",
    "sg:postcode":"35210",
    "sg:province":"AL",
    "sg:tags":[
        "automotive",
        "used",
        "dealer",
        "car"
    ],
    "sg:website":"www.withyoudowntheroad.com",
    "wof:name":"Benchmark Chrysler Jeep Dodge",
    "wof:placetype":"venue"
},
  "geometry": {"coordinates":[-86.680182,33.533207],"type":"Point"}
}