{
  "type": "Feature",
  "properties": {
    "addr:full":"166 Commerce St Montgomery AL 36104",
    "addr:housenumber":"166",
    "addr:postcode":"36104",
    "addr:street":"Commerce St",
    "iso:country":"US",
    "sg:address":"166 Commerce St",
    "sg:city":"Montgomery",
    "sg:classifiers":[
        {
            "category":"Real Estate",
            "subcategory":"Architect",
            "type":"Services"
        }
    ],
    "sg:phone":"+1 334 263 6401",
    "sg:postcode":"36104",
    "sg:province":"AL",
    "wof:name":"2 Wr Holmes Wilkins Architects",
    "wof:placetype":"venue"
},
  "geometry": {"coordinates":[-86.311173,32.379406],"type":"Point"}
}