{
  "type": "Feature",
  "properties": {
    "addr:full":"2740 Zelda Rd Montgomery AL 36106",
    "addr:housenumber":"2740",
    "addr:postcode":"36106",
    "addr:street":"Zelda Rd",
    "iso:country":"US",
    "sg:address":"2740 Zelda Rd",
    "sg:city":"Montgomery",
    "sg:classifiers":[
        {
            "category":"Professional",
            "subcategory":"Lawyer & Legal Services",
            "type":"Services"
        }
    ],
    "sg:phone":"+1 334 409 2245",
    "sg:postcode":"36106",
    "sg:province":"AL",
    "sg:tags":[
        "attorney"
    ],
    "wof:name":"David B Hughes",
    "wof:placetype":"venue"
},
  "geometry": {"coordinates":[-86.266598,32.363362],"type":"Point"}
}