{
  "type": "Feature",
  "properties": {
    "iso:country":"US",
    "sg:address":"320 Church Ave SE",
    "sg:city":"Jacksonville",
    "sg:classifiers":[
        {
            "category":"Social Services",
            "type":"Services"
        }
    ],
    "sg:phone":"+1 256 435 9199",
    "sg:postcode":"36265",
    "sg:province":"AL",
    "sg:tags":[
        "senior",
        "center",
        "citizen"
    ],
    "wof:name":"Senior Citizens Center",
    "wof:placetype":"venue"
},
  "geometry": {"coordinates":[-85.75989,33.813873],"type":"Point"}
}