{
  "type": "Feature",
  "properties": {
    "addr:full":"507 Church Ave NE Jacksonville AL 36265",
    "addr:housenumber":"507",
    "addr:postcode":"36265",
    "addr:street":"Church Ave Ne",
    "iso:country":"US",
    "sg:address":"507 Church Ave NE",
    "sg:city":"Jacksonville",
    "sg:classifiers":[
        {
            "category":"Wholesale",
            "subcategory":"Non-durable Goods",
            "type":"Manufacturing & Wholesale Goods"
        }
    ],
    "sg:phone":"+1 256 435 2566",
    "sg:postcode":"36265",
    "sg:province":"AL",
    "sg:tags":[
        "art"
    ],
    "wof:name":"Wrens Nest Inc",
    "wof:placetype":"venue"
},
  "geometry": {"coordinates":[-85.759699,33.822984],"type":"Point"}
}