{
  "type": "Feature",
  "properties": {
    "iso:country":"US",
    "sg:address":"221 McKenzie St",
    "sg:city":"Foley",
    "sg:classifiers":[
        {
            "category":"Food & Beverages",
            "subcategory":"Liquor & Beverages",
            "type":"Retail Goods"
        }
    ],
    "sg:phone":"+1 251 943 7611",
    "sg:postcode":"36535",
    "sg:province":"AL",
    "wof:name":"ABC Store",
    "wof:placetype":"venue"
},
  "geometry": {"coordinates":[-87.683744,30.40552],"type":"Point"}
}