{
  "type": "Feature",
  "properties": {
    "addr:full":"2238 Pelham Pkwy Pelham AL 35124",
    "addr:housenumber":"2238",
    "addr:postcode":"35124",
    "addr:street":"Pelham Pkwy",
    "iso:country":"US",
    "sg:address":"2238 Pelham Pkwy",
    "sg:city":"Pelham",
    "sg:classifiers":[
        {
            "category":"Restaurant",
            "type":"Food & Drink"
        }
    ],
    "sg:phone":"+1 205 682 9191",
    "sg:postcode":"35124",
    "sg:province":"AL",
    "wof:name":"Firehouse Subs",
    "wof:placetype":"venue"
},
  "geometry": {"coordinates":[-86.791887,33.334304],"type":"Point"}
}