{
  "type": "Feature",
  "properties": {
    "iso:country":"US",
    "sg:address":"500 2nd Ave SW",
    "sg:city":"Cullman",
    "sg:classifiers":[
        {
            "category":"Government",
            "subcategory":"Police Station",
            "type":"Public Place"
        }
    ],
    "sg:phone":"+1 256 734 0342",
    "sg:postcode":"35055",
    "sg:province":"AL",
    "sg:tags":[
        "county",
        "sheriff"
    ],
    "wof:name":"Sherrifs Dept",
    "wof:placetype":"venue"
},
  "geometry": {"coordinates":[-86.842469,34.172777],"type":"Point"}
}