{
  "type": "Feature",
  "properties": {
    "iso:country":"US",
    "sg:address":"6700 Milkhouse Ct",
    "sg:city":"Mobile",
    "sg:classifiers":[
        {
            "category":"Professional",
            "subcategory":"Management & Consulting",
            "type":"Services"
        }
    ],
    "sg:phone":"+1 251 607 0946",
    "sg:postcode":"36695",
    "sg:province":"AL",
    "wof:name":"Pendergrass John",
    "wof:placetype":"venue"
},
  "geometry": {"coordinates":[-88.200162,30.656516],"type":"Point"}
}