{
  "type": "Feature",
  "properties": {
    "iso:country":"US",
    "sg:address":"1232 Eastdale Mall",
    "sg:city":"Montgomery",
    "sg:classifiers":[
        {
            "category":"Recreation",
            "subcategory":"Amusement Park",
            "type":"Entertainment"
        },
        {
            "category":"Recreation",
            "subcategory":"Arcade",
            "type":"Entertainment"
        }
    ],
    "sg:phone":"+1 334 272 1066",
    "sg:postcode":"36117",
    "sg:province":"AL",
    "wof:name":"Aladdin's Castle",
    "wof:placetype":"venue"
},
  "geometry": {"coordinates":[-86.205011,32.385114],"type":"Point"}
}