{
  "type": "Feature",
  "properties": {
    "addr:full":"102 W 4th St Sheffield AL 35660",
    "addr:housenumber":"102",
    "addr:postcode":"35660",
    "addr:street":"W 4Th St",
    "iso:country":"US",
    "sg:address":"102 W 4th St",
    "sg:city":"Sheffield",
    "sg:classifiers":[
        {
            "category":"Organizations",
            "subcategory":"Religious Organization",
            "type":"Services"
        }
    ],
    "sg:phone":"+1 256 314 4588",
    "sg:postcode":"35660",
    "sg:province":"AL",
    "wof:name":"New Song Family Ministry",
    "wof:placetype":"venue"
},
  "geometry": {"coordinates":[-87.69918800000001,34.761954],"type":"Point"}
}