{
  "type": "Feature",
  "properties": {
    "iso:country":"US",
    "sg:address":"3425 Hooper Ln SE",
    "sg:city":"Decatur",
    "sg:classifiers":[
        {
            "category":"Building & Trades",
            "subcategory":"Construction",
            "type":"Services"
        }
    ],
    "sg:phone":"+1 256 351 8211",
    "sg:postcode":"35603",
    "sg:province":"AL",
    "sg:tags":[
        "downspouts",
        "gutter"
    ],
    "wof:name":"Decatur Gutter Svc",
    "wof:placetype":"venue"
},
  "geometry": {"coordinates":[-86.96617000000001,34.54242],"type":"Point"}
}