{
  "type": "Feature",
  "properties": {
    "addr:full":"218 Arad Thompson Rd NE Arab AL 35016",
    "addr:housenumber":"218",
    "addr:postcode":"35016",
    "addr:street":"Thompson Rd Ne",
    "iso:country":"US",
    "sg:address":"218 Arad Thompson Rd NE",
    "sg:city":"Arab",
    "sg:classifiers":[
        {
            "category":"Manufacturing",
            "subcategory":"Tools & Machinery",
            "type":"Manufacturing & Wholesale Goods"
        }
    ],
    "sg:phone":"+1 256 586 8152",
    "sg:postcode":"35016",
    "sg:province":"AL",
    "sg:tags":[
        "cylinder"
    ],
    "sg:website":"www.hyco.net",
    "wof:name":"Hyco Alabama",
    "wof:placetype":"venue"
},
  "geometry": {"coordinates":[-86.477334,34.31441],"type":"Point"}
}