{
  "type": "Feature",
  "properties": {
    "iso:country":"US",
    "sg:address":"141 Baltzer Rd",
    "sg:city":"Wetumpka",
    "sg:classifiers":[
        {
            "category":"Building & Trades",
            "subcategory":"Plumbing",
            "type":"Services"
        }
    ],
    "sg:phone":"+1 334 567 5951",
    "sg:postcode":"36092",
    "sg:province":"AL",
    "sg:tags":[
        "contractor"
    ],
    "wof:name":"Nixon Services Inc",
    "wof:placetype":"venue"
},
  "geometry": {"coordinates":[-86.31273,32.557111],"type":"Point"}
}