{
  "type": "Feature",
  "properties": {
    "iso:country":"US",
    "sg:address":"139 Folmar Pkwy",
    "sg:city":"Montgomery",
    "sg:classifiers":[
        {
            "category":"Wholesale",
            "subcategory":"Electrical",
            "type":"Manufacturing & Wholesale Goods"
        }
    ],
    "sg:phone":"+1 334 280 2790",
    "sg:postcode":"36105",
    "sg:province":"AL",
    "sg:tags":[
        "electric",
        "motor"
    ],
    "wof:name":"Motor City Logistics LLC",
    "wof:placetype":"venue"
},
  "geometry": {"coordinates":[-86.357277,32.268555],"type":"Point"}
}