{
  "type": "Feature",
  "properties": {
    "addr:full":"3828 Old Leeds Rd Birmingham AL 35213",
    "addr:housenumber":"3828",
    "addr:postcode":"35213",
    "addr:street":"Old Leeds Rd",
    "iso:country":"US",
    "sg:address":"3828 Old Leeds Rd",
    "sg:city":"Birmingham",
    "sg:classifiers":[
        {
            "category":"Professional",
            "subcategory":"Business Services",
            "type":"Services"
        }
    ],
    "sg:phone":"+1 205 870 7116",
    "sg:postcode":"35213",
    "sg:province":"AL",
    "wof:name":"Parnell Allene Interiors",
    "wof:placetype":"venue"
},
  "geometry": {"coordinates":[-86.74092899999999,33.499368],"type":"Point"}
}