{
  "type": "Feature",
  "properties": {
    "iso:country":"US",
    "sg:address":"505 Hartley Rd",
    "sg:city":"Saraland",
    "sg:classifiers":[
        {
            "category":"Personal",
            "subcategory":"Beauty Salon",
            "type":"Services"
        }
    ],
    "sg:phone":"+1 251 679 8739",
    "sg:postcode":"36571",
    "sg:province":"AL",
    "sg:tags":[
        "shop"
    ],
    "wof:name":"Shanas Hair & Beauty Care",
    "wof:placetype":"venue"
},
  "geometry": {"coordinates":[-88.06836,30.833369],"type":"Point"}
}