{
  "type": "Feature",
  "properties": {
    "iso:country":"US",
    "sg:address":"3584 Bankhead Ave",
    "sg:city":"Montgomery",
    "sg:classifiers":[
        {
            "category":"Personal",
            "type":"Services"
        }
    ],
    "sg:phone":"+1 334 286 0043",
    "sg:postcode":"36111",
    "sg:province":"AL",
    "sg:tags":[
        "information",
        "financial",
        "acquisition"
    ],
    "wof:name":"Kara Tech Enterprises Inc",
    "wof:placetype":"venue"
},
  "geometry": {"coordinates":[-86.288834,32.341307],"type":"Point"}
}