{
  "type": "Feature",
  "properties": {
    "addr:full":"2216 W Clinton Ave Huntsville AL 35805",
    "addr:housenumber":"2216",
    "addr:postcode":"35805",
    "addr:street":"W Clinton Ave",
    "iso:country":"US",
    "sg:address":"2216 W Clinton Ave",
    "sg:city":"Huntsville",
    "sg:classifiers":[
        {
            "category":"Wholesale",
            "subcategory":"Electrical",
            "type":"Manufacturing & Wholesale Goods"
        }
    ],
    "sg:phone":"+1 256 534 0376",
    "sg:postcode":"35805",
    "sg:province":"AL",
    "sg:tags":[
        "electronic",
        "merchandise"
    ],
    "wof:name":"W & W Electronics Inc",
    "wof:placetype":"venue"
},
  "geometry": {"coordinates":[-86.60121100000001,34.723655],"type":"Point"}
}