{
  "type": "Feature",
  "properties": {
    "iso:country":"US",
    "sg:address":"2691 Sandlin Rd SW",
    "sg:city":"Decatur",
    "sg:classifiers":[
        {
            "category":"Professional",
            "subcategory":"Business Services",
            "type":"Services"
        }
    ],
    "sg:phone":"+1 256 355 8253",
    "sg:postcode":"35601",
    "sg:province":"AL",
    "wof:name":"Prometric Testing Center",
    "wof:placetype":"venue"
},
  "geometry": {"coordinates":[-86.99118,34.562345],"type":"Point"}
}