{
  "type": "Feature",
  "properties": {
    "iso:country":"US",
    "sg:address":"4917 Emerald Bay Dr",
    "sg:city":"Northport",
    "sg:classifiers":[
        {
            "category":"Real Estate",
            "subcategory":"Surveying",
            "type":"Services"
        }
    ],
    "sg:phone":"+1 205 339 9595",
    "sg:postcode":"35473",
    "sg:province":"AL",
    "sg:tags":[
        "surveyor"
    ],
    "wof:name":"Acorn Corp",
    "wof:placetype":"venue"
},
  "geometry": {"coordinates":[-87.574624,33.255252],"type":"Point"}
}