{
  "type": "Feature",
  "properties": {
    "iso:country":"US",
    "sg:address":"1735 Opelika Rd",
    "sg:city":"Auburn",
    "sg:classifiers":[
        {
            "category":"Home & Garden",
            "subcategory":"Furniture",
            "type":"Retail Goods"
        }
    ],
    "sg:phone":"+1 334 887 5455",
    "sg:postcode":"36830",
    "sg:province":"AL",
    "sg:website":"www.farmersfurniture.com",
    "wof:name":"Farmers Furniture",
    "wof:placetype":"venue"
},
  "geometry": {"coordinates":[-85.446497,32.624847],"type":"Point"}
}