{
  "type": "Feature",
  "properties": {
    "addr:full":"1735 Opelika Rd Auburn AL 36830",
    "addr:housenumber":"1735",
    "addr:postcode":"36830",
    "addr:street":"Opelika Rd",
    "iso:country":"US",
    "sg:address":"1735 Opelika Rd",
    "sg:city":"Auburn",
    "sg:classifiers":[
        {
            "category":"Home & Garden",
            "subcategory":"Furniture",
            "type":"Retail Goods"
        }
    ],
    "sg:phone":"+1 334 887 5455",
    "sg:postcode":"36830",
    "sg:province":"AL",
    "sg:website":"www.farmersfurniture.com",
    "wof:name":"Farmers Furniture",
    "wof:placetype":"venue"
},
  "geometry": {"coordinates":[-85.44649699999999,32.624847],"type":"Point"}
}