{
  "type": "Feature",
  "properties": {
    "iso:country":"US",
    "sg:address":"4319 Spartacus Dr SW",
    "sg:city":"Huntsville",
    "sg:classifiers":[
        {
            "category":"Building & Trades",
            "subcategory":"Plumbing",
            "type":"Services"
        }
    ],
    "sg:phone":"+1 256 882 0491",
    "sg:postcode":"35805",
    "sg:province":"AL",
    "sg:tags":[
        "conditioning",
        "air",
        "system",
        "contractor"
    ],
    "wof:name":"Alabama HVAC",
    "wof:placetype":"venue"
},
  "geometry": {"coordinates":[-86.59966900000001,34.693728],"type":"Point"}
}