{
  "type": "Feature",
  "properties": {
    "iso:country":"US",
    "sg:address":"1508 Mulberry St",
    "sg:city":"Montgomery",
    "sg:classifiers":[
        {
            "category":"Personal",
            "subcategory":"Beauty Salon",
            "type":"Services"
        }
    ],
    "sg:phone":"+1 334 269 4938",
    "sg:postcode":"36106",
    "sg:province":"AL",
    "sg:tags":[
        "shop"
    ],
    "wof:name":"Cynde Hassell Studio",
    "wof:placetype":"venue"
},
  "geometry": {"coordinates":[-86.28319999999999,32.364341],"type":"Point"}
}