{
  "type": "Feature",
  "properties": {
    "iso:country":"US",
    "sg:address":"1340 Carmichael Way",
    "sg:city":"Montgomery",
    "sg:classifiers":[
        {
            "category":"Banks & Credit Unions",
            "subcategory":"Investment Brokerage",
            "type":"Services"
        }
    ],
    "sg:phone":"+1 334 279 7596",
    "sg:postcode":"36106",
    "sg:province":"AL",
    "sg:tags":[
        "consultant",
        "planning",
        "financial"
    ],
    "wof:name":"AIG Sunamerica",
    "wof:placetype":"venue"
},
  "geometry": {"coordinates":[-86.240896,32.356552],"type":"Point"}
}