{
  "type": "Feature",
  "properties": {
    "iso:country":"US",
    "sg:address":"3355 State Rte 14",
    "sg:city":"Millbrook",
    "sg:classifiers":[
        {
            "category":"Personal",
            "subcategory":"Beauty Salon",
            "type":"Services"
        }
    ],
    "sg:phone":"+1 334 290 1316",
    "sg:postcode":"36054",
    "sg:province":"AL",
    "sg:tags":[
        "shop"
    ],
    "wof:name":"Styles Diva",
    "wof:placetype":"venue"
},
  "geometry": {"coordinates":[-86.364207,32.5235],"type":"Point"}
}