{
  "type": "Feature",
  "properties": {
    "iso:country":"US",
    "sg:address":"901 S Hull St",
    "sg:city":"Montgomery",
    "sg:classifiers":[
        {
            "category":"Professional",
            "subcategory":"Employment Agencies",
            "type":"Services"
        }
    ],
    "sg:phone":"+1 334 263 0370",
    "sg:postcode":"36104",
    "sg:province":"AL",
    "sg:tags":[
        "opportunity"
    ],
    "wof:name":"Industrial Staffing Of Al",
    "wof:placetype":"venue"
},
  "geometry": {"coordinates":[-86.30320399999999,32.364492],"type":"Point"}
}