{
  "type": "Feature",
  "properties": {
    "iso:country":"US",
    "sg:address":"2856 18th St S",
    "sg:city":"Birmingham",
    "sg:classifiers":[
        {
            "category":"Personal",
            "subcategory":"Shoe Repair & Shine",
            "type":"Services"
        }
    ],
    "sg:phone":"+1 205 879 2329",
    "sg:postcode":"35209",
    "sg:province":"AL",
    "sg:tags":[
        "parlor"
    ],
    "wof:name":"Homewood Shoe Hospital",
    "wof:placetype":"venue"
},
  "geometry": {"coordinates":[-86.791814,33.479152],"type":"Point"}
}