{
  "type": "Feature",
  "properties": {
    "iso:country":"US",
    "sg:address":"2116 University Blvd",
    "sg:city":"Birmingham",
    "sg:classifiers":[
        {
            "category":"Retail",
            "subcategory":"Funeral Services",
            "type":"Services"
        }
    ],
    "sg:phone":"+1 205 251 5254",
    "sg:postcode":"35233",
    "sg:province":"AL",
    "sg:tags":[
        "director",
        "plans-pre-arranged"
    ],
    "wof:name":"Birmingham Central Services",
    "wof:placetype":"venue"
},
  "geometry": {"coordinates":[-86.797466,33.5055],"type":"Point"}
}