{
  "type": "Feature",
  "properties": {
    "iso:country":"US",
    "sg:address":"2806 Summit Pl",
    "sg:city":"Birmingham",
    "sg:classifiers":[
        {
            "category":"Manufacturing",
            "subcategory":"Metals",
            "type":"Manufacturing & Wholesale Goods"
        }
    ],
    "sg:phone":"+1 205 967 4266",
    "sg:postcode":"35243",
    "sg:province":"AL",
    "sg:tags":[
        "steel",
        "processing"
    ],
    "wof:name":"APS Inc",
    "wof:placetype":"venue"
},
  "geometry": {"coordinates":[-86.730138,33.450405],"type":"Point"}
}