{
  "type": "Feature",
  "properties": {
    "iso:country":"US",
    "sg:address":"322 S 3rd St",
    "sg:city":"Gadsden",
    "sg:classifiers":[
        {
            "category":"Retail",
            "subcategory":"Laundry & Dry Cleaning",
            "type":"Services"
        }
    ],
    "sg:phone":"+1 256 546 3071",
    "sg:postcode":"35901",
    "sg:province":"AL",
    "sg:tags":[
        "cleaners",
        "cold",
        "storage"
    ],
    "wof:name":"Gieger Cleaners & Laundry Inc",
    "wof:placetype":"venue"
},
  "geometry": {"coordinates":[-86.004266,34.008727],"type":"Point"}
}