{
  "type": "Feature",
  "properties": {
    "iso:country":"US",
    "sg:address":"1593 Co Rd 242",
    "sg:city":"Smiths Station",
    "sg:classifiers":[
        {
            "category":"Social Services",
            "type":"Services"
        }
    ],
    "sg:phone":"+1 334 297 9101",
    "sg:postcode":"36877",
    "sg:province":"AL",
    "sg:tags":[
        "senior",
        "citizen"
    ],
    "wof:name":"Smith Station Senior Ctr",
    "wof:placetype":"venue"
},
  "geometry": {"coordinates":[-85.142895,32.517756],"type":"Point"}
}