{
  "type": "Feature",
  "properties": {
    "iso:country":"US",
    "sg:address":"3081 US Hwy 278",
    "sg:city":"Altoona",
    "sg:classifiers":[
        {
            "category":"Bars & Pubs",
            "type":"Food & Drink"
        }
    ],
    "sg:phone":"+1 205 589 4378",
    "sg:postcode":"35952",
    "sg:province":"AL",
    "wof:name":"Old Tyme Saloon",
    "wof:placetype":"venue"
},
  "geometry": {"coordinates":[-86.321492,34.072267],"type":"Point"}
}