{
  "type": "Feature",
  "properties": {
    "addr:full":"3081 US Hwy 278 Altoona AL 35952",
    "addr:housenumber":"3081",
    "addr:postcode":"35952",
    "addr:street":"Us Hwy 278",
    "iso:country":"US",
    "sg:address":"3081 US Hwy 278",
    "sg:city":"Altoona",
    "sg:classifiers":[
        {
            "category":"Bars & Pubs",
            "type":"Food & Drink"
        }
    ],
    "sg:phone":"+1 205 589 4378",
    "sg:postcode":"35952",
    "sg:province":"AL",
    "wof:name":"Old Tyme Saloon",
    "wof:placetype":"venue"
},
  "geometry": {"coordinates":[-86.32149200000001,34.072267],"type":"Point"}
}