{
  "type": "Feature",
  "properties": {
    "addr:full":"405 Macon Dr Tuskegee AL 36083",
    "addr:housenumber":"405",
    "addr:postcode":"36083",
    "addr:street":"Macon Dr Tuskegee",
    "iso:country":"US",
    "sg:address":"405 Macon Dr",
    "sg:city":"Tuskegee",
    "sg:classifiers":[
        {
            "category":"Organizations",
            "subcategory":"Membership Organization",
            "type":"Services"
        }
    ],
    "sg:phone":"+1 334 727 4200",
    "sg:postcode":"36083",
    "sg:province":"AL",
    "wof:name":"Macon County Council On Retard",
    "wof:placetype":"venue"
},
  "geometry": {"coordinates":[-85.678825,32.430029],"type":"Point"}
}