{
  "type": "Feature",
  "properties": {
    "iso:country":"US",
    "sg:address":"305 S Edgewood Dr",
    "sg:city":"Dothan",
    "sg:classifiers":[
        {
            "category":"Health Services",
            "subcategory":"Chiropractor",
            "type":"Services"
        }
    ],
    "sg:phone":"+1 334 794 3031",
    "sg:postcode":"36301",
    "sg:province":"AL",
    "wof:name":"David K Arnold DC",
    "wof:placetype":"venue"
},
  "geometry": {"coordinates":[-85.404392,31.224092],"type":"Point"}
}