{
  "type": "Feature",
  "properties": {
    "addr:full":"2020 Valleydale Rd Birmingham AL 35244",
    "addr:housenumber":"2020",
    "addr:postcode":"35244",
    "addr:street":"Valleydale Rd",
    "iso:country":"US",
    "sg:address":"2020 Valleydale Rd",
    "sg:city":"Birmingham",
    "sg:classifiers":[
        {
            "category":"Building & Trades",
            "subcategory":"Construction",
            "type":"Services"
        }
    ],
    "sg:phone":"+1 205 989 6455",
    "sg:postcode":"35244",
    "sg:province":"AL",
    "sg:tags":[
        "contractor"
    ],
    "wof:name":"Dunn Building Co",
    "wof:placetype":"venue"
},
  "geometry": {"coordinates":[-86.792844,33.346739],"type":"Point"}
}