{
  "type": "Feature",
  "properties": {
    "iso:country":"US",
    "sg:address":"5456 Cottage Hill Rd",
    "sg:city":"Mobile",
    "sg:classifiers":[
        {
            "category":"Shopping",
            "subcategory":"Jewelry",
            "type":"Retail Goods"
        }
    ],
    "sg:phone":"+1 251 661 9846",
    "sg:postcode":"36609",
    "sg:province":"AL",
    "sg:tags":[
        "jeweler"
    ],
    "wof:name":"Hayes Jewelers Inc",
    "wof:placetype":"venue"
},
  "geometry": {"coordinates":[-88.166673,30.646669],"type":"Point"}
}