{
  "type": "Feature",
  "properties": {
    "iso:country":"US",
    "sg:address":"455 Kenneth Rd",
    "sg:city":"Atmore",
    "sg:classifiers":[
        {
            "category":"Shopping",
            "subcategory":"Clothing, Apparel, & Fashions",
            "type":"Retail Goods"
        }
    ],
    "sg:phone":"+1 251 446 8170",
    "sg:postcode":"36502",
    "sg:province":"AL",
    "sg:tags":[
        "family"
    ],
    "wof:name":"Bishop Family Clothing",
    "wof:placetype":"venue"
},
  "geometry": {"coordinates":[-87.52503299999999,31.082742],"type":"Point"}
}