{
  "type": "Feature",
  "properties": {
    "iso:country":"US",
    "sg:address":"1807 US Hwy 31",
    "sg:city":"Hartselle",
    "sg:classifiers":[
        {
            "category":"Shopping",
            "subcategory":"Computers & Home Electronics",
            "type":"Retail Goods"
        }
    ],
    "sg:phone":"+1 256 773 3044",
    "sg:postcode":"35640",
    "sg:province":"AL",
    "sg:tags":[
        "equipment",
        "dealer"
    ],
    "wof:name":"Ess Computers Inc",
    "wof:placetype":"venue"
},
  "geometry": {"coordinates":[-86.947616,34.460084],"type":"Point"}
}