{
  "type": "Feature",
  "properties": {
    "addr:full":"801 Church St NE Decatur AL 35601",
    "addr:housenumber":"801",
    "addr:postcode":"35601",
    "addr:street":"Church St Ne",
    "iso:country":"US",
    "sg:address":"801 Church St NE",
    "sg:city":"Decatur",
    "sg:classifiers":[
        {
            "category":"Health Services",
            "subcategory":"Clinic",
            "type":"Services"
        }
    ],
    "sg:phone":"+1 256 353 9116",
    "sg:postcode":"35601",
    "sg:province":"AL",
    "sg:tags":[
        "specialty",
        "outpatient"
    ],
    "wof:name":"Quest Recovery Center",
    "wof:placetype":"venue"
},
  "geometry": {"coordinates":[-86.975253,34.606776],"type":"Point"}
}