{
  "type": "Feature",
  "properties": {
    "iso:country":"US",
    "sg:address":"3301 20th St SW",
    "sg:city":"Lanett",
    "sg:classifiers":[
        {
            "category":"Retail",
            "subcategory":"Auto Repair",
            "type":"Services"
        }
    ],
    "sg:phone":"+1 334 576 8598",
    "sg:postcode":"36863",
    "sg:province":"AL",
    "sg:tags":[
        "road",
        "trailer"
    ],
    "wof:name":"Neils Trailer Repair & SE",
    "wof:placetype":"venue"
},
  "geometry": {"coordinates":[-85.230183,32.842247],"type":"Point"}
}