{
  "type": "Feature",
  "properties": {
    "iso:country":"US",
    "sg:address":"4651 Co Rd 126",
    "sg:city":"Henagar",
    "sg:classifiers":[
        {
            "category":"Building & Trades",
            "subcategory":"Construction",
            "type":"Services"
        }
    ],
    "sg:phone":"+1 256 657 1151",
    "sg:postcode":"35978",
    "sg:province":"AL",
    "sg:tags":[
        "general",
        "contractor"
    ],
    "wof:name":"Rogers Construction Inc",
    "wof:placetype":"venue"
},
  "geometry": {"coordinates":[-85.669189,34.610994],"type":"Point"}
}