{
  "type": "Feature",
  "properties": {
    "iso:country":"US",
    "sg:address":"2654 Hackwood Pl",
    "sg:city":"Birmingham",
    "sg:classifiers":[
        {
            "category":"Organizations",
            "subcategory":"Religious Organization",
            "type":"Services"
        }
    ],
    "sg:phone":"+1 205 823 0977",
    "sg:postcode":"35226",
    "sg:province":"AL",
    "wof:name":"Neal Schooley Rev",
    "wof:placetype":"venue"
},
  "geometry": {"coordinates":[-86.81304900000001,33.411275],"type":"Point"}
}