{
  "type": "Feature",
  "properties": {
    "iso:country":"US",
    "sg:address":"2620 Acton Rd",
    "sg:city":"Birmingham",
    "sg:classifiers":[
        {
            "category":"Professional",
            "subcategory":"Testing Lab",
            "type":"Services"
        }
    ],
    "sg:phone":"+1 205 967 5688",
    "sg:postcode":"35243",
    "sg:province":"AL",
    "sg:tags":[
        "consultant",
        "forensic"
    ],
    "wof:name":"International Research Svc",
    "wof:placetype":"venue"
},
  "geometry": {"coordinates":[-86.749849,33.419098],"type":"Point"}
}