{
  "type": "Feature",
  "properties": {
    "iso:country":"US",
    "sg:address":"13916 State Rte 157",
    "sg:city":"Florence",
    "sg:classifiers":[
        {
            "category":"Autos & Motor Vehicles",
            "subcategory":"Automobile Sales",
            "type":"Retail Goods"
        }
    ],
    "sg:phone":"+1 256 767 0270",
    "sg:postcode":"35633",
    "sg:province":"AL",
    "sg:tags":[
        "car",
        "dealer"
    ],
    "wof:name":"D & S Auto Sales",
    "wof:placetype":"venue"
},
  "geometry": {"coordinates":[-87.802182,34.97226],"type":"Point"}
}