{
  "type": "Feature",
  "properties": {
    "addr:full":"1317 4th Ave S Birmingham AL 35233",
    "addr:housenumber":"1317",
    "addr:postcode":"35233",
    "addr:street":"4Th Ave S",
    "iso:country":"US",
    "sg:address":"1317 4th Ave S",
    "sg:city":"Birmingham",
    "sg:classifiers":[
        {
            "category":"Health Services",
            "subcategory":"Doctor",
            "type":"Services"
        }
    ],
    "sg:phone":"+1 205 458 5000",
    "sg:postcode":"35233",
    "sg:province":"AL",
    "sg:tags":[
        "physician",
        "surgeon",
        "medical"
    ],
    "wof:name":"Alabama Colon & Rectal Inst PC",
    "wof:placetype":"venue"
},
  "geometry": {"coordinates":[-86.81055600000001,33.504927],"type":"Point"}
}