{
  "type": "Feature",
  "properties": {
    "iso:country":"US",
    "sg:address":"1905 Davis Ave",
    "sg:city":"Anniston",
    "sg:classifiers":[
        {
            "category":"Freight",
            "type":"Transportation"
        }
    ],
    "sg:phone":"+1 256 237 3225",
    "sg:postcode":"36207",
    "sg:province":"AL",
    "sg:tags":[
        "delivery"
    ],
    "wof:name":"Special Delivery",
    "wof:placetype":"venue"
},
  "geometry": {"coordinates":[-85.818986,33.669231],"type":"Point"}
}