{
  "type": "Feature",
  "properties": {
    "iso:country":"US",
    "sg:address":"20730 Co Rd 27",
    "sg:city":"Fairhope",
    "sg:classifiers":[
        {
            "category":"Shopping",
            "subcategory":"Discount & Variety Stores",
            "type":"Retail Goods"
        }
    ],
    "sg:phone":"+1 251 929 2638",
    "sg:postcode":"36532",
    "sg:province":"AL",
    "sg:tags":[
        "merchandise",
        "general"
    ],
    "wof:name":"Cayemart Marine Exchange",
    "wof:placetype":"venue"
},
  "geometry": {"coordinates":[-87.852394,30.525212],"type":"Point"}
}