{
  "type": "Feature",
  "properties": {
    "iso:country":"US",
    "sg:address":"114 N Pontiac Ave",
    "sg:city":"Dothan",
    "sg:classifiers":[
        {
            "category":"Professional",
            "type":"Services"
        }
    ],
    "sg:phone":"+1 334 793 7442",
    "sg:postcode":"36303",
    "sg:province":"AL",
    "wof:name":"Farish Concepts Inc",
    "wof:placetype":"venue"
},
  "geometry": {"coordinates":[-85.414648,31.22873],"type":"Point"}
}