{
  "type": "Feature",
  "properties": {
    "iso:country":"US",
    "sg:address":"234 1st St NW",
    "sg:city":"Hamilton",
    "sg:classifiers":[
        {
            "category":"Professional",
            "subcategory":"Accounting & Tax Preparation",
            "type":"Services"
        }
    ],
    "sg:phone":"+1 205 921 3126",
    "sg:postcode":"35570",
    "sg:province":"AL",
    "sg:tags":[
        "accountant"
    ],
    "wof:name":"Wayne L Riggs PC",
    "wof:placetype":"venue"
},
  "geometry": {"coordinates":[-87.98891399999999,34.144664],"type":"Point"}
}