{
  "type": "Feature",
  "properties": {
    "iso:country":"US",
    "sg:address":"1047 Opelika Rd",
    "sg:city":"Auburn",
    "sg:classifiers":[
        {
            "category":"Retail",
            "subcategory":"Auto Repair",
            "type":"Services"
        }
    ],
    "sg:phone":"+1 334 887 6867",
    "sg:postcode":"36830",
    "sg:province":"AL",
    "sg:tags":[
        "general"
    ],
    "wof:name":"Auburn Automotives",
    "wof:placetype":"venue"
},
  "geometry": {"coordinates":[-85.46337,32.617228],"type":"Point"}
}