{
  "type": "Feature",
  "properties": {
    "iso:country":"US",
    "sg:address":"2511 Triana Blvd SW",
    "sg:city":"Huntsville",
    "sg:classifiers":[
        {
            "category":"Wholesale",
            "subcategory":"Construction Materials",
            "type":"Manufacturing & Wholesale Goods"
        }
    ],
    "sg:phone":"+1 256 534 6400",
    "sg:postcode":"35805",
    "sg:province":"AL",
    "sg:tags":[
        "building",
        "supply"
    ],
    "wof:name":"Huntsville Wholesale Bldg Sup",
    "wof:placetype":"venue"
},
  "geometry": {"coordinates":[-86.609058,34.713731],"type":"Point"}
}