{
  "type": "Feature",
  "properties": {
    "addr:full":"1176 Azalea Rd Mobile AL 36693",
    "addr:housenumber":"1176",
    "addr:postcode":"36693",
    "addr:street":"Azalea Rd",
    "iso:country":"US",
    "sg:address":"1176 Azalea Rd",
    "sg:city":"Mobile",
    "sg:classifiers":[
        {
            "category":"Education",
            "subcategory":"School",
            "type":"Public Place"
        }
    ],
    "sg:phone":"+1 251 666 0047",
    "sg:postcode":"36693",
    "sg:province":"AL",
    "sg:tags":[
        "elementary"
    ],
    "wof:name":"Kate Shepard Elementary School",
    "wof:placetype":"venue"
},
  "geometry": {"coordinates":[-88.140079,30.642279],"type":"Point"}
}