{
  "type": "Feature",
  "properties": {
    "iso:country":"US",
    "sg:address":"2504 Brookwater Cir",
    "sg:city":"Birmingham",
    "sg:classifiers":[
        {
            "category":"Professional",
            "subcategory":"Management & Consulting",
            "type":"Services"
        }
    ],
    "sg:phone":"+1 205 967 7954",
    "sg:postcode":"35243",
    "sg:province":"AL",
    "sg:tags":[
        "retail",
        "direct",
        "sales"
    ],
    "wof:name":"Silver Expressions",
    "wof:placetype":"venue"
},
  "geometry": {"coordinates":[-86.766339,33.432811],"type":"Point"}
}