{
  "type": "Feature",
  "properties": {
    "iso:country":"US",
    "sg:address":"400 W 10th St",
    "sg:city":"Anniston",
    "sg:classifiers":[
        {
            "category":"Utilities",
            "subcategory":"Electric",
            "type":"Services"
        }
    ],
    "sg:phone":"+1 256 237 9448",
    "sg:postcode":"36201",
    "sg:province":"AL",
    "sg:tags":[
        "company"
    ],
    "wof:name":"Alabama Power Co",
    "wof:placetype":"venue"
},
  "geometry": {"coordinates":[-85.835136,33.657002],"type":"Point"}
}