{
  "type": "Feature",
  "properties": {
    "iso:country":"US",
    "sg:address":"408 Palisades Blvd",
    "sg:city":"Birmingham",
    "sg:classifiers":[
        {
            "category":"Wholesale",
            "subcategory":"Non-durable Goods",
            "type":"Manufacturing & Wholesale Goods"
        }
    ],
    "sg:phone":"+1 205 824 0330",
    "sg:postcode":"35209",
    "sg:province":"AL",
    "wof:name":"Accounting Resource Group",
    "wof:placetype":"venue"
},
  "geometry": {"coordinates":[-86.81788400000001,33.469883],"type":"Point"}
}