{
  "type": "Feature",
  "properties": {
    "iso:country":"US",
    "sg:address":"1545 Co Rd 330",
    "sg:city":"Crane Hill",
    "sg:classifiers":[
        {
            "category":"Marine",
            "type":"Transportation"
        }
    ],
    "sg:phone":"+1 256 747 3637",
    "sg:postcode":"35053",
    "sg:province":"AL",
    "sg:tags":[
        "water",
        "transport"
    ],
    "wof:name":"Papas Trace",
    "wof:placetype":"venue"
},
  "geometry": {"coordinates":[-87.064195,34.045283],"type":"Point"}
}