{
  "type": "Feature",
  "properties": {
    "iso:country":"US",
    "sg:address":"1309 Industrial Dr SE",
    "sg:city":"Hartselle",
    "sg:classifiers":[
        {
            "category":"Wholesale",
            "subcategory":"Durable Goods & Equipment",
            "type":"Manufacturing & Wholesale Goods"
        }
    ],
    "sg:phone":"+1 256 773 4032",
    "sg:postcode":"35640",
    "sg:province":"AL",
    "sg:tags":[
        "exporter"
    ],
    "wof:name":"Tennessee Valley Trailers",
    "wof:placetype":"venue"
},
  "geometry": {"coordinates":[-86.913701,34.418455],"type":"Point"}
}