{
  "type": "Feature",
  "properties": {
    "iso:country":"US",
    "sg:address":"431 N Pine St",
    "sg:city":"Florence",
    "sg:classifiers":[
        {
            "category":"Retail",
            "subcategory":"Portrait Studio",
            "type":"Services"
        }
    ],
    "sg:phone":"+1 256 766 7544",
    "sg:postcode":"35630",
    "sg:province":"AL",
    "sg:tags":[
        "photo"
    ],
    "wof:name":"Pool Studio",
    "wof:placetype":"venue"
},
  "geometry": {"coordinates":[-87.68052400000001,34.804725],"type":"Point"}
}