{
  "type": "Feature",
  "properties": {
    "iso:country":"US",
    "sg:address":"3401 Greensboro Ave",
    "sg:city":"Tuscaloosa",
    "sg:classifiers":[
        {
            "category":"Freight",
            "type":"Transportation"
        }
    ],
    "sg:phone":"+1 205 758 5033",
    "sg:postcode":"35401",
    "sg:province":"AL",
    "sg:tags":[
        "general"
    ],
    "wof:name":"Tuacaloosa Warehouse Plaza",
    "wof:placetype":"venue"
},
  "geometry": {"coordinates":[-87.552392,33.180571],"type":"Point"}
}