{
  "type": "Feature",
  "properties": {
    "addr:full":"905 Ridgewood Cir Birmingham AL 35235",
    "addr:housenumber":"905",
    "addr:postcode":"35235",
    "addr:street":"Ridgewood Cir",
    "iso:country":"US",
    "sg:address":"905 Ridgewood Cir",
    "sg:city":"Birmingham",
    "sg:classifiers":[
        {
            "category":"Banks & Credit Unions",
            "subcategory":"Financial Services",
            "type":"Services"
        }
    ],
    "sg:phone":"+1 205 856 0555",
    "sg:postcode":"35235",
    "sg:province":"AL",
    "sg:tags":[
        "broker",
        "mortgage"
    ],
    "wof:name":"Alan and Associates",
    "wof:placetype":"venue"
},
  "geometry": {"coordinates":[-86.685219,33.603331],"type":"Point"}
}