{
  "type": "Feature",
  "properties": {
    "iso:country":"US",
    "sg:address":"1 Croydon Rd",
    "sg:city":"Mobile",
    "sg:classifiers":[
        {
            "category":"Social Services",
            "subcategory":"Child Care",
            "type":"Services"
        }
    ],
    "sg:phone":"+1 251 342 5536",
    "sg:postcode":"36608",
    "sg:province":"AL",
    "sg:tags":[
        "day"
    ],
    "wof:name":"Peake John Day Dr",
    "wof:placetype":"venue"
},
  "geometry": {"coordinates":[-88.14981299999999,30.68529],"type":"Point"}
}