{
  "type": "Feature",
  "properties": {
    "iso:country":"US",
    "sg:address":"9059 Madison Blvd",
    "sg:city":"Madison",
    "sg:classifiers":[
        {
            "category":"Professional",
            "subcategory":"Business Services",
            "type":"Services"
        },
        {
            "category":"Insurance",
            "subcategory":"Insurance Agent",
            "type":"Services"
        }
    ],
    "sg:phone":"+1 256 461 9309",
    "sg:postcode":"35758",
    "sg:province":"AL",
    "wof:name":"Richardson Agency",
    "wof:placetype":"venue"
},
  "geometry": {"coordinates":[-86.75657,34.674621],"type":"Point"}
}