{
  "type": "Feature",
  "properties": {
    "iso:country":"US",
    "sg:address":"570 Bannister Ln",
    "sg:city":"Oxford",
    "sg:classifiers":[
        {
            "category":"Wholesale",
            "subcategory":"Machinery & Supplies",
            "type":"Manufacturing & Wholesale Goods"
        },
        {
            "category":"Shopping",
            "type":"Retail Goods"
        }
    ],
    "sg:phone":"+1 256 831 3929",
    "sg:postcode":"36203",
    "sg:province":"AL",
    "sg:tags":[
        "heavy",
        "farm",
        "tractor",
        "equipment"
    ],
    "wof:name":"Bannister Tractor Co Inc",
    "wof:placetype":"venue"
},
  "geometry": {"coordinates":[-85.809906,33.557334],"type":"Point"}
}