{
  "type": "Feature",
  "properties": {
    "iso:country":"US",
    "sg:address":"242 Parker Rd",
    "sg:city":"Moulton",
    "sg:classifiers":[
        {
            "category":"Government",
            "subcategory":"Jail",
            "type":"Public Place"
        }
    ],
    "sg:phone":"+1 256 974 9291",
    "sg:postcode":"35650",
    "sg:province":"AL",
    "sg:tags":[
        "correctional",
        "institution"
    ],
    "wof:name":"Lawrence County Jail",
    "wof:placetype":"venue"
},
  "geometry": {"coordinates":[-87.28510900000001,34.510898],"type":"Point"}
}