{
  "type": "Feature",
  "properties": {
    "iso:country":"US",
    "sg:address":"2768 Co Rd 1422",
    "sg:city":"Cullman",
    "sg:classifiers":[
        {
            "category":"Farming",
            "subcategory":"Poultry Farm",
            "type":"Manufacturing & Wholesale Goods"
        }
    ],
    "sg:phone":"+1 256 739 1590",
    "sg:postcode":"35058",
    "sg:province":"AL",
    "sg:tags":[
        "hatchery"
    ],
    "wof:name":"Bill Dyer",
    "wof:placetype":"venue"
},
  "geometry": {"coordinates":[-86.791192,34.245683],"type":"Point"}
}