{
  "type": "Feature",
  "properties": {
    "addr:full":"24610 Tarpon Ln Orange Beach AL 36561",
    "addr:housenumber":"24610",
    "addr:postcode":"36561",
    "addr:street":"Tarpon Ln",
    "iso:country":"US",
    "sg:address":"24610 Tarpon Ln",
    "sg:city":"Orange Beach",
    "sg:classifiers":[
        {
            "category":"Recreation",
            "type":"Entertainment"
        }
    ],
    "sg:phone":"+1 251 929 0580",
    "sg:postcode":"36561",
    "sg:province":"AL",
    "sg:tags":[
        "guide"
    ],
    "wof:name":"Team Intruder Charters",
    "wof:placetype":"venue"
},
  "geometry": {"coordinates":[-87.60874099999999,30.283495],"type":"Point"}
}