{
  "type": "Feature",
  "properties": {
    "iso:country":"US",
    "sg:address":"727 N Memorial Dr",
    "sg:city":"Prattville",
    "sg:classifiers":[
        {
            "category":"Organizations",
            "subcategory":"Religious Organization",
            "type":"Services"
        }
    ],
    "sg:phone":"+1 334 365 3168",
    "sg:postcode":"36067",
    "sg:province":"AL",
    "wof:name":"First Chrisitan Church Inc",
    "wof:placetype":"venue"
},
  "geometry": {"coordinates":[-86.451892,32.480913],"type":"Point"}
}