{
  "type": "Feature",
  "properties": {
    "addr:full":"2086 Montgomery Hwy Dothan AL 36303",
    "addr:housenumber":"2086",
    "addr:postcode":"36303",
    "addr:street":"Montgomery Hwy",
    "iso:country":"US",
    "sg:address":"2086 Montgomery Hwy",
    "sg:city":"Dothan",
    "sg:classifiers":[
        {
            "category":"Recreation",
            "type":"Entertainment"
        }
    ],
    "sg:phone":"+1 334 793 9644",
    "sg:postcode":"36303",
    "sg:province":"AL",
    "sg:tags":[
        "parlor",
        "billiard"
    ],
    "wof:name":"Pockets Lounge Grill & Bllrds",
    "wof:placetype":"venue"
},
  "geometry": {"coordinates":[-85.409217,31.239172],"type":"Point"}
}