{
  "type": "Feature",
  "properties": {
    "addr:full":"2700 University Blvd Birmingham AL 35233",
    "addr:housenumber":"2700",
    "addr:postcode":"35233",
    "addr:street":"University Blvd",
    "iso:country":"US",
    "sg:address":"2700 University Blvd",
    "sg:city":"Birmingham",
    "sg:classifiers":[
        {
            "category":"Autos & Motor Vehicles",
            "subcategory":"Fuel & Gas Station",
            "type":"Retail Goods"
        }
    ],
    "sg:phone":"+1 205 322 0895",
    "sg:postcode":"35233",
    "sg:province":"AL",
    "sg:tags":[
        "oil"
    ],
    "wof:name":"Glenn Houser Texaco Svc",
    "wof:placetype":"venue"
},
  "geometry": {"coordinates":[-86.788979,33.509634],"type":"Point"}
}