{
  "type": "Feature",
  "properties": {
    "iso:country":"US",
    "sg:address":"4801 Mill Springs Cir",
    "sg:city":"Birmingham",
    "sg:classifiers":[
        {
            "category":"Health Services",
            "subcategory":"Doctor",
            "type":"Services"
        }
    ],
    "sg:phone":"+1 205 502 6817",
    "sg:postcode":"35223",
    "sg:province":"AL",
    "sg:tags":[
        "medical"
    ],
    "wof:name":"Southern Perioperative Svcs PC",
    "wof:placetype":"venue"
},
  "geometry": {"coordinates":[-86.706176,33.50832],"type":"Point"}
}