{
  "type": "Feature",
  "properties": {
    "iso:country":"US",
    "sg:address":"3057 Lorna Rd",
    "sg:city":"Birmingham",
    "sg:classifiers":[
        {
            "category":"Banks & Credit Unions",
            "subcategory":"Investment Brokerage",
            "type":"Services"
        }
    ],
    "sg:phone":"+1 205 879 7370",
    "sg:postcode":"35216",
    "sg:province":"AL",
    "sg:tags":[
        "security"
    ],
    "wof:name":"Flanders Financial",
    "wof:placetype":"venue"
},
  "geometry": {"coordinates":[-86.804996,33.406481],"type":"Point"}
}