{
  "type": "Feature",
  "properties": {
    "addr:full":"2421 Center Point Pkwy Birmingham AL 35215",
    "addr:housenumber":"2421",
    "addr:postcode":"35215",
    "addr:street":"Center Point Pkwy",
    "iso:country":"US",
    "sg:address":"2421 Center Point Pkwy",
    "sg:city":"Birmingham",
    "sg:classifiers":[
        {
            "category":"Banks & Credit Unions",
            "subcategory":"Bank",
            "type":"Services"
        }
    ],
    "sg:phone":"+1 205 854 5075",
    "sg:postcode":"35215",
    "sg:province":"AL",
    "sg:tags":[
        "cashing",
        "check"
    ],
    "wof:name":"Check Depot",
    "wof:placetype":"venue"
},
  "geometry": {"coordinates":[-86.683059,33.650753],"type":"Point"}
}