{
  "type": "Feature",
  "properties": {
    "iso:country":"US",
    "sg:address":"2089 Florence Blvd",
    "sg:city":"Florence",
    "sg:classifiers":[
        {
            "category":"Utilities",
            "subcategory":"Mobile Phone",
            "type":"Services"
        }
    ],
    "sg:phone":"+1 256 764 9500",
    "sg:postcode":"35630",
    "sg:province":"AL",
    "sg:tags":[
        "communication",
        "radiotelephone"
    ],
    "wof:name":"GTE",
    "wof:placetype":"venue"
},
  "geometry": {"coordinates":[-87.646079,34.824497],"type":"Point"}
}