{
  "type": "Feature",
  "properties": {
    "iso:country":"US",
    "sg:address":"420 Ave A SE",
    "sg:city":"Lafayette",
    "sg:classifiers":[
        {
            "category":"Building & Trades",
            "subcategory":"Construction",
            "type":"Services"
        }
    ],
    "sg:phone":"+1 334 864 8243",
    "sg:postcode":"36862",
    "sg:province":"AL",
    "sg:tags":[
        "contractor"
    ],
    "wof:name":"Hodge Drywall",
    "wof:placetype":"venue"
},
  "geometry": {"coordinates":[-85.393587,32.89736],"type":"Point"}
}