{
  "type": "Feature",
  "properties": {
    "iso:country":"US",
    "sg:address":"6607 Valley Lake Dr",
    "sg:city":"Gadsden",
    "sg:classifiers":[
        {
            "category":"Bus Charters",
            "type":"Transportation"
        }
    ],
    "sg:phone":"+1 256 442 0462",
    "sg:postcode":"35907",
    "sg:province":"AL",
    "sg:tags":[
        "rental"
    ],
    "wof:name":"B & D Coach Charters",
    "wof:placetype":"venue"
},
  "geometry": {"coordinates":[-86.047092,33.858266],"type":"Point"}
}