{
  "type": "Feature",
  "properties": {
    "addr:full":"101 N 29th St Gadsden AL 35904",
    "addr:housenumber":"101",
    "addr:postcode":"35904",
    "addr:street":"N 29Th St",
    "iso:country":"US",
    "sg:address":"101 N 29th St",
    "sg:city":"Gadsden",
    "sg:classifiers":[
        {
            "category":"Organizations",
            "subcategory":"Religious Organization",
            "type":"Services"
        }
    ],
    "sg:phone":"+1 256 546 5968",
    "sg:postcode":"35904",
    "sg:province":"AL",
    "sg:tags":[
        "church"
    ],
    "wof:name":"First Baptist Church Ala Cy",
    "wof:placetype":"venue"
},
  "geometry": {"coordinates":[-86.049009,34.019732],"type":"Point"}
}