{
  "type": "Feature",
  "properties": {
    "iso:country":"US",
    "sg:address":"630 E Broad St",
    "sg:city":"Eufaula",
    "sg:classifiers":[
        {
            "category":"Real Estate",
            "subcategory":"Real Estate Agent",
            "type":"Services"
        }
    ],
    "sg:phone":"+1 334 688 1000",
    "sg:postcode":"36027",
    "sg:province":"AL",
    "wof:name":"Crow Realty",
    "wof:placetype":"venue"
},
  "geometry": {"coordinates":[-85.136831,31.893096],"type":"Point"}
}