{
  "type": "Feature",
  "properties": {
    "iso:country":"US",
    "sg:address":"1011 E 2nd St",
    "sg:city":"Sheffield",
    "sg:classifiers":[
        {
            "category":"Building & Trades",
            "subcategory":"Plumbing",
            "type":"Services"
        }
    ],
    "sg:phone":"+1 256 383 1345",
    "sg:postcode":"35660",
    "sg:province":"AL",
    "sg:tags":[
        "heat",
        "pump"
    ],
    "wof:name":"Comfort Zone Heating &Air Cond",
    "wof:placetype":"venue"
},
  "geometry": {"coordinates":[-87.682847,34.759668],"type":"Point"}
}