{
  "type": "Feature",
  "properties": {
    "iso:country":"US",
    "sg:address":"110 Indian Forest Trl",
    "sg:city":"Pelham",
    "sg:classifiers":[
        {
            "category":"Health Services",
            "subcategory":"Clinic",
            "type":"Services"
        }
    ],
    "sg:phone":"+1 205 991 8422",
    "sg:postcode":"35124",
    "sg:province":"AL",
    "wof:name":"Southern Family Health LL",
    "wof:placetype":"venue"
},
  "geometry": {"coordinates":[-86.735919,33.372594],"type":"Point"}
}