{
  "type": "Feature",
  "properties": {
    "iso:country":"US",
    "sg:address":"3415 Broad St",
    "sg:city":"Phil Campbell",
    "sg:classifiers":[
        {
            "category":"Cinema",
            "subcategory":"Movie Rental",
            "type":"Entertainment"
        }
    ],
    "sg:phone":"+1 205 993 5343",
    "sg:postcode":"35581",
    "sg:province":"AL",
    "sg:tags":[
        "leasing",
        "video",
        "disc",
        "tape"
    ],
    "wof:name":"Video Adventure",
    "wof:placetype":"venue"
},
  "geometry": {"coordinates":[-87.701358,34.344995],"type":"Point"}
}