{
  "type": "Feature",
  "properties": {
    "addr:full":"195 Wayne Dr Tuscumbia AL 35674",
    "addr:housenumber":"195",
    "addr:postcode":"35674",
    "addr:street":"Wayne Dr Tuscumbia",
    "iso:country":"US",
    "sg:address":"195 Wayne Dr",
    "sg:city":"Tuscumbia",
    "sg:classifiers":[
        {
            "category":"Shopping",
            "subcategory":"Discount & Variety Stores",
            "type":"Retail Goods"
        }
    ],
    "sg:phone":"+1 256 383 2776",
    "sg:postcode":"35674",
    "sg:province":"AL",
    "sg:tags":[
        "house",
        "general",
        "merchandise",
        "mail"
    ],
    "wof:name":"Karen Handley",
    "wof:placetype":"venue"
},
  "geometry": {"coordinates":[-87.66861299999999,34.631225],"type":"Point"}
}