{
  "type": "Feature",
  "properties": {
    "iso:country":"US",
    "sg:address":"195 Wayne Dr",
    "sg:city":"Tuscumbia",
    "sg:classifiers":[
        {
            "category":"Shopping",
            "subcategory":"Discount & Variety Stores",
            "type":"Retail Goods"
        }
    ],
    "sg:phone":"+1 256 383 2776",
    "sg:postcode":"35674",
    "sg:province":"AL",
    "sg:tags":[
        "house",
        "general",
        "merchandise",
        "mail"
    ],
    "wof:name":"Karen Handley",
    "wof:placetype":"venue"
},
  "geometry": {"coordinates":[-87.668613,34.631225],"type":"Point"}
}