{
  "type": "Feature",
  "properties": {
    "iso:country":"US",
    "sg:address":"3705 Eastern Blvd",
    "sg:city":"Montgomery",
    "sg:classifiers":[
        {
            "category":"Shopping",
            "subcategory":"Hobbies, Toys, & Games",
            "type":"Retail Goods"
        }
    ],
    "sg:phone":"+1 334 396 3778",
    "sg:postcode":"36116",
    "sg:province":"AL",
    "sg:tags":[
        "arts",
        "craft",
        "specialty",
        "store"
    ],
    "wof:name":"Michaels 9980",
    "wof:placetype":"venue"
},
  "geometry": {"coordinates":[-86.234375,32.328542],"type":"Point"}
}