{
  "type": "Feature",
  "properties": {
    "addr:full":"2255 Highland Ave S Birmingham AL 35205",
    "addr:housenumber":"2255",
    "addr:postcode":"35205",
    "addr:street":"Highland Ave S",
    "iso:country":"US",
    "sg:address":"2255 Highland Ave S",
    "sg:city":"Birmingham",
    "sg:classifiers":[
        {
            "category":"Restaurant",
            "type":"Food & Drink"
        }
    ],
    "sg:phone":"+1 205 933 0600",
    "sg:postcode":"35205",
    "sg:province":"AL",
    "sg:tags":[
        "shop",
        "coffee"
    ],
    "sg:website":"www.highlandcoffeecompany.com",
    "wof:name":"Highland Coffee Catering",
    "wof:placetype":"venue"
},
  "geometry": {"coordinates":[-86.78899199999999,33.502937],"type":"Point"}
}