{
  "type": "Feature",
  "properties": {
    "addr:full":"227 1st Ave E Oneonta AL 35121",
    "addr:housenumber":"227",
    "addr:postcode":"35121",
    "addr:street":"1St Ave E",
    "iso:country":"US",
    "sg:address":"227 1st Ave E",
    "sg:city":"Oneonta",
    "sg:classifiers":[
        {
            "category":"Shopping",
            "subcategory":"Books",
            "type":"Retail Goods"
        }
    ],
    "sg:phone":"+1 205 274 4640",
    "sg:postcode":"35121",
    "sg:province":"AL",
    "sg:tags":[
        "dealer"
    ],
    "wof:name":"Tammy's Book Nook",
    "wof:placetype":"venue"
},
  "geometry": {"coordinates":[-86.47497300000001,33.945475],"type":"Point"}
}