{
  "type": "Feature",
  "properties": {
    "iso:country":"US",
    "sg:address":"701 17th St",
    "sg:city":"Tuscaloosa",
    "sg:classifiers":[
        {
            "category":"Social Services",
            "type":"Services"
        }
    ],
    "sg:phone":"+1 205 752 6371",
    "sg:postcode":"35401",
    "sg:province":"AL",
    "sg:tags":[
        "organization",
        "welfare"
    ],
    "wof:name":"Partnership For A Drug Free",
    "wof:placetype":"venue"
},
  "geometry": {"coordinates":[-87.547724,33.196722],"type":"Point"}
}