{
  "type": "Feature",
  "properties": {
    "iso:country":"US",
    "sg:address":"408 2nd Ave E",
    "sg:city":"Oneonta",
    "sg:classifiers":[
        {
            "category":"Insurance",
            "subcategory":"Insurance Agent",
            "type":"Services"
        }
    ],
    "sg:phone":"+1 205 625 4962",
    "sg:postcode":"35121",
    "sg:province":"AL",
    "wof:name":"Blount Insurance Inc",
    "wof:placetype":"venue"
},
  "geometry": {"coordinates":[-86.472812,33.948032],"type":"Point"}
}