{
  "type": "Feature",
  "properties": {
    "iso:country":"US",
    "sg:address":"410 E Broad St",
    "sg:city":"Eufaula",
    "sg:classifiers":[
        {
            "category":"Wholesale",
            "subcategory":"Farm Supplies",
            "type":"Manufacturing & Wholesale Goods"
        }
    ],
    "sg:phone":"+1 334 687 6566",
    "sg:postcode":"36027",
    "sg:province":"AL",
    "wof:name":"Rainbow Farm Ctr",
    "wof:placetype":"venue"
},
  "geometry": {"coordinates":[-85.139735,31.89321],"type":"Point"}
}