{
  "type": "Feature",
  "properties": {
    "iso:country":"US",
    "sg:address":"2314 University Blvd",
    "sg:city":"Tuscaloosa",
    "sg:classifiers":[
        {
            "category":"Shopping",
            "subcategory":"Used Merchandise",
            "type":"Retail Goods"
        }
    ],
    "sg:phone":"+1 205 349 3310",
    "sg:postcode":"35401",
    "sg:province":"AL",
    "sg:tags":[
        "antique",
        "accessory"
    ],
    "wof:name":"Penage Inc",
    "wof:placetype":"venue"
},
  "geometry": {"coordinates":[-87.568163,33.210032],"type":"Point"}
}