{
  "type": "Feature",
  "properties": {
    "iso:country":"US",
    "sg:address":"517 Woodvale Rd",
    "sg:city":"Prattville",
    "sg:classifiers":[
        {
            "category":"Professional",
            "type":"Services"
        }
    ],
    "sg:phone":"+1 334 365 0936",
    "sg:postcode":"36067",
    "sg:province":"AL",
    "wof:name":"Clifton Gibbons",
    "wof:placetype":"venue"
},
  "geometry": {"coordinates":[-86.455184,32.474104],"type":"Point"}
}