{
  "type": "Feature",
  "properties": {
    "iso:country":"US",
    "sg:address":"3728 Pleasant Hill Rd",
    "sg:city":"Wetumpka",
    "sg:classifiers":[
        {
            "category":"Manufacturing",
            "subcategory":"Tools & Machinery",
            "type":"Manufacturing & Wholesale Goods"
        }
    ],
    "sg:phone":"+1 334 541 3982",
    "sg:postcode":"36092",
    "sg:province":"AL",
    "sg:tags":[
        "industrial",
        "mfg"
    ],
    "wof:name":"Lazenby Machine Works",
    "wof:placetype":"venue"
},
  "geometry": {"coordinates":[-86.073509,32.628049],"type":"Point"}
}