{
  "type": "Feature",
  "properties": {
    "iso:country":"US",
    "sg:address":"100 Essex Ct",
    "sg:city":"Madison",
    "sg:classifiers":[
        {
            "category":"Social Services",
            "type":"Services"
        }
    ],
    "sg:phone":"+1 256 464 9755",
    "sg:postcode":"35758",
    "sg:province":"AL",
    "sg:tags":[
        "counselor",
        "marriage",
        "family"
    ],
    "wof:name":"Pellant Psychotherapy",
    "wof:placetype":"venue"
},
  "geometry": {"coordinates":[-86.754008,34.679781],"type":"Point"}
}