{
  "type": "Feature",
  "properties": {
    "iso:country":"US",
    "sg:address":"25067 State Rte 48",
    "sg:city":"Woodland",
    "sg:classifiers":[
        {
            "category":"Food & Beverages",
            "subcategory":"Groceries & Convenience Stores",
            "type":"Retail Goods"
        }
    ],
    "sg:phone":"+1 256 449 2080",
    "sg:postcode":"36280",
    "sg:province":"AL",
    "sg:tags":[
        "gas"
    ],
    "wof:name":"K & L One Stop/Citgo",
    "wof:placetype":"venue"
},
  "geometry": {"coordinates":[-85.390806,33.378785],"type":"Point"}
}