{
  "type": "Feature",
  "properties": {
    "addr:full":"411 Springdale Rd Attalla AL 35954",
    "addr:housenumber":"411",
    "addr:postcode":"35954",
    "addr:street":"Springdale Rd",
    "iso:country":"US",
    "sg:address":"411 Springdale Rd",
    "sg:city":"Attalla",
    "sg:classifiers":[
        {
            "category":"Freight",
            "type":"Transportation"
        }
    ],
    "sg:phone":"+1 256 538 3698",
    "sg:postcode":"35954",
    "sg:province":"AL",
    "sg:tags":[
        "operator",
        "trucking"
    ],
    "wof:name":"Roger Freeman Transport",
    "wof:placetype":"venue"
},
  "geometry": {"coordinates":[-86.108481,34.104454],"type":"Point"}
}