{
  "type": "Feature",
  "properties": {
    "iso:country":"US",
    "sg:address":"25 Bryant Rd",
    "sg:city":"Boaz",
    "sg:classifiers":[
        {
            "category":"Building & Trades",
            "subcategory":"Plumbing",
            "type":"Services"
        }
    ],
    "sg:phone":"+1 256 593 8462",
    "sg:postcode":"35956",
    "sg:province":"AL",
    "sg:tags":[
        "plumbing",
        "electrical",
        "contractor"
    ],
    "wof:name":"Creative Designs",
    "wof:placetype":"venue"
},
  "geometry": {"coordinates":[-86.115035,34.166733],"type":"Point"}
}