{
  "type": "Feature",
  "properties": {
    "iso:country":"US",
    "sg:address":"301 Markate Ave",
    "sg:city":"Muscle Shoals",
    "sg:classifiers":[
        {
            "category":"Shopping",
            "type":"Retail Goods"
        }
    ],
    "sg:phone":"+1 256 389 8111",
    "sg:postcode":"35661",
    "sg:province":"AL",
    "sg:tags":[
        "art",
        "gallery",
        "dealer"
    ],
    "wof:name":"Reflections In Art",
    "wof:placetype":"venue"
},
  "geometry": {"coordinates":[-87.616788,34.779652],"type":"Point"}
}