{
  "type": "Feature",
  "properties": {
    "addr:full":"113 S Main St Enterprise AL 36330",
    "addr:housenumber":"113",
    "addr:postcode":"36330",
    "addr:street":"S Main St",
    "iso:country":"US",
    "sg:address":"113 S Main St",
    "sg:city":"Enterprise",
    "sg:classifiers":[
        {
            "category":"Retail",
            "subcategory":"Repair Shop",
            "type":"Services"
        }
    ],
    "sg:phone":"+1 334 347 5625",
    "sg:postcode":"36330",
    "sg:province":"AL",
    "sg:tags":[
        "lock",
        "locksmith"
    ],
    "wof:name":"Enterprise Precision",
    "wof:placetype":"venue"
},
  "geometry": {"coordinates":[-85.85115999999999,31.31112],"type":"Point"}
}