{
  "type": "Feature",
  "properties": {
    "iso:country":"US",
    "sg:address":"28 Saraland Blvd N",
    "sg:city":"Saraland",
    "sg:classifiers":[
        {
            "category":"Restaurant",
            "type":"Food & Drink"
        }
    ],
    "sg:phone":"+1 251 679 4500",
    "sg:postcode":"36571",
    "sg:province":"AL",
    "wof:name":"Butch's Restaurant",
    "wof:placetype":"venue"
},
  "geometry": {"coordinates":[-88.06997800000001,30.822325],"type":"Point"}
}