{
  "type": "Feature",
  "properties": {
    "addr:full":"941 Mason Ave SW Birmingham AL 35211",
    "addr:housenumber":"941",
    "addr:postcode":"35211",
    "addr:street":"Mason Ave Sw",
    "iso:country":"US",
    "sg:address":"941 Mason Ave SW",
    "sg:city":"Birmingham",
    "sg:classifiers":[
        {
            "category":"Organizations",
            "subcategory":"Religious Organization",
            "type":"Services"
        }
    ],
    "sg:phone":"+1 205 323 5721",
    "sg:postcode":"35211",
    "sg:province":"AL",
    "wof:name":"First Baptist Church",
    "wof:placetype":"venue"
},
  "geometry": {"coordinates":[-86.843896,33.476928],"type":"Point"}
}