{
  "type": "Feature",
  "properties": {
    "iso:country":"US",
    "sg:address":"2612 Drennen Pl",
    "sg:city":"Birmingham",
    "sg:classifiers":[
        {
            "category":"Professional",
            "subcategory":"Management & Consulting",
            "type":"Services"
        }
    ],
    "sg:phone":"+1 205 991 4468",
    "sg:postcode":"35242",
    "sg:province":"AL",
    "wof:name":"Royal Waffle King",
    "wof:placetype":"venue"
},
  "geometry": {"coordinates":[-86.713764,33.396015],"type":"Point"}
}