{
  "type": "Feature",
  "properties": {
    "iso:country":"US",
    "sg:address":"593 Tram Rd",
    "sg:city":"Marbury",
    "sg:classifiers":[
        {
            "category":"Manufacturing",
            "subcategory":"Furniture",
            "type":"Manufacturing & Wholesale Goods"
        }
    ],
    "sg:phone":"+1 334 569 1255",
    "sg:postcode":"36051",
    "sg:province":"AL",
    "sg:tags":[
        "mfg",
        "cabinet"
    ],
    "wof:name":"B & J Cabinets",
    "wof:placetype":"venue"
},
  "geometry": {"coordinates":[-86.403673,32.709789],"type":"Point"}
}