{
  "type": "Feature",
  "properties": {
    "addr:full":"6181 Rock Point Rd Mobile AL 36605",
    "addr:housenumber":"6181",
    "addr:postcode":"36605",
    "addr:street":"Rock Point Rd",
    "iso:country":"US",
    "sg:address":"6181 Rock Point Rd",
    "sg:city":"Mobile",
    "sg:classifiers":[
        {
            "category":"Retail",
            "subcategory":"Auto Repair",
            "type":"Services"
        }
    ],
    "sg:phone":"+1 251 408 0883",
    "sg:postcode":"36605",
    "sg:province":"AL",
    "sg:tags":[
        "repairing",
        "automobile"
    ],
    "wof:name":"Boxer Auto Repair & Towing",
    "wof:placetype":"venue"
},
  "geometry": {"coordinates":[-88.094039,30.563701],"type":"Point"}
}