{
  "type": "Feature",
  "properties": {
    "iso:country":"US",
    "sg:address":"16230 US Hwy 280",
    "sg:city":"Smiths",
    "sg:classifiers":[
        {
            "category":"Building & Trades",
            "subcategory":"Equipment Rental",
            "type":"Services"
        }
    ],
    "sg:phone":"+1 334 448 4022",
    "sg:postcode":"36877",
    "sg:province":"AL",
    "sg:tags":[
        "grocery"
    ],
    "wof:name":"Delta 5 Coastal 23144",
    "wof:placetype":"venue"
},
  "geometry": {"coordinates":[-85.12555,32.562955],"type":"Point"}
}