{
  "type": "Feature",
  "properties": {
    "iso:country":"US",
    "sg:address":"363 E Glenn Ave",
    "sg:city":"Auburn",
    "sg:classifiers":[
        {
            "category":"Real Estate",
            "subcategory":"Real Estate Services",
            "type":"Services"
        }
    ],
    "sg:phone":"+1 334 826 8613",
    "sg:postcode":"36830",
    "sg:province":"AL",
    "sg:tags":[
        "company",
        "title"
    ],
    "wof:name":"Covenant Land & Title LLC",
    "wof:placetype":"venue"
},
  "geometry": {"coordinates":[-85.47597500000001,32.609135],"type":"Point"}
}