{
  "type": "Feature",
  "properties": {
    "iso:country":"US",
    "sg:address":"4651 Birmingham Hwy",
    "sg:city":"Opelika",
    "sg:classifiers":[
        {
            "category":"Restaurant",
            "type":"Food & Drink"
        }
    ],
    "sg:phone":"+1 334 737 1415",
    "sg:postcode":"36801",
    "sg:province":"AL",
    "sg:tags":[
        "eating"
    ],
    "wof:name":"Fred's Barbecue",
    "wof:placetype":"venue"
},
  "geometry": {"coordinates":[-85.427656,32.645183],"type":"Point"}
}