{
  "type": "Feature",
  "properties": {
    "iso:country":"US",
    "sg:address":"208 Main Ave SW",
    "sg:city":"Cullman",
    "sg:classifiers":[
        {
            "category":"Retail",
            "subcategory":"Repair Shop",
            "type":"Services"
        },
        {
            "category":"Wholesale",
            "subcategory":"Auto Parts",
            "type":"Manufacturing & Wholesale Goods"
        }
    ],
    "sg:phone":"+1 256 734 5679",
    "sg:postcode":"35055",
    "sg:province":"AL",
    "sg:tags":[
        "engine",
        "chainsaw"
    ],
    "wof:name":"Randy's Small Engine Parts",
    "wof:placetype":"venue"
},
  "geometry": {"coordinates":[-86.848067,34.170381],"type":"Point"}
}