{
  "type": "Feature",
  "properties": {
    "iso:country":"US",
    "sg:address":"633 W Collins St",
    "sg:city":"Eclectic",
    "sg:classifiers":[
        {
            "category":"Professional",
            "subcategory":"Printing & Photocopies",
            "type":"Services"
        },
        {
            "category":"Manufacturing",
            "subcategory":"Printing",
            "type":"Manufacturing & Wholesale Goods"
        }
    ],
    "sg:phone":"+1 334 541 3902",
    "sg:postcode":"36024",
    "sg:province":"AL",
    "sg:tags":[
        "photocopying",
        "printer",
        "typesetting"
    ],
    "wof:name":"Source One Printing",
    "wof:placetype":"venue"
},
  "geometry": {"coordinates":[-86.045037,32.636967],"type":"Point"}
}