{
  "type": "Feature",
  "properties": {
    "iso:country":"US",
    "sg:address":"626 Daleville Ave",
    "sg:city":"Daleville",
    "sg:classifiers":[
        {
            "category":"Education",
            "subcategory":"School",
            "type":"Public Place"
        }
    ],
    "sg:phone":"+1 334 598 4463",
    "sg:postcode":"36322",
    "sg:province":"AL",
    "sg:tags":[
        "district"
    ],
    "wof:name":"Daleville City School District",
    "wof:placetype":"venue"
},
  "geometry": {"coordinates":[-85.711303,31.31453],"type":"Point"}
}