{
  "type": "Feature",
  "properties": {
    "iso:country":"US",
    "sg:address":"1001 Ashley Brook Ln",
    "sg:city":"Helena",
    "sg:classifiers":[
        {
            "category":"Health Services",
            "subcategory":"Doctor",
            "type":"Services"
        }
    ],
    "sg:phone":"+1 205 621 3100",
    "sg:postcode":"35080",
    "sg:province":"AL",
    "sg:tags":[
        "dentist"
    ],
    "wof:name":"Helena Family Dentistry",
    "wof:placetype":"venue"
},
  "geometry": {"coordinates":[-86.850741,33.275495],"type":"Point"}
}