{
  "type": "Feature",
  "properties": {
    "addr:full":"1800 Ensley 5 Points W Ave Birmingham AL 35218",
    "addr:housenumber":"1800;5",
    "addr:postcode":"35218",
    "addr:street":"Ensley;W Ave",
    "iso:country":"US",
    "sg:address":"1800 Ensley 5 Points W Ave",
    "sg:city":"Birmingham",
    "sg:classifiers":[
        {
            "category":"Organizations",
            "subcategory":"Religious Organization",
            "type":"Services"
        }
    ],
    "sg:phone":"+1 205 785 9023",
    "sg:postcode":"35218",
    "sg:province":"AL",
    "wof:name":"Trinity AME Zion Church",
    "wof:placetype":"venue"
},
  "geometry": {"coordinates":[-86.885893,33.51092],"type":"Point"}
}