{
  "type": "Feature",
  "properties": {
    "iso:country":"US",
    "sg:address":"307 Clinton Ave W",
    "sg:city":"Huntsville",
    "sg:classifiers":[
        {
            "category":"Professional",
            "subcategory":"Employment Agencies",
            "type":"Services"
        }
    ],
    "sg:phone":"+1 256 533 9610",
    "sg:postcode":"35801",
    "sg:province":"AL",
    "sg:tags":[
        "opportunity"
    ],
    "wof:name":"RWA Assoc",
    "wof:placetype":"venue"
},
  "geometry": {"coordinates":[-86.588909,34.729949],"type":"Point"}
}