{
  "type": "Feature",
  "properties": {
    "iso:country":"US",
    "sg:address":"1840 Cherokee Ave SW",
    "sg:city":"Cullman",
    "sg:classifiers":[
        {
            "category":"Restaurant",
            "type":"Food & Drink"
        }
    ],
    "sg:menulink":"http://www.allmenus.com/al/cullman/159684-arbys/menu/",
    "sg:phone":"+1 256 775 3999",
    "sg:postcode":"35055",
    "sg:province":"AL",
    "sg:tags":[
        "burger",
        "american"
    ],
    "wof:name":"Arby's",
    "wof:placetype":"venue"
},
  "geometry": {"coordinates":[-86.84136100000001,34.153235],"type":"Point"}
}