{
  "type": "Feature",
  "properties": {
    "addr:full":"201 Dyar Dr Boaz AL 35957",
    "addr:housenumber":"201",
    "addr:postcode":"35957",
    "addr:street":"Dyar Dr",
    "iso:country":"US",
    "sg:address":"201 Dyar Dr",
    "sg:city":"Boaz",
    "sg:classifiers":[
        {
            "category":"Banks & Credit Unions",
            "subcategory":"Bank",
            "type":"Services"
        }
    ],
    "sg:phone":"+1 256 840 0200",
    "sg:postcode":"35957",
    "sg:province":"AL",
    "sg:website":"www.southtrust.com",
    "wof:name":"South Trust Bank",
    "wof:placetype":"venue"
},
  "geometry": {"coordinates":[-86.295148,34.135969],"type":"Point"}
}