{
  "type": "Feature",
  "properties": {
    "iso:country":"US",
    "sg:address":"1580 W Main St",
    "sg:city":"Centre",
    "sg:classifiers":[
        {
            "category":"Restaurant",
            "type":"Food & Drink"
        }
    ],
    "sg:menulink":"http://www.allmenus.com/al/centre/101551-huddle-house/menu/",
    "sg:phone":"+1 256 927 8345",
    "sg:postcode":"35960",
    "sg:province":"AL",
    "sg:tags":[
        "american",
        "diner"
    ],
    "wof:name":"Huddle House",
    "wof:placetype":"venue"
},
  "geometry": {"coordinates":[-85.699389,34.156891],"type":"Point"}
}