{
  "type": "Feature",
  "properties": {
    "addr:full":"5880 Bayou Rd Mobile AL 36605",
    "addr:housenumber":"5880",
    "addr:postcode":"36605",
    "addr:street":"Bayou Rd",
    "iso:country":"US",
    "sg:address":"5880 Bayou Rd",
    "sg:city":"Mobile",
    "sg:classifiers":[
        {
            "category":"Building & Trades",
            "subcategory":"Construction",
            "type":"Services"
        }
    ],
    "sg:phone":"+1 251 443 7449",
    "sg:postcode":"36605",
    "sg:province":"AL",
    "sg:tags":[
        "handyman"
    ],
    "wof:name":"Lil' Handymans Adventures LLC",
    "wof:placetype":"venue"
},
  "geometry": {"coordinates":[-88.10142999999999,30.56906],"type":"Point"}
}