{
  "type": "Feature",
  "properties": {
    "addr:full":"200 Elizabeth St Boaz AL 35957",
    "addr:housenumber":"200",
    "addr:postcode":"35957",
    "addr:street":"Elizabeth St",
    "iso:country":"US",
    "sg:address":"200 Elizabeth St",
    "sg:city":"Boaz",
    "sg:classifiers":[
        {
            "category":"Shopping",
            "subcategory":"Department Store",
            "type":"Retail Goods"
        }
    ],
    "sg:phone":"+1 256 840 0203",
    "sg:postcode":"35957",
    "sg:province":"AL",
    "sg:tags":[
        "shop"
    ],
    "wof:name":"Dollar Discount",
    "wof:placetype":"venue"
},
  "geometry": {"coordinates":[-86.15922999999999,34.197953],"type":"Point"}
}