{
  "type": "Feature",
  "properties": {
    "iso:country":"US",
    "sg:address":"741 Oliver Rd",
    "sg:city":"Montgomery",
    "sg:classifiers":[
        {
            "category":"Manufacturing",
            "subcategory":"Printing",
            "type":"Manufacturing & Wholesale Goods"
        }
    ],
    "sg:phone":"+1 334 270 0015",
    "sg:postcode":"36117",
    "sg:province":"AL",
    "sg:tags":[
        "commercial",
        "manifold",
        "mfg"
    ],
    "wof:name":"Southeastern Business Printers",
    "wof:placetype":"venue"
},
  "geometry": {"coordinates":[-86.206808,32.399771],"type":"Point"}
}