{
  "type": "Feature",
  "properties": {
    "iso:country":"US",
    "sg:address":"35410 US Hwy 280",
    "sg:city":"Sylacauga",
    "sg:classifiers":[
        {
            "category":"Personal",
            "subcategory":"Barber",
            "type":"Services"
        }
    ],
    "sg:phone":"+1 256 378 3494",
    "sg:postcode":"35150",
    "sg:province":"AL",
    "wof:name":"Blessed Barber & Stylist",
    "wof:placetype":"venue"
},
  "geometry": {"coordinates":[-86.334902,33.242171],"type":"Point"}
}