{
  "type": "Feature",
  "properties": {
    "addr:full":"1189 Center Point Pkwy Birmingham AL 35215",
    "addr:housenumber":"1189",
    "addr:postcode":"35215",
    "addr:street":"Center Point Pkwy",
    "iso:country":"US",
    "sg:address":"1189 Center Point Pkwy",
    "sg:city":"Birmingham",
    "sg:classifiers":[
        {
            "category":"Restaurant",
            "type":"Food & Drink"
        }
    ],
    "sg:phone":"+1 205 815 3000",
    "sg:postcode":"35215",
    "sg:province":"AL",
    "sg:tags":[
        "eating"
    ],
    "wof:name":"Guthries Restaurant",
    "wof:placetype":"venue"
},
  "geometry": {"coordinates":[-86.68556700000001,33.615305],"type":"Point"}
}