{
  "type": "Feature",
  "properties": {
    "iso:country":"US",
    "sg:address":"1189 Center Point Pkwy",
    "sg:city":"Birmingham",
    "sg:classifiers":[
        {
            "category":"Restaurant",
            "type":"Food & Drink"
        }
    ],
    "sg:phone":"+1 205 815 3000",
    "sg:postcode":"35215",
    "sg:province":"AL",
    "sg:tags":[
        "eating"
    ],
    "wof:name":"Guthries Restaurant",
    "wof:placetype":"venue"
},
  "geometry": {"coordinates":[-86.685567,33.615305],"type":"Point"}
}