{
  "type": "Feature",
  "properties": {
    "iso:country":"US",
    "sg:address":"6267 US Hwy 43",
    "sg:city":"Jackson",
    "sg:classifiers":[
        {
            "category":"Shopping",
            "subcategory":"Used Merchandise",
            "type":"Retail Goods"
        }
    ],
    "sg:phone":"+1 251 246 3389",
    "sg:postcode":"36545",
    "sg:province":"AL",
    "wof:name":"Dacys Antiques Inc",
    "wof:placetype":"venue"
},
  "geometry": {"coordinates":[-87.880396,31.579087],"type":"Point"}
}