{
  "type": "Feature",
  "properties": {
    "iso:country":"US",
    "sg:address":"998 Railroad St NW",
    "sg:city":"Hartselle",
    "sg:classifiers":[
        {
            "category":"Manufacturing",
            "subcategory":"Metals",
            "type":"Manufacturing & Wholesale Goods"
        },
        {
            "category":"Wholesale",
            "subcategory":"Auto Parts",
            "type":"Manufacturing & Wholesale Goods"
        }
    ],
    "sg:phone":"+1 256 754 0034",
    "sg:postcode":"35640",
    "sg:province":"AL",
    "sg:tags":[
        "plate",
        "mfg",
        "work",
        "fabricated",
        "equipment",
        "heat",
        "truck"
    ],
    "wof:name":"Fleet Air Technologies Inc",
    "wof:placetype":"venue"
},
  "geometry": {"coordinates":[-86.938916,34.455964],"type":"Point"}
}