{
  "type": "Feature",
  "properties": {
    "addr:full":"144 W 3rd St Falkville AL 35622",
    "addr:housenumber":"144",
    "addr:postcode":"35622",
    "addr:street":"W 3Rd St",
    "iso:country":"US",
    "sg:address":"144 W 3rd St",
    "sg:city":"Falkville",
    "sg:classifiers":[
        {
            "category":"Real Estate",
            "subcategory":"Real Estate Operator",
            "type":"Services"
        }
    ],
    "sg:phone":"+1 256 784 5441",
    "sg:postcode":"35622",
    "sg:province":"AL",
    "sg:tags":[
        "apartment"
    ],
    "wof:name":"Russell Apartments",
    "wof:placetype":"venue"
},
  "geometry": {"coordinates":[-86.911951,34.368509],"type":"Point"}
}