{
  "type": "Feature",
  "properties": {
    "iso:country":"US",
    "sg:address":"312 Robert Lee Rd",
    "sg:city":"Gadsden",
    "sg:classifiers":[
        {
            "category":"Utilities",
            "subcategory":"Water",
            "type":"Services"
        }
    ],
    "sg:phone":"+1 256 492 1081",
    "sg:postcode":"35903",
    "sg:province":"AL",
    "sg:tags":[
        "company",
        "sewage"
    ],
    "wof:name":"Tillison Bend Water Authority",
    "wof:placetype":"venue"
},
  "geometry": {"coordinates":[-85.94249600000001,34.012111],"type":"Point"}
}