{
  "type": "Feature",
  "properties": {
    "iso:country":"US",
    "sg:address":"362 Boone Ln",
    "sg:city":"Fairhope",
    "sg:classifiers":[
        {
            "category":"Shopping",
            "type":"Retail Goods"
        }
    ],
    "sg:phone":"+1 251 928 1110",
    "sg:postcode":"36532",
    "sg:province":"AL",
    "sg:tags":[
        "merchandise"
    ],
    "wof:name":"Watercolors By Willoweise Galy",
    "wof:placetype":"venue"
},
  "geometry": {"coordinates":[-87.90462,30.515736],"type":"Point"}
}