{
  "type": "Feature",
  "properties": {
    "addr:full":"701 Main St Gardendale AL 35071",
    "addr:housenumber":"701",
    "addr:postcode":"35071",
    "addr:street":"Main St",
    "iso:country":"US",
    "sg:address":"701 Main St",
    "sg:city":"Gardendale",
    "sg:classifiers":[
        {
            "category":"Autos & Motor Vehicles",
            "subcategory":"Auto Supplies",
            "type":"Retail Goods"
        },
        {
            "category":"Retail",
            "subcategory":"Auto Repair",
            "type":"Services"
        }
    ],
    "sg:phone":"+1 205 631 5514",
    "sg:postcode":"35071",
    "sg:province":"AL",
    "sg:tags":[
        "wheel",
        "recap",
        "retread",
        "tire"
    ],
    "wof:name":"Files Discount Tires",
    "wof:placetype":"venue"
},
  "geometry": {"coordinates":[-86.80995900000001,33.640759],"type":"Point"}
}