{
  "type": "Feature",
  "properties": {
    "addr:full":"9967 Brown Rd Bay Minette AL 36507",
    "addr:housenumber":"9967",
    "addr:postcode":"36507",
    "addr:street":"Brown Rd",
    "iso:country":"US",
    "sg:address":"9967 Brown Rd",
    "sg:city":"Bay Minette",
    "sg:classifiers":[
        {
            "category":"Professional",
            "type":"Services"
        }
    ],
    "sg:phone":"+1 251 937 1355",
    "sg:postcode":"36507",
    "sg:province":"AL",
    "wof:name":"American Air",
    "wof:placetype":"venue"
},
  "geometry": {"coordinates":[-87.852301,30.788372],"type":"Point"}
}