{
  "type": "Feature",
  "properties": {
    "iso:country":"US",
    "sg:address":"600 US Hwy 31",
    "sg:city":"Hartselle",
    "sg:classifiers":[
        {
            "category":"Food & Beverages",
            "subcategory":"Groceries & Convenience Stores",
            "type":"Retail Goods"
        }
    ],
    "sg:phone":"+1 256 773 5733",
    "sg:postcode":"35640",
    "sg:province":"AL",
    "wof:name":"Jr's Place",
    "wof:placetype":"venue"
},
  "geometry": {"coordinates":[-86.944616,34.448142],"type":"Point"}
}