{
  "type": "Feature",
  "properties": {
    "iso:country":"US",
    "sg:address":"109 W 6th St",
    "sg:city":"Muscle Shoals",
    "sg:classifiers":[
        {
            "category":"Shopping",
            "subcategory":"Photographic Equipment",
            "type":"Retail Goods"
        }
    ],
    "sg:phone":"+1 256 383 7183",
    "sg:postcode":"35661",
    "sg:province":"AL",
    "sg:tags":[
        "supply"
    ],
    "wof:name":"Gas",
    "wof:placetype":"venue"
},
  "geometry": {"coordinates":[-87.679969,34.730441],"type":"Point"}
}