{
  "type": "Feature",
  "properties": {
    "addr:full":"902 S Memorial Dr Prattville AL 36067",
    "addr:housenumber":"902",
    "addr:postcode":"36067",
    "addr:street":"S Memorial Dr",
    "iso:country":"US",
    "sg:address":"902 S Memorial Dr",
    "sg:city":"Prattville",
    "sg:classifiers":[
        {
            "category":"Health Services",
            "subcategory":"Chiropractor",
            "type":"Services"
        }
    ],
    "sg:phone":"+1 334 361 1200",
    "sg:postcode":"36067",
    "sg:province":"AL",
    "wof:name":"Autauga Spine Ctr",
    "wof:placetype":"venue"
},
  "geometry": {"coordinates":[-86.446628,32.454988],"type":"Point"}
}