{
  "type": "Feature",
  "properties": {
    "iso:country":"US",
    "sg:address":"3117 Highway 31 S",
    "sg:city":"Decatur",
    "sg:classifiers":[
        {
            "category":"Bars & Pubs",
            "type":"Food & Drink"
        },
        {
            "category":"Shopping",
            "subcategory":"Party Supplies",
            "type":"Retail Goods"
        },
        {
            "category":"Sports & Exercise",
            "subcategory":"Bowling",
            "type":"Entertainment"
        }
    ],
    "sg:phone":"+1 256 353 3162",
    "sg:postcode":"35603",
    "sg:province":"AL",
    "sg:tags":[
        "children's",
        "planning"
    ],
    "sg:website":"http://www.amf.com",
    "wof:name":"AMF River City Lanes",
    "wof:placetype":"venue"
},
  "geometry": {"coordinates":[-86.973732,34.550441],"type":"Point"}
}