{
  "type": "Feature",
  "properties": {
    "addr:full":"307 Eberhart Rd SE Fort Payne AL 35967",
    "addr:housenumber":"307",
    "addr:postcode":"35967",
    "addr:street":"Eberhart Rd Se",
    "iso:country":"US",
    "sg:address":"307 Eberhart Rd SE",
    "sg:city":"Fort Payne",
    "sg:classifiers":[
        {
            "category":"Professional",
            "type":"Services"
        }
    ],
    "sg:phone":"+1 256 845 7736",
    "sg:postcode":"35967",
    "sg:province":"AL",
    "wof:name":"Anita Evatt Misc Svc",
    "wof:placetype":"venue"
},
  "geometry": {"coordinates":[-85.696547,34.406947],"type":"Point"}
}