{
  "type": "Feature",
  "properties": {
    "addr:full":"1009 S 4th St Gadsden AL 35901",
    "addr:housenumber":"1009",
    "addr:postcode":"35901",
    "addr:street":"S 4Th St",
    "iso:country":"US",
    "sg:address":"1009 S 4th St",
    "sg:city":"Gadsden",
    "sg:classifiers":[
        {
            "category":"Shopping",
            "subcategory":"Clothing, Apparel, & Fashions",
            "type":"Retail Goods"
        }
    ],
    "sg:phone":"+1 256 546 3621",
    "sg:postcode":"35901",
    "sg:province":"AL",
    "sg:tags":[
        "item",
        "boutique"
    ],
    "wof:name":"Bliss Boutique",
    "wof:placetype":"venue"
},
  "geometry": {"coordinates":[-86.004757,33.997715],"type":"Point"}
}