{
  "type": "Feature",
  "properties": {
    "iso:country":"US",
    "sg:address":"210 E Walnut St",
    "sg:city":"Troy",
    "sg:classifiers":[
        {
            "category":"Manufacturing",
            "subcategory":"Printing",
            "type":"Manufacturing & Wholesale Goods"
        }
    ],
    "sg:phone":"+1 334 566 9700",
    "sg:postcode":"36081",
    "sg:province":"AL",
    "sg:tags":[
        "printer"
    ],
    "wof:name":"Ideal Graphics",
    "wof:placetype":"venue"
},
  "geometry": {"coordinates":[-85.97132499999999,31.808613],"type":"Point"}
}