{
  "type": "Feature",
  "properties": {
    "addr:full":"300 Co Rd 406 Shelby AL 35143",
    "addr:housenumber":"300",
    "addr:postcode":"35143",
    "addr:street":"Co Rd 406",
    "iso:country":"US",
    "sg:address":"300 Co Rd 406",
    "sg:city":"Shelby",
    "sg:classifiers":[
        {
            "category":"Building & Trades",
            "subcategory":"Construction",
            "type":"Services"
        }
    ],
    "sg:phone":"+1 205 669 0921",
    "sg:postcode":"35143",
    "sg:province":"AL",
    "sg:tags":[
        "contractor"
    ],
    "wof:name":"Brothers Tile & Marble",
    "wof:placetype":"venue"
},
  "geometry": {"coordinates":[-86.49482,33.108586],"type":"Point"}
}