{
  "type": "Feature",
  "properties": {
    "iso:country":"US",
    "sg:address":"919 31st St",
    "sg:city":"Tuscaloosa",
    "sg:classifiers":[
        {
            "category":"Wholesale",
            "subcategory":"Groceries",
            "type":"Manufacturing & Wholesale Goods"
        }
    ],
    "sg:phone":"+1 205 758 9787",
    "sg:postcode":"35401",
    "sg:province":"AL",
    "sg:tags":[
        "beverage"
    ],
    "wof:name":"Supreme Beverage Co",
    "wof:placetype":"venue"
},
  "geometry": {"coordinates":[-87.549378,33.182949],"type":"Point"}
}