{
  "type": "Feature",
  "properties": {
    "iso:country":"US",
    "sg:address":"165 Graves Cemetery Rd",
    "sg:city":"Blountsville",
    "sg:classifiers":[
        {
            "category":"Farming",
            "subcategory":"Poultry Farm",
            "type":"Manufacturing & Wholesale Goods"
        }
    ],
    "sg:phone":"+1 205 429 4648",
    "sg:postcode":"35031",
    "sg:province":"AL",
    "sg:tags":[
        "chicken",
        "beef",
        "feedlot",
        "cattle"
    ],
    "wof:name":"Hamrick Farms",
    "wof:placetype":"venue"
},
  "geometry": {"coordinates":[-86.534629,34.073196],"type":"Point"}
}