{
  "type": "Feature",
  "properties": {
    "iso:country":"US",
    "sg:address":"1705 Ashley St",
    "sg:city":"Scottsboro",
    "sg:classifiers":[
        {
            "category":"Manufacturing",
            "subcategory":"Metals",
            "type":"Manufacturing & Wholesale Goods"
        }
    ],
    "sg:phone":"+1 256 574 2755",
    "sg:postcode":"35768",
    "sg:province":"AL",
    "sg:tags":[
        "fabricated",
        "structural"
    ],
    "wof:name":"Tennessee River Steel LLC",
    "wof:placetype":"venue"
},
  "geometry": {"coordinates":[-86.010787,34.680715],"type":"Point"}
}