{
  "type": "Feature",
  "properties": {
    "iso:country":"US",
    "sg:address":"125 Ridgegate Pl",
    "sg:city":"Huntsville",
    "sg:classifiers":[
        {
            "category":"Real Estate",
            "subcategory":"Real Estate Operator",
            "type":"Services"
        }
    ],
    "sg:phone":"+1 256 536 6707",
    "sg:postcode":"35801",
    "sg:province":"AL",
    "sg:tags":[
        "apartment"
    ],
    "sg:website":"www.montesanoapartments.com",
    "wof:name":"Monte Sano Terrace",
    "wof:placetype":"venue"
},
  "geometry": {"coordinates":[-86.55813499999999,34.740688],"type":"Point"}
}