{
  "type": "Feature",
  "properties": {
    "iso:country":"US",
    "sg:address":"3124 Triana Blvd SW",
    "sg:city":"Huntsville",
    "sg:classifiers":[
        {
            "category":"Organizations",
            "subcategory":"Religious Organization",
            "type":"Services"
        }
    ],
    "sg:phone":"+1 256 534 7781",
    "sg:postcode":"35805",
    "sg:province":"AL",
    "sg:tags":[
        "church"
    ],
    "wof:name":"Huntsville Pk Church of Christ",
    "wof:placetype":"venue"
},
  "geometry": {"coordinates":[-86.609415,34.705746],"type":"Point"}
}