{
  "type": "Feature",
  "properties": {
    "addr:full":"18750 Silver Hill Ave Robertsdale AL 36567",
    "addr:housenumber":"18750",
    "addr:postcode":"36567",
    "addr:street":"Silver Hill Ave",
    "iso:country":"US",
    "sg:address":"18750 Silver Hill Ave",
    "sg:city":"Robertsdale",
    "sg:classifiers":[
        {
            "category":"Manufacturing",
            "subcategory":"Food",
            "type":"Manufacturing & Wholesale Goods"
        }
    ],
    "sg:phone":"+1 251 947 5757",
    "sg:postcode":"36567",
    "sg:province":"AL",
    "sg:tags":[
        "ice"
    ],
    "wof:name":"Morgan's Ice",
    "wof:placetype":"venue"
},
  "geometry": {"coordinates":[-87.704404,30.545747],"type":"Point"}
}