{
  "type": "Feature",
  "properties": {
    "iso:country":"US",
    "sg:address":"700 Pelham Rd N",
    "sg:city":"Jacksonville",
    "sg:classifiers":[
        {
            "category":"Restaurant",
            "type":"Food & Drink"
        }
    ],
    "sg:phone":"+1 256 782 8123",
    "sg:postcode":"36265",
    "sg:province":"AL",
    "sg:tags":[
        "eating"
    ],
    "wof:name":"Chick-Fil-A",
    "wof:placetype":"venue"
},
  "geometry": {"coordinates":[-85.76345499999999,33.823854],"type":"Point"}
}