{
  "type": "Feature",
  "properties": {
    "iso:country":"US",
    "sg:address":"2524 Valleydale Rd",
    "sg:city":"Birmingham",
    "sg:classifiers":[
        {
            "category":"Professional",
            "subcategory":"Management & Consulting",
            "type":"Services"
        }
    ],
    "sg:phone":"+1 205 981 2370",
    "sg:postcode":"35244",
    "sg:province":"AL",
    "sg:tags":[
        "painting",
        "administration",
        "contractor"
    ],
    "sg:website":"http://www.sherwin-williams.com/",
    "wof:name":"Sherwin-Williams",
    "wof:placetype":"venue"
},
  "geometry": {"coordinates":[-86.752043,33.376868],"type":"Point"}
}