{
  "type": "Feature",
  "properties": {
    "iso:country":"US",
    "sg:address":"6823 Lexington Oaks Dr",
    "sg:city":"Trussville",
    "sg:classifiers":[
        {
            "category":"Wholesale",
            "subcategory":"Drugs",
            "type":"Manufacturing & Wholesale Goods"
        }
    ],
    "sg:phone":"+1 205 661 0603",
    "sg:postcode":"35173",
    "sg:province":"AL",
    "sg:tags":[
        "pharmaceutical",
        "product"
    ],
    "wof:name":"Atley Pharmaceuticals",
    "wof:placetype":"venue"
},
  "geometry": {"coordinates":[-86.59654399999999,33.593378],"type":"Point"}
}