{
  "type": "Feature",
  "properties": {
    "addr:full":"145 Mandy Cir Wetumpka AL 36093",
    "addr:housenumber":"145",
    "addr:postcode":"36093",
    "addr:street":"Mandy Cir",
    "iso:country":"US",
    "sg:address":"145 Mandy Cir",
    "sg:city":"Wetumpka",
    "sg:classifiers":[
        {
            "category":"Building & Trades",
            "subcategory":"Construction",
            "type":"Services"
        }
    ],
    "sg:phone":"+1 334 514 0964",
    "sg:postcode":"36093",
    "sg:province":"AL",
    "sg:tags":[
        "carpentry"
    ],
    "wof:name":"Cherokee Construction LLC",
    "wof:placetype":"venue"
},
  "geometry": {"coordinates":[-86.16678,32.529592],"type":"Point"}
}