{
  "type": "Feature",
  "properties": {
    "iso:country":"US",
    "sg:address":"133 Nixon Chapel Rd",
    "sg:city":"Albertville",
    "sg:classifiers":[
        {
            "category":"Professional",
            "subcategory":"Business Services",
            "type":"Services"
        }
    ],
    "sg:phone":"+1 256 878 3442",
    "sg:postcode":"35950",
    "sg:province":"AL",
    "sg:tags":[
        "auctioneer"
    ],
    "wof:name":"Holder Bill Auction",
    "wof:placetype":"venue"
},
  "geometry": {"coordinates":[-86.286958,34.266321],"type":"Point"}
}