{
  "type": "Feature",
  "properties": {
    "addr:full":"28210 State Hwy 75 Oneonta AL 35121",
    "addr:housenumber":"28210",
    "addr:postcode":"35121",
    "addr:street":"State Hwy 75",
    "iso:country":"US",
    "sg:address":"28210 State Hwy 75",
    "sg:city":"Oneonta",
    "sg:classifiers":[
        {
            "category":"Retail",
            "subcategory":"Auto Rental",
            "type":"Services"
        }
    ],
    "sg:phone":"+1 205 625 6179",
    "sg:postcode":"35121",
    "sg:province":"AL",
    "sg:tags":[
        "truck"
    ],
    "wof:name":"U-Haul",
    "wof:placetype":"venue"
},
  "geometry": {"coordinates":[-86.486296,33.940373],"type":"Point"}
}