{
  "type": "Feature",
  "properties": {
    "addr:full":"3400 Clairmont Ave S Birmingham AL 35222",
    "addr:housenumber":"3400",
    "addr:postcode":"35222",
    "addr:street":"Clairmont Ave S",
    "iso:country":"US",
    "sg:address":"3400 Clairmont Ave S",
    "sg:city":"Birmingham",
    "sg:classifiers":[
        {
            "category":"Professional",
            "type":"Services"
        }
    ],
    "sg:phone":"+1 205 323 7551",
    "sg:postcode":"35222",
    "sg:province":"AL",
    "wof:name":"Donald E Evans Jr",
    "wof:placetype":"venue"
},
  "geometry": {"coordinates":[-86.776786,33.513981],"type":"Point"}
}