{
  "type": "Feature",
  "properties": {
    "iso:country":"US",
    "sg:address":"105 Liberty Ln",
    "sg:city":"Scottsboro",
    "sg:classifiers":[
        {
            "category":"Restaurant",
            "type":"Food & Drink"
        }
    ],
    "sg:phone":"+1 256 574 4444",
    "sg:postcode":"35769",
    "sg:province":"AL",
    "sg:tags":[
        "delicatessen"
    ],
    "wof:name":"Downtown Deli",
    "wof:placetype":"venue"
},
  "geometry": {"coordinates":[-86.0171,34.659015],"type":"Point"}
}