{
  "type": "Feature",
  "properties": {
    "iso:country":"US",
    "sg:address":"700 Pratt Ave NE",
    "sg:city":"Huntsville",
    "sg:classifiers":[
        {
            "category":"Insurance",
            "subcategory":"Hazard Insurance",
            "type":"Services"
        }
    ],
    "sg:phone":"+1 256 534 1717",
    "sg:postcode":"35801",
    "sg:province":"AL",
    "sg:tags":[
        "bond"
    ],
    "wof:name":"Alpha Bail Bond Co",
    "wof:placetype":"venue"
},
  "geometry": {"coordinates":[-86.575501,34.738755],"type":"Point"}
}