{
  "type": "Feature",
  "properties": {
    "iso:country":"US",
    "sg:address":"2073 Halcyon Blvd",
    "sg:city":"Montgomery",
    "sg:classifiers":[
        {
            "category":"Professional",
            "subcategory":"Engineering",
            "type":"Services"
        }
    ],
    "sg:phone":"+1 334 277 8546",
    "sg:postcode":"36117",
    "sg:province":"AL",
    "wof:name":"Pierce Crtis T Engrg Land Srve",
    "wof:placetype":"venue"
},
  "geometry": {"coordinates":[-86.166043,32.346957],"type":"Point"}
}