{
  "type": "Feature",
  "properties": {
    "iso:country":"US",
    "sg:address":"4304 20th Ave",
    "sg:city":"Valley",
    "sg:classifiers":[
        {
            "category":"Autos & Motor Vehicles",
            "subcategory":"Automobile Sales",
            "type":"Retail Goods"
        }
    ],
    "sg:phone":"+1 334 756 7000",
    "sg:postcode":"36854",
    "sg:province":"AL",
    "sg:tags":[
        "used"
    ],
    "wof:name":"Steves Auto Market",
    "wof:placetype":"venue"
},
  "geometry": {"coordinates":[-85.175274,32.82929],"type":"Point"}
}