{
  "type": "Feature",
  "properties": {
    "addr:full":"1031 Cherry Tree Rd Gurley AL 35748",
    "addr:housenumber":"1031",
    "addr:postcode":"35748",
    "addr:street":"Cherry Tree Rd",
    "iso:country":"US",
    "sg:address":"1031 Cherry Tree Rd",
    "sg:city":"Gurley",
    "sg:classifiers":[
        {
            "category":"Building & Trades",
            "subcategory":"Plumbing",
            "type":"Services"
        }
    ],
    "sg:phone":"+1 256 776 3026",
    "sg:postcode":"35748",
    "sg:province":"AL",
    "sg:tags":[
        "contractor"
    ],
    "wof:name":"Bills Plumbing Co",
    "wof:placetype":"venue"
},
  "geometry": {"coordinates":[-86.40379799999999,34.63783],"type":"Point"}
}