{
  "type": "Feature",
  "properties": {
    "iso:country":"US",
    "sg:address":"8190 Seaton Pl",
    "sg:city":"Montgomery",
    "sg:classifiers":[
        {
            "category":"Health Services",
            "subcategory":"Doctor",
            "type":"Services"
        }
    ],
    "sg:phone":"+1 334 396 9100",
    "sg:postcode":"36116",
    "sg:province":"AL",
    "sg:tags":[
        "medicine",
        "physician",
        "practice",
        "surgeons",
        "family"
    ],
    "wof:name":"Montgomery Family Medicine",
    "wof:placetype":"venue"
},
  "geometry": {"coordinates":[-86.171261,32.337873],"type":"Point"}
}