{
  "type": "Feature",
  "properties": {
    "iso:country":"US",
    "sg:address":"1013 N Jefferson St",
    "sg:city":"Athens",
    "sg:classifiers":[
        {
            "category":"Retail",
            "subcategory":"Repair Shop",
            "type":"Services"
        }
    ],
    "sg:phone":"+1 256 232 4152",
    "sg:postcode":"35611",
    "sg:province":"AL",
    "sg:tags":[
        "appliance"
    ],
    "wof:name":"Mc Cravy Appliance Repair Svc",
    "wof:placetype":"venue"
},
  "geometry": {"coordinates":[-86.97206799999999,34.813947],"type":"Point"}
}