{
  "type": "Feature",
  "properties": {
    "iso:country":"US",
    "sg:address":"520 Inlet Rd",
    "sg:city":"Eufaula",
    "sg:classifiers":[
        {
            "category":"Communications",
            "type":"Services"
        }
    ],
    "sg:phone":"+1 334 616 6334",
    "sg:postcode":"36027",
    "sg:province":"AL",
    "sg:tags":[
        "communication"
    ],
    "wof:name":"Irwinton Communications I",
    "wof:placetype":"venue"
},
  "geometry": {"coordinates":[-85.14267100000001,31.873525],"type":"Point"}
}