{
  "type": "Feature",
  "properties": {
    "iso:country":"US",
    "sg:address":"108 Lenwood Rd SE",
    "sg:city":"Decatur",
    "sg:classifiers":[
        {
            "category":"Retail",
            "subcategory":"Auto Repair",
            "type":"Services"
        }
    ],
    "sg:phone":"+1 256 350 6930",
    "sg:postcode":"35603",
    "sg:province":"AL",
    "sg:tags":[
        "machine",
        "shop",
        "precision"
    ],
    "wof:name":"M-Tech Inc",
    "wof:placetype":"venue"
},
  "geometry": {"coordinates":[-86.982459,34.540872],"type":"Point"}
}