{
  "type": "Feature",
  "properties": {
    "iso:country":"US",
    "sg:address":"1008 37th St E",
    "sg:city":"Tuscaloosa",
    "sg:classifiers":[
        {
            "category":"Building & Trades",
            "subcategory":"Construction",
            "type":"Services"
        }
    ],
    "sg:phone":"+1 205 553 7720",
    "sg:postcode":"35405",
    "sg:province":"AL",
    "sg:tags":[
        "general",
        "contractor"
    ],
    "wof:name":"N C Morgan Construction Co",
    "wof:placetype":"venue"
},
  "geometry": {"coordinates":[-87.52432899999999,33.175366],"type":"Point"}
}