{
  "type": "Feature",
  "properties": {
    "iso:country":"US",
    "sg:address":"21241 Oakland Meadows",
    "sg:city":"Athens",
    "sg:classifiers":[
        {
            "category":"Building & Trades",
            "subcategory":"Construction",
            "type":"Services"
        }
    ],
    "sg:phone":"+1 256 232 4492",
    "sg:postcode":"35613",
    "sg:province":"AL",
    "sg:tags":[
        "concrete",
        "contractor"
    ],
    "wof:name":"Kopps Concrete",
    "wof:placetype":"venue"
},
  "geometry": {"coordinates":[-86.851966,34.867851],"type":"Point"}
}