{
  "type": "Feature",
  "properties": {
    "iso:country":"US",
    "sg:address":"3703 Adair St NW",
    "sg:city":"Huntsville",
    "sg:classifiers":[
        {
            "category":"Building & Trades",
            "subcategory":"Construction",
            "type":"Services"
        }
    ],
    "sg:phone":"+1 256 859 3588",
    "sg:postcode":"35810",
    "sg:province":"AL",
    "sg:tags":[
        "general",
        "contractor"
    ],
    "wof:name":"Gene Mc Nary Construction",
    "wof:placetype":"venue"
},
  "geometry": {"coordinates":[-86.630148,34.775419],"type":"Point"}
}