{
  "type": "Feature",
  "properties": {
    "iso:country":"US",
    "sg:address":"9 Office Park Cir",
    "sg:city":"Birmingham",
    "sg:classifiers":[
        {
            "category":"Professional",
            "subcategory":"Engineering",
            "type":"Services"
        }
    ],
    "sg:phone":"+1 205 879 8601",
    "sg:postcode":"35223",
    "sg:province":"AL",
    "sg:tags":[
        "consulting",
        "engineer"
    ],
    "wof:name":"Ritchie & Montgmry Cnslt Engr",
    "wof:placetype":"venue"
},
  "geometry": {"coordinates":[-86.769523,33.478772],"type":"Point"}
}