{
  "type": "Feature",
  "properties": {
    "iso:country":"US",
    "sg:address":"6 Office Park Cir",
    "sg:city":"Birmingham",
    "sg:classifiers":[
        {
            "category":"Building & Trades",
            "subcategory":"Construction",
            "type":"Services"
        }
    ],
    "sg:phone":"+1 205 414 6051",
    "sg:postcode":"35223",
    "sg:province":"AL",
    "wof:name":"Bennett & Bennett Construction",
    "wof:placetype":"venue"
},
  "geometry": {"coordinates":[-86.76957299999999,33.478915],"type":"Point"}
}