{
  "type": "Feature",
  "properties": {
    "addr:full":"600 20th St N Birmingham AL 35203",
    "addr:housenumber":"600",
    "addr:postcode":"35203",
    "addr:street":"20Th St N",
    "iso:country":"US",
    "sg:address":"600 20th St N",
    "sg:city":"Birmingham",
    "sg:classifiers":[
        {
            "category":"Banks & Credit Unions",
            "subcategory":"Investment Brokerage",
            "type":"Services"
        }
    ],
    "sg:phone":"+1 205 328 3098",
    "sg:postcode":"35203",
    "sg:province":"AL",
    "sg:tags":[
        "advisory",
        "financial"
    ],
    "sg:website":"www.fhlcapital.com",
    "wof:name":"FHL Capital Corp",
    "wof:placetype":"venue"
},
  "geometry": {"coordinates":[-86.809331,33.519914],"type":"Point"}
}