{
  "type": "Feature",
  "properties": {
    "iso:country":"US",
    "sg:address":"102 Item Ave",
    "sg:city":"Mobile",
    "sg:classifiers":[
        {
            "category":"Professional",
            "subcategory":"Credit Reporting & Collection",
            "type":"Services"
        }
    ],
    "sg:phone":"+1 251 470 0907",
    "sg:postcode":"36607",
    "sg:province":"AL",
    "sg:tags":[
        "agency"
    ],
    "wof:name":"Miracle Debt Recovery",
    "wof:placetype":"venue"
},
  "geometry": {"coordinates":[-88.100829,30.694756],"type":"Point"}
}