{
  "type": "Feature",
  "properties": {
    "addr:full":"6920 Airport Blvd Svc Rd Mobile AL 36608",
    "addr:housenumber":"6920",
    "addr:postcode":"36608",
    "addr:street":"Airport Blvd",
    "iso:country":"US",
    "sg:address":"6920 Airport Blvd Svc Rd",
    "sg:city":"Mobile",
    "sg:classifiers":[
        {
            "category":"Shopping",
            "subcategory":"Clothing, Apparel, & Fashions",
            "type":"Retail Goods"
        }
    ],
    "sg:phone":"+1 251 345 3335",
    "sg:postcode":"36608",
    "sg:province":"AL",
    "sg:tags":[
        "alteration"
    ],
    "wof:name":"Seams To Fit",
    "wof:placetype":"venue"
},
  "geometry": {"coordinates":[-88.201793,30.683516],"type":"Point"}
}