{
  "type": "Feature",
  "properties": {
    "iso:country":"US",
    "sg:address":"964 Kelly Lynn Dr",
    "sg:city":"Anniston",
    "sg:classifiers":[
        {
            "category":"Building & Trades",
            "subcategory":"Construction",
            "type":"Services"
        }
    ],
    "sg:phone":"+1 256 236 3388",
    "sg:postcode":"36207",
    "sg:province":"AL",
    "sg:tags":[
        "house"
    ],
    "wof:name":"Helms Terry Construction",
    "wof:placetype":"venue"
},
  "geometry": {"coordinates":[-85.747261,33.639691],"type":"Point"}
}