{
  "type": "Feature",
  "properties": {
    "iso:country":"US",
    "sg:address":"48 Main St",
    "sg:city":"Somerville",
    "sg:classifiers":[
        {
            "category":"Social Services",
            "type":"Services"
        }
    ],
    "sg:phone":"+1 256 778 7643",
    "sg:postcode":"35670",
    "sg:province":"AL",
    "sg:tags":[
        "senior",
        "citizen"
    ],
    "wof:name":"Somerville Nutrition Site",
    "wof:placetype":"venue"
},
  "geometry": {"coordinates":[-86.798163,34.471077],"type":"Point"}
}