{
  "type": "Feature",
  "properties": {
    "iso:country":"US",
    "sg:address":"2026 E 4th St",
    "sg:city":"Montgomery",
    "sg:classifiers":[
        {
            "category":"Organizations",
            "subcategory":"Religious Organization",
            "type":"Services"
        }
    ],
    "sg:phone":"+1 334 269 5726",
    "sg:postcode":"36106",
    "sg:province":"AL",
    "sg:tags":[
        "church"
    ],
    "wof:name":"Forest Park Baptist Church",
    "wof:placetype":"venue"
},
  "geometry": {"coordinates":[-86.28191,32.36199],"type":"Point"}
}