{
  "type": "Feature",
  "properties": {
    "iso:country":"US",
    "sg:address":"3299 Bel Air Mall",
    "sg:city":"Mobile",
    "sg:classifiers":[
        {
            "category":"Shopping",
            "subcategory":"Crafts & Fabrics",
            "type":"Retail Goods"
        }
    ],
    "sg:phone":"+1 251 471 6080",
    "sg:postcode":"36606",
    "sg:province":"AL",
    "sg:tags":[
        "monogram"
    ],
    "wof:name":"Just Darlin",
    "wof:placetype":"venue"
},
  "geometry": {"coordinates":[-88.123287,30.673331],"type":"Point"}
}