{
  "type": "Feature",
  "properties": {
    "iso:country":"US",
    "sg:address":"2107 Shady Brook Ln",
    "sg:city":"Dothan",
    "sg:classifiers":[
        {
            "category":"Professional",
            "type":"Services"
        }
    ],
    "sg:phone":"+1 334 699 2519",
    "sg:postcode":"36303",
    "sg:province":"AL",
    "wof:name":"Todd & Anna Bailey",
    "wof:placetype":"venue"
},
  "geometry": {"coordinates":[-85.41820800000001,31.260508],"type":"Point"}
}