{
  "type": "Feature",
  "properties": {
    "iso:country":"US",
    "sg:address":"201 Co Rd 496",
    "sg:city":"Fort Payne",
    "sg:classifiers":[
        {
            "category":"Bus Charters",
            "type":"Transportation"
        }
    ],
    "sg:phone":"+1 256 492 5775",
    "sg:postcode":"35986",
    "sg:province":"AL",
    "sg:tags":[
        "rental"
    ],
    "wof:name":"Band Busses Inc",
    "wof:placetype":"venue"
},
  "geometry": {"coordinates":[-85.75055,34.498166],"type":"Point"}
}