{
  "type": "Feature",
  "properties": {
    "addr:full":"1518 Manhattan St Birmingham AL 35209",
    "addr:housenumber":"1518",
    "addr:postcode":"35209",
    "addr:street":"Manhattan St",
    "iso:country":"US",
    "sg:address":"1518 Manhattan St",
    "sg:city":"Birmingham",
    "sg:classifiers":[
        {
            "category":"Professional",
            "subcategory":"Business Services",
            "type":"Services"
        }
    ],
    "sg:phone":"+1 205 870 1456",
    "sg:postcode":"35209",
    "sg:province":"AL",
    "wof:name":"R&T Enterprises LLC",
    "wof:placetype":"venue"
},
  "geometry": {"coordinates":[-86.80136,33.476505],"type":"Point"}
}