{
  "type": "Feature",
  "properties": {
    "addr:full":"2000 Park Pl Birmingham AL 35203",
    "addr:housenumber":"2000",
    "addr:postcode":"35203",
    "addr:street":"Park Pl",
    "iso:country":"US",
    "sg:address":"2000 Park Pl",
    "sg:city":"Birmingham",
    "sg:classifiers":[
        {
            "category":"Professional",
            "subcategory":"Lawyer & Legal Services",
            "type":"Services"
        }
    ],
    "sg:phone":"+1 205 322 7707",
    "sg:postcode":"35203",
    "sg:province":"AL",
    "sg:tags":[
        "attorney"
    ],
    "wof:name":"Wooten & Lentine PC",
    "wof:placetype":"venue"
},
  "geometry": {"coordinates":[-86.80941799999999,33.519872],"type":"Point"}
}