{
  "type": "Feature",
  "properties": {
    "addr:full":"2264 Mount Meigs Rd Montgomery AL 36107",
    "addr:housenumber":"2264",
    "addr:postcode":"36107",
    "addr:street":"Mount Meigs Rd",
    "iso:country":"US",
    "sg:address":"2264 Mount Meigs Rd",
    "sg:city":"Montgomery",
    "sg:classifiers":[
        {
            "category":"Building & Trades",
            "subcategory":"Equipment Rental",
            "type":"Services"
        }
    ],
    "sg:phone":"+1 334 834 1241",
    "sg:postcode":"36107",
    "sg:province":"AL",
    "sg:tags":[
        "own",
        "offer",
        "to",
        "rent",
        "which",
        "home",
        "electronics",
        "store"
    ],
    "wof:name":"Rent-A-Center",
    "wof:placetype":"venue"
},
  "geometry": {"coordinates":[-86.275227,32.379738],"type":"Point"}
}