{
  "type": "Feature",
  "properties": {
    "iso:country":"US",
    "sg:address":"1311 Wind River Cir SE",
    "sg:city":"Huntsville",
    "sg:classifiers":[
        {
            "category":"Organizations",
            "subcategory":"Community Association",
            "type":"Services"
        }
    ],
    "sg:phone":"+1 256 881 7667",
    "sg:postcode":"35802",
    "sg:province":"AL",
    "wof:name":"Optimist International",
    "wof:placetype":"venue"
},
  "geometry": {"coordinates":[-86.531861,34.655514],"type":"Point"}
}