{
  "type": "Feature",
  "properties": {
    "iso:country":"US",
    "sg:address":"307 4th St SW",
    "sg:city":"Cullman",
    "sg:classifiers":[
        {
            "category":"Health Services",
            "subcategory":"Medical Lab",
            "type":"Services"
        }
    ],
    "sg:phone":"+1 256 734 3140",
    "sg:postcode":"35055",
    "sg:province":"AL",
    "sg:tags":[
        "laboratory",
        "dental"
    ],
    "wof:name":"Full Service Dental Lab Inc",
    "wof:placetype":"venue"
},
  "geometry": {"coordinates":[-86.844262,34.173421],"type":"Point"}
}