{
  "type": "Feature",
  "properties": {
    "iso:country":"US",
    "sg:address":"14413 Co Rd 23",
    "sg:city":"Vina",
    "sg:classifiers":[
        {
            "category":"Shopping",
            "type":"Retail Goods"
        }
    ],
    "sg:phone":"+1 256 356 2109",
    "sg:postcode":"35593",
    "sg:province":"AL",
    "sg:tags":[
        "monument"
    ],
    "wof:name":"Martin Monuments",
    "wof:placetype":"venue"
},
  "geometry": {"coordinates":[-88.039722,34.451862],"type":"Point"}
}