{
  "type": "Feature",
  "properties": {
    "iso:country":"US",
    "sg:address":"2215 Linde St NW",
    "sg:city":"Huntsville",
    "sg:classifiers":[
        {
            "category":"Organizations",
            "subcategory":"Religious Organization",
            "type":"Services"
        }
    ],
    "sg:phone":"+1 256 852 1175",
    "sg:postcode":"35810",
    "sg:province":"AL",
    "wof:name":"Sparkman Drive Church Christ",
    "wof:placetype":"venue"
},
  "geometry": {"coordinates":[-86.61662200000001,34.754575],"type":"Point"}
}