{
  "type": "Feature",
  "properties": {
    "iso:country":"US",
    "sg:address":"1613 Hillwood Dr",
    "sg:city":"Montgomery",
    "sg:classifiers":[
        {
            "category":"Professional",
            "type":"Services"
        }
    ],
    "sg:phone":"+1 334 272 6441",
    "sg:postcode":"36106",
    "sg:province":"AL",
    "wof:name":"Buford Inc",
    "wof:placetype":"venue"
},
  "geometry": {"coordinates":[-86.254688,32.357307],"type":"Point"}
}