{
  "type": "Feature",
  "properties": {
    "iso:country":"US",
    "sg:address":"8340 US Hwy 43",
    "sg:city":"Guin",
    "sg:classifiers":[
        {
            "category":"Organizations",
            "subcategory":"Religious Organization",
            "type":"Services"
        }
    ],
    "sg:phone":"+1 205 468 3569",
    "sg:postcode":"35563",
    "sg:province":"AL",
    "sg:tags":[
        "clergy"
    ],
    "wof:name":"Thomas L Hammons",
    "wof:placetype":"venue"
},
  "geometry": {"coordinates":[-87.91749299999999,33.980042],"type":"Point"}
}