{
  "type": "Feature",
  "properties": {
    "iso:country":"US",
    "sg:address":"304 S Hambrick St",
    "sg:city":"Albertville",
    "sg:classifiers":[
        {
            "category":"Building & Trades",
            "subcategory":"Electrical",
            "type":"Services"
        }
    ],
    "sg:phone":"+1 256 891 4823",
    "sg:postcode":"35950",
    "sg:province":"AL",
    "sg:tags":[
        "electric",
        "contractor"
    ],
    "wof:name":"Master Electric Svc",
    "wof:placetype":"venue"
},
  "geometry": {"coordinates":[-86.212086,34.266414],"type":"Point"}
}