{
  "type": "Feature",
  "properties": {
    "iso:country":"US",
    "sg:address":"3385 Ross Clark Cir",
    "sg:city":"Dothan",
    "sg:classifiers":[
        {
            "category":"Restaurant",
            "type":"Food & Drink"
        }
    ],
    "sg:menulink":"http://www.allmenus.com/al/dothan/8527-hooters/menu/",
    "sg:phone":"+1 334 673 4668",
    "sg:postcode":"36303",
    "sg:province":"AL",
    "sg:tags":[
        "american",
        "wing"
    ],
    "wof:name":"Hooters",
    "wof:placetype":"venue"
},
  "geometry": {"coordinates":[-85.430874,31.241155],"type":"Point"}
}