{
  "type": "Feature",
  "properties": {
    "addr:full":"337 Valley Crest Dr Birmingham AL 35215",
    "addr:housenumber":"337",
    "addr:postcode":"35215",
    "addr:street":"Valley Crest Dr",
    "iso:country":"US",
    "sg:address":"337 Valley Crest Dr",
    "sg:city":"Birmingham",
    "sg:classifiers":[
        {
            "category":"Building & Trades",
            "subcategory":"Landscaping Services",
            "type":"Services"
        }
    ],
    "sg:phone":"+1 205 856 6232",
    "sg:postcode":"35215",
    "sg:province":"AL",
    "wof:name":"Brians Tree Service",
    "wof:placetype":"venue"
},
  "geometry": {"coordinates":[-86.72266,33.617529],"type":"Point"}
}