{
  "type": "Feature",
  "properties": {
    "iso:country":"US",
    "sg:address":"606 Triana Blvd NW",
    "sg:city":"Huntsville",
    "sg:classifiers":[
        {
            "category":"Wholesale",
            "subcategory":"Scrap",
            "type":"Manufacturing & Wholesale Goods"
        }
    ],
    "sg:phone":"+1 256 539 0770",
    "sg:postcode":"35805",
    "sg:province":"AL",
    "sg:tags":[
        "recycling",
        "center"
    ],
    "sg:website":"www.tvrllc.com",
    "wof:name":"Tennessee Valley Recycling",
    "wof:placetype":"venue"
},
  "geometry": {"coordinates":[-86.60908499999999,34.723514],"type":"Point"}
}