{
  "type": "Feature",
  "properties": {
    "iso:country":"US",
    "sg:address":"219 Lorna Sq",
    "sg:city":"Birmingham",
    "sg:classifiers":[
        {
            "category":"Professional",
            "subcategory":"Business Services",
            "type":"Services"
        }
    ],
    "sg:phone":"+1 205 823 8006",
    "sg:postcode":"35216",
    "sg:province":"AL",
    "wof:name":"Y M L Designs",
    "wof:placetype":"venue"
},
  "geometry": {"coordinates":[-86.803129,33.396635],"type":"Point"}
}