{
  "type": "Feature",
  "properties": {
    "iso:country":"US",
    "sg:address":"1100 Kershaw St",
    "sg:city":"Montgomery",
    "sg:classifiers":[
        {
            "category":"Home & Garden",
            "subcategory":"Building Materials",
            "type":"Retail Goods"
        }
    ],
    "sg:phone":"+1 334 262 3594",
    "sg:postcode":"36108",
    "sg:province":"AL",
    "wof:name":"Alpha Lumber & Supply Co",
    "wof:placetype":"venue"
},
  "geometry": {"coordinates":[-86.35486400000001,32.354225],"type":"Point"}
}