{
  "type": "Feature",
  "properties": {
    "iso:country":"US",
    "sg:address":"4252 Old Leeds Rd",
    "sg:city":"Birmingham",
    "sg:classifiers":[
        {
            "category":"Professional",
            "type":"Services"
        }
    ],
    "sg:phone":"+1 205 967 2037",
    "sg:postcode":"35213",
    "sg:province":"AL",
    "wof:name":"Monticello Fund LLC",
    "wof:placetype":"venue"
},
  "geometry": {"coordinates":[-86.72256,33.500504],"type":"Point"}
}