{
  "type": "Feature",
  "properties": {
    "addr:full":"5441 Nanette Dr Mobile AL 36619",
    "addr:housenumber":"5441",
    "addr:postcode":"36619",
    "addr:street":"Nanette Dr",
    "iso:country":"US",
    "sg:address":"5441 Nanette Dr",
    "sg:city":"Mobile",
    "sg:classifiers":[
        {
            "category":"Government",
            "subcategory":"Post Office",
            "type":"Public Place"
        }
    ],
    "sg:phone":"+1 251 342 9114",
    "sg:postcode":"36619",
    "sg:province":"AL",
    "sg:tags":[
        "postal",
        "us"
    ],
    "wof:name":"US Post Office",
    "wof:placetype":"venue"
},
  "geometry": {"coordinates":[-88.20477,30.582923],"type":"Point"}
}