{
  "type": "Feature",
  "properties": {
    "iso:country":"US",
    "sg:address":"11505 Memorial Pkwy SW",
    "sg:city":"Huntsville",
    "sg:classifiers":[
        {
            "category":"Banks & Credit Unions",
            "subcategory":"Bank",
            "type":"Services"
        }
    ],
    "sg:phone":"+1 256 880 0565",
    "sg:postcode":"35803",
    "sg:province":"AL",
    "sg:tags":[
        "loan",
        "real estate"
    ],
    "wof:name":"AFC Mortgage",
    "wof:placetype":"venue"
},
  "geometry": {"coordinates":[-86.566793,34.62867],"type":"Point"}
}