{
  "type": "Feature",
  "properties": {
    "iso:country":"US",
    "sg:address":"2633 Alta Glen Dr",
    "sg:city":"Birmingham",
    "sg:classifiers":[
        {
            "category":"Social Services",
            "type":"Services"
        }
    ],
    "sg:phone":"+1 205 969 1323",
    "sg:postcode":"35243",
    "sg:province":"AL",
    "wof:name":"Marriage and Family Counseling",
    "wof:placetype":"venue"
},
  "geometry": {"coordinates":[-86.74805499999999,33.43209],"type":"Point"}
}