{
  "type": "Feature",
  "properties": {
    "iso:country":"US",
    "sg:address":"1419 Leighton Ave",
    "sg:city":"Anniston",
    "sg:classifiers":[
        {
            "category":"Professional",
            "type":"Services"
        }
    ],
    "sg:phone":"+1 256 238 8880",
    "sg:postcode":"36207",
    "sg:province":"AL",
    "wof:name":"Harold D Grant",
    "wof:placetype":"venue"
},
  "geometry": {"coordinates":[-85.82499,33.663479],"type":"Point"}
}