{
  "type": "Feature",
  "properties": {
    "addr:full":"412 Governors Dr SW Huntsville AL 35801",
    "addr:housenumber":"412",
    "addr:postcode":"35801",
    "addr:street":"Governors Dr Sw",
    "iso:country":"US",
    "sg:address":"412 Governors Dr SW",
    "sg:city":"Huntsville",
    "sg:classifiers":[
        {
            "category":"Shopping",
            "subcategory":"Clothing, Apparel, & Fashions",
            "type":"Retail Goods"
        }
    ],
    "sg:phone":"+1 256 539 0155",
    "sg:postcode":"35801",
    "sg:province":"AL",
    "wof:name":"UNIFORM Corner",
    "wof:placetype":"venue"
},
  "geometry": {"coordinates":[-86.58607000000001,34.720066],"type":"Point"}
}