{
  "type": "Feature",
  "properties": {
    "iso:country":"US",
    "sg:address":"2572 Co Rd 50",
    "sg:city":"Mount Hope",
    "sg:classifiers":[
        {
            "category":"Food & Beverages",
            "subcategory":"Groceries & Convenience Stores",
            "type":"Retail Goods"
        }
    ],
    "sg:phone":"+1 256 974 6390",
    "sg:postcode":"35651",
    "sg:province":"AL",
    "sg:tags":[
        "station",
        "gasoline"
    ],
    "wof:name":"Johnny Riggs Grocery",
    "wof:placetype":"venue"
},
  "geometry": {"coordinates":[-87.445672,34.494664],"type":"Point"}
}