{
  "type": "Feature",
  "properties": {
    "addr:full":"7456 US Hwy 431 Alexandria AL 36250",
    "addr:housenumber":"7456",
    "addr:postcode":"36250",
    "addr:street":"Us Hwy 431",
    "iso:country":"US",
    "sg:address":"7456 US Hwy 431",
    "sg:city":"Alexandria",
    "sg:classifiers":[
        {
            "category":"Organizations",
            "subcategory":"Religious Organization",
            "type":"Services"
        }
    ],
    "sg:phone":"+1 256 847 0700",
    "sg:postcode":"36250",
    "sg:province":"AL",
    "sg:tags":[
        "church"
    ],
    "sg:website":"www.agapecf.com",
    "wof:name":"Agage Christian Fellowship",
    "wof:placetype":"venue"
},
  "geometry": {"coordinates":[-85.894897,33.7763],"type":"Point"}
}