{
  "type": "Feature",
  "properties": {
    "iso:country":"US",
    "sg:address":"100 Church St SW",
    "sg:city":"Huntsville",
    "sg:classifiers":[
        {
            "category":"Professional",
            "type":"Services"
        }
    ],
    "sg:phone":"+1 256 539 4238",
    "sg:postcode":"35801",
    "sg:province":"AL",
    "wof:name":"Spring Jam",
    "wof:placetype":"venue"
},
  "geometry": {"coordinates":[-86.588388,34.729921],"type":"Point"}
}