{
  "type": "Feature",
  "properties": {
    "addr:full":"1634 Montgomery Hwy S Birmingham AL 35216",
    "addr:housenumber":"1634",
    "addr:postcode":"35216",
    "addr:street":"Montgomery Hwy S",
    "iso:country":"US",
    "sg:address":"1634 Montgomery Hwy S",
    "sg:city":"Birmingham",
    "sg:classifiers":[
        {
            "category":"Building & Trades",
            "subcategory":"Landscaping Services",
            "type":"Services"
        }
    ],
    "sg:phone":"+1 205 222 7646",
    "sg:postcode":"35216",
    "sg:province":"AL",
    "wof:name":"Mark Schroeters Lawn & Ldscp",
    "wof:placetype":"venue"
},
  "geometry": {"coordinates":[-86.806321,33.3963],"type":"Point"}
}