{
  "type": "Feature",
  "properties": {
    "iso:country":"US",
    "sg:address":"3021 Lorna Rd",
    "sg:city":"Birmingham",
    "sg:classifiers":[
        {
            "category":"Wholesale",
            "subcategory":"Computers",
            "type":"Manufacturing & Wholesale Goods"
        }
    ],
    "sg:phone":"+1 205 979 1128",
    "sg:postcode":"35216",
    "sg:province":"AL",
    "wof:name":"Nextira Solutions LLC",
    "wof:placetype":"venue"
},
  "geometry": {"coordinates":[-86.804367,33.403362],"type":"Point"}
}