{
  "type": "Feature",
  "properties": {
    "iso:country":"US",
    "sg:address":"986 Anderton Rd",
    "sg:city":"Scottsboro",
    "sg:classifiers":[
        {
            "category":"Professional",
            "type":"Services"
        }
    ],
    "sg:phone":"+1 256 728 2623",
    "sg:postcode":"35769",
    "sg:province":"AL",
    "wof:name":"Jorene Fuell",
    "wof:placetype":"venue"
},
  "geometry": {"coordinates":[-86.179174,34.597202],"type":"Point"}
}