{
  "type": "Feature",
  "properties": {
    "iso:country":"US",
    "sg:address":"401 Fairhope Ave",
    "sg:city":"Fairhope",
    "sg:classifiers":[
        {
            "category":"Shopping",
            "subcategory":"Gifts & Souvenirs",
            "type":"Retail Goods"
        }
    ],
    "sg:phone":"+1 251 928 3797",
    "sg:postcode":"36532",
    "sg:province":"AL",
    "wof:name":"Across The Street Inc",
    "wof:placetype":"venue"
},
  "geometry": {"coordinates":[-87.901967,30.522963],"type":"Point"}
}