{
  "type": "Feature",
  "properties": {
    "addr:full":"2152 Co Rd 537 Crossville AL 35962",
    "addr:housenumber":"2152",
    "addr:postcode":"35962",
    "addr:street":"Co Rd 537",
    "iso:country":"US",
    "sg:address":"2152 Co Rd 537",
    "sg:city":"Crossville",
    "sg:classifiers":[
        {
            "category":"Manufacturing",
            "subcategory":"Lumber",
            "type":"Manufacturing & Wholesale Goods"
        }
    ],
    "sg:phone":"+1 256 528 7778",
    "sg:postcode":"35962",
    "sg:province":"AL",
    "sg:tags":[
        "logging"
    ],
    "wof:name":"Driskill Logging Company",
    "wof:placetype":"venue"
},
  "geometry": {"coordinates":[-85.95895,34.264029],"type":"Point"}
}