{
  "type": "Feature",
  "properties": {
    "addr:full":"151 Plaza Ln Oxford AL 36203",
    "addr:housenumber":"151",
    "addr:postcode":"36203",
    "addr:street":"Plaza Ln",
    "iso:country":"US",
    "sg:address":"151 Plaza Ln",
    "sg:city":"Oxford",
    "sg:classifiers":[
        {
            "category":"Restaurant",
            "type":"Food & Drink"
        }
    ],
    "sg:menulink":"http://www.allmenus.com/al/anniston/56130-firehouse-subs/menu/",
    "sg:phone":"+1 256 835 4660",
    "sg:postcode":"36203",
    "sg:province":"AL",
    "sg:tags":[
        "wrap",
        "american",
        "sandwich"
    ],
    "wof:name":"Firehouse Subs",
    "wof:placetype":"venue"
},
  "geometry": {"coordinates":[-85.834656,33.600474],"type":"Point"}
}