{
  "type": "Feature",
  "properties": {
    "iso:country":"US",
    "sg:address":"1085 Co Rd 209",
    "sg:city":"Jemison",
    "sg:classifiers":[
        {
            "category":"Organizations",
            "subcategory":"Religious Organization",
            "type":"Services"
        }
    ],
    "sg:phone":"+1 205 688 4031",
    "sg:postcode":"35085",
    "sg:province":"AL",
    "wof:name":"Shiloh Baptist Church",
    "wof:placetype":"venue"
},
  "geometry": {"coordinates":[-86.82204299999999,32.929801],"type":"Point"}
}