{
  "type": "Feature",
  "properties": {
    "addr:full":"153 Canal St Mobile AL 36603",
    "addr:housenumber":"153",
    "addr:postcode":"36603",
    "addr:street":"Canal St",
    "iso:country":"US",
    "sg:address":"153 Canal St",
    "sg:city":"Mobile",
    "sg:classifiers":[
        {
            "category":"Insurance",
            "subcategory":"Hazard Insurance",
            "type":"Services"
        }
    ],
    "sg:phone":"+1 251 438 1234",
    "sg:postcode":"36603",
    "sg:province":"AL",
    "sg:tags":[
        "bond"
    ],
    "wof:name":"Jail Busters Inc",
    "wof:placetype":"venue"
},
  "geometry": {"coordinates":[-88.04192500000001,30.683212],"type":"Point"}
}