{
  "type": "Feature",
  "properties": {
    "iso:country":"US",
    "sg:address":"340 Fair Ave",
    "sg:city":"Ozark",
    "sg:classifiers":[
        {
            "category":"Building & Trades",
            "subcategory":"Construction",
            "type":"Services"
        }
    ],
    "sg:phone":"+1 334 726 3995",
    "sg:postcode":"36360",
    "sg:province":"AL",
    "sg:tags":[
        "home",
        "improvement"
    ],
    "wof:name":"Parker & Parker",
    "wof:placetype":"venue"
},
  "geometry": {"coordinates":[-85.63153200000001,31.441976],"type":"Point"}
}