{
  "type": "Feature",
  "properties": {
    "iso:country":"US",
    "sg:address":"7321 Old Pascagoula Rd",
    "sg:city":"Theodore",
    "sg:classifiers":[
        {
            "category":"Retail",
            "subcategory":"Auto Repair",
            "type":"Services"
        }
    ],
    "sg:phone":"+1 251 653 8310",
    "sg:postcode":"36582",
    "sg:province":"AL",
    "sg:tags":[
        "repairing",
        "engine"
    ],
    "wof:name":"Alexander Small Engine",
    "wof:placetype":"venue"
},
  "geometry": {"coordinates":[-88.214398,30.563833],"type":"Point"}
}