{
  "type": "Feature",
  "properties": {
    "addr:full":"2071 Alpine Village Birmingham AL 35216",
    "addr:housenumber":"2071",
    "addr:postcode":"35216",
    "addr:street":"Alpine Village",
    "iso:country":"US",
    "sg:address":"2071 Alpine Village",
    "sg:city":"Birmingham",
    "sg:classifiers":[
        {
            "category":"Real Estate",
            "subcategory":"Real Estate Operator",
            "type":"Services"
        }
    ],
    "sg:phone":"+1 205 987 0806",
    "sg:postcode":"35216",
    "sg:province":"AL",
    "sg:tags":[
        "apartment"
    ],
    "wof:name":"Alpine Apartments",
    "wof:placetype":"venue"
},
  "geometry": {"coordinates":[-86.795878,33.382819],"type":"Point"}
}