{
  "type": "Feature",
  "properties": {
    "iso:country":"US",
    "sg:address":"815 W Carroll St",
    "sg:city":"Dothan",
    "sg:classifiers":[
        {
            "category":"Personal",
            "subcategory":"Beauty Salon",
            "type":"Services"
        },
        {
            "category":"Personal",
            "subcategory":"Barber",
            "type":"Services"
        }
    ],
    "sg:phone":"+1 334 712 1510",
    "sg:postcode":"36301",
    "sg:province":"AL",
    "sg:tags":[
        "shop"
    ],
    "wof:name":"Angie's Style Shop",
    "wof:placetype":"venue"
},
  "geometry": {"coordinates":[-85.41063800000001,31.199235],"type":"Point"}
}