{
  "type": "Feature",
  "properties": {
    "iso:country":"US",
    "sg:address":"6212 Old Madison Pike NW",
    "sg:city":"Huntsville",
    "sg:classifiers":[
        {
            "category":"Shopping",
            "subcategory":"Used Merchandise",
            "type":"Retail Goods"
        }
    ],
    "sg:phone":"+1 256 430 6855",
    "sg:postcode":"35806",
    "sg:province":"AL",
    "sg:tags":[
        "antique"
    ],
    "wof:name":"Sherwood Antiques",
    "wof:placetype":"venue"
},
  "geometry": {"coordinates":[-86.658625,34.713234],"type":"Point"}
}