{
  "type": "Feature",
  "properties": {
    "addr:full":"2811 Keego Rd Brewton AL 36426",
    "addr:housenumber":"2811",
    "addr:postcode":"36426",
    "addr:street":"Keego Rd",
    "iso:country":"US",
    "sg:address":"2811 Keego Rd",
    "sg:city":"Brewton",
    "sg:classifiers":[
        {
            "category":"Mining & Drilling",
            "type":"Manufacturing & Wholesale Goods"
        }
    ],
    "sg:phone":"+1 251 867 5457",
    "sg:postcode":"36426",
    "sg:province":"AL",
    "sg:tags":[
        "timber",
        "gas",
        "oil",
        "exploration",
        "tract"
    ],
    "wof:name":"Marco Land & Petroleum Inc",
    "wof:placetype":"venue"
},
  "geometry": {"coordinates":[-87.128338,31.066994],"type":"Point"}
}