{
  "type": "Feature",
  "properties": {
    "iso:country":"US",
    "sg:address":"591 Co Rd 55",
    "sg:city":"Fort Payne",
    "sg:phone":"+1 256 523 3886",
    "sg:postcode":"35961",
    "sg:province":"AL",
    "sg:tags":[
        "farm",
        "field",
        "crop"
    ],
    "wof:name":"Calvin Jones",
    "wof:placetype":"venue"
},
  "geometry": {"coordinates":[-85.784843,34.31052],"type":"Point"}
}