{
  "type": "Feature",
  "properties": {
    "iso:country":"US",
    "sg:address":"9350 US Hwy 278",
    "sg:city":"Cullman",
    "sg:classifiers":[
        {
            "category":"Autos & Motor Vehicles",
            "subcategory":"Automobile Sales",
            "type":"Retail Goods"
        }
    ],
    "sg:phone":"+1 256 796 2108",
    "sg:postcode":"35055",
    "sg:province":"AL",
    "sg:tags":[
        "used"
    ],
    "wof:name":"Double R Motors",
    "wof:placetype":"venue"
},
  "geometry": {"coordinates":[-86.643091,34.174644],"type":"Point"}
}