{
  "type": "Feature",
  "properties": {
    "iso:country":"US",
    "sg:address":"508 Ward Ave NE",
    "sg:city":"Huntsville",
    "sg:classifiers":[
        {
            "category":"Social Services",
            "type":"Services"
        }
    ],
    "sg:phone":"+1 256 658 6358",
    "sg:postcode":"35801",
    "sg:province":"AL",
    "wof:name":"Shamatha Counseling LLC",
    "wof:placetype":"venue"
},
  "geometry": {"coordinates":[-86.578116,34.739751],"type":"Point"}
}