{
  "type": "Feature",
  "properties": {
    "iso:country":"US",
    "sg:address":"4724 Indian Valley Rd",
    "sg:city":"Birmingham",
    "sg:classifiers":[
        {
            "category":"Professional",
            "subcategory":"Computer Services",
            "type":"Services"
        }
    ],
    "sg:phone":"+1 205 849 9191",
    "sg:postcode":"35217",
    "sg:province":"AL",
    "sg:tags":[
        "related"
    ],
    "wof:name":"PC Control",
    "wof:placetype":"venue"
},
  "geometry": {"coordinates":[-86.747559,33.642777],"type":"Point"}
}