{
  "type": "Feature",
  "properties": {
    "addr:full":"1711 2nd Ave SW Cullman AL 35055",
    "addr:housenumber":"1711",
    "addr:postcode":"35055",
    "addr:street":"2Nd Ave Sw",
    "iso:country":"US",
    "sg:address":"1711 2nd Ave SW",
    "sg:city":"Cullman",
    "sg:classifiers":[
        {
            "category":"Retail",
            "subcategory":"Auto Repair",
            "type":"Services"
        }
    ],
    "sg:phone":"+1 256 737 5465",
    "sg:postcode":"35055",
    "sg:province":"AL",
    "wof:name":"Express Oil Change",
    "wof:placetype":"venue"
},
  "geometry": {"coordinates":[-86.823528,34.139517],"type":"Point"}
}