{
  "type": "Feature",
  "properties": {
    "addr:full":"3736 Everest Dr Montgomery AL 36106",
    "addr:housenumber":"3736",
    "addr:postcode":"36106",
    "addr:street":"Everest Dr",
    "iso:country":"US",
    "sg:address":"3736 Everest Dr",
    "sg:city":"Montgomery",
    "sg:classifiers":[
        {
            "category":"Professional",
            "type":"Services"
        }
    ],
    "sg:phone":"+1 334 271 5572",
    "sg:postcode":"36106",
    "sg:province":"AL",
    "wof:name":"Bailey Wood Products Inc",
    "wof:placetype":"venue"
},
  "geometry": {"coordinates":[-86.246645,32.346074],"type":"Point"}
}