{
  "type": "Feature",
  "properties": {
    "addr:full":"1405 Barry St Oxford AL 36203",
    "addr:housenumber":"1405",
    "addr:postcode":"36203",
    "addr:street":"Barry St",
    "iso:country":"US",
    "sg:address":"1405 Barry St",
    "sg:city":"Oxford",
    "sg:classifiers":[
        {
            "category":"Restaurant",
            "type":"Food & Drink"
        }
    ],
    "sg:menulink":"http://www.allmenus.com/al/anniston/231581-sonic/menu/",
    "sg:phone":"+1 256 832 5400",
    "sg:postcode":"36203",
    "sg:province":"AL",
    "sg:tags":[
        "burger",
        "american"
    ],
    "wof:name":"Sonic",
    "wof:placetype":"venue"
},
  "geometry": {"coordinates":[-85.8382,33.607382],"type":"Point"}
}