{
  "type": "Feature",
  "properties": {
    "addr:full":"70 Co Rd 1488 Cullman AL 35058",
    "addr:housenumber":"70",
    "addr:postcode":"1488;35058",
    "addr:street":"Co Rd",
    "iso:country":"US",
    "sg:address":"70 Co Rd 1488",
    "sg:city":"Cullman",
    "sg:classifiers":[
        {
            "category":"Retail",
            "subcategory":"Repair Shop",
            "type":"Services"
        }
    ],
    "sg:phone":"+1 256 796 2374",
    "sg:postcode":"35058",
    "sg:province":"AL",
    "sg:tags":[
        "tractor"
    ],
    "wof:name":"Joes Tractor Repair",
    "wof:placetype":"venue"
},
  "geometry": {"coordinates":[-86.761346,34.263103],"type":"Point"}
}