{
  "type": "Feature",
  "properties": {
    "addr:full":"6817 Warrior River Rd Hueytown AL 35023",
    "addr:housenumber":"6817",
    "addr:postcode":"35023",
    "addr:street":"Warrior River Rd",
    "iso:country":"US",
    "sg:address":"6817 Warrior River Rd",
    "sg:city":"Hueytown",
    "sg:classifiers":[
        {
            "category":"Food & Beverages",
            "subcategory":"Fruits & Vegetables",
            "type":"Retail Goods"
        }
    ],
    "sg:phone":"+1 205 491 8988",
    "sg:postcode":"35023",
    "sg:province":"AL",
    "sg:tags":[
        "produce"
    ],
    "wof:name":"Little Giant #2",
    "wof:placetype":"venue"
},
  "geometry": {"coordinates":[-87.069395,33.481172],"type":"Point"}
}