{
  "type": "Feature",
  "properties": {
    "addr:full":"2720 Colonial Dr NE Tuscaloosa AL 35404",
    "addr:housenumber":"2720",
    "addr:postcode":"35404",
    "addr:street":"Colonial Dr Ne",
    "iso:country":"US",
    "sg:address":"2720 Colonial Dr NE",
    "sg:city":"Tuscaloosa",
    "sg:classifiers":[
        {
            "category":"Professional",
            "subcategory":"Advertising",
            "type":"Services"
        }
    ],
    "sg:phone":"+1 205 553 9424",
    "sg:postcode":"35404",
    "sg:province":"AL",
    "sg:tags":[
        "outdoor"
    ],
    "wof:name":"Boardworks Outdoor Advg Co",
    "wof:placetype":"venue"
},
  "geometry": {"coordinates":[-87.50164599999999,33.218587],"type":"Point"}
}