{
  "type": "Feature",
  "properties": {
    "iso:country":"US",
    "sg:address":"600 Boll Weevil Cir",
    "sg:city":"Enterprise",
    "sg:classifiers":[
        {
            "category":"Shopping",
            "type":"Retail Goods"
        }
    ],
    "sg:phone":"+1 334 347 0074",
    "sg:postcode":"36330",
    "sg:province":"AL",
    "sg:tags":[
        "miscellaneous",
        "store"
    ],
    "wof:name":"Buds Warehouse Outlet",
    "wof:placetype":"venue"
},
  "geometry": {"coordinates":[-85.864482,31.333523],"type":"Point"}
}