{
  "type": "Feature",
  "properties": {
    "iso:country":"US",
    "sg:address":"1349 Mount Lebanon Rd",
    "sg:city":"Toney",
    "sg:classifiers":[
        {
            "category":"Building & Trades",
            "subcategory":"Construction",
            "type":"Services"
        }
    ],
    "sg:phone":"+1 256 828 3069",
    "sg:postcode":"35773",
    "sg:province":"AL",
    "sg:tags":[
        "general",
        "contractor"
    ],
    "wof:name":"Hereford O S Construction Co",
    "wof:placetype":"venue"
},
  "geometry": {"coordinates":[-86.606883,34.87025],"type":"Point"}
}