{
  "type": "Feature",
  "properties": {
    "iso:country":"US",
    "sg:address":"3305 32nd Ave",
    "sg:city":"Northport",
    "sg:classifiers":[
        {
            "category":"Building & Trades",
            "subcategory":"Construction",
            "type":"Services"
        }
    ],
    "sg:phone":"+1 205 333 2537",
    "sg:postcode":"35476",
    "sg:province":"AL",
    "sg:tags":[
        "general",
        "contractor"
    ],
    "wof:name":"Kelly Construction",
    "wof:placetype":"venue"
},
  "geometry": {"coordinates":[-87.588332,33.239568],"type":"Point"}
}