{
  "type": "Feature",
  "properties": {
    "iso:country":"US",
    "sg:address":"112 Lily Flagg Rd SW",
    "sg:city":"Huntsville",
    "sg:classifiers":[
        {
            "category":"Health Services",
            "subcategory":"Doctor",
            "type":"Services"
        }
    ],
    "sg:phone":"+1 256 881 4580",
    "sg:postcode":"35802",
    "sg:province":"AL",
    "sg:tags":[
        "dentist"
    ],
    "wof:name":"Marvin D Bishop DDS",
    "wof:placetype":"venue"
},
  "geometry": {"coordinates":[-86.568116,34.658123],"type":"Point"}
}