{
  "type": "Feature",
  "properties": {
    "iso:country":"US",
    "sg:address":"500 Forrest Ave",
    "sg:city":"Brewton",
    "sg:classifiers":[
        {
            "category":"Shopping",
            "subcategory":"Hobbies, Toys, & Games",
            "type":"Retail Goods"
        }
    ],
    "sg:phone":"+1 251 867 2121",
    "sg:postcode":"36426",
    "sg:province":"AL",
    "sg:tags":[
        "craft",
        "supply"
    ],
    "wof:name":"Blushing Brush",
    "wof:placetype":"venue"
},
  "geometry": {"coordinates":[-87.06301499999999,31.096064],"type":"Point"}
}