{
  "type": "Feature",
  "properties": {
    "iso:country":"US",
    "sg:address":"355 Co Rd 1662",
    "sg:city":"Cullman",
    "sg:classifiers":[
        {
            "category":"Farming",
            "subcategory":"Livestock Farm",
            "type":"Manufacturing & Wholesale Goods"
        }
    ],
    "sg:phone":"+1 256 796 2896",
    "sg:postcode":"35058",
    "sg:province":"AL",
    "sg:tags":[
        "beef",
        "feedlot",
        "cattle"
    ],
    "wof:name":"Haynes Darell",
    "wof:placetype":"venue"
},
  "geometry": {"coordinates":[-86.693009,34.23924],"type":"Point"}
}