{
  "type": "Feature",
  "properties": {
    "iso:country":"US",
    "sg:address":"509 18th St SW",
    "sg:city":"Birmingham",
    "sg:classifiers":[
        {
            "category":"Organizations",
            "subcategory":"Religious Organization",
            "type":"Services"
        }
    ],
    "sg:phone":"+1 205 923 2421",
    "sg:postcode":"35211",
    "sg:province":"AL",
    "wof:name":"Abundant Harvest Church",
    "wof:placetype":"venue"
},
  "geometry": {"coordinates":[-86.865683,33.485824],"type":"Point"}
}