{
  "type": "Feature",
  "properties": {
    "addr:full":"530 George Wallace Dr Gadsden AL 35903",
    "addr:housenumber":"530",
    "addr:postcode":"35903",
    "addr:street":"George Wallace Dr",
    "iso:country":"US",
    "sg:address":"530 George Wallace Dr",
    "sg:city":"Gadsden",
    "sg:classifiers":[
        {
            "category":"Shopping",
            "subcategory":"Stationery & Office Supplies",
            "type":"Retail Goods"
        }
    ],
    "sg:phone":"+1 256 543 8256",
    "sg:postcode":"35903",
    "sg:province":"AL",
    "sg:website":"www.officemax.com",
    "wof:name":"Office Max",
    "wof:placetype":"venue"
},
  "geometry": {"coordinates":[-85.99562,34.001742],"type":"Point"}
}