{
  "type": "Feature",
  "properties": {
    "addr:full":"827 Bishop Trl Montgomery AL 36105",
    "addr:housenumber":"827",
    "addr:postcode":"36105",
    "addr:street":"Bishop Trl",
    "iso:country":"US",
    "sg:address":"827 Bishop Trl",
    "sg:city":"Montgomery",
    "sg:classifiers":[
        {
            "category":"Building & Trades",
            "subcategory":"Construction",
            "type":"Services"
        }
    ],
    "sg:phone":"+1 334 288 3000",
    "sg:postcode":"36105",
    "sg:province":"AL",
    "sg:tags":[
        "house",
        "improvement",
        "home"
    ],
    "wof:name":"B & B Vinyl Siding LLC",
    "wof:placetype":"venue"
},
  "geometry": {"coordinates":[-86.322084,32.212703],"type":"Point"}
}