{
  "type": "Feature",
  "properties": {
    "iso:country":"US",
    "sg:address":"6605 Barrow Ct",
    "sg:city":"Mobile",
    "sg:classifiers":[
        {
            "category":"Building & Trades",
            "subcategory":"Construction",
            "type":"Services"
        }
    ],
    "sg:phone":"+1 251 660 8875",
    "sg:postcode":"36695",
    "sg:province":"AL",
    "sg:tags":[
        "resurfacing",
        "laying",
        "refinishing",
        "floor"
    ],
    "wof:name":"Rouse Flooring Contracting",
    "wof:placetype":"venue"
},
  "geometry": {"coordinates":[-88.195729,30.621149],"type":"Point"}
}