{
  "type": "Feature",
  "properties": {
    "iso:country":"US",
    "sg:address":"1953 Cobbs Ford Rd",
    "sg:city":"Prattville",
    "sg:classifiers":[
        {
            "category":"Shopping",
            "subcategory":"Books",
            "type":"Retail Goods"
        }
    ],
    "sg:phone":"+1 334 361 8996",
    "sg:postcode":"36066",
    "sg:province":"AL",
    "sg:tags":[
        "dealer"
    ],
    "wof:name":"Bookland",
    "wof:placetype":"venue"
},
  "geometry": {"coordinates":[-86.416213,32.460168],"type":"Point"}
}