{
  "type": "Feature",
  "properties": {
    "iso:country":"US",
    "sg:address":"1304 Cove Lake Cir",
    "sg:city":"Birmingham",
    "sg:classifiers":[
        {
            "category":"Professional",
            "subcategory":"Computer Services",
            "type":"Services"
        }
    ],
    "sg:phone":"+1 205 408 0227",
    "sg:postcode":"35242",
    "sg:province":"AL",
    "wof:name":"Cataserv",
    "wof:placetype":"venue"
},
  "geometry": {"coordinates":[-86.625653,33.432848],"type":"Point"}
}