{
  "type": "Feature",
  "properties": {
    "addr:full":"11550 Dauphin Island Pkwy Theodore AL 36582",
    "addr:housenumber":"11550",
    "addr:postcode":"36582",
    "addr:street":"Dauphin Island Pkwy",
    "iso:country":"US",
    "sg:address":"11550 Dauphin Island Pkwy",
    "sg:city":"Theodore",
    "sg:classifiers":[
        {
            "category":"Home & Garden",
            "subcategory":"Hardware",
            "type":"Retail Goods"
        }
    ],
    "sg:phone":"+1 251 973 2472",
    "sg:postcode":"36582",
    "sg:province":"AL",
    "wof:name":"Faulkner Supply Co",
    "wof:placetype":"venue"
},
  "geometry": {"coordinates":[-88.115762,30.454423],"type":"Point"}
}