{
  "type": "Feature",
  "properties": {
    "addr:full":"17645 US Hwy 31 Cullman AL 35058",
    "addr:housenumber":"17645",
    "addr:postcode":"35058",
    "addr:street":"Us Hwy 31",
    "iso:country":"US",
    "sg:address":"17645 US Hwy 31",
    "sg:city":"Cullman",
    "sg:classifiers":[
        {
            "category":"Farming",
            "subcategory":"Livestock Farm",
            "type":"Manufacturing & Wholesale Goods"
        }
    ],
    "sg:phone":"+1 256 739 4959",
    "sg:postcode":"35058",
    "sg:province":"AL",
    "sg:tags":[
        "animal",
        "general"
    ],
    "wof:name":"Cullman County AG Trade Ctr",
    "wof:placetype":"venue"
},
  "geometry": {"coordinates":[-86.859275,34.223518],"type":"Point"}
}