{
  "type": "Feature",
  "properties": {
    "iso:country":"US",
    "sg:address":"3208 Co Rd 1488",
    "sg:city":"Cullman",
    "sg:classifiers":[
        {
            "category":"Farming",
            "subcategory":"Livestock Farm",
            "type":"Manufacturing & Wholesale Goods"
        }
    ],
    "sg:phone":"+1 256 796 5306",
    "sg:postcode":"35058",
    "sg:province":"AL",
    "sg:tags":[
        "beef",
        "feedlot",
        "cattle"
    ],
    "wof:name":"Robert Raburn",
    "wof:placetype":"venue"
},
  "geometry": {"coordinates":[-86.726376,34.277108],"type":"Point"}
}