{
  "type": "Feature",
  "properties": {
    "iso:country":"US",
    "sg:address":"2311 Big Cove Rd SE",
    "sg:city":"Huntsville",
    "sg:classifiers":[
        {
            "category":"Building & Trades",
            "subcategory":"Construction",
            "type":"Services"
        }
    ],
    "sg:phone":"+1 256 533 3682",
    "sg:postcode":"35801",
    "sg:province":"AL",
    "sg:tags":[
        "repairing",
        "remodeling",
        "contractor"
    ],
    "wof:name":"DLH Remodeling",
    "wof:placetype":"venue"
},
  "geometry": {"coordinates":[-86.545359,34.720203],"type":"Point"}
}