{
  "type": "Feature",
  "properties": {
    "iso:country":"US",
    "sg:address":"633 S Union Ave",
    "sg:city":"Ozark",
    "sg:classifiers":[
        {
            "category":"Health Services",
            "subcategory":"Doctor",
            "type":"Services"
        }
    ],
    "sg:phone":"+1 334 774 1412",
    "sg:postcode":"36360",
    "sg:province":"AL",
    "sg:tags":[
        "physician",
        "surgeon",
        "medical"
    ],
    "wof:name":"Ozark Pediatric Association",
    "wof:placetype":"venue"
},
  "geometry": {"coordinates":[-85.638398,31.454099],"type":"Point"}
}