{
  "type": "Feature",
  "properties": {
    "addr:full":"701 Princeton Ave SW Birmingham AL 35211",
    "addr:housenumber":"701",
    "addr:postcode":"35211",
    "addr:street":"Princeton Ave Sw",
    "iso:country":"US",
    "sg:address":"701 Princeton Ave SW",
    "sg:city":"Birmingham",
    "sg:classifiers":[
        {
            "category":"Health Services",
            "subcategory":"Doctor",
            "type":"Services"
        }
    ],
    "sg:phone":"+1 205 783 3240",
    "sg:postcode":"35211",
    "sg:province":"AL",
    "sg:tags":[
        "physician",
        "surgeon"
    ],
    "wof:name":"BMC Pathology",
    "wof:placetype":"venue"
},
  "geometry": {"coordinates":[-86.84707,33.498519],"type":"Point"}
}