{
  "type": "Feature",
  "properties": {
    "iso:country":"US",
    "sg:address":"2201 Vaughn Lakes Blvd",
    "sg:city":"Montgomery",
    "sg:classifiers":[
        {
            "category":"Building & Trades",
            "subcategory":"Construction",
            "type":"Services"
        }
    ],
    "sg:phone":"+1 334 277 9010",
    "sg:postcode":"36117",
    "sg:province":"AL",
    "sg:tags":[
        "designer",
        "dealer",
        "pool",
        "swimming"
    ],
    "wof:name":"SOS Pools",
    "wof:placetype":"venue"
},
  "geometry": {"coordinates":[-86.215435,32.344598],"type":"Point"}
}