{
  "type": "Feature",
  "properties": {
    "iso:country":"US",
    "sg:address":"1124 College Ave",
    "sg:city":"Boaz",
    "sg:classifiers":[
        {
            "category":"Government",
            "subcategory":"Office",
            "type":"Public Place"
        }
    ],
    "sg:phone":"+1 256 593 3173",
    "sg:postcode":"35957",
    "sg:province":"AL",
    "sg:tags":[
        "village"
    ],
    "wof:name":"Boaz Sewage Treatment Plant",
    "wof:placetype":"venue"
},
  "geometry": {"coordinates":[-86.184673,34.201969],"type":"Point"}
}