{
  "type": "Feature",
  "properties": {
    "iso:country":"US",
    "sg:address":"68 McGlathery Ln",
    "sg:city":"Falkville",
    "sg:classifiers":[
        {
            "category":"Building & Trades",
            "subcategory":"Construction",
            "type":"Services"
        }
    ],
    "sg:phone":"+1 256 784 9255",
    "sg:postcode":"35622",
    "sg:province":"AL",
    "sg:tags":[
        "house"
    ],
    "wof:name":"Ross Beard Custom Homes Inc",
    "wof:placetype":"venue"
},
  "geometry": {"coordinates":[-86.85934,34.360409],"type":"Point"}
}