{
  "type": "Feature",
  "properties": {
    "addr:full":"543 Brookwood Pl Birmingham AL 35209",
    "addr:housenumber":"543",
    "addr:postcode":"35209",
    "addr:street":"Brookwood Pl",
    "iso:country":"US",
    "sg:address":"543 Brookwood Pl",
    "sg:city":"Birmingham",
    "sg:classifiers":[
        {
            "category":"Retail",
            "subcategory":"Veterinary Services",
            "type":"Services"
        }
    ],
    "sg:phone":"+1 205 870 4500",
    "sg:postcode":"35209",
    "sg:province":"AL",
    "wof:name":"Brookwood Animal Clinic PA",
    "wof:placetype":"venue"
},
  "geometry": {"coordinates":[-86.77109,33.467305],"type":"Point"}
}