{
  "type": "Feature",
  "properties": {
    "iso:country":"US",
    "sg:address":"2003 New Center Rd",
    "sg:city":"Somerville",
    "sg:classifiers":[
        {
            "category":"Organizations",
            "subcategory":"Labor Organization",
            "type":"Services"
        }
    ],
    "sg:phone":"+1 256 351 9407",
    "sg:postcode":"35670",
    "sg:province":"AL",
    "wof:name":"International Brotherhood",
    "wof:placetype":"venue"
},
  "geometry": {"coordinates":[-86.855923,34.498858],"type":"Point"}
}