{
  "type": "Feature",
  "properties": {
    "iso:country":"US",
    "sg:address":"415 Main Ave",
    "sg:city":"Northport",
    "sg:classifiers":[
        {
            "category":"Shopping",
            "subcategory":"Clothing, Apparel, & Fashions",
            "type":"Retail Goods"
        }
    ],
    "sg:phone":"+1 205 758 7583",
    "sg:postcode":"35476",
    "sg:province":"AL",
    "wof:name":"Faucett's",
    "wof:placetype":"venue"
},
  "geometry": {"coordinates":[-87.578378,33.218837],"type":"Point"}
}