{
  "type": "Feature",
  "properties": {
    "iso:country":"US",
    "sg:address":"118 Kelley Rd",
    "sg:city":"Albertville",
    "sg:classifiers":[
        {
            "category":"Shopping",
            "subcategory":"Computers & Home Electronics",
            "type":"Retail Goods"
        }
    ],
    "sg:phone":"+1 256 894 7815",
    "sg:postcode":"35950",
    "sg:province":"AL",
    "sg:tags":[
        "programing",
        "custom"
    ],
    "wof:name":"Computer Barn",
    "wof:placetype":"venue"
},
  "geometry": {"coordinates":[-86.31498000000001,34.283227],"type":"Point"}
}