{
  "type": "Feature",
  "properties": {
    "addr:full":"13804 Shell Belt Rd Bayou La Batre AL 36509",
    "addr:housenumber":"13804",
    "addr:postcode":"36509",
    "addr:street":"Shell Belt Rd;La",
    "iso:country":"US",
    "sg:address":"13804 Shell Belt Rd",
    "sg:city":"Bayou La Batre",
    "sg:classifiers":[
        {
            "category":"Restaurant",
            "type":"Food & Drink"
        }
    ],
    "sg:phone":"+1 251 824 7388",
    "sg:postcode":"36509",
    "sg:province":"AL",
    "sg:tags":[
        "eating"
    ],
    "wof:name":"Cafe Creation",
    "wof:placetype":"venue"
},
  "geometry": {"coordinates":[-88.25000199999999,30.403509],"type":"Point"}
}