{
  "type": "Feature",
  "properties": {
    "addr:full":"93 Grimes Ln Boaz AL 35957",
    "addr:housenumber":"93",
    "addr:postcode":"35957",
    "addr:street":"Grimes Ln",
    "iso:country":"US",
    "sg:address":"93 Grimes Ln",
    "sg:city":"Boaz",
    "sg:classifiers":[
        {
            "category":"Farming",
            "subcategory":"Farm",
            "type":"Manufacturing & Wholesale Goods"
        }
    ],
    "sg:phone":"+1 256 593 7896",
    "sg:postcode":"35957",
    "sg:province":"AL",
    "sg:tags":[
        "general"
    ],
    "wof:name":"Hayes Welton",
    "wof:placetype":"venue"
},
  "geometry": {"coordinates":[-86.277317,34.191132],"type":"Point"}
}