{
  "type": "Feature",
  "properties": {
    "iso:country":"US",
    "sg:address":"501 Burke Ave SE",
    "sg:city":"Attalla",
    "sg:classifiers":[
        {
            "category":"Professional",
            "type":"Services"
        }
    ],
    "sg:phone":"+1 256 538 9518",
    "sg:postcode":"35954",
    "sg:province":"AL",
    "wof:name":"J R Mayo",
    "wof:placetype":"venue"
},
  "geometry": {"coordinates":[-86.104548,33.989132],"type":"Point"}
}