{
  "type": "Feature",
  "properties": {
    "addr:full":"501 Main Ave Northport AL 35476",
    "addr:housenumber":"501",
    "addr:postcode":"35476",
    "addr:street":"Main Ave",
    "iso:country":"US",
    "sg:address":"501 Main Ave",
    "sg:city":"Northport",
    "sg:classifiers":[
        {
            "category":"Wholesale",
            "subcategory":"Construction Materials",
            "type":"Manufacturing & Wholesale Goods"
        }
    ],
    "sg:phone":"+1 205 758 3772",
    "sg:postcode":"35476",
    "sg:province":"AL",
    "sg:tags":[
        "art",
        "work",
        "metal"
    ],
    "wof:name":"Sunheart Metal Works",
    "wof:placetype":"venue"
},
  "geometry": {"coordinates":[-87.579104,33.220687],"type":"Point"}
}