{
  "type": "Feature",
  "properties": {
    "addr:full":"14328 Frank Lary Rd Northport AL 35475",
    "addr:housenumber":"14328",
    "addr:postcode":"35475",
    "addr:street":"Frank Lary Rd",
    "iso:country":"US",
    "sg:address":"14328 Frank Lary Rd",
    "sg:city":"Northport",
    "sg:classifiers":[
        {
            "category":"Home & Garden",
            "subcategory":"Furniture",
            "type":"Retail Goods"
        }
    ],
    "sg:phone":"+1 205 339 8779",
    "sg:postcode":"35475",
    "sg:province":"AL",
    "sg:tags":[
        "cabinet"
    ],
    "wof:name":"Cox's Wood Working Inc",
    "wof:placetype":"venue"
},
  "geometry": {"coordinates":[-87.59312799999999,33.32741],"type":"Point"}
}