{
  "type": "Feature",
  "properties": {
    "addr:full":"2933 Virginia Rd Birmingham AL 35223",
    "addr:housenumber":"2933",
    "addr:postcode":"35223",
    "addr:street":"Virginia Rd",
    "iso:country":"US",
    "sg:address":"2933 Virginia Rd",
    "sg:city":"Birmingham",
    "sg:classifiers":[
        {
            "category":"Real Estate",
            "subcategory":"Architect",
            "type":"Services"
        }
    ],
    "sg:phone":"+1 205 802 3990",
    "sg:postcode":"35223",
    "sg:province":"AL",
    "wof:name":"Hollingsworth Carey Architect",
    "wof:placetype":"venue"
},
  "geometry": {"coordinates":[-86.757977,33.488818],"type":"Point"}
}