{
  "type": "Feature",
  "properties": {
    "addr:full":"41 W Park Cir Birmingham AL 35211",
    "addr:housenumber":"41",
    "addr:postcode":"35211",
    "addr:street":"W Park Cir",
    "iso:country":"US",
    "sg:address":"41 W Park Cir",
    "sg:city":"Birmingham",
    "sg:classifiers":[
        {
            "category":"Wholesale",
            "subcategory":"Electrical",
            "type":"Manufacturing & Wholesale Goods"
        }
    ],
    "sg:phone":"+1 205 942 0200",
    "sg:postcode":"35211",
    "sg:province":"AL",
    "sg:tags":[
        "fire",
        "alarm",
        "system"
    ],
    "sg:website":"www.centralfireprotection.com",
    "wof:name":"Central Fire Alarm & Security",
    "wof:placetype":"venue"
},
  "geometry": {"coordinates":[-86.84284,33.459792],"type":"Point"}
}