{
  "type": "Feature",
  "properties": {
    "iso:country":"US",
    "sg:address":"322 S Wilson Ave",
    "sg:city":"Mobile",
    "sg:classifiers":[
        {
            "category":"Shopping",
            "type":"Retail Goods"
        }
    ],
    "sg:phone":"+1 251 456 2133",
    "sg:postcode":"36610",
    "sg:province":"AL",
    "sg:tags":[
        "merchandise"
    ],
    "wof:name":"Elijah Prophet Spiritual Candl",
    "wof:placetype":"venue"
},
  "geometry": {"coordinates":[-88.08255800000001,30.731779],"type":"Point"}
}