{
  "type": "Feature",
  "properties": {
    "iso:country":"US",
    "sg:address":"4607 1st Ave N",
    "sg:city":"Birmingham",
    "sg:classifiers":[
        {
            "category":"Building & Trades",
            "subcategory":"Construction",
            "type":"Services"
        }
    ],
    "sg:phone":"+1 205 595 4741",
    "sg:postcode":"35222",
    "sg:province":"AL",
    "wof:name":"A & L Contractors",
    "wof:placetype":"venue"
},
  "geometry": {"coordinates":[-86.766673,33.532844],"type":"Point"}
}