{
  "type": "Feature",
  "properties": {
    "iso:country":"US",
    "sg:address":"228 Todd St",
    "sg:city":"Cottonwood",
    "sg:classifiers":[
        {
            "category":"Organizations",
            "subcategory":"Religious Organization",
            "type":"Services"
        }
    ],
    "sg:phone":"+1 334 691 2702",
    "sg:postcode":"36320",
    "sg:province":"AL",
    "sg:tags":[
        "clergy"
    ],
    "wof:name":"Calvary Baptist Pastorium",
    "wof:placetype":"venue"
},
  "geometry": {"coordinates":[-85.305818,31.067516],"type":"Point"}
}