{
  "type": "Feature",
  "properties": {
    "addr:full":"185 Howelton Church Rd Altoona AL 35952",
    "addr:housenumber":"185",
    "addr:postcode":"35952",
    "addr:street":"Howelton Church Rd",
    "iso:country":"US",
    "sg:address":"185 Howelton Church Rd",
    "sg:city":"Altoona",
    "sg:classifiers":[
        {
            "category":"Organizations",
            "subcategory":"Religious Organization",
            "type":"Services"
        }
    ],
    "sg:phone":"+1 205 589 4447",
    "sg:postcode":"35952",
    "sg:province":"AL",
    "sg:tags":[
        "church"
    ],
    "wof:name":"Howelton Methodist Church",
    "wof:placetype":"venue"
},
  "geometry": {"coordinates":[-86.180859,34.056055],"type":"Point"}
}