{
  "type": "Feature",
  "properties": {
    "addr:full":"28170 N Main St Daphne AL 36526",
    "addr:housenumber":"28170",
    "addr:postcode":"36526",
    "addr:street":"N Main St",
    "iso:country":"US",
    "sg:address":"28170 N Main St",
    "sg:city":"Daphne",
    "sg:classifiers":[
        {
            "category":"Utilities",
            "subcategory":"Water",
            "type":"Services"
        }
    ],
    "sg:phone":"+1 251 626 5981",
    "sg:postcode":"36526",
    "sg:province":"AL",
    "sg:tags":[
        "company",
        "sewage"
    ],
    "wof:name":"Park City Water Authority",
    "wof:placetype":"venue"
},
  "geometry": {"coordinates":[-87.91056500000001,30.640107],"type":"Point"}
}