{
  "type": "Feature",
  "properties": {
    "addr:full":"214 S Andrews St Scottsboro AL 35768",
    "addr:housenumber":"214",
    "addr:postcode":"35768",
    "addr:street":"S Andrews St",
    "iso:country":"US",
    "sg:address":"214 S Andrews St",
    "sg:city":"Scottsboro",
    "sg:classifiers":[
        {
            "category":"Manufacturing",
            "subcategory":"Printing",
            "type":"Manufacturing & Wholesale Goods"
        }
    ],
    "sg:phone":"+1 256 259 1042",
    "sg:postcode":"35768",
    "sg:province":"AL",
    "sg:tags":[
        "newspaper"
    ],
    "wof:name":"Huntsville Times Jackson Cnty",
    "wof:placetype":"venue"
},
  "geometry": {"coordinates":[-86.03256,34.67263],"type":"Point"}
}