{
  "type": "Feature",
  "properties": {
    "iso:country":"US",
    "sg:address":"2737 Southside Dr",
    "sg:city":"Tuscaloosa",
    "sg:classifiers":[
        {
            "category":"Wholesale",
            "subcategory":"Construction Materials",
            "type":"Manufacturing & Wholesale Goods"
        }
    ],
    "sg:phone":"+1 205 752 0004",
    "sg:postcode":"35401",
    "sg:province":"AL",
    "sg:tags":[
        "siding"
    ],
    "wof:name":"Aluma Kraft Sales",
    "wof:placetype":"venue"
},
  "geometry": {"coordinates":[-87.559459,33.185976],"type":"Point"}
}