{
  "type": "Feature",
  "properties": {
    "iso:country":"US",
    "sg:address":"3370 Co Rd 42",
    "sg:city":"Oneonta",
    "sg:classifiers":[
        {
            "category":"Freight",
            "type":"Transportation"
        }
    ],
    "sg:phone":"+1 205 589 2691",
    "sg:postcode":"35121",
    "sg:province":"AL",
    "sg:tags":[
        "hauling",
        "trucking"
    ],
    "wof:name":"Sand Valley Enterprises",
    "wof:placetype":"venue"
},
  "geometry": {"coordinates":[-86.39552999999999,34.023379],"type":"Point"}
}