{
  "type": "Feature",
  "properties": {
    "addr:full":"5181 Co Rd 434 Trinity AL 35673",
    "addr:housenumber":"5181;434",
    "addr:postcode":"35673",
    "addr:street":"Co Rd;Trinity",
    "iso:country":"US",
    "sg:address":"5181 Co Rd 434",
    "sg:city":"Trinity",
    "sg:classifiers":[
        {
            "category":"Building & Trades",
            "subcategory":"Construction",
            "type":"Services"
        }
    ],
    "sg:phone":"+1 256 974 0564",
    "sg:postcode":"35673",
    "sg:province":"AL",
    "sg:tags":[
        "hanging",
        "contractor"
    ],
    "wof:name":"Tim Blaxton Painter",
    "wof:placetype":"venue"
},
  "geometry": {"coordinates":[-87.159251,34.551179],"type":"Point"}
}