{
  "type": "Feature",
  "properties": {
    "addr:full":"2419 Crestwood Dr SW Huntsville AL 35805",
    "addr:housenumber":"2419",
    "addr:postcode":"35805",
    "addr:street":"Crestwood Dr Sw",
    "iso:country":"US",
    "sg:address":"2419 Crestwood Dr SW",
    "sg:city":"Huntsville",
    "sg:classifiers":[
        {
            "category":"Building & Trades",
            "subcategory":"Electrical",
            "type":"Services"
        }
    ],
    "sg:phone":"+1 256 746 9937",
    "sg:postcode":"35805",
    "sg:province":"AL",
    "sg:tags":[
        "electric",
        "contractor"
    ],
    "wof:name":"Electrical Support",
    "wof:placetype":"venue"
},
  "geometry": {"coordinates":[-86.63175699999999,34.713867],"type":"Point"}
}