{
  "type": "Feature",
  "properties": {
    "iso:country":"US",
    "sg:address":"2519 12th St",
    "sg:city":"Tuscaloosa",
    "sg:classifiers":[
        {
            "category":"Retail",
            "subcategory":"Auto Repair",
            "type":"Services"
        }
    ],
    "sg:phone":"+1 205 752 2524",
    "sg:postcode":"35401",
    "sg:province":"AL",
    "sg:tags":[
        "repairing",
        "automobile"
    ],
    "sg:website":"www.goodyear.com",
    "wof:name":"Goodyear Tire Ctr",
    "wof:placetype":"venue"
},
  "geometry": {"coordinates":[-87.568126,33.202387],"type":"Point"}
}