{
  "type": "Feature",
  "properties": {
    "iso:country":"US",
    "sg:address":"10900 US Hwy 278 E",
    "sg:city":"Piedmont",
    "sg:classifiers":[
        {
            "category":"Farming",
            "subcategory":"Livestock Farm",
            "type":"Manufacturing & Wholesale Goods"
        }
    ],
    "sg:phone":"+1 256 492 3537",
    "sg:postcode":"36272",
    "sg:province":"AL",
    "sg:tags":[
        "beef",
        "feedlot",
        "cattle"
    ],
    "wof:name":"Ralph Sims",
    "wof:placetype":"venue"
},
  "geometry": {"coordinates":[-85.777533,33.97098],"type":"Point"}
}