{
  "type": "Feature",
  "properties": {
    "addr:full":"10900 US Hwy 278 E Piedmont AL 36272",
    "addr:housenumber":"10900",
    "addr:postcode":"36272",
    "addr:street":"Us Hwy 278 E",
    "iso:country":"US",
    "sg:address":"10900 US Hwy 278 E",
    "sg:city":"Piedmont",
    "sg:classifiers":[
        {
            "category":"Farming",
            "subcategory":"Livestock Farm",
            "type":"Manufacturing & Wholesale Goods"
        }
    ],
    "sg:phone":"+1 256 492 3537",
    "sg:postcode":"36272",
    "sg:province":"AL",
    "sg:tags":[
        "beef",
        "feedlot",
        "cattle"
    ],
    "wof:name":"Ralph Sims",
    "wof:placetype":"venue"
},
  "geometry": {"coordinates":[-85.77753300000001,33.97098],"type":"Point"}
}