{
  "type": "Feature",
  "properties": {
    "addr:full":"1016 E Commerce St Greenville AL 36037",
    "addr:housenumber":"1016",
    "addr:postcode":"36037",
    "addr:street":"E Commerce St",
    "iso:country":"US",
    "sg:address":"1016 E Commerce St",
    "sg:city":"Greenville",
    "sg:classifiers":[
        {
            "category":"Recreation",
            "type":"Entertainment"
        }
    ],
    "sg:phone":"+1 334 382 9891",
    "sg:postcode":"36037",
    "sg:province":"AL",
    "sg:tags":[
        "parks"
    ],
    "wof:name":"Greenville Recreation Dept",
    "wof:placetype":"venue"
},
  "geometry": {"coordinates":[-86.612268,31.829971],"type":"Point"}
}