{
  "type": "Feature",
  "properties": {
    "iso:country":"US",
    "sg:address":"2200 Pinson Valley Pkwy",
    "sg:city":"Birmingham",
    "sg:classifiers":[
        {
            "category":"Manufacturing",
            "subcategory":"Tools & Machinery",
            "type":"Manufacturing & Wholesale Goods"
        }
    ],
    "sg:phone":"+1 205 841 0421",
    "sg:postcode":"35217",
    "sg:province":"AL",
    "sg:tags":[
        "engine"
    ],
    "sg:website":"www.alabama.cummins.com",
    "wof:name":"Cummins Mid South LLC",
    "wof:placetype":"venue"
},
  "geometry": {"coordinates":[-86.759759,33.596761],"type":"Point"}
}