{
  "type": "Feature",
  "properties": {
    "iso:country":"US",
    "sg:address":"214 Magnolia Ave",
    "sg:city":"Fairhope",
    "sg:classifiers":[
        {
            "category":"Personal",
            "subcategory":"Beauty Salon",
            "type":"Services"
        }
    ],
    "sg:phone":"+1 251 928 2801",
    "sg:postcode":"36532",
    "sg:province":"AL",
    "sg:tags":[
        "shop"
    ],
    "wof:name":"Dana's Beauty Salon",
    "wof:placetype":"venue"
},
  "geometry": {"coordinates":[-87.904973,30.524357],"type":"Point"}
}