{
  "type": "Feature",
  "properties": {
    "addr:full":"5400 US Hwy 278 Cullman AL 35057",
    "addr:housenumber":"5400",
    "addr:postcode":"35057",
    "addr:street":"Us Hwy 278",
    "iso:country":"US",
    "sg:address":"5400 US Hwy 278",
    "sg:city":"Cullman",
    "sg:classifiers":[
        {
            "category":"Organizations",
            "subcategory":"Religious Organization",
            "type":"Services"
        }
    ],
    "sg:phone":"+1 256 775 6307",
    "sg:postcode":"35057",
    "sg:province":"AL",
    "sg:tags":[
        "church"
    ],
    "wof:name":"Spring Hill Baptist Church",
    "wof:placetype":"venue"
},
  "geometry": {"coordinates":[-86.954519,34.194683],"type":"Point"}
}