{
  "type": "Feature",
  "properties": {
    "iso:country":"US",
    "sg:address":"806 Governors Dr SW",
    "sg:city":"Huntsville",
    "sg:classifiers":[
        {
            "category":"Restaurant",
            "type":"Food & Drink"
        }
    ],
    "sg:phone":"+1 256 830 5919",
    "sg:postcode":"35801",
    "sg:province":"AL",
    "sg:tags":[
        "eating"
    ],
    "wof:name":"Catfish Entertainment Inc",
    "wof:placetype":"venue"
},
  "geometry": {"coordinates":[-86.592128,34.720149],"type":"Point"}
}