{
  "type": "Feature",
  "properties": {
    "iso:country":"US",
    "sg:address":"3550 Creek Path Rd",
    "sg:city":"Guntersville",
    "sg:classifiers":[
        {
            "category":"Government",
            "subcategory":"Office",
            "type":"Public Place"
        }
    ],
    "sg:phone":"+1 256 582 3602",
    "sg:postcode":"35976",
    "sg:province":"AL",
    "sg:tags":[
        "armory",
        "national",
        "guard"
    ],
    "wof:name":"Alabama National Guard",
    "wof:placetype":"venue"
},
  "geometry": {"coordinates":[-86.33286,34.323336],"type":"Point"}
}