{
  "type": "Feature",
  "properties": {
    "iso:country":"US",
    "sg:address":"1001 George Wallace Dr",
    "sg:city":"Gadsden",
    "sg:classifiers":[
        {
            "category":"Social Services",
            "subcategory":"Child Care",
            "type":"Services"
        }
    ],
    "sg:phone":"+1 256 546 7819",
    "sg:postcode":"35903",
    "sg:province":"AL",
    "wof:name":"Child Care Central",
    "wof:placetype":"venue"
},
  "geometry": {"coordinates":[-85.989098,33.994145],"type":"Point"}
}