{
  "type": "Feature",
  "properties": {
    "iso:country":"US",
    "sg:address":"2825 Montrose Dr SW",
    "sg:city":"Decatur",
    "sg:classifiers":[
        {
            "category":"Professional",
            "type":"Services"
        }
    ],
    "sg:phone":"+1 256 350 0128",
    "sg:postcode":"35603",
    "sg:province":"AL",
    "wof:name":"Perry Baker",
    "wof:placetype":"venue"
},
  "geometry": {"coordinates":[-87.026273,34.556542],"type":"Point"}
}