{
  "type": "Feature",
  "properties": {
    "iso:country":"US",
    "sg:address":"2932 Ross Clark Cir",
    "sg:city":"Dothan",
    "sg:classifiers":[
        {
            "category":"Building & Trades",
            "subcategory":"Construction",
            "type":"Services"
        }
    ],
    "sg:phone":"+1 334 618 0406",
    "sg:postcode":"36301",
    "sg:province":"AL",
    "sg:tags":[
        "house"
    ],
    "wof:name":"Miller Construction",
    "wof:placetype":"venue"
},
  "geometry": {"coordinates":[-85.432055,31.221034],"type":"Point"}
}