{
  "type": "Feature",
  "properties": {
    "addr:full":"22 Co Rd 9 Crossville AL 35962",
    "addr:housenumber":"22",
    "addr:postcode":"35962",
    "addr:street":"Co Rd 9",
    "iso:country":"US",
    "sg:address":"22 Co Rd 9",
    "sg:city":"Crossville",
    "sg:classifiers":[
        {
            "category":"Manufacturing",
            "subcategory":"Metals",
            "type":"Manufacturing & Wholesale Goods"
        }
    ],
    "sg:phone":"+1 256 659 4395",
    "sg:postcode":"35962",
    "sg:province":"AL",
    "sg:tags":[
        "metalwork",
        "sheet",
        "mfg"
    ],
    "wof:name":"Jennings Awning Co",
    "wof:placetype":"venue"
},
  "geometry": {"coordinates":[-86.089947,34.30845],"type":"Point"}
}