{
  "type": "Feature",
  "properties": {
    "addr:full":"1210 Highway 31 NW Hartselle AL 35640",
    "addr:housenumber":"1210",
    "addr:postcode":"35640",
    "addr:street":"Highway 31 Nw",
    "iso:country":"US",
    "sg:address":"1210 Highway 31 NW",
    "sg:city":"Hartselle",
    "sg:classifiers":[
        {
            "category":"Personal",
            "subcategory":"Beauty Salon",
            "type":"Services"
        }
    ],
    "sg:phone":"+1 256 751 0209",
    "sg:postcode":"35640",
    "sg:province":"AL",
    "wof:name":"Ebony Ivory Beauty Salon",
    "wof:placetype":"venue"
},
  "geometry": {"coordinates":[-86.946906,34.454993],"type":"Point"}
}