{
  "type": "Feature",
  "properties": {
    "iso:country":"US",
    "sg:address":"13042 US Hwy 72",
    "sg:city":"Rogersville",
    "sg:classifiers":[
        {
            "category":"Manufacturing",
            "subcategory":"Textiles",
            "type":"Manufacturing & Wholesale Goods"
        }
    ],
    "sg:phone":"+1 256 247 0722",
    "sg:postcode":"35652",
    "sg:province":"AL",
    "sg:tags":[
        "mill",
        "fabric",
        "cotton"
    ],
    "wof:name":"Thorton Aireal Service",
    "wof:placetype":"venue"
},
  "geometry": {"coordinates":[-87.3683,34.842663],"type":"Point"}
}