{
  "type": "Feature",
  "properties": {
    "addr:full":"277 Mallard Rd Winfield AL 35594",
    "addr:housenumber":"277",
    "addr:postcode":"35594",
    "addr:street":"Mallard Rd",
    "iso:country":"US",
    "sg:address":"277 Mallard Rd",
    "sg:city":"Winfield",
    "sg:classifiers":[
        {
            "category":"Retail",
            "subcategory":"Laundry & Dry Cleaning",
            "type":"Services"
        }
    ],
    "sg:phone":"+1 205 487 6474",
    "sg:postcode":"35594",
    "sg:province":"AL",
    "sg:tags":[
        "cleaners"
    ],
    "wof:name":"City Laundry & Cleaners",
    "wof:placetype":"venue"
},
  "geometry": {"coordinates":[-87.81838,33.92514],"type":"Point"}
}