{
  "type": "Feature",
  "properties": {
    "addr:full":"8735 State Rte 59 Foley AL 36535",
    "addr:housenumber":"8735",
    "addr:postcode":"36535",
    "addr:street":"State Rte 59",
    "iso:country":"US",
    "sg:address":"8735 State Rte 59",
    "sg:city":"Foley",
    "sg:classifiers":[
        {
            "category":"Personal",
            "subcategory":"Beauty Salon",
            "type":"Services"
        }
    ],
    "sg:phone":"+1 251 943 3225",
    "sg:postcode":"36535",
    "sg:province":"AL",
    "sg:tags":[
        "shop"
    ],
    "wof:name":"Cutting Edge",
    "wof:placetype":"venue"
},
  "geometry": {"coordinates":[-87.682975,30.345034],"type":"Point"}
}