{
  "type": "Feature",
  "properties": {
    "addr:full":"2201 7th Ave N Pell City AL 35125",
    "addr:housenumber":"2201",
    "addr:postcode":"35125",
    "addr:street":"7Th Ave N",
    "iso:country":"US",
    "sg:address":"2201 7th Ave N",
    "sg:city":"Pell City",
    "sg:classifiers":[
        {
            "category":"Restaurant",
            "type":"Food & Drink"
        }
    ],
    "sg:menulink":"http://www.allmenus.com/al/pell-city/72753-pizza-hut/menu/",
    "sg:phone":"+1 205 338 2211",
    "sg:postcode":"35125",
    "sg:province":"AL",
    "sg:tags":[
        "american",
        "pizza"
    ],
    "wof:name":"Pizza Hut",
    "wof:placetype":"venue"
},
  "geometry": {"coordinates":[-86.284218,33.595296],"type":"Point"}
}