{
  "type": "Feature",
  "properties": {
    "addr:full":"350 Co Rd 357 Florence AL 35633",
    "addr:housenumber":"350",
    "addr:postcode":"35633",
    "addr:street":"Co Rd 357",
    "iso:country":"US",
    "sg:address":"350 Co Rd 357",
    "sg:city":"Florence",
    "sg:classifiers":[
        {
            "category":"Retail",
            "subcategory":"Auto Repair",
            "type":"Services"
        }
    ],
    "sg:phone":"+1 256 766 2149",
    "sg:postcode":"35633",
    "sg:province":"AL",
    "sg:tags":[
        "body",
        "used",
        "parts"
    ],
    "wof:name":"Bevis Steve Used Cars",
    "wof:placetype":"venue"
},
  "geometry": {"coordinates":[-87.687093,34.864985],"type":"Point"}
}