{
  "type": "Feature",
  "properties": {
    "iso:country":"US",
    "sg:address":"3613 Eastern Blvd",
    "sg:city":"Montgomery",
    "sg:classifiers":[
        {
            "category":"Professional",
            "subcategory":"Accounting & Tax Preparation",
            "type":"Services"
        }
    ],
    "sg:phone":"+1 334 277 2368",
    "sg:postcode":"36116",
    "sg:province":"AL",
    "sg:tags":[
        "return",
        "filing"
    ],
    "wof:name":"Downs Quik Tax",
    "wof:placetype":"venue"
},
  "geometry": {"coordinates":[-86.23205400000001,32.330264],"type":"Point"}
}