{
  "type": "Feature",
  "properties": {
    "addr:full":"601 S 4th St Opelika AL 36801",
    "addr:housenumber":"601",
    "addr:postcode":"36801",
    "addr:street":"S 4Th St",
    "iso:country":"US",
    "sg:address":"601 S 4th St",
    "sg:city":"Opelika",
    "sg:classifiers":[
        {
            "category":"Social Services",
            "subcategory":"Child Care",
            "type":"Services"
        }
    ],
    "sg:phone":"+1 334 821 8336",
    "sg:postcode":"36801",
    "sg:province":"AL",
    "wof:name":"Head Start",
    "wof:placetype":"venue"
},
  "geometry": {"coordinates":[-85.36855199999999,32.645623],"type":"Point"}
}