{
  "type": "Feature",
  "properties": {
    "addr:full":"8209 Franklin St Thorsby AL 35171",
    "addr:housenumber":"8209",
    "addr:postcode":"35171",
    "addr:street":"Franklin St",
    "iso:country":"US",
    "sg:address":"8209 Franklin St",
    "sg:city":"Thorsby",
    "sg:classifiers":[
        {
            "category":"Home & Garden",
            "subcategory":"Mobile Homes",
            "type":"Retail Goods"
        }
    ],
    "sg:phone":"+1 205 646 3731",
    "sg:postcode":"35171",
    "sg:province":"AL",
    "wof:name":"Lindas Repos",
    "wof:placetype":"venue"
},
  "geometry": {"coordinates":[-86.727541,32.912934],"type":"Point"}
}