{
  "type": "Feature",
  "properties": {
    "iso:country":"US",
    "sg:address":"124 S Main St",
    "sg:city":"Arab",
    "sg:classifiers":[
        {
            "category":"Professional",
            "subcategory":"Accounting & Tax Preparation",
            "type":"Services"
        }
    ],
    "sg:phone":"+1 256 355 2252",
    "sg:postcode":"35016",
    "sg:province":"AL",
    "sg:tags":[
        "return"
    ],
    "wof:name":"Cook & Lagrone",
    "wof:placetype":"venue"
},
  "geometry": {"coordinates":[-86.495965,34.315093],"type":"Point"}
}