{
  "type": "Feature",
  "properties": {
    "iso:country":"US",
    "sg:address":"2146 Cedarbark Ln",
    "sg:city":"Birmingham",
    "sg:classifiers":[
        {
            "category":"Shopping",
            "subcategory":"Discount & Variety Stores",
            "type":"Retail Goods"
        }
    ],
    "sg:phone":"+1 205 823 5844",
    "sg:postcode":"35216",
    "sg:province":"AL",
    "sg:tags":[
        "merchandise",
        "general"
    ],
    "wof:name":"John W Pennington",
    "wof:placetype":"venue"
},
  "geometry": {"coordinates":[-86.800619,33.446826],"type":"Point"}
}