{
  "type": "Feature",
  "properties": {
    "iso:country":"US",
    "sg:address":"963 Forest Ave",
    "sg:city":"Luverne",
    "sg:classifiers":[
        {
            "category":"Retail",
            "subcategory":"Auto Repair",
            "type":"Services"
        }
    ],
    "sg:phone":"+1 334 335 5032",
    "sg:postcode":"36049",
    "sg:province":"AL",
    "wof:name":"Jones Towing",
    "wof:placetype":"venue"
},
  "geometry": {"coordinates":[-86.263669,31.710835],"type":"Point"}
}