{
  "type": "Feature",
  "properties": {
    "iso:country":"US",
    "sg:address":"1717 Gilmer Ave",
    "sg:city":"Tallassee",
    "sg:classifiers":[
        {
            "category":"Social Services",
            "subcategory":"Child Care",
            "type":"Services"
        }
    ],
    "sg:phone":"+1 334 283 2885",
    "sg:postcode":"36078",
    "sg:province":"AL",
    "wof:name":"Linville Day Care Ctr",
    "wof:placetype":"venue"
},
  "geometry": {"coordinates":[-85.928941,32.560592],"type":"Point"}
}