{
  "type": "Feature",
  "properties": {
    "addr:full":"212 5th St NW Fort Payne AL 35967",
    "addr:housenumber":"212",
    "addr:postcode":"35967",
    "addr:street":"5Th St Nw",
    "iso:country":"US",
    "sg:address":"212 5th St NW",
    "sg:city":"Fort Payne",
    "sg:classifiers":[
        {
            "category":"Professional",
            "type":"Services"
        }
    ],
    "sg:phone":"+1 256 997 9282",
    "sg:postcode":"35967",
    "sg:province":"AL",
    "sg:tags":[
        "establishment"
    ],
    "wof:name":"Fort Payne Memorycall",
    "wof:placetype":"venue"
},
  "geometry": {"coordinates":[-85.72071699999999,34.445073],"type":"Point"}
}