{
  "type": "Feature",
  "properties": {
    "iso:country":"US",
    "sg:address":"7660 Marie Rd",
    "sg:city":"Theodore",
    "sg:classifiers":[
        {
            "category":"Retail",
            "subcategory":"Auto Repair",
            "type":"Services"
        }
    ],
    "sg:phone":"+1 251 653 1789",
    "sg:postcode":"36582",
    "sg:province":"AL",
    "sg:tags":[
        "general"
    ],
    "wof:name":"Garrys Automotive",
    "wof:placetype":"venue"
},
  "geometry": {"coordinates":[-88.221102,30.552923],"type":"Point"}
}