{
  "type": "Feature",
  "properties": {
    "iso:country":"US",
    "sg:address":"531 4th Ave SW",
    "sg:city":"Bessemer",
    "sg:classifiers":[
        {
            "category":"Food & Beverages",
            "subcategory":"Groceries & Convenience Stores",
            "type":"Retail Goods"
        }
    ],
    "sg:phone":"+1 205 425 5117",
    "sg:postcode":"35022",
    "sg:province":"AL",
    "wof:name":"Joes One Stop",
    "wof:placetype":"venue"
},
  "geometry": {"coordinates":[-86.97582199999999,33.376343],"type":"Point"}
}