{
  "type": "Feature",
  "properties": {
    "iso:country":"US",
    "sg:address":"1113 Mountain Oaks Dr",
    "sg:city":"Birmingham",
    "sg:classifiers":[
        {
            "category":"Organizations",
            "subcategory":"Religious Organization",
            "type":"Services"
        }
    ],
    "sg:phone":"+1 205 824 7788",
    "sg:postcode":"35226",
    "sg:province":"AL",
    "wof:name":"Steve Barrett Rev",
    "wof:placetype":"venue"
},
  "geometry": {"coordinates":[-86.828121,33.423197],"type":"Point"}
}