{
  "type": "Feature",
  "properties": {
    "addr:full":"18431 Kevin Boone Dr Fairhope AL 36532",
    "addr:housenumber":"18431",
    "addr:postcode":"36532",
    "addr:street":"Kevin Boone Dr",
    "iso:country":"US",
    "sg:address":"18431 Kevin Boone Dr",
    "sg:city":"Fairhope",
    "sg:classifiers":[
        {
            "category":"Building & Trades",
            "subcategory":"Landscaping Services",
            "type":"Services"
        }
    ],
    "sg:phone":"+1 251 990 5912",
    "sg:postcode":"36532",
    "sg:province":"AL",
    "sg:tags":[
        "landscape",
        "contractor"
    ],
    "wof:name":"All-Pro Solutions",
    "wof:placetype":"venue"
},
  "geometry": {"coordinates":[-87.809327,30.493485],"type":"Point"}
}