{
  "type": "Feature",
  "properties": {
    "iso:country":"US",
    "sg:address":"16205 Court St",
    "sg:city":"Moulton",
    "sg:classifiers":[
        {
            "category":"Wholesale",
            "subcategory":"Scrap",
            "type":"Manufacturing & Wholesale Goods"
        }
    ],
    "sg:phone":"+1 256 974 9247",
    "sg:postcode":"35650",
    "sg:province":"AL",
    "sg:tags":[
        "recycling",
        "center"
    ],
    "wof:name":"Metal Exchange Corp",
    "wof:placetype":"venue"
},
  "geometry": {"coordinates":[-87.26293699999999,34.491746],"type":"Point"}
}