{
  "type": "Feature",
  "properties": {
    "addr:full":"120 Mitcham Ave Auburn AL 36830",
    "addr:housenumber":"120",
    "addr:postcode":"36830",
    "addr:street":"Mitcham Ave",
    "iso:country":"US",
    "sg:address":"120 Mitcham Ave",
    "sg:city":"Auburn",
    "sg:classifiers":[
        {
            "category":"Building & Trades",
            "subcategory":"Construction",
            "type":"Services"
        }
    ],
    "sg:phone":"+1 334 821 7850",
    "sg:postcode":"36830",
    "sg:province":"AL",
    "sg:tags":[
        "home",
        "new",
        "renovation",
        "family",
        "contractor"
    ],
    "wof:name":"Shelton Woods Construction Co",
    "wof:placetype":"venue"
},
  "geometry": {"coordinates":[-85.48024100000001,32.610338],"type":"Point"}
}