{
  "type": "Feature",
  "properties": {
    "iso:country":"US",
    "sg:address":"609 14th St SE",
    "sg:city":"Decatur",
    "sg:classifiers":[
        {
            "category":"Restaurant",
            "type":"Food & Drink"
        }
    ],
    "sg:phone":"+1 256 355 0863",
    "sg:postcode":"35601",
    "sg:province":"AL",
    "wof:name":"Ryan's Grill Buffet & Bakery",
    "wof:placetype":"venue"
},
  "geometry": {"coordinates":[-86.978799,34.578323],"type":"Point"}
}