{
  "type": "Feature",
  "properties": {
    "addr:full":"307 S Academy St Geneva AL 36340",
    "addr:housenumber":"307",
    "addr:postcode":"36340",
    "addr:street":"S Academy St",
    "iso:country":"US",
    "sg:address":"307 S Academy St",
    "sg:city":"Geneva",
    "sg:classifiers":[
        {
            "category":"Travel",
            "subcategory":"Hotels & Motels",
            "type":"Entertainment"
        }
    ],
    "sg:phone":"+1 334 684 2489",
    "sg:postcode":"36340",
    "sg:province":"AL",
    "sg:tags":[
        "breakfast",
        "inn",
        "bed"
    ],
    "wof:name":"Live Oaks Bed & Breakfast",
    "wof:placetype":"venue"
},
  "geometry": {"coordinates":[-85.86585100000001,31.034809],"type":"Point"}
}