{
  "type": "Feature",
  "properties": {
    "iso:country":"US",
    "sg:address":"2001 Mountain St NE",
    "sg:city":"Jacksonville",
    "sg:classifiers":[
        {
            "category":"Building & Trades",
            "subcategory":"Construction",
            "type":"Services"
        }
    ],
    "sg:phone":"+1 256 435 3987",
    "sg:postcode":"36265",
    "sg:province":"AL",
    "sg:tags":[
        "house",
        "hanging"
    ],
    "wof:name":"Curlee Painting Co",
    "wof:placetype":"venue"
},
  "geometry": {"coordinates":[-85.742004,33.818724],"type":"Point"}
}