{
  "type": "Feature",
  "properties": {
    "iso:country":"US",
    "sg:address":"222 Broad St",
    "sg:city":"Gadsden",
    "sg:classifiers":[
        {
            "category":"Autos & Motor Vehicles",
            "subcategory":"Automobile Sales",
            "type":"Retail Goods"
        }
    ],
    "sg:phone":"+1 256 547 5272",
    "sg:postcode":"35901",
    "sg:province":"AL",
    "wof:name":"Auto Sales M and S",
    "wof:placetype":"venue"
},
  "geometry": {"coordinates":[-86.001778,34.012106],"type":"Point"}
}