{
  "type": "Feature",
  "properties": {
    "iso:country":"US",
    "sg:address":"4309 Brewer Rd",
    "sg:city":"Montgomery",
    "sg:classifiers":[
        {
            "category":"Restaurant",
            "type":"Food & Drink"
        }
    ],
    "sg:phone":"+1 334 288 0716",
    "sg:postcode":"36108",
    "sg:province":"AL",
    "sg:tags":[
        "caterer"
    ],
    "wof:name":"Uncle Ed's Old Fashioned Smoke",
    "wof:placetype":"venue"
},
  "geometry": {"coordinates":[-86.388196,32.311464],"type":"Point"}
}