{
  "type": "Feature",
  "properties": {
    "addr:full":"172 Justiss Dr Wetumpka AL 36092",
    "addr:housenumber":"172",
    "addr:postcode":"36092",
    "addr:street":"Justiss Dr Wetumpka",
    "iso:country":"US",
    "sg:address":"172 Justiss Dr",
    "sg:city":"Wetumpka",
    "sg:classifiers":[
        {
            "category":"Retail",
            "subcategory":"Repair Shop",
            "type":"Services"
        },
        {
            "category":"Professional",
            "type":"Services"
        }
    ],
    "sg:phone":"+1 334 567 3474",
    "sg:postcode":"36092",
    "sg:province":"AL",
    "sg:tags":[
        "related"
    ],
    "wof:name":"Dixie Custom Wagons LLC",
    "wof:placetype":"venue"
},
  "geometry": {"coordinates":[-86.17038100000001,32.592745],"type":"Point"}
}