{
  "type": "Feature",
  "properties": {
    "iso:country":"US",
    "sg:address":"1255 Old Hwy 231 N",
    "sg:city":"Troy",
    "sg:classifiers":[
        {
            "category":"Shopping",
            "subcategory":"Discount & Variety Stores",
            "type":"Retail Goods"
        }
    ],
    "sg:phone":"+1 334 670 0410",
    "sg:postcode":"36079",
    "sg:province":"AL",
    "wof:name":"Family Dollar Stores",
    "wof:placetype":"venue"
},
  "geometry": {"coordinates":[-86.00266499999999,31.865774],"type":"Point"}
}