{
  "type": "Feature",
  "properties": {
    "addr:full":"3058 31st Ave N Birmingham AL 35207",
    "addr:housenumber":"3058",
    "addr:postcode":"35207",
    "addr:street":"31St Ave N",
    "iso:country":"US",
    "sg:address":"3058 31st Ave N",
    "sg:city":"Birmingham",
    "sg:classifiers":[
        {
            "category":"Restaurant",
            "type":"Food & Drink"
        }
    ],
    "sg:phone":"+1 205 327 3750",
    "sg:postcode":"35207",
    "sg:province":"AL",
    "sg:tags":[
        "chicken"
    ],
    "wof:name":"Roys Hamburger And Chicken",
    "wof:placetype":"venue"
},
  "geometry": {"coordinates":[-86.80714500000001,33.554151],"type":"Point"}
}