{
  "type": "Feature",
  "properties": {
    "iso:country":"US",
    "sg:address":"3290 Allison-Bonnett Memorial Dr",
    "sg:city":"Bessemer",
    "sg:classifiers":[
        {
            "category":"Personal",
            "subcategory":"Beauty Salon",
            "type":"Services"
        }
    ],
    "sg:phone":"+1 205 491 8600",
    "sg:postcode":"35023",
    "sg:province":"AL",
    "sg:tags":[
        "shop"
    ],
    "wof:name":"Happy Hair",
    "wof:placetype":"venue"
},
  "geometry": {"coordinates":[-87.00807399999999,33.454312],"type":"Point"}
}