{
  "type": "Feature",
  "properties": {
    "iso:country":"US",
    "sg:address":"1318 Pelham Rd S",
    "sg:city":"Jacksonville",
    "sg:classifiers":[
        {
            "category":"Shopping",
            "subcategory":"Jewelry",
            "type":"Retail Goods"
        }
    ],
    "sg:phone":"+1 256 435 7900",
    "sg:postcode":"36265",
    "sg:province":"AL",
    "wof:name":"Jax Pawn Shop & Car Title Loan",
    "wof:placetype":"venue"
},
  "geometry": {"coordinates":[-85.760973,33.79086],"type":"Point"}
}