{
  "type": "Feature",
  "properties": {
    "iso:country":"US",
    "sg:address":"1428 Lomb Ave",
    "sg:city":"Birmingham",
    "sg:classifiers":[
        {
            "category":"Retail",
            "subcategory":"Car Wash",
            "type":"Services"
        }
    ],
    "sg:phone":"+1 205 781 5188",
    "sg:postcode":"35208",
    "sg:province":"AL",
    "sg:tags":[
        "carwash"
    ],
    "wof:name":"New Image Detailing Shop",
    "wof:placetype":"venue"
},
  "geometry": {"coordinates":[-86.860278,33.500362],"type":"Point"}
}