{
  "type": "Feature",
  "properties": {
    "addr:full":"2308 US Hwy 78 Oxford AL 36203",
    "addr:housenumber":"2308",
    "addr:postcode":"36203",
    "addr:street":"Us Hwy 78",
    "iso:country":"US",
    "sg:address":"2308 US Hwy 78",
    "sg:city":"Oxford",
    "sg:classifiers":[
        {
            "category":"Restaurant",
            "type":"Food & Drink"
        }
    ],
    "sg:phone":"+1 256 831 0200",
    "sg:postcode":"36203",
    "sg:province":"AL",
    "sg:tags":[
        "eating"
    ],
    "wof:name":"C J's Family Restaurant",
    "wof:placetype":"venue"
},
  "geometry": {"coordinates":[-85.884332,33.59217],"type":"Point"}
}