{
  "type": "Feature",
  "properties": {
    "iso:country":"US",
    "sg:address":"109 Old Hwy 231 N",
    "sg:city":"Troy",
    "sg:classifiers":[
        {
            "category":"Insurance",
            "subcategory":"Insurance Agent",
            "type":"Services"
        }
    ],
    "sg:phone":"+1 334 566 8777",
    "sg:postcode":"36079",
    "sg:province":"AL",
    "wof:name":"Kreis Agency",
    "wof:placetype":"venue"
},
  "geometry": {"coordinates":[-85.99719,31.854354],"type":"Point"}
}