{
  "type": "Feature",
  "properties": {
    "iso:country":"US",
    "sg:address":"1095 Industrial Pkwy",
    "sg:city":"Saraland",
    "sg:phone":"+1 251 675 8000",
    "sg:postcode":"36571",
    "sg:province":"AL",
    "sg:website":"http://clickserve.dartsearch.net/link/click?lid=43000000308049899",
    "wof:name":"T-Mobile",
    "wof:placetype":"venue"
},
  "geometry": {"coordinates":[-88.099519,30.802091],"type":"Point"}
}