{
  "type": "Feature",
  "properties": {
    "addr:full":"103 Ash Dr Abbeville AL 36310",
    "addr:housenumber":"103",
    "addr:postcode":"36310",
    "addr:street":"Ash Dr",
    "iso:country":"US",
    "sg:address":"103 Ash Dr",
    "sg:city":"Abbeville",
    "sg:classifiers":[
        {
            "category":"Organizations",
            "subcategory":"Religious Organization",
            "type":"Services"
        }
    ],
    "sg:phone":"+1 334 585 5449",
    "sg:postcode":"36310",
    "sg:province":"AL",
    "wof:name":"First Assembly Of God",
    "wof:placetype":"venue"
},
  "geometry": {"coordinates":[-85.252268,31.561386],"type":"Point"}
}