{
  "type": "Feature",
  "properties": {
    "addr:full":"1450 Sparkman St SW Hartselle AL 35640",
    "addr:housenumber":"1450",
    "addr:postcode":"35640",
    "addr:street":"Sparkman St Sw",
    "iso:country":"US",
    "sg:address":"1450 Sparkman St SW",
    "sg:city":"Hartselle",
    "sg:classifiers":[
        {
            "category":"Organizations",
            "subcategory":"Religious Organization",
            "type":"Services"
        }
    ],
    "sg:phone":"+1 256 773 4206",
    "sg:postcode":"35640",
    "sg:province":"AL",
    "sg:tags":[
        "church"
    ],
    "wof:name":"St Barnabus Episcopal Church",
    "wof:placetype":"venue"
},
  "geometry": {"coordinates":[-86.926917,34.423503],"type":"Point"}
}