{
  "type": "Feature",
  "properties": {
    "iso:country":"US",
    "sg:address":"312 Sanford Ave",
    "sg:city":"Eufaula",
    "sg:classifiers":[
        {
            "category":"Building & Trades",
            "subcategory":"Construction",
            "type":"Services"
        }
    ],
    "sg:phone":"+1 334 687 3173",
    "sg:postcode":"36027",
    "sg:province":"AL",
    "sg:tags":[
        "house"
    ],
    "wof:name":"Kornegay Construction Co",
    "wof:placetype":"venue"
},
  "geometry": {"coordinates":[-85.150805,31.89671],"type":"Point"}
}