{
  "type": "Feature",
  "properties": {
    "iso:country":"US",
    "sg:address":"123 Hilltop Business Center Dr",
    "sg:city":"Pelham",
    "sg:classifiers":[
        {
            "category":"Professional",
            "subcategory":"Computer Services",
            "type":"Services"
        }
    ],
    "sg:phone":"+1 205 982 7774",
    "sg:postcode":"35124",
    "sg:province":"AL",
    "sg:tags":[
        "consultant",
        "designer"
    ],
    "wof:name":"Pro Soft",
    "wof:placetype":"venue"
},
  "geometry": {"coordinates":[-86.795162,33.336108],"type":"Point"}
}