{
  "type": "Feature",
  "properties": {
    "iso:country":"US",
    "sg:address":"1565 Mount Vernon Rd",
    "sg:city":"Boaz",
    "sg:classifiers":[
        {
            "category":"Retail",
            "subcategory":"Portrait Studio",
            "type":"Services"
        }
    ],
    "sg:phone":"+1 256 593 9710",
    "sg:postcode":"35957",
    "sg:province":"AL",
    "sg:tags":[
        "photographer"
    ],
    "wof:name":"Tomorrow's Treasures Photo",
    "wof:placetype":"venue"
},
  "geometry": {"coordinates":[-86.186688,34.213874],"type":"Point"}
}