{
  "type": "Feature",
  "properties": {
    "iso:country":"US",
    "sg:address":"5548 Matt Aaron Ln",
    "sg:city":"Birmingham",
    "sg:classifiers":[
        {
            "category":"Wholesale",
            "subcategory":"Vending Machines",
            "type":"Manufacturing & Wholesale Goods"
        }
    ],
    "sg:phone":"+1 205 853 7242",
    "sg:postcode":"35215",
    "sg:province":"AL",
    "sg:tags":[
        "operator"
    ],
    "wof:name":"T & T Vending",
    "wof:placetype":"venue"
},
  "geometry": {"coordinates":[-86.65798599999999,33.651408],"type":"Point"}
}