{
  "type": "Feature",
  "properties": {
    "iso:country":"US",
    "sg:address":"201 E 4th St",
    "sg:city":"Sheffield",
    "sg:classifiers":[
        {
            "category":"Insurance",
            "subcategory":"Insurance Agent",
            "type":"Services"
        }
    ],
    "sg:phone":"+1 256 383 3553",
    "sg:postcode":"35660",
    "sg:province":"AL",
    "wof:name":"Ashe-Box Insurance Inc",
    "wof:placetype":"venue"
},
  "geometry": {"coordinates":[-87.696955,34.761848],"type":"Point"}
}