{
  "type": "Feature",
  "properties": {
    "iso:country":"US",
    "sg:address":"107 Lake Forest Dr",
    "sg:city":"Montgomery",
    "sg:classifiers":[
        {
            "category":"Personal",
            "subcategory":"Beauty Salon",
            "type":"Services"
        }
    ],
    "sg:phone":"+1 334 272 6727",
    "sg:postcode":"36117",
    "sg:province":"AL",
    "sg:tags":[
        "shop"
    ],
    "wof:name":"Nails By Linda Massage Therapy",
    "wof:placetype":"venue"
},
  "geometry": {"coordinates":[-86.160804,32.3842],"type":"Point"}
}