{
  "type": "Feature",
  "properties": {
    "iso:country":"US",
    "sg:address":"1911 Crapemyrtle Green SE",
    "sg:city":"Huntsville",
    "sg:classifiers":[
        {
            "category":"Building & Trades",
            "subcategory":"Equipment Rental",
            "type":"Services"
        }
    ],
    "sg:phone":"+1 256 881 5249",
    "sg:postcode":"35803",
    "sg:province":"AL",
    "wof:name":"La & E",
    "wof:placetype":"venue"
},
  "geometry": {"coordinates":[-86.536835,34.636376],"type":"Point"}
}