{
  "type": "Feature",
  "properties": {
    "addr:full":"105 Nichols Ave Fairhope AL 36532",
    "addr:housenumber":"105",
    "addr:postcode":"36532",
    "addr:street":"Nichols Ave",
    "iso:country":"US",
    "sg:address":"105 Nichols Ave",
    "sg:city":"Fairhope",
    "sg:classifiers":[
        {
            "category":"Home & Garden",
            "subcategory":"Garden Supply",
            "type":"Retail Goods"
        }
    ],
    "sg:phone":"+1 251 990 0847",
    "sg:postcode":"36532",
    "sg:province":"AL",
    "wof:name":"Busak & Shamban South",
    "wof:placetype":"venue"
},
  "geometry": {"coordinates":[-87.911551,30.517625],"type":"Point"}
}