{
  "type": "Feature",
  "properties": {
    "addr:full":"2821 Buckskin Dr Gardendale AL 35071",
    "addr:housenumber":"2821",
    "addr:postcode":"35071",
    "addr:street":"Buckskin Dr",
    "iso:country":"US",
    "sg:address":"2821 Buckskin Dr",
    "sg:city":"Gardendale",
    "sg:classifiers":[
        {
            "category":"Building & Trades",
            "subcategory":"Construction",
            "type":"Services"
        }
    ],
    "sg:phone":"+1 205 631 9574",
    "sg:postcode":"35071",
    "sg:province":"AL",
    "sg:tags":[
        "hanging",
        "contractor"
    ],
    "wof:name":"Cates Painting",
    "wof:placetype":"venue"
},
  "geometry": {"coordinates":[-86.83004099999999,33.694495],"type":"Point"}
}