{
  "type": "Feature",
  "properties": {
    "iso:country":"US",
    "sg:address":"2821 Buckskin Dr",
    "sg:city":"Gardendale",
    "sg:classifiers":[
        {
            "category":"Building & Trades",
            "subcategory":"Construction",
            "type":"Services"
        }
    ],
    "sg:phone":"+1 205 631 9574",
    "sg:postcode":"35071",
    "sg:province":"AL",
    "sg:tags":[
        "hanging",
        "contractor"
    ],
    "wof:name":"Cates Painting",
    "wof:placetype":"venue"
},
  "geometry": {"coordinates":[-86.830041,33.694495],"type":"Point"}
}