{
  "type": "Feature",
  "properties": {
    "iso:country":"US",
    "sg:address":"6005 Monticello Dr",
    "sg:city":"Montgomery",
    "sg:classifiers":[
        {
            "category":"Manufacturing",
            "subcategory":"Printing",
            "type":"Manufacturing & Wholesale Goods"
        }
    ],
    "sg:phone":"+1 334 272 6000",
    "sg:postcode":"36117",
    "sg:province":"AL",
    "sg:tags":[
        "newspaper"
    ],
    "wof:name":"Bulletin Board",
    "wof:placetype":"venue"
},
  "geometry": {"coordinates":[-86.204994,32.365414],"type":"Point"}
}