{
  "type": "Feature",
  "properties": {
    "iso:country":"US",
    "sg:address":"101 Oakwood Ave NE",
    "sg:city":"Huntsville",
    "sg:classifiers":[
        {
            "category":"Banks & Credit Unions",
            "subcategory":"Bank",
            "type":"Services"
        }
    ],
    "sg:phone":"+1 256 535 6999",
    "sg:postcode":"35811",
    "sg:province":"AL",
    "wof:name":"AM South Bank",
    "wof:placetype":"venue"
},
  "geometry": {"coordinates":[-86.582122,34.749178],"type":"Point"}
}