{
  "type": "Feature",
  "properties": {
    "iso:country":"US",
    "sg:address":"406 Randolph Ave SE",
    "sg:city":"Huntsville",
    "sg:classifiers":[
        {
            "category":"Organizations",
            "subcategory":"Religious Organization",
            "type":"Services"
        }
    ],
    "sg:phone":"+1 256 534 8446",
    "sg:postcode":"35801",
    "sg:province":"AL",
    "wof:name":"Hawthorne Conservatory",
    "wof:placetype":"venue"
},
  "geometry": {"coordinates":[-86.564127,34.735375],"type":"Point"}
}