{
  "type": "Feature",
  "properties": {
    "iso:country":"US",
    "sg:address":"24249 US Hwy 98",
    "sg:city":"Daphne",
    "sg:classifiers":[
        {
            "category":"Building & Trades",
            "subcategory":"Construction",
            "type":"Services"
        }
    ],
    "sg:phone":"+1 251 928 6997",
    "sg:postcode":"36526",
    "sg:province":"AL",
    "wof:name":"Affordable Structures Inc",
    "wof:placetype":"venue"
},
  "geometry": {"coordinates":[-87.898399,30.577954],"type":"Point"}
}