{
  "type": "Feature",
  "properties": {
    "addr:full":"28404 US Hwy 72 Hollywood AL 35752",
    "addr:housenumber":"28404",
    "addr:postcode":"35752",
    "addr:street":"Us Hwy 72",
    "iso:country":"US",
    "sg:address":"28404 US Hwy 72",
    "sg:city":"Hollywood",
    "sg:classifiers":[
        {
            "category":"Manufacturing",
            "subcategory":"Signs",
            "type":"Manufacturing & Wholesale Goods"
        }
    ],
    "sg:phone":"+1 256 259 1039",
    "sg:postcode":"35752",
    "sg:province":"AL",
    "wof:name":"Thomas Sign Co",
    "wof:placetype":"venue"
},
  "geometry": {"coordinates":[-85.976562,34.706801],"type":"Point"}
}