{
  "type": "Feature",
  "properties": {
    "addr:full":"177 Dexter Cir Madison AL 35757",
    "addr:housenumber":"177",
    "addr:postcode":"35757",
    "addr:street":"Dexter Cir",
    "iso:country":"US",
    "sg:address":"177 Dexter Cir",
    "sg:city":"Madison",
    "sg:classifiers":[
        {
            "category":"Building & Trades",
            "subcategory":"Construction",
            "type":"Services"
        }
    ],
    "sg:phone":"+1 256 721 7545",
    "sg:postcode":"35757",
    "sg:province":"AL",
    "sg:tags":[
        "contractor"
    ],
    "wof:name":"Langford Masonry",
    "wof:placetype":"venue"
},
  "geometry": {"coordinates":[-86.751846,34.800337],"type":"Point"}
}