{
  "type": "Feature",
  "properties": {
    "addr:full":"2310 Skyland Blvd E Tuscaloosa AL 35405",
    "addr:housenumber":"2310",
    "addr:postcode":"35405",
    "addr:street":"Skyland Blvd E",
    "iso:country":"US",
    "sg:address":"2310 Skyland Blvd E",
    "sg:city":"Tuscaloosa",
    "sg:classifiers":[
        {
            "category":"Organizations",
            "subcategory":"Religious Organization",
            "type":"Services"
        }
    ],
    "sg:phone":"+1 205 553 7282",
    "sg:postcode":"35405",
    "sg:province":"AL",
    "sg:tags":[
        "church"
    ],
    "sg:website":"www.matthiaschurch.org",
    "wof:name":"St Matthias' Episcopal Church",
    "wof:placetype":"venue"
},
  "geometry": {"coordinates":[-87.506514,33.169329],"type":"Point"}
}