{
  "type": "Feature",
  "properties": {
    "addr:full":"801 US Hwy 31 Bay Minette AL 36507",
    "addr:housenumber":"801",
    "addr:postcode":"36507",
    "addr:street":"Us Hwy 31",
    "iso:country":"US",
    "sg:address":"801 US Hwy 31",
    "sg:city":"Bay Minette",
    "sg:classifiers":[
        {
            "category":"Manufacturing",
            "subcategory":"Furniture",
            "type":"Manufacturing & Wholesale Goods"
        }
    ],
    "sg:phone":"+1 251 937 6741",
    "sg:postcode":"36507",
    "sg:province":"AL",
    "sg:website":"www.grand-designs.com",
    "wof:name":"Standard Furniture Mfg Co",
    "wof:placetype":"venue"
},
  "geometry": {"coordinates":[-87.764709,30.887052],"type":"Point"}
}