{
  "type": "Feature",
  "properties": {
    "iso:country":"US",
    "sg:address":"3959 Higgins Rd",
    "sg:city":"Mobile",
    "sg:classifiers":[
        {
            "category":"Manufacturing",
            "subcategory":"Watercraft",
            "type":"Manufacturing & Wholesale Goods"
        }
    ],
    "sg:phone":"+1 251 661 3080",
    "sg:postcode":"36619",
    "sg:province":"AL",
    "sg:tags":[
        "boating",
        "school"
    ],
    "wof:name":"Ocean & Coast Wise Eductl Svcs",
    "wof:placetype":"venue"
},
  "geometry": {"coordinates":[-88.131586,30.592816],"type":"Point"}
}