{
  "type": "Feature",
  "properties": {
    "addr:full":"3928 Cloverdale Rd Florence AL 35633",
    "addr:housenumber":"3928",
    "addr:postcode":"35633",
    "addr:street":"Cloverdale Rd",
    "iso:country":"US",
    "sg:address":"3928 Cloverdale Rd",
    "sg:city":"Florence",
    "sg:classifiers":[
        {
            "category":"Shopping",
            "subcategory":"Discount & Variety Stores",
            "type":"Retail Goods"
        },
        {
            "category":"Shopping",
            "subcategory":"Department Store",
            "type":"Retail Goods"
        }
    ],
    "sg:phone":"+1 256 766 1566",
    "sg:postcode":"35633",
    "sg:province":"AL",
    "sg:tags":[
        "shop"
    ],
    "wof:name":"Family Dollar Stores",
    "wof:placetype":"venue"
},
  "geometry": {"coordinates":[-87.691627,34.861505],"type":"Point"}
}