{
  "type": "Feature",
  "properties": {
    "addr:full":"2980 Hartford Hwy Dothan AL 36305",
    "addr:housenumber":"2980",
    "addr:postcode":"36305",
    "addr:street":"Hartford Hwy",
    "iso:country":"US",
    "sg:address":"2980 Hartford Hwy",
    "sg:city":"Dothan",
    "sg:classifiers":[
        {
            "category":"Retail",
            "subcategory":"Auto Repair",
            "type":"Services"
        }
    ],
    "sg:phone":"+1 334 702 7917",
    "sg:postcode":"36305",
    "sg:province":"AL",
    "sg:tags":[
        "repairing",
        "automobile",
        "general"
    ],
    "wof:name":"Ormes Automotive",
    "wof:placetype":"venue"
},
  "geometry": {"coordinates":[-85.438081,31.198693],"type":"Point"}
}