{
  "type": "Feature",
  "properties": {
    "iso:country":"US",
    "sg:address":"8033 Howells Ferry Rd",
    "sg:city":"Semmes",
    "sg:classifiers":[
        {
            "category":"Professional",
            "subcategory":"Management & Consulting",
            "type":"Services"
        }
    ],
    "sg:phone":"+1 251 645 8668",
    "sg:postcode":"36575",
    "sg:province":"AL",
    "sg:tags":[
        "consultant",
        "business"
    ],
    "wof:name":"Chosen Inc",
    "wof:placetype":"venue"
},
  "geometry": {"coordinates":[-88.228144,30.717971],"type":"Point"}
}