{
  "type": "Feature",
  "properties": {
    "addr:full":"5369 Nanette Dr Mobile AL 36619",
    "addr:housenumber":"5369",
    "addr:postcode":"36619",
    "addr:street":"Nanette Dr",
    "iso:country":"US",
    "sg:address":"5369 Nanette Dr",
    "sg:city":"Mobile",
    "sg:classifiers":[
        {
            "category":"Restaurant",
            "type":"Food & Drink"
        }
    ],
    "sg:phone":"+1 251 660 1011",
    "sg:postcode":"36619",
    "sg:province":"AL",
    "sg:tags":[
        "eating"
    ],
    "wof:name":"Canton Chinese Restaurant",
    "wof:placetype":"venue"
},
  "geometry": {"coordinates":[-88.204716,30.58287],"type":"Point"}
}