{
  "type": "Feature",
  "properties": {
    "iso:country":"US",
    "sg:address":"300 1st Ave N",
    "sg:city":"Birmingham",
    "sg:classifiers":[
        {
            "category":"Wholesale",
            "subcategory":"Auto Parts",
            "type":"Manufacturing & Wholesale Goods"
        }
    ],
    "sg:phone":"+1 205 328 5140",
    "sg:postcode":"35204",
    "sg:province":"AL",
    "sg:tags":[
        "accessory"
    ],
    "wof:name":"Rocco & Cheaters Speed Shop",
    "wof:placetype":"venue"
},
  "geometry": {"coordinates":[-86.828373,33.503819],"type":"Point"}
}