{
  "type": "Feature",
  "properties": {
    "iso:country":"US",
    "sg:address":"21455 State Rte 79",
    "sg:city":"Scottsboro",
    "sg:classifiers":[
        {
            "category":"Shopping",
            "subcategory":"Discount & Variety Stores",
            "type":"Retail Goods"
        },
        {
            "category":"Shopping",
            "subcategory":"Department Store",
            "type":"Retail Goods"
        }
    ],
    "sg:phone":"+1 256 587 3110",
    "sg:postcode":"35768",
    "sg:province":"AL",
    "sg:tags":[
        "shop"
    ],
    "wof:name":"Dollar General",
    "wof:placetype":"venue"
},
  "geometry": {"coordinates":[-86.10911900000001,34.653963],"type":"Point"}
}