{
  "type": "Feature",
  "properties": {
    "addr:full":"109 Andover Ln Huntsville AL 35811",
    "addr:housenumber":"109",
    "addr:postcode":"35811",
    "addr:street":"Andover Ln",
    "iso:country":"US",
    "sg:address":"109 Andover Ln",
    "sg:city":"Huntsville",
    "sg:classifiers":[
        {
            "category":"Professional",
            "subcategory":"Computer Services",
            "type":"Services"
        }
    ],
    "sg:phone":"+1 256 746 9917",
    "sg:postcode":"35811",
    "sg:province":"AL",
    "sg:tags":[
        "custom",
        "e",
        "system",
        "software"
    ],
    "wof:name":"J Cooper LLC",
    "wof:placetype":"venue"
},
  "geometry": {"coordinates":[-86.51272899999999,34.820114],"type":"Point"}
}