{
  "type": "Feature",
  "properties": {
    "addr:full":"1308 Buckhead Way Birmingham AL 35216",
    "addr:housenumber":"1308",
    "addr:postcode":"35216",
    "addr:street":"Buckhead Way",
    "iso:country":"US",
    "sg:address":"1308 Buckhead Way",
    "sg:city":"Birmingham",
    "sg:classifiers":[
        {
            "category":"Professional",
            "type":"Services"
        }
    ],
    "sg:phone":"+1 205 979 9523",
    "sg:postcode":"35216",
    "sg:province":"AL",
    "wof:name":"Life Sciences Technologie",
    "wof:placetype":"venue"
},
  "geometry": {"coordinates":[-86.77915,33.4132],"type":"Point"}
}