{
  "type": "Feature",
  "properties": {
    "iso:country":"US",
    "sg:address":"2917 Riverview Rd",
    "sg:city":"Birmingham",
    "sg:classifiers":[
        {
            "category":"Building & Trades",
            "subcategory":"Construction",
            "type":"Services"
        }
    ],
    "sg:phone":"+1 205 991 4414",
    "sg:postcode":"35242",
    "sg:province":"AL",
    "sg:tags":[
        "house"
    ],
    "wof:name":"C H Deason & Company",
    "wof:placetype":"venue"
},
  "geometry": {"coordinates":[-86.719054,33.429569],"type":"Point"}
}