{
  "type": "Feature",
  "properties": {
    "iso:country":"US",
    "sg:address":"316 Knight Ave",
    "sg:city":"Roanoke",
    "sg:classifiers":[
        {
            "category":"Wholesale",
            "subcategory":"Electrical",
            "type":"Manufacturing & Wholesale Goods"
        }
    ],
    "sg:phone":"+1 334 863 5800",
    "sg:postcode":"36274",
    "sg:province":"AL",
    "sg:tags":[
        "electronic"
    ],
    "wof:name":"Ruric Inc",
    "wof:placetype":"venue"
},
  "geometry": {"coordinates":[-85.372187,33.154525],"type":"Point"}
}