{
  "type": "Feature",
  "properties": {
    "addr:full":"1234 Union Grove Rd Adamsville AL 35005",
    "addr:housenumber":"1234",
    "addr:postcode":"35005",
    "addr:street":"Union Grove Rd",
    "iso:country":"US",
    "sg:address":"1234 Union Grove Rd",
    "sg:city":"Adamsville",
    "sg:classifiers":[
        {
            "category":"Food & Beverages",
            "subcategory":"Groceries & Convenience Stores",
            "type":"Retail Goods"
        }
    ],
    "sg:phone":"+1 205 674 2717",
    "sg:postcode":"35005",
    "sg:province":"AL",
    "wof:name":"Mosley Mart",
    "wof:placetype":"venue"
},
  "geometry": {"coordinates":[-86.98309,33.597252],"type":"Point"}
}