{
  "type": "Feature",
  "properties": {
    "addr:full":"501 S Brundidge St Troy AL 36081",
    "addr:housenumber":"501",
    "addr:postcode":"36081",
    "addr:street":"S Brundidge St",
    "iso:country":"US",
    "sg:address":"501 S Brundidge St",
    "sg:city":"Troy",
    "sg:classifiers":[
        {
            "category":"Autos & Motor Vehicles",
            "subcategory":"Auto Supplies",
            "type":"Retail Goods"
        }
    ],
    "sg:phone":"+1 334 670 0019",
    "sg:postcode":"36081",
    "sg:province":"AL",
    "sg:tags":[
        "tire"
    ],
    "wof:name":"Expert Tire",
    "wof:placetype":"venue"
},
  "geometry": {"coordinates":[-85.96673699999999,31.80344],"type":"Point"}
}