{
  "type": "Feature",
  "properties": {
    "addr:full":"396 W Oxmoor Rd Birmingham AL 35209",
    "addr:housenumber":"396",
    "addr:postcode":"35209",
    "addr:street":"W Oxmoor Rd",
    "iso:country":"US",
    "sg:address":"396 W Oxmoor Rd",
    "sg:city":"Birmingham",
    "sg:classifiers":[
        {
            "category":"Health Services",
            "subcategory":"Clinic",
            "type":"Services"
        }
    ],
    "sg:phone":"+1 205 943 6000",
    "sg:postcode":"35209",
    "sg:province":"AL",
    "sg:tags":[
        "banks",
        "blood",
        "center"
    ],
    "sg:website":"www.lifesouth.org",
    "wof:name":"Lifesouth Community Blood Ctr",
    "wof:placetype":"venue"
},
  "geometry": {"coordinates":[-86.843784,33.436614],"type":"Point"}
}