{
  "type": "Feature",
  "properties": {
    "addr:full":"2022 6th Ave SE Decatur AL 35601",
    "addr:housenumber":"2022",
    "addr:postcode":"35601",
    "addr:street":"6Th Ave Se",
    "iso:country":"US",
    "sg:address":"2022 6th Ave SE",
    "sg:city":"Decatur",
    "sg:classifiers":[
        {
            "category":"Professional",
            "subcategory":"Detective & Security Services",
            "type":"Services"
        }
    ],
    "sg:phone":"+1 256 350 6681",
    "sg:postcode":"35601",
    "sg:province":"AL",
    "sg:tags":[
        "car",
        "guard",
        "patrol"
    ],
    "wof:name":"Murray Guard Inc",
    "wof:placetype":"venue"
},
  "geometry": {"coordinates":[-86.973296,34.572817],"type":"Point"}
}