{
  "type": "Feature",
  "properties": {
    "iso:country":"US",
    "sg:address":"29550 Mason Woodfin Rd",
    "sg:city":"Harvest",
    "sg:classifiers":[
        {
            "category":"Autos & Motor Vehicles",
            "subcategory":"Fuel & Gas Station",
            "type":"Retail Goods"
        }
    ],
    "sg:phone":"+1 256 722 8041",
    "sg:postcode":"35749",
    "sg:province":"AL",
    "sg:tags":[
        "automotive",
        "station",
        "gasoline"
    ],
    "wof:name":"Pattersons Towing",
    "wof:placetype":"venue"
},
  "geometry": {"coordinates":[-86.787031,34.845471],"type":"Point"}
}