{
  "type": "Feature",
  "properties": {
    "addr:full":"13078 Co Rd 16 Maplesville AL 36750",
    "addr:housenumber":"13078;16",
    "addr:postcode":"36750",
    "addr:street":"Co Rd",
    "iso:country":"US",
    "sg:address":"13078 Co Rd 16",
    "sg:city":"Maplesville",
    "sg:classifiers":[
        {
            "category":"Organizations",
            "subcategory":"Religious Organization",
            "type":"Services"
        }
    ],
    "sg:phone":"+1 334 366 4610",
    "sg:postcode":"36750",
    "sg:province":"AL",
    "wof:name":"Mount Crmel No 2 Baptst Church",
    "wof:placetype":"venue"
},
  "geometry": {"coordinates":[-86.832622,32.739315],"type":"Point"}
}