{
  "type": "Feature",
  "properties": {
    "iso:country":"US",
    "sg:address":"584 Oliver Rd",
    "sg:city":"Montgomery",
    "sg:classifiers":[
        {
            "category":"Professional",
            "subcategory":"Business Services",
            "type":"Services"
        }
    ],
    "sg:phone":"+1 334 277 9927",
    "sg:postcode":"36117",
    "sg:province":"AL",
    "wof:name":"Flooring Services Inc",
    "wof:placetype":"venue"
},
  "geometry": {"coordinates":[-86.208748,32.394474],"type":"Point"}
}