{
  "type": "Feature",
  "properties": {
    "iso:country":"US",
    "sg:address":"25325 US Hwy 98",
    "sg:city":"Daphne",
    "sg:classifiers":[
        {
            "category":"Food & Beverages",
            "subcategory":"Groceries & Convenience Stores",
            "type":"Retail Goods"
        },
        {
            "category":"Food & Beverages",
            "subcategory":"Specialty",
            "type":"Retail Goods"
        }
    ],
    "sg:phone":"+1 251 621 0600",
    "sg:postcode":"36526",
    "sg:province":"AL",
    "sg:tags":[
        "health",
        "diet"
    ],
    "wof:name":"Squash Blossom Market",
    "wof:placetype":"venue"
},
  "geometry": {"coordinates":[-87.898273,30.593551],"type":"Point"}
}