{
  "type": "Feature",
  "properties": {
    "addr:full":"2060 N Country Club Dr Montgomery AL 36106",
    "addr:housenumber":"2060",
    "addr:postcode":"36106",
    "addr:street":"N Country Club Dr",
    "iso:country":"US",
    "sg:address":"2060 N Country Club Dr",
    "sg:city":"Montgomery",
    "sg:classifiers":[
        {
            "category":"Health Services",
            "subcategory":"Nursing And Care Facility",
            "type":"Services"
        }
    ],
    "sg:phone":"+1 334 264 2039",
    "sg:postcode":"36106",
    "sg:province":"AL",
    "sg:tags":[
        "lease",
        "manages",
        "owns",
        "operates"
    ],
    "wof:name":"James T Williams Education Ctr",
    "wof:placetype":"venue"
},
  "geometry": {"coordinates":[-86.279319,32.358364],"type":"Point"}
}