{
  "type": "Feature",
  "properties": {
    "addr:full":"106 Dorman Ave Tallassee AL 36078",
    "addr:housenumber":"106",
    "addr:postcode":"36078",
    "addr:street":"Dorman Ave",
    "iso:country":"US",
    "sg:address":"106 Dorman Ave",
    "sg:city":"Tallassee",
    "sg:classifiers":[
        {
            "category":"Travel",
            "subcategory":"Travel Agent",
            "type":"Entertainment"
        }
    ],
    "sg:phone":"+1 334 252 0031",
    "sg:postcode":"36078",
    "sg:province":"AL",
    "sg:tags":[
        "operator",
        "tour"
    ],
    "wof:name":"Ad Tours",
    "wof:placetype":"venue"
},
  "geometry": {"coordinates":[-85.87911200000001,32.534149],"type":"Point"}
}