{
  "type": "Feature",
  "properties": {
    "iso:country":"US",
    "sg:address":"24022 Canal Rd",
    "sg:city":"Orange Beach",
    "sg:classifiers":[
        {
            "category":"Professional",
            "type":"Services"
        },
        {
            "category":"Shopping",
            "subcategory":"Bicycles & Sporting Goods",
            "type":"Retail Goods"
        }
    ],
    "sg:phone":"+1 251 981 6508",
    "sg:postcode":"36561",
    "sg:province":"AL",
    "sg:tags":[
        "tackle",
        "fishing"
    ],
    "wof:name":"Rod Room",
    "wof:placetype":"venue"
},
  "geometry": {"coordinates":[-87.619275,30.290194],"type":"Point"}
}