{
  "type": "Feature",
  "properties": {
    "iso:country":"US",
    "sg:address":"115 Stadium Dr",
    "sg:city":"Cleveland",
    "sg:classifiers":[
        {
            "category":"Education",
            "subcategory":"School",
            "type":"Public Place"
        }
    ],
    "sg:phone":"+1 205 274 2223",
    "sg:postcode":"35049",
    "sg:province":"AL",
    "sg:website":"www.blountcountyschools.net",
    "wof:name":"Cleveland Elementary School",
    "wof:placetype":"venue"
},
  "geometry": {"coordinates":[-86.57261800000001,33.994704],"type":"Point"}
}