{
  "type": "Feature",
  "properties": {
    "addr:full":"604 Geneva Ave Muscle Shoals AL 35661",
    "addr:housenumber":"604",
    "addr:postcode":"35661",
    "addr:street":"Geneva Ave",
    "iso:country":"US",
    "sg:address":"604 Geneva Ave",
    "sg:city":"Muscle Shoals",
    "sg:classifiers":[
        {
            "category":"Insurance",
            "subcategory":"Insurance Agent",
            "type":"Services"
        }
    ],
    "sg:phone":"+1 256 389 8454",
    "sg:postcode":"35661",
    "sg:province":"AL",
    "wof:name":"Jerry Freeman Cotton States",
    "wof:placetype":"venue"
},
  "geometry": {"coordinates":[-87.66540000000001,34.758442],"type":"Point"}
}