{
  "type": "Feature",
  "properties": {
    "iso:country":"US",
    "sg:address":"1509 Gault Ave N",
    "sg:city":"Fort Payne",
    "sg:classifiers":[
        {
            "category":"Food & Beverages",
            "subcategory":"Groceries & Convenience Stores",
            "type":"Retail Goods"
        }
    ],
    "sg:phone":"+1 256 997 0375",
    "sg:postcode":"35967",
    "sg:province":"AL",
    "wof:name":"Don Rojo Grocery",
    "wof:placetype":"venue"
},
  "geometry": {"coordinates":[-85.709542,34.45594],"type":"Point"}
}