{
  "type": "Feature",
  "properties": {
    "iso:country":"US",
    "sg:address":"9150 State Rte 77",
    "sg:city":"Ohatchee",
    "sg:classifiers":[
        {
            "category":"Organizations",
            "subcategory":"Religious Organization",
            "type":"Services"
        }
    ],
    "sg:phone":"+1 256 892 4645",
    "sg:postcode":"36271",
    "sg:province":"AL",
    "wof:name":"Ten Island Baptist Church",
    "wof:placetype":"venue"
},
  "geometry": {"coordinates":[-86.036365,33.80216],"type":"Point"}
}