{
  "type": "Feature",
  "properties": {
    "iso:country":"US",
    "sg:address":"646 W Carroll St",
    "sg:city":"Dothan",
    "sg:classifiers":[
        {
            "category":"Retail",
            "subcategory":"Repair Shop",
            "type":"Services"
        },
        {
            "category":"Building & Trades",
            "subcategory":"Construction",
            "type":"Services"
        }
    ],
    "sg:phone":"+1 334 702 1642",
    "sg:postcode":"36301",
    "sg:province":"AL",
    "sg:tags":[
        "ironwork",
        "contractor"
    ],
    "wof:name":"Smith's Custom Ironworks",
    "wof:placetype":"venue"
},
  "geometry": {"coordinates":[-85.40674799999999,31.199293],"type":"Point"}
}