{
  "type": "Feature",
  "properties": {
    "addr:full":"118 W Walnut St Troy AL 36081",
    "addr:housenumber":"118",
    "addr:postcode":"36081",
    "addr:street":"W Walnut St",
    "iso:country":"US",
    "sg:address":"118 W Walnut St",
    "sg:city":"Troy",
    "sg:classifiers":[
        {
            "category":"Building & Trades",
            "subcategory":"Construction",
            "type":"Services"
        }
    ],
    "sg:phone":"+1 334 566 2561",
    "sg:postcode":"36081",
    "sg:province":"AL",
    "sg:tags":[
        "maintenance",
        "contractor"
    ],
    "wof:name":"Troy Comercial Bldg Mntnc LLC",
    "wof:placetype":"venue"
},
  "geometry": {"coordinates":[-85.97234400000001,31.808495],"type":"Point"}
}