{
  "type": "Feature",
  "properties": {
    "addr:full":"2290 Paul Bear Bryant Rd Alpine AL 35014",
    "addr:housenumber":"2290",
    "addr:postcode":"35014",
    "addr:street":"Paul Bear Bryant Rd",
    "iso:country":"US",
    "sg:address":"2290 Paul Bear Bryant Rd",
    "sg:city":"Alpine",
    "sg:classifiers":[
        {
            "category":"Travel",
            "subcategory":"Campground",
            "type":"Entertainment"
        }
    ],
    "sg:phone":"+1 256 268 2007",
    "sg:postcode":"35014",
    "sg:province":"AL",
    "sg:tags":[
        "camp"
    ],
    "sg:website":"www.campcosby.org",
    "wof:name":"YMCA Camp Cosby",
    "wof:placetype":"venue"
},
  "geometry": {"coordinates":[-86.277046,33.442285],"type":"Point"}
}