{
  "type": "Feature",
  "properties": {
    "addr:full":"805 Shenandoah Rd Hamilton AL 35570",
    "addr:housenumber":"805",
    "addr:postcode":"35570",
    "addr:street":"Shenandoah Rd",
    "iso:country":"US",
    "sg:address":"805 Shenandoah Rd",
    "sg:city":"Hamilton",
    "sg:classifiers":[
        {
            "category":"Building & Trades",
            "subcategory":"Electrical",
            "type":"Services"
        }
    ],
    "sg:phone":"+1 205 921 4242",
    "sg:postcode":"35570",
    "sg:province":"AL",
    "sg:tags":[
        "electrical",
        "contractor"
    ],
    "wof:name":"Young Electric Co",
    "wof:placetype":"venue"
},
  "geometry": {"coordinates":[-87.904169,34.126015],"type":"Point"}
}