{
  "type": "Feature",
  "properties": {
    "addr:full":"18180 Co Rd 12 S Foley AL 36535",
    "addr:housenumber":"18180;12",
    "addr:postcode":"36535",
    "addr:street":"Co Rd;S Foley",
    "iso:country":"US",
    "sg:address":"18180 Co Rd 12 S",
    "sg:city":"Foley",
    "sg:classifiers":[
        {
            "category":"Wholesale",
            "subcategory":"Hardware",
            "type":"Manufacturing & Wholesale Goods"
        }
    ],
    "sg:phone":"+1 251 970 1110",
    "sg:postcode":"36535",
    "sg:province":"AL",
    "sg:tags":[
        "refrigerating"
    ],
    "wof:name":"A & A Refrigeration & Food Svc",
    "wof:placetype":"venue"
},
  "geometry": {"coordinates":[-87.714572,30.35558],"type":"Point"}
}