{
  "type": "Feature",
  "properties": {
    "iso:country":"US",
    "sg:address":"1218 Co Rd 61",
    "sg:city":"Spruce Pine",
    "sg:classifiers":[
        {
            "category":"Farming",
            "subcategory":"Farm",
            "type":"Manufacturing & Wholesale Goods"
        }
    ],
    "sg:phone":"+1 256 332 9956",
    "sg:postcode":"35585",
    "sg:province":"AL",
    "sg:tags":[
        "crop",
        "general"
    ],
    "wof:name":"Lazy T Farms",
    "wof:placetype":"venue"
},
  "geometry": {"coordinates":[-87.790664,34.435285],"type":"Point"}
}