{
  "type": "Feature",
  "properties": {
    "iso:country":"US",
    "sg:address":"2630 19th St N",
    "sg:city":"Bessemer",
    "sg:classifiers":[
        {
            "category":"Retail",
            "subcategory":"Repair Shop",
            "type":"Services"
        }
    ],
    "sg:phone":"+1 205 497 3532",
    "sg:postcode":"35023",
    "sg:province":"AL",
    "wof:name":"Hueytown Custom",
    "wof:placetype":"venue"
},
  "geometry": {"coordinates":[-86.983941,33.419987],"type":"Point"}
}