{
  "type": "Feature",
  "properties": {
    "iso:country":"US",
    "sg:address":"4407 Danville Rd SW",
    "sg:city":"Decatur",
    "sg:classifiers":[
        {
            "category":"Building & Trades",
            "subcategory":"Plumbing",
            "type":"Services"
        }
    ],
    "sg:phone":"+1 256 350 1240",
    "sg:postcode":"35603",
    "sg:province":"AL",
    "sg:tags":[
        "contractor"
    ],
    "wof:name":"Shelton Heating & Air",
    "wof:placetype":"venue"
},
  "geometry": {"coordinates":[-87.014606,34.522679],"type":"Point"}
}