{
  "type": "Feature",
  "properties": {
    "iso:country":"US",
    "sg:address":"97 Hughes Rd",
    "sg:city":"Madison",
    "sg:classifiers":[
        {
            "category":"Tea Room",
            "subcategory":"None",
            "type":"Food & Drink"
        },
        {
            "category":"Coffee & Tea",
            "type":"Food & Drink"
        }
    ],
    "sg:phone":"+1 256 461 6388",
    "sg:postcode":"35758",
    "sg:province":"AL",
    "sg:tags":[
        "espresso",
        "restaurant"
    ],
    "wof:name":"Kenny Mango's Coffee",
    "wof:placetype":"venue"
},
  "geometry": {"coordinates":[-86.74163799999999,34.698269],"type":"Point"}
}