{
  "type": "Feature",
  "properties": {
    "addr:full":"2501 Mastin Lake Rd NW Huntsville AL 35810",
    "addr:housenumber":"2501",
    "addr:postcode":"35810",
    "addr:street":"Mastin Lake Rd Nw",
    "iso:country":"US",
    "sg:address":"2501 Mastin Lake Rd NW",
    "sg:city":"Huntsville",
    "sg:classifiers":[
        {
            "category":"Government",
            "subcategory":"Post Office",
            "type":"Public Place"
        }
    ],
    "sg:phone":"+1 256 852 7094",
    "sg:postcode":"35810",
    "sg:province":"AL",
    "sg:tags":[
        "postal",
        "us"
    ],
    "wof:name":"Mastin Lake Station",
    "wof:placetype":"venue"
},
  "geometry": {"coordinates":[-86.596625,34.772182],"type":"Point"}
}