{
  "type": "Feature",
  "properties": {
    "addr:full":"500 E Avalon Ave Muscle Shoals AL 35661",
    "addr:housenumber":"500",
    "addr:postcode":"35661",
    "addr:street":"E Avalon Ave",
    "iso:country":"US",
    "sg:address":"500 E Avalon Ave",
    "sg:city":"Muscle Shoals",
    "sg:classifiers":[
        {
            "category":"Restaurant",
            "type":"Food & Drink"
        }
    ],
    "sg:phone":"+1 256 383 4325",
    "sg:postcode":"35661",
    "sg:province":"AL",
    "wof:name":"China House",
    "wof:placetype":"venue"
},
  "geometry": {"coordinates":[-87.69549000000001,34.745221],"type":"Point"}
}