{
  "type": "Feature",
  "properties": {
    "iso:country":"US",
    "sg:address":"3737 Government Blvd",
    "sg:city":"Mobile",
    "sg:classifiers":[
        {
            "category":"Building & Trades",
            "subcategory":"Construction",
            "type":"Services"
        }
    ],
    "sg:phone":"+1 251 666 0265",
    "sg:postcode":"36693",
    "sg:province":"AL",
    "sg:tags":[
        "contractor"
    ],
    "wof:name":"L K Crenshaw Construction Co",
    "wof:placetype":"venue"
},
  "geometry": {"coordinates":[-88.13311,30.643594],"type":"Point"}
}