{
  "type": "Feature",
  "properties": {
    "iso:country":"US",
    "sg:address":"1818 Lake St",
    "sg:city":"Montgomery",
    "sg:classifiers":[
        {
            "category":"Social Services",
            "subcategory":"Child Care",
            "type":"Services"
        }
    ],
    "sg:phone":"+1 334 834 1144",
    "sg:postcode":"36104",
    "sg:province":"AL",
    "wof:name":"Motherly Care Family Svc",
    "wof:placetype":"venue"
},
  "geometry": {"coordinates":[-86.285279,32.370278],"type":"Point"}
}