{
  "type": "Feature",
  "properties": {
    "addr:full":"6371 S Chalkville Rd Trussville AL 35173",
    "addr:housenumber":"6371",
    "addr:postcode":"35173",
    "addr:street":"S Chalkville Rd",
    "iso:country":"US",
    "sg:address":"6371 S Chalkville Rd",
    "sg:city":"Trussville",
    "sg:classifiers":[
        {
            "category":"Autos & Motor Vehicles",
            "subcategory":"Auto Supplies",
            "type":"Retail Goods"
        }
    ],
    "sg:phone":"+1 205 655 2447",
    "sg:postcode":"35173",
    "sg:province":"AL",
    "wof:name":"NAPA Trussville Parts",
    "wof:placetype":"venue"
},
  "geometry": {"coordinates":[-86.607339,33.615935],"type":"Point"}
}