{
  "type": "Feature",
  "properties": {
    "iso:country":"US",
    "sg:address":"9445 Co Rd 279",
    "sg:city":"Valley",
    "sg:classifiers":[
        {
            "category":"Wholesale",
            "subcategory":"Auto Parts",
            "type":"Manufacturing & Wholesale Goods"
        }
    ],
    "sg:phone":"+1 334 749 3096",
    "sg:postcode":"36854",
    "sg:province":"AL",
    "sg:tags":[
        "automobile",
        "rebuilt"
    ],
    "wof:name":"Larry's Auto Parts & Access",
    "wof:placetype":"venue"
},
  "geometry": {"coordinates":[-85.19707,32.694474],"type":"Point"}
}