{
  "type": "Feature",
  "properties": {
    "iso:country":"US",
    "sg:address":"3363 State Rte 10",
    "sg:city":"Camden",
    "sg:classifiers":[
        {
            "category":"Building & Trades",
            "subcategory":"Construction",
            "type":"Services"
        }
    ],
    "sg:phone":"+1 334 682 4779",
    "sg:postcode":"36726",
    "sg:province":"AL",
    "sg:tags":[
        "heavy"
    ],
    "wof:name":"Dan Dailey Construction Inc",
    "wof:placetype":"venue"
},
  "geometry": {"coordinates":[-87.205607,31.976559],"type":"Point"}
}