{
  "type": "Feature",
  "properties": {
    "iso:country":"US",
    "sg:address":"92 Wildberry Ln",
    "sg:city":"Wetumpka",
    "sg:classifiers":[
        {
            "category":"Professional",
            "subcategory":"Business Services",
            "type":"Services"
        }
    ],
    "sg:phone":"+1 334 567 7610",
    "sg:postcode":"36092",
    "sg:province":"AL",
    "wof:name":"A-1 Pools",
    "wof:placetype":"venue"
},
  "geometry": {"coordinates":[-86.295568,32.568203],"type":"Point"}
}