{
  "type": "Feature",
  "properties": {
    "iso:country":"US",
    "sg:address":"2640 Creekview Dr",
    "sg:city":"Birmingham",
    "sg:classifiers":[
        {
            "category":"Professional",
            "subcategory":"Management & Consulting",
            "type":"Services"
        }
    ],
    "sg:phone":"+1 205 979 8362",
    "sg:postcode":"35226",
    "sg:province":"AL",
    "sg:tags":[
        "public",
        "relations"
    ],
    "wof:name":"Paul Lemay",
    "wof:placetype":"venue"
},
  "geometry": {"coordinates":[-86.812788,33.406989],"type":"Point"}
}