{
  "type": "Feature",
  "properties": {
    "addr:full":"240 Oxmoor Cir Birmingham AL 35209",
    "addr:housenumber":"240",
    "addr:postcode":"35209",
    "addr:street":"Oxmoor Cir",
    "iso:country":"US",
    "sg:address":"240 Oxmoor Cir",
    "sg:city":"Birmingham",
    "sg:classifiers":[
        {
            "category":"Restaurant",
            "type":"Food & Drink"
        }
    ],
    "sg:phone":"+1 205 942 7294",
    "sg:postcode":"35209",
    "sg:province":"AL",
    "wof:name":"Sneaky Petes",
    "wof:placetype":"venue"
},
  "geometry": {"coordinates":[-86.837343,33.453132],"type":"Point"}
}