{
  "type": "Feature",
  "properties": {
    "iso:country":"US",
    "sg:address":"222 S Dearborn St",
    "sg:city":"Mobile",
    "sg:classifiers":[
        {
            "category":"Professional",
            "subcategory":"Lawyer & Legal Services",
            "type":"Services"
        }
    ],
    "sg:phone":"+1 251 433 1948",
    "sg:postcode":"36602",
    "sg:province":"AL",
    "sg:tags":[
        "attorney"
    ],
    "wof:name":"Bert P Noojin",
    "wof:placetype":"venue"
},
  "geometry": {"coordinates":[-88.04853900000001,30.685242],"type":"Point"}
}