{
  "type": "Feature",
  "properties": {
    "iso:country":"US",
    "sg:address":"3100 Opelika Rd",
    "sg:city":"Phenix City",
    "sg:classifiers":[
        {
            "category":"Autos & Motor Vehicles",
            "subcategory":"Automobile Sales",
            "type":"Retail Goods"
        }
    ],
    "sg:phone":"+1 334 298 9292",
    "sg:postcode":"36870",
    "sg:province":"AL",
    "sg:tags":[
        "car",
        "dealer"
    ],
    "wof:name":"Ace Affordable Car Enterprise",
    "wof:placetype":"venue"
},
  "geometry": {"coordinates":[-85.042425,32.49118],"type":"Point"}
}