{
  "type": "Feature",
  "properties": {
    "iso:country":"US",
    "sg:address":"1627 Opelika Rd",
    "sg:city":"Auburn",
    "sg:classifiers":[
        {
            "category":"Shopping",
            "subcategory":"Clothing, Apparel, & Fashions",
            "type":"Retail Goods"
        }
    ],
    "sg:phone":"+1 334 501 9383",
    "sg:postcode":"36830",
    "sg:province":"AL",
    "sg:tags":[
        "sportswear"
    ],
    "wof:name":"Aeropostale Inc",
    "wof:placetype":"venue"
},
  "geometry": {"coordinates":[-85.447875,32.624182],"type":"Point"}
}