{
  "type": "Feature",
  "properties": {
    "addr:full":"5955 Old Shell Rd Mobile AL 36608",
    "addr:housenumber":"5955",
    "addr:postcode":"36608",
    "addr:street":"Old Shell Rd",
    "iso:country":"US",
    "sg:address":"5955 Old Shell Rd",
    "sg:city":"Mobile",
    "sg:classifiers":[
        {
            "category":"Restaurant",
            "type":"Food & Drink"
        }
    ],
    "sg:phone":"+1 251 344 9899",
    "sg:postcode":"36608",
    "sg:province":"AL",
    "wof:name":"Picklefish",
    "wof:placetype":"venue"
},
  "geometry": {"coordinates":[-88.180385,30.689966],"type":"Point"}
}