{
  "type": "Feature",
  "properties": {
    "iso:country":"US",
    "sg:address":"1801 Broad Ave",
    "sg:city":"Lanett",
    "sg:classifiers":[
        {
            "category":"Shopping",
            "subcategory":"Computers & Home Electronics",
            "type":"Retail Goods"
        }
    ],
    "sg:phone":"+1 334 644 3687",
    "sg:postcode":"36863",
    "sg:province":"AL",
    "sg:tags":[
        "software"
    ],
    "wof:name":"Southern Internet",
    "wof:placetype":"venue"
},
  "geometry": {"coordinates":[-85.190998,32.853507],"type":"Point"}
}