{
  "type": "Feature",
  "properties": {
    "iso:country":"US",
    "sg:address":"303 Jordan Ln NW",
    "sg:city":"Huntsville",
    "sg:classifiers":[
        {
            "category":"Shopping",
            "subcategory":"Clothing, Apparel, & Fashions",
            "type":"Retail Goods"
        }
    ],
    "sg:phone":"+1 256 721 9117",
    "sg:postcode":"35805",
    "sg:province":"AL",
    "sg:tags":[
        "alteration"
    ],
    "wof:name":"Man's Alteration Shop",
    "wof:placetype":"venue"
},
  "geometry": {"coordinates":[-86.627644,34.723163],"type":"Point"}
}