{
  "type": "Feature",
  "properties": {
    "iso:country":"US",
    "sg:address":"4887 Valleydale Rd",
    "sg:city":"Birmingham",
    "sg:classifiers":[
        {
            "category":"Organizations",
            "subcategory":"Religious Organization",
            "type":"Services"
        }
    ],
    "sg:phone":"+1 205 995 9673",
    "sg:postcode":"35242",
    "sg:province":"AL",
    "wof:name":"Shepherd Hills Lutheran Church",
    "wof:placetype":"venue"
},
  "geometry": {"coordinates":[-86.72134800000001,33.392227],"type":"Point"}
}