{
  "type": "Feature",
  "properties": {
    "iso:country":"US",
    "sg:address":"1405 Bonita Ave",
    "sg:city":"Opelika",
    "sg:classifiers":[
        {
            "category":"Building & Trades",
            "subcategory":"Construction",
            "type":"Services"
        }
    ],
    "sg:phone":"+1 334 745 6309",
    "sg:postcode":"36801",
    "sg:province":"AL",
    "sg:tags":[
        "house"
    ],
    "wof:name":"Roberts & Assoc LLC",
    "wof:placetype":"venue"
},
  "geometry": {"coordinates":[-85.39437100000001,32.654182],"type":"Point"}
}