{
  "type": "Feature",
  "properties": {
    "iso:country":"US",
    "sg:address":"3943 Richard Arrington Jr Blvd N",
    "sg:city":"Birmingham",
    "sg:classifiers":[
        {
            "category":"Wholesale",
            "subcategory":"Machinery & Supplies",
            "type":"Manufacturing & Wholesale Goods"
        }
    ],
    "sg:phone":"+1 205 592 6373",
    "sg:postcode":"35234",
    "sg:province":"AL",
    "sg:tags":[
        "equipment",
        "industrial",
        "retail"
    ],
    "wof:name":"Bwmci",
    "wof:placetype":"venue"
},
  "geometry": {"coordinates":[-86.779457,33.540039],"type":"Point"}
}