{
  "type": "Feature",
  "properties": {
    "iso:country":"US",
    "sg:address":"3503 Elamville St",
    "sg:city":"Clio",
    "sg:classifiers":[
        {
            "category":"Wholesale",
            "subcategory":"Farm Supplies",
            "type":"Manufacturing & Wholesale Goods"
        }
    ],
    "sg:phone":"+1 334 397 4812",
    "sg:postcode":"36017",
    "sg:province":"AL",
    "sg:tags":[
        "peanuts"
    ],
    "wof:name":"Farmers Peanut Co Of Clio",
    "wof:placetype":"venue"
},
  "geometry": {"coordinates":[-85.624477,31.687974],"type":"Point"}
}