{
  "type": "Feature",
  "properties": {
    "iso:country":"US",
    "sg:address":"505 Georgian Dr",
    "sg:city":"Mobile",
    "sg:classifiers":[
        {
            "category":"Health Services",
            "subcategory":"Doctor",
            "type":"Services"
        }
    ],
    "sg:phone":"+1 251 342 1644",
    "sg:postcode":"36609",
    "sg:province":"AL",
    "sg:tags":[
        "dentist"
    ],
    "wof:name":"Brown & Woodall",
    "wof:placetype":"venue"
},
  "geometry": {"coordinates":[-88.16658,30.663611],"type":"Point"}
}