{
  "type": "Feature",
  "properties": {
    "addr:full":"15858 US Hwy 231 Union Grove AL 35175",
    "addr:postcode":"15858;35175",
    "addr:street":"Us Hwy 231",
    "iso:country":"US",
    "sg:address":"15858 US Hwy 231",
    "sg:city":"Union Grove",
    "sg:classifiers":[
        {
            "category":"Building & Trades",
            "subcategory":"Construction",
            "type":"Services"
        }
    ],
    "sg:phone":"+1 256 498 3795",
    "sg:postcode":"35175",
    "sg:province":"AL",
    "sg:tags":[
        "contractor"
    ],
    "wof:name":"Metro Glass & Mirror",
    "wof:placetype":"venue"
},
  "geometry": {"coordinates":[-86.56468099999999,34.467253],"type":"Point"}
}