{
  "type": "Feature",
  "properties": {
    "iso:country":"US",
    "sg:address":"2560 McKenzie St",
    "sg:city":"Foley",
    "sg:classifiers":[
        {
            "category":"Home & Garden",
            "subcategory":"Building Materials",
            "type":"Retail Goods"
        }
    ],
    "sg:phone":"+1 251 943 7222",
    "sg:postcode":"36535",
    "sg:province":"AL",
    "sg:tags":[
        "door",
        "gate",
        "operating",
        "devices"
    ],
    "wof:name":"Garage USA",
    "wof:placetype":"venue"
},
  "geometry": {"coordinates":[-87.683379,30.37281],"type":"Point"}
}