{
  "type": "Feature",
  "properties": {
    "addr:full":"101 Woods Cove Rd Scottsboro AL 35768",
    "addr:housenumber":"101",
    "addr:postcode":"35768",
    "addr:street":"Woods Cove Rd",
    "iso:country":"US",
    "sg:address":"101 Woods Cove Rd",
    "sg:city":"Scottsboro",
    "sg:classifiers":[
        {
            "category":"Personal",
            "subcategory":"Beauty Salon",
            "type":"Services"
        }
    ],
    "sg:phone":"+1 256 574 3736",
    "sg:postcode":"35768",
    "sg:province":"AL",
    "sg:tags":[
        "shop"
    ],
    "wof:name":"Syble's A-Cut-Above",
    "wof:placetype":"venue"
},
  "geometry": {"coordinates":[-86.043271,34.665066],"type":"Point"}
}