{
  "type": "Feature",
  "properties": {
    "iso:country":"US",
    "sg:address":"2160 Carson Rd",
    "sg:city":"Birmingham",
    "sg:classifiers":[
        {
            "category":"Wholesale",
            "subcategory":"Office Equipment",
            "type":"Manufacturing & Wholesale Goods"
        }
    ],
    "sg:phone":"+1 205 854 3434",
    "sg:postcode":"35215",
    "sg:province":"AL",
    "wof:name":"Advance Copier Services",
    "wof:placetype":"venue"
},
  "geometry": {"coordinates":[-86.70344299999999,33.639377],"type":"Point"}
}