{
  "type": "Feature",
  "properties": {
    "iso:country":"US",
    "sg:address":"1705 Serene Cir",
    "sg:city":"Birmingham",
    "sg:classifiers":[
        {
            "category":"Building & Trades",
            "subcategory":"Pest Control",
            "type":"Services"
        }
    ],
    "sg:phone":"+1 205 853 8490",
    "sg:postcode":"35215",
    "sg:province":"AL",
    "wof:name":"Lady Bug Pest Control",
    "wof:placetype":"venue"
},
  "geometry": {"coordinates":[-86.668089,33.628605],"type":"Point"}
}