{
  "type": "Feature",
  "properties": {
    "iso:country":"US",
    "sg:address":"5890 Valley Rd",
    "sg:city":"Birmingham",
    "sg:classifiers":[
        {
            "category":"Health Services",
            "subcategory":"Doctor",
            "type":"Services"
        }
    ],
    "sg:phone":"+1 205 655 7600",
    "sg:postcode":"35235",
    "sg:province":"AL",
    "wof:name":"Gray Brian MD",
    "wof:placetype":"venue"
},
  "geometry": {"coordinates":[-86.615915,33.639482],"type":"Point"}
}