{
  "type": "Feature",
  "properties": {
    "iso:country":"US",
    "sg:address":"640 US Hwy 31",
    "sg:city":"Garden City",
    "sg:classifiers":[
        {
            "category":"Retail",
            "subcategory":"Repair Shop",
            "type":"Services"
        }
    ],
    "sg:phone":"+1 256 352 1885",
    "sg:postcode":"35077",
    "sg:province":"AL",
    "wof:name":"C & U Upholstery Supplies",
    "wof:placetype":"venue"
},
  "geometry": {"coordinates":[-86.747198,34.024676],"type":"Point"}
}