{
  "type": "Feature",
  "properties": {
    "iso:country":"US",
    "sg:address":"1308 Industrial Dr SE",
    "sg:city":"Hartselle",
    "sg:classifiers":[
        {
            "category":"Wholesale",
            "subcategory":"Construction Materials",
            "type":"Manufacturing & Wholesale Goods"
        }
    ],
    "sg:phone":"+1 256 773 8844",
    "sg:postcode":"35640",
    "sg:province":"AL",
    "sg:tags":[
        "paneling"
    ],
    "wof:name":"Panel Craft Inc",
    "wof:placetype":"venue"
},
  "geometry": {"coordinates":[-86.913707,34.418305],"type":"Point"}
}