{
  "type": "Feature",
  "properties": {
    "iso:country":"US",
    "sg:address":"1422 Ardsley Pl",
    "sg:city":"Birmingham",
    "sg:classifiers":[
        {
            "category":"Building & Trades",
            "subcategory":"Construction",
            "type":"Services"
        }
    ],
    "sg:phone":"+1 205 870 0567",
    "sg:postcode":"35209",
    "sg:province":"AL",
    "sg:tags":[
        "nonresidential"
    ],
    "wof:name":"Brett Wingo",
    "wof:placetype":"venue"
},
  "geometry": {"coordinates":[-86.803637,33.478136],"type":"Point"}
}