{
  "type": "Feature",
  "properties": {
    "iso:country":"US",
    "sg:address":"66 Becky Rd",
    "sg:city":"Dothan",
    "sg:classifiers":[
        {
            "category":"Farming",
            "subcategory":"Farm",
            "type":"Manufacturing & Wholesale Goods"
        }
    ],
    "sg:phone":"+1 334 678 7767",
    "sg:postcode":"36301",
    "sg:province":"AL",
    "wof:name":"B & B Farms",
    "wof:placetype":"venue"
},
  "geometry": {"coordinates":[-85.39994,31.123881],"type":"Point"}
}