{
  "type": "Feature",
  "properties": {
    "iso:country":"US",
    "sg:address":"150 Katie Ln",
    "sg:city":"Hope Hull",
    "sg:classifiers":[
        {
            "category":"Professional",
            "subcategory":"Engineering",
            "type":"Services"
        }
    ],
    "sg:phone":"+1 334 284 6343",
    "sg:postcode":"36043",
    "sg:province":"AL",
    "wof:name":"Hydro-Ngineering Solutions LLC",
    "wof:placetype":"venue"
},
  "geometry": {"coordinates":[-86.345635,32.239988],"type":"Point"}
}