{
  "type": "Feature",
  "properties": {
    "addr:full":"2065 Coliseum Blvd Montgomery AL 36110",
    "addr:housenumber":"2065",
    "addr:postcode":"36110",
    "addr:street":"Coliseum Blvd",
    "iso:country":"US",
    "sg:address":"2065 Coliseum Blvd",
    "sg:city":"Montgomery",
    "sg:classifiers":[
        {
            "category":"Wholesale",
            "subcategory":"Machinery & Supplies",
            "type":"Manufacturing & Wholesale Goods"
        }
    ],
    "sg:phone":"+1 334 244 1699",
    "sg:postcode":"36110",
    "sg:province":"AL",
    "sg:tags":[
        "equipment",
        "establishment"
    ],
    "wof:name":"Lee Beauty Supply",
    "wof:placetype":"venue"
},
  "geometry": {"coordinates":[-86.26870599999999,32.420111],"type":"Point"}
}