{
  "type": "Feature",
  "properties": {
    "addr:full":"3105 Pine Ridge Rd Birmingham AL 35213",
    "addr:housenumber":"3105",
    "addr:postcode":"35213",
    "addr:street":"Pine Ridge Rd",
    "iso:country":"US",
    "sg:address":"3105 Pine Ridge Rd",
    "sg:city":"Birmingham",
    "sg:classifiers":[
        {
            "category":"Professional",
            "subcategory":"Business Services",
            "type":"Services"
        }
    ],
    "sg:phone":"+1 205 870 5586",
    "sg:postcode":"35213",
    "sg:province":"AL",
    "wof:name":"Surgical Solutions LLC",
    "wof:placetype":"venue"
},
  "geometry": {"coordinates":[-86.752349,33.489758],"type":"Point"}
}