{
  "type": "Feature",
  "properties": {
    "addr:full":"1415 Honeysuckle Rd Dothan AL 36305",
    "addr:housenumber":"1415",
    "addr:postcode":"36305",
    "addr:street":"Honeysuckle Rd",
    "iso:country":"US",
    "sg:address":"1415 Honeysuckle Rd",
    "sg:city":"Dothan",
    "sg:classifiers":[
        {
            "category":"Education",
            "subcategory":"Dance Studio",
            "type":"Public Place"
        }
    ],
    "sg:phone":"+1 334 792 6309",
    "sg:postcode":"36305",
    "sg:province":"AL",
    "sg:tags":[
        "instruction",
        "dancing"
    ],
    "wof:name":"Oz Performing Art Ctr",
    "wof:placetype":"venue"
},
  "geometry": {"coordinates":[-85.43519499999999,31.209304],"type":"Point"}
}