{
  "type": "Feature",
  "properties": {
    "addr:full":"17684 State Rte 41 Minter AL 36761",
    "addr:housenumber":"17684",
    "addr:postcode":"36761",
    "addr:street":"State Rte 41 Minter",
    "iso:country":"US",
    "sg:address":"17684 State Rte 41",
    "sg:city":"Minter",
    "sg:classifiers":[
        {
            "category":"Farming",
            "subcategory":"Nursery",
            "type":"Manufacturing & Wholesale Goods"
        }
    ],
    "sg:phone":"+1 334 872 3989",
    "sg:postcode":"36761",
    "sg:province":"AL",
    "sg:tags":[
        "ornamental"
    ],
    "wof:name":"James S Wilkinson Sr Corp",
    "wof:placetype":"venue"
},
  "geometry": {"coordinates":[-87.073673,32.148885],"type":"Point"}
}