{
  "type": "Feature",
  "properties": {
    "iso:country":"US",
    "sg:address":"1420 Dr Martin L King Jr Ave",
    "sg:city":"Mobile",
    "sg:classifiers":[
        {
            "category":"Personal",
            "subcategory":"Beauty Salon",
            "type":"Services"
        }
    ],
    "sg:phone":"+1 251 433 2373",
    "sg:postcode":"36603",
    "sg:province":"AL",
    "sg:tags":[
        "hair"
    ],
    "wof:name":"Reel Time",
    "wof:placetype":"venue"
},
  "geometry": {"coordinates":[-88.069572,30.701528],"type":"Point"}
}