{
  "type": "Feature",
  "properties": {
    "iso:country":"US",
    "sg:address":"1802 Woodland St",
    "sg:city":"Opelika",
    "sg:classifiers":[
        {
            "category":"Professional",
            "subcategory":"Business Services",
            "type":"Services"
        }
    ],
    "sg:phone":"+1 334 745 2306",
    "sg:postcode":"36801",
    "sg:province":"AL",
    "sg:tags":[
        "clothing",
        "family"
    ],
    "wof:name":"JD Powell Enterprises Inc",
    "wof:placetype":"venue"
},
  "geometry": {"coordinates":[-85.372045,32.670741],"type":"Point"}
}