{
  "type": "Feature",
  "properties": {
    "addr:full":"1283 Center Point Pkwy Birmingham AL 35215",
    "addr:housenumber":"1283",
    "addr:postcode":"35215",
    "addr:street":"Center Point Pkwy",
    "iso:country":"US",
    "sg:address":"1283 Center Point Pkwy",
    "sg:city":"Birmingham",
    "sg:classifiers":[
        {
            "category":"Autos & Motor Vehicles",
            "subcategory":"Fuel & Gas Station",
            "type":"Retail Goods"
        }
    ],
    "sg:phone":"+1 205 856 8744",
    "sg:postcode":"35215",
    "sg:province":"AL",
    "wof:name":"Parkway East Exxon",
    "wof:placetype":"venue"
},
  "geometry": {"coordinates":[-86.685097,33.6189],"type":"Point"}
}