{
  "type": "Feature",
  "properties": {
    "iso:country":"US",
    "sg:address":"2110 Williamsburg Way",
    "sg:city":"Birmingham",
    "sg:classifiers":[
        {
            "category":"Professional",
            "subcategory":"Management & Consulting",
            "type":"Services"
        }
    ],
    "sg:phone":"+1 205 879 0985",
    "sg:postcode":"35223",
    "sg:province":"AL",
    "sg:tags":[
        "business"
    ],
    "wof:name":"Weissman Consulting",
    "wof:placetype":"venue"
},
  "geometry": {"coordinates":[-86.784597,33.488624],"type":"Point"}
}