{
  "type": "Feature",
  "properties": {
    "iso:country":"US",
    "sg:address":"406 Co Rd 44",
    "sg:city":"Eldridge",
    "sg:classifiers":[
        {
            "category":"Recreation",
            "type":"Entertainment"
        }
    ],
    "sg:phone":"+1 205 487 6946",
    "sg:postcode":"35554",
    "sg:province":"AL",
    "wof:name":"Horse Shows",
    "wof:placetype":"venue"
},
  "geometry": {"coordinates":[-87.689509,33.845307],"type":"Point"}
}