{
  "type": "Feature",
  "properties": {
    "addr:full":"1038 Commerce Blvd Pelham AL 35124",
    "addr:housenumber":"1038",
    "addr:postcode":"35124",
    "addr:street":"Commerce Blvd",
    "iso:country":"US",
    "sg:address":"1038 Commerce Blvd",
    "sg:city":"Pelham",
    "sg:classifiers":[
        {
            "category":"Building & Trades",
            "subcategory":"Plumbing",
            "type":"Services"
        }
    ],
    "sg:phone":"+1 205 988 3666",
    "sg:postcode":"35124",
    "sg:province":"AL",
    "sg:tags":[
        "plumbing",
        "contractor"
    ],
    "wof:name":"M & M Plumbing Company Inc",
    "wof:placetype":"venue"
},
  "geometry": {"coordinates":[-86.79058999999999,33.335897],"type":"Point"}
}