{
  "type": "Feature",
  "properties": {
    "iso:country":"US",
    "sg:address":"5330 Stadium Trace Pkwy",
    "sg:city":"Birmingham",
    "sg:classifiers":[
        {
            "category":"Professional",
            "subcategory":"Lawyer & Legal Services",
            "type":"Services"
        }
    ],
    "sg:phone":"+1 205 733 1303",
    "sg:postcode":"35244",
    "sg:province":"AL",
    "sg:tags":[
        "attorney"
    ],
    "wof:name":"Anne R Strickland",
    "wof:placetype":"venue"
},
  "geometry": {"coordinates":[-86.850938,33.339754],"type":"Point"}
}