{
  "type": "Feature",
  "properties": {
    "iso:country":"US",
    "sg:address":"5546 Katrix Ln",
    "sg:city":"Pinson",
    "sg:classifiers":[
        {
            "category":"Personal",
            "type":"Services"
        }
    ],
    "sg:phone":"+1 205 223 6197",
    "sg:postcode":"35126",
    "sg:province":"AL",
    "sg:tags":[
        "handyman"
    ],
    "wof:name":"Handyman Improvement & Repair",
    "wof:placetype":"venue"
},
  "geometry": {"coordinates":[-86.645503,33.693678],"type":"Point"}
}