{
  "type": "Feature",
  "properties": {
    "iso:country":"US",
    "sg:address":"6377 State Rte 69",
    "sg:city":"Cullman",
    "sg:classifiers":[
        {
            "category":"Retail",
            "subcategory":"Auto Repair",
            "type":"Services"
        }
    ],
    "sg:phone":"+1 256 796 6459",
    "sg:postcode":"35058",
    "sg:province":"AL",
    "sg:tags":[
        "transmission",
        "general"
    ],
    "wof:name":"Miller's Transmission",
    "wof:placetype":"venue"
},
  "geometry": {"coordinates":[-86.700726,34.241284],"type":"Point"}
}