{
  "type": "Feature",
  "properties": {
    "addr:full":"555 State Rte 75 Albertville AL 35951",
    "addr:housenumber":"555",
    "addr:postcode":"35951",
    "addr:street":"State Rte 75",
    "iso:country":"US",
    "sg:address":"555 State Rte 75",
    "sg:city":"Albertville",
    "sg:classifiers":[
        {
            "category":"Autos & Motor Vehicles",
            "subcategory":"Automobile Sales",
            "type":"Retail Goods"
        }
    ],
    "sg:phone":"+1 256 878 7282",
    "sg:postcode":"35951",
    "sg:province":"AL",
    "sg:tags":[
        "car",
        "dealer"
    ],
    "sg:website":"www.billythrash.com",
    "wof:name":"Billy Thrash Automotive",
    "wof:placetype":"venue"
},
  "geometry": {"coordinates":[-86.19552899999999,34.28077],"type":"Point"}
}