{
  "type": "Feature",
  "properties": {
    "iso:country":"US",
    "sg:address":"7524 Mossy Oak Dr",
    "sg:city":"Montgomery",
    "sg:classifiers":[
        {
            "category":"Professional",
            "type":"Services"
        }
    ],
    "sg:phone":"+1 334 395 8233",
    "sg:postcode":"36117",
    "sg:province":"AL",
    "wof:name":"Alexander Emergency Services P",
    "wof:placetype":"venue"
},
  "geometry": {"coordinates":[-86.142103,32.345798],"type":"Point"}
}