{
  "type": "Feature",
  "properties": {
    "addr:full":"9650 Celeste Rd Saraland AL 36571",
    "addr:housenumber":"9650",
    "addr:postcode":"36571",
    "addr:street":"Celeste Rd",
    "iso:country":"US",
    "sg:address":"9650 Celeste Rd",
    "sg:city":"Saraland",
    "sg:classifiers":[
        {
            "category":"Building & Trades",
            "subcategory":"Construction",
            "type":"Services"
        }
    ],
    "sg:phone":"+1 251 675 5747",
    "sg:postcode":"36571",
    "sg:province":"AL",
    "sg:tags":[
        "general",
        "contractor"
    ],
    "wof:name":"J & J Construction & Mntnc Inc",
    "wof:placetype":"venue"
},
  "geometry": {"coordinates":[-88.12441,30.894091],"type":"Point"}
}