{
  "type": "Feature",
  "properties": {
    "addr:full":"1593 S Eufaula Ave Eufaula AL 36027",
    "addr:housenumber":"1593",
    "addr:postcode":"36027",
    "addr:street":"S Eufaula Ave",
    "iso:country":"US",
    "sg:address":"1593 S Eufaula Ave",
    "sg:city":"Eufaula",
    "sg:classifiers":[
        {
            "category":"Food & Beverages",
            "subcategory":"Specialty",
            "type":"Retail Goods"
        }
    ],
    "sg:phone":"+1 334 616 0060",
    "sg:postcode":"36027",
    "sg:province":"AL",
    "wof:name":"LA Azteca",
    "wof:placetype":"venue"
},
  "geometry": {"coordinates":[-85.156263,31.870874],"type":"Point"}
}