{
  "type": "Feature",
  "properties": {
    "iso:country":"US",
    "sg:address":"10096 Co Rd 55",
    "sg:city":"Cottonwood",
    "sg:classifiers":[
        {
            "category":"Personal",
            "subcategory":"Beauty Salon",
            "type":"Services"
        }
    ],
    "sg:phone":"+1 334 691 3648",
    "sg:postcode":"36320",
    "sg:province":"AL",
    "sg:tags":[
        "shop"
    ],
    "wof:name":"Lindas Style Shop & Glory Tans",
    "wof:placetype":"venue"
},
  "geometry": {"coordinates":[-85.298761,31.059832],"type":"Point"}
}