{
  "type": "Feature",
  "properties": {
    "addr:full":"907 N Broad St Scottsboro AL 35768",
    "addr:housenumber":"907",
    "addr:postcode":"35768",
    "addr:street":"N Broad St",
    "iso:country":"US",
    "sg:address":"907 N Broad St",
    "sg:city":"Scottsboro",
    "sg:classifiers":[
        {
            "category":"Personal",
            "subcategory":"Beauty Salon",
            "type":"Services"
        }
    ],
    "sg:phone":"+1 256 574 1276",
    "sg:postcode":"35768",
    "sg:province":"AL",
    "wof:name":"Designers Hair & Nail Salon",
    "wof:placetype":"venue"
},
  "geometry": {"coordinates":[-86.034904,34.662891],"type":"Point"}
}