{
  "type": "Feature",
  "properties": {
    "iso:country":"US",
    "sg:address":"1805 Main St",
    "sg:city":"Daphne",
    "sg:classifiers":[
        {
            "category":"Manufacturing",
            "subcategory":"Printing",
            "type":"Manufacturing & Wholesale Goods"
        }
    ],
    "sg:phone":"+1 251 626 9300",
    "sg:postcode":"36526",
    "sg:province":"AL",
    "sg:tags":[
        "newspaper"
    ],
    "wof:name":"Bulletin",
    "wof:placetype":"venue"
},
  "geometry": {"coordinates":[-87.90281,30.60394],"type":"Point"}
}