{
  "type": "Feature",
  "properties": {
    "iso:country":"US",
    "sg:address":"2330 Balsam Ave SW",
    "sg:city":"Birmingham",
    "sg:classifiers":[
        {
            "category":"Wholesale",
            "subcategory":"Machinery & Supplies",
            "type":"Manufacturing & Wholesale Goods"
        }
    ],
    "sg:phone":"+1 205 945 1555",
    "sg:postcode":"35211",
    "sg:province":"AL",
    "sg:tags":[
        "tanker",
        "petroleum",
        "parts",
        "trailer"
    ],
    "wof:name":"Werts Welding & Tank Service",
    "wof:placetype":"venue"
},
  "geometry": {"coordinates":[-86.878114,33.460087],"type":"Point"}
}