{
  "type": "Feature",
  "properties": {
    "iso:country":"US",
    "sg:address":"5735 Joyce Ave",
    "sg:city":"Eight Mile",
    "sg:classifiers":[
        {
            "category":"Building & Trades",
            "subcategory":"Construction",
            "type":"Services"
        }
    ],
    "sg:phone":"+1 251 454 4700",
    "sg:postcode":"36613",
    "sg:province":"AL",
    "sg:tags":[
        "painter"
    ],
    "wof:name":"Imms Industrial Coatings Inc",
    "wof:placetype":"venue"
},
  "geometry": {"coordinates":[-88.195688,30.811663],"type":"Point"}
}