{
  "type": "Feature",
  "properties": {
    "iso:country":"US",
    "sg:address":"250 Jake Mintz Rd",
    "sg:city":"Gadsden",
    "sg:classifiers":[
        {
            "category":"Farming",
            "subcategory":"Livestock Farm",
            "type":"Manufacturing & Wholesale Goods"
        },
        {
            "category":"Social Services",
            "type":"Services"
        }
    ],
    "sg:phone":"+1 256 892 0773",
    "sg:postcode":"35905",
    "sg:province":"AL",
    "sg:tags":[
        "organization",
        "welfare",
        "animal",
        "general"
    ],
    "sg:website":"www.bigoak.org",
    "wof:name":"Big Oak Ranch For Boys Inc",
    "wof:placetype":"venue"
},
  "geometry": {"coordinates":[-85.985908,33.872783],"type":"Point"}
}