{
  "type": "Feature",
  "properties": {
    "iso:country":"US",
    "sg:address":"3186 Pelham Pkwy",
    "sg:city":"Pelham",
    "sg:classifiers":[
        {
            "category":"Personal",
            "subcategory":"Shoe Repair & Shine",
            "type":"Services"
        }
    ],
    "sg:phone":"+1 205 663 9919",
    "sg:postcode":"35124",
    "sg:province":"AL",
    "sg:tags":[
        "repairing",
        "parlor",
        "boot"
    ],
    "wof:name":"Cobblestone Shoes & Boots",
    "wof:placetype":"venue"
},
  "geometry": {"coordinates":[-86.81065599999999,33.283266],"type":"Point"}
}