{
  "type": "Feature",
  "properties": {
    "iso:country":"US",
    "sg:address":"337 E Thach Ave",
    "sg:city":"Auburn",
    "sg:classifiers":[
        {
            "category":"Real Estate",
            "subcategory":"Architect",
            "type":"Services"
        }
    ],
    "sg:phone":"+1 334 821 1311",
    "sg:postcode":"36830",
    "sg:province":"AL",
    "wof:name":"Fretwell Architects",
    "wof:placetype":"venue"
},
  "geometry": {"coordinates":[-85.477631,32.604303],"type":"Point"}
}