{
  "type": "Feature",
  "properties": {
    "iso:country":"US",
    "sg:address":"23 Samford Ave",
    "sg:city":"Opelika",
    "sg:classifiers":[
        {
            "category":"Wholesale",
            "subcategory":"Metals & Minerals",
            "type":"Manufacturing & Wholesale Goods"
        }
    ],
    "sg:phone":"+1 334 745 2001",
    "sg:postcode":"36801",
    "sg:province":"AL",
    "sg:tags":[
        "ind",
        "industrial",
        "center",
        "supply"
    ],
    "wof:name":"H & E Steel Wldg & Indus Sup",
    "wof:placetype":"venue"
},
  "geometry": {"coordinates":[-85.37366299999999,32.656061],"type":"Point"}
}