{
  "type": "Feature",
  "properties": {
    "iso:country":"US",
    "sg:address":"1100 23rd St S",
    "sg:city":"Birmingham",
    "sg:classifiers":[
        {
            "category":"Shopping",
            "subcategory":"Optical Goods",
            "type":"Retail Goods"
        }
    ],
    "sg:phone":"+1 205 933 5367",
    "sg:postcode":"35205",
    "sg:province":"AL",
    "wof:name":"Opticians Southside",
    "wof:placetype":"venue"
},
  "geometry": {"coordinates":[-86.790735,33.50336],"type":"Point"}
}