{
  "type": "Feature",
  "properties": {
    "addr:full":"1330 Springhill Ave Mobile AL 36604",
    "addr:housenumber":"1330",
    "addr:postcode":"36604",
    "addr:street":"Springhill Ave",
    "iso:country":"US",
    "sg:address":"1330 Springhill Ave",
    "sg:city":"Mobile",
    "sg:classifiers":[
        {
            "category":"Banks & Credit Unions",
            "subcategory":"Bank",
            "type":"Services"
        }
    ],
    "sg:phone":"+1 251 432 8472",
    "sg:postcode":"36604",
    "sg:province":"AL",
    "sg:tags":[
        "loan"
    ],
    "wof:name":"Title Cash",
    "wof:placetype":"venue"
},
  "geometry": {"coordinates":[-88.067926,30.692672],"type":"Point"}
}