{
  "type": "Feature",
  "properties": {
    "addr:full":"3283 Louisville St Clio AL 36017",
    "addr:housenumber":"3283",
    "addr:postcode":"36017",
    "addr:street":"Louisville St",
    "iso:country":"US",
    "sg:address":"3283 Louisville St",
    "sg:city":"Clio",
    "sg:classifiers":[
        {
            "category":"Home & Garden",
            "subcategory":"Hardware",
            "type":"Retail Goods"
        }
    ],
    "sg:phone":"+1 334 397 2611",
    "sg:postcode":"36017",
    "sg:province":"AL",
    "wof:name":"Tyler's Hardware",
    "wof:placetype":"venue"
},
  "geometry": {"coordinates":[-85.609921,31.710005],"type":"Point"}
}