{
  "type": "Feature",
  "properties": {
    "iso:country":"US",
    "sg:address":"2516 Rocky Ridge Rd",
    "sg:city":"Birmingham",
    "sg:classifiers":[
        {
            "category":"Cinema",
            "subcategory":"Movie Rental",
            "type":"Entertainment"
        }
    ],
    "sg:phone":"+1 205 979 1386",
    "sg:postcode":"35243",
    "sg:province":"AL",
    "sg:tags":[
        "video",
        "store"
    ],
    "wof:name":"Movie Gallery",
    "wof:placetype":"venue"
},
  "geometry": {"coordinates":[-86.772728,33.424521],"type":"Point"}
}