{
  "type": "Feature",
  "properties": {
    "iso:country":"US",
    "sg:address":"1414 Co Rd 445",
    "sg:city":"Collinsville",
    "sg:classifiers":[
        {
            "category":"Farming",
            "subcategory":"Farm & Veterinary Services",
            "type":"Manufacturing & Wholesale Goods"
        }
    ],
    "sg:phone":"+1 256 623 3677",
    "sg:postcode":"35961",
    "sg:province":"AL",
    "sg:tags":[
        "livestock"
    ],
    "wof:name":"Terry Bryant",
    "wof:placetype":"venue"
},
  "geometry": {"coordinates":[-85.862436,34.417178],"type":"Point"}
}