{
  "type": "Feature",
  "properties": {
    "iso:country":"US",
    "sg:address":"940 N Burbank Dr",
    "sg:city":"Montgomery",
    "sg:classifiers":[
        {
            "category":"Utilities",
            "subcategory":"Fuel Oil & Lpg",
            "type":"Services"
        }
    ],
    "sg:phone":"+1 334 272 0056",
    "sg:postcode":"36117",
    "sg:province":"AL",
    "sg:tags":[
        "dealer"
    ],
    "wof:name":"Felts Tree Service",
    "wof:placetype":"venue"
},
  "geometry": {"coordinates":[-86.198122,32.400328],"type":"Point"}
}