{
  "type": "Feature",
  "properties": {
    "iso:country":"US",
    "sg:address":"3330 Messer Airport Hwy",
    "sg:city":"Birmingham",
    "sg:classifiers":[
        {
            "category":"Autos & Motor Vehicles",
            "subcategory":"Automobile Sales",
            "type":"Retail Goods"
        }
    ],
    "sg:phone":"+1 205 326 6170",
    "sg:postcode":"35222",
    "sg:province":"AL",
    "wof:name":"Isuzu Trucks of Birmingham",
    "wof:placetype":"venue"
},
  "geometry": {"coordinates":[-86.788393,33.527318],"type":"Point"}
}