{
  "type": "Feature",
  "properties": {
    "addr:full":"3777 US Hwy 431 Phenix City AL 36867",
    "addr:housenumber":"3777",
    "addr:postcode":"36867",
    "addr:street":"Us Hwy 431 Phenix City Al",
    "iso:country":"US",
    "sg:address":"3777 US Hwy 431",
    "sg:city":"Phenix City",
    "sg:classifiers":[
        {
            "category":"Organizations",
            "subcategory":"Religious Organization",
            "type":"Services"
        }
    ],
    "sg:phone":"+1 334 298 9890",
    "sg:postcode":"36867",
    "sg:province":"AL",
    "sg:tags":[
        "church"
    ],
    "wof:name":"First Assembly Of God",
    "wof:placetype":"venue"
},
  "geometry": {"coordinates":[-85.04986100000001,32.503104],"type":"Point"}
}