{
  "type": "Feature",
  "properties": {
    "iso:country":"US",
    "sg:address":"1015 S Montgomery Ave",
    "sg:city":"Sheffield",
    "sg:classifiers":[
        {
            "category":"Retail",
            "subcategory":"Veterinary Services",
            "type":"Services"
        }
    ],
    "sg:phone":"+1 256 383 2626",
    "sg:postcode":"35660",
    "sg:province":"AL",
    "wof:name":"North Alabama Animal Hospital",
    "wof:placetype":"venue"
},
  "geometry": {"coordinates":[-87.698791,34.748617],"type":"Point"}
}