{
  "type": "Feature",
  "properties": {
    "addr:full":"3128 Co Rd 157 Hamilton AL 35570",
    "addr:housenumber":"3128;157",
    "addr:postcode":"35570",
    "addr:street":"Co Rd",
    "iso:country":"US",
    "sg:address":"3128 Co Rd 157",
    "sg:city":"Hamilton",
    "sg:classifiers":[
        {
            "category":"Manufacturing",
            "subcategory":"Lumber",
            "type":"Manufacturing & Wholesale Goods"
        }
    ],
    "sg:phone":"+1 205 921 4609",
    "sg:postcode":"35570",
    "sg:province":"AL",
    "sg:tags":[
        "company",
        "logging"
    ],
    "wof:name":"Randy Harbor Logging Inc",
    "wof:placetype":"venue"
},
  "geometry": {"coordinates":[-88.09148500000001,34.241831],"type":"Point"}
}