{
  "type": "Feature",
  "properties": {
    "addr:full":"6987 Halcyon Park Dr Montgomery AL 36117",
    "addr:housenumber":"6987",
    "addr:postcode":"36117",
    "addr:street":"Halcyon Park Dr",
    "iso:country":"US",
    "sg:address":"6987 Halcyon Park Dr",
    "sg:city":"Montgomery",
    "sg:classifiers":[
        {
            "category":"Professional",
            "subcategory":"Lawyer & Legal Services",
            "type":"Services"
        }
    ],
    "sg:phone":"+1 334 409 0545",
    "sg:postcode":"36117",
    "sg:province":"AL",
    "sg:tags":[
        "attorney"
    ],
    "wof:name":"Dan W Taliaferro Atty At Law",
    "wof:placetype":"venue"
},
  "geometry": {"coordinates":[-86.17333499999999,32.340261],"type":"Point"}
}