{
  "type": "Feature",
  "properties": {
    "iso:country":"US",
    "sg:address":"22 Westwood St",
    "sg:city":"Mobile",
    "sg:classifiers":[
        {
            "category":"Professional",
            "subcategory":"Computer Services",
            "type":"Services"
        }
    ],
    "sg:phone":"+1 251 473 3378",
    "sg:postcode":"36606",
    "sg:province":"AL",
    "sg:tags":[
        "prepackaged",
        "software"
    ],
    "wof:name":"Bruce Marr",
    "wof:placetype":"venue"
},
  "geometry": {"coordinates":[-88.09387599999999,30.685512],"type":"Point"}
}