{
  "type": "Feature",
  "properties": {
    "iso:country":"US",
    "sg:address":"106 Ivy Chase Dr",
    "sg:city":"Madison",
    "sg:classifiers":[
        {
            "category":"Restaurant",
            "type":"Food & Drink"
        }
    ],
    "sg:phone":"+1 256 461 8082",
    "sg:postcode":"35758",
    "sg:province":"AL",
    "sg:tags":[
        "grill",
        "bar"
    ],
    "wof:name":"Game Day Grill",
    "wof:placetype":"venue"
},
  "geometry": {"coordinates":[-86.780029,34.703541],"type":"Point"}
}