{
  "type": "Feature",
  "properties": {
    "addr:full":"540 Tecumseh Point Rd Eclectic AL 36024",
    "addr:housenumber":"540",
    "addr:postcode":"36024",
    "addr:street":"Tecumseh Point Rd",
    "iso:country":"US",
    "sg:address":"540 Tecumseh Point Rd",
    "sg:city":"Eclectic",
    "sg:classifiers":[
        {
            "category":"Building & Trades",
            "subcategory":"Construction",
            "type":"Services"
        }
    ],
    "sg:phone":"+1 334 857 3185",
    "sg:postcode":"36024",
    "sg:province":"AL",
    "sg:tags":[
        "house",
        "general",
        "contractor"
    ],
    "wof:name":"Willgriff Construction Co Inc",
    "wof:placetype":"venue"
},
  "geometry": {"coordinates":[-85.966971,32.715296],"type":"Point"}
}