{
  "type": "Feature",
  "properties": {
    "iso:country":"US",
    "sg:address":"314 James Rd",
    "sg:city":"Owens Cross Rds",
    "sg:classifiers":[
        {
            "category":"Organizations",
            "subcategory":"Religious Organization",
            "type":"Services"
        }
    ],
    "sg:phone":"+1 256 518 9328",
    "sg:postcode":"35763",
    "sg:province":"AL",
    "sg:tags":[
        "church"
    ],
    "sg:website":"www.newsalembc.com",
    "wof:name":"New Salem Baptist Church",
    "wof:placetype":"venue"
},
  "geometry": {"coordinates":[-86.49294,34.66618],"type":"Point"}
}