{
  "type": "Feature",
  "properties": {
    "iso:country":"US",
    "sg:address":"3659 Lorna Rd",
    "sg:city":"Birmingham",
    "sg:classifiers":[
        {
            "category":"Restaurant",
            "type":"Food & Drink"
        }
    ],
    "sg:phone":"+1 205 988 9112",
    "sg:postcode":"35216",
    "sg:province":"AL",
    "sg:tags":[
        "cafe"
    ],
    "wof:name":"Chefs Cafe",
    "wof:placetype":"venue"
},
  "geometry": {"coordinates":[-86.801244,33.378585],"type":"Point"}
}