{
  "type": "Feature",
  "properties": {
    "addr:full":"6235 State Rte 36 Somerville AL 35670",
    "addr:housenumber":"6235",
    "addr:postcode":"35670",
    "addr:street":"State Rte 36",
    "iso:country":"US",
    "sg:address":"6235 State Rte 36",
    "sg:city":"Somerville",
    "sg:classifiers":[
        {
            "category":"Food & Beverages",
            "subcategory":"Groceries & Convenience Stores",
            "type":"Retail Goods"
        }
    ],
    "sg:phone":"+1 256 778 9776",
    "sg:postcode":"35670",
    "sg:province":"AL",
    "wof:name":"Cotaco Grocery",
    "wof:placetype":"venue"
},
  "geometry": {"coordinates":[-86.69378,34.474761],"type":"Point"}
}