{
  "type": "Feature",
  "properties": {
    "iso:country":"US",
    "sg:address":"3380 Overton Rd",
    "sg:city":"Birmingham",
    "sg:classifiers":[
        {
            "category":"Building & Trades",
            "subcategory":"Construction",
            "type":"Services"
        }
    ],
    "sg:phone":"+1 205 967 6769",
    "sg:postcode":"35223",
    "sg:province":"AL",
    "sg:tags":[
        "contractor"
    ],
    "wof:name":"Alabama Fence LLC",
    "wof:placetype":"venue"
},
  "geometry": {"coordinates":[-86.724585,33.477347],"type":"Point"}
}