{
  "type": "Feature",
  "properties": {
    "addr:full":"887 Glenwood Rd Luverne AL 36049",
    "addr:housenumber":"887",
    "addr:postcode":"36049",
    "addr:street":"Glenwood Rd",
    "iso:country":"US",
    "sg:address":"887 Glenwood Rd",
    "sg:city":"Luverne",
    "sg:classifiers":[
        {
            "category":"Organizations",
            "subcategory":"Religious Organization",
            "type":"Services"
        }
    ],
    "sg:phone":"+1 334 335 6885",
    "sg:postcode":"36049",
    "sg:province":"AL",
    "wof:name":"South Luverne Baptist Church",
    "wof:placetype":"venue"
},
  "geometry": {"coordinates":[-86.25188,31.703673],"type":"Point"}
}