{
  "type": "Feature",
  "properties": {
    "iso:country":"US",
    "sg:address":"1810 Co Rd 41",
    "sg:city":"Russellville",
    "sg:classifiers":[
        {
            "category":"Professional",
            "subcategory":"Business Services",
            "type":"Services"
        }
    ],
    "sg:phone":"+1 256 332 2234",
    "sg:postcode":"35653",
    "sg:province":"AL",
    "wof:name":"Bragwell Enterprises Inc",
    "wof:placetype":"venue"
},
  "geometry": {"coordinates":[-87.851506,34.511448],"type":"Point"}
}