{
  "type": "Feature",
  "properties": {
    "addr:full":"312 Clinton Ave W Huntsville AL 35801",
    "addr:housenumber":"312",
    "addr:postcode":"35801",
    "addr:street":"Clinton Ave W",
    "iso:country":"US",
    "sg:address":"312 Clinton Ave W",
    "sg:city":"Huntsville",
    "sg:classifiers":[
        {
            "category":"Banks & Credit Unions",
            "subcategory":"Bank",
            "type":"Services"
        }
    ],
    "sg:phone":"+1 256 533 5548",
    "sg:postcode":"35801",
    "sg:province":"AL",
    "sg:website":"www.unionplanters.com",
    "wof:name":"Union Planters Bank",
    "wof:placetype":"venue"
},
  "geometry": {"coordinates":[-86.58888,34.730136],"type":"Point"}
}