{
  "type": "Feature",
  "properties": {
    "iso:country":"US",
    "sg:address":"8103 US Hwy 72 Alt",
    "sg:city":"Madison",
    "sg:classifiers":[
        {
            "category":"Real Estate",
            "subcategory":"Real Estate Agent",
            "type":"Services"
        }
    ],
    "sg:phone":"+1 256 830 8900",
    "sg:postcode":"35758",
    "sg:province":"AL",
    "wof:name":"Re/Max Madison",
    "wof:placetype":"venue"
},
  "geometry": {"coordinates":[-86.72133599999999,34.68866],"type":"Point"}
}