{
  "type": "Feature",
  "properties": {
    "iso:country":"US",
    "sg:address":"3500 8th Ave SW",
    "sg:city":"Huntsville",
    "sg:classifiers":[
        {
            "category":"Manufacturing",
            "subcategory":"Retail Goods",
            "type":"Manufacturing & Wholesale Goods"
        },
        {
            "category":"Manufacturing",
            "subcategory":"Printing",
            "type":"Manufacturing & Wholesale Goods"
        }
    ],
    "sg:phone":"+1 256 536 2063",
    "sg:postcode":"35805",
    "sg:province":"AL",
    "sg:tags":[
        "trim",
        "product",
        "co",
        "mfg",
        "screen",
        "lithographic"
    ],
    "wof:name":"Seoloc Screening Incorporated",
    "wof:placetype":"venue"
},
  "geometry": {"coordinates":[-86.614336,34.716881],"type":"Point"}
}