{
  "type": "Feature",
  "properties": {
    "iso:country":"US",
    "sg:address":"2220 White Ave",
    "sg:city":"Gadsden",
    "sg:classifiers":[
        {
            "category":"Health Services",
            "subcategory":"Doctor",
            "type":"Services"
        }
    ],
    "sg:phone":"+1 256 492 0131",
    "sg:postcode":"35904",
    "sg:province":"AL",
    "sg:tags":[
        "physician",
        "surgeon"
    ],
    "wof:name":"Emma Sansom Pro Care",
    "wof:placetype":"venue"
},
  "geometry": {"coordinates":[-86.036818,34.021036],"type":"Point"}
}