{
  "type": "Feature",
  "properties": {
    "iso:country":"US",
    "sg:address":"3310 10th Ct",
    "sg:city":"Phenix City",
    "sg:classifiers":[
        {
            "category":"Organizations",
            "subcategory":"Religious Organization",
            "type":"Services"
        }
    ],
    "sg:phone":"+1 334 297 1537",
    "sg:postcode":"36867",
    "sg:province":"AL",
    "wof:name":"First Presbt Church Phoenix Cy",
    "wof:placetype":"venue"
},
  "geometry": {"coordinates":[-85.008136,32.494845],"type":"Point"}
}