{
  "type": "Feature",
  "properties": {
    "iso:country":"US",
    "sg:address":"3571 Wilmington Rd",
    "sg:city":"Montgomery",
    "sg:classifiers":[
        {
            "category":"Professional",
            "type":"Services"
        }
    ],
    "sg:phone":"+1 334 269 2042",
    "sg:postcode":"36105",
    "sg:province":"AL",
    "wof:name":"Ulysses Robinson",
    "wof:placetype":"venue"
},
  "geometry": {"coordinates":[-86.300713,32.339939],"type":"Point"}
}