{
  "type": "Feature",
  "properties": {
    "addr:full":"12 Will Ave Phenix City AL 36869",
    "addr:housenumber":"12",
    "addr:postcode":"36869",
    "addr:street":"Will Ave Phenix City Al",
    "iso:country":"US",
    "sg:address":"12 Will Ave",
    "sg:city":"Phenix City",
    "sg:classifiers":[
        {
            "category":"Building & Trades",
            "subcategory":"Construction",
            "type":"Services"
        }
    ],
    "sg:phone":"+1 334 480 0535",
    "sg:postcode":"36869",
    "sg:province":"AL",
    "sg:tags":[
        "contractor"
    ],
    "wof:name":"Wayne Denneys Roofing",
    "wof:placetype":"venue"
},
  "geometry": {"coordinates":[-85.088221,32.441984],"type":"Point"}
}