{
  "type": "Feature",
  "properties": {
    "iso:country":"US",
    "sg:address":"5524 Crestwood Blvd",
    "sg:city":"Birmingham",
    "sg:classifiers":[
        {
            "category":"Retail",
            "subcategory":"Auto Repair",
            "type":"Services"
        }
    ],
    "sg:phone":"+1 205 592 8098",
    "sg:postcode":"35212",
    "sg:province":"AL",
    "sg:tags":[
        "automotive",
        "station",
        "gasoline",
        "general"
    ],
    "wof:name":"Chevron",
    "wof:placetype":"venue"
},
  "geometry": {"coordinates":[-86.746938,33.529036],"type":"Point"}
}