{
  "type": "Feature",
  "properties": {
    "iso:country":"US",
    "sg:address":"4320 Blvd Park S",
    "sg:city":"Mobile",
    "sg:classifiers":[
        {
            "category":"Shopping",
            "subcategory":"Computers & Home Electronics",
            "type":"Retail Goods"
        }
    ],
    "sg:phone":"+1 251 343 9595",
    "sg:postcode":"36609",
    "sg:province":"AL",
    "sg:tags":[
        "software"
    ],
    "sg:website":"www.costflex.com",
    "wof:name":"Cost Flex Systems",
    "wof:placetype":"venue"
},
  "geometry": {"coordinates":[-88.162665,30.662199],"type":"Point"}
}