{
  "type": "Feature",
  "properties": {
    "iso:country":"US",
    "sg:address":"6759 Biltmore Ct",
    "sg:city":"Mobile",
    "sg:classifiers":[
        {
            "category":"Building & Trades",
            "subcategory":"Construction",
            "type":"Services"
        }
    ],
    "sg:phone":"+1 251 661 4267",
    "sg:postcode":"36695",
    "sg:province":"AL",
    "sg:tags":[
        "house"
    ],
    "wof:name":"Rdr Construction",
    "wof:placetype":"venue"
},
  "geometry": {"coordinates":[-88.19990300000001,30.638013],"type":"Point"}
}