{
  "type": "Feature",
  "properties": {
    "iso:country":"US",
    "sg:address":"400 Maxwell Rd SE",
    "sg:city":"Bessemer",
    "sg:classifiers":[
        {
            "category":"Personal",
            "type":"Services"
        }
    ],
    "sg:phone":"+1 205 428 7550",
    "sg:postcode":"35022",
    "sg:province":"AL",
    "wof:name":"My Nanny & ME Inc",
    "wof:placetype":"venue"
},
  "geometry": {"coordinates":[-86.882566,33.372496],"type":"Point"}
}