{
  "type": "Feature",
  "properties": {
    "iso:country":"US",
    "sg:address":"1265 Co Rd 162",
    "sg:city":"Centre",
    "sg:phone":"+1 256 475 3398",
    "sg:postcode":"35960",
    "sg:province":"AL",
    "sg:tags":[
        "farm",
        "cotton"
    ],
    "wof:name":"J and J Farms",
    "wof:placetype":"venue"
},
  "geometry": {"coordinates":[-85.49301,34.109315],"type":"Point"}
}