{
  "type": "Feature",
  "properties": {
    "iso:country":"US",
    "sg:address":"714 2nd Ave",
    "sg:city":"Opelika",
    "sg:classifiers":[
        {
            "category":"Travel",
            "subcategory":"Hotels & Motels",
            "type":"Entertainment"
        }
    ],
    "sg:phone":"+1 334 705 0485",
    "sg:postcode":"36801",
    "sg:province":"AL",
    "sg:tags":[
        "breakfast",
        "accommodation",
        "bed"
    ],
    "wof:name":"Heritage House Inn",
    "wof:placetype":"venue"
},
  "geometry": {"coordinates":[-85.381151,32.65024],"type":"Point"}
}