{
  "type": "Feature",
  "properties": {
    "iso:country":"US",
    "sg:address":"2 6th Ave S",
    "sg:city":"Birmingham",
    "sg:classifiers":[
        {
            "category":"Education",
            "subcategory":"Library",
            "type":"Public Place"
        }
    ],
    "sg:phone":"+1 205 583 5093",
    "sg:postcode":"35205",
    "sg:province":"AL",
    "wof:name":"Birmingham Public Library",
    "wof:placetype":"venue"
},
  "geometry": {"coordinates":[-86.83103199999999,33.49258],"type":"Point"}
}