{
  "type": "Feature",
  "properties": {
    "iso:country":"US",
    "sg:address":"170 Persimmon Pl",
    "sg:city":"Thomaston",
    "sg:classifiers":[
        {
            "category":"Freight",
            "type":"Transportation"
        }
    ],
    "sg:phone":"+1 334 627 3777",
    "sg:postcode":"36783",
    "sg:province":"AL",
    "sg:tags":[
        "trucking"
    ],
    "wof:name":"Harmony Hill Trucking",
    "wof:placetype":"venue"
},
  "geometry": {"coordinates":[-87.611786,32.270575],"type":"Point"}
}