{
  "type": "Feature",
  "properties": {
    "addr:full":"7675 US Hwy 78 Dora AL 35062",
    "addr:housenumber":"7675",
    "addr:postcode":"35062",
    "addr:street":"Us Hwy 78 Dora",
    "iso:country":"US",
    "sg:address":"7675 US Hwy 78",
    "sg:city":"Dora",
    "sg:classifiers":[
        {
            "category":"Shopping",
            "subcategory":"Clothing, Apparel, & Fashions",
            "type":"Retail Goods"
        }
    ],
    "sg:phone":"+1 205 648 7944",
    "sg:postcode":"35062",
    "sg:province":"AL",
    "sg:tags":[
        "uniform"
    ],
    "wof:name":"Fashionable School Uniforms",
    "wof:placetype":"venue"
},
  "geometry": {"coordinates":[-87.01955700000001,33.735258],"type":"Point"}
}