{
  "type": "Feature",
  "properties": {
    "iso:country":"US",
    "sg:address":"2701 Martin Luther King Jr Blvd",
    "sg:city":"Tuscaloosa",
    "sg:classifiers":[
        {
            "category":"Retail",
            "subcategory":"Funeral Services",
            "type":"Services"
        }
    ],
    "sg:phone":"+1 205 759 4202",
    "sg:postcode":"35401",
    "sg:province":"AL",
    "wof:name":"Rollins Mortuary Inc",
    "wof:placetype":"venue"
},
  "geometry": {"coordinates":[-87.577478,33.186116],"type":"Point"}
}