{
  "type": "Feature",
  "properties": {
    "iso:country":"US",
    "sg:address":"744 Oliver Rd",
    "sg:city":"Montgomery",
    "sg:classifiers":[
        {
            "category":"Building & Trades",
            "subcategory":"Cleaning & Sanitation",
            "type":"Services"
        }
    ],
    "sg:phone":"+1 334 273 0011",
    "sg:postcode":"36117",
    "sg:province":"AL",
    "sg:tags":[
        "maintenance"
    ],
    "wof:name":"ServiceMaster",
    "wof:placetype":"venue"
},
  "geometry": {"coordinates":[-86.20665200000001,32.399856],"type":"Point"}
}