{
  "type": "Feature",
  "properties": {
    "iso:country":"US",
    "sg:address":"319 S Brundidge St",
    "sg:city":"Troy",
    "sg:classifiers":[
        {
            "category":"Food & Beverages",
            "subcategory":"Bakery",
            "type":"Retail Goods"
        }
    ],
    "sg:phone":"+1 334 807 0680",
    "sg:postcode":"36081",
    "sg:province":"AL",
    "sg:tags":[
        "baker"
    ],
    "wof:name":"Cake House",
    "wof:placetype":"venue"
},
  "geometry": {"coordinates":[-85.968299,31.80632],"type":"Point"}
}