{
  "type": "Feature",
  "properties": {
    "iso:country":"US",
    "sg:address":"2611 Bridge Rd NW",
    "sg:city":"Huntsville",
    "sg:classifiers":[
        {
            "category":"Building & Trades",
            "subcategory":"Plumbing",
            "type":"Services"
        }
    ],
    "sg:phone":"+1 256 851 7081",
    "sg:postcode":"35810",
    "sg:province":"AL",
    "sg:tags":[
        "conditioning",
        "air",
        "system",
        "contractor"
    ],
    "wof:name":"Comfort Air Quality & Eff",
    "wof:placetype":"venue"
},
  "geometry": {"coordinates":[-86.602231,34.766698],"type":"Point"}
}