{
  "type": "Feature",
  "properties": {
    "addr:full":"608 Regency East Dr Birmingham AL 35210",
    "addr:housenumber":"608",
    "addr:postcode":"35210",
    "addr:street":"Regency East Dr",
    "iso:country":"US",
    "sg:address":"608 Regency East Dr",
    "sg:city":"Birmingham",
    "sg:classifiers":[
        {
            "category":"Shopping",
            "subcategory":"Florist",
            "type":"Retail Goods"
        }
    ],
    "sg:phone":"+1 205 951 0103",
    "sg:postcode":"35210",
    "sg:province":"AL",
    "wof:name":"Custom Floral Creations",
    "wof:placetype":"venue"
},
  "geometry": {"coordinates":[-86.692317,33.522093],"type":"Point"}
}