{
  "type": "Feature",
  "properties": {
    "addr:full":"32941 US Hwy 280 Childersburg AL 35044",
    "addr:postcode":"32941;35044",
    "addr:street":"Us Hwy 280",
    "iso:country":"US",
    "sg:address":"32941 US Hwy 280",
    "sg:city":"Childersburg",
    "sg:classifiers":[
        {
            "category":"Professional",
            "subcategory":"Lawyer & Legal Services",
            "type":"Services"
        }
    ],
    "sg:phone":"+1 256 378 7666",
    "sg:postcode":"35044",
    "sg:province":"AL",
    "wof:name":"Rogers & Assoc",
    "wof:placetype":"venue"
},
  "geometry": {"coordinates":[-86.357851,33.274678],"type":"Point"}
}