{
  "type": "Feature",
  "properties": {
    "iso:country":"US",
    "sg:address":"22873 US Hwy 98",
    "sg:city":"Fairhope",
    "sg:classifiers":[
        {
            "category":"Wholesale",
            "subcategory":"Durable Goods & Equipment",
            "type":"Manufacturing & Wholesale Goods"
        }
    ],
    "sg:phone":"+1 251 928 4836",
    "sg:postcode":"36532",
    "sg:province":"AL",
    "sg:tags":[
        "exporter"
    ],
    "wof:name":"Channel Track",
    "wof:placetype":"venue"
},
  "geometry": {"coordinates":[-87.89386,30.558559],"type":"Point"}
}