{
  "type": "Feature",
  "properties": {
    "iso:country":"US",
    "sg:address":"210 Main St W",
    "sg:city":"Hartselle",
    "sg:classifiers":[
        {
            "category":"Shopping",
            "subcategory":"Used Merchandise",
            "type":"Retail Goods"
        }
    ],
    "sg:phone":"+1 256 773 0116",
    "sg:postcode":"35640",
    "sg:province":"AL",
    "wof:name":"Holladay Antiques",
    "wof:placetype":"venue"
},
  "geometry": {"coordinates":[-86.934798,34.443483],"type":"Point"}
}