{
  "type": "Feature",
  "properties": {
    "iso:country":"US",
    "sg:address":"10406 US Hwy 80",
    "sg:city":"Montgomery",
    "sg:classifiers":[
        {
            "category":"Home & Garden",
            "subcategory":"Building Materials",
            "type":"Retail Goods"
        }
    ],
    "sg:phone":"+1 334 215 0901",
    "sg:postcode":"36117",
    "sg:province":"AL",
    "wof:name":"Builders Supply Company Inc",
    "wof:placetype":"venue"
},
  "geometry": {"coordinates":[-86.129081,32.367638],"type":"Point"}
}