{
  "type": "Feature",
  "properties": {
    "addr:full":"6414 Hillcrest Park Ct Mobile AL 36695",
    "addr:housenumber":"6414",
    "addr:postcode":"36695",
    "addr:street":"Hillcrest Park Ct",
    "iso:country":"US",
    "sg:address":"6414 Hillcrest Park Ct",
    "sg:city":"Mobile",
    "sg:classifiers":[
        {
            "category":"Wholesale",
            "subcategory":"Chemicals & Plastics",
            "type":"Manufacturing & Wholesale Goods"
        }
    ],
    "sg:phone":"+1 251 473 5122",
    "sg:postcode":"36695",
    "sg:province":"AL",
    "sg:tags":[
        "oxygen"
    ],
    "wof:name":"Lincare",
    "wof:placetype":"venue"
},
  "geometry": {"coordinates":[-88.191007,30.66232],"type":"Point"}
}