{
  "type": "Feature",
  "properties": {
    "iso:country":"US",
    "sg:address":"310 Murphy Cir",
    "sg:city":"Madison",
    "sg:phone":"+1 256 772 1355",
    "sg:postcode":"35756",
    "sg:province":"AL",
    "sg:tags":[
        "farm",
        "cotton"
    ],
    "wof:name":"Murphy Farm",
    "wof:placetype":"venue"
},
  "geometry": {"coordinates":[-86.74848799999999,34.598946],"type":"Point"}
}