{
  "type": "Feature",
  "properties": {
    "iso:country":"US",
    "sg:address":"1950 Max Luther Dr NW",
    "sg:city":"Huntsville",
    "sg:classifiers":[
        {
            "category":"Personal",
            "type":"Services"
        }
    ],
    "sg:phone":"+1 256 851 1550",
    "sg:postcode":"35811",
    "sg:province":"AL",
    "sg:tags":[
        "theatrical",
        "supply",
        "make",
        "up",
        "costume",
        "party",
        "rental"
    ],
    "wof:name":"Enchanted Masquerade Inc",
    "wof:placetype":"venue"
},
  "geometry": {"coordinates":[-86.589125,34.757977],"type":"Point"}
}