{
  "type": "Feature",
  "properties": {
    "iso:country":"US",
    "sg:address":"2525 US Hwy 431",
    "sg:city":"Boaz",
    "sg:classifiers":[
        {
            "category":"Professional",
            "subcategory":"Lawyer & Legal Services",
            "type":"Services"
        }
    ],
    "sg:phone":"+1 256 878 7117",
    "sg:postcode":"35957",
    "sg:province":"AL",
    "sg:tags":[
        "attorney"
    ],
    "wof:name":"Hanson & Beaird",
    "wof:placetype":"venue"
},
  "geometry": {"coordinates":[-86.15955200000001,34.221861],"type":"Point"}
}