{
  "type": "Feature",
  "properties": {
    "iso:country":"US",
    "sg:address":"6048 Eastbrook Dr",
    "sg:city":"Tuscaloosa",
    "sg:classifiers":[
        {
            "category":"Shopping",
            "subcategory":"Discount & Variety Stores",
            "type":"Retail Goods"
        }
    ],
    "sg:phone":"+1 205 556 8125",
    "sg:postcode":"35405",
    "sg:province":"AL",
    "sg:tags":[
        "merchandise",
        "general"
    ],
    "wof:name":"Marchant Corp",
    "wof:placetype":"venue"
},
  "geometry": {"coordinates":[-87.460453,33.149958],"type":"Point"}
}