{
  "type": "Feature",
  "properties": {
    "addr:full":"2001 Z Ave Birmingham AL 35208",
    "addr:housenumber":"2001",
    "addr:postcode":"35208",
    "addr:street":"Z Ave",
    "iso:country":"US",
    "sg:address":"2001 Z Ave",
    "sg:city":"Birmingham",
    "sg:classifiers":[
        {
            "category":"Organizations",
            "subcategory":"Religious Organization",
            "type":"Services"
        }
    ],
    "sg:phone":"+1 205 781 3425",
    "sg:postcode":"35208",
    "sg:province":"AL",
    "wof:name":"Faith Church",
    "wof:placetype":"venue"
},
  "geometry": {"coordinates":[-86.87444600000001,33.508479],"type":"Point"}
}