{
  "type": "Feature",
  "properties": {
    "iso:country":"US",
    "sg:address":"348 Jeff Rd NW",
    "sg:city":"Huntsville",
    "sg:classifiers":[
        {
            "category":"Professional",
            "subcategory":"Art Services",
            "type":"Services"
        }
    ],
    "sg:phone":"+1 256 722 9292",
    "sg:postcode":"35806",
    "sg:province":"AL",
    "sg:tags":[
        "photo",
        "photography",
        "commercial",
        "studio",
        "portrait"
    ],
    "sg:website":"www.unclelew.com",
    "wof:name":"Signature Studios",
    "wof:placetype":"venue"
},
  "geometry": {"coordinates":[-86.714323,34.762665],"type":"Point"}
}