{
  "type": "Feature",
  "properties": {
    "addr:full":"3535 Carter Hill Rd Montgomery AL 36111",
    "addr:housenumber":"3535",
    "addr:postcode":"36111",
    "addr:street":"Carter Hill Rd",
    "iso:country":"US",
    "sg:address":"3535 Carter Hill Rd",
    "sg:city":"Montgomery",
    "sg:classifiers":[
        {
            "category":"Social Services",
            "type":"Services"
        }
    ],
    "sg:phone":"+1 334 288 9949",
    "sg:postcode":"36111",
    "sg:province":"AL",
    "sg:tags":[
        "youth",
        "substance",
        "homeless",
        "abuse"
    ],
    "wof:name":"Paul Outreach Services Inc",
    "wof:placetype":"venue"
},
  "geometry": {"coordinates":[-86.260772,32.340491],"type":"Point"}
}