{
  "type": "Feature",
  "properties": {
    "addr:full":"917 Willowbrook Dr SE Huntsville AL 35802",
    "addr:housenumber":"917",
    "addr:postcode":"35802",
    "addr:street":"Willowbrook Dr Se",
    "iso:country":"US",
    "sg:address":"917 Willowbrook Dr SE",
    "sg:city":"Huntsville",
    "sg:classifiers":[
        {
            "category":"Professional",
            "subcategory":"Art Services",
            "type":"Services"
        }
    ],
    "sg:phone":"+1 256 650 2177",
    "sg:postcode":"35802",
    "sg:province":"AL",
    "sg:tags":[
        "commercial",
        "design",
        "marketing"
    ],
    "wof:name":"Advance Design Communications",
    "wof:placetype":"venue"
},
  "geometry": {"coordinates":[-86.54092,34.658517],"type":"Point"}
}