{
  "type": "Feature",
  "properties": {
    "iso:country":"US",
    "sg:address":"910 Meridian St N",
    "sg:city":"Huntsville",
    "sg:classifiers":[
        {
            "category":"Autos & Motor Vehicles",
            "subcategory":"Auto Supplies",
            "type":"Retail Goods"
        }
    ],
    "sg:phone":"+1 256 534 7999",
    "sg:postcode":"35801",
    "sg:province":"AL",
    "wof:name":"E L Hampton Tire Service",
    "wof:placetype":"venue"
},
  "geometry": {"coordinates":[-86.58496,34.742412],"type":"Point"}
}