{
  "type": "Feature",
  "properties": {
    "iso:country":"US",
    "sg:address":"11359 State Rte 65",
    "sg:city":"Hollytree",
    "sg:classifiers":[
        {
            "category":"Building & Trades",
            "subcategory":"Construction",
            "type":"Services"
        }
    ],
    "sg:phone":"+1 256 776 9427",
    "sg:postcode":"35751",
    "sg:province":"AL",
    "sg:tags":[
        "hanging",
        "contractor"
    ],
    "wof:name":"Pro Select Painting",
    "wof:placetype":"venue"
},
  "geometry": {"coordinates":[-86.25132499999999,34.798451],"type":"Point"}
}