{
  "type": "Feature",
  "properties": {
    "iso:country":"US",
    "sg:address":"2228 Bessemer Rd",
    "sg:city":"Birmingham",
    "sg:classifiers":[
        {
            "category":"Education",
            "subcategory":"Library",
            "type":"Public Place"
        }
    ],
    "sg:phone":"+1 205 226 4013",
    "sg:postcode":"35208",
    "sg:province":"AL",
    "wof:name":"Five Points West Library",
    "wof:placetype":"venue"
},
  "geometry": {"coordinates":[-86.878092,33.495991],"type":"Point"}
}