{
  "type": "Feature",
  "properties": {
    "addr:full":"1507 Montgomery St Opelika AL 36801",
    "addr:housenumber":"1507",
    "addr:postcode":"36801",
    "addr:street":"Montgomery St",
    "iso:country":"US",
    "sg:address":"1507 Montgomery St",
    "sg:city":"Opelika",
    "sg:classifiers":[
        {
            "category":"Building & Trades",
            "subcategory":"Construction",
            "type":"Services"
        }
    ],
    "sg:phone":"+1 334 749 2951",
    "sg:postcode":"36801",
    "sg:province":"AL",
    "sg:tags":[
        "floor",
        "laying",
        "contractor"
    ],
    "wof:name":"Spann Flooring",
    "wof:placetype":"venue"
},
  "geometry": {"coordinates":[-85.392591,32.634938],"type":"Point"}
}