{
  "type": "Feature",
  "properties": {
    "iso:country":"US",
    "sg:address":"909 Alberta Dr",
    "sg:city":"Tuscaloosa",
    "sg:classifiers":[
        {
            "category":"Home & Garden",
            "subcategory":"Building Materials",
            "type":"Retail Goods"
        }
    ],
    "sg:phone":"+1 205 633 2066",
    "sg:postcode":"35404",
    "sg:province":"AL",
    "sg:tags":[
        "overhead",
        "door",
        "installation"
    ],
    "wof:name":"Kirkland Overhead Door Co Inc",
    "wof:placetype":"venue"
},
  "geometry": {"coordinates":[-87.507667,33.205037],"type":"Point"}
}