{
  "type": "Feature",
  "properties": {
    "iso:country":"US",
    "sg:address":"1901 Gulf Shores Pkwy",
    "sg:city":"Gulf Shores",
    "sg:classifiers":[
        {
            "category":"Autos & Motor Vehicles",
            "subcategory":"Fuel & Gas Station",
            "type":"Retail Goods"
        }
    ],
    "sg:phone":"+1 251 968 7456",
    "sg:postcode":"36542",
    "sg:province":"AL",
    "sg:tags":[
        "oil"
    ],
    "wof:name":"Gulf Shores BP Inc",
    "wof:placetype":"venue"
},
  "geometry": {"coordinates":[-87.68744700000001,30.272759],"type":"Point"}
}