{
  "type": "Feature",
  "properties": {
    "iso:country":"US",
    "sg:address":"802 Gant Rd",
    "sg:city":"Scottsboro",
    "sg:classifiers":[
        {
            "category":"Wholesale",
            "subcategory":"Petroleum",
            "type":"Manufacturing & Wholesale Goods"
        }
    ],
    "sg:phone":"+1 256 587 3510",
    "sg:postcode":"35769",
    "sg:province":"AL",
    "sg:tags":[
        "grocery",
        "gas"
    ],
    "wof:name":"Rock Store The",
    "wof:placetype":"venue"
},
  "geometry": {"coordinates":[-85.98709100000001,34.65724],"type":"Point"}
}