{
  "type": "Feature",
  "properties": {
    "addr:full":"6808 Airport Blvd Svc Rd Mobile AL 36608",
    "addr:housenumber":"6808",
    "addr:postcode":"36608",
    "addr:street":"Airport Blvd",
    "iso:country":"US",
    "sg:address":"6808 Airport Blvd Svc Rd",
    "sg:city":"Mobile",
    "sg:classifiers":[
        {
            "category":"Professional",
            "subcategory":"Business Services",
            "type":"Services"
        },
        {
            "category":"Wholesale",
            "subcategory":"Home Furnishings",
            "type":"Manufacturing & Wholesale Goods"
        }
    ],
    "sg:phone":"+1 251 344 5644",
    "sg:postcode":"36608",
    "sg:province":"AL",
    "sg:tags":[
        "interior",
        "consultant",
        "design",
        "decorator"
    ],
    "wof:name":"Finishing Touches",
    "wof:placetype":"venue"
},
  "geometry": {"coordinates":[-88.200316,30.682684],"type":"Point"}
}