{
  "type": "Feature",
  "properties": {
    "iso:country":"US",
    "sg:address":"502 S 4th St",
    "sg:city":"Gadsden",
    "sg:classifiers":[
        {
            "category":"Professional",
            "subcategory":"Lawyer & Legal Services",
            "type":"Services"
        }
    ],
    "sg:phone":"+1 256 546 3331",
    "sg:postcode":"35901",
    "sg:province":"AL",
    "sg:tags":[
        "attorney"
    ],
    "wof:name":"Stover Stewart & Phillips",
    "wof:placetype":"venue"
},
  "geometry": {"coordinates":[-86.005216,34.005561],"type":"Point"}
}