{
  "type": "Feature",
  "properties": {
    "addr:full":"401 W Washington St Athens AL 35611",
    "addr:housenumber":"401",
    "addr:postcode":"35611",
    "addr:street":"W Washington St",
    "iso:country":"US",
    "sg:address":"401 W Washington St",
    "sg:city":"Athens",
    "sg:classifiers":[
        {
            "category":"Restaurant",
            "type":"Food & Drink"
        }
    ],
    "sg:phone":"+1 256 232 9130",
    "sg:postcode":"35611",
    "sg:province":"AL",
    "sg:tags":[
        "eating"
    ],
    "wof:name":"Kreme Delite",
    "wof:placetype":"venue"
},
  "geometry": {"coordinates":[-86.97447099999999,34.80252],"type":"Point"}
}