{
  "type": "Feature",
  "properties": {
    "addr:full":"300 Cahaba Park Cir Birmingham AL 35242",
    "addr:housenumber":"300",
    "addr:postcode":"35242",
    "addr:street":"Cahaba Park Cir",
    "iso:country":"US",
    "sg:address":"300 Cahaba Park Cir",
    "sg:city":"Birmingham",
    "sg:classifiers":[
        {
            "category":"Freight",
            "type":"Transportation"
        }
    ],
    "sg:phone":"+1 205 991 7907",
    "sg:postcode":"35242",
    "sg:province":"AL",
    "sg:tags":[
        "arrangement"
    ],
    "wof:name":"Ryder",
    "wof:placetype":"venue"
},
  "geometry": {"coordinates":[-86.70660599999999,33.428993],"type":"Point"}
}