{
  "type": "Feature",
  "properties": {
    "iso:country":"US",
    "sg:address":"2416 State Rte 14",
    "sg:city":"Selma",
    "sg:classifiers":[
        {
            "category":"Professional",
            "type":"Services"
        }
    ],
    "sg:phone":"+1 334 872 2276",
    "sg:postcode":"36703",
    "sg:province":"AL",
    "wof:name":"Rib Rack Smokehouse",
    "wof:placetype":"venue"
},
  "geometry": {"coordinates":[-86.97977,32.431683],"type":"Point"}
}