{
  "type": "Feature",
  "properties": {
    "iso:country":"US",
    "sg:address":"339 Main St",
    "sg:city":"Trussville",
    "sg:classifiers":[
        {
            "category":"Retail",
            "subcategory":"Auto Repair",
            "type":"Services"
        }
    ],
    "sg:phone":"+1 205 655 4117",
    "sg:postcode":"35173",
    "sg:province":"AL",
    "sg:tags":[
        "repairing",
        "automobile"
    ],
    "wof:name":"Complete Auto Svc",
    "wof:placetype":"venue"
},
  "geometry": {"coordinates":[-86.612386,33.618283],"type":"Point"}
}