{
  "type": "Feature",
  "properties": {
    "iso:country":"US",
    "sg:address":"212 N Broadway St",
    "sg:city":"Ashford",
    "sg:classifiers":[
        {
            "category":"Building & Trades",
            "subcategory":"Cleaning & Sanitation",
            "type":"Services"
        }
    ],
    "sg:phone":"+1 334 899 8008",
    "sg:postcode":"36312",
    "sg:province":"AL",
    "sg:tags":[
        "janitor"
    ],
    "wof:name":"Creek Services",
    "wof:placetype":"venue"
},
  "geometry": {"coordinates":[-85.23437,31.221921],"type":"Point"}
}