{
  "type": "Feature",
  "properties": {
    "addr:full":"449 Reinier Ln Munford AL 36268",
    "addr:housenumber":"449",
    "addr:postcode":"36268",
    "addr:street":"Reinier Ln",
    "iso:country":"US",
    "sg:address":"449 Reinier Ln",
    "sg:city":"Munford",
    "sg:classifiers":[
        {
            "category":"Manufacturing",
            "subcategory":"Tools & Machinery",
            "type":"Manufacturing & Wholesale Goods"
        }
    ],
    "sg:phone":"+1 256 358 4763",
    "sg:postcode":"36268",
    "sg:province":"AL",
    "sg:tags":[
        "industrial",
        "mfg"
    ],
    "wof:name":"Lineville Machine & Mfg Co",
    "wof:placetype":"venue"
},
  "geometry": {"coordinates":[-85.981342,33.508397],"type":"Point"}
}