{
  "type": "Feature",
  "properties": {
    "iso:country":"US",
    "sg:address":"432 Industrial Ln",
    "sg:city":"Birmingham",
    "sg:classifiers":[
        {
            "category":"Retail",
            "subcategory":"Repair Shop",
            "type":"Services"
        }
    ],
    "sg:phone":"+1 205 621 3830",
    "sg:postcode":"35211",
    "sg:province":"AL",
    "sg:tags":[
        "electrical"
    ],
    "wof:name":"Tritel Communication",
    "wof:placetype":"venue"
},
  "geometry": {"coordinates":[-86.85331499999999,33.450992],"type":"Point"}
}