{
  "type": "Feature",
  "properties": {
    "iso:country":"US",
    "sg:address":"3440 Broad St",
    "sg:city":"Phil Campbell",
    "sg:classifiers":[
        {
            "category":"Personal",
            "subcategory":"Barber",
            "type":"Services"
        }
    ],
    "sg:phone":"+1 205 993 5500",
    "sg:postcode":"35581",
    "sg:province":"AL",
    "wof:name":"Bragwell Barber Shop",
    "wof:placetype":"venue"
},
  "geometry": {"coordinates":[-87.701358,34.344995],"type":"Point"}
}