{
  "type": "Feature",
  "properties": {
    "iso:country":"US",
    "sg:address":"3591 Young Dr",
    "sg:city":"Montgomery",
    "sg:classifiers":[
        {
            "category":"Government",
            "subcategory":"Office",
            "type":"Public Place"
        }
    ],
    "sg:phone":"+1 334 284 7937",
    "sg:postcode":"36108",
    "sg:province":"AL",
    "sg:tags":[
        "village"
    ],
    "wof:name":"Cedar Park Community Ctr",
    "wof:placetype":"venue"
},
  "geometry": {"coordinates":[-86.342201,32.340601],"type":"Point"}
}