{
  "type": "Feature",
  "properties": {
    "addr:full":"2048 Carters Gin Rd Toney AL 35773",
    "addr:housenumber":"2048",
    "addr:postcode":"35773",
    "addr:street":"Carters Gin Rd",
    "iso:country":"US",
    "sg:address":"2048 Carters Gin Rd",
    "sg:city":"Toney",
    "sg:classifiers":[
        {
            "category":"Retail",
            "subcategory":"Portrait Studio",
            "type":"Services"
        }
    ],
    "sg:phone":"+1 256 851 9291",
    "sg:postcode":"35773",
    "sg:province":"AL",
    "sg:tags":[
        "photographer"
    ],
    "sg:website":"www.pioneerstudio.com",
    "wof:name":"Pioneer Studios Photo Svc",
    "wof:placetype":"venue"
},
  "geometry": {"coordinates":[-86.687555,34.866719],"type":"Point"}
}