{
  "type": "Feature",
  "properties": {
    "iso:country":"US",
    "sg:address":"7015 State Rte 21",
    "sg:city":"Sylacauga",
    "sg:classifiers":[
        {
            "category":"Food & Beverages",
            "subcategory":"Groceries & Convenience Stores",
            "type":"Retail Goods"
        }
    ],
    "sg:phone":"+1 256 249 9164",
    "sg:postcode":"35151",
    "sg:province":"AL",
    "sg:tags":[
        "video",
        "grocer",
        "station",
        "gasoline",
        "tape"
    ],
    "wof:name":"Hawthorne Grocery & Video",
    "wof:placetype":"venue"
},
  "geometry": {"coordinates":[-86.251846,33.109285],"type":"Point"}
}