{
  "type": "Feature",
  "properties": {
    "addr:full":"1017 River Falls St Andalusia AL 36420",
    "addr:housenumber":"1017",
    "addr:postcode":"36420",
    "addr:street":"River Falls St",
    "iso:country":"US",
    "sg:address":"1017 River Falls St",
    "sg:city":"Andalusia",
    "sg:classifiers":[
        {
            "category":"Shopping",
            "subcategory":"Pharmacy",
            "type":"Retail Goods"
        }
    ],
    "sg:phone":"+1 334 222 9414",
    "sg:postcode":"36420",
    "sg:province":"AL",
    "wof:name":"Rite Aid Pharmacy",
    "wof:placetype":"venue"
},
  "geometry": {"coordinates":[-86.49829200000001,31.318161],"type":"Point"}
}