{
  "type": "Feature",
  "properties": {
    "iso:country":"US",
    "sg:address":"9320 State Rte 14",
    "sg:city":"Selma",
    "sg:classifiers":[
        {
            "category":"Building & Trades",
            "subcategory":"Landscaping Services",
            "type":"Services"
        }
    ],
    "sg:phone":"+1 334 418 4813",
    "sg:postcode":"36703",
    "sg:province":"AL",
    "sg:tags":[
        "landscape"
    ],
    "wof:name":"Big Mulberry Nursey & Landscap",
    "wof:placetype":"venue"
},
  "geometry": {"coordinates":[-86.876684,32.469379],"type":"Point"}
}