{
  "type": "Feature",
  "properties": {
    "iso:country":"US",
    "sg:address":"178 Derby Dr",
    "sg:city":"Ozark",
    "sg:classifiers":[
        {
            "category":"Organizations",
            "subcategory":"Membership Organization",
            "type":"Services"
        }
    ],
    "sg:phone":"+1 334 774 7037",
    "sg:postcode":"36360",
    "sg:province":"AL",
    "wof:name":"National Society Daughters",
    "wof:placetype":"venue"
},
  "geometry": {"coordinates":[-85.629311,31.472734],"type":"Point"}
}