{
  "type": "Feature",
  "properties": {
    "iso:country":"US",
    "sg:address":"7981 Vaughn Rd",
    "sg:city":"Montgomery",
    "sg:classifiers":[
        {
            "category":"Shopping",
            "subcategory":"Clothing, Apparel, & Fashions",
            "type":"Retail Goods"
        }
    ],
    "sg:phone":"+1 334 277 7100",
    "sg:postcode":"36116",
    "sg:province":"AL",
    "wof:name":"Gazebo",
    "wof:placetype":"venue"
},
  "geometry": {"coordinates":[-86.175653,32.338787],"type":"Point"}
}