{
  "type": "Feature",
  "properties": {
    "iso:country":"US",
    "sg:address":"372 S Central Ave",
    "sg:city":"Alexander City",
    "sg:classifiers":[
        {
            "category":"Professional",
            "type":"Services"
        }
    ],
    "sg:phone":"+1 256 409 1865",
    "sg:postcode":"35010",
    "sg:province":"AL",
    "wof:name":"Covey Rise",
    "wof:placetype":"venue"
},
  "geometry": {"coordinates":[-85.956143,32.942001],"type":"Point"}
}