{
  "type": "Feature",
  "properties": {
    "iso:country":"US",
    "sg:address":"4206 Huntsville Rd",
    "sg:city":"Florence",
    "sg:classifiers":[
        {
            "category":"Food & Beverages",
            "subcategory":"Groceries & Convenience Stores",
            "type":"Retail Goods"
        }
    ],
    "sg:phone":"+1 256 766 3067",
    "sg:postcode":"35630",
    "sg:province":"AL",
    "wof:name":"Foodland",
    "wof:placetype":"venue"
},
  "geometry": {"coordinates":[-87.625544,34.823421],"type":"Point"}
}