{
  "type": "Feature",
  "properties": {
    "iso:country":"US",
    "sg:address":"1991 Montgomery Hwy",
    "sg:city":"Dothan",
    "sg:classifiers":[
        {
            "category":"Autos & Motor Vehicles",
            "subcategory":"Auto Supplies",
            "type":"Retail Goods"
        }
    ],
    "sg:phone":"+1 334 671 1088",
    "sg:postcode":"36303",
    "sg:province":"AL",
    "sg:tags":[
        "battery",
        "automobile",
        "parts"
    ],
    "wof:name":"O'Reilly Auto Parts",
    "wof:placetype":"venue"
},
  "geometry": {"coordinates":[-85.410607,31.239303],"type":"Point"}
}