{
  "type": "Feature",
  "properties": {
    "iso:country":"US",
    "sg:address":"309 Bryan St",
    "sg:city":"Columbia",
    "sg:classifiers":[
        {
            "category":"Food & Beverages",
            "subcategory":"Groceries & Convenience Stores",
            "type":"Retail Goods"
        }
    ],
    "sg:phone":"+1 334 696 2010",
    "sg:postcode":"36319",
    "sg:province":"AL",
    "wof:name":"M&M Food Stores Inc",
    "wof:placetype":"venue"
},
  "geometry": {"coordinates":[-85.117124,31.294841],"type":"Point"}
}