{
  "type": "Feature",
  "properties": {
    "iso:country":"US",
    "sg:address":"28 Glenwood Rd",
    "sg:city":"Luverne",
    "sg:classifiers":[
        {
            "category":"Food & Beverages",
            "subcategory":"Groceries & Convenience Stores",
            "type":"Retail Goods"
        }
    ],
    "sg:phone":"+1 334 335 3903",
    "sg:postcode":"36049",
    "sg:province":"AL",
    "wof:name":"B E Horn and Son",
    "wof:placetype":"venue"
},
  "geometry": {"coordinates":[-86.263749,31.707384],"type":"Point"}
}