{
  "type": "Feature",
  "properties": {
    "addr:full":"544 S McQueen Smith Rd Prattville AL 36066",
    "addr:housenumber":"544",
    "addr:postcode":"36066",
    "addr:street":"S Mcqueen Smith Rd",
    "iso:country":"US",
    "sg:address":"544 S McQueen Smith Rd",
    "sg:city":"Prattville",
    "sg:classifiers":[
        {
            "category":"Wholesale",
            "subcategory":"Medical Equipment & Supplies",
            "type":"Manufacturing & Wholesale Goods"
        }
    ],
    "sg:phone":"+1 334 358 0320",
    "sg:postcode":"36066",
    "sg:province":"AL",
    "wof:name":"First Choice Chiropractic",
    "wof:placetype":"venue"
},
  "geometry": {"coordinates":[-86.418178,32.464139],"type":"Point"}
}