{
  "type": "Feature",
  "properties": {
    "iso:country":"US",
    "sg:address":"100 W 5th St",
    "sg:city":"Sheffield",
    "sg:classifiers":[
        {
            "category":"Food & Beverages",
            "subcategory":"Groceries & Convenience Stores",
            "type":"Retail Goods"
        }
    ],
    "sg:phone":"+1 256 381 6421",
    "sg:postcode":"35660",
    "sg:province":"AL",
    "wof:name":"Jan's Market",
    "wof:placetype":"venue"
},
  "geometry": {"coordinates":[-87.699055,34.762919],"type":"Point"}
}