{
  "type": "Feature",
  "properties": {
    "iso:country":"US",
    "sg:address":"1300 1st Ave W",
    "sg:city":"Birmingham",
    "sg:classifiers":[
        {
            "category":"Organizations",
            "subcategory":"Religious Organization",
            "type":"Services"
        }
    ],
    "sg:phone":"+1 205 781 1367",
    "sg:postcode":"35208",
    "sg:province":"AL",
    "wof:name":"Bethel AME Church",
    "wof:placetype":"venue"
},
  "geometry": {"coordinates":[-86.859861,33.50123],"type":"Point"}
}