{
  "type": "Feature",
  "properties": {
    "iso:country":"US",
    "sg:address":"3949 Todd Ln",
    "sg:city":"Gulf Shores",
    "sg:classifiers":[
        {
            "category":"Retail",
            "subcategory":"Repair Shop",
            "type":"Services"
        }
    ],
    "sg:phone":"+1 251 968 7948",
    "sg:postcode":"36542",
    "sg:province":"AL",
    "sg:tags":[
        "electrical"
    ],
    "wof:name":"Industrial Devices Repair",
    "wof:placetype":"venue"
},
  "geometry": {"coordinates":[-87.743734,30.283298],"type":"Point"}
}