{
  "type": "Feature",
  "properties": {
    "addr:full":"636 Landess Cir Madison AL 35756",
    "addr:housenumber":"636",
    "addr:postcode":"35756",
    "addr:street":"Landess Cir",
    "iso:country":"US",
    "sg:address":"636 Landess Cir",
    "sg:city":"Madison",
    "sg:classifiers":[
        {
            "category":"Retail",
            "subcategory":"Auto Repair",
            "type":"Services"
        }
    ],
    "sg:phone":"+1 256 772 1717",
    "sg:postcode":"35756",
    "sg:province":"AL",
    "wof:name":"We Care Auto Repair",
    "wof:placetype":"venue"
},
  "geometry": {"coordinates":[-86.764388,34.567778],"type":"Point"}
}