{
  "type": "Feature",
  "properties": {
    "iso:country":"US",
    "sg:address":"609 US Hwy 72 W",
    "sg:city":"Athens",
    "sg:classifiers":[
        {
            "category":"Food & Beverages",
            "subcategory":"Specialty",
            "type":"Retail Goods"
        }
    ],
    "sg:phone":"+1 256 233 0073",
    "sg:postcode":"35611",
    "sg:province":"AL",
    "sg:tags":[
        "health",
        "diet"
    ],
    "wof:name":"Herbs & More",
    "wof:placetype":"venue"
},
  "geometry": {"coordinates":[-86.976753,34.790056],"type":"Point"}
}