{
  "type": "Feature",
  "properties": {
    "iso:country":"US",
    "sg:address":"215 N Cherry Dr",
    "sg:city":"Lanett",
    "sg:classifiers":[
        {
            "category":"Autos & Motor Vehicles",
            "subcategory":"Automobile Sales",
            "type":"Retail Goods"
        }
    ],
    "sg:phone":"+1 334 642 6490",
    "sg:postcode":"36863",
    "sg:province":"AL",
    "sg:tags":[
        "used"
    ],
    "wof:name":"Valley Auto Sales",
    "wof:placetype":"venue"
},
  "geometry": {"coordinates":[-85.186623,32.874575],"type":"Point"}
}