{
  "type": "Feature",
  "properties": {
    "addr:full":"11203 Memorial Pkwy SW Huntsville AL 35803",
    "addr:housenumber":"11203",
    "addr:postcode":"35803",
    "addr:street":"Memorial Pkwy Sw",
    "iso:country":"US",
    "sg:address":"11203 Memorial Pkwy SW",
    "sg:city":"Huntsville",
    "sg:classifiers":[
        {
            "category":"Personal",
            "subcategory":"Beauty Salon",
            "type":"Services"
        }
    ],
    "sg:phone":"+1 256 882 7323",
    "sg:postcode":"35803",
    "sg:province":"AL",
    "sg:tags":[
        "shop"
    ],
    "wof:name":"Big Tease",
    "wof:placetype":"venue"
},
  "geometry": {"coordinates":[-86.566597,34.640621],"type":"Point"}
}