{
  "type": "Feature",
  "properties": {
    "iso:country":"US",
    "sg:address":"3621 6th Ave S",
    "sg:city":"Birmingham",
    "sg:classifiers":[
        {
            "category":"Arts & Performance",
            "subcategory":"Theater",
            "type":"Entertainment"
        }
    ],
    "sg:phone":"+1 205 251 6929",
    "sg:postcode":"35222",
    "sg:province":"AL",
    "sg:tags":[
        "musician"
    ],
    "sg:website":"www.alabamasymphony.com",
    "wof:name":"Alabama Symphony Orchestra",
    "wof:placetype":"venue"
},
  "geometry": {"coordinates":[-86.77773000000001,33.518181],"type":"Point"}
}