{
  "type": "Feature",
  "properties": {
    "iso:country":"US",
    "sg:address":"295 Brookwood Ln",
    "sg:city":"Hayden",
    "sg:classifiers":[
        {
            "category":"Building & Trades",
            "subcategory":"Electrical",
            "type":"Services"
        }
    ],
    "sg:phone":"+1 205 647 8528",
    "sg:postcode":"35079",
    "sg:province":"AL",
    "sg:tags":[
        "electrical",
        "contractor"
    ],
    "wof:name":"A West Electric Co Inc",
    "wof:placetype":"venue"
},
  "geometry": {"coordinates":[-86.877361,33.88863],"type":"Point"}
}