{
  "type": "Feature",
  "properties": {
    "addr:full":"111 E Fontana Cir Dothan AL 36305",
    "addr:housenumber":"111",
    "addr:postcode":"36305",
    "addr:street":"E Fontana Cir",
    "iso:country":"US",
    "sg:address":"111 E Fontana Cir",
    "sg:city":"Dothan",
    "sg:classifiers":[
        {
            "category":"Professional",
            "type":"Services"
        }
    ],
    "sg:phone":"+1 334 699 2003",
    "sg:postcode":"36305",
    "sg:province":"AL",
    "wof:name":"Glenn & Sheila Rizzi",
    "wof:placetype":"venue"
},
  "geometry": {"coordinates":[-85.45807499999999,31.2267],"type":"Point"}
}