{
  "type": "Feature",
  "properties": {
    "iso:country":"US",
    "sg:address":"50 Commerce Dr",
    "sg:city":"Pelham",
    "sg:classifiers":[
        {
            "category":"Building & Trades",
            "subcategory":"Plumbing",
            "type":"Services"
        }
    ],
    "sg:phone":"+1 205 664 5403",
    "sg:postcode":"35124",
    "sg:province":"AL",
    "sg:tags":[
        "conditioning",
        "air",
        "system",
        "contractor"
    ],
    "wof:name":"Invensys Intelligent Building",
    "wof:placetype":"venue"
},
  "geometry": {"coordinates":[-86.80163,33.291787],"type":"Point"}
}