{
  "type": "Feature",
  "properties": {
    "iso:country":"US",
    "sg:address":"36708 US Hwy 280",
    "sg:city":"Sylacauga",
    "sg:classifiers":[
        {
            "category":"Manufacturing",
            "subcategory":"Tools & Machinery",
            "type":"Manufacturing & Wholesale Goods"
        }
    ],
    "sg:phone":"+1 256 245 2627",
    "sg:postcode":"35150",
    "sg:province":"AL",
    "sg:tags":[
        "equipment",
        "pump",
        "pumping"
    ],
    "wof:name":"M & N Alloy Cast Product",
    "wof:placetype":"venue"
},
  "geometry": {"coordinates":[-86.328137,33.232734],"type":"Point"}
}