{
  "type": "Feature",
  "properties": {
    "iso:country":"US",
    "sg:address":"1542 Florence Blvd",
    "sg:city":"Florence",
    "sg:classifiers":[
        {
            "category":"Home & Garden",
            "subcategory":"Furniture",
            "type":"Retail Goods"
        }
    ],
    "sg:phone":"+1 256 718 0894",
    "sg:postcode":"35630",
    "sg:province":"AL",
    "wof:name":"Wood You Furniture",
    "wof:placetype":"venue"
},
  "geometry": {"coordinates":[-87.65692300000001,34.81916],"type":"Point"}
}