{
  "type": "Feature",
  "properties": {
    "addr:full":"2325 Whitesburg Dr S Huntsville AL 35801",
    "addr:housenumber":"2325",
    "addr:postcode":"35801",
    "addr:street":"Whitesburg Dr S",
    "iso:country":"US",
    "sg:address":"2325 Whitesburg Dr S",
    "sg:city":"Huntsville",
    "sg:classifiers":[
        {
            "category":"Personal",
            "subcategory":"Beauty Salon",
            "type":"Services"
        }
    ],
    "sg:phone":"+1 256 533 6626",
    "sg:postcode":"35801",
    "sg:province":"AL",
    "sg:tags":[
        "shop"
    ],
    "wof:name":"Tresses Salon",
    "wof:placetype":"venue"
},
  "geometry": {"coordinates":[-86.575683,34.714346],"type":"Point"}
}