{
  "type": "Feature",
  "properties": {
    "iso:country":"US",
    "sg:address":"101 S 3rd Ave",
    "sg:city":"Hartford",
    "sg:classifiers":[
        {
            "category":"Banks & Credit Unions",
            "subcategory":"Bank",
            "type":"Services"
        },
        {
            "category":"Banks & Credit Unions",
            "subcategory":"Financial Services",
            "type":"Services"
        }
    ],
    "sg:phone":"+1 334 588 2211",
    "sg:postcode":"36344",
    "sg:province":"AL",
    "sg:tags":[
        "loan",
        "mortgage"
    ],
    "sg:website":"http://www.fnbhartford.com",
    "wof:name":"First National Bank",
    "wof:placetype":"venue"
},
  "geometry": {"coordinates":[-85.696043,31.078538],"type":"Point"}
}