{
  "type": "Feature",
  "properties": {
    "addr:full":"1010 Henderson Rd NW Huntsville AL 35816",
    "addr:housenumber":"1010",
    "addr:postcode":"35816",
    "addr:street":"Henderson Rd Nw",
    "iso:country":"US",
    "sg:address":"1010 Henderson Rd NW",
    "sg:city":"Huntsville",
    "sg:classifiers":[
        {
            "category":"Restaurant",
            "type":"Food & Drink"
        }
    ],
    "sg:phone":"+1 256 837 0405",
    "sg:postcode":"35816",
    "sg:province":"AL",
    "sg:tags":[
        "eating"
    ],
    "wof:name":"Sophisticated Catering",
    "wof:placetype":"venue"
},
  "geometry": {"coordinates":[-86.632634,34.732399],"type":"Point"}
}