{
  "type": "Feature",
  "properties": {
    "addr:full":"3085 Swann Bridge Rd Cleveland AL 35049",
    "addr:housenumber":"3085",
    "addr:postcode":"35049",
    "addr:street":"Swann Bridge Rd",
    "iso:country":"US",
    "sg:address":"3085 Swann Bridge Rd",
    "sg:city":"Cleveland",
    "sg:classifiers":[
        {
            "category":"Professional",
            "subcategory":"Management & Consulting",
            "type":"Services"
        }
    ],
    "sg:phone":"+1 205 625 5822",
    "sg:postcode":"35049",
    "sg:province":"AL",
    "sg:tags":[
        "marketing",
        "program"
    ],
    "wof:name":"Love Marketing Svc",
    "wof:placetype":"venue"
},
  "geometry": {"coordinates":[-86.579195,33.994787],"type":"Point"}
}