{
  "type": "Feature",
  "properties": {
    "addr:full":"410 13th St Opp AL 36467",
    "addr:housenumber":"410",
    "addr:postcode":"36467",
    "addr:street":"13Th St Opp",
    "iso:country":"US",
    "sg:address":"410 13th St",
    "sg:city":"Opp",
    "sg:classifiers":[
        {
            "category":"Personal",
            "subcategory":"Beauty Salon",
            "type":"Services"
        }
    ],
    "sg:phone":"+1 334 493 3472",
    "sg:postcode":"36467",
    "sg:province":"AL",
    "sg:tags":[
        "shop"
    ],
    "wof:name":"Glendas House of Beauty",
    "wof:placetype":"venue"
},
  "geometry": {"coordinates":[-86.275083,31.277477],"type":"Point"}
}