{
  "type": "Feature",
  "properties": {
    "iso:country":"US",
    "sg:address":"2600 N Jackson Hwy",
    "sg:city":"Sheffield",
    "sg:classifiers":[
        {
            "category":"Retail",
            "subcategory":"Auto Repair",
            "type":"Services"
        }
    ],
    "sg:phone":"+1 256 383 9777",
    "sg:postcode":"35660",
    "sg:province":"AL",
    "sg:tags":[
        "body"
    ],
    "wof:name":"Advantage Customs",
    "wof:placetype":"venue"
},
  "geometry": {"coordinates":[-87.68455899999999,34.76083],"type":"Point"}
}