{
  "type": "Feature",
  "properties": {
    "iso:country":"US",
    "sg:address":"1058 US Hwy 280",
    "sg:city":"Alexander City",
    "sg:classifiers":[
        {
            "category":"Personal",
            "subcategory":"Barber",
            "type":"Services"
        }
    ],
    "sg:phone":"+1 256 329 2287",
    "sg:postcode":"35010",
    "sg:province":"AL",
    "wof:name":"Cut Hut",
    "wof:placetype":"venue"
},
  "geometry": {"coordinates":[-85.99794300000001,32.956814],"type":"Point"}
}