{
  "type": "Feature",
  "properties": {
    "iso:country":"US",
    "sg:address":"2950 Pinson Valley Pkwy",
    "sg:city":"Birmingham",
    "sg:classifiers":[
        {
            "category":"Social Services",
            "subcategory":"Adult Care",
            "type":"Services"
        }
    ],
    "sg:phone":"+1 205 841 9895",
    "sg:postcode":"35217",
    "sg:province":"AL",
    "sg:tags":[
        "equipment",
        "tree",
        "supply"
    ],
    "wof:name":"Vermeer Alabama Inc",
    "wof:placetype":"venue"
},
  "geometry": {"coordinates":[-86.73776700000001,33.619991],"type":"Point"}
}