{
  "type": "Feature",
  "properties": {
    "iso:country":"US",
    "sg:address":"1008 Coosa St W",
    "sg:city":"Talladega",
    "sg:classifiers":[
        {
            "category":"Organizations",
            "subcategory":"Religious Organization",
            "type":"Services"
        }
    ],
    "sg:phone":"+1 256 761 1060",
    "sg:postcode":"35160",
    "sg:province":"AL",
    "sg:tags":[
        "church"
    ],
    "wof:name":"Mount Zebalon Afm Church God",
    "wof:placetype":"venue"
},
  "geometry": {"coordinates":[-86.118189,33.435905],"type":"Point"}
}