{
  "type": "Feature",
  "properties": {
    "iso:country":"US",
    "sg:address":"2167 Mount Zion Rd",
    "sg:city":"Wetumpka",
    "sg:classifiers":[
        {
            "category":"Organizations",
            "subcategory":"Religious Organization",
            "type":"Services"
        }
    ],
    "sg:phone":"+1 334 567 8367",
    "sg:postcode":"36092",
    "sg:province":"AL",
    "sg:tags":[
        "church"
    ],
    "wof:name":"Mount Zion Baptist Church",
    "wof:placetype":"venue"
},
  "geometry": {"coordinates":[-86.118031,32.67614],"type":"Point"}
}