{
  "type": "Feature",
  "properties": {
    "iso:country":"US",
    "sg:address":"9531 Key Largo",
    "sg:city":"Fairhope",
    "sg:classifiers":[
        {
            "category":"Real Estate",
            "subcategory":"Real Estate Operator",
            "type":"Services"
        }
    ],
    "sg:phone":"+1 251 990 0009",
    "sg:postcode":"36532",
    "sg:province":"AL",
    "sg:tags":[
        "mobile",
        "home",
        "community"
    ],
    "wof:name":"Key Allegro Villas",
    "wof:placetype":"venue"
},
  "geometry": {"coordinates":[-87.859015,30.420118],"type":"Point"}
}