{
  "type": "Feature",
  "properties": {
    "addr:full":"105 8th St S Gadsden AL 35903",
    "addr:housenumber":"105",
    "addr:postcode":"35903",
    "addr:street":"8Th St S",
    "iso:country":"US",
    "sg:address":"105 8th St S",
    "sg:city":"Gadsden",
    "sg:classifiers":[
        {
            "category":"Home & Garden",
            "subcategory":"Carpets & Floor Coverings",
            "type":"Retail Goods"
        }
    ],
    "sg:phone":"+1 256 492 1273",
    "sg:postcode":"35903",
    "sg:province":"AL",
    "wof:name":"Glencoe Carpet Outlet",
    "wof:placetype":"venue"
},
  "geometry": {"coordinates":[-85.985356,34.002626],"type":"Point"}
}