{
  "type": "Feature",
  "properties": {
    "iso:country":"US",
    "sg:address":"507 Jordan St",
    "sg:city":"Chatom",
    "sg:classifiers":[
        {
            "category":"Personal",
            "subcategory":"Beauty Salon",
            "type":"Services"
        }
    ],
    "sg:phone":"+1 251 847 6470",
    "sg:postcode":"36518",
    "sg:province":"AL",
    "sg:tags":[
        "shop"
    ],
    "wof:name":"Reflections",
    "wof:placetype":"venue"
},
  "geometry": {"coordinates":[-88.25254700000001,31.470652],"type":"Point"}
}