{
  "type": "Feature",
  "properties": {
    "iso:country":"US",
    "sg:address":"8265 Co Rd 44",
    "sg:city":"Cedar Bluff",
    "sg:classifiers":[
        {
            "category":"Professional",
            "subcategory":"Business Services",
            "type":"Services"
        }
    ],
    "sg:phone":"+1 256 779 4428",
    "sg:postcode":"35959",
    "sg:province":"AL",
    "wof:name":"Odom Construction System",
    "wof:placetype":"venue"
},
  "geometry": {"coordinates":[-85.640413,34.233346],"type":"Point"}
}