{
  "type": "Feature",
  "properties": {
    "iso:country":"US",
    "sg:address":"199 Beechnut St",
    "sg:city":"Trussville",
    "sg:classifiers":[
        {
            "category":"Restaurant",
            "type":"Food & Drink"
        }
    ],
    "sg:phone":"+1 205 655 7272",
    "sg:postcode":"35173",
    "sg:province":"AL",
    "sg:tags":[
        "mexican"
    ],
    "wof:name":"Loros Mexican Restaurant",
    "wof:placetype":"venue"
},
  "geometry": {"coordinates":[-86.607221,33.615717],"type":"Point"}
}