{
  "type": "Feature",
  "properties": {
    "iso:country":"US",
    "sg:address":"201 E Willow St",
    "sg:city":"Scottsboro",
    "sg:classifiers":[
        {
            "category":"Retail",
            "subcategory":"Car Wash",
            "type":"Services"
        }
    ],
    "sg:phone":"+1 256 259 3221",
    "sg:postcode":"35768",
    "sg:province":"AL",
    "sg:tags":[
        "automobile",
        "detail",
        "clean"
    ],
    "wof:name":"Donnie's Willow Street Clean",
    "wof:placetype":"venue"
},
  "geometry": {"coordinates":[-86.033193,34.673563],"type":"Point"}
}