{
  "type": "Feature",
  "properties": {
    "addr:full":"1200 Old Talladega Hwy Sylacauga AL 35150",
    "addr:housenumber":"1200",
    "addr:postcode":"35150",
    "addr:street":"Old Talladega Hwy",
    "iso:country":"US",
    "sg:address":"1200 Old Talladega Hwy",
    "sg:city":"Sylacauga",
    "sg:classifiers":[
        {
            "category":"Autos & Motor Vehicles",
            "subcategory":"Fuel & Gas Station",
            "type":"Retail Goods"
        }
    ],
    "sg:phone":"+1 256 245 7918",
    "sg:postcode":"35150",
    "sg:province":"AL",
    "sg:tags":[
        "oil"
    ],
    "wof:name":"Shell",
    "wof:placetype":"venue"
},
  "geometry": {"coordinates":[-86.242875,33.185074],"type":"Point"}
}