{
  "type": "Feature",
  "properties": {
    "iso:country":"US",
    "sg:address":"735 Forestwood Dr",
    "sg:city":"Birmingham",
    "sg:classifiers":[
        {
            "category":"Farming",
            "subcategory":"Dairy Farm",
            "type":"Manufacturing & Wholesale Goods"
        }
    ],
    "sg:phone":"+1 205 798 0952",
    "sg:postcode":"35214",
    "sg:province":"AL",
    "wof:name":"Tradition Trk",
    "wof:placetype":"venue"
},
  "geometry": {"coordinates":[-86.886574,33.569002],"type":"Point"}
}