{
  "type": "Feature",
  "properties": {
    "iso:country":"US",
    "sg:address":"5654 Dogwood Trl",
    "sg:city":"Eight Mile",
    "sg:classifiers":[
        {
            "category":"Building & Trades",
            "subcategory":"Construction",
            "type":"Services"
        }
    ],
    "sg:phone":"+1 251 679 1938",
    "sg:postcode":"36613",
    "sg:province":"AL",
    "wof:name":"Goldman Construction Inc",
    "wof:placetype":"venue"
},
  "geometry": {"coordinates":[-88.176613,30.809885],"type":"Point"}
}