{
  "type": "Feature",
  "properties": {
    "iso:country":"US",
    "sg:address":"1231 S Union Ave",
    "sg:city":"Ozark",
    "sg:classifiers":[
        {
            "category":"Retail",
            "subcategory":"Car Wash",
            "type":"Services"
        }
    ],
    "sg:phone":"+1 334 774 1101",
    "sg:postcode":"36360",
    "sg:province":"AL",
    "sg:tags":[
        "carwash"
    ],
    "wof:name":"Jacksons Car Care",
    "wof:placetype":"venue"
},
  "geometry": {"coordinates":[-85.631625,31.437511],"type":"Point"}
}