{
  "type": "Feature",
  "properties": {
    "addr:full":"12099 Co Rd 37 Selma AL 36701",
    "addr:housenumber":"12099;37",
    "addr:postcode":"36701",
    "addr:street":"Co Rd",
    "iso:country":"US",
    "sg:address":"12099 Co Rd 37",
    "sg:city":"Selma",
    "sg:classifiers":[
        {
            "category":"Wholesale",
            "subcategory":"Construction Materials",
            "type":"Manufacturing & Wholesale Goods"
        },
        {
            "category":"Manufacturing",
            "subcategory":"Metals",
            "type":"Manufacturing & Wholesale Goods"
        }
    ],
    "sg:phone":"+1 334 872 2832",
    "sg:postcode":"36701",
    "sg:province":"AL",
    "sg:tags":[
        "mfg",
        "electrical",
        "architectural",
        "fence",
        "contractor"
    ],
    "wof:name":"Morrow Ornamental Iron Inc",
    "wof:placetype":"venue"
},
  "geometry": {"coordinates":[-86.997871,32.558024],"type":"Point"}
}