{
  "type": "Feature",
  "properties": {
    "iso:country":"US",
    "sg:address":"1215 Blount Ave",
    "sg:city":"Guntersville",
    "sg:classifiers":[
        {
            "category":"Building & Trades",
            "subcategory":"Plumbing",
            "type":"Services"
        }
    ],
    "sg:phone":"+1 256 582 8284",
    "sg:postcode":"35976",
    "sg:province":"AL",
    "sg:tags":[
        "plumbing"
    ],
    "wof:name":"Mazama Services LLC",
    "wof:placetype":"venue"
},
  "geometry": {"coordinates":[-86.299684,34.348299],"type":"Point"}
}