{
  "type": "Feature",
  "properties": {
    "addr:full":"1410 E Commerce St Greenville AL 36037",
    "addr:housenumber":"1410",
    "addr:postcode":"36037",
    "addr:street":"E Commerce St",
    "iso:country":"US",
    "sg:address":"1410 E Commerce St",
    "sg:city":"Greenville",
    "sg:classifiers":[
        {
            "category":"Autos & Motor Vehicles",
            "subcategory":"Automobile Sales",
            "type":"Retail Goods"
        }
    ],
    "sg:phone":"+1 334 382 2738",
    "sg:postcode":"36037",
    "sg:province":"AL",
    "sg:tags":[
        "used"
    ],
    "wof:name":"Simmons Auto Sales",
    "wof:placetype":"venue"
},
  "geometry": {"coordinates":[-86.606014,31.831279],"type":"Point"}
}