{
  "type": "Feature",
  "properties": {
    "addr:full":"2501 Hamilton Cir Pelham AL 35124",
    "addr:housenumber":"2501",
    "addr:postcode":"35124",
    "addr:street":"Hamilton Cir",
    "iso:country":"US",
    "sg:address":"2501 Hamilton Cir",
    "sg:city":"Pelham",
    "sg:classifiers":[
        {
            "category":"Professional",
            "subcategory":"Management & Consulting",
            "type":"Services"
        }
    ],
    "sg:phone":"+1 205 663 0272",
    "sg:postcode":"35124",
    "sg:province":"AL",
    "sg:tags":[
        "consultant"
    ],
    "wof:name":"D S & D Cast Solutions Inc",
    "wof:placetype":"venue"
},
  "geometry": {"coordinates":[-86.80956999999999,33.325078],"type":"Point"}
}