{
  "type": "Feature",
  "properties": {
    "iso:country":"US",
    "sg:address":"24815 Wolf Bay Ter",
    "sg:city":"Orange Beach",
    "sg:classifiers":[
        {
            "category":"Shopping",
            "subcategory":"Gifts & Souvenirs",
            "type":"Retail Goods"
        }
    ],
    "sg:phone":"+1 205 822 1818",
    "sg:postcode":"36561",
    "sg:province":"AL",
    "wof:name":"William Morris Home Fashions",
    "wof:placetype":"venue"
},
  "geometry": {"coordinates":[-87.599425,30.292965],"type":"Point"}
}