{
  "type": "Feature",
  "properties": {
    "iso:country":"US",
    "sg:address":"1015 S Memorial Dr",
    "sg:city":"Prattville",
    "sg:classifiers":[
        {
            "category":"Autos & Motor Vehicles",
            "subcategory":"Automobile Sales",
            "type":"Retail Goods"
        }
    ],
    "sg:phone":"+1 334 361 4030",
    "sg:postcode":"36067",
    "sg:province":"AL",
    "sg:tags":[
        "used"
    ],
    "wof:name":"Triple D Auto Sales",
    "wof:placetype":"venue"
},
  "geometry": {"coordinates":[-86.445695,32.454386],"type":"Point"}
}