{
  "type": "Feature",
  "properties": {
    "iso:country":"US",
    "sg:address":"601 Shoffner St",
    "sg:city":"East Brewton",
    "sg:classifiers":[
        {
            "category":"Professional",
            "subcategory":"Accounting & Tax Preparation",
            "type":"Services"
        }
    ],
    "sg:phone":"+1 251 867 9362",
    "sg:postcode":"36426",
    "sg:province":"AL",
    "sg:tags":[
        "accountant"
    ],
    "wof:name":"Hartman Blackmon & Kilgore",
    "wof:placetype":"venue"
},
  "geometry": {"coordinates":[-87.062097,31.096045],"type":"Point"}
}