{
  "type": "Feature",
  "properties": {
    "iso:country":"US",
    "sg:address":"7728 2nd Ave S",
    "sg:city":"Birmingham",
    "sg:classifiers":[
        {
            "category":"Health Services",
            "subcategory":"Doctor",
            "type":"Services"
        }
    ],
    "sg:phone":"+1 205 833 5295",
    "sg:postcode":"35206",
    "sg:province":"AL",
    "wof:name":"East Lake Family Dentistry",
    "wof:placetype":"venue"
},
  "geometry": {"coordinates":[-86.724484,33.560957],"type":"Point"}
}