{
  "type": "Feature",
  "properties": {
    "addr:full":"6368 Ingram Rd Deatsville AL 36022",
    "addr:housenumber":"6368",
    "addr:postcode":"36022",
    "addr:street":"Ingram Rd",
    "iso:country":"US",
    "sg:address":"6368 Ingram Rd",
    "sg:city":"Deatsville",
    "sg:classifiers":[
        {
            "category":"Personal",
            "subcategory":"Beauty Salon",
            "type":"Services"
        },
        {
            "category":"Personal",
            "subcategory":"Barber",
            "type":"Services"
        }
    ],
    "sg:phone":"+1 334 285 3112",
    "sg:postcode":"36022",
    "sg:province":"AL",
    "sg:tags":[
        "shop"
    ],
    "wof:name":"Country Style Shop & Tan",
    "wof:placetype":"venue"
},
  "geometry": {"coordinates":[-86.403497,32.590209],"type":"Point"}
}