{
  "type": "Feature",
  "properties": {
    "iso:country":"US",
    "sg:address":"109 Green Acres St",
    "sg:city":"Cropwell",
    "sg:classifiers":[
        {
            "category":"Professional",
            "type":"Services"
        }
    ],
    "sg:phone":"+1 205 338 1813",
    "sg:postcode":"35054",
    "sg:province":"AL",
    "wof:name":"Wesco 2 Inc",
    "wof:placetype":"venue"
},
  "geometry": {"coordinates":[-86.27643999999999,33.550809],"type":"Point"}
}