{
  "type": "Feature",
  "properties": {
    "addr:full":"234 Joyce Rd Laceys Spring AL 35754",
    "addr:housenumber":"234",
    "addr:postcode":"35754",
    "addr:street":"Joyce Rd",
    "iso:country":"US",
    "sg:address":"234 Joyce Rd",
    "sg:city":"Laceys Spring",
    "sg:classifiers":[
        {
            "category":"Building & Trades",
            "subcategory":"Electrical",
            "type":"Services"
        }
    ],
    "sg:phone":"+1 256 880 0486",
    "sg:postcode":"35754",
    "sg:province":"AL",
    "sg:tags":[
        "electrical",
        "contractor"
    ],
    "wof:name":"Belco",
    "wof:placetype":"venue"
},
  "geometry": {"coordinates":[-86.58407800000001,34.560922],"type":"Point"}
}