{
  "type": "Feature",
  "properties": {
    "iso:country":"US",
    "sg:address":"915 Merchant Walk",
    "sg:city":"Huntsville",
    "sg:classifiers":[
        {
            "category":"Banks & Credit Unions",
            "subcategory":"Bank",
            "type":"Services"
        }
    ],
    "sg:phone":"+1 256 539 9800",
    "sg:postcode":"35801",
    "sg:province":"AL",
    "sg:tags":[
        "loan",
        "real estate"
    ],
    "wof:name":"Hamilton Mortgage Corp",
    "wof:placetype":"venue"
},
  "geometry": {"coordinates":[-86.589881,34.712571],"type":"Point"}
}