{
  "type": "Feature",
  "properties": {
    "addr:full":"2918 20th Ave Valley AL 36854",
    "addr:housenumber":"2918",
    "addr:postcode":"36854",
    "addr:street":"20Th Ave",
    "iso:country":"US",
    "sg:address":"2918 20th Ave",
    "sg:city":"Valley",
    "sg:classifiers":[
        {
            "category":"Shopping",
            "subcategory":"Discount & Variety Stores",
            "type":"Retail Goods"
        },
        {
            "category":"Shopping",
            "subcategory":"Department Store",
            "type":"Retail Goods"
        }
    ],
    "sg:phone":"+1 334 768 3564",
    "sg:postcode":"36854",
    "sg:province":"AL",
    "sg:tags":[
        "shop"
    ],
    "wof:name":"Dollar General",
    "wof:placetype":"venue"
},
  "geometry": {"coordinates":[-85.152317,32.776555],"type":"Point"}
}