{
  "type": "Feature",
  "properties": {
    "iso:country":"US",
    "sg:address":"115 W Mill St",
    "sg:city":"Hartford",
    "sg:classifiers":[
        {
            "category":"Restaurant",
            "type":"Food & Drink"
        }
    ],
    "sg:phone":"+1 334 588 8889",
    "sg:postcode":"36344",
    "sg:province":"AL",
    "wof:name":"Super Wanton",
    "wof:placetype":"venue"
},
  "geometry": {"coordinates":[-85.696949,31.102249],"type":"Point"}
}