{
  "type": "Feature",
  "properties": {
    "iso:country":"US",
    "sg:address":"2101 Co Rd 7",
    "sg:city":"Florence",
    "sg:classifiers":[
        {
            "category":"Restaurant",
            "type":"Food & Drink"
        }
    ],
    "sg:phone":"+1 256 766 5912",
    "sg:postcode":"35633",
    "sg:province":"AL",
    "sg:tags":[
        "eating"
    ],
    "wof:name":"Drive In Chatn Chew",
    "wof:placetype":"venue"
},
  "geometry": {"coordinates":[-87.69774200000001,34.885827],"type":"Point"}
}