{
  "type": "Feature",
  "properties": {
    "iso:country":"US",
    "sg:address":"1717 S College St",
    "sg:city":"Auburn",
    "sg:classifiers":[
        {
            "category":"Banks & Credit Unions",
            "subcategory":"Bank",
            "type":"Services"
        }
    ],
    "sg:phone":"+1 334 502 7272",
    "sg:postcode":"36832",
    "sg:province":"AL",
    "wof:name":"Auburn Bank",
    "wof:placetype":"venue"
},
  "geometry": {"coordinates":[-85.498706,32.575342],"type":"Point"}
}