{
  "type": "Feature",
  "properties": {
    "iso:country":"US",
    "sg:address":"5506 Heatherbrooke Pkwy",
    "sg:city":"Birmingham",
    "sg:classifiers":[
        {
            "category":"Travel",
            "subcategory":"Hotels & Motels",
            "type":"Entertainment"
        }
    ],
    "sg:phone":"+1 205 408 8746",
    "sg:postcode":"35242",
    "sg:province":"AL",
    "sg:tags":[
        "operation"
    ],
    "wof:name":"Marriott Cluster Sales",
    "wof:placetype":"venue"
},
  "geometry": {"coordinates":[-86.699369,33.425022],"type":"Point"}
}