{
  "type": "Feature",
  "properties": {
    "iso:country":"US",
    "sg:address":"182 University Ln",
    "sg:city":"Tuscaloosa",
    "sg:classifiers":[
        {
            "category":"Restaurant",
            "type":"Food & Drink"
        }
    ],
    "sg:phone":"+1 205 556 5674",
    "sg:postcode":"35401",
    "sg:province":"AL",
    "sg:tags":[
        "eating"
    ],
    "wof:name":"Taco Casa",
    "wof:placetype":"venue"
},
  "geometry": {"coordinates":[-87.544231,33.18339],"type":"Point"}
}