{
  "type": "Feature",
  "properties": {
    "addr:full":"7115 McFarland Blvd Northport AL 35476",
    "addr:housenumber":"7115",
    "addr:postcode":"35476",
    "addr:street":"Mcfarland Blvd",
    "iso:country":"US",
    "sg:address":"7115 McFarland Blvd",
    "sg:city":"Northport",
    "sg:classifiers":[
        {
            "category":"Organizations",
            "subcategory":"Religious Organization",
            "type":"Services"
        }
    ],
    "sg:phone":"+1 205 333 7906",
    "sg:postcode":"35476",
    "sg:province":"AL",
    "sg:tags":[
        "church"
    ],
    "wof:name":"Trinity Christian Ctr",
    "wof:placetype":"venue"
},
  "geometry": {"coordinates":[-87.631012,33.23292],"type":"Point"}
}