{
  "type": "Feature",
  "properties": {
    "addr:full":"1023 E Main St Albertville AL 35951",
    "addr:housenumber":"1023",
    "addr:postcode":"35951",
    "addr:street":"E Main St",
    "iso:country":"US",
    "sg:address":"1023 E Main St",
    "sg:city":"Albertville",
    "sg:classifiers":[
        {
            "category":"Professional",
            "type":"Services"
        }
    ],
    "sg:phone":"+1 256 878 6407",
    "sg:postcode":"35951",
    "sg:province":"AL",
    "wof:name":"Odus W McBrier",
    "wof:placetype":"venue"
},
  "geometry": {"coordinates":[-86.186701,34.265346],"type":"Point"}
}