{
  "type": "Feature",
  "properties": {
    "addr:full":"8550 State Rte 21 Frisco City AL 36445",
    "addr:housenumber":"8550",
    "addr:postcode":"36445",
    "addr:street":"State Rte 21",
    "iso:country":"US",
    "sg:address":"8550 State Rte 21",
    "sg:city":"Frisco City",
    "sg:classifiers":[
        {
            "category":"Organizations",
            "subcategory":"Religious Organization",
            "type":"Services"
        }
    ],
    "sg:phone":"+1 251 267 3810",
    "sg:postcode":"36445",
    "sg:province":"AL",
    "sg:tags":[
        "church"
    ],
    "wof:name":"Megargel Assembly-God Church",
    "wof:placetype":"venue"
},
  "geometry": {"coordinates":[-87.42872699999999,31.381885],"type":"Point"}
}