{
  "type": "Feature",
  "properties": {
    "iso:country":"US",
    "sg:address":"40 Church St",
    "sg:city":"Birmingham",
    "sg:classifiers":[
        {
            "category":"Shopping",
            "subcategory":"Florist",
            "type":"Retail Goods"
        }
    ],
    "sg:phone":"+1 205 870 5061",
    "sg:postcode":"35213",
    "sg:province":"AL",
    "wof:name":"Lagniappe Designs Inc",
    "wof:placetype":"venue"
},
  "geometry": {"coordinates":[-86.754747,33.501299],"type":"Point"}
}