{
  "type": "Feature",
  "properties": {
    "addr:full":"3001 Memorial Pkwy NW Huntsville AL 35810",
    "addr:housenumber":"3001",
    "addr:postcode":"35810",
    "addr:street":"Memorial Pkwy Nw",
    "iso:country":"US",
    "sg:address":"3001 Memorial Pkwy NW",
    "sg:city":"Huntsville",
    "sg:classifiers":[
        {
            "category":"Restaurant",
            "type":"Food & Drink"
        }
    ],
    "sg:menulink":"http://www.allmenus.com/al/huntsville/96841-ihop/menu/",
    "sg:phone":"+1 256 288 0070",
    "sg:postcode":"35810",
    "sg:province":"AL",
    "sg:tags":[
        "sandwich",
        "salad",
        "burger",
        "soup",
        "american",
        "steakhouse",
        "wrap"
    ],
    "wof:name":"IHOP",
    "wof:placetype":"venue"
},
  "geometry": {"coordinates":[-86.589803,34.762202],"type":"Point"}
}