{
  "type": "Feature",
  "properties": {
    "iso:country":"US",
    "sg:address":"340 Queen Ann Rd",
    "sg:city":"Wetumpka",
    "sg:classifiers":[
        {
            "category":"Government",
            "subcategory":"Office",
            "type":"Public Place"
        }
    ],
    "sg:phone":"+1 334 567 6301",
    "sg:postcode":"36092",
    "sg:province":"AL",
    "sg:tags":[
        "agricultural",
        "regulation",
        "marketing"
    ],
    "wof:name":"Elmore Office",
    "wof:placetype":"venue"
},
  "geometry": {"coordinates":[-86.232856,32.536314],"type":"Point"}
}