{
  "type": "Feature",
  "properties": {
    "iso:country":"US",
    "sg:address":"3337 Cherrybrook Dr",
    "sg:city":"Graysville",
    "sg:classifiers":[
        {
            "category":"Building & Trades",
            "subcategory":"Plumbing",
            "type":"Services"
        }
    ],
    "sg:phone":"+1 205 674 3964",
    "sg:postcode":"35073",
    "sg:province":"AL",
    "wof:name":"Pickle Wade Septic Tank & Plumbling",
    "wof:placetype":"venue"
},
  "geometry": {"coordinates":[-86.966202,33.6605],"type":"Point"}
}