{
  "type": "Feature",
  "properties": {
    "iso:country":"US",
    "sg:address":"7759 Old Pascagoula Rd",
    "sg:city":"Theodore",
    "sg:classifiers":[
        {
            "category":"Home & Garden",
            "subcategory":"Home Furnishings",
            "type":"Retail Goods"
        }
    ],
    "sg:phone":"+1 251 653 5077",
    "sg:postcode":"36582",
    "sg:province":"AL",
    "sg:tags":[
        "lighting",
        "fixture"
    ],
    "wof:name":"Coastal Lighting and Supply In",
    "wof:placetype":"venue"
},
  "geometry": {"coordinates":[-88.223774,30.559964],"type":"Point"}
}