{
  "type": "Feature",
  "properties": {
    "iso:country":"US",
    "sg:address":"1206 Gault Ave S",
    "sg:city":"Fort Payne",
    "sg:classifiers":[
        {
            "category":"Retail",
            "subcategory":"Auto Rental",
            "type":"Services"
        }
    ],
    "sg:phone":"+1 256 845 6321",
    "sg:postcode":"35967",
    "sg:province":"AL",
    "sg:tags":[
        "truck",
        "trailer",
        "utility"
    ],
    "wof:name":"U-Haul",
    "wof:placetype":"venue"
},
  "geometry": {"coordinates":[-85.732822,34.429923],"type":"Point"}
}