{
  "type": "Feature",
  "properties": {
    "iso:country":"US",
    "sg:address":"1797 Glenwood Rd",
    "sg:city":"Morris",
    "sg:classifiers":[
        {
            "category":"Building & Trades",
            "subcategory":"Construction",
            "type":"Services"
        }
    ],
    "sg:phone":"+1 205 681 7966",
    "sg:postcode":"35116",
    "sg:province":"AL",
    "sg:tags":[
        "industrial",
        "contractor"
    ],
    "wof:name":"McCain Inc",
    "wof:placetype":"venue"
},
  "geometry": {"coordinates":[-86.76422700000001,33.721149],"type":"Point"}
}