{
  "type": "Feature",
  "properties": {
    "iso:country":"US",
    "sg:address":"1003 2nd Ave E",
    "sg:city":"Oneonta",
    "sg:classifiers":[
        {
            "category":"Restaurant",
            "type":"Food & Drink"
        }
    ],
    "sg:phone":"+1 205 625 5765",
    "sg:postcode":"35121",
    "sg:province":"AL",
    "sg:tags":[
        "eating"
    ],
    "wof:name":"Tonala Mexican Restaurant",
    "wof:placetype":"venue"
},
  "geometry": {"coordinates":[-86.464216,33.957052],"type":"Point"}
}