{
  "type": "Feature",
  "properties": {
    "iso:country":"US",
    "sg:address":"417 20th St N",
    "sg:city":"Birmingham",
    "sg:classifiers":[
        {
            "category":"Utilities",
            "subcategory":"Electric",
            "type":"Services"
        }
    ],
    "sg:phone":"+1 205 822 7257",
    "sg:postcode":"35203",
    "sg:province":"AL",
    "sg:tags":[
        "equipment",
        "tape",
        "dispensing"
    ],
    "wof:name":"Triner Scales-Sales And Service",
    "wof:placetype":"venue"
},
  "geometry": {"coordinates":[-86.807574,33.517356],"type":"Point"}
}