{
  "type": "Feature",
  "properties": {
    "addr:full":"901 Gault Ave N Fort Payne AL 35967",
    "addr:housenumber":"901",
    "addr:postcode":"35967",
    "addr:street":"Gault Ave N",
    "iso:country":"US",
    "sg:address":"901 Gault Ave N",
    "sg:city":"Fort Payne",
    "sg:classifiers":[
        {
            "category":"Retail",
            "subcategory":"Auto Repair",
            "type":"Services"
        }
    ],
    "sg:phone":"+1 256 845 1611",
    "sg:postcode":"35967",
    "sg:province":"AL",
    "sg:tags":[
        "automotive"
    ],
    "sg:website":"www.ftpayne.com",
    "wof:name":"Right Connection",
    "wof:placetype":"venue"
},
  "geometry": {"coordinates":[-85.713691,34.450714],"type":"Point"}
}