{
  "type": "Feature",
  "properties": {
    "iso:country":"US",
    "sg:address":"1011 Eastdale Mall",
    "sg:city":"Montgomery",
    "sg:classifiers":[
        {
            "category":"Shopping",
            "subcategory":"Jewelry",
            "type":"Retail Goods"
        }
    ],
    "sg:phone":"+1 334 271 7602",
    "sg:postcode":"36117",
    "sg:province":"AL",
    "sg:tags":[
        "jeweler"
    ],
    "wof:name":"Creative Accent",
    "wof:placetype":"venue"
},
  "geometry": {"coordinates":[-86.204539,32.385217],"type":"Point"}
}