{
  "type": "Feature",
  "properties": {
    "addr:full":"206 Wood Gate Dr Elmore AL 36025",
    "addr:housenumber":"206",
    "addr:postcode":"36025",
    "addr:street":"Wood Gate Dr",
    "iso:country":"US",
    "sg:address":"206 Wood Gate Dr",
    "sg:city":"Elmore",
    "sg:classifiers":[
        {
            "category":"Professional",
            "subcategory":"Management & Consulting",
            "type":"Services"
        }
    ],
    "sg:phone":"+1 334 285 0715",
    "sg:postcode":"36025",
    "sg:province":"AL",
    "sg:tags":[
        "business"
    ],
    "wof:name":"Performance Visions",
    "wof:placetype":"venue"
},
  "geometry": {"coordinates":[-86.351727,32.531934],"type":"Point"}
}