{
  "type": "Feature",
  "properties": {
    "iso:country":"US",
    "sg:address":"173 Crawford Rd",
    "sg:city":"Scottsboro",
    "sg:classifiers":[
        {
            "category":"Retail",
            "subcategory":"Repair Shop",
            "type":"Services"
        }
    ],
    "sg:phone":"+1 256 574 1150",
    "sg:postcode":"35769",
    "sg:province":"AL",
    "sg:tags":[
        "upholsterer"
    ],
    "wof:name":"Custom Covers Upholstery & Rpr",
    "wof:placetype":"venue"
},
  "geometry": {"coordinates":[-86.000463,34.65887],"type":"Point"}
}