{
  "type": "Feature",
  "properties": {
    "addr:full":"15342 Hillview Rd Coker AL 35452",
    "addr:housenumber":"15342",
    "addr:postcode":"35452",
    "addr:street":"Hillview Rd",
    "iso:country":"US",
    "sg:address":"15342 Hillview Rd",
    "sg:city":"Coker",
    "sg:classifiers":[
        {
            "category":"Building & Trades",
            "subcategory":"Electrical",
            "type":"Services"
        },
        {
            "category":"Retail",
            "subcategory":"Auto Repair",
            "type":"Services"
        }
    ],
    "sg:phone":"+1 205 361 0191",
    "sg:postcode":"35452",
    "sg:province":"AL",
    "sg:tags":[
        "automotive",
        "electric",
        "contractor"
    ],
    "wof:name":"VSR Electrical Servics Inc",
    "wof:placetype":"venue"
},
  "geometry": {"coordinates":[-87.71612,33.241715],"type":"Point"}
}