{
  "type": "Feature",
  "properties": {
    "iso:country":"US",
    "sg:address":"186 Co Rd 1672",
    "sg:city":"Cullman",
    "sg:classifiers":[
        {
            "category":"Retail",
            "subcategory":"Auto Repair",
            "type":"Services"
        }
    ],
    "sg:phone":"+1 256 796 5614",
    "sg:postcode":"35058",
    "sg:province":"AL",
    "sg:tags":[
        "general"
    ],
    "wof:name":"Out Back Auto Service",
    "wof:placetype":"venue"
},
  "geometry": {"coordinates":[-86.667555,34.229422],"type":"Point"}
}