{
  "type": "Feature",
  "properties": {
    "iso:country":"US",
    "sg:address":"9491 Riverside Rd",
    "sg:city":"Athens",
    "sg:classifiers":[
        {
            "category":"Shopping",
            "subcategory":"Used Merchandise",
            "type":"Retail Goods"
        }
    ],
    "sg:phone":"+1 256 777 0844",
    "sg:postcode":"35611",
    "sg:province":"AL",
    "wof:name":"Straight Stuff Antiques",
    "wof:placetype":"venue"
},
  "geometry": {"coordinates":[-87.143275,34.740483],"type":"Point"}
}