{
  "type": "Feature",
  "properties": {
    "iso:country":"US",
    "sg:address":"308 Natasha Dr",
    "sg:city":"Albertville",
    "sg:classifiers":[
        {
            "category":"Retail",
            "subcategory":"Auto Repair",
            "type":"Services"
        }
    ],
    "sg:phone":"+1 256 878 6801",
    "sg:postcode":"35950",
    "sg:province":"AL",
    "sg:tags":[
        "body",
        "automobile",
        "painting"
    ],
    "wof:name":"Tonys Frame Shop",
    "wof:placetype":"venue"
},
  "geometry": {"coordinates":[-86.17739899999999,34.246473],"type":"Point"}
}