{
  "type": "Feature",
  "properties": {
    "iso:country":"US",
    "sg:address":"3406 Florence Blvd",
    "sg:city":"Florence",
    "sg:classifiers":[
        {
            "category":"Restaurant",
            "type":"Food & Drink"
        }
    ],
    "sg:phone":"+1 256 766 6866",
    "sg:postcode":"35634",
    "sg:province":"AL",
    "wof:name":"Newbern's Restaurant",
    "wof:placetype":"venue"
},
  "geometry": {"coordinates":[-87.607176,34.836185],"type":"Point"}
}