{
  "type": "Feature",
  "properties": {
    "addr:full":"8050 Wards Ln Semmes AL 36575",
    "addr:housenumber":"8050",
    "addr:postcode":"36575",
    "addr:street":"Wards Ln",
    "iso:country":"US",
    "sg:address":"8050 Wards Ln",
    "sg:city":"Semmes",
    "sg:classifiers":[
        {
            "category":"Retail",
            "subcategory":"Auto Repair",
            "type":"Services"
        }
    ],
    "sg:phone":"+1 251 422 4400",
    "sg:postcode":"36575",
    "sg:province":"AL",
    "sg:tags":[
        "automobile",
        "top",
        "upholstery"
    ],
    "wof:name":"A J's Upholstery",
    "wof:placetype":"venue"
},
  "geometry": {"coordinates":[-88.229839,30.756833],"type":"Point"}
}