{
  "type": "Feature",
  "properties": {
    "iso:country":"US",
    "sg:address":"279 Pine Hollow Dr",
    "sg:city":"Newell",
    "sg:classifiers":[
        {
            "category":"Freight",
            "type":"Transportation"
        }
    ],
    "sg:phone":"+1 256 363 2018",
    "sg:postcode":"36280",
    "sg:province":"AL",
    "sg:tags":[
        "hauling",
        "trucking"
    ],
    "wof:name":"Cross Roads Trucking",
    "wof:placetype":"venue"
},
  "geometry": {"coordinates":[-85.496994,33.424772],"type":"Point"}
}