{
  "type": "Feature",
  "properties": {
    "iso:country":"US",
    "sg:address":"27418 US Hwy 98",
    "sg:city":"Elberta",
    "sg:classifiers":[
        {
            "category":"Building & Trades",
            "subcategory":"Construction",
            "type":"Services"
        }
    ],
    "sg:phone":"+1 251 986 3168",
    "sg:postcode":"36530",
    "sg:province":"AL",
    "sg:tags":[
        "subcontractor",
        "work",
        "mill"
    ],
    "wof:name":"Autumn Custom Millwork L L C",
    "wof:placetype":"venue"
},
  "geometry": {"coordinates":[-87.560855,30.414379],"type":"Point"}
}