{
  "type": "Feature",
  "properties": {
    "iso:country":"US",
    "sg:address":"9188 Woodland Dr",
    "sg:city":"Elberta",
    "sg:classifiers":[
        {
            "category":"Building & Trades",
            "subcategory":"Landscaping Services",
            "type":"Services"
        }
    ],
    "sg:phone":"+1 251 987 5105",
    "sg:postcode":"36530",
    "sg:province":"AL",
    "wof:name":"Lawn Service & Maintenance",
    "wof:placetype":"venue"
},
  "geometry": {"coordinates":[-87.568691,30.356489],"type":"Point"}
}