{
  "type": "Feature",
  "properties": {
    "iso:country":"US",
    "sg:address":"2204 Whitesburg Dr S",
    "sg:city":"Huntsville",
    "sg:classifiers":[
        {
            "category":"Building & Trades",
            "subcategory":"Construction",
            "type":"Services"
        }
    ],
    "sg:phone":"+1 256 518 9457",
    "sg:postcode":"35801",
    "sg:province":"AL",
    "sg:tags":[
        "general",
        "contractor"
    ],
    "sg:website":"www.kenmcdanielhomes.com",
    "wof:name":"Ken Mc Daniel Homes Inc",
    "wof:placetype":"venue"
},
  "geometry": {"coordinates":[-86.577785,34.717411],"type":"Point"}
}