{
  "type": "Feature",
  "properties": {
    "addr:full":"892 Kokomo Rd Georgiana AL 36033",
    "addr:postcode":"36033",
    "addr:street":"892 Kokomo Rd",
    "iso:country":"US",
    "sg:address":"892 Kokomo Rd",
    "sg:city":"Georgiana",
    "sg:classifiers":[
        {
            "category":"Professional",
            "type":"Services"
        }
    ],
    "sg:phone":"+1 334 376 9962",
    "sg:postcode":"36033",
    "sg:province":"AL",
    "sg:tags":[
        "establishment"
    ],
    "wof:name":"Feagin Crystella",
    "wof:placetype":"venue"
},
  "geometry": {"coordinates":[-86.75135400000001,31.592245],"type":"Point"}
}