{
  "type": "Feature",
  "properties": {
    "addr:full":"2501 27th St N Birmingham AL 35234",
    "addr:housenumber":"2501",
    "addr:postcode":"35234",
    "addr:street":"27Th St N",
    "iso:country":"US",
    "sg:address":"2501 27th St N",
    "sg:city":"Birmingham",
    "sg:classifiers":[
        {
            "category":"Freight",
            "type":"Transportation"
        }
    ],
    "sg:phone":"+1 205 328 6009",
    "sg:postcode":"35234",
    "sg:province":"AL",
    "sg:tags":[
        "trucking"
    ],
    "wof:name":"Church Transportation & Lgstcs",
    "wof:placetype":"venue"
},
  "geometry": {"coordinates":[-86.81444399999999,33.547191],"type":"Point"}
}