{
  "type": "Feature",
  "properties": {
    "iso:country":"US",
    "sg:address":"1868 E Main St",
    "sg:city":"Prattville",
    "sg:classifiers":[
        {
            "category":"Shopping",
            "subcategory":"Gifts & Souvenirs",
            "type":"Retail Goods"
        }
    ],
    "sg:phone":"+1 334 365 4155",
    "sg:postcode":"36066",
    "sg:province":"AL",
    "sg:tags":[
        "shop",
        "cards"
    ],
    "wof:name":"Scot's Hallmark",
    "wof:placetype":"venue"
},
  "geometry": {"coordinates":[-86.420545,32.460437],"type":"Point"}
}