{
  "type": "Feature",
  "properties": {
    "iso:country":"US",
    "sg:address":"5510 US Hwy 280",
    "sg:city":"Birmingham",
    "sg:classifiers":[
        {
            "category":"Travel",
            "subcategory":"Travel Agent",
            "type":"Entertainment"
        }
    ],
    "sg:phone":"+1 205 980 4944",
    "sg:postcode":"35242",
    "sg:province":"AL",
    "sg:tags":[
        "agency"
    ],
    "wof:name":"Travel Network",
    "wof:placetype":"venue"
},
  "geometry": {"coordinates":[-86.663977,33.407053],"type":"Point"}
}