{
  "type": "Feature",
  "properties": {
    "iso:country":"US",
    "sg:address":"10122 US Hwy 431",
    "sg:city":"New Hope",
    "sg:classifiers":[
        {
            "category":"Food & Beverages",
            "subcategory":"Groceries & Convenience Stores",
            "type":"Retail Goods"
        }
    ],
    "sg:phone":"+1 256 723 4115",
    "sg:postcode":"35760",
    "sg:province":"AL",
    "wof:name":"Kim's Food Shop",
    "wof:placetype":"venue"
},
  "geometry": {"coordinates":[-86.433742,34.551173],"type":"Point"}
}