{
  "type": "Feature",
  "properties": {
    "iso:country":"US",
    "sg:address":"8606 US Hwy 431",
    "sg:city":"Owens Cross Roads",
    "sg:classifiers":[
        {
            "category":"Utilities",
            "subcategory":"Fuel Oil & Lpg",
            "type":"Services"
        }
    ],
    "sg:phone":"+1 256 725 2818",
    "sg:postcode":"35763",
    "sg:province":"AL",
    "sg:tags":[
        "liquefied",
        "gas",
        "petroleum"
    ],
    "wof:name":"Cornerstone Propane LP",
    "wof:placetype":"venue"
},
  "geometry": {"coordinates":[-86.45298200000001,34.596607],"type":"Point"}
}