{
  "type": "Feature",
  "properties": {
    "addr:full":"600 Blvd South SW Huntsville AL 35802",
    "addr:housenumber":"600",
    "addr:postcode":"35802",
    "addr:street":"Blvd South Sw",
    "iso:country":"US",
    "sg:address":"600 Blvd South SW",
    "sg:city":"Huntsville",
    "sg:classifiers":[
        {
            "category":"Professional",
            "subcategory":"Engineering",
            "type":"Services"
        },
        {
            "category":"Manufacturing",
            "subcategory":"Tools & Machinery",
            "type":"Manufacturing & Wholesale Goods"
        }
    ],
    "sg:phone":"+1 256 705 3535",
    "sg:postcode":"35802",
    "sg:province":"AL",
    "sg:tags":[
        "industry",
        "aerospace"
    ],
    "wof:name":"Peduzzi Associates",
    "wof:placetype":"venue"
},
  "geometry": {"coordinates":[-86.57537000000001,34.669621],"type":"Point"}
}