{
  "type": "Feature",
  "properties": {
    "iso:country":"US",
    "sg:address":"311 Applegate Pkwy",
    "sg:city":"Pelham",
    "sg:classifiers":[
        {
            "category":"Wholesale",
            "subcategory":"Electrical",
            "type":"Manufacturing & Wholesale Goods"
        }
    ],
    "sg:phone":"+1 205 620 4000",
    "sg:postcode":"35124",
    "sg:province":"AL",
    "sg:tags":[
        "control"
    ],
    "wof:name":"Hile Controls Of Alabama",
    "wof:placetype":"venue"
},
  "geometry": {"coordinates":[-86.786923,33.273521],"type":"Point"}
}