{
  "type": "Feature",
  "properties": {
    "iso:country":"US",
    "sg:address":"3337 Rainbow Dr",
    "sg:city":"Rainbow City",
    "sg:classifiers":[
        {
            "category":"Restaurant",
            "type":"Food & Drink"
        }
    ],
    "sg:phone":"+1 256 442 8530",
    "sg:postcode":"35906",
    "sg:province":"AL",
    "wof:name":"Wendy's",
    "wof:placetype":"venue"
},
  "geometry": {"coordinates":[-86.03523,33.959961],"type":"Point"}
}