{
  "type": "Feature",
  "properties": {
    "addr:full":"19765 N 3rd St Citronelle AL 36522",
    "addr:housenumber":"19765",
    "addr:postcode":"36522",
    "addr:street":"N 3Rd St",
    "iso:country":"US",
    "sg:address":"19765 N 3rd St",
    "sg:city":"Citronelle",
    "sg:classifiers":[
        {
            "category":"Restaurant",
            "type":"Food & Drink"
        }
    ],
    "sg:menulink":"http://www.allmenus.com/al/citronelle/154160-hardees/menu/",
    "sg:phone":"+1 251 866 0325",
    "sg:postcode":"36522",
    "sg:province":"AL",
    "sg:tags":[
        "burger",
        "american"
    ],
    "wof:name":"Hardee's",
    "wof:placetype":"venue"
},
  "geometry": {"coordinates":[-88.238128,31.103041],"type":"Point"}
}