{
  "type": "Feature",
  "properties": {
    "iso:country":"US",
    "sg:address":"60 Springhill Church Rd",
    "sg:city":"Gordon",
    "sg:classifiers":[
        {
            "category":"Farming",
            "subcategory":"Farm",
            "type":"Manufacturing & Wholesale Goods"
        }
    ],
    "sg:phone":"+1 334 522 3501",
    "sg:postcode":"36343",
    "sg:province":"AL",
    "sg:tags":[
        "crop",
        "general"
    ],
    "wof:name":"Williams Farm Inc",
    "wof:placetype":"venue"
},
  "geometry": {"coordinates":[-85.097608,31.13316],"type":"Point"}
}