{
  "type": "Feature",
  "properties": {
    "iso:country":"US",
    "sg:address":"104 Betty Cir",
    "sg:city":"Daphne",
    "sg:classifiers":[
        {
            "category":"Building & Trades",
            "subcategory":"Construction",
            "type":"Services"
        }
    ],
    "sg:phone":"+1 251 621 8416",
    "sg:postcode":"36526",
    "sg:province":"AL",
    "sg:tags":[
        "contractor"
    ],
    "wof:name":"Brad Kilborn Construction",
    "wof:placetype":"venue"
},
  "geometry": {"coordinates":[-87.878566,30.648381],"type":"Point"}
}