{
  "type": "Feature",
  "properties": {
    "iso:country":"US",
    "sg:address":"2091 Blackshear Dr",
    "sg:city":"Montgomery",
    "sg:classifiers":[
        {
            "category":"Building & Trades",
            "subcategory":"Construction",
            "type":"Services"
        }
    ],
    "sg:phone":"+1 334 265 1700",
    "sg:postcode":"36108",
    "sg:province":"AL",
    "sg:tags":[
        "project"
    ],
    "wof:name":"Sippial Electric & Constr Co",
    "wof:placetype":"venue"
},
  "geometry": {"coordinates":[-86.348819,32.362344],"type":"Point"}
}