{
  "type": "Feature",
  "properties": {
    "iso:country":"US",
    "sg:address":"2250 US Hwy 43",
    "sg:city":"Winfield",
    "sg:classifiers":[
        {
            "category":"Utilities",
            "subcategory":"Mobile Phone",
            "type":"Services"
        }
    ],
    "sg:phone":"+1 205 487 1577",
    "sg:postcode":"35594",
    "sg:province":"AL",
    "sg:tags":[
        "telephone",
        "cellular"
    ],
    "wof:name":"Wireless Innovations",
    "wof:placetype":"venue"
},
  "geometry": {"coordinates":[-87.832375,33.933652],"type":"Point"}
}