{
  "type": "Feature",
  "properties": {
    "iso:country":"US",
    "sg:address":"6751 Moffett Rd",
    "sg:city":"Mobile",
    "sg:classifiers":[
        {
            "category":"Travel",
            "subcategory":"Hotels & Motels",
            "type":"Entertainment"
        }
    ],
    "sg:phone":"+1 251 344 0538",
    "sg:postcode":"36618",
    "sg:province":"AL",
    "sg:tags":[
        "operation",
        "real estate"
    ],
    "wof:name":"Lyle Realty",
    "wof:placetype":"venue"
},
  "geometry": {"coordinates":[-88.201342,30.753277],"type":"Point"}
}