{
  "type": "Feature",
  "properties": {
    "iso:country":"US",
    "sg:address":"4049 Dalewood St",
    "sg:city":"Northport",
    "sg:classifiers":[
        {
            "category":"Professional",
            "subcategory":"Management & Consulting",
            "type":"Services"
        }
    ],
    "sg:phone":"+1 205 333 2477",
    "sg:postcode":"35475",
    "sg:province":"AL",
    "sg:website":"www.sufa.com",
    "wof:name":"Southern Urban Forestry Assoc",
    "wof:placetype":"venue"
},
  "geometry": {"coordinates":[-87.596892,33.2998],"type":"Point"}
}