{
  "type": "Feature",
  "properties": {
    "addr:full":"1535 Kinsey Rd Dothan AL 36303",
    "addr:housenumber":"1535",
    "addr:postcode":"36303",
    "addr:street":"Kinsey Rd",
    "iso:country":"US",
    "sg:address":"1535 Kinsey Rd",
    "sg:city":"Dothan",
    "sg:classifiers":[
        {
            "category":"Wholesale",
            "subcategory":"Hardware",
            "type":"Manufacturing & Wholesale Goods"
        }
    ],
    "sg:phone":"+1 334 793 2330",
    "sg:postcode":"36303",
    "sg:province":"AL",
    "sg:tags":[
        "fastener"
    ],
    "wof:name":"Fastener Service Inc",
    "wof:placetype":"venue"
},
  "geometry": {"coordinates":[-85.37835800000001,31.24513],"type":"Point"}
}