{
  "type": "Feature",
  "properties": {
    "addr:full":"3299 Bel Air Mall Mobile AL 36606",
    "addr:housenumber":"3299",
    "addr:postcode":"36606",
    "addr:street":"Bel Air Mall",
    "iso:country":"US",
    "sg:address":"3299 Bel Air Mall",
    "sg:city":"Mobile",
    "sg:classifiers":[
        {
            "category":"Shopping",
            "subcategory":"Music",
            "type":"Retail Goods"
        }
    ],
    "sg:phone":"+1 251 479 2350",
    "sg:postcode":"36606",
    "sg:province":"AL",
    "sg:tags":[
        "video",
        "disc",
        "tape",
        "cassette"
    ],
    "wof:name":"Suncoast Motion Picture Co",
    "wof:placetype":"venue"
},
  "geometry": {"coordinates":[-88.123287,30.673331],"type":"Point"}
}