{
  "type": "Feature",
  "properties": {
    "iso:country":"US",
    "sg:address":"13396 Grants Creek Rd",
    "sg:city":"Fosters",
    "sg:classifiers":[
        {
            "category":"Organizations",
            "subcategory":"Religious Organization",
            "type":"Services"
        }
    ],
    "sg:phone":"+1 205 752 4354",
    "sg:postcode":"35463",
    "sg:province":"AL",
    "sg:tags":[
        "church"
    ],
    "wof:name":"Grants Creek Baptist Church",
    "wof:placetype":"venue"
},
  "geometry": {"coordinates":[-87.707024,33.096071],"type":"Point"}
}