{
  "type": "Feature",
  "properties": {
    "addr:full":"6755 University Dr NW Huntsville AL 35806",
    "addr:housenumber":"6755",
    "addr:postcode":"35806",
    "addr:street":"University Dr Nw",
    "iso:country":"US",
    "sg:address":"6755 University Dr NW",
    "sg:city":"Huntsville",
    "sg:classifiers":[
        {
            "category":"Shopping",
            "subcategory":"Bicycles & Sporting Goods",
            "type":"Retail Goods"
        }
    ],
    "sg:phone":"+1 256 489 4930",
    "sg:postcode":"35806",
    "sg:province":"AL",
    "wof:name":"Philly's Hot Corner",
    "wof:placetype":"venue"
},
  "geometry": {"coordinates":[-86.699309,34.750569],"type":"Point"}
}