{
  "type": "Feature",
  "properties": {
    "iso:country":"US",
    "sg:address":"930 Chickakee Rd",
    "sg:city":"Haleyville",
    "sg:classifiers":[
        {
            "category":"Professional",
            "type":"Services"
        }
    ],
    "sg:phone":"+1 205 486 9919",
    "sg:postcode":"35565",
    "sg:province":"AL",
    "wof:name":"Lifestyle Services",
    "wof:placetype":"venue"
},
  "geometry": {"coordinates":[-87.61797799999999,34.265997],"type":"Point"}
}