{
  "type": "Feature",
  "properties": {
    "iso:country":"US",
    "sg:address":"29253 US Hwy 98",
    "sg:city":"Elberta",
    "sg:classifiers":[
        {
            "category":"Autos & Motor Vehicles",
            "subcategory":"Automobile Sales",
            "type":"Retail Goods"
        }
    ],
    "sg:phone":"+1 251 986 6516",
    "sg:postcode":"36530",
    "sg:province":"AL",
    "sg:tags":[
        "car",
        "dealer"
    ],
    "wof:name":"Bay Auto Sales",
    "wof:placetype":"venue"
},
  "geometry": {"coordinates":[-87.529963,30.414428],"type":"Point"}
}