{
  "type": "Feature",
  "properties": {
    "addr:full":"177 E Fleming Rd Montgomery AL 36105",
    "addr:housenumber":"177",
    "addr:postcode":"36105",
    "addr:street":"E Fleming Rd",
    "iso:country":"US",
    "sg:address":"177 E Fleming Rd",
    "sg:city":"Montgomery",
    "sg:classifiers":[
        {
            "category":"Building & Trades",
            "subcategory":"Construction",
            "type":"Services"
        }
    ],
    "sg:phone":"+1 334 613 6749",
    "sg:postcode":"36105",
    "sg:province":"AL",
    "wof:name":"Star Construction LLC",
    "wof:placetype":"venue"
},
  "geometry": {"coordinates":[-86.30270899999999,32.322706],"type":"Point"}
}