{
  "type": "Feature",
  "properties": {
    "addr:full":"7823 State Rte 59 Foley AL 36535",
    "addr:housenumber":"7823",
    "addr:postcode":"36535",
    "addr:street":"State Rte 59",
    "iso:country":"US",
    "sg:address":"7823 State Rte 59",
    "sg:city":"Foley",
    "sg:classifiers":[
        {
            "category":"Professional",
            "subcategory":"Lawyer & Legal Services",
            "type":"Services"
        }
    ],
    "sg:phone":"+1 251 955 5155",
    "sg:postcode":"36535",
    "sg:province":"AL",
    "sg:tags":[
        "attorney"
    ],
    "wof:name":"Stone Granade & Crosby PC Inc",
    "wof:placetype":"venue"
},
  "geometry": {"coordinates":[-87.683053,30.350168],"type":"Point"}
}