{
  "type": "Feature",
  "properties": {
    "addr:full":"1608 Hwy 77 Gadsden AL 35907",
    "addr:housenumber":"1608",
    "addr:postcode":"35907",
    "addr:street":"Hwy 77",
    "iso:country":"US",
    "sg:address":"1608 Hwy 77",
    "sg:city":"Gadsden",
    "sg:classifiers":[
        {
            "category":"Personal",
            "subcategory":"Beauty Salon",
            "type":"Services"
        }
    ],
    "sg:phone":"+1 256 442 6111",
    "sg:postcode":"35907",
    "sg:province":"AL",
    "sg:tags":[
        "shop"
    ],
    "wof:name":"Cutting Edge",
    "wof:placetype":"venue"
},
  "geometry": {"coordinates":[-86.0239,33.929318],"type":"Point"}
}