{
  "type": "Feature",
  "properties": {
    "iso:country":"US",
    "sg:address":"2400 Riverchase Galleria",
    "sg:city":"Birmingham",
    "sg:classifiers":[
        {
            "category":"Shopping",
            "subcategory":"Clothing, Apparel, & Fashions",
            "type":"Retail Goods"
        }
    ],
    "sg:phone":"+1 205 403 0901",
    "sg:postcode":"35244",
    "sg:province":"AL",
    "sg:tags":[
        "maternity",
        "wear"
    ],
    "wof:name":"Motherhood Maternity",
    "wof:placetype":"venue"
},
  "geometry": {"coordinates":[-86.81134900000001,33.379158],"type":"Point"}
}