{
  "type": "Feature",
  "properties": {
    "iso:country":"US",
    "sg:address":"303 Jackson Ave N",
    "sg:city":"Russellville",
    "sg:classifiers":[
        {
            "category":"Shopping",
            "subcategory":"Florist",
            "type":"Retail Goods"
        }
    ],
    "sg:phone":"+1 256 356 2695",
    "sg:postcode":"35653",
    "sg:province":"AL",
    "wof:name":"Hall's Florist & Gift Shop Inc",
    "wof:placetype":"venue"
},
  "geometry": {"coordinates":[-87.728575,34.508573],"type":"Point"}
}