{
  "type": "Feature",
  "properties": {
    "iso:country":"US",
    "sg:address":"1009 Co Rd 332",
    "sg:city":"Pelham",
    "sg:classifiers":[
        {
            "category":"Organizations",
            "subcategory":"Religious Organization",
            "type":"Services"
        }
    ],
    "sg:phone":"+1 205 620 5545",
    "sg:postcode":"35124",
    "sg:province":"AL",
    "wof:name":"Word of God Company",
    "wof:placetype":"venue"
},
  "geometry": {"coordinates":[-86.765701,33.279765],"type":"Point"}
}