{
  "type": "Feature",
  "properties": {
    "iso:country":"US",
    "sg:address":"101 1st St",
    "sg:city":"Warrior",
    "sg:classifiers":[
        {
            "category":"Education",
            "subcategory":"Library",
            "type":"Public Place"
        }
    ],
    "sg:phone":"+1 205 647 3006",
    "sg:postcode":"35180",
    "sg:province":"AL",
    "sg:tags":[
        "executive"
    ],
    "wof:name":"Evelyn Thrnton Warrior Pub Lib",
    "wof:placetype":"venue"
},
  "geometry": {"coordinates":[-86.80449,33.813224],"type":"Point"}
}