{
  "type": "Feature",
  "properties": {
    "addr:full":"1924 Green Acres Dr Montgomery AL 36106",
    "addr:housenumber":"1924",
    "addr:postcode":"36106",
    "addr:street":"Green Acres Dr",
    "iso:country":"US",
    "sg:address":"1924 Green Acres Dr",
    "sg:city":"Montgomery",
    "sg:classifiers":[
        {
            "category":"Shopping",
            "subcategory":"Clothing, Apparel, & Fashions",
            "type":"Retail Goods"
        }
    ],
    "sg:phone":"+1 334 284 4373",
    "sg:postcode":"36106",
    "sg:province":"AL",
    "wof:name":"Stones Designer Unique Botique",
    "wof:placetype":"venue"
},
  "geometry": {"coordinates":[-86.24199299999999,32.349219],"type":"Point"}
}