{
  "type": "Feature",
  "properties": {
    "iso:country":"US",
    "sg:address":"6146 Norris Mill Rd",
    "sg:city":"Hartselle",
    "sg:classifiers":[
        {
            "category":"Manufacturing",
            "subcategory":"Toys & Sporting Goods",
            "type":"Manufacturing & Wholesale Goods"
        }
    ],
    "sg:phone":"+1 256 751 0681",
    "sg:postcode":"35640",
    "sg:province":"AL",
    "sg:tags":[
        "mfg"
    ],
    "wof:name":"Kreative Keepsakes",
    "wof:placetype":"venue"
},
  "geometry": {"coordinates":[-86.99529800000001,34.477918],"type":"Point"}
}