{
  "type": "Feature",
  "properties": {
    "addr:full":"7346 Moores Mill Rd Huntsville AL 35811",
    "addr:housenumber":"7346",
    "addr:postcode":"35811",
    "addr:street":"Moores Mill Rd",
    "iso:country":"US",
    "sg:address":"7346 Moores Mill Rd",
    "sg:city":"Huntsville",
    "sg:classifiers":[
        {
            "category":"Food & Beverages",
            "subcategory":"Groceries & Convenience Stores",
            "type":"Retail Goods"
        }
    ],
    "sg:phone":"+1 256 851 9672",
    "sg:postcode":"35811",
    "sg:province":"AL",
    "sg:tags":[
        "station",
        "gasoline"
    ],
    "wof:name":"Moores Mill Grocery",
    "wof:placetype":"venue"
},
  "geometry": {"coordinates":[-86.51919100000001,34.837413],"type":"Point"}
}