{
  "type": "Feature",
  "properties": {
    "iso:country":"US",
    "sg:address":"404 Main St W",
    "sg:city":"Rainsville",
    "sg:classifiers":[
        {
            "category":"Building & Trades",
            "subcategory":"Pest Control",
            "type":"Services"
        }
    ],
    "sg:phone":"+1 256 638 4592",
    "sg:postcode":"35986",
    "sg:province":"AL",
    "sg:website":"www.morrispestcontrol.com",
    "wof:name":"Morris Pest Control",
    "wof:placetype":"venue"
},
  "geometry": {"coordinates":[-85.853236,34.498113],"type":"Point"}
}