{
  "type": "Feature",
  "properties": {
    "addr:full":"14002 Graylynn Dr SW Huntsville AL 35803",
    "addr:housenumber":"14002",
    "addr:postcode":"35803",
    "addr:street":"Graylynn Dr Sw",
    "iso:country":"US",
    "sg:address":"14002 Graylynn Dr SW",
    "sg:city":"Huntsville",
    "sg:classifiers":[
        {
            "category":"Building & Trades",
            "subcategory":"Construction",
            "type":"Services"
        }
    ],
    "sg:phone":"+1 256 883 7470",
    "sg:postcode":"35803",
    "sg:province":"AL",
    "sg:tags":[
        "hanging",
        "contractor"
    ],
    "wof:name":"Painters Touch",
    "wof:placetype":"venue"
},
  "geometry": {"coordinates":[-86.582306,34.599387],"type":"Point"}
}