{
  "type": "Feature",
  "properties": {
    "addr:full":"302 6th Ave NW Attalla AL 35954",
    "addr:housenumber":"302",
    "addr:postcode":"35954",
    "addr:street":"6Th Ave Nw Attalla",
    "iso:country":"US",
    "sg:address":"302 6th Ave NW",
    "sg:city":"Attalla",
    "sg:classifiers":[
        {
            "category":"Communications",
            "type":"Services"
        }
    ],
    "sg:phone":"+1 256 570 0963",
    "sg:postcode":"35954",
    "sg:province":"AL",
    "wof:name":"Inmate Communications Inc",
    "wof:placetype":"venue"
},
  "geometry": {"coordinates":[-86.088064,34.023649],"type":"Point"}
}