{
  "type": "Feature",
  "properties": {
    "iso:country":"US",
    "sg:address":"236 Hillsdale Dr",
    "sg:city":"Scottsboro",
    "sg:classifiers":[
        {
            "category":"Utilities",
            "subcategory":"Telephone",
            "type":"Services"
        }
    ],
    "sg:phone":"+1 256 259 6281",
    "sg:postcode":"35769",
    "sg:province":"AL",
    "sg:tags":[
        "communications"
    ],
    "wof:name":"Dulaney Tele Communications",
    "wof:placetype":"venue"
},
  "geometry": {"coordinates":[-86.058588,34.608808],"type":"Point"}
}