{
  "type": "Feature",
  "properties": {
    "iso:country":"US",
    "sg:address":"2215 US Hwy 98",
    "sg:city":"Daphne",
    "sg:classifiers":[
        {
            "category":"Retail",
            "subcategory":"Auto Rental",
            "type":"Services"
        }
    ],
    "sg:phone":"+1 251 621 7087",
    "sg:postcode":"36526",
    "sg:province":"AL",
    "sg:tags":[
        "renting",
        "truck",
        "leasing"
    ],
    "wof:name":"U-Haul Co",
    "wof:placetype":"venue"
},
  "geometry": {"coordinates":[-87.890982,30.549875],"type":"Point"}
}