{
  "type": "Feature",
  "properties": {
    "iso:country":"US",
    "sg:address":"27294 Gatlin Rd",
    "sg:city":"Ardmore",
    "sg:classifiers":[
        {
            "category":"Retail",
            "subcategory":"Repair Shop",
            "type":"Services"
        }
    ],
    "sg:phone":"+1 256 423 8527",
    "sg:postcode":"35739",
    "sg:province":"AL",
    "sg:tags":[
        "refrigeration"
    ],
    "wof:name":"Eagles Heating AC Inc",
    "wof:placetype":"venue"
},
  "geometry": {"coordinates":[-86.81937499999999,34.952327],"type":"Point"}
}