{
  "type": "Feature",
  "properties": {
    "iso:country":"US",
    "sg:address":"401 Meadows Dr",
    "sg:city":"Birmingham",
    "sg:classifiers":[
        {
            "category":"Building & Trades",
            "subcategory":"Construction",
            "type":"Services"
        }
    ],
    "sg:phone":"+1 205 655 6762",
    "sg:postcode":"35235",
    "sg:province":"AL",
    "sg:tags":[
        "painter"
    ],
    "wof:name":"Gene Spitzley Painting/Wallcvg",
    "wof:placetype":"venue"
},
  "geometry": {"coordinates":[-86.64672299999999,33.599035],"type":"Point"}
}