{
  "type": "Feature",
  "properties": {
    "iso:country":"US",
    "sg:address":"7826 State Rte 95",
    "sg:city":"Columbia",
    "sg:classifiers":[
        {
            "category":"Retail",
            "subcategory":"Repair Shop",
            "type":"Services"
        }
    ],
    "sg:phone":"+1 334 899 5181",
    "sg:postcode":"36319",
    "sg:province":"AL",
    "sg:tags":[
        "equipment",
        "industrial",
        "maintenance"
    ],
    "wof:name":"Williams Service Group Inc",
    "wof:placetype":"venue"
},
  "geometry": {"coordinates":[-85.12481,31.224766],"type":"Point"}
}