{
  "type": "Feature",
  "properties": {
    "iso:country":"US",
    "sg:address":"61020 Lottie Rd",
    "sg:city":"Atmore",
    "sg:classifiers":[
        {
            "category":"Organizations",
            "subcategory":"Religious Organization",
            "type":"Services"
        }
    ],
    "sg:phone":"+1 251 577 6477",
    "sg:postcode":"36502",
    "sg:province":"AL",
    "sg:tags":[
        "church"
    ],
    "wof:name":"Lottie Baptist Church",
    "wof:placetype":"venue"
},
  "geometry": {"coordinates":[-87.632359,31.101855],"type":"Point"}
}