{
  "type": "Feature",
  "properties": {
    "iso:country":"US",
    "sg:address":"22074 State Rte 216",
    "sg:city":"Mc Calla",
    "sg:classifiers":[
        {
            "category":"Restaurant",
            "type":"Food & Drink"
        }
    ],
    "sg:phone":"+1 205 477 7795",
    "sg:postcode":"35111",
    "sg:province":"AL",
    "sg:tags":[
        "eating"
    ],
    "wof:name":"Plaza Cafe",
    "wof:placetype":"venue"
},
  "geometry": {"coordinates":[-87.105537,33.280557],"type":"Point"}
}