{
  "type": "Feature",
  "properties": {
    "iso:country":"US",
    "sg:address":"217 N Seminary St",
    "sg:city":"Florence",
    "sg:classifiers":[
        {
            "category":"Professional",
            "subcategory":"Business Services",
            "type":"Services"
        },
        {
            "category":"Professional",
            "subcategory":"Advertising",
            "type":"Services"
        }
    ],
    "sg:phone":"+1 256 767 9937",
    "sg:postcode":"35630",
    "sg:province":"AL",
    "sg:tags":[
        "counselor",
        "management",
        "agency",
        "consult"
    ],
    "wof:name":"Morse Group The Inc",
    "wof:placetype":"venue"
},
  "geometry": {"coordinates":[-87.675693,34.802325],"type":"Point"}
}