{
  "type": "Feature",
  "properties": {
    "iso:country":"US",
    "sg:address":"3180 Chana Creek Rd",
    "sg:city":"Eclectic",
    "sg:classifiers":[
        {
            "category":"Shopping",
            "type":"Retail Goods"
        }
    ],
    "sg:phone":"+1 334 541 2390",
    "sg:postcode":"36024",
    "sg:province":"AL",
    "sg:tags":[
        "farm",
        "feed",
        "supply"
    ],
    "wof:name":"Feed Mill",
    "wof:placetype":"venue"
},
  "geometry": {"coordinates":[-85.98442799999999,32.621161],"type":"Point"}
}