{
  "type": "Feature",
  "properties": {
    "iso:country":"US",
    "sg:address":"129 Taylor Rd",
    "sg:city":"Florence",
    "sg:classifiers":[
        {
            "category":"Manufacturing",
            "subcategory":"Building Materials",
            "type":"Manufacturing & Wholesale Goods"
        }
    ],
    "sg:phone":"+1 256 767 3216",
    "sg:postcode":"35633",
    "sg:province":"AL",
    "sg:tags":[
        "mfg",
        "wood",
        "kitchen",
        "furniture"
    ],
    "wof:name":"Jaynes Millwork Inc",
    "wof:placetype":"venue"
},
  "geometry": {"coordinates":[-87.68870699999999,34.855623],"type":"Point"}
}