{
  "type": "Feature",
  "properties": {
    "addr:full":"317 1st Ave E Oneonta AL 35121",
    "addr:housenumber":"317",
    "addr:postcode":"35121",
    "addr:street":"1St Ave E",
    "iso:country":"US",
    "sg:address":"317 1st Ave E",
    "sg:city":"Oneonta",
    "sg:classifiers":[
        {
            "category":"Personal",
            "subcategory":"Barber",
            "type":"Services"
        }
    ],
    "sg:phone":"+1 205 274 7485",
    "sg:postcode":"35121",
    "sg:province":"AL",
    "sg:tags":[
        "shop"
    ],
    "wof:name":"Sculptur Room",
    "wof:placetype":"venue"
},
  "geometry": {"coordinates":[-86.473574,33.946376],"type":"Point"}
}