{
  "type": "Feature",
  "properties": {
    "iso:country":"US",
    "sg:address":"1508 Moulton St W",
    "sg:city":"Decatur",
    "sg:classifiers":[
        {
            "category":"Shopping",
            "subcategory":"Used Merchandise",
            "type":"Retail Goods"
        }
    ],
    "sg:phone":"+1 256 355 1018",
    "sg:postcode":"35601",
    "sg:province":"AL",
    "wof:name":"AAA Pawn Shop",
    "wof:placetype":"venue"
},
  "geometry": {"coordinates":[-87.005219,34.604318],"type":"Point"}
}