{
  "type": "Feature",
  "properties": {
    "iso:country":"US",
    "sg:address":"124 N 2nd Ave",
    "sg:city":"Lisman",
    "sg:classifiers":[
        {
            "category":"Organizations",
            "subcategory":"Religious Organization",
            "type":"Services"
        }
    ],
    "sg:phone":"+1 205 398 7506",
    "sg:postcode":"36912",
    "sg:province":"AL",
    "sg:tags":[
        "church"
    ],
    "wof:name":"Trinity Tabernacle Of Faith",
    "wof:placetype":"venue"
},
  "geometry": {"coordinates":[-88.279094,32.171938],"type":"Point"}
}