{
  "type": "Feature",
  "properties": {
    "addr:full":"204 15th St E Tuscaloosa AL 35401",
    "addr:housenumber":"204",
    "addr:postcode":"35401",
    "addr:street":"15Th St",
    "iso:country":"US",
    "sg:address":"204 15th St E",
    "sg:city":"Tuscaloosa",
    "sg:classifiers":[
        {
            "category":"Restaurant",
            "type":"Food & Drink"
        }
    ],
    "sg:menulink":"http://www.allmenus.com/al/tuscaloosa/173938-wendys/menu/",
    "sg:phone":"+1 205 758 8855",
    "sg:postcode":"35401",
    "sg:province":"AL",
    "sg:tags":[
        "burger",
        "american",
        "soup"
    ],
    "wof:name":"Wendy's",
    "wof:placetype":"venue"
},
  "geometry": {"coordinates":[-87.534469,33.198063],"type":"Point"}
}