{
  "type": "Feature",
  "properties": {
    "addr:full":"102 N Main St Tuscumbia AL 35674",
    "addr:housenumber":"102",
    "addr:postcode":"35674",
    "addr:street":"N Main St",
    "iso:country":"US",
    "sg:address":"102 N Main St",
    "sg:city":"Tuscumbia",
    "sg:classifiers":[
        {
            "category":"Personal",
            "subcategory":"Beauty Salon",
            "type":"Services"
        }
    ],
    "sg:phone":"+1 256 381 1500",
    "sg:postcode":"35674",
    "sg:province":"AL",
    "wof:name":"Shekinah House-Glorious Hair",
    "wof:placetype":"venue"
},
  "geometry": {"coordinates":[-87.703475,34.733364],"type":"Point"}
}