{
  "type": "Feature",
  "properties": {
    "addr:full":"6232 Bell Rd Ct Montgomery AL 36117",
    "addr:housenumber":"6232",
    "addr:postcode":"36117",
    "addr:street":"Bell Rd Ct",
    "iso:country":"US",
    "sg:address":"6232 Bell Rd Ct",
    "sg:city":"Montgomery",
    "sg:classifiers":[
        {
            "category":"Organizations",
            "subcategory":"Religious Organization",
            "type":"Services"
        }
    ],
    "sg:phone":"+1 334 409 0940",
    "sg:postcode":"36117",
    "sg:province":"AL",
    "wof:name":"Bishop Clarence E Stewart Jr",
    "wof:placetype":"venue"
},
  "geometry": {"coordinates":[-86.18970400000001,32.376507],"type":"Point"}
}