{
  "type": "Feature",
  "properties": {
    "iso:country":"US",
    "sg:address":"13033 Old Marion Rd",
    "sg:city":"Tuscaloosa",
    "sg:classifiers":[
        {
            "category":"Professional",
            "subcategory":"Advertising",
            "type":"Services"
        }
    ],
    "sg:phone":"+1 205 345 3566",
    "sg:postcode":"35405",
    "sg:province":"AL",
    "sg:tags":[
        "counselor"
    ],
    "wof:name":"JDL Publishing LLC",
    "wof:placetype":"venue"
},
  "geometry": {"coordinates":[-87.520052,33.102323],"type":"Point"}
}