{
  "type": "Feature",
  "properties": {
    "iso:country":"US",
    "sg:address":"325 Green Cove Rd SE",
    "sg:city":"Huntsville",
    "sg:classifiers":[
        {
            "category":"Manufacturing",
            "subcategory":"Tools & Machinery",
            "type":"Manufacturing & Wholesale Goods"
        }
    ],
    "sg:phone":"+1 256 882 0515",
    "sg:postcode":"35803",
    "sg:province":"AL",
    "sg:tags":[
        "manufacture",
        "environmental",
        "control",
        "technical"
    ],
    "wof:name":"Dale Technical Services Inc",
    "wof:placetype":"venue"
},
  "geometry": {"coordinates":[-86.556435,34.595285],"type":"Point"}
}