{
  "type": "Feature",
  "properties": {
    "iso:country":"US",
    "sg:address":"2024 Main Ave SW",
    "sg:city":"Cullman",
    "sg:classifiers":[
        {
            "category":"Personal",
            "type":"Services"
        }
    ],
    "sg:phone":"+1 256 737 0102",
    "sg:postcode":"35055",
    "sg:province":"AL",
    "wof:name":"Dr Vitkins",
    "wof:placetype":"venue"
},
  "geometry": {"coordinates":[-86.848392,34.145545],"type":"Point"}
}