{
  "type": "Feature",
  "properties": {
    "iso:country":"US",
    "sg:address":"535 Aldridge Rd",
    "sg:city":"Kennedy",
    "sg:classifiers":[
        {
            "category":"Freight",
            "type":"Transportation"
        }
    ],
    "sg:phone":"+1 205 596 3615",
    "sg:postcode":"35574",
    "sg:province":"AL",
    "sg:tags":[
        "operator",
        "local",
        "trucking"
    ],
    "wof:name":"Larry Crowley",
    "wof:placetype":"venue"
},
  "geometry": {"coordinates":[-87.970488,33.637373],"type":"Point"}
}