{
  "type": "Feature",
  "properties": {
    "addr:full":"1922 Charlotte Ct Florence AL 35630",
    "addr:housenumber":"1922",
    "addr:postcode":"35630",
    "addr:street":"Charlotte Ct",
    "iso:country":"US",
    "sg:address":"1922 Charlotte Ct",
    "sg:city":"Florence",
    "sg:classifiers":[
        {
            "category":"Organizations",
            "subcategory":"Professional Association",
            "type":"Services"
        }
    ],
    "sg:phone":"+1 256 446 5115",
    "sg:postcode":"35630",
    "sg:province":"AL",
    "sg:tags":[
        "consulting",
        "business"
    ],
    "wof:name":"S C O R E",
    "wof:placetype":"venue"
},
  "geometry": {"coordinates":[-87.665109,34.831984],"type":"Point"}
}