{
  "type": "Feature",
  "properties": {
    "addr:full":"1404 Old Patton Ferry Rd Adger AL 35006",
    "addr:housenumber":"1404",
    "addr:postcode":"35006",
    "addr:street":"Old Patton Ferry Rd",
    "iso:country":"US",
    "sg:address":"1404 Old Patton Ferry Rd",
    "sg:city":"Adger",
    "sg:classifiers":[
        {
            "category":"Bars & Pubs",
            "type":"Food & Drink"
        }
    ],
    "sg:phone":"+1 205 426 4600",
    "sg:postcode":"35006",
    "sg:province":"AL",
    "sg:tags":[
        "drinking"
    ],
    "wof:name":"Kings Point Lounge LLC",
    "wof:placetype":"venue"
},
  "geometry": {"coordinates":[-87.326266,33.489066],"type":"Point"}
}