{
  "type": "Feature",
  "properties": {
    "iso:country":"US",
    "sg:address":"99 21st Ave",
    "sg:city":"Tuscaloosa",
    "sg:classifiers":[
        {
            "category":"Building & Trades",
            "subcategory":"Construction",
            "type":"Services"
        }
    ],
    "sg:phone":"+1 205 758 3774",
    "sg:postcode":"35401",
    "sg:province":"AL",
    "sg:tags":[
        "maintenance",
        "contractor"
    ],
    "wof:name":"R & D Maintenance Svc",
    "wof:placetype":"venue"
},
  "geometry": {"coordinates":[-87.5655,33.214106],"type":"Point"}
}