{
  "type": "Feature",
  "properties": {
    "iso:country":"US",
    "sg:address":"1701 Mcfarland Blvd E",
    "sg:city":"Tuscaloosa",
    "sg:classifiers":[
        {
            "category":"Restaurant",
            "type":"Food & Drink"
        }
    ],
    "sg:menulink":"http://www.allmenus.com/al/tuscaloosa/72174-sbarro/menu/",
    "sg:phone":"+1 205 556 9811",
    "sg:postcode":"35404",
    "sg:province":"AL",
    "sg:tags":[
        "american",
        "pizza"
    ],
    "wof:name":"Sbarro",
    "wof:placetype":"venue"
},
  "geometry": {"coordinates":[-87.525903,33.194982],"type":"Point"}
}