{
  "type": "Feature",
  "properties": {
    "iso:country":"US",
    "sg:address":"3422 Bel Air Mall",
    "sg:city":"Mobile",
    "sg:classifiers":[
        {
            "category":"Recreation",
            "subcategory":"Amusement Park",
            "type":"Entertainment"
        },
        {
            "category":"Recreation",
            "subcategory":"Arcade",
            "type":"Entertainment"
        }
    ],
    "sg:phone":"+1 251 478 1081",
    "sg:postcode":"36606",
    "sg:province":"AL",
    "sg:tags":[
        "device",
        "operator"
    ],
    "wof:name":"Cyberstation",
    "wof:placetype":"venue"
},
  "geometry": {"coordinates":[-88.12293,30.67119],"type":"Point"}
}