{
  "type": "Feature",
  "properties": {
    "iso:country":"US",
    "sg:address":"327 E 16th St",
    "sg:city":"Anniston",
    "sg:classifiers":[
        {
            "category":"Personal",
            "subcategory":"Beauty Salon",
            "type":"Services"
        }
    ],
    "sg:phone":"+1 256 237 5548",
    "sg:postcode":"36207",
    "sg:province":"AL",
    "sg:tags":[
        "shop"
    ],
    "wof:name":"Carnaby Street Salon",
    "wof:placetype":"venue"
},
  "geometry": {"coordinates":[-85.824521,33.665129],"type":"Point"}
}