{
  "type": "Feature",
  "properties": {
    "iso:country":"US",
    "sg:address":"20 S Conception St",
    "sg:city":"Mobile",
    "sg:classifiers":[
        {
            "category":"Bars & Pubs",
            "type":"Food & Drink"
        }
    ],
    "sg:phone":"+1 251 432 9056",
    "sg:postcode":"36602",
    "sg:province":"AL",
    "sg:tags":[
        "drinking"
    ],
    "wof:name":"On The Roxx Lounge",
    "wof:placetype":"venue"
},
  "geometry": {"coordinates":[-88.042601,30.691099],"type":"Point"}
}