{
  "type": "Feature",
  "properties": {
    "addr:full":"1800 Greenbrier Dear Rd Anniston AL 36207",
    "addr:housenumber":"1800",
    "addr:postcode":"36207",
    "addr:street":"Greenbrier Dear Rd",
    "iso:country":"US",
    "sg:address":"1800 Greenbrier Dear Rd",
    "sg:city":"Anniston",
    "sg:classifiers":[
        {
            "category":"Manufacturing",
            "subcategory":"Metals",
            "type":"Manufacturing & Wholesale Goods"
        },
        {
            "category":"Professional",
            "type":"Services"
        }
    ],
    "sg:phone":"+1 256 835 5005",
    "sg:postcode":"36207",
    "sg:province":"AL",
    "sg:tags":[
        "industrial",
        "valve",
        "mfg"
    ],
    "wof:name":"Vellano Brothers Inc",
    "wof:placetype":"venue"
},
  "geometry": {"coordinates":[-85.800821,33.629222],"type":"Point"}
}