{
  "type": "Feature",
  "properties": {
    "iso:country":"US",
    "sg:address":"400 Argo-Margaret Rd",
    "sg:city":"Trussville",
    "sg:classifiers":[
        {
            "category":"Professional",
            "type":"Services"
        }
    ],
    "sg:phone":"+1 205 467 9487",
    "sg:postcode":"35173",
    "sg:province":"AL",
    "wof:name":"Queen Enterprises",
    "wof:placetype":"venue"
},
  "geometry": {"coordinates":[-86.514725,33.70073],"type":"Point"}
}