{
  "type": "Feature",
  "properties": {
    "iso:country":"US",
    "sg:address":"500 Fieldstone Rd",
    "sg:city":"Oneonta",
    "sg:classifiers":[
        {
            "category":"Local Transit",
            "type":"Transportation"
        }
    ],
    "sg:phone":"+1 205 625 3433",
    "sg:postcode":"35121",
    "sg:province":"AL",
    "sg:tags":[
        "passenger"
    ],
    "wof:name":"Co of Blount",
    "wof:placetype":"venue"
},
  "geometry": {"coordinates":[-86.487956,33.932147],"type":"Point"}
}