{
  "type": "Feature",
  "properties": {
    "iso:country":"US",
    "sg:address":"2969 Pelham Pkwy",
    "sg:city":"Pelham",
    "sg:classifiers":[
        {
            "category":"Professional",
            "subcategory":"Advertising",
            "type":"Services"
        }
    ],
    "sg:phone":"+1 205 664 7473",
    "sg:postcode":"35124",
    "sg:province":"AL",
    "sg:tags":[
        "marketing"
    ],
    "wof:name":"Rent-A-Center",
    "wof:placetype":"venue"
},
  "geometry": {"coordinates":[-86.810677,33.297602],"type":"Point"}
}