{
  "type": "Feature",
  "properties": {
    "iso:country":"US",
    "sg:address":"703 US Hwy 278",
    "sg:city":"Piedmont",
    "sg:classifiers":[
        {
            "category":"Shopping",
            "subcategory":"Clothing, Apparel, & Fashions",
            "type":"Retail Goods"
        }
    ],
    "sg:phone":"+1 256 447 7244",
    "sg:postcode":"36272",
    "sg:province":"AL",
    "wof:name":"Factory Connection 107",
    "wof:placetype":"venue"
},
  "geometry": {"coordinates":[-85.624167,33.933368],"type":"Point"}
}