{
  "type": "Feature",
  "properties": {
    "iso:country":"US",
    "sg:address":"5775 Gunn Rd",
    "sg:city":"Mobile",
    "sg:classifiers":[
        {
            "category":"Home & Garden",
            "subcategory":"Mobile Homes",
            "type":"Retail Goods"
        }
    ],
    "sg:phone":"+1 251 605 3981",
    "sg:postcode":"36619",
    "sg:province":"AL",
    "sg:tags":[
        "parts"
    ],
    "wof:name":"A-1 Mobile Home Parts",
    "wof:placetype":"venue"
},
  "geometry": {"coordinates":[-88.221172,30.570213],"type":"Point"}
}