{
  "type": "Feature",
  "properties": {
    "iso:country":"US",
    "sg:address":"32534 Arbor Ridge Cir",
    "sg:city":"Lillian",
    "sg:classifiers":[
        {
            "category":"Education",
            "subcategory":"Special Training",
            "type":"Public Place"
        }
    ],
    "sg:phone":"+1 251 962 2237",
    "sg:postcode":"36549",
    "sg:province":"AL",
    "sg:tags":[
        "financial"
    ],
    "wof:name":"Sunsand Venture",
    "wof:placetype":"venue"
},
  "geometry": {"coordinates":[-87.464899,30.380868],"type":"Point"}
}