{
  "type": "Feature",
  "properties": {
    "iso:country":"US",
    "sg:address":"313 Parkway Dr SW",
    "sg:city":"Leeds",
    "sg:classifiers":[
        {
            "category":"Food & Beverages",
            "subcategory":"Groceries & Convenience Stores",
            "type":"Retail Goods"
        }
    ],
    "sg:phone":"+1 205 699 3729",
    "sg:postcode":"35094",
    "sg:province":"AL",
    "wof:name":"H & V Food Mart",
    "wof:placetype":"venue"
},
  "geometry": {"coordinates":[-86.554125,33.545008],"type":"Point"}
}