{
  "type": "Feature",
  "properties": {
    "iso:country":"US",
    "sg:address":"782 Co Rd 44",
    "sg:city":"Eldridge",
    "sg:classifiers":[
        {
            "category":"Building & Trades",
            "subcategory":"Construction",
            "type":"Services"
        }
    ],
    "sg:phone":"+1 205 487 6190",
    "sg:postcode":"35554",
    "sg:province":"AL",
    "sg:tags":[
        "excavation",
        "contractor"
    ],
    "wof:name":"Ricky Hollingsworth Excavating",
    "wof:placetype":"venue"
},
  "geometry": {"coordinates":[-87.68931,33.845317],"type":"Point"}
}