{
  "type": "Feature",
  "properties": {
    "iso:country":"US",
    "sg:address":"337 Reedy Cir",
    "sg:city":"Boaz",
    "sg:classifiers":[
        {
            "category":"Shopping",
            "type":"Retail Goods"
        }
    ],
    "sg:phone":"+1 256 840 5399",
    "sg:postcode":"35957",
    "sg:province":"AL",
    "sg:tags":[
        "merchandise"
    ],
    "wof:name":"Gone Costal DOT Net",
    "wof:placetype":"venue"
},
  "geometry": {"coordinates":[-86.15402899999999,34.190202],"type":"Point"}
}