{
  "type": "Feature",
  "properties": {
    "iso:country":"US",
    "sg:address":"709 9th St SE",
    "sg:city":"Decatur",
    "sg:classifiers":[
        {
            "category":"Organizations",
            "subcategory":"Religious Organization",
            "type":"Services"
        }
    ],
    "sg:phone":"+1 256 353 8814",
    "sg:postcode":"35601",
    "sg:province":"AL",
    "sg:website":"www.southsidebaptist.net",
    "wof:name":"Southside Baptist Church",
    "wof:placetype":"venue"
},
  "geometry": {"coordinates":[-86.977952,34.587615],"type":"Point"}
}