{
  "type": "Feature",
  "properties": {
    "iso:country":"US",
    "sg:address":"2475 Maple Dr",
    "sg:city":"Mobile",
    "sg:classifiers":[
        {
            "category":"Building & Trades",
            "subcategory":"Construction",
            "type":"Services"
        }
    ],
    "sg:phone":"+1 251 639 1680",
    "sg:postcode":"36695",
    "sg:province":"AL",
    "sg:tags":[
        "house"
    ],
    "wof:name":"Robert A Payne Construction",
    "wof:placetype":"venue"
},
  "geometry": {"coordinates":[-88.22187,30.642353],"type":"Point"}
}