{
  "type": "Feature",
  "properties": {
    "iso:country":"US",
    "sg:address":"300 Circle Ave",
    "sg:city":"Bessemer",
    "sg:classifiers":[
        {
            "category":"Building & Trades",
            "subcategory":"Cleaning & Sanitation",
            "type":"Services"
        }
    ],
    "sg:phone":"+1 205 426 2772",
    "sg:postcode":"35020",
    "sg:province":"AL",
    "sg:tags":[
        "maintenance"
    ],
    "wof:name":"Don Jamal Janitorial Service",
    "wof:placetype":"venue"
},
  "geometry": {"coordinates":[-86.924319,33.419925],"type":"Point"}
}