{
  "type": "Feature",
  "properties": {
    "addr:full":"2891 US Hwy 431 Boaz AL 35957",
    "addr:housenumber":"2891",
    "addr:postcode":"35957",
    "addr:street":"Us Hwy 431",
    "iso:country":"US",
    "sg:address":"2891 US Hwy 431",
    "sg:city":"Boaz",
    "sg:classifiers":[
        {
            "category":"Health Services",
            "subcategory":"Doctor",
            "type":"Services"
        }
    ],
    "sg:phone":"+1 256 891 0865",
    "sg:postcode":"35957",
    "sg:province":"AL",
    "sg:tags":[
        "physician",
        "surgeon"
    ],
    "wof:name":"Albertville Pediatric Ctr",
    "wof:placetype":"venue"
},
  "geometry": {"coordinates":[-86.16143599999999,34.22675],"type":"Point"}
}