{
  "type": "Feature",
  "properties": {
    "iso:country":"US",
    "sg:address":"1000 Urban Center Dr",
    "sg:city":"Birmingham",
    "sg:classifiers":[
        {
            "category":"Banks & Credit Unions",
            "subcategory":"Investment Brokerage",
            "type":"Services"
        }
    ],
    "sg:phone":"+1 205 262 2600",
    "sg:postcode":"35242",
    "sg:province":"AL",
    "sg:tags":[
        "advisory",
        "financial"
    ],
    "wof:name":"FNBB Capital Markets",
    "wof:placetype":"venue"
},
  "geometry": {"coordinates":[-86.704354,33.483798],"type":"Point"}
}