{
  "type": "Feature",
  "properties": {
    "iso:country":"US",
    "sg:address":"1020 W Tallassee St",
    "sg:city":"Wetumpka",
    "sg:classifiers":[
        {
            "category":"Organizations",
            "subcategory":"Religious Organization",
            "type":"Services"
        }
    ],
    "sg:phone":"+1 334 567 0620",
    "sg:postcode":"36092",
    "sg:province":"AL",
    "sg:tags":[
        "church"
    ],
    "wof:name":"Tabernacle Baptist Church",
    "wof:placetype":"venue"
},
  "geometry": {"coordinates":[-86.21955699999999,32.542651],"type":"Point"}
}