{
  "type": "Feature",
  "properties": {
    "iso:country":"US",
    "sg:address":"25600 Smithfield Rd",
    "sg:city":"Elkmont",
    "sg:classifiers":[
        {
            "category":"Real Estate",
            "subcategory":"Real Estate Operator",
            "type":"Services"
        }
    ],
    "sg:phone":"+1 256 732 4124",
    "sg:postcode":"35620",
    "sg:province":"AL",
    "sg:tags":[
        "apartment"
    ],
    "wof:name":"Greenridge Apartments",
    "wof:placetype":"venue"
},
  "geometry": {"coordinates":[-86.981454,34.930259],"type":"Point"}
}