{
  "type": "Feature",
  "properties": {
    "addr:full":"1644 2nd Ave SW Cullman AL 35055",
    "addr:housenumber":"1644",
    "addr:postcode":"35055",
    "addr:street":"2Nd Ave Sw",
    "iso:country":"US",
    "sg:address":"1644 2nd Ave SW",
    "sg:city":"Cullman",
    "sg:classifiers":[
        {
            "category":"Cinema",
            "subcategory":"Movie Rental",
            "type":"Entertainment"
        }
    ],
    "sg:phone":"+1 256 775 0026",
    "sg:postcode":"35055",
    "sg:province":"AL",
    "sg:tags":[
        "video"
    ],
    "wof:name":"Blockbuster",
    "wof:placetype":"venue"
},
  "geometry": {"coordinates":[-86.82361299999999,34.139603],"type":"Point"}
}