{
  "type": "Feature",
  "properties": {
    "iso:country":"US",
    "sg:address":"506 Center St",
    "sg:city":"Scottsboro",
    "sg:classifiers":[
        {
            "category":"Professional",
            "type":"Services"
        }
    ],
    "sg:phone":"+1 256 259 1506",
    "sg:postcode":"35768",
    "sg:province":"AL",
    "wof:name":"Parker Stacy Reanne",
    "wof:placetype":"venue"
},
  "geometry": {"coordinates":[-86.02268100000001,34.677129],"type":"Point"}
}