{
  "type": "Feature",
  "properties": {
    "addr:full":"2100 Richard Arrington Jr Blvd N Birmingham AL 35203",
    "addr:housenumber":"2100",
    "addr:postcode":"35203",
    "addr:street":"Richard Arrington Jr Blvd N",
    "iso:country":"US",
    "sg:address":"2100 Richard Arrington Jr Blvd N",
    "sg:city":"Birmingham",
    "sg:classifiers":[
        {
            "category":"Arts & Performance",
            "subcategory":"Theater",
            "type":"Entertainment"
        },
        {
            "category":"Professional",
            "subcategory":"Business Services",
            "type":"Services"
        }
    ],
    "sg:phone":"+1 205 458 8401",
    "sg:postcode":"35203",
    "sg:province":"AL",
    "sg:tags":[
        "conference",
        "center"
    ],
    "wof:name":"Birmingham-Jefferson Cnvntn",
    "wof:placetype":"venue"
},
  "geometry": {"coordinates":[-86.80957600000001,33.525613],"type":"Point"}
}