{
  "type": "Feature",
  "properties": {
    "addr:full":"2551 Magnolia Park Cir Tuscaloosa AL 35405",
    "addr:housenumber":"2551",
    "addr:postcode":"35405",
    "addr:street":"Magnolia Park Cir",
    "iso:country":"US",
    "sg:address":"2551 Magnolia Park Cir",
    "sg:city":"Tuscaloosa",
    "sg:classifiers":[
        {
            "category":"Wholesale",
            "subcategory":"Durable Goods & Equipment",
            "type":"Manufacturing & Wholesale Goods"
        }
    ],
    "sg:phone":"+1 205 343 9307",
    "sg:postcode":"35405",
    "sg:province":"AL",
    "wof:name":"S&D Wholesale",
    "wof:placetype":"venue"
},
  "geometry": {"coordinates":[-87.569895,33.114401],"type":"Point"}
}