{
  "type": "Feature",
  "properties": {
    "iso:country":"US",
    "sg:address":"201 N Jefferson St",
    "sg:city":"Athens",
    "sg:classifiers":[
        {
            "category":"Professional",
            "subcategory":"Advertising",
            "type":"Services"
        }
    ],
    "sg:phone":"+1 256 216 8188",
    "sg:postcode":"35611",
    "sg:province":"AL",
    "wof:name":"Athens Plus",
    "wof:placetype":"venue"
},
  "geometry": {"coordinates":[-86.972017,34.805673],"type":"Point"}
}