{
  "type": "Feature",
  "properties": {
    "iso:country":"US",
    "sg:address":"4307 20th Ave",
    "sg:city":"Valley",
    "sg:classifiers":[
        {
            "category":"Professional",
            "subcategory":"Lawyer & Legal Services",
            "type":"Services"
        }
    ],
    "sg:phone":"+1 334 756 0737",
    "sg:postcode":"36854",
    "sg:province":"AL",
    "sg:tags":[
        "attorney"
    ],
    "wof:name":"Brandy C Easlick",
    "wof:placetype":"venue"
},
  "geometry": {"coordinates":[-85.175411,32.829223],"type":"Point"}
}