{
  "type": "Feature",
  "properties": {
    "iso:country":"US",
    "sg:address":"1103 Tacoma St",
    "sg:city":"Dothan",
    "sg:classifiers":[
        {
            "category":"Professional",
            "type":"Services"
        }
    ],
    "sg:phone":"+1 334 671 8078",
    "sg:postcode":"36303",
    "sg:province":"AL",
    "wof:name":"Gladys Pope",
    "wof:placetype":"venue"
},
  "geometry": {"coordinates":[-85.40609000000001,31.234333],"type":"Point"}
}