{
  "type": "Feature",
  "properties": {
    "addr:full":"6401 Us Highway 431 Alexandria AL 36250",
    "addr:housenumber":"6401",
    "addr:postcode":"36250",
    "addr:street":"Us Highway 431",
    "iso:country":"US",
    "sg:address":"6401 Us Highway 431",
    "sg:city":"Alexandria",
    "sg:classifiers":[
        {
            "category":"Restaurant",
            "type":"Food & Drink"
        }
    ],
    "sg:menulink":"http://www.allmenus.com/al/websters-chapel-alexandria-valley/231500-sonic/menu/",
    "sg:phone":"+1 256 820 2628",
    "sg:postcode":"36250",
    "sg:province":"AL",
    "sg:tags":[
        "burger",
        "american"
    ],
    "wof:name":"Sonic",
    "wof:placetype":"venue"
},
  "geometry": {"coordinates":[-85.888718,33.764711],"type":"Point"}
}