{
  "type": "Feature",
  "properties": {
    "iso:country":"US",
    "sg:address":"2804 8th St",
    "sg:city":"Tuscaloosa",
    "sg:classifiers":[
        {
            "category":"Real Estate",
            "subcategory":"Architect",
            "type":"Services"
        }
    ],
    "sg:phone":"+1 205 752 1117",
    "sg:postcode":"35401",
    "sg:province":"AL",
    "sg:tags":[
        "architectural"
    ],
    "wof:name":"Marcum Architects LLC",
    "wof:placetype":"venue"
},
  "geometry": {"coordinates":[-87.57384399999999,33.205148],"type":"Point"}
}