{
  "type": "Feature",
  "properties": {
    "iso:country":"US",
    "sg:address":"204 Co Rd 405",
    "sg:city":"Shelby",
    "sg:classifiers":[
        {
            "category":"Building & Trades",
            "subcategory":"Pest Control",
            "type":"Services"
        }
    ],
    "sg:phone":"+1 205 669 9609",
    "sg:postcode":"35143",
    "sg:province":"AL",
    "wof:name":"Over The Mountain Pest Control",
    "wof:placetype":"venue"
},
  "geometry": {"coordinates":[-86.520173,33.096863],"type":"Point"}
}