{
  "type": "Feature",
  "properties": {
    "iso:country":"US",
    "sg:address":"205 Hunters Cove Rd",
    "sg:city":"Huntsville",
    "sg:classifiers":[
        {
            "category":"Professional",
            "subcategory":"Computer Services",
            "type":"Services"
        }
    ],
    "sg:phone":"+1 256 489 3352",
    "sg:postcode":"35806",
    "sg:province":"AL",
    "sg:tags":[
        "consulting",
        "training",
        "software"
    ],
    "wof:name":"Networking America Inc",
    "wof:placetype":"venue"
},
  "geometry": {"coordinates":[-86.690882,34.80284],"type":"Point"}
}