{
  "type": "Feature",
  "properties": {
    "iso:country":"US",
    "sg:address":"305 N Cahill Rd",
    "sg:city":"Albertville",
    "sg:classifiers":[
        {
            "category":"Autos & Motor Vehicles",
            "subcategory":"Automobile Sales",
            "type":"Retail Goods"
        }
    ],
    "sg:phone":"+1 256 891 2940",
    "sg:postcode":"35950",
    "sg:province":"AL",
    "sg:tags":[
        "used"
    ],
    "wof:name":"Classic Cars Inc",
    "wof:placetype":"venue"
},
  "geometry": {"coordinates":[-86.218875,34.277996],"type":"Point"}
}