{
  "type": "Feature",
  "properties": {
    "iso:country":"US",
    "sg:address":"3021 Lorna Rd Suite 111",
    "sg:city":"Birmingham",
    "sg:classifiers":[
        {
            "category":"Insurance",
            "subcategory":"Hazard Insurance",
            "type":"Services"
        },
        {
            "category":"Insurance",
            "subcategory":"Insurance Agent",
            "type":"Services"
        },
        {
            "category":"Insurance",
            "subcategory":"Life Insurance",
            "type":"Services"
        },
        {
            "category":"Insurance",
            "subcategory":"Title Insurance",
            "type":"Services"
        }
    ],
    "sg:phone":"+1 205 979 4331",
    "sg:postcode":"35216",
    "sg:province":"AL",
    "sg:tags":[
        "auto",
        "homeowner"
    ],
    "sg:website":"http://www.nationwide.com/agent/Birmingham-ALABAMA-insurance-agent/ashley-bruette/office.html",
    "wof:name":"Ashley A Bruette Agency - Nationwide Insurance",
    "wof:placetype":"venue"
},
  "geometry": {"coordinates":[-86.805029,33.405777],"type":"Point"}
}