{
  "type": "Feature",
  "properties": {
    "iso:country":"US",
    "sg:address":"922 6th Ave SE",
    "sg:city":"Decatur",
    "sg:classifiers":[
        {
            "category":"Insurance",
            "subcategory":"Insurance Agent",
            "type":"Services"
        }
    ],
    "sg:phone":"+1 256 353 8952",
    "sg:postcode":"35601",
    "sg:province":"AL",
    "wof:name":"Met Life",
    "wof:placetype":"venue"
},
  "geometry": {"coordinates":[-86.98018399999999,34.5935],"type":"Point"}
}