{
  "type": "Feature",
  "properties": {
    "iso:country":"US",
    "sg:address":"700 Towncenter Blvd",
    "sg:city":"Tuscaloosa",
    "sg:classifiers":[
        {
            "category":"Health Services",
            "subcategory":"Health Practitioner",
            "type":"Services"
        }
    ],
    "sg:phone":"+1 205 752 1650",
    "sg:postcode":"35406",
    "sg:province":"AL",
    "wof:name":"Innerfit of Tuscaloosa",
    "wof:placetype":"venue"
},
  "geometry": {"coordinates":[-87.536331,33.23284],"type":"Point"}
}