{
  "type": "Feature",
  "properties": {
    "iso:country":"US",
    "sg:address":"352 Government St",
    "sg:city":"Mobile",
    "sg:classifiers":[
        {
            "category":"Insurance",
            "subcategory":"Title Insurance",
            "type":"Services"
        }
    ],
    "sg:phone":"+1 251 433 6956",
    "sg:postcode":"36602",
    "sg:province":"AL",
    "wof:name":"Transcontinental Title Co",
    "wof:placetype":"venue"
},
  "geometry": {"coordinates":[-88.045598,30.688798],"type":"Point"}
}