{
  "type": "Feature",
  "properties": {
    "addr:full":"2598 Alton Rd Birmingham AL 35210",
    "addr:housenumber":"2598",
    "addr:postcode":"35210",
    "addr:street":"Alton Rd",
    "iso:country":"US",
    "sg:address":"2598 Alton Rd",
    "sg:city":"Birmingham",
    "sg:classifiers":[
        {
            "category":"Wholesale",
            "subcategory":"Machinery & Supplies",
            "type":"Manufacturing & Wholesale Goods"
        }
    ],
    "sg:phone":"+1 205 833 1210",
    "sg:postcode":"35210",
    "sg:province":"AL",
    "sg:tags":[
        "equipment",
        "industrial"
    ],
    "sg:website":"www.durawear.net",
    "wof:name":"Dura Wear Corp",
    "wof:placetype":"venue"
},
  "geometry": {"coordinates":[-86.641704,33.578267],"type":"Point"}
}