{
  "type": "Feature",
  "properties": {
    "iso:country":"US",
    "sg:address":"3120 North St",
    "sg:city":"Guntersville",
    "sg:classifiers":[
        {
            "category":"Health Services",
            "subcategory":"Health Practitioner",
            "type":"Services"
        }
    ],
    "sg:phone":"+1 256 582 6006",
    "sg:postcode":"35976",
    "sg:province":"AL",
    "wof:name":"Sunbelt Therapy MGT Svcs",
    "wof:placetype":"venue"
},
  "geometry": {"coordinates":[-86.311943,34.316403],"type":"Point"}
}