{
  "type": "Feature",
  "properties": {
    "iso:country":"US",
    "sg:address":"1149 Simmsville Rd",
    "sg:city":"Alabaster",
    "sg:classifiers":[
        {
            "category":"Wholesale",
            "subcategory":"Non-durable Goods",
            "type":"Manufacturing & Wholesale Goods"
        }
    ],
    "sg:phone":"+1 205 620 2932",
    "sg:postcode":"35007",
    "sg:province":"AL",
    "sg:tags":[
        "merchandise",
        "general"
    ],
    "wof:name":"PDS Enterprises",
    "wof:placetype":"venue"
},
  "geometry": {"coordinates":[-86.803013,33.252845],"type":"Point"}
}