{
  "type": "Feature",
  "properties": {
    "addr:full":"1944 Montgomery Hwy Birmingham AL 35244",
    "addr:housenumber":"1944",
    "addr:postcode":"35244",
    "addr:street":"Montgomery Hwy",
    "iso:country":"US",
    "sg:address":"1944 Montgomery Hwy",
    "sg:city":"Birmingham",
    "sg:classifiers":[
        {
            "category":"Food & Beverages",
            "subcategory":"Groceries & Convenience Stores",
            "type":"Retail Goods"
        }
    ],
    "sg:phone":"+1 205 987 3401",
    "sg:postcode":"35244",
    "sg:province":"AL",
    "wof:name":"Publix",
    "wof:placetype":"venue"
},
  "geometry": {"coordinates":[-86.79548200000001,33.348363],"type":"Point"}
}