{
  "type": "Feature",
  "properties": {
    "addr:full":"8425 State Rte 119 Alabaster AL 35007",
    "addr:housenumber":"8425",
    "addr:postcode":"35007",
    "addr:street":"State Rte 119",
    "iso:country":"US",
    "sg:address":"8425 State Rte 119",
    "sg:city":"Alabaster",
    "sg:classifiers":[
        {
            "category":"Recreation",
            "type":"Entertainment"
        }
    ],
    "sg:phone":"+1 205 663 8177",
    "sg:postcode":"35007",
    "sg:province":"AL",
    "sg:tags":[
        "range",
        "practice",
        "golf"
    ],
    "wof:name":"Greg's Golf Driving Range",
    "wof:placetype":"venue"
},
  "geometry": {"coordinates":[-86.82840299999999,33.203063],"type":"Point"}
}