{
  "type": "Feature",
  "properties": {
    "iso:country":"US",
    "sg:address":"2403 10th St",
    "sg:city":"Phenix City",
    "sg:classifiers":[
        {
            "category":"Autos & Motor Vehicles",
            "subcategory":"Auto Supplies",
            "type":"Retail Goods"
        }
    ],
    "sg:phone":"+1 334 298 4047",
    "sg:postcode":"36869",
    "sg:province":"AL",
    "sg:tags":[
        "tire"
    ],
    "wof:name":"Phenix Firestone Store",
    "wof:placetype":"venue"
},
  "geometry": {"coordinates":[-85.027797,32.464386],"type":"Point"}
}