{
  "type": "Feature",
  "properties": {
    "iso:country":"US",
    "sg:address":"8514 Holtville Rd",
    "sg:city":"Wetumpka",
    "sg:classifiers":[
        {
            "category":"Building & Trades",
            "subcategory":"Electrical",
            "type":"Services"
        }
    ],
    "sg:phone":"+1 334 569 4398",
    "sg:postcode":"36092",
    "sg:province":"AL",
    "sg:tags":[
        "electrical",
        "electric",
        "contractor"
    ],
    "wof:name":"Redden Electric Co Inc",
    "wof:placetype":"venue"
},
  "geometry": {"coordinates":[-86.292834,32.626693],"type":"Point"}
}