{
  "type": "Feature",
  "properties": {
    "iso:country":"US",
    "sg:address":"3325 Lorna Rd",
    "sg:city":"Birmingham",
    "sg:classifiers":[
        {
            "category":"Restaurant",
            "type":"Food & Drink"
        }
    ],
    "sg:phone":"+1 205 823 5828",
    "sg:postcode":"35216",
    "sg:province":"AL",
    "sg:tags":[
        "eating"
    ],
    "wof:name":"Original Pancake House",
    "wof:placetype":"venue"
},
  "geometry": {"coordinates":[-86.798344,33.393943],"type":"Point"}
}