{
  "type": "Feature",
  "properties": {
    "iso:country":"US",
    "sg:address":"6565 Narrow Lane Rd",
    "sg:city":"Montgomery",
    "sg:classifiers":[
        {
            "category":"Building & Trades",
            "subcategory":"Cleaning & Sanitation",
            "type":"Services"
        }
    ],
    "sg:phone":"+1 334 281 7177",
    "sg:postcode":"36116",
    "sg:province":"AL",
    "sg:tags":[
        "contracting",
        "commercial",
        "gen"
    ],
    "wof:name":"W and W Enterprise LLC",
    "wof:placetype":"venue"
},
  "geometry": {"coordinates":[-86.26551600000001,32.287031],"type":"Point"}
}