{
  "type": "Feature",
  "properties": {
    "iso:country":"US",
    "sg:address":"3707 W Chapel Hill Rd",
    "sg:city":"Decatur",
    "sg:classifiers":[
        {
            "category":"Retail",
            "subcategory":"Repair Shop",
            "type":"Services"
        }
    ],
    "sg:phone":"+1 256 351 9777",
    "sg:postcode":"35603",
    "sg:province":"AL",
    "sg:tags":[
        "refinishing",
        "furniture"
    ],
    "wof:name":"Gary's Antique Restoration",
    "wof:placetype":"venue"
},
  "geometry": {"coordinates":[-87.07270200000001,34.554396],"type":"Point"}
}