{
  "type": "Feature",
  "properties": {
    "iso:country":"US",
    "sg:address":"331 S Wilson Ave",
    "sg:city":"Mobile",
    "sg:classifiers":[
        {
            "category":"Shopping",
            "subcategory":"Clothing, Apparel, & Fashions",
            "type":"Retail Goods"
        }
    ],
    "sg:phone":"+1 251 452 4964",
    "sg:postcode":"36610",
    "sg:province":"AL",
    "wof:name":"T R Wig Shop",
    "wof:placetype":"venue"
},
  "geometry": {"coordinates":[-88.082394,30.731865],"type":"Point"}
}