{
  "type": "Feature",
  "properties": {
    "iso:country":"US",
    "sg:address":"1507 Crabapple St",
    "sg:city":"Attalla",
    "sg:classifiers":[
        {
            "category":"Organizations",
            "subcategory":"Religious Organization",
            "type":"Services"
        }
    ],
    "sg:phone":"+1 256 538 0861",
    "sg:postcode":"35954",
    "sg:province":"AL",
    "wof:name":"Mountainview Church",
    "wof:placetype":"venue"
},
  "geometry": {"coordinates":[-86.119646,34.007172],"type":"Point"}
}