{
  "type": "Feature",
  "properties": {
    "iso:country":"US",
    "sg:address":"4919 Windwood Cir",
    "sg:city":"Birmingham",
    "sg:classifiers":[
        {
            "category":"Government",
            "subcategory":"Office",
            "type":"Public Place"
        }
    ],
    "sg:phone":"+1 205 991 7143",
    "sg:postcode":"35242",
    "sg:province":"AL",
    "sg:tags":[
        "housing",
        "program"
    ],
    "wof:name":"Marlee Villa LLC",
    "wof:placetype":"venue"
},
  "geometry": {"coordinates":[-86.72921599999999,33.381979],"type":"Point"}
}