{
  "type": "Feature",
  "properties": {
    "addr:full":"5741 Balboa Ter Pinson AL 35126",
    "addr:housenumber":"5741",
    "addr:postcode":"35126",
    "addr:street":"Balboa Ter Pinson",
    "iso:country":"US",
    "sg:address":"5741 Balboa Ter",
    "sg:city":"Pinson",
    "sg:classifiers":[
        {
            "category":"Professional",
            "type":"Services"
        }
    ],
    "sg:phone":"+1 205 856 1584",
    "sg:postcode":"35126",
    "sg:province":"AL",
    "wof:name":"David R Higginbotham",
    "wof:placetype":"venue"
},
  "geometry": {"coordinates":[-86.64867700000001,33.669612],"type":"Point"}
}