{
  "type": "Feature",
  "properties": {
    "iso:country":"US",
    "sg:address":"37 1st Pl S",
    "sg:city":"Birmingham",
    "sg:classifiers":[
        {
            "category":"Personal",
            "subcategory":"Beauty Salon",
            "type":"Services"
        }
    ],
    "sg:phone":"+1 205 252 1924",
    "sg:postcode":"35205",
    "sg:province":"AL",
    "sg:tags":[
        "shop",
        "garment",
        "agent"
    ],
    "wof:name":"B Chic Boutique",
    "wof:placetype":"venue"
},
  "geometry": {"coordinates":[-86.83135299999999,33.498745],"type":"Point"}
}