{
  "type": "Feature",
  "properties": {
    "addr:full":"1111 2nd Ave N Bessemer AL 35020",
    "addr:housenumber":"1111",
    "addr:postcode":"35020",
    "addr:street":"2Nd Ave N",
    "iso:country":"US",
    "sg:address":"1111 2nd Ave N",
    "sg:city":"Bessemer",
    "sg:classifiers":[
        {
            "category":"Government",
            "subcategory":"Fire Station",
            "type":"Public Place"
        }
    ],
    "sg:phone":"+1 205 428 5151",
    "sg:postcode":"35020",
    "sg:province":"AL",
    "sg:tags":[
        "department"
    ],
    "sg:website":"www.bessemerfire.com",
    "wof:name":"Bessemer Fire Chief",
    "wof:placetype":"venue"
},
  "geometry": {"coordinates":[-86.959006,33.3938],"type":"Point"}
}