{
  "type": "Feature",
  "properties": {
    "iso:country":"US",
    "sg:address":"10500 Co Rd 66",
    "sg:city":"Heflin",
    "sg:classifiers":[
        {
            "category":"Manufacturing",
            "subcategory":"Tools & Machinery",
            "type":"Manufacturing & Wholesale Goods"
        }
    ],
    "sg:phone":"+1 256 748 2135",
    "sg:postcode":"36264",
    "sg:province":"AL",
    "sg:tags":[
        "mfg"
    ],
    "wof:name":"Sunfly Jigs",
    "wof:placetype":"venue"
},
  "geometry": {"coordinates":[-85.458734,33.685553],"type":"Point"}
}