{
  "type": "Feature",
  "properties": {
    "iso:country":"US",
    "sg:address":"4736 Airport Blvd",
    "sg:city":"Mobile",
    "sg:classifiers":[
        {
            "category":"Health Services",
            "subcategory":"Doctor",
            "type":"Services"
        }
    ],
    "sg:phone":"+1 251 342 0015",
    "sg:postcode":"36608",
    "sg:province":"AL",
    "sg:tags":[
        "dentist"
    ],
    "wof:name":"Rick Rutland DDS",
    "wof:placetype":"venue"
},
  "geometry": {"coordinates":[-88.17512,30.676176],"type":"Point"}
}