{
  "type": "Feature",
  "properties": {
    "iso:country":"US",
    "sg:address":"11543 US Hwy 431",
    "sg:city":"Meridianville",
    "sg:classifiers":[
        {
            "category":"Food & Beverages",
            "subcategory":"Groceries & Convenience Stores",
            "type":"Retail Goods"
        }
    ],
    "sg:phone":"+1 256 828 1449",
    "sg:postcode":"35759",
    "sg:province":"AL",
    "wof:name":"L P Mart",
    "wof:placetype":"venue"
},
  "geometry": {"coordinates":[-86.571466,34.84674],"type":"Point"}
}