{
  "type": "Feature",
  "properties": {
    "addr:full":"5809 US Hwy 43 Satsuma AL 36572",
    "addr:housenumber":"5809",
    "addr:postcode":"36572",
    "addr:street":"Us Hwy 43",
    "iso:country":"US",
    "sg:address":"5809 US Hwy 43",
    "sg:city":"Satsuma",
    "sg:classifiers":[
        {
            "category":"Retail",
            "subcategory":"Repair Shop",
            "type":"Services"
        }
    ],
    "sg:phone":"+1 251 675 6902",
    "sg:postcode":"36572",
    "sg:province":"AL",
    "wof:name":"Davis Forklift Service & Repr",
    "wof:placetype":"venue"
},
  "geometry": {"coordinates":[-88.051084,30.864052],"type":"Point"}
}