{
  "type": "Feature",
  "properties": {
    "iso:country":"US",
    "sg:address":"1120 W Andrews Ave",
    "sg:city":"Ozark",
    "sg:classifiers":[
        {
            "category":"Shopping",
            "subcategory":"Used Merchandise",
            "type":"Retail Goods"
        }
    ],
    "sg:phone":"+1 334 774 4700",
    "sg:postcode":"36360",
    "sg:province":"AL",
    "sg:tags":[
        "pawnbroker"
    ],
    "wof:name":"Show Gun & Pawn Inc",
    "wof:placetype":"venue"
},
  "geometry": {"coordinates":[-85.662781,31.444174],"type":"Point"}
}