{
  "type": "Feature",
  "properties": {
    "iso:country":"US",
    "sg:address":"1800 5th Ave N",
    "sg:city":"Birmingham",
    "sg:classifiers":[
        {
            "category":"Government",
            "subcategory":"Office",
            "type":"Public Place"
        }
    ],
    "sg:phone":"+1 205 731 2262",
    "sg:postcode":"35203",
    "sg:province":"AL",
    "sg:tags":[
        "investigation"
    ],
    "wof:name":"Investigations Office",
    "wof:placetype":"venue"
},
  "geometry": {"coordinates":[-86.80958200000001,33.517429],"type":"Point"}
}