{
  "type": "Feature",
  "properties": {
    "iso:country":"US",
    "sg:address":"428 Co Rd 148",
    "sg:city":"Opelika",
    "sg:classifiers":[
        {
            "category":"Manufacturing",
            "subcategory":"Tools & Machinery",
            "type":"Manufacturing & Wholesale Goods"
        }
    ],
    "sg:phone":"+1 334 745 4911",
    "sg:postcode":"36804",
    "sg:province":"AL",
    "sg:tags":[
        "mold"
    ],
    "wof:name":"Brown Tool & Mold",
    "wof:placetype":"venue"
},
  "geometry": {"coordinates":[-85.32365299999999,32.588798],"type":"Point"}
}