{
  "type": "Feature",
  "properties": {
    "addr:full":"3183 Cloverdale Rd Florence AL 35633",
    "addr:housenumber":"3183",
    "addr:postcode":"35633",
    "addr:street":"Cloverdale Rd",
    "iso:country":"US",
    "sg:address":"3183 Cloverdale Rd",
    "sg:city":"Florence",
    "sg:classifiers":[
        {
            "category":"Restaurant",
            "type":"Food & Drink"
        }
    ],
    "sg:menulink":"http://www.allmenus.com/al/florence/190175-mcdonalds/menu/",
    "sg:postcode":"35633",
    "sg:province":"AL",
    "sg:tags":[
        "burger",
        "american"
    ],
    "wof:name":"McDonald's",
    "wof:placetype":"venue"
},
  "geometry": {"coordinates":[-87.69026700000001,34.849569],"type":"Point"}
}