{
  "type": "Feature",
  "properties": {
    "iso:country":"US",
    "sg:address":"190 Porter Johnson Rd",
    "sg:city":"Piedmont",
    "sg:classifiers":[
        {
            "category":"Retail",
            "subcategory":"Auto Repair",
            "type":"Services"
        }
    ],
    "sg:phone":"+1 256 447 9165",
    "sg:postcode":"36272",
    "sg:province":"AL",
    "sg:tags":[
        "truck"
    ],
    "wof:name":"Baggett Truck Svc",
    "wof:placetype":"venue"
},
  "geometry": {"coordinates":[-85.640309,33.939194],"type":"Point"}
}