{
  "type": "Feature",
  "properties": {
    "iso:country":"US",
    "sg:address":"116 Jefferson St S",
    "sg:city":"Huntsville",
    "sg:classifiers":[
        {
            "category":"Professional",
            "subcategory":"Lawyer & Legal Services",
            "type":"Services"
        }
    ],
    "sg:phone":"+1 256 533 1421",
    "sg:postcode":"35801",
    "sg:province":"AL",
    "sg:tags":[
        "attorney"
    ],
    "wof:name":"Bell Richardson",
    "wof:placetype":"venue"
},
  "geometry": {"coordinates":[-86.5861,34.730508],"type":"Point"}
}