{
  "type": "Feature",
  "properties": {
    "iso:country":"US",
    "sg:address":"700 Battle St E",
    "sg:city":"Talladega",
    "sg:classifiers":[
        {
            "category":"Restaurant",
            "type":"Food & Drink"
        }
    ],
    "sg:menulink":"http://www.allmenus.com/al/talladega/121071-subway/menu/",
    "sg:phone":"+1 256 362 0741",
    "sg:postcode":"35160",
    "sg:province":"AL",
    "sg:tags":[
        "american",
        "sandwich"
    ],
    "wof:name":"Subway",
    "wof:placetype":"venue"
},
  "geometry": {"coordinates":[-86.086431,33.438139],"type":"Point"}
}