{
  "type": "Feature",
  "properties": {
    "addr:full":"1223 Larkwood Dr NE Cullman AL 35055",
    "addr:housenumber":"1223",
    "addr:postcode":"35055",
    "addr:street":"Larkwood Dr Ne",
    "iso:country":"US",
    "sg:address":"1223 Larkwood Dr NE",
    "sg:city":"Cullman",
    "sg:classifiers":[
        {
            "category":"Professional",
            "subcategory":"Management & Consulting",
            "type":"Services"
        }
    ],
    "sg:phone":"+1 256 737 0118",
    "sg:postcode":"35055",
    "sg:province":"AL",
    "sg:tags":[
        "business"
    ],
    "wof:name":"Network Consulting Services",
    "wof:placetype":"venue"
},
  "geometry": {"coordinates":[-86.809073,34.184055],"type":"Point"}
}