{
  "type": "Feature",
  "properties": {
    "addr:full":"318 Monroe Ave Muscle Shoals AL 35661",
    "addr:housenumber":"318",
    "addr:postcode":"35661",
    "addr:street":"Monroe Ave",
    "iso:country":"US",
    "sg:address":"318 Monroe Ave",
    "sg:city":"Muscle Shoals",
    "sg:classifiers":[
        {
            "category":"Professional",
            "subcategory":"Advertising",
            "type":"Services"
        }
    ],
    "sg:phone":"+1 402 902 4141",
    "sg:postcode":"35661",
    "sg:province":"AL",
    "sg:tags":[
        "professional-design",
        "solid-development",
        "css",
        "php",
        "web-design",
        "seo",
        "standards"
    ],
    "sg:website":"http://www.elevatevc.com",
    "wof:name":"Elevate Visual Communications",
    "wof:placetype":"venue"
},
  "geometry": {"coordinates":[-87.62924599999999,34.73382],"type":"Point"}
}