{
  "type": "Feature",
  "properties": {
    "iso:country":"US",
    "sg:address":"318 Westgate Pkwy",
    "sg:city":"Dothan",
    "sg:classifiers":[
        {
            "category":"Health Services",
            "subcategory":"Doctor",
            "type":"Services"
        }
    ],
    "sg:phone":"+1 334 794 3727",
    "sg:postcode":"36303",
    "sg:province":"AL",
    "sg:tags":[
        "dentist"
    ],
    "wof:name":"David A Dauphin DDS",
    "wof:placetype":"venue"
},
  "geometry": {"coordinates":[-85.434464,31.233564],"type":"Point"}
}