{
  "type": "Feature",
  "properties": {
    "iso:country":"US",
    "sg:address":"1075 Birch Cir",
    "sg:city":"Auburn",
    "sg:classifiers":[
        {
            "category":"Shopping",
            "subcategory":"Computers & Home Electronics",
            "type":"Retail Goods"
        }
    ],
    "sg:phone":"+1 334 826 4003",
    "sg:postcode":"36830",
    "sg:province":"AL",
    "sg:tags":[
        "equipment",
        "dealer"
    ],
    "wof:name":"Keown Computer",
    "wof:placetype":"venue"
},
  "geometry": {"coordinates":[-85.45970699999999,32.611544],"type":"Point"}
}