{
  "type": "Feature",
  "properties": {
    "addr:full":"16051 US Hwy 431 Glencoe AL 35905",
    "addr:housenumber":"16051",
    "addr:postcode":"35905",
    "addr:street":"Us Hwy 431",
    "iso:country":"US",
    "sg:address":"16051 US Hwy 431",
    "sg:city":"Glencoe",
    "sg:classifiers":[
        {
            "category":"Food & Beverages",
            "subcategory":"Groceries & Convenience Stores",
            "type":"Retail Goods"
        },
        {
            "category":"Autos & Motor Vehicles",
            "subcategory":"Fuel & Gas Station",
            "type":"Retail Goods"
        }
    ],
    "sg:phone":"+1 256 492 9104",
    "sg:postcode":"35905",
    "sg:province":"AL",
    "sg:tags":[
        "oil"
    ],
    "wof:name":"James' Place",
    "wof:placetype":"venue"
},
  "geometry": {"coordinates":[-85.91750999999999,33.899843],"type":"Point"}
}