{
  "type": "Feature",
  "properties": {
    "iso:country":"US",
    "sg:address":"32910 Marlin Key Dr",
    "sg:city":"Orange Beach",
    "sg:classifiers":[
        {
            "category":"Manufacturing",
            "subcategory":"Tools & Machinery",
            "type":"Manufacturing & Wholesale Goods"
        }
    ],
    "sg:phone":"+1 251 980 1156",
    "sg:postcode":"36561",
    "sg:province":"AL",
    "sg:tags":[
        "equipment",
        "lighting",
        "mfg"
    ],
    "wof:name":"Satellite Tech Implmnttion LLC",
    "wof:placetype":"venue"
},
  "geometry": {"coordinates":[-87.467139,30.303395],"type":"Point"}
}