{
  "type": "Feature",
  "properties": {
    "addr:full":"3443 Colonnade Pkwy Birmingham AL 35243",
    "addr:housenumber":"3443",
    "addr:postcode":"35243",
    "addr:street":"Colonnade Pkwy",
    "iso:country":"US",
    "sg:address":"3443 Colonnade Pkwy",
    "sg:city":"Birmingham",
    "sg:classifiers":[
        {
            "category":"Banks & Credit Unions",
            "subcategory":"Bank",
            "type":"Services"
        }
    ],
    "sg:phone":"+1 205 967 0585",
    "sg:postcode":"35243",
    "sg:province":"AL",
    "sg:tags":[
        "loan",
        "real estate"
    ],
    "sg:website":"www.countrywide.com",
    "wof:name":"Countrywide Home Loans",
    "wof:placetype":"venue"
},
  "geometry": {"coordinates":[-86.73339,33.434811],"type":"Point"}
}