{
  "type": "Feature",
  "properties": {
    "addr:full":"548 Memorial Dr Bessemer AL 35022",
    "addr:housenumber":"548",
    "addr:postcode":"35022",
    "addr:street":"Memorial Dr",
    "iso:country":"US",
    "sg:address":"548 Memorial Dr",
    "sg:city":"Bessemer",
    "sg:classifiers":[
        {
            "category":"Freight",
            "type":"Transportation"
        }
    ],
    "sg:phone":"+1 205 426 3088",
    "sg:postcode":"35022",
    "sg:province":"AL",
    "wof:name":"Roncarco Inc",
    "wof:placetype":"venue"
},
  "geometry": {"coordinates":[-86.98249199999999,33.3707],"type":"Point"}
}