{
  "type": "Feature",
  "properties": {
    "iso:country":"US",
    "sg:address":"450 Malaga Dr",
    "sg:city":"Satsuma",
    "sg:classifiers":[
        {
            "category":"Shopping",
            "subcategory":"Gifts & Souvenirs",
            "type":"Retail Goods"
        }
    ],
    "sg:phone":"+1 251 955 2395",
    "sg:postcode":"36572",
    "sg:province":"AL",
    "wof:name":"Favor Candles & Gifts",
    "wof:placetype":"venue"
},
  "geometry": {"coordinates":[-88.036653,30.868043],"type":"Point"}
}