{
  "type": "Feature",
  "properties": {
    "addr:full":"2200 E Bay Dr Daphne AL 36526",
    "addr:housenumber":"2200",
    "addr:postcode":"36526",
    "addr:street":"E Bay Dr",
    "iso:country":"US",
    "sg:address":"2200 E Bay Dr",
    "sg:city":"Daphne",
    "sg:classifiers":[
        {
            "category":"Building & Trades",
            "subcategory":"Landscaping Services",
            "type":"Services"
        }
    ],
    "sg:phone":"+1 251 626 0502",
    "sg:postcode":"36526",
    "sg:province":"AL",
    "wof:name":"Southern Pride Lanscaping",
    "wof:placetype":"venue"
},
  "geometry": {"coordinates":[-87.91363699999999,30.634002],"type":"Point"}
}