{
  "type": "Feature",
  "properties": {
    "addr:full":"106 E Peachtree St Scottsboro AL 35768",
    "addr:housenumber":"106",
    "addr:postcode":"35768",
    "addr:street":"E Peachtree St",
    "iso:country":"US",
    "sg:address":"106 E Peachtree St",
    "sg:city":"Scottsboro",
    "sg:classifiers":[
        {
            "category":"Shopping",
            "type":"Retail Goods"
        }
    ],
    "sg:phone":"+1 256 218 3096",
    "sg:postcode":"35768",
    "sg:province":"AL",
    "sg:tags":[
        "merchandise"
    ],
    "wof:name":"Thrifts & Trendz",
    "wof:placetype":"venue"
},
  "geometry": {"coordinates":[-86.03334700000001,34.671578],"type":"Point"}
}