{
  "type": "Feature",
  "properties": {
    "iso:country":"US",
    "sg:address":"3908 Lera Dr",
    "sg:city":"Anniston",
    "sg:classifiers":[
        {
            "category":"Freight",
            "type":"Transportation"
        }
    ],
    "sg:phone":"+1 256 236 7718",
    "sg:postcode":"36207",
    "sg:province":"AL",
    "sg:tags":[
        "operator",
        "local",
        "trucking"
    ],
    "wof:name":"Nct Inc",
    "wof:placetype":"venue"
},
  "geometry": {"coordinates":[-85.774521,33.637981],"type":"Point"}
}