{
  "type": "Feature",
  "properties": {
    "addr:full":"1139 Lightwood Rd Deatsville AL 36022",
    "addr:housenumber":"1139",
    "addr:postcode":"36022",
    "addr:street":"Lightwood Rd",
    "iso:country":"US",
    "sg:address":"1139 Lightwood Rd",
    "sg:city":"Deatsville",
    "sg:classifiers":[
        {
            "category":"Shopping",
            "type":"Retail Goods"
        }
    ],
    "sg:phone":"+1 334 569 1667",
    "sg:postcode":"36022",
    "sg:province":"AL",
    "sg:tags":[
        "candle"
    ],
    "wof:name":"Ta's Scented Treasures",
    "wof:placetype":"venue"
},
  "geometry": {"coordinates":[-86.324978,32.650918],"type":"Point"}
}