{
  "type": "Feature",
  "properties": {
    "iso:country":"US",
    "sg:address":"3336 Ridgely Cir",
    "sg:city":"Birmingham",
    "sg:classifiers":[
        {
            "category":"Building & Trades",
            "subcategory":"Construction",
            "type":"Services"
        }
    ],
    "sg:phone":"+1 205 967 7028",
    "sg:postcode":"35243",
    "sg:province":"AL",
    "sg:tags":[
        "home",
        "remodeling"
    ],
    "wof:name":"Acton Contractors Inc",
    "wof:placetype":"venue"
},
  "geometry": {"coordinates":[-86.722021,33.456153],"type":"Point"}
}