{
  "type": "Feature",
  "properties": {
    "addr:full":"7960 Zeigler Blvd Mobile AL 36608",
    "addr:housenumber":"7960",
    "addr:postcode":"36608",
    "addr:street":"Zeigler Blvd",
    "iso:country":"US",
    "sg:address":"7960 Zeigler Blvd",
    "sg:city":"Mobile",
    "sg:classifiers":[
        {
            "category":"Building & Trades",
            "subcategory":"Construction",
            "type":"Services"
        }
    ],
    "sg:phone":"+1 251 633 5386",
    "sg:postcode":"36608",
    "sg:province":"AL",
    "sg:tags":[
        "general",
        "contractor"
    ],
    "wof:name":"Ro Con",
    "wof:placetype":"venue"
},
  "geometry": {"coordinates":[-88.229797,30.704898],"type":"Point"}
}