{
  "type": "Feature",
  "properties": {
    "iso:country":"US",
    "sg:address":"8740 Old Marion Rd",
    "sg:city":"Tuscaloosa",
    "sg:classifiers":[
        {
            "category":"Professional",
            "subcategory":"Business Services",
            "type":"Services"
        }
    ],
    "sg:phone":"+1 205 752 5171",
    "sg:postcode":"35405",
    "sg:province":"AL",
    "sg:tags":[
        "appraiser"
    ],
    "wof:name":"Wheat Appraisal Svc",
    "wof:placetype":"venue"
},
  "geometry": {"coordinates":[-87.527266,33.117823],"type":"Point"}
}