{
  "type": "Feature",
  "properties": {
    "iso:country":"US",
    "sg:address":"8207 State Rte 59",
    "sg:city":"Foley",
    "sg:classifiers":[
        {
            "category":"Home & Garden",
            "subcategory":"Building Materials",
            "type":"Retail Goods"
        }
    ],
    "sg:phone":"+1 251 955 2699",
    "sg:postcode":"36535",
    "sg:province":"AL",
    "sg:tags":[
        "glass",
        "window",
        "plate"
    ],
    "wof:name":"Island Glass Corp",
    "wof:placetype":"venue"
},
  "geometry": {"coordinates":[-87.682979,30.348769],"type":"Point"}
}