{
  "type": "Feature",
  "properties": {
    "iso:country":"US",
    "sg:address":"700 Cedar Lake Rd SW",
    "sg:city":"Decatur",
    "sg:classifiers":[
        {
            "category":"Real Estate",
            "subcategory":"Real Estate Services",
            "type":"Services"
        },
        {
            "category":"Real Estate",
            "subcategory":"Real Estate Operator",
            "type":"Services"
        }
    ],
    "sg:phone":"+1 256 341 0150",
    "sg:postcode":"35603",
    "sg:province":"AL",
    "sg:tags":[
        "vacancy",
        "apartment",
        "rental",
        "finder",
        "listing"
    ],
    "wof:name":"Wesley Glenn Apartments",
    "wof:placetype":"venue"
},
  "geometry": {"coordinates":[-86.994517,34.552774],"type":"Point"}
}