{
  "type": "Feature",
  "properties": {
    "iso:country":"US",
    "sg:address":"1833 Mance Newton Rd",
    "sg:city":"Dothan",
    "sg:classifiers":[
        {
            "category":"Shopping",
            "subcategory":"Gifts & Souvenirs",
            "type":"Retail Goods"
        }
    ],
    "sg:phone":"+1 334 792 5226",
    "sg:postcode":"36303",
    "sg:province":"AL",
    "sg:tags":[
        "basket",
        "parcel"
    ],
    "wof:name":"Gift Baskets Galore",
    "wof:placetype":"venue"
},
  "geometry": {"coordinates":[-85.471528,31.291602],"type":"Point"}
}