{
  "type": "Feature",
  "properties": {
    "addr:full":"3068 Gregory Ct Semmes AL 36575",
    "addr:housenumber":"3068",
    "addr:postcode":"36575",
    "addr:street":"Gregory Ct",
    "iso:country":"US",
    "sg:address":"3068 Gregory Ct",
    "sg:city":"Semmes",
    "sg:classifiers":[
        {
            "category":"Building & Trades",
            "subcategory":"Electrical",
            "type":"Services"
        }
    ],
    "sg:phone":"+1 251 442 4705",
    "sg:postcode":"36575",
    "sg:province":"AL",
    "sg:tags":[
        "electrician"
    ],
    "wof:name":"Magnolia Electrical Services LLC",
    "wof:placetype":"venue"
},
  "geometry": {"coordinates":[-88.268719,30.755524],"type":"Point"}
}