{
  "type": "Feature",
  "properties": {
    "iso:country":"US",
    "sg:address":"211 North St E",
    "sg:city":"Talladega",
    "sg:classifiers":[
        {
            "category":"Professional",
            "subcategory":"Lawyer & Legal Services",
            "type":"Services"
        }
    ],
    "sg:phone":"+1 256 362 1821",
    "sg:postcode":"35160",
    "sg:province":"AL",
    "sg:tags":[
        "attorney"
    ],
    "wof:name":"Mark D Owsley",
    "wof:placetype":"venue"
},
  "geometry": {"coordinates":[-86.098834,33.436166],"type":"Point"}
}