{
  "type": "Feature",
  "properties": {
    "iso:country":"US",
    "sg:address":"1263 Landline Rd",
    "sg:city":"Selma",
    "sg:classifiers":[
        {
            "category":"Communications",
            "subcategory":"Television Station",
            "type":"Services"
        }
    ],
    "sg:phone":"+1 334 872 5759",
    "sg:postcode":"36701",
    "sg:province":"AL",
    "wof:name":"Waka TV Channel 8",
    "wof:placetype":"venue"
},
  "geometry": {"coordinates":[-87.083395,32.40694],"type":"Point"}
}