{
  "type": "Feature",
  "properties": {
    "iso:country":"US",
    "sg:address":"908 Merchant Walk",
    "sg:city":"Huntsville",
    "sg:classifiers":[
        {
            "category":"Wholesale",
            "subcategory":"Electrical",
            "type":"Manufacturing & Wholesale Goods"
        }
    ],
    "sg:phone":"+1 256 536 8850",
    "sg:postcode":"35801",
    "sg:province":"AL",
    "sg:tags":[
        "equipment",
        "electronic",
        "supply"
    ],
    "wof:name":"Component Distributors Inc",
    "wof:placetype":"venue"
},
  "geometry": {"coordinates":[-86.58936,34.713105],"type":"Point"}
}