{
  "type": "Feature",
  "properties": {
    "addr:full":"49 Clara Day Cir Alexandria AL 36250",
    "addr:housenumber":"49",
    "addr:postcode":"36250",
    "addr:street":"Clara Day Cir",
    "iso:country":"US",
    "sg:address":"49 Clara Day Cir",
    "sg:city":"Alexandria",
    "sg:classifiers":[
        {
            "category":"Building & Trades",
            "subcategory":"Electrical",
            "type":"Services"
        }
    ],
    "sg:phone":"+1 256 820 3192",
    "sg:postcode":"36250",
    "sg:province":"AL",
    "sg:tags":[
        "work",
        "electrical",
        "electric",
        "contractor"
    ],
    "wof:name":"Edwards Quality Electric Svc",
    "wof:placetype":"venue"
},
  "geometry": {"coordinates":[-85.88352500000001,33.782539],"type":"Point"}
}