{
  "type": "Feature",
  "properties": {
    "addr:full":"205 Annandale Cres Birmingham AL 35223",
    "addr:housenumber":"205",
    "addr:postcode":"35223",
    "addr:street":"Annandale Cres",
    "iso:country":"US",
    "sg:address":"205 Annandale Cres",
    "sg:city":"Birmingham",
    "sg:classifiers":[
        {
            "category":"Professional",
            "subcategory":"Engineering",
            "type":"Services"
        }
    ],
    "sg:phone":"+1 205 992 5161",
    "sg:postcode":"35223",
    "sg:province":"AL",
    "wof:name":"Cobb E F",
    "wof:placetype":"venue"
},
  "geometry": {"coordinates":[-86.752753,33.462429],"type":"Point"}
}