{
  "type": "Feature",
  "properties": {
    "iso:country":"US",
    "sg:address":"3140 Club Dr",
    "sg:city":"Birmingham",
    "sg:classifiers":[
        {
            "category":"Sports & Exercise",
            "subcategory":"Tennis Court",
            "type":"Entertainment"
        }
    ],
    "sg:phone":"+1 205 978 0375",
    "sg:postcode":"35226",
    "sg:province":"AL",
    "sg:tags":[
        "equipment",
        "supply"
    ],
    "wof:name":"Boo Mason Tennis Inc",
    "wof:placetype":"venue"
},
  "geometry": {"coordinates":[-86.81669599999999,33.399063],"type":"Point"}
}