{
  "type": "Feature",
  "properties": {
    "addr:full":"1513 Ridgeland Rd W Mobile AL 36695",
    "addr:housenumber":"1513",
    "addr:postcode":"36695",
    "addr:street":"Ridgeland Rd W",
    "iso:country":"US",
    "sg:address":"1513 Ridgeland Rd W",
    "sg:city":"Mobile",
    "sg:classifiers":[
        {
            "category":"Building & Trades",
            "subcategory":"Construction",
            "type":"Services"
        }
    ],
    "sg:phone":"+1 251 634 0582",
    "sg:postcode":"36695",
    "sg:province":"AL",
    "sg:tags":[
        "paper",
        "painting",
        "hanging"
    ],
    "wof:name":"T & S Quality Painting Inc",
    "wof:placetype":"venue"
},
  "geometry": {"coordinates":[-88.201503,30.657366],"type":"Point"}
}