{
  "type": "Feature",
  "properties": {
    "iso:country":"US",
    "sg:address":"1988 Chandalar Ct",
    "sg:city":"Pelham",
    "sg:classifiers":[
        {
            "category":"Professional",
            "subcategory":"Lawyer & Legal Services",
            "type":"Services"
        }
    ],
    "sg:phone":"+1 205 663 1639",
    "sg:postcode":"35124",
    "sg:province":"AL",
    "sg:tags":[
        "attorney"
    ],
    "wof:name":"Harry Lyon",
    "wof:placetype":"venue"
},
  "geometry": {"coordinates":[-86.801328,33.318825],"type":"Point"}
}