{
  "type": "Feature",
  "properties": {
    "iso:country":"US",
    "sg:address":"1713 Selma Ave",
    "sg:city":"Selma",
    "sg:classifiers":[
        {
            "category":"Personal",
            "subcategory":"Beauty Salon",
            "type":"Services"
        }
    ],
    "sg:phone":"+1 334 872 0941",
    "sg:postcode":"36703",
    "sg:province":"AL",
    "wof:name":"Hair Fashion Salon",
    "wof:placetype":"venue"
},
  "geometry": {"coordinates":[-87.015534,32.411141],"type":"Point"}
}