{
  "type": "Feature",
  "properties": {
    "iso:country":"US",
    "sg:address":"2463 Meadow Ridge Ln",
    "sg:city":"Montgomery",
    "sg:classifiers":[
        {
            "category":"Building & Trades",
            "subcategory":"Construction",
            "type":"Services"
        }
    ],
    "sg:phone":"+1 334 356 8661",
    "sg:postcode":"36117",
    "sg:province":"AL",
    "sg:tags":[
        "carpentry",
        "contractor"
    ],
    "wof:name":"GA Gj Inc",
    "wof:placetype":"venue"
},
  "geometry": {"coordinates":[-86.215928,32.350635],"type":"Point"}
}