{
  "type": "Feature",
  "properties": {
    "addr:full":"616 Main St Montevallo AL 35115",
    "addr:housenumber":"616",
    "addr:postcode":"35115",
    "addr:street":"Main St",
    "iso:country":"US",
    "sg:address":"616 Main St",
    "sg:city":"Montevallo",
    "sg:classifiers":[
        {
            "category":"Personal",
            "subcategory":"Tattoo Parlor",
            "type":"Services"
        }
    ],
    "sg:phone":"+1 205 665 5088",
    "sg:postcode":"35115",
    "sg:province":"AL",
    "sg:tags":[
        "tattooing"
    ],
    "wof:name":"No Holes Barred",
    "wof:placetype":"venue"
},
  "geometry": {"coordinates":[-86.863128,33.100159],"type":"Point"}
}