{
  "type": "Feature",
  "properties": {
    "addr:full":"1710 Cherokee Ave SW Cullman AL 35055",
    "addr:housenumber":"1710",
    "addr:postcode":"35055",
    "addr:street":"Cherokee Ave Sw",
    "iso:country":"US",
    "sg:address":"1710 Cherokee Ave SW",
    "sg:city":"Cullman",
    "sg:classifiers":[
        {
            "category":"Banks & Credit Unions",
            "subcategory":"Bank",
            "type":"Services"
        }
    ],
    "sg:phone":"+1 256 255 2000",
    "sg:postcode":"35055",
    "sg:province":"AL",
    "wof:name":"Eva Bank",
    "wof:placetype":"venue"
},
  "geometry": {"coordinates":[-86.84663399999999,34.145612],"type":"Point"}
}