{
  "type": "Feature",
  "properties": {
    "iso:country":"US",
    "sg:address":"541 Old Daphne Rd",
    "sg:city":"Bay Minette",
    "sg:classifiers":[
        {
            "category":"Organizations",
            "subcategory":"Religious Organization",
            "type":"Services"
        }
    ],
    "sg:phone":"+1 251 937 2677",
    "sg:postcode":"36507",
    "sg:province":"AL",
    "sg:tags":[
        "church"
    ],
    "wof:name":"Abundant Life Christian Ctr",
    "wof:placetype":"venue"
},
  "geometry": {"coordinates":[-87.776357,30.873964],"type":"Point"}
}