{
  "type": "Feature",
  "properties": {
    "iso:country":"US",
    "sg:address":"1005 Warrior Rd",
    "sg:city":"Birmingham",
    "sg:classifiers":[
        {
            "category":"Restaurant",
            "type":"Food & Drink"
        }
    ],
    "sg:phone":"+1 205 780 9527",
    "sg:postcode":"35218",
    "sg:province":"AL",
    "wof:name":"Oakland Barbecue",
    "wof:placetype":"venue"
},
  "geometry": {"coordinates":[-86.899664,33.494967],"type":"Point"}
}