{
  "type": "Feature",
  "properties": {
    "iso:country":"US",
    "sg:address":"501 5th St W",
    "sg:city":"Jasper",
    "sg:classifiers":[
        {
            "category":"Building & Trades",
            "subcategory":"Construction",
            "type":"Services"
        }
    ],
    "sg:phone":"+1 205 221 7872",
    "sg:postcode":"35501",
    "sg:province":"AL",
    "sg:tags":[
        "excavating",
        "contractor"
    ],
    "wof:name":"Borden Dirt Construction",
    "wof:placetype":"venue"
},
  "geometry": {"coordinates":[-87.280924,33.846828],"type":"Point"}
}