{
  "type": "Feature",
  "properties": {
    "iso:country":"US",
    "sg:address":"5970 S Park Ave",
    "sg:city":"Dothan",
    "sg:classifiers":[
        {
            "category":"Building & Trades",
            "subcategory":"Electrical",
            "type":"Services"
        }
    ],
    "sg:phone":"+1 334 792 7729",
    "sg:postcode":"36301",
    "sg:province":"AL",
    "sg:tags":[
        "industrial",
        "electrician",
        "electric",
        "contractors-commercial"
    ],
    "wof:name":"J J J Electric Repair",
    "wof:placetype":"venue"
},
  "geometry": {"coordinates":[-85.447855,31.163129],"type":"Point"}
}