{
  "type": "Feature",
  "properties": {
    "iso:country":"US",
    "sg:address":"407 Ford St",
    "sg:city":"Muscle Shoals",
    "sg:classifiers":[
        {
            "category":"Banks & Credit Unions",
            "subcategory":"Bank",
            "type":"Services"
        }
    ],
    "sg:phone":"+1 256 381 8150",
    "sg:postcode":"35661",
    "sg:province":"AL",
    "sg:tags":[
        "loan",
        "real estate"
    ],
    "wof:name":"Family First Mortgage",
    "wof:placetype":"venue"
},
  "geometry": {"coordinates":[-87.671914,34.752368],"type":"Point"}
}