{
  "type": "Feature",
  "properties": {
    "iso:country":"US",
    "sg:address":"12711 Co Rd 7",
    "sg:city":"Sardis",
    "sg:classifiers":[
        {
            "category":"Restaurant",
            "type":"Food & Drink"
        }
    ],
    "sg:phone":"+1 334 877 1706",
    "sg:postcode":"36775",
    "sg:province":"AL",
    "sg:tags":[
        "eating"
    ],
    "wof:name":"Miss Mary's",
    "wof:placetype":"venue"
},
  "geometry": {"coordinates":[-86.911185,32.163752],"type":"Point"}
}