{
  "type": "Feature",
  "properties": {
    "iso:country":"US",
    "sg:address":"1420 Co Rd 112",
    "sg:city":"Opelika",
    "sg:classifiers":[
        {
            "category":"Professional",
            "subcategory":"Business Services",
            "type":"Services"
        }
    ],
    "sg:phone":"+1 334 705 0306",
    "sg:postcode":"36804",
    "sg:province":"AL",
    "wof:name":"Sherry Cox",
    "wof:placetype":"venue"
},
  "geometry": {"coordinates":[-85.387757,32.545292],"type":"Point"}
}