{
  "type": "Feature",
  "properties": {
    "addr:full":"1420 Co Rd 112 Opelika AL 36804",
    "addr:housenumber":"1420",
    "addr:postcode":"36804",
    "addr:street":"Co Rd 112",
    "iso:country":"US",
    "sg:address":"1420 Co Rd 112",
    "sg:city":"Opelika",
    "sg:classifiers":[
        {
            "category":"Professional",
            "subcategory":"Business Services",
            "type":"Services"
        }
    ],
    "sg:phone":"+1 334 705 0306",
    "sg:postcode":"36804",
    "sg:province":"AL",
    "wof:name":"Sherry Cox",
    "wof:placetype":"venue"
},
  "geometry": {"coordinates":[-85.38775699999999,32.545292],"type":"Point"}
}