{
  "type": "Feature",
  "properties": {
    "iso:country":"US",
    "sg:address":"214 Linden St",
    "sg:city":"Russellville",
    "sg:classifiers":[
        {
            "category":"Retail",
            "subcategory":"Repair Shop",
            "type":"Services"
        }
    ],
    "sg:phone":"+1 256 332 6580",
    "sg:postcode":"35653",
    "sg:province":"AL",
    "sg:tags":[
        "small",
        "engine"
    ],
    "wof:name":"Russellville Small Engines",
    "wof:placetype":"venue"
},
  "geometry": {"coordinates":[-87.718028,34.514726],"type":"Point"}
}