{
  "type": "Feature",
  "properties": {
    "addr:full":"107 Meadowhill Rd Sheffield AL 35660",
    "addr:housenumber":"107",
    "addr:postcode":"35660",
    "addr:street":"Meadowhill Rd",
    "iso:country":"US",
    "sg:address":"107 Meadowhill Rd",
    "sg:city":"Sheffield",
    "sg:classifiers":[
        {
            "category":"Professional",
            "type":"Services"
        }
    ],
    "sg:phone":"+1 256 381 3233",
    "sg:postcode":"35660",
    "sg:province":"AL",
    "wof:name":"Sign On Corp",
    "wof:placetype":"venue"
},
  "geometry": {"coordinates":[-87.719801,34.734858],"type":"Point"}
}