{
  "type": "Feature",
  "properties": {
    "iso:country":"US",
    "sg:address":"330 S Albert Rains Blvd",
    "sg:city":"Gadsden",
    "sg:classifiers":[
        {
            "category":"Restaurant",
            "type":"Food & Drink"
        }
    ],
    "sg:phone":"+1 256 547 7570",
    "sg:postcode":"35901",
    "sg:province":"AL",
    "sg:tags":[
        "eating"
    ],
    "wof:name":"Mango's Restaurant",
    "wof:placetype":"venue"
},
  "geometry": {"coordinates":[-86.001198,34.005179],"type":"Point"}
}