{
  "type": "Feature",
  "properties": {
    "iso:country":"US",
    "sg:address":"1531 13th Pl S",
    "sg:city":"Birmingham",
    "sg:classifiers":[
        {
            "category":"Food & Beverages",
            "subcategory":"Groceries & Convenience Stores",
            "type":"Retail Goods"
        }
    ],
    "sg:phone":"+1 205 930 0235",
    "sg:postcode":"35205",
    "sg:province":"AL",
    "sg:tags":[
        "grocer"
    ],
    "wof:name":"Lorino's Food Ctr",
    "wof:placetype":"venue"
},
  "geometry": {"coordinates":[-86.804775,33.49119],"type":"Point"}
}