{
  "type": "Feature",
  "properties": {
    "addr:full":"3040 Allison Bonnett Memorial Dr Bessemer AL 35023",
    "addr:housenumber":"3040",
    "addr:postcode":"35023",
    "addr:street":"Allison Bonnett Memorial Dr",
    "iso:country":"US",
    "sg:address":"3040 Allison Bonnett Memorial Dr",
    "sg:city":"Bessemer",
    "sg:classifiers":[
        {
            "category":"Restaurant",
            "type":"Food & Drink"
        }
    ],
    "sg:menulink":"http://www.allmenus.com/al/birmingham/231546-sonic/menu/",
    "sg:phone":"+1 205 497 1007",
    "sg:postcode":"35023",
    "sg:province":"AL",
    "sg:tags":[
        "burger",
        "american"
    ],
    "wof:name":"Sonic",
    "wof:placetype":"venue"
},
  "geometry": {"coordinates":[-86.98057799999999,33.450744],"type":"Point"}
}