{
  "type": "Feature",
  "properties": {
    "addr:full":"906 Church St Selma AL 36701",
    "addr:housenumber":"906",
    "addr:postcode":"36701",
    "addr:street":"Church St",
    "iso:country":"US",
    "sg:address":"906 Church St",
    "sg:city":"Selma",
    "sg:classifiers":[
        {
            "category":"Building & Trades",
            "subcategory":"Construction",
            "type":"Services"
        }
    ],
    "sg:phone":"+1 334 872 3187",
    "sg:postcode":"36701",
    "sg:province":"AL",
    "sg:tags":[
        "contractor"
    ],
    "wof:name":"Associates Builders Group",
    "wof:placetype":"venue"
},
  "geometry": {"coordinates":[-87.026034,32.414039],"type":"Point"}
}