{
  "type": "Feature",
  "properties": {
    "iso:country":"US",
    "sg:address":"703 Old Lee Hwy",
    "sg:city":"Tuscumbia",
    "sg:classifiers":[
        {
            "category":"Personal",
            "subcategory":"Barber",
            "type":"Services"
        }
    ],
    "sg:phone":"+1 256 383 9853",
    "sg:postcode":"35674",
    "sg:province":"AL",
    "sg:tags":[
        "shop"
    ],
    "wof:name":"Family Barber Shop",
    "wof:placetype":"venue"
},
  "geometry": {"coordinates":[-87.71213,34.726689],"type":"Point"}
}