{
  "type": "Feature",
  "properties": {
    "iso:country":"US",
    "sg:address":"801 20th Ave E",
    "sg:city":"Jasper",
    "sg:classifiers":[
        {
            "category":"Health Services",
            "subcategory":"Doctor",
            "type":"Services"
        }
    ],
    "sg:phone":"+1 205 384 9004",
    "sg:postcode":"35501",
    "sg:province":"AL",
    "sg:tags":[
        "medical"
    ],
    "wof:name":"Smith Judson W Dr",
    "wof:placetype":"venue"
},
  "geometry": {"coordinates":[-87.251855,33.841844],"type":"Point"}
}