{
  "type": "Feature",
  "properties": {
    "iso:country":"US",
    "sg:address":"206 Monte Vista Dr",
    "sg:city":"Madison",
    "sg:classifiers":[
        {
            "category":"Building & Trades",
            "subcategory":"Construction",
            "type":"Services"
        }
    ],
    "sg:phone":"+1 256 772 9068",
    "sg:postcode":"35758",
    "sg:province":"AL",
    "sg:tags":[
        "hanging",
        "contractor"
    ],
    "wof:name":"VA Painting",
    "wof:placetype":"venue"
},
  "geometry": {"coordinates":[-86.755248,34.688793],"type":"Point"}
}