{
  "type": "Feature",
  "properties": {
    "addr:full":"3102 Allison-Bonnett Memorial Dr Hueytown AL 35023",
    "addr:housenumber":"3102",
    "addr:postcode":"35023",
    "addr:street":"Allison-Bonnett Memorial Dr",
    "iso:country":"US",
    "sg:address":"3102 Allison-Bonnett Memorial Dr",
    "sg:city":"Hueytown",
    "sg:classifiers":[
        {
            "category":"Retail",
            "subcategory":"Self-service Laundry",
            "type":"Services"
        }
    ],
    "sg:phone":"+1 205 491 9728",
    "sg:postcode":"35023",
    "sg:province":"AL",
    "wof:name":"Holly Ridge Laundry & Cleaners",
    "wof:placetype":"venue"
},
  "geometry": {"coordinates":[-86.989131,33.454668],"type":"Point"}
}