{
  "type": "Feature",
  "properties": {
    "iso:country":"US",
    "sg:address":"524 W 9th St",
    "sg:city":"Sylacauga",
    "sg:classifiers":[
        {
            "category":"Building & Trades",
            "subcategory":"Construction",
            "type":"Services"
        }
    ],
    "sg:phone":"+1 256 245 8078",
    "sg:postcode":"35150",
    "sg:province":"AL",
    "sg:tags":[
        "general",
        "contractor"
    ],
    "wof:name":"Midway Contractors",
    "wof:placetype":"venue"
},
  "geometry": {"coordinates":[-86.262083,33.179272],"type":"Point"}
}