{
  "type": "Feature",
  "properties": {
    "iso:country":"US",
    "sg:address":"15796 Sanderson Ln",
    "sg:city":"Athens",
    "sg:classifiers":[
        {
            "category":"Professional",
            "type":"Services"
        }
    ],
    "sg:phone":"+1 256 232 7815",
    "sg:postcode":"35613",
    "sg:province":"AL",
    "wof:name":"Glynn Snider",
    "wof:placetype":"venue"
},
  "geometry": {"coordinates":[-86.871852,34.786504],"type":"Point"}
}