{
  "type": "Feature",
  "properties": {
    "iso:country":"US",
    "sg:address":"1503 E Shan Dr",
    "sg:city":"Mobile",
    "sg:classifiers":[
        {
            "category":"Building & Trades",
            "subcategory":"Construction",
            "type":"Services"
        }
    ],
    "sg:phone":"+1 251 666 4997",
    "sg:postcode":"36693",
    "sg:province":"AL",
    "sg:tags":[
        "house"
    ],
    "wof:name":"All Service Painting & Cnstr",
    "wof:placetype":"venue"
},
  "geometry": {"coordinates":[-88.14416799999999,30.627722],"type":"Point"}
}