{
  "type": "Feature",
  "properties": {
    "iso:country":"US",
    "sg:address":"4050 Rushton St",
    "sg:city":"Florence",
    "sg:classifiers":[
        {
            "category":"Shopping",
            "subcategory":"Clothing, Apparel, & Fashions",
            "type":"Retail Goods"
        }
    ],
    "sg:phone":"+1 256 740 6500",
    "sg:postcode":"35630",
    "sg:province":"AL",
    "sg:tags":[
        "t"
    ],
    "wof:name":"Tee Jays Mfg Co Inc",
    "wof:placetype":"venue"
},
  "geometry": {"coordinates":[-87.650989,34.859811],"type":"Point"}
}