{
  "type": "Feature",
  "properties": {
    "addr:full":"1539 S Main St Graysville AL 35073",
    "addr:housenumber":"1539",
    "addr:postcode":"35073",
    "addr:street":"S Main St",
    "iso:country":"US",
    "sg:address":"1539 S Main St",
    "sg:city":"Graysville",
    "sg:classifiers":[
        {
            "category":"Restaurant",
            "type":"Food & Drink"
        }
    ],
    "sg:phone":"+1 205 674 2800",
    "sg:postcode":"35073",
    "sg:province":"AL",
    "sg:tags":[
        "eating"
    ],
    "wof:name":"Greens Steakhouse & Restaurant",
    "wof:placetype":"venue"
},
  "geometry": {"coordinates":[-86.96435,33.612331],"type":"Point"}
}