{
  "type": "Feature",
  "properties": {
    "addr:full":"2224 Enon Rd Webb AL 36376",
    "addr:housenumber":"2224",
    "addr:postcode":"36376",
    "addr:street":"Enon Rd",
    "iso:country":"US",
    "sg:address":"2224 Enon Rd",
    "sg:city":"Webb",
    "sg:phone":"+1 334 899 3959",
    "sg:postcode":"36376",
    "sg:province":"AL",
    "sg:tags":[
        "farm",
        "field",
        "corn",
        "soybean",
        "crop"
    ],
    "wof:name":"Ronnie Crawford",
    "wof:placetype":"venue"
},
  "geometry": {"coordinates":[-85.276794,31.228554],"type":"Point"}
}