{
  "type": "Feature",
  "properties": {
    "iso:country":"US",
    "sg:address":"79 Rabbit Branch Rd",
    "sg:city":"Cropwell",
    "sg:classifiers":[
        {
            "category":"Recreation",
            "subcategory":"Marina",
            "type":"Entertainment"
        }
    ],
    "sg:phone":"+1 205 525 5562",
    "sg:postcode":"35054",
    "sg:province":"AL",
    "sg:tags":[
        "operation"
    ],
    "wof:name":"Rabbit Branch Marina Inc",
    "wof:placetype":"venue"
},
  "geometry": {"coordinates":[-86.313236,33.501439],"type":"Point"}
}