{
  "type": "Feature",
  "properties": {
    "iso:country":"US",
    "sg:address":"53 County Line Rd",
    "sg:city":"Phenix City",
    "sg:classifiers":[
        {
            "category":"Retail",
            "subcategory":"Laundry & Dry Cleaning",
            "type":"Services"
        }
    ],
    "sg:phone":"+1 334 297 2615",
    "sg:postcode":"36870",
    "sg:province":"AL",
    "wof:name":"J & W Carpet Cleaning",
    "wof:placetype":"venue"
},
  "geometry": {"coordinates":[-85.060229,32.496806],"type":"Point"}
}