{
  "type": "Feature",
  "properties": {
    "iso:country":"US",
    "sg:address":"606 Clay St",
    "sg:city":"Montgomery",
    "sg:classifiers":[
        {
            "category":"Wholesale",
            "subcategory":"Stationery",
            "type":"Manufacturing & Wholesale Goods"
        }
    ],
    "sg:phone":"+1 334 834 9494",
    "sg:postcode":"36104",
    "sg:province":"AL",
    "sg:tags":[
        "business",
        "form",
        "system"
    ],
    "wof:name":"Safeguard Business Systems",
    "wof:placetype":"venue"
},
  "geometry": {"coordinates":[-86.320832,32.376576],"type":"Point"}
}