{
  "type": "Feature",
  "properties": {
    "iso:country":"US",
    "sg:address":"900 S 4th St",
    "sg:city":"Gadsden",
    "sg:classifiers":[
        {
            "category":"Insurance",
            "subcategory":"Insurance Agent",
            "type":"Services"
        }
    ],
    "sg:phone":"+1 256 543 2019",
    "sg:postcode":"35901",
    "sg:province":"AL",
    "wof:name":"State Farm Insurance",
    "wof:placetype":"venue"
},
  "geometry": {"coordinates":[-86.00560299999999,33.998588],"type":"Point"}
}