{
  "type": "Feature",
  "properties": {
    "addr:full":"919 Co Rd 20 Dawson AL 35963",
    "addr:housenumber":"919;20",
    "addr:postcode":"35963",
    "addr:street":"Co Rd",
    "iso:country":"US",
    "sg:address":"919 Co Rd 20",
    "sg:city":"Dawson",
    "sg:classifiers":[
        {
            "category":"Farming",
            "subcategory":"Livestock Farm",
            "type":"Manufacturing & Wholesale Goods"
        }
    ],
    "sg:phone":"+1 256 659 4935",
    "sg:postcode":"35963",
    "sg:province":"AL",
    "sg:tags":[
        "beef",
        "feedlot",
        "cattle"
    ],
    "wof:name":"Whitmore Farms",
    "wof:placetype":"venue"
},
  "geometry": {"coordinates":[-85.93358499999999,34.30956],"type":"Point"}
}