{
  "type": "Feature",
  "properties": {
    "addr:full":"330 Railway Fuel St Parrish AL 35580",
    "addr:housenumber":"330",
    "addr:postcode":"35580",
    "addr:street":"Railway Fuel St",
    "iso:country":"US",
    "sg:address":"330 Railway Fuel St",
    "sg:city":"Parrish",
    "sg:classifiers":[
        {
            "category":"Manufacturing",
            "subcategory":"Signs",
            "type":"Manufacturing & Wholesale Goods"
        }
    ],
    "sg:phone":"+1 205 686 5356",
    "sg:postcode":"35580",
    "sg:province":"AL",
    "sg:tags":[
        "specialty",
        "mfg"
    ],
    "wof:name":"Greens Custom Sign",
    "wof:placetype":"venue"
},
  "geometry": {"coordinates":[-87.27797099999999,33.732053],"type":"Point"}
}