{
  "type": "Feature",
  "properties": {
    "iso:country":"US",
    "sg:address":"3060 Mobile Hwy",
    "sg:city":"Montgomery",
    "sg:classifiers":[
        {
            "category":"Government",
            "subcategory":"Office",
            "type":"Public Place"
        }
    ],
    "sg:phone":"+1 334 293 6450",
    "sg:postcode":"36108",
    "sg:province":"AL",
    "sg:tags":[
        "county",
        "resource"
    ],
    "wof:name":"Montgomery County WIC",
    "wof:placetype":"venue"
},
  "geometry": {"coordinates":[-86.337566,32.350589],"type":"Point"}
}