{
  "type": "Feature",
  "properties": {
    "iso:country":"US",
    "sg:address":"102 Eleanor Ave",
    "sg:city":"Harvest",
    "sg:classifiers":[
        {
            "category":"Real Estate",
            "subcategory":"Real Estate Agent",
            "type":"Services"
        }
    ],
    "sg:phone":"+1 256 722 9333",
    "sg:postcode":"35749",
    "sg:province":"AL",
    "wof:name":"Tommy Purett Real Estate Inc",
    "wof:placetype":"venue"
},
  "geometry": {"coordinates":[-86.760464,34.81036],"type":"Point"}
}