{
  "type": "Feature",
  "properties": {
    "iso:country":"US",
    "sg:address":"711 Industrial Pkwy",
    "sg:city":"Saraland",
    "sg:classifiers":[
        {
            "category":"Manufacturing",
            "subcategory":"Wood Products",
            "type":"Manufacturing & Wholesale Goods"
        }
    ],
    "sg:phone":"+1 251 675 3080",
    "sg:postcode":"36571",
    "sg:province":"AL",
    "sg:tags":[
        "mfg"
    ],
    "wof:name":"Parkway Pallets Inc",
    "wof:placetype":"venue"
},
  "geometry": {"coordinates":[-88.091161,30.800028],"type":"Point"}
}