{
  "type": "Feature",
  "properties": {
    "iso:country":"US",
    "sg:address":"15 Mountain Woods Lake Rd",
    "sg:city":"Warrior",
    "sg:classifiers":[
        {
            "category":"Personal",
            "subcategory":"Beauty Salon",
            "type":"Services"
        }
    ],
    "sg:phone":"+1 205 647 6698",
    "sg:postcode":"35180",
    "sg:province":"AL",
    "sg:tags":[
        "shop"
    ],
    "wof:name":"Expressions Hair Studio",
    "wof:placetype":"venue"
},
  "geometry": {"coordinates":[-86.785205,33.869874],"type":"Point"}
}