{
  "type": "Feature",
  "properties": {
    "iso:country":"US",
    "sg:address":"445 Providence Main St NW",
    "sg:city":"Huntsville",
    "sg:classifiers":[
        {
            "category":"Deli",
            "type":"Food & Drink"
        },
        {
            "category":"Cafe",
            "type":"Food & Drink"
        }
    ],
    "sg:menulink":"http://www.allmenus.com/al/huntsville/246653-market-street-cafe/menu/",
    "sg:phone":"+1 256 489 6273",
    "sg:postcode":"35806",
    "sg:province":"AL",
    "sg:tags":[
        "american"
    ],
    "wof:name":"Market Street Cafe",
    "wof:placetype":"venue"
},
  "geometry": {"coordinates":[-86.69289999999999,34.753747],"type":"Point"}
}