{
  "type": "Feature",
  "properties": {
    "addr:full":"102 Shine Dr Pelham AL 35124",
    "addr:housenumber":"102",
    "addr:postcode":"35124",
    "addr:street":"Shine Dr",
    "iso:country":"US",
    "sg:address":"102 Shine Dr",
    "sg:city":"Pelham",
    "sg:classifiers":[
        {
            "category":"Building & Trades",
            "subcategory":"Construction",
            "type":"Services"
        }
    ],
    "sg:phone":"+1 205 987 0059",
    "sg:postcode":"35124",
    "sg:province":"AL",
    "sg:tags":[
        "house"
    ],
    "wof:name":"Frisbee Construction",
    "wof:placetype":"venue"
},
  "geometry": {"coordinates":[-86.815113,33.325605],"type":"Point"}
}