{
  "type": "Feature",
  "properties": {
    "addr:full":"3780 S Park Ave Dothan AL 36301",
    "addr:housenumber":"3780",
    "addr:postcode":"36301",
    "addr:street":"S Park Ave",
    "iso:country":"US",
    "sg:address":"3780 S Park Ave",
    "sg:city":"Dothan",
    "sg:classifiers":[
        {
            "category":"Professional",
            "type":"Services"
        }
    ],
    "sg:phone":"+1 334 699 3118",
    "sg:postcode":"36301",
    "sg:province":"AL",
    "wof:name":"D Davis",
    "wof:placetype":"venue"
},
  "geometry": {"coordinates":[-85.422366,31.183028],"type":"Point"}
}