{
  "type": "Feature",
  "properties": {
    "iso:country":"US",
    "sg:address":"2307 Kala St",
    "sg:city":"Helena",
    "sg:classifiers":[
        {
            "category":"Professional",
            "subcategory":"Management & Consulting",
            "type":"Services"
        }
    ],
    "sg:phone":"+1 205 663 0515",
    "sg:postcode":"35080",
    "sg:province":"AL",
    "sg:tags":[
        "aviation",
        "support",
        "construction",
        "safety",
        "grading"
    ],
    "wof:name":"JD Mith & Sons",
    "wof:placetype":"venue"
},
  "geometry": {"coordinates":[-86.847465,33.272171],"type":"Point"}
}