{
  "type": "Feature",
  "properties": {
    "iso:country":"US",
    "sg:address":"21824 US Hwy 431",
    "sg:city":"Guntersville",
    "sg:classifiers":[
        {
            "category":"Wholesale",
            "subcategory":"Machinery & Supplies",
            "type":"Manufacturing & Wholesale Goods"
        }
    ],
    "sg:phone":"+1 256 505 0064",
    "sg:postcode":"35976",
    "sg:province":"AL",
    "sg:tags":[
        "truck"
    ],
    "wof:name":"Regional Lift Truck Inc",
    "wof:placetype":"venue"
},
  "geometry": {"coordinates":[-86.266509,34.417245],"type":"Point"}
}