{
  "type": "Feature",
  "properties": {
    "iso:country":"US",
    "sg:address":"474 Lakewood Dr",
    "sg:city":"Gadsden",
    "sg:classifiers":[
        {
            "category":"Organizations",
            "subcategory":"Religious Organization",
            "type":"Services"
        }
    ],
    "sg:phone":"+1 256 442 2580",
    "sg:postcode":"35901",
    "sg:province":"AL",
    "wof:name":"Riverbend Baptist Church",
    "wof:placetype":"venue"
},
  "geometry": {"coordinates":[-86.002273,33.946697],"type":"Point"}
}