{
  "type": "Feature",
  "properties": {
    "addr:full":"910 Ploof Dr Bessemer AL 35023",
    "addr:housenumber":"910",
    "addr:postcode":"35023",
    "addr:street":"Ploof Dr",
    "iso:country":"US",
    "sg:address":"910 Ploof Dr",
    "sg:city":"Bessemer",
    "sg:classifiers":[
        {
            "category":"Building & Trades",
            "subcategory":"Electrical",
            "type":"Services"
        },
        {
            "category":"Manufacturing",
            "subcategory":"Electronics",
            "type":"Manufacturing & Wholesale Goods"
        }
    ],
    "sg:phone":"+1 205 491 8665",
    "sg:postcode":"35023",
    "sg:province":"AL",
    "sg:tags":[
        "mfg",
        "contractor",
        "electrical",
        "printed",
        "circuit",
        "etched"
    ],
    "wof:name":"Dexter Fortson Assoc Inc",
    "wof:placetype":"venue"
},
  "geometry": {"coordinates":[-86.975684,33.438735],"type":"Point"}
}