{
  "type": "Feature",
  "properties": {
    "iso:country":"US",
    "sg:address":"2221 Ross Clark Cir",
    "sg:city":"Dothan",
    "sg:classifiers":[
        {
            "category":"Retail",
            "subcategory":"Repair Shop",
            "type":"Services"
        }
    ],
    "sg:phone":"+1 334 774 8000",
    "sg:postcode":"36301",
    "sg:province":"AL",
    "sg:tags":[
        "television",
        "station"
    ],
    "wof:name":"Wdfx TV",
    "wof:placetype":"venue"
},
  "geometry": {"coordinates":[-85.401679,31.190462],"type":"Point"}
}