{
  "type": "Feature",
  "properties": {
    "iso:country":"US",
    "sg:address":"402 Pelham Rd N",
    "sg:city":"Jacksonville",
    "sg:classifiers":[
        {
            "category":"Personal",
            "subcategory":"Tattoo Parlor",
            "type":"Services"
        }
    ],
    "sg:phone":"+1 256 782 3744",
    "sg:postcode":"36265",
    "sg:province":"AL",
    "sg:tags":[
        "tattooing"
    ],
    "wof:name":"Ink Smart Body Art",
    "wof:placetype":"venue"
},
  "geometry": {"coordinates":[-85.761151,33.818043],"type":"Point"}
}