{
  "type": "Feature",
  "properties": {
    "iso:country":"US",
    "sg:address":"739 Main St",
    "sg:city":"Roanoke",
    "sg:classifiers":[
        {
            "category":"Professional",
            "subcategory":"Lawyer & Legal Services",
            "type":"Services"
        }
    ],
    "sg:phone":"+1 334 863 8945",
    "sg:postcode":"36274",
    "sg:province":"AL",
    "wof:name":"John A Tinney Attorney At Law",
    "wof:placetype":"venue"
},
  "geometry": {"coordinates":[-85.370202,33.150841],"type":"Point"}
}