{
  "type": "Feature",
  "properties": {
    "addr:full":"2705 19th St N Bessemer AL 35023",
    "addr:housenumber":"2705",
    "addr:postcode":"35023",
    "addr:street":"19Th St N",
    "iso:country":"US",
    "sg:address":"2705 19th St N",
    "sg:city":"Bessemer",
    "sg:classifiers":[
        {
            "category":"Personal",
            "subcategory":"Beauty Salon",
            "type":"Services"
        }
    ],
    "sg:phone":"+1 205 491 9850",
    "sg:postcode":"35023",
    "sg:province":"AL",
    "sg:tags":[
        "shop"
    ],
    "wof:name":"Cutters",
    "wof:placetype":"venue"
},
  "geometry": {"coordinates":[-86.98450099999999,33.421445],"type":"Point"}
}