{
  "type": "Feature",
  "properties": {
    "addr:full":"1926 Tower Dr NE Arab AL 35016",
    "addr:housenumber":"1926",
    "addr:postcode":"35016",
    "addr:street":"Tower Dr Ne",
    "iso:country":"US",
    "sg:address":"1926 Tower Dr NE",
    "sg:city":"Arab",
    "sg:classifiers":[
        {
            "category":"Freight",
            "type":"Transportation"
        }
    ],
    "sg:phone":"+1 256 586 5667",
    "sg:postcode":"35016",
    "sg:province":"AL",
    "sg:tags":[
        "operator",
        "local",
        "trucking"
    ],
    "wof:name":"Kelvin Blackmon Trucking LLC",
    "wof:placetype":"venue"
},
  "geometry": {"coordinates":[-86.46339399999999,34.352151],"type":"Point"}
}