{
  "type": "Feature",
  "properties": {
    "iso:country":"US",
    "sg:address":"5744 US Hwy 84",
    "sg:city":"Cowarts",
    "sg:classifiers":[
        {
            "category":"Autos & Motor Vehicles",
            "subcategory":"Fuel & Gas Station",
            "type":"Retail Goods"
        }
    ],
    "sg:phone":"+1 334 793 1544",
    "sg:postcode":"36321",
    "sg:province":"AL",
    "sg:tags":[
        "bulk",
        "gasoline",
        "station",
        "petroleum"
    ],
    "wof:name":"Hobo Pantry Food Stores",
    "wof:placetype":"venue"
},
  "geometry": {"coordinates":[-85.312519,31.192854],"type":"Point"}
}