{
  "type": "Feature",
  "properties": {
    "iso:country":"US",
    "sg:address":"974 W Carroll St",
    "sg:city":"Dothan",
    "sg:classifiers":[
        {
            "category":"Professional",
            "subcategory":"Accounting & Tax Preparation",
            "type":"Services"
        }
    ],
    "sg:phone":"+1 334 792 7159",
    "sg:postcode":"36301",
    "sg:province":"AL",
    "sg:tags":[
        "accountant"
    ],
    "wof:name":"Bedsole Bryant & Assoc",
    "wof:placetype":"venue"
},
  "geometry": {"coordinates":[-85.414052,31.199374],"type":"Point"}
}