{
  "type": "Feature",
  "properties": {
    "addr:full":"1211 Pattillo St SW Hartselle AL 35640",
    "addr:housenumber":"1211",
    "addr:postcode":"35640",
    "addr:street":"Pattillo St Sw",
    "iso:country":"US",
    "sg:address":"1211 Pattillo St SW",
    "sg:city":"Hartselle",
    "sg:classifiers":[
        {
            "category":"Organizations",
            "subcategory":"Religious Organization",
            "type":"Services"
        }
    ],
    "sg:phone":"+1 256 773 2478",
    "sg:postcode":"35640",
    "sg:province":"AL",
    "sg:tags":[
        "church"
    ],
    "wof:name":"Church Of God Pattillo Street",
    "wof:placetype":"venue"
},
  "geometry": {"coordinates":[-86.941931,34.431643],"type":"Point"}
}