{
  "type": "Feature",
  "properties": {
    "addr:full":"325 N Glendale St Geneva AL 36340",
    "addr:housenumber":"325",
    "addr:postcode":"36340",
    "addr:street":"N Glendale St",
    "iso:country":"US",
    "sg:address":"325 N Glendale St",
    "sg:city":"Geneva",
    "sg:classifiers":[
        {
            "category":"Professional",
            "type":"Services"
        }
    ],
    "sg:phone":"+1 334 684 1757",
    "sg:postcode":"36340",
    "sg:province":"AL",
    "wof:name":"Stamp Lori",
    "wof:placetype":"venue"
},
  "geometry": {"coordinates":[-85.894659,31.054367],"type":"Point"}
}