{
  "type": "Feature",
  "properties": {
    "iso:country":"US",
    "sg:address":"346 N Seneca Dr",
    "sg:city":"Trinity",
    "sg:classifiers":[
        {
            "category":"Professional",
            "subcategory":"Employment Agencies",
            "type":"Services"
        }
    ],
    "sg:phone":"+1 256 341 0380",
    "sg:postcode":"35673",
    "sg:province":"AL",
    "sg:tags":[
        "opportunity"
    ],
    "wof:name":"One Man Jobs",
    "wof:placetype":"venue"
},
  "geometry": {"coordinates":[-87.089991,34.596834],"type":"Point"}
}