{
  "type": "Feature",
  "properties": {
    "addr:full":"4304 Johnson St Adamsville AL 35005",
    "addr:housenumber":"4304",
    "addr:postcode":"35005",
    "addr:street":"Johnson St",
    "iso:country":"US",
    "sg:address":"4304 Johnson St",
    "sg:city":"Adamsville",
    "sg:classifiers":[
        {
            "category":"Retail",
            "subcategory":"Funeral Services",
            "type":"Services"
        }
    ],
    "sg:phone":"+1 205 674 5691",
    "sg:postcode":"35005",
    "sg:province":"AL",
    "sg:tags":[
        "cemetery"
    ],
    "wof:name":"Crestview Memorial Gardens Inc",
    "wof:placetype":"venue"
},
  "geometry": {"coordinates":[-86.969803,33.601101],"type":"Point"}
}